{
  "type": "Feature",
  "properties": {
    "iso:country":"US",
    "sg:address":"2949 W River Rd N",
    "sg:city":"Elyria",
    "sg:classifiers":[
        {
            "category":"Organizations",
            "subcategory":"Religious Organization",
            "type":"Services"
        }
    ],
    "sg:phone":"+1 440 324 1202",
    "sg:postcode":"44035",
    "sg:province":"OH",
    "sg:tags":[
        "church"
    ],
    "wof:name":"Cornerstone United Mthdst Chr",
    "wof:placetype":"venue"
},
  "geometry": {"coordinates":[-82.107172,41.400061],"type":"Point"}
}