{
  "type": "Feature",
  "properties": {
    "addr:full":"2949 W River Rd N Elyria OH 44035",
    "addr:housenumber":"2949",
    "addr:postcode":"44035",
    "addr:street":"W River Rd N",
    "iso:country":"US",
    "sg:address":"2949 W River Rd N",
    "sg:city":"Elyria",
    "sg:classifiers":[
        {
            "category":"Organizations",
            "subcategory":"Religious Organization",
            "type":"Services"
        }
    ],
    "sg:phone":"+1 440 324 1202",
    "sg:postcode":"44035",
    "sg:province":"OH",
    "sg:tags":[
        "church"
    ],
    "wof:name":"Cornerstone United Mthdst Chr",
    "wof:placetype":"venue"
},
  "geometry": {"coordinates":[-82.10717200000001,41.400061],"type":"Point"}
}