{
  "type": "Feature",
  "properties": {
    "addr:full": "1464 N Portage Path Akron OH 44313",
    "addr:housenumber": "1464",
    "addr:postcode": "44313",
    "addr:street": "N Portage Path",
    "iso:country": "US",
    "sg:address": "1464 N Portage Path",
    "sg:city": "Akron",
    "sg:classifiers": [
      {
        "category": "Shopping",
        "subcategory": "Used Merchandise",
        "type": "Retail Goods"
      }
    ],
    "sg:phone": "+1 330 864 4001",
    "sg:postcode": "44313",
    "sg:province": "OH",
    "sg:tags": [
      "antique"
    ],
    "wof:name": "Needful Things In The Valley",
    "wof:placetype": "venue"
  },
  "geometry": {"coordinates":[-81.547838,41.135487],"type":"Point"}
}
