{
  "type": "Feature",
  "properties": {
    "addr:full":"1781 Octavia Rd Cleveland OH 44112",
    "addr:housenumber":"1781",
    "addr:postcode":"44112",
    "addr:street":"Octavia Rd",
    "iso:country":"US",
    "sg:address":"1781 Octavia Rd",
    "sg:city":"Cleveland",
    "sg:classifiers":[
        {
            "category":"Manufacturing",
            "subcategory":"Tools & Machinery",
            "type":"Manufacturing & Wholesale Goods"
        }
    ],
    "sg:phone":"+1 216 692 7900",
    "sg:postcode":"44112",
    "sg:province":"OH",
    "sg:tags":[
        "mfg",
        "equipment",
        "industrial",
        "pattern"
    ],
    "wof:name":"Sherwood Refractores",
    "wof:placetype":"venue"
},
  "geometry": {"coordinates":[-81.565009,41.547915],"type":"Point"}
}