{
  "type": "Feature",
  "properties": {
    "addr:full": "28286 Osborn Rd Coolville OH 45723",
    "addr:housenumber": "28286",
    "addr:postcode": "45723",
    "addr:street": "Osborn Rd",
    "iso:country": "US",
    "sg:address": "28286 Osborn Rd",
    "sg:city": "Coolville",
    "sg:classifiers": [
      {
        "category": "Professional",
        "type": "Services"
      }
    ],
    "sg:phone": "+1 740 667 3667",
    "sg:postcode": "45723",
    "sg:province": "OH",
    "wof:name": "Mettler",
    "wof:placetype": "venue"
  },
  "geometry": {"coordinates":[-81.758952,39.24018],"type":"Point"}
}
