{
  "type": "Feature",
  "properties": {
    "iso:country":"US",
    "sg:address":"28286 Osborn Rd",
    "sg:city":"Coolville",
    "sg:classifiers":[
        {
            "category":"Professional",
            "type":"Services"
        }
    ],
    "sg:phone":"+1 740 667 3667",
    "sg:postcode":"45723",
    "sg:province":"OH",
    "wof:name":"Mettler",
    "wof:placetype":"venue"
},
  "geometry": {"coordinates":[-81.75895199999999,39.24018],"type":"Point"}
}