{
  "type": "Feature",
  "properties": {
    "addr:full": "1475 Twp Hwy 262 Bloomingdale OH 43910",
    "addr:housenumber": "1475",
    "addr:postcode": "43910",
    "addr:street": "Twp Hwy 262",
    "iso:country": "US",
    "sg:address": "1475 Twp Hwy 262",
    "sg:city": "Bloomingdale",
    "sg:classifiers": [
      {
        "category": "Farming",
        "subcategory": "Dairy Farm",
        "type": "Manufacturing \u0026 Wholesale Goods"
      }
    ],
    "sg:phone": "+1 740 543 3387",
    "sg:postcode": "43910",
    "sg:province": "OH",
    "wof:name": "Calvin Pethtel Sr",
    "wof:placetype": "venue"
  },
  "geometry": {"coordinates":[-80.834183,40.447672],"type":"Point"}
}
