{
  "type": "Feature",
  "properties": {
    "iso:country":"US",
    "sg:address":"1475 Twp Hwy 262",
    "sg:city":"Bloomingdale",
    "sg:classifiers":[
        {
            "category":"Farming",
            "subcategory":"Dairy Farm",
            "type":"Manufacturing & Wholesale Goods"
        }
    ],
    "sg:phone":"+1 740 543 3387",
    "sg:postcode":"43910",
    "sg:province":"OH",
    "wof:name":"Calvin Pethtel Sr",
    "wof:placetype":"venue"
},
  "geometry": {"coordinates":[-80.834183,40.447672],"type":"Point"}
}