{
  "type": "Feature",
  "properties": {
    "addr:full": "430 S Main St St Marys OH 45885",
    "addr:housenumber": "430",
    "addr:postcode": "45885",
    "addr:street": "S Main St",
    "iso:country": "US",
    "sg:address": "430 S Main St",
    "sg:city": "St Marys",
    "sg:classifiers": [
      {
        "category": "Wholesale",
        "subcategory": "Durable Goods \u0026 Equipment",
        "type": "Manufacturing \u0026 Wholesale Goods"
      }
    ],
    "sg:phone": "+1 419 394 2540",
    "sg:postcode": "45885",
    "sg:province": "OH",
    "sg:tags": [
      "fire",
      "extinguisher"
    ],
    "wof:name": "Lear Fire Equipment Co",
    "wof:placetype": "venue"
  },
  "geometry": {"coordinates":[-84.387814,40.538408],"type":"Point"}
}
