{
  "type": "Feature",
  "properties": {
    "iso:country":"US",
    "sg:address":"430 S Main St",
    "sg:city":"St Marys",
    "sg:classifiers":[
        {
            "category":"Wholesale",
            "subcategory":"Durable Goods & Equipment",
            "type":"Manufacturing & Wholesale Goods"
        }
    ],
    "sg:phone":"+1 419 394 2540",
    "sg:postcode":"45885",
    "sg:province":"OH",
    "sg:tags":[
        "fire",
        "extinguisher"
    ],
    "wof:name":"Lear Fire Equipment Co",
    "wof:placetype":"venue"
},
  "geometry": {"coordinates":[-84.38781400000001,40.538408],"type":"Point"}
}