{
  "type": "Feature",
  "properties": {
    "addr:full": "9223 Russellville-Winchester Rd Winchester OH 45168",
    "addr:housenumber": "9223",
    "addr:postcode": "45168",
    "addr:street": "Russellville-Winchester Rd",
    "iso:country": "US",
    "sg:address": "9223 Russellville-Winchester Rd",
    "sg:city": "Winchester",
    "sg:classifiers": [
      {
        "category": "Autos \u0026 Motor Vehicles",
        "subcategory": "Automobile Sales",
        "type": "Retail Goods"
      }
    ],
    "sg:phone": "+1 937 377 2164",
    "sg:postcode": "45168",
    "sg:province": "OH",
    "wof:name": "Gerald \u0026 Mary Helen Bick",
    "wof:placetype": "venue"
  },
  "geometry": {"coordinates":[-83.72965,38.876024],"type":"Point"}
}
