{
  "type": "Feature",
  "properties": {
    "iso:country":"US",
    "sg:address":"9223 Russellville-Winchester Rd",
    "sg:city":"Winchester",
    "sg:classifiers":[
        {
            "category":"Autos & Motor Vehicles",
            "subcategory":"Automobile Sales",
            "type":"Retail Goods"
        }
    ],
    "sg:phone":"+1 937 377 2164",
    "sg:postcode":"45168",
    "sg:province":"OH",
    "wof:name":"Gerald & Mary Helen Bick",
    "wof:placetype":"venue"
},
  "geometry": {"coordinates":[-83.72965000000001,38.876024],"type":"Point"}
}