{
  "type": "Feature",
  "properties": {
    "addr:full": "2931 Youngstown Rd SE Warren OH 44484",
    "addr:housenumber": "2931",
    "addr:postcode": "44484",
    "addr:street": "Youngstown Rd Se",
    "iso:country": "US",
    "sg:address": "2931 Youngstown Rd SE",
    "sg:city": "Warren",
    "sg:classifiers": [
      {
        "category": "Government",
        "subcategory": "Office",
        "type": "Public Place"
      }
    ],
    "sg:phone": "+1 330 675 2673",
    "sg:postcode": "44484",
    "sg:province": "OH",
    "sg:tags": [
      "educational",
      "program",
      "administrative"
    ],
    "wof:name": "Office of Litter Prevention",
    "wof:placetype": "venue"
  },
  "geometry": {"coordinates":[-80.781877,41.221148],"type":"Point"}
}
