{
  "type": "Feature",
  "properties": {
    "addr:full": "960 State Rte 28 Milford OH 45150",
    "addr:housenumber": "960",
    "addr:postcode": "45150",
    "addr:street": "State Rte 28",
    "iso:country": "US",
    "sg:address": "960 State Rte 28",
    "sg:city": "Milford",
    "sg:classifiers": [
      {
        "category": "Retail",
        "subcategory": "Auto Repair",
        "type": "Services"
      }
    ],
    "sg:phone": "+1 513 831 0616",
    "sg:postcode": "45150",
    "sg:province": "OH",
    "sg:tags": [
      "shop",
      "automotive"
    ],
    "wof:name": "Car-X Muffler \u0026 Brake",
    "wof:placetype": "venue"
  },
  "geometry": {"coordinates":[-84.248352,39.192311],"type":"Point"}
}
