{
  "type": "Feature",
  "properties": {
    "iso:country":"US",
    "sg:address":"960 State Rte 28",
    "sg:city":"Milford",
    "sg:classifiers":[
        {
            "category":"Retail",
            "subcategory":"Auto Repair",
            "type":"Services"
        }
    ],
    "sg:phone":"+1 513 831 0616",
    "sg:postcode":"45150",
    "sg:province":"OH",
    "sg:tags":[
        "shop",
        "automotive"
    ],
    "wof:name":"Car-X Muffler & Brake",
    "wof:placetype":"venue"
},
  "geometry": {"coordinates":[-84.248352,39.192311],"type":"Point"}
}