{
  "type": "Feature",
  "properties": {
    "iso:country":"US",
    "sg:address":"131 Hoak Dr",
    "sg:city":"Fairborn",
    "sg:classifiers":[
        {
            "category":"Building & Trades",
            "subcategory":"Construction",
            "type":"Services"
        }
    ],
    "sg:phone":"+1 937 878 8459",
    "sg:postcode":"45324",
    "sg:province":"OH",
    "sg:tags":[
        "house"
    ],
    "wof:name":"Gayheart Construction Har",
    "wof:placetype":"venue"
},
  "geometry": {"coordinates":[-84.029421,39.79355],"type":"Point"}
}