{
  "type": "Feature",
  "properties": {
    "addr:full": "8081 Saddle Run Powell OH 43065",
    "addr:housenumber": "8081",
    "addr:postcode": "43065",
    "addr:street": "Saddle Run",
    "iso:country": "US",
    "sg:address": "8081 Saddle Run",
    "sg:city": "Powell",
    "sg:classifiers": [
      {
        "category": "Education",
        "subcategory": "School",
        "type": "Public Place"
      }
    ],
    "sg:phone": "+1 614 883 2950",
    "sg:postcode": "43065",
    "sg:province": "OH",
    "sg:website": "www.worthington.k12.oh.us",
    "wof:name": "Liberty Elementary School",
    "wof:placetype": "venue"
  },
  "geometry": {"coordinates":[-83.063074,40.121891],"type":"Point"}
}
