{
  "type": "Feature",
  "properties": {
    "addr:full":"2919 Brandeberry Rd Fostoria OH 44830",
    "addr:housenumber":"2919",
    "addr:postcode":"44830",
    "addr:street":"Brandeberry Rd",
    "iso:country":"US",
    "sg:address":"2919 Brandeberry Rd",
    "sg:city":"Fostoria",
    "sg:phone":"+1 419 435 5086",
    "sg:postcode":"44830",
    "sg:province":"OH",
    "sg:tags":[
        "farm",
        "corn",
        "wheat",
        "soybean"
    ],
    "wof:name":"Paul Dibling",
    "wof:placetype":"venue"
},
  "geometry": {"coordinates":[-83.44709,41.202908],"type":"Point"}
}