{
  "type": "Feature",
  "properties": {
    "iso:country":"US",
    "sg:address":"3939 Valley Rd",
    "sg:city":"Cleveland",
    "sg:classifiers":[
        {
            "category":"Building & Trades",
            "subcategory":"Construction",
            "type":"Services"
        }
    ],
    "sg:phone":"+1 216 661 7723",
    "sg:postcode":"44109",
    "sg:province":"OH",
    "sg:tags":[
        "asphalt",
        "installs",
        "contractor",
        "concrete",
        "paving",
        "build"
    ],
    "wof:name":"Parma Contracting Co",
    "wof:placetype":"venue"
},
  "geometry": {"coordinates":[-81.69110499999999,41.446132],"type":"Point"}
}