{
  "type": "Feature",
  "properties": {
    "addr:full": "1866 Marion-Waldo Rd Marion OH 43302",
    "addr:housenumber": "1866",
    "addr:postcode": "43302",
    "addr:street": "Marion-Waldo Rd",
    "iso:country": "US",
    "sg:address": "1866 Marion-Waldo Rd",
    "sg:city": "Marion",
    "sg:classifiers": [
      {
        "category": "Autos \u0026 Motor Vehicles",
        "subcategory": "Automobile Sales",
        "type": "Retail Goods"
      }
    ],
    "sg:phone": "+1 740 389 2341",
    "sg:postcode": "43302",
    "sg:province": "OH",
    "sg:tags": [
      "passenger",
      "general",
      "dealer",
      "car",
      "repair"
    ],
    "wof:name": "Mathews Dodge Chrysler Jeep",
    "wof:placetype": "venue"
  },
  "geometry": {"coordinates":[-83.115481,40.553406],"type":"Point"}
}
