{
  "type": "Feature",
  "properties": {
    "addr:full":"423 S Plum St Troy OH 45373",
    "addr:housenumber":"423",
    "addr:postcode":"45373",
    "addr:street":"S Plum St",
    "iso:country":"US",
    "sg:address":"423 S Plum St",
    "sg:city":"Troy",
    "sg:classifiers":[
        {
            "category":"Shopping",
            "subcategory":"Gifts & Souvenirs",
            "type":"Retail Goods"
        }
    ],
    "sg:phone":"+1 937 339 2952",
    "sg:postcode":"45373",
    "sg:province":"OH",
    "sg:tags":[
        "shop"
    ],
    "wof:name":"K & J Gift & Assoc",
    "wof:placetype":"venue"
},
  "geometry": {"coordinates":[-84.20865999999999,40.035767],"type":"Point"}
}