{
  "type": "Feature",
  "properties": {
    "addr:full": "12222 Williams St Perrysburg OH 43551",
    "addr:housenumber": "12222",
    "addr:postcode": "43551",
    "addr:street": "Williams St",
    "iso:country": "US",
    "sg:address": "12222 Williams St",
    "sg:city": "Perrysburg",
    "sg:classifiers": [
      {
        "category": "Retail",
        "subcategory": "Auto Rental",
        "type": "Services"
      }
    ],
    "sg:phone": "+1 419 873 8611",
    "sg:postcode": "43551",
    "sg:province": "OH",
    "sg:tags": [
      "truck"
    ],
    "wof:name": "Penske",
    "wof:placetype": "venue"
  },
  "geometry": {"coordinates":[-83.629855,41.527848],"type":"Point"}
}
