{
  "type": "Feature",
  "properties": {
    "iso:country":"US",
    "sg:address":"4119 Nevada Ave",
    "sg:city":"Dayton",
    "sg:classifiers":[
        {
            "category":"Utilities",
            "subcategory":"Refuse",
            "type":"Services"
        }
    ],
    "sg:phone":"+1 937 274 9986",
    "sg:postcode":"45416",
    "sg:province":"OH",
    "sg:tags":[
        "garbage",
        "collection"
    ],
    "wof:name":"Plant Priority Svc Inc",
    "wof:placetype":"venue"
},
  "geometry": {"coordinates":[-84.26644400000001,39.802611],"type":"Point"}
}