{
  "type": "Feature",
  "properties": {
    "addr:full":"325 S Stone St Fremont OH 43420",
    "addr:housenumber":"325",
    "addr:postcode":"43420",
    "addr:street":"S Stone St",
    "iso:country":"US",
    "sg:address":"325 S Stone St",
    "sg:city":"Fremont",
    "sg:classifiers":[
        {
            "category":"Manufacturing",
            "subcategory":"Glass & Minerals",
            "type":"Manufacturing & Wholesale Goods"
        }
    ],
    "sg:phone":"+1 419 435 0844",
    "sg:postcode":"43420",
    "sg:province":"OH",
    "sg:tags":[
        "concrete",
        "product",
        "mfg"
    ],
    "wof:name":"Seneca Precast Co",
    "wof:placetype":"venue"
},
  "geometry": {"coordinates":[-83.13648000000001,41.343979],"type":"Point"}
}