{
  "type": "Feature",
  "properties": {
    "iso:country":"US",
    "sg:address":"989 Joyce Dr",
    "sg:city":"Batavia",
    "sg:classifiers":[
        {
            "category":"Building & Trades",
            "subcategory":"Construction",
            "type":"Services"
        }
    ],
    "sg:phone":"+1 513 553 1327",
    "sg:postcode":"45103",
    "sg:province":"OH",
    "sg:tags":[
        "hanging",
        "contractor"
    ],
    "wof:name":"Adament Designers Painting",
    "wof:placetype":"venue"
},
  "geometry": {"coordinates":[-84.25849100000001,39.094741],"type":"Point"}
}