{
  "type": "Feature",
  "properties": {
    "iso:country":"US",
    "sg:address":"6659 State Rte 734",
    "sg:city":"Jamestown",
    "sg:classifiers":[
        {
            "category":"Freight",
            "type":"Transportation"
        }
    ],
    "sg:phone":"+1 937 675 2884",
    "sg:postcode":"45335",
    "sg:province":"OH",
    "sg:tags":[
        "operator",
        "local",
        "trucking"
    ],
    "wof:name":"B&N Woods Trucking LLC",
    "wof:placetype":"venue"
},
  "geometry": {"coordinates":[-83.691289,39.655453],"type":"Point"}
}