{
  "type": "Feature",
  "properties": {
    "addr:full": "905 E Columbus St Kenton OH 43326",
    "addr:housenumber": "905",
    "addr:postcode": "43326",
    "addr:street": "E Columbus St",
    "iso:country": "US",
    "sg:address": "905 E Columbus St",
    "sg:city": "Kenton",
    "sg:classifiers": [
      {
        "category": "Building \u0026 Trades",
        "subcategory": "Equipment Rental",
        "type": "Services"
      }
    ],
    "sg:phone": "+1 419 673 2222",
    "sg:postcode": "43326",
    "sg:province": "OH",
    "sg:tags": [
      "leasing",
      "furniture"
    ],
    "wof:name": "Showplace Rent To Own Inc",
    "wof:placetype": "venue"
  },
  "geometry": {"coordinates":[-83.590763,40.652213],"type":"Point"}
}
