{
  "type": "Feature",
  "properties": {
    "addr:full":"10523 Mahoning Ave North Jackson OH 44451",
    "addr:housenumber":"10523",
    "addr:postcode":"44451",
    "addr:street":"Mahoning Ave North",
    "iso:country":"US",
    "sg:address":"10523 Mahoning Ave",
    "sg:city":"North Jackson",
    "sg:classifiers":[
        {
            "category":"Building & Trades",
            "subcategory":"Construction",
            "type":"Services"
        }
    ],
    "sg:phone":"+1 330 538 2244",
    "sg:postcode":"44451",
    "sg:province":"OH",
    "sg:tags":[
        "concrete",
        "contractor"
    ],
    "wof:name":"Jackson Concrete Inc",
    "wof:placetype":"venue"
},
  "geometry": {"coordinates":[-80.849373,41.100129],"type":"Point"}
}