{
  "type": "Feature",
  "properties": {
    "addr:full":"1020 Leesburg Ave Washington Ct Hs OH 43160",
    "addr:housenumber":"1020",
    "addr:postcode":"43160",
    "addr:street":"Leesburg Ave Washington Ct",
    "iso:country":"US",
    "sg:address":"1020 Leesburg Ave",
    "sg:city":"Washington Ct Hs",
    "sg:classifiers":[
        {
            "category":"Manufacturing",
            "subcategory":"Printing",
            "type":"Manufacturing & Wholesale Goods"
        }
    ],
    "sg:phone":"+1 740 335 8030",
    "sg:postcode":"43160",
    "sg:province":"OH",
    "sg:tags":[
        "newspaper",
        "commercial"
    ],
    "wof:name":"Print Shop",
    "wof:placetype":"venue"
},
  "geometry": {"coordinates":[-83.451021,39.529053],"type":"Point"}
}