{
  "type": "Feature",
  "properties": {
    "addr:full":"9123 Primrose Dr Loveland OH 45140",
    "addr:housenumber":"9123",
    "addr:postcode":"45140",
    "addr:street":"Primrose Dr",
    "iso:country":"US",
    "sg:address":"9123 Primrose Dr",
    "sg:city":"Loveland",
    "sg:classifiers":[
        {
            "category":"Building & Trades",
            "subcategory":"Construction",
            "type":"Services"
        }
    ],
    "sg:phone":"+1 513 683 0358",
    "sg:postcode":"45140",
    "sg:province":"OH",
    "sg:tags":[
        "contractor",
        "product",
        "wood",
        "carpentry",
        "mfg"
    ],
    "wof:name":"Meyer Matthew Interior Wdwkg",
    "wof:placetype":"venue"
},
  "geometry": {"coordinates":[-84.263025,39.302506],"type":"Point"}
}