{
  "type": "Feature",
  "properties": {
    "addr:full":"8745 Factory Shops Blvd Jeffersonville OH 43128",
    "addr:housenumber":"8745",
    "addr:postcode":"43128",
    "addr:street":"Factory Shops Blvd",
    "iso:country":"US",
    "sg:address":"8745 Factory Shops Blvd",
    "sg:city":"Jeffersonville",
    "sg:classifiers":[
        {
            "category":"Shopping",
            "subcategory":"Clothing, Apparel, & Fashions",
            "type":"Retail Goods"
        }
    ],
    "sg:phone":"+1 740 948 2662",
    "sg:postcode":"43128",
    "sg:province":"OH",
    "sg:tags":[
        "infant",
        "wear"
    ],
    "sg:website":"www.childrensplace.com",
    "wof:name":"Children's Place",
    "wof:placetype":"venue"
},
  "geometry": {"coordinates":[-83.60202099999999,39.617092],"type":"Point"}
}