{
  "type": "Feature",
  "properties": {
    "addr:full": "1602 Race St Cincinnati OH 45202",
    "addr:housenumber": "1602",
    "addr:postcode": "45202",
    "addr:street": "Race St",
    "iso:country": "US",
    "sg:address": "1602 Race St",
    "sg:city": "Cincinnati",
    "sg:classifiers": [
      {
        "category": "Professional",
        "subcategory": "Management \u0026 Consulting",
        "type": "Services"
      }
    ],
    "sg:phone": "+1 513 768 8870",
    "sg:postcode": "45202",
    "sg:province": "OH",
    "sg:tags": [
      "consultant",
      "business"
    ],
    "wof:name": "Liberty Management",
    "wof:placetype": "venue"
  },
  "geometry": {"coordinates":[-84.517755,39.113774],"type":"Point"}
}
