{
  "type": "Feature",
  "properties": {
    "iso:country":"US",
    "sg:address":"3991 State Rte 20",
    "sg:city":"Collins",
    "sg:classifiers":[
        {
            "category":"Freight",
            "type":"Transportation"
        }
    ],
    "sg:phone":"+1 419 663 5823",
    "sg:postcode":"44826",
    "sg:province":"OH",
    "sg:tags":[
        "operator",
        "local",
        "trucking"
    ],
    "wof:name":"Wacker Trucking",
    "wof:placetype":"venue"
},
  "geometry": {"coordinates":[-82.446239,41.247111],"type":"Point"}
}