{
  "type": "Feature",
  "properties": {
    "addr:full":"1986 Cleveland Ave Columbus OH 43211",
    "addr:housenumber":"1986",
    "addr:postcode":"43211",
    "addr:street":"Cleveland Ave",
    "iso:country":"US",
    "sg:address":"1986 Cleveland Ave",
    "sg:city":"Columbus",
    "sg:classifiers":[
        {
            "category":"Professional",
            "subcategory":"Business Services",
            "type":"Services"
        }
    ],
    "sg:phone":"+1 614 297 0935",
    "sg:postcode":"43211",
    "sg:province":"OH",
    "wof:name":"Peggy's Monogramming",
    "wof:placetype":"venue"
},
  "geometry": {"coordinates":[-82.97172,40.00628],"type":"Point"}
}