{
  "type": "Feature",
  "properties": {
    "addr:full": "848 E Franklin St Dayton OH 45459",
    "addr:housenumber": "848",
    "addr:postcode": "45459",
    "addr:street": "E Franklin St",
    "iso:country": "US",
    "sg:address": "848 E Franklin St",
    "sg:city": "Dayton",
    "sg:classifiers": [
      {
        "category": "Professional",
        "subcategory": "Employment Agencies",
        "type": "Services"
      }
    ],
    "sg:phone": "+1 937 434 8470",
    "sg:postcode": "45459",
    "sg:province": "OH",
    "sg:tags": [
      "opportunity"
    ],
    "wof:name": "Affinity Search Group",
    "wof:placetype": "venue"
  },
  "geometry": {"coordinates":[-84.142872,39.628491],"type":"Point"}
}
