{
  "type": "Feature",
  "properties": {
    "iso:country":"US",
    "sg:address":"1921 W 65th St",
    "sg:city":"Cleveland",
    "sg:classifiers":[
        {
            "category":"Food & Beverages",
            "subcategory":"Specialty",
            "type":"Retail Goods"
        }
    ],
    "sg:phone":"+1 216 281 6695",
    "sg:postcode":"44102",
    "sg:province":"OH",
    "wof:name":"Great Lakes Nutrition",
    "wof:placetype":"venue"
},
  "geometry": {"coordinates":[-81.730174,41.479583],"type":"Point"}
}