{
  "type": "Feature",
  "properties": {
    "addr:full":"1921 W 65th St Cleveland OH 44102",
    "addr:housenumber":"1921",
    "addr:postcode":"44102",
    "addr:street":"W 65Th St",
    "iso:country":"US",
    "sg:address":"1921 W 65th St",
    "sg:city":"Cleveland",
    "sg:classifiers":[
        {
            "category":"Food & Beverages",
            "subcategory":"Specialty",
            "type":"Retail Goods"
        }
    ],
    "sg:phone":"+1 216 281 6695",
    "sg:postcode":"44102",
    "sg:province":"OH",
    "wof:name":"Great Lakes Nutrition",
    "wof:placetype":"venue"
},
  "geometry": {"coordinates":[-81.73017400000001,41.479583],"type":"Point"}
}