{
  "type": "Feature",
  "properties": {
    "addr:full": "1676 Cascade Dr Marion OH 43302",
    "addr:housenumber": "1676",
    "addr:postcode": "43302",
    "addr:street": "Cascade Dr",
    "iso:country": "US",
    "sg:address": "1676 Cascade Dr",
    "sg:city": "Marion",
    "sg:classifiers": [
      {
        "category": "Manufacturing",
        "subcategory": "Tools \u0026 Machinery",
        "type": "Manufacturing \u0026 Wholesale Goods"
      }
    ],
    "sg:phone": "+1 740 223 1695",
    "sg:postcode": "43302",
    "sg:province": "OH",
    "sg:tags": [
      "machine",
      "shop"
    ],
    "wof:name": "Turbo Parts",
    "wof:placetype": "venue"
  },
  "geometry": {"coordinates":[-83.088807,40.615824],"type":"Point"}
}
