{
  "type": "Feature",
  "properties": {
    "iso:country":"US",
    "sg:address":"1676 Cascade Dr",
    "sg:city":"Marion",
    "sg:classifiers":[
        {
            "category":"Manufacturing",
            "subcategory":"Tools & Machinery",
            "type":"Manufacturing & Wholesale Goods"
        }
    ],
    "sg:phone":"+1 740 223 1695",
    "sg:postcode":"43302",
    "sg:province":"OH",
    "sg:tags":[
        "machine",
        "shop"
    ],
    "wof:name":"Turbo Parts",
    "wof:placetype":"venue"
},
  "geometry": {"coordinates":[-83.088807,40.615824],"type":"Point"}
}