{
  "type": "Feature",
  "properties": {
    "iso:country":"US",
    "sg:address":"9000 Saltcoats Ct",
    "sg:city":"Dublin",
    "sg:classifiers":[
        {
            "category":"Insurance",
            "subcategory":"Insurance Agent",
            "type":"Services"
        }
    ],
    "sg:phone":"+1 614 932 9811",
    "sg:postcode":"43017",
    "sg:province":"OH",
    "wof:name":"LDW Insurance",
    "wof:placetype":"venue"
},
  "geometry": {"coordinates":[-83.148617,40.148036],"type":"Point"}
}