{
  "type": "Feature",
  "properties": {
    "iso:country":"US",
    "sg:address":"461 E Pike St",
    "sg:city":"Morrow",
    "sg:classifiers":[
        {
            "category":"Building & Trades",
            "subcategory":"Plumbing",
            "type":"Services"
        }
    ],
    "sg:phone":"+1 513 899 9002",
    "sg:postcode":"45152",
    "sg:province":"OH",
    "sg:tags":[
        "contractor"
    ],
    "wof:name":"Air Tech",
    "wof:placetype":"venue"
},
  "geometry": {"coordinates":[-84.121264,39.356167],"type":"Point"}
}