{
  "type": "Feature",
  "properties": {
    "addr:full":"166 Park Ave W Mansfield OH 44902",
    "addr:housenumber":"166",
    "addr:postcode":"44902",
    "addr:street":"Park Ave W",
    "iso:country":"US",
    "sg:address":"166 Park Ave W",
    "sg:city":"Mansfield",
    "sg:classifiers":[
        {
            "category":"Insurance",
            "subcategory":"Insurance Agent",
            "type":"Services"
        }
    ],
    "sg:phone":"+1 419 525 1181",
    "sg:postcode":"44902",
    "sg:province":"OH",
    "wof:name":"Richard Weemhoff Agency",
    "wof:placetype":"venue"
},
  "geometry": {"coordinates":[-82.522881,40.758948],"type":"Point"}
}