{
  "type": "Feature",
  "properties": {
    "iso:country":"US",
    "sg:address":"10422 Eaton Pike",
    "sg:city":"New Lebanon",
    "sg:classifiers":[
        {
            "category":"Autos & Motor Vehicles",
            "subcategory":"Automobile Sales",
            "type":"Retail Goods"
        }
    ],
    "sg:phone":"+1 937 687 4050",
    "sg:postcode":"45345",
    "sg:province":"OH",
    "sg:tags":[
        "used"
    ],
    "wof:name":"R & S Auto Sales",
    "wof:placetype":"venue"
},
  "geometry": {"coordinates":[-84.373135,39.745659],"type":"Point"}
}