{
  "type": "Feature",
  "properties": {
    "addr:full": "267 Bowman Ct London OH 43140",
    "addr:housenumber": "267",
    "addr:postcode": "43140",
    "addr:street": "Bowman Ct",
    "iso:country": "US",
    "sg:address": "267 Bowman Ct",
    "sg:city": "London",
    "sg:classifiers": [
      {
        "category": "Real Estate",
        "subcategory": "Real Estate Operator",
        "type": "Services"
      }
    ],
    "sg:phone": "+1 740 852 2721",
    "sg:postcode": "43140",
    "sg:province": "OH",
    "sg:tags": [
      "apartment"
    ],
    "wof:name": "Londonerry Limited Apartments",
    "wof:placetype": "venue"
  },
  "geometry": {"coordinates":[-83.455585,39.876695],"type":"Point"}
}
