{
  "type": "Feature",
  "properties": {
    "addr:full":"1330 Stimmel Rd Columbus OH 43223",
    "addr:housenumber":"1330",
    "addr:postcode":"43223",
    "addr:street":"Stimmel Rd",
    "iso:country":"US",
    "sg:address":"1330 Stimmel Rd",
    "sg:city":"Columbus",
    "sg:classifiers":[
        {
            "category":"Wholesale",
            "subcategory":"Electrical",
            "type":"Manufacturing & Wholesale Goods"
        }
    ],
    "sg:phone":"+1 614 276 5552",
    "sg:postcode":"43223",
    "sg:province":"OH",
    "sg:tags":[
        "repair",
        "radio",
        "install",
        "equipment"
    ],
    "sg:website":"www.bccomm.biz",
    "wof:name":"B & C Communications",
    "wof:placetype":"venue"
},
  "geometry": {"coordinates":[-83.021846,39.936308],"type":"Point"}
}