{
  "type": "Feature",
  "properties": {
    "addr:full":"1030 Old Henderson Rd Columbus OH 43220",
    "addr:housenumber":"1030",
    "addr:postcode":"43220",
    "addr:street":"Old Henderson Rd",
    "iso:country":"US",
    "sg:address":"1030 Old Henderson Rd",
    "sg:city":"Columbus",
    "sg:classifiers":[
        {
            "category":"Home & Garden",
            "subcategory":"Building Materials",
            "type":"Retail Goods"
        }
    ],
    "sg:phone":"+1 614 457 3619",
    "sg:postcode":"43220",
    "sg:province":"OH",
    "wof:name":"Speedy Auto Glass",
    "wof:placetype":"venue"
},
  "geometry": {"coordinates":[-83.049263,40.051604],"type":"Point"}
}