{
  "type": "Feature",
  "properties": {
    "addr:full":"203 N Main St Bowling Green OH 43402",
    "addr:housenumber":"203",
    "addr:postcode":"43402",
    "addr:street":"N Main St",
    "iso:country":"US",
    "sg:address":"203 N Main St",
    "sg:city":"Bowling Green",
    "sg:classifiers":[
        {
            "category":"Restaurant",
            "type":"Food & Drink"
        }
    ],
    "sg:menulink":"http://www.allmenus.com/oh/bowling-green/17874-pisanellos-pizza/menu/",
    "sg:phone":"+1 419 352 5166",
    "sg:postcode":"43402",
    "sg:province":"OH",
    "sg:tags":[
        "american",
        "pizza"
    ],
    "wof:name":"Pisanello's Pizza",
    "wof:placetype":"venue"
},
  "geometry": {"coordinates":[-83.65042,41.375945],"type":"Point"}
}