{
  "type": "Feature",
  "properties": {
    "iso:country":"US",
    "sg:address":"7471 Hetzler Rd",
    "sg:city":"Middletown",
    "sg:classifiers":[
        {
            "category":"Building & Trades",
            "subcategory":"Construction",
            "type":"Services"
        }
    ],
    "sg:phone":"+1 513 422 2507",
    "sg:postcode":"45042",
    "sg:province":"OH",
    "sg:tags":[
        "concrete",
        "contractor"
    ],
    "wof:name":"Mc Monigle Foundation Inc",
    "wof:placetype":"venue"
},
  "geometry": {"coordinates":[-84.425282,39.574632],"type":"Point"}
}