{
  "type": "Feature",
  "properties": {
    "addr:full": "7471 Hetzler Rd Middletown OH 45042",
    "addr:housenumber": "7471",
    "addr:postcode": "45042",
    "addr:street": "Hetzler Rd",
    "iso:country": "US",
    "sg:address": "7471 Hetzler Rd",
    "sg:city": "Middletown",
    "sg:classifiers": [
      {
        "category": "Building \u0026 Trades",
        "subcategory": "Construction",
        "type": "Services"
      }
    ],
    "sg:phone": "+1 513 422 2507",
    "sg:postcode": "45042",
    "sg:province": "OH",
    "sg:tags": [
      "concrete",
      "contractor"
    ],
    "wof:name": "Mc Monigle Foundation Inc",
    "wof:placetype": "venue"
  },
  "geometry": {"coordinates":[-84.425282,39.574632],"type":"Point"}
}
