{
  "type": "Feature",
  "properties": {
    "iso:country":"US",
    "sg:address":"5230 Detroit Rd",
    "sg:city":"Elyria",
    "sg:classifiers":[
        {
            "category":"Autos & Motor Vehicles",
            "subcategory":"Fuel & Gas Station",
            "type":"Retail Goods"
        }
    ],
    "sg:phone":"+1 440 365 3461",
    "sg:postcode":"44035",
    "sg:province":"OH",
    "sg:tags":[
        "station",
        "gasoline"
    ],
    "wof:name":"Speedway Superamerica LLC",
    "wof:placetype":"venue"
},
  "geometry": {"coordinates":[-82.080234,41.425139],"type":"Point"}
}