{
  "type": "Feature",
  "properties": {
    "addr:full": "2138 N 4th St Columbus OH 43201",
    "addr:housenumber": "2138",
    "addr:postcode": "43201",
    "addr:street": "N 4Th St",
    "iso:country": "US",
    "sg:address": "2138 N 4th St",
    "sg:city": "Columbus",
    "sg:classifiers": [
      {
        "category": "Professional",
        "subcategory": "Management \u0026 Consulting",
        "type": "Services"
      }
    ],
    "sg:phone": "+1 614 298 0225",
    "sg:postcode": "43201",
    "sg:province": "OH",
    "wof:name": "Stelling Group",
    "wof:placetype": "venue"
  },
  "geometry": {"coordinates":[-82.998164,40.00703],"type":"Point"}
}
