{
  "type": "Feature",
  "properties": {
    "iso:country":"US",
    "sg:address":"25574 Bagley Rd",
    "sg:city":"Cleveland",
    "sg:classifiers":[
        {
            "category":"Shopping",
            "subcategory":"Hobbies, Toys, & Games",
            "type":"Retail Goods"
        }
    ],
    "sg:phone":"+1 440 235 4777",
    "sg:postcode":"44138",
    "sg:province":"OH",
    "sg:tags":[
        "model",
        "supply"
    ],
    "wof:name":"Grand Pacific Junction Model",
    "wof:placetype":"venue"
},
  "geometry": {"coordinates":[-81.90266200000001,41.372817],"type":"Point"}
}