{
  "type": "Feature",
  "properties": {
    "addr:full": "621 Cleveland Ave Amherst OH 44001",
    "addr:housenumber": "621",
    "addr:postcode": "44001",
    "addr:street": "Cleveland Ave",
    "iso:country": "US",
    "sg:address": "621 Cleveland Ave",
    "sg:city": "Amherst",
    "sg:classifiers": [
      {
        "category": "Government",
        "subcategory": "Office",
        "type": "Public Place"
      }
    ],
    "sg:phone": "+1 440 988 2817",
    "sg:postcode": "44001",
    "sg:province": "OH",
    "sg:tags": [
      "city",
      "resource",
      "human"
    ],
    "wof:name": "Amherst Area Office On Aging",
    "wof:placetype": "venue"
  },
  "geometry": {"coordinates":[-82.220608,41.4012],"type":"Point"}
}
