{
  "type": "Feature",
  "properties": {
    "iso:country":"US",
    "sg:address":"2035 Benton St SE",
    "sg:city":"Warren",
    "sg:classifiers":[
        {
            "category":"Real Estate",
            "subcategory":"Real Estate Operator",
            "type":"Services"
        }
    ],
    "sg:phone":"+1 330 369 4171",
    "sg:postcode":"44484",
    "sg:province":"OH",
    "sg:tags":[
        "apartment"
    ],
    "wof:name":"Draper Street Apartments",
    "wof:placetype":"venue"
},
  "geometry": {"coordinates":[-80.79378,41.214681],"type":"Point"}
}