{
  "type": "Feature",
  "properties": {
    "addr:full":"44091 Stang Rd Elyria OH 44035",
    "addr:housenumber":"44091",
    "addr:postcode":"44035",
    "addr:street":"Stang Rd",
    "iso:country":"US",
    "sg:address":"44091 Stang Rd",
    "sg:city":"Elyria",
    "sg:classifiers":[
        {
            "category":"Building & Trades",
            "subcategory":"Plumbing",
            "type":"Services"
        }
    ],
    "sg:phone":"+1 440 984 2937",
    "sg:postcode":"44035",
    "sg:province":"OH",
    "sg:tags":[
        "contractor"
    ],
    "wof:name":"Professional Irrigation Svcs",
    "wof:placetype":"venue"
},
  "geometry": {"coordinates":[-82.173064,41.391017],"type":"Point"}
}