{
  "type": "Feature",
  "properties": {
    "addr:full":"5929 Britton Pkwy Dublin OH 43016",
    "addr:housenumber":"5929",
    "addr:postcode":"43016",
    "addr:street":"Britton Pkwy",
    "iso:country":"US",
    "sg:address":"5929 Britton Pkwy",
    "sg:city":"Dublin",
    "sg:classifiers":[
        {
            "category":"Wholesale",
            "subcategory":"Home Furnishings",
            "type":"Manufacturing & Wholesale Goods"
        }
    ],
    "sg:phone":"+1 614 760 2550",
    "sg:postcode":"43016",
    "sg:province":"OH",
    "sg:website":"www.thomasville.com",
    "wof:name":"Thomasville Home Furnishings",
    "wof:placetype":"venue"
},
  "geometry": {"coordinates":[-83.140125,40.074859],"type":"Point"}
}