{
  "type": "Feature",
  "properties": {
    "addr:full":"321 Riley St Celina OH 45822",
    "addr:housenumber":"321",
    "addr:postcode":"45822",
    "addr:street":"Riley St",
    "iso:country":"US",
    "sg:address":"321 Riley St",
    "sg:city":"Celina",
    "sg:classifiers":[
        {
            "category":"Government",
            "subcategory":"Office",
            "type":"Public Place"
        }
    ],
    "sg:phone":"+1 419 586 7759",
    "sg:postcode":"45822",
    "sg:province":"OH",
    "wof:name":"Mercer Engineer's Office",
    "wof:placetype":"venue"
},
  "geometry": {"coordinates":[-84.580833,40.549712],"type":"Point"}
}