{
  "type": "Feature",
  "properties": {
    "addr:full":"1106 Race St Cincinnati OH 45202",
    "addr:housenumber":"1106",
    "addr:postcode":"45202",
    "addr:street":"Race St",
    "iso:country":"US",
    "sg:address":"1106 Race St",
    "sg:city":"Cincinnati",
    "sg:classifiers":[
        {
            "category":"Real Estate",
            "subcategory":"Architect",
            "type":"Services"
        }
    ],
    "sg:phone":"+1 513 651 3484",
    "sg:postcode":"45202",
    "sg:province":"OH",
    "wof:name":"Kaneta Robinson",
    "wof:placetype":"venue"
},
  "geometry": {"coordinates":[-84.5163,39.108003],"type":"Point"}
}