{
  "type": "Feature",
  "properties": {
    "addr:full":"802 W Alexis Rd Toledo OH 43612",
    "addr:housenumber":"802",
    "addr:postcode":"43612",
    "addr:street":"W Alexis Rd",
    "iso:country":"US",
    "sg:address":"802 W Alexis Rd",
    "sg:city":"Toledo",
    "sg:classifiers":[
        {
            "category":"Wholesale",
            "subcategory":"Chemicals & Plastics",
            "type":"Manufacturing & Wholesale Goods"
        }
    ],
    "sg:phone":"+1 419 382 3611",
    "sg:postcode":"43612",
    "sg:province":"OH",
    "sg:tags":[
        "oxygen"
    ],
    "wof:name":"MTB Oxygen & Equiopment",
    "wof:placetype":"venue"
},
  "geometry": {"coordinates":[-83.566473,41.721652],"type":"Point"}
}