{
  "type": "Feature",
  "properties": {
    "addr:full": "3107 Gilbert Ave Cincinnati OH 45206",
    "addr:housenumber": "3107",
    "addr:postcode": "45206",
    "addr:street": "Gilbert Ave",
    "iso:country": "US",
    "sg:address": "3107 Gilbert Ave",
    "sg:city": "Cincinnati",
    "sg:classifiers": [
      {
        "category": "Retail",
        "subcategory": "Auto Repair",
        "type": "Services"
      }
    ],
    "sg:phone": "+1 513 861 3362",
    "sg:postcode": "45206",
    "sg:province": "OH",
    "sg:tags": [
      "wrecker"
    ],
    "wof:name": "Efficient Express Motion",
    "wof:placetype": "venue"
  },
  "geometry": {"coordinates":[-84.481774,39.137886],"type":"Point"}
}
