{
  "type": "Feature",
  "properties": {
    "addr:full":"125 Kreiner Ave Akron OH 44312",
    "addr:housenumber":"125",
    "addr:postcode":"44312",
    "addr:street":"Kreiner Ave",
    "iso:country":"US",
    "sg:address":"125 Kreiner Ave",
    "sg:city":"Akron",
    "sg:classifiers":[
        {
            "category":"Building & Trades",
            "subcategory":"Construction",
            "type":"Services"
        }
    ],
    "sg:phone":"+1 330 628 0319",
    "sg:postcode":"44312",
    "sg:province":"OH",
    "sg:tags":[
        "hanging",
        "contractor"
    ],
    "wof:name":"Ld Painting",
    "wof:placetype":"venue"
},
  "geometry": {"coordinates":[-81.421881,41.050539],"type":"Point"}
}