{
  "type": "Feature",
  "properties": {
    "addr:full":"224 Dewey Ave Cambridge OH 43725",
    "addr:housenumber":"224",
    "addr:postcode":"43725",
    "addr:street":"Dewey Ave",
    "iso:country":"US",
    "sg:address":"224 Dewey Ave",
    "sg:city":"Cambridge",
    "sg:classifiers":[
        {
            "category":"Banks & Credit Unions",
            "subcategory":"Bank",
            "type":"Services"
        }
    ],
    "sg:phone":"+1 740 439 0000",
    "sg:postcode":"43725",
    "sg:province":"OH",
    "sg:tags":[
        "loan"
    ],
    "wof:name":"Urgentcash",
    "wof:placetype":"venue"
},
  "geometry": {"coordinates":[-81.5967,40.023683],"type":"Point"}
}