{
  "type": "Feature",
  "properties": {
    "addr:full":"9462 Bruce Dr Franklin OH 45005",
    "addr:housenumber":"9462",
    "addr:postcode":"45005",
    "addr:street":"Bruce Dr",
    "iso:country":"US",
    "sg:address":"9462 Bruce Dr",
    "sg:city":"Franklin",
    "sg:classifiers":[
        {
            "category":"Wholesale",
            "subcategory":"Construction Materials",
            "type":"Manufacturing & Wholesale Goods"
        }
    ],
    "sg:phone":"+1 937 901 7640",
    "sg:postcode":"45005",
    "sg:province":"OH",
    "sg:tags":[
        "fence"
    ],
    "wof:name":"Dalton Fence",
    "wof:placetype":"venue"
},
  "geometry": {"coordinates":[-84.260823,39.579838],"type":"Point"}
}