{
  "type": "Feature",
  "properties": {
    "addr:full": "1290 W 6th St Cleveland OH 44113",
    "addr:housenumber": "1290",
    "addr:postcode": "44113",
    "addr:street": "W 6Th St",
    "iso:country": "US",
    "sg:address": "1290 W 6th St",
    "sg:city": "Cleveland",
    "sg:classifiers": [
      {
        "category": "Restaurant",
        "type": "Food \u0026 Drink"
      }
    ],
    "sg:phone": "+1 216 523 7070",
    "sg:postcode": "44113",
    "sg:province": "OH",
    "sg:tags": [
      "eating"
    ],
    "wof:name": "Panini Bar \u0026 Grill",
    "wof:placetype": "venue"
  },
  "geometry": {"coordinates":[-81.699069,41.50027],"type":"Point"}
}
