{
  "type": "Feature",
  "properties": {
    "addr:full": "1089 E Tallmadge Ave Akron OH 44310",
    "addr:housenumber": "1089",
    "addr:postcode": "44310",
    "addr:street": "E Tallmadge Ave",
    "iso:country": "US",
    "sg:address": "1089 E Tallmadge Ave",
    "sg:city": "Akron",
    "sg:classifiers": [
      {
        "category": "Health Services",
        "subcategory": "Health Practitioner",
        "type": "Services"
      }
    ],
    "sg:phone": "+1 330 634 1089",
    "sg:postcode": "44310",
    "sg:province": "OH",
    "sg:tags": [
      "nutritionist"
    ],
    "wof:name": "TKO Inc",
    "wof:placetype": "venue"
  },
  "geometry": {"coordinates":[-81.476645,41.102121],"type":"Point"}
}
