{
  "type": "Feature",
  "properties": {
    "addr:full":"12045 Johnstown-Utica Rd NW Johnstown OH 43031",
    "addr:housenumber":"12045",
    "addr:postcode":"43031",
    "addr:street":"Johnstown-Utica Rd Nw",
    "iso:country":"US",
    "sg:address":"12045 Johnstown-Utica Rd NW",
    "sg:city":"Johnstown",
    "sg:classifiers":[
        {
            "category":"Retail",
            "subcategory":"Auto Repair",
            "type":"Services"
        }
    ],
    "sg:phone":"+1 740 967 2218",
    "sg:postcode":"43031",
    "sg:province":"OH",
    "sg:tags":[
        "transmission"
    ],
    "wof:name":"Hard Shift Transmissions",
    "wof:placetype":"venue"
},
  "geometry": {"coordinates":[-82.705476,40.145421],"type":"Point"}
}