{
  "type": "Feature",
  "properties": {
    "addr:full":"5188 Longrifle Ct Westerville OH 43081",
    "addr:housenumber":"5188",
    "addr:postcode":"43081",
    "addr:street":"Longrifle Ct",
    "iso:country":"US",
    "sg:address":"5188 Longrifle Ct",
    "sg:city":"Westerville",
    "sg:classifiers":[
        {
            "category":"Building & Trades",
            "subcategory":"Construction",
            "type":"Services"
        }
    ],
    "sg:phone":"+1 614 891 1017",
    "sg:postcode":"43081",
    "sg:province":"OH",
    "sg:tags":[
        "house"
    ],
    "wof:name":"NC Construction Co",
    "wof:placetype":"venue"
},
  "geometry": {"coordinates":[-82.883353,40.08173],"type":"Point"}
}