{
  "type": "Feature",
  "properties": {
    "addr:full": "2659 Beulah Rd Columbus OH 43211",
    "addr:housenumber": "2659",
    "addr:postcode": "43211",
    "addr:street": "Beulah Rd",
    "iso:country": "US",
    "sg:address": "2659 Beulah Rd",
    "sg:city": "Columbus",
    "sg:classifiers": [
      {
        "category": "Building \u0026 Trades",
        "subcategory": "Construction",
        "type": "Services"
      }
    ],
    "sg:phone": "+1 614 268 9555",
    "sg:postcode": "43211",
    "sg:province": "OH",
    "sg:tags": [
      "painting",
      "contractor"
    ],
    "wof:name": "Debellis Painting Service Co",
    "wof:placetype": "venue"
  },
  "geometry": {"coordinates":[-82.994208,40.019799],"type":"Point"}
}
