{
  "type": "Feature",
  "properties": {
    "addr:full": "1290 Grandview Ave Columbus OH 43212",
    "addr:housenumber": "1290",
    "addr:postcode": "43212",
    "addr:street": "Grandview Ave",
    "iso:country": "US",
    "sg:address": "1290 Grandview Ave",
    "sg:city": "Columbus",
    "sg:classifiers": [
      {
        "category": "Professional",
        "subcategory": "Management \u0026 Consulting",
        "type": "Services"
      }
    ],
    "sg:phone": "+1 614 488 3123",
    "sg:postcode": "43212",
    "sg:province": "OH",
    "sg:tags": [
      "consultant",
      "market",
      "research"
    ],
    "wof:name": "Dwight Spencer \u0026 Associates",
    "wof:placetype": "venue"
  },
  "geometry": {"coordinates":[-83.044752,39.984062],"type":"Point"}
}
