{
  "type": "Feature",
  "properties": {
    "addr:full": "400 W Mc Creight Ave Springfield OH 45504",
    "addr:housenumber": "400",
    "addr:postcode": "45504",
    "addr:street": "W Mc Creight Ave",
    "iso:country": "US",
    "sg:address": "400 W Mc Creight Ave",
    "sg:city": "Springfield",
    "sg:classifiers": [
      {
        "category": "Education",
        "subcategory": "Dance Studio",
        "type": "Public Place"
      }
    ],
    "sg:phone": "+1 937 399 5855",
    "sg:postcode": "45504",
    "sg:province": "OH",
    "sg:tags": [
      "instruction",
      "dancing"
    ],
    "wof:name": "Sonie's School Of Dance",
    "wof:placetype": "venue"
  },
  "geometry": {"coordinates":[-83.818047,39.939303],"type":"Point"}
}
