{
  "type": "Feature",
  "properties": {
    "iso:country":"US",
    "sg:address":"919 Gephart Rd",
    "sg:city":"Wheelersburg",
    "sg:classifiers":[
        {
            "category":"Utilities",
            "subcategory":"Refuse",
            "type":"Services"
        }
    ],
    "sg:phone":"+1 740 776 7733",
    "sg:postcode":"45694",
    "sg:province":"OH",
    "sg:tags":[
        "sanitation"
    ],
    "wof:name":"Mary Baker",
    "wof:placetype":"venue"
},
  "geometry": {"coordinates":[-82.802722,38.782695],"type":"Point"}
}