{
  "type": "Feature",
  "properties": {
    "addr:full":"3975 Georges Creek Rd Gallipolis OH 45631",
    "addr:housenumber":"3975",
    "addr:postcode":"45631",
    "addr:street":"Georges Creek Rd",
    "iso:country":"US",
    "sg:address":"3975 Georges Creek Rd",
    "sg:city":"Gallipolis",
    "sg:classifiers":[
        {
            "category":"Organizations",
            "subcategory":"Religious Organization",
            "type":"Services"
        }
    ],
    "sg:phone":"+1 740 446 8305",
    "sg:postcode":"45631",
    "sg:province":"OH",
    "sg:tags":[
        "clergy"
    ],
    "wof:name":"Good News Baptist Church",
    "wof:placetype":"venue"
},
  "geometry": {"coordinates":[-82.19035700000001,38.866309],"type":"Point"}
}