{
  "type": "Feature",
  "properties": {
    "addr:full":"1645 Allegheny Cir Cleveland OH 44112",
    "addr:housenumber":"1645",
    "addr:postcode":"44112",
    "addr:street":"Allegheny Cir",
    "iso:country":"US",
    "sg:address":"1645 Allegheny Cir",
    "sg:city":"Cleveland",
    "sg:classifiers":[
        {
            "category":"Building & Trades",
            "subcategory":"Construction",
            "type":"Services"
        }
    ],
    "sg:phone":"+1 216 761 2414",
    "sg:postcode":"44112",
    "sg:province":"OH",
    "sg:tags":[
        "general",
        "contractor"
    ],
    "wof:name":"Civic Construction",
    "wof:placetype":"venue"
},
  "geometry": {"coordinates":[-81.583629,41.533214],"type":"Point"}
}