{
  "type": "Feature",
  "properties": {
    "addr:full":"8049 State Rte 726 Eldorado OH 45321",
    "addr:housenumber":"8049",
    "addr:postcode":"45321",
    "addr:street":"State Rte 726",
    "iso:country":"US",
    "sg:address":"8049 State Rte 726",
    "sg:city":"Eldorado",
    "sg:classifiers":[
        {
            "category":"Building & Trades",
            "subcategory":"Construction",
            "type":"Services"
        }
    ],
    "sg:phone":"+1 937 273 4965",
    "sg:postcode":"45321",
    "sg:province":"OH",
    "sg:tags":[
        "excavation",
        "contractor"
    ],
    "wof:name":"Marlan G Hart Excavating",
    "wof:placetype":"venue"
},
  "geometry": {"coordinates":[-84.67723700000001,39.890724],"type":"Point"}
}