{
  "type": "Feature",
  "properties": {
    "addr:full":"9257 Rd 176 Paulding OH 45879",
    "addr:housenumber":"9257",
    "addr:postcode":"45879",
    "addr:street":"Rd 176",
    "iso:country":"US",
    "sg:address":"9257 Rd 176",
    "sg:city":"Paulding",
    "sg:phone":"+1 419 399 3743",
    "sg:postcode":"45879",
    "sg:province":"OH",
    "sg:tags":[
        "wheat",
        "beef",
        "farm",
        "corn",
        "soybean",
        "cattle",
        "feedlot"
    ],
    "wof:name":"Sukup Farms",
    "wof:placetype":"venue"
},
  "geometry": {"coordinates":[-84.64281200000001,41.179417],"type":"Point"}
}