{
  "type": "Feature",
  "properties": {
    "iso:country":"US",
    "sg:address":"14952 E Broad St",
    "sg:city":"Reynoldsburg",
    "sg:classifiers":[
        {
            "category":"Bars & Pubs",
            "type":"Food & Drink"
        }
    ],
    "sg:phone":"+1 740 927 3003",
    "sg:postcode":"43068",
    "sg:province":"OH",
    "sg:tags":[
        "drinking"
    ],
    "wof:name":"1st Brake",
    "wof:placetype":"venue"
},
  "geometry": {"coordinates":[-82.765457,39.988184],"type":"Point"}
}