{
  "type": "Feature",
  "properties": {
    "addr:full": "1289 E Livingston Ave Columbus OH 43205",
    "addr:housenumber": "1289",
    "addr:postcode": "43205",
    "addr:street": "E Livingston Ave",
    "iso:country": "US",
    "sg:address": "1289 E Livingston Ave",
    "sg:city": "Columbus",
    "sg:classifiers": [
      {
        "category": "Health Services",
        "subcategory": "Clinic",
        "type": "Services"
      },
      {
        "category": "Health Services",
        "subcategory": "Doctor",
        "type": "Services"
      }
    ],
    "sg:phone": "+1 614 252 0917",
    "sg:postcode": "43205",
    "sg:province": "OH",
    "sg:tags": [
      "physician",
      "surgeon",
      "care",
      "outpatient",
      "facility"
    ],
    "wof:name": "Livingston-Lockbourne Avenue",
    "wof:placetype": "venue"
  },
  "geometry": {"coordinates":[-82.963683,39.949375],"type":"Point"}
}
