{
  "type": "Feature",
  "properties": {
    "addr:full":"250 S Chestnut St Ravenna OH 44266",
    "addr:housenumber":"250",
    "addr:postcode":"44266",
    "addr:street":"S Chestnut St",
    "iso:country":"US",
    "sg:address":"250 S Chestnut St",
    "sg:city":"Ravenna",
    "sg:classifiers":[
        {
            "category":"Real Estate",
            "subcategory":"Real Estate Services",
            "type":"Services"
        }
    ],
    "sg:phone":"+1 330 296 6609",
    "sg:postcode":"44266",
    "sg:province":"OH",
    "sg:tags":[
        "company",
        "abstract",
        "title"
    ],
    "wof:name":"Timely Searches",
    "wof:placetype":"venue"
},
  "geometry": {"coordinates":[-81.24328800000001,41.155637],"type":"Point"}
}