{
  "type": "Feature",
  "properties": {
    "addr:full": "1449 Boardman Poland Rd Youngstown OH 44512",
    "addr:housenumber": "1449",
    "addr:postcode": "44512",
    "addr:street": "Boardman Poland Rd",
    "iso:country": "US",
    "sg:address": "1449 Boardman Poland Rd",
    "sg:city": "Youngstown",
    "sg:classifiers": [
      {
        "category": "Restaurant",
        "type": "Food \u0026 Drink"
      }
    ],
    "sg:phone": "+1 330 726 4766",
    "sg:postcode": "44512",
    "sg:province": "OH",
    "sg:tags": [
      "eating"
    ],
    "wof:name": "Flaming Ice Cube",
    "wof:placetype": "venue"
  },
  "geometry": {"coordinates":[-80.627407,41.024106],"type":"Point"}
}
