{
  "type": "Feature",
  "properties": {
    "iso:country":"US",
    "sg:address":"1449 Boardman Poland Rd",
    "sg:city":"Youngstown",
    "sg:classifiers":[
        {
            "category":"Restaurant",
            "type":"Food & Drink"
        }
    ],
    "sg:phone":"+1 330 726 4766",
    "sg:postcode":"44512",
    "sg:province":"OH",
    "sg:tags":[
        "eating"
    ],
    "wof:name":"Flaming Ice Cube",
    "wof:placetype":"venue"
},
  "geometry": {"coordinates":[-80.62740700000001,41.024106],"type":"Point"}
}