{
  "type": "Feature",
  "properties": {
    "addr:full": "103 W Walnut St Oxford IN 45056",
    "addr:housenumber": "103",
    "addr:postcode": "45056",
    "addr:street": "W Walnut St",
    "iso:country": "US",
    "sg:address": "103 W Walnut St",
    "sg:city": "Oxford",
    "sg:classifiers": [
      {
        "category": "Social Services",
        "type": "Services"
      }
    ],
    "sg:phone": "+1 513 523 0677",
    "sg:postcode": "45056",
    "sg:province": "IN",
    "sg:tags": [
      "counseling"
    ],
    "wof:name": "Susan R Callan",
    "wof:placetype": "venue"
  },
  "geometry": {"coordinates":[-84.744058,39.509398],"type":"Point"}
}
