{
  "type": "Feature",
  "properties": {
    "addr:full": "2600 17th St SE Canton OH 44730",
    "addr:housenumber": "2600",
    "addr:postcode": "44730",
    "addr:street": "17Th St Se",
    "iso:country": "US",
    "sg:address": "2600 17th St SE",
    "sg:city": "Canton",
    "sg:classifiers": [
      {
        "category": "Retail",
        "subcategory": "Repair Shop",
        "type": "Services"
      }
    ],
    "sg:phone": "+1 330 452 9122",
    "sg:postcode": "44730",
    "sg:province": "OH",
    "sg:tags": [
      "telecommunication",
      "circuit"
    ],
    "wof:name": "J A H Electronics Inc",
    "wof:placetype": "venue"
  },
  "geometry": {"coordinates":[-81.34416,40.778622],"type":"Point"}
}
