{
  "type": "Feature",
  "properties": {
    "addr:full": "2736 N Ridge Rd Painesville OH 44077",
    "addr:housenumber": "2736",
    "addr:postcode": "44077",
    "addr:street": "N Ridge Rd",
    "iso:country": "US",
    "sg:address": "2736 N Ridge Rd",
    "sg:city": "Painesville",
    "sg:classifiers": [
      {
        "category": "Government",
        "subcategory": "Office",
        "type": "Public Place"
      }
    ],
    "sg:phone": "+1 440 350 2580",
    "sg:postcode": "44077",
    "sg:province": "OH",
    "wof:name": "Courts Clerk-Auto Title",
    "wof:placetype": "venue"
  },
  "geometry": {"coordinates":[-81.183744,41.765061],"type":"Point"}
}
