{
  "type": "Feature",
  "properties": {
    "addr:full":"4934 Glenway Ave Cincinnati OH 45238",
    "addr:housenumber":"4934",
    "addr:postcode":"45238",
    "addr:street":"Glenway Ave",
    "iso:country":"US",
    "sg:address":"4934 Glenway Ave",
    "sg:city":"Cincinnati",
    "sg:classifiers":[
        {
            "category":"Professional",
            "type":"Services"
        }
    ],
    "sg:phone":"+1 513 678 2744",
    "sg:postcode":"45238",
    "sg:province":"OH",
    "sg:tags":[
        "establishment"
    ],
    "wof:name":"Magic Hands",
    "wof:placetype":"venue"
},
  "geometry": {"coordinates":[-84.60036100000001,39.120274],"type":"Point"}
}