{
  "type": "Feature",
  "properties": {
    "addr:full":"1438 Whitaker Way Montpelier OH 43543",
    "addr:housenumber":"1438",
    "addr:postcode":"43543",
    "addr:street":"Whitaker Way",
    "iso:country":"US",
    "sg:address":"1438 Whitaker Way",
    "sg:city":"Montpelier",
    "sg:classifiers":[
        {
            "category":"Cinema",
            "subcategory":"Movie Rental",
            "type":"Entertainment"
        }
    ],
    "sg:phone":"+1 419 485 8343",
    "sg:postcode":"43543",
    "sg:province":"OH",
    "sg:tags":[
        "leasing",
        "video",
        "disc",
        "tape"
    ],
    "wof:name":"Video Max",
    "wof:placetype":"venue"
},
  "geometry": {"coordinates":[-84.583294,41.586469],"type":"Point"}
}