{
  "type": "Feature",
  "properties": {
    "iso:country":"US",
    "sg:address":"7261 Engle Rd",
    "sg:city":"Cleveland",
    "sg:classifiers":[
        {
            "category":"Restaurant",
            "type":"Food & Drink"
        }
    ],
    "sg:phone":"+1 440 239 8118",
    "sg:postcode":"44130",
    "sg:province":"OH",
    "sg:tags":[
        "delicatessen",
        "eating"
    ],
    "wof:name":"A & A Cafe",
    "wof:placetype":"venue"
},
  "geometry": {"coordinates":[-81.825052,41.365563],"type":"Point"}
}