{
  "type": "Feature",
  "properties": {
    "addr:full": "7261 Engle Rd Cleveland OH 44130",
    "addr:housenumber": "7261",
    "addr:postcode": "44130",
    "addr:street": "Engle Rd",
    "iso:country": "US",
    "sg:address": "7261 Engle Rd",
    "sg:city": "Cleveland",
    "sg:classifiers": [
      {
        "category": "Restaurant",
        "type": "Food \u0026 Drink"
      }
    ],
    "sg:phone": "+1 440 239 8118",
    "sg:postcode": "44130",
    "sg:province": "OH",
    "sg:tags": [
      "delicatessen",
      "eating"
    ],
    "wof:name": "A \u0026 A Cafe",
    "wof:placetype": "venue"
  },
  "geometry": {"coordinates":[-81.825052,41.365563],"type":"Point"}
}
