{
  "type": "Feature",
  "properties": {
    "addr:full": "4425 Bates Rd Athens OH 45701",
    "addr:housenumber": "4425",
    "addr:postcode": "45701",
    "addr:street": "Bates Rd",
    "iso:country": "US",
    "sg:address": "4425 Bates Rd",
    "sg:city": "Athens",
    "sg:classifiers": [
      {
        "category": "Manufacturing",
        "subcategory": "Metals",
        "type": "Manufacturing \u0026 Wholesale Goods"
      }
    ],
    "sg:phone": "+1 740 593 7818",
    "sg:postcode": "45701",
    "sg:province": "OH",
    "sg:tags": [
      "engraver"
    ],
    "wof:name": "Custom Trophies \u0026 Engraving",
    "wof:placetype": "venue"
  },
  "geometry": {"coordinates":[-82.087176,39.260921],"type":"Point"}
}
