{
  "type": "Feature",
  "properties": {
    "addr:full":"29405 Grand Blvd Wickliffe OH 44092",
    "addr:housenumber":"29405",
    "addr:postcode":"44092",
    "addr:street":"Grand Blvd",
    "iso:country":"US",
    "sg:address":"29405 Grand Blvd",
    "sg:city":"Wickliffe",
    "sg:classifiers":[
        {
            "category":"Professional",
            "type":"Services"
        }
    ],
    "sg:phone":"+1 440 943 3673",
    "sg:postcode":"44092",
    "sg:province":"OH",
    "sg:tags":[
        "establishment"
    ],
    "wof:name":"Mondonet Inc",
    "wof:placetype":"venue"
},
  "geometry": {"coordinates":[-81.48429299999999,41.619931],"type":"Point"}
}