{
  "type": "Feature",
  "properties": {
    "addr:full":"591 Canton Rd Akron OH 44312",
    "addr:housenumber":"591",
    "addr:postcode":"44312",
    "addr:street":"Canton Rd",
    "iso:country":"US",
    "sg:address":"591 Canton Rd",
    "sg:city":"Akron",
    "sg:classifiers":[
        {
            "category":"Retail",
            "subcategory":"Auto Repair",
            "type":"Services"
        }
    ],
    "sg:phone":"+1 330 794 0600",
    "sg:postcode":"44312",
    "sg:province":"OH",
    "sg:tags":[
        "oil",
        "center",
        "change"
    ],
    "wof:name":"Lube Stop Inc",
    "wof:placetype":"venue"
},
  "geometry": {"coordinates":[-81.43732799999999,41.048028],"type":"Point"}
}