{
  "type": "Feature",
  "properties": {
    "iso:country":"US",
    "sg:address":"122 2nd St SE",
    "sg:city":"New Philadelphia",
    "sg:classifiers":[
        {
            "category":"Government",
            "subcategory":"Police Station",
            "type":"Public Place"
        }
    ],
    "sg:phone":"+1 330 343 4488",
    "sg:postcode":"44663",
    "sg:province":"OH",
    "sg:tags":[
        "department"
    ],
    "wof:name":"Police Department",
    "wof:placetype":"venue"
},
  "geometry": {"coordinates":[-81.443629,40.488535],"type":"Point"}
}