{
  "type": "Feature",
  "properties": {
    "addr:full":"8545 Factory Shops Blvd Jeffersonville OH 43128",
    "addr:housenumber":"8545",
    "addr:postcode":"43128",
    "addr:street":"Factory Shops Blvd",
    "iso:country":"US",
    "sg:address":"8545 Factory Shops Blvd",
    "sg:city":"Jeffersonville",
    "sg:classifiers":[
        {
            "category":"Shopping",
            "type":"Retail Goods"
        }
    ],
    "sg:phone":"+1 740 948 9660",
    "sg:postcode":"43128",
    "sg:province":"OH",
    "sg:tags":[
        "merchandise"
    ],
    "wof:name":"Oneida Factory Store",
    "wof:placetype":"venue"
},
  "geometry": {"coordinates":[-83.601697,39.617426],"type":"Point"}
}