{
  "type": "Feature",
  "properties": {
    "iso:country":"US",
    "sg:address":"480 E Town St",
    "sg:city":"Columbus",
    "sg:classifiers":[
        {
            "category":"Shopping",
            "type":"Retail Goods"
        }
    ],
    "sg:phone":"+1 614 645 0197",
    "sg:postcode":"43215",
    "sg:province":"OH",
    "sg:tags":[
        "merchandise"
    ],
    "wof:name":"Topiary Park Museum Store",
    "wof:placetype":"venue"
},
  "geometry": {"coordinates":[-82.988141,39.960186],"type":"Point"}
}