{
  "type": "Feature",
  "properties": {
    "addr:full": "7700 Staeger Rd Celina OH 45822",
    "addr:postcode": "7700;45822",
    "addr:street": "Staeger Rd",
    "iso:country": "US",
    "sg:address": "7700 Staeger Rd",
    "sg:city": "Celina",
    "sg:classifiers": [
      {
        "category": "Building \u0026 Trades",
        "subcategory": "Construction",
        "type": "Services"
      }
    ],
    "sg:phone": "+1 419 586 1121",
    "sg:postcode": "45822",
    "sg:province": "OH",
    "sg:tags": [
      "house"
    ],
    "wof:name": "Go TEC Builders",
    "wof:placetype": "venue"
  },
  "geometry": {"coordinates":[-84.522552,40.569977],"type":"Point"}
}
