{
  "type": "Feature",
  "properties": {
    "addr:full":"8272 Whiteridge Cir North Canton OH 44720",
    "addr:housenumber":"8272",
    "addr:postcode":"44720",
    "addr:street":"Whiteridge Cir",
    "iso:country":"US",
    "sg:address":"8272 Whiteridge Cir",
    "sg:city":"North Canton",
    "sg:classifiers":[
        {
            "category":"Building & Trades",
            "subcategory":"Landscaping Services",
            "type":"Services"
        }
    ],
    "sg:phone":"+1 330 494 7223",
    "sg:postcode":"44720",
    "sg:province":"OH",
    "sg:tags":[
        "landscape",
        "contractor"
    ],
    "wof:name":"Evan & Earth",
    "wof:placetype":"venue"
},
  "geometry": {"coordinates":[-81.407993,40.905373],"type":"Point"}
}