{
  "type": "Feature",
  "properties": {
    "iso:country":"US",
    "sg:address":"113 Holl Rd NE",
    "sg:city":"Canton",
    "sg:classifiers":[
        {
            "category":"Real Estate",
            "subcategory":"Real Estate Operator",
            "type":"Services"
        }
    ],
    "sg:phone":"+1 330 494 7804",
    "sg:postcode":"44720",
    "sg:province":"OH",
    "sg:tags":[
        "building",
        "apartment"
    ],
    "wof:name":"Centre Court Townhouse",
    "wof:placetype":"venue"
},
  "geometry": {"coordinates":[-81.402807,40.887778],"type":"Point"}
}