{
  "type": "Feature",
  "properties": {
    "iso:country":"US",
    "sg:address":"1850 Scott St",
    "sg:city":"Napoleon",
    "sg:classifiers":[
        {
            "category":"Restaurant",
            "type":"Food & Drink"
        }
    ],
    "sg:phone":"+1 419 599 1192",
    "sg:postcode":"43545",
    "sg:province":"OH",
    "wof:name":"Mc Donald's",
    "wof:placetype":"venue"
},
  "geometry": {"coordinates":[-84.13195,41.400761],"type":"Point"}
}