{
  "type": "Feature",
  "properties": {
    "addr:full": "1850 Scott St Napoleon OH 43545",
    "addr:housenumber": "1850",
    "addr:postcode": "43545",
    "addr:street": "Scott St",
    "iso:country": "US",
    "sg:address": "1850 Scott St",
    "sg:city": "Napoleon",
    "sg:classifiers": [
      {
        "category": "Restaurant",
        "type": "Food \u0026 Drink"
      }
    ],
    "sg:phone": "+1 419 599 1192",
    "sg:postcode": "43545",
    "sg:province": "OH",
    "wof:name": "Mc Donald's",
    "wof:placetype": "venue"
  },
  "geometry": {"coordinates":[-84.13195,41.400761],"type":"Point"}
}
