{
  "type": "Feature",
  "properties": {
    "addr:full":"475 Western Ave Chillicothe OH 45601",
    "addr:housenumber":"475",
    "addr:postcode":"45601",
    "addr:street":"Western Ave",
    "iso:country":"US",
    "sg:address":"475 Western Ave",
    "sg:city":"Chillicothe",
    "sg:classifiers":[
        {
            "category":"Professional",
            "type":"Services"
        }
    ],
    "sg:phone":"+1 740 773 3792",
    "sg:postcode":"45601",
    "sg:province":"OH",
    "sg:tags":[
        "establishment"
    ],
    "wof:name":"ODNR Div Of Soil & Wtr",
    "wof:placetype":"venue"
},
  "geometry": {"coordinates":[-83.001287,39.334841],"type":"Point"}
}