{
  "type": "Feature",
  "properties": {
    "addr:full": "9431 Mentor Ave Mentor OH 44060",
    "addr:housenumber": "9431",
    "addr:postcode": "44060",
    "addr:street": "Mentor Ave",
    "iso:country": "US",
    "sg:address": "9431 Mentor Ave",
    "sg:city": "Mentor",
    "sg:classifiers": [
      {
        "category": "Home \u0026 Garden",
        "subcategory": "Carpets \u0026 Floor Coverings",
        "type": "Retail Goods"
      }
    ],
    "sg:phone": "+1 440 946 6544",
    "sg:postcode": "44060",
    "sg:province": "OH",
    "sg:tags": [
      "dealer",
      "rug"
    ],
    "sg:website": "www.blanescarpetmart.com",
    "wof:name": "Carpet Mart",
    "wof:placetype": "venue"
  },
  "geometry": {"coordinates":[-81.301812,41.680182],"type":"Point"}
}
