{
  "type": "Feature",
  "properties": {
    "addr:full":"565 Lovers Ln Steubenville OH 43953",
    "addr:housenumber":"565",
    "addr:postcode":"43953",
    "addr:street":"Lovers Ln",
    "iso:country":"US",
    "sg:address":"565 Lovers Ln",
    "sg:city":"Steubenville",
    "sg:classifiers":[
        {
            "category":"Organizations",
            "subcategory":"Religious Organization",
            "type":"Services"
        }
    ],
    "sg:phone":"+1 740 264 1227",
    "sg:postcode":"43953",
    "sg:province":"OH",
    "sg:tags":[
        "god",
        "assembly",
        "church"
    ],
    "wof:name":"Word of Life Fellowshp Assmbly",
    "wof:placetype":"venue"
},
  "geometry": {"coordinates":[-80.667462,40.359413],"type":"Point"}
}