{
  "type": "Feature",
  "properties": {
    "addr:full":"2404 Far Hills Ave Dayton OH 45419",
    "addr:housenumber":"2404",
    "addr:postcode":"45419",
    "addr:street":"Far Hills Ave",
    "iso:country":"US",
    "sg:address":"2404 Far Hills Ave",
    "sg:city":"Dayton",
    "sg:classifiers":[
        {
            "category":"Real Estate",
            "subcategory":"Real Estate Agent",
            "type":"Services"
        }
    ],
    "sg:phone":"+1 937 293 1732",
    "sg:postcode":"45419",
    "sg:province":"OH",
    "wof:name":"Kinzeler George G Realtor",
    "wof:placetype":"venue"
},
  "geometry": {"coordinates":[-84.17093,39.709052],"type":"Point"}
}