{
  "type": "Feature",
  "properties": {
    "addr:full": "1600 Mary St Findlay OH 45840",
    "addr:housenumber": "1600",
    "addr:postcode": "45840",
    "addr:street": "Mary St",
    "iso:country": "US",
    "sg:address": "1600 Mary St",
    "sg:city": "Findlay",
    "sg:classifiers": [
      {
        "category": "Building \u0026 Trades",
        "subcategory": "Construction",
        "type": "Services"
      }
    ],
    "sg:phone": "+1 419 422 4747",
    "sg:postcode": "45840",
    "sg:province": "OH",
    "sg:tags": [
      "road",
      "contractor"
    ],
    "wof:name": "Highway Dept",
    "wof:placetype": "venue"
  },
  "geometry": {"coordinates":[-83.674601,41.040251],"type":"Point"}
}
