{
  "type": "Feature",
  "properties": {
    "addr:full":"15 Eswin St Cincinnati OH 45218",
    "addr:housenumber":"15",
    "addr:postcode":"45218",
    "addr:street":"Eswin St",
    "iso:country":"US",
    "sg:address":"15 Eswin St",
    "sg:city":"Cincinnati",
    "sg:classifiers":[
        {
            "category":"Organizations",
            "subcategory":"Professional Association",
            "type":"Services"
        }
    ],
    "sg:phone":"+1 513 742 2203",
    "sg:postcode":"45218",
    "sg:province":"OH",
    "sg:website":"www.coalitionpartnership.org",
    "wof:name":"Winton Woods Cmnty Coalition",
    "wof:placetype":"venue"
},
  "geometry": {"coordinates":[-84.522998,39.267153],"type":"Point"}
}