{
  "type": "Feature",
  "properties": {
    "addr:full": "5236 Ridge Rd Cleveland OH 44129",
    "addr:housenumber": "5236",
    "addr:postcode": "44129",
    "addr:street": "Ridge Rd",
    "iso:country": "US",
    "sg:address": "5236 Ridge Rd",
    "sg:city": "Cleveland",
    "sg:classifiers": [
      {
        "category": "Professional",
        "subcategory": "Employment Agencies",
        "type": "Services"
      }
    ],
    "sg:phone": "+1 216 335 9675",
    "sg:postcode": "44129",
    "sg:province": "OH",
    "sg:tags": [
      "help",
      "contractor"
    ],
    "wof:name": "Labor Leaders Inc",
    "wof:placetype": "venue"
  },
  "geometry": {"coordinates":[-81.734541,41.417276],"type":"Point"}
}
