{
  "type": "Feature",
  "properties": {
    "iso:country":"US",
    "sg:address":"5236 Ridge Rd",
    "sg:city":"Cleveland",
    "sg:classifiers":[
        {
            "category":"Professional",
            "subcategory":"Employment Agencies",
            "type":"Services"
        }
    ],
    "sg:phone":"+1 216 335 9675",
    "sg:postcode":"44129",
    "sg:province":"OH",
    "sg:tags":[
        "help",
        "contractor"
    ],
    "wof:name":"Labor Leaders Inc",
    "wof:placetype":"venue"
},
  "geometry": {"coordinates":[-81.73454099999999,41.417276],"type":"Point"}
}