{
  "type": "Feature",
  "properties": {
    "addr:full": "12277 State Rte 118 Rockford OH 45882",
    "addr:housenumber": "12277",
    "addr:postcode": "45882",
    "addr:street": "State Rte 118",
    "iso:country": "US",
    "sg:address": "12277 State Rte 118",
    "sg:city": "Rockford",
    "sg:classifiers": [
      {
        "category": "Building \u0026 Trades",
        "subcategory": "Construction",
        "type": "Services"
      }
    ],
    "sg:phone": "+1 419 363 3100",
    "sg:postcode": "45882",
    "sg:province": "OH",
    "sg:tags": [
      "house"
    ],
    "wof:name": "Hileman Construction",
    "wof:placetype": "venue"
  },
  "geometry": {"coordinates":[-84.644657,40.700347],"type":"Point"}
}
