{
  "type": "Feature",
  "properties": {
    "addr:full":"1515 Mifflin Ave Ashland OH 44805",
    "addr:housenumber":"1515",
    "addr:postcode":"44805",
    "addr:street":"Mifflin Ave",
    "iso:country":"US",
    "sg:address":"1515 Mifflin Ave",
    "sg:city":"Ashland",
    "sg:classifiers":[
        {
            "category":"Organizations",
            "subcategory":"Religious Organization",
            "type":"Services"
        }
    ],
    "sg:phone":"+1 419 281 1420",
    "sg:postcode":"44805",
    "sg:province":"OH",
    "sg:tags":[
        "church"
    ],
    "wof:name":"St Matthews Episcopal Church",
    "wof:placetype":"venue"
},
  "geometry": {"coordinates":[-82.332869,40.85049],"type":"Point"}
}