{
  "type": "Feature",
  "properties": {
    "addr:full":"219 Saint Clair Dr Chillicothe OH 45601",
    "addr:housenumber":"219",
    "addr:postcode":"45601",
    "addr:street":"Saint Clair Dr",
    "iso:country":"US",
    "sg:address":"219 Saint Clair Dr",
    "sg:city":"Chillicothe",
    "sg:classifiers":[
        {
            "category":"Organizations",
            "subcategory":"Professional Association",
            "type":"Services"
        }
    ],
    "sg:phone":"+1 740 773 4466",
    "sg:postcode":"45601",
    "sg:province":"OH",
    "wof:name":"Governor's Place Assn",
    "wof:placetype":"venue"
},
  "geometry": {"coordinates":[-83.007666,39.334162],"type":"Point"}
}