{
  "type": "Feature",
  "properties": {
    "addr:full": "4683 Morse Rd Columbus OH 43230",
    "addr:housenumber": "4683",
    "addr:postcode": "43230",
    "addr:street": "Morse Rd",
    "iso:country": "US",
    "sg:address": "4683 Morse Rd",
    "sg:city": "Columbus",
    "sg:classifiers": [
      {
        "category": "Restaurant",
        "type": "Food \u0026 Drink"
      }
    ],
    "sg:menulink": "http://www.allmenus.com/oh/columbus/83261-papa-johns-pizza/menu/",
    "sg:phone": "+1 614 478 3322",
    "sg:postcode": "43230",
    "sg:province": "OH",
    "sg:tags": [
      "american",
      "pizza"
    ],
    "wof:name": "Papa John's Pizza",
    "wof:placetype": "venue"
  },
  "geometry": {"coordinates":[-82.869674,40.055591],"type":"Point"}
}
