{
  "type": "Feature",
  "properties": {
    "addr:full":"252 Westview Dr Morrow OH 45152",
    "addr:housenumber":"252",
    "addr:postcode":"45152",
    "addr:street":"Westview Dr",
    "iso:country":"US",
    "sg:address":"252 Westview Dr",
    "sg:city":"Morrow",
    "sg:classifiers":[
        {
            "category":"Building & Trades",
            "subcategory":"Construction",
            "type":"Services"
        }
    ],
    "sg:phone":"+1 513 899 3351",
    "sg:postcode":"45152",
    "sg:province":"OH",
    "sg:tags":[
        "house"
    ],
    "wof:name":"B J Home Repairs",
    "wof:placetype":"venue"
},
  "geometry": {"coordinates":[-84.12242999999999,39.352938],"type":"Point"}
}