{
  "type": "Feature",
  "properties": {
    "addr:full": "4086 Co Rd H Edon OH 43518",
    "addr:housenumber": "4086",
    "addr:postcode": "43518",
    "addr:street": "Co Rd H",
    "iso:country": "US",
    "sg:address": "4086 Co Rd H",
    "sg:city": "Edon",
    "sg:classifiers": [
      {
        "category": "Freight",
        "type": "Transportation"
      }
    ],
    "sg:phone": "+1 419 272 2346",
    "sg:postcode": "43518",
    "sg:province": "OH",
    "sg:tags": [
      "commercial",
      "storage"
    ],
    "wof:name": "Edon Mini Storage",
    "wof:placetype": "venue"
  },
  "geometry": {"coordinates":[-84.748513,41.527529],"type":"Point"}
}
