{
  "type": "Feature",
  "properties": {
    "addr:full": "9591 Colerain Ave Cincinnati OH 45251",
    "addr:housenumber": "9591",
    "addr:postcode": "45251",
    "addr:street": "Colerain Ave",
    "iso:country": "US",
    "sg:address": "9591 Colerain Ave",
    "sg:city": "Cincinnati",
    "sg:classifiers": [
      {
        "category": "Restaurant",
        "type": "Food \u0026 Drink"
      }
    ],
    "sg:phone": "+1 513 385 8700",
    "sg:postcode": "45251",
    "sg:province": "OH",
    "wof:name": "Frullati Cafe \u0026 Bakery",
    "wof:placetype": "venue"
  },
  "geometry": {"coordinates":[-84.596336,39.247157],"type":"Point"}
}
