{
  "type": "Feature",
  "properties": {
    "iso:country":"US",
    "sg:address":"9591 Colerain Ave",
    "sg:city":"Cincinnati",
    "sg:classifiers":[
        {
            "category":"Restaurant",
            "type":"Food & Drink"
        }
    ],
    "sg:phone":"+1 513 385 8700",
    "sg:postcode":"45251",
    "sg:province":"OH",
    "wof:name":"Frullati Cafe & Bakery",
    "wof:placetype":"venue"
},
  "geometry": {"coordinates":[-84.59633599999999,39.247157],"type":"Point"}
}