{
  "type": "Feature",
  "properties": {
    "addr:full":"1492 Westdale Rd Cleveland OH 44121",
    "addr:housenumber":"1492",
    "addr:postcode":"44121",
    "addr:street":"Westdale Rd",
    "iso:country":"US",
    "sg:address":"1492 Westdale Rd",
    "sg:city":"Cleveland",
    "sg:classifiers":[
        {
            "category":"Building & Trades",
            "subcategory":"Construction",
            "type":"Services"
        }
    ],
    "sg:phone":"+1 216 531 9564",
    "sg:postcode":"44121",
    "sg:province":"OH",
    "sg:tags":[
        "contractor"
    ],
    "wof:name":"Clarkstone Contracting Company",
    "wof:placetype":"venue"
},
  "geometry": {"coordinates":[-81.527458,41.519985],"type":"Point"}
}