{
  "type": "Feature",
  "properties": {
    "addr:full":"732 Illinois Ave Maumee OH 43537",
    "addr:housenumber":"732",
    "addr:postcode":"43537",
    "addr:street":"Illinois Ave",
    "iso:country":"US",
    "sg:address":"732 Illinois Ave",
    "sg:city":"Maumee",
    "sg:classifiers":[
        {
            "category":"Home & Garden",
            "subcategory":"Building Materials",
            "type":"Retail Goods"
        }
    ],
    "sg:phone":"+1 419 893 8400",
    "sg:postcode":"43537",
    "sg:province":"OH",
    "sg:tags":[
        "lumber"
    ],
    "sg:website":"www.84lumber.com",
    "wof:name":"84 Lumber Co",
    "wof:placetype":"venue"
},
  "geometry": {"coordinates":[-83.673498,41.569406],"type":"Point"}
}