{
  "type": "Feature",
  "properties": {
    "addr:full": "302 Ash Dr Pioneer OH 43554",
    "addr:housenumber": "302",
    "addr:postcode": "43554",
    "addr:street": "Ash Dr",
    "iso:country": "US",
    "sg:address": "302 Ash Dr",
    "sg:city": "Pioneer",
    "sg:classifiers": [
      {
        "category": "Freight",
        "type": "Transportation"
      }
    ],
    "sg:phone": "+1 419 737 3036",
    "sg:postcode": "43554",
    "sg:province": "OH",
    "sg:tags": [
      "operator",
      "trucking"
    ],
    "wof:name": "Mark J Dennis",
    "wof:placetype": "venue"
  },
  "geometry": {"coordinates":[-84.562518,41.678805],"type":"Point"}
}
