{
  "type": "Feature",
  "properties": {
    "iso:country":"US",
    "sg:address":"3918 E 140th St",
    "sg:city":"Cleveland",
    "sg:classifiers":[
        {
            "category":"Food & Beverages",
            "subcategory":"Groceries & Convenience Stores",
            "type":"Retail Goods"
        }
    ],
    "sg:phone":"+1 216 491 1885",
    "sg:postcode":"44128",
    "sg:province":"OH",
    "sg:tags":[
        "grocer"
    ],
    "wof:name":"Peoples Food Market",
    "wof:placetype":"venue"
},
  "geometry": {"coordinates":[-81.584671,41.4524],"type":"Point"}
}