{
  "type": "Feature",
  "properties": {
    "addr:full": "437 E Liberty St Hubbard OH 44425",
    "addr:housenumber": "437",
    "addr:postcode": "44425",
    "addr:street": "E Liberty St",
    "iso:country": "US",
    "sg:address": "437 E Liberty St",
    "sg:city": "Hubbard",
    "sg:classifiers": [
      {
        "category": "Home \u0026 Garden",
        "subcategory": "Furniture",
        "type": "Retail Goods"
      }
    ],
    "sg:phone": "+1 330 534 4645",
    "sg:postcode": "44425",
    "sg:province": "OH",
    "wof:name": "Price Less Furniture Ware",
    "wof:placetype": "venue"
  },
  "geometry": {"coordinates":[-80.561479,41.156327],"type":"Point"}
}
