{
  "type": "Feature",
  "properties": {
    "addr:full": "1725 Mount Vernon Rd Newark OH 43055",
    "addr:housenumber": "1725",
    "addr:postcode": "43055",
    "addr:street": "Mount Vernon Rd",
    "iso:country": "US",
    "sg:address": "1725 Mount Vernon Rd",
    "sg:city": "Newark",
    "sg:classifiers": [
      {
        "category": "Wholesale",
        "subcategory": "Electrical",
        "type": "Manufacturing \u0026 Wholesale Goods"
      }
    ],
    "sg:phone": "+1 740 366 6850",
    "sg:postcode": "43055",
    "sg:province": "OH",
    "sg:tags": [
      "control",
      "transformer",
      "electric",
      "motor"
    ],
    "wof:name": "Cardinal Electric Inc",
    "wof:placetype": "venue"
  },
  "geometry": {"coordinates":[-82.425544,40.103332],"type":"Point"}
}
