{
  "type": "Feature",
  "properties": {
    "iso:country":"US",
    "sg:address":"2296 E Dorothy Ln",
    "sg:city":"Dayton",
    "sg:classifiers":[
        {
            "category":"Shopping",
            "subcategory":"Discount & Variety Stores",
            "type":"Retail Goods"
        }
    ],
    "sg:phone":"+1 937 299 2576",
    "sg:postcode":"45420",
    "sg:province":"OH",
    "wof:name":"Dollar General",
    "wof:placetype":"venue"
},
  "geometry": {"coordinates":[-84.123211,39.702554],"type":"Point"}
}