{
  "type": "Feature",
  "properties": {
    "addr:full": "7121 Winnow Ct Reynoldsburg OH 43068",
    "addr:postcode": "7121;43068",
    "addr:street": "Winnow Ct",
    "iso:country": "US",
    "sg:address": "7121 Winnow Ct",
    "sg:city": "Reynoldsburg",
    "sg:classifiers": [
      {
        "category": "Building \u0026 Trades",
        "subcategory": "Construction",
        "type": "Services"
      }
    ],
    "sg:phone": "+1 614 863 5499",
    "sg:postcode": "43068",
    "sg:province": "OH",
    "sg:tags": [
      "house"
    ],
    "wof:name": "One 2 Call",
    "wof:placetype": "venue"
  },
  "geometry": {"coordinates":[-82.808466,39.917042],"type":"Point"}
}
