{
  "type": "Feature",
  "properties": {
    "addr:full": "247 E Main St Alliance OH 44601",
    "addr:housenumber": "247",
    "addr:postcode": "44601",
    "addr:street": "E Main St",
    "iso:country": "US",
    "sg:address": "247 E Main St",
    "sg:city": "Alliance",
    "sg:classifiers": [
      {
        "category": "Real Estate",
        "subcategory": "Developer",
        "type": "Services"
      }
    ],
    "sg:phone": "+1 330 821 9838",
    "sg:postcode": "44601",
    "sg:province": "OH",
    "wof:name": "Development Alliance Inc",
    "wof:placetype": "venue"
  },
  "geometry": {"coordinates":[-81.101784,40.921712],"type":"Point"}
}
