{
  "type": "Feature",
  "properties": {
    "iso:country":"US",
    "sg:address":"247 E Main St",
    "sg:city":"Alliance",
    "sg:classifiers":[
        {
            "category":"Real Estate",
            "subcategory":"Developer",
            "type":"Services"
        }
    ],
    "sg:phone":"+1 330 821 9838",
    "sg:postcode":"44601",
    "sg:province":"OH",
    "wof:name":"Development Alliance Inc",
    "wof:placetype":"venue"
},
  "geometry": {"coordinates":[-81.10178399999999,40.921712],"type":"Point"}
}