{
  "type": "Feature",
  "properties": {
    "iso:country":"US",
    "sg:address":"1663 Tracy St",
    "sg:city":"Toledo",
    "sg:classifiers":[
        {
            "category":"Manufacturing",
            "subcategory":"Metals",
            "type":"Manufacturing & Wholesale Goods"
        }
    ],
    "sg:phone":"+1 419 666 0100",
    "sg:postcode":"43605",
    "sg:province":"OH",
    "sg:tags":[
        "brass",
        "foundry",
        "bronze"
    ],
    "sg:website":"www.tristate.com",
    "wof:name":"Tri-State Aluminum",
    "wof:placetype":"venue"
},
  "geometry": {"coordinates":[-83.528108,41.620836],"type":"Point"}
}