{
  "type": "Feature",
  "properties": {
    "iso:country":"US",
    "sg:address":"3707 York Ln",
    "sg:city":"Cincinnati",
    "sg:classifiers":[
        {
            "category":"Building & Trades",
            "subcategory":"Construction",
            "type":"Services"
        }
    ],
    "sg:phone":"+1 513 646 2412",
    "sg:postcode":"45215",
    "sg:province":"OH",
    "sg:tags":[
        "carpentry",
        "contractor"
    ],
    "wof:name":"Kevin Dowdy",
    "wof:placetype":"venue"
},
  "geometry": {"coordinates":[-84.48055600000001,39.215617],"type":"Point"}
}