{
  "type": "Feature",
  "properties": {
    "addr:full": "3707 York Ln Cincinnati OH 45215",
    "addr:housenumber": "3707",
    "addr:postcode": "45215",
    "addr:street": "York Ln",
    "iso:country": "US",
    "sg:address": "3707 York Ln",
    "sg:city": "Cincinnati",
    "sg:classifiers": [
      {
        "category": "Building \u0026 Trades",
        "subcategory": "Construction",
        "type": "Services"
      }
    ],
    "sg:phone": "+1 513 646 2412",
    "sg:postcode": "45215",
    "sg:province": "OH",
    "sg:tags": [
      "carpentry",
      "contractor"
    ],
    "wof:name": "Kevin Dowdy",
    "wof:placetype": "venue"
  },
  "geometry": {"coordinates":[-84.480556,39.215617],"type":"Point"}
}
