{
  "type": "Feature",
  "properties": {
    "addr:full": "800 Compton Rd Cincinnati OH 45231",
    "addr:housenumber": "800",
    "addr:postcode": "45231",
    "addr:street": "Compton Rd",
    "iso:country": "US",
    "sg:address": "800 Compton Rd",
    "sg:city": "Cincinnati",
    "sg:classifiers": [
      {
        "category": "Health Services",
        "subcategory": "Health Practitioner",
        "type": "Services"
      }
    ],
    "sg:phone": "+1 513 521 1555",
    "sg:postcode": "45231",
    "sg:province": "OH",
    "sg:tags": [
      "psychotherapist"
    ],
    "wof:name": "Hines \u0026 Assoc",
    "wof:placetype": "venue"
  },
  "geometry": {"coordinates":[-84.511915,39.233935],"type":"Point"}
}
