{
  "type": "Feature",
  "properties": {
    "addr:full": "16239 State Rte 37 Corning OH 43730",
    "addr:housenumber": "16239",
    "addr:postcode": "43730",
    "addr:street": "State Rte 37",
    "iso:country": "US",
    "sg:address": "16239 State Rte 37",
    "sg:city": "Corning",
    "sg:classifiers": [
      {
        "category": "Professional",
        "subcategory": "Accounting \u0026 Tax Preparation",
        "type": "Services"
      }
    ],
    "sg:phone": "+1 740 342 4349",
    "sg:postcode": "43730",
    "sg:province": "OH",
    "sg:tags": [
      "bookkeeping",
      "general"
    ],
    "wof:name": "Ross \u0026 Assoc",
    "wof:placetype": "venue"
  },
  "geometry": {"coordinates":[-82.031313,39.676081],"type":"Point"}
}
