{
  "type": "Feature",
  "properties": {
    "iso:country":"US",
    "sg:address":"16239 State Rte 37",
    "sg:city":"Corning",
    "sg:classifiers":[
        {
            "category":"Professional",
            "subcategory":"Accounting & Tax Preparation",
            "type":"Services"
        }
    ],
    "sg:phone":"+1 740 342 4349",
    "sg:postcode":"43730",
    "sg:province":"OH",
    "sg:tags":[
        "bookkeeping",
        "general"
    ],
    "wof:name":"Ross & Assoc",
    "wof:placetype":"venue"
},
  "geometry": {"coordinates":[-82.031313,39.676081],"type":"Point"}
}