{
  "type": "Feature",
  "properties": {
    "iso:country":"US",
    "sg:address":"580 E Washington St",
    "sg:city":"Sabina",
    "sg:classifiers":[
        {
            "category":"Health Services",
            "subcategory":"Nursing And Care Facility",
            "type":"Services"
        }
    ],
    "sg:phone":"+1 937 584 2497",
    "sg:postcode":"45169",
    "sg:province":"OH",
    "sg:tags":[
        "intermediate",
        "convalescent",
        "home"
    ],
    "wof:name":"Autumn Years Nursing Center",
    "wof:placetype":"venue"
},
  "geometry": {"coordinates":[-83.628084,39.489588],"type":"Point"}
}