{
  "type": "Feature",
  "properties": {
    "addr:full": "8109 Miller Rd Shelby OH 44875",
    "addr:housenumber": "8109",
    "addr:postcode": "44875",
    "addr:street": "Miller Rd",
    "iso:country": "US",
    "sg:address": "8109 Miller Rd",
    "sg:city": "Shelby",
    "sg:classifiers": [
      {
        "category": "Farming",
        "subcategory": "Farm",
        "type": "Manufacturing \u0026 Wholesale Goods"
      }
    ],
    "sg:phone": "+1 419 347 5570",
    "sg:postcode": "44875",
    "sg:province": "OH",
    "sg:tags": [
      "crop",
      "general"
    ],
    "wof:name": "Raymond Metzger",
    "wof:placetype": "venue"
  },
  "geometry": {"coordinates":[-82.732389,40.893748],"type":"Point"}
}
