{
  "type": "Feature",
  "properties": {
    "iso:country":"US",
    "sg:address":"855 Co Hwy 1904",
    "sg:city":"Ashland",
    "sg:classifiers":[
        {
            "category":"Building & Trades",
            "subcategory":"Construction",
            "type":"Services"
        },
        {
            "category":"Social Services",
            "type":"Services"
        }
    ],
    "sg:phone":"+1 419 368 8432",
    "sg:postcode":"44805",
    "sg:province":"OH",
    "sg:tags":[
        "excavation",
        "organization",
        "home",
        "welfare"
    ],
    "wof:name":"George Miller Excavating",
    "wof:placetype":"venue"
},
  "geometry": {"coordinates":[-82.29503699999999,40.784083],"type":"Point"}
}