{
  "type": "Feature",
  "properties": {
    "iso:country":"US",
    "sg:address":"27540 Detroit Rd",
    "sg:city":"Cleveland",
    "sg:classifiers":[
        {
            "category":"Professional",
            "type":"Services"
        },
        {
            "category":"Health Services",
            "subcategory":"Doctor",
            "type":"Services"
        }
    ],
    "sg:phone":"+1 440 835 1611",
    "sg:postcode":"44145",
    "sg:province":"OH",
    "sg:tags":[
        "dentist"
    ],
    "wof:name":"Brian R Toth D D S Inc",
    "wof:placetype":"venue"
},
  "geometry": {"coordinates":[-81.922965,41.467248],"type":"Point"}
}