{
  "type": "Feature",
  "properties": {
    "addr:full": "245 Locust St Marion OH 43314",
    "addr:housenumber": "245",
    "addr:postcode": "43314",
    "addr:street": "Locust St",
    "iso:country": "US",
    "sg:address": "245 Locust St",
    "sg:city": "Marion",
    "sg:classifiers": [
      {
        "category": "Shopping",
        "type": "Retail Goods"
      }
    ],
    "sg:phone": "+1 740 383 2444",
    "sg:postcode": "43314",
    "sg:province": "OH",
    "sg:tags": [
      "wedding",
      "supply"
    ],
    "wof:name": "Wedding By Design",
    "wof:placetype": "venue"
  },
  "geometry": {"coordinates":[-82.970633,40.634031],"type":"Point"}
}
