{
  "type": "Feature",
  "properties": {
    "iso:country":"US",
    "sg:address":"1000 Urlin Ave",
    "sg:city":"Columbus",
    "sg:classifiers":[
        {
            "category":"Real Estate",
            "subcategory":"Real Estate Operator",
            "type":"Services"
        },
        {
            "category":"Organizations",
            "subcategory":"Community Association",
            "type":"Services"
        }
    ],
    "sg:phone":"+1 614 486 5917",
    "sg:postcode":"43212",
    "sg:province":"OH",
    "sg:tags":[
        "condominium"
    ],
    "wof:name":"Summit Chase Condominium",
    "wof:placetype":"venue"
},
  "geometry": {"coordinates":[-83.050505,39.977796],"type":"Point"}
}