{
  "type": "Feature",
  "properties": {
    "addr:full": "1085 Parsons Ave Columbus OH 43206",
    "addr:housenumber": "1085",
    "addr:postcode": "43206",
    "addr:street": "Parsons Ave",
    "iso:country": "US",
    "sg:address": "1085 Parsons Ave",
    "sg:city": "Columbus",
    "sg:classifiers": [
      {
        "category": "Food \u0026 Beverages",
        "subcategory": "Liquor \u0026 Beverages",
        "type": "Retail Goods"
      }
    ],
    "sg:phone": "+1 614 444 5970",
    "sg:postcode": "43206",
    "sg:province": "OH",
    "sg:tags": [
      "alcoholic"
    ],
    "wof:name": "O M I State Liquor Agency",
    "wof:placetype": "venue"
  },
  "geometry": {"coordinates":[-82.983282,39.940993],"type":"Point"}
}
