{
  "type": "Feature",
  "properties": {
    "iso:country":"US",
    "sg:address":"1085 Parsons Ave",
    "sg:city":"Columbus",
    "sg:classifiers":[
        {
            "category":"Food & Beverages",
            "subcategory":"Liquor & Beverages",
            "type":"Retail Goods"
        }
    ],
    "sg:phone":"+1 614 444 5970",
    "sg:postcode":"43206",
    "sg:province":"OH",
    "sg:tags":[
        "alcoholic"
    ],
    "wof:name":"O M I State Liquor Agency",
    "wof:placetype":"venue"
},
  "geometry": {"coordinates":[-82.983282,39.940993],"type":"Point"}
}