{
  "type": "Feature",
  "properties": {
    "iso:country":"US",
    "sg:address":"2200 Losantiville Ave",
    "sg:city":"Cincinnati",
    "sg:classifiers":[
        {
            "category":"Professional",
            "subcategory":"Management & Consulting",
            "type":"Services"
        }
    ],
    "sg:phone":"+1 513 841 2834",
    "sg:postcode":"45237",
    "sg:province":"OH",
    "sg:tags":[
        "fuel"
    ],
    "wof:name":"Infinity Management",
    "wof:placetype":"venue"
},
  "geometry": {"coordinates":[-84.450695,39.191013],"type":"Point"}
}