{
  "type": "Feature",
  "properties": {
    "addr:full":"312 Pataskala Ridge Dr SW Pataskala OH 43062",
    "addr:housenumber":"312",
    "addr:postcode":"43062",
    "addr:street":"Pataskala Ridge Dr Sw",
    "iso:country":"US",
    "sg:address":"312 Pataskala Ridge Dr SW",
    "sg:city":"Pataskala",
    "sg:classifiers":[
        {
            "category":"Building & Trades",
            "subcategory":"Construction",
            "type":"Services"
        }
    ],
    "sg:phone":"+1 740 964 0012",
    "sg:postcode":"43062",
    "sg:province":"OH",
    "sg:tags":[
        "house"
    ],
    "sg:website":"www.dominionhomes.com",
    "wof:name":"Dominion Homes Inc",
    "wof:placetype":"venue"
},
  "geometry": {"coordinates":[-82.676891,39.990699],"type":"Point"}
}