{
  "type": "Feature",
  "properties": {
    "iso:country":"US",
    "sg:address":"4601 Eastgate Blvd",
    "sg:city":"Cincinnati",
    "sg:classifiers":[
        {
            "category":"Shopping",
            "subcategory":"Clothing, Apparel, & Fashions",
            "type":"Retail Goods"
        }
    ],
    "sg:phone":"+1 513 752 4755",
    "sg:postcode":"45245",
    "sg:province":"OH",
    "sg:tags":[
        "leather"
    ],
    "wof:name":"Wilson's Suede & Leather",
    "wof:placetype":"venue"
},
  "geometry": {"coordinates":[-84.27309099999999,39.10214],"type":"Point"}
}