{
  "type": "Feature",
  "properties": {
    "addr:full": "4601 Eastgate Blvd Cincinnati OH 45245",
    "addr:housenumber": "4601",
    "addr:postcode": "45245",
    "addr:street": "Eastgate Blvd",
    "iso:country": "US",
    "sg:address": "4601 Eastgate Blvd",
    "sg:city": "Cincinnati",
    "sg:classifiers": [
      {
        "category": "Shopping",
        "subcategory": "Clothing, Apparel, \u0026 Fashions",
        "type": "Retail Goods"
      }
    ],
    "sg:phone": "+1 513 752 4755",
    "sg:postcode": "45245",
    "sg:province": "OH",
    "sg:tags": [
      "leather"
    ],
    "wof:name": "Wilson's Suede \u0026 Leather",
    "wof:placetype": "venue"
  },
  "geometry": {"coordinates":[-84.273091,39.10214],"type":"Point"}
}
