{
  "type": "Feature",
  "properties": {
    "addr:full":"3887 Shaker Rd Franklin OH 45005",
    "addr:housenumber":"3887",
    "addr:postcode":"45005",
    "addr:street":"Shaker Rd",
    "iso:country":"US",
    "sg:address":"3887 Shaker Rd",
    "sg:city":"Franklin",
    "sg:classifiers":[
        {
            "category":"Building & Trades",
            "subcategory":"Construction",
            "type":"Services"
        }
    ],
    "sg:phone":"+1 937 746 3291",
    "sg:postcode":"45005",
    "sg:province":"OH",
    "sg:tags":[
        "house"
    ],
    "wof:name":"Carothers Contracting",
    "wof:placetype":"venue"
},
  "geometry": {"coordinates":[-84.295642,39.500787],"type":"Point"}
}