{
  "type": "Feature",
  "properties": {
    "iso:country":"US",
    "sg:address":"2714 Marion-Marysville Rd",
    "sg:city":"Marion",
    "sg:classifiers":[
        {
            "category":"Retail",
            "subcategory":"Repair Shop",
            "type":"Services"
        }
    ],
    "sg:phone":"+1 740 387 5802",
    "sg:postcode":"43302",
    "sg:province":"OH",
    "sg:tags":[
        "product",
        "wood",
        "upholsterer",
        "mfg"
    ],
    "wof:name":"Hartay Upholstery & Woodwkg",
    "wof:placetype":"venue"
},
  "geometry": {"coordinates":[-83.157268,40.534815],"type":"Point"}
}