{
  "type": "Feature",
  "properties": {
    "addr:full": "2714 Marion-Marysville Rd Marion OH 43302",
    "addr:housenumber": "2714",
    "addr:postcode": "43302",
    "addr:street": "Marion-Marysville Rd",
    "iso:country": "US",
    "sg:address": "2714 Marion-Marysville Rd",
    "sg:city": "Marion",
    "sg:classifiers": [
      {
        "category": "Retail",
        "subcategory": "Repair Shop",
        "type": "Services"
      }
    ],
    "sg:phone": "+1 740 387 5802",
    "sg:postcode": "43302",
    "sg:province": "OH",
    "sg:tags": [
      "product",
      "wood",
      "upholsterer",
      "mfg"
    ],
    "wof:name": "Hartay Upholstery \u0026 Woodwkg",
    "wof:placetype": "venue"
  },
  "geometry": {"coordinates":[-83.157268,40.534815],"type":"Point"}
}
