{
  "type": "Feature",
  "properties": {
    "iso:country":"US",
    "sg:address":"20851 Priday Ave",
    "sg:city":"Euclid",
    "sg:classifiers":[
        {
            "category":"Shopping",
            "subcategory":"Hobbies, Toys, & Games",
            "type":"Retail Goods"
        }
    ],
    "sg:phone":"+1 216 486 4976",
    "sg:postcode":"44123",
    "sg:province":"OH",
    "wof:name":"Karnes Golden Moments",
    "wof:placetype":"venue"
},
  "geometry": {"coordinates":[-81.537773,41.598747],"type":"Point"}
}