{
  "type": "Feature",
  "properties": {
    "addr:full":"1400 Brandywine Blvd Zanesville OH 43701",
    "addr:housenumber":"1400",
    "addr:postcode":"43701",
    "addr:street":"Brandywine Blvd",
    "iso:country":"US",
    "sg:address":"1400 Brandywine Blvd",
    "sg:city":"Zanesville",
    "sg:classifiers":[
        {
            "category":"Professional",
            "subcategory":"Advertising",
            "type":"Services"
        }
    ],
    "sg:phone":"+1 740 452 4541",
    "sg:postcode":"43701",
    "sg:province":"OH",
    "sg:tags":[
        "counselor"
    ],
    "wof:name":"Sarel Limited Art & Adv",
    "wof:placetype":"venue"
},
  "geometry": {"coordinates":[-82.02563600000001,39.984221],"type":"Point"}
}