{
  "type": "Feature",
  "properties": {
    "addr:full": "12930 Fairhill Rd Cleveland OH 44120",
    "addr:housenumber": "12930",
    "addr:postcode": "44120",
    "addr:street": "Fairhill Rd",
    "iso:country": "US",
    "sg:address": "12930 Fairhill Rd",
    "sg:city": "Cleveland",
    "sg:classifiers": [
      {
        "category": "Building \u0026 Trades",
        "subcategory": "Landscaping Services",
        "type": "Services"
      }
    ],
    "sg:phone": "+1 216 402 2543",
    "sg:postcode": "44120",
    "sg:province": "OH",
    "sg:tags": [
      "landscape",
      "contractor"
    ],
    "wof:name": "Yardkat Landscaping 76",
    "wof:placetype": "venue"
  },
  "geometry": {"coordinates":[-81.59074,41.491406],"type":"Point"}
}
