{
  "type": "Feature",
  "properties": {
    "addr:full": "2865 Olentangy River Rd Columbus OH 43202",
    "addr:housenumber": "2865",
    "addr:postcode": "43202",
    "addr:street": "Olentangy River Rd",
    "iso:country": "US",
    "sg:address": "2865 Olentangy River Rd",
    "sg:city": "Columbus",
    "sg:classifiers": [
      {
        "category": "Restaurant",
        "type": "Food \u0026 Drink"
      }
    ],
    "sg:menulink": "http://www.allmenus.com/oh/columbus/195143-mcdonalds/menu/",
    "sg:postcode": "43202",
    "sg:province": "OH",
    "sg:tags": [
      "burger",
      "american"
    ],
    "wof:name": "McDonald's",
    "wof:placetype": "venue"
  },
  "geometry": {"coordinates":[-83.024356,40.019526],"type":"Point"}
}
