{
  "type": "Feature",
  "properties": {
    "addr:full":"217 N Ogden Ave Columbus OH 43204",
    "addr:housenumber":"217",
    "addr:postcode":"43204",
    "addr:street":"N Ogden Ave",
    "iso:country":"US",
    "sg:address":"217 N Ogden Ave",
    "sg:city":"Columbus",
    "sg:classifiers":[
        {
            "category":"Professional",
            "type":"Services"
        }
    ],
    "sg:phone":"+1 614 351 9775",
    "sg:postcode":"43204",
    "sg:province":"OH",
    "wof:name":"United Worldwide Brands",
    "wof:placetype":"venue"
},
  "geometry": {"coordinates":[-83.071383,39.959818],"type":"Point"}
}