{
  "type": "Feature",
  "properties": {
    "iso:country":"US",
    "sg:address":"136 S McCord Rd",
    "sg:city":"Holland",
    "sg:classifiers":[
        {
            "category":"Building & Trades",
            "subcategory":"Landscaping Services",
            "type":"Services"
        }
    ],
    "sg:phone":"+1 419 861 2202",
    "sg:postcode":"43528",
    "sg:province":"OH",
    "sg:tags":[
        "tree"
    ],
    "wof:name":"All City Tree Svc",
    "wof:placetype":"venue"
},
  "geometry": {"coordinates":[-83.703591,41.636433],"type":"Point"}
}