{
  "type": "Feature",
  "properties": {
    "addr:full":"1069 Skillman Dr Cincinnati OH 45215",
    "addr:housenumber":"1069",
    "addr:postcode":"45215",
    "addr:street":"Skillman Dr",
    "iso:country":"US",
    "sg:address":"1069 Skillman Dr",
    "sg:city":"Cincinnati",
    "sg:classifiers":[
        {
            "category":"Shopping",
            "type":"Retail Goods"
        },
        {
            "category":"Professional",
            "subcategory":"Accounting & Tax Preparation",
            "type":"Services"
        }
    ],
    "sg:phone":"+1 513 326 4630",
    "sg:postcode":"45215",
    "sg:province":"OH",
    "sg:tags":[
        "receivable",
        "account",
        "apparatus",
        "supply",
        "medical",
        "payable"
    ],
    "wof:name":"Hamiltons Health Aid Services",
    "wof:placetype":"venue"
},
  "geometry": {"coordinates":[-84.45573,39.258975],"type":"Point"}
}