{
  "type": "Feature",
  "properties": {
    "iso:country":"US",
    "sg:address":"5586 Earhart Ave",
    "sg:city":"Columbus",
    "sg:classifiers":[
        {
            "category":"Real Estate",
            "subcategory":"Real Estate Operator",
            "type":"Services"
        }
    ],
    "sg:phone":"+1 614 853 4710",
    "sg:postcode":"43228",
    "sg:province":"OH",
    "sg:tags":[
        "building",
        "apartment"
    ],
    "wof:name":"Bolton Estates Apts",
    "wof:placetype":"venue"
},
  "geometry": {"coordinates":[-83.142149,39.928683],"type":"Point"}
}