{
  "type": "Feature",
  "properties": {
    "addr:full":"719 Mosgrove St Urbana OH 43078",
    "addr:housenumber":"719",
    "addr:postcode":"43078",
    "addr:street":"Mosgrove St",
    "iso:country":"US",
    "sg:address":"719 Mosgrove St",
    "sg:city":"Urbana",
    "sg:classifiers":[
        {
            "category":"Real Estate",
            "subcategory":"Real Estate Operator",
            "type":"Services"
        }
    ],
    "sg:phone":"+1 937 652 2195",
    "sg:postcode":"43078",
    "sg:province":"OH",
    "sg:tags":[
        "building",
        "apartment"
    ],
    "wof:name":"Urbana Village North Ltd",
    "wof:placetype":"venue"
},
  "geometry": {"coordinates":[-83.76618499999999,40.114905],"type":"Point"}
}