{
  "type": "Feature",
  "properties": {
    "iso:country":"US",
    "sg:address":"3045 Olentangy River Rd",
    "sg:city":"Columbus",
    "sg:classifiers":[
        {
            "category":"Travel",
            "subcategory":"Hotels & Motels",
            "type":"Entertainment"
        },
        {
            "category":"Retail",
            "subcategory":"Event Space",
            "type":"Services"
        }
    ],
    "sg:phone":"+1 800 345 8082",
    "sg:postcode":"43202",
    "sg:province":"OH",
    "sg:tags":[
        "facility",
        "banquet",
        "reception",
        "lodging",
        "corporate",
        "hall"
    ],
    "sg:website":"http://ad.doubleclick.net/clk;222816988;46581822;v?http://www.hiexpress.com/redirect?path=hd&brandCode=ex&hotelCode=cmhol&_PMID=99601036&cm_mmc=mdpr-_-yellowpages-_-ex-_-cmhol",
    "wof:name":"Holiday Inn Express Hotel & Suites Columbus Univ Area - Osu",
    "wof:placetype":"venue"
},
  "geometry": {"coordinates":[-83.025947,40.022934],"type":"Point"}
}