{
  "type": "Feature",
  "properties": {
    "iso:country":"US",
    "sg:address":"18319 Nottingham Rd",
    "sg:city":"Cleveland",
    "sg:classifiers":[
        {
            "category":"Wholesale",
            "subcategory":"Farm Supplies",
            "type":"Manufacturing & Wholesale Goods"
        }
    ],
    "sg:phone":"+1 216 481 8404",
    "sg:postcode":"44119",
    "sg:province":"OH",
    "sg:tags":[
        "control",
        "equipment",
        "pest"
    ],
    "wof:name":"Southern Mill Creek Products",
    "wof:placetype":"venue"
},
  "geometry": {"coordinates":[-81.55064,41.576375],"type":"Point"}
}