{
  "type": "Feature",
  "properties": {
    "addr:full":"3780 State Rte 60 Mc Connelsville OH 43756",
    "addr:housenumber":"3780",
    "addr:postcode":"43756",
    "addr:street":"State Rte 60 Mc",
    "iso:country":"US",
    "sg:address":"3780 State Rte 60",
    "sg:city":"Mc Connelsville",
    "sg:classifiers":[
        {
            "category":"Farming",
            "subcategory":"Livestock Farm",
            "type":"Manufacturing & Wholesale Goods"
        }
    ],
    "sg:phone":"+1 740 962 2060",
    "sg:postcode":"43756",
    "sg:province":"OH",
    "sg:tags":[
        "corn",
        "general"
    ],
    "wof:name":"Eddie Lindimore",
    "wof:placetype":"venue"
},
  "geometry": {"coordinates":[-81.86201199999999,39.654317],"type":"Point"}
}