{
  "type": "Feature",
  "properties": {
    "addr:full": "74 Robinson Ave Barberton OH 44203",
    "addr:housenumber": "74",
    "addr:postcode": "44203",
    "addr:street": "Robinson Ave",
    "iso:country": "US",
    "sg:address": "74 Robinson Ave",
    "sg:city": "Barberton",
    "sg:classifiers": [
      {
        "category": "Wholesale",
        "subcategory": "Hardware",
        "type": "Manufacturing \u0026 Wholesale Goods"
      }
    ],
    "sg:phone": "+1 330 753 9750",
    "sg:postcode": "44203",
    "sg:province": "OH",
    "sg:tags": [
      "used",
      "boiler"
    ],
    "sg:website": "www.babcock.com",
    "wof:name": "Babcock \u0026 Wilcox",
    "wof:placetype": "venue"
  },
  "geometry": {"coordinates":[-81.603167,41.010353],"type":"Point"}
}
