{
  "type": "Feature",
  "properties": {
    "iso:country":"US",
    "sg:address":"74 Robinson Ave",
    "sg:city":"Barberton",
    "sg:classifiers":[
        {
            "category":"Wholesale",
            "subcategory":"Hardware",
            "type":"Manufacturing & Wholesale Goods"
        }
    ],
    "sg:phone":"+1 330 753 9750",
    "sg:postcode":"44203",
    "sg:province":"OH",
    "sg:tags":[
        "used",
        "boiler"
    ],
    "sg:website":"www.babcock.com",
    "wof:name":"Babcock & Wilcox",
    "wof:placetype":"venue"
},
  "geometry": {"coordinates":[-81.603167,41.010353],"type":"Point"}
}