{
  "type": "Feature",
  "properties": {
    "iso:country":"US",
    "sg:address":"154 S. Jefferson St.",
    "sg:city":"Urbana",
    "sg:classifiers":[
        {
            "category":"Restaurant",
            "type":"Food & Drink"
        }
    ],
    "sg:menulink":"http://www.allmenus.com/oh/urbana/88029-cassanos-pizza-king/menu/",
    "sg:phone":"+1 888 294 5464",
    "sg:postcode":"43078",
    "sg:province":"OH",
    "sg:tags":[
        "american",
        "pizza"
    ],
    "wof:name":"Cassano's Pizza King",
    "wof:placetype":"venue"
},
  "geometry": {"coordinates":[-83.737786,40.105397],"type":"Point"}
}