{
  "type": "Feature",
  "properties": {
    "iso:country":"US",
    "sg:address":"141 N Murray St",
    "sg:city":"Springfield",
    "sg:classifiers":[
        {
            "category":"Retail",
            "subcategory":"Laundry & Dry Cleaning",
            "type":"Services"
        }
    ],
    "sg:phone":"+1 937 323 5544",
    "sg:postcode":"45503",
    "sg:province":"OH",
    "sg:tags":[
        "linen",
        "industrial",
        "supply"
    ],
    "wof:name":"Millers Textiles",
    "wof:placetype":"venue"
},
  "geometry": {"coordinates":[-83.800287,39.924998],"type":"Point"}
}