{
  "type": "Feature",
  "properties": {
    "iso:country":"US",
    "sg:address":"5819 Kentshire Dr",
    "sg:city":"Kettering",
    "sg:classifiers":[
        {
            "category":"Social Services",
            "subcategory":"Child Care",
            "type":"Services"
        }
    ],
    "sg:phone":"+1 937 435 8808",
    "sg:postcode":"45440",
    "sg:province":"OH",
    "wof:name":"Delightful Day Learing Ctr",
    "wof:placetype":"venue"
},
  "geometry": {"coordinates":[-84.13099,39.659952],"type":"Point"}
}