{
  "type": "Feature",
  "properties": {
    "addr:full": "951 W North Bend Rd Cincinnati OH 45224",
    "addr:housenumber": "951",
    "addr:postcode": "45224",
    "addr:street": "W North Bend Rd",
    "iso:country": "US",
    "sg:address": "951 W North Bend Rd",
    "sg:city": "Cincinnati",
    "sg:classifiers": [
      {
        "category": "Personal",
        "subcategory": "Beauty Salon",
        "type": "Services"
      }
    ],
    "sg:phone": "+1 513 541 2544",
    "sg:postcode": "45224",
    "sg:province": "OH",
    "wof:name": "Michael's J's Hair Design",
    "wof:placetype": "venue"
  },
  "geometry": {"coordinates":[-84.521168,39.201292],"type":"Point"}
}
