{
  "type": "Feature",
  "properties": {
    "addr:full":"4270 Tuller Rd Dublin OH 43017",
    "addr:housenumber":"4270",
    "addr:postcode":"43017",
    "addr:street":"Tuller Rd",
    "iso:country":"US",
    "sg:address":"4270 Tuller Rd",
    "sg:city":"Dublin",
    "sg:classifiers":[
        {
            "category":"Utilities",
            "subcategory":"Telephone",
            "type":"Services"
        }
    ],
    "sg:phone":"+1 614 793 8246",
    "sg:postcode":"43017",
    "sg:province":"OH",
    "sg:tags":[
        "company"
    ],
    "wof:name":"Time Warner Telecom Inc",
    "wof:placetype":"venue"
},
  "geometry": {"coordinates":[-83.105141,40.107741],"type":"Point"}
}