{
  "type": "Feature",
  "properties": {
    "addr:full": "904 Scott St Napoleon OH 43545",
    "addr:housenumber": "904",
    "addr:postcode": "43545",
    "addr:street": "Scott St",
    "iso:country": "US",
    "sg:address": "904 Scott St",
    "sg:city": "Napoleon",
    "sg:classifiers": [
      {
        "category": "Autos \u0026 Motor Vehicles",
        "subcategory": "Fuel \u0026 Gas Station",
        "type": "Retail Goods"
      }
    ],
    "sg:phone": "+1 419 592 1926",
    "sg:postcode": "43545",
    "sg:province": "OH",
    "sg:tags": [
      "grocery",
      "station",
      "gasoline"
    ],
    "wof:name": "Speedway 1505",
    "wof:placetype": "venue"
  },
  "geometry": {"coordinates":[-84.128272,41.393166],"type":"Point"}
}
