{
  "type": "Feature",
  "properties": {
    "iso:country":"US",
    "sg:address":"904 Scott St",
    "sg:city":"Napoleon",
    "sg:classifiers":[
        {
            "category":"Autos & Motor Vehicles",
            "subcategory":"Fuel & Gas Station",
            "type":"Retail Goods"
        }
    ],
    "sg:phone":"+1 419 592 1926",
    "sg:postcode":"43545",
    "sg:province":"OH",
    "sg:tags":[
        "grocery",
        "station",
        "gasoline"
    ],
    "wof:name":"Speedway 1505",
    "wof:placetype":"venue"
},
  "geometry": {"coordinates":[-84.128272,41.393166],"type":"Point"}
}