{
  "type": "Feature",
  "properties": {
    "addr:full":"4008 Lewis Ave Toledo OH 43612",
    "addr:housenumber":"4008",
    "addr:postcode":"43612",
    "addr:street":"Lewis Ave",
    "iso:country":"US",
    "sg:address":"4008 Lewis Ave",
    "sg:city":"Toledo",
    "sg:classifiers":[
        {
            "category":"Wholesale",
            "subcategory":"Medical Equipment & Supplies",
            "type":"Manufacturing & Wholesale Goods"
        }
    ],
    "sg:phone":"+1 419 478 0099",
    "sg:postcode":"43612",
    "sg:province":"OH",
    "sg:tags":[
        "hospital"
    ],
    "wof:name":"Cousins Medical Supply Inc",
    "wof:placetype":"venue"
},
  "geometry": {"coordinates":[-83.56533,41.693498],"type":"Point"}
}