{
  "type": "Feature",
  "properties": {
    "addr:full": "19370 Trotwood Park Strongsville OH 44149",
    "addr:postcode": "19370;44149",
    "addr:street": "Park",
    "iso:country": "US",
    "sg:address": "19370 Trotwood Park",
    "sg:city": "Strongsville",
    "sg:classifiers": [
      {
        "category": "Wholesale",
        "subcategory": "Drugs",
        "type": "Manufacturing \u0026 Wholesale Goods"
      }
    ],
    "sg:phone": "+1 440 846 8540",
    "sg:postcode": "44149",
    "sg:province": "OH",
    "wof:name": "Diller Leisa",
    "wof:placetype": "venue"
  },
  "geometry": {"coordinates":[-81.840144,41.307974],"type":"Point"}
}
