{
  "type": "Feature",
  "properties": {
    "addr:full": "407 Ottawa St Kalida OH 45853",
    "addr:housenumber": "407",
    "addr:postcode": "45853",
    "addr:street": "Ottawa St",
    "iso:country": "US",
    "sg:address": "407 Ottawa St",
    "sg:city": "Kalida",
    "sg:classifiers": [
      {
        "category": "Home \u0026 Garden",
        "subcategory": "Home Furnishings",
        "type": "Retail Goods"
      }
    ],
    "sg:phone": "+1 419 532 2043",
    "sg:postcode": "45853",
    "sg:province": "OH",
    "sg:tags": [
      "curtain",
      "made",
      "drapery"
    ],
    "wof:name": "Back Yard",
    "wof:placetype": "venue"
  },
  "geometry": {"coordinates":[-84.194032,40.981331],"type":"Point"}
}
