{
  "type": "Feature",
  "properties": {
    "iso:country":"US",
    "sg:address":"407 Ottawa St",
    "sg:city":"Kalida",
    "sg:classifiers":[
        {
            "category":"Home & Garden",
            "subcategory":"Home Furnishings",
            "type":"Retail Goods"
        }
    ],
    "sg:phone":"+1 419 532 2043",
    "sg:postcode":"45853",
    "sg:province":"OH",
    "sg:tags":[
        "curtain",
        "made",
        "drapery"
    ],
    "wof:name":"Back Yard",
    "wof:placetype":"venue"
},
  "geometry": {"coordinates":[-84.19403200000001,40.981331],"type":"Point"}
}