{
  "type": "Feature",
  "properties": {
    "addr:full": "34 E Main St Dellroy OH 44620",
    "addr:housenumber": "34",
    "addr:postcode": "44620",
    "addr:street": "E Main St",
    "iso:country": "US",
    "sg:address": "34 E Main St",
    "sg:city": "Dellroy",
    "sg:classifiers": [
      {
        "category": "Education",
        "subcategory": "School",
        "type": "Public Place"
      }
    ],
    "sg:phone": "+1 330 735 2850",
    "sg:postcode": "44620",
    "sg:province": "OH",
    "wof:name": "Dellroy Elementary School",
    "wof:placetype": "venue"
  },
  "geometry": {"coordinates":[-81.197071,40.5546],"type":"Point"}
}
