{
  "type": "Feature",
  "properties": {
    "iso:country":"US",
    "sg:address":"34 E Main St",
    "sg:city":"Dellroy",
    "sg:classifiers":[
        {
            "category":"Education",
            "subcategory":"School",
            "type":"Public Place"
        }
    ],
    "sg:phone":"+1 330 735 2850",
    "sg:postcode":"44620",
    "sg:province":"OH",
    "wof:name":"Dellroy Elementary School",
    "wof:placetype":"venue"
},
  "geometry": {"coordinates":[-81.19707099999999,40.5546],"type":"Point"}
}