{
  "type": "Feature",
  "properties": {
    "iso:country":"US",
    "sg:address":"2194 Westbelt Dr",
    "sg:city":"Columbus",
    "sg:classifiers":[
        {
            "category":"Wholesale",
            "subcategory":"Non-durable Goods",
            "type":"Manufacturing & Wholesale Goods"
        }
    ],
    "sg:phone":"+1 614 777 7774",
    "sg:postcode":"43228",
    "sg:province":"OH",
    "wof:name":"Eversole Run",
    "wof:placetype":"venue"
},
  "geometry": {"coordinates":[-83.124159,39.99177],"type":"Point"}
}