{
  "type": "Feature",
  "properties": {
    "addr:full":"5020 Reed Rd Columbus OH 43220",
    "addr:housenumber":"5020",
    "addr:postcode":"43220",
    "addr:street":"Reed Rd",
    "iso:country":"US",
    "sg:address":"5020 Reed Rd",
    "sg:city":"Columbus",
    "sg:classifiers":[
        {
            "category":"Banks & Credit Unions",
            "subcategory":"Investment Brokerage",
            "type":"Services"
        }
    ],
    "sg:phone":"+1 614 459 7159",
    "sg:postcode":"43220",
    "sg:province":"OH",
    "sg:tags":[
        "security"
    ],
    "wof:name":"Edward Jones Co",
    "wof:placetype":"venue"
},
  "geometry": {"coordinates":[-83.066558,40.061479],"type":"Point"}
}