{
  "type": "Feature",
  "properties": {
    "addr:full": "2608 Hull Rd Huron OH 44839",
    "addr:housenumber": "2608",
    "addr:postcode": "44839",
    "addr:street": "Hull Rd",
    "iso:country": "US",
    "sg:address": "2608 Hull Rd",
    "sg:city": "Huron",
    "sg:classifiers": [
      {
        "category": "Wholesale",
        "subcategory": "Durable Goods \u0026 Equipment",
        "type": "Manufacturing \u0026 Wholesale Goods"
      }
    ],
    "sg:phone": "+1 419 624 1092",
    "sg:postcode": "44839",
    "sg:province": "OH",
    "wof:name": "Always Grows Greenhouse Sups",
    "wof:placetype": "venue"
  },
  "geometry": {"coordinates":[-82.644887,41.410091],"type":"Point"}
}
