{
  "type": "Feature",
  "properties": {
    "addr:full": "1001 S Main St Baltimore OH 43105",
    "addr:housenumber": "1001",
    "addr:postcode": "43105",
    "addr:street": "S Main St",
    "iso:country": "US",
    "sg:address": "1001 S Main St",
    "sg:city": "Baltimore",
    "sg:classifiers": [
      {
        "category": "Food \u0026 Beverages",
        "subcategory": "Groceries \u0026 Convenience Stores",
        "type": "Retail Goods"
      }
    ],
    "sg:phone": "+1 740 862 4422",
    "sg:postcode": "43105",
    "sg:province": "OH",
    "sg:tags": [
      "product"
    ],
    "wof:name": "Baltimore Food Value",
    "wof:placetype": "venue"
  },
  "geometry": {"coordinates":[-82.60519,39.836604],"type":"Point"}
}
