{
  "type": "Feature",
  "properties": {
    "iso:country":"US",
    "sg:address":"9500 US Hwy 22",
    "sg:city":"Williamsport",
    "sg:classifiers":[
        {
            "category":"Sports & Exercise",
            "subcategory":"Golf",
            "type":"Entertainment"
        }
    ],
    "sg:phone":"+1 740 986 4653",
    "sg:postcode":"43164",
    "sg:province":"OH",
    "sg:tags":[
        "course"
    ],
    "wof:name":"Crown Hill Golf Course LLC",
    "wof:placetype":"venue"
},
  "geometry": {"coordinates":[-83.131138,39.58372],"type":"Point"}
}