{
  "type": "Feature",
  "properties": {
    "addr:full": "28222 State Rte 58 Sullivan OH 44880",
    "addr:housenumber": "28222",
    "addr:postcode": "44880",
    "addr:street": "State Rte 58",
    "iso:country": "US",
    "sg:address": "28222 State Rte 58",
    "sg:city": "Sullivan",
    "sg:classifiers": [
      {
        "category": "Building \u0026 Trades",
        "subcategory": "Construction",
        "type": "Services"
      }
    ],
    "sg:phone": "+1 440 647 3743",
    "sg:postcode": "44880",
    "sg:province": "OH",
    "sg:tags": [
      "contractor"
    ],
    "wof:name": "Quality Top",
    "wof:placetype": "venue"
  },
  "geometry": {"coordinates":[-82.220994,41.079834],"type":"Point"}
}
