{
  "type": "Feature",
  "properties": {
    "addr:full":"3181 State Rte 681 N Albany OH 45710",
    "addr:housenumber":"3181",
    "addr:postcode":"45710",
    "addr:street":"State Rte 681 N",
    "iso:country":"US",
    "sg:address":"3181 State Rte 681 N",
    "sg:city":"Albany",
    "sg:classifiers":[
        {
            "category":"Shopping",
            "subcategory":"Computers & Home Electronics",
            "type":"Retail Goods"
        }
    ],
    "sg:phone":"+1 740 698 9902",
    "sg:postcode":"45710",
    "sg:province":"OH",
    "wof:name":"Nitro Computers",
    "wof:placetype":"venue"
},
  "geometry": {"coordinates":[-82.217735,39.249277],"type":"Point"}
}