{
  "type": "Feature",
  "properties": {
    "iso:country":"US",
    "sg:address":"10945 Reed Hartman Hwy",
    "sg:city":"Cincinnati",
    "sg:classifiers":[
        {
            "category":"Banks & Credit Unions",
            "subcategory":"Bank",
            "type":"Services"
        }
    ],
    "sg:phone":"+1 513 793 9555",
    "sg:postcode":"45242",
    "sg:province":"OH",
    "sg:tags":[
        "loan",
        "real estate"
    ],
    "wof:name":"Premier Mortgage",
    "wof:placetype":"venue"
},
  "geometry": {"coordinates":[-84.376316,39.269065],"type":"Point"}
}