{
  "type": "Feature",
  "properties": {
    "iso:country":"US",
    "sg:address":"404 E Lincoln Way",
    "sg:city":"Minerva",
    "sg:classifiers":[
        {
            "category":"Shopping",
            "subcategory":"Gifts & Souvenirs",
            "type":"Retail Goods"
        }
    ],
    "sg:phone":"+1 330 868 2229",
    "sg:postcode":"44657",
    "sg:province":"OH",
    "wof:name":"Eclectic Collection",
    "wof:placetype":"venue"
},
  "geometry": {"coordinates":[-81.099463,40.731446],"type":"Point"}
}