{
  "type": "Feature",
  "properties": {
    "iso:country":"US",
    "sg:address":"4637 Kinsman Rd",
    "sg:city":"Middlefield",
    "sg:classifiers":[
        {
            "category":"Building & Trades",
            "subcategory":"Construction",
            "type":"Services"
        }
    ],
    "sg:phone":"+1 440 693 4264",
    "sg:postcode":"44062",
    "sg:province":"OH",
    "sg:tags":[
        "carpentry",
        "contractor"
    ],
    "wof:name":"M E Miller & Sons",
    "wof:placetype":"venue"
},
  "geometry": {"coordinates":[-80.966984,41.458376],"type":"Point"}
}