{
  "type": "Feature",
  "properties": {
    "addr:full": "224 E High St Hicksville OH 43526",
    "addr:housenumber": "224",
    "addr:postcode": "43526",
    "addr:street": "E High St",
    "iso:country": "US",
    "sg:address": "224 E High St",
    "sg:city": "Hicksville",
    "sg:classifiers": [
      {
        "category": "Professional",
        "subcategory": "Accounting \u0026 Tax Preparation",
        "type": "Services"
      }
    ],
    "sg:phone": "+1 419 542 6909",
    "sg:postcode": "43526",
    "sg:province": "OH",
    "sg:tags": [
      "return"
    ],
    "wof:name": "Expertax Inc",
    "wof:placetype": "venue"
  },
  "geometry": {"coordinates":[-84.759451,41.29506],"type":"Point"}
}
