{
  "type": "Feature",
  "properties": {
    "iso:country":"US",
    "sg:address":"3939 Mark Ave",
    "sg:city":"Rocky River",
    "sg:classifiers":[
        {
            "category":"Home & Garden",
            "subcategory":"Hardware",
            "type":"Retail Goods"
        }
    ],
    "sg:phone":"+1 440 895 0007",
    "sg:postcode":"44116",
    "sg:province":"OH",
    "wof:name":"Websters True Value Hardware",
    "wof:placetype":"venue"
},
  "geometry": {"coordinates":[-81.844736,41.454654],"type":"Point"}
}