{
  "type": "Feature",
  "properties": {
    "addr:full":"46 Co Rd 204 Centerburg OH 43011",
    "addr:housenumber":"46",
    "addr:postcode":"43011",
    "addr:street":"Co Rd 204",
    "iso:country":"US",
    "sg:address":"46 Co Rd 204",
    "sg:city":"Centerburg",
    "sg:phone":"+1 740 625 6673",
    "sg:postcode":"43011",
    "sg:province":"OH",
    "sg:tags":[
        "farm",
        "grain",
        "cash"
    ],
    "wof:name":"Raymond Hilton Farm",
    "wof:placetype":"venue"
},
  "geometry": {"coordinates":[-82.724914,40.362005],"type":"Point"}
}