{
  "type": "Feature",
  "properties": {
    "iso:country":"US",
    "sg:address":"3177 Rocky River Dr",
    "sg:city":"Cleveland",
    "sg:classifiers":[
        {
            "category":"Real Estate",
            "subcategory":"Real Estate Agent",
            "type":"Services"
        }
    ],
    "sg:phone":"+1 216 316 0187",
    "sg:postcode":"44111",
    "sg:province":"OH",
    "wof:name":"Sundance Ohio Properties",
    "wof:placetype":"venue"
},
  "geometry": {"coordinates":[-81.813574,41.465093],"type":"Point"}
}