{
  "type": "Feature",
  "properties": {
    "iso:country":"US",
    "sg:address":"2165 N Cole St",
    "sg:city":"Lima",
    "sg:classifiers":[
        {
            "category":"Organizations",
            "subcategory":"Community Association",
            "type":"Services"
        }
    ],
    "sg:phone":"+1 419 223 4661",
    "sg:postcode":"45801",
    "sg:province":"OH",
    "sg:tags":[
        "club"
    ],
    "wof:name":"Masonic Lodge",
    "wof:placetype":"venue"
},
  "geometry": {"coordinates":[-84.127996,40.768225],"type":"Point"}
}