{
  "type": "Feature",
  "properties": {
    "addr:full": "44685 Telegraph Rd Elyria OH 44035",
    "addr:housenumber": "44685",
    "addr:postcode": "44035",
    "addr:street": "Telegraph Rd",
    "iso:country": "US",
    "sg:address": "44685 Telegraph Rd",
    "sg:city": "Elyria",
    "sg:classifiers": [
      {
        "category": "Social Services",
        "subcategory": "Adult Care",
        "type": "Services"
      }
    ],
    "sg:phone": "+1 440 322 8886",
    "sg:postcode": "44035",
    "sg:province": "OH",
    "sg:tags": [
      "residential"
    ],
    "wof:name": "Plumbrook LLC",
    "wof:placetype": "venue"
  },
  "geometry": {"coordinates":[-82.179327,41.368785],"type":"Point"}
}
