{
  "type": "Feature",
  "properties": {
    "addr:full":"6632 Stillington Dr Hamilton OH 45011",
    "addr:housenumber":"6632",
    "addr:postcode":"45011",
    "addr:street":"Stillington Dr",
    "iso:country":"US",
    "sg:address":"6632 Stillington Dr",
    "sg:city":"Hamilton",
    "sg:classifiers":[
        {
            "category":"Building & Trades",
            "subcategory":"Construction",
            "type":"Services"
        }
    ],
    "sg:phone":"+1 513 382 2392",
    "sg:postcode":"45011",
    "sg:province":"OH",
    "sg:tags":[
        "home",
        "builder"
    ],
    "wof:name":"R L Varelmann Builders Inc",
    "wof:placetype":"venue"
},
  "geometry": {"coordinates":[-84.418278,39.383683],"type":"Point"}
}