{
  "type": "Feature",
  "properties": {
    "addr:full":"3687 Langton Rd Cleveland OH 44121",
    "addr:housenumber":"3687",
    "addr:postcode":"44121",
    "addr:street":"Langton Rd",
    "iso:country":"US",
    "sg:address":"3687 Langton Rd",
    "sg:city":"Cleveland",
    "sg:classifiers":[
        {
            "category":"Organizations",
            "subcategory":"Religious Organization",
            "type":"Services"
        }
    ],
    "sg:phone":"+1 216 291 9503",
    "sg:postcode":"44121",
    "sg:province":"OH",
    "sg:tags":[
        "clergy"
    ],
    "wof:name":"Benjamin G Finney",
    "wof:placetype":"venue"
},
  "geometry": {"coordinates":[-81.55027200000001,41.540555],"type":"Point"}
}