{
  "type": "Feature",
  "properties": {
    "iso:country":"US",
    "sg:address":"2725 Floribunda Dr",
    "sg:city":"Columbus",
    "sg:classifiers":[
        {
            "category":"Manufacturing",
            "subcategory":"Tools & Machinery",
            "type":"Manufacturing & Wholesale Goods"
        }
    ],
    "sg:phone":"+1 614 238 9000",
    "sg:postcode":"43209",
    "sg:province":"OH",
    "sg:tags":[
        "equipment",
        "purifying",
        "cleaning",
        "air"
    ],
    "wof:name":"General Innovations & Goods",
    "wof:placetype":"venue"
},
  "geometry": {"coordinates":[-82.91986799999999,39.937789],"type":"Point"}
}