{
  "type": "Feature",
  "properties": {
    "addr:full": "2725 Floribunda Dr Columbus OH 43209",
    "addr:housenumber": "2725",
    "addr:postcode": "43209",
    "addr:street": "Floribunda Dr",
    "iso:country": "US",
    "sg:address": "2725 Floribunda Dr",
    "sg:city": "Columbus",
    "sg:classifiers": [
      {
        "category": "Manufacturing",
        "subcategory": "Tools \u0026 Machinery",
        "type": "Manufacturing \u0026 Wholesale Goods"
      }
    ],
    "sg:phone": "+1 614 238 9000",
    "sg:postcode": "43209",
    "sg:province": "OH",
    "sg:tags": [
      "equipment",
      "purifying",
      "cleaning",
      "air"
    ],
    "wof:name": "General Innovations \u0026 Goods",
    "wof:placetype": "venue"
  },
  "geometry": {"coordinates":[-82.919868,39.937789],"type":"Point"}
}
