{
  "type": "Feature",
  "properties": {
    "addr:full": "4130 Linden Ave Dayton OH 45432",
    "addr:housenumber": "4130",
    "addr:postcode": "45432",
    "addr:street": "Linden Ave",
    "iso:country": "US",
    "sg:address": "4130 Linden Ave",
    "sg:city": "Dayton",
    "sg:classifiers": [
      {
        "category": "Professional",
        "subcategory": "Detective \u0026 Security Services",
        "type": "Services"
      }
    ],
    "sg:phone": "+1 937 253 0193",
    "sg:postcode": "45432",
    "sg:province": "OH",
    "sg:tags": [
      "car"
    ],
    "wof:name": "U S Security Associates Inc",
    "wof:placetype": "venue"
  },
  "geometry": {"coordinates":[-84.122486,39.745184],"type":"Point"}
}
