{
  "type": "Feature",
  "properties": {
    "addr:full":"3976 Mayfield Rd Cleveland OH 44121",
    "addr:housenumber":"3976",
    "addr:postcode":"44121",
    "addr:street":"Mayfield Rd",
    "iso:country":"US",
    "sg:address":"3976 Mayfield Rd",
    "sg:city":"Cleveland",
    "sg:classifiers":[
        {
            "category":"Retail",
            "subcategory":"Repair Shop",
            "type":"Services"
        }
    ],
    "sg:phone":"+1 216 691 9344",
    "sg:postcode":"44121",
    "sg:province":"OH",
    "sg:tags":[
        "upholsterer"
    ],
    "wof:name":"By The Yard",
    "wof:placetype":"venue"
},
  "geometry": {"coordinates":[-81.53698199999999,41.520618],"type":"Point"}
}