{
  "type": "Feature",
  "properties": {
    "addr:full": "1170 E 152nd St Cleveland OH 44110",
    "addr:housenumber": "1170",
    "addr:postcode": "44110",
    "addr:street": "E 152Nd St",
    "iso:country": "US",
    "sg:address": "1170 E 152nd St",
    "sg:city": "Cleveland",
    "sg:classifiers": [
      {
        "category": "Shopping",
        "subcategory": "Hobbies, Toys, \u0026 Games",
        "type": "Retail Goods"
      }
    ],
    "sg:phone": "+1 216 268 2152",
    "sg:postcode": "44110",
    "sg:province": "OH",
    "sg:tags": [
      "model",
      "supply"
    ],
    "wof:name": "R C Spectrum",
    "wof:placetype": "venue"
  },
  "geometry": {"coordinates":[-81.575425,41.545968],"type":"Point"}
}
