{
  "type": "Feature",
  "properties": {
    "iso:country":"US",
    "sg:address":"231 Main St",
    "sg:city":"Chardon",
    "sg:classifiers":[
        {
            "category":"Government",
            "subcategory":"Office",
            "type":"Public Place"
        }
    ],
    "sg:phone":"+1 440 285 2305",
    "sg:postcode":"44077",
    "sg:province":"OH",
    "wof:name":"Geauga Cnty Juvenile Probate",
    "wof:placetype":"venue"
},
  "geometry": {"coordinates":[-81.240973,41.726239],"type":"Point"}
}