{
  "type": "Feature",
  "properties": {
    "addr:full": "1275 Roosevelt Ave Zanesville OH 43701",
    "addr:housenumber": "1275",
    "addr:postcode": "43701",
    "addr:street": "Roosevelt Ave",
    "iso:country": "US",
    "sg:address": "1275 Roosevelt Ave",
    "sg:city": "Zanesville",
    "sg:classifiers": [
      {
        "category": "Education",
        "subcategory": "School",
        "type": "Public Place"
      }
    ],
    "sg:phone": "+1 740 453 0711",
    "sg:postcode": "43701",
    "sg:province": "OH",
    "sg:website": "www.zanesville.k12.oh.us",
    "wof:name": "Roosevelt Middle School",
    "wof:placetype": "venue"
  },
  "geometry": {"coordinates":[-82.019284,39.950841],"type":"Point"}
}
