{
  "type": "Feature",
  "properties": {
    "addr:full": "491 Ohio Pike Cincinnati OH 45255",
    "addr:housenumber": "491",
    "addr:postcode": "45255",
    "addr:street": "Ohio Pike",
    "iso:country": "US",
    "sg:address": "491 Ohio Pike",
    "sg:city": "Cincinnati",
    "sg:classifiers": [
      {
        "category": "Recreation",
        "subcategory": "Amusement Park",
        "type": "Entertainment"
      }
    ],
    "sg:phone": "+1 513 528 3696",
    "sg:postcode": "45255",
    "sg:province": "OH",
    "sg:tags": [
      "party",
      "planning",
      "event"
    ],
    "sg:website": "www.scallywagtag.com",
    "wof:name": "Scallywag Tag Laser Tag",
    "wof:placetype": "venue"
  },
  "geometry": {"coordinates":[-84.307962,39.071353],"type":"Point"}
}
