{
  "type": "Feature",
  "properties": {
    "addr:full":"135 S James Rd Columbus OH 43213",
    "addr:housenumber":"135",
    "addr:postcode":"43213",
    "addr:street":"S James Rd",
    "iso:country":"US",
    "sg:address":"135 S James Rd",
    "sg:city":"Columbus",
    "sg:classifiers":[
        {
            "category":"Professional",
            "subcategory":"Computer Services",
            "type":"Services"
        }
    ],
    "sg:phone":"+1 614 236 8487",
    "sg:postcode":"43213",
    "sg:province":"OH",
    "sg:tags":[
        "consultant",
        "designer"
    ],
    "wof:name":"Zebulun Enterprises Inc",
    "wof:placetype":"venue"
},
  "geometry": {"coordinates":[-82.913752,39.970078],"type":"Point"}
}