{
  "type": "Feature",
  "properties": {
    "addr:full":"955 Eastwind Dr Westerville OH 43081",
    "addr:housenumber":"955",
    "addr:postcode":"43081",
    "addr:street":"Eastwind Dr",
    "iso:country":"US",
    "sg:address":"955 Eastwind Dr",
    "sg:city":"Westerville",
    "sg:classifiers":[
        {
            "category":"Building & Trades",
            "subcategory":"Equipment Rental",
            "type":"Services"
        }
    ],
    "sg:phone":"+1 614 891 3629",
    "sg:postcode":"43081",
    "sg:province":"OH",
    "sg:tags":[
        "leasing"
    ],
    "wof:name":"Moore Leasing Co",
    "wof:placetype":"venue"
},
  "geometry": {"coordinates":[-82.91788699999999,40.100916],"type":"Point"}
}