{
  "type": "Feature",
  "properties": {
    "addr:full":"120 Corry St Yellow Springs OH 45387",
    "addr:housenumber":"120",
    "addr:postcode":"45387",
    "addr:street":"Corry St",
    "iso:country":"US",
    "sg:address":"120 Corry St",
    "sg:city":"Yellow Springs",
    "sg:classifiers":[
        {
            "category":"Government",
            "subcategory":"Post Office",
            "type":"Public Place"
        }
    ],
    "sg:phone":"+1 937 767 7458",
    "sg:postcode":"45387",
    "sg:province":"OH",
    "wof:name":"US Post Office",
    "wof:placetype":"venue"
},
  "geometry": {"coordinates":[-83.888482,39.806651],"type":"Point"}
}