{
  "type": "Feature",
  "properties": {
    "addr:full":"4125 Bradley Rd Westlake OH 44145",
    "addr:housenumber":"4125",
    "addr:postcode":"44145",
    "addr:street":"Bradley Rd",
    "iso:country":"US",
    "sg:address":"4125 Bradley Rd",
    "sg:city":"Westlake",
    "sg:classifiers":[
        {
            "category":"Freight",
            "type":"Transportation"
        }
    ],
    "sg:phone":"+1 216 661 5511",
    "sg:postcode":"44145",
    "sg:province":"OH",
    "sg:tags":[
        "general"
    ],
    "wof:name":"Farrous Metal Transfer Company",
    "wof:placetype":"venue"
},
  "geometry": {"coordinates":[-81.96149699999999,41.429759],"type":"Point"}
}