{
  "type": "Feature",
  "properties": {
    "addr:full": "20337 Shadley Valley Rd Danville OH 43014",
    "addr:housenumber": "20337",
    "addr:postcode": "43014",
    "addr:street": "Shadley Valley Rd",
    "iso:country": "US",
    "sg:address": "20337 Shadley Valley Rd",
    "sg:city": "Danville",
    "sg:classifiers": [
      {
        "category": "Organizations",
        "subcategory": "Membership Organization",
        "type": "Services"
      }
    ],
    "sg:phone": "+1 740 599 6074",
    "sg:postcode": "43014",
    "sg:province": "OH",
    "wof:name": "Progress Club of Loudonvi",
    "wof:placetype": "venue"
  },
  "geometry": {"coordinates":[-82.285375,40.520464],"type":"Point"}
}
