{
  "type": "Feature",
  "properties": {
    "addr:full":"3801 Shady Run Rd Youngstown OH 44502",
    "addr:housenumber":"3801",
    "addr:postcode":"44502",
    "addr:street":"Shady Run Rd",
    "iso:country":"US",
    "sg:address":"3801 Shady Run Rd",
    "sg:city":"Youngstown",
    "sg:classifiers":[
        {
            "category":"Restaurant",
            "type":"Food & Drink"
        }
    ],
    "sg:phone":"+1 330 781 1980",
    "sg:postcode":"44502",
    "sg:province":"OH",
    "sg:tags":[
        "caterer"
    ],
    "wof:name":"Peppers Gourmet Foods & Ctrng",
    "wof:placetype":"venue"
},
  "geometry": {"coordinates":[-80.63390800000001,41.063834],"type":"Point"}
}