{
  "type": "Feature",
  "properties": {
    "addr:full": "11777 W Airport Svc Rd Swanton OH 43558",
    "addr:housenumber": "11777",
    "addr:postcode": "43558",
    "addr:street": "W Airport Svc Rd",
    "iso:country": "US",
    "sg:address": "11777 W Airport Svc Rd",
    "sg:city": "Swanton",
    "sg:classifiers": [
      {
        "category": "Freight",
        "type": "Transportation"
      }
    ],
    "sg:phone": "+1 419 861 6707",
    "sg:postcode": "43558",
    "sg:province": "OH",
    "wof:name": "Grand Logistics LLC",
    "wof:placetype": "venue"
  },
  "geometry": {"coordinates":[-83.817634,41.589897],"type":"Point"}
}
