{
  "type": "Feature",
  "properties": {
    "iso:country":"US",
    "sg:address":"7575 Tyler Blvd",
    "sg:city":"Mentor",
    "sg:classifiers":[
        {
            "category":"Arts & Performance",
            "subcategory":"Theater",
            "type":"Entertainment"
        }
    ],
    "sg:phone":"+1 440 602 9935",
    "sg:postcode":"44060",
    "sg:province":"OH",
    "sg:tags":[
        "live",
        "music"
    ],
    "wof:name":"Blazin Entertainment",
    "wof:placetype":"venue"
},
  "geometry": {"coordinates":[-81.35912999999999,41.679077],"type":"Point"}
}