{
  "type": "Feature",
  "properties": {
    "addr:full": "7575 Tyler Blvd Mentor OH 44060",
    "addr:housenumber": "7575",
    "addr:postcode": "44060",
    "addr:street": "Tyler Blvd",
    "iso:country": "US",
    "sg:address": "7575 Tyler Blvd",
    "sg:city": "Mentor",
    "sg:classifiers": [
      {
        "category": "Arts \u0026 Performance",
        "subcategory": "Theater",
        "type": "Entertainment"
      }
    ],
    "sg:phone": "+1 440 602 9935",
    "sg:postcode": "44060",
    "sg:province": "OH",
    "sg:tags": [
      "live",
      "music"
    ],
    "wof:name": "Blazin Entertainment",
    "wof:placetype": "venue"
  },
  "geometry": {"coordinates":[-81.35913,41.679077],"type":"Point"}
}
