{
  "type": "Feature",
  "properties": {
    "addr:full": "5366 Co Hwy 349 Millersburg OH 44654",
    "addr:housenumber": "5366",
    "addr:postcode": "44654",
    "addr:street": "Co Hwy 349",
    "iso:country": "US",
    "sg:address": "5366 Co Hwy 349",
    "sg:city": "Millersburg",
    "sg:classifiers": [
      {
        "category": "Manufacturing",
        "subcategory": "Glass \u0026 Minerals",
        "type": "Manufacturing \u0026 Wholesale Goods"
      }
    ],
    "sg:phone": "+1 330 674 4254",
    "sg:postcode": "44654",
    "sg:province": "OH",
    "sg:tags": [
      "ready"
    ],
    "wof:name": "Menuez Bros Sand \u0026 Gravel Inc",
    "wof:placetype": "venue"
  },
  "geometry": {"coordinates":[-81.933822,40.567556],"type":"Point"}
}
