{
  "type": "Feature",
  "properties": {
    "iso:country":"US",
    "sg:address":"5366 Co Hwy 349",
    "sg:city":"Millersburg",
    "sg:classifiers":[
        {
            "category":"Manufacturing",
            "subcategory":"Glass & Minerals",
            "type":"Manufacturing & Wholesale Goods"
        }
    ],
    "sg:phone":"+1 330 674 4254",
    "sg:postcode":"44654",
    "sg:province":"OH",
    "sg:tags":[
        "ready"
    ],
    "wof:name":"Menuez Bros Sand & Gravel Inc",
    "wof:placetype":"venue"
},
  "geometry": {"coordinates":[-81.93382200000001,40.567556],"type":"Point"}
}