{
  "type": "Feature",
  "properties": {
    "addr:full":"11132 Luschek Dr Cincinnati OH 45241",
    "addr:housenumber":"11132",
    "addr:postcode":"45241",
    "addr:street":"Luschek Dr",
    "iso:country":"US",
    "sg:address":"11132 Luschek Dr",
    "sg:city":"Cincinnati",
    "sg:classifiers":[
        {
            "category":"Professional",
            "subcategory":"Research",
            "type":"Services"
        }
    ],
    "sg:phone":"+1 513 923 9000",
    "sg:postcode":"45241",
    "sg:province":"OH",
    "sg:tags":[
        "control",
        "system",
        "controls",
        "regulator",
        "environmental",
        "ecological"
    ],
    "sg:website":"http://www.cecinc.com",
    "wof:name":"Superior Environmental Corp.",
    "wof:placetype":"venue"
},
  "geometry": {"coordinates":[-84.380315,39.269125],"type":"Point"}
}