{
  "type": "Feature",
  "properties": {
    "iso:country":"US",
    "sg:address":"24656 Albert Ln",
    "sg:city":"Cleveland",
    "sg:classifiers":[
        {
            "category":"Insurance",
            "subcategory":"Insurance Agent",
            "type":"Services"
        }
    ],
    "sg:phone":"+1 216 292 6933",
    "sg:postcode":"44122",
    "sg:province":"OH",
    "wof:name":"Marvin S Krasney & Assoc Inc",
    "wof:placetype":"venue"
},
  "geometry": {"coordinates":[-81.50435,41.484996],"type":"Point"}
}