{
  "type": "Feature",
  "properties": {
    "iso:country":"US",
    "sg:address":"625 E Main St",
    "sg:city":"Alliance",
    "sg:classifiers":[
        {
            "category":"Social Services",
            "type":"Services"
        }
    ],
    "sg:phone":"+1 330 823 1301",
    "sg:postcode":"44601",
    "sg:province":"OH",
    "sg:tags":[
        "organization",
        "welfare"
    ],
    "wof:name":"Alliance Friendship Ctr",
    "wof:placetype":"venue"
},
  "geometry": {"coordinates":[-81.09643199999999,40.921701],"type":"Point"}
}