{
  "type": "Feature",
  "properties": {
    "iso:country":"US",
    "sg:address":"1083 High St",
    "sg:city":"Hamilton",
    "sg:classifiers":[
        {
            "category":"Shopping",
            "subcategory":"Used Merchandise",
            "type":"Retail Goods"
        }
    ],
    "sg:phone":"+1 513 868 6200",
    "sg:postcode":"45011",
    "sg:province":"OH",
    "sg:tags":[
        "pawnbroker"
    ],
    "wof:name":"Southern Ohio Gold Silver Exch",
    "wof:placetype":"venue"
},
  "geometry": {"coordinates":[-84.551045,39.396488],"type":"Point"}
}