{
  "type": "Feature",
  "properties": {
    "addr:full": "9305 Olde Eight Rd Northfield OH 44067",
    "addr:housenumber": "9305",
    "addr:postcode": "44067",
    "addr:street": "Olde Eight Rd",
    "iso:country": "US",
    "sg:address": "9305 Olde Eight Rd",
    "sg:city": "Northfield",
    "sg:classifiers": [
      {
        "category": "Social Services",
        "subcategory": "Child Care",
        "type": "Services"
      }
    ],
    "sg:phone": "+1 330 467 7800",
    "sg:postcode": "44067",
    "sg:province": "OH",
    "wof:name": "First Class Pre-School Ctr",
    "wof:placetype": "venue"
  },
  "geometry": {"coordinates":[-81.536774,41.311642],"type":"Point"}
}
