{
  "type": "Feature",
  "properties": {
    "addr:full":"1104 N High St Columbus OH 43201",
    "addr:housenumber":"1104",
    "addr:postcode":"43201",
    "addr:street":"N High St",
    "iso:country":"US",
    "sg:address":"1104 N High St",
    "sg:city":"Columbus",
    "sg:classifiers":[
        {
            "category":"Shopping",
            "subcategory":"Clothing, Apparel, & Fashions",
            "type":"Retail Goods"
        }
    ],
    "sg:phone":"+1 614 294 2022",
    "sg:postcode":"43201",
    "sg:province":"OH",
    "sg:tags":[
        "family"
    ],
    "wof:name":"Friday The 13th LLC",
    "wof:placetype":"venue"
},
  "geometry": {"coordinates":[-83.004926,39.984283],"type":"Point"}
}