{
  "type": "Feature",
  "properties": {
    "addr:full": "4009 E 86th St Cleveland OH 44105",
    "addr:housenumber": "4009",
    "addr:postcode": "44105",
    "addr:street": "E 86Th St",
    "iso:country": "US",
    "sg:address": "4009 E 86th St",
    "sg:city": "Cleveland",
    "sg:classifiers": [
      {
        "category": "Wholesale",
        "subcategory": "Auto Parts",
        "type": "Manufacturing \u0026 Wholesale Goods"
      }
    ],
    "sg:phone": "+1 216 254 1758",
    "sg:postcode": "44105",
    "sg:province": "OH",
    "sg:tags": [
      "automobile",
      "wrecking"
    ],
    "wof:name": "J Mobley's Recycling",
    "wof:placetype": "venue"
  },
  "geometry": {"coordinates":[-81.626687,41.448926],"type":"Point"}
}
