{
  "type": "Feature",
  "properties": {
    "iso:country":"US",
    "sg:address":"4009 E 86th St",
    "sg:city":"Cleveland",
    "sg:classifiers":[
        {
            "category":"Wholesale",
            "subcategory":"Auto Parts",
            "type":"Manufacturing & Wholesale Goods"
        }
    ],
    "sg:phone":"+1 216 254 1758",
    "sg:postcode":"44105",
    "sg:province":"OH",
    "sg:tags":[
        "automobile",
        "wrecking"
    ],
    "wof:name":"J Mobley's Recycling",
    "wof:placetype":"venue"
},
  "geometry": {"coordinates":[-81.626687,41.448926],"type":"Point"}
}