{
  "type": "Feature",
  "properties": {
    "iso:country":"US",
    "sg:address":"137 S Main St",
    "sg:city":"Bethel",
    "sg:classifiers":[
        {
            "category":"Building & Trades",
            "subcategory":"Construction",
            "type":"Services"
        }
    ],
    "sg:phone":"+1 513 734 6889",
    "sg:postcode":"45106",
    "sg:province":"OH",
    "sg:tags":[
        "house",
        "general",
        "contractor"
    ],
    "wof:name":"Sugartree Construction Co",
    "wof:placetype":"venue"
},
  "geometry": {"coordinates":[-84.081371,38.962078],"type":"Point"}
}