{
  "type": "Feature",
  "properties": {
    "addr:full":"1606 Goodman Ave Cincinnati OH 45239",
    "addr:housenumber":"1606",
    "addr:postcode":"45239",
    "addr:street":"Goodman Ave",
    "iso:country":"US",
    "sg:address":"1606 Goodman Ave",
    "sg:city":"Cincinnati",
    "sg:classifiers":[
        {
            "category":"Professional",
            "subcategory":"Art Services",
            "type":"Services"
        }
    ],
    "sg:phone":"+1 513 522 5733",
    "sg:postcode":"45239",
    "sg:province":"OH",
    "sg:tags":[
        "photographer"
    ],
    "wof:name":"Huitger Photography",
    "wof:placetype":"venue"
},
  "geometry": {"coordinates":[-84.551436,39.21635],"type":"Point"}
}