{
  "type": "Feature",
  "properties": {
    "addr:full": "294 E Main St Jackson OH 45640",
    "addr:housenumber": "294",
    "addr:postcode": "45640",
    "addr:street": "E Main St",
    "iso:country": "US",
    "sg:address": "294 E Main St",
    "sg:city": "Jackson",
    "sg:classifiers": [
      {
        "category": "Banks \u0026 Credit Unions",
        "subcategory": "Bank",
        "type": "Services"
      }
    ],
    "sg:phone": "+1 740 286 6699",
    "sg:postcode": "45640",
    "sg:province": "OH",
    "sg:tags": [
      "depository",
      "banking",
      "check",
      "cashing"
    ],
    "wof:name": "Ohio Valley Check Cashing \u0026 Ln",
    "wof:placetype": "venue"
  },
  "geometry": {"coordinates":[-82.631346,39.047001],"type":"Point"}
}
