{
  "type": "Feature",
  "properties": {
    "iso:country":"US",
    "sg:address":"19751 Co Rd D",
    "sg:city":"Archbold",
    "sg:phone":"+1 419 445 7316",
    "sg:postcode":"43502",
    "sg:province":"OH",
    "sg:tags":[
        "farm",
        "corn",
        "soybean"
    ],
    "wof:name":"Beck Garold",
    "wof:placetype":"venue"
},
  "geometry": {"coordinates":[-84.24366999999999,41.528797],"type":"Point"}
}