{
  "type": "Feature",
  "properties": {
    "addr:full": "5685 Ravenna Ave NE Louisville OH 44641",
    "addr:housenumber": "5685",
    "addr:postcode": "44641",
    "addr:street": "Ravenna Ave Ne",
    "iso:country": "US",
    "sg:address": "5685 Ravenna Ave NE",
    "sg:city": "Louisville",
    "sg:classifiers": [
      {
        "category": "Wholesale",
        "subcategory": "Groceries",
        "type": "Manufacturing \u0026 Wholesale Goods"
      }
    ],
    "sg:phone": "+1 330 875 1441",
    "sg:postcode": "44641",
    "sg:province": "OH",
    "sg:tags": [
      "food",
      "broker"
    ],
    "wof:name": "Specialty Foods",
    "wof:placetype": "venue"
  },
  "geometry": {"coordinates":[-81.258865,40.853284],"type":"Point"}
}
