{
  "type": "Feature",
  "properties": {
    "iso:country":"US",
    "sg:address":"5685 Ravenna Ave NE",
    "sg:city":"Louisville",
    "sg:classifiers":[
        {
            "category":"Wholesale",
            "subcategory":"Groceries",
            "type":"Manufacturing & Wholesale Goods"
        }
    ],
    "sg:phone":"+1 330 875 1441",
    "sg:postcode":"44641",
    "sg:province":"OH",
    "sg:tags":[
        "food",
        "broker"
    ],
    "wof:name":"Specialty Foods",
    "wof:placetype":"venue"
},
  "geometry": {"coordinates":[-81.258865,40.853284],"type":"Point"}
}