{
  "type": "Feature",
  "properties": {
    "addr:full":"2131 Salem Ave Dayton OH 45406",
    "addr:housenumber":"2131",
    "addr:postcode":"45406",
    "addr:street":"Salem Ave",
    "iso:country":"US",
    "sg:address":"2131 Salem Ave",
    "sg:city":"Dayton",
    "sg:classifiers":[
        {
            "category":"Wholesale",
            "subcategory":"Non-durable Goods",
            "type":"Manufacturing & Wholesale Goods"
        }
    ],
    "sg:phone":"+1 937 274 1111",
    "sg:postcode":"45406",
    "sg:province":"OH",
    "sg:tags":[
        "piece",
        "man"
    ],
    "wof:name":"Ambassador Designs",
    "wof:placetype":"venue"
},
  "geometry": {"coordinates":[-84.227239,39.783461],"type":"Point"}
}