{
  "type": "Feature",
  "properties": {
    "addr:full":"48 Northfield Rd Bedford OH 44146",
    "addr:housenumber":"48",
    "addr:postcode":"44146",
    "addr:street":"Northfield Rd",
    "iso:country":"US",
    "sg:address":"48 Northfield Rd",
    "sg:city":"Bedford",
    "sg:classifiers":[
        {
            "category":"Retail",
            "subcategory":"Auto Repair",
            "type":"Services"
        }
    ],
    "sg:phone":"+1 440 439 8177",
    "sg:postcode":"44146",
    "sg:province":"OH",
    "sg:tags":[
        "transmission",
        "shop"
    ],
    "wof:name":"Cottman Transmission Ctr",
    "wof:placetype":"venue"
},
  "geometry": {"coordinates":[-81.526983,41.382239],"type":"Point"}
}