{
  "type": "Feature",
  "properties": {
    "addr:full": "4660 Creek Rd Cincinnati OH 45242",
    "addr:housenumber": "4660",
    "addr:postcode": "45242",
    "addr:street": "Creek Rd",
    "iso:country": "US",
    "sg:address": "4660 Creek Rd",
    "sg:city": "Cincinnati",
    "sg:classifiers": [
      {
        "category": "Travel",
        "subcategory": "Hotels \u0026 Motels",
        "type": "Entertainment"
      },
      {
        "category": "Retail",
        "subcategory": "Event Space",
        "type": "Services"
      }
    ],
    "sg:phone": "+1 800 345 8082",
    "sg:postcode": "45242",
    "sg:province": "OH",
    "sg:tags": [
      "facility",
      "banquet",
      "reception",
      "lodging",
      "corporate",
      "hall"
    ],
    "sg:website": "http://ad.doubleclick.net/clk;222816988;46581822;v?http://www.hiexpress.com/redirect?path=hd\u0026brandCode=ex\u0026hotelCode=blhoh\u0026_PMID=99601036\u0026cm_mmc=mdpr-_-yellowpages-_-ex-_-blhoh",
    "wof:name": "Holiday Inn Express Hotel \u0026 Suites Cincinnati-Blue Ash",
    "wof:placetype": "venue"
  },
  "geometry": {"coordinates":[-84.378602,39.259147],"type":"Point"}
}
