{
  "type": "Feature",
  "properties": {
    "addr:full":"11203 Lawnford Ave Beach City OH 44608",
    "addr:housenumber":"11203",
    "addr:postcode":"44608",
    "addr:street":"Lawnford Ave",
    "iso:country":"US",
    "sg:address":"11203 Lawnford Ave",
    "sg:city":"Beach City",
    "sg:classifiers":[
        {
            "category":"Retail",
            "subcategory":"Auto Repair",
            "type":"Services"
        }
    ],
    "sg:phone":"+1 330 359 5966",
    "sg:postcode":"44608",
    "sg:province":"OH",
    "sg:tags":[
        "repairing",
        "automobile"
    ],
    "wof:name":"Lawnford Repair",
    "wof:placetype":"venue"
},
  "geometry": {"coordinates":[-81.637484,40.654742],"type":"Point"}
}