{
  "type": "Feature",
  "properties": {
    "addr:full": "917 Two Ridge Rd Steubenville OH 43953",
    "addr:housenumber": "917",
    "addr:postcode": "43953",
    "addr:street": "Two Ridge Rd",
    "iso:country": "US",
    "sg:address": "917 Two Ridge Rd",
    "sg:city": "Steubenville",
    "sg:classifiers": [
      {
        "category": "Food \u0026 Beverages",
        "subcategory": "Groceries \u0026 Convenience Stores",
        "type": "Retail Goods"
      }
    ],
    "sg:phone": "+1 740 266 7660",
    "sg:postcode": "43953",
    "sg:province": "OH",
    "wof:name": "Two Ridge Market",
    "wof:placetype": "venue"
  },
  "geometry": {"coordinates":[-80.728894,40.38714],"type":"Point"}
}
