{
  "type": "Feature",
  "properties": {
    "addr:full": "1001 S Main St Dayton OH 45409",
    "addr:housenumber": "1001",
    "addr:postcode": "45409",
    "addr:street": "S Main St",
    "iso:country": "US",
    "sg:address": "1001 S Main St",
    "sg:city": "Dayton",
    "sg:classifiers": [
      {
        "category": "Government",
        "subcategory": "Office",
        "type": "Public Place"
      }
    ],
    "sg:phone": "+1 937 224 9654",
    "sg:postcode": "45409",
    "sg:province": "OH",
    "sg:tags": [
      "agricultural",
      "regulation",
      "marketing"
    ],
    "wof:name": "Montgomery County EXT Agcy",
    "wof:placetype": "venue"
  },
  "geometry": {"coordinates":[-84.187482,39.74371],"type":"Point"}
}
