{
  "type": "Feature",
  "properties": {
    "addr:full":"9912 Carver Rd Cincinnati OH 45242",
    "addr:housenumber":"9912",
    "addr:postcode":"45242",
    "addr:street":"Carver Rd",
    "iso:country":"US",
    "sg:address":"9912 Carver Rd",
    "sg:city":"Cincinnati",
    "sg:classifiers":[
        {
            "category":"Real Estate",
            "subcategory":"Real Estate Agent",
            "type":"Services"
        }
    ],
    "sg:phone":"+1 513 769 2500",
    "sg:postcode":"45242",
    "sg:province":"OH",
    "sg:tags":[
        "manager"
    ],
    "wof:name":"Everest Group The Inc",
    "wof:placetype":"venue"
},
  "geometry": {"coordinates":[-84.385367,39.243608],"type":"Point"}
}