{
  "type": "Feature",
  "properties": {
    "iso:country":"US",
    "sg:address":"51323 Co Rd 16",
    "sg:city":"Coshocton",
    "sg:classifiers":[
        {
            "category":"Shopping",
            "subcategory":"Florist",
            "type":"Retail Goods"
        }
    ],
    "sg:phone":"+1 740 622 0999",
    "sg:postcode":"43812",
    "sg:province":"OH",
    "wof:name":"Flowers By Road Silk Flowers",
    "wof:placetype":"venue"
},
  "geometry": {"coordinates":[-81.79106400000001,40.277699],"type":"Point"}
}