{
  "type": "Feature",
  "properties": {
    "addr:full": "2487 Stringtown Rd Grove City OH 43123",
    "addr:housenumber": "2487",
    "addr:postcode": "43123",
    "addr:street": "Stringtown Rd",
    "iso:country": "US",
    "sg:address": "2487 Stringtown Rd",
    "sg:city": "Grove City",
    "sg:classifiers": [
      {
        "category": "Autos \u0026 Motor Vehicles",
        "subcategory": "Fuel \u0026 Gas Station",
        "type": "Retail Goods"
      }
    ],
    "sg:phone": "+1 614 871 2602",
    "sg:postcode": "43123",
    "sg:province": "OH",
    "sg:tags": [
      "oil"
    ],
    "wof:name": "BP Oil Co",
    "wof:placetype": "venue"
  },
  "geometry": {"coordinates":[-83.06495,39.879326],"type":"Point"}
}
