{
  "type": "Feature",
  "properties": {
    "addr:full": "1829 Vine St Cincinnati OH 45202",
    "addr:housenumber": "1829",
    "addr:postcode": "45202",
    "addr:street": "Vine St",
    "iso:country": "US",
    "sg:address": "1829 Vine St",
    "sg:city": "Cincinnati",
    "sg:classifiers": [
      {
        "category": "Food \u0026 Beverages",
        "subcategory": "Groceries \u0026 Convenience Stores",
        "type": "Retail Goods"
      }
    ],
    "sg:phone": "+1 513 381 2281",
    "sg:postcode": "45202",
    "sg:province": "OH",
    "sg:tags": [
      "alcoholic"
    ],
    "wof:name": "B \u0026 C",
    "wof:placetype": "venue"
  },
  "geometry": {"coordinates":[-84.516966,39.116676],"type":"Point"}
}
