{
  "type": "Feature",
  "properties": {
    "iso:country":"US",
    "sg:address":"209 N Reynolds Rd",
    "sg:city":"Toledo",
    "sg:classifiers":[
        {
            "category":"Real Estate",
            "subcategory":"Real Estate Agent",
            "type":"Services"
        }
    ],
    "sg:phone":"+1 419 535 1363",
    "sg:postcode":"43615",
    "sg:province":"OH",
    "wof:name":"Danberry Realtors",
    "wof:placetype":"venue"
},
  "geometry": {"coordinates":[-83.664637,41.641135],"type":"Point"}
}