{
  "type": "Feature",
  "properties": {
    "addr:full":"985 W Locust St Wilmington OH 45177",
    "addr:housenumber":"985",
    "addr:postcode":"45177",
    "addr:street":"W Locust St",
    "iso:country":"US",
    "sg:address":"985 W Locust St",
    "sg:city":"Wilmington",
    "sg:classifiers":[
        {
            "category":"Insurance",
            "subcategory":"Hazard Insurance",
            "type":"Services"
        }
    ],
    "sg:phone":"+1 937 382 1156",
    "sg:postcode":"45177",
    "sg:province":"OH",
    "sg:tags":[
        "carrier",
        "surety"
    ],
    "wof:name":"Midway Affidavit Service Inc",
    "wof:placetype":"venue"
},
  "geometry": {"coordinates":[-83.845099,39.447452],"type":"Point"}
}