{
  "type": "Feature",
  "properties": {
    "iso:country":"US",
    "sg:address":"195 Reed Rd",
    "sg:city":"Springboro",
    "sg:classifiers":[
        {
            "category":"Health Services",
            "subcategory":"Clinic",
            "type":"Services"
        }
    ],
    "sg:phone":"+1 937 886 2915",
    "sg:postcode":"45066",
    "sg:province":"OH",
    "wof:name":"Genesis Health Ventures",
    "wof:placetype":"venue"
},
  "geometry": {"coordinates":[-84.193561,39.575743],"type":"Point"}
}