{
  "type": "Feature",
  "properties": {
    "addr:full": "195 Reed Rd Springboro OH 45066",
    "addr:housenumber": "195",
    "addr:postcode": "45066",
    "addr:street": "Reed Rd",
    "iso:country": "US",
    "sg:address": "195 Reed Rd",
    "sg:city": "Springboro",
    "sg:classifiers": [
      {
        "category": "Health Services",
        "subcategory": "Clinic",
        "type": "Services"
      }
    ],
    "sg:phone": "+1 937 886 2915",
    "sg:postcode": "45066",
    "sg:province": "OH",
    "wof:name": "Genesis Health Ventures",
    "wof:placetype": "venue"
  },
  "geometry": {"coordinates":[-84.193561,39.575743],"type":"Point"}
}
