{
  "type": "Feature",
  "properties": {
    "iso:country":"US",
    "sg:address":"5725 Canal Rd",
    "sg:city":"Cleveland",
    "sg:classifiers":[
        {
            "category":"Shopping",
            "type":"Retail Goods"
        },
        {
            "category":"Retail",
            "subcategory":"Repair Shop",
            "type":"Services"
        }
    ],
    "sg:phone":"+1 216 573 0977",
    "sg:postcode":"44125",
    "sg:province":"OH",
    "sg:tags":[
        "installs",
        "equipment",
        "supply",
        "system",
        "telephone"
    ],
    "wof:name":"Digital Matrix Inc",
    "wof:placetype":"venue"
},
  "geometry": {"coordinates":[-81.62790200000001,41.408919],"type":"Point"}
}