{
  "type": "Feature",
  "properties": {
    "addr:full": "9260 Mentor Ave Mentor OH 44060",
    "addr:housenumber": "9260",
    "addr:postcode": "44060",
    "addr:street": "Mentor Ave",
    "iso:country": "US",
    "sg:address": "9260 Mentor Ave",
    "sg:city": "Mentor",
    "sg:classifiers": [
      {
        "category": "Shopping",
        "subcategory": "Stationery \u0026 Office Supplies",
        "type": "Retail Goods"
      }
    ],
    "sg:phone": "+1 440 205 0830",
    "sg:postcode": "44060",
    "sg:province": "OH",
    "sg:website": "www.staples.com",
    "wof:name": "Staples",
    "wof:placetype": "venue"
  },
  "geometry": {"coordinates":[-81.3108,41.676592],"type":"Point"}
}
