{
  "type": "Feature",
  "properties": {
    "iso:country":"US",
    "sg:address":"1100 N High St",
    "sg:city":"Hillsboro",
    "sg:classifiers":[
        {
            "category":"Shopping",
            "subcategory":"Department Store",
            "type":"Retail Goods"
        }
    ],
    "sg:phone":"+1 937 393 5101",
    "sg:postcode":"45133",
    "sg:province":"OH",
    "sg:website":"www.peebles.com",
    "wof:name":"Peebles",
    "wof:placetype":"venue"
},
  "geometry": {"coordinates":[-83.60860099999999,39.220868],"type":"Point"}
}