{
  "type": "Feature",
  "properties": {
    "addr:full": "26988 Springside Ln Olmsted Falls OH 44138",
    "addr:housenumber": "26988",
    "addr:postcode": "44138",
    "addr:street": "Springside Ln",
    "iso:country": "US",
    "sg:address": "26988 Springside Ln",
    "sg:city": "Olmsted Falls",
    "sg:classifiers": [
      {
        "category": "Professional",
        "type": "Services"
      }
    ],
    "sg:phone": "+1 440 235 4323",
    "sg:postcode": "44138",
    "sg:province": "OH",
    "wof:name": "Theresa Garrity",
    "wof:placetype": "venue"
  },
  "geometry": {"coordinates":[-81.934607,41.359552],"type":"Point"}
}
