{
  "type": "Feature",
  "properties": {
    "iso:country":"US",
    "sg:address":"4900 Reed Rd",
    "sg:city":"Columbus",
    "sg:classifiers":[
        {
            "category":"Transit Center",
            "subcategory":"Freight",
            "type":"Transportation"
        },
        {
            "category":"Freight",
            "type":"Transportation"
        },
        {
            "category":"Local Transit",
            "type":"Transportation"
        }
    ],
    "sg:phone":"+1 614 459 3577",
    "sg:postcode":"43220",
    "sg:province":"OH",
    "sg:tags":[
        "bus",
        "line",
        "public",
        "trucking-motor",
        "trucking"
    ],
    "wof:name":"Dublin Transport",
    "wof:placetype":"venue"
},
  "geometry": {"coordinates":[-83.06680299999999,40.056971],"type":"Point"}
}