{
  "type": "Feature",
  "properties": {
    "addr:full":"1 Belvidere Ave Columbus OH 43223",
    "addr:housenumber":"1",
    "addr:postcode":"43223",
    "addr:street":"Belvidere Ave",
    "iso:country":"US",
    "sg:address":"1 Belvidere Ave",
    "sg:city":"Columbus",
    "sg:classifiers":[
        {
            "category":"Farming",
            "subcategory":"Dairy Farm",
            "type":"Manufacturing & Wholesale Goods"
        }
    ],
    "sg:phone":"+1 614 308 0200",
    "sg:postcode":"43223",
    "sg:province":"OH",
    "wof:name":"Rock Woods & Dave Ward",
    "wof:placetype":"venue"
},
  "geometry": {"coordinates":[-83.055184,39.954685],"type":"Point"}
}