{
  "type": "Feature",
  "properties": {
    "addr:full": "6915 Cloister Rd Toledo OH 43617",
    "addr:housenumber": "6915",
    "addr:postcode": "43617",
    "addr:street": "Cloister Rd",
    "iso:country": "US",
    "sg:address": "6915 Cloister Rd",
    "sg:city": "Toledo",
    "sg:classifiers": [
      {
        "category": "Wholesale",
        "subcategory": "Metals \u0026 Minerals",
        "type": "Manufacturing \u0026 Wholesale Goods"
      }
    ],
    "sg:phone": "+1 419 841 7691",
    "sg:postcode": "43617",
    "sg:province": "OH",
    "sg:tags": [
      "steel",
      "stamping"
    ],
    "wof:name": "M \u0026 A Sales",
    "wof:placetype": "venue"
  },
  "geometry": {"coordinates":[-83.707865,41.660855],"type":"Point"}
}
