{
  "type": "Feature",
  "properties": {
    "iso:country":"US",
    "sg:address":"6915 Cloister Rd",
    "sg:city":"Toledo",
    "sg:classifiers":[
        {
            "category":"Wholesale",
            "subcategory":"Metals & Minerals",
            "type":"Manufacturing & Wholesale Goods"
        }
    ],
    "sg:phone":"+1 419 841 7691",
    "sg:postcode":"43617",
    "sg:province":"OH",
    "sg:tags":[
        "steel",
        "stamping"
    ],
    "wof:name":"M & A Sales",
    "wof:placetype":"venue"
},
  "geometry": {"coordinates":[-83.707865,41.660855],"type":"Point"}
}