{
  "type": "Feature",
  "properties": {
    "iso:country":"US",
    "sg:address":"4520 Frazer Ave NW",
    "sg:city":"Canton",
    "sg:classifiers":[
        {
            "category":"Building & Trades",
            "subcategory":"Construction",
            "type":"Services"
        }
    ],
    "sg:phone":"+1 330 497 4898",
    "sg:postcode":"44709",
    "sg:province":"OH",
    "sg:tags":[
        "home",
        "builder"
    ],
    "wof:name":"Ray P Monat Custom Builders",
    "wof:placetype":"venue"
},
  "geometry": {"coordinates":[-81.37388199999999,40.85003],"type":"Point"}
}