{
  "type": "Feature",
  "properties": {
    "addr:full": "4520 Frazer Ave NW Canton OH 44709",
    "addr:housenumber": "4520",
    "addr:postcode": "44709",
    "addr:street": "Frazer Ave Nw",
    "iso:country": "US",
    "sg:address": "4520 Frazer Ave NW",
    "sg:city": "Canton",
    "sg:classifiers": [
      {
        "category": "Building \u0026 Trades",
        "subcategory": "Construction",
        "type": "Services"
      }
    ],
    "sg:phone": "+1 330 497 4898",
    "sg:postcode": "44709",
    "sg:province": "OH",
    "sg:tags": [
      "home",
      "builder"
    ],
    "wof:name": "Ray P Monat Custom Builders",
    "wof:placetype": "venue"
  },
  "geometry": {"coordinates":[-81.373882,40.85003],"type":"Point"}
}
