{
  "type": "Feature",
  "properties": {
    "iso:country":"US",
    "sg:address":"1516 Cambridge Ave",
    "sg:city":"North Canton",
    "sg:classifiers":[
        {
            "category":"Organizations",
            "subcategory":"Religious Organization",
            "type":"Services"
        }
    ],
    "sg:phone":"+1 330 497 0924",
    "sg:postcode":"44709",
    "sg:province":"OH",
    "sg:tags":[
        "clergy"
    ],
    "wof:name":"Terrence T Taylor",
    "wof:placetype":"venue"
},
  "geometry": {"coordinates":[-81.414621,40.85791],"type":"Point"}
}