{
  "type": "Feature",
  "properties": {
    "addr:full":"1728 Marion-Waldo Rd Marion OH 43302",
    "addr:housenumber":"1728",
    "addr:postcode":"43302",
    "addr:street":"Marion-Waldo Rd",
    "iso:country":"US",
    "sg:address":"1728 Marion-Waldo Rd",
    "sg:city":"Marion",
    "sg:classifiers":[
        {
            "category":"Health Services",
            "subcategory":"Doctor",
            "type":"Services"
        }
    ],
    "sg:phone":"+1 740 725 8300",
    "sg:postcode":"43302",
    "sg:province":"OH",
    "sg:tags":[
        "physician",
        "surgeon"
    ],
    "wof:name":"Marion Area Neurological Cnslt",
    "wof:placetype":"venue"
},
  "geometry": {"coordinates":[-83.116522,40.555944],"type":"Point"}
}