{
  "type": "Feature",
  "properties": {
    "addr:full": "2674 Federated Blvd Columbus OH 43235",
    "addr:postcode": "2674;43235",
    "addr:street": "Federated Blvd",
    "iso:country": "US",
    "sg:address": "2674 Federated Blvd",
    "sg:city": "Columbus",
    "sg:classifiers": [
      {
        "category": "Building \u0026 Trades",
        "subcategory": "Plumbing",
        "type": "Services"
      }
    ],
    "sg:phone": "+1 614 659 0662",
    "sg:postcode": "43235",
    "sg:province": "OH",
    "sg:tags": [
      "product",
      "management",
      "energy",
      "system"
    ],
    "sg:website": "www.deltaenergyllc.com",
    "wof:name": "Delta Energy LLC",
    "wof:placetype": "venue"
  },
  "geometry": {"coordinates":[-83.09032,40.101762],"type":"Point"}
}
