{
  "type": "Feature",
  "properties": {
    "addr:full":"10771 Mayfield Rd Chardon OH 44024",
    "addr:housenumber":"10771",
    "addr:postcode":"44024",
    "addr:street":"Mayfield Rd",
    "iso:country":"US",
    "sg:address":"10771 Mayfield Rd",
    "sg:city":"Chardon",
    "sg:classifiers":[
        {
            "category":"Professional",
            "type":"Services"
        }
    ],
    "sg:phone":"+1 440 285 7154",
    "sg:postcode":"44024",
    "sg:province":"OH",
    "wof:name":"Catholic Services",
    "wof:placetype":"venue"
},
  "geometry": {"coordinates":[-81.258719,41.526613],"type":"Point"}
}