{
  "type": "Feature",
  "properties": {
    "addr:full":"6513 Milan Rd Sandusky OH 44870",
    "addr:housenumber":"6513",
    "addr:postcode":"44870",
    "addr:street":"Milan Rd",
    "iso:country":"US",
    "sg:address":"6513 Milan Rd",
    "sg:city":"Sandusky",
    "sg:classifiers":[
        {
            "category":"Freight",
            "type":"Transportation"
        }
    ],
    "sg:phone":"+1 419 625 6907",
    "sg:postcode":"44870",
    "sg:province":"OH",
    "sg:tags":[
        "delivery"
    ],
    "wof:name":"Greyhound Package Express",
    "wof:placetype":"venue"
},
  "geometry": {"coordinates":[-82.64858099999999,41.388618],"type":"Point"}
}