{
  "type": "Feature",
  "properties": {
    "iso:country":"US",
    "sg:address":"1800 Tiffin Ave",
    "sg:city":"Findlay",
    "sg:classifiers":[
        {
            "category":"Shopping",
            "subcategory":"Department Store",
            "type":"Retail Goods"
        },
        {
            "category":"Shopping",
            "subcategory":"Beauty & Cosmetics",
            "type":"Retail Goods"
        },
        {
            "category":"Home & Garden",
            "subcategory":"Home Furnishings",
            "type":"Retail Goods"
        },
        {
            "category":"Shopping",
            "type":"Retail Goods"
        },
        {
            "category":"Shopping",
            "subcategory":"Catalog Store",
            "type":"Retail Goods"
        },
        {
            "category":"Professional",
            "subcategory":"Art Services",
            "type":"Services"
        },
        {
            "category":"Shopping",
            "subcategory":"Shoes",
            "type":"Retail Goods"
        },
        {
            "category":"Personal",
            "subcategory":"Beauty Salon",
            "type":"Services"
        },
        {
            "category":"Shopping",
            "subcategory":"Jewelry",
            "type":"Retail Goods"
        }
    ],
    "sg:phone":"+1 419 422 9022",
    "sg:postcode":"45840",
    "sg:province":"OH",
    "sg:tags":[
        "draperies",
        "designer",
        "stylist",
        "vertical",
        "supply",
        "braiding",
        "blinds-venetian",
        "jeweler",
        "hair",
        "equipment",
        "window",
        "interior",
        "treatment",
        "housewares",
        "curtain",
        "showroom",
        "decorator",
        "merchandise"
    ],
    "sg:website":"http://www.jcpenney.com",
    "wof:name":"JCPenney Salon",
    "wof:placetype":"venue"
},
  "geometry": {"coordinates":[-83.615993,41.052704],"type":"Point"}
}