{
  "type": "Feature",
  "properties": {
    "addr:full":"106 N Main St Christiansburg OH 45389",
    "addr:housenumber":"106",
    "addr:postcode":"45389",
    "addr:street":"N Main St",
    "iso:country":"US",
    "sg:address":"106 N Main St",
    "sg:city":"Christiansburg",
    "sg:classifiers":[
        {
            "category":"Restaurant",
            "type":"Food & Drink"
        }
    ],
    "sg:phone":"+1 937 857 9031",
    "sg:postcode":"45389",
    "sg:province":"OH",
    "wof:name":"Karen's Pizzaria",
    "wof:placetype":"venue"
},
  "geometry": {"coordinates":[-84.025704,40.056413],"type":"Point"}
}