{
  "type": "Feature",
  "properties": {
    "iso:country":"US",
    "sg:address":"5200 Turney Rd",
    "sg:city":"Cleveland",
    "sg:classifiers":[
        {
            "category":"Personal",
            "subcategory":"Beauty Salon",
            "type":"Services"
        }
    ],
    "sg:phone":"+1 216 663 2988",
    "sg:postcode":"44125",
    "sg:province":"OH",
    "wof:name":"Ginuine Cuts",
    "wof:placetype":"venue"
},
  "geometry": {"coordinates":[-81.608632,41.420405],"type":"Point"}
}