{
  "type": "Feature",
  "properties": {
    "addr:full":"1994 Madison Rd Cincinnati OH 45208",
    "addr:housenumber":"1994",
    "addr:postcode":"45208",
    "addr:street":"Madison Rd",
    "iso:country":"US",
    "sg:address":"1994 Madison Rd",
    "sg:city":"Cincinnati",
    "sg:classifiers":[
        {
            "category":"Professional",
            "type":"Services"
        }
    ],
    "sg:phone":"+1 513 321 7002",
    "sg:postcode":"45208",
    "sg:province":"OH",
    "sg:tags":[
        "arts",
        "artist"
    ],
    "sg:website":"www.butzgaskins.com",
    "wof:name":"Butz Gaskins Inc",
    "wof:placetype":"venue"
},
  "geometry": {"coordinates":[-84.46423900000001,39.131636],"type":"Point"}
}