{
  "type": "Feature",
  "properties": {
    "addr:full": "519 Mound Ct Lebanon OH 45036",
    "addr:housenumber": "519",
    "addr:postcode": "45036",
    "addr:street": "Mound Ct",
    "iso:country": "US",
    "sg:address": "519 Mound Ct",
    "sg:city": "Lebanon",
    "sg:classifiers": [
      {
        "category": "Building \u0026 Trades",
        "subcategory": "Landscaping Services",
        "type": "Services"
      }
    ],
    "sg:phone": "+1 513 398 5758",
    "sg:postcode": "45036",
    "sg:province": "OH",
    "sg:tags": [
      "landscape"
    ],
    "wof:name": "Smith Landscaping \u0026 Garden Ctr",
    "wof:placetype": "venue"
  },
  "geometry": {"coordinates":[-84.198523,39.43437],"type":"Point"}
}
