{
  "type": "Feature",
  "properties": {
    "addr:full":"6306 W Bancroft St Toledo OH 43615",
    "addr:housenumber":"6306",
    "addr:postcode":"43615",
    "addr:street":"W Bancroft St",
    "iso:country":"US",
    "sg:address":"6306 W Bancroft St",
    "sg:city":"Toledo",
    "sg:classifiers":[
        {
            "category":"Freight",
            "type":"Transportation"
        }
    ],
    "sg:phone":"+1 419 478 1638",
    "sg:postcode":"43615",
    "sg:province":"OH",
    "sg:tags":[
        "delivery"
    ],
    "wof:name":"Fox Relocation Svc",
    "wof:placetype":"venue"
},
  "geometry": {"coordinates":[-83.693051,41.661123],"type":"Point"}
}