{
  "type": "Feature",
  "properties": {
    "addr:full": "20814 Watson Rd Maple Heights OH 44137",
    "addr:housenumber": "20814",
    "addr:postcode": "44137",
    "addr:street": "Watson Rd",
    "iso:country": "US",
    "sg:address": "20814 Watson Rd",
    "sg:city": "Maple Heights",
    "sg:classifiers": [
      {
        "category": "Freight",
        "type": "Transportation"
      }
    ],
    "sg:phone": "+1 216 662 3072",
    "sg:postcode": "44137",
    "sg:province": "OH",
    "sg:tags": [
      "operator",
      "local",
      "trucking"
    ],
    "wof:name": "Jl Wiley Transport Inc",
    "wof:placetype": "venue"
  },
  "geometry": {"coordinates":[-81.531977,41.422595],"type":"Point"}
}
