{
  "type": "Feature",
  "properties": {
    "addr:full": "2105 South Ave Youngstown OH 44502",
    "addr:housenumber": "2105",
    "addr:postcode": "44502",
    "addr:street": "South Ave",
    "iso:country": "US",
    "sg:address": "2105 South Ave",
    "sg:city": "Youngstown",
    "sg:classifiers": [
      {
        "category": "Bars \u0026 Pubs",
        "type": "Food \u0026 Drink"
      }
    ],
    "sg:phone": "+1 330 746 5511",
    "sg:postcode": "44502",
    "sg:province": "OH",
    "wof:name": "Mighty Duck's Bar \u0026 Grill",
    "wof:placetype": "venue"
  },
  "geometry": {"coordinates":[-80.646175,41.078563],"type":"Point"}
}
