{
  "type": "Feature",
  "properties": {
    "addr:full": "2710 Jackson Rd Zanesville OH 43701",
    "addr:housenumber": "2710",
    "addr:postcode": "43701",
    "addr:street": "Jackson Rd",
    "iso:country": "US",
    "sg:address": "2710 Jackson Rd",
    "sg:city": "Zanesville",
    "sg:classifiers": [
      {
        "category": "Sports \u0026 Exercise",
        "subcategory": "Golf",
        "type": "Entertainment"
      }
    ],
    "sg:phone": "+1 740 452 1860",
    "sg:postcode": "43701",
    "sg:province": "OH",
    "sg:tags": [
      "course"
    ],
    "wof:name": "Jaycee Public Golf Course",
    "wof:placetype": "venue"
  },
  "geometry": {"coordinates":[-81.923299,39.989212],"type":"Point"}
}
