{
  "type": "Feature",
  "properties": {
    "iso:country":"US",
    "sg:address":"8888 Bliss Rd",
    "sg:city":"Delphos",
    "sg:classifiers":[
        {
            "category":"Farming",
            "subcategory":"Livestock Farm",
            "type":"Manufacturing & Wholesale Goods"
        }
    ],
    "sg:phone":"+1 419 339 1788",
    "sg:postcode":"45833",
    "sg:province":"OH",
    "sg:tags":[
        "beef",
        "feedlot",
        "cattle"
    ],
    "wof:name":"Thomas G Hesseling",
    "wof:placetype":"venue"
},
  "geometry": {"coordinates":[-84.27382799999999,40.798665],"type":"Point"}
}