{
  "type": "Feature",
  "properties": {
    "addr:full": "1504 Linn St Cincinnati OH 45214",
    "addr:housenumber": "1504",
    "addr:postcode": "45214",
    "addr:street": "Linn St",
    "iso:country": "US",
    "sg:address": "1504 Linn St",
    "sg:city": "Cincinnati",
    "sg:classifiers": [
      {
        "category": "Professional",
        "subcategory": "Accounting \u0026 Tax Preparation",
        "type": "Services"
      }
    ],
    "sg:phone": "+1 513 729 1040",
    "sg:postcode": "45214",
    "sg:province": "OH",
    "sg:tags": [
      "return",
      "filing"
    ],
    "wof:name": "Instant Refund Tax Svc",
    "wof:placetype": "venue"
  },
  "geometry": {"coordinates":[-84.527438,39.112336],"type":"Point"}
}
