{
  "type": "Feature",
  "properties": {
    "iso:country":"US",
    "sg:address":"1504 Linn St",
    "sg:city":"Cincinnati",
    "sg:classifiers":[
        {
            "category":"Professional",
            "subcategory":"Accounting & Tax Preparation",
            "type":"Services"
        }
    ],
    "sg:phone":"+1 513 729 1040",
    "sg:postcode":"45214",
    "sg:province":"OH",
    "sg:tags":[
        "return",
        "filing"
    ],
    "wof:name":"Instant Refund Tax Svc",
    "wof:placetype":"venue"
},
  "geometry": {"coordinates":[-84.527438,39.112336],"type":"Point"}
}