{
  "type": "Feature",
  "properties": {
    "addr:full": "2714 Springboro Rd Dayton OH 45439",
    "addr:housenumber": "2714",
    "addr:postcode": "45439",
    "addr:street": "Springboro Rd",
    "iso:country": "US",
    "sg:address": "2714 Springboro Rd",
    "sg:city": "Dayton",
    "sg:classifiers": [
      {
        "category": "Retail",
        "subcategory": "Veterinary Services",
        "type": "Services"
      }
    ],
    "sg:phone": "+1 937 293 2714",
    "sg:postcode": "45439",
    "sg:province": "OH",
    "sg:tags": [
      "veterinarian"
    ],
    "wof:name": "Dayton Emergency Veterinary",
    "wof:placetype": "venue"
  },
  "geometry": {"coordinates":[-84.215829,39.714379],"type":"Point"}
}
