{
  "type": "Feature",
  "properties": {
    "addr:full": "6607 Simmons Church Rd Centerburg OH 43011",
    "addr:housenumber": "6607",
    "addr:postcode": "43011",
    "addr:street": "Simmons Church Rd",
    "iso:country": "US",
    "sg:address": "6607 Simmons Church Rd",
    "sg:city": "Centerburg",
    "sg:classifiers": [
      {
        "category": "Farming",
        "subcategory": "Dairy Farm",
        "type": "Manufacturing \u0026 Wholesale Goods"
      }
    ],
    "sg:phone": "+1 740 625 5739",
    "sg:postcode": "43011",
    "sg:province": "OH",
    "sg:tags": [
      "farmer"
    ],
    "wof:name": "William Mark Larimore",
    "wof:placetype": "venue"
  },
  "geometry": {"coordinates":[-82.625366,40.336766],"type":"Point"}
}
