{
  "type": "Feature",
  "properties": {
    "iso:country":"US",
    "sg:address":"9499 Hoose Rd",
    "sg:city":"Mentor",
    "sg:classifiers":[
        {
            "category":"Real Estate",
            "subcategory":"Real Estate Agent",
            "type":"Services"
        }
    ],
    "sg:phone":"+1 440 255 5252",
    "sg:postcode":"44060",
    "sg:province":"OH",
    "sg:tags":[
        "inspection"
    ],
    "sg:website":"www.weinspectforyou.com",
    "wof:name":"Camelot Home Inspection Inc",
    "wof:placetype":"venue"
},
  "geometry": {"coordinates":[-81.299183,41.65443],"type":"Point"}
}