{
  "type": "Feature",
  "properties": {
    "addr:full":"44829 White Rd Lisbon OH 44432",
    "addr:housenumber":"44829",
    "addr:postcode":"44432",
    "addr:street":"White Rd",
    "iso:country":"US",
    "sg:address":"44829 White Rd",
    "sg:city":"Lisbon",
    "sg:classifiers":[
        {
            "category":"Home & Garden",
            "subcategory":"Garden Supply",
            "type":"Retail Goods"
        }
    ],
    "sg:phone":"+1 330 386 7842",
    "sg:postcode":"44432",
    "sg:province":"OH",
    "sg:tags":[
        "landscaping"
    ],
    "wof:name":"Sticks & Stones",
    "wof:placetype":"venue"
},
  "geometry": {"coordinates":[-80.660551,40.691379],"type":"Point"}
}