{
  "type": "Feature",
  "properties": {
    "addr:full": "1810 W 47th St Cleveland OH 44102",
    "addr:housenumber": "1810",
    "addr:postcode": "44102",
    "addr:street": "W 47Th St",
    "iso:country": "US",
    "sg:address": "1810 W 47th St",
    "sg:city": "Cleveland",
    "sg:classifiers": [
      {
        "category": "Manufacturing",
        "subcategory": "Chemicals \u0026 Compounds",
        "type": "Manufacturing \u0026 Wholesale Goods"
      }
    ],
    "sg:phone": "+1 216 651 5803",
    "sg:postcode": "44102",
    "sg:province": "OH",
    "sg:tags": [
      "preparation",
      "toilet",
      "mfg"
    ],
    "wof:name": "House of Delara Fragrances",
    "wof:placetype": "venue"
  },
  "geometry": {"coordinates":[-81.718974,41.483719],"type":"Point"}
}
