{
  "type": "Feature",
  "properties": {
    "iso:country":"US",
    "sg:address":"1810 W 47th St",
    "sg:city":"Cleveland",
    "sg:classifiers":[
        {
            "category":"Manufacturing",
            "subcategory":"Chemicals & Compounds",
            "type":"Manufacturing & Wholesale Goods"
        }
    ],
    "sg:phone":"+1 216 651 5803",
    "sg:postcode":"44102",
    "sg:province":"OH",
    "sg:tags":[
        "preparation",
        "toilet",
        "mfg"
    ],
    "wof:name":"House of Delara Fragrances",
    "wof:placetype":"venue"
},
  "geometry": {"coordinates":[-81.718974,41.483719],"type":"Point"}
}