{
  "type": "Feature",
  "properties": {
    "iso:country":"US",
    "sg:address":"541 S 9th St",
    "sg:city":"Hamilton",
    "sg:classifiers":[
        {
            "category":"Education",
            "subcategory":"School",
            "type":"Public Place"
        }
    ],
    "sg:phone":"+1 513 887 5020",
    "sg:postcode":"45011",
    "sg:province":"OH",
    "wof:name":"Hamilton Adult Basic Education",
    "wof:placetype":"venue"
},
  "geometry": {"coordinates":[-84.554171,39.392672],"type":"Point"}
}