{
  "type": "Feature",
  "properties": {
    "addr:full": "10242 Crosby Rd Harrison OH 45030",
    "addr:housenumber": "10242",
    "addr:postcode": "45030",
    "addr:street": "Crosby Rd",
    "iso:country": "US",
    "sg:address": "10242 Crosby Rd",
    "sg:city": "Harrison",
    "sg:classifiers": [
      {
        "category": "Home \u0026 Garden",
        "subcategory": "Building Materials",
        "type": "Retail Goods"
      },
      {
        "category": "Manufacturing",
        "subcategory": "Glass \u0026 Minerals",
        "type": "Manufacturing \u0026 Wholesale Goods"
      }
    ],
    "sg:phone": "+1 513 738 3222",
    "sg:postcode": "45030",
    "sg:province": "OH",
    "sg:tags": [
      "product",
      "window",
      "screen",
      "mfg"
    ],
    "wof:name": "Jones Glass \u0026 Screen Service",
    "wof:placetype": "venue"
  },
  "geometry": {"coordinates":[-84.711105,39.26514],"type":"Point"}
}
