{
  "type": "Feature",
  "properties": {
    "iso:country":"US",
    "sg:address":"10242 Crosby Rd",
    "sg:city":"Harrison",
    "sg:classifiers":[
        {
            "category":"Home & Garden",
            "subcategory":"Building Materials",
            "type":"Retail Goods"
        },
        {
            "category":"Manufacturing",
            "subcategory":"Glass & Minerals",
            "type":"Manufacturing & Wholesale Goods"
        }
    ],
    "sg:phone":"+1 513 738 3222",
    "sg:postcode":"45030",
    "sg:province":"OH",
    "sg:tags":[
        "product",
        "window",
        "screen",
        "mfg"
    ],
    "wof:name":"Jones Glass & Screen Service",
    "wof:placetype":"venue"
},
  "geometry": {"coordinates":[-84.711105,39.26514],"type":"Point"}
}