{
  "type": "Feature",
  "properties": {
    "addr:full": "11122 Allenhurst Blvd W Cincinnati OH 45241",
    "addr:housenumber": "11122",
    "addr:postcode": "45241",
    "addr:street": "Allenhurst Blvd W",
    "iso:country": "US",
    "sg:address": "11122 Allenhurst Blvd W",
    "sg:city": "Cincinnati",
    "sg:classifiers": [
      {
        "category": "Organizations",
        "subcategory": "Professional Association",
        "type": "Services"
      }
    ],
    "sg:phone": "+1 513 563 1196",
    "sg:postcode": "45241",
    "sg:province": "OH",
    "wof:name": "Waterford Homeowners Assn",
    "wof:placetype": "venue"
  },
  "geometry": {"coordinates":[-84.392217,39.271116],"type":"Point"}
}
