{
  "type": "Feature",
  "properties": {
    "addr:full":"501 Newman St Mansfield OH 44902",
    "addr:housenumber":"501",
    "addr:postcode":"44902",
    "addr:street":"Newman St",
    "iso:country":"US",
    "sg:address":"501 Newman St",
    "sg:city":"Mansfield",
    "sg:classifiers":[
        {
            "category":"Manufacturing",
            "subcategory":"Metals",
            "type":"Manufacturing & Wholesale Goods"
        }
    ],
    "sg:phone":"+1 419 747 4161",
    "sg:postcode":"44902",
    "sg:province":"OH",
    "sg:tags":[
        "automobile",
        "frame",
        "mfg",
        "seat"
    ],
    "sg:website":"www.jayindinc.com",
    "wof:name":"SARCA Mfg",
    "wof:placetype":"venue"
},
  "geometry": {"coordinates":[-82.508122,40.772901],"type":"Point"}
}