{
  "type": "Feature",
  "properties": {
    "iso:country":"US",
    "sg:address":"18975 Villaview Rd",
    "sg:city":"Cleveland",
    "sg:classifiers":[
        {
            "category":"Insurance",
            "subcategory":"Insurance Agent",
            "type":"Services"
        }
    ],
    "sg:phone":"+1 216 696 5589",
    "sg:postcode":"44119",
    "sg:province":"OH",
    "wof:name":"Urbancic Corporation",
    "wof:placetype":"venue"
},
  "geometry": {"coordinates":[-81.547383,41.579853],"type":"Point"}
}