{
  "type": "Feature",
  "properties": {
    "addr:full": "26300 Cedar Rd Cleveland OH 44122",
    "addr:housenumber": "26300",
    "addr:postcode": "44122",
    "addr:street": "Cedar Rd",
    "iso:country": "US",
    "sg:address": "26300 Cedar Rd",
    "sg:city": "Cleveland",
    "sg:classifiers": [
      {
        "category": "Shopping",
        "subcategory": "Luggage \u0026 Leather Goods",
        "type": "Retail Goods"
      },
      {
        "category": "Manufacturing",
        "subcategory": "Leather Goods",
        "type": "Manufacturing \u0026 Wholesale Goods"
      }
    ],
    "sg:phone": "+1 216 464 6288",
    "sg:postcode": "44122",
    "sg:province": "OH",
    "sg:tags": [
      "sample",
      "case"
    ],
    "wof:name": "Cleveland Trunk Co",
    "wof:placetype": "venue"
  },
  "geometry": {"coordinates":[-81.493205,41.501129],"type":"Point"}
}
