{
  "type": "Feature",
  "properties": {
    "iso:country":"US",
    "sg:address":"1462 State Rte 635",
    "sg:city":"Tiffin",
    "sg:classifiers":[
        {
            "category":"Building & Trades",
            "subcategory":"Landscaping Services",
            "type":"Services"
        }
    ],
    "sg:phone":"+1 419 937 2215",
    "sg:postcode":"44883",
    "sg:province":"OH",
    "wof:name":"Fast Eddies Hauling",
    "wof:placetype":"venue"
},
  "geometry": {"coordinates":[-83.285122,41.151269],"type":"Point"}
}