{
  "type": "Feature",
  "properties": {
    "iso:country":"US",
    "sg:address":"3401 Enterprise Pkwy",
    "sg:city":"Cleveland",
    "sg:classifiers":[
        {
            "category":"Banks & Credit Unions",
            "subcategory":"Bank",
            "type":"Services"
        }
    ],
    "sg:phone":"+1 216 766 5795",
    "sg:postcode":"44122",
    "sg:province":"OH",
    "sg:tags":[
        "loan",
        "real estate"
    ],
    "wof:name":"Birmingham Bancorp Mortgage",
    "wof:placetype":"venue"
},
  "geometry": {"coordinates":[-81.494602,41.466431],"type":"Point"}
}