{
  "type": "Feature",
  "properties": {
    "addr:full":"50 Trl End Aurora OH 44202",
    "addr:postcode":"44202",
    "addr:street":"50 Trl",
    "iso:country":"US",
    "sg:address":"50 Trl End",
    "sg:city":"Aurora",
    "sg:classifiers":[
        {
            "category":"Recreation",
            "type":"Entertainment"
        },
        {
            "category":"Shopping",
            "subcategory":"Bicycles & Sporting Goods",
            "type":"Retail Goods"
        }
    ],
    "sg:phone":"+1 330 562 8188",
    "sg:postcode":"44202",
    "sg:province":"OH",
    "sg:tags":[
        "club",
        "country",
        "membership"
    ],
    "sg:website":"www.auroracountryclub.org",
    "wof:name":"Aurora Golf & Country Club",
    "wof:placetype":"venue"
},
  "geometry": {"coordinates":[-81.32720999999999,41.311109],"type":"Point"}
}