{
  "type": "Feature",
  "properties": {
    "addr:full":"3001 Bethel Rd Columbus OH 43220",
    "addr:housenumber":"3001",
    "addr:postcode":"43220",
    "addr:street":"Bethel Rd",
    "iso:country":"US",
    "sg:address":"3001 Bethel Rd",
    "sg:city":"Columbus",
    "sg:classifiers":[
        {
            "category":"Professional",
            "subcategory":"Management & Consulting",
            "type":"Services"
        }
    ],
    "sg:phone":"+1 614 326 5282",
    "sg:postcode":"43220",
    "sg:province":"OH",
    "sg:tags":[
        "business"
    ],
    "wof:name":"Planet Telecom",
    "wof:placetype":"venue"
},
  "geometry": {"coordinates":[-83.097855,40.065039],"type":"Point"}
}