{
  "type": "Feature",
  "properties": {
    "addr:full": "3028 N High St Columbus OH 43202",
    "addr:housenumber": "3028",
    "addr:postcode": "43202",
    "addr:street": "N High St",
    "iso:country": "US",
    "sg:address": "3028 N High St",
    "sg:city": "Columbus",
    "sg:classifiers": [
      {
        "category": "Bars \u0026 Pubs",
        "type": "Food \u0026 Drink"
      }
    ],
    "sg:phone": "+1 614 267 5515",
    "sg:postcode": "43202",
    "sg:province": "OH",
    "wof:name": "Brew-Stirs Clintonville Tavern",
    "wof:placetype": "venue"
  },
  "geometry": {"coordinates":[-83.013667,40.023481],"type":"Point"}
}
