{
  "type": "Feature",
  "properties": {
    "iso:country":"US",
    "sg:address":"335 N Superior St",
    "sg:city":"Toledo",
    "sg:classifiers":[
        {
            "category":"Shopping",
            "subcategory":"Musical Instruments",
            "type":"Retail Goods"
        }
    ],
    "sg:phone":"+1 419 244 7551",
    "sg:postcode":"43604",
    "sg:province":"OH",
    "wof:name":"Guitar Station",
    "wof:placetype":"venue"
},
  "geometry": {"coordinates":[-83.535076,41.652678],"type":"Point"}
}