{
  "type": "Feature",
  "properties": {
    "addr:full": "8550 Bridlehurst Trl Willoughby OH 44094",
    "addr:housenumber": "8550",
    "addr:postcode": "44094",
    "addr:street": "Bridlehurst Trl",
    "iso:country": "US",
    "sg:address": "8550 Bridlehurst Trl",
    "sg:city": "Willoughby",
    "sg:classifiers": [
      {
        "category": "Freight",
        "type": "Transportation"
      }
    ],
    "sg:phone": "+1 440 256 1615",
    "sg:postcode": "44094",
    "sg:province": "OH",
    "sg:tags": [
      "operator",
      "local",
      "trucking"
    ],
    "wof:name": "Bestway Trucking",
    "wof:placetype": "venue"
  },
  "geometry": {"coordinates":[-81.339332,41.572007],"type":"Point"}
}
