{
  "type": "Feature",
  "properties": {
    "addr:full": "6740 Lincoln Way Wooster OH 44691",
    "addr:housenumber": "6740",
    "addr:postcode": "44691",
    "addr:street": "Lincoln Way",
    "iso:country": "US",
    "sg:address": "6740 Lincoln Way",
    "sg:city": "Wooster",
    "sg:classifiers": [
      {
        "category": "Manufacturing",
        "subcategory": "Metals",
        "type": "Manufacturing \u0026 Wholesale Goods"
      }
    ],
    "sg:phone": "+1 330 262 1881",
    "sg:postcode": "44691",
    "sg:province": "OH",
    "sg:tags": [
      "steel",
      "pipe",
      "finishing"
    ],
    "wof:name": "Northeast Tubular Service Inc",
    "wof:placetype": "venue"
  },
  "geometry": {"coordinates":[-81.844926,40.797615],"type":"Point"}
}
