{
  "type": "Feature",
  "properties": {
    "addr:full": "2467 Lenox-New Lyme Rd Jefferson OH 44047",
    "addr:housenumber": "2467",
    "addr:postcode": "44047",
    "addr:street": "Lenox-New Lyme Rd",
    "iso:country": "US",
    "sg:address": "2467 Lenox-New Lyme Rd",
    "sg:city": "Jefferson",
    "sg:classifiers": [
      {
        "category": "Building \u0026 Trades",
        "subcategory": "Plumbing",
        "type": "Services"
      }
    ],
    "sg:phone": "+1 440 576 0305",
    "sg:postcode": "44047",
    "sg:province": "OH",
    "sg:tags": [
      "plumbing",
      "contractor"
    ],
    "wof:name": "Brining Plumbing \u0026 Pump Svc",
    "wof:placetype": "venue"
  },
  "geometry": {"coordinates":[-80.761551,41.684055],"type":"Point"}
}
