{
  "type": "Feature",
  "properties": {
    "addr:full": "421 Anderson Ferry Rd Cincinnati OH 45238",
    "addr:housenumber": "421",
    "addr:postcode": "45238",
    "addr:street": "Anderson Ferry Rd",
    "iso:country": "US",
    "sg:address": "421 Anderson Ferry Rd",
    "sg:city": "Cincinnati",
    "sg:classifiers": [
      {
        "category": "Insurance",
        "subcategory": "Insurance Agent",
        "type": "Services"
      }
    ],
    "sg:phone": "+1 513 244 9754",
    "sg:postcode": "45238",
    "sg:province": "OH",
    "wof:name": "United Insurance Systems",
    "wof:placetype": "venue"
  },
  "geometry": {"coordinates":[-84.618115,39.095369],"type":"Point"}
}
