{
  "type": "Feature",
  "properties": {
    "addr:full": "2153 Fulton Rd Cleveland OH 44113",
    "addr:housenumber": "2153",
    "addr:postcode": "44113",
    "addr:street": "Fulton Rd",
    "iso:country": "US",
    "sg:address": "2153 Fulton Rd",
    "sg:city": "Cleveland",
    "sg:classifiers": [
      {
        "category": "Manufacturing",
        "subcategory": "Apparel",
        "type": "Manufacturing \u0026 Wholesale Goods"
      }
    ],
    "sg:phone": "+1 216 651 4056",
    "sg:postcode": "44113",
    "sg:province": "OH",
    "sg:tags": [
      "textile",
      "product",
      "fabricated",
      "mfg"
    ],
    "wof:name": "Morgan Mc Kinney Sewing",
    "wof:placetype": "venue"
  },
  "geometry": {"coordinates":[-81.709404,41.478729],"type":"Point"}
}
