{
  "type": "Feature",
  "properties": {
    "iso:country":"US",
    "sg:address":"2153 Fulton Rd",
    "sg:city":"Cleveland",
    "sg:classifiers":[
        {
            "category":"Manufacturing",
            "subcategory":"Apparel",
            "type":"Manufacturing & Wholesale Goods"
        }
    ],
    "sg:phone":"+1 216 651 4056",
    "sg:postcode":"44113",
    "sg:province":"OH",
    "sg:tags":[
        "textile",
        "product",
        "fabricated",
        "mfg"
    ],
    "wof:name":"Morgan Mc Kinney Sewing",
    "wof:placetype":"venue"
},
  "geometry": {"coordinates":[-81.70940400000001,41.478729],"type":"Point"}
}