{
  "type": "Feature",
  "properties": {
    "addr:full": "13950 Stoney Creek Dr Cleveland OH 44133",
    "addr:housenumber": "13950",
    "addr:postcode": "44133",
    "addr:street": "Stoney Creek Dr",
    "iso:country": "US",
    "sg:address": "13950 Stoney Creek Dr",
    "sg:city": "Cleveland",
    "sg:classifiers": [
      {
        "category": "Shopping",
        "subcategory": "Computers \u0026 Home Electronics",
        "type": "Retail Goods"
      }
    ],
    "sg:phone": "+1 440 582 2667",
    "sg:postcode": "44133",
    "sg:province": "OH",
    "sg:tags": [
      "publishing"
    ],
    "wof:name": "Genetech Office Systems",
    "wof:placetype": "venue"
  },
  "geometry": {"coordinates":[-81.710045,41.316425],"type":"Point"}
}
