{
  "type": "Feature",
  "properties": {
    "iso:country":"US",
    "sg:address":"1817 S Jefferson Rd",
    "sg:city":"Wooster",
    "sg:classifiers":[
        {
            "category":"Freight",
            "type":"Transportation"
        }
    ],
    "sg:phone":"+1 330 264 4733",
    "sg:postcode":"44691",
    "sg:province":"OH",
    "sg:tags":[
        "operator",
        "local",
        "trucking"
    ],
    "wof:name":"Speicher Trucking",
    "wof:placetype":"venue"
},
  "geometry": {"coordinates":[-82.023111,40.782301],"type":"Point"}
}