{
  "type": "Feature",
  "properties": {
    "addr:full": "2758 Kensington Pl W Columbus OH 43202",
    "addr:housenumber": "2758",
    "addr:postcode": "43202",
    "addr:street": "Kensington Pl W",
    "iso:country": "US",
    "sg:address": "2758 Kensington Pl W",
    "sg:city": "Columbus",
    "sg:classifiers": [
      {
        "category": "Communications",
        "subcategory": "Film \u0026 Video Production",
        "type": "Services"
      }
    ],
    "sg:phone": "+1 614 784 0924",
    "sg:postcode": "43202",
    "sg:province": "OH",
    "sg:tags": [
      "taping"
    ],
    "wof:name": "Liquid Digital Video",
    "wof:placetype": "venue"
  },
  "geometry": {"coordinates":[-83.000687,40.02],"type":"Point"}
}
