{
  "type": "Feature",
  "properties": {
    "addr:full": "2211 Portman Ave Cleveland OH 44109",
    "addr:housenumber": "2211",
    "addr:postcode": "44109",
    "addr:street": "Portman Ave",
    "iso:country": "US",
    "sg:address": "2211 Portman Ave",
    "sg:city": "Cleveland",
    "sg:classifiers": [
      {
        "category": "Building \u0026 Trades",
        "subcategory": "Construction",
        "type": "Services"
      }
    ],
    "sg:phone": "+1 216 661 9710",
    "sg:postcode": "44109",
    "sg:province": "OH",
    "sg:tags": [
      "contractor"
    ],
    "wof:name": "Craigar Masonry",
    "wof:placetype": "venue"
  },
  "geometry": {"coordinates":[-81.70032,41.427362],"type":"Point"}
}
