{
  "type": "Feature",
  "properties": {
    "addr:full": "1068 Linden Ave Zanesville OH 43701",
    "addr:housenumber": "1068",
    "addr:postcode": "43701",
    "addr:street": "Linden Ave",
    "iso:country": "US",
    "sg:address": "1068 Linden Ave",
    "sg:city": "Zanesville",
    "sg:classifiers": [
      {
        "category": "Personal",
        "subcategory": "Beauty Salon",
        "type": "Services"
      }
    ],
    "sg:phone": "+1 740 454 0515",
    "sg:postcode": "43701",
    "sg:province": "OH",
    "wof:name": "Pat's Shear Design",
    "wof:placetype": "venue"
  },
  "geometry": {"coordinates":[-82.00763,39.950908],"type":"Point"}
}
