{
  "type": "Feature",
  "properties": {
    "addr:full":"11477 Co Hwy 58 De Graff OH 43318",
    "addr:housenumber":"11477",
    "addr:postcode":"43318",
    "addr:street":"Co Hwy 58 De",
    "iso:country":"US",
    "sg:address":"11477 Co Hwy 58",
    "sg:city":"De Graff",
    "sg:classifiers":[
        {
            "category":"Government",
            "subcategory":"Office",
            "type":"Public Place"
        }
    ],
    "sg:phone":"+1 937 585 6161",
    "sg:postcode":"43318",
    "sg:province":"OH",
    "sg:tags":[
        "executive"
    ],
    "wof:name":"Bloomfield Township",
    "wof:placetype":"venue"
},
  "geometry": {"coordinates":[-83.949642,40.376629],"type":"Point"}
}