{
  "type": "Feature",
  "properties": {
    "addr:full":"2650 E 112th St Cleveland OH 44104",
    "addr:housenumber":"2650",
    "addr:postcode":"44104",
    "addr:street":"E 112Th St",
    "iso:country":"US",
    "sg:address":"2650 E 112th St",
    "sg:city":"Cleveland",
    "sg:classifiers":[
        {
            "category":"Building & Trades",
            "subcategory":"Landscaping Services",
            "type":"Services"
        }
    ],
    "sg:phone":"+1 216 791 5529",
    "sg:postcode":"44104",
    "sg:province":"OH",
    "wof:name":"Pleasure Scapes of Ohio",
    "wof:placetype":"venue"
},
  "geometry": {"coordinates":[-81.607029,41.488035],"type":"Point"}
}