{
  "type": "Feature",
  "properties": {
    "addr:full": "2966 E 111th St Cleveland OH 44104",
    "addr:housenumber": "2966",
    "addr:postcode": "44104",
    "addr:street": "E 111Th St",
    "iso:country": "US",
    "sg:address": "2966 E 111th St",
    "sg:city": "Cleveland",
    "sg:classifiers": [
      {
        "category": "Bars \u0026 Pubs",
        "type": "Food \u0026 Drink"
      }
    ],
    "sg:phone": "+1 216 229 3703",
    "sg:postcode": "44104",
    "sg:province": "OH",
    "sg:tags": [
      "lounge"
    ],
    "wof:name": "Gold Spot Cocktail Lounge",
    "wof:placetype": "venue"
  },
  "geometry": {"coordinates":[-81.608551,41.479622],"type":"Point"}
}
