{
  "type": "Feature",
  "properties": {
    "iso:country":"US",
    "sg:address":"2966 E 111th St",
    "sg:city":"Cleveland",
    "sg:classifiers":[
        {
            "category":"Bars & Pubs",
            "type":"Food & Drink"
        }
    ],
    "sg:phone":"+1 216 229 3703",
    "sg:postcode":"44104",
    "sg:province":"OH",
    "sg:tags":[
        "lounge"
    ],
    "wof:name":"Gold Spot Cocktail Lounge",
    "wof:placetype":"venue"
},
  "geometry": {"coordinates":[-81.60855100000001,41.479622],"type":"Point"}
}