{
  "type": "Feature",
  "properties": {
    "addr:full": "8455 County Home Rd Lisbon OH 44432",
    "addr:housenumber": "8455",
    "addr:postcode": "44432",
    "addr:street": "County Home Rd",
    "iso:country": "US",
    "sg:address": "8455 County Home Rd",
    "sg:city": "Lisbon",
    "sg:classifiers": [
      {
        "category": "Retail",
        "subcategory": "Animal Services",
        "type": "Services"
      }
    ],
    "sg:phone": "+1 330 424 5458",
    "sg:postcode": "44432",
    "sg:province": "OH",
    "wof:name": "Dog Pound",
    "wof:placetype": "venue"
  },
  "geometry": {"coordinates":[-80.828703,40.77847],"type":"Point"}
}
