{
  "type": "Feature",
  "properties": {
    "iso:country":"US",
    "sg:address":"221 N Cedar St",
    "sg:city":"Newark",
    "sg:classifiers":[
        {
            "category":"Restaurant",
            "type":"Food & Drink"
        }
    ],
    "sg:phone":"+1 740 345 0544",
    "sg:postcode":"43055",
    "sg:province":"OH",
    "wof:name":"Crenos Pizza",
    "wof:placetype":"venue"
},
  "geometry": {"coordinates":[-82.385963,40.06415],"type":"Point"}
}