{
  "type": "Feature",
  "properties": {
    "addr:full":"500 S Main St Mt Vernon OH 43050",
    "addr:housenumber":"500",
    "addr:postcode":"43050",
    "addr:street":"S Main St",
    "iso:country":"US",
    "sg:address":"500 S Main St",
    "sg:city":"Mt Vernon",
    "sg:classifiers":[
        {
            "category":"Restaurant",
            "type":"Food & Drink"
        }
    ],
    "sg:phone":"+1 740 397 7827",
    "sg:postcode":"43050",
    "sg:province":"OH",
    "wof:name":"Submakers",
    "wof:placetype":"venue"
},
  "geometry": {"coordinates":[-82.485823,40.388521],"type":"Point"}
}