{
  "type": "Feature",
  "properties": {
    "addr:full": "4640 Turney Rd Cleveland OH 44125",
    "addr:housenumber": "4640",
    "addr:postcode": "44125",
    "addr:street": "Turney Rd",
    "iso:country": "US",
    "sg:address": "4640 Turney Rd",
    "sg:city": "Cleveland",
    "sg:classifiers": [
      {
        "category": "Retail",
        "subcategory": "Funeral Services",
        "type": "Services"
      }
    ],
    "sg:phone": "+1 216 641 6321",
    "sg:postcode": "44125",
    "sg:province": "OH",
    "sg:tags": [
      "director"
    ],
    "wof:name": "Rybicki \u0026 Son Funeral Homes",
    "wof:placetype": "venue"
  },
  "geometry": {"coordinates":[-81.61796,41.432959],"type":"Point"}
}
