{
  "type": "Feature",
  "properties": {
    "addr:full": "808 Cody Ct NW Canton OH 44703",
    "addr:housenumber": "808",
    "addr:postcode": "44703",
    "addr:street": "Cody Ct Nw",
    "iso:country": "US",
    "sg:address": "808 Cody Ct NW",
    "sg:city": "Canton",
    "sg:classifiers": [
      {
        "category": "Professional",
        "type": "Services"
      }
    ],
    "sg:phone": "+1 330 452 2543",
    "sg:postcode": "44703",
    "sg:province": "OH",
    "wof:name": "David R \u0026 Rose L Harmon",
    "wof:placetype": "venue"
  },
  "geometry": {"coordinates":[-81.38829,40.805526],"type":"Point"}
}
