{
  "type": "Feature",
  "properties": {
    "iso:country":"US",
    "sg:address":"3418 S Arlington Rd",
    "sg:city":"Akron",
    "sg:classifiers":[
        {
            "category":"Organizations",
            "subcategory":"Religious Organization",
            "type":"Services"
        }
    ],
    "sg:phone":"+1 330 644 8666",
    "sg:postcode":"44312",
    "sg:province":"OH",
    "sg:tags":[
        "church"
    ],
    "wof:name":"First Baptist Church Green Twp",
    "wof:placetype":"venue"
},
  "geometry": {"coordinates":[-81.493381,40.976318],"type":"Point"}
}