{
  "type": "Feature",
  "properties": {
    "iso:country":"US",
    "sg:address":"5566 Chambersburg Rd",
    "sg:city":"Dayton",
    "sg:classifiers":[
        {
            "category":"Organizations",
            "subcategory":"Religious Organization",
            "type":"Services"
        }
    ],
    "sg:phone":"+1 937 233 4632",
    "sg:postcode":"45424",
    "sg:province":"OH",
    "sg:tags":[
        "church"
    ],
    "sg:website":"www.forministry.com",
    "wof:name":"Saint Matthew Lutheran Church",
    "wof:placetype":"venue"
},
  "geometry": {"coordinates":[-84.13079500000001,39.847809],"type":"Point"}
}