{
  "type": "Feature",
  "properties": {
    "addr:full":"19562 N Dixie Hwy Bowling Green OH 43402",
    "addr:housenumber":"19562",
    "addr:postcode":"43402",
    "addr:street":"N Dixie Hwy",
    "iso:country":"US",
    "sg:address":"19562 N Dixie Hwy",
    "sg:city":"Bowling Green",
    "sg:classifiers":[
        {
            "category":"Wholesale",
            "subcategory":"Hardware",
            "type":"Manufacturing & Wholesale Goods"
        },
        {
            "category":"Retail",
            "subcategory":"Repair Shop",
            "type":"Services"
        }
    ],
    "sg:phone":"+1 419 354 3131",
    "sg:postcode":"43402",
    "sg:province":"OH",
    "sg:tags":[
        "conditioning",
        "refrigerating",
        "air"
    ],
    "wof:name":"Journeyman Refrigeration Co",
    "wof:placetype":"venue"
},
  "geometry": {"coordinates":[-83.650831,41.443172],"type":"Point"}
}