{
  "type": "Feature",
  "properties": {
    "addr:full": "443 E Central Ave Miamisburg OH 45342",
    "addr:housenumber": "443",
    "addr:postcode": "45342",
    "addr:street": "E Central Ave",
    "iso:country": "US",
    "sg:address": "443 E Central Ave",
    "sg:city": "Miamisburg",
    "sg:classifiers": [
      {
        "category": "Professional",
        "subcategory": "Accounting \u0026 Tax Preparation",
        "type": "Services"
      }
    ],
    "sg:phone": "+1 937 865 0089",
    "sg:postcode": "45342",
    "sg:province": "OH",
    "sg:tags": [
      "accountant"
    ],
    "wof:name": "Ronald E Powers CPA",
    "wof:placetype": "venue"
  },
  "geometry": {"coordinates":[-84.28377,39.641644],"type":"Point"}
}
