{
  "type": "Feature",
  "properties": {
    "iso:country":"US",
    "sg:address":"443 E Central Ave",
    "sg:city":"Miamisburg",
    "sg:classifiers":[
        {
            "category":"Professional",
            "subcategory":"Accounting & Tax Preparation",
            "type":"Services"
        }
    ],
    "sg:phone":"+1 937 865 0089",
    "sg:postcode":"45342",
    "sg:province":"OH",
    "sg:tags":[
        "accountant"
    ],
    "wof:name":"Ronald E Powers CPA",
    "wof:placetype":"venue"
},
  "geometry": {"coordinates":[-84.28377,39.641644],"type":"Point"}
}