{
  "type": "Feature",
  "properties": {
    "addr:full": "820 N Washington St Van Wert OH 45891",
    "addr:housenumber": "820",
    "addr:postcode": "45891",
    "addr:street": "N Washington St",
    "iso:country": "US",
    "sg:address": "820 N Washington St",
    "sg:city": "Van Wert",
    "sg:classifiers": [
      {
        "category": "Restaurant",
        "type": "Food \u0026 Drink"
      }
    ],
    "sg:phone": "+1 419 238 9115",
    "sg:postcode": "45891",
    "sg:province": "OH",
    "wof:name": "Lock Sixteen Catering Inc",
    "wof:placetype": "venue"
  },
  "geometry": {"coordinates":[-84.583035,40.880626],"type":"Point"}
}
