{
  "type": "Feature",
  "properties": {
    "iso:country":"US",
    "sg:address":"820 N Washington St",
    "sg:city":"Van Wert",
    "sg:classifiers":[
        {
            "category":"Restaurant",
            "type":"Food & Drink"
        }
    ],
    "sg:phone":"+1 419 238 9115",
    "sg:postcode":"45891",
    "sg:province":"OH",
    "wof:name":"Lock Sixteen Catering Inc",
    "wof:placetype":"venue"
},
  "geometry": {"coordinates":[-84.583035,40.880626],"type":"Point"}
}