{
  "type": "Feature",
  "properties": {
    "iso:country":"US",
    "sg:address":"37 Lawrence Ave",
    "sg:city":"Miamisburg",
    "sg:classifiers":[
        {
            "category":"Insurance",
            "subcategory":"Insurance Agent",
            "type":"Services"
        }
    ],
    "sg:phone":"+1 937 847 8683",
    "sg:postcode":"45342",
    "sg:province":"OH",
    "wof:name":"AFLAC",
    "wof:placetype":"venue"
},
  "geometry": {"coordinates":[-84.27012499999999,39.639139],"type":"Point"}
}