{
  "type": "Feature",
  "properties": {
    "addr:full":"11300 Jefferson St Cincinnati OH 45241",
    "addr:housenumber":"11300",
    "addr:postcode":"45241",
    "addr:street":"Jefferson St",
    "iso:country":"US",
    "sg:address":"11300 Jefferson St",
    "sg:city":"Cincinnati",
    "sg:classifiers":[
        {
            "category":"Professional",
            "subcategory":"Business Services",
            "type":"Services"
        }
    ],
    "sg:phone":"+1 513 769 3049",
    "sg:postcode":"45241",
    "sg:province":"OH",
    "sg:tags":[
        "auctioneer"
    ],
    "sg:website":"http://www.hiltonauctioneer.com",
    "wof:name":"Hilton Auctioneers",
    "wof:placetype":"venue"
},
  "geometry": {"coordinates":[-84.413521,39.2756],"type":"Point"}
}