{
  "type": "Feature",
  "properties": {
    "addr:full": "153 E Main St Hopedale OH 43976",
    "addr:housenumber": "153",
    "addr:postcode": "43976",
    "addr:street": "E Main St",
    "iso:country": "US",
    "sg:address": "153 E Main St",
    "sg:city": "Hopedale",
    "sg:classifiers": [
      {
        "category": "Restaurant",
        "type": "Food \u0026 Drink"
      }
    ],
    "sg:phone": "+1 740 937 2122",
    "sg:postcode": "43976",
    "sg:province": "OH",
    "sg:tags": [
      "eating"
    ],
    "wof:name": "Alameda Inn",
    "wof:placetype": "venue"
  },
  "geometry": {"coordinates":[-80.894598,40.325957],"type":"Point"}
}
