{
  "type": "Feature",
  "properties": {
    "iso:country":"US",
    "sg:address":"153 E Main St",
    "sg:city":"Hopedale",
    "sg:classifiers":[
        {
            "category":"Restaurant",
            "type":"Food & Drink"
        }
    ],
    "sg:phone":"+1 740 937 2122",
    "sg:postcode":"43976",
    "sg:province":"OH",
    "sg:tags":[
        "eating"
    ],
    "wof:name":"Alameda Inn",
    "wof:placetype":"venue"
},
  "geometry": {"coordinates":[-80.894598,40.325957],"type":"Point"}
}