{
  "type": "Feature",
  "properties": {
    "addr:full":"2279 Maylo Path Akron OH 44312",
    "addr:housenumber":"2279",
    "addr:postcode":"44312",
    "addr:street":"Maylo Path",
    "iso:country":"US",
    "sg:address":"2279 Maylo Path",
    "sg:city":"Akron",
    "sg:classifiers":[
        {
            "category":"Shopping",
            "subcategory":"Computers & Home Electronics",
            "type":"Retail Goods"
        }
    ],
    "sg:phone":"+1 330 592 4430",
    "sg:postcode":"44312",
    "sg:province":"OH",
    "wof:name":"T&D Computers",
    "wof:placetype":"venue"
},
  "geometry": {"coordinates":[-81.440882,40.982338],"type":"Point"}
}