{
  "type": "Feature",
  "properties": {
    "iso:country":"US",
    "sg:address":"8501 Tanglewood Sq",
    "sg:city":"Chagrin Falls",
    "sg:classifiers":[
        {
            "category":"Banks & Credit Unions",
            "subcategory":"Bank",
            "type":"Services"
        }
    ],
    "sg:phone":"+1 440 543 5155",
    "sg:postcode":"44023",
    "sg:province":"OH",
    "wof:name":"Chase",
    "wof:placetype":"venue"
},
  "geometry": {"coordinates":[-81.336776,41.391235],"type":"Point"}
}