{
  "type": "Feature",
  "properties": {
    "addr:full":"169 Linden Dr Painesville OH 44077",
    "addr:housenumber":"169",
    "addr:postcode":"44077",
    "addr:street":"Linden Dr",
    "iso:country":"US",
    "sg:address":"169 Linden Dr",
    "sg:city":"Painesville",
    "sg:classifiers":[
        {
            "category":"Building & Trades",
            "subcategory":"Construction",
            "type":"Services"
        }
    ],
    "sg:phone":"+1 440 352 8247",
    "sg:postcode":"44077",
    "sg:province":"OH",
    "sg:tags":[
        "hanging",
        "contractor"
    ],
    "wof:name":"Guardian Painting",
    "wof:placetype":"venue"
},
  "geometry": {"coordinates":[-81.26572899999999,41.702331],"type":"Point"}
}