{
  "type": "Feature",
  "properties": {
    "addr:full": "4550 Glendale Milford Rd Cincinnati OH 45242",
    "addr:housenumber": "4550",
    "addr:postcode": "45242",
    "addr:street": "Glendale Milford Rd",
    "iso:country": "US",
    "sg:address": "4550 Glendale Milford Rd",
    "sg:city": "Cincinnati",
    "sg:classifiers": [
      {
        "category": "Restaurant",
        "type": "Food \u0026 Drink"
      }
    ],
    "sg:phone": "+1 513 563 9464",
    "sg:postcode": "45242",
    "sg:province": "OH",
    "sg:website": "www.buffalowildwings.com",
    "wof:name": "Buffalo Wild Wings Grill \u0026 Bar",
    "wof:placetype": "venue"
  },
  "geometry": {"coordinates":[-84.39228,39.252865],"type":"Point"}
}
