{
  "type": "Feature",
  "properties": {
    "addr:full":"6601 Hasler Ln Cincinnati OH 45216",
    "addr:housenumber":"6601",
    "addr:postcode":"45216",
    "addr:street":"Hasler Ln",
    "iso:country":"US",
    "sg:address":"6601 Hasler Ln",
    "sg:city":"Cincinnati",
    "sg:classifiers":[
        {
            "category":"Building & Trades",
            "subcategory":"Plumbing",
            "type":"Services"
        }
    ],
    "sg:phone":"+1 513 242 0520",
    "sg:postcode":"45216",
    "sg:province":"OH",
    "sg:tags":[
        "contractor"
    ],
    "wof:name":"Royal Plumbing Co",
    "wof:placetype":"venue"
},
  "geometry": {"coordinates":[-84.482377,39.188812],"type":"Point"}
}