{
  "type": "Feature",
  "properties": {
    "addr:full":"3572 Lossing St Cincinnati OH 45220",
    "addr:postcode":"3572;45220",
    "addr:street":"Lossing St",
    "iso:country":"US",
    "sg:address":"3572 Lossing St",
    "sg:city":"Cincinnati",
    "sg:classifiers":[
        {
            "category":"Professional",
            "type":"Services"
        }
    ],
    "sg:phone":"+1 513 961 7420",
    "sg:postcode":"45220",
    "sg:province":"OH",
    "sg:tags":[
        "writer"
    ],
    "wof:name":"Sandy's Writings",
    "wof:placetype":"venue"
},
  "geometry": {"coordinates":[-84.50939200000001,39.149532],"type":"Point"}
}