{
  "type": "Feature",
  "properties": {
    "addr:full":"145 Duis Ave Wheelersburg OH 45694",
    "addr:housenumber":"145",
    "addr:postcode":"45694",
    "addr:street":"Duis Ave",
    "iso:country":"US",
    "sg:address":"145 Duis Ave",
    "sg:city":"Wheelersburg",
    "sg:classifiers":[
        {
            "category":"Autos & Motor Vehicles",
            "subcategory":"Boat Sales",
            "type":"Retail Goods"
        }
    ],
    "sg:phone":"+1 740 574 5600",
    "sg:postcode":"45694",
    "sg:province":"OH",
    "sg:tags":[
        "dealer",
        "sales"
    ],
    "wof:name":"Freedom Outdoors",
    "wof:placetype":"venue"
},
  "geometry": {"coordinates":[-82.861456,38.732545],"type":"Point"}
}