{
  "type": "Feature",
  "properties": {
    "addr:full": "1104 N Court St Medina OH 44256",
    "addr:housenumber": "1104",
    "addr:postcode": "44256",
    "addr:street": "N Court St",
    "iso:country": "US",
    "sg:address": "1104 N Court St",
    "sg:city": "Medina",
    "sg:classifiers": [
      {
        "category": "Shopping",
        "subcategory": "Computers \u0026 Home Electronics",
        "type": "Retail Goods"
      }
    ],
    "sg:phone": "+1 330 723 6030",
    "sg:postcode": "44256",
    "sg:province": "OH",
    "sg:tags": [
      "game",
      "video"
    ],
    "wof:name": "EB Games",
    "wof:placetype": "venue"
  },
  "geometry": {"coordinates":[-81.862752,41.153705],"type":"Point"}
}
