{
  "type": "Feature",
  "properties": {
    "iso:country":"US",
    "sg:address":"184 Heatherdown Dr",
    "sg:city":"Westerville",
    "sg:classifiers":[
        {
            "category":"Organizations",
            "subcategory":"Religious Organization",
            "type":"Services"
        }
    ],
    "sg:phone":"+1 614 865 1201",
    "sg:postcode":"43081",
    "sg:province":"OH",
    "sg:tags":[
        "church"
    ],
    "wof:name":"Church Authority - The Belief",
    "wof:placetype":"venue"
},
  "geometry": {"coordinates":[-82.92549699999999,40.105756],"type":"Point"}
}