{
  "type": "Feature",
  "properties": {
    "iso:country":"US",
    "sg:address":"9676 Looney Rd",
    "sg:city":"Piqua",
    "sg:classifiers":[
        {
            "category":"Manufacturing",
            "subcategory":"Metals",
            "type":"Manufacturing & Wholesale Goods"
        }
    ],
    "sg:phone":"+1 937 773 0767",
    "sg:postcode":"45356",
    "sg:province":"OH",
    "sg:tags":[
        "finisher"
    ],
    "wof:name":"Didders & Co",
    "wof:placetype":"venue"
},
  "geometry": {"coordinates":[-84.214533,40.172225],"type":"Point"}
}