{
  "type": "Feature",
  "properties": {
    "addr:full": "1300 S Canfield Niles Rd Youngstown OH 44515",
    "addr:housenumber": "1300",
    "addr:postcode": "44515",
    "addr:street": "S Canfield Niles Rd",
    "iso:country": "US",
    "sg:address": "1300 S Canfield Niles Rd",
    "sg:city": "Youngstown",
    "sg:classifiers": [
      {
        "category": "Health Services",
        "subcategory": "Podiatrist",
        "type": "Services"
      }
    ],
    "sg:phone": "+1 330 792 6519",
    "sg:postcode": "44515",
    "sg:province": "OH",
    "wof:name": "Karlock Lwrnce Krlock Ctherine",
    "wof:placetype": "venue"
  },
  "geometry": {"coordinates":[-80.762903,41.087393],"type":"Point"}
}
