{
  "type": "Feature",
  "properties": {
    "addr:full": "521 E Main St Mc Connelsville OH 43756",
    "addr:housenumber": "521",
    "addr:postcode": "43756",
    "addr:street": "E Main St",
    "iso:country": "US",
    "sg:address": "521 E Main St",
    "sg:city": "Mc Connelsville",
    "sg:classifiers": [
      {
        "category": "Professional",
        "type": "Services"
      }
    ],
    "sg:phone": "+1 740 962 5140",
    "sg:postcode": "43756",
    "sg:province": "OH",
    "sg:tags": [
      "establishment"
    ],
    "wof:name": "Phones Unlimited",
    "wof:placetype": "venue"
  },
  "geometry": {"coordinates":[-81.847223,39.6482],"type":"Point"}
}
