{
  "type": "Feature",
  "properties": {
    "addr:full":"201 N Church St New Carlisle OH 45344",
    "addr:housenumber":"201",
    "addr:postcode":"45344",
    "addr:street":"N Church St",
    "iso:country":"US",
    "sg:address":"201 N Church St",
    "sg:city":"New Carlisle",
    "sg:classifiers":[
        {
            "category":"Health Services",
            "subcategory":"Optometrist",
            "type":"Services"
        }
    ],
    "sg:phone":"+1 937 845 9444",
    "sg:postcode":"45344",
    "sg:province":"OH",
    "wof:name":"Pflaumer & Gehm",
    "wof:placetype":"venue"
},
  "geometry": {"coordinates":[-84.02612999999999,39.93825],"type":"Point"}
}