{
  "type": "Feature",
  "properties": {
    "iso:country":"US",
    "sg:address":"325 S High St",
    "sg:city":"Cortland",
    "sg:classifiers":[
        {
            "category":"Banks & Credit Unions",
            "subcategory":"Bank",
            "type":"Services"
        }
    ],
    "sg:phone":"+1 330 373 1221",
    "sg:postcode":"44410",
    "sg:province":"OH",
    "wof:name":"First Place",
    "wof:placetype":"venue"
},
  "geometry": {"coordinates":[-80.727174,41.324628],"type":"Point"}
}