{
  "type": "Feature",
  "properties": {
    "addr:full":"200 Parmely Ave Elyria OH 44035",
    "addr:housenumber":"200",
    "addr:postcode":"44035",
    "addr:street":"Parmely Ave",
    "iso:country":"US",
    "sg:address":"200 Parmely Ave",
    "sg:city":"Elyria",
    "sg:classifiers":[
        {
            "category":"Manufacturing",
            "subcategory":"Metals",
            "type":"Manufacturing & Wholesale Goods"
        }
    ],
    "sg:phone":"+1 440 323 2084",
    "sg:postcode":"44035",
    "sg:province":"OH",
    "sg:tags":[
        "machine",
        "screw",
        "product",
        "mfg"
    ],
    "wof:name":"Lasco Products Inc",
    "wof:placetype":"venue"
},
  "geometry": {"coordinates":[-82.12127599999999,41.38827],"type":"Point"}
}