{
  "type": "Feature",
  "properties": {
    "addr:full": "530 Lime St Woodville OH 43469",
    "addr:housenumber": "530",
    "addr:postcode": "43469",
    "addr:street": "Lime St",
    "iso:country": "US",
    "sg:address": "530 Lime St",
    "sg:city": "Woodville",
    "sg:classifiers": [
      {
        "category": "Government",
        "subcategory": "Office",
        "type": "Public Place"
      }
    ],
    "sg:phone": "+1 419 849 3031",
    "sg:postcode": "43469",
    "sg:province": "OH",
    "sg:tags": [
      "village"
    ],
    "sg:website": "www.villageofwoodville.com",
    "wof:name": "Light \u0026 Water Plant",
    "wof:placetype": "venue"
  },
  "geometry": {"coordinates":[-83.367452,41.457585],"type":"Point"}
}
