{
  "type": "Feature",
  "properties": {
    "addr:full": "11025 Ashbury Ave Cleveland OH 44106",
    "addr:housenumber": "11025",
    "addr:postcode": "44106",
    "addr:street": "Ashbury Ave",
    "iso:country": "US",
    "sg:address": "11025 Ashbury Ave",
    "sg:city": "Cleveland",
    "sg:classifiers": [
      {
        "category": "Food \u0026 Beverages",
        "subcategory": "Groceries \u0026 Convenience Stores",
        "type": "Retail Goods"
      }
    ],
    "sg:phone": "+1 216 721 2200",
    "sg:postcode": "44106",
    "sg:province": "OH",
    "wof:name": "Lexus Grocery Inc",
    "wof:placetype": "venue"
  },
  "geometry": {"coordinates":[-81.608577,41.517124],"type":"Point"}
}
