{
  "type": "Feature",
  "properties": {
    "addr:full": "1 Marion Ave Mansfield OH 44903",
    "addr:housenumber": "1",
    "addr:postcode": "44903",
    "addr:street": "Marion Ave",
    "iso:country": "US",
    "sg:address": "1 Marion Ave",
    "sg:city": "Mansfield",
    "sg:classifiers": [
      {
        "category": "Wholesale",
        "subcategory": "Durable Goods \u0026 Equipment",
        "type": "Manufacturing \u0026 Wholesale Goods"
      }
    ],
    "sg:phone": "+1 419 524 0300",
    "sg:postcode": "44903",
    "sg:province": "OH",
    "sg:tags": [
      "representative",
      "manufacturer"
    ],
    "wof:name": "Hursh Sales DG Co",
    "wof:placetype": "venue"
  },
  "geometry": {"coordinates":[-82.524344,40.758472],"type":"Point"}
}
