{
  "type": "Feature",
  "properties": {
    "addr:full": "1499 Polaris Pkwy Columbus OH 43240",
    "addr:housenumber": "1499",
    "addr:postcode": "43240",
    "addr:street": "Polaris Pkwy",
    "iso:country": "US",
    "sg:address": "1499 Polaris Pkwy",
    "sg:city": "Columbus",
    "sg:classifiers": [
      {
        "category": "Shopping",
        "subcategory": "Jewelry",
        "type": "Retail Goods"
      },
      {
        "category": "Manufacturing",
        "subcategory": "Jewelry",
        "type": "Manufacturing \u0026 Wholesale Goods"
      }
    ],
    "sg:phone": "+1 614 433 0671",
    "sg:postcode": "43240",
    "sg:province": "OH",
    "sg:tags": [
      "stone",
      "designer",
      "jewelers-wholesale",
      "jeweler",
      "precious",
      "semi-precious",
      "manufacturer"
    ],
    "wof:name": "Jared Galleria Of Jewelry",
    "wof:placetype": "venue"
  },
  "geometry": {"coordinates":[-82.978354,40.141272],"type":"Point"}
}
