{
  "type": "Feature",
  "properties": {
    "iso:country":"US",
    "sg:address":"13800 Shaker Blvd",
    "sg:city":"Cleveland",
    "sg:classifiers":[
        {
            "category":"Real Estate",
            "subcategory":"Real Estate Operator",
            "type":"Services"
        }
    ],
    "sg:phone":"+1 216 561 8675",
    "sg:postcode":"44120",
    "sg:province":"OH",
    "sg:tags":[
        "condominium",
        "association"
    ],
    "sg:website":"www.shakertowers.com",
    "wof:name":"Shaker Towers Condo Assn",
    "wof:placetype":"venue"
},
  "geometry": {"coordinates":[-81.58757,41.483752],"type":"Point"}
}