{
  "type": "Feature",
  "properties": {
    "addr:full": "865 E Center St Marion OH 43302",
    "addr:housenumber": "865",
    "addr:postcode": "43302",
    "addr:street": "E Center St",
    "iso:country": "US",
    "sg:address": "865 E Center St",
    "sg:city": "Marion",
    "sg:classifiers": [
      {
        "category": "Health Services",
        "subcategory": "Health Practitioner",
        "type": "Services"
      }
    ],
    "sg:phone": "+1 740 382 0022",
    "sg:postcode": "43302",
    "sg:province": "OH",
    "sg:tags": [
      "psychologist"
    ],
    "wof:name": "Counseling \u0026 Psychological Svc",
    "wof:placetype": "venue"
  },
  "geometry": {"coordinates":[-83.108721,40.589348],"type":"Point"}
}
