{
  "type": "Feature",
  "properties": {
    "iso:country":"US",
    "sg:address":"1034 Ottawa Ave",
    "sg:city":"Defiance",
    "sg:classifiers":[
        {
            "category":"Food & Beverages",
            "subcategory":"Groceries & Convenience Stores",
            "type":"Retail Goods"
        },
        {
            "category":"Restaurant",
            "type":"Food & Drink"
        }
    ],
    "sg:phone":"+1 419 784 3219",
    "sg:postcode":"43512",
    "sg:province":"OH",
    "sg:tags":[
        "out"
    ],
    "wof:name":"Trevino's Foods",
    "wof:placetype":"venue"
},
  "geometry": {"coordinates":[-84.350341,41.274857],"type":"Point"}
}