{
  "type": "Feature",
  "properties": {
    "addr:full": "1034 Ottawa Ave Defiance OH 43512",
    "addr:housenumber": "1034",
    "addr:postcode": "43512",
    "addr:street": "Ottawa Ave",
    "iso:country": "US",
    "sg:address": "1034 Ottawa Ave",
    "sg:city": "Defiance",
    "sg:classifiers": [
      {
        "category": "Food \u0026 Beverages",
        "subcategory": "Groceries \u0026 Convenience Stores",
        "type": "Retail Goods"
      },
      {
        "category": "Restaurant",
        "type": "Food \u0026 Drink"
      }
    ],
    "sg:phone": "+1 419 784 3219",
    "sg:postcode": "43512",
    "sg:province": "OH",
    "sg:tags": [
      "out"
    ],
    "wof:name": "Trevino's Foods",
    "wof:placetype": "venue"
  },
  "geometry": {"coordinates":[-84.350341,41.274857],"type":"Point"}
}
