{
  "type": "Feature",
  "properties": {
    "iso:country":"US",
    "sg:address":"811 Hillcrest Ave NW",
    "sg:city":"North Canton",
    "sg:classifiers":[
        {
            "category":"Building & Trades",
            "subcategory":"Construction",
            "type":"Services"
        }
    ],
    "sg:phone":"+1 330 499 3393",
    "sg:postcode":"44720",
    "sg:province":"OH",
    "sg:tags":[
        "painter"
    ],
    "wof:name":"B & E Painting",
    "wof:placetype":"venue"
},
  "geometry": {"coordinates":[-81.406208,40.88342],"type":"Point"}
}