{
  "type": "Feature",
  "properties": {
    "iso:country":"US",
    "sg:address":"4723 Cedarhurst Rd",
    "sg:city":"Toledo",
    "sg:classifiers":[
        {
            "category":"Building & Trades",
            "subcategory":"Construction",
            "type":"Services"
        }
    ],
    "sg:phone":"+1 419 475 1959",
    "sg:postcode":"43613",
    "sg:province":"OH",
    "sg:tags":[
        "equipment",
        "computer",
        "rooms"
    ],
    "wof:name":"Diamond Environmental Constr",
    "wof:placetype":"venue"
},
  "geometry": {"coordinates":[-83.616719,41.702958],"type":"Point"}
}