{
  "type": "Feature",
  "properties": {
    "iso:country":"US",
    "sg:address":"8055 Corporate Blvd",
    "sg:city":"Plain City",
    "sg:classifiers":[
        {
            "category":"Retail",
            "subcategory":"Repair Shop",
            "type":"Services"
        }
    ],
    "sg:phone":"+1 614 873 5551",
    "sg:postcode":"43064",
    "sg:province":"OH",
    "sg:tags":[
        "equipment",
        "electronic",
        "supply"
    ],
    "wof:name":"E Cycle",
    "wof:placetype":"venue"
},
  "geometry": {"coordinates":[-83.196704,40.131176],"type":"Point"}
}