{
  "type": "Feature",
  "properties": {
    "iso:country":"US",
    "sg:address":"6600 Salem Ave",
    "sg:city":"Clayton",
    "sg:classifiers":[
        {
            "category":"Social Services",
            "subcategory":"Child Care",
            "type":"Services"
        }
    ],
    "sg:phone":"+1 937 854 2506",
    "sg:postcode":"45315",
    "sg:province":"OH",
    "wof:name":"Crestview Learning Ctr",
    "wof:placetype":"venue"
},
  "geometry": {"coordinates":[-84.310909,39.840851],"type":"Point"}
}