{
  "type": "Feature",
  "properties": {
    "iso:country":"US",
    "sg:address":"2220 Raber Rd",
    "sg:city":"Uniontown",
    "sg:classifiers":[
        {
            "category":"Shopping",
            "subcategory":"Bicycles & Sporting Goods",
            "type":"Retail Goods"
        }
    ],
    "sg:phone":"+1 330 699 4692",
    "sg:postcode":"44685",
    "sg:province":"OH",
    "wof:name":"Demuesy Golf",
    "wof:placetype":"venue"
},
  "geometry": {"coordinates":[-81.44122299999999,40.965605],"type":"Point"}
}