{
  "type": "Feature",
  "properties": {
    "iso:country":"US",
    "sg:address":"23017 Main St",
    "sg:city":"Homeworth",
    "sg:classifiers":[
        {
            "category":"Building & Trades",
            "subcategory":"Construction",
            "type":"Services"
        }
    ],
    "sg:phone":"+1 330 525 7652",
    "sg:postcode":"44634",
    "sg:province":"OH",
    "sg:tags":[
        "excavating",
        "contractor"
    ],
    "wof:name":"Kaiser Construction",
    "wof:placetype":"venue"
},
  "geometry": {"coordinates":[-81.0679,40.836373],"type":"Point"}
}