{
  "type": "Feature",
  "properties": {
    "addr:full":"2157 Twp Hwy 188 Marengo OH 43334",
    "addr:housenumber":"2157",
    "addr:postcode":"43334",
    "addr:street":"Twp Hwy 188",
    "iso:country":"US",
    "sg:address":"2157 Twp Hwy 188",
    "sg:city":"Marengo",
    "sg:classifiers":[
        {
            "category":"Building & Trades",
            "subcategory":"Plumbing",
            "type":"Services"
        }
    ],
    "sg:phone":"+1 419 768 9903",
    "sg:postcode":"43334",
    "sg:province":"OH",
    "sg:tags":[
        "contractor"
    ],
    "wof:name":"Bowmar Plumbing",
    "wof:placetype":"venue"
},
  "geometry": {"coordinates":[-82.71866900000001,40.424767],"type":"Point"}
}