{
  "type": "Feature",
  "properties": {
    "addr:full":"1427 Oakland Park Ave Columbus OH 43224",
    "addr:housenumber":"1427",
    "addr:postcode":"43224",
    "addr:street":"Oakland Park Ave",
    "iso:country":"US",
    "sg:address":"1427 Oakland Park Ave",
    "sg:city":"Columbus",
    "sg:classifiers":[
        {
            "category":"Bars & Pubs",
            "type":"Food & Drink"
        }
    ],
    "sg:phone":"+1 614 261 6925",
    "sg:postcode":"43224",
    "sg:province":"OH",
    "wof:name":"Oakland Park Bar & Grill",
    "wof:placetype":"venue"
},
  "geometry": {"coordinates":[-82.97359400000001,40.031692],"type":"Point"}
}