{
  "type": "Feature",
  "properties": {
    "iso:country":"US",
    "sg:address":"1427 Oakland Park Ave",
    "sg:city":"Columbus",
    "sg:classifiers":[
        {
            "category":"Bars & Pubs",
            "type":"Food & Drink"
        }
    ],
    "sg:phone":"+1 614 261 6925",
    "sg:postcode":"43224",
    "sg:province":"OH",
    "wof:name":"Oakland Park Bar & Grill",
    "wof:placetype":"venue"
},
  "geometry": {"coordinates":[-82.973594,40.031692],"type":"Point"}
}