{
  "type": "Feature",
  "properties": {
    "addr:full":"5311 Sims Rd Groveport OH 43125",
    "addr:housenumber":"5311",
    "addr:postcode":"43125",
    "addr:street":"Sims Rd",
    "iso:country":"US",
    "sg:address":"5311 Sims Rd",
    "sg:city":"Groveport",
    "sg:classifiers":[
        {
            "category":"Autos & Motor Vehicles",
            "subcategory":"Fuel & Gas Station",
            "type":"Retail Goods"
        }
    ],
    "sg:phone":"+1 614 836 3860",
    "sg:postcode":"43125",
    "sg:province":"OH",
    "sg:tags":[
        "station",
        "gasoline"
    ],
    "wof:name":"Sunoco",
    "wof:placetype":"venue"
},
  "geometry": {"coordinates":[-82.84790099999999,39.862676],"type":"Point"}
}