{
  "type": "Feature",
  "properties": {
    "addr:full":"14461 Gaskill Dr NE Alliance OH 44601",
    "addr:housenumber":"14461",
    "addr:postcode":"44601",
    "addr:street":"Gaskill Dr Ne",
    "iso:country":"US",
    "sg:address":"14461 Gaskill Dr NE",
    "sg:city":"Alliance",
    "sg:classifiers":[
        {
            "category":"Manufacturing",
            "subcategory":"Textiles",
            "type":"Manufacturing & Wholesale Goods"
        }
    ],
    "sg:phone":"+1 330 821 1293",
    "sg:postcode":"44601",
    "sg:province":"OH",
    "sg:tags":[
        "hosiery"
    ],
    "wof:name":"Forepleasure",
    "wof:placetype":"venue"
},
  "geometry": {"coordinates":[-81.12124799999999,40.943008],"type":"Point"}
}