{
  "type": "Feature",
  "properties": {
    "addr:full":"621 E Mehring Way Cincinnati OH 45202",
    "addr:housenumber":"621",
    "addr:postcode":"45202",
    "addr:street":"E Mehring Way",
    "iso:country":"US",
    "sg:address":"621 E Mehring Way",
    "sg:city":"Cincinnati",
    "sg:classifiers":[
        {
            "category":"Real Estate",
            "subcategory":"Real Estate Agent",
            "type":"Services"
        }
    ],
    "sg:phone":"+1 513 469 8818",
    "sg:postcode":"45202",
    "sg:province":"OH",
    "sg:tags":[
        "finding",
        "apartment",
        "rental"
    ],
    "wof:name":"United Advertising Media",
    "wof:placetype":"venue"
},
  "geometry": {"coordinates":[-84.511167,39.094787],"type":"Point"}
}