{
  "type": "Feature",
  "properties": {
    "addr:full": "1972 Slaton Ct Columbus OH 43235",
    "addr:housenumber": "1972",
    "addr:postcode": "43235",
    "addr:street": "Slaton Ct",
    "iso:country": "US",
    "sg:address": "1972 Slaton Ct",
    "sg:city": "Columbus",
    "sg:classifiers": [
      {
        "category": "Building \u0026 Trades",
        "subcategory": "Construction",
        "type": "Services"
      }
    ],
    "sg:phone": "+1 614 596 3218",
    "sg:postcode": "43235",
    "sg:province": "OH",
    "sg:tags": [
      "general",
      "contractor"
    ],
    "wof:name": "Orv's Handyman Svc",
    "wof:placetype": "venue"
  },
  "geometry": {"coordinates":[-83.066728,40.113363],"type":"Point"}
}
