{
  "type": "Feature",
  "properties": {
    "addr:full":"55 Maryann St Portsmouth OH 45662",
    "addr:housenumber":"55",
    "addr:postcode":"45662",
    "addr:street":"Maryann St",
    "iso:country":"US",
    "sg:address":"55 Maryann St",
    "sg:city":"Portsmouth",
    "sg:classifiers":[
        {
            "category":"Government",
            "subcategory":"Office",
            "type":"Public Place"
        }
    ],
    "sg:phone":"+1 740 354 7766",
    "sg:postcode":"45662",
    "sg:province":"OH",
    "sg:tags":[
        "village"
    ],
    "wof:name":"Portsmouth Service Dept",
    "wof:placetype":"venue"
},
  "geometry": {"coordinates":[-82.98294199999999,38.729713],"type":"Point"}
}