{
  "type": "Feature",
  "properties": {
    "addr:full": "2916 W US Hwy 36 Urbana OH 43078",
    "addr:housenumber": "2916",
    "addr:postcode": "43078",
    "addr:street": "W Us Hwy 36",
    "iso:country": "US",
    "sg:address": "2916 W US Hwy 36",
    "sg:city": "Urbana",
    "sg:classifiers": [
      {
        "category": "Building \u0026 Trades",
        "subcategory": "Construction",
        "type": "Services"
      }
    ],
    "sg:phone": "+1 937 653 6170",
    "sg:postcode": "43078",
    "sg:province": "OH",
    "sg:tags": [
      "general",
      "contractor"
    ],
    "wof:name": "Bair Construction",
    "wof:placetype": "venue"
  },
  "geometry": {"coordinates":[-83.816707,40.108434],"type":"Point"}
}
