{
  "type": "Feature",
  "properties": {
    "addr:full":"1717 36th St NW Canton OH 44709",
    "addr:housenumber":"1717",
    "addr:postcode":"44709",
    "addr:street":"36Th St Nw",
    "iso:country":"US",
    "sg:address":"1717 36th St NW",
    "sg:city":"Canton",
    "sg:classifiers":[
        {
            "category":"Personal",
            "subcategory":"Barber",
            "type":"Services"
        }
    ],
    "sg:phone":"+1 330 492 2760",
    "sg:postcode":"44709",
    "sg:province":"OH",
    "wof:name":"Cutters Unlimited",
    "wof:placetype":"venue"
},
  "geometry": {"coordinates":[-81.387747,40.838312],"type":"Point"}
}