{
  "type": "Feature",
  "properties": {
    "addr:full":"125 Whiting Ave Toledo OH 43609",
    "addr:housenumber":"125",
    "addr:postcode":"43609",
    "addr:street":"Whiting Ave",
    "iso:country":"US",
    "sg:address":"125 Whiting Ave",
    "sg:city":"Toledo",
    "sg:classifiers":[
        {
            "category":"Professional",
            "type":"Services"
        }
    ],
    "sg:phone":"+1 419 389 1019",
    "sg:postcode":"43609",
    "sg:province":"OH",
    "wof:name":"Sharon Gamble",
    "wof:placetype":"venue"
},
  "geometry": {"coordinates":[-83.586342,41.63553],"type":"Point"}
}