{
  "type": "Feature",
  "properties": {
    "addr:full": "10 S Xenia St Enon OH 45323",
    "addr:housenumber": "10",
    "addr:postcode": "45323",
    "addr:street": "S Xenia St",
    "iso:country": "US",
    "sg:address": "10 S Xenia St",
    "sg:city": "Enon",
    "sg:classifiers": [
      {
        "category": "Retail",
        "subcategory": "Animal Services",
        "type": "Services"
      }
    ],
    "sg:phone": "+1 937 864 5108",
    "sg:postcode": "45323",
    "sg:province": "OH",
    "wof:name": "Hair of Dog",
    "wof:placetype": "venue"
  },
  "geometry": {"coordinates":[-83.936882,39.877683],"type":"Point"}
}
