{
  "type": "Feature",
  "properties": {
    "addr:full":"1021 Vicksburg Dr Cleveland OH 44134",
    "addr:housenumber":"1021",
    "addr:postcode":"44134",
    "addr:street":"Vicksburg Dr",
    "iso:country":"US",
    "sg:address":"1021 Vicksburg Dr",
    "sg:city":"Cleveland",
    "sg:classifiers":[
        {
            "category":"Building & Trades",
            "subcategory":"Electrical",
            "type":"Services"
        }
    ],
    "sg:phone":"+1 440 845 6930",
    "sg:postcode":"44134",
    "sg:province":"OH",
    "sg:tags":[
        "electrical",
        "contractor"
    ],
    "wof:name":"Ted Electric Service",
    "wof:placetype":"venue"
},
  "geometry": {"coordinates":[-81.68479600000001,41.3691],"type":"Point"}
}