{
  "type": "Feature",
  "properties": {
    "addr:full": "105 Ventoura Vista Dr Toronto OH 43964",
    "addr:housenumber": "105",
    "addr:postcode": "43964",
    "addr:street": "Ventoura Vista Dr",
    "iso:country": "US",
    "sg:address": "105 Ventoura Vista Dr",
    "sg:city": "Toronto",
    "sg:classifiers": [
      {
        "category": "Restaurant",
        "type": "Food \u0026 Drink"
      }
    ],
    "sg:phone": "+1 740 537 4457",
    "sg:postcode": "43964",
    "sg:province": "OH",
    "sg:tags": [
      "eating"
    ],
    "wof:name": "Tazs Pizza",
    "wof:placetype": "venue"
  },
  "geometry": {"coordinates":[-80.598344,40.477292],"type":"Point"}
}
