{
  "type": "Feature",
  "properties": {
    "iso:country":"US",
    "sg:address":"105 Ventoura Vista Dr",
    "sg:city":"Toronto",
    "sg:classifiers":[
        {
            "category":"Restaurant",
            "type":"Food & Drink"
        }
    ],
    "sg:phone":"+1 740 537 4457",
    "sg:postcode":"43964",
    "sg:province":"OH",
    "sg:tags":[
        "eating"
    ],
    "wof:name":"Tazs Pizza",
    "wof:placetype":"venue"
},
  "geometry": {"coordinates":[-80.598344,40.477292],"type":"Point"}
}