{
  "type": "Feature",
  "properties": {
    "iso:country":"US",
    "sg:address":"3979 Parkway Ln",
    "sg:city":"Hilliard",
    "sg:classifiers":[
        {
            "category":"Professional",
            "type":"Services"
        }
    ],
    "sg:phone":"+1 614 771 0171",
    "sg:postcode":"43026",
    "sg:province":"OH",
    "wof:name":"RCA Svc Co Div",
    "wof:placetype":"venue"
},
  "geometry": {"coordinates":[-83.131245,40.032282],"type":"Point"}
}