{
  "type": "Feature",
  "properties": {
    "iso:country":"US",
    "sg:address":"4320 Home Rd",
    "sg:city":"Powell",
    "sg:classifiers":[
        {
            "category":"Professional",
            "subcategory":"Secretarial Services",
            "type":"Services"
        }
    ],
    "sg:phone":"+1 740 881 5500",
    "sg:postcode":"43065",
    "sg:province":"OH",
    "sg:tags":[
        "resume"
    ],
    "wof:name":"C S Lind & Assoc",
    "wof:placetype":"venue"
},
  "geometry": {"coordinates":[-83.110665,40.196568],"type":"Point"}
}