{
  "type": "Feature",
  "properties": {
    "addr:full": "120 E Main St Pandora OH 45877",
    "addr:housenumber": "120",
    "addr:postcode": "45877",
    "addr:street": "E Main St",
    "iso:country": "US",
    "sg:address": "120 E Main St",
    "sg:city": "Pandora",
    "sg:classifiers": [
      {
        "category": "Government",
        "subcategory": "Post Office",
        "type": "Public Place"
      }
    ],
    "sg:phone": "+1 419 384 3401",
    "sg:postcode": "45877",
    "sg:province": "OH",
    "wof:name": "US Post Office",
    "wof:placetype": "venue"
  },
  "geometry": {"coordinates":[-83.96189,40.948095],"type":"Point"}
}
