{
  "type": "Feature",
  "properties": {
    "iso:country":"US",
    "sg:address":"195 E Satin St",
    "sg:city":"Jefferson",
    "sg:classifiers":[
        {
            "category":"Autos & Motor Vehicles",
            "subcategory":"Automobile Sales",
            "type":"Retail Goods"
        }
    ],
    "sg:phone":"+1 440 576 4861",
    "sg:postcode":"44047",
    "sg:province":"OH",
    "sg:tags":[
        "truck"
    ],
    "wof:name":"Tank Trucks",
    "wof:placetype":"venue"
},
  "geometry": {"coordinates":[-80.759676,41.736364],"type":"Point"}
}