{
  "type": "Feature",
  "properties": {
    "iso:country":"US",
    "sg:address":"806 6th St",
    "sg:city":"Portsmouth",
    "sg:classifiers":[
        {
            "category":"Professional",
            "subcategory":"Lawyer & Legal Services",
            "type":"Services"
        }
    ],
    "sg:phone":"+1 740 354 3600",
    "sg:postcode":"45662",
    "sg:province":"OH",
    "sg:tags":[
        "attorney"
    ],
    "wof:name":"Miller Searl & Fitch",
    "wof:placetype":"venue"
},
  "geometry": {"coordinates":[-82.99642900000001,38.734708],"type":"Point"}
}