{
  "type": "Feature",
  "properties": {
    "addr:full": "806 6th St Portsmouth OH 45662",
    "addr:housenumber": "806",
    "addr:postcode": "45662",
    "addr:street": "6Th St",
    "iso:country": "US",
    "sg:address": "806 6th St",
    "sg:city": "Portsmouth",
    "sg:classifiers": [
      {
        "category": "Professional",
        "subcategory": "Lawyer \u0026 Legal Services",
        "type": "Services"
      }
    ],
    "sg:phone": "+1 740 354 3600",
    "sg:postcode": "45662",
    "sg:province": "OH",
    "sg:tags": [
      "attorney"
    ],
    "wof:name": "Miller Searl \u0026 Fitch",
    "wof:placetype": "venue"
  },
  "geometry": {"coordinates":[-82.996429,38.734708],"type":"Point"}
}
