{
  "type": "Feature",
  "properties": {
    "iso:country":"US",
    "sg:address":"11525 Chester Rd",
    "sg:city":"Cincinnati",
    "sg:classifiers":[
        {
            "category":"Professional",
            "type":"Services"
        },
        {
            "category":"Restaurant",
            "type":"Food & Drink"
        }
    ],
    "sg:phone":"+1 513 771 0022",
    "sg:postcode":"45246",
    "sg:province":"OH",
    "sg:tags":[
        "italian",
        "caterer"
    ],
    "wof:name":"Vincenzo's Restaurant",
    "wof:placetype":"venue"
},
  "geometry": {"coordinates":[-84.443147,39.283344],"type":"Point"}
}