{
  "type": "Feature",
  "properties": {
    "addr:full": "9030 Montgomery Rd Cincinnati OH 45242",
    "addr:housenumber": "9030",
    "addr:postcode": "45242",
    "addr:street": "Montgomery Rd",
    "iso:country": "US",
    "sg:address": "9030 Montgomery Rd",
    "sg:city": "Cincinnati",
    "sg:classifiers": [
      {
        "category": "Health Services",
        "subcategory": "Podiatrist",
        "type": "Services"
      }
    ],
    "sg:phone": "+1 513 745 9988",
    "sg:postcode": "45242",
    "sg:province": "OH",
    "wof:name": "Affiliated Foot \u0026 Ankle Ctr",
    "wof:placetype": "venue"
  },
  "geometry": {"coordinates":[-84.357726,39.217907],"type":"Point"}
}
