{
  "type": "Feature",
  "properties": {
    "addr:full": "18947 Burkhart Rd Dalton OH 44618",
    "addr:postcode": "18947;44618",
    "addr:street": "Burkhart Rd",
    "iso:country": "US",
    "sg:address": "18947 Burkhart Rd",
    "sg:city": "Dalton",
    "sg:classifiers": [
      {
        "category": "Freight",
        "type": "Transportation"
      }
    ],
    "sg:phone": "+1 330 828 8282",
    "sg:postcode": "44618",
    "sg:province": "OH",
    "sg:tags": [
      "operator",
      "local",
      "trucking"
    ],
    "wof:name": "Byall Dale Trucking",
    "wof:placetype": "venue"
  },
  "geometry": {"coordinates":[-81.653328,40.83631],"type":"Point"}
}
