{
  "type": "Feature",
  "properties": {
    "addr:full": "6406 Stumph Rd Cleveland OH 44130",
    "addr:housenumber": "6406",
    "addr:postcode": "44130",
    "addr:street": "Stumph Rd",
    "iso:country": "US",
    "sg:address": "6406 Stumph Rd",
    "sg:city": "Cleveland",
    "sg:classifiers": [
      {
        "category": "Health Services",
        "subcategory": "Chiropractor",
        "type": "Services"
      }
    ],
    "sg:phone": "+1 440 886 2222",
    "sg:postcode": "44130",
    "sg:province": "OH",
    "wof:name": "Zymler Chiropractic Office Inc",
    "wof:placetype": "venue"
  },
  "geometry": {"coordinates":[-81.766502,41.390774],"type":"Point"}
}
