{
  "type": "Feature",
  "properties": {
    "iso:country":"US",
    "sg:address":"3705 E 116th St",
    "sg:city":"Cleveland",
    "sg:classifiers":[
        {
            "category":"Restaurant",
            "type":"Food & Drink"
        }
    ],
    "sg:phone":"+1 216 751 1177",
    "sg:postcode":"44105",
    "sg:province":"OH",
    "sg:tags":[
        "eating"
    ],
    "wof:name":"Big Bite",
    "wof:placetype":"venue"
},
  "geometry": {"coordinates":[-81.60278599999999,41.458404],"type":"Point"}
}