{
  "type": "Feature",
  "properties": {
    "addr:full": "3705 E 116th St Cleveland OH 44105",
    "addr:housenumber": "3705",
    "addr:postcode": "44105",
    "addr:street": "E 116Th St",
    "iso:country": "US",
    "sg:address": "3705 E 116th St",
    "sg:city": "Cleveland",
    "sg:classifiers": [
      {
        "category": "Restaurant",
        "type": "Food \u0026 Drink"
      }
    ],
    "sg:phone": "+1 216 751 1177",
    "sg:postcode": "44105",
    "sg:province": "OH",
    "sg:tags": [
      "eating"
    ],
    "wof:name": "Big Bite",
    "wof:placetype": "venue"
  },
  "geometry": {"coordinates":[-81.602786,41.458404],"type":"Point"}
}
