{
  "type": "Feature",
  "properties": {
    "addr:full":"1662 S Galena Rd Galena OH 43021",
    "addr:housenumber":"1662",
    "addr:postcode":"43021",
    "addr:street":"S Galena Rd",
    "iso:country":"US",
    "sg:address":"1662 S Galena Rd",
    "sg:city":"Galena",
    "sg:classifiers":[
        {
            "category":"Shopping",
            "subcategory":"Jewelry",
            "type":"Retail Goods"
        }
    ],
    "sg:phone":"+1 740 965 3035",
    "sg:postcode":"43021",
    "sg:province":"OH",
    "wof:name":"Sandcastle Jewelry Designs",
    "wof:placetype":"venue"
},
  "geometry": {"coordinates":[-82.883926,40.229376],"type":"Point"}
}