{
  "type": "Feature",
  "properties": {
    "addr:full": "1115 W 5th Ave Lancaster OH 43130",
    "addr:housenumber": "1115",
    "addr:postcode": "43130",
    "addr:street": "W 5Th Ave",
    "iso:country": "US",
    "sg:address": "1115 W 5th Ave",
    "sg:city": "Lancaster",
    "sg:classifiers": [
      {
        "category": "Manufacturing",
        "subcategory": "Glass \u0026 Minerals",
        "type": "Manufacturing \u0026 Wholesale Goods"
      }
    ],
    "sg:phone": "+1 740 653 2527",
    "sg:postcode": "43130",
    "sg:province": "OH",
    "wof:name": "Anchor Hocking Corp",
    "wof:placetype": "venue"
  },
  "geometry": {"coordinates":[-82.618935,39.719155],"type":"Point"}
}
