{
  "type": "Feature",
  "properties": {
    "iso:country":"US",
    "sg:address":"1115 W 5th Ave",
    "sg:city":"Lancaster",
    "sg:classifiers":[
        {
            "category":"Manufacturing",
            "subcategory":"Glass & Minerals",
            "type":"Manufacturing & Wholesale Goods"
        }
    ],
    "sg:phone":"+1 740 653 2527",
    "sg:postcode":"43130",
    "sg:province":"OH",
    "wof:name":"Anchor Hocking Corp",
    "wof:placetype":"venue"
},
  "geometry": {"coordinates":[-82.618935,39.719155],"type":"Point"}
}