{
  "type": "Feature",
  "properties": {
    "addr:full": "3049 E Pioneer Trl Aurora OH 44202",
    "addr:housenumber": "3049",
    "addr:postcode": "44202",
    "addr:street": "E Pioneer Trl",
    "iso:country": "US",
    "sg:address": "3049 E Pioneer Trl",
    "sg:city": "Aurora",
    "sg:classifiers": [
      {
        "category": "Home \u0026 Garden",
        "subcategory": "Household Appliances",
        "type": "Retail Goods"
      }
    ],
    "sg:phone": "+1 330 562 8850",
    "sg:postcode": "44202",
    "sg:province": "OH",
    "sg:tags": [
      "pump"
    ],
    "wof:name": "Max Herr \u0026 Sons Well Drilling",
    "wof:placetype": "venue"
  },
  "geometry": {"coordinates":[-81.285155,41.296912],"type":"Point"}
}
