{
  "type": "Feature",
  "properties": {
    "iso:country":"US",
    "sg:address":"2658 Wieland Rd",
    "sg:city":"Defiance",
    "sg:classifiers":[
        {
            "category":"Farming",
            "subcategory":"Farm",
            "type":"Manufacturing & Wholesale Goods"
        }
    ],
    "sg:phone":"+1 419 428 4295",
    "sg:postcode":"43512",
    "sg:province":"OH",
    "sg:tags":[
        "crop",
        "general"
    ],
    "wof:name":"Mack Farm",
    "wof:placetype":"venue"
},
  "geometry": {"coordinates":[-84.419301,41.401949],"type":"Point"}
}