{
  "type": "Feature",
  "properties": {
    "addr:full":"316 Oakley Rd Wooster OH 44691",
    "addr:housenumber":"316",
    "addr:postcode":"44691",
    "addr:street":"Oakley Rd",
    "iso:country":"US",
    "sg:address":"316 Oakley Rd",
    "sg:city":"Wooster",
    "sg:classifiers":[
        {
            "category":"Professional",
            "type":"Services"
        }
    ],
    "sg:phone":"+1 330 263 9151",
    "sg:postcode":"44691",
    "sg:province":"OH",
    "wof:name":"Helmick",
    "wof:placetype":"venue"
},
  "geometry": {"coordinates":[-81.94080700000001,40.82055],"type":"Point"}
}