{
  "type": "Feature",
  "properties": {
    "addr:full":"6 Main St Centerburg OH 43011",
    "addr:housenumber":"6",
    "addr:postcode":"43011",
    "addr:street":"Main St",
    "iso:country":"US",
    "sg:address":"6 Main St",
    "sg:city":"Centerburg",
    "sg:classifiers":[
        {
            "category":"Real Estate",
            "subcategory":"Real Estate Agent",
            "type":"Services"
        }
    ],
    "sg:phone":"+1 740 625 6400",
    "sg:postcode":"43011",
    "sg:province":"OH",
    "wof:name":"Real Estate Showcase Inc",
    "wof:placetype":"venue"
},
  "geometry": {"coordinates":[-82.69551199999999,40.305036],"type":"Point"}
}