{
  "type": "Feature",
  "properties": {
    "addr:full": "20105 Scottsdale Blvd Cleveland OH 44122",
    "addr:housenumber": "20105",
    "addr:postcode": "44122",
    "addr:street": "Scottsdale Blvd",
    "iso:country": "US",
    "sg:address": "20105 Scottsdale Blvd",
    "sg:city": "Cleveland",
    "sg:classifiers": [
      {
        "category": "Building \u0026 Trades",
        "subcategory": "Construction",
        "type": "Services"
      }
    ],
    "sg:phone": "+1 216 491 9265",
    "sg:postcode": "44122",
    "sg:province": "OH",
    "sg:tags": [
      "house"
    ],
    "wof:name": "Aimee Pergalski Master Bldr",
    "wof:placetype": "venue"
  },
  "geometry": {"coordinates":[-81.537478,41.457767],"type":"Point"}
}
