{
  "type": "Feature",
  "properties": {
    "iso:country":"US",
    "sg:address":"101 E Court St",
    "sg:city":"Sidney",
    "sg:classifiers":[
        {
            "category":"Banks & Credit Unions",
            "subcategory":"Financial Services",
            "type":"Services"
        }
    ],
    "sg:phone":"+1 937 492 6129",
    "sg:postcode":"45365",
    "sg:province":"OH",
    "sg:tags":[
        "loan",
        "co",
        "savings",
        "for",
        "holding"
    ],
    "sg:website":"www.peoplesfederalsandl.com",
    "wof:name":"Peoples-Sidney Financial Corp",
    "wof:placetype":"venue"
},
  "geometry": {"coordinates":[-84.155067,40.284403],"type":"Point"}
}