{
  "type": "Feature",
  "properties": {
    "addr:full":"2616 Chapparal Rd West Union OH 45693",
    "addr:housenumber":"2616",
    "addr:postcode":"45693",
    "addr:street":"Chapparal Rd",
    "iso:country":"US",
    "sg:address":"2616 Chapparal Rd",
    "sg:city":"West Union",
    "sg:classifiers":[
        {
            "category":"Building & Trades",
            "subcategory":"Construction",
            "type":"Services"
        }
    ],
    "sg:phone":"+1 937 544 2468",
    "sg:postcode":"45693",
    "sg:province":"OH",
    "sg:tags":[
        "house"
    ],
    "wof:name":"Oscar W Hoskins",
    "wof:placetype":"venue"
},
  "geometry": {"coordinates":[-83.5711,38.8377],"type":"Point"}
}