{
  "type": "Feature",
  "properties": {
    "iso:country":"US",
    "sg:address":"1009 Refugee Rd",
    "sg:city":"Pickerington",
    "sg:classifiers":[
        {
            "category":"Retail",
            "subcategory":"Car Wash",
            "type":"Services"
        }
    ],
    "sg:phone":"+1 614 577 0005",
    "sg:postcode":"43147",
    "sg:province":"OH",
    "sg:tags":[
        "polishing",
        "washing"
    ],
    "wof:name":"Clean Cat's Car Wash",
    "wof:placetype":"venue"
},
  "geometry": {"coordinates":[-82.78318899999999,39.91019],"type":"Point"}
}