{
  "type": "Feature",
  "properties": {
    "addr:full": "1009 Refugee Rd Pickerington OH 43147",
    "addr:housenumber": "1009",
    "addr:postcode": "43147",
    "addr:street": "Refugee Rd",
    "iso:country": "US",
    "sg:address": "1009 Refugee Rd",
    "sg:city": "Pickerington",
    "sg:classifiers": [
      {
        "category": "Retail",
        "subcategory": "Car Wash",
        "type": "Services"
      }
    ],
    "sg:phone": "+1 614 577 0005",
    "sg:postcode": "43147",
    "sg:province": "OH",
    "sg:tags": [
      "polishing",
      "washing"
    ],
    "wof:name": "Clean Cat's Car Wash",
    "wof:placetype": "venue"
  },
  "geometry": {"coordinates":[-82.783189,39.91019],"type":"Point"}
}
