{
  "type": "Feature",
  "properties": {
    "addr:full": "53 S Main St London OH 43140",
    "addr:housenumber": "53",
    "addr:postcode": "43140",
    "addr:street": "S Main St",
    "iso:country": "US",
    "sg:address": "53 S Main St",
    "sg:city": "London",
    "sg:classifiers": [
      {
        "category": "Real Estate",
        "subcategory": "Real Estate Agent",
        "type": "Services"
      }
    ],
    "sg:phone": "+1 740 852 0330",
    "sg:postcode": "43140",
    "sg:province": "OH",
    "sg:website": "www.wallsandbennett.com",
    "wof:name": "Walls \u0026 Bennett Realty Inc",
    "wof:placetype": "venue"
  },
  "geometry": {"coordinates":[-83.447536,39.885289],"type":"Point"}
}
