{
  "type": "Feature",
  "properties": {
    "addr:full": "135 W Main St Mc Comb OH 45858",
    "addr:housenumber": "135",
    "addr:postcode": "45858",
    "addr:street": "W Main St Mc Comb",
    "iso:country": "US",
    "sg:address": "135 W Main St",
    "sg:city": "Mc Comb",
    "sg:classifiers": [
      {
        "category": "Government",
        "subcategory": "Office",
        "type": "Public Place"
      }
    ],
    "sg:phone": "+1 419 293 2143",
    "sg:postcode": "45858",
    "sg:province": "OH",
    "sg:tags": [
      "govt",
      "city"
    ],
    "wof:name": "Mc Comb Water \u0026 Sewer Dept",
    "wof:placetype": "venue"
  },
  "geometry": {"coordinates":[-83.791787,41.107466],"type":"Point"}
}
