{
  "type": "Feature",
  "properties": {
    "iso:country":"US",
    "sg:address":"135 W Main St",
    "sg:city":"Mc Comb",
    "sg:classifiers":[
        {
            "category":"Government",
            "subcategory":"Office",
            "type":"Public Place"
        }
    ],
    "sg:phone":"+1 419 293 2143",
    "sg:postcode":"45858",
    "sg:province":"OH",
    "sg:tags":[
        "govt",
        "city"
    ],
    "wof:name":"Mc Comb Water & Sewer Dept",
    "wof:placetype":"venue"
},
  "geometry": {"coordinates":[-83.791787,41.107466],"type":"Point"}
}