{
  "type": "Feature",
  "properties": {
    "addr:full":"45 N Linwood Ave Norwalk OH 44857",
    "addr:housenumber":"45",
    "addr:postcode":"44857",
    "addr:street":"N Linwood Ave",
    "iso:country":"US",
    "sg:address":"45 N Linwood Ave",
    "sg:city":"Norwalk",
    "sg:classifiers":[
        {
            "category":"Government",
            "subcategory":"Court House",
            "type":"Public Place"
        }
    ],
    "sg:phone":"+1 419 663 6750",
    "sg:postcode":"44857",
    "sg:province":"OH",
    "wof:name":"Norwalk Municipal Court",
    "wof:placetype":"venue"
},
  "geometry": {"coordinates":[-82.61601400000001,41.244358],"type":"Point"}
}