{
  "type": "Feature",
  "properties": {
    "iso:country":"US",
    "sg:address":"7917 Euclid Ave",
    "sg:city":"Cleveland",
    "sg:classifiers":[
        {
            "category":"Restaurant",
            "type":"Food & Drink"
        }
    ],
    "sg:menulink":"http://www.allmenus.com/oh/cleveland/134824-subway/menu/",
    "sg:phone":"+1 216 721 8080",
    "sg:postcode":"44103",
    "sg:province":"OH",
    "sg:tags":[
        "american",
        "sandwich"
    ],
    "wof:name":"Subway",
    "wof:placetype":"venue"
},
  "geometry": {"coordinates":[-81.633402,41.503819],"type":"Point"}
}