{
  "type": "Feature",
  "properties": {
    "addr:full":"4235 Neely Rd Elida OH 45807",
    "addr:housenumber":"4235",
    "addr:postcode":"45807",
    "addr:street":"Neely Rd",
    "iso:country":"US",
    "sg:address":"4235 Neely Rd",
    "sg:city":"Elida",
    "sg:classifiers":[
        {
            "category":"Building & Trades",
            "subcategory":"Plumbing",
            "type":"Services"
        }
    ],
    "sg:phone":"+1 419 339 8320",
    "sg:postcode":"45807",
    "sg:province":"OH",
    "sg:tags":[
        "plumbing",
        "contractor"
    ],
    "wof:name":"Kantosky Plumbing Inc",
    "wof:placetype":"venue"
},
  "geometry": {"coordinates":[-84.177668,40.765666],"type":"Point"}
}