{
  "type": "Feature",
  "properties": {
    "iso:country":"US",
    "sg:address":"16004 Detroit Ave",
    "sg:city":"Cleveland",
    "sg:classifiers":[
        {
            "category":"Professional",
            "subcategory":"Management & Consulting",
            "type":"Services"
        }
    ],
    "sg:phone":"+1 216 521 1712",
    "sg:postcode":"44107",
    "sg:province":"OH",
    "sg:tags":[
        "consultant",
        "educational"
    ],
    "sg:website":"www.pesg.com",
    "wof:name":"Professional Ed Strategies",
    "wof:placetype":"venue"
},
  "geometry": {"coordinates":[-81.809146,41.485258],"type":"Point"}
}