{
  "type": "Feature",
  "properties": {
    "addr:full": "16004 Detroit Ave Cleveland OH 44107",
    "addr:housenumber": "16004",
    "addr:postcode": "44107",
    "addr:street": "Detroit Ave",
    "iso:country": "US",
    "sg:address": "16004 Detroit Ave",
    "sg:city": "Cleveland",
    "sg:classifiers": [
      {
        "category": "Professional",
        "subcategory": "Management \u0026 Consulting",
        "type": "Services"
      }
    ],
    "sg:phone": "+1 216 521 1712",
    "sg:postcode": "44107",
    "sg:province": "OH",
    "sg:tags": [
      "consultant",
      "educational"
    ],
    "sg:website": "www.pesg.com",
    "wof:name": "Professional Ed Strategies",
    "wof:placetype": "venue"
  },
  "geometry": {"coordinates":[-81.809146,41.485258],"type":"Point"}
}
