{
  "type": "Feature",
  "properties": {
    "addr:full": "4342 Hughes Rd Prospect OH 43342",
    "addr:housenumber": "4342",
    "addr:postcode": "43342",
    "addr:street": "Hughes Rd",
    "iso:country": "US",
    "sg:address": "4342 Hughes Rd",
    "sg:city": "Prospect",
    "sg:classifiers": [
      {
        "category": "Real Estate",
        "subcategory": "Real Estate Operator",
        "type": "Services"
      }
    ],
    "sg:phone": "+1 740 389 3403",
    "sg:postcode": "43342",
    "sg:province": "OH",
    "sg:tags": [
      "property",
      "lessor"
    ],
    "wof:name": "Hoch Giles",
    "wof:placetype": "venue"
  },
  "geometry": {"coordinates":[-83.175475,40.502144],"type":"Point"}
}
