{
  "type": "Feature",
  "properties": {
    "addr:full": "530 Euclid Ave Cleveland OH 44114",
    "addr:housenumber": "530",
    "addr:postcode": "44114",
    "addr:street": "Euclid Ave",
    "iso:country": "US",
    "sg:address": "530 Euclid Ave",
    "sg:city": "Cleveland",
    "sg:classifiers": [
      {
        "category": "Shopping",
        "type": "Retail Goods"
      }
    ],
    "sg:phone": "+1 216 241 0419",
    "sg:postcode": "44114",
    "sg:province": "OH",
    "sg:tags": [
      "art",
      "gallery",
      "dealer"
    ],
    "wof:name": "Frame Design Gallery",
    "wof:placetype": "venue"
  },
  "geometry": {"coordinates":[-81.687409,41.500067],"type":"Point"}
}
