{
  "type": "Feature",
  "properties": {
    "iso:country":"US",
    "sg:address":"8585 Kirtland Chardon Rd",
    "sg:city":"Willoughby",
    "sg:classifiers":[
        {
            "category":"Shopping",
            "subcategory":"Gifts & Souvenirs",
            "type":"Retail Goods"
        }
    ],
    "sg:phone":"+1 440 256 4822",
    "sg:postcode":"44094",
    "sg:province":"OH",
    "sg:tags":[
        "cards",
        "greeting"
    ],
    "wof:name":"Terri's Greeting Cards",
    "wof:placetype":"venue"
},
  "geometry": {"coordinates":[-81.333513,41.614225],"type":"Point"}
}