{
  "type": "Feature",
  "properties": {
    "iso:country":"US",
    "sg:address":"739 Old Pond Ln",
    "sg:city":"Powell",
    "sg:classifiers":[
        {
            "category":"Professional",
            "subcategory":"Computer Services",
            "type":"Services"
        }
    ],
    "sg:phone":"+1 614 888 2414",
    "sg:postcode":"43065",
    "sg:province":"OH",
    "sg:tags":[
        "consultant",
        "designer"
    ],
    "wof:name":"URS Technologies",
    "wof:placetype":"venue"
},
  "geometry": {"coordinates":[-83.056375,40.156097],"type":"Point"}
}