{
  "type": "Feature",
  "properties": {
    "addr:full": "33 N 3rd St Columbus OH 43215",
    "addr:housenumber": "33",
    "addr:postcode": "43215",
    "addr:street": "N 3Rd St",
    "iso:country": "US",
    "sg:address": "33 N 3rd St",
    "sg:city": "Columbus",
    "sg:classifiers": [
      {
        "category": "Professional",
        "subcategory": "Management \u0026 Consulting",
        "type": "Services"
      }
    ],
    "sg:phone": "+1 614 221 7157",
    "sg:postcode": "43215",
    "sg:province": "OH",
    "sg:tags": [
      "lobbyist"
    ],
    "wof:name": "Towner Policy Group",
    "wof:placetype": "venue"
  },
  "geometry": {"coordinates":[-82.998301,39.963767],"type":"Point"}
}
