{
  "type": "Feature",
  "properties": {
    "addr:full":"10950 Lorain Ave Cleveland OH 44111",
    "addr:housenumber":"10950",
    "addr:postcode":"44111",
    "addr:street":"Lorain Ave",
    "iso:country":"US",
    "sg:address":"10950 Lorain Ave",
    "sg:city":"Cleveland",
    "sg:classifiers":[
        {
            "category":"Food & Beverages",
            "subcategory":"Groceries & Convenience Stores",
            "type":"Retail Goods"
        }
    ],
    "sg:phone":"+1 216 251 5718",
    "sg:postcode":"44111",
    "sg:province":"OH",
    "sg:tags":[
        "grocer"
    ],
    "wof:name":"Tops Friendly Market",
    "wof:placetype":"venue"
},
  "geometry": {"coordinates":[-81.76066,41.464853],"type":"Point"}
}