{
  "type": "Feature",
  "properties": {
    "addr:full": "6711 N Ridge Rd Madison OH 44057",
    "addr:housenumber": "6711",
    "addr:postcode": "44057",
    "addr:street": "N Ridge Rd",
    "iso:country": "US",
    "sg:address": "6711 N Ridge Rd",
    "sg:city": "Madison",
    "sg:classifiers": [
      {
        "category": "Retail",
        "subcategory": "Repair Shop",
        "type": "Services"
      }
    ],
    "sg:phone": "+1 440 428 4574",
    "sg:postcode": "44057",
    "sg:province": "OH",
    "sg:tags": [
      "repairing",
      "piano",
      "refinishing"
    ],
    "wof:name": "Ayers New Music",
    "wof:placetype": "venue"
  },
  "geometry": {"coordinates":[-81.046931,41.802029],"type":"Point"}
}
