{
  "type": "Feature",
  "properties": {
    "iso:country":"US",
    "sg:address":"6 E Shenango St",
    "sg:city":"Sharpsville",
    "sg:classifiers":[
        {
            "category":"Health Services",
            "subcategory":"Doctor",
            "type":"Services"
        }
    ],
    "sg:phone":"+1   ",
    "sg:postcode":"16150",
    "sg:province":"OH",
    "sg:tags":[
        "medical"
    ],
    "wof:name":"Listopad Cunningham & Assoc",
    "wof:placetype":"venue"
},
  "geometry": {"coordinates":[-80.474349,41.266032],"type":"Point"}
}