{
  "type": "Feature",
  "properties": {
    "addr:full": "6 E Shenango St Sharpsville OH 16150",
    "addr:housenumber": "6",
    "addr:postcode": "16150",
    "addr:street": "E Shenango St",
    "iso:country": "US",
    "sg:address": "6 E Shenango St",
    "sg:city": "Sharpsville",
    "sg:classifiers": [
      {
        "category": "Health Services",
        "subcategory": "Doctor",
        "type": "Services"
      }
    ],
    "sg:phone": "+1   ",
    "sg:postcode": "16150",
    "sg:province": "OH",
    "sg:tags": [
      "medical"
    ],
    "wof:name": "Listopad Cunningham \u0026 Assoc",
    "wof:placetype": "venue"
  },
  "geometry": {"coordinates":[-80.474349,41.266032],"type":"Point"}
}
