{
  "type": "Feature",
  "properties": {
    "addr:full": "3741 Port Union Rd Fairfield OH 45014",
    "addr:housenumber": "3741",
    "addr:postcode": "45014",
    "addr:street": "Port Union Rd",
    "iso:country": "US",
    "sg:address": "3741 Port Union Rd",
    "sg:city": "Fairfield",
    "sg:classifiers": [
      {
        "category": "Manufacturing",
        "subcategory": "Printing",
        "type": "Manufacturing \u0026 Wholesale Goods"
      }
    ],
    "sg:phone": "+1 513 874 5325",
    "sg:postcode": "45014",
    "sg:province": "OH",
    "sg:tags": [
      "print",
      "lithographic",
      "commercial",
      "mfg"
    ],
    "sg:website": "www.htpco.com",
    "wof:name": "Hi-Tech Printing Co",
    "wof:placetype": "venue"
  },
  "geometry": {"coordinates":[-84.502179,39.3358],"type":"Point"}
}
