{
  "type": "Feature",
  "properties": {
    "addr:full":"115 Clubhouse Ln Lebanon OH 45036",
    "addr:housenumber":"115",
    "addr:postcode":"45036",
    "addr:street":"Clubhouse Ln",
    "iso:country":"US",
    "sg:address":"115 Clubhouse Ln",
    "sg:city":"Lebanon",
    "sg:classifiers":[
        {
            "category":"Wholesale",
            "subcategory":"Stationery",
            "type":"Manufacturing & Wholesale Goods"
        }
    ],
    "sg:phone":"+1 513 934 0233",
    "sg:postcode":"45036",
    "sg:province":"OH",
    "sg:tags":[
        "product",
        "paper"
    ],
    "sg:website":"www.unisourcelink.com",
    "wof:name":"Unisource",
    "wof:placetype":"venue"
},
  "geometry": {"coordinates":[-84.230428,39.435842],"type":"Point"}
}