{
  "type": "Feature",
  "properties": {
    "addr:full": "6449 Wilson Mills Rd Cleveland OH 44143",
    "addr:housenumber": "6449",
    "addr:postcode": "44143",
    "addr:street": "Wilson Mills Rd",
    "iso:country": "US",
    "sg:address": "6449 Wilson Mills Rd",
    "sg:city": "Cleveland",
    "sg:classifiers": [
      {
        "category": "Education",
        "subcategory": "Special Training",
        "type": "Public Place"
      }
    ],
    "sg:phone": "+1 440 461 9450",
    "sg:postcode": "44143",
    "sg:province": "OH",
    "sg:tags": [
      "tutoring"
    ],
    "sg:website": "www.learningrx.com",
    "wof:name": "Learning Rx",
    "wof:placetype": "venue"
  },
  "geometry": {"coordinates":[-81.445719,41.539003],"type":"Point"}
}
