{
  "type": "Feature",
  "properties": {
    "iso:country":"US",
    "sg:address":"2244 Harbor Ave",
    "sg:city":"Ashtabula",
    "sg:classifiers":[
        {
            "category":"Organizations",
            "subcategory":"Religious Organization",
            "type":"Services"
        }
    ],
    "sg:phone":"+1 440 997 3410",
    "sg:postcode":"44004",
    "sg:province":"OH",
    "sg:tags":[
        "church"
    ],
    "wof:name":"Ashtabula Church Of God",
    "wof:placetype":"venue"
},
  "geometry": {"coordinates":[-80.791439,41.885555],"type":"Point"}
}