{
  "type": "Feature",
  "properties": {
    "iso:country":"US",
    "sg:address":"12560 Middleton Pike",
    "sg:city":"Bowling Green",
    "sg:classifiers":[
        {
            "category":"Government",
            "subcategory":"Office",
            "type":"Public Place"
        }
    ],
    "sg:phone":"+1 419 352 4805",
    "sg:postcode":"43402",
    "sg:province":"OH",
    "sg:tags":[
        "county",
        "govt"
    ],
    "wof:name":"Wood County Water & Sewer",
    "wof:placetype":"venue"
},
  "geometry": {"coordinates":[-83.640237,41.458354],"type":"Point"}
}