{
  "type": "Feature",
  "properties": {
    "addr:full": "3301 Colerain Ave Cincinnati OH 45225",
    "addr:housenumber": "3301",
    "addr:postcode": "45225",
    "addr:street": "Colerain Ave",
    "iso:country": "US",
    "sg:address": "3301 Colerain Ave",
    "sg:city": "Cincinnati",
    "sg:classifiers": [
      {
        "category": "Shopping",
        "subcategory": "Discount \u0026 Variety Stores",
        "type": "Retail Goods"
      }
    ],
    "sg:phone": "+1 513 681 8677",
    "sg:postcode": "45225",
    "sg:province": "OH",
    "sg:tags": [
      "merchandise",
      "general"
    ],
    "wof:name": "Brower Products Inc Bldr Shwrm",
    "wof:placetype": "venue"
  },
  "geometry": {"coordinates":[-84.538388,39.144604],"type":"Point"}
}
