{
  "type": "Feature",
  "properties": {
    "addr:full": "4726 Security Dr Springfield OH 45503",
    "addr:housenumber": "4726",
    "addr:postcode": "45503",
    "addr:street": "Security Dr",
    "iso:country": "US",
    "sg:address": "4726 Security Dr",
    "sg:city": "Springfield",
    "sg:classifiers": [
      {
        "category": "Building \u0026 Trades",
        "subcategory": "Construction",
        "type": "Services"
      }
    ],
    "sg:phone": "+1 937 399 8123",
    "sg:postcode": "45503",
    "sg:province": "OH",
    "sg:tags": [
      "home",
      "builder"
    ],
    "wof:name": "Robert C Henry Homes",
    "wof:placetype": "venue"
  },
  "geometry": {"coordinates":[-83.775626,39.991842],"type":"Point"}
}
