{
  "type": "Feature",
  "properties": {
    "addr:full": "129 E Elm St Wauseon OH 43567",
    "addr:housenumber": "129",
    "addr:postcode": "43567",
    "addr:street": "E Elm St",
    "iso:country": "US",
    "sg:address": "129 E Elm St",
    "sg:city": "Wauseon",
    "sg:classifiers": [
      {
        "category": "Organizations",
        "subcategory": "Religious Organization",
        "type": "Services"
      }
    ],
    "sg:phone": "+1 419 335 4557",
    "sg:postcode": "43567",
    "sg:province": "OH",
    "sg:tags": [
      "church"
    ],
    "wof:name": "First Christian Church",
    "wof:placetype": "venue"
  },
  "geometry": {"coordinates":[-84.1385,41.549723],"type":"Point"}
}
