{
  "type": "Feature",
  "properties": {
    "addr:full":"18739 Sheldon Rd Cleveland OH 44130",
    "addr:housenumber":"18739",
    "addr:postcode":"44130",
    "addr:street":"Sheldon Rd",
    "iso:country":"US",
    "sg:address":"18739 Sheldon Rd",
    "sg:city":"Cleveland",
    "sg:classifiers":[
        {
            "category":"Wholesale",
            "subcategory":"Groceries",
            "type":"Manufacturing & Wholesale Goods"
        }
    ],
    "sg:phone":"+1 216 676 6414",
    "sg:postcode":"44130",
    "sg:province":"OH",
    "wof:name":"Magnetic Springs Water Company",
    "wof:placetype":"venue"
},
  "geometry": {"coordinates":[-81.832098,41.388968],"type":"Point"}
}