{
  "type": "Feature",
  "properties": {
    "addr:full": "4407 Broadway Grove City OH 43123",
    "addr:housenumber": "4407",
    "addr:postcode": "43123",
    "addr:street": "Broadway",
    "iso:country": "US",
    "sg:address": "4407 Broadway",
    "sg:city": "Grove City",
    "sg:classifiers": [
      {
        "category": "Retail",
        "subcategory": "Auto Rental",
        "type": "Services"
      }
    ],
    "sg:phone": "+1 614 539 1440",
    "sg:postcode": "43123",
    "sg:province": "OH",
    "sg:tags": [
      "automobile",
      "leasing"
    ],
    "wof:name": "National Auto Lease Inc",
    "wof:placetype": "venue"
  },
  "geometry": {"coordinates":[-83.100169,39.874684],"type":"Point"}
}
