{
  "type": "Feature",
  "properties": {
    "iso:country":"US",
    "sg:address":"1710 Commerce Dr",
    "sg:city":"Piqua",
    "sg:classifiers":[
        {
            "category":"Manufacturing",
            "subcategory":"Paper Products",
            "type":"Manufacturing & Wholesale Goods"
        }
    ],
    "sg:phone":"+1 937 773 8933",
    "sg:postcode":"45356",
    "sg:province":"OH",
    "sg:tags":[
        "mill"
    ],
    "wof:name":"Kimberly-Clark",
    "wof:placetype":"venue"
},
  "geometry": {"coordinates":[-84.26908299999999,40.145081],"type":"Point"}
}