{
  "type": "Feature",
  "properties": {
    "iso:country":"US",
    "sg:address":"4050 Sintz Rd",
    "sg:city":"Springfield",
    "sg:classifiers":[
        {
            "category":"Building & Trades",
            "subcategory":"Landscaping Services",
            "type":"Services"
        }
    ],
    "sg:phone":"+1 937 390 9176",
    "sg:postcode":"45504",
    "sg:province":"OH",
    "sg:tags":[
        "lawn",
        "maintenance",
        "grounds"
    ],
    "wof:name":"B W 's Lawn Maintenance",
    "wof:placetype":"venue"
},
  "geometry": {"coordinates":[-83.892864,39.941228],"type":"Point"}
}