{
  "type": "Feature",
  "properties": {
    "iso:country":"US",
    "sg:address":"13604 Euclid Ave",
    "sg:city":"Cleveland",
    "sg:classifiers":[
        {
            "category":"Professional",
            "subcategory":"Accounting & Tax Preparation",
            "type":"Services"
        }
    ],
    "sg:phone":"+1 216 681 0301",
    "sg:postcode":"44112",
    "sg:province":"OH",
    "sg:tags":[
        "return",
        "filing"
    ],
    "wof:name":"Instant Tax Svc",
    "wof:placetype":"venue"
},
  "geometry": {"coordinates":[-81.588801,41.523392],"type":"Point"}
}