{
  "type": "Feature",
  "properties": {
    "addr:full": "407 Vine St Clyde OH 43410",
    "addr:housenumber": "407",
    "addr:postcode": "43410",
    "addr:street": "Vine St",
    "iso:country": "US",
    "sg:address": "407 Vine St",
    "sg:city": "Clyde",
    "sg:classifiers": [
      {
        "category": "Shopping",
        "subcategory": "Clothing, Apparel, \u0026 Fashions",
        "type": "Retail Goods"
      }
    ],
    "sg:phone": "+1 419 547 4898",
    "sg:postcode": "43410",
    "sg:province": "OH",
    "wof:name": "Fairy Tale Weddings \u0026 Bridal",
    "wof:placetype": "venue"
  },
  "geometry": {"coordinates":[-82.981456,41.304278],"type":"Point"}
}
