{
  "type": "Feature",
  "properties": {
    "addr:full":"3608 Roosevelt Blvd Middletown OH 45044",
    "addr:housenumber":"3608",
    "addr:postcode":"45044",
    "addr:street":"Roosevelt Blvd",
    "iso:country":"US",
    "sg:address":"3608 Roosevelt Blvd",
    "sg:city":"Middletown",
    "sg:classifiers":[
        {
            "category":"Building & Trades",
            "subcategory":"Construction",
            "type":"Services"
        }
    ],
    "sg:phone":"+1 513 425 9358",
    "sg:postcode":"45044",
    "sg:province":"OH",
    "sg:tags":[
        "painter"
    ],
    "wof:name":"No-Drip Painting",
    "wof:placetype":"venue"
},
  "geometry": {"coordinates":[-84.364993,39.499696],"type":"Point"}
}