{
  "type": "Feature",
  "properties": {
    "addr:full":"7700 Market St Youngstown OH 44512",
    "addr:housenumber":"7700",
    "addr:postcode":"44512",
    "addr:street":"Market St",
    "iso:country":"US",
    "sg:address":"7700 Market St",
    "sg:city":"Youngstown",
    "sg:classifiers":[
        {
            "category":"Shopping",
            "subcategory":"Hobbies, Toys, & Games",
            "type":"Retail Goods"
        },
        {
            "category":"Home & Garden",
            "subcategory":"Garden Supply",
            "type":"Retail Goods"
        }
    ],
    "sg:phone":"+1 330 758 2114",
    "sg:postcode":"44512",
    "sg:province":"OH",
    "sg:tags":[
        "equipment",
        "lawn"
    ],
    "sg:website":"www.agnewlawnandgarden.com",
    "wof:name":"Agnew Farm Equipment Inc",
    "wof:placetype":"venue"
},
  "geometry": {"coordinates":[-80.662818,41.012727],"type":"Point"}
}