{
  "type": "Feature",
  "properties": {
    "iso:country":"US",
    "sg:address":"1300 Brimfield Dr",
    "sg:city":"Kent",
    "sg:classifiers":[
        {
            "category":"Utilities",
            "subcategory":"Cable",
            "type":"Services"
        }
    ],
    "sg:phone":"+1 330 474 0748",
    "sg:postcode":"44240",
    "sg:province":"OH",
    "sg:tags":[
        "television"
    ],
    "wof:name":"Signal 1 Satellite",
    "wof:placetype":"venue"
},
  "geometry": {"coordinates":[-81.346336,41.114154],"type":"Point"}
}