{
  "type": "Feature",
  "properties": {
    "addr:full":"4382 Roundtree Dr Dayton OH 45432",
    "addr:housenumber":"4382",
    "addr:postcode":"45432",
    "addr:street":"Roundtree Dr",
    "iso:country":"US",
    "sg:address":"4382 Roundtree Dr",
    "sg:city":"Dayton",
    "sg:classifiers":[
        {
            "category":"Building & Trades",
            "subcategory":"Plumbing",
            "type":"Services"
        }
    ],
    "sg:phone":"+1 937 427 1124",
    "sg:postcode":"45432",
    "sg:province":"OH",
    "sg:tags":[
        "air",
        "heating",
        "contractor",
        "system",
        "conditioning"
    ],
    "wof:name":"Frantz Mechanical",
    "wof:placetype":"venue"
},
  "geometry": {"coordinates":[-84.095815,39.745669],"type":"Point"}
}