{
  "type": "Feature",
  "properties": {
    "iso:country":"US",
    "sg:address":"26175 Raintree Blvd",
    "sg:city":"Cleveland",
    "sg:classifiers":[
        {
            "category":"Education",
            "subcategory":"Dance Studio",
            "type":"Public Place"
        }
    ],
    "sg:phone":"+1 440 235 9350",
    "sg:postcode":"44138",
    "sg:province":"OH",
    "sg:tags":[
        "instruction",
        "dancing"
    ],
    "wof:name":"Dance Concept",
    "wof:placetype":"venue"
},
  "geometry": {"coordinates":[-81.912741,41.352092],"type":"Point"}
}