{
  "type": "Feature",
  "properties": {
    "addr:full":"1101 12th St NE Canton OH 44703",
    "addr:housenumber":"1101",
    "addr:postcode":"44703",
    "addr:street":"12Th St Ne",
    "iso:country":"US",
    "sg:address":"1101 12th St NE",
    "sg:city":"Canton",
    "sg:classifiers":[
        {
            "category":"Restaurant",
            "type":"Food & Drink"
        }
    ],
    "sg:phone":"+1 330 454 6343",
    "sg:postcode":"44703",
    "sg:province":"OH",
    "sg:tags":[
        "tavern"
    ],
    "wof:name":"Sparta Steak House & Lounge",
    "wof:placetype":"venue"
},
  "geometry": {"coordinates":[-81.382531,40.809473],"type":"Point"}
}