{
  "type": "Feature",
  "properties": {
    "addr:full": "8523 Ridge Rd Cleveland OH 44133",
    "addr:housenumber": "8523",
    "addr:postcode": "44133",
    "addr:street": "Ridge Rd",
    "iso:country": "US",
    "sg:address": "8523 Ridge Rd",
    "sg:city": "Cleveland",
    "sg:classifiers": [
      {
        "category": "Health Services",
        "subcategory": "Doctor",
        "type": "Services"
      }
    ],
    "sg:phone": "+1 440 237 7730",
    "sg:postcode": "44133",
    "sg:province": "OH",
    "sg:tags": [
      "dentist"
    ],
    "wof:name": "Manbir Pannu DDS",
    "wof:placetype": "venue"
  },
  "geometry": {"coordinates":[-81.735849,41.349798],"type":"Point"}
}
