{
  "type": "Feature",
  "properties": {
    "addr:full":"8057 Taylorsville Rd Dayton OH 45424",
    "addr:housenumber":"8057",
    "addr:postcode":"45424",
    "addr:street":"Taylorsville Rd",
    "iso:country":"US",
    "sg:address":"8057 Taylorsville Rd",
    "sg:city":"Dayton",
    "sg:classifiers":[
        {
            "category":"Freight",
            "type":"Transportation"
        }
    ],
    "sg:phone":"+1 937 890 8612",
    "sg:postcode":"45424",
    "sg:province":"OH",
    "sg:tags":[
        "operator",
        "local",
        "trucking"
    ],
    "wof:name":"Partin Trucking Co",
    "wof:placetype":"venue"
},
  "geometry": {"coordinates":[-84.099951,39.860705],"type":"Point"}
}