{
  "type": "Feature",
  "properties": {
    "iso:country":"US",
    "sg:address":"7300 Whipple Ave NW",
    "sg:city":"North Canton",
    "sg:classifiers":[
        {
            "category":"Professional",
            "subcategory":"Employment Agencies",
            "type":"Services"
        }
    ],
    "sg:phone":"+1 330 497 0122",
    "sg:postcode":"44720",
    "sg:province":"OH",
    "sg:tags":[
        "opportunity"
    ],
    "wof:name":"Management Recruiters",
    "wof:placetype":"venue"
},
  "geometry": {"coordinates":[-81.42390899999999,40.888387],"type":"Point"}
}