{
  "type": "Feature",
  "properties": {
    "addr:full": "7300 Whipple Ave NW North Canton OH 44720",
    "addr:housenumber": "7300",
    "addr:postcode": "44720",
    "addr:street": "Whipple Ave Nw",
    "iso:country": "US",
    "sg:address": "7300 Whipple Ave NW",
    "sg:city": "North Canton",
    "sg:classifiers": [
      {
        "category": "Professional",
        "subcategory": "Employment Agencies",
        "type": "Services"
      }
    ],
    "sg:phone": "+1 330 497 0122",
    "sg:postcode": "44720",
    "sg:province": "OH",
    "sg:tags": [
      "opportunity"
    ],
    "wof:name": "Management Recruiters",
    "wof:placetype": "venue"
  },
  "geometry": {"coordinates":[-81.423909,40.888387],"type":"Point"}
}
