{
  "type": "Feature",
  "properties": {
    "addr:full": "14807 Elm Ave Cleveland OH 44112",
    "addr:housenumber": "14807",
    "addr:postcode": "44112",
    "addr:street": "Elm Ave",
    "iso:country": "US",
    "sg:address": "14807 Elm Ave",
    "sg:city": "Cleveland",
    "sg:classifiers": [
      {
        "category": "Professional",
        "subcategory": "Secretarial Services",
        "type": "Services"
      }
    ],
    "sg:phone": "+1 216 851 1760",
    "sg:postcode": "44112",
    "sg:province": "OH",
    "sg:tags": [
      "reporting",
      "court"
    ],
    "wof:name": "Divine Intervention",
    "wof:placetype": "venue"
  },
  "geometry": {"coordinates":[-81.576201,41.542281],"type":"Point"}
}
