{
  "type": "Feature",
  "properties": {
    "addr:full": "105 W 4th St Cincinnati OH 45202",
    "addr:housenumber": "105",
    "addr:postcode": "45202",
    "addr:street": "W 4Th St",
    "iso:country": "US",
    "sg:address": "105 W 4th St",
    "sg:city": "Cincinnati",
    "sg:classifiers": [
      {
        "category": "Organizations",
        "subcategory": "Professional Association",
        "type": "Services"
      }
    ],
    "sg:phone": "+1 513 361 2100",
    "sg:postcode": "45202",
    "sg:province": "OH",
    "wof:name": "Leukemia \u0026 Lymphoma Society",
    "wof:placetype": "venue"
  },
  "geometry": {"coordinates":[-84.515817,39.099397],"type":"Point"}
}
