{
  "type": "Feature",
  "properties": {
    "iso:country":"US",
    "sg:address":"1945 S Union Ave",
    "sg:city":"Alliance",
    "sg:classifiers":[
        {
            "category":"Shopping",
            "subcategory":"Department Store",
            "type":"Retail Goods"
        }
    ],
    "sg:phone":"+1 330 821 3164",
    "sg:postcode":"44601",
    "sg:province":"OH",
    "wof:name":"Family Dollar Store",
    "wof:placetype":"venue"
},
  "geometry": {"coordinates":[-81.10596700000001,40.902098],"type":"Point"}
}