{
  "type": "Feature",
  "properties": {
    "addr:full":"120 N Fayette St Washington Ct Hs OH 43160",
    "addr:housenumber":"120",
    "addr:postcode":"43160",
    "addr:street":"N Fayette St",
    "iso:country":"US",
    "sg:address":"120 N Fayette St",
    "sg:city":"Washington Ct Hs",
    "sg:classifiers":[
        {
            "category":"Education",
            "subcategory":"Dance Studio",
            "type":"Public Place"
        }
    ],
    "sg:phone":"+1 740 335 1022",
    "sg:postcode":"43160",
    "sg:province":"OH",
    "sg:tags":[
        "instruction",
        "dancing"
    ],
    "wof:name":"Terrie's Dance Spectrum",
    "wof:placetype":"venue"
},
  "geometry": {"coordinates":[-83.43951199999999,39.537322],"type":"Point"}
}