{
  "type": "Feature",
  "properties": {
    "iso:country":"US",
    "sg:address":"29 Bennington Dr",
    "sg:city":"Dayton",
    "sg:classifiers":[
        {
            "category":"Personal",
            "subcategory":"Beauty Salon",
            "type":"Services"
        }
    ],
    "sg:phone":"+1 937 279 0808",
    "sg:postcode":"45405",
    "sg:province":"OH",
    "wof:name":"Authentic Cuts",
    "wof:placetype":"venue"
},
  "geometry": {"coordinates":[-84.22469599999999,39.8042],"type":"Point"}
}