{
  "type": "Feature",
  "properties": {
    "iso:country":"US",
    "sg:address":"158 S Main St",
    "sg:city":"Woodsfield",
    "sg:classifiers":[
        {
            "category":"Social Services",
            "type":"Services"
        }
    ],
    "sg:phone":"+1 740 472 1312",
    "sg:postcode":"43793",
    "sg:province":"OH",
    "sg:tags":[
        "senior",
        "citizen"
    ],
    "wof:name":"Monroe County Senior Citizens",
    "wof:placetype":"venue"
},
  "geometry": {"coordinates":[-81.116367,39.761581],"type":"Point"}
}