{
  "type": "Feature",
  "properties": {
    "addr:full": "10806 Millington Ct Cincinnati OH 45242",
    "addr:housenumber": "10806",
    "addr:postcode": "45242",
    "addr:street": "Millington Ct",
    "iso:country": "US",
    "sg:address": "10806 Millington Ct",
    "sg:city": "Cincinnati",
    "sg:classifiers": [
      {
        "category": "Manufacturing",
        "subcategory": "Metals",
        "type": "Manufacturing \u0026 Wholesale Goods"
      }
    ],
    "sg:phone": "+1 513 793 7846",
    "sg:postcode": "45242",
    "sg:province": "OH",
    "sg:tags": [
      "machine",
      "screw",
      "product"
    ],
    "wof:name": "ABCO Bar \u0026 Tube-Cutting Svc",
    "wof:placetype": "venue"
  },
  "geometry": {"coordinates":[-84.362692,39.260711],"type":"Point"}
}
