{
  "type": "Feature",
  "properties": {
    "iso:country":"US",
    "sg:address":"10806 Millington Ct",
    "sg:city":"Cincinnati",
    "sg:classifiers":[
        {
            "category":"Manufacturing",
            "subcategory":"Metals",
            "type":"Manufacturing & Wholesale Goods"
        }
    ],
    "sg:phone":"+1 513 793 7846",
    "sg:postcode":"45242",
    "sg:province":"OH",
    "sg:tags":[
        "machine",
        "screw",
        "product"
    ],
    "wof:name":"ABCO Bar & Tube-Cutting Svc",
    "wof:placetype":"venue"
},
  "geometry": {"coordinates":[-84.362692,39.260711],"type":"Point"}
}