{
  "type": "Feature",
  "properties": {
    "addr:full": "1958 Neil Ave Columbus OH 43210",
    "addr:housenumber": "1958",
    "addr:postcode": "43210",
    "addr:street": "Neil Ave",
    "iso:country": "US",
    "sg:address": "1958 Neil Ave",
    "sg:city": "Columbus",
    "sg:classifiers": [
      {
        "category": "Education",
        "subcategory": "College",
        "type": "Public Place"
      }
    ],
    "sg:phone": "+1 614 292 2866",
    "sg:postcode": "43210",
    "sg:province": "OH",
    "sg:tags": [
      "academic",
      "school"
    ],
    "wof:name": "Ohio State Univ Statistics",
    "wof:placetype": "venue"
  },
  "geometry": {"coordinates":[-83.015415,40.001374],"type":"Point"}
}
