{
  "type": "Feature",
  "properties": {
    "addr:full":"28 W 4th St Cincinnati OH 45202",
    "addr:housenumber":"28",
    "addr:postcode":"45202",
    "addr:street":"W 4Th St",
    "iso:country":"US",
    "sg:address":"28 W 4th St",
    "sg:city":"Cincinnati",
    "sg:classifiers":[
        {
            "category":"Real Estate",
            "subcategory":"Real Estate Operator",
            "type":"Services"
        }
    ],
    "sg:phone":"+1 513 241 7700",
    "sg:postcode":"45202",
    "sg:province":"OH",
    "sg:tags":[
        "building",
        "commercial",
        "owns"
    ],
    "wof:name":"Tower Place Ltd Partnership",
    "wof:placetype":"venue"
},
  "geometry": {"coordinates":[-84.51396,39.099854],"type":"Point"}
}