{
  "type": "Feature",
  "properties": {
    "addr:full":"5416 N Summit St Toledo OH 43611",
    "addr:housenumber":"5416",
    "addr:postcode":"43611",
    "addr:street":"N Summit St",
    "iso:country":"US",
    "sg:address":"5416 N Summit St",
    "sg:city":"Toledo",
    "sg:classifiers":[
        {
            "category":"Organizations",
            "subcategory":"Community Association",
            "type":"Services"
        }
    ],
    "sg:phone":"+1 419 729 9282",
    "sg:postcode":"43611",
    "sg:province":"OH",
    "sg:tags":[
        "military"
    ],
    "sg:website":"www.vfw.org",
    "wof:name":"Veterans Of Foreign Wars",
    "wof:placetype":"venue"
},
  "geometry": {"coordinates":[-83.47920999999999,41.719061],"type":"Point"}
}