{
  "type": "Feature",
  "properties": {
    "addr:full": "10124 Bissell Dr Twinsburg OH 44087",
    "addr:housenumber": "10124",
    "addr:postcode": "44087",
    "addr:street": "Bissell Dr",
    "iso:country": "US",
    "sg:address": "10124 Bissell Dr",
    "sg:city": "Twinsburg",
    "sg:classifiers": [
      {
        "category": "Professional",
        "subcategory": "Management \u0026 Consulting",
        "type": "Services"
      }
    ],
    "sg:phone": "+1 330 963 0011",
    "sg:postcode": "44087",
    "sg:province": "OH",
    "sg:tags": [
      "consultant",
      "business"
    ],
    "wof:name": "Professionalism International",
    "wof:placetype": "venue"
  },
  "geometry": {"coordinates":[-81.421613,41.338867],"type":"Point"}
}
