{
  "type": "Feature",
  "properties": {
    "addr:full": "313 N 5th St Coshocton OH 43812",
    "addr:housenumber": "313",
    "addr:postcode": "43812",
    "addr:street": "N 5Th St",
    "iso:country": "US",
    "sg:address": "313 N 5th St",
    "sg:city": "Coshocton",
    "sg:classifiers": [
      {
        "category": "Manufacturing",
        "subcategory": "Printing",
        "type": "Manufacturing \u0026 Wholesale Goods"
      }
    ],
    "sg:phone": "+1 740 622 3000",
    "sg:postcode": "43812",
    "sg:province": "OH",
    "sg:tags": [
      "printer"
    ],
    "wof:name": "Speedy Print TCAS Inc",
    "wof:placetype": "venue"
  },
  "geometry": {"coordinates":[-81.863433,40.277379],"type":"Point"}
}
