{
  "type": "Feature",
  "properties": {
    "iso:country":"US",
    "sg:address":"3319 Nebraska Ave",
    "sg:city":"Toledo",
    "sg:classifiers":[
        {
            "category":"Education",
            "subcategory":"School",
            "type":"Public Place"
        }
    ],
    "sg:phone":"+1 419 534 2304",
    "sg:postcode":"43607",
    "sg:province":"OH",
    "wof:name":"Victory Academy Of Toledo",
    "wof:placetype":"venue"
},
  "geometry": {"coordinates":[-83.622693,41.645471],"type":"Point"}
}