{
  "type": "Feature",
  "properties": {
    "addr:full":"12531 Gar Hwy Chardon OH 44024",
    "addr:housenumber":"12531",
    "addr:postcode":"44024",
    "addr:street":"Gar Hwy",
    "iso:country":"US",
    "sg:address":"12531 Gar Hwy",
    "sg:city":"Chardon",
    "sg:classifiers":[
        {
            "category":"Autos & Motor Vehicles",
            "subcategory":"Automobile Sales",
            "type":"Retail Goods"
        }
    ],
    "sg:phone":"+1 440 285 7037",
    "sg:postcode":"44024",
    "sg:province":"OH",
    "sg:tags":[
        "car",
        "used",
        "dealer"
    ],
    "wof:name":"Working Man Motors Inc",
    "wof:placetype":"venue"
},
  "geometry": {"coordinates":[-81.171605,41.592864],"type":"Point"}
}