{
  "type": "Feature",
  "properties": {
    "iso:country":"US",
    "sg:address":"120 Center St",
    "sg:city":"Jewett",
    "sg:classifiers":[
        {
            "category":"Retail",
            "subcategory":"Auto Repair",
            "type":"Services"
        }
    ],
    "sg:phone":"+1 740 946 0104",
    "sg:postcode":"43986",
    "sg:province":"OH",
    "sg:tags":[
        "automobile",
        "restoration",
        "classic"
    ],
    "wof:name":"Jewett Classic Auto Repair",
    "wof:placetype":"venue"
},
  "geometry": {"coordinates":[-81.00358199999999,40.367222],"type":"Point"}
}