{
  "type": "Feature",
  "properties": {
    "addr:full":"11382 Pyle South Amherst Rd Oberlin OH 44074",
    "addr:housenumber":"11382",
    "addr:postcode":"44074",
    "addr:street":"Pyle South Amherst Rd",
    "iso:country":"US",
    "sg:address":"11382 Pyle South Amherst Rd",
    "sg:city":"Oberlin",
    "sg:phone":"+1 440 775 7947",
    "sg:postcode":"44074",
    "sg:province":"OH",
    "sg:tags":[
        "farm",
        "grain",
        "cash"
    ],
    "wof:name":"Abraham Farms",
    "wof:placetype":"venue"
},
  "geometry": {"coordinates":[-82.242722,41.323933],"type":"Point"}
}