{
  "type": "Feature",
  "properties": {
    "iso:country":"US",
    "sg:address":"2261 Cooper Foster Park Rd",
    "sg:city":"Amherst",
    "sg:classifiers":[
        {
            "category":"Insurance",
            "subcategory":"Insurance Agent",
            "type":"Services"
        }
    ],
    "sg:phone":"+1 440 282 6500",
    "sg:postcode":"44001",
    "sg:province":"OH",
    "wof:name":"Randy E Bevins/Jesse T Moralez",
    "wof:placetype":"venue"
},
  "geometry": {"coordinates":[-82.21587599999999,41.418255],"type":"Point"}
}