{
  "type": "Feature",
  "properties": {
    "iso:country":"US",
    "sg:address":"5900 W Liberty St",
    "sg:city":"Hubbard",
    "sg:classifiers":[
        {
            "category":"Organizations",
            "subcategory":"Religious Organization",
            "type":"Services"
        }
    ],
    "sg:phone":"+1 330 534 2820",
    "sg:postcode":"44425",
    "sg:province":"OH",
    "sg:tags":[
        "church"
    ],
    "wof:name":"First Assembly Of God-Hubbard",
    "wof:placetype":"venue"
},
  "geometry": {"coordinates":[-80.604286,41.157769],"type":"Point"}
}