{
  "type": "Feature",
  "properties": {
    "iso:country":"US",
    "sg:address":"9901 Regatta Dr",
    "sg:city":"Cincinnati",
    "sg:classifiers":[
        {
            "category":"Organizations",
            "subcategory":"Religious Organization",
            "type":"Services"
        }
    ],
    "sg:phone":"+1 513 851 6583",
    "sg:postcode":"45252",
    "sg:province":"OH",
    "sg:tags":[
        "clergy"
    ],
    "wof:name":"R B Craft",
    "wof:placetype":"venue"
},
  "geometry": {"coordinates":[-84.60925,39.254157],"type":"Point"}
}