{
  "type": "Feature",
  "properties": {
    "addr:full": "402 E Gates St Columbus OH 43206",
    "addr:housenumber": "402",
    "addr:postcode": "43206",
    "addr:street": "E Gates St",
    "iso:country": "US",
    "sg:address": "402 E Gates St",
    "sg:city": "Columbus",
    "sg:classifiers": [
      {
        "category": "Building \u0026 Trades",
        "subcategory": "Plumbing",
        "type": "Services"
      }
    ],
    "sg:phone": "+1 614 445 9435",
    "sg:postcode": "43206",
    "sg:province": "OH",
    "sg:tags": [
      "plumbing"
    ],
    "wof:name": "M \u0026 S Gas and Plumbing Repair",
    "wof:placetype": "venue"
  },
  "geometry": {"coordinates":[-82.983673,39.937305],"type":"Point"}
}
