{
  "type": "Feature",
  "properties": {
    "addr:full":"5555 Airport Hwy Toledo OH 43615",
    "addr:housenumber":"5555",
    "addr:postcode":"43615",
    "addr:street":"Airport Hwy",
    "iso:country":"US",
    "sg:address":"5555 Airport Hwy",
    "sg:city":"Toledo",
    "sg:classifiers":[
        {
            "category":"Professional",
            "subcategory":"Management & Consulting",
            "type":"Services"
        },
        {
            "category":"Insurance",
            "subcategory":"Insurance Agent",
            "type":"Services"
        }
    ],
    "sg:phone":"+1 419 244 6455",
    "sg:postcode":"43615",
    "sg:province":"OH",
    "wof:name":"Corvel",
    "wof:placetype":"venue"
},
  "geometry": {"coordinates":[-83.674156,41.615693],"type":"Point"}
}