{
  "type": "Feature",
  "properties": {
    "addr:full":"1555 N Cable Rd Lima OH 45805",
    "addr:housenumber":"1555",
    "addr:postcode":"45805",
    "addr:street":"N Cable Rd",
    "iso:country":"US",
    "sg:address":"1555 N Cable Rd",
    "sg:city":"Lima",
    "sg:classifiers":[
        {
            "category":"Shopping",
            "subcategory":"Shoes",
            "type":"Retail Goods"
        }
    ],
    "sg:phone":"+1 419 331 9959",
    "sg:postcode":"45805",
    "sg:province":"OH",
    "wof:name":"Naturalizer Shoes",
    "wof:placetype":"venue"
},
  "geometry": {"coordinates":[-84.147277,40.760893],"type":"Point"}
}