{
  "type": "Feature",
  "properties": {
    "addr:full":"5414 Keeley St Columbus OH 43235",
    "addr:housenumber":"5414",
    "addr:postcode":"43235",
    "addr:street":"Keeley St",
    "iso:country":"US",
    "sg:address":"5414 Keeley St",
    "sg:city":"Columbus",
    "sg:classifiers":[
        {
            "category":"Real Estate",
            "subcategory":"Real Estate Agent",
            "type":"Services"
        }
    ],
    "sg:phone":"+1 614 326 0989",
    "sg:postcode":"43235",
    "sg:province":"OH",
    "wof:name":"J L Hall Company Ltd",
    "wof:placetype":"venue"
},
  "geometry": {"coordinates":[-83.05797699999999,40.067435],"type":"Point"}
}