{
  "type": "Feature",
  "properties": {
    "addr:full":"323 Main St Coshocton OH 43812",
    "addr:housenumber":"323",
    "addr:postcode":"43812",
    "addr:street":"Main St",
    "iso:country":"US",
    "sg:address":"323 Main St",
    "sg:city":"Coshocton",
    "sg:classifiers":[
        {
            "category":"Home & Garden",
            "subcategory":"Building Materials",
            "type":"Retail Goods"
        }
    ],
    "sg:phone":"+1 740 622 3854",
    "sg:postcode":"43812",
    "sg:province":"OH",
    "sg:tags":[
        "paint",
        "floor",
        "covering"
    ],
    "wof:name":"Sherwin-Williams Paints",
    "wof:placetype":"venue"
},
  "geometry": {"coordinates":[-81.86633,40.273576],"type":"Point"}
}