{
  "type": "Feature",
  "properties": {
    "addr:full":"535 Highland Rd E Macedonia OH 44056",
    "addr:housenumber":"535",
    "addr:postcode":"44056",
    "addr:street":"Highland Rd E",
    "iso:country":"US",
    "sg:address":"535 Highland Rd E",
    "sg:city":"Macedonia",
    "sg:classifiers":[
        {
            "category":"Autos & Motor Vehicles",
            "subcategory":"Automobile Sales",
            "type":"Retail Goods"
        }
    ],
    "sg:phone":"+1 330 467 8207",
    "sg:postcode":"44056",
    "sg:province":"OH",
    "sg:tags":[
        "car",
        "dealer"
    ],
    "wof:name":"Adams",
    "wof:placetype":"venue"
},
  "geometry": {"coordinates":[-81.505331,41.299107],"type":"Point"}
}