{
  "type": "Feature",
  "properties": {
    "addr:full": "5388 Sextro Rd Minster OH 45865",
    "addr:housenumber": "5388",
    "addr:postcode": "45865",
    "addr:street": "Sextro Rd",
    "iso:country": "US",
    "sg:address": "5388 Sextro Rd",
    "sg:city": "Minster",
    "sg:classifiers": [
      {
        "category": "Shopping",
        "subcategory": "Gifts \u0026 Souvenirs",
        "type": "Retail Goods"
      }
    ],
    "sg:phone": "+1 419 628 2345",
    "sg:postcode": "45865",
    "sg:province": "OH",
    "wof:name": "Metzger Collectibles",
    "wof:placetype": "venue"
  },
  "geometry": {"coordinates":[-84.334653,40.415533],"type":"Point"}
}
