{
  "type": "Feature",
  "properties": {
    "iso:country":"US",
    "sg:address":"167 Parkwood Dr",
    "sg:city":"Berea",
    "sg:classifiers":[
        {
            "category":"Professional",
            "subcategory":"Management & Consulting",
            "type":"Services"
        }
    ],
    "sg:phone":"+1 440 234 3509",
    "sg:postcode":"44017",
    "sg:province":"OH",
    "wof:name":"Powerpoint Marketing",
    "wof:placetype":"venue"
},
  "geometry": {"coordinates":[-81.87297599999999,41.368805],"type":"Point"}
}