{
  "type": "Feature",
  "properties": {
    "addr:full": "2455 Maysville Pike Zanesville OH 43701",
    "addr:housenumber": "2455",
    "addr:postcode": "43701",
    "addr:street": "Maysville Pike",
    "iso:country": "US",
    "sg:address": "2455 Maysville Pike",
    "sg:city": "Zanesville",
    "sg:classifiers": [
      {
        "category": "Retail",
        "subcategory": "Car Wash",
        "type": "Services"
      }
    ],
    "sg:phone": "+1 740 454 0058",
    "sg:postcode": "43701",
    "sg:province": "OH",
    "sg:tags": [
      "polishing",
      "washing"
    ],
    "wof:name": "Splash \u0026 Dash Touchless Car",
    "wof:placetype": "venue"
  },
  "geometry": {"coordinates":[-82.027971,39.899868],"type":"Point"}
}
