{
  "type": "Feature",
  "properties": {
    "addr:full":"1912 S Taylor Rd Cleveland OH 44118",
    "addr:housenumber":"1912",
    "addr:postcode":"44118",
    "addr:street":"S Taylor Rd",
    "iso:country":"US",
    "sg:address":"1912 S Taylor Rd",
    "sg:city":"Cleveland",
    "sg:classifiers":[
        {
            "category":"Insurance",
            "subcategory":"Insurance Agent",
            "type":"Services"
        }
    ],
    "sg:phone":"+1 216 371 5011",
    "sg:postcode":"44118",
    "sg:province":"OH",
    "wof:name":"Allstate Insurance",
    "wof:placetype":"venue"
},
  "geometry": {"coordinates":[-81.555897,41.507928],"type":"Point"}
}