{
  "type": "Feature",
  "properties": {
    "iso:country":"US",
    "sg:address":"4838 Co Rd 13",
    "sg:city":"Kansas",
    "sg:classifiers":[
        {
            "category":"Freight",
            "type":"Transportation"
        }
    ],
    "sg:phone":"+1 419 986 5275",
    "sg:postcode":"44841",
    "sg:province":"OH",
    "sg:tags":[
        "operator",
        "trucking"
    ],
    "wof:name":"Ronald Timmons Trucking Inc",
    "wof:placetype":"venue"
},
  "geometry": {"coordinates":[-83.303992,41.26888],"type":"Point"}
}