{
  "type": "Feature",
  "properties": {
    "addr:full":"172 Midhurst Rd Columbus OH 43230",
    "addr:housenumber":"172",
    "addr:postcode":"43230",
    "addr:street":"Midhurst Rd",
    "iso:country":"US",
    "sg:address":"172 Midhurst Rd",
    "sg:city":"Columbus",
    "sg:classifiers":[
        {
            "category":"Building & Trades",
            "subcategory":"Construction",
            "type":"Services"
        }
    ],
    "sg:phone":"+1 614 471 0945",
    "sg:postcode":"43230",
    "sg:province":"OH",
    "sg:tags":[
        "hanging",
        "contractor"
    ],
    "wof:name":"Devaneys Painting",
    "wof:placetype":"venue"
},
  "geometry": {"coordinates":[-82.880065,40.055152],"type":"Point"}
}