{
  "type": "Feature",
  "properties": {
    "addr:full": "2907 Monterey Rd Batavia OH 45103",
    "addr:housenumber": "2907",
    "addr:postcode": "45103",
    "addr:street": "Monterey Rd",
    "iso:country": "US",
    "sg:address": "2907 Monterey Rd",
    "sg:city": "Batavia",
    "sg:classifiers": [
      {
        "category": "Building \u0026 Trades",
        "subcategory": "Construction",
        "type": "Services"
      }
    ],
    "sg:phone": "+1 513 625 6569",
    "sg:postcode": "45103",
    "sg:province": "OH",
    "sg:tags": [
      "excavation",
      "contractor"
    ],
    "wof:name": "Gilkison Excavating",
    "wof:placetype": "venue"
  },
  "geometry": {"coordinates":[-84.086577,39.143016],"type":"Point"}
}
