{
  "type": "Feature",
  "properties": {
    "addr:full": "184 Melmore St Tiffin OH 44883",
    "addr:housenumber": "184",
    "addr:postcode": "44883",
    "addr:street": "Melmore St",
    "iso:country": "US",
    "sg:address": "184 Melmore St",
    "sg:city": "Tiffin",
    "sg:classifiers": [
      {
        "category": "Building \u0026 Trades",
        "subcategory": "Construction",
        "type": "Services"
      }
    ],
    "sg:phone": "+1 419 447 8880",
    "sg:postcode": "44883",
    "sg:province": "OH",
    "sg:tags": [
      "house"
    ],
    "wof:name": "Kelly Construction and Drywall",
    "wof:placetype": "venue"
  },
  "geometry": {"coordinates":[-83.171688,41.105304],"type":"Point"}
}
