{
  "type": "Feature",
  "properties": {
    "iso:country":"US",
    "sg:address":"184 Melmore St",
    "sg:city":"Tiffin",
    "sg:classifiers":[
        {
            "category":"Building & Trades",
            "subcategory":"Construction",
            "type":"Services"
        }
    ],
    "sg:phone":"+1 419 447 8880",
    "sg:postcode":"44883",
    "sg:province":"OH",
    "sg:tags":[
        "house"
    ],
    "wof:name":"Kelly Construction and Drywall",
    "wof:placetype":"venue"
},
  "geometry": {"coordinates":[-83.171688,41.105304],"type":"Point"}
}