{
  "type": "Feature",
  "properties": {
    "addr:full": "6839 Ashfield Dr Cincinnati OH 45242",
    "addr:housenumber": "6839",
    "addr:postcode": "45242",
    "addr:street": "Ashfield Dr",
    "iso:country": "US",
    "sg:address": "6839 Ashfield Dr",
    "sg:city": "Cincinnati",
    "sg:classifiers": [
      {
        "category": "Building \u0026 Trades",
        "subcategory": "Construction",
        "type": "Services"
      }
    ],
    "sg:phone": "+1 513 891 6340",
    "sg:postcode": "45242",
    "sg:province": "OH",
    "sg:tags": [
      "cabinet",
      "maker",
      "woodworker"
    ],
    "wof:name": "C \u0026 W Custom Woodworking",
    "wof:placetype": "venue"
  },
  "geometry": {"coordinates":[-84.359609,39.265067],"type":"Point"}
}
