{
  "type": "Feature",
  "properties": {
    "iso:country":"US",
    "sg:address":"6839 Ashfield Dr",
    "sg:city":"Cincinnati",
    "sg:classifiers":[
        {
            "category":"Building & Trades",
            "subcategory":"Construction",
            "type":"Services"
        }
    ],
    "sg:phone":"+1 513 891 6340",
    "sg:postcode":"45242",
    "sg:province":"OH",
    "sg:tags":[
        "cabinet",
        "maker",
        "woodworker"
    ],
    "wof:name":"C & W Custom Woodworking",
    "wof:placetype":"venue"
},
  "geometry": {"coordinates":[-84.35960900000001,39.265067],"type":"Point"}
}