{
  "type": "Feature",
  "properties": {
    "addr:full":"14221 Country View Cir Columbiana OH 44408",
    "addr:housenumber":"14221",
    "addr:postcode":"44408",
    "addr:street":"Country View Cir",
    "iso:country":"US",
    "sg:address":"14221 Country View Cir",
    "sg:city":"Columbiana",
    "sg:classifiers":[
        {
            "category":"Manufacturing",
            "subcategory":"Petroleum Products",
            "type":"Manufacturing & Wholesale Goods"
        }
    ],
    "sg:phone":"+1 330 549 3372",
    "sg:postcode":"44408",
    "sg:province":"OH",
    "sg:tags":[
        "contract"
    ],
    "wof:name":"Brave Industries",
    "wof:placetype":"venue"
},
  "geometry": {"coordinates":[-80.660234,40.911908],"type":"Point"}
}