{
  "type": "Feature",
  "properties": {
    "addr:full": "3870 Morse Rd Columbus OH 43219",
    "addr:housenumber": "3870",
    "addr:postcode": "43219",
    "addr:street": "Morse Rd",
    "iso:country": "US",
    "sg:address": "3870 Morse Rd",
    "sg:city": "Columbus",
    "sg:classifiers": [
      {
        "category": "Wholesale",
        "subcategory": "Apparel",
        "type": "Manufacturing \u0026 Wholesale Goods"
      }
    ],
    "sg:phone": "+1 614 476 7444",
    "sg:postcode": "43219",
    "sg:province": "OH",
    "sg:tags": [
      "footwear"
    ],
    "wof:name": "Boot Shop",
    "wof:placetype": "venue"
  },
  "geometry": {"coordinates":[-82.918224,40.057891],"type":"Point"}
}
