{
  "type": "Feature",
  "properties": {
    "iso:country":"US",
    "sg:address":"10999 Reed Hartman Hwy",
    "sg:city":"Cincinnati",
    "sg:classifiers":[
        {
            "category":"Banks & Credit Unions",
            "subcategory":"Bank",
            "type":"Services"
        }
    ],
    "sg:phone":"+1 513 793 6361",
    "sg:postcode":"45242",
    "sg:province":"OH",
    "sg:tags":[
        "loan",
        "real estate"
    ],
    "wof:name":"One Stop Mortgage",
    "wof:placetype":"venue"
},
  "geometry": {"coordinates":[-84.37730000000001,39.267867],"type":"Point"}
}