{
  "type": "Feature",
  "properties": {
    "iso:country":"US",
    "sg:address":"3031 Brecksville Rd",
    "sg:city":"Richfield",
    "sg:classifiers":[
        {
            "category":"Shopping",
            "subcategory":"Clothing, Apparel, & Fashions",
            "type":"Retail Goods"
        }
    ],
    "sg:phone":"+1 330 659 2970",
    "sg:postcode":"44286",
    "sg:province":"OH",
    "sg:tags":[
        "uniform"
    ],
    "wof:name":"Hudson Workwear Co",
    "wof:placetype":"venue"
},
  "geometry": {"coordinates":[-81.638009,41.214202],"type":"Point"}
}