{
  "type": "Feature",
  "properties": {
    "addr:full": "3031 Brecksville Rd Richfield OH 44286",
    "addr:housenumber": "3031",
    "addr:postcode": "44286",
    "addr:street": "Brecksville Rd",
    "iso:country": "US",
    "sg:address": "3031 Brecksville Rd",
    "sg:city": "Richfield",
    "sg:classifiers": [
      {
        "category": "Shopping",
        "subcategory": "Clothing, Apparel, \u0026 Fashions",
        "type": "Retail Goods"
      }
    ],
    "sg:phone": "+1 330 659 2970",
    "sg:postcode": "44286",
    "sg:province": "OH",
    "sg:tags": [
      "uniform"
    ],
    "wof:name": "Hudson Workwear Co",
    "wof:placetype": "venue"
  },
  "geometry": {"coordinates":[-81.638009,41.214202],"type":"Point"}
}
