{
  "type": "Feature",
  "properties": {
    "addr:full":"1850 Bethlehem Rd Winchester OH 45697",
    "addr:housenumber":"1850",
    "addr:postcode":"45697",
    "addr:street":"Bethlehem Rd",
    "iso:country":"US",
    "sg:address":"1850 Bethlehem Rd",
    "sg:city":"Winchester",
    "sg:classifiers":[
        {
            "category":"Building & Trades",
            "subcategory":"Construction",
            "type":"Services"
        }
    ],
    "sg:phone":"+1 513 532 8211",
    "sg:postcode":"45697",
    "sg:province":"OH",
    "sg:tags":[
        "residential"
    ],
    "wof:name":"Power Construction Inc",
    "wof:placetype":"venue"
},
  "geometry": {"coordinates":[-83.67697699999999,38.882394],"type":"Point"}
}