{
  "type": "Feature",
  "properties": {
    "iso:country":"US",
    "sg:address":"73 Maplewood Dr",
    "sg:city":"Athens",
    "sg:classifiers":[
        {
            "category":"Professional",
            "type":"Services"
        }
    ],
    "sg:phone":"+1 740 594 5200",
    "sg:postcode":"45701",
    "sg:province":"OH",
    "sg:tags":[
        "inventor"
    ],
    "wof:name":"Docie Marketing",
    "wof:placetype":"venue"
},
  "geometry": {"coordinates":[-82.091629,39.33482],"type":"Point"}
}