{
  "type": "Feature",
  "properties": {
    "addr:full":"4551 Coolbrook Dr Hilliard OH 43026",
    "addr:housenumber":"4551",
    "addr:postcode":"43026",
    "addr:street":"Coolbrook Dr",
    "iso:country":"US",
    "sg:address":"4551 Coolbrook Dr",
    "sg:city":"Hilliard",
    "sg:classifiers":[
        {
            "category":"Shopping",
            "subcategory":"Computers & Home Electronics",
            "type":"Retail Goods"
        }
    ],
    "sg:phone":"+1 614 777 9201",
    "sg:postcode":"43026",
    "sg:province":"OH",
    "wof:name":"Affordabble Reliable Customs",
    "wof:placetype":"venue"
},
  "geometry": {"coordinates":[-83.11139799999999,40.049012],"type":"Point"}
}