{
  "type": "Feature",
  "properties": {
    "addr:full": "101 E Main St Berlin Heights OH 44814",
    "addr:housenumber": "101",
    "addr:postcode": "44814",
    "addr:street": "E Main St",
    "iso:country": "US",
    "sg:address": "101 E Main St",
    "sg:city": "Berlin Heights",
    "sg:classifiers": [
      {
        "category": "Autos \u0026 Motor Vehicles",
        "subcategory": "Fuel \u0026 Gas Station",
        "type": "Retail Goods"
      }
    ],
    "sg:phone": "+1 419 588 2525",
    "sg:postcode": "44814",
    "sg:province": "OH",
    "sg:tags": [
      "oil"
    ],
    "wof:name": "Berlin Heights Marathon",
    "wof:placetype": "venue"
  },
  "geometry": {"coordinates":[-82.48198,41.325179],"type":"Point"}
}
