{
  "type": "Feature",
  "properties": {
    "iso:country":"US",
    "sg:address":"11050 Avenue Rd",
    "sg:city":"Perrysburg",
    "sg:classifiers":[
        {
            "category":"Organizations",
            "subcategory":"Religious Organization",
            "type":"Services"
        }
    ],
    "sg:phone":"+1 419 872 0252",
    "sg:postcode":"43551",
    "sg:province":"OH",
    "sg:tags":[
        "church"
    ],
    "wof:name":"Church Of Jesus Christ Of Lds",
    "wof:placetype":"venue"
},
  "geometry": {"coordinates":[-83.607727,41.56468],"type":"Point"}
}