{
  "type": "Feature",
  "properties": {
    "addr:full": "8468 Sunfish Ln Maineville OH 45039",
    "addr:housenumber": "8468",
    "addr:postcode": "45039",
    "addr:street": "Sunfish Ln",
    "iso:country": "US",
    "sg:address": "8468 Sunfish Ln",
    "sg:city": "Maineville",
    "sg:classifiers": [
      {
        "category": "Restaurant",
        "type": "Food \u0026 Drink"
      }
    ],
    "sg:phone": "+1 513 346 3650",
    "sg:postcode": "45039",
    "sg:province": "OH",
    "sg:tags": [
      "eating"
    ],
    "wof:name": "Cafe Espress Yourself Inc",
    "wof:placetype": "venue"
  },
  "geometry": {"coordinates":[-84.28274,39.315407],"type":"Point"}
}
