{
  "type": "Feature",
  "properties": {
    "iso:country":"US",
    "sg:address":"3281 Smiley Rd",
    "sg:city":"Columbus",
    "sg:classifiers":[
        {
            "category":"Professional",
            "type":"Services"
        }
    ],
    "sg:phone":"+1 614 771 1111",
    "sg:postcode":"43221",
    "sg:province":"OH",
    "wof:name":"7realty Co",
    "wof:placetype":"venue"
},
  "geometry": {"coordinates":[-83.10489,40.022267],"type":"Point"}
}