{
  "type": "Feature",
  "properties": {
    "addr:full":"32 W Walnut St Marengo OH 43334",
    "addr:housenumber":"32",
    "addr:postcode":"43334",
    "addr:street":"W Walnut St",
    "iso:country":"US",
    "sg:address":"32 W Walnut St",
    "sg:city":"Marengo",
    "sg:classifiers":[
        {
            "category":"Real Estate",
            "subcategory":"Real Estate Agent",
            "type":"Services"
        }
    ],
    "sg:phone":"+1 419 253 4611",
    "sg:postcode":"43334",
    "sg:province":"OH",
    "wof:name":"King Realty",
    "wof:placetype":"venue"
},
  "geometry": {"coordinates":[-82.813361,40.400079],"type":"Point"}
}