{
  "type": "Feature",
  "properties": {
    "addr:full": "1832 Elwood Ln Springfield OH 45506",
    "addr:housenumber": "1832",
    "addr:postcode": "45506",
    "addr:street": "Elwood Ln",
    "iso:country": "US",
    "sg:address": "1832 Elwood Ln",
    "sg:city": "Springfield",
    "sg:classifiers": [
      {
        "category": "Building \u0026 Trades",
        "subcategory": "Construction",
        "type": "Services"
      }
    ],
    "sg:phone": "+1 937 328 3247",
    "sg:postcode": "45506",
    "sg:province": "OH",
    "sg:tags": [
      "mobile",
      "home"
    ],
    "wof:name": "Derr's Mobile Home Svc",
    "wof:placetype": "venue"
  },
  "geometry": {"coordinates":[-83.852524,39.864096],"type":"Point"}
}
