{
  "type": "Feature",
  "properties": {
    "iso:country":"US",
    "sg:address":"429 E Central Ave",
    "sg:city":"Miamisburg",
    "sg:classifiers":[
        {
            "category":"Building & Trades",
            "subcategory":"Plumbing",
            "type":"Services"
        }
    ],
    "sg:phone":"+1 937 866 7475",
    "sg:postcode":"45342",
    "sg:province":"OH",
    "sg:tags":[
        "contractor"
    ],
    "wof:name":"Baneco Plumbing",
    "wof:placetype":"venue"
},
  "geometry": {"coordinates":[-84.28360000000001,39.641633],"type":"Point"}
}