{
  "type": "Feature",
  "properties": {
    "addr:full": "429 E Central Ave Miamisburg OH 45342",
    "addr:housenumber": "429",
    "addr:postcode": "45342",
    "addr:street": "E Central Ave",
    "iso:country": "US",
    "sg:address": "429 E Central Ave",
    "sg:city": "Miamisburg",
    "sg:classifiers": [
      {
        "category": "Building \u0026 Trades",
        "subcategory": "Plumbing",
        "type": "Services"
      }
    ],
    "sg:phone": "+1 937 866 7475",
    "sg:postcode": "45342",
    "sg:province": "OH",
    "sg:tags": [
      "contractor"
    ],
    "wof:name": "Baneco Plumbing",
    "wof:placetype": "venue"
  },
  "geometry": {"coordinates":[-84.2836,39.641633],"type":"Point"}
}
