{
  "type": "Feature",
  "properties": {
    "addr:full": "5021 Groh Ln Fairfield OH 45014",
    "addr:postcode": "5021;45014",
    "addr:street": "Groh Ln",
    "iso:country": "US",
    "sg:address": "5021 Groh Ln",
    "sg:city": "Fairfield",
    "sg:classifiers": [
      {
        "category": "Government",
        "subcategory": "Office",
        "type": "Public Place"
      },
      {
        "category": "Manufacturing",
        "subcategory": "Tools \u0026 Machinery",
        "type": "Manufacturing \u0026 Wholesale Goods"
      }
    ],
    "sg:phone": "+1 513 867 5382",
    "sg:postcode": "45014",
    "sg:province": "OH",
    "sg:tags": [
      "city",
      "supply",
      "industry",
      "mfg",
      "water",
      "govt"
    ],
    "wof:name": "Public Utilities Water Div",
    "wof:placetype": "venue"
  },
  "geometry": {"coordinates":[-84.583841,39.3438],"type":"Point"}
}
