{
  "type": "Feature",
  "properties": {
    "iso:country":"US",
    "sg:address":"5021 Groh Ln",
    "sg:city":"Fairfield",
    "sg:classifiers":[
        {
            "category":"Government",
            "subcategory":"Office",
            "type":"Public Place"
        },
        {
            "category":"Manufacturing",
            "subcategory":"Tools & Machinery",
            "type":"Manufacturing & Wholesale Goods"
        }
    ],
    "sg:phone":"+1 513 867 5382",
    "sg:postcode":"45014",
    "sg:province":"OH",
    "sg:tags":[
        "city",
        "supply",
        "industry",
        "mfg",
        "water",
        "govt"
    ],
    "wof:name":"Public Utilities Water Div",
    "wof:placetype":"venue"
},
  "geometry": {"coordinates":[-84.58384100000001,39.3438],"type":"Point"}
}