{
  "type": "Feature",
  "properties": {
    "addr:full": "4635 Richmond Rd Cleveland OH 44128",
    "addr:housenumber": "4635",
    "addr:postcode": "44128",
    "addr:street": "Richmond Rd",
    "iso:country": "US",
    "sg:address": "4635 Richmond Rd",
    "sg:city": "Cleveland",
    "sg:classifiers": [
      {
        "category": "Building \u0026 Trades",
        "subcategory": "Plumbing",
        "type": "Services"
      }
    ],
    "sg:phone": "+1 216 464 3990",
    "sg:postcode": "44128",
    "sg:province": "OH",
    "sg:tags": [
      "conditioning",
      "air",
      "system",
      "contractor"
    ],
    "wof:name": "A A Furnace \u0026 Boiler Co",
    "wof:placetype": "venue"
  },
  "geometry": {"coordinates":[-81.497831,41.431266],"type":"Point"}
}
