{
  "type": "Feature",
  "properties": {
    "iso:country":"US",
    "sg:address":"4635 Richmond Rd",
    "sg:city":"Cleveland",
    "sg:classifiers":[
        {
            "category":"Building & Trades",
            "subcategory":"Plumbing",
            "type":"Services"
        }
    ],
    "sg:phone":"+1 216 464 3990",
    "sg:postcode":"44128",
    "sg:province":"OH",
    "sg:tags":[
        "conditioning",
        "air",
        "system",
        "contractor"
    ],
    "wof:name":"A A Furnace & Boiler Co",
    "wof:placetype":"venue"
},
  "geometry": {"coordinates":[-81.49783100000001,41.431266],"type":"Point"}
}