{
  "type": "Feature",
  "properties": {
    "addr:full":"2510 Barryknoll St Dayton OH 45420",
    "addr:housenumber":"2510",
    "addr:postcode":"45420",
    "addr:street":"Barryknoll St",
    "iso:country":"US",
    "sg:address":"2510 Barryknoll St",
    "sg:city":"Dayton",
    "sg:classifiers":[
        {
            "category":"Wholesale",
            "subcategory":"Machinery & Supplies",
            "type":"Manufacturing & Wholesale Goods"
        }
    ],
    "sg:phone":"+1 937 299 7873",
    "sg:postcode":"45420",
    "sg:province":"OH",
    "sg:tags":[
        "equipment",
        "irrigation",
        "system"
    ],
    "wof:name":"Sure Green",
    "wof:placetype":"venue"
},
  "geometry": {"coordinates":[-84.121392,39.710639],"type":"Point"}
}