{
  "type": "Feature",
  "properties": {
    "iso:country":"US",
    "sg:address":"2232 Dixie Hwy",
    "sg:city":"Hamilton",
    "sg:classifiers":[
        {
            "category":"Recreation",
            "type":"Entertainment"
        }
    ],
    "sg:phone":"+1 513 863 6611",
    "sg:postcode":"45015",
    "sg:province":"OH",
    "sg:tags":[
        "course",
        "golf"
    ],
    "wof:name":"Putt Putt Golf & Games",
    "wof:placetype":"venue"
},
  "geometry": {"coordinates":[-84.548599,39.372929],"type":"Point"}
}