{
  "type": "Feature",
  "properties": {
    "addr:full": "2232 Dixie Hwy Hamilton OH 45015",
    "addr:housenumber": "2232",
    "addr:postcode": "45015",
    "addr:street": "Dixie Hwy",
    "iso:country": "US",
    "sg:address": "2232 Dixie Hwy",
    "sg:city": "Hamilton",
    "sg:classifiers": [
      {
        "category": "Recreation",
        "type": "Entertainment"
      }
    ],
    "sg:phone": "+1 513 863 6611",
    "sg:postcode": "45015",
    "sg:province": "OH",
    "sg:tags": [
      "course",
      "golf"
    ],
    "wof:name": "Putt Putt Golf \u0026 Games",
    "wof:placetype": "venue"
  },
  "geometry": {"coordinates":[-84.548599,39.372929],"type":"Point"}
}
