{
  "type": "Feature",
  "properties": {
    "addr:full":"951 E Johnstown Rd Gahanna OH 43230",
    "addr:housenumber":"951",
    "addr:postcode":"43230",
    "addr:street":"E Johnstown Rd",
    "iso:country":"US",
    "sg:address":"951 E Johnstown Rd",
    "sg:city":"Gahanna",
    "sg:classifiers":[
        {
            "category":"Recreation",
            "subcategory":"Arcade",
            "type":"Entertainment"
        }
    ],
    "sg:phone":"+1 614 476 3050",
    "sg:postcode":"43230",
    "sg:province":"OH",
    "sg:tags":[
        "machine",
        "pinball"
    ],
    "wof:name":"Tilt Pinball",
    "wof:placetype":"venue"
},
  "geometry": {"coordinates":[-82.86339599999999,40.040534],"type":"Point"}
}