{
  "type": "Feature",
  "properties": {
    "iso:country":"US",
    "sg:address":"55 W Waterloo Rd",
    "sg:city":"Akron",
    "sg:classifiers":[
        {
            "category":"Bars & Pubs",
            "type":"Food & Drink"
        }
    ],
    "sg:phone":"+1 330 785 4440",
    "sg:postcode":"44319",
    "sg:province":"OH",
    "wof:name":"Drink",
    "wof:placetype":"venue"
},
  "geometry": {"coordinates":[-81.527293,41.028822],"type":"Point"}
}