{
  "type": "Feature",
  "properties": {
    "addr:full": "1211 Schreier Rd Rossford OH 43460",
    "addr:housenumber": "1211",
    "addr:postcode": "43460",
    "addr:street": "Schreier Rd",
    "iso:country": "US",
    "sg:address": "1211 Schreier Rd",
    "sg:city": "Rossford",
    "sg:classifiers": [
      {
        "category": "Food \u0026 Beverages",
        "subcategory": "Groceries \u0026 Convenience Stores",
        "type": "Retail Goods"
      }
    ],
    "sg:phone": "+1 419 666 6455",
    "sg:postcode": "43460",
    "sg:province": "OH",
    "wof:name": "Convenience Plus Inc",
    "wof:placetype": "venue"
  },
  "geometry": {"coordinates":[-83.569589,41.597809],"type":"Point"}
}
