{
  "type": "Feature",
  "properties": {
    "iso:country":"US",
    "sg:address":"248 E Stroop Rd",
    "sg:city":"Dayton",
    "sg:classifiers":[
        {
            "category":"Shopping",
            "subcategory":"Computers & Home Electronics",
            "type":"Retail Goods"
        }
    ],
    "sg:phone":"+1 937 294 7277",
    "sg:postcode":"45429",
    "sg:province":"OH",
    "wof:name":"Radio Shack",
    "wof:placetype":"venue"
},
  "geometry": {"coordinates":[-84.168002,39.689493],"type":"Point"}
}