{
  "type": "Feature",
  "properties": {
    "addr:full": "52 N Westwood Ave Toledo OH 43607",
    "addr:housenumber": "52",
    "addr:postcode": "43607",
    "addr:street": "N Westwood Ave",
    "iso:country": "US",
    "sg:address": "52 N Westwood Ave",
    "sg:city": "Toledo",
    "sg:classifiers": [
      {
        "category": "Wholesale",
        "subcategory": "Office Equipment",
        "type": "Manufacturing \u0026 Wholesale Goods"
      }
    ],
    "sg:phone": "+1 419 531 1100",
    "sg:postcode": "43607",
    "sg:province": "OH",
    "sg:tags": [
      "machine",
      "business"
    ],
    "wof:name": "MCR Nrthern Ohio Cash Rgisters",
    "wof:placetype": "venue"
  },
  "geometry": {"coordinates":[-83.606571,41.638908],"type":"Point"}
}
