{
  "type": "Feature",
  "properties": {
    "iso:country":"US",
    "sg:address":"500 Summer St",
    "sg:city":"New Lexington",
    "sg:classifiers":[
        {
            "category":"Building & Trades",
            "subcategory":"Construction",
            "type":"Services"
        }
    ],
    "sg:phone":"+1 740 342 2700",
    "sg:postcode":"43764",
    "sg:province":"OH",
    "sg:tags":[
        "general",
        "remodeling",
        "contractor"
    ],
    "wof:name":"Tom Hankinson Building & Rmdlg",
    "wof:placetype":"venue"
},
  "geometry": {"coordinates":[-82.21090100000001,39.707867],"type":"Point"}
}