{
  "type": "Feature",
  "properties": {
    "addr:full": "500 Summer St New Lexington OH 43764",
    "addr:housenumber": "500",
    "addr:postcode": "43764",
    "addr:street": "Summer St",
    "iso:country": "US",
    "sg:address": "500 Summer St",
    "sg:city": "New Lexington",
    "sg:classifiers": [
      {
        "category": "Building \u0026 Trades",
        "subcategory": "Construction",
        "type": "Services"
      }
    ],
    "sg:phone": "+1 740 342 2700",
    "sg:postcode": "43764",
    "sg:province": "OH",
    "sg:tags": [
      "general",
      "remodeling",
      "contractor"
    ],
    "wof:name": "Tom Hankinson Building \u0026 Rmdlg",
    "wof:placetype": "venue"
  },
  "geometry": {"coordinates":[-82.210901,39.707867],"type":"Point"}
}
