{
  "type": "Feature",
  "properties": {
    "addr:full":"5115 Glendale Ave Toledo OH 43614",
    "addr:housenumber":"5115",
    "addr:postcode":"43614",
    "addr:street":"Glendale Ave",
    "iso:country":"US",
    "sg:address":"5115 Glendale Ave",
    "sg:city":"Toledo",
    "sg:classifiers":[
        {
            "category":"Communications",
            "subcategory":"Radio Station",
            "type":"Services"
        }
    ],
    "sg:phone":"+1 419 240 1937",
    "sg:postcode":"43614",
    "sg:province":"OH",
    "sg:tags":[
        "company",
        "broadcasting"
    ],
    "wof:name":"Y Es FM Request Line",
    "wof:placetype":"venue"
},
  "geometry": {"coordinates":[-83.659493,41.6047],"type":"Point"}
}