{
  "type": "Feature",
  "properties": {
    "addr:full": "7439 Oakmeadows Dr Columbus OH 43085",
    "addr:housenumber": "7439",
    "addr:postcode": "43085",
    "addr:street": "Oakmeadows Dr",
    "iso:country": "US",
    "sg:address": "7439 Oakmeadows Dr",
    "sg:city": "Columbus",
    "sg:classifiers": [
      {
        "category": "Building \u0026 Trades",
        "subcategory": "Construction",
        "type": "Services"
      }
    ],
    "sg:phone": "+1 614 431 2504",
    "sg:postcode": "43085",
    "sg:province": "OH",
    "sg:tags": [
      "contractor"
    ],
    "wof:name": "Paul Davis Restoration",
    "wof:placetype": "venue"
  },
  "geometry": {"coordinates":[-82.97934,40.117642],"type":"Point"}
}
