{
  "type": "Feature",
  "properties": {
    "addr:full": "9866 Chatham Rd Spencer OH 44275",
    "addr:housenumber": "9866",
    "addr:postcode": "44275",
    "addr:street": "Chatham Rd",
    "iso:country": "US",
    "sg:address": "9866 Chatham Rd",
    "sg:city": "Spencer",
    "sg:classifiers": [
      {
        "category": "Freight",
        "type": "Transportation"
      }
    ],
    "sg:phone": "+1 330 667 2274",
    "sg:postcode": "44275",
    "sg:province": "OH",
    "sg:tags": [
      "operator",
      "trucking"
    ],
    "wof:name": "After-Hours Transport",
    "wof:placetype": "venue"
  },
  "geometry": {"coordinates":[-82.048174,41.099745],"type":"Point"}
}
