{
  "type": "Feature",
  "properties": {
    "addr:full":"26481 Cannon Rd Cleveland OH 44146",
    "addr:housenumber":"26481",
    "addr:postcode":"44146",
    "addr:street":"Cannon Rd",
    "iso:country":"US",
    "sg:address":"26481 Cannon Rd",
    "sg:city":"Cleveland",
    "sg:classifiers":[
        {
            "category":"Professional",
            "type":"Services"
        }
    ],
    "sg:phone":"+1 440 786 8508",
    "sg:postcode":"44146",
    "sg:province":"OH",
    "sg:tags":[
        "establishment"
    ],
    "wof:name":"Chaplin Block Co",
    "wof:placetype":"venue"
},
  "geometry": {"coordinates":[-81.494595,41.409517],"type":"Point"}
}