{
  "type": "Feature",
  "properties": {
    "addr:full":"8161 Center St Garrettsville OH 44231",
    "addr:housenumber":"8161",
    "addr:postcode":"44231",
    "addr:street":"Center St",
    "iso:country":"US",
    "sg:address":"8161 Center St",
    "sg:city":"Garrettsville",
    "sg:classifiers":[
        {
            "category":"Home & Garden",
            "subcategory":"Hardware",
            "type":"Retail Goods"
        }
    ],
    "sg:phone":"+1 330 527 2553",
    "sg:postcode":"44231",
    "sg:province":"OH",
    "wof:name":"Irwin Hardware",
    "wof:placetype":"venue"
},
  "geometry": {"coordinates":[-81.09639199999999,41.284521],"type":"Point"}
}