{
  "type": "Feature",
  "properties": {
    "iso:country":"US",
    "sg:address":"688 E Main St",
    "sg:city":"Williamsburg",
    "sg:classifiers":[
        {
            "category":"Social Services",
            "subcategory":"Adult Care",
            "type":"Services"
        }
    ],
    "sg:phone":"+1 513 724 3925",
    "sg:postcode":"45176",
    "sg:province":"OH",
    "sg:tags":[
        "home",
        "group"
    ],
    "wof:name":"Pine Ridge-Pine Village Rsdntl",
    "wof:placetype":"venue"
},
  "geometry": {"coordinates":[-84.04072600000001,39.048776],"type":"Point"}
}