{
  "type": "Feature",
  "properties": {
    "addr:full": "688 E Main St Williamsburg OH 45176",
    "addr:housenumber": "688",
    "addr:postcode": "45176",
    "addr:street": "E Main St",
    "iso:country": "US",
    "sg:address": "688 E Main St",
    "sg:city": "Williamsburg",
    "sg:classifiers": [
      {
        "category": "Social Services",
        "subcategory": "Adult Care",
        "type": "Services"
      }
    ],
    "sg:phone": "+1 513 724 3925",
    "sg:postcode": "45176",
    "sg:province": "OH",
    "sg:tags": [
      "home",
      "group"
    ],
    "wof:name": "Pine Ridge-Pine Village Rsdntl",
    "wof:placetype": "venue"
  },
  "geometry": {"coordinates":[-84.040726,39.048776],"type":"Point"}
}
