{
  "type": "Feature",
  "properties": {
    "addr:full": "1516 Starr Ave Toledo OH 43605",
    "addr:housenumber": "1516",
    "addr:postcode": "43605",
    "addr:street": "Starr Ave",
    "iso:country": "US",
    "sg:address": "1516 Starr Ave",
    "sg:city": "Toledo",
    "sg:classifiers": [
      {
        "category": "Professional",
        "subcategory": "Management \u0026 Consulting",
        "type": "Services"
      }
    ],
    "sg:phone": "+1 419 698 2628",
    "sg:postcode": "43605",
    "sg:province": "OH",
    "sg:tags": [
      "marketing",
      "consultant"
    ],
    "wof:name": "Team-Up Assoc",
    "wof:placetype": "venue"
  },
  "geometry": {"coordinates":[-83.508829,41.643521],"type":"Point"}
}
