{
  "type": "Feature",
  "properties": {
    "iso:country":"US",
    "sg:address":"1516 Starr Ave",
    "sg:city":"Toledo",
    "sg:classifiers":[
        {
            "category":"Professional",
            "subcategory":"Management & Consulting",
            "type":"Services"
        }
    ],
    "sg:phone":"+1 419 698 2628",
    "sg:postcode":"43605",
    "sg:province":"OH",
    "sg:tags":[
        "marketing",
        "consultant"
    ],
    "wof:name":"Team-Up Assoc",
    "wof:placetype":"venue"
},
  "geometry": {"coordinates":[-83.50882900000001,41.643521],"type":"Point"}
}