{
  "type": "Feature",
  "properties": {
    "addr:full": "16709 Co Rd D Wauseon OH 43567",
    "addr:housenumber": "16709",
    "addr:postcode": "43567",
    "addr:street": "Co Rd D",
    "iso:country": "US",
    "sg:address": "16709 Co Rd D",
    "sg:city": "Wauseon",
    "sg:phone": "+1 419 335 1679",
    "sg:postcode": "43567",
    "sg:province": "OH",
    "sg:tags": [
      "farm",
      "corn",
      "soybean"
    ],
    "wof:name": "Lawrence Rabe",
    "wof:placetype": "venue"
  },
  "geometry": {"coordinates":[-84.186275,41.529249],"type":"Point"}
}
