{
  "type": "Feature",
  "properties": {
    "addr:full":"1710 W Schrock Rd Westerville OH 43081",
    "addr:housenumber":"1710",
    "addr:postcode":"43081",
    "addr:street":"W Schrock Rd",
    "iso:country":"US",
    "sg:address":"1710 W Schrock Rd",
    "sg:city":"Westerville",
    "sg:classifiers":[
        {
            "category":"Building & Trades",
            "subcategory":"Electrical",
            "type":"Services"
        }
    ],
    "sg:phone":"+1 614 891 8600",
    "sg:postcode":"43081",
    "sg:province":"OH",
    "sg:tags":[
        "telecommunication",
        "contractor"
    ],
    "wof:name":"Sears Amer Window & Sash Inc",
    "wof:placetype":"venue"
},
  "geometry": {"coordinates":[-82.94897400000001,40.110721],"type":"Point"}
}