{
  "type": "Feature",
  "properties": {
    "iso:country":"US",
    "sg:address":"2699 E 51st St",
    "sg:city":"Cleveland",
    "sg:classifiers":[
        {
            "category":"Retail",
            "subcategory":"Auto Rental",
            "type":"Services"
        }
    ],
    "sg:phone":"+1 216 432 3645",
    "sg:postcode":"44104",
    "sg:province":"OH",
    "sg:tags":[
        "renting",
        "truck",
        "leasing"
    ],
    "wof:name":"Ryder",
    "wof:placetype":"venue"
},
  "geometry": {"coordinates":[-81.653998,41.485737],"type":"Point"}
}