{
  "type": "Feature",
  "properties": {
    "addr:full": "116 W Columbus Ave Bellefontaine OH 43311",
    "addr:housenumber": "116",
    "addr:postcode": "43311",
    "addr:street": "W Columbus Ave",
    "iso:country": "US",
    "sg:address": "116 W Columbus Ave",
    "sg:city": "Bellefontaine",
    "sg:classifiers": [
      {
        "category": "Wholesale",
        "subcategory": "Jewelry",
        "type": "Manufacturing \u0026 Wholesale Goods"
      }
    ],
    "sg:phone": "+1 937 592 0899",
    "sg:postcode": "43311",
    "sg:province": "OH",
    "sg:tags": [
      "beads"
    ],
    "wof:name": "Artistic Treasures",
    "wof:placetype": "venue"
  },
  "geometry": {"coordinates":[-83.760135,40.361254],"type":"Point"}
}
