{
  "type": "Feature",
  "properties": {
    "addr:full": "730 N Summit St Toledo OH 43604",
    "addr:housenumber": "730",
    "addr:postcode": "43604",
    "addr:street": "N Summit St",
    "iso:country": "US",
    "sg:address": "730 N Summit St",
    "sg:city": "Toledo",
    "sg:classifiers": [
      {
        "category": "Communications",
        "subcategory": "Television Station",
        "type": "Services"
      }
    ],
    "sg:phone": "+1 419 248 1111",
    "sg:postcode": "43604",
    "sg:province": "OH",
    "sg:tags": [
      "broadcasting",
      "co"
    ],
    "sg:website": "www.wtol.com",
    "wof:name": "WTOL",
    "wof:placetype": "venue"
  },
  "geometry": {"coordinates":[-83.529072,41.655401],"type":"Point"}
}
