{
  "type": "Feature",
  "properties": {
    "iso:country":"US",
    "sg:address":"7726 Lake Shore Blvd",
    "sg:city":"Mentor",
    "sg:classifiers":[
        {
            "category":"Personal",
            "subcategory":"Tattoo Parlor",
            "type":"Services"
        }
    ],
    "sg:phone":"+1 440 209 8400",
    "sg:postcode":"44060",
    "sg:province":"OH",
    "sg:tags":[
        "tattooing"
    ],
    "wof:name":"Mad Lab Tattoos & Body Prcng",
    "wof:placetype":"venue"
},
  "geometry": {"coordinates":[-81.363304,41.704508],"type":"Point"}
}