{
  "type": "Feature",
  "properties": {
    "iso:country":"US",
    "sg:address":"14 Franklin St",
    "sg:city":"Gratis",
    "sg:classifiers":[
        {
            "category":"Banks & Credit Unions",
            "subcategory":"Bank",
            "type":"Services"
        }
    ],
    "sg:phone":"+1 937 787 3121",
    "sg:postcode":"45330",
    "sg:province":"OH",
    "wof:name":"Twin Valley Bank",
    "wof:placetype":"venue"
},
  "geometry": {"coordinates":[-84.527331,39.648826],"type":"Point"}
}