{
  "type": "Feature",
  "properties": {
    "addr:full":"1003 N North St Washington Ct Hs OH 43160",
    "addr:housenumber":"1003",
    "addr:postcode":"43160",
    "addr:street":"N North St",
    "iso:country":"US",
    "sg:address":"1003 N North St",
    "sg:city":"Washington Ct Hs",
    "sg:classifiers":[
        {
            "category":"Organizations",
            "subcategory":"Religious Organization",
            "type":"Services"
        }
    ],
    "sg:phone":"+1 740 335 4682",
    "sg:postcode":"43160",
    "sg:province":"OH",
    "sg:tags":[
        "church"
    ],
    "wof:name":"Good Shepherd Lutheran Church",
    "wof:placetype":"venue"
},
  "geometry": {"coordinates":[-83.446196,39.545116],"type":"Point"}
}