{
  "type": "Feature",
  "properties": {
    "addr:full": "1919 Gest St Cincinnati OH 45204",
    "addr:housenumber": "1919",
    "addr:postcode": "45204",
    "addr:street": "Gest St",
    "iso:country": "US",
    "sg:address": "1919 Gest St",
    "sg:city": "Cincinnati",
    "sg:classifiers": [
      {
        "category": "Manufacturing",
        "subcategory": "Tools \u0026 Machinery",
        "type": "Manufacturing \u0026 Wholesale Goods"
      }
    ],
    "sg:phone": "+1 513 821 0096",
    "sg:postcode": "45204",
    "sg:province": "OH",
    "sg:tags": [
      "physician",
      "surgeon"
    ],
    "wof:name": "Mobility Engineering",
    "wof:placetype": "venue"
  },
  "geometry": {"coordinates":[-84.549771,39.107669],"type":"Point"}
}
