{
  "type": "Feature",
  "properties": {
    "addr:full": "965 Debolt Rd Utica OH 43080",
    "addr:housenumber": "965",
    "addr:postcode": "43080",
    "addr:street": "Debolt Rd",
    "iso:country": "US",
    "sg:address": "965 Debolt Rd",
    "sg:city": "Utica",
    "sg:classifiers": [
      {
        "category": "Professional",
        "type": "Services"
      }
    ],
    "sg:phone": "+1 740 892 3393",
    "sg:postcode": "43080",
    "sg:province": "OH",
    "wof:name": "Dewitt Family Ltd Partner",
    "wof:placetype": "venue"
  },
  "geometry": {"coordinates":[-82.436264,40.24875],"type":"Point"}
}
