{
  "type": "Feature",
  "properties": {
    "addr:full":"21598 Hilliard Blvd Rocky River OH 44116",
    "addr:housenumber":"21598",
    "addr:postcode":"44116",
    "addr:street":"Hilliard Blvd",
    "iso:country":"US",
    "sg:address":"21598 Hilliard Blvd",
    "sg:city":"Rocky River",
    "sg:classifiers":[
        {
            "category":"Shopping",
            "subcategory":"Gifts & Souvenirs",
            "type":"Retail Goods"
        }
    ],
    "sg:phone":"+1 440 333 8137",
    "sg:postcode":"44116",
    "sg:province":"OH",
    "wof:name":"Jmr Craft Design",
    "wof:placetype":"venue"
},
  "geometry": {"coordinates":[-81.858976,41.46512],"type":"Point"}
}