{
  "type": "Feature",
  "properties": {
    "iso:country":"US",
    "sg:address":"1 N Sandusky St",
    "sg:city":"Delaware",
    "sg:classifiers":[
        {
            "category":"Building & Trades",
            "subcategory":"Equipment Rental",
            "type":"Services"
        }
    ],
    "sg:phone":"+1 740 368 9966",
    "sg:postcode":"43015",
    "sg:province":"OH",
    "sg:tags":[
        "instrument",
        "musical"
    ],
    "wof:name":"Crossroads Music LTD",
    "wof:placetype":"venue"
},
  "geometry": {"coordinates":[-83.067652,40.300171],"type":"Point"}
}