{
  "type": "Feature",
  "properties": {
    "addr:full": "180 Silver St Marion OH 43302",
    "addr:housenumber": "180",
    "addr:postcode": "43302",
    "addr:street": "Silver St",
    "iso:country": "US",
    "sg:address": "180 Silver St",
    "sg:city": "Marion",
    "sg:classifiers": [
      {
        "category": "Professional",
        "type": "Services"
      }
    ],
    "sg:phone": "+1 740 387 7162",
    "sg:postcode": "43302",
    "sg:province": "OH",
    "sg:tags": [
      "establishment"
    ],
    "wof:name": "Buckeye Family Inc",
    "wof:placetype": "venue"
  },
  "geometry": {"coordinates":[-83.131513,40.593027],"type":"Point"}
}
