{
  "type": "Feature",
  "properties": {
    "addr:full": "104 Pearl Rd Brunswick OH 44212",
    "addr:housenumber": "104",
    "addr:postcode": "44212",
    "addr:street": "Pearl Rd",
    "iso:country": "US",
    "sg:address": "104 Pearl Rd",
    "sg:city": "Brunswick",
    "sg:classifiers": [
      {
        "category": "Shopping",
        "type": "Retail Goods"
      }
    ],
    "sg:phone": "+1 330 273 6863",
    "sg:postcode": "44212",
    "sg:province": "OH",
    "sg:tags": [
      "trophy",
      "medal",
      "award"
    ],
    "wof:name": "Quinn's Sports \u0026 Trophies",
    "wof:placetype": "venue"
  },
  "geometry": {"coordinates":[-81.837042,41.273856],"type":"Point"}
}
