{
  "type": "Feature",
  "properties": {
    "iso:country":"US",
    "sg:address":"104 Pearl Rd",
    "sg:city":"Brunswick",
    "sg:classifiers":[
        {
            "category":"Shopping",
            "type":"Retail Goods"
        }
    ],
    "sg:phone":"+1 330 273 6863",
    "sg:postcode":"44212",
    "sg:province":"OH",
    "sg:tags":[
        "trophy",
        "medal",
        "award"
    ],
    "wof:name":"Quinn's Sports & Trophies",
    "wof:placetype":"venue"
},
  "geometry": {"coordinates":[-81.837042,41.273856],"type":"Point"}
}