{
  "type": "Feature",
  "properties": {
    "addr:full":"2009 Stanley Ave Dayton OH 45404",
    "addr:housenumber":"2009",
    "addr:postcode":"45404",
    "addr:street":"Stanley Ave",
    "iso:country":"US",
    "sg:address":"2009 Stanley Ave",
    "sg:city":"Dayton",
    "sg:classifiers":[
        {
            "category":"Wholesale",
            "subcategory":"Electrical",
            "type":"Manufacturing & Wholesale Goods"
        }
    ],
    "sg:phone":"+1 937 222 0602",
    "sg:postcode":"45404",
    "sg:province":"OH",
    "sg:tags":[
        "equipment"
    ],
    "wof:name":"Interstate Batteries Wstn Ohio",
    "wof:placetype":"venue"
},
  "geometry": {"coordinates":[-84.177228,39.788093],"type":"Point"}
}