{
  "type": "Feature",
  "properties": {
    "iso:country":"US",
    "sg:address":"79 Hill Dr",
    "sg:city":"Youngstown",
    "sg:classifiers":[
        {
            "category":"Organizations",
            "subcategory":"Religious Organization",
            "type":"Services"
        }
    ],
    "sg:phone":"+1 330 757 9258",
    "sg:postcode":"44514",
    "sg:province":"OH",
    "sg:tags":[
        "church"
    ],
    "wof:name":"Poland Village Baptist Church",
    "wof:placetype":"venue"
},
  "geometry": {"coordinates":[-80.60708200000001,41.030158],"type":"Point"}
}