{
  "type": "Feature",
  "properties": {
    "addr:full": "2326 Lincoln Way E Massillon OH 44646",
    "addr:housenumber": "2326",
    "addr:postcode": "44646",
    "addr:street": "Lincoln Way E",
    "iso:country": "US",
    "sg:address": "2326 Lincoln Way E",
    "sg:city": "Massillon",
    "sg:classifiers": [
      {
        "category": "Autos \u0026 Motor Vehicles",
        "subcategory": "Automobile Sales",
        "type": "Retail Goods"
      }
    ],
    "sg:phone": "+1 330 830 0500",
    "sg:postcode": "44646",
    "sg:province": "OH",
    "wof:name": "Waiken Honday Kia",
    "wof:placetype": "venue"
  },
  "geometry": {"coordinates":[-81.491937,40.798501],"type":"Point"}
}
