{
  "type": "Feature",
  "properties": {
    "iso:country":"US",
    "sg:address":"2326 Lincoln Way E",
    "sg:city":"Massillon",
    "sg:classifiers":[
        {
            "category":"Autos & Motor Vehicles",
            "subcategory":"Automobile Sales",
            "type":"Retail Goods"
        }
    ],
    "sg:phone":"+1 330 830 0500",
    "sg:postcode":"44646",
    "sg:province":"OH",
    "wof:name":"Waiken Honday Kia",
    "wof:placetype":"venue"
},
  "geometry": {"coordinates":[-81.49193699999999,40.798501],"type":"Point"}
}