{
  "type": "Feature",
  "properties": {
    "iso:country":"US",
    "sg:address":"5400 Kennedy Ave",
    "sg:city":"Cincinnati",
    "sg:classifiers":[
        {
            "category":"Health Services",
            "subcategory":"Health Practitioner",
            "type":"Services"
        }
    ],
    "sg:phone":"+1 513 924 5499",
    "sg:postcode":"45213",
    "sg:province":"OH",
    "sg:tags":[
        "acupuncture"
    ],
    "wof:name":"Acupunture By Carole Paine",
    "wof:placetype":"venue"
},
  "geometry": {"coordinates":[-84.418182,39.173066],"type":"Point"}
}