{
  "type": "Feature",
  "properties": {
    "addr:full":"3152 Lighthouse Dr Fairfield OH 45014",
    "addr:housenumber":"3152",
    "addr:postcode":"45014",
    "addr:street":"Lighthouse Dr",
    "iso:country":"US",
    "sg:address":"3152 Lighthouse Dr",
    "sg:city":"Fairfield",
    "sg:classifiers":[
        {
            "category":"Manufacturing",
            "subcategory":"Printing",
            "type":"Manufacturing & Wholesale Goods"
        }
    ],
    "sg:phone":"+1 513 874 4494",
    "sg:postcode":"45014",
    "sg:province":"OH",
    "sg:tags":[
        "lithographic",
        "printer",
        "commercial"
    ],
    "wof:name":"Graphic Instant Printing",
    "wof:placetype":"venue"
},
  "geometry": {"coordinates":[-84.511455,39.325578],"type":"Point"}
}