{
  "type": "Feature",
  "properties": {
    "iso:country":"US",
    "sg:address":"34 S Main St",
    "sg:city":"Johnstown",
    "sg:classifiers":[
        {
            "category":"Personal",
            "subcategory":"Beauty Salon",
            "type":"Services"
        }
    ],
    "sg:phone":"+1 740 967 6766",
    "sg:postcode":"43031",
    "sg:province":"OH",
    "sg:tags":[
        "hair",
        "shop",
        "stylist"
    ],
    "wof:name":"Hair After & Tanning Center",
    "wof:placetype":"venue"
},
  "geometry": {"coordinates":[-82.684349,40.153311],"type":"Point"}
}