{
  "type": "Feature",
  "properties": {
    "addr:full": "34 S Main St Johnstown OH 43031",
    "addr:housenumber": "34",
    "addr:postcode": "43031",
    "addr:street": "S Main St",
    "iso:country": "US",
    "sg:address": "34 S Main St",
    "sg:city": "Johnstown",
    "sg:classifiers": [
      {
        "category": "Personal",
        "subcategory": "Beauty Salon",
        "type": "Services"
      }
    ],
    "sg:phone": "+1 740 967 6766",
    "sg:postcode": "43031",
    "sg:province": "OH",
    "sg:tags": [
      "hair",
      "shop",
      "stylist"
    ],
    "wof:name": "Hair After \u0026 Tanning Center",
    "wof:placetype": "venue"
  },
  "geometry": {"coordinates":[-82.684349,40.153311],"type":"Point"}
}
