{
  "type": "Feature",
  "properties": {
    "addr:full": "224 W Franklin St Kenton OH 43326",
    "addr:housenumber": "224",
    "addr:postcode": "43326",
    "addr:street": "W Franklin St",
    "iso:country": "US",
    "sg:address": "224 W Franklin St",
    "sg:city": "Kenton",
    "sg:classifiers": [
      {
        "category": "Personal",
        "subcategory": "Barber",
        "type": "Services"
      }
    ],
    "sg:phone": "+1 419 673 7218",
    "sg:postcode": "43326",
    "sg:province": "OH",
    "wof:name": "Varsity K Barber Shop",
    "wof:placetype": "venue"
  },
  "geometry": {"coordinates":[-83.610309,40.647309],"type":"Point"}
}
