{
  "type": "Feature",
  "properties": {
    "addr:full": "7469 Worthington Galena Rd Columbus OH 43085",
    "addr:housenumber": "7469",
    "addr:postcode": "43085",
    "addr:street": "Worthington Galena Rd",
    "iso:country": "US",
    "sg:address": "7469 Worthington Galena Rd",
    "sg:city": "Columbus",
    "sg:classifiers": [
      {
        "category": "Manufacturing",
        "subcategory": "Toys \u0026 Sporting Goods",
        "type": "Manufacturing \u0026 Wholesale Goods"
      },
      {
        "category": "Shopping",
        "subcategory": "Bicycles \u0026 Sporting Goods",
        "type": "Retail Goods"
      }
    ],
    "sg:phone": "+1 614 841 9390",
    "sg:postcode": "43085",
    "sg:province": "OH",
    "sg:tags": [
      "mfg"
    ],
    "wof:name": "Elephant Balls LTD",
    "wof:placetype": "venue"
  },
  "geometry": {"coordinates":[-82.991281,40.115409],"type":"Point"}
}
