{
  "type": "Feature",
  "properties": {
    "iso:country":"US",
    "sg:address":"2741 Wingate Ave",
    "sg:city":"Akron",
    "sg:classifiers":[
        {
            "category":"Manufacturing",
            "subcategory":"Metals",
            "type":"Manufacturing & Wholesale Goods"
        }
    ],
    "sg:phone":"+1 330 753 7791",
    "sg:postcode":"44314",
    "sg:province":"OH",
    "sg:tags":[
        "stampings",
        "stamping",
        "mfg"
    ],
    "sg:website":"www.hamlinsteel.com",
    "wof:name":"Hamlin Steel Products Inc",
    "wof:placetype":"venue"
},
  "geometry": {"coordinates":[-81.563289,41.02878],"type":"Point"}
}