{
  "type": "Feature",
  "properties": {
    "addr:full": "749 N Perry St Ottawa OH 45875",
    "addr:housenumber": "749",
    "addr:postcode": "45875",
    "addr:street": "N Perry St",
    "iso:country": "US",
    "sg:address": "749 N Perry St",
    "sg:city": "Ottawa",
    "sg:classifiers": [
      {
        "category": "Insurance",
        "subcategory": "Insurance Agent",
        "type": "Services"
      }
    ],
    "sg:phone": "+1 419 523 5527",
    "sg:postcode": "45875",
    "sg:province": "OH",
    "wof:name": "Nationwide",
    "wof:placetype": "venue"
  },
  "geometry": {"coordinates":[-84.047034,41.025886],"type":"Point"}
}
