{
  "type": "Feature",
  "properties": {
    "iso:country":"US",
    "sg:address":"4872 Darrow Rd",
    "sg:city":"Stow",
    "sg:classifiers":[
        {
            "category":"Organizations",
            "subcategory":"Religious Organization",
            "type":"Services"
        }
    ],
    "sg:phone":"+1 330 650 2266",
    "sg:postcode":"44224",
    "sg:province":"OH",
    "sg:tags":[
        "church"
    ],
    "wof:name":"First Baptist Church Of Stow",
    "wof:placetype":"venue"
},
  "geometry": {"coordinates":[-81.440531,41.1961],"type":"Point"}
}