{
  "type": "Feature",
  "properties": {
    "addr:full":"617 Portage Trail Extended W Cuyahoga Falls OH 44223",
    "addr:housenumber":"617",
    "addr:postcode":"44223",
    "addr:street":"Portage Trail Extended W",
    "iso:country":"US",
    "sg:address":"617 Portage Trail Extended W",
    "sg:city":"Cuyahoga Falls",
    "sg:classifiers":[
        {
            "category":"Bars & Pubs",
            "type":"Food & Drink"
        }
    ],
    "sg:phone":"+1 330 920 9007",
    "sg:postcode":"44223",
    "sg:province":"OH",
    "wof:name":"Kelly's Bar & Grill",
    "wof:placetype":"venue"
},
  "geometry": {"coordinates":[-81.522462,41.140966],"type":"Point"}
}