{
  "type": "Feature",
  "properties": {
    "iso:country":"US",
    "sg:address":"12370 Twp Rd 172",
    "sg:city":"Findlay",
    "sg:classifiers":[
        {
            "category":"Wholesale",
            "subcategory":"Metals & Minerals",
            "type":"Manufacturing & Wholesale Goods"
        }
    ],
    "sg:phone":"+1 419 424 8222",
    "sg:postcode":"45840",
    "sg:province":"OH",
    "sg:tags":[
        "pipe"
    ],
    "sg:website":"www.hancor.com",
    "wof:name":"Hancor Inc",
    "wof:placetype":"venue"
},
  "geometry": {"coordinates":[-83.648298,40.983232],"type":"Point"}
}