{
  "type": "Feature",
  "properties": {
    "addr:full": "12370 Twp Rd 172 Findlay OH 45840",
    "addr:housenumber": "172",
    "addr:postcode": "12370;45840",
    "addr:street": "Twp Rd",
    "iso:country": "US",
    "sg:address": "12370 Twp Rd 172",
    "sg:city": "Findlay",
    "sg:classifiers": [
      {
        "category": "Wholesale",
        "subcategory": "Metals \u0026 Minerals",
        "type": "Manufacturing \u0026 Wholesale Goods"
      }
    ],
    "sg:phone": "+1 419 424 8222",
    "sg:postcode": "45840",
    "sg:province": "OH",
    "sg:tags": [
      "pipe"
    ],
    "sg:website": "www.hancor.com",
    "wof:name": "Hancor Inc",
    "wof:placetype": "venue"
  },
  "geometry": {"coordinates":[-83.648298,40.983232],"type":"Point"}
}
