{
  "type": "Feature",
  "properties": {
    "addr:full": "6777 Engle Rd Cleveland OH 44130",
    "addr:housenumber": "6777",
    "addr:postcode": "44130",
    "addr:street": "Engle Rd",
    "iso:country": "US",
    "sg:address": "6777 Engle Rd",
    "sg:city": "Cleveland",
    "sg:classifiers": [
      {
        "category": "Shopping",
        "subcategory": "Computers \u0026 Home Electronics",
        "type": "Retail Goods"
      }
    ],
    "sg:phone": "+1 440 891 9797",
    "sg:postcode": "44130",
    "sg:province": "OH",
    "sg:tags": [
      "player",
      "recorder",
      "video"
    ],
    "wof:name": "RPC Video Inc",
    "wof:placetype": "venue"
  },
  "geometry": {"coordinates":[-81.824428,41.37818],"type":"Point"}
}
