{
  "type": "Feature",
  "properties": {
    "iso:country":"US",
    "sg:address":"2992 Wadsworth Rd",
    "sg:city":"Barberton",
    "sg:classifiers":[
        {
            "category":"Personal",
            "subcategory":"Beauty Salon",
            "type":"Services"
        }
    ],
    "sg:phone":"+1 330 825 3232",
    "sg:postcode":"44203",
    "sg:province":"OH",
    "sg:tags":[
        "shop"
    ],
    "wof:name":"Hair Gallery",
    "wof:placetype":"venue"
},
  "geometry": {"coordinates":[-81.634773,41.050724],"type":"Point"}
}