{
  "type": "Feature",
  "properties": {
    "addr:full":"6065 Dublinshire Dr Dublin OH 43017",
    "addr:housenumber":"6065",
    "addr:postcode":"43017",
    "addr:street":"Dublinshire Dr",
    "iso:country":"US",
    "sg:address":"6065 Dublinshire Dr",
    "sg:city":"Dublin",
    "sg:classifiers":[
        {
            "category":"Professional",
            "type":"Services"
        }
    ],
    "sg:phone":"+1 614 791 8985",
    "sg:postcode":"43017",
    "sg:province":"OH",
    "wof:name":"Adel Abdrabbo",
    "wof:placetype":"venue"
},
  "geometry": {"coordinates":[-83.154973,40.121541],"type":"Point"}
}