{
  "type": "Feature",
  "properties": {
    "iso:country":"US",
    "sg:address":"468 Rader Dr",
    "sg:city":"Vandalia",
    "sg:classifiers":[
        {
            "category":"Organizations",
            "subcategory":"Religious Organization",
            "type":"Services"
        }
    ],
    "sg:phone":"+1 937 898 6940",
    "sg:postcode":"45377",
    "sg:province":"OH",
    "sg:tags":[
        "clergy"
    ],
    "wof:name":"Thomas L Weeks",
    "wof:placetype":"venue"
},
  "geometry": {"coordinates":[-84.191019,39.886267],"type":"Point"}
}