{
  "type": "Feature",
  "properties": {
    "iso:country":"US",
    "sg:address":"5280 State Rte 741",
    "sg:city":"Mason",
    "sg:classifiers":[
        {
            "category":"Retail",
            "subcategory":"Animal Services",
            "type":"Services"
        }
    ],
    "sg:phone":"+1 513 459 2153",
    "sg:postcode":"45040",
    "sg:province":"OH",
    "sg:tags":[
        "pet",
        "boarding",
        "sitting"
    ],
    "wof:name":"It's A Dogs World",
    "wof:placetype":"venue"
},
  "geometry": {"coordinates":[-84.279999,39.359328],"type":"Point"}
}