{
  "type": "Feature",
  "properties": {
    "addr:full": "8733 1st St Mineral City OH 44656",
    "addr:housenumber": "8733",
    "addr:postcode": "44656",
    "addr:street": "1St St",
    "iso:country": "US",
    "sg:address": "8733 1st St",
    "sg:city": "Mineral City",
    "sg:classifiers": [
      {
        "category": "Organizations",
        "subcategory": "Religious Organization",
        "type": "Services"
      }
    ],
    "sg:phone": "+1 330 859 2337",
    "sg:postcode": "44656",
    "sg:province": "OH",
    "sg:tags": [
      "church"
    ],
    "wof:name": "St Paul's Community Church",
    "wof:placetype": "venue"
  },
  "geometry": {"coordinates":[-81.363107,40.606081],"type":"Point"}
}
