{
  "type": "Feature",
  "properties": {
    "addr:full":"12983 Sanders Rd Richwood OH 43344",
    "addr:housenumber":"12983",
    "addr:postcode":"43344",
    "addr:street":"Sanders Rd",
    "iso:country":"US",
    "sg:address":"12983 Sanders Rd",
    "sg:city":"Richwood",
    "sg:phone":"+1 740 943 2503",
    "sg:postcode":"43344",
    "sg:province":"OH",
    "sg:tags":[
        "farm",
        "corn",
        "wheat",
        "soybean"
    ],
    "wof:name":"Gary Baker",
    "wof:placetype":"venue"
},
  "geometry": {"coordinates":[-83.315096,40.494432],"type":"Point"}
}