{
  "type": "Feature",
  "properties": {
    "addr:full": "21007 Southgate Park Blvd Cleveland OH 44137",
    "addr:housenumber": "21007",
    "addr:postcode": "44137",
    "addr:street": "Southgate Park Blvd",
    "iso:country": "US",
    "sg:address": "21007 Southgate Park Blvd",
    "sg:city": "Cleveland",
    "sg:classifiers": [
      {
        "category": "Government",
        "subcategory": "Office",
        "type": "Public Place"
      }
    ],
    "sg:phone": "+1 216 987 7000",
    "sg:postcode": "44137",
    "sg:province": "OH",
    "wof:name": "Cuyahoga County Entitlement",
    "wof:placetype": "venue"
  },
  "geometry": {"coordinates":[-81.529388,41.414163],"type":"Point"}
}
