{
  "type": "Feature",
  "properties": {
    "iso:country":"US",
    "sg:address":"8121 Fox Lake Rd",
    "sg:city":"Sterling",
    "sg:classifiers":[
        {
            "category":"Farming",
            "subcategory":"Dairy Farm",
            "type":"Manufacturing & Wholesale Goods"
        }
    ],
    "sg:phone":"+1 330 669 3715",
    "sg:postcode":"44276",
    "sg:province":"OH",
    "wof:name":"Horst Farms",
    "wof:placetype":"venue"
},
  "geometry": {"coordinates":[-81.828916,40.888425],"type":"Point"}
}