{
  "type": "Feature",
  "properties": {
    "addr:full":"8121 Fox Lake Rd Sterling OH 44276",
    "addr:housenumber":"8121",
    "addr:postcode":"44276",
    "addr:street":"Fox Lake Rd",
    "iso:country":"US",
    "sg:address":"8121 Fox Lake Rd",
    "sg:city":"Sterling",
    "sg:classifiers":[
        {
            "category":"Farming",
            "subcategory":"Dairy Farm",
            "type":"Manufacturing & Wholesale Goods"
        }
    ],
    "sg:phone":"+1 330 669 3715",
    "sg:postcode":"44276",
    "sg:province":"OH",
    "wof:name":"Horst Farms",
    "wof:placetype":"venue"
},
  "geometry": {"coordinates":[-81.82891600000001,40.888425],"type":"Point"}
}