{
  "type": "Feature",
  "properties": {
    "addr:full": "126 Hamilton St Celina OH 45822",
    "addr:housenumber": "126",
    "addr:postcode": "45822",
    "addr:street": "Hamilton St",
    "iso:country": "US",
    "sg:address": "126 Hamilton St",
    "sg:city": "Celina",
    "sg:classifiers": [
      {
        "category": "Building \u0026 Trades",
        "subcategory": "Construction",
        "type": "Services"
      }
    ],
    "sg:phone": "+1 419 586 1739",
    "sg:postcode": "45822",
    "sg:province": "OH",
    "sg:tags": [
      "house"
    ],
    "wof:name": "Dennis Construction",
    "wof:placetype": "venue"
  },
  "geometry": {"coordinates":[-84.550348,40.549153],"type":"Point"}
}
