{
  "type": "Feature",
  "properties": {
    "addr:full":"28172 Chardon Rd Wickliffe OH 44092",
    "addr:housenumber":"28172",
    "addr:postcode":"44092",
    "addr:street":"Chardon Rd",
    "iso:country":"US",
    "sg:address":"28172 Chardon Rd",
    "sg:city":"Wickliffe",
    "sg:classifiers":[
        {
            "category":"Shopping",
            "type":"Retail Goods"
        }
    ],
    "sg:phone":"+1 440 944 5586",
    "sg:postcode":"44092",
    "sg:province":"OH",
    "sg:tags":[
        "merchandise"
    ],
    "wof:name":"Henningers Inc",
    "wof:placetype":"venue"
},
  "geometry": {"coordinates":[-81.480231,41.583501],"type":"Point"}
}