{
  "type": "Feature",
  "properties": {
    "addr:full": "3250 W Market St Akron OH 44333",
    "addr:housenumber": "3250",
    "addr:postcode": "44333",
    "addr:street": "W Market St",
    "iso:country": "US",
    "sg:address": "3250 W Market St",
    "sg:city": "Akron",
    "sg:classifiers": [
      {
        "category": "Real Estate",
        "subcategory": "Real Estate Operator",
        "type": "Services"
      }
    ],
    "sg:phone": "+1 330 384 1555",
    "sg:postcode": "44333",
    "sg:province": "OH",
    "sg:tags": [
      "building",
      "manager",
      "apartment",
      "an"
    ],
    "wof:name": "Humility of Mary Hsing Program",
    "wof:placetype": "venue"
  },
  "geometry": {"coordinates":[-81.619372,41.132607],"type":"Point"}
}
