{
  "type": "Feature",
  "properties": {
    "addr:full":"296 E Stroop Rd Dayton OH 45429",
    "addr:housenumber":"296",
    "addr:postcode":"45429",
    "addr:street":"E Stroop Rd",
    "iso:country":"US",
    "sg:address":"296 E Stroop Rd",
    "sg:city":"Dayton",
    "sg:classifiers":[
        {
            "category":"Shopping",
            "subcategory":"Bicycles & Sporting Goods",
            "type":"Retail Goods"
        }
    ],
    "sg:phone":"+1 937 424 4865",
    "sg:postcode":"45429",
    "sg:province":"OH",
    "wof:name":"Kettering Town & Country Ctr",
    "wof:placetype":"venue"
},
  "geometry": {"coordinates":[-84.16812299999999,39.689498],"type":"Point"}
}