{
  "type": "Feature",
  "properties": {
    "iso:country":"US",
    "sg:address":"2691 Ridge Ave SE",
    "sg:city":"Warren",
    "sg:classifiers":[
        {
            "category":"Restaurant",
            "type":"Food & Drink"
        }
    ],
    "sg:phone":"+1 330 369 4646",
    "sg:postcode":"44484",
    "sg:province":"OH",
    "sg:tags":[
        "eating"
    ],
    "wof:name":"Knowbuddy You Know",
    "wof:placetype":"venue"
},
  "geometry": {"coordinates":[-80.78157,41.217174],"type":"Point"}
}