{
  "type": "Feature",
  "properties": {
    "addr:full": "2691 Ridge Ave SE Warren OH 44484",
    "addr:housenumber": "2691",
    "addr:postcode": "44484",
    "addr:street": "Ridge Ave Se",
    "iso:country": "US",
    "sg:address": "2691 Ridge Ave SE",
    "sg:city": "Warren",
    "sg:classifiers": [
      {
        "category": "Restaurant",
        "type": "Food \u0026 Drink"
      }
    ],
    "sg:phone": "+1 330 369 4646",
    "sg:postcode": "44484",
    "sg:province": "OH",
    "sg:tags": [
      "eating"
    ],
    "wof:name": "Knowbuddy You Know",
    "wof:placetype": "venue"
  },
  "geometry": {"coordinates":[-80.78157,41.217174],"type":"Point"}
}
