{
  "type": "Feature",
  "properties": {
    "iso:country":"US",
    "sg:address":"2740 Carnegie Ave",
    "sg:city":"Cleveland",
    "sg:classifiers":[
        {
            "category":"Health Services",
            "subcategory":"Doctor",
            "type":"Services"
        }
    ],
    "sg:phone":"+1 216 621 6132",
    "sg:postcode":"44115",
    "sg:province":"OH",
    "sg:tags":[
        "ophthalmologist"
    ],
    "sg:website":"www.clevelandeyeclinic.com",
    "wof:name":"Cleveland Eye Clinic",
    "wof:placetype":"venue"
},
  "geometry": {"coordinates":[-81.66947399999999,41.499539],"type":"Point"}
}