{
  "type": "Feature",
  "properties": {
    "addr:full":"6025 Keefus Rd Conneaut OH 44030",
    "addr:housenumber":"6025",
    "addr:postcode":"44030",
    "addr:street":"Keefus Rd",
    "iso:country":"US",
    "sg:address":"6025 Keefus Rd",
    "sg:city":"Conneaut",
    "sg:classifiers":[
        {
            "category":"Building & Trades",
            "subcategory":"Construction",
            "type":"Services"
        }
    ],
    "sg:phone":"+1 440 599 7600",
    "sg:postcode":"44030",
    "sg:province":"OH",
    "sg:tags":[
        "house"
    ],
    "wof:name":"Sedmak Construction",
    "wof:placetype":"venue"
},
  "geometry": {"coordinates":[-80.604316,41.891355],"type":"Point"}
}