{
  "type": "Feature",
  "properties": {
    "iso:country":"US",
    "sg:address":"1621 Dorr St",
    "sg:city":"Toledo",
    "sg:classifiers":[
        {
            "category":"Organizations",
            "subcategory":"Religious Organization",
            "type":"Services"
        }
    ],
    "sg:phone":"+1 419 242 5684",
    "sg:postcode":"43607",
    "sg:province":"OH",
    "sg:tags":[
        "church"
    ],
    "wof:name":"Church El-Bethel",
    "wof:placetype":"venue"
},
  "geometry": {"coordinates":[-83.583292,41.652791],"type":"Point"}
}