{
  "type": "Feature",
  "properties": {
    "addr:full": "1094 Wellington Blvd Columbus OH 43219",
    "addr:housenumber": "1094",
    "addr:postcode": "43219",
    "addr:street": "Wellington Blvd",
    "iso:country": "US",
    "sg:address": "1094 Wellington Blvd",
    "sg:city": "Columbus",
    "sg:classifiers": [
      {
        "category": "Shopping",
        "subcategory": "Used Merchandise",
        "type": "Retail Goods"
      }
    ],
    "sg:phone": "+1 614 252 4781",
    "sg:postcode": "43219",
    "sg:province": "OH",
    "wof:name": "Michelles Antiques",
    "wof:placetype": "venue"
  },
  "geometry": {"coordinates":[-82.94456,39.99009],"type":"Point"}
}
