{
  "type": "Feature",
  "properties": {
    "addr:full": "1517 Henson Rd Bethel OH 45106",
    "addr:housenumber": "1517",
    "addr:postcode": "45106",
    "addr:street": "Henson Rd",
    "iso:country": "US",
    "sg:address": "1517 Henson Rd",
    "sg:city": "Bethel",
    "sg:classifiers": [
      {
        "category": "Building \u0026 Trades",
        "subcategory": "Construction",
        "type": "Services"
      }
    ],
    "sg:phone": "+1 513 876 3984",
    "sg:postcode": "45106",
    "sg:province": "OH",
    "sg:tags": [
      "general"
    ],
    "wof:name": "Henson Construction",
    "wof:placetype": "venue"
  },
  "geometry": {"coordinates":[-84.079463,38.880575],"type":"Point"}
}
