{
  "type": "Feature",
  "properties": {
    "addr:full":"7169 Erie Dr Mentor OH 44060",
    "addr:housenumber":"7169",
    "addr:postcode":"44060",
    "addr:street":"Erie Dr",
    "iso:country":"US",
    "sg:address":"7169 Erie Dr",
    "sg:city":"Mentor",
    "sg:classifiers":[
        {
            "category":"Restaurant",
            "type":"Food & Drink"
        }
    ],
    "sg:phone":"+1 440 951 0846",
    "sg:postcode":"44060",
    "sg:province":"OH",
    "sg:tags":[
        "eating"
    ],
    "wof:name":"Mad Chef Enterprises Inc",
    "wof:placetype":"venue"
},
  "geometry": {"coordinates":[-81.380707,41.669466],"type":"Point"}
}