{
  "type": "Feature",
  "properties": {
    "addr:full":"14409 Kneisel Rd Vermilion OH 44089",
    "addr:housenumber":"14409",
    "addr:postcode":"44089",
    "addr:street":"Kneisel Rd",
    "iso:country":"US",
    "sg:address":"14409 Kneisel Rd",
    "sg:city":"Vermilion",
    "sg:classifiers":[
        {
            "category":"Wholesale",
            "subcategory":"Farm Supplies",
            "type":"Manufacturing & Wholesale Goods"
        }
    ],
    "sg:phone":"+1 440 967 3985",
    "sg:postcode":"44089",
    "sg:province":"OH",
    "sg:tags":[
        "bean",
        "beef",
        "cattle"
    ],
    "wof:name":"Vermilion Elevator",
    "wof:placetype":"venue"
},
  "geometry": {"coordinates":[-82.377546,41.401135],"type":"Point"}
}