{
  "type": "Feature",
  "properties": {
    "iso:country":"US",
    "sg:address":"175 S 3rd St",
    "sg:city":"Columbus",
    "sg:classifiers":[
        {
            "category":"Professional",
            "type":"Services"
        },
        {
            "category":"Professional",
            "subcategory":"Lawyer & Legal Services",
            "type":"Services"
        }
    ],
    "sg:phone":"+1 614 228 7272",
    "sg:postcode":"43215",
    "sg:province":"OH",
    "sg:tags":[
        "attorney",
        "establishment"
    ],
    "wof:name":"Weltman Weinberg & Reis Co Lpa",
    "wof:placetype":"venue"
},
  "geometry": {"coordinates":[-82.997173,39.958104],"type":"Point"}
}