{
  "type": "Feature",
  "properties": {
    "addr:full": "13065 Mayfield Rd Chardon OH 44024",
    "addr:housenumber": "13065",
    "addr:postcode": "44024",
    "addr:street": "Mayfield Rd",
    "iso:country": "US",
    "sg:address": "13065 Mayfield Rd",
    "sg:city": "Chardon",
    "sg:classifiers": [
      {
        "category": "Wholesale",
        "subcategory": "Furniture",
        "type": "Manufacturing \u0026 Wholesale Goods"
      }
    ],
    "sg:phone": "+1 440 285 2509",
    "sg:postcode": "44024",
    "sg:province": "OH",
    "wof:name": "Alpine Structures",
    "wof:placetype": "venue"
  },
  "geometry": {"coordinates":[-81.169196,41.533545],"type":"Point"}
}
