{
  "type": "Feature",
  "properties": {
    "addr:full":"909 W Smith Rd Medina OH 44256",
    "addr:housenumber":"909",
    "addr:postcode":"44256",
    "addr:street":"W Smith Rd",
    "iso:country":"US",
    "sg:address":"909 W Smith Rd",
    "sg:city":"Medina",
    "sg:classifiers":[
        {
            "category":"Banks & Credit Unions",
            "subcategory":"Financial Services",
            "type":"Services"
        }
    ],
    "sg:phone":"+1 330 722 8999",
    "sg:postcode":"44256",
    "sg:province":"OH",
    "sg:tags":[
        "investor"
    ],
    "wof:name":"Wall Street Investor Relations",
    "wof:placetype":"venue"
},
  "geometry": {"coordinates":[-81.88847800000001,41.136209],"type":"Point"}
}