{
  "type": "Feature",
  "properties": {
    "addr:full": "10558 Taconic Ter Cincinnati OH 45215",
    "addr:postcode": "10558;45215",
    "addr:street": "Taconic Ter",
    "iso:country": "US",
    "sg:address": "10558 Taconic Ter",
    "sg:city": "Cincinnati",
    "sg:classifiers": [
      {
        "category": "Manufacturing",
        "subcategory": "Signs",
        "type": "Manufacturing \u0026 Wholesale Goods"
      }
    ],
    "sg:phone": "+1 513 771 8848",
    "sg:postcode": "45215",
    "sg:province": "OH",
    "sg:tags": [
      "manufacture",
      "interior",
      "graphics"
    ],
    "wof:name": "Plastigraphics Inc",
    "wof:placetype": "venue"
  },
  "geometry": {"coordinates":[-84.459962,39.25778],"type":"Point"}
}
