{
  "type": "Feature",
  "properties": {
    "addr:full":"5440 Muskopf Rd Fairfield OH 45014",
    "addr:housenumber":"5440",
    "addr:postcode":"45014",
    "addr:street":"Muskopf Rd",
    "iso:country":"US",
    "sg:address":"5440 Muskopf Rd",
    "sg:city":"Fairfield",
    "sg:classifiers":[
        {
            "category":"Farming",
            "subcategory":"Farm",
            "type":"Manufacturing & Wholesale Goods"
        }
    ],
    "sg:phone":"+1 513 829 6241",
    "sg:postcode":"45014",
    "sg:province":"OH",
    "sg:tags":[
        "crop",
        "general"
    ],
    "wof:name":"Eaton Farm LLC",
    "wof:placetype":"venue"
},
  "geometry": {"coordinates":[-84.577628,39.331853],"type":"Point"}
}