{
  "type": "Feature",
  "properties": {
    "iso:country":"US",
    "sg:address":"6025 Avery Rd",
    "sg:city":"Dublin",
    "sg:classifiers":[
        {
            "category":"Professional",
            "subcategory":"Accounting & Tax Preparation",
            "type":"Services"
        }
    ],
    "sg:phone":"+1 614 793 8297",
    "sg:postcode":"43016",
    "sg:province":"OH",
    "sg:tags":[
        "auditing",
        "bookkeeping"
    ],
    "wof:name":"Frazier & Co",
    "wof:placetype":"venue"
},
  "geometry": {"coordinates":[-83.15839699999999,40.091037],"type":"Point"}
}