{
  "type": "Feature",
  "properties": {
    "addr:full":"9891 Sugar St Germantown OH 45327",
    "addr:housenumber":"9891",
    "addr:postcode":"45327",
    "addr:street":"Sugar St",
    "iso:country":"US",
    "sg:address":"9891 Sugar St",
    "sg:city":"Germantown",
    "sg:classifiers":[
        {
            "category":"Building & Trades",
            "subcategory":"Construction",
            "type":"Services"
        }
    ],
    "sg:phone":"+1 937 855 6362",
    "sg:postcode":"45327",
    "sg:province":"OH",
    "sg:tags":[
        "glazier"
    ],
    "wof:name":"Div 8",
    "wof:placetype":"venue"
},
  "geometry": {"coordinates":[-84.36560299999999,39.613037],"type":"Point"}
}