{
  "type": "Feature",
  "properties": {
    "iso:country":"US",
    "sg:address":"34800 Dorchester Rd",
    "sg:city":"Gates Mills",
    "sg:classifiers":[
        {
            "category":"Real Estate",
            "subcategory":"Real Estate Agent",
            "type":"Services"
        }
    ],
    "sg:phone":"+1 440 684 0944",
    "sg:postcode":"44040",
    "sg:province":"OH",
    "wof:name":"Hersch Linda & Assoc",
    "wof:placetype":"venue"
},
  "geometry": {"coordinates":[-81.4311,41.506325],"type":"Point"}
}