{
  "type": "Feature",
  "properties": {
    "iso:country":"US",
    "sg:address":"2795 Eldean Rd",
    "sg:city":"Troy",
    "sg:classifiers":[
        {
            "category":"Real Estate",
            "subcategory":"Real Estate Operator",
            "type":"Services"
        }
    ],
    "sg:phone":"+1 937 339 8083",
    "sg:postcode":"45373",
    "sg:province":"OH",
    "sg:tags":[
        "farm",
        "property",
        "crop",
        "lessor",
        "general"
    ],
    "wof:name":"Carl Holfinger",
    "wof:placetype":"venue"
},
  "geometry": {"coordinates":[-84.257054,40.076101],"type":"Point"}
}