{
  "type": "Feature",
  "properties": {
    "addr:full":"300 Locust St Akron OH 44302",
    "addr:housenumber":"300",
    "addr:postcode":"44302",
    "addr:street":"Locust St",
    "iso:country":"US",
    "sg:address":"300 Locust St",
    "sg:city":"Akron",
    "sg:classifiers":[
        {
            "category":"Health Services",
            "subcategory":"Doctor",
            "type":"Services"
        }
    ],
    "sg:phone":"+1 330 543 8530",
    "sg:postcode":"44302",
    "sg:province":"OH",
    "sg:tags":[
        "physician",
        "surgeon"
    ],
    "wof:name":"Locust Pediatric Care Group",
    "wof:placetype":"venue"
},
  "geometry": {"coordinates":[-81.525549,41.080583],"type":"Point"}
}