{
  "type": "Feature",
  "properties": {
    "iso:country":"US",
    "sg:address":"2017 S Baney Rd",
    "sg:city":"Ashland",
    "sg:classifiers":[
        {
            "category":"Professional",
            "subcategory":"Management & Consulting",
            "type":"Services"
        }
    ],
    "sg:phone":"+1 419 281 2554",
    "sg:postcode":"44805",
    "sg:province":"OH",
    "wof:name":"Farmers State Bank",
    "wof:placetype":"venue"
},
  "geometry": {"coordinates":[-82.349056,40.844979],"type":"Point"}
}