{
  "type": "Feature",
  "properties": {
    "iso:country":"US",
    "sg:address":"389 John Scott Hwy",
    "sg:city":"Steubenville",
    "sg:classifiers":[
        {
            "category":"Restaurant",
            "type":"Food & Drink"
        }
    ],
    "sg:menulink":"http://www.allmenus.com/oh/steubenville/88801-applebees/menu/",
    "sg:phone":"+1 740 264 9448",
    "sg:postcode":"43952",
    "sg:province":"OH",
    "sg:tags":[
        "burger",
        "american",
        "sandwich",
        "soup"
    ],
    "wof:name":"Applebee's",
    "wof:placetype":"venue"
},
  "geometry": {"coordinates":[-80.656025,40.378806],"type":"Point"}
}