{
  "type": "Feature",
  "properties": {
    "addr:full": "8837 Whitney Dr Lewis Center OH 43035",
    "addr:housenumber": "8837",
    "addr:postcode": "43035",
    "addr:street": "Whitney Dr",
    "iso:country": "US",
    "sg:address": "8837 Whitney Dr",
    "sg:city": "Lewis Center",
    "sg:classifiers": [
      {
        "category": "Real Estate",
        "subcategory": "Real Estate Agent",
        "type": "Services"
      }
    ],
    "sg:phone": "+1 740 549 2707",
    "sg:postcode": "43035",
    "sg:province": "OH",
    "sg:tags": [
      "appraiser"
    ],
    "wof:name": "Home Team Appraisal Services",
    "wof:placetype": "venue"
  },
  "geometry": {"coordinates":[-83.00853,40.158556],"type":"Point"}
}
