{
  "type": "Feature",
  "properties": {
    "iso:country":"US",
    "sg:address":"8050 W Chester Rd",
    "sg:city":"West Chester",
    "sg:classifiers":[
        {
            "category":"Health Services",
            "subcategory":"Health Practitioner",
            "type":"Services"
        }
    ],
    "sg:phone":"+1 513 860 2313",
    "sg:postcode":"45069",
    "sg:province":"OH",
    "sg:tags":[
        "psychologist"
    ],
    "wof:name":"West Chester Psychological",
    "wof:placetype":"venue"
},
  "geometry": {"coordinates":[-84.361062,39.317789],"type":"Point"}
}