{
  "type": "Feature",
  "properties": {
    "addr:full":"4700 Alkire Rd Grove City OH 43123",
    "addr:housenumber":"4700",
    "addr:postcode":"43123",
    "addr:street":"Alkire Rd",
    "iso:country":"US",
    "sg:address":"4700 Alkire Rd",
    "sg:city":"Grove City",
    "sg:classifiers":[
        {
            "category":"Manufacturing",
            "subcategory":"Paper Products",
            "type":"Manufacturing & Wholesale Goods"
        }
    ],
    "sg:phone":"+1 614 870 2000",
    "sg:postcode":"43123",
    "sg:province":"OH",
    "sg:tags":[
        "corrugated",
        "solid",
        "fiber",
        "box"
    ],
    "sg:website":"www.americancorrugated.com",
    "wof:name":"American Corrugated Products",
    "wof:placetype":"venue"
},
  "geometry": {"coordinates":[-83.12969,39.910759],"type":"Point"}
}