{
  "type": "Feature",
  "properties": {
    "addr:full":"4538 Indianola Ave Columbus OH 43214",
    "addr:housenumber":"4538",
    "addr:postcode":"43214",
    "addr:street":"Indianola Ave",
    "iso:country":"US",
    "sg:address":"4538 Indianola Ave",
    "sg:city":"Columbus",
    "sg:classifiers":[
        {
            "category":"Wholesale",
            "subcategory":"Farm Supplies",
            "type":"Manufacturing & Wholesale Goods"
        }
    ],
    "sg:phone":"+1 614 263 2440",
    "sg:postcode":"43214",
    "sg:province":"OH",
    "wof:name":"Magic Home Gardens",
    "wof:placetype":"venue"
},
  "geometry": {"coordinates":[-83.00054299999999,40.056733],"type":"Point"}
}