{
  "type": "Feature",
  "properties": {
    "addr:full": "371 Ceader Hill Dr Waverly OH 45616",
    "addr:housenumber": "371",
    "addr:postcode": "45616",
    "addr:street": "Ceader Hill Dr",
    "iso:country": "US",
    "sg:address": "371 Ceader Hill Dr",
    "sg:city": "Waverly",
    "sg:classifiers": [
      {
        "category": "Building \u0026 Trades",
        "subcategory": "Plumbing",
        "type": "Services"
      }
    ],
    "sg:phone": "+1 740 947 4463",
    "sg:postcode": "45616",
    "sg:province": "OH",
    "sg:tags": [
      "heating",
      "contractor"
    ],
    "wof:name": "Kelly's Heating \u0026 Air",
    "wof:placetype": "venue"
  },
  "geometry": {"coordinates":[-83.393902,38.820354],"type":"Point"}
}
