{
  "type": "Feature",
  "properties": {
    "addr:full": "1900 Englewood Ave Akron OH 44312",
    "addr:housenumber": "1900",
    "addr:postcode": "44312",
    "addr:street": "Englewood Ave",
    "iso:country": "US",
    "sg:address": "1900 Englewood Ave",
    "sg:city": "Akron",
    "sg:classifiers": [
      {
        "category": "Manufacturing",
        "subcategory": "Metals",
        "type": "Manufacturing \u0026 Wholesale Goods"
      }
    ],
    "sg:phone": "+1 330 798 9091",
    "sg:postcode": "44312",
    "sg:province": "OH",
    "sg:tags": [
      "brass",
      "foundry",
      "aluminum",
      "bronze",
      "mfg"
    ],
    "sg:website": "www.rotocastmold.com",
    "wof:name": "Rotocast Technologies Inc",
    "wof:placetype": "venue"
  },
  "geometry": {"coordinates":[-81.457211,41.060448],"type":"Point"}
}
