{
  "type": "Feature",
  "properties": {
    "addr:full":"1474 E 133rd St Cleveland OH 44112",
    "addr:housenumber":"1474",
    "addr:postcode":"44112",
    "addr:street":"E 133Rd St",
    "iso:country":"US",
    "sg:address":"1474 E 133rd St",
    "sg:city":"Cleveland",
    "sg:classifiers":[
        {
            "category":"Personal",
            "subcategory":"Beauty Salon",
            "type":"Services"
        }
    ],
    "sg:phone":"+1 216 249 1443",
    "sg:postcode":"44112",
    "sg:province":"OH",
    "sg:tags":[
        "manicuring"
    ],
    "wof:name":"Lila's Nails",
    "wof:placetype":"venue"
},
  "geometry": {"coordinates":[-81.59031899999999,41.539744],"type":"Point"}
}