{
  "type": "Feature",
  "properties": {
    "iso:country":"US",
    "sg:address":"6615 Center Rd",
    "sg:city":"Valley City",
    "sg:classifiers":[
        {
            "category":"Government",
            "subcategory":"Office",
            "type":"Public Place"
        }
    ],
    "sg:phone":"+1 330 483 5919",
    "sg:postcode":"44280",
    "sg:province":"OH",
    "sg:tags":[
        "village"
    ],
    "wof:name":"Liverpool Twp Depot Meeting",
    "wof:placetype":"venue"
},
  "geometry": {"coordinates":[-81.92433699999999,41.237653],"type":"Point"}
}