{
  "type": "Feature",
  "properties": {
    "addr:full": "6615 Center Rd Valley City OH 44280",
    "addr:housenumber": "6615",
    "addr:postcode": "44280",
    "addr:street": "Center Rd",
    "iso:country": "US",
    "sg:address": "6615 Center Rd",
    "sg:city": "Valley City",
    "sg:classifiers": [
      {
        "category": "Government",
        "subcategory": "Office",
        "type": "Public Place"
      }
    ],
    "sg:phone": "+1 330 483 5919",
    "sg:postcode": "44280",
    "sg:province": "OH",
    "sg:tags": [
      "village"
    ],
    "wof:name": "Liverpool Twp Depot Meeting",
    "wof:placetype": "venue"
  },
  "geometry": {"coordinates":[-81.924337,41.237653],"type":"Point"}
}
