{
  "type": "Feature",
  "properties": {
    "addr:full": "15471 Riddle Rd Chagrin Falls OH 44022",
    "addr:housenumber": "15471",
    "addr:postcode": "44022",
    "addr:street": "Riddle Rd",
    "iso:country": "US",
    "sg:address": "15471 Riddle Rd",
    "sg:city": "Chagrin Falls",
    "sg:classifiers": [
      {
        "category": "Professional",
        "subcategory": "Management \u0026 Consulting",
        "type": "Services"
      }
    ],
    "sg:phone": "+1 440 247 8315",
    "sg:postcode": "44022",
    "sg:province": "OH",
    "sg:tags": [
      "development",
      "technology",
      "advanced",
      "software"
    ],
    "wof:name": "Vertech",
    "wof:placetype": "venue"
  },
  "geometry": {"coordinates":[-81.365328,41.446348],"type":"Point"}
}
