{
  "type": "Feature",
  "properties": {
    "iso:country":"US",
    "sg:address":"15471 Riddle Rd",
    "sg:city":"Chagrin Falls",
    "sg:classifiers":[
        {
            "category":"Professional",
            "subcategory":"Management & Consulting",
            "type":"Services"
        }
    ],
    "sg:phone":"+1 440 247 8315",
    "sg:postcode":"44022",
    "sg:province":"OH",
    "sg:tags":[
        "development",
        "technology",
        "advanced",
        "software"
    ],
    "wof:name":"Vertech",
    "wof:placetype":"venue"
},
  "geometry": {"coordinates":[-81.36532800000001,41.446348],"type":"Point"}
}