{
  "type": "Feature",
  "properties": {
    "iso:country":"US",
    "sg:address":"516 Cliffwood Ave",
    "sg:city":"Zanesville",
    "sg:classifiers":[
        {
            "category":"Organizations",
            "subcategory":"Religious Organization",
            "type":"Services"
        }
    ],
    "sg:phone":"+1 740 454 8205",
    "sg:postcode":"43701",
    "sg:province":"OH",
    "sg:tags":[
        "church"
    ],
    "wof:name":"Church Of God & Saints-Christ",
    "wof:placetype":"venue"
},
  "geometry": {"coordinates":[-82.013188,39.931969],"type":"Point"}
}