{
  "type": "Feature",
  "properties": {
    "addr:full": "516 Cliffwood Ave Zanesville OH 43701",
    "addr:housenumber": "516",
    "addr:postcode": "43701",
    "addr:street": "Cliffwood Ave",
    "iso:country": "US",
    "sg:address": "516 Cliffwood Ave",
    "sg:city": "Zanesville",
    "sg:classifiers": [
      {
        "category": "Organizations",
        "subcategory": "Religious Organization",
        "type": "Services"
      }
    ],
    "sg:phone": "+1 740 454 8205",
    "sg:postcode": "43701",
    "sg:province": "OH",
    "sg:tags": [
      "church"
    ],
    "wof:name": "Church Of God \u0026 Saints-Christ",
    "wof:placetype": "venue"
  },
  "geometry": {"coordinates":[-82.013188,39.931969],"type":"Point"}
}
