{
  "type": "Feature",
  "properties": {
    "addr:full":"2108 Widding Rd Grove City OH 43123",
    "addr:housenumber":"2108",
    "addr:postcode":"43123",
    "addr:street":"Widding Rd",
    "iso:country":"US",
    "sg:address":"2108 Widding Rd",
    "sg:city":"Grove City",
    "sg:classifiers":[
        {
            "category":"Manufacturing",
            "subcategory":"Retail Goods",
            "type":"Manufacturing & Wholesale Goods"
        }
    ],
    "sg:phone":"+1 614 277 9325",
    "sg:postcode":"43123",
    "sg:province":"OH",
    "sg:tags":[
        "product",
        "mfg"
    ],
    "wof:name":"Pf Designs",
    "wof:placetype":"venue"
},
  "geometry": {"coordinates":[-83.08872,39.9115],"type":"Point"}
}