{
  "type": "Feature",
  "properties": {
    "iso:country":"US",
    "sg:address":"247 S Burnett Rd",
    "sg:city":"Springfield",
    "sg:classifiers":[
        {
            "category":"Health Services",
            "subcategory":"Doctor",
            "type":"Services"
        }
    ],
    "sg:phone":"+1 937 328 8921",
    "sg:postcode":"45505",
    "sg:province":"OH",
    "sg:tags":[
        "clinic"
    ],
    "wof:name":"Clark County Dialysis Facility",
    "wof:placetype":"venue"
},
  "geometry": {"coordinates":[-83.77,39.919698],"type":"Point"}
}