{
  "type": "Feature",
  "properties": {
    "iso:country":"US",
    "sg:address":"3360 Patriot Blvd",
    "sg:city":"Columbus",
    "sg:classifiers":[
        {
            "category":"Organizations",
            "subcategory":"Religious Organization",
            "type":"Services"
        }
    ],
    "sg:phone":"+1 614 475 6444",
    "sg:postcode":"43219",
    "sg:province":"OH",
    "sg:tags":[
        "church"
    ],
    "wof:name":"Mifflin Church Of The Nazarene",
    "wof:placetype":"venue"
},
  "geometry": {"coordinates":[-82.926947,40.042686],"type":"Point"}
}