{
  "type": "Feature",
  "properties": {
    "addr:full":"28325 Clark Rd Wellington OH 44090",
    "addr:housenumber":"28325",
    "addr:postcode":"44090",
    "addr:street":"Clark Rd",
    "iso:country":"US",
    "sg:address":"28325 Clark Rd",
    "sg:city":"Wellington",
    "sg:phone":"+1 440 647 3306",
    "sg:postcode":"44090",
    "sg:province":"OH",
    "sg:tags":[
        "farm",
        "soybean"
    ],
    "wof:name":"Moskal Farm",
    "wof:placetype":"venue"
},
  "geometry": {"coordinates":[-82.240185,41.079331],"type":"Point"}
}