{
  "type": "Feature",
  "properties": {
    "addr:full":"4140 N Conant Rd Delphos OH 45807",
    "addr:housenumber":"4140",
    "addr:postcode":"45807",
    "addr:street":"N Conant Rd",
    "iso:country":"US",
    "sg:address":"4140 N Conant Rd",
    "sg:city":"Delphos",
    "sg:phone":"+1 419 339 1600",
    "sg:postcode":"45807",
    "sg:province":"OH",
    "sg:tags":[
        "farm",
        "corn",
        "soybean"
    ],
    "wof:name":"Michael Dickrede",
    "wof:placetype":"venue"
},
  "geometry": {"coordinates":[-84.28079700000001,40.796683],"type":"Point"}
}