{
  "type": "Feature",
  "properties": {
    "addr:full": "2830 Fisher Rd Columbus OH 43204",
    "addr:housenumber": "2830",
    "addr:postcode": "43204",
    "addr:street": "Fisher Rd",
    "iso:country": "US",
    "sg:address": "2830 Fisher Rd",
    "sg:city": "Columbus",
    "sg:classifiers": [
      {
        "category": "Professional",
        "subcategory": "Research",
        "type": "Services"
      }
    ],
    "sg:phone": "+1 614 278 9445",
    "sg:postcode": "43204",
    "sg:province": "OH",
    "sg:tags": [
      "consultant",
      "recycling"
    ],
    "wof:name": "Keep Franklin County Beautiful",
    "wof:placetype": "venue"
  },
  "geometry": {"coordinates":[-83.079242,39.972379],"type":"Point"}
}
