{
  "type": "Feature",
  "properties": {
    "iso:country":"US",
    "sg:address":"116 Windward Dr",
    "sg:city":"Pataskala",
    "sg:classifiers":[
        {
            "category":"Professional",
            "type":"Services"
        }
    ],
    "sg:phone":"+1 740 964 0768",
    "sg:postcode":"43062",
    "sg:province":"OH",
    "wof:name":"J Nelson",
    "wof:placetype":"venue"
},
  "geometry": {"coordinates":[-82.752436,40.001666],"type":"Point"}
}