{
  "type": "Feature",
  "properties": {
    "iso:country":"US",
    "sg:address":"100 Broadway St",
    "sg:city":"Cincinnati",
    "sg:classifiers":[
        {
            "category":"Recreation",
            "subcategory":"Amusement Park",
            "type":"Entertainment"
        }
    ],
    "sg:phone":"+1 513 421 3222",
    "sg:postcode":"45202",
    "sg:province":"OH",
    "wof:name":"Cincinnati Swarm",
    "wof:placetype":"venue"
},
  "geometry": {"coordinates":[-84.50501199999999,39.096725],"type":"Point"}
}