{
  "type": "Feature",
  "properties": {
    "iso:country":"US",
    "sg:address":"7000 State Rte 104",
    "sg:city":"Lockbourne",
    "sg:classifiers":[
        {
            "category":"Manufacturing",
            "subcategory":"Chemicals & Compounds",
            "type":"Manufacturing & Wholesale Goods"
        }
    ],
    "sg:phone":"+1 614 645 3152",
    "sg:postcode":"43137",
    "sg:province":"OH",
    "sg:tags":[
        "compost"
    ],
    "wof:name":"Compost Facility",
    "wof:placetype":"venue"
},
  "geometry": {"coordinates":[-83.032735,39.813804],"type":"Point"}
}