{
  "type": "Feature",
  "properties": {
    "addr:full": "7000 State Rte 104 Lockbourne OH 43137",
    "addr:housenumber": "7000",
    "addr:postcode": "43137",
    "addr:street": "State Rte 104",
    "iso:country": "US",
    "sg:address": "7000 State Rte 104",
    "sg:city": "Lockbourne",
    "sg:classifiers": [
      {
        "category": "Manufacturing",
        "subcategory": "Chemicals \u0026 Compounds",
        "type": "Manufacturing \u0026 Wholesale Goods"
      }
    ],
    "sg:phone": "+1 614 645 3152",
    "sg:postcode": "43137",
    "sg:province": "OH",
    "sg:tags": [
      "compost"
    ],
    "wof:name": "Compost Facility",
    "wof:placetype": "venue"
  },
  "geometry": {"coordinates":[-83.032735,39.813804],"type":"Point"}
}
