{
  "type": "Feature",
  "properties": {
    "iso:country":"US",
    "sg:address":"2021 Adams St",
    "sg:city":"Toledo",
    "sg:classifiers":[
        {
            "category":"Shopping",
            "subcategory":"Hobbies, Toys, & Games",
            "type":"Retail Goods"
        }
    ],
    "sg:phone":"+1 419 242 6456",
    "sg:postcode":"43604",
    "sg:province":"OH",
    "sg:tags":[
        "craft"
    ],
    "wof:name":"Letter Craft",
    "wof:placetype":"venue"
},
  "geometry": {"coordinates":[-83.54773,41.659243],"type":"Point"}
}