{
  "type": "Feature",
  "properties": {
    "addr:full": "2021 Adams St Toledo OH 43604",
    "addr:housenumber": "2021",
    "addr:postcode": "43604",
    "addr:street": "Adams St",
    "iso:country": "US",
    "sg:address": "2021 Adams St",
    "sg:city": "Toledo",
    "sg:classifiers": [
      {
        "category": "Shopping",
        "subcategory": "Hobbies, Toys, \u0026 Games",
        "type": "Retail Goods"
      }
    ],
    "sg:phone": "+1 419 242 6456",
    "sg:postcode": "43604",
    "sg:province": "OH",
    "sg:tags": [
      "craft"
    ],
    "wof:name": "Letter Craft",
    "wof:placetype": "venue"
  },
  "geometry": {"coordinates":[-83.54773,41.659243],"type":"Point"}
}
