{
  "type": "Feature",
  "properties": {
    "addr:full": "1009 Steubenville Ave Cambridge OH 43725",
    "addr:housenumber": "1009",
    "addr:postcode": "43725",
    "addr:street": "Steubenville Ave",
    "iso:country": "US",
    "sg:address": "1009 Steubenville Ave",
    "sg:city": "Cambridge",
    "sg:classifiers": [
      {
        "category": "Retail",
        "subcategory": "Funeral Services",
        "type": "Services"
      }
    ],
    "sg:phone": "+1 740 432 5631",
    "sg:postcode": "43725",
    "sg:province": "OH",
    "sg:tags": [
      "director"
    ],
    "wof:name": "Scott Funeral Home Inc",
    "wof:placetype": "venue"
  },
  "geometry": {"coordinates":[-81.586374,40.026099],"type":"Point"}
}
