{
  "type": "Feature",
  "properties": {
    "addr:full":"1435 Warren Rd Lakewood OH 44107",
    "addr:housenumber":"1435",
    "addr:postcode":"44107",
    "addr:street":"Warren Rd",
    "iso:country":"US",
    "sg:address":"1435 Warren Rd",
    "sg:city":"Lakewood",
    "sg:classifiers":[
        {
            "category":"Banks & Credit Unions",
            "subcategory":"Bank",
            "type":"Services"
        }
    ],
    "sg:phone":"+1 216 226 0850",
    "sg:postcode":"44107",
    "sg:province":"OH",
    "sg:tags":[
        "national",
        "commercial"
    ],
    "wof:name":"Keybank National Association",
    "wof:placetype":"venue"
},
  "geometry": {"coordinates":[-81.79948,41.484843],"type":"Point"}
}