{
  "type": "Feature",
  "properties": {
    "addr:full": "9 Mount Vernon Ave Mt Vernon OH 43050",
    "addr:housenumber": "9",
    "addr:postcode": "43050",
    "addr:street": "Mount Vernon Ave",
    "iso:country": "US",
    "sg:address": "9 Mount Vernon Ave",
    "sg:city": "Mt Vernon",
    "sg:classifiers": [
      {
        "category": "Retail",
        "subcategory": "Laundry \u0026 Dry Cleaning",
        "type": "Services"
      }
    ],
    "sg:phone": "+1 740 397 4778",
    "sg:postcode": "43050",
    "sg:province": "OH",
    "sg:tags": [
      "cleaners",
      "rug",
      "carpet"
    ],
    "wof:name": "Premier Dry Carpet Cleaning",
    "wof:placetype": "venue"
  },
  "geometry": {"coordinates":[-82.484841,40.384807],"type":"Point"}
}
