{
  "type": "Feature",
  "properties": {
    "addr:full": "5383 Massillon Rd Canton OH 44720",
    "addr:housenumber": "5383",
    "addr:postcode": "44720",
    "addr:street": "Massillon Rd",
    "iso:country": "US",
    "sg:address": "5383 Massillon Rd",
    "sg:city": "Canton",
    "sg:classifiers": [
      {
        "category": "Government",
        "subcategory": "Office",
        "type": "Public Place"
      }
    ],
    "sg:phone": "+1 330 896 6924",
    "sg:postcode": "44720",
    "sg:province": "OH",
    "sg:tags": [
      "village"
    ],
    "wof:name": "Green City Stormwater Div",
    "wof:placetype": "venue"
  },
  "geometry": {"coordinates":[-81.462691,40.919829],"type":"Point"}
}
