{
  "type": "Feature",
  "properties": {
    "iso:country":"US",
    "sg:address":"716 W Main Cross St",
    "sg:city":"Findlay",
    "sg:classifiers":[
        {
            "category":"Retail",
            "subcategory":"Repair Shop",
            "type":"Services"
        }
    ],
    "sg:phone":"+1 419 422 4903",
    "sg:postcode":"45840",
    "sg:province":"OH",
    "sg:tags":[
        "refinishing",
        "furniture"
    ],
    "wof:name":"Mathias Cabinet Shop",
    "wof:placetype":"venue"
},
  "geometry": {"coordinates":[-83.66117199999999,41.040212],"type":"Point"}
}