{
  "type": "Feature",
  "properties": {
    "addr:full": "716 W Main Cross St Findlay OH 45840",
    "addr:housenumber": "716",
    "addr:postcode": "45840",
    "addr:street": "W Main Cross St",
    "iso:country": "US",
    "sg:address": "716 W Main Cross St",
    "sg:city": "Findlay",
    "sg:classifiers": [
      {
        "category": "Retail",
        "subcategory": "Repair Shop",
        "type": "Services"
      }
    ],
    "sg:phone": "+1 419 422 4903",
    "sg:postcode": "45840",
    "sg:province": "OH",
    "sg:tags": [
      "refinishing",
      "furniture"
    ],
    "wof:name": "Mathias Cabinet Shop",
    "wof:placetype": "venue"
  },
  "geometry": {"coordinates":[-83.661172,41.040212],"type":"Point"}
}
