{
  "type": "Feature",
  "properties": {
    "addr:full": "5655 N High St Columbus OH 43085",
    "addr:housenumber": "5655",
    "addr:postcode": "43085",
    "addr:street": "N High St",
    "iso:country": "US",
    "sg:address": "5655 N High St",
    "sg:city": "Columbus",
    "sg:classifiers": [
      {
        "category": "Real Estate",
        "subcategory": "Real Estate Agent",
        "type": "Services"
      }
    ],
    "sg:phone": "+1 614 430 0570",
    "sg:postcode": "43085",
    "sg:province": "OH",
    "wof:name": "Clifford Masten Rudolph Assoc",
    "wof:placetype": "venue"
  },
  "geometry": {"coordinates":[-83.018781,40.077381],"type":"Point"}
}
