{
  "type": "Feature",
  "properties": {
    "addr:full":"700 N Leavitt Rd Amherst OH 44001",
    "addr:housenumber":"700",
    "addr:postcode":"44001",
    "addr:street":"N Leavitt Rd",
    "iso:country":"US",
    "sg:address":"700 N Leavitt Rd",
    "sg:city":"Amherst",
    "sg:classifiers":[
        {
            "category":"Restaurant",
            "type":"Food & Drink"
        }
    ],
    "sg:menulink":"http://www.allmenus.com/oh/amherst/42820-bob-evans/menu/",
    "sg:phone":"+1 440 988 8894",
    "sg:postcode":"44001",
    "sg:province":"OH",
    "sg:tags":[
        "american"
    ],
    "wof:name":"Bob Evans",
    "wof:placetype":"venue"
},
  "geometry": {"coordinates":[-82.2092,41.411882],"type":"Point"}
}