{
  "type": "Feature",
  "properties": {
    "iso:country":"US",
    "sg:address":"925 S 2nd St",
    "sg:city":"Hamilton",
    "sg:classifiers":[
        {
            "category":"Education",
            "subcategory":"School",
            "type":"Public Place"
        }
    ],
    "sg:phone":"+1 513 863 8758",
    "sg:postcode":"45011",
    "sg:province":"OH",
    "wof:name":"St Joseph Consolidated School",
    "wof:placetype":"venue"
},
  "geometry": {"coordinates":[-84.565063,39.390629],"type":"Point"}
}