{
  "type": "Feature",
  "properties": {
    "addr:full": "5680 Chevrolet Blvd Cleveland OH 44130",
    "addr:housenumber": "5680",
    "addr:postcode": "44130",
    "addr:street": "Chevrolet Blvd",
    "iso:country": "US",
    "sg:address": "5680 Chevrolet Blvd",
    "sg:city": "Cleveland",
    "sg:classifiers": [
      {
        "category": "Parking",
        "type": "Transportation"
      }
    ],
    "sg:phone": "+1 440 885 8983",
    "sg:postcode": "44130",
    "sg:province": "OH",
    "sg:tags": [
      "automobile"
    ],
    "wof:name": "Parma Service Garage",
    "wof:placetype": "venue"
  },
  "geometry": {"coordinates":[-81.769015,41.407546],"type":"Point"}
}
