{
  "type": "Feature",
  "properties": {
    "addr:full": "14470 York Rd Cleveland OH 44133",
    "addr:housenumber": "14470",
    "addr:postcode": "44133",
    "addr:street": "York Rd",
    "iso:country": "US",
    "sg:address": "14470 York Rd",
    "sg:city": "Cleveland",
    "sg:classifiers": [
      {
        "category": "Building \u0026 Trades",
        "subcategory": "Construction",
        "type": "Services"
      }
    ],
    "sg:phone": "+1 440 237 1300",
    "sg:postcode": "44133",
    "sg:province": "OH",
    "sg:tags": [
      "general",
      "contractor"
    ],
    "wof:name": "Stevens Painton Corp",
    "wof:placetype": "venue"
  },
  "geometry": {"coordinates":[-81.754851,41.306883],"type":"Point"}
}
