{
  "type": "Feature",
  "properties": {
    "addr:full":"125 Diana Dr Youngstown OH 44514",
    "addr:housenumber":"125",
    "addr:postcode":"44514",
    "addr:street":"Diana Dr",
    "iso:country":"US",
    "sg:address":"125 Diana Dr",
    "sg:city":"Youngstown",
    "sg:classifiers":[
        {
            "category":"Building & Trades",
            "subcategory":"Construction",
            "type":"Services"
        }
    ],
    "sg:phone":"+1 330 757 8608",
    "sg:postcode":"44514",
    "sg:province":"OH",
    "sg:tags":[
        "house"
    ],
    "wof:name":"Thomas Duncan",
    "wof:placetype":"venue"
},
  "geometry": {"coordinates":[-80.602209,41.021809],"type":"Point"}
}