{
  "type": "Feature",
  "properties": {
    "addr:full": "504 Main St Toledo OH 43605",
    "addr:housenumber": "504",
    "addr:postcode": "43605",
    "addr:street": "Main St",
    "iso:country": "US",
    "sg:address": "504 Main St",
    "sg:city": "Toledo",
    "sg:classifiers": [
      {
        "category": "Government",
        "subcategory": "Post Office",
        "type": "Public Place"
      }
    ],
    "sg:phone": "+1 419 693 9181",
    "sg:postcode": "43605",
    "sg:province": "OH",
    "wof:name": "Arthur Daly Post Number",
    "wof:placetype": "venue"
  },
  "geometry": {"coordinates":[-83.519989,41.645382],"type":"Point"}
}
