{
  "type": "Feature",
  "properties": {
    "addr:full":"1700 E Monument Ave Dayton OH 45402",
    "addr:housenumber":"1700",
    "addr:postcode":"45402",
    "addr:street":"E Monument Ave",
    "iso:country":"US",
    "sg:address":"1700 E Monument Ave",
    "sg:city":"Dayton",
    "sg:classifiers":[
        {
            "category":"Freight",
            "type":"Transportation"
        }
    ],
    "sg:phone":"+1 937 226 1559",
    "sg:postcode":"45402",
    "sg:province":"OH",
    "wof:name":"Dayton Synchronous Support Ctr",
    "wof:placetype":"venue"
},
  "geometry": {"coordinates":[-84.169093,39.768508],"type":"Point"}
}