{
  "type": "Feature",
  "properties": {
    "iso:country":"US",
    "sg:address":"162 Marvin Ave",
    "sg:city":"Akron",
    "sg:classifiers":[
        {
            "category":"Building & Trades",
            "subcategory":"Construction",
            "type":"Services"
        }
    ],
    "sg:phone":"+1 330 836 4811",
    "sg:postcode":"44302",
    "sg:province":"OH",
    "sg:tags":[
        "paper",
        "painting",
        "hanging"
    ],
    "wof:name":"R T Sherlock",
    "wof:placetype":"venue"
},
  "geometry": {"coordinates":[-81.551509,41.09702],"type":"Point"}
}