{
  "type": "Feature",
  "properties": {
    "iso:country":"US",
    "sg:address":"1351 Leesburg Ave",
    "sg:city":"Washington Court House",
    "sg:classifiers":[
        {
            "category":"Government",
            "subcategory":"Office",
            "type":"Public Place"
        }
    ],
    "sg:phone":"+1 740 335 1391",
    "sg:postcode":"43160",
    "sg:province":"OH",
    "sg:tags":[
        "legislative",
        "body",
        "program",
        "health",
        "administrative"
    ],
    "wof:name":"Fayette Cnty Bd Mntal Rtrdtion",
    "wof:placetype":"venue"
},
  "geometry": {"coordinates":[-83.45916800000001,39.524443],"type":"Point"}
}