{
  "type": "Feature",
  "properties": {
    "iso:country":"US",
    "sg:address":"322 Ryder Rd",
    "sg:city":"Toledo",
    "sg:classifiers":[
        {
            "category":"Wholesale",
            "subcategory":"Machinery & Supplies",
            "type":"Manufacturing & Wholesale Goods"
        }
    ],
    "sg:phone":"+1 419 536 1212",
    "sg:postcode":"43607",
    "sg:province":"OH",
    "sg:tags":[
        "janitor"
    ],
    "sg:website":"www.midwestpaper.com",
    "wof:name":"Midwest Paper Specialties",
    "wof:placetype":"venue"
},
  "geometry": {"coordinates":[-83.61895699999999,41.645265],"type":"Point"}
}