{
  "type": "Feature",
  "properties": {
    "addr:full": "322 Ryder Rd Toledo OH 43607",
    "addr:housenumber": "322",
    "addr:postcode": "43607",
    "addr:street": "Ryder Rd",
    "iso:country": "US",
    "sg:address": "322 Ryder Rd",
    "sg:city": "Toledo",
    "sg:classifiers": [
      {
        "category": "Wholesale",
        "subcategory": "Machinery \u0026 Supplies",
        "type": "Manufacturing \u0026 Wholesale Goods"
      }
    ],
    "sg:phone": "+1 419 536 1212",
    "sg:postcode": "43607",
    "sg:province": "OH",
    "sg:tags": [
      "janitor"
    ],
    "sg:website": "www.midwestpaper.com",
    "wof:name": "Midwest Paper Specialties",
    "wof:placetype": "venue"
  },
  "geometry": {"coordinates":[-83.618957,41.645265],"type":"Point"}
}
