{
  "type": "Feature",
  "properties": {
    "addr:full": "355 S Delaware Dr Crooksville OH 43731",
    "addr:housenumber": "355",
    "addr:postcode": "43731",
    "addr:street": "S Delaware Dr",
    "iso:country": "US",
    "sg:address": "355 S Delaware Dr",
    "sg:city": "Crooksville",
    "sg:classifiers": [
      {
        "category": "Building \u0026 Trades",
        "subcategory": "Plumbing",
        "type": "Services"
      }
    ],
    "sg:phone": "+1 740 982 0396",
    "sg:postcode": "43731",
    "sg:province": "OH",
    "sg:tags": [
      "specializing",
      "conditioning",
      "contractor",
      "heating",
      "air"
    ],
    "wof:name": "Professional Energy",
    "wof:placetype": "venue"
  },
  "geometry": {"coordinates":[-82.090322,39.77427],"type":"Point"}
}
