{
  "type": "Feature",
  "properties": {
    "iso:country":"US",
    "sg:address":"4426 N Ridge Rd W",
    "sg:city":"Geneva",
    "sg:classifiers":[
        {
            "category":"Retail",
            "subcategory":"Auto Repair",
            "type":"Services"
        }
    ],
    "sg:phone":"+1 440 466 1102",
    "sg:postcode":"44041",
    "sg:province":"OH",
    "sg:tags":[
        "wrecker"
    ],
    "wof:name":"Phillips Imports & Salvage Inc",
    "wof:placetype":"venue"
},
  "geometry": {"coordinates":[-80.914047,41.815255],"type":"Point"}
}