{
  "type": "Feature",
  "properties": {
    "iso:country":"US",
    "sg:address":"1305 W Vine St",
    "sg:city":"Alliance",
    "sg:classifiers":[
        {
            "category":"Building & Trades",
            "subcategory":"Construction",
            "type":"Services"
        }
    ],
    "sg:phone":"+1 330 823 9814",
    "sg:postcode":"44601",
    "sg:province":"OH",
    "sg:tags":[
        "painter"
    ],
    "wof:name":"Classic Improvements",
    "wof:placetype":"venue"
},
  "geometry": {"coordinates":[-81.12512,40.930616],"type":"Point"}
}