{
  "type": "Feature",
  "properties": {
    "addr:full": "1305 W Vine St Alliance OH 44601",
    "addr:housenumber": "1305",
    "addr:postcode": "44601",
    "addr:street": "W Vine St",
    "iso:country": "US",
    "sg:address": "1305 W Vine St",
    "sg:city": "Alliance",
    "sg:classifiers": [
      {
        "category": "Building \u0026 Trades",
        "subcategory": "Construction",
        "type": "Services"
      }
    ],
    "sg:phone": "+1 330 823 9814",
    "sg:postcode": "44601",
    "sg:province": "OH",
    "sg:tags": [
      "painter"
    ],
    "wof:name": "Classic Improvements",
    "wof:placetype": "venue"
  },
  "geometry": {"coordinates":[-81.12512,40.930616],"type":"Point"}
}
