{
  "type": "Feature",
  "properties": {
    "addr:full": "8 S Maple St Orwell OH 44076",
    "addr:housenumber": "8",
    "addr:postcode": "44076",
    "addr:street": "S Maple St",
    "iso:country": "US",
    "sg:address": "8 S Maple St",
    "sg:city": "Orwell",
    "sg:classifiers": [
      {
        "category": "Autos \u0026 Motor Vehicles",
        "subcategory": "Auto Supplies",
        "type": "Retail Goods"
      }
    ],
    "sg:phone": "+1 440 437 6336",
    "sg:postcode": "44076",
    "sg:province": "OH",
    "sg:tags": [
      "automobile",
      "parts"
    ],
    "wof:name": "Orwell Auto Parts",
    "wof:placetype": "venue"
  },
  "geometry": {"coordinates":[-80.867807,41.53496],"type":"Point"}
}
