{
  "type": "Feature",
  "properties": {
    "addr:full":"1711 16th St SE Massillon OH 44646",
    "addr:housenumber":"1711",
    "addr:postcode":"44646",
    "addr:street":"16Th St Se",
    "iso:country":"US",
    "sg:address":"1711 16th St SE",
    "sg:city":"Massillon",
    "sg:classifiers":[
        {
            "category":"Real Estate",
            "subcategory":"Real Estate Operator",
            "type":"Services"
        }
    ],
    "sg:phone":"+1 330 837 9392",
    "sg:postcode":"44646",
    "sg:province":"OH",
    "sg:tags":[
        "apartment"
    ],
    "wof:name":"Stark Metropolitan Housing",
    "wof:placetype":"venue"
},
  "geometry": {"coordinates":[-81.505757,40.776812],"type":"Point"}
}