{
  "type": "Feature",
  "properties": {
    "addr:full":"260 Cole Ave Akron OH 44301",
    "addr:housenumber":"260",
    "addr:postcode":"44301",
    "addr:street":"Cole Ave",
    "iso:country":"US",
    "sg:address":"260 Cole Ave",
    "sg:city":"Akron",
    "sg:classifiers":[
        {
            "category":"Building & Trades",
            "subcategory":"Construction",
            "type":"Services"
        }
    ],
    "sg:phone":"+1 330 724 1884",
    "sg:postcode":"44301",
    "sg:province":"OH",
    "sg:tags":[
        "new",
        "remodeling",
        "family",
        "home"
    ],
    "wof:name":"Contemporary Renovations Inc",
    "wof:placetype":"venue"
},
  "geometry": {"coordinates":[-81.518806,41.050754],"type":"Point"}
}