{
  "type": "Feature",
  "properties": {
    "iso:country":"US",
    "sg:address":"2917 Philadelphia Dr",
    "sg:city":"Dayton",
    "sg:classifiers":[
        {
            "category":"Shopping",
            "subcategory":"Jewelry",
            "type":"Retail Goods"
        }
    ],
    "sg:phone":"+1 937 275 7442",
    "sg:postcode":"45405",
    "sg:province":"OH",
    "sg:tags":[
        "jeweler"
    ],
    "sg:website":"www.finlayenterprises.com",
    "wof:name":"Finlay Fine Jewelry",
    "wof:placetype":"venue"
},
  "geometry": {"coordinates":[-84.235277,39.800191],"type":"Point"}
}