{
  "type": "Feature",
  "properties": {
    "addr:full": "8285 S Bedford Rd Macedonia OH 44056",
    "addr:housenumber": "8285",
    "addr:postcode": "44056",
    "addr:street": "S Bedford Rd",
    "iso:country": "US",
    "sg:address": "8285 S Bedford Rd",
    "sg:city": "Macedonia",
    "sg:classifiers": [
      {
        "category": "Manufacturing",
        "subcategory": "Printing",
        "type": "Manufacturing \u0026 Wholesale Goods"
      }
    ],
    "sg:phone": "+1 330 908 0518",
    "sg:postcode": "44056",
    "sg:province": "OH",
    "sg:tags": [
      "lithographic",
      "commercial"
    ],
    "wof:name": "Basic Printing",
    "wof:placetype": "venue"
  },
  "geometry": {"coordinates":[-81.508943,41.310027],"type":"Point"}
}
