{
  "type": "Feature",
  "properties": {
    "iso:country":"US",
    "sg:address":"8285 S Bedford Rd",
    "sg:city":"Macedonia",
    "sg:classifiers":[
        {
            "category":"Manufacturing",
            "subcategory":"Printing",
            "type":"Manufacturing & Wholesale Goods"
        }
    ],
    "sg:phone":"+1 330 908 0518",
    "sg:postcode":"44056",
    "sg:province":"OH",
    "sg:tags":[
        "lithographic",
        "commercial"
    ],
    "wof:name":"Basic Printing",
    "wof:placetype":"venue"
},
  "geometry": {"coordinates":[-81.508943,41.310027],"type":"Point"}
}