{
  "type": "Feature",
  "properties": {
    "addr:full": "3602 W Pleasant Valley Rd Cleveland OH 44134",
    "addr:housenumber": "3602",
    "addr:postcode": "44134",
    "addr:street": "W Pleasant Valley Rd",
    "iso:country": "US",
    "sg:address": "3602 W Pleasant Valley Rd",
    "sg:city": "Cleveland",
    "sg:classifiers": [
      {
        "category": "Health Services",
        "subcategory": "Doctor",
        "type": "Services"
      }
    ],
    "sg:phone": "+1 440 888 8811",
    "sg:postcode": "44134",
    "sg:province": "OH",
    "wof:name": "Progressive Dentistry",
    "wof:placetype": "venue"
  },
  "geometry": {"coordinates":[-81.716895,41.36405],"type":"Point"}
}
