{
  "type": "Feature",
  "properties": {
    "addr:full": "8517 Fallgold Ln Westerville OH 43086",
    "addr:housenumber": "8517",
    "addr:postcode": "43086",
    "addr:street": "Fallgold Ln",
    "iso:country": "US",
    "sg:address": "8517 Fallgold Ln",
    "sg:city": "Westerville",
    "sg:classifiers": [
      {
        "category": "Manufacturing",
        "subcategory": "Printing",
        "type": "Manufacturing \u0026 Wholesale Goods"
      }
    ],
    "sg:phone": "+1 614 794 2246",
    "sg:postcode": "43086",
    "sg:province": "OH",
    "sg:tags": [
      "book"
    ],
    "wof:name": "Progressive Publishing Co",
    "wof:placetype": "venue"
  },
  "geometry": {"coordinates":[-82.88445,40.157048],"type":"Point"}
}
