{
  "type": "Feature",
  "properties": {
    "addr:full":"6696 Canaan Cir Dublin OH 43017",
    "addr:housenumber":"6696",
    "addr:postcode":"43017",
    "addr:street":"Canaan Cir",
    "iso:country":"US",
    "sg:address":"6696 Canaan Cir",
    "sg:city":"Dublin",
    "sg:classifiers":[
        {
            "category":"Professional",
            "subcategory":"Management & Consulting",
            "type":"Services"
        }
    ],
    "sg:phone":"+1 614 408 0105",
    "sg:postcode":"43017",
    "sg:province":"OH",
    "sg:tags":[
        "consultant",
        "business"
    ],
    "wof:name":"Cannon Iv Inc",
    "wof:placetype":"venue"
},
  "geometry": {"coordinates":[-83.10648399999999,40.089613],"type":"Point"}
}