{
  "type": "Feature",
  "properties": {
    "iso:country":"US",
    "sg:address":"1124 Twp Hwy 262",
    "sg:city":"Bloomingdale",
    "sg:classifiers":[
        {
            "category":"Freight",
            "type":"Transportation"
        }
    ],
    "sg:phone":"+1 740 543 3768",
    "sg:postcode":"43910",
    "sg:province":"OH",
    "sg:tags":[
        "operator",
        "local",
        "trucking"
    ],
    "wof:name":"C J Hauling",
    "wof:placetype":"venue"
},
  "geometry": {"coordinates":[-80.832235,40.45006],"type":"Point"}
}