{
  "type": "Feature",
  "properties": {
    "iso:country":"US",
    "sg:address":"3878 E 93rd St",
    "sg:city":"Cleveland",
    "sg:classifiers":[
        {
            "category":"Wholesale",
            "subcategory":"Metals & Minerals",
            "type":"Manufacturing & Wholesale Goods"
        }
    ],
    "sg:phone":"+1 216 641 9220",
    "sg:postcode":"44105",
    "sg:province":"OH",
    "sg:tags":[
        "steel",
        "warehouse"
    ],
    "wof:name":"Bar Steel",
    "wof:placetype":"venue"
},
  "geometry": {"coordinates":[-81.621458,41.452704],"type":"Point"}
}