{
  "type": "Feature",
  "properties": {
    "addr:full": "6570 Sosna Dr Fairfield OH 45014",
    "addr:housenumber": "6570",
    "addr:postcode": "45014",
    "addr:street": "Sosna Dr",
    "iso:country": "US",
    "sg:address": "6570 Sosna Dr",
    "sg:city": "Fairfield",
    "sg:classifiers": [
      {
        "category": "Shopping",
        "subcategory": "Stationery \u0026 Office Supplies",
        "type": "Retail Goods"
      }
    ],
    "sg:phone": "+1 513 942 3181",
    "sg:postcode": "45014",
    "sg:province": "OH",
    "wof:name": "Butler Behaviorial Health Svcs",
    "wof:placetype": "venue"
  },
  "geometry": {"coordinates":[-84.495622,39.319961],"type":"Point"}
}
