{
  "type": "Feature",
  "properties": {
    "iso:country":"US",
    "sg:address":"569 Park Hill Dr",
    "sg:city":"Akron",
    "sg:classifiers":[
        {
            "category":"Wholesale",
            "subcategory":"Metals & Minerals",
            "type":"Manufacturing & Wholesale Goods"
        }
    ],
    "sg:phone":"+1 330 836 4944",
    "sg:postcode":"44333",
    "sg:province":"OH",
    "sg:tags":[
        "importer",
        "exporter",
        "fabrication",
        "stamping"
    ],
    "wof:name":"A&A International",
    "wof:placetype":"venue"
},
  "geometry": {"coordinates":[-81.613078,41.11411],"type":"Point"}
}