{
  "type": "Feature",
  "properties": {
    "addr:full": "569 Park Hill Dr Akron OH 44333",
    "addr:housenumber": "569",
    "addr:postcode": "44333",
    "addr:street": "Park Hill Dr",
    "iso:country": "US",
    "sg:address": "569 Park Hill Dr",
    "sg:city": "Akron",
    "sg:classifiers": [
      {
        "category": "Wholesale",
        "subcategory": "Metals \u0026 Minerals",
        "type": "Manufacturing \u0026 Wholesale Goods"
      }
    ],
    "sg:phone": "+1 330 836 4944",
    "sg:postcode": "44333",
    "sg:province": "OH",
    "sg:tags": [
      "importer",
      "exporter",
      "fabrication",
      "stamping"
    ],
    "wof:name": "A\u0026A International",
    "wof:placetype": "venue"
  },
  "geometry": {"coordinates":[-81.613078,41.11411],"type":"Point"}
}
