{
  "type": "Feature",
  "properties": {
    "addr:full":"317 N Liberty St Delaware OH 43015",
    "addr:housenumber":"317",
    "addr:postcode":"43015",
    "addr:street":"N Liberty St",
    "iso:country":"US",
    "sg:address":"317 N Liberty St",
    "sg:city":"Delaware",
    "sg:classifiers":[
        {
            "category":"Insurance",
            "subcategory":"Insurance Agent",
            "type":"Services"
        }
    ],
    "sg:phone":"+1 740 369 0504",
    "sg:postcode":"43015",
    "sg:province":"OH",
    "sg:tags":[
        "carrier"
    ],
    "wof:name":"J W ONeal & Associates",
    "wof:placetype":"venue"
},
  "geometry": {"coordinates":[-83.072187,40.309367],"type":"Point"}
}