{
  "type": "Feature",
  "properties": {
    "addr:full": "19707 Center Ridge Rd Cleveland OH 44116",
    "addr:housenumber": "19707",
    "addr:postcode": "44116",
    "addr:street": "Center Ridge Rd",
    "iso:country": "US",
    "sg:address": "19707 Center Ridge Rd",
    "sg:city": "Cleveland",
    "sg:classifiers": [
      {
        "category": "Shopping",
        "subcategory": "Department Store",
        "type": "Retail Goods"
      }
    ],
    "sg:phone": "+1 440 331 2181",
    "sg:postcode": "44116",
    "sg:province": "OH",
    "sg:tags": [
      "shop"
    ],
    "sg:website": "www.pier1.com",
    "wof:name": "Pier 1 Imports",
    "wof:placetype": "venue"
  },
  "geometry": {"coordinates":[-81.840627,41.46513],"type":"Point"}
}
