{
  "type": "Feature",
  "properties": {
    "iso:country":"US",
    "sg:address":"8520 Akron Canfield Rd",
    "sg:city":"Canfield",
    "sg:classifiers":[
        {
            "category":"Professional",
            "subcategory":"Business Services",
            "type":"Services"
        }
    ],
    "sg:phone":"+1 330 533 2322",
    "sg:postcode":"44406",
    "sg:province":"OH",
    "sg:tags":[
        "recording",
        "studio"
    ],
    "wof:name":"Mainsail Music & Audio Prdctn",
    "wof:placetype":"venue"
},
  "geometry": {"coordinates":[-80.809765,41.024666],"type":"Point"}
}