{
  "type": "Feature",
  "properties": {
    "iso:country":"US",
    "sg:address":"3216 National Rd SW",
    "sg:city":"Hebron",
    "sg:classifiers":[
        {
            "category":"Professional",
            "subcategory":"Business Services",
            "type":"Services"
        }
    ],
    "sg:phone":"+1 740 928 4806",
    "sg:postcode":"43025",
    "sg:province":"OH",
    "sg:tags":[
        "water",
        "treatment"
    ],
    "wof:name":"Ohio Gas & Water Conditioning",
    "wof:placetype":"venue"
},
  "geometry": {"coordinates":[-82.55733600000001,39.958028],"type":"Point"}
}