{
  "type": "Feature",
  "properties": {
    "addr:full": "3216 National Rd SW Hebron OH 43025",
    "addr:housenumber": "3216",
    "addr:postcode": "43025",
    "addr:street": "National Rd Sw",
    "iso:country": "US",
    "sg:address": "3216 National Rd SW",
    "sg:city": "Hebron",
    "sg:classifiers": [
      {
        "category": "Professional",
        "subcategory": "Business Services",
        "type": "Services"
      }
    ],
    "sg:phone": "+1 740 928 4806",
    "sg:postcode": "43025",
    "sg:province": "OH",
    "sg:tags": [
      "water",
      "treatment"
    ],
    "wof:name": "Ohio Gas \u0026 Water Conditioning",
    "wof:placetype": "venue"
  },
  "geometry": {"coordinates":[-82.557336,39.958028],"type":"Point"}
}
