{
  "type": "Feature",
  "properties": {
    "iso:country":"US",
    "sg:address":"4925 Galaxy Pkwy",
    "sg:city":"Cleveland",
    "sg:classifiers":[
        {
            "category":"Professional",
            "subcategory":"Management & Consulting",
            "type":"Services"
        }
    ],
    "sg:phone":"+1 216 514 8411",
    "sg:postcode":"44128",
    "sg:province":"OH",
    "sg:tags":[
        "party",
        "planning"
    ],
    "sg:website":"www.party411.com",
    "wof:name":"Party 411",
    "wof:placetype":"venue"
},
  "geometry": {"coordinates":[-81.50143199999999,41.425297],"type":"Point"}
}