{
  "type": "Feature",
  "properties": {
    "iso:country":"US",
    "sg:address":"2757 Bender Ave",
    "sg:city":"Akron",
    "sg:classifiers":[
        {
            "category":"Retail",
            "subcategory":"Repair Shop",
            "type":"Services"
        }
    ],
    "sg:phone":"+1 330 644 4217",
    "sg:postcode":"44319",
    "sg:province":"OH",
    "sg:tags":[
        "sharpening"
    ],
    "wof:name":"Sharpening Place",
    "wof:placetype":"venue"
},
  "geometry": {"coordinates":[-81.51889,41.007903],"type":"Point"}
}