{
  "type": "Feature",
  "properties": {
    "addr:full": "4332 River Rd Cincinnati OH 45204",
    "addr:housenumber": "4332",
    "addr:postcode": "45204",
    "addr:street": "River Rd",
    "iso:country": "US",
    "sg:address": "4332 River Rd",
    "sg:city": "Cincinnati",
    "sg:classifiers": [
      {
        "category": "Building \u0026 Trades",
        "subcategory": "Construction",
        "type": "Services"
      }
    ],
    "sg:phone": "+1 513 451 5100",
    "sg:postcode": "45204",
    "sg:province": "OH",
    "sg:tags": [
      "masonry",
      "contractor"
    ],
    "wof:name": "A 1 Masonry",
    "wof:placetype": "venue"
  },
  "geometry": {"coordinates":[-84.614937,39.076682],"type":"Point"}
}
