{
  "type": "Feature",
  "properties": {
    "iso:country":"US",
    "sg:address":"4332 River Rd",
    "sg:city":"Cincinnati",
    "sg:classifiers":[
        {
            "category":"Building & Trades",
            "subcategory":"Construction",
            "type":"Services"
        }
    ],
    "sg:phone":"+1 513 451 5100",
    "sg:postcode":"45204",
    "sg:province":"OH",
    "sg:tags":[
        "masonry",
        "contractor"
    ],
    "wof:name":"A 1 Masonry",
    "wof:placetype":"venue"
},
  "geometry": {"coordinates":[-84.614937,39.076682],"type":"Point"}
}