{
  "type": "Feature",
  "properties": {
    "iso:country":"US",
    "sg:address":"34940 Lakeland Blvd",
    "sg:city":"Willoughby",
    "sg:classifiers":[
        {
            "category":"Wholesale",
            "subcategory":"Machinery & Supplies",
            "type":"Manufacturing & Wholesale Goods"
        }
    ],
    "sg:phone":"+1 440 942 9999",
    "sg:postcode":"44095",
    "sg:province":"OH",
    "wof:name":"Servo Products Co",
    "wof:placetype":"venue"
},
  "geometry": {"coordinates":[-81.446315,41.630845],"type":"Point"}
}