{
  "type": "Feature",
  "properties": {
    "addr:full": "34940 Lakeland Blvd Willoughby OH 44095",
    "addr:housenumber": "34940",
    "addr:postcode": "44095",
    "addr:street": "Lakeland Blvd",
    "iso:country": "US",
    "sg:address": "34940 Lakeland Blvd",
    "sg:city": "Willoughby",
    "sg:classifiers": [
      {
        "category": "Wholesale",
        "subcategory": "Machinery \u0026 Supplies",
        "type": "Manufacturing \u0026 Wholesale Goods"
      }
    ],
    "sg:phone": "+1 440 942 9999",
    "sg:postcode": "44095",
    "sg:province": "OH",
    "wof:name": "Servo Products Co",
    "wof:placetype": "venue"
  },
  "geometry": {"coordinates":[-81.446315,41.630845],"type":"Point"}
}
