{
  "type": "Feature",
  "properties": {
    "addr:full": "515 W Cumberland St Lewisburg OH 45338",
    "addr:housenumber": "515",
    "addr:postcode": "45338",
    "addr:street": "W Cumberland St",
    "iso:country": "US",
    "sg:address": "515 W Cumberland St",
    "sg:city": "Lewisburg",
    "sg:classifiers": [
      {
        "category": "Social Services",
        "subcategory": "Child Care",
        "type": "Services"
      }
    ],
    "sg:phone": "+1 937 962 8687",
    "sg:postcode": "45338",
    "sg:province": "OH",
    "wof:name": "Kid Connection Child Care Ctr",
    "wof:placetype": "venue"
  },
  "geometry": {"coordinates":[-84.543647,39.854285],"type":"Point"}
}
