{
  "type": "Feature",
  "properties": {
    "addr:full":"525 Ridge St Bowling Green OH 43402",
    "addr:housenumber":"525",
    "addr:postcode":"43402",
    "addr:street":"Ridge St",
    "iso:country":"US",
    "sg:address":"525 Ridge St",
    "sg:city":"Bowling Green",
    "sg:classifiers":[
        {
            "category":"Professional",
            "subcategory":"Printing & Photocopies",
            "type":"Services"
        }
    ],
    "sg:phone":"+1 419 354 3278",
    "sg:postcode":"43402",
    "sg:province":"OH",
    "sg:tags":[
        "duplicating",
        "copying"
    ],
    "wof:name":"Fast Co",
    "wof:placetype":"venue"
},
  "geometry": {"coordinates":[-83.643061,41.378362],"type":"Point"}
}