{
  "type": "Feature",
  "properties": {
    "addr:full": "3810 Lacon Rd Hilliard OH 43026",
    "addr:housenumber": "3810",
    "addr:postcode": "43026",
    "addr:street": "Lacon Rd",
    "iso:country": "US",
    "sg:address": "3810 Lacon Rd",
    "sg:city": "Hilliard",
    "sg:classifiers": [
      {
        "category": "Professional",
        "subcategory": "Advertising",
        "type": "Services"
      }
    ],
    "sg:phone": "+1 614 771 1220",
    "sg:postcode": "43026",
    "sg:province": "OH",
    "sg:tags": [
      "representative",
      "vehicle"
    ],
    "wof:name": "Interstate-Truckway Inc",
    "wof:placetype": "venue"
  },
  "geometry": {"coordinates":[-83.13448,40.031825],"type":"Point"}
}
