{
  "type": "Feature",
  "properties": {
    "addr:full":"19090 State Rte 12 Arcadia OH 44804",
    "addr:housenumber":"19090",
    "addr:postcode":"44804",
    "addr:street":"State Rte 12",
    "iso:country":"US",
    "sg:address":"19090 State Rte 12",
    "sg:city":"Arcadia",
    "sg:classifiers":[
        {
            "category":"Retail",
            "subcategory":"Auto Repair",
            "type":"Services"
        }
    ],
    "sg:phone":"+1 419 894 6447",
    "sg:postcode":"44804",
    "sg:province":"OH",
    "sg:tags":[
        "repairing",
        "automobile"
    ],
    "wof:name":"Arcadia Auto Svc",
    "wof:placetype":"venue"
},
  "geometry": {"coordinates":[-83.497817,41.116554],"type":"Point"}
}