{
  "type": "Feature",
  "properties": {
    "iso:country":"US",
    "sg:address":"131 Pendleton St",
    "sg:city":"Lisbon",
    "sg:classifiers":[
        {
            "category":"Social Services",
            "subcategory":"Adult Care",
            "type":"Services"
        }
    ],
    "sg:phone":"+1 330 424 9788",
    "sg:postcode":"44432",
    "sg:province":"OH",
    "sg:tags":[
        "home",
        "residential"
    ],
    "wof:name":"Allay Senior Care",
    "wof:placetype":"venue"
},
  "geometry": {"coordinates":[-80.770383,40.77865],"type":"Point"}
}