{
  "type": "Feature",
  "properties": {
    "iso:country":"US",
    "sg:address":"710 E Market St",
    "sg:city":"Warren",
    "sg:classifiers":[
        {
            "category":"Restaurant",
            "type":"Food & Drink"
        }
    ],
    "sg:phone":"+1 330 392 5640",
    "sg:postcode":"44481",
    "sg:province":"OH",
    "wof:name":"Brothers Sub Shop Inc",
    "wof:placetype":"venue"
},
  "geometry": {"coordinates":[-80.809546,41.236178],"type":"Point"}
}