{
  "type": "Feature",
  "properties": {
    "addr:full": "710 E Market St Warren OH 44481",
    "addr:housenumber": "710",
    "addr:postcode": "44481",
    "addr:street": "E Market St",
    "iso:country": "US",
    "sg:address": "710 E Market St",
    "sg:city": "Warren",
    "sg:classifiers": [
      {
        "category": "Restaurant",
        "type": "Food \u0026 Drink"
      }
    ],
    "sg:phone": "+1 330 392 5640",
    "sg:postcode": "44481",
    "sg:province": "OH",
    "wof:name": "Brothers Sub Shop Inc",
    "wof:placetype": "venue"
  },
  "geometry": {"coordinates":[-80.809546,41.236178],"type":"Point"}
}
