{
  "type": "Feature",
  "properties": {
    "addr:full":"100 E Water St Sandusky OH 44870",
    "addr:housenumber":"100",
    "addr:postcode":"44870",
    "addr:street":"E Water St",
    "iso:country":"US",
    "sg:address":"100 E Water St",
    "sg:city":"Sandusky",
    "sg:classifiers":[
        {
            "category":"Banks & Credit Unions",
            "subcategory":"Bank",
            "type":"Services"
        },
        {
            "category":"Banks & Credit Unions",
            "subcategory":"Financial Services",
            "type":"Services"
        }
    ],
    "sg:phone":"+1 419 625 4121",
    "sg:postcode":"44870",
    "sg:province":"OH",
    "sg:tags":[
        "broker",
        "mortgage"
    ],
    "wof:name":"Citizens Banking Co the",
    "wof:placetype":"venue"
},
  "geometry": {"coordinates":[-82.711502,41.457401],"type":"Point"}
}