{
  "type": "Feature",
  "properties": {
    "iso:country":"US",
    "sg:address":"4406 Broadhurst Dr",
    "sg:city":"Columbus",
    "sg:classifiers":[
        {
            "category":"Professional",
            "type":"Services"
        }
    ],
    "sg:phone":"+1 614 238 3856",
    "sg:postcode":"43213",
    "sg:province":"OH",
    "wof:name":"Inspired Images",
    "wof:placetype":"venue"
},
  "geometry": {"coordinates":[-82.883695,39.967996],"type":"Point"}
}