{
  "type": "Feature",
  "properties": {
    "addr:full": "701 Magnolia St Saint Marys OH 45885",
    "addr:housenumber": "701",
    "addr:postcode": "45885",
    "addr:street": "Magnolia St",
    "iso:country": "US",
    "sg:address": "701 Magnolia St",
    "sg:city": "Saint Marys",
    "sg:classifiers": [
      {
        "category": "Real Estate",
        "subcategory": "Real Estate Operator",
        "type": "Services"
      }
    ],
    "sg:phone": "+1 419 394 3054",
    "sg:postcode": "45885",
    "sg:province": "OH",
    "sg:tags": [
      "building",
      "nonresidential"
    ],
    "wof:name": "N\u0026W Hoenie Properties LLC",
    "wof:placetype": "venue"
  },
  "geometry": {"coordinates":[-84.411735,40.549445],"type":"Point"}
}
