{
  "type": "Feature",
  "properties": {
    "iso:country":"US",
    "sg:address":"701 Magnolia St",
    "sg:city":"Saint Marys",
    "sg:classifiers":[
        {
            "category":"Real Estate",
            "subcategory":"Real Estate Operator",
            "type":"Services"
        }
    ],
    "sg:phone":"+1 419 394 3054",
    "sg:postcode":"45885",
    "sg:province":"OH",
    "sg:tags":[
        "building",
        "nonresidential"
    ],
    "wof:name":"N&W Hoenie Properties LLC",
    "wof:placetype":"venue"
},
  "geometry": {"coordinates":[-84.41173499999999,40.549445],"type":"Point"}
}