{
  "type": "Feature",
  "properties": {
    "iso:country":"US",
    "sg:address":"10975 Houdeshell Rd",
    "sg:city":"St Louisville",
    "sg:classifiers":[
        {
            "category":"Manufacturing",
            "subcategory":"Retail Goods",
            "type":"Manufacturing & Wholesale Goods"
        },
        {
            "category":"Manufacturing",
            "subcategory":"Tools & Machinery",
            "type":"Manufacturing & Wholesale Goods"
        }
    ],
    "sg:phone":"+1 740 745 5045",
    "sg:postcode":"43071",
    "sg:province":"OH",
    "sg:tags":[
        "machine",
        "shop",
        "product",
        "mfg"
    ],
    "sg:website":"www.loweryindustries.com",
    "wof:name":"Lowery Industries",
    "wof:placetype":"venue"
},
  "geometry": {"coordinates":[-82.33731,40.17492],"type":"Point"}
}