{
  "type": "Feature",
  "properties": {
    "iso:country":"US",
    "sg:address":"3100 Maysville Pike",
    "sg:city":"Zanesville",
    "sg:classifiers":[
        {
            "category":"Home & Garden",
            "subcategory":"Mobile Homes",
            "type":"Retail Goods"
        }
    ],
    "sg:phone":"+1 740 450 4200",
    "sg:postcode":"43701",
    "sg:province":"OH",
    "wof:name":"Discovery Custom Homes",
    "wof:placetype":"venue"
},
  "geometry": {"coordinates":[-82.04871799999999,39.889153],"type":"Point"}
}