{
  "type": "Feature",
  "properties": {
    "addr:full": "3100 Maysville Pike Zanesville OH 43701",
    "addr:postcode": "3100;43701",
    "addr:street": "Maysville Pike",
    "iso:country": "US",
    "sg:address": "3100 Maysville Pike",
    "sg:city": "Zanesville",
    "sg:classifiers": [
      {
        "category": "Home \u0026 Garden",
        "subcategory": "Mobile Homes",
        "type": "Retail Goods"
      }
    ],
    "sg:phone": "+1 740 450 4200",
    "sg:postcode": "43701",
    "sg:province": "OH",
    "wof:name": "Discovery Custom Homes",
    "wof:placetype": "venue"
  },
  "geometry": {"coordinates":[-82.048718,39.889153],"type":"Point"}
}
