{
  "type": "Feature",
  "properties": {
    "addr:full":"1707 Squaw Creek Dr Girard OH 44420",
    "addr:housenumber":"1707",
    "addr:postcode":"44420",
    "addr:street":"Squaw Creek Dr",
    "iso:country":"US",
    "sg:address":"1707 Squaw Creek Dr",
    "sg:city":"Girard",
    "sg:classifiers":[
        {
            "category":"Building & Trades",
            "subcategory":"Construction",
            "type":"Services"
        }
    ],
    "sg:phone":"+1 330 545 2015",
    "sg:postcode":"44420",
    "sg:province":"OH",
    "sg:tags":[
        "contractor"
    ],
    "wof:name":"Gaylord F Teter",
    "wof:placetype":"venue"
},
  "geometry": {"coordinates":[-80.701876,41.172677],"type":"Point"}
}