{
  "type": "Feature",
  "properties": {
    "iso:country":"US",
    "sg:address":"3625 Elida Rd",
    "sg:city":"Lima",
    "sg:classifiers":[
        {
            "category":"Shopping",
            "subcategory":"Clothing, Apparel, & Fashions",
            "type":"Retail Goods"
        }
    ],
    "sg:phone":"+1 419 224 1910",
    "sg:postcode":"45807",
    "sg:province":"OH",
    "wof:name":"R T A",
    "wof:placetype":"venue"
},
  "geometry": {"coordinates":[-84.17247500000001,40.773766],"type":"Point"}
}