{
  "type": "Feature",
  "properties": {
    "addr:full":"33544 Aurora Rd Solon OH 44139",
    "addr:housenumber":"33544",
    "addr:postcode":"44139",
    "addr:street":"Aurora Rd",
    "iso:country":"US",
    "sg:address":"33544 Aurora Rd",
    "sg:city":"Solon",
    "sg:classifiers":[
        {
            "category":"Shopping",
            "subcategory":"Jewelry",
            "type":"Retail Goods"
        },
        {
            "category":"Shopping",
            "subcategory":"Pawn Shop",
            "type":"Retail Goods"
        }
    ],
    "sg:phone":"+1 216 789 4798",
    "sg:postcode":"44139",
    "sg:province":"OH",
    "sg:website":"www.650gold.com",
    "wof:name":"650 Gold",
    "wof:placetype":"venue"
},
  "geometry": {"coordinates":[-81.44136,41.384856],"type":"Point"}
}