{
  "type": "Feature",
  "properties": {
    "addr:full": "13875 Custers Point Rd Thornville OH 43076",
    "addr:housenumber": "13875",
    "addr:postcode": "43076",
    "addr:street": "Custers Point Rd",
    "iso:country": "US",
    "sg:address": "13875 Custers Point Rd",
    "sg:city": "Thornville",
    "sg:classifiers": [
      {
        "category": "Banks \u0026 Credit Unions",
        "subcategory": "Financial Services",
        "type": "Services"
      }
    ],
    "sg:phone": "+1 740 246 4568",
    "sg:postcode": "43076",
    "sg:province": "OH",
    "sg:tags": [
      "investor"
    ],
    "wof:name": "Shoreline Investment Prop",
    "wof:placetype": "venue"
  },
  "geometry": {"coordinates":[-82.46466,39.912871],"type":"Point"}
}
