{
  "type": "Feature",
  "properties": {
    "addr:full": "15690 S Boone Rd Columbia Station OH 44028",
    "addr:housenumber": "15690",
    "addr:postcode": "44028",
    "addr:street": "S Boone Rd",
    "iso:country": "US",
    "sg:address": "15690 S Boone Rd",
    "sg:city": "Columbia Station",
    "sg:classifiers": [
      {
        "category": "Real Estate",
        "subcategory": "Real Estate Agent",
        "type": "Services"
      }
    ],
    "sg:phone": "+1 440 236 9055",
    "sg:postcode": "44028",
    "sg:province": "OH",
    "wof:name": "R C H Co",
    "wof:placetype": "venue"
  },
  "geometry": {"coordinates":[-81.897303,41.303565],"type":"Point"}
}
