{
  "type": "Feature",
  "properties": {
    "iso:country":"US",
    "sg:address":"15690 S Boone Rd",
    "sg:city":"Columbia Station",
    "sg:classifiers":[
        {
            "category":"Real Estate",
            "subcategory":"Real Estate Agent",
            "type":"Services"
        }
    ],
    "sg:phone":"+1 440 236 9055",
    "sg:postcode":"44028",
    "sg:province":"OH",
    "wof:name":"R C H Co",
    "wof:placetype":"venue"
},
  "geometry": {"coordinates":[-81.89730299999999,41.303565],"type":"Point"}
}