{
  "type": "Feature",
  "properties": {
    "addr:full":"5225 Secor Rd Toledo OH 43623",
    "addr:housenumber":"5225",
    "addr:postcode":"43623",
    "addr:street":"Secor Rd",
    "iso:country":"US",
    "sg:address":"5225 Secor Rd",
    "sg:city":"Toledo",
    "sg:classifiers":[
        {
            "category":"Real Estate",
            "subcategory":"Surveying",
            "type":"Services"
        }
    ],
    "sg:phone":"+1 419 474 5716",
    "sg:postcode":"43623",
    "sg:province":"OH",
    "sg:tags":[
        "surveyor",
        "engineering"
    ],
    "wof:name":"M Freels Survey",
    "wof:placetype":"venue"
},
  "geometry": {"coordinates":[-83.623912,41.709485],"type":"Point"}
}