{
  "type": "Feature",
  "properties": {
    "addr:full": "13830 Quarry Rd North Baltimore OH 45872",
    "addr:housenumber": "13830",
    "addr:postcode": "45872",
    "addr:street": "Quarry Rd",
    "iso:country": "US",
    "sg:address": "13830 Quarry Rd",
    "sg:city": "North Baltimore",
    "sg:phone": "+1 419 257 3549",
    "sg:postcode": "45872",
    "sg:province": "OH",
    "sg:tags": [
      "farm",
      "corn",
      "wheat",
      "soybean"
    ],
    "wof:name": "Ned Casey",
    "wof:placetype": "venue"
  },
  "geometry": {"coordinates":[-83.667038,41.190063],"type":"Point"}
}
