{
  "type": "Feature",
  "properties": {
    "iso:country":"US",
    "sg:address":"291 W Center St",
    "sg:city":"Marion",
    "sg:classifiers":[
        {
            "category":"Restaurant",
            "type":"Food & Drink"
        }
    ],
    "sg:phone":"+1 740 387 7397",
    "sg:postcode":"43302",
    "sg:province":"OH",
    "sg:tags":[
        "eating"
    ],
    "wof:name":"Nicks Pizza II",
    "wof:placetype":"venue"
},
  "geometry": {"coordinates":[-83.133883,40.588387],"type":"Point"}
}