{
  "type": "Feature",
  "properties": {
    "addr:full":"12347 Hillcrest Dr Chesterland OH 44026",
    "addr:housenumber":"12347",
    "addr:postcode":"44026",
    "addr:street":"Hillcrest Dr",
    "iso:country":"US",
    "sg:address":"12347 Hillcrest Dr",
    "sg:city":"Chesterland",
    "sg:classifiers":[
        {
            "category":"Health Services",
            "subcategory":"Clinic",
            "type":"Services"
        }
    ],
    "sg:phone":"+1 440 235 6900",
    "sg:postcode":"44026",
    "sg:province":"OH",
    "sg:tags":[
        "home"
    ],
    "wof:name":"National Healthcare Resources",
    "wof:placetype":"venue"
},
  "geometry": {"coordinates":[-81.29545400000001,41.534112],"type":"Point"}
}