{
  "type": "Feature",
  "properties": {
    "addr:full":"21 E State St Trenton OH 45067",
    "addr:housenumber":"21",
    "addr:postcode":"45067",
    "addr:street":"E State St",
    "iso:country":"US",
    "sg:address":"21 E State St",
    "sg:city":"Trenton",
    "sg:classifiers":[
        {
            "category":"Education",
            "subcategory":"Library",
            "type":"Public Place"
        }
    ],
    "sg:phone":"+1 513 988 9050",
    "sg:postcode":"45067",
    "sg:province":"OH",
    "sg:website":"www.middletownlibrary.org",
    "wof:name":"Middletown Public Library",
    "wof:placetype":"venue"
},
  "geometry": {"coordinates":[-84.45797399999999,39.480965],"type":"Point"}
}