{
  "type": "Feature",
  "properties": {
    "addr:full": "1174 Sparrowwood Blvd Batavia OH 45103",
    "addr:housenumber": "1174",
    "addr:postcode": "45103",
    "addr:street": "Sparrowwood Blvd",
    "iso:country": "US",
    "sg:address": "1174 Sparrowwood Blvd",
    "sg:city": "Batavia",
    "sg:classifiers": [
      {
        "category": "Professional",
        "subcategory": "Accounting \u0026 Tax Preparation",
        "type": "Services"
      }
    ],
    "sg:phone": "+1 513 753 8900",
    "sg:postcode": "45103",
    "sg:province": "OH",
    "sg:tags": [
      "bookkeeping",
      "general"
    ],
    "wof:name": "Medtech Billing Svc",
    "wof:placetype": "venue"
  },
  "geometry": {"coordinates":[-84.240425,39.076744],"type":"Point"}
}
