{
  "type": "Feature",
  "properties": {
    "iso:country":"US",
    "sg:address":"1174 Sparrowwood Blvd",
    "sg:city":"Batavia",
    "sg:classifiers":[
        {
            "category":"Professional",
            "subcategory":"Accounting & Tax Preparation",
            "type":"Services"
        }
    ],
    "sg:phone":"+1 513 753 8900",
    "sg:postcode":"45103",
    "sg:province":"OH",
    "sg:tags":[
        "bookkeeping",
        "general"
    ],
    "wof:name":"Medtech Billing Svc",
    "wof:placetype":"venue"
},
  "geometry": {"coordinates":[-84.240425,39.076744],"type":"Point"}
}