{
  "type": "Feature",
  "properties": {
    "addr:full":"2013 Heron Glen Ct Macedonia OH 44056",
    "addr:housenumber":"2013",
    "addr:postcode":"44056",
    "addr:street":"Heron Glen Ct",
    "iso:country":"US",
    "sg:address":"2013 Heron Glen Ct",
    "sg:city":"Macedonia",
    "sg:classifiers":[
        {
            "category":"Building & Trades",
            "subcategory":"Construction",
            "type":"Services"
        }
    ],
    "sg:phone":"+1 330 468 5006",
    "sg:postcode":"44056",
    "sg:province":"OH",
    "sg:tags":[
        "hanging",
        "contractor"
    ],
    "wof:name":"Palmari Painting Paul",
    "wof:placetype":"venue"
},
  "geometry": {"coordinates":[-81.527123,41.328569],"type":"Point"}
}