{
  "type": "Feature",
  "properties": {
    "addr:full":"60 2nd St Athens OH 45701",
    "addr:housenumber":"60",
    "addr:postcode":"45701",
    "addr:street":"2Nd St",
    "iso:country":"US",
    "sg:address":"60 2nd St",
    "sg:city":"Athens",
    "sg:classifiers":[
        {
            "category":"Shopping",
            "subcategory":"Catalog Store",
            "type":"Retail Goods"
        }
    ],
    "sg:phone":"+1 740 593 7102",
    "sg:postcode":"45701",
    "sg:province":"OH",
    "sg:tags":[
        "mail",
        "house"
    ],
    "wof:name":"Starving Sawmi Press",
    "wof:placetype":"venue"
},
  "geometry": {"coordinates":[-82.107985,39.336576],"type":"Point"}
}