{
  "type": "Feature",
  "properties": {
    "iso:country":"US",
    "sg:address":"2441 W 5th St",
    "sg:city":"Cleveland",
    "sg:classifiers":[
        {
            "category":"Social Services",
            "subcategory":"Child Care",
            "type":"Services"
        }
    ],
    "sg:phone":"+1 216 589 0599",
    "sg:postcode":"44113",
    "sg:province":"OH",
    "wof:name":"Brenda's Day Care",
    "wof:placetype":"venue"
},
  "geometry": {"coordinates":[-81.680429,41.480276],"type":"Point"}
}