{
  "type": "Feature",
  "properties": {
    "addr:full":"2544 Chamberlain Rd Fairlawn OH 44333",
    "addr:housenumber":"2544",
    "addr:postcode":"44333",
    "addr:street":"Chamberlain Rd",
    "iso:country":"US",
    "sg:address":"2544 Chamberlain Rd",
    "sg:city":"Fairlawn",
    "sg:classifiers":[
        {
            "category":"Personal",
            "subcategory":"Beauty Salon",
            "type":"Services"
        }
    ],
    "sg:phone":"+1 330 867 8223",
    "sg:postcode":"44333",
    "sg:province":"OH",
    "wof:name":"Sanctuary Nail",
    "wof:placetype":"venue"
},
  "geometry": {"coordinates":[-81.608592,41.125133],"type":"Point"}
}