{
  "type": "Feature",
  "properties": {
    "iso:country":"US",
    "sg:address":"546 Uxbridge Ave",
    "sg:city":"Columbus",
    "sg:classifiers":[
        {
            "category":"Professional",
            "subcategory":"Management & Consulting",
            "type":"Services"
        }
    ],
    "sg:phone":"+1 614 933 8705",
    "sg:postcode":"43230",
    "sg:province":"OH",
    "sg:tags":[
        "consultant"
    ],
    "wof:name":"JMD Consultants",
    "wof:placetype":"venue"
},
  "geometry": {"coordinates":[-82.855603,40.032149],"type":"Point"}
}