{
  "type": "Feature",
  "properties": {
    "addr:full":"17164 Penny Pines Cir Strongsville OH 44136",
    "addr:housenumber":"17164",
    "addr:postcode":"44136",
    "addr:street":"Penny Pines Cir",
    "iso:country":"US",
    "sg:address":"17164 Penny Pines Cir",
    "sg:city":"Strongsville",
    "sg:classifiers":[
        {
            "category":"Building & Trades",
            "subcategory":"Construction",
            "type":"Services"
        }
    ],
    "sg:phone":"+1 440 238 1206",
    "sg:postcode":"44136",
    "sg:province":"OH",
    "sg:tags":[
        "hanging",
        "contractor"
    ],
    "wof:name":"J L Hubka Painting Co",
    "wof:placetype":"venue"
},
  "geometry": {"coordinates":[-81.819023,41.286385],"type":"Point"}
}