{
  "type": "Feature",
  "properties": {
    "iso:country":"US",
    "sg:address":"2574 Co Rd 74",
    "sg:city":"Gibsonburg",
    "sg:classifiers":[
        {
            "category":"Recreation",
            "type":"Entertainment"
        }
    ],
    "sg:phone":"+1 419 637 3001",
    "sg:postcode":"43431",
    "sg:province":"OH",
    "sg:tags":[
        "stable"
    ],
    "wof:name":"Sidell & Co",
    "wof:placetype":"venue"
},
  "geometry": {"coordinates":[-83.279088,41.410016],"type":"Point"}
}