{
  "type": "Feature",
  "properties": {
    "iso:country":"US",
    "sg:address":"25051 Hopewell Rd",
    "sg:city":"Gambier",
    "sg:classifiers":[
        {
            "category":"Farming",
            "subcategory":"Livestock Farm",
            "type":"Manufacturing & Wholesale Goods"
        }
    ],
    "sg:phone":"+1 740 668 4444",
    "sg:postcode":"43022",
    "sg:province":"OH",
    "sg:tags":[
        "beef",
        "feedlot",
        "cattle"
    ],
    "wof:name":"Edwin Rine",
    "wof:placetype":"venue"
},
  "geometry": {"coordinates":[-82.300422,40.300576],"type":"Point"}
}