{
  "type": "Feature",
  "properties": {
    "addr:full": "1385 Stony Creek Rd Troy OH 45373",
    "addr:housenumber": "1385",
    "addr:postcode": "45373",
    "addr:street": "Stony Creek Rd",
    "iso:country": "US",
    "sg:address": "1385 Stony Creek Rd",
    "sg:city": "Troy",
    "sg:classifiers": [
      {
        "category": "Professional",
        "subcategory": "Business Services",
        "type": "Services"
      },
      {
        "category": "Professional",
        "subcategory": "Computer Services",
        "type": "Services"
      }
    ],
    "sg:phone": "+1 937 440 8510",
    "sg:postcode": "45373",
    "sg:province": "OH",
    "sg:website": "www.buckeyebusiness.net",
    "wof:name": "Buckeye Business Solutions LLC",
    "wof:placetype": "venue"
  },
  "geometry": {"coordinates":[-84.225377,40.048293],"type":"Point"}
}
