{
  "type": "Feature",
  "properties": {
    "addr:full": "1451 NE Catawba Rd Port Clinton OH 43452",
    "addr:housenumber": "1451",
    "addr:postcode": "43452",
    "addr:street": "Ne Catawba Rd",
    "iso:country": "US",
    "sg:address": "1451 NE Catawba Rd",
    "sg:city": "Port Clinton",
    "sg:classifiers": [
      {
        "category": "Recreation",
        "subcategory": "Marina",
        "type": "Entertainment"
      }
    ],
    "sg:phone": "+1 419 797 2377",
    "sg:postcode": "43452",
    "sg:province": "OH",
    "sg:tags": [
      "operation"
    ],
    "wof:name": "Harbor Park Marina Inc",
    "wof:placetype": "venue"
  },
  "geometry": {"coordinates":[-82.848315,41.543022],"type":"Point"}
}
