{
  "type": "Feature",
  "properties": {
    "addr:full": "547 W Main St Lebanon OH 45036",
    "addr:housenumber": "547",
    "addr:postcode": "45036",
    "addr:street": "W Main St",
    "iso:country": "US",
    "sg:address": "547 W Main St",
    "sg:city": "Lebanon",
    "sg:classifiers": [
      {
        "category": "Building \u0026 Trades",
        "subcategory": "Construction",
        "type": "Services"
      }
    ],
    "sg:phone": "+1 513 934 1796",
    "sg:postcode": "45036",
    "sg:province": "OH",
    "sg:tags": [
      "general",
      "contractor"
    ],
    "wof:name": "Complete General Contractors",
    "wof:placetype": "venue"
  },
  "geometry": {"coordinates":[-84.216328,39.43379],"type":"Point"}
}
