{
  "type": "Feature",
  "properties": {
    "addr:full": "2505 W Erie Ave Lorain OH 44053",
    "addr:housenumber": "2505",
    "addr:postcode": "44053",
    "addr:street": "W Erie Ave",
    "iso:country": "US",
    "sg:address": "2505 W Erie Ave",
    "sg:city": "Lorain",
    "sg:classifiers": [
      {
        "category": "Shopping",
        "type": "Retail Goods"
      }
    ],
    "sg:phone": "+1 440 245 3479",
    "sg:postcode": "44053",
    "sg:province": "OH",
    "sg:tags": [
      "merchandise"
    ],
    "wof:name": "Kents Pro Fireworks",
    "wof:placetype": "venue"
  },
  "geometry": {"coordinates":[-82.20417,41.457789],"type":"Point"}
}
