{
  "type": "Feature",
  "properties": {
    "addr:full": "96 E Broad St Elyria OH 44035",
    "addr:housenumber": "96",
    "addr:postcode": "44035",
    "addr:street": "E Broad St",
    "iso:country": "US",
    "sg:address": "96 E Broad St",
    "sg:city": "Elyria",
    "sg:classifiers": [
      {
        "category": "Retail",
        "subcategory": "Veterinary Services",
        "type": "Services"
      }
    ],
    "sg:phone": "+1 440 322 3220",
    "sg:postcode": "44035",
    "sg:province": "OH",
    "wof:name": "Broad Street Animal Clinic",
    "wof:placetype": "venue"
  },
  "geometry": {"coordinates":[-82.098147,41.367652],"type":"Point"}
}
