{
  "type": "Feature",
  "properties": {
    "addr:full":"5232 Crookshank Rd Cincinnati OH 45238",
    "addr:housenumber":"5232",
    "addr:postcode":"45238",
    "addr:street":"Crookshank Rd",
    "iso:country":"US",
    "sg:address":"5232 Crookshank Rd",
    "sg:city":"Cincinnati",
    "sg:classifiers":[
        {
            "category":"Professional",
            "type":"Services"
        }
    ],
    "sg:phone":"+1 513 451 5421",
    "sg:postcode":"45238",
    "sg:province":"OH",
    "sg:website":"www.cincinnaticontractpackaging.com",
    "wof:name":"Cincinnati Contract Packaging",
    "wof:placetype":"venue"
},
  "geometry": {"coordinates":[-84.612627,39.128033],"type":"Point"}
}