{
  "type": "Feature",
  "properties": {
    "addr:full": "25701 Richmond Rd Cleveland OH 44146",
    "addr:housenumber": "25701",
    "addr:postcode": "44146",
    "addr:street": "Richmond Rd",
    "iso:country": "US",
    "sg:address": "25701 Richmond Rd",
    "sg:city": "Cleveland",
    "sg:classifiers": [
      {
        "category": "Wholesale",
        "subcategory": "Construction Materials",
        "type": "Manufacturing \u0026 Wholesale Goods"
      }
    ],
    "sg:phone": "+1 216 464 6511",
    "sg:postcode": "44146",
    "sg:province": "OH",
    "sg:tags": [
      "lumber"
    ],
    "wof:name": "B \u0026 B Wood Products",
    "wof:placetype": "venue"
  },
  "geometry": {"coordinates":[-81.488549,41.41167],"type":"Point"}
}
