{
  "type": "Feature",
  "properties": {
    "iso:country":"US",
    "sg:address":"29525 Chagrin Blvd Ste 306",
    "sg:city":"Beachwood",
    "sg:classifiers":[
        {
            "category":"Banks & Credit Unions",
            "subcategory":"Financial Services",
            "type":"Services"
        }
    ],
    "sg:phone":"+1 216 765 8988",
    "sg:postcode":"44122",
    "sg:province":"OH",
    "sg:tags":[
        "broker",
        "mortgage"
    ],
    "wof:name":"West Park Financial Inc",
    "wof:placetype":"venue"
},
  "geometry": {"coordinates":[-81.480598,41.462299],"type":"Point"}
}