{
  "type": "Feature",
  "properties": {
    "addr:full": "29525 Chagrin Blvd Ste 306 Beachwood OH 44122",
    "addr:housenumber": "29525",
    "addr:postcode": "44122",
    "addr:street": "Chagrin Blvd Ste 306",
    "iso:country": "US",
    "sg:address": "29525 Chagrin Blvd Ste 306",
    "sg:city": "Beachwood",
    "sg:classifiers": [
      {
        "category": "Banks \u0026 Credit Unions",
        "subcategory": "Financial Services",
        "type": "Services"
      }
    ],
    "sg:phone": "+1 216 765 8988",
    "sg:postcode": "44122",
    "sg:province": "OH",
    "sg:tags": [
      "broker",
      "mortgage"
    ],
    "wof:name": "West Park Financial Inc",
    "wof:placetype": "venue"
  },
  "geometry": {"coordinates":[-81.480598,41.462299],"type":"Point"}
}
