{
  "type": "Feature",
  "properties": {
    "addr:full": "81 N Portage St Doylestown OH 44230",
    "addr:housenumber": "81",
    "addr:postcode": "44230",
    "addr:street": "N Portage St",
    "iso:country": "US",
    "sg:address": "81 N Portage St",
    "sg:city": "Doylestown",
    "sg:classifiers": [
      {
        "category": "Utilities",
        "subcategory": "Telephone",
        "type": "Services"
      }
    ],
    "sg:phone": "+1 330 658 2121",
    "sg:postcode": "44230",
    "sg:province": "OH",
    "sg:tags": [
      "company"
    ],
    "sg:website": "www.doylestowntelephone.com",
    "wof:name": "Doylestown Telephone Co",
    "wof:placetype": "venue"
  },
  "geometry": {"coordinates":[-81.696559,40.969748],"type":"Point"}
}
