{
  "type": "Feature",
  "properties": {
    "addr:full": "2919 Old Railroad Rd Sandusky OH 44870",
    "addr:housenumber": "2919",
    "addr:postcode": "44870",
    "addr:street": "Old Railroad Rd",
    "iso:country": "US",
    "sg:address": "2919 Old Railroad Rd",
    "sg:city": "Sandusky",
    "sg:phone": "+1 419 625 2287",
    "sg:postcode": "44870",
    "sg:province": "OH",
    "sg:tags": [
      "farm",
      "corn",
      "soybean"
    ],
    "wof:name": "Dwelle Farms",
    "wof:placetype": "venue"
  },
  "geometry": {"coordinates":[-82.732507,41.426677],"type":"Point"}
}
