{
  "type": "Feature",
  "properties": {
    "addr:full":"1989 Madison Rd Cincinnati OH 45208",
    "addr:housenumber":"1989",
    "addr:postcode":"45208",
    "addr:street":"Madison Rd",
    "iso:country":"US",
    "sg:address":"1989 Madison Rd",
    "sg:city":"Cincinnati",
    "sg:classifiers":[
        {
            "category":"Shopping",
            "type":"Retail Goods"
        }
    ],
    "sg:phone":"+1 513 871 2150",
    "sg:postcode":"45208",
    "sg:province":"OH",
    "sg:tags":[
        "pet",
        "food",
        "supply"
    ],
    "wof:name":"LA De Dog & The Cats Meow",
    "wof:placetype":"venue"
},
  "geometry": {"coordinates":[-84.464011,39.131601],"type":"Point"}
}