{
  "type": "Feature",
  "properties": {
    "addr:full":"1050 N University Blvd Middletown OH 45042",
    "addr:housenumber":"1050",
    "addr:postcode":"45042",
    "addr:street":"N University Blvd",
    "iso:country":"US",
    "sg:address":"1050 N University Blvd",
    "sg:city":"Middletown",
    "sg:classifiers":[
        {
            "category":"Insurance",
            "subcategory":"Insurance Agent",
            "type":"Services"
        }
    ],
    "sg:phone":"+1 513 424 2005",
    "sg:postcode":"45042",
    "sg:province":"OH",
    "wof:name":"Redding Insurance",
    "wof:placetype":"venue"
},
  "geometry": {"coordinates":[-84.370848,39.523557],"type":"Point"}
}