{
  "type": "Feature",
  "properties": {
    "addr:full": "384 W Pershing St Salem OH 44460",
    "addr:housenumber": "384",
    "addr:postcode": "44460",
    "addr:street": "W Pershing St",
    "iso:country": "US",
    "sg:address": "384 W Pershing St",
    "sg:city": "Salem",
    "sg:classifiers": [
      {
        "category": "Retail",
        "subcategory": "Repair Shop",
        "type": "Services"
      }
    ],
    "sg:phone": "+1 330 337 1022",
    "sg:postcode": "44460",
    "sg:province": "OH",
    "sg:tags": [
      "plumbing",
      "drain",
      "cleaning",
      "sewer"
    ],
    "wof:name": "Salem Sewer \u0026 Drain",
    "wof:placetype": "venue"
  },
  "geometry": {"coordinates":[-80.861237,40.89989],"type":"Point"}
}
