{
  "type": "Feature",
  "properties": {
    "addr:full":"5090 Pleasant Ave Fairfield OH 45014",
    "addr:housenumber":"5090",
    "addr:postcode":"45014",
    "addr:street":"Pleasant Ave",
    "iso:country":"US",
    "sg:address":"5090 Pleasant Ave",
    "sg:city":"Fairfield",
    "sg:classifiers":[
        {
            "category":"Retail",
            "subcategory":"Laundry & Dry Cleaning",
            "type":"Services"
        }
    ],
    "sg:phone":"+1 513 863 7132",
    "sg:postcode":"45014",
    "sg:province":"OH",
    "sg:tags":[
        "cleaners"
    ],
    "wof:name":"Dry Cleaning N More",
    "wof:placetype":"venue"
},
  "geometry": {"coordinates":[-84.559675,39.341939],"type":"Point"}
}