{
  "type": "Feature",
  "properties": {
    "addr:full": "2813 Germantown St Dayton OH 45408",
    "addr:housenumber": "2813",
    "addr:postcode": "45408",
    "addr:street": "Germantown St",
    "iso:country": "US",
    "sg:address": "2813 Germantown St",
    "sg:city": "Dayton",
    "sg:classifiers": [
      {
        "category": "Food \u0026 Beverages",
        "subcategory": "Groceries \u0026 Convenience Stores",
        "type": "Retail Goods"
      }
    ],
    "sg:phone": "+1 937 263 3832",
    "sg:postcode": "45408",
    "sg:province": "OH",
    "wof:name": "Westside Supermarket",
    "wof:placetype": "venue"
  },
  "geometry": {"coordinates":[-84.24119,39.738346],"type":"Point"}
}
