{
  "type": "Feature",
  "properties": {
    "iso:country":"US",
    "sg:address":"2813 Germantown St",
    "sg:city":"Dayton",
    "sg:classifiers":[
        {
            "category":"Food & Beverages",
            "subcategory":"Groceries & Convenience Stores",
            "type":"Retail Goods"
        }
    ],
    "sg:phone":"+1 937 263 3832",
    "sg:postcode":"45408",
    "sg:province":"OH",
    "wof:name":"Westside Supermarket",
    "wof:placetype":"venue"
},
  "geometry": {"coordinates":[-84.24119,39.738346],"type":"Point"}
}