{
  "type": "Feature",
  "properties": {
    "addr:full":"13387 US Hwy 127 Paulding OH 45879",
    "addr:housenumber":"13387",
    "addr:postcode":"45879",
    "addr:street":"Us Hwy 127",
    "iso:country":"US",
    "sg:address":"13387 US Hwy 127",
    "sg:city":"Paulding",
    "sg:classifiers":[
        {
            "category":"Government",
            "subcategory":"Office",
            "type":"Public Place"
        }
    ],
    "sg:phone":"+1 419 399 9728",
    "sg:postcode":"45879",
    "sg:province":"OH",
    "wof:name":"Paulding County Dog Warden",
    "wof:placetype":"venue"
},
  "geometry": {"coordinates":[-84.58334499999999,41.17931],"type":"Point"}
}