{
  "type": "Feature",
  "properties": {
    "addr:full": "930 Trailwood Dr Youngstown OH 44512",
    "addr:housenumber": "930",
    "addr:postcode": "44512",
    "addr:street": "Trailwood Dr",
    "iso:country": "US",
    "sg:address": "930 Trailwood Dr",
    "sg:city": "Youngstown",
    "sg:classifiers": [
      {
        "category": "Manufacturing",
        "subcategory": "Tools \u0026 Machinery",
        "type": "Manufacturing \u0026 Wholesale Goods"
      }
    ],
    "sg:phone": "+1 330 758 1143",
    "sg:postcode": "44512",
    "sg:province": "OH",
    "sg:tags": [
      "fit",
      "mfg",
      "appliance",
      "prosthetic",
      "orthopedic",
      "braces"
    ],
    "wof:name": "ABI Orthotic/Prosthetic Labs",
    "wof:placetype": "venue"
  },
  "geometry": {"coordinates":[-80.642764,41.027499],"type":"Point"}
}
