{
  "type": "Feature",
  "properties": {
    "addr:full": "114 Mansfield St Galion OH 44833",
    "addr:housenumber": "114",
    "addr:postcode": "44833",
    "addr:street": "Mansfield St",
    "iso:country": "US",
    "sg:address": "114 Mansfield St",
    "sg:city": "Galion",
    "sg:classifiers": [
      {
        "category": "Insurance",
        "subcategory": "Insurance Agent",
        "type": "Services"
      }
    ],
    "sg:phone": "+1 419 468 1405",
    "sg:postcode": "44833",
    "sg:province": "OH",
    "wof:name": "Carrier-Wisler Agency",
    "wof:placetype": "venue"
  },
  "geometry": {"coordinates":[-82.770359,40.734512],"type":"Point"}
}
