{
  "type": "Feature",
  "properties": {
    "iso:country":"US",
    "sg:address":"6057 Sebring Warner Rd",
    "sg:city":"Greenville",
    "sg:classifiers":[
        {
            "category":"Real Estate",
            "subcategory":"Real Estate Operator",
            "type":"Services"
        }
    ],
    "sg:phone":"+1 937 548 8438",
    "sg:postcode":"45331",
    "sg:province":"OH",
    "sg:tags":[
        "mobile",
        "home",
        "site"
    ],
    "wof:name":"Olwine Mobile Hm Pk Sls & Svc",
    "wof:placetype":"venue"
},
  "geometry": {"coordinates":[-84.613404,40.09058],"type":"Point"}
}