{
  "type": "Feature",
  "properties": {
    "addr:full": "6057 Sebring Warner Rd Greenville OH 45331",
    "addr:postcode": "6057;45331",
    "addr:street": "Warner Rd",
    "iso:country": "US",
    "sg:address": "6057 Sebring Warner Rd",
    "sg:city": "Greenville",
    "sg:classifiers": [
      {
        "category": "Real Estate",
        "subcategory": "Real Estate Operator",
        "type": "Services"
      }
    ],
    "sg:phone": "+1 937 548 8438",
    "sg:postcode": "45331",
    "sg:province": "OH",
    "sg:tags": [
      "mobile",
      "home",
      "site"
    ],
    "wof:name": "Olwine Mobile Hm Pk Sls \u0026 Svc",
    "wof:placetype": "venue"
  },
  "geometry": {"coordinates":[-84.613404,40.09058],"type":"Point"}
}
