{
  "type": "Feature",
  "properties": {
    "addr:full": "1 Federal St Dayton OH 45406",
    "addr:housenumber": "1",
    "addr:postcode": "45406",
    "addr:street": "Federal St",
    "iso:country": "US",
    "sg:address": "1 Federal St",
    "sg:city": "Dayton",
    "sg:classifiers": [
      {
        "category": "Banks \u0026 Credit Unions",
        "subcategory": "Bank",
        "type": "Services"
      }
    ],
    "sg:phone": "+1 937 223 4234",
    "sg:postcode": "45406",
    "sg:province": "OH",
    "sg:tags": [
      "state",
      "commercial"
    ],
    "wof:name": "Fifth Third Bank",
    "wof:placetype": "venue"
  },
  "geometry": {"coordinates":[-84.207658,39.767339],"type":"Point"}
}
