{
  "type": "Feature",
  "properties": {
    "addr:full": "7875 Montgomery Rd Ste 2 Cincinnati OH 45236",
    "addr:housenumber": "7875",
    "addr:postcode": "45236",
    "addr:street": "Montgomery Rd Ste 2",
    "iso:country": "US",
    "sg:address": "7875 Montgomery Rd Ste 2",
    "sg:city": "Cincinnati",
    "sg:classifiers": [
      {
        "category": "Restaurant",
        "type": "Food \u0026 Drink"
      }
    ],
    "sg:phone": "+1 513 791 8283",
    "sg:postcode": "45236",
    "sg:province": "OH",
    "sg:tags": [
      "cajun",
      "creole"
    ],
    "wof:name": "Kelly's Cajun Grill",
    "wof:placetype": "venue"
  },
  "geometry": {"coordinates":[-84.377688,39.199917],"type":"Point"}
}
