{
  "type": "Feature",
  "properties": {
    "addr:full":"7105 Highpoint Blvd Hamilton OH 45011",
    "addr:housenumber":"7105",
    "addr:postcode":"45011",
    "addr:street":"Highpoint Blvd",
    "iso:country":"US",
    "sg:address":"7105 Highpoint Blvd",
    "sg:city":"Hamilton",
    "sg:classifiers":[
        {
            "category":"Building & Trades",
            "subcategory":"Construction",
            "type":"Services"
        }
    ],
    "sg:phone":"+1 513 844 1436",
    "sg:postcode":"45011",
    "sg:province":"OH",
    "sg:tags":[
        "hanging",
        "contractor"
    ],
    "wof:name":"McMahan and Son Painting",
    "wof:placetype":"venue"
},
  "geometry": {"coordinates":[-84.458956,39.376007],"type":"Point"}
}