{
  "type": "Feature",
  "properties": {
    "addr:full": "23575 Detroit Rd Westlake OH 44145",
    "addr:housenumber": "23575",
    "addr:postcode": "44145",
    "addr:street": "Detroit Rd",
    "iso:country": "US",
    "sg:address": "23575 Detroit Rd",
    "sg:city": "Westlake",
    "sg:classifiers": [
      {
        "category": "Restaurant",
        "type": "Food \u0026 Drink"
      }
    ],
    "sg:menulink": "http://www.allmenus.com/oh/westlake/100430-buca-di-beppo/menu/",
    "sg:phone": "+1 440 356 2276",
    "sg:postcode": "44145",
    "sg:province": "OH",
    "sg:tags": [
      "italian"
    ],
    "wof:name": "Buca di Beppo",
    "wof:placetype": "venue"
  },
  "geometry": {"coordinates":[-81.88078,41.470756],"type":"Point"}
}
