{
  "type": "Feature",
  "properties": {
    "iso:country":"US",
    "sg:address":"321 S 11th St",
    "sg:city":"Cambridge",
    "sg:classifiers":[
        {
            "category":"Personal",
            "subcategory":"Beauty Salon",
            "type":"Services"
        }
    ],
    "sg:phone":"+1 740 432 3175",
    "sg:postcode":"43725",
    "sg:province":"OH",
    "wof:name":"Stylette Hair & Tanning Salon",
    "wof:placetype":"venue"
},
  "geometry": {"coordinates":[-81.584777,40.022204],"type":"Point"}
}