{
  "type": "Feature",
  "properties": {
    "iso:country":"US",
    "sg:address":"158 S Abbe Rd",
    "sg:city":"Elyria",
    "sg:classifiers":[
        {
            "category":"Home & Garden",
            "subcategory":"Building Materials",
            "type":"Retail Goods"
        }
    ],
    "sg:phone":"+1 440 322 6744",
    "sg:postcode":"44035",
    "sg:province":"OH",
    "sg:tags":[
        "door"
    ],
    "sg:website":"www.oldetownewindows.com",
    "wof:name":"Olde Towne Windows & Doors",
    "wof:placetype":"venue"
},
  "geometry": {"coordinates":[-82.077772,41.374171],"type":"Point"}
}