{
  "type": "Feature",
  "properties": {
    "addr:full": "1650 W Market St Akron OH 44313",
    "addr:housenumber": "1650",
    "addr:postcode": "44313",
    "addr:street": "W Market St",
    "iso:country": "US",
    "sg:address": "1650 W Market St",
    "sg:city": "Akron",
    "sg:classifiers": [
      {
        "category": "Banks \u0026 Credit Unions",
        "subcategory": "Bank",
        "type": "Services"
      }
    ],
    "sg:phone": "+1 330 835 4816",
    "sg:postcode": "44313",
    "sg:province": "OH",
    "sg:tags": [
      "loan",
      "real estate"
    ],
    "wof:name": "Mortgage Professional Of Ohio",
    "wof:placetype": "venue"
  },
  "geometry": {"coordinates":[-81.570308,41.109973],"type":"Point"}
}
