{
  "type": "Feature",
  "properties": {
    "addr:full": "6115 E Livingston Ave Columbus OH 43232",
    "addr:housenumber": "6115",
    "addr:postcode": "43232",
    "addr:street": "E Livingston Ave",
    "iso:country": "US",
    "sg:address": "6115 E Livingston Ave",
    "sg:city": "Columbus",
    "sg:classifiers": [
      {
        "category": "Bars \u0026 Pubs",
        "type": "Food \u0026 Drink"
      },
      {
        "category": "Restaurant",
        "type": "Food \u0026 Drink"
      }
    ],
    "sg:phone": "+1 614 322 2239",
    "sg:postcode": "43232",
    "sg:province": "OH",
    "sg:tags": [
      "eating"
    ],
    "wof:name": "Spanky's Pub",
    "wof:placetype": "venue"
  },
  "geometry": {"coordinates":[-82.83023,39.942007],"type":"Point"}
}
