{
  "type": "Feature",
  "properties": {
    "iso:country":"US",
    "sg:address":"6115 E Livingston Ave",
    "sg:city":"Columbus",
    "sg:classifiers":[
        {
            "category":"Bars & Pubs",
            "type":"Food & Drink"
        },
        {
            "category":"Restaurant",
            "type":"Food & Drink"
        }
    ],
    "sg:phone":"+1 614 322 2239",
    "sg:postcode":"43232",
    "sg:province":"OH",
    "sg:tags":[
        "eating"
    ],
    "wof:name":"Spanky's Pub",
    "wof:placetype":"venue"
},
  "geometry": {"coordinates":[-82.83023,39.942007],"type":"Point"}
}