{
  "type": "Feature",
  "properties": {
    "addr:full": "398 Lahm Dr Hopedale OH 43976",
    "addr:housenumber": "398",
    "addr:postcode": "43976",
    "addr:street": "Lahm Dr",
    "iso:country": "US",
    "sg:address": "398 Lahm Dr",
    "sg:city": "Hopedale",
    "sg:classifiers": [
      {
        "category": "Health Services",
        "subcategory": "Nursing And Care Facility",
        "type": "Services"
      }
    ],
    "sg:phone": "+1 740 937 2694",
    "sg:postcode": "43976",
    "sg:province": "OH",
    "sg:tags": [
      "home",
      "skilled",
      "convalescent"
    ],
    "wof:name": "Gables Training Center",
    "wof:placetype": "venue"
  },
  "geometry": {"coordinates":[-80.9022,40.32676],"type":"Point"}
}
