{
  "type": "Feature",
  "properties": {
    "addr:full":"2570 Pressler Rd Akron OH 44312",
    "addr:housenumber":"2570",
    "addr:postcode":"44312",
    "addr:street":"Pressler Rd",
    "iso:country":"US",
    "sg:address":"2570 Pressler Rd",
    "sg:city":"Akron",
    "sg:classifiers":[
        {
            "category":"Building & Trades",
            "subcategory":"Construction",
            "type":"Services"
        }
    ],
    "sg:phone":"+1 330 644 4098",
    "sg:postcode":"44312",
    "sg:province":"OH",
    "sg:tags":[
        "excavating",
        "contractor"
    ],
    "wof:name":"Precision Excavation & Grading",
    "wof:placetype":"venue"
},
  "geometry": {"coordinates":[-81.44463,40.988981],"type":"Point"}
}