{
  "type": "Feature",
  "properties": {
    "addr:full":"2902 Sunbury Sq Columbus OH 43219",
    "addr:housenumber":"2902",
    "addr:postcode":"43219",
    "addr:street":"Sunbury Sq",
    "iso:country":"US",
    "sg:address":"2902 Sunbury Sq",
    "sg:city":"Columbus",
    "sg:classifiers":[
        {
            "category":"Real Estate",
            "subcategory":"Real Estate Operator",
            "type":"Services"
        }
    ],
    "sg:phone":"+1 614 337 1525",
    "sg:postcode":"43219",
    "sg:province":"OH",
    "sg:tags":[
        "apartment"
    ],
    "wof:name":"Sunbury Square",
    "wof:placetype":"venue"
},
  "geometry": {"coordinates":[-82.933127,40.024614],"type":"Point"}
}