{
  "type": "Feature",
  "properties": {
    "addr:full":"3975 Sable Ridge Dr Bellbrook OH 45305",
    "addr:housenumber":"3975",
    "addr:postcode":"45305",
    "addr:street":"Sable Ridge Dr",
    "iso:country":"US",
    "sg:address":"3975 Sable Ridge Dr",
    "sg:city":"Bellbrook",
    "sg:classifiers":[
        {
            "category":"Shopping",
            "subcategory":"Computers & Home Electronics",
            "type":"Retail Goods"
        }
    ],
    "sg:phone":"+1 937 848 8966",
    "sg:postcode":"45305",
    "sg:province":"OH",
    "sg:tags":[
        "software"
    ],
    "wof:name":"Bailey Computer Solutions",
    "wof:placetype":"venue"
},
  "geometry": {"coordinates":[-84.086603,39.642792],"type":"Point"}
}