{
  "type": "Feature",
  "properties": {
    "addr:full": "848 N High St Columbus OH 43215",
    "addr:housenumber": "848",
    "addr:postcode": "43215",
    "addr:street": "N High St",
    "iso:country": "US",
    "sg:address": "848 N High St",
    "sg:city": "Columbus",
    "sg:classifiers": [
      {
        "category": "Shopping",
        "subcategory": "Music",
        "type": "Retail Goods"
      }
    ],
    "sg:phone": "+1 614 291 7962",
    "sg:postcode": "43215",
    "sg:province": "OH",
    "sg:tags": [
      "tape",
      "video",
      "rental"
    ],
    "wof:name": "Metro Video",
    "wof:placetype": "venue"
  },
  "geometry": {"coordinates":[-83.003923,39.979231],"type":"Point"}
}
