{
  "type": "Feature",
  "properties": {
    "iso:country":"US",
    "sg:address":"26 West St",
    "sg:city":"Akron",
    "sg:classifiers":[
        {
            "category":"Organizations",
            "subcategory":"Religious Organization",
            "type":"Services"
        }
    ],
    "sg:phone":"+1 330 745 0683",
    "sg:postcode":"44303",
    "sg:province":"OH",
    "wof:name":"Corporation of President of Th",
    "wof:placetype":"venue"
},
  "geometry": {"coordinates":[-81.525571,41.089367],"type":"Point"}
}