{
  "type": "Feature",
  "properties": {
    "iso:country":"US",
    "sg:address":"44403 State Rte 14",
    "sg:city":"Columbiana",
    "sg:classifiers":[
        {
            "category":"Organizations",
            "subcategory":"Community Association",
            "type":"Services"
        }
    ],
    "sg:phone":"+1 330 482 9657",
    "sg:postcode":"44408",
    "sg:province":"OH",
    "sg:tags":[
        "military"
    ],
    "wof:name":"American Legion",
    "wof:placetype":"venue"
},
  "geometry": {"coordinates":[-80.658351,40.885479],"type":"Point"}
}