{
  "type": "Feature",
  "properties": {
    "addr:full":"17610 Burson Rd Lore City OH 43755",
    "addr:housenumber":"17610",
    "addr:postcode":"43755",
    "addr:street":"Burson Rd",
    "iso:country":"US",
    "sg:address":"17610 Burson Rd",
    "sg:city":"Lore City",
    "sg:phone":"+1 740 489 5683",
    "sg:postcode":"43755",
    "sg:province":"OH",
    "sg:tags":[
        "farm",
        "field",
        "crop"
    ],
    "wof:name":"Cooper John",
    "wof:placetype":"venue"
},
  "geometry": {"coordinates":[-81.41019300000001,40.093717],"type":"Point"}
}