{
  "type": "Feature",
  "properties": {
    "addr:full":"7320 Fairground Blvd Canfield OH 44406",
    "addr:housenumber":"7320",
    "addr:postcode":"44406",
    "addr:street":"Fairground Blvd",
    "iso:country":"US",
    "sg:address":"7320 Fairground Blvd",
    "sg:city":"Canfield",
    "sg:classifiers":[
        {
            "category":"Building & Trades",
            "subcategory":"Construction",
            "type":"Services"
        }
    ],
    "sg:phone":"+1 330 533 4406",
    "sg:postcode":"44406",
    "sg:province":"OH",
    "sg:tags":[
        "house",
        "nonresidential"
    ],
    "wof:name":"J L Builders Inc",
    "wof:placetype":"venue"
},
  "geometry": {"coordinates":[-80.749559,41.015767],"type":"Point"}
}