{
  "type": "Feature",
  "properties": {
    "addr:full":"3141 Paris Ave SE Paris OH 44669",
    "addr:housenumber":"3141",
    "addr:postcode":"44669",
    "addr:street":"Paris Ave Se",
    "iso:country":"US",
    "sg:address":"3141 Paris Ave SE",
    "sg:city":"Paris",
    "sg:classifiers":[
        {
            "category":"Farming",
            "subcategory":"Farm",
            "type":"Manufacturing & Wholesale Goods"
        }
    ],
    "sg:phone":"+1 330 862 2688",
    "sg:postcode":"44669",
    "sg:province":"OH",
    "sg:tags":[
        "crop",
        "general"
    ],
    "wof:name":"Sluss Elden",
    "wof:placetype":"venue"
},
  "geometry": {"coordinates":[-81.15721499999999,40.764735],"type":"Point"}
}