{
  "type": "Feature",
  "properties": {
    "addr:full": "1595 Twinsburg Rd Twinsburg OH 44087",
    "addr:housenumber": "1595",
    "addr:postcode": "44087",
    "addr:street": "Twinsburg Rd",
    "iso:country": "US",
    "sg:address": "1595 Twinsburg Rd",
    "sg:city": "Twinsburg",
    "sg:classifiers": [
      {
        "category": "Building \u0026 Trades",
        "subcategory": "Landscaping Services",
        "type": "Services"
      }
    ],
    "sg:phone": "+1 330 405 9179",
    "sg:postcode": "44087",
    "sg:province": "OH",
    "sg:tags": [
      "landscape",
      "contractor"
    ],
    "wof:name": "Warestates",
    "wof:placetype": "venue"
  },
  "geometry": {"coordinates":[-81.45478,41.28179],"type":"Point"}
}
