{
  "type": "Feature",
  "properties": {
    "iso:country":"US",
    "sg:address":"2020 High St",
    "sg:city":"Cuyahoga Falls",
    "sg:classifiers":[
        {
            "category":"Food & Beverages",
            "subcategory":"Specialty",
            "type":"Retail Goods"
        }
    ],
    "sg:phone":"+1 330 929 5894",
    "sg:postcode":"44221",
    "sg:province":"OH",
    "sg:tags":[
        "health",
        "diet"
    ],
    "wof:name":"Shaklee Distributor",
    "wof:placetype":"venue"
},
  "geometry": {"coordinates":[-81.473033,41.134289],"type":"Point"}
}