{
  "type": "Feature",
  "properties": {
    "addr:full":"3414 State Rte 309 Ada OH 45810",
    "addr:housenumber":"3414",
    "addr:postcode":"45810",
    "addr:street":"State Rte 309",
    "iso:country":"US",
    "sg:address":"3414 State Rte 309",
    "sg:city":"Ada",
    "sg:classifiers":[
        {
            "category":"Shopping",
            "subcategory":"Bicycles & Sporting Goods",
            "type":"Retail Goods"
        }
    ],
    "sg:phone":"+1 419 634 6269",
    "sg:postcode":"45810",
    "sg:province":"OH",
    "wof:name":"Tb Outdoor Supply",
    "wof:placetype":"venue"
},
  "geometry": {"coordinates":[-83.81592499999999,40.73289],"type":"Point"}
}