{
  "type": "Feature",
  "properties": {
    "iso:country":"US",
    "sg:address":"6480 Rockside Woods Blvd S",
    "sg:city":"Cleveland",
    "sg:classifiers":[
        {
            "category":"Real Estate",
            "subcategory":"Real Estate Services",
            "type":"Services"
        }
    ],
    "sg:phone":"+1 216 447 4070",
    "sg:postcode":"44131",
    "sg:province":"OH",
    "sg:tags":[
        "company",
        "title"
    ],
    "wof:name":"Revere Title Agency Inc",
    "wof:placetype":"venue"
},
  "geometry": {"coordinates":[-81.646063,41.394501],"type":"Point"}
}