{
  "type": "Feature",
  "properties": {
    "iso:country":"US",
    "sg:address":"253 Crouse Rd",
    "sg:city":"Wilmington",
    "sg:classifiers":[
        {
            "category":"Shopping",
            "subcategory":"Gifts & Souvenirs",
            "type":"Retail Goods"
        }
    ],
    "sg:phone":"+1 937 685 5891",
    "sg:postcode":"45177",
    "sg:province":"OH",
    "wof:name":"Primetimesports Card Bin",
    "wof:placetype":"venue"
},
  "geometry": {"coordinates":[-83.787322,39.376975],"type":"Point"}
}