{
  "type": "Feature",
  "properties": {
    "iso:country":"US",
    "sg:address":"338 Oak Village Dr",
    "sg:city":"Columbus",
    "sg:classifiers":[
        {
            "category":"Building & Trades",
            "subcategory":"Cleaning & Sanitation",
            "type":"Services"
        }
    ],
    "sg:phone":"+1 614 492 1067",
    "sg:postcode":"43207",
    "sg:province":"OH",
    "sg:tags":[
        "janitor"
    ],
    "wof:name":"Service Corp Plus",
    "wof:placetype":"venue"
},
  "geometry": {"coordinates":[-82.992983,39.874868],"type":"Point"}
}