{
  "type": "Feature",
  "properties": {
    "iso:country":"US",
    "sg:address":"5375 Maple Canyon Ave",
    "sg:city":"Columbus",
    "sg:classifiers":[
        {
            "category":"Freight",
            "type":"Transportation"
        }
    ],
    "sg:phone":"+1 614 846 0530",
    "sg:postcode":"43229",
    "sg:province":"OH",
    "sg:tags":[
        "truck",
        "driver"
    ],
    "wof:name":"Gary Root",
    "wof:placetype":"venue"
},
  "geometry": {"coordinates":[-82.96337699999999,40.078756],"type":"Point"}
}