{
  "type": "Feature",
  "properties": {
    "addr:full": "5375 Maple Canyon Ave Columbus OH 43229",
    "addr:housenumber": "5375",
    "addr:postcode": "43229",
    "addr:street": "Maple Canyon Ave",
    "iso:country": "US",
    "sg:address": "5375 Maple Canyon Ave",
    "sg:city": "Columbus",
    "sg:classifiers": [
      {
        "category": "Freight",
        "type": "Transportation"
      }
    ],
    "sg:phone": "+1 614 846 0530",
    "sg:postcode": "43229",
    "sg:province": "OH",
    "sg:tags": [
      "truck",
      "driver"
    ],
    "wof:name": "Gary Root",
    "wof:placetype": "venue"
  },
  "geometry": {"coordinates":[-82.963377,40.078756],"type":"Point"}
}
