{
  "type": "Feature",
  "properties": {
    "addr:full": "340 E Town St Columbus OH 43215",
    "addr:housenumber": "340",
    "addr:postcode": "43215",
    "addr:street": "E Town St",
    "iso:country": "US",
    "sg:address": "340 E Town St",
    "sg:city": "Columbus",
    "sg:classifiers": [
      {
        "category": "Health Services",
        "subcategory": "Doctor",
        "type": "Services"
      }
    ],
    "sg:phone": "+1 614 221 2888",
    "sg:postcode": "43215",
    "sg:province": "OH",
    "sg:tags": [
      "physician",
      "surgeon",
      "medical"
    ],
    "wof:name": "Metropolitan Urologists",
    "wof:placetype": "venue"
  },
  "geometry": {"coordinates":[-82.991645,39.959841],"type":"Point"}
}
