{
  "type": "Feature",
  "properties": {
    "iso:country":"US",
    "sg:address":"3217 Westgate",
    "sg:city":"Cleveland",
    "sg:classifiers":[
        {
            "category":"Restaurant",
            "type":"Food & Drink"
        }
    ],
    "sg:phone":"+1 440 331 1510",
    "sg:postcode":"44126",
    "sg:province":"OH",
    "sg:tags":[
        "eating"
    ],
    "wof:name":"McDonalds",
    "wof:placetype":"venue"
},
  "geometry": {"coordinates":[-81.852795,41.458355],"type":"Point"}
}