{
  "type": "Feature",
  "properties": {
    "iso:country":"US",
    "sg:address":"2910 Consaul St",
    "sg:city":"Toledo",
    "sg:classifiers":[
        {
            "category":"Restaurant",
            "type":"Food & Drink"
        }
    ],
    "sg:phone":"+1 419 410 6539",
    "sg:postcode":"43605",
    "sg:province":"OH",
    "sg:tags":[
        "caterer"
    ],
    "wof:name":"Amore Catering",
    "wof:placetype":"venue"
},
  "geometry": {"coordinates":[-83.47777000000001,41.658608],"type":"Point"}
}