{
  "type": "Feature",
  "properties": {
    "addr:full": "2910 Consaul St Toledo OH 43605",
    "addr:postcode": "2910;43605",
    "addr:street": "Consaul St",
    "iso:country": "US",
    "sg:address": "2910 Consaul St",
    "sg:city": "Toledo",
    "sg:classifiers": [
      {
        "category": "Restaurant",
        "type": "Food \u0026 Drink"
      }
    ],
    "sg:phone": "+1 419 410 6539",
    "sg:postcode": "43605",
    "sg:province": "OH",
    "sg:tags": [
      "caterer"
    ],
    "wof:name": "Amore Catering",
    "wof:placetype": "venue"
  },
  "geometry": {"coordinates":[-83.47777,41.658608],"type":"Point"}
}
