{
  "type": "Feature",
  "properties": {
    "addr:full": "4230 N Holland Sylvania Ave Toledo OH 43623",
    "addr:housenumber": "4230",
    "addr:postcode": "43623",
    "addr:street": "N Holland Sylvania Ave",
    "iso:country": "US",
    "sg:address": "4230 N Holland Sylvania Ave",
    "sg:city": "Toledo",
    "sg:classifiers": [
      {
        "category": "Professional",
        "subcategory": "Business Services",
        "type": "Services"
      }
    ],
    "sg:phone": "+1 419 882 2264",
    "sg:postcode": "43623",
    "sg:province": "OH",
    "sg:tags": [
      "interior",
      "consultant",
      "design",
      "decorator"
    ],
    "wof:name": "Boxell Interiors Inc",
    "wof:placetype": "venue"
  },
  "geometry": {"coordinates":[-83.686723,41.692608],"type":"Point"}
}
