{
  "type": "Feature",
  "properties": {
    "addr:full": "223 Highland Rd E Macedonia OH 44056",
    "addr:housenumber": "223",
    "addr:postcode": "44056",
    "addr:street": "Highland Rd E",
    "iso:country": "US",
    "sg:address": "223 Highland Rd E",
    "sg:city": "Macedonia",
    "sg:classifiers": [
      {
        "category": "Professional",
        "subcategory": "Computer Services",
        "type": "Services"
      }
    ],
    "sg:phone": "+1 330 467 1440",
    "sg:postcode": "44056",
    "sg:province": "OH",
    "sg:tags": [
      "repair"
    ],
    "wof:name": "Expectec Technology",
    "wof:placetype": "venue"
  },
  "geometry": {"coordinates":[-81.518899,41.298692],"type":"Point"}
}
