{
  "type": "Feature",
  "properties": {
    "addr:full":"4989 State Rte 37 Delaware OH 43015",
    "addr:housenumber":"4989",
    "addr:postcode":"43015",
    "addr:street":"State Rte 37",
    "iso:country":"US",
    "sg:address":"4989 State Rte 37",
    "sg:city":"Delaware",
    "sg:classifiers":[
        {
            "category":"Retail",
            "subcategory":"Animal Services",
            "type":"Services"
        }
    ],
    "sg:phone":"+1 740 548 4447",
    "sg:postcode":"43015",
    "sg:province":"OH",
    "sg:tags":[
        "training",
        "dog"
    ],
    "sg:website":"www.caninecompanions.org",
    "wof:name":"Canine Companions",
    "wof:placetype":"venue"
},
  "geometry": {"coordinates":[-83.166304,40.322022],"type":"Point"}
}