{
  "type": "Feature",
  "properties": {
    "addr:full":"121 W High St Lima OH 45801",
    "addr:housenumber":"121",
    "addr:postcode":"45801",
    "addr:street":"W High St",
    "iso:country":"US",
    "sg:address":"121 W High St",
    "sg:city":"Lima",
    "sg:classifiers":[
        {
            "category":"Banks & Credit Unions",
            "subcategory":"Investment Brokerage",
            "type":"Services"
        },
        {
            "category":"Banks & Credit Unions",
            "subcategory":"Bank",
            "type":"Services"
        }
    ],
    "sg:phone":"+1 419 221 5850",
    "sg:postcode":"45801",
    "sg:province":"OH",
    "sg:tags":[
        "security"
    ],
    "sg:website":"www.bankone.com",
    "wof:name":"Bank One",
    "wof:placetype":"venue"
},
  "geometry": {"coordinates":[-84.10564100000001,40.741279],"type":"Point"}
}