{
  "type": "Feature",
  "properties": {
    "iso:country":"US",
    "sg:address":"417 S Main St",
    "sg:city":"Fostoria",
    "sg:classifiers":[
        {
            "category":"Organizations",
            "subcategory":"Religious Organization",
            "type":"Services"
        }
    ],
    "sg:phone":"+1 419 435 4541",
    "sg:postcode":"44830",
    "sg:province":"OH",
    "sg:tags":[
        "church"
    ],
    "wof:name":"First Freewill Baptist Church",
    "wof:placetype":"venue"
},
  "geometry": {"coordinates":[-83.414152,41.153922],"type":"Point"}
}