{
  "type": "Feature",
  "properties": {
    "iso:country":"US",
    "sg:address":"7419 W Chester Rd",
    "sg:city":"West Chester",
    "sg:classifiers":[
        {
            "category":"Professional",
            "subcategory":"Accounting & Tax Preparation",
            "type":"Services"
        }
    ],
    "sg:phone":"+1 513 777 4533",
    "sg:postcode":"45069",
    "sg:province":"OH",
    "sg:tags":[
        "accountant"
    ],
    "sg:website":"www.ugjcpa.com",
    "wof:name":"Umble Gayhart & Jacobsen",
    "wof:placetype":"venue"
},
  "geometry": {"coordinates":[-84.379981,39.319882],"type":"Point"}
}