{
  "type": "Feature",
  "properties": {
    "addr:full": "3889 E Galbraith Rd Cincinnati OH 45236",
    "addr:housenumber": "3889",
    "addr:postcode": "45236",
    "addr:street": "E Galbraith Rd",
    "iso:country": "US",
    "sg:address": "3889 E Galbraith Rd",
    "sg:city": "Cincinnati",
    "sg:classifiers": [
      {
        "category": "Health Services",
        "subcategory": "Nursing And Care Facility",
        "type": "Services"
      }
    ],
    "sg:phone": "+1 513 984 5220",
    "sg:postcode": "45236",
    "sg:province": "OH",
    "sg:tags": [
      "home",
      "convalescent"
    ],
    "wof:name": "Galbraith Nursing Home",
    "wof:placetype": "venue"
  },
  "geometry": {"coordinates":[-84.404917,39.208806],"type":"Point"}
}
