{
  "type": "Feature",
  "properties": {
    "addr:full":"4750 E Main St Columbus OH 43213",
    "addr:housenumber":"4750",
    "addr:postcode":"43213",
    "addr:street":"E Main St",
    "iso:country":"US",
    "sg:address":"4750 E Main St",
    "sg:city":"Columbus",
    "sg:classifiers":[
        {
            "category":"Bakery",
            "type":"Food & Drink"
        }
    ],
    "sg:menulink":"http://www.allmenus.com/oh/whitehall/100173-golden-corral/menu/",
    "sg:phone":"+1 614 864 0810",
    "sg:postcode":"43213",
    "sg:province":"OH",
    "sg:tags":[
        "american",
        "pastry"
    ],
    "wof:name":"Golden Corral",
    "wof:placetype":"venue"
},
  "geometry": {"coordinates":[-82.87052,39.955863],"type":"Point"}
}