{
  "type": "Feature",
  "properties": {
    "addr:full": "227 W Emmitt Ave Waverly OH 45690",
    "addr:housenumber": "227",
    "addr:postcode": "45690",
    "addr:street": "W Emmitt Ave",
    "iso:country": "US",
    "sg:address": "227 W Emmitt Ave",
    "sg:city": "Waverly",
    "sg:classifiers": [
      {
        "category": "Autos \u0026 Motor Vehicles",
        "subcategory": "Auto Supplies",
        "type": "Retail Goods"
      }
    ],
    "sg:phone": "+1 740 941 1414",
    "sg:postcode": "45690",
    "sg:province": "OH",
    "sg:tags": [
      "automobile",
      "stereo",
      "radio"
    ],
    "wof:name": "Waverly Buy Sell \u0026 Trade",
    "wof:placetype": "venue"
  },
  "geometry": {"coordinates":[-82.986493,39.126041],"type":"Point"}
}
