{
  "type": "Feature",
  "properties": {
    "iso:country":"US",
    "sg:address":"227 W Emmitt Ave",
    "sg:city":"Waverly",
    "sg:classifiers":[
        {
            "category":"Autos & Motor Vehicles",
            "subcategory":"Auto Supplies",
            "type":"Retail Goods"
        }
    ],
    "sg:phone":"+1 740 941 1414",
    "sg:postcode":"45690",
    "sg:province":"OH",
    "sg:tags":[
        "automobile",
        "stereo",
        "radio"
    ],
    "wof:name":"Waverly Buy Sell & Trade",
    "wof:placetype":"venue"
},
  "geometry": {"coordinates":[-82.986493,39.126041],"type":"Point"}
}