{
  "type": "Feature",
  "properties": {
    "addr:full": "1287 King Ave Columbus OH 43212",
    "addr:housenumber": "1287",
    "addr:postcode": "43212",
    "addr:street": "King Ave",
    "iso:country": "US",
    "sg:address": "1287 King Ave",
    "sg:city": "Columbus",
    "sg:classifiers": [
      {
        "category": "Professional",
        "subcategory": "Computer Services",
        "type": "Services"
      }
    ],
    "sg:phone": "+1 614 488 8829",
    "sg:postcode": "43212",
    "sg:province": "OH",
    "sg:tags": [
      "website",
      "design"
    ],
    "sg:website": "www.pageville.com",
    "wof:name": "Arlington Web Svc",
    "wof:placetype": "venue"
  },
  "geometry": {"coordinates":[-83.043877,39.991485],"type":"Point"}
}
