{
  "type": "Feature",
  "properties": {
    "addr:full": "3311 N West St Lima OH 45801",
    "addr:housenumber": "3311",
    "addr:postcode": "45801",
    "addr:street": "N West St",
    "iso:country": "US",
    "sg:address": "3311 N West St",
    "sg:city": "Lima",
    "sg:classifiers": [
      {
        "category": "Shopping",
        "type": "Retail Goods"
      }
    ],
    "sg:phone": "+1 419 222 5332",
    "sg:postcode": "45801",
    "sg:province": "OH",
    "sg:tags": [
      "merchandise"
    ],
    "sg:website": "www.impactnetwork.com",
    "wof:name": "Impact Network Solutions Inc",
    "wof:placetype": "venue"
  },
  "geometry": {"coordinates":[-84.108896,40.78631],"type":"Point"}
}
