{
  "type": "Feature",
  "properties": {
    "addr:full": "6740 Hardwood Dr Galloway OH 43119",
    "addr:housenumber": "6740",
    "addr:postcode": "43119",
    "addr:street": "Hardwood Dr",
    "iso:country": "US",
    "sg:address": "6740 Hardwood Dr",
    "sg:city": "Galloway",
    "sg:phone": "+1 614 878 1054",
    "sg:postcode": "43119",
    "sg:province": "OH",
    "sg:tags": [
      "farm",
      "corn",
      "soybean"
    ],
    "wof:name": "Hunter Farm",
    "wof:placetype": "venue"
  },
  "geometry": {"coordinates":[-83.184497,39.970261],"type":"Point"}
}
