{
  "type": "Feature",
  "properties": {
    "iso:country":"US",
    "sg:address":"6740 Hardwood Dr",
    "sg:city":"Galloway",
    "sg:phone":"+1 614 878 1054",
    "sg:postcode":"43119",
    "sg:province":"OH",
    "sg:tags":[
        "farm",
        "corn",
        "soybean"
    ],
    "wof:name":"Hunter Farm",
    "wof:placetype":"venue"
},
  "geometry": {"coordinates":[-83.18449699999999,39.970261],"type":"Point"}
}