{
  "type": "Feature",
  "properties": {
    "iso:country":"US",
    "sg:address":"2437 Covington Rd",
    "sg:city":"Akron",
    "sg:classifiers":[
        {
            "category":"Building & Trades",
            "subcategory":"Construction",
            "type":"Services"
        }
    ],
    "sg:phone":"+1 330 867 9695",
    "sg:postcode":"44313",
    "sg:province":"OH",
    "sg:tags":[
        "hanging",
        "contractor"
    ],
    "wof:name":"Gray Painting",
    "wof:placetype":"venue"
},
  "geometry": {"coordinates":[-81.60153699999999,41.120731],"type":"Point"}
}