{
  "type": "Feature",
  "properties": {
    "addr:full": "2437 Covington Rd Akron OH 44313",
    "addr:housenumber": "2437",
    "addr:postcode": "44313",
    "addr:street": "Covington Rd",
    "iso:country": "US",
    "sg:address": "2437 Covington Rd",
    "sg:city": "Akron",
    "sg:classifiers": [
      {
        "category": "Building \u0026 Trades",
        "subcategory": "Construction",
        "type": "Services"
      }
    ],
    "sg:phone": "+1 330 867 9695",
    "sg:postcode": "44313",
    "sg:province": "OH",
    "sg:tags": [
      "hanging",
      "contractor"
    ],
    "wof:name": "Gray Painting",
    "wof:placetype": "venue"
  },
  "geometry": {"coordinates":[-81.601537,41.120731],"type":"Point"}
}
