{
  "type": "Feature",
  "properties": {
    "addr:full": "318 Louisiana Ave Perrysburg OH 43551",
    "addr:housenumber": "318",
    "addr:postcode": "43551",
    "addr:street": "Louisiana Ave",
    "iso:country": "US",
    "sg:address": "318 Louisiana Ave",
    "sg:city": "Perrysburg",
    "sg:classifiers": [
      {
        "category": "Shopping",
        "type": "Retail Goods"
      }
    ],
    "sg:phone": "+1 419 873 1783",
    "sg:postcode": "43551",
    "sg:province": "OH",
    "sg:tags": [
      "hearing",
      "equipment",
      "supply",
      "impaired"
    ],
    "wof:name": "Perrysburg Hearing Ctr LLC",
    "wof:placetype": "venue"
  },
  "geometry": {"coordinates":[-83.627967,41.557212],"type":"Point"}
}
