{
  "type": "Feature",
  "properties": {
    "iso:country":"US",
    "sg:address":"4455 Bethany Rd",
    "sg:city":"Mason",
    "sg:classifiers":[
        {
            "category":"Building & Trades",
            "subcategory":"Construction",
            "type":"Services"
        }
    ],
    "sg:phone":"+1 513 770 6767",
    "sg:postcode":"45040",
    "sg:province":"OH",
    "sg:tags":[
        "steel",
        "erectors",
        "fabrication",
        "welding"
    ],
    "wof:name":"Global Steel",
    "wof:placetype":"venue"
},
  "geometry": {"coordinates":[-84.30154,39.37841],"type":"Point"}
}