{
  "type": "Feature",
  "properties": {
    "iso:country":"US",
    "sg:address":"368 Ridge Rd",
    "sg:city":"Apple Creek",
    "sg:classifiers":[
        {
            "category":"Building & Trades",
            "subcategory":"Construction",
            "type":"Services"
        }
    ],
    "sg:phone":"+1 330 698 3708",
    "sg:postcode":"44657",
    "sg:province":"OH",
    "sg:tags":[
        "masonry",
        "contractor"
    ],
    "wof:name":"R D Masonry",
    "wof:placetype":"venue"
},
  "geometry": {"coordinates":[-81.076146,40.727263],"type":"Point"}
}