{
  "type": "Feature",
  "properties": {
    "iso:country":"US",
    "sg:address":"1609 S Main St",
    "sg:city":"Lima",
    "sg:classifiers":[
        {
            "category":"Organizations",
            "subcategory":"Religious Organization",
            "type":"Services"
        }
    ],
    "sg:phone":"+1 419 228 7777",
    "sg:postcode":"45804",
    "sg:province":"OH",
    "sg:tags":[
        "church"
    ],
    "wof:name":"Gospel Tabernacle Seventh Day",
    "wof:placetype":"venue"
},
  "geometry": {"coordinates":[-84.105282,40.712856],"type":"Point"}
}