{
  "type": "Feature",
  "properties": {
    "addr:full": "1609 S Main St Lima OH 45804",
    "addr:housenumber": "1609",
    "addr:postcode": "45804",
    "addr:street": "S Main St",
    "iso:country": "US",
    "sg:address": "1609 S Main St",
    "sg:city": "Lima",
    "sg:classifiers": [
      {
        "category": "Organizations",
        "subcategory": "Religious Organization",
        "type": "Services"
      }
    ],
    "sg:phone": "+1 419 228 7777",
    "sg:postcode": "45804",
    "sg:province": "OH",
    "sg:tags": [
      "church"
    ],
    "wof:name": "Gospel Tabernacle Seventh Day",
    "wof:placetype": "venue"
  },
  "geometry": {"coordinates":[-84.105282,40.712856],"type":"Point"}
}
