{
  "type": "Feature",
  "properties": {
    "addr:full":"2680 Hillvista Ln Cincinnati OH 45239",
    "addr:housenumber":"2680",
    "addr:postcode":"45239",
    "addr:street":"Hillvista Ln",
    "iso:country":"US",
    "sg:address":"2680 Hillvista Ln",
    "sg:city":"Cincinnati",
    "sg:classifiers":[
        {
            "category":"Real Estate",
            "subcategory":"Real Estate Agent",
            "type":"Services"
        }
    ],
    "sg:phone":"+1 513 542 4041",
    "sg:postcode":"45239",
    "sg:province":"OH",
    "sg:tags":[
        "management"
    ],
    "wof:name":"Shanandoah Inc",
    "wof:placetype":"venue"
},
  "geometry": {"coordinates":[-84.573525,39.192115],"type":"Point"}
}