{
  "type": "Feature",
  "properties": {
    "iso:country":"US",
    "sg:address":"9895 Softspring Dr",
    "sg:city":"Cincinnati",
    "sg:classifiers":[
        {
            "category":"Shopping",
            "subcategory":"Gifts & Souvenirs",
            "type":"Retail Goods"
        }
    ],
    "sg:phone":"+1 513 891 2056",
    "sg:postcode":"45241",
    "sg:province":"OH",
    "sg:tags":[
        "shop"
    ],
    "wof:name":"Crabtree and Evelyn",
    "wof:placetype":"venue"
},
  "geometry": {"coordinates":[-84.378086,39.30213],"type":"Point"}
}