{
  "type": "Feature",
  "properties": {
    "addr:full": "840 Pine St Wauseon OH 43567",
    "addr:housenumber": "840",
    "addr:postcode": "43567",
    "addr:street": "Pine St",
    "iso:country": "US",
    "sg:address": "840 Pine St",
    "sg:city": "Wauseon",
    "sg:classifiers": [
      {
        "category": "Professional",
        "subcategory": "Computer Services",
        "type": "Services"
      }
    ],
    "sg:phone": "+1 419 388 9210",
    "sg:postcode": "43567",
    "sg:province": "OH",
    "sg:tags": [
      "hardware",
      "provider",
      "internet",
      "software"
    ],
    "wof:name": "Page-Zone Web Hosting",
    "wof:placetype": "venue"
  },
  "geometry": {"coordinates":[-84.126184,41.557844],"type":"Point"}
}
