{
  "type": "Feature",
  "properties": {
    "iso:country":"US",
    "sg:address":"840 Pine St",
    "sg:city":"Wauseon",
    "sg:classifiers":[
        {
            "category":"Professional",
            "subcategory":"Computer Services",
            "type":"Services"
        }
    ],
    "sg:phone":"+1 419 388 9210",
    "sg:postcode":"43567",
    "sg:province":"OH",
    "sg:tags":[
        "hardware",
        "provider",
        "internet",
        "software"
    ],
    "wof:name":"Page-Zone Web Hosting",
    "wof:placetype":"venue"
},
  "geometry": {"coordinates":[-84.12618399999999,41.557844],"type":"Point"}
}