{
  "type": "Feature",
  "properties": {
    "iso:country":"US",
    "sg:address":"162 Main St",
    "sg:city":"Painesville",
    "sg:classifiers":[
        {
            "category":"Real Estate",
            "subcategory":"Real Estate Services",
            "type":"Services"
        }
    ],
    "sg:phone":"+1 440 942 6957",
    "sg:postcode":"44077",
    "sg:province":"OH",
    "sg:tags":[
        "abstract",
        "title"
    ],
    "wof:name":"Conway Title",
    "wof:placetype":"venue"
},
  "geometry": {"coordinates":[-81.241567,41.725766],"type":"Point"}
}