{
  "type": "Feature",
  "properties": {
    "addr:full": "156 Moorewood Ave Avon Lake OH 44012",
    "addr:housenumber": "156",
    "addr:postcode": "44012",
    "addr:street": "Moorewood Ave",
    "iso:country": "US",
    "sg:address": "156 Moorewood Ave",
    "sg:city": "Avon Lake",
    "sg:classifiers": [
      {
        "category": "Building \u0026 Trades",
        "subcategory": "Electrical",
        "type": "Services"
      }
    ],
    "sg:phone": "+1 440 670 2788",
    "sg:postcode": "44012",
    "sg:province": "OH",
    "sg:tags": [
      "electric",
      "contractor"
    ],
    "wof:name": "Bell's Electric Inc",
    "wof:placetype": "venue"
  },
  "geometry": {"coordinates":[-82.029953,41.507607],"type":"Point"}
}
