{
  "type": "Feature",
  "properties": {
    "addr:full": "426 Roosevelt Ct Portsmouth OH 45662",
    "addr:housenumber": "426",
    "addr:postcode": "45662",
    "addr:street": "Roosevelt Ct",
    "iso:country": "US",
    "sg:address": "426 Roosevelt Ct",
    "sg:city": "Portsmouth",
    "sg:classifiers": [
      {
        "category": "Shopping",
        "type": "Retail Goods"
      },
      {
        "category": "Wholesale",
        "subcategory": "Electrical",
        "type": "Manufacturing \u0026 Wholesale Goods"
      }
    ],
    "sg:phone": "+1 740 353 5900",
    "sg:postcode": "45662",
    "sg:province": "OH",
    "sg:tags": [
      "extinguisher",
      "supply",
      "fire",
      "equipment",
      "protection",
      "safety"
    ],
    "wof:name": "Jett Fire Equipment",
    "wof:placetype": "venue"
  },
  "geometry": {"coordinates":[-82.990056,38.733704],"type":"Point"}
}
