{
  "type": "Feature",
  "properties": {
    "addr:full":"6485 Maplecrest Ave Cleveland OH 44130",
    "addr:housenumber":"6485",
    "addr:postcode":"44130",
    "addr:street":"Maplecrest Ave",
    "iso:country":"US",
    "sg:address":"6485 Maplecrest Ave",
    "sg:city":"Cleveland",
    "sg:classifiers":[
        {
            "category":"Building & Trades",
            "subcategory":"Construction",
            "type":"Services"
        }
    ],
    "sg:phone":"+1 440 888 0479",
    "sg:postcode":"44130",
    "sg:province":"OH",
    "sg:tags":[
        "house"
    ],
    "wof:name":"Leone Remodeling",
    "wof:placetype":"venue"
},
  "geometry": {"coordinates":[-81.768033,41.387079],"type":"Point"}
}