{
  "type": "Feature",
  "properties": {
    "addr:full":"38017 French Creek Rd Avon OH 44011",
    "addr:housenumber":"38017",
    "addr:postcode":"44011",
    "addr:street":"French Creek Rd",
    "iso:country":"US",
    "sg:address":"38017 French Creek Rd",
    "sg:city":"Avon",
    "sg:classifiers":[
        {
            "category":"Building & Trades",
            "subcategory":"Electrical",
            "type":"Services"
        }
    ],
    "sg:phone":"+1 440 934 6011",
    "sg:postcode":"44011",
    "sg:province":"OH",
    "sg:tags":[
        "electrical",
        "contractor"
    ],
    "wof:name":"Moon Beam Power",
    "wof:placetype":"venue"
},
  "geometry": {"coordinates":[-82.050189,41.452589],"type":"Point"}
}