{
  "type": "Feature",
  "properties": {
    "addr:full": "859 2nd St Lancaster OH 43130",
    "addr:housenumber": "859",
    "addr:postcode": "43130",
    "addr:street": "2Nd St",
    "iso:country": "US",
    "sg:address": "859 2nd St",
    "sg:city": "Lancaster",
    "sg:classifiers": [
      {
        "category": "Building \u0026 Trades",
        "subcategory": "Construction",
        "type": "Services"
      }
    ],
    "sg:phone": "+1 740 689 2501",
    "sg:postcode": "43130",
    "sg:province": "OH",
    "sg:tags": [
      "roofing",
      "contractor"
    ],
    "wof:name": "Mike's Home Improvement",
    "wof:placetype": "venue"
  },
  "geometry": {"coordinates":[-82.601707,39.701566],"type":"Point"}
}
