{
  "type": "Feature",
  "properties": {
    "addr:full": "940 Fox Rd Middle Bass OH 43446",
    "addr:housenumber": "940",
    "addr:postcode": "43446",
    "addr:street": "Fox Rd Middle",
    "iso:country": "US",
    "sg:address": "940 Fox Rd",
    "sg:city": "Middle Bass",
    "sg:classifiers": [
      {
        "category": "Shopping",
        "subcategory": "Discount \u0026 Variety Stores",
        "type": "Retail Goods"
      }
    ],
    "sg:phone": "+1 419 285 2608",
    "sg:postcode": "43446",
    "sg:province": "OH",
    "sg:tags": [
      "merchandise",
      "general"
    ],
    "wof:name": "Middle Bass General Store",
    "wof:placetype": "venue"
  },
  "geometry": {"coordinates":[-82.812422,41.682192],"type":"Point"}
}
