{
  "type": "Feature",
  "properties": {
    "iso:country":"US",
    "sg:address":"4300 Plainville Rd",
    "sg:city":"Cincinnati",
    "sg:classifiers":[
        {
            "category":"Autos & Motor Vehicles",
            "subcategory":"Auto Supplies",
            "type":"Retail Goods"
        }
    ],
    "sg:phone":"+1 513 271 0343",
    "sg:postcode":"45227",
    "sg:province":"OH",
    "sg:tags":[
        "automobile",
        "parts"
    ],
    "wof:name":"Marfay Auto Parts Inc",
    "wof:placetype":"venue"
},
  "geometry": {"coordinates":[-84.379662,39.150628],"type":"Point"}
}