{
  "type": "Feature",
  "properties": {
    "addr:full":"17631 Rd 15 Columbus Grove OH 45830",
    "addr:housenumber":"17631",
    "addr:postcode":"45830",
    "addr:street":"Rd 15 Columbus Grove",
    "iso:country":"US",
    "sg:address":"17631 Rd 15",
    "sg:city":"Columbus Grove",
    "sg:classifiers":[
        {
            "category":"Manufacturing",
            "subcategory":"Metals",
            "type":"Manufacturing & Wholesale Goods"
        }
    ],
    "sg:phone":"+1 419 659 6030",
    "sg:postcode":"45830",
    "sg:province":"OH",
    "sg:tags":[
        "tower"
    ],
    "wof:name":"SBA Towers Inc",
    "wof:placetype":"venue"
},
  "geometry": {"coordinates":[-84.14870999999999,40.923746],"type":"Point"}
}