{
  "type": "Feature",
  "properties": {
    "addr:full":"5608 Harrison Ave Cincinnati OH 45248",
    "addr:housenumber":"5608",
    "addr:postcode":"45248",
    "addr:street":"Harrison Ave",
    "iso:country":"US",
    "sg:address":"5608 Harrison Ave",
    "sg:city":"Cincinnati",
    "sg:classifiers":[
        {
            "category":"Professional",
            "subcategory":"Lawyer & Legal Services",
            "type":"Services"
        }
    ],
    "sg:phone":"+1 513 251 1247",
    "sg:postcode":"45248",
    "sg:province":"OH",
    "sg:tags":[
        "attorney"
    ],
    "wof:name":"Ahlrichs & Ahlrichs",
    "wof:placetype":"venue"
},
  "geometry": {"coordinates":[-84.633715,39.165566],"type":"Point"}
}