{
  "type": "Feature",
  "properties": {
    "iso:country":"US",
    "sg:address":"1758 Lincoln Ave",
    "sg:city":"Girard",
    "sg:classifiers":[
        {
            "category":"Wholesale",
            "subcategory":"Office Equipment",
            "type":"Manufacturing & Wholesale Goods"
        }
    ],
    "sg:phone":"+1 330 539 6710",
    "sg:postcode":"44420",
    "sg:province":"OH",
    "sg:tags":[
        "machine",
        "business"
    ],
    "wof:name":"Royal Business Machines",
    "wof:placetype":"venue"
},
  "geometry": {"coordinates":[-80.666213,41.179431],"type":"Point"}
}