{
  "type": "Feature",
  "properties": {
    "addr:full": "1758 Lincoln Ave Girard OH 44420",
    "addr:housenumber": "1758",
    "addr:postcode": "44420",
    "addr:street": "Lincoln Ave",
    "iso:country": "US",
    "sg:address": "1758 Lincoln Ave",
    "sg:city": "Girard",
    "sg:classifiers": [
      {
        "category": "Wholesale",
        "subcategory": "Office Equipment",
        "type": "Manufacturing \u0026 Wholesale Goods"
      }
    ],
    "sg:phone": "+1 330 539 6710",
    "sg:postcode": "44420",
    "sg:province": "OH",
    "sg:tags": [
      "machine",
      "business"
    ],
    "wof:name": "Royal Business Machines",
    "wof:placetype": "venue"
  },
  "geometry": {"coordinates":[-80.666213,41.179431],"type":"Point"}
}
