{
  "type": "Feature",
  "properties": {
    "addr:full": "125 N Clay St Millersburg OH 44654",
    "addr:housenumber": "125",
    "addr:postcode": "44654",
    "addr:street": "N Clay St",
    "iso:country": "US",
    "sg:address": "125 N Clay St",
    "sg:city": "Millersburg",
    "sg:classifiers": [
      {
        "category": "Organizations",
        "subcategory": "Religious Organization",
        "type": "Services"
      }
    ],
    "sg:phone": "+1 330 674 1646",
    "sg:postcode": "44654",
    "sg:province": "OH",
    "sg:tags": [
      "church"
    ],
    "wof:name": "Christian Church-Millersburg",
    "wof:placetype": "venue"
  },
  "geometry": {"coordinates":[-81.917178,40.556117],"type":"Point"}
}
