{
  "type": "Feature",
  "properties": {
    "addr:full": "1362 Hamlin Dr Ashtabula OH 44004",
    "addr:housenumber": "1362",
    "addr:postcode": "44004",
    "addr:street": "Hamlin Dr",
    "iso:country": "US",
    "sg:address": "1362 Hamlin Dr",
    "sg:city": "Ashtabula",
    "sg:classifiers": [
      {
        "category": "Freight",
        "type": "Transportation"
      }
    ],
    "sg:phone": "+1 440 992 6870",
    "sg:postcode": "44004",
    "sg:province": "OH",
    "sg:tags": [
      "operator",
      "local",
      "trucking"
    ],
    "wof:name": "Wes Trucking",
    "wof:placetype": "venue"
  },
  "geometry": {"coordinates":[-80.797462,41.85246],"type":"Point"}
}
