{
  "type": "Feature",
  "properties": {
    "addr:full": "220 3rd Ave Gallipolis OH 45631",
    "addr:housenumber": "220",
    "addr:postcode": "45631",
    "addr:street": "3Rd Ave",
    "iso:country": "US",
    "sg:address": "220 3rd Ave",
    "sg:city": "Gallipolis",
    "sg:classifiers": [
      {
        "category": "Retail",
        "subcategory": "Car Wash",
        "type": "Services"
      }
    ],
    "sg:phone": "+1 740 441 9334",
    "sg:postcode": "45631",
    "sg:province": "OH",
    "sg:tags": [
      "automobile",
      "detail",
      "clean"
    ],
    "wof:name": "A \u0026 A Auto Detail",
    "wof:placetype": "venue"
  },
  "geometry": {"coordinates":[-82.208675,38.807252],"type":"Point"}
}
