{
  "type": "Feature",
  "properties": {
    "iso:country":"US",
    "sg:address":"231 W 3rd St",
    "sg:city":"Dover",
    "sg:classifiers":[
        {
            "category":"Professional",
            "subcategory":"Business Services",
            "type":"Services"
        }
    ],
    "sg:phone":"+1 330 364 2788",
    "sg:postcode":"44622",
    "sg:province":"OH",
    "wof:name":"Quality Business & Financial",
    "wof:placetype":"venue"
},
  "geometry": {"coordinates":[-81.47896,40.520579],"type":"Point"}
}