{
  "type": "Feature",
  "properties": {
    "addr:full":"804 Pike St Marietta OH 45750",
    "addr:housenumber":"804",
    "addr:postcode":"45750",
    "addr:street":"Pike St",
    "iso:country":"US",
    "sg:address":"804 Pike St",
    "sg:city":"Marietta",
    "sg:classifiers":[
        {
            "category":"Personal",
            "subcategory":"Beauty Salon",
            "type":"Services"
        }
    ],
    "sg:phone":"+1 740 374 5756",
    "sg:postcode":"45750",
    "sg:province":"OH",
    "sg:tags":[
        "manicuring"
    ],
    "wof:name":"California Nail USA",
    "wof:placetype":"venue"
},
  "geometry": {"coordinates":[-81.42156199999999,39.408174],"type":"Point"}
}