{
  "type": "Feature",
  "properties": {
    "addr:full":"1025 Hanover St Hamilton OH 45011",
    "addr:housenumber":"1025",
    "addr:postcode":"45011",
    "addr:street":"Hanover St",
    "iso:country":"US",
    "sg:address":"1025 Hanover St",
    "sg:city":"Hamilton",
    "sg:classifiers":[
        {
            "category":"Retail",
            "subcategory":"Repair Shop",
            "type":"Services"
        }
    ],
    "sg:phone":"+1 513 868 1661",
    "sg:postcode":"45011",
    "sg:province":"OH",
    "sg:tags":[
        "appliance"
    ],
    "wof:name":"George's Furniture & Appliance",
    "wof:placetype":"venue"
},
  "geometry": {"coordinates":[-84.552277,39.389625],"type":"Point"}
}