{
  "type": "Feature",
  "properties": {
    "iso:country":"US",
    "sg:address":"8734 Stonehenge Cir NW",
    "sg:city":"Pickerington",
    "sg:classifiers":[
        {
            "category":"Food & Beverages",
            "subcategory":"Groceries & Convenience Stores",
            "type":"Retail Goods"
        }
    ],
    "sg:phone":"+1 614 863 3109",
    "sg:postcode":"43147",
    "sg:province":"OH",
    "sg:tags":[
        "station",
        "gas"
    ],
    "wof:name":"BP",
    "wof:placetype":"venue"
},
  "geometry": {"coordinates":[-82.748806,39.934411],"type":"Point"}
}