{
  "type": "Feature",
  "properties": {
    "addr:full":"115 E Center St Blanchester OH 45107",
    "addr:housenumber":"115",
    "addr:postcode":"45107",
    "addr:street":"E Center St",
    "iso:country":"US",
    "sg:address":"115 E Center St",
    "sg:city":"Blanchester",
    "sg:classifiers":[
        {
            "category":"Shopping",
            "subcategory":"Florist",
            "type":"Retail Goods"
        }
    ],
    "sg:phone":"+1 937 783 3972",
    "sg:postcode":"45107",
    "sg:province":"OH",
    "wof:name":"Flowers By June",
    "wof:placetype":"venue"
},
  "geometry": {"coordinates":[-83.98835,39.294559],"type":"Point"}
}