{
  "type": "Feature",
  "properties": {
    "addr:full": "2811 Burkettsville-St Henry Rd Saint Henry OH 45883",
    "addr:housenumber": "2811",
    "addr:postcode": "45883",
    "addr:street": "Burkettsville-St Henry Rd",
    "iso:country": "US",
    "sg:address": "2811 Burkettsville-St Henry Rd",
    "sg:city": "Saint Henry",
    "sg:classifiers": [
      {
        "category": "Farming",
        "subcategory": "Farm",
        "type": "Manufacturing \u0026 Wholesale Goods"
      }
    ],
    "sg:phone": "+1 419 678 4209",
    "sg:postcode": "45883",
    "sg:province": "OH",
    "sg:tags": [
      "crop",
      "general"
    ],
    "wof:name": "Victor Moeder",
    "wof:placetype": "venue"
  },
  "geometry": {"coordinates":[-84.648282,40.433854],"type":"Point"}
}
