{
  "type": "Feature",
  "properties": {
    "addr:full":"23123 Center Ridge Rd Cleveland OH 44145",
    "addr:housenumber":"23123",
    "addr:postcode":"44145",
    "addr:street":"Center Ridge Rd",
    "iso:country":"US",
    "sg:address":"23123 Center Ridge Rd",
    "sg:city":"Cleveland",
    "sg:classifiers":[
        {
            "category":"Home & Garden",
            "subcategory":"Furniture",
            "type":"Retail Goods"
        }
    ],
    "sg:phone":"+1 440 331 4830",
    "sg:postcode":"44145",
    "sg:province":"OH",
    "sg:tags":[
        "interior",
        "decorating"
    ],
    "wof:name":"Warner Interiors Inc",
    "wof:placetype":"venue"
},
  "geometry": {"coordinates":[-81.87663999999999,41.456483],"type":"Point"}
}