{
  "type": "Feature",
  "properties": {
    "iso:country":"US",
    "sg:address":"4025 Amber Ct",
    "sg:city":"West Alexandria",
    "sg:classifiers":[
        {
            "category":"Building & Trades",
            "subcategory":"Electrical",
            "type":"Services"
        }
    ],
    "sg:phone":"+1 937 839 5752",
    "sg:postcode":"45381",
    "sg:province":"OH",
    "sg:tags":[
        "electric",
        "contractor"
    ],
    "wof:name":"Bitner Electrical Svc",
    "wof:placetype":"venue"
},
  "geometry": {"coordinates":[-84.555396,39.73049],"type":"Point"}
}