{
  "type": "Feature",
  "properties": {
    "addr:full":"38545 N Bay Dr Willoughby OH 44094",
    "addr:housenumber":"38545",
    "addr:postcode":"44094",
    "addr:street":"N Bay Dr",
    "iso:country":"US",
    "sg:address":"38545 N Bay Dr",
    "sg:city":"Willoughby",
    "sg:classifiers":[
        {
            "category":"Manufacturing",
            "subcategory":"Tools & Machinery",
            "type":"Manufacturing & Wholesale Goods"
        }
    ],
    "sg:phone":"+1 440 951 4995",
    "sg:postcode":"44094",
    "sg:province":"OH",
    "sg:tags":[
        "measuring",
        "material",
        "temperature"
    ],
    "sg:website":"www.dynametricsltd.com",
    "wof:name":"Dynametrics",
    "wof:placetype":"venue"
},
  "geometry": {"coordinates":[-81.39007599999999,41.67849],"type":"Point"}
}