{
  "type": "Feature",
  "properties": {
    "addr:full": "8876 State Rte 103 Upper Sandusky OH 43351",
    "addr:housenumber": "8876",
    "addr:postcode": "43351",
    "addr:street": "State Rte 103",
    "iso:country": "US",
    "sg:address": "8876 State Rte 103",
    "sg:city": "Upper Sandusky",
    "sg:phone": "+1 419 396 6274",
    "sg:postcode": "43351",
    "sg:province": "OH",
    "sg:tags": [
      "farm",
      "corn",
      "wheat",
      "soybean"
    ],
    "wof:name": "Mewhorter Farm",
    "wof:placetype": "venue"
  },
  "geometry": {"coordinates":[-83.289243,40.941887],"type":"Point"}
}
