{
  "type": "Feature",
  "properties": {
    "iso:country":"US",
    "sg:address":"3787 E 147th St",
    "sg:city":"Cleveland",
    "sg:classifiers":[
        {
            "category":"Building & Trades",
            "subcategory":"Plumbing",
            "type":"Services"
        }
    ],
    "sg:phone":"+1 216 283 4597",
    "sg:postcode":"44128",
    "sg:province":"OH",
    "sg:tags":[
        "contractor"
    ],
    "wof:name":"W Primm Plumbing Inc",
    "wof:placetype":"venue"
},
  "geometry": {"coordinates":[-81.578471,41.454041],"type":"Point"}
}