{
  "type": "Feature",
  "properties": {
    "addr:full": "501 8th Dr NE New Philadelphia OH 44663",
    "addr:housenumber": "501",
    "addr:postcode": "44663",
    "addr:street": "8Th Dr Ne",
    "iso:country": "US",
    "sg:address": "501 8th Dr NE",
    "sg:city": "New Philadelphia",
    "sg:classifiers": [
      {
        "category": "Retail",
        "subcategory": "Repair Shop",
        "type": "Services"
      }
    ],
    "sg:phone": "+1 330 364 1144",
    "sg:postcode": "44663",
    "sg:province": "OH",
    "sg:tags": [
      "upholsterer"
    ],
    "wof:name": "Kalt's Upholstering",
    "wof:placetype": "venue"
  },
  "geometry": {"coordinates":[-81.42751,40.484299],"type":"Point"}
}
