{
  "type": "Feature",
  "properties": {
    "iso:country":"US",
    "sg:address":"7 W Twenty Nine Dr",
    "sg:city":"Nelsonville",
    "sg:classifiers":[
        {
            "category":"Government",
            "subcategory":"Jail",
            "type":"Public Place"
        }
    ],
    "sg:phone":"+1 740 753 5000",
    "sg:postcode":"45764",
    "sg:province":"OH",
    "sg:tags":[
        "parole",
        "center"
    ],
    "wof:name":"Septa Correctional Facility",
    "wof:placetype":"venue"
},
  "geometry": {"coordinates":[-82.243489,39.457312],"type":"Point"}
}