{
  "type": "Feature",
  "properties": {
    "iso:country":"US",
    "sg:address":"1700 Pearl Rd",
    "sg:city":"Brunswick",
    "sg:classifiers":[
        {
            "category":"Autos & Motor Vehicles",
            "subcategory":"Automobile Sales",
            "type":"Retail Goods"
        }
    ],
    "sg:phone":"+1 330 225 3700",
    "sg:postcode":"44212",
    "sg:province":"OH",
    "sg:tags":[
        "car",
        "dealer"
    ],
    "sg:website":"www.mullinaxlm.com",
    "wof:name":"Mullinax Lincoln Mercury",
    "wof:placetype":"venue"
},
  "geometry": {"coordinates":[-81.841492,41.228426],"type":"Point"}
}