{
  "type": "Feature",
  "properties": {
    "addr:full":"50 Park Ave E Mansfield OH 44902",
    "addr:housenumber":"50",
    "addr:postcode":"44902",
    "addr:street":"Park Ave E",
    "iso:country":"US",
    "sg:address":"50 Park Ave E",
    "sg:city":"Mansfield",
    "sg:classifiers":[
        {
            "category":"Government",
            "subcategory":"Office",
            "type":"Public Place"
        }
    ],
    "sg:phone":"+1 419 755 5550",
    "sg:postcode":"44902",
    "sg:province":"OH",
    "sg:tags":[
        "executive"
    ],
    "wof:name":"County of Richland",
    "wof:placetype":"venue"
},
  "geometry": {"coordinates":[-82.513212,40.758468],"type":"Point"}
}