{
  "type": "Feature",
  "properties": {
    "addr:full":"683 Miamisburg Centerville Rd Dayton OH 45459",
    "addr:housenumber":"683",
    "addr:postcode":"45459",
    "addr:street":"Miamisburg Centerville Rd",
    "iso:country":"US",
    "sg:address":"683 Miamisburg Centerville Rd",
    "sg:city":"Dayton",
    "sg:classifiers":[
        {
            "category":"Professional",
            "subcategory":"Lawyer & Legal Services",
            "type":"Services"
        }
    ],
    "sg:phone":"+1 937 434 2249",
    "sg:postcode":"45459",
    "sg:province":"OH",
    "sg:tags":[
        "attorney"
    ],
    "wof:name":"Richard L Kaplan",
    "wof:placetype":"venue"
},
  "geometry": {"coordinates":[-84.17075199999999,39.62805],"type":"Point"}
}