{
  "type": "Feature",
  "properties": {
    "addr:full": "121 W River Rd N Elyria OH 44035",
    "addr:housenumber": "121",
    "addr:postcode": "44035",
    "addr:street": "W River Rd N",
    "iso:country": "US",
    "sg:address": "121 W River Rd N",
    "sg:city": "Elyria",
    "sg:classifiers": [
      {
        "category": "Education",
        "subcategory": "School",
        "type": "Public Place"
      }
    ],
    "sg:phone": "+1 440 323 6526",
    "sg:postcode": "44035",
    "sg:province": "OH",
    "wof:name": "Elyria Family Ctr",
    "wof:placetype": "venue"
  },
  "geometry": {"coordinates":[-82.116106,41.365788],"type":"Point"}
}
