{
  "type": "Feature",
  "properties": {
    "iso:country":"US",
    "sg:address":"628 Jefferson St",
    "sg:city":"Fairborn",
    "sg:classifiers":[
        {
            "category":"Building & Trades",
            "subcategory":"Construction",
            "type":"Services"
        }
    ],
    "sg:phone":"+1 937 878 8786",
    "sg:postcode":"45324",
    "sg:province":"OH",
    "sg:tags":[
        "hanging",
        "contractor"
    ],
    "wof:name":"Painting Etc",
    "wof:placetype":"venue"
},
  "geometry": {"coordinates":[-84.009252,39.828226],"type":"Point"}
}