{
  "type": "Feature",
  "properties": {
    "iso:country":"US",
    "sg:address":"1910 W Market St",
    "sg:city":"Akron",
    "sg:classifiers":[
        {
            "category":"Utilities",
            "subcategory":"Electric",
            "type":"Services"
        }
    ],
    "sg:phone":"+1 419 625 7420",
    "sg:postcode":"44313",
    "sg:province":"OH",
    "wof:name":"Ohio Edison Company",
    "wof:placetype":"venue"
},
  "geometry": {"coordinates":[-81.576075,41.112413],"type":"Point"}
}