{
  "type": "Feature",
  "properties": {
    "addr:full":"818 E 185th St Cleveland OH 44119",
    "addr:housenumber":"818",
    "addr:postcode":"44119",
    "addr:street":"E 185Th St",
    "iso:country":"US",
    "sg:address":"818 E 185th St",
    "sg:city":"Cleveland",
    "sg:classifiers":[
        {
            "category":"Restaurant",
            "type":"Food & Drink"
        }
    ],
    "sg:phone":"+1 216 486 7777",
    "sg:postcode":"44119",
    "sg:province":"OH",
    "sg:tags":[
        "shop",
        "coffee"
    ],
    "wof:name":"Arabica",
    "wof:placetype":"venue"
},
  "geometry": {"coordinates":[-81.549931,41.585696],"type":"Point"}
}