{
  "type": "Feature",
  "properties": {
    "addr:full":"105 Keewaydin Dr Willoughby OH 44095",
    "addr:housenumber":"105",
    "addr:postcode":"44095",
    "addr:street":"Keewaydin Dr",
    "iso:country":"US",
    "sg:address":"105 Keewaydin Dr",
    "sg:city":"Willoughby",
    "sg:classifiers":[
        {
            "category":"Wholesale",
            "subcategory":"Auto Parts",
            "type":"Manufacturing & Wholesale Goods"
        }
    ],
    "sg:phone":"+1 440 975 1938",
    "sg:postcode":"44095",
    "sg:province":"OH",
    "wof:name":"Foreign and Dom Auto Bdy Sp",
    "wof:placetype":"venue"
},
  "geometry": {"coordinates":[-81.43728400000001,41.6674],"type":"Point"}
}