{
  "type": "Feature",
  "properties": {
    "addr:full": "650 Graham Rd Cuyahoga Falls OH 44221",
    "addr:housenumber": "650",
    "addr:postcode": "44221",
    "addr:street": "Graham Rd",
    "iso:country": "US",
    "sg:address": "650 Graham Rd",
    "sg:city": "Cuyahoga Falls",
    "sg:classifiers": [
      {
        "category": "Health Services",
        "subcategory": "Doctor",
        "type": "Services"
      }
    ],
    "sg:phone": "+1 330 923 0822",
    "sg:postcode": "44221",
    "sg:province": "OH",
    "sg:tags": [
      "dentist"
    ],
    "wof:name": "Robert J Kinkoph DDS",
    "wof:placetype": "venue"
  },
  "geometry": {"coordinates":[-81.491187,41.159248],"type":"Point"}
}
