{
  "type": "Feature",
  "properties": {
    "iso:country":"US",
    "sg:address":"974 State Rte 28",
    "sg:city":"Milford",
    "sg:classifiers":[
        {
            "category":"Home & Garden",
            "subcategory":"Building Materials",
            "type":"Retail Goods"
        }
    ],
    "sg:phone":"+1 513 831 4395",
    "sg:postcode":"45150",
    "sg:province":"OH",
    "sg:tags":[
        "lumber"
    ],
    "wof:name":"Hardwood Warehouse LLC",
    "wof:placetype":"venue"
},
  "geometry": {"coordinates":[-84.24703,39.192632],"type":"Point"}
}