{
  "type": "Feature",
  "properties": {
    "addr:full": "974 State Rte 28 Milford OH 45150",
    "addr:housenumber": "974",
    "addr:postcode": "45150",
    "addr:street": "State Rte 28",
    "iso:country": "US",
    "sg:address": "974 State Rte 28",
    "sg:city": "Milford",
    "sg:classifiers": [
      {
        "category": "Home \u0026 Garden",
        "subcategory": "Building Materials",
        "type": "Retail Goods"
      }
    ],
    "sg:phone": "+1 513 831 4395",
    "sg:postcode": "45150",
    "sg:province": "OH",
    "sg:tags": [
      "lumber"
    ],
    "wof:name": "Hardwood Warehouse LLC",
    "wof:placetype": "venue"
  },
  "geometry": {"coordinates":[-84.24703,39.192632],"type":"Point"}
}
