{
  "type": "Feature",
  "properties": {
    "iso:country":"US",
    "sg:address":"2 S Main St",
    "sg:city":"Akron",
    "sg:classifiers":[
        {
            "category":"Government",
            "subcategory":"Office",
            "type":"Public Place"
        }
    ],
    "sg:phone":"+1 330 375 5820",
    "sg:postcode":"44308",
    "sg:province":"OH",
    "sg:tags":[
        "federal",
        "wage",
        "control",
        "agency"
    ],
    "wof:name":"Employment Standards ADM",
    "wof:placetype":"venue"
},
  "geometry": {"coordinates":[-81.51787299999999,41.082629],"type":"Point"}
}