{
  "type": "Feature",
  "properties": {
    "addr:full": "3708 Elm Rd Stow OH 44224",
    "addr:housenumber": "3708",
    "addr:postcode": "44224",
    "addr:street": "Elm Rd",
    "iso:country": "US",
    "sg:address": "3708 Elm Rd",
    "sg:city": "Stow",
    "sg:classifiers": [
      {
        "category": "Professional",
        "type": "Services"
      }
    ],
    "sg:phone": "+1 330 524 1542",
    "sg:postcode": "44224",
    "sg:province": "OH",
    "wof:name": "John A Roseman",
    "wof:placetype": "venue"
  },
  "geometry": {"coordinates":[-81.442406,41.164769],"type":"Point"}
}
