{
  "type": "Feature",
  "properties": {
    "addr:full":"4030 Smith Rd Cincinnati OH 45212",
    "addr:housenumber":"4030",
    "addr:postcode":"45212",
    "addr:street":"Smith Rd",
    "iso:country":"US",
    "sg:address":"4030 Smith Rd",
    "sg:city":"Cincinnati",
    "sg:classifiers":[
        {
            "category":"Health Services",
            "subcategory":"Doctor",
            "type":"Services"
        }
    ],
    "sg:phone":"+1 513 984 0330",
    "sg:postcode":"45212",
    "sg:province":"OH",
    "sg:tags":[
        "physician",
        "surgeon"
    ],
    "wof:name":"Vein Solutions",
    "wof:placetype":"venue"
},
  "geometry": {"coordinates":[-84.44588,39.152192],"type":"Point"}
}