{
  "type": "Feature",
  "properties": {
    "iso:country":"US",
    "sg:address":"6161 Busch Blvd",
    "sg:city":"Columbus",
    "sg:classifiers":[
        {
            "category":"Local Transit",
            "type":"Transportation"
        }
    ],
    "sg:phone":"+1 614 846 2227",
    "sg:postcode":"43229",
    "sg:province":"OH",
    "sg:tags":[
        "handicapped"
    ],
    "wof:name":"People's Transportation Inc",
    "wof:placetype":"venue"
},
  "geometry": {"coordinates":[-82.99268499999999,40.090008],"type":"Point"}
}