{
  "type": "Feature",
  "properties": {
    "addr:full":"14410 Shade Rd Shade OH 45776",
    "addr:housenumber":"14410",
    "addr:postcode":"45776",
    "addr:street":"Shade Rd",
    "iso:country":"US",
    "sg:address":"14410 Shade Rd",
    "sg:city":"Shade",
    "sg:classifiers":[
        {
            "category":"Building & Trades",
            "subcategory":"Construction",
            "type":"Services"
        }
    ],
    "sg:phone":"+1 740 592 3481",
    "sg:postcode":"45776",
    "sg:province":"OH",
    "sg:tags":[
        "contractor"
    ],
    "wof:name":"Ralphs Welding & Fabrication",
    "wof:placetype":"venue"
},
  "geometry": {"coordinates":[-82.02804,39.225995],"type":"Point"}
}