{
  "type": "Feature",
  "properties": {
    "iso:country":"US",
    "sg:address":"1617 33rd St SW",
    "sg:city":"Canton",
    "sg:classifiers":[
        {
            "category":"Professional",
            "type":"Services"
        }
    ],
    "sg:phone":"+1 330 484 7426",
    "sg:postcode":"44706",
    "sg:province":"OH",
    "wof:name":"Brian S Mitchell",
    "wof:placetype":"venue"
},
  "geometry": {"coordinates":[-81.394116,40.761551],"type":"Point"}
}