{
  "type": "Feature",
  "properties": {
    "addr:full":"2980 S Hametown Rd Barberton OH 44203",
    "addr:housenumber":"2980",
    "addr:postcode":"44203",
    "addr:street":"S Hametown Rd",
    "iso:country":"US",
    "sg:address":"2980 S Hametown Rd",
    "sg:city":"Barberton",
    "sg:classifiers":[
        {
            "category":"Shopping",
            "subcategory":"Used Merchandise",
            "type":"Retail Goods"
        }
    ],
    "sg:phone":"+1 330 825 8695",
    "sg:postcode":"44203",
    "sg:province":"OH",
    "sg:tags":[
        "antique"
    ],
    "wof:name":"Norton Antique Mall",
    "wof:placetype":"venue"
},
  "geometry": {"coordinates":[-81.667001,41.050302],"type":"Point"}
}