{
  "type": "Feature",
  "properties": {
    "addr:full":"214 Broadway St Jackson OH 45640",
    "addr:housenumber":"214",
    "addr:postcode":"45640",
    "addr:street":"Broadway St",
    "iso:country":"US",
    "sg:address":"214 Broadway St",
    "sg:city":"Jackson",
    "sg:classifiers":[
        {
            "category":"Shopping",
            "subcategory":"Jewelry",
            "type":"Retail Goods"
        }
    ],
    "sg:phone":"+1 740 286 2326",
    "sg:postcode":"45640",
    "sg:province":"OH",
    "sg:tags":[
        "jeweler"
    ],
    "wof:name":"A L Terry Jewelers",
    "wof:placetype":"venue"
},
  "geometry": {"coordinates":[-82.637079,39.051747],"type":"Point"}
}