{
  "type": "Feature",
  "properties": {
    "iso:country":"US",
    "sg:address":"4495 Mount Carmel Tobasco Rd",
    "sg:city":"Cincinnati",
    "sg:classifiers":[
        {
            "category":"Health Services",
            "subcategory":"Clinic",
            "type":"Services"
        }
    ],
    "sg:phone":"+1 513 752 5533",
    "sg:postcode":"45244",
    "sg:province":"OH",
    "sg:tags":[
        "home"
    ],
    "wof:name":"Comfort Keepers",
    "wof:placetype":"venue"
},
  "geometry": {"coordinates":[-84.299505,39.1028],"type":"Point"}
}