{
  "type": "Feature",
  "properties": {
    "iso:country":"US",
    "sg:address":"2889 W Johnstown Rd",
    "sg:city":"Columbus",
    "sg:classifiers":[
        {
            "category":"Wholesale",
            "subcategory":"Machinery & Supplies",
            "type":"Manufacturing & Wholesale Goods"
        }
    ],
    "sg:phone":"+1 614 475 2166",
    "sg:postcode":"43219",
    "sg:province":"OH",
    "sg:tags":[
        "equipment",
        "industrial"
    ],
    "wof:name":"Rapid Screen Products Corp",
    "wof:placetype":"venue"
},
  "geometry": {"coordinates":[-82.90683,40.008791],"type":"Point"}
}