{
  "type": "Feature",
  "properties": {
    "addr:full": "2889 W Johnstown Rd Columbus OH 43219",
    "addr:housenumber": "2889",
    "addr:postcode": "43219",
    "addr:street": "W Johnstown Rd",
    "iso:country": "US",
    "sg:address": "2889 W Johnstown Rd",
    "sg:city": "Columbus",
    "sg:classifiers": [
      {
        "category": "Wholesale",
        "subcategory": "Machinery \u0026 Supplies",
        "type": "Manufacturing \u0026 Wholesale Goods"
      }
    ],
    "sg:phone": "+1 614 475 2166",
    "sg:postcode": "43219",
    "sg:province": "OH",
    "sg:tags": [
      "equipment",
      "industrial"
    ],
    "wof:name": "Rapid Screen Products Corp",
    "wof:placetype": "venue"
  },
  "geometry": {"coordinates":[-82.90683,40.008791],"type":"Point"}
}
