{
  "type": "Feature",
  "properties": {
    "addr:full":"8240 Infirmary Rd Ravenna OH 44266",
    "addr:postcode":"8240;44266",
    "addr:street":"Infirmary Rd",
    "iso:country":"US",
    "sg:address":"8240 Infirmary Rd",
    "sg:city":"Ravenna",
    "sg:classifiers":[
        {
            "category":"Government",
            "subcategory":"Police Station",
            "type":"Public Place"
        }
    ],
    "sg:phone":"+1 330 325 1023",
    "sg:postcode":"44266",
    "sg:province":"OH",
    "sg:tags":[
        "sheriff"
    ],
    "sg:website":"www.co.portage.oh.us",
    "wof:name":"Portage County Sheriff's Dept",
    "wof:placetype":"venue"
},
  "geometry": {"coordinates":[-81.260431,41.213632],"type":"Point"}
}