{
  "type": "Feature",
  "properties": {
    "addr:full":"9112 Joppa Rd Huron OH 44839",
    "addr:housenumber":"9112",
    "addr:postcode":"44839",
    "addr:street":"Joppa Rd",
    "iso:country":"US",
    "sg:address":"9112 Joppa Rd",
    "sg:city":"Huron",
    "sg:classifiers":[
        {
            "category":"Farming",
            "subcategory":"Farm",
            "type":"Manufacturing & Wholesale Goods"
        }
    ],
    "sg:phone":"+1 440 965 4251",
    "sg:postcode":"44839",
    "sg:province":"OH",
    "sg:tags":[
        "crop",
        "general"
    ],
    "wof:name":"Nuhn Farms",
    "wof:placetype":"venue"
},
  "geometry": {"coordinates":[-82.433493,41.355727],"type":"Point"}
}