{
  "type": "Feature",
  "properties": {
    "addr:full":"1130 1/2 Hubbard Rd Youngstown OH 44505",
    "addr:housenumber":"1130 1 / 2",
    "addr:postcode":"44505",
    "addr:street":"Hubbard Rd",
    "iso:country":"US",
    "sg:address":"1130 1/2 Hubbard Rd",
    "sg:city":"Youngstown",
    "sg:classifiers":[
        {
            "category":"Wholesale",
            "subcategory":"Machinery & Supplies",
            "type":"Manufacturing & Wholesale Goods"
        }
    ],
    "sg:phone":"+1 330 743 8118",
    "sg:postcode":"44505",
    "sg:province":"OH",
    "sg:tags":[
        "equipment",
        "welding"
    ],
    "wof:name":"Davis Mfg",
    "wof:placetype":"venue"
},
  "geometry": {"coordinates":[-80.630501,41.123989],"type":"Point"}
}