{
  "type": "Feature",
  "properties": {
    "addr:full": "413 W Church St Newark OH 43055",
    "addr:housenumber": "413",
    "addr:postcode": "43055",
    "addr:street": "W Church St",
    "iso:country": "US",
    "sg:address": "413 W Church St",
    "sg:city": "Newark",
    "sg:classifiers": [
      {
        "category": "Personal",
        "subcategory": "Beauty Salon",
        "type": "Services"
      }
    ],
    "sg:phone": "+1 740 345 7714",
    "sg:postcode": "43055",
    "sg:province": "OH",
    "wof:name": "Terrific Hair \u0026 Nails",
    "wof:placetype": "venue"
  },
  "geometry": {"coordinates":[-82.419837,40.057341],"type":"Point"}
}
