{
  "type": "Feature",
  "properties": {
    "addr:full":"129 Broad St Wadsworth OH 44281",
    "addr:housenumber":"129",
    "addr:postcode":"44281",
    "addr:street":"Broad St",
    "iso:country":"US",
    "sg:address":"129 Broad St",
    "sg:city":"Wadsworth",
    "sg:classifiers":[
        {
            "category":"Wholesale",
            "subcategory":"Auto Parts",
            "type":"Manufacturing & Wholesale Goods"
        }
    ],
    "sg:phone":"+1 330 334 2578",
    "sg:postcode":"44281",
    "sg:province":"OH",
    "wof:name":"NAPA Auto Parts",
    "wof:placetype":"venue"
},
  "geometry": {"coordinates":[-81.728657,41.025376],"type":"Point"}
}