{
  "type": "Feature",
  "properties": {
    "addr:full": "8642 Mentor Ave Mentor OH 44060",
    "addr:housenumber": "8642",
    "addr:postcode": "44060",
    "addr:street": "Mentor Ave",
    "iso:country": "US",
    "sg:address": "8642 Mentor Ave",
    "sg:city": "Mentor",
    "sg:classifiers": [
      {
        "category": "Manufacturing",
        "subcategory": "Food",
        "type": "Manufacturing \u0026 Wholesale Goods"
      }
    ],
    "sg:phone": "+1 440 255 4740",
    "sg:postcode": "44060",
    "sg:province": "OH",
    "sg:tags": [
      "mfg"
    ],
    "wof:name": "My Personal Winery",
    "wof:placetype": "venue"
  },
  "geometry": {"coordinates":[-81.331811,41.669864],"type":"Point"}
}
