{
  "type": "Feature",
  "properties": {
    "iso:country":"US",
    "sg:address":"211 W Coshocton St",
    "sg:city":"Johnstown",
    "sg:classifiers":[
        {
            "category":"Government",
            "subcategory":"Post Office",
            "type":"Public Place"
        }
    ],
    "sg:phone":"+1 740 967 7021",
    "sg:postcode":"43031",
    "sg:province":"OH",
    "wof:name":"US Post Office",
    "wof:placetype":"venue"
},
  "geometry": {"coordinates":[-82.689162,40.151285],"type":"Point"}
}