{
  "type": "Feature",
  "properties": {
    "iso:country":"US",
    "sg:address":"116 W 5th St",
    "sg:city":"Dayton",
    "sg:classifiers":[
        {
            "category":"Manufacturing",
            "subcategory":"Metals",
            "type":"Manufacturing & Wholesale Goods"
        }
    ],
    "sg:phone":"+1 937 281 2385",
    "sg:postcode":"45402",
    "sg:province":"OH",
    "sg:tags":[
        "pipe",
        "lining",
        "coating"
    ],
    "wof:name":"Abbots Road & Gallery",
    "wof:placetype":"venue"
},
  "geometry": {"coordinates":[-84.19425200000001,39.756165],"type":"Point"}
}