{
  "type": "Feature",
  "properties": {
    "addr:full": "703 E Weber Rd Columbus OH 43211",
    "addr:housenumber": "703",
    "addr:postcode": "43211",
    "addr:street": "E Weber Rd",
    "iso:country": "US",
    "sg:address": "703 E Weber Rd",
    "sg:city": "Columbus",
    "sg:classifiers": [
      {
        "category": "Autos \u0026 Motor Vehicles",
        "subcategory": "Automobile Sales",
        "type": "Retail Goods"
      }
    ],
    "sg:phone": "+1 614 472 2886",
    "sg:postcode": "43211",
    "sg:province": "OH",
    "sg:tags": [
      "used"
    ],
    "wof:name": "Corvi Auto Sales",
    "wof:placetype": "venue"
  },
  "geometry": {"coordinates":[-82.993066,40.023936],"type":"Point"}
}
