{
  "type": "Feature",
  "properties": {
    "addr:full": "2387 Vendome Dr Columbus OH 43219",
    "addr:housenumber": "2387",
    "addr:postcode": "43219",
    "addr:street": "Vendome Dr",
    "iso:country": "US",
    "sg:address": "2387 Vendome Dr",
    "sg:city": "Columbus",
    "sg:classifiers": [
      {
        "category": "Manufacturing",
        "subcategory": "Printing",
        "type": "Manufacturing \u0026 Wholesale Goods"
      }
    ],
    "sg:phone": "+1 614 257 0296",
    "sg:postcode": "43219",
    "sg:province": "OH",
    "sg:tags": [
      "publishing"
    ],
    "wof:name": "New Creation Graphics",
    "wof:placetype": "venue"
  },
  "geometry": {"coordinates":[-82.945151,40.00247],"type":"Point"}
}
