{
  "type": "Feature",
  "properties": {
    "addr:full": "1785 Valley Brook Pl Dayton OH 45459",
    "addr:housenumber": "1785",
    "addr:postcode": "45459",
    "addr:street": "Valley Brook Pl",
    "iso:country": "US",
    "sg:address": "1785 Valley Brook Pl",
    "sg:city": "Dayton",
    "sg:classifiers": [
      {
        "category": "Banks \u0026 Credit Unions",
        "subcategory": "Financial Services",
        "type": "Services"
      }
    ],
    "sg:phone": "+1 937 435 7566",
    "sg:postcode": "45459",
    "sg:province": "OH",
    "sg:tags": [
      "trust",
      "investment",
      "real estate"
    ],
    "wof:name": "Next Move Investments LLC",
    "wof:placetype": "venue"
  },
  "geometry": {"coordinates":[-84.121681,39.631444],"type":"Point"}
}
