{
  "type": "Feature",
  "properties": {
    "iso:country":"US",
    "sg:address":"1785 Valley Brook Pl",
    "sg:city":"Dayton",
    "sg:classifiers":[
        {
            "category":"Banks & Credit Unions",
            "subcategory":"Financial Services",
            "type":"Services"
        }
    ],
    "sg:phone":"+1 937 435 7566",
    "sg:postcode":"45459",
    "sg:province":"OH",
    "sg:tags":[
        "trust",
        "investment",
        "real estate"
    ],
    "wof:name":"Next Move Investments LLC",
    "wof:placetype":"venue"
},
  "geometry": {"coordinates":[-84.121681,39.631444],"type":"Point"}
}