{
  "type": "Feature",
  "properties": {
    "iso:country":"US",
    "sg:address":"928 Van Buren Way",
    "sg:city":"Medina",
    "sg:classifiers":[
        {
            "category":"Building & Trades",
            "subcategory":"Construction",
            "type":"Services"
        }
    ],
    "sg:phone":"+1 330 722 3242",
    "sg:postcode":"44256",
    "sg:province":"OH",
    "sg:tags":[
        "carpentry",
        "contractor"
    ],
    "wof:name":"Creative Carpentry",
    "wof:placetype":"venue"
},
  "geometry": {"coordinates":[-81.888357,41.147205],"type":"Point"}
}