{
  "type": "Feature",
  "properties": {
    "addr:full":"2138 Lee Rd Cleveland OH 44118",
    "addr:housenumber":"2138",
    "addr:postcode":"44118",
    "addr:street":"Lee Rd",
    "iso:country":"US",
    "sg:address":"2138 Lee Rd",
    "sg:city":"Cleveland",
    "sg:classifiers":[
        {
            "category":"Building & Trades",
            "subcategory":"Construction",
            "type":"Services"
        }
    ],
    "sg:phone":"+1 216 321 6695",
    "sg:postcode":"44118",
    "sg:province":"OH",
    "sg:tags":[
        "house",
        "general",
        "contractor"
    ],
    "wof:name":"Sagamore Builders Inc",
    "wof:placetype":"venue"
},
  "geometry": {"coordinates":[-81.565551,41.502155],"type":"Point"}
}