{
  "type": "Feature",
  "properties": {
    "iso:country":"US",
    "sg:address":"655 Fox Run Rd",
    "sg:city":"Findlay",
    "sg:classifiers":[
        {
            "category":"Organizations",
            "subcategory":"Non-profit Organization",
            "type":"Services"
        }
    ],
    "sg:phone":"+1 419 422 3833",
    "sg:postcode":"45840",
    "sg:province":"OH",
    "wof:name":"Heartland Board-Realtors",
    "wof:placetype":"venue"
},
  "geometry": {"coordinates":[-83.602839,41.046074],"type":"Point"}
}