{
  "type": "Feature",
  "properties": {
    "iso:country":"US",
    "sg:address":"1308 Research Park Dr",
    "sg:city":"Beavercreek",
    "sg:classifiers":[
        {
            "category":"Professional",
            "subcategory":"Management & Consulting",
            "type":"Services"
        }
    ],
    "sg:phone":"+1 937 431 1900",
    "sg:postcode":"45432",
    "sg:province":"OH",
    "sg:tags":[
        "consultant",
        "business"
    ],
    "wof:name":"International Trade Bridge",
    "wof:placetype":"venue"
},
  "geometry": {"coordinates":[-84.06594,39.732481],"type":"Point"}
}