{
  "type": "Feature",
  "properties": {
    "addr:full": "5499 Constitution Blvd Hilliard OH 43026",
    "addr:housenumber": "5499",
    "addr:postcode": "43026",
    "addr:street": "Constitution Blvd",
    "iso:country": "US",
    "sg:address": "5499 Constitution Blvd",
    "sg:city": "Hilliard",
    "sg:classifiers": [
      {
        "category": "Sports \u0026 Exercise",
        "subcategory": "Bowling",
        "type": "Entertainment"
      }
    ],
    "sg:phone": "+1 614 876 2475",
    "sg:postcode": "43026",
    "sg:province": "OH",
    "sg:tags": [
      "lounge",
      "lane",
      "cocktail"
    ],
    "wof:name": "Northwest Lanes",
    "wof:placetype": "venue"
  },
  "geometry": {"coordinates":[-83.160384,40.023978],"type":"Point"}
}
