{
  "type": "Feature",
  "properties": {
    "iso:country":"US",
    "sg:address":"5499 Constitution Blvd",
    "sg:city":"Hilliard",
    "sg:classifiers":[
        {
            "category":"Sports & Exercise",
            "subcategory":"Bowling",
            "type":"Entertainment"
        }
    ],
    "sg:phone":"+1 614 876 2475",
    "sg:postcode":"43026",
    "sg:province":"OH",
    "sg:tags":[
        "lounge",
        "lane",
        "cocktail"
    ],
    "wof:name":"Northwest Lanes",
    "wof:placetype":"venue"
},
  "geometry": {"coordinates":[-83.16038399999999,40.023978],"type":"Point"}
}