{
  "type": "Feature",
  "properties": {
    "addr:full":"8120 Garnet Dr Dayton OH 45458",
    "addr:housenumber":"8120",
    "addr:postcode":"45458",
    "addr:street":"Garnet Dr",
    "iso:country":"US",
    "sg:address":"8120 Garnet Dr",
    "sg:city":"Dayton",
    "sg:classifiers":[
        {
            "category":"Health Services",
            "subcategory":"Doctor",
            "type":"Services"
        }
    ],
    "sg:phone":"+1 937 291 2511",
    "sg:postcode":"45458",
    "sg:province":"OH",
    "sg:tags":[
        "physician",
        "surgeon"
    ],
    "wof:name":"Prime Health Medical Svc",
    "wof:placetype":"venue"
},
  "geometry": {"coordinates":[-84.185832,39.620941],"type":"Point"}
}