{
  "type": "Feature",
  "properties": {
    "iso:country":"US",
    "sg:address":"10801 Reading Rd",
    "sg:city":"Cincinnati",
    "sg:classifiers":[
        {
            "category":"Wholesale",
            "subcategory":"Construction Materials",
            "type":"Manufacturing & Wholesale Goods"
        },
        {
            "category":"Home & Garden",
            "subcategory":"Furniture",
            "type":"Retail Goods"
        }
    ],
    "sg:phone":"+1 513 671 1440",
    "sg:postcode":"45241",
    "sg:province":"OH",
    "sg:tags":[
        "equipment",
        "kitchen",
        "marble",
        "cabinet"
    ],
    "wof:name":"Nisbet Brower",
    "wof:placetype":"venue"
},
  "geometry": {"coordinates":[-84.415007,39.264762],"type":"Point"}
}