{
  "type": "Feature",
  "properties": {
    "iso:country":"US",
    "sg:address":"901 Canterbury Rd",
    "sg:city":"Cleveland",
    "sg:classifiers":[
        {
            "category":"Professional",
            "subcategory":"Advertising",
            "type":"Services"
        }
    ],
    "sg:phone":"+1 440 835 5872",
    "sg:postcode":"44145",
    "sg:province":"OH",
    "sg:tags":[
        "mailing",
        "shipping"
    ],
    "wof:name":"Mail Pouch Mailing Svc",
    "wof:placetype":"venue"
},
  "geometry": {"coordinates":[-81.91144300000001,41.471514],"type":"Point"}
}