{
  "type": "Feature",
  "properties": {
    "addr:full":"330 Hess Rd Washington Ct Hs OH 43160",
    "addr:housenumber":"330",
    "addr:postcode":"43160",
    "addr:street":"Hess Rd",
    "iso:country":"US",
    "sg:address":"330 Hess Rd",
    "sg:city":"Washington Ct Hs",
    "sg:classifiers":[
        {
            "category":"Building & Trades",
            "subcategory":"Cleaning & Sanitation",
            "type":"Services"
        }
    ],
    "sg:phone":"+1 740 335 6195",
    "sg:postcode":"43160",
    "sg:province":"OH",
    "sg:tags":[
        "house"
    ],
    "wof:name":"Merry Maids Inc",
    "wof:placetype":"venue"
},
  "geometry": {"coordinates":[-83.33461800000001,39.548623],"type":"Point"}
}