{
  "type": "Feature",
  "properties": {
    "addr:full": "1420 Finch Ln Milford OH 45150",
    "addr:housenumber": "1420",
    "addr:postcode": "45150",
    "addr:street": "Finch Ln",
    "iso:country": "US",
    "sg:address": "1420 Finch Ln",
    "sg:city": "Milford",
    "sg:classifiers": [
      {
        "category": "Wholesale",
        "subcategory": "Stationery",
        "type": "Manufacturing \u0026 Wholesale Goods"
      }
    ],
    "sg:phone": "+1 513 575 9955",
    "sg:postcode": "45150",
    "sg:province": "OH",
    "sg:tags": [
      "business",
      "form",
      "system"
    ],
    "sg:website": "www.proforma-cincy.com",
    "wof:name": "Proforma Business Solutions",
    "wof:placetype": "venue"
  },
  "geometry": {"coordinates":[-84.207361,39.186773],"type":"Point"}
}
