{
  "type": "Feature",
  "properties": {
    "iso:country":"US",
    "sg:address":"1420 Finch Ln",
    "sg:city":"Milford",
    "sg:classifiers":[
        {
            "category":"Wholesale",
            "subcategory":"Stationery",
            "type":"Manufacturing & Wholesale Goods"
        }
    ],
    "sg:phone":"+1 513 575 9955",
    "sg:postcode":"45150",
    "sg:province":"OH",
    "sg:tags":[
        "business",
        "form",
        "system"
    ],
    "sg:website":"www.proforma-cincy.com",
    "wof:name":"Proforma Business Solutions",
    "wof:placetype":"venue"
},
  "geometry": {"coordinates":[-84.20736100000001,39.186773],"type":"Point"}
}