{
  "type": "Feature",
  "properties": {
    "iso:country":"US",
    "sg:address":"403 Southward Dr",
    "sg:city":"Youngstown",
    "sg:classifiers":[
        {
            "category":"Organizations",
            "subcategory":"Membership Organization",
            "type":"Services"
        }
    ],
    "sg:phone":"+1 330 793 6893",
    "sg:postcode":"44515",
    "sg:province":"OH",
    "wof:name":"Gamblers Anonymous",
    "wof:placetype":"venue"
},
  "geometry": {"coordinates":[-80.727908,41.091392],"type":"Point"}
}