{
  "type": "Feature",
  "properties": {
    "iso:country":"US",
    "sg:address":"6645 Morley Rd",
    "sg:city":"Painesville",
    "sg:classifiers":[
        {
            "category":"Real Estate",
            "subcategory":"Real Estate Agent",
            "type":"Services"
        }
    ],
    "sg:phone":"+1 440 358 0508",
    "sg:postcode":"44077",
    "sg:province":"OH",
    "wof:name":"Property Maintenance Matters",
    "wof:placetype":"venue"
},
  "geometry": {"coordinates":[-81.258144,41.689122],"type":"Point"}
}