{
  "type": "Feature",
  "properties": {
    "addr:full": "7142 Temperance Point St Westerville OH 43082",
    "addr:housenumber": "7142",
    "addr:postcode": "43082",
    "addr:street": "Temperance Point St",
    "iso:country": "US",
    "sg:address": "7142 Temperance Point St",
    "sg:city": "Westerville",
    "sg:classifiers": [
      {
        "category": "Social Services",
        "type": "Services"
      }
    ],
    "sg:phone": "+1 614 794 6991",
    "sg:postcode": "43082",
    "sg:province": "OH",
    "sg:tags": [
      "instruction",
      "health",
      "care"
    ],
    "wof:name": "West Edge Medical Care Inc",
    "wof:placetype": "venue"
  },
  "geometry": {"coordinates":[-82.942287,40.159906],"type":"Point"}
}
