{
  "type": "Feature",
  "properties": {
    "addr:full": "11921 Miles Ave Cleveland OH 44105",
    "addr:housenumber": "11921",
    "addr:postcode": "44105",
    "addr:street": "Miles Ave",
    "iso:country": "US",
    "sg:address": "11921 Miles Ave",
    "sg:city": "Cleveland",
    "sg:classifiers": [
      {
        "category": "Food \u0026 Beverages",
        "subcategory": "Meat \u0026 Fish",
        "type": "Retail Goods"
      },
      {
        "category": "Restaurant",
        "type": "Food \u0026 Drink"
      }
    ],
    "sg:phone": "+1 216 429 0075",
    "sg:postcode": "44105",
    "sg:province": "OH",
    "sg:tags": [
      "delicatessen",
      "grocery"
    ],
    "wof:name": "Lakia's Delicatessen",
    "wof:placetype": "venue"
  },
  "geometry": {"coordinates":[-81.598947,41.445349],"type":"Point"}
}
