{
  "type": "Feature",
  "properties": {
    "iso:country":"US",
    "sg:address":"11921 Miles Ave",
    "sg:city":"Cleveland",
    "sg:classifiers":[
        {
            "category":"Food & Beverages",
            "subcategory":"Meat & Fish",
            "type":"Retail Goods"
        },
        {
            "category":"Restaurant",
            "type":"Food & Drink"
        }
    ],
    "sg:phone":"+1 216 429 0075",
    "sg:postcode":"44105",
    "sg:province":"OH",
    "sg:tags":[
        "delicatessen",
        "grocery"
    ],
    "wof:name":"Lakia's Delicatessen",
    "wof:placetype":"venue"
},
  "geometry": {"coordinates":[-81.598947,41.445349],"type":"Point"}
}