{
  "type": "Feature",
  "properties": {
    "addr:full": "4223 Fulton Rd Cleveland OH 44144",
    "addr:housenumber": "4223",
    "addr:postcode": "44144",
    "addr:street": "Fulton Rd",
    "iso:country": "US",
    "sg:address": "4223 Fulton Rd",
    "sg:city": "Cleveland",
    "sg:classifiers": [
      {
        "category": "Health Services",
        "subcategory": "Doctor",
        "type": "Services"
      }
    ],
    "sg:phone": "+1 216 459 0344",
    "sg:postcode": "44144",
    "sg:province": "OH",
    "sg:tags": [
      "dentist"
    ],
    "wof:name": "Di Bauda \u0026 Raybuck",
    "wof:placetype": "venue"
  },
  "geometry": {"coordinates":[-81.723282,41.445034],"type":"Point"}
}
