{
  "type": "Feature",
  "properties": {
    "iso:country":"US",
    "sg:address":"4223 Fulton Rd",
    "sg:city":"Cleveland",
    "sg:classifiers":[
        {
            "category":"Health Services",
            "subcategory":"Doctor",
            "type":"Services"
        }
    ],
    "sg:phone":"+1 216 459 0344",
    "sg:postcode":"44144",
    "sg:province":"OH",
    "sg:tags":[
        "dentist"
    ],
    "wof:name":"Di Bauda & Raybuck",
    "wof:placetype":"venue"
},
  "geometry": {"coordinates":[-81.723282,41.445034],"type":"Point"}
}