{
  "type": "Feature",
  "properties": {
    "addr:full":"5504 Mosiman Rd Middletown OH 45042",
    "addr:housenumber":"5504",
    "addr:postcode":"45042",
    "addr:street":"Mosiman Rd",
    "iso:country":"US",
    "sg:address":"5504 Mosiman Rd",
    "sg:city":"Middletown",
    "sg:classifiers":[
        {
            "category":"Home & Garden",
            "subcategory":"Building Materials",
            "type":"Retail Goods"
        }
    ],
    "sg:phone":"+1 513 423 7121",
    "sg:postcode":"45042",
    "sg:province":"OH",
    "wof:name":"Jim Thorpe Windows & Doors",
    "wof:placetype":"venue"
},
  "geometry": {"coordinates":[-84.448887,39.528902],"type":"Point"}
}