{
  "type": "Feature",
  "properties": {
    "addr:full": "3424 State Rte 309 Galion OH 44833",
    "addr:housenumber": "3424",
    "addr:postcode": "44833",
    "addr:street": "State Rte 309",
    "iso:country": "US",
    "sg:address": "3424 State Rte 309",
    "sg:city": "Galion",
    "sg:classifiers": [
      {
        "category": "Manufacturing",
        "subcategory": "Retail Goods",
        "type": "Manufacturing \u0026 Wholesale Goods"
      }
    ],
    "sg:phone": "+1 419 468 5095",
    "sg:postcode": "44833",
    "sg:province": "OH",
    "sg:tags": [
      "manufacturer"
    ],
    "wof:name": "Refuse Parts LLC",
    "wof:placetype": "venue"
  },
  "geometry": {"coordinates":[-82.856671,40.665879],"type":"Point"}
}
