{
  "type": "Feature",
  "properties": {
    "addr:full":"3647 Snodgrass Rd Mansfield OH 44903",
    "addr:postcode":"3647;44903",
    "addr:street":"Snodgrass Rd",
    "iso:country":"US",
    "sg:address":"3647 Snodgrass Rd",
    "sg:city":"Mansfield",
    "sg:classifiers":[
        {
            "category":"Real Estate",
            "subcategory":"Real Estate Agent",
            "type":"Services"
        }
    ],
    "sg:phone":"+1 419 529 4811",
    "sg:postcode":"44903",
    "sg:province":"OH",
    "wof:name":"Appraisal Associates",
    "wof:placetype":"venue"
},
  "geometry": {"coordinates":[-82.647668,40.78346],"type":"Point"}
}