{
  "type": "Feature",
  "properties": {
    "addr:full":"7986 S Bloomfield Royalton Rd Ashville OH 43103",
    "addr:housenumber":"7986",
    "addr:postcode":"43103",
    "addr:street":"S Bloomfield Royalton Rd",
    "iso:country":"US",
    "sg:address":"7986 S Bloomfield Royalton Rd",
    "sg:city":"Ashville",
    "sg:classifiers":[
        {
            "category":"Wholesale",
            "subcategory":"Stationery",
            "type":"Manufacturing & Wholesale Goods"
        }
    ],
    "sg:phone":"+1 740 983 9300",
    "sg:postcode":"43103",
    "sg:province":"OH",
    "sg:tags":[
        "supply"
    ],
    "wof:name":"Buell LLC",
    "wof:placetype":"venue"
},
  "geometry": {"coordinates":[-82.891661,39.704588],"type":"Point"}
}