{
  "type": "Feature",
  "properties": {
    "addr:full": "4181 Avon Lake Rd Litchfield OH 44253",
    "addr:housenumber": "4181",
    "addr:postcode": "44253",
    "addr:street": "Avon Lake Rd",
    "iso:country": "US",
    "sg:address": "4181 Avon Lake Rd",
    "sg:city": "Litchfield",
    "sg:classifiers": [
      {
        "category": "Farming",
        "subcategory": "Livestock Farm",
        "type": "Manufacturing \u0026 Wholesale Goods"
      }
    ],
    "sg:phone": "+1 330 723 3698",
    "sg:postcode": "44253",
    "sg:province": "OH",
    "sg:tags": [
      "alpaca"
    ],
    "wof:name": "Pride Of The Andes Inc",
    "wof:placetype": "venue"
  },
  "geometry": {"coordinates":[-82.023088,41.160233],"type":"Point"}
}
