{
  "type": "Feature",
  "properties": {
    "iso:country":"US",
    "sg:address":"4181 Avon Lake Rd",
    "sg:city":"Litchfield",
    "sg:classifiers":[
        {
            "category":"Farming",
            "subcategory":"Livestock Farm",
            "type":"Manufacturing & Wholesale Goods"
        }
    ],
    "sg:phone":"+1 330 723 3698",
    "sg:postcode":"44253",
    "sg:province":"OH",
    "sg:tags":[
        "alpaca"
    ],
    "wof:name":"Pride Of The Andes Inc",
    "wof:placetype":"venue"
},
  "geometry": {"coordinates":[-82.023088,41.160233],"type":"Point"}
}