{
  "type": "Feature",
  "properties": {
    "iso:country":"US",
    "sg:address":"360 N Locust St",
    "sg:city":"Ottawa",
    "sg:classifiers":[
        {
            "category":"Organizations",
            "subcategory":"Religious Organization",
            "type":"Services"
        }
    ],
    "sg:phone":"+1 419 523 6146",
    "sg:postcode":"45875",
    "sg:province":"OH",
    "sg:tags":[
        "monastery",
        "convent"
    ],
    "wof:name":"Sisters Of The Precious Blood",
    "wof:placetype":"venue"
},
  "geometry": {"coordinates":[-84.044125,41.022443],"type":"Point"}
}