{
  "type": "Feature",
  "properties": {
    "iso:country":"US",
    "sg:address":"5828 Washington Ave",
    "sg:city":"Ashtabula",
    "sg:classifiers":[
        {
            "category":"Building & Trades",
            "subcategory":"Construction",
            "type":"Services"
        }
    ],
    "sg:phone":"+1 440 993 3263",
    "sg:postcode":"44004",
    "sg:province":"OH",
    "sg:tags":[
        "hanging",
        "painter",
        "contractor"
    ],
    "wof:name":"Joslin Painting Co",
    "wof:placetype":"venue"
},
  "geometry": {"coordinates":[-80.78861000000001,41.854986],"type":"Point"}
}