{
  "type": "Feature",
  "properties": {
    "addr:full": "1844 Ira Turpin Way NE Canton OH 44705",
    "addr:housenumber": "1844",
    "addr:postcode": "44705",
    "addr:street": "Ira Turpin Way Ne",
    "iso:country": "US",
    "sg:address": "1844 Ira Turpin Way NE",
    "sg:city": "Canton",
    "sg:classifiers": [
      {
        "category": "Restaurant",
        "type": "Food \u0026 Drink"
      }
    ],
    "sg:phone": "+1 330 580 9098",
    "sg:postcode": "44705",
    "sg:province": "OH",
    "sg:tags": [
      "banquet",
      "rooms"
    ],
    "wof:name": "Canton Negro Oldtimers Actvy",
    "wof:placetype": "venue"
  },
  "geometry": {"coordinates":[-81.352284,40.806382],"type":"Point"}
}
