{
  "type": "Feature",
  "properties": {
    "addr:full": "915 Flat Run Rd Seaman OH 45679",
    "addr:housenumber": "915",
    "addr:postcode": "45679",
    "addr:street": "Flat Run Rd",
    "iso:country": "US",
    "sg:address": "915 Flat Run Rd",
    "sg:city": "Seaman",
    "sg:phone": "+1 937 764 1174",
    "sg:postcode": "45679",
    "sg:province": "OH",
    "sg:tags": [
      "farm",
      "tobacco"
    ],
    "wof:name": "James Chambers",
    "wof:placetype": "venue"
  },
  "geometry": {"coordinates":[-83.535407,39.019565],"type":"Point"}
}
