{
  "type": "Feature",
  "properties": {
    "iso:country":"US",
    "sg:address":"5100 Springfield St",
    "sg:city":"Dayton",
    "sg:classifiers":[
        {
            "category":"Professional",
            "subcategory":"Research",
            "type":"Services"
        }
    ],
    "sg:phone":"+1 937 258 6700",
    "sg:postcode":"45431",
    "sg:province":"OH",
    "sg:tags":[
        "scientific"
    ],
    "sg:website":"www.battelle.org",
    "wof:name":"Battelle Dayton Operations",
    "wof:placetype":"venue"
},
  "geometry": {"coordinates":[-84.118025,39.783149],"type":"Point"}
}