{
  "type": "Feature",
  "properties": {
    "addr:full":"38015 US Hwy 30 Lisbon OH 44432",
    "addr:postcode":"38015;44432",
    "addr:street":"Us Hwy 30",
    "iso:country":"US",
    "sg:address":"38015 US Hwy 30",
    "sg:city":"Lisbon",
    "sg:classifiers":[
        {
            "category":"Personal",
            "subcategory":"Beauty Salon",
            "type":"Services"
        }
    ],
    "sg:phone":"+1 330 424 5842",
    "sg:postcode":"44432",
    "sg:province":"OH",
    "wof:name":"House Of Beauty",
    "wof:placetype":"venue"
},
  "geometry": {"coordinates":[-80.78193899999999,40.772195],"type":"Point"}
}