{
  "type": "Feature",
  "properties": {
    "iso:country":"US",
    "sg:address":"3594 Liberty Ave",
    "sg:city":"Vermilion",
    "sg:classifiers":[
        {
            "category":"Food & Beverages",
            "subcategory":"Groceries & Convenience Stores",
            "type":"Retail Goods"
        }
    ],
    "sg:phone":"+1 440 967 6270",
    "sg:postcode":"44089",
    "sg:province":"OH",
    "wof:name":"7-Eleven",
    "wof:placetype":"venue"
},
  "geometry": {"coordinates":[-82.317798,41.424916],"type":"Point"}
}