{
  "type": "Feature",
  "properties": {
    "iso:country":"US",
    "sg:address":"1300 Cameron Ave",
    "sg:city":"Lewis Center",
    "sg:classifiers":[
        {
            "category":"Restaurant",
            "type":"Food & Drink"
        }
    ],
    "sg:menulink":"http://www.allmenus.com/oh/orange/200037-long-john-silvers/menu/",
    "sg:phone":"+1 614 985 5590",
    "sg:postcode":"43035",
    "sg:province":"OH",
    "sg:tags":[
        "seafood",
        "american"
    ],
    "wof:name":"Long John Silver's",
    "wof:placetype":"venue"
},
  "geometry": {"coordinates":[-83.000635,40.154314],"type":"Point"}
}