{
  "type": "Feature",
  "properties": {
    "iso:country":"US",
    "sg:address":"7575 Deer Park Way",
    "sg:city":"Reynoldsburg",
    "sg:classifiers":[
        {
            "category":"Professional",
            "subcategory":"Management & Consulting",
            "type":"Services"
        }
    ],
    "sg:phone":"+1 614 866 8629",
    "sg:postcode":"43068",
    "sg:province":"OH",
    "sg:tags":[
        "marketing",
        "consultant"
    ],
    "sg:website":"www.bltproductions.com",
    "wof:name":"BLT Productions Inc",
    "wof:placetype":"venue"
},
  "geometry": {"coordinates":[-82.793699,39.983491],"type":"Point"}
}