{
  "type": "Feature",
  "properties": {
    "iso:country":"US",
    "sg:address":"3414 Edwards Rd",
    "sg:city":"Cincinnati",
    "sg:classifiers":[
        {
            "category":"Health Services",
            "subcategory":"Health Practitioner",
            "type":"Services"
        }
    ],
    "sg:phone":"+1 513 361 0031",
    "sg:postcode":"45208",
    "sg:province":"OH",
    "sg:tags":[
        "psychologist"
    ],
    "wof:name":"Todd F Walker",
    "wof:placetype":"venue"
},
  "geometry": {"coordinates":[-84.443302,39.139216],"type":"Point"}
}