{
  "type": "Feature",
  "properties": {
    "addr:full":"594 W Market St Akron OH 44303",
    "addr:housenumber":"594",
    "addr:postcode":"44303",
    "addr:street":"W Market St",
    "iso:country":"US",
    "sg:address":"594 W Market St",
    "sg:city":"Akron",
    "sg:classifiers":[
        {
            "category":"Bars & Pubs",
            "type":"Food & Drink"
        }
    ],
    "sg:phone":"+1 330 535 4133",
    "sg:postcode":"44303",
    "sg:province":"OH",
    "sg:tags":[
        "drinking"
    ],
    "wof:name":"Grand Central Station",
    "wof:placetype":"venue"
},
  "geometry": {"coordinates":[-81.535552,41.093109],"type":"Point"}
}