{
  "type": "Feature",
  "properties": {
    "iso:country":"US",
    "sg:address":"17 S Ohio Ave",
    "sg:city":"Wellston",
    "sg:classifiers":[
        {
            "category":"Wholesale",
            "subcategory":"Non-durable Goods",
            "type":"Manufacturing & Wholesale Goods"
        }
    ],
    "sg:phone":"+1 740 384 9975",
    "sg:postcode":"45692",
    "sg:province":"OH",
    "wof:name":"Fish Feathers",
    "wof:placetype":"venue"
},
  "geometry": {"coordinates":[-82.534263,39.123401],"type":"Point"}
}