{
  "type": "Feature",
  "properties": {
    "addr:full":"46700 Co Rd 405 Coshocton OH 43812",
    "addr:housenumber":"46700;405",
    "addr:postcode":"43812",
    "addr:street":"Co Rd",
    "iso:country":"US",
    "sg:address":"46700 Co Rd 405",
    "sg:city":"Coshocton",
    "sg:classifiers":[
        {
            "category":"Home & Garden",
            "subcategory":"Building Materials",
            "type":"Retail Goods"
        }
    ],
    "sg:phone":"+1 740 623 2782",
    "sg:postcode":"43812",
    "sg:province":"OH",
    "sg:tags":[
        "door"
    ],
    "wof:name":"J & R Door",
    "wof:placetype":"venue"
},
  "geometry": {"coordinates":[-81.886596,40.36339],"type":"Point"}
}