{
  "type": "Feature",
  "properties": {
    "iso:country":"US",
    "sg:address":"151 Akron Rd",
    "sg:city":"Norwalk",
    "sg:classifiers":[
        {
            "category":"Building & Trades",
            "subcategory":"Construction",
            "type":"Services"
        }
    ],
    "sg:phone":"+1 419 668 1022",
    "sg:postcode":"44857",
    "sg:province":"OH",
    "sg:tags":[
        "paving",
        "contractor"
    ],
    "wof:name":"A J Riley Inc",
    "wof:placetype":"venue"
},
  "geometry": {"coordinates":[-82.594158,41.243437],"type":"Point"}
}