{
  "type": "Feature",
  "properties": {
    "addr:full":"68 S Washington St Tiffin OH 44883",
    "addr:housenumber":"68",
    "addr:postcode":"44883",
    "addr:street":"S Washington St",
    "iso:country":"US",
    "sg:address":"68 S Washington St",
    "sg:city":"Tiffin",
    "sg:classifiers":[
        {
            "category":"Manufacturing",
            "subcategory":"Signs",
            "type":"Manufacturing & Wholesale Goods"
        }
    ],
    "sg:phone":"+1 419 448 7874",
    "sg:postcode":"44883",
    "sg:province":"OH",
    "wof:name":"Rush Business Forms",
    "wof:placetype":"venue"
},
  "geometry": {"coordinates":[-83.17680300000001,41.115596],"type":"Point"}
}