{
  "type": "Feature",
  "properties": {
    "iso:country":"US",
    "sg:address":"5005 Dresden Rd",
    "sg:city":"Zanesville",
    "sg:classifiers":[
        {
            "category":"Freight",
            "type":"Transportation"
        }
    ],
    "sg:phone":"+1 740 454 2699",
    "sg:postcode":"43701",
    "sg:province":"OH",
    "sg:tags":[
        "operator",
        "trucking"
    ],
    "wof:name":"PCC Marketing",
    "wof:placetype":"venue"
},
  "geometry": {"coordinates":[-82.008932,40.016826],"type":"Point"}
}