{
  "type": "Feature",
  "properties": {
    "addr:full": "775 W Smith Rd Medina OH 44256",
    "addr:housenumber": "775",
    "addr:postcode": "44256",
    "addr:street": "W Smith Rd",
    "iso:country": "US",
    "sg:address": "775 W Smith Rd",
    "sg:city": "Medina",
    "sg:classifiers": [
      {
        "category": "Insurance",
        "subcategory": "Insurance Agent",
        "type": "Services"
      }
    ],
    "sg:phone": "+1 330 722 8889",
    "sg:postcode": "44256",
    "sg:province": "OH",
    "wof:name": "Randy Heller Agency",
    "wof:placetype": "venue"
  },
  "geometry": {"coordinates":[-81.886533,41.136224],"type":"Point"}
}
