{
  "type": "Feature",
  "properties": {
    "iso:country":"US",
    "sg:address":"5873 Karric Square Dr",
    "sg:city":"Dublin",
    "sg:classifiers":[
        {
            "category":"Retail",
            "subcategory":"Laundry & Dry Cleaning",
            "type":"Services"
        }
    ],
    "sg:phone":"+1 614 798 9124",
    "sg:postcode":"43016",
    "sg:province":"OH",
    "sg:tags":[
        "cleaners"
    ],
    "wof:name":"Top Cleaners",
    "wof:placetype":"venue"
},
  "geometry": {"coordinates":[-83.124262,40.07584],"type":"Point"}
}