{
  "type": "Feature",
  "properties": {
    "iso:country":"US",
    "sg:address":"3542 State Rte 93",
    "sg:city":"Oak Hill",
    "sg:classifiers":[
        {
            "category":"Manufacturing",
            "subcategory":"Glass & Minerals",
            "type":"Manufacturing & Wholesale Goods"
        }
    ],
    "sg:phone":"+1 740 682 7794",
    "sg:postcode":"45656",
    "sg:province":"OH",
    "sg:tags":[
        "treated",
        "or"
    ],
    "sg:website":"www.rescoproducts.com",
    "wof:name":"Cedar Heights Clay Co",
    "wof:placetype":"venue"
},
  "geometry": {"coordinates":[-82.575695,38.882967],"type":"Point"}
}