{
  "type": "Feature",
  "properties": {
    "addr:full": "3584 Home Rd Powell OH 43065",
    "addr:housenumber": "3584",
    "addr:postcode": "43065",
    "addr:street": "Home Rd",
    "iso:country": "US",
    "sg:address": "3584 Home Rd",
    "sg:city": "Powell",
    "sg:classifiers": [
      {
        "category": "Education",
        "subcategory": "School",
        "type": "Public Place"
      }
    ],
    "sg:phone": "+1 740 657 4200",
    "sg:postcode": "43065",
    "sg:province": "OH",
    "sg:website": "www.olentangy.k12.oh.us",
    "wof:name": "Liberty High School",
    "wof:placetype": "venue"
  },
  "geometry": {"coordinates":[-83.096738,40.195975],"type":"Point"}
}
