{
  "type": "Feature",
  "properties": {
    "addr:full":"6060 Broadview Rd Cleveland OH 44134",
    "addr:housenumber":"6060",
    "addr:postcode":"44134",
    "addr:street":"Broadview Rd",
    "iso:country":"US",
    "sg:address":"6060 Broadview Rd",
    "sg:city":"Cleveland",
    "sg:classifiers":[
        {
            "category":"Shopping",
            "type":"Retail Goods"
        }
    ],
    "sg:phone":"+1 216 398 7001",
    "sg:postcode":"44134",
    "sg:province":"OH",
    "sg:tags":[
        "durable",
        "merchandise"
    ],
    "wof:name":"Rubber Age Stamps",
    "wof:placetype":"venue"
},
  "geometry": {"coordinates":[-81.688666,41.39925],"type":"Point"}
}