{
  "type": "Feature",
  "properties": {
    "iso:country":"US",
    "sg:address":"37 W Broad St",
    "sg:city":"Columbus",
    "sg:classifiers":[
        {
            "category":"Government",
            "subcategory":"Office",
            "type":"Public Place"
        }
    ],
    "sg:phone":"+1 614 469 5186",
    "sg:postcode":"43215",
    "sg:province":"OH",
    "sg:tags":[
        "legislative",
        "body"
    ],
    "wof:name":"US Congress Senators",
    "wof:placetype":"venue"
},
  "geometry": {"coordinates":[-83.002217,39.961974],"type":"Point"}
}