{
  "type": "Feature",
  "properties": {
    "addr:full":"8200 Seville Rd Lodi OH 44254",
    "addr:housenumber":"8200",
    "addr:postcode":"44254",
    "addr:street":"Seville Rd",
    "iso:country":"US",
    "sg:address":"8200 Seville Rd",
    "sg:city":"Lodi",
    "sg:classifiers":[
        {
            "category":"Building & Trades",
            "subcategory":"Construction",
            "type":"Services"
        }
    ],
    "sg:phone":"+1 330 948 1494",
    "sg:postcode":"44254",
    "sg:province":"OH",
    "sg:tags":[
        "underground",
        "installation",
        "upgrading",
        "removal"
    ],
    "sg:website":"www.petroenviro.com",
    "wof:name":"Petro Environmental",
    "wof:placetype":"venue"
},
  "geometry": {"coordinates":[-81.988535,41.012521],"type":"Point"}
}