{
  "type": "Feature",
  "properties": {
    "addr:full": "1297 S Prospect St Marion OH 43302",
    "addr:housenumber": "1297",
    "addr:postcode": "43302",
    "addr:street": "S Prospect St",
    "iso:country": "US",
    "sg:address": "1297 S Prospect St",
    "sg:city": "Marion",
    "sg:classifiers": [
      {
        "category": "Food \u0026 Beverages",
        "subcategory": "Groceries \u0026 Convenience Stores",
        "type": "Retail Goods"
      }
    ],
    "sg:phone": "+1 740 387 5237",
    "sg:postcode": "43302",
    "sg:province": "OH",
    "wof:name": "Marion Moto Mart",
    "wof:placetype": "venue"
  },
  "geometry": {"coordinates":[-83.13891,40.564295],"type":"Point"}
}
