{
  "type": "Feature",
  "properties": {
    "iso:country":"US",
    "sg:address":"1297 S Prospect St",
    "sg:city":"Marion",
    "sg:classifiers":[
        {
            "category":"Food & Beverages",
            "subcategory":"Groceries & Convenience Stores",
            "type":"Retail Goods"
        }
    ],
    "sg:phone":"+1 740 387 5237",
    "sg:postcode":"43302",
    "sg:province":"OH",
    "wof:name":"Marion Moto Mart",
    "wof:placetype":"venue"
},
  "geometry": {"coordinates":[-83.13891,40.564295],"type":"Point"}
}