{
  "type": "Feature",
  "properties": {
    "iso:country":"US",
    "sg:address":"1819 Tuxworth Ave",
    "sg:city":"Cincinnati",
    "sg:classifiers":[
        {
            "category":"Shopping",
            "subcategory":"Florist",
            "type":"Retail Goods"
        }
    ],
    "sg:phone":"+1 513 921 1642",
    "sg:postcode":"45238",
    "sg:province":"OH",
    "wof:name":"Designs By Katie Inc",
    "wof:placetype":"venue"
},
  "geometry": {"coordinates":[-84.59079300000001,39.121716],"type":"Point"}
}