{
  "type": "Feature",
  "properties": {
    "iso:country":"US",
    "sg:address":"19291 Lorain Rd",
    "sg:city":"Cleveland",
    "sg:classifiers":[
        {
            "category":"Shopping",
            "subcategory":"Gifts & Souvenirs",
            "type":"Retail Goods"
        }
    ],
    "sg:phone":"+1 440 331 9441",
    "sg:postcode":"44126",
    "sg:province":"OH",
    "wof:name":"Memories",
    "wof:placetype":"venue"
},
  "geometry": {"coordinates":[-81.83243,41.452897],"type":"Point"}
}