{
  "type": "Feature",
  "properties": {
    "addr:full": "2045 Cincinnati-Zanesville Rd SW Lancaster OH 43130",
    "addr:housenumber": "2045",
    "addr:postcode": "43130",
    "addr:street": "Cincinnati-Zanesville Rd Sw",
    "iso:country": "US",
    "sg:address": "2045 Cincinnati-Zanesville Rd SW",
    "sg:city": "Lancaster",
    "sg:classifiers": [
      {
        "category": "Real Estate",
        "subcategory": "Real Estate Agent",
        "type": "Services"
      }
    ],
    "sg:phone": "+1 740 652 1267",
    "sg:postcode": "43130",
    "sg:province": "OH",
    "sg:tags": [
      "cooperative"
    ],
    "wof:name": "River Valley Co Op",
    "wof:placetype": "venue"
  },
  "geometry": {"coordinates":[-82.639306,39.697799],"type":"Point"}
}
