{
  "type": "Feature",
  "properties": {
    "iso:country":"US",
    "sg:address":"4930 Reed Rd",
    "sg:city":"Columbus",
    "sg:classifiers":[
        {
            "category":"Real Estate",
            "subcategory":"Developer",
            "type":"Services"
        }
    ],
    "sg:phone":"+1 614 457 4050",
    "sg:postcode":"43220",
    "sg:province":"OH",
    "wof:name":"Jet Link Development Ltd",
    "wof:placetype":"venue"
},
  "geometry": {"coordinates":[-83.06694299999999,40.053988],"type":"Point"}
}