{
  "type": "Feature",
  "properties": {
    "iso:country":"US",
    "sg:address":"27 W 2nd St",
    "sg:city":"Manchester",
    "sg:classifiers":[
        {
            "category":"Professional",
            "type":"Services"
        }
    ],
    "sg:phone":"+1 937 549 4158",
    "sg:postcode":"45144",
    "sg:province":"OH",
    "sg:tags":[
        "establishment"
    ],
    "wof:name":"Frank's Place",
    "wof:placetype":"venue"
},
  "geometry": {"coordinates":[-83.60910699999999,38.687171],"type":"Point"}
}