{
  "type": "Feature",
  "properties": {
    "iso:country":"US",
    "sg:address":"4455 Baughman Rd",
    "sg:city":"Zanesville",
    "sg:phone":"+1 740 453 5358",
    "sg:postcode":"43701",
    "sg:province":"OH",
    "sg:tags":[
        "farm",
        "field",
        "crop"
    ],
    "wof:name":"Lynn Hay Farms",
    "wof:placetype":"venue"
},
  "geometry": {"coordinates":[-82.068203,40.008012],"type":"Point"}
}