{
  "type": "Feature",
  "properties": {
    "addr:full": "87 Brooklyn Ave Youngstown OH 44507",
    "addr:housenumber": "87",
    "addr:postcode": "44507",
    "addr:street": "Brooklyn Ave",
    "iso:country": "US",
    "sg:address": "87 Brooklyn Ave",
    "sg:city": "Youngstown",
    "sg:classifiers": [
      {
        "category": "Wholesale",
        "subcategory": "Fruits \u0026 Vegetables",
        "type": "Manufacturing \u0026 Wholesale Goods"
      }
    ],
    "sg:phone": "+1 330 783 1890",
    "sg:postcode": "44507",
    "sg:province": "OH",
    "wof:name": "American Farms Produce II",
    "wof:placetype": "venue"
  },
  "geometry": {"coordinates":[-80.655396,41.067672],"type":"Point"}
}
