{
  "type": "Feature",
  "properties": {
    "iso:country":"US",
    "sg:address":"87 Brooklyn Ave",
    "sg:city":"Youngstown",
    "sg:classifiers":[
        {
            "category":"Wholesale",
            "subcategory":"Fruits & Vegetables",
            "type":"Manufacturing & Wholesale Goods"
        }
    ],
    "sg:phone":"+1 330 783 1890",
    "sg:postcode":"44507",
    "sg:province":"OH",
    "wof:name":"American Farms Produce II",
    "wof:placetype":"venue"
},
  "geometry": {"coordinates":[-80.655396,41.067672],"type":"Point"}
}