{
  "type": "Feature",
  "properties": {
    "addr:full": "3799 Madison Rd Cincinnati OH 45209",
    "addr:housenumber": "3799",
    "addr:postcode": "45209",
    "addr:street": "Madison Rd",
    "iso:country": "US",
    "sg:address": "3799 Madison Rd",
    "sg:city": "Cincinnati",
    "sg:classifiers": [
      {
        "category": "Building \u0026 Trades",
        "subcategory": "Construction",
        "type": "Services"
      }
    ],
    "sg:phone": "+1 513 321 2502",
    "sg:postcode": "45209",
    "sg:province": "OH",
    "sg:tags": [
      "contractor"
    ],
    "wof:name": "UNISTRUT OF CINCINNATI/DAYTON",
    "wof:placetype": "venue"
  },
  "geometry": {"coordinates":[-84.416553,39.160486],"type":"Point"}
}
