{
  "type": "Feature",
  "properties": {
    "iso:country":"US",
    "sg:address":"3799 Madison Rd",
    "sg:city":"Cincinnati",
    "sg:classifiers":[
        {
            "category":"Building & Trades",
            "subcategory":"Construction",
            "type":"Services"
        }
    ],
    "sg:phone":"+1 513 321 2502",
    "sg:postcode":"45209",
    "sg:province":"OH",
    "sg:tags":[
        "contractor"
    ],
    "wof:name":"UNISTRUT OF CINCINNATI/DAYTON",
    "wof:placetype":"venue"
},
  "geometry": {"coordinates":[-84.41655299999999,39.160486],"type":"Point"}
}