{
  "type": "Feature",
  "properties": {
    "addr:full": "4500 Riverview Ave Middletown OH 45042",
    "addr:housenumber": "4500",
    "addr:postcode": "45042",
    "addr:street": "Riverview Ave",
    "iso:country": "US",
    "sg:address": "4500 Riverview Ave",
    "sg:city": "Middletown",
    "sg:classifiers": [
      {
        "category": "Social Services",
        "subcategory": "Child Care",
        "type": "Services"
      },
      {
        "category": "Organizations",
        "subcategory": "Religious Organization",
        "type": "Services"
      }
    ],
    "sg:phone": "+1 513 423 5511",
    "sg:postcode": "45042",
    "sg:province": "OH",
    "sg:tags": [
      "day",
      "church"
    ],
    "sg:website": "www.fbcmiddletown.org",
    "wof:name": "First Baptist Church Day Care",
    "wof:placetype": "venue"
  },
  "geometry": {"coordinates":[-84.346684,39.531469],"type":"Point"}
}
