{
  "type": "Feature",
  "properties": {
    "addr:full": "7599 1st Pl Bedford OH 44146",
    "addr:housenumber": "7599",
    "addr:postcode": "44146",
    "addr:street": "1St Pl",
    "iso:country": "US",
    "sg:address": "7599 1st Pl",
    "sg:city": "Bedford",
    "sg:classifiers": [
      {
        "category": "Building \u0026 Trades",
        "subcategory": "Electrical",
        "type": "Services"
      }
    ],
    "sg:phone": "+1 440 786 9777",
    "sg:postcode": "44146",
    "sg:province": "OH",
    "sg:tags": [
      "plumbing",
      "contracting",
      "electrical",
      "mechanical"
    ],
    "wof:name": "The Fowler Company",
    "wof:placetype": "venue"
  },
  "geometry": {"coordinates":[-81.511053,41.376392],"type":"Point"}
}
