{
  "type": "Feature",
  "properties": {
    "iso:country":"US",
    "sg:address":"4499 Padanarum Rd",
    "sg:city":"Geneva",
    "sg:classifiers":[
        {
            "category":"Recreation",
            "type":"Entertainment"
        }
    ],
    "sg:phone":"+1 440 466 8400",
    "sg:postcode":"44041",
    "sg:province":"OH",
    "sg:tags":[
        "parks"
    ],
    "wof:name":"Geneva State Park",
    "wof:placetype":"venue"
},
  "geometry": {"coordinates":[-80.973918,41.843576],"type":"Point"}
}