{
  "type": "Feature",
  "properties": {
    "iso:country":"US",
    "sg:address":"810 Richard St",
    "sg:city":"Miamisburg",
    "sg:classifiers":[
        {
            "category":"Professional",
            "type":"Services"
        }
    ],
    "sg:phone":"+1 937 866 3403",
    "sg:postcode":"45342",
    "sg:province":"OH",
    "wof:name":"Dean E Colton",
    "wof:placetype":"venue"
},
  "geometry": {"coordinates":[-84.27713900000001,39.65043],"type":"Point"}
}