{
  "type": "Feature",
  "properties": {
    "iso:country":"US",
    "sg:address":"4150 Belden Village St NW",
    "sg:city":"Canton",
    "sg:classifiers":[
        {
            "category":"Banks & Credit Unions",
            "subcategory":"Bank",
            "type":"Services"
        }
    ],
    "sg:phone":"+1 330 649 7700",
    "sg:postcode":"44718",
    "sg:province":"OH",
    "sg:tags":[
        "loan",
        "broker",
        "mortgage"
    ],
    "wof:name":"Pride Mortgage Inc",
    "wof:placetype":"venue"
},
  "geometry": {"coordinates":[-81.42420300000001,40.855065],"type":"Point"}
}