{
  "type": "Feature",
  "properties": {
    "addr:full":"10206 Quebec Ave Cleveland OH 44106",
    "addr:housenumber":"10206",
    "addr:postcode":"44106",
    "addr:street":"Quebec Ave",
    "iso:country":"US",
    "sg:address":"10206 Quebec Ave",
    "sg:city":"Cleveland",
    "sg:classifiers":[
        {
            "category":"Building & Trades",
            "subcategory":"Plumbing",
            "type":"Services"
        }
    ],
    "sg:phone":"+1 216 791 5495",
    "sg:postcode":"44106",
    "sg:province":"OH",
    "sg:tags":[
        "plumbing",
        "contractor"
    ],
    "wof:name":"Cook's General Contracting",
    "wof:placetype":"venue"
},
  "geometry": {"coordinates":[-81.615258,41.494338],"type":"Point"}
}