{
  "type": "Feature",
  "properties": {
    "addr:full": "3773 Liberty Rd Delaware OH 43015",
    "addr:housenumber": "3773",
    "addr:postcode": "43015",
    "addr:street": "Liberty Rd",
    "iso:country": "US",
    "sg:address": "3773 Liberty Rd",
    "sg:city": "Delaware",
    "sg:classifiers": [
      {
        "category": "Building \u0026 Trades",
        "subcategory": "Landscaping Services",
        "type": "Services"
      }
    ],
    "sg:phone": "+1 740 362 5667",
    "sg:postcode": "43015",
    "sg:province": "OH",
    "wof:name": "Lawn Solutions Inc",
    "wof:placetype": "venue"
  },
  "geometry": {"coordinates":[-83.082254,40.249772],"type":"Point"}
}
