{
  "type": "Feature",
  "properties": {
    "iso:country":"US",
    "sg:address":"3773 Liberty Rd",
    "sg:city":"Delaware",
    "sg:classifiers":[
        {
            "category":"Building & Trades",
            "subcategory":"Landscaping Services",
            "type":"Services"
        }
    ],
    "sg:phone":"+1 740 362 5667",
    "sg:postcode":"43015",
    "sg:province":"OH",
    "wof:name":"Lawn Solutions Inc",
    "wof:placetype":"venue"
},
  "geometry": {"coordinates":[-83.08225400000001,40.249772],"type":"Point"}
}