{
  "type": "Feature",
  "properties": {
    "addr:full":"1300 Starlight Dr Akron OH 44306",
    "addr:housenumber":"1300",
    "addr:postcode":"44306",
    "addr:street":"Starlight Dr",
    "iso:country":"US",
    "sg:address":"1300 Starlight Dr",
    "sg:city":"Akron",
    "sg:classifiers":[
        {
            "category":"Wholesale",
            "subcategory":"Construction Materials",
            "type":"Manufacturing & Wholesale Goods"
        }
    ],
    "sg:phone":"+1 330 773 8201",
    "sg:postcode":"44306",
    "sg:province":"OH",
    "sg:tags":[
        "windows",
        "door",
        "aluminum"
    ],
    "wof:name":"Norandex / Reynolds",
    "wof:placetype":"venue"
},
  "geometry": {"coordinates":[-81.480715,41.023546],"type":"Point"}
}