{
  "type": "Feature",
  "properties": {
    "addr:full": "311 Spring St Piqua OH 45356",
    "addr:housenumber": "311",
    "addr:postcode": "45356",
    "addr:street": "Spring St",
    "iso:country": "US",
    "sg:address": "311 Spring St",
    "sg:city": "Piqua",
    "sg:classifiers": [
      {
        "category": "Shopping",
        "subcategory": "Computers \u0026 Home Electronics",
        "type": "Retail Goods"
      }
    ],
    "sg:phone": "+1 937 773 3329",
    "sg:postcode": "45356",
    "sg:province": "OH",
    "wof:name": "N T R S Computer Sales \u0026 Svc",
    "wof:placetype": "venue"
  },
  "geometry": {"coordinates":[-84.238167,40.149668],"type":"Point"}
}
