{
  "type": "Feature",
  "properties": {
    "iso:country":"US",
    "sg:address":"330 Locust St",
    "sg:city":"Akron",
    "sg:classifiers":[
        {
            "category":"Health Services",
            "subcategory":"Doctor",
            "type":"Services"
        }
    ],
    "sg:phone":"+1 330 253 1713",
    "sg:postcode":"44302",
    "sg:province":"OH",
    "sg:tags":[
        "physician",
        "surgeon"
    ],
    "wof:name":"Bruce F Rothmann MD",
    "wof:placetype":"venue"
},
  "geometry": {"coordinates":[-81.526281,41.079388],"type":"Point"}
}