{
  "type": "Feature",
  "properties": {
    "iso:country":"US",
    "sg:address":"1450 Riverside Dr",
    "sg:city":"Cleveland",
    "sg:classifiers":[
        {
            "category":"Organizations",
            "subcategory":"Religious Organization",
            "type":"Services"
        }
    ],
    "sg:phone":"+1 216 227 0551",
    "sg:postcode":"44107",
    "sg:province":"OH",
    "sg:tags":[
        "monastery",
        "convent"
    ],
    "wof:name":"Sisters-Charity-St Augustine",
    "wof:placetype":"venue"
},
  "geometry": {"coordinates":[-81.82670299999999,41.482292],"type":"Point"}
}