{
  "type": "Feature",
  "properties": {
    "addr:full":"1964 W Market St Akron OH 44313",
    "addr:housenumber":"1964",
    "addr:postcode":"44313",
    "addr:street":"W Market St",
    "iso:country":"US",
    "sg:address":"1964 W Market St",
    "sg:city":"Akron",
    "sg:classifiers":[
        {
            "category":"Bars & Pubs",
            "type":"Food & Drink"
        }
    ],
    "sg:phone":"+1 330 864 8162",
    "sg:postcode":"44313",
    "sg:province":"OH",
    "wof:name":"Larry's Main Entrance",
    "wof:placetype":"venue"
},
  "geometry": {"coordinates":[-81.578475,41.113417],"type":"Point"}
}