{
  "type": "Feature",
  "properties": {
    "iso:country":"US",
    "sg:address":"2408 Valley Pike",
    "sg:city":"Dayton",
    "sg:classifiers":[
        {
            "category":"Arts & Performance",
            "subcategory":"Theater",
            "type":"Entertainment"
        }
    ],
    "sg:phone":"+1 937 237 1852",
    "sg:postcode":"45404",
    "sg:province":"OH",
    "sg:tags":[
        "karaoke"
    ],
    "wof:name":"Tammy & Dan's Karaoke",
    "wof:placetype":"venue"
},
  "geometry": {"coordinates":[-84.138363,39.792578],"type":"Point"}
}