{
  "type": "Feature",
  "properties": {
    "iso:country":"US",
    "sg:address":"9696 International Blvd",
    "sg:city":"Cincinnati",
    "sg:classifiers":[
        {
            "category":"Wholesale",
            "subcategory":"Durable Goods & Equipment",
            "type":"Manufacturing & Wholesale Goods"
        },
        {
            "category":"Manufacturing",
            "subcategory":"Electronics",
            "type":"Manufacturing & Wholesale Goods"
        }
    ],
    "sg:phone":"+1 513 874 7326",
    "sg:postcode":"45246",
    "sg:province":"OH",
    "sg:tags":[
        "magnetic",
        "material",
        "devices",
        "magnet",
        "importer",
        "flexible"
    ],
    "wof:name":"Tytek Industries Inc",
    "wof:placetype":"venue"
},
  "geometry": {"coordinates":[-84.44320399999999,39.30948],"type":"Point"}
}