{
  "type": "Feature",
  "properties": {
    "addr:full": "9696 International Blvd Cincinnati OH 45246",
    "addr:housenumber": "9696",
    "addr:postcode": "45246",
    "addr:street": "International Blvd",
    "iso:country": "US",
    "sg:address": "9696 International Blvd",
    "sg:city": "Cincinnati",
    "sg:classifiers": [
      {
        "category": "Wholesale",
        "subcategory": "Durable Goods \u0026 Equipment",
        "type": "Manufacturing \u0026 Wholesale Goods"
      },
      {
        "category": "Manufacturing",
        "subcategory": "Electronics",
        "type": "Manufacturing \u0026 Wholesale Goods"
      }
    ],
    "sg:phone": "+1 513 874 7326",
    "sg:postcode": "45246",
    "sg:province": "OH",
    "sg:tags": [
      "magnetic",
      "material",
      "devices",
      "magnet",
      "importer",
      "flexible"
    ],
    "wof:name": "Tytek Industries Inc",
    "wof:placetype": "venue"
  },
  "geometry": {"coordinates":[-84.443204,39.30948],"type":"Point"}
}
