{
  "type": "Feature",
  "properties": {
    "iso:country":"US",
    "sg:address":"2310 2nd St",
    "sg:city":"Cuyahoga Falls",
    "sg:classifiers":[
        {
            "category":"Government",
            "subcategory":"Police Station",
            "type":"Public Place"
        }
    ],
    "sg:phone":"+1 330 971 8338",
    "sg:postcode":"44221",
    "sg:province":"OH",
    "sg:tags":[
        "department"
    ],
    "wof:name":"Cuyahoga Falls Narcotics",
    "wof:placetype":"venue"
},
  "geometry": {"coordinates":[-81.483711,41.138461],"type":"Point"}
}