{
  "type": "Feature",
  "properties": {
    "iso:country":"US",
    "sg:address":"42960 Co Rd 19",
    "sg:city":"Coshocton",
    "sg:classifiers":[
        {
            "category":"Mining & Drilling",
            "type":"Manufacturing & Wholesale Goods"
        }
    ],
    "sg:phone":"+1 740 587 0902",
    "sg:postcode":"43812",
    "sg:province":"OH",
    "sg:tags":[
        "well"
    ],
    "wof:name":"B F I Energy",
    "wof:placetype":"venue"
},
  "geometry": {"coordinates":[-81.960148,40.43207],"type":"Point"}
}