{
  "type": "Feature",
  "properties": {
    "iso:country":"US",
    "sg:address":"88 Thivener Rd",
    "sg:city":"Gallipolis",
    "sg:classifiers":[
        {
            "category":"Building & Trades",
            "subcategory":"Landscaping Services",
            "type":"Services"
        }
    ],
    "sg:phone":"+1 740 446 2015",
    "sg:postcode":"45631",
    "sg:province":"OH",
    "wof:name":"Tree Care Specialists",
    "wof:placetype":"venue"
},
  "geometry": {"coordinates":[-82.242622,38.73713],"type":"Point"}
}