{
  "type": "Feature",
  "properties": {
    "iso:country":"US",
    "sg:address":"240 Tod Ln",
    "sg:city":"Youngstown",
    "sg:classifiers":[
        {
            "category":"Organizations",
            "subcategory":"Religious Organization",
            "type":"Services"
        }
    ],
    "sg:phone":"+1 330 743 2308",
    "sg:postcode":"44504",
    "sg:province":"OH",
    "sg:tags":[
        "church"
    ],
    "wof:name":"St Edward's Church",
    "wof:placetype":"venue"
},
  "geometry": {"coordinates":[-80.650719,41.1253],"type":"Point"}
}