{
  "type": "Feature",
  "properties": {
    "addr:full": "590 E Western Reserve Rd Youngstown OH 44514",
    "addr:housenumber": "590",
    "addr:postcode": "44514",
    "addr:street": "E Western Reserve Rd",
    "iso:country": "US",
    "sg:address": "590 E Western Reserve Rd",
    "sg:city": "Youngstown",
    "sg:classifiers": [
      {
        "category": "Health Services",
        "subcategory": "Doctor",
        "type": "Services"
      }
    ],
    "sg:phone": "+1 330 726 3261",
    "sg:postcode": "44514",
    "sg:province": "OH",
    "sg:tags": [
      "physician",
      "surgeon"
    ],
    "wof:name": "Community Medical Corp",
    "wof:placetype": "venue"
  },
  "geometry": {"coordinates":[-80.648884,40.987983],"type":"Point"}
}
