{
  "type": "Feature",
  "properties": {
    "addr:full":"2016 Troy Pike Dayton OH 45404",
    "addr:housenumber":"2016",
    "addr:postcode":"45404",
    "addr:street":"Troy Pike",
    "iso:country":"US",
    "sg:address":"2016 Troy Pike",
    "sg:city":"Dayton",
    "sg:classifiers":[
        {
            "category":"Retail",
            "subcategory":"Animal Services",
            "type":"Services"
        }
    ],
    "sg:phone":"+1 937 233 6281",
    "sg:postcode":"45404",
    "sg:province":"OH",
    "sg:tags":[
        "merchandise"
    ],
    "wof:name":"Torok Boarding Kennels",
    "wof:placetype":"venue"
},
  "geometry": {"coordinates":[-84.166515,39.790587],"type":"Point"}
}