{
  "type": "Feature",
  "properties": {
    "addr:full":"3107 Belmont Ave Youngstown OH 44505",
    "addr:housenumber":"3107",
    "addr:postcode":"44505",
    "addr:street":"Belmont Ave",
    "iso:country":"US",
    "sg:address":"3107 Belmont Ave",
    "sg:city":"Youngstown",
    "sg:classifiers":[
        {
            "category":"Shopping",
            "subcategory":"Clothing, Apparel, & Fashions",
            "type":"Retail Goods"
        }
    ],
    "sg:phone":"+1 330 759 7707",
    "sg:postcode":"44505",
    "sg:province":"OH",
    "sg:tags":[
        "uniform"
    ],
    "wof:name":"Uniforms Inc",
    "wof:placetype":"venue"
},
  "geometry": {"coordinates":[-80.665437,41.138381],"type":"Point"}
}