{
  "type": "Feature",
  "properties": {
    "addr:full":"9743 Co Rd 195 Kenton OH 43326",
    "addr:housenumber":"9743;195",
    "addr:postcode":"43326",
    "addr:street":"Co Rd",
    "iso:country":"US",
    "sg:address":"9743 Co Rd 195",
    "sg:city":"Kenton",
    "sg:classifiers":[
        {
            "category":"Social Services",
            "type":"Services"
        }
    ],
    "sg:phone":"+1 419 673 1410",
    "sg:postcode":"43326",
    "sg:province":"OH",
    "sg:tags":[
        "organization",
        "welfare"
    ],
    "wof:name":"Consumer's Choice",
    "wof:placetype":"venue"
},
  "geometry": {"coordinates":[-83.53807999999999,40.676388],"type":"Point"}
}