{
  "type": "Feature",
  "properties": {
    "iso:country":"US",
    "sg:address":"4492 Cemetery Rd",
    "sg:city":"Hilliard",
    "sg:classifiers":[
        {
            "category":"Health Services",
            "subcategory":"Chiropractor",
            "type":"Services"
        }
    ],
    "sg:phone":"+1 614 771 7500",
    "sg:postcode":"43026",
    "sg:province":"OH",
    "wof:name":"Hilliard Family Chiropractic",
    "wof:placetype":"venue"
},
  "geometry": {"coordinates":[-83.136211,40.032132],"type":"Point"}
}