{
  "type": "Feature",
  "properties": {
    "iso:country":"US",
    "sg:address":"2070 N Medina Line Rd",
    "sg:city":"Akron",
    "sg:classifiers":[
        {
            "category":"Farming",
            "subcategory":"Farm",
            "type":"Manufacturing & Wholesale Goods"
        }
    ],
    "sg:phone":"+1 330 659 7282",
    "sg:postcode":"44333",
    "sg:province":"OH",
    "sg:tags":[
        "crop",
        "general"
    ],
    "wof:name":"Willow Ridge Farm LLC",
    "wof:placetype":"venue"
},
  "geometry": {"coordinates":[-81.68012400000001,41.197699],"type":"Point"}
}