{
  "type": "Feature",
  "properties": {
    "addr:full": "2070 N Medina Line Rd Akron OH 44333",
    "addr:housenumber": "2070",
    "addr:postcode": "44333",
    "addr:street": "N Medina Line Rd",
    "iso:country": "US",
    "sg:address": "2070 N Medina Line Rd",
    "sg:city": "Akron",
    "sg:classifiers": [
      {
        "category": "Farming",
        "subcategory": "Farm",
        "type": "Manufacturing \u0026 Wholesale Goods"
      }
    ],
    "sg:phone": "+1 330 659 7282",
    "sg:postcode": "44333",
    "sg:province": "OH",
    "sg:tags": [
      "crop",
      "general"
    ],
    "wof:name": "Willow Ridge Farm LLC",
    "wof:placetype": "venue"
  },
  "geometry": {"coordinates":[-81.680124,41.197699],"type":"Point"}
}
