{
  "type": "Feature",
  "properties": {
    "addr:full":"8366 W Chester Rd West Chester OH 45069",
    "addr:housenumber":"8366",
    "addr:postcode":"45069",
    "addr:street":"W Chester Rd",
    "iso:country":"US",
    "sg:address":"8366 W Chester Rd",
    "sg:city":"West Chester",
    "sg:classifiers":[
        {
            "category":"Home & Garden",
            "subcategory":"Hardware",
            "type":"Retail Goods"
        }
    ],
    "sg:phone":"+1 513 942 1867",
    "sg:postcode":"45069",
    "sg:province":"OH",
    "wof:name":"TNT Results Inc",
    "wof:placetype":"venue"
},
  "geometry": {"coordinates":[-84.351935,39.317628],"type":"Point"}
}