{
  "type": "Feature",
  "properties": {
    "addr:full":"45 S Main St Dayton OH 45402",
    "addr:housenumber":"45",
    "addr:postcode":"45402",
    "addr:street":"S Main St",
    "iso:country":"US",
    "sg:address":"45 S Main St",
    "sg:city":"Dayton",
    "sg:classifiers":[
        {
            "category":"Shopping",
            "subcategory":"Used Merchandise",
            "type":"Retail Goods"
        }
    ],
    "sg:phone":"+1 937 222 2410",
    "sg:postcode":"45402",
    "sg:province":"OH",
    "sg:tags":[
        "shop",
        "consignment"
    ],
    "wof:name":"Suney's Outlet",
    "wof:placetype":"venue"
},
  "geometry": {"coordinates":[-84.191705,39.759045],"type":"Point"}
}