{
  "type": "Feature",
  "properties": {
    "addr:full": "4333 Tuller Rd Dublin OH 43017",
    "addr:housenumber": "4333",
    "addr:postcode": "43017",
    "addr:street": "Tuller Rd",
    "iso:country": "US",
    "sg:address": "4333 Tuller Rd",
    "sg:city": "Dublin",
    "sg:classifiers": [
      {
        "category": "Professional",
        "subcategory": "Management \u0026 Consulting",
        "type": "Services"
      }
    ],
    "sg:phone": "+1 614 718 9416",
    "sg:postcode": "43017",
    "sg:province": "OH",
    "sg:tags": [
      "fuel"
    ],
    "wof:name": "Schottenstein Management",
    "wof:placetype": "venue"
  },
  "geometry": {"coordinates":[-83.108548,40.107734],"type":"Point"}
}
