{
  "type": "Feature",
  "properties": {
    "iso:country":"US",
    "sg:address":"3122 E Hudson St",
    "sg:city":"Columbus",
    "sg:classifiers":[
        {
            "category":"Shopping",
            "subcategory":"Clothing, Apparel, & Fashions",
            "type":"Retail Goods"
        }
    ],
    "sg:phone":"+1 614 476 5504",
    "sg:postcode":"43219",
    "sg:province":"OH",
    "wof:name":"Ashley's Boutique",
    "wof:placetype":"venue"
},
  "geometry": {"coordinates":[-82.926039,40.011807],"type":"Point"}
}