{
  "type": "Feature",
  "properties": {
    "iso:country":"US",
    "sg:address":"8072 Beechmont Ave Ste B",
    "sg:city":"Cincinnati",
    "sg:classifiers":[
        {
            "category":"Health Services",
            "subcategory":"Doctor",
            "type":"Services"
        }
    ],
    "sg:phone":"+1 513 474 1700",
    "sg:postcode":"45255",
    "sg:province":"OH",
    "sg:tags":[
        "surgeon",
        "oral"
    ],
    "sg:website":"www.jmkirznerdds.com",
    "wof:name":"Kirzner Jerrold M DDS",
    "wof:placetype":"venue"
},
  "geometry": {"coordinates":[-84.33000199999999,39.073002],"type":"Point"}
}