{
  "type": "Feature",
  "properties": {
    "addr:full": "33 Erie Rd Tallmadge OH 44278",
    "addr:housenumber": "33",
    "addr:postcode": "44278",
    "addr:street": "Erie Rd",
    "iso:country": "US",
    "sg:address": "33 Erie Rd",
    "sg:city": "Tallmadge",
    "sg:classifiers": [
      {
        "category": "Sports \u0026 Exercise",
        "subcategory": "Gym",
        "type": "Entertainment"
      }
    ],
    "sg:phone": "+1 330 634 9835",
    "sg:postcode": "44278",
    "sg:province": "OH",
    "sg:tags": [
      "club",
      "health",
      "studio",
      "gymnasium"
    ],
    "wof:name": "Curves For Women",
    "wof:placetype": "venue"
  },
  "geometry": {"coordinates":[-81.438214,41.100442],"type":"Point"}
}
