{
  "type": "Feature",
  "properties": {
    "iso:country":"US",
    "sg:address":"21382 Lunn Rd",
    "sg:city":"Strongsville",
    "sg:classifiers":[
        {
            "category":"Building & Trades",
            "subcategory":"Construction",
            "type":"Services"
        }
    ],
    "sg:phone":"+1 440 235 4450",
    "sg:postcode":"44149",
    "sg:province":"OH",
    "sg:tags":[
        "concrete",
        "contractor"
    ],
    "wof:name":"Martin Concrete Construction",
    "wof:placetype":"venue"
},
  "geometry": {"coordinates":[-81.85791999999999,41.302593],"type":"Point"}
}