{
  "type": "Feature",
  "properties": {
    "addr:full":"8516 Beechmont Ave Cincinnati OH 45255",
    "addr:housenumber":"8516",
    "addr:postcode":"45255",
    "addr:street":"Beechmont Ave",
    "iso:country":"US",
    "sg:address":"8516 Beechmont Ave",
    "sg:city":"Cincinnati",
    "sg:classifiers":[
        {
            "category":"Social Services",
            "subcategory":"Child Care",
            "type":"Services"
        }
    ],
    "sg:phone":"+1 513 474 7800",
    "sg:postcode":"45255",
    "sg:province":"OH",
    "sg:tags":[
        "day"
    ],
    "wof:name":"Little Anderson Inc the",
    "wof:placetype":"venue"
},
  "geometry": {"coordinates":[-84.316597,39.071899],"type":"Point"}
}