{
  "type": "Feature",
  "properties": {
    "addr:full": "721 Beechwood Ave Cincinnati OH 45232",
    "addr:housenumber": "721",
    "addr:postcode": "45232",
    "addr:street": "Beechwood Ave",
    "iso:country": "US",
    "sg:address": "721 Beechwood Ave",
    "sg:city": "Cincinnati",
    "sg:classifiers": [
      {
        "category": "Retail",
        "subcategory": "Repair Shop",
        "type": "Services"
      }
    ],
    "sg:phone": "+1 513 541 5151",
    "sg:postcode": "45232",
    "sg:province": "OH",
    "sg:tags": [
      "bathtub",
      "sink",
      "refinishing"
    ],
    "wof:name": "Perry Porcelain Refinishing",
    "wof:placetype": "venue"
  },
  "geometry": {"coordinates":[-84.51656,39.175124],"type":"Point"}
}
