{
  "type": "Feature",
  "properties": {
    "addr:full":"16600 Hilliard Rd Cleveland OH 44107",
    "addr:housenumber":"16600",
    "addr:postcode":"44107",
    "addr:street":"Hilliard Rd",
    "iso:country":"US",
    "sg:address":"16600 Hilliard Rd",
    "sg:city":"Cleveland",
    "sg:classifiers":[
        {
            "category":"Education",
            "subcategory":"School",
            "type":"Public Place"
        }
    ],
    "sg:phone":"+1 216 529 4311",
    "sg:postcode":"44107",
    "sg:province":"OH",
    "wof:name":"Lakewood School Dist Attndnc",
    "wof:placetype":"venue"
},
  "geometry": {"coordinates":[-81.81267099999999,41.475835],"type":"Point"}
}