{
  "type": "Feature",
  "properties": {
    "addr:full":"23240 Chagrin Blvd Cleveland OH 44122",
    "addr:housenumber":"23240",
    "addr:postcode":"44122",
    "addr:street":"Chagrin Blvd",
    "iso:country":"US",
    "sg:address":"23240 Chagrin Blvd",
    "sg:city":"Cleveland",
    "sg:classifiers":[
        {
            "category":"Building & Trades",
            "subcategory":"Plumbing",
            "type":"Services"
        }
    ],
    "sg:phone":"+1 216 514 8448",
    "sg:postcode":"44122",
    "sg:province":"OH",
    "sg:tags":[
        "product",
        "management",
        "energy",
        "system"
    ],
    "wof:name":"Mid American Energy Co",
    "wof:placetype":"venue"
},
  "geometry": {"coordinates":[-81.505557,41.464401],"type":"Point"}
}