{
  "type": "Feature",
  "properties": {
    "addr:full": "4863 Tatersall Ct Columbus OH 43230",
    "addr:housenumber": "4863",
    "addr:postcode": "43230",
    "addr:street": "Tatersall Ct",
    "iso:country": "US",
    "sg:address": "4863 Tatersall Ct",
    "sg:city": "Columbus",
    "sg:classifiers": [
      {
        "category": "Wholesale",
        "subcategory": "Electrical",
        "type": "Manufacturing \u0026 Wholesale Goods"
      }
    ],
    "sg:phone": "+1 614 475 3614",
    "sg:postcode": "43230",
    "sg:province": "OH",
    "sg:tags": [
      "signal",
      "traffic",
      "sign"
    ],
    "wof:name": "Econolite Control Products Inc",
    "wof:placetype": "venue"
  },
  "geometry": {"coordinates":[-82.864705,40.076921],"type":"Point"}
}
