{
  "type": "Feature",
  "properties": {
    "iso:country":"US",
    "sg:address":"206 S Pike St",
    "sg:city":"Anna",
    "sg:classifiers":[
        {
            "category":"Shopping",
            "subcategory":"Department Store",
            "type":"Retail Goods"
        }
    ],
    "sg:phone":"+1 937 394 7141",
    "sg:postcode":"45302",
    "sg:province":"OH",
    "wof:name":"Triple K Enterprises",
    "wof:placetype":"venue"
},
  "geometry": {"coordinates":[-84.173106,40.393916],"type":"Point"}
}