{
  "type": "Feature",
  "properties": {
    "addr:full": "8398 Kinsman Rd Novelty OH 44072",
    "addr:housenumber": "8398",
    "addr:postcode": "44072",
    "addr:street": "Kinsman Rd",
    "iso:country": "US",
    "sg:address": "8398 Kinsman Rd",
    "sg:city": "Novelty",
    "sg:classifiers": [
      {
        "category": "Real Estate",
        "subcategory": "Real Estate Agent",
        "type": "Services"
      }
    ],
    "sg:phone": "+1 440 338 3868",
    "sg:postcode": "44072",
    "sg:province": "OH",
    "sg:tags": [
      "appraiser"
    ],
    "wof:name": "Lee Lynch Oley Assoc",
    "wof:placetype": "venue"
  },
  "geometry": {"coordinates":[-81.344842,41.462656],"type":"Point"}
}
