{
  "type": "Feature",
  "properties": {
    "addr:full": "1750 W Mulberry St Lancaster OH 43130",
    "addr:housenumber": "1750",
    "addr:postcode": "43130",
    "addr:street": "W Mulberry St",
    "iso:country": "US",
    "sg:address": "1750 W Mulberry St",
    "sg:city": "Lancaster",
    "sg:classifiers": [
      {
        "category": "Professional",
        "type": "Services"
      }
    ],
    "sg:phone": "+1 740 687 2292",
    "sg:postcode": "43130",
    "sg:province": "OH",
    "wof:name": "Hook Up",
    "wof:placetype": "venue"
  },
  "geometry": {"coordinates":[-82.629881,39.71841],"type":"Point"}
}
