{
  "type": "Feature",
  "properties": {
    "addr:full": "263 S Washington St Tiffin OH 44883",
    "addr:housenumber": "263",
    "addr:postcode": "44883",
    "addr:street": "S Washington St",
    "iso:country": "US",
    "sg:address": "263 S Washington St",
    "sg:city": "Tiffin",
    "sg:classifiers": [
      {
        "category": "Home \u0026 Garden",
        "subcategory": "Carpets \u0026 Floor Coverings",
        "type": "Retail Goods"
      }
    ],
    "sg:phone": "+1 419 447 7343",
    "sg:postcode": "44883",
    "sg:province": "OH",
    "sg:tags": [
      "rug",
      "drapery",
      "dealer"
    ],
    "wof:name": "Lee's Floor Coverings Inc",
    "wof:placetype": "venue"
  },
  "geometry": {"coordinates":[-83.175812,41.110327],"type":"Point"}
}
