{
  "type": "Feature",
  "properties": {
    "iso:country":"US",
    "sg:address":"263 S Washington St",
    "sg:city":"Tiffin",
    "sg:classifiers":[
        {
            "category":"Home & Garden",
            "subcategory":"Carpets & Floor Coverings",
            "type":"Retail Goods"
        }
    ],
    "sg:phone":"+1 419 447 7343",
    "sg:postcode":"44883",
    "sg:province":"OH",
    "sg:tags":[
        "rug",
        "drapery",
        "dealer"
    ],
    "wof:name":"Lee's Floor Coverings Inc",
    "wof:placetype":"venue"
},
  "geometry": {"coordinates":[-83.17581199999999,41.110327],"type":"Point"}
}