{
  "type": "Feature",
  "properties": {
    "addr:full": "240 Elmwood Dr Dayton OH 45459",
    "addr:housenumber": "240",
    "addr:postcode": "45459",
    "addr:street": "Elmwood Dr",
    "iso:country": "US",
    "sg:address": "240 Elmwood Dr",
    "sg:city": "Dayton",
    "sg:classifiers": [
      {
        "category": "Banks \u0026 Credit Unions",
        "subcategory": "Investment Brokerage",
        "type": "Services"
      }
    ],
    "sg:phone": "+1 937 434 9300",
    "sg:postcode": "45459",
    "sg:province": "OH",
    "sg:tags": [
      "advisory",
      "financial"
    ],
    "wof:name": "Cogent Financial Group",
    "wof:placetype": "venue"
  },
  "geometry": {"coordinates":[-84.15265,39.637111],"type":"Point"}
}
