{
  "type": "Feature",
  "properties": {
    "addr:full": "6237 Houchard Rd Amlin OH 43016",
    "addr:housenumber": "6237",
    "addr:postcode": "43016",
    "addr:street": "Houchard Rd",
    "iso:country": "US",
    "sg:address": "6237 Houchard Rd",
    "sg:city": "Amlin",
    "sg:classifiers": [
      {
        "category": "Manufacturing",
        "subcategory": "Glass \u0026 Minerals",
        "type": "Manufacturing \u0026 Wholesale Goods"
      }
    ],
    "sg:phone": "+1 614 873 5373",
    "sg:postcode": "43016",
    "sg:province": "OH",
    "sg:tags": [
      "ready",
      "concrete",
      "manufacturer"
    ],
    "wof:name": "Ellis Brothers Inc",
    "wof:placetype": "venue"
  },
  "geometry": {"coordinates":[-83.2018,40.103024],"type":"Point"}
}
