{
  "type": "Feature",
  "properties": {
    "iso:country":"US",
    "sg:address":"6237 Houchard Rd",
    "sg:city":"Amlin",
    "sg:classifiers":[
        {
            "category":"Manufacturing",
            "subcategory":"Glass & Minerals",
            "type":"Manufacturing & Wholesale Goods"
        }
    ],
    "sg:phone":"+1 614 873 5373",
    "sg:postcode":"43016",
    "sg:province":"OH",
    "sg:tags":[
        "ready",
        "concrete",
        "manufacturer"
    ],
    "wof:name":"Ellis Brothers Inc",
    "wof:placetype":"venue"
},
  "geometry": {"coordinates":[-83.20180000000001,40.103024],"type":"Point"}
}