{
  "type": "Feature",
  "properties": {
    "iso:country":"US",
    "sg:address":"1415 Worthington Center Dr",
    "sg:city":"Columbus",
    "sg:classifiers":[
        {
            "category":"Shopping",
            "subcategory":"Discount & Variety Stores",
            "type":"Retail Goods"
        }
    ],
    "sg:phone":"+1 614 985 4667",
    "sg:postcode":"43085",
    "sg:province":"OH",
    "wof:name":"Dollar Tree",
    "wof:placetype":"venue"
},
  "geometry": {"coordinates":[-82.980625,40.123199],"type":"Point"}
}