{
  "type": "Feature",
  "properties": {
    "iso:country":"US",
    "sg:address":"31340 Noble Summit Rd",
    "sg:city":"Middleport",
    "sg:classifiers":[
        {
            "category":"Farming",
            "subcategory":"Nursery",
            "type":"Manufacturing & Wholesale Goods"
        }
    ],
    "sg:phone":"+1 740 992 7960",
    "sg:postcode":"45760",
    "sg:province":"OH",
    "sg:tags":[
        "greenhouse"
    ],
    "wof:name":"Ed's Greenhouses",
    "wof:placetype":"venue"
},
  "geometry": {"coordinates":[-82.093806,39.019957],"type":"Point"}
}