{
  "type": "Feature",
  "properties": {
    "iso:country":"US",
    "sg:address":"9669 Colerain Ave",
    "sg:city":"Cincinnati",
    "sg:classifiers":[
        {
            "category":"Personal",
            "type":"Services"
        }
    ],
    "sg:phone":"+1 513 923 1771",
    "sg:postcode":"45251",
    "sg:province":"OH",
    "sg:tags":[
        "formal",
        "retail",
        "wear",
        "accessory",
        "rent"
    ],
    "wof:name":"Skeffingtons Formalwear Inc",
    "wof:placetype":"venue"
},
  "geometry": {"coordinates":[-84.595893,39.245739],"type":"Point"}
}