{
  "type": "Feature",
  "properties": {
    "addr:full":"106 W Market St Exd Warren OH 44481",
    "addr:housenumber":"106",
    "addr:postcode":"44481",
    "addr:street":"W Market St Exd",
    "iso:country":"US",
    "sg:address":"106 W Market St Exd",
    "sg:city":"Warren",
    "sg:classifiers":[
        {
            "category":"Professional",
            "subcategory":"Lawyer & Legal Services",
            "type":"Services"
        }
    ],
    "sg:phone":"+1 330 394 3126",
    "sg:postcode":"44481",
    "sg:province":"OH",
    "sg:tags":[
        "attorney"
    ],
    "wof:name":"Phelps & King",
    "wof:placetype":"venue"
},
  "geometry": {"coordinates":[-80.81993300000001,41.236163],"type":"Point"}
}