{
  "type": "Feature",
  "properties": {
    "iso:country":"US",
    "sg:address":"1988 Presidential Pkwy",
    "sg:city":"Twinsburg",
    "sg:classifiers":[
        {
            "category":"Shopping",
            "type":"Retail Goods"
        }
    ],
    "sg:phone":"+1 330 963 5497",
    "sg:postcode":"44087",
    "sg:province":"OH",
    "sg:tags":[
        "craft",
        "gallery",
        "dealer"
    ],
    "wof:name":"Weathervain & Things",
    "wof:placetype":"venue"
},
  "geometry": {"coordinates":[-81.463869,41.327378],"type":"Point"}
}