{
  "type": "Feature",
  "properties": {
    "addr:full": "1988 Presidential Pkwy Twinsburg OH 44087",
    "addr:housenumber": "1988",
    "addr:postcode": "44087",
    "addr:street": "Presidential Pkwy",
    "iso:country": "US",
    "sg:address": "1988 Presidential Pkwy",
    "sg:city": "Twinsburg",
    "sg:classifiers": [
      {
        "category": "Shopping",
        "type": "Retail Goods"
      }
    ],
    "sg:phone": "+1 330 963 5497",
    "sg:postcode": "44087",
    "sg:province": "OH",
    "sg:tags": [
      "craft",
      "gallery",
      "dealer"
    ],
    "wof:name": "Weathervain \u0026 Things",
    "wof:placetype": "venue"
  },
  "geometry": {"coordinates":[-81.463869,41.327378],"type":"Point"}
}
