{
  "type": "Feature",
  "properties": {
    "addr:full": "11471 Glynwood Rd Wapakoneta OH 45895",
    "addr:housenumber": "11471",
    "addr:postcode": "45895",
    "addr:street": "Glynwood Rd",
    "iso:country": "US",
    "sg:address": "11471 Glynwood Rd",
    "sg:city": "Wapakoneta",
    "sg:classifiers": [
      {
        "category": "Professional",
        "subcategory": "Accounting \u0026 Tax Preparation",
        "type": "Services"
      }
    ],
    "sg:phone": "+1 419 738 6021",
    "sg:postcode": "45895",
    "sg:province": "OH",
    "sg:tags": [
      "return",
      "filing"
    ],
    "wof:name": "Now Bookkeeping \u0026 Tax Svc",
    "wof:placetype": "venue"
  },
  "geometry": {"coordinates":[-84.229651,40.585437],"type":"Point"}
}
