{
  "type": "Feature",
  "properties": {
    "addr:full":"1985 W Henderson Rd Columbus OH 43220",
    "addr:housenumber":"1985",
    "addr:postcode":"43220",
    "addr:street":"W Henderson Rd",
    "iso:country":"US",
    "sg:address":"1985 W Henderson Rd",
    "sg:city":"Columbus",
    "sg:classifiers":[
        {
            "category":"Professional",
            "subcategory":"Business Services",
            "type":"Services"
        }
    ],
    "sg:phone":"+1 614 538 8905",
    "sg:postcode":"43220",
    "sg:province":"OH",
    "sg:tags":[
        "packaging"
    ],
    "wof:name":"Pak Mail Ctr",
    "wof:placetype":"venue"
},
  "geometry": {"coordinates":[-83.071713,40.05586],"type":"Point"}
}