{
  "type": "Feature",
  "properties": {
    "addr:full": "4339 Talmadge Rd Toledo OH 43623",
    "addr:housenumber": "4339",
    "addr:postcode": "43623",
    "addr:street": "Talmadge Rd",
    "iso:country": "US",
    "sg:address": "4339 Talmadge Rd",
    "sg:city": "Toledo",
    "sg:classifiers": [
      {
        "category": "Health Services",
        "subcategory": "Doctor",
        "type": "Services"
      }
    ],
    "sg:phone": "+1 419 472 5725",
    "sg:postcode": "43623",
    "sg:province": "OH",
    "sg:tags": [
      "dentist"
    ],
    "wof:name": "Jardin \u0026 Buganski",
    "wof:placetype": "venue"
  },
  "geometry": {"coordinates":[-83.644917,41.696711],"type":"Point"}
}
