{
  "type": "Feature",
  "properties": {
    "iso:country":"US",
    "sg:address":"4339 Talmadge Rd",
    "sg:city":"Toledo",
    "sg:classifiers":[
        {
            "category":"Health Services",
            "subcategory":"Doctor",
            "type":"Services"
        }
    ],
    "sg:phone":"+1 419 472 5725",
    "sg:postcode":"43623",
    "sg:province":"OH",
    "sg:tags":[
        "dentist"
    ],
    "wof:name":"Jardin & Buganski",
    "wof:placetype":"venue"
},
  "geometry": {"coordinates":[-83.64491700000001,41.696711],"type":"Point"}
}