{
  "type": "Feature",
  "properties": {
    "addr:full": "5163 State Rte 98 Bucyrus OH 44820",
    "addr:housenumber": "5163",
    "addr:postcode": "44820",
    "addr:street": "State Rte 98",
    "iso:country": "US",
    "sg:address": "5163 State Rte 98",
    "sg:city": "Bucyrus",
    "sg:classifiers": [
      {
        "category": "Restaurant",
        "type": "Food \u0026 Drink"
      }
    ],
    "sg:phone": "+1 419 562 8547",
    "sg:postcode": "44820",
    "sg:province": "OH",
    "sg:tags": [
      "eating"
    ],
    "wof:name": "Crums Banquet \u0026 Catering LLC",
    "wof:placetype": "venue"
  },
  "geometry": {"coordinates":[-82.8362,40.892677],"type":"Point"}
}
