{
  "type": "Feature",
  "properties": {
    "iso:country":"US",
    "sg:address":"5163 State Rte 98",
    "sg:city":"Bucyrus",
    "sg:classifiers":[
        {
            "category":"Restaurant",
            "type":"Food & Drink"
        }
    ],
    "sg:phone":"+1 419 562 8547",
    "sg:postcode":"44820",
    "sg:province":"OH",
    "sg:tags":[
        "eating"
    ],
    "wof:name":"Crums Banquet & Catering LLC",
    "wof:placetype":"venue"
},
  "geometry": {"coordinates":[-82.83620000000001,40.892677],"type":"Point"}
}