{
  "type": "Feature",
  "properties": {
    "addr:full": "2057 Harshman Rd Dayton OH 45424",
    "addr:housenumber": "2057",
    "addr:postcode": "45424",
    "addr:street": "Harshman Rd",
    "iso:country": "US",
    "sg:address": "2057 Harshman Rd",
    "sg:city": "Dayton",
    "sg:classifiers": [
      {
        "category": "Restaurant",
        "type": "Food \u0026 Drink"
      }
    ],
    "sg:menulink": "http://www.allmenus.com/oh/riverside/134289-subway/menu/",
    "sg:phone": "+1 937 237 1606",
    "sg:postcode": "45424",
    "sg:province": "OH",
    "sg:tags": [
      "american",
      "sandwich"
    ],
    "wof:name": "Subway",
    "wof:placetype": "venue"
  },
  "geometry": {"coordinates":[-84.129673,39.799367],"type":"Point"}
}
