{
  "type": "Feature",
  "properties": {
    "addr:full": "13450 State Rte 576 Montpelier OH 43543",
    "addr:housenumber": "13450",
    "addr:postcode": "43543",
    "addr:street": "State Rte 576",
    "iso:country": "US",
    "sg:address": "13450 State Rte 576",
    "sg:city": "Montpelier",
    "sg:classifiers": [
      {
        "category": "Wholesale",
        "subcategory": "Construction Materials",
        "type": "Manufacturing \u0026 Wholesale Goods"
      }
    ],
    "sg:phone": "+1 419 485 2124",
    "sg:postcode": "43543",
    "sg:province": "OH",
    "sg:tags": [
      "sand",
      "gravel"
    ],
    "wof:name": "St Joe Sand \u0026 Gravel LLC",
    "wof:placetype": "venue"
  },
  "geometry": {"coordinates":[-84.613176,41.609428],"type":"Point"}
}
