{
  "type": "Feature",
  "properties": {
    "addr:full":"1647 E 361st St Willoughby OH 44095",
    "addr:housenumber":"1647",
    "addr:postcode":"44095",
    "addr:street":"E 361St St",
    "iso:country":"US",
    "sg:address":"1647 E 361st St",
    "sg:city":"Willoughby",
    "sg:classifiers":[
        {
            "category":"Building & Trades",
            "subcategory":"Construction",
            "type":"Services"
        }
    ],
    "sg:phone":"+1 440 951 4008",
    "sg:postcode":"44095",
    "sg:province":"OH",
    "sg:tags":[
        "concrete",
        "paving",
        "asphalt",
        "contractor"
    ],
    "sg:website":"www.northeasternasphalt.com",
    "wof:name":"Northeastern Asphalt & Paving",
    "wof:placetype":"venue"
},
  "geometry": {"coordinates":[-81.430835,41.637899],"type":"Point"}
}