{
  "type": "Feature",
  "properties": {
    "iso:country":"US",
    "sg:address":"6063 Frantz Rd",
    "sg:city":"Dublin",
    "sg:classifiers":[
        {
            "category":"Professional",
            "subcategory":"Business Services",
            "type":"Services"
        }
    ],
    "sg:phone":"+1 614 889 9985",
    "sg:postcode":"43017",
    "sg:province":"OH",
    "sg:tags":[
        "interior",
        "consultant",
        "design",
        "decorator"
    ],
    "wof:name":"Susan R Matrka Interiors Inc",
    "wof:placetype":"venue"
},
  "geometry": {"coordinates":[-83.123972,40.090216],"type":"Point"}
}