{
  "type": "Feature",
  "properties": {
    "iso:country":"US",
    "sg:address":"24 S Cucumber St",
    "sg:city":"Jefferson",
    "sg:classifiers":[
        {
            "category":"Retail",
            "subcategory":"Veterinary Services",
            "type":"Services"
        }
    ],
    "sg:phone":"+1 440 576 9440",
    "sg:postcode":"44047",
    "sg:province":"OH",
    "sg:tags":[
        "veterinarian"
    ],
    "wof:name":"Country Doctor Veterinary",
    "wof:placetype":"venue"
},
  "geometry": {"coordinates":[-80.753874,41.738065],"type":"Point"}
}