{
  "type": "Feature",
  "properties": {
    "addr:full": "66 S Miller Rd Fairlawn OH 44333",
    "addr:housenumber": "66",
    "addr:postcode": "44333",
    "addr:street": "S Miller Rd",
    "iso:country": "US",
    "sg:address": "66 S Miller Rd",
    "sg:city": "Fairlawn",
    "sg:classifiers": [
      {
        "category": "Professional",
        "subcategory": "Employment Agencies",
        "type": "Services"
      }
    ],
    "sg:phone": "+1 330 836 1133",
    "sg:postcode": "44333",
    "sg:province": "OH",
    "sg:tags": [
      "modeling"
    ],
    "wof:name": "Ryan \u0026 Orem Modeling \u0026 Talent",
    "wof:placetype": "venue"
  },
  "geometry": {"coordinates":[-81.609852,41.126218],"type":"Point"}
}
