{
  "type": "Feature",
  "properties": {
    "iso:country":"US",
    "sg:address":"8001 Ravines Edge Ct",
    "sg:city":"Columbus",
    "sg:classifiers":[
        {
            "category":"Professional",
            "subcategory":"Lawyer & Legal Services",
            "type":"Services"
        }
    ],
    "sg:phone":"+1 614 885 0038",
    "sg:postcode":"43235",
    "sg:province":"OH",
    "sg:tags":[
        "attorney"
    ],
    "wof:name":"Sinno & Hamilton",
    "wof:placetype":"venue"
},
  "geometry": {"coordinates":[-83.019262,40.126585],"type":"Point"}
}