{
  "type": "Feature",
  "properties": {
    "addr:full": "8001 Ravines Edge Ct Columbus OH 43235",
    "addr:postcode": "8001;43235",
    "addr:street": "Ravines Edge Ct",
    "iso:country": "US",
    "sg:address": "8001 Ravines Edge Ct",
    "sg:city": "Columbus",
    "sg:classifiers": [
      {
        "category": "Professional",
        "subcategory": "Lawyer \u0026 Legal Services",
        "type": "Services"
      }
    ],
    "sg:phone": "+1 614 885 0038",
    "sg:postcode": "43235",
    "sg:province": "OH",
    "sg:tags": [
      "attorney"
    ],
    "wof:name": "Sinno \u0026 Hamilton",
    "wof:placetype": "venue"
  },
  "geometry": {"coordinates":[-83.019262,40.126585],"type":"Point"}
}
