{
  "type": "Feature",
  "properties": {
    "addr:full": "24600 Center Ridge Rd Cleveland OH 44145",
    "addr:housenumber": "24600",
    "addr:postcode": "44145",
    "addr:street": "Center Ridge Rd",
    "iso:country": "US",
    "sg:address": "24600 Center Ridge Rd",
    "sg:city": "Cleveland",
    "sg:classifiers": [
      {
        "category": "Professional",
        "subcategory": "Management \u0026 Consulting",
        "type": "Services"
      }
    ],
    "sg:phone": "+1 440 808 6800",
    "sg:postcode": "44145",
    "sg:province": "OH",
    "sg:tags": [
      "personnel",
      "consultant"
    ],
    "wof:name": "Executive Dynamics",
    "wof:placetype": "venue"
  },
  "geometry": {"coordinates":[-81.890756,41.458101],"type":"Point"}
}
