{
  "type": "Feature",
  "properties": {
    "iso:country":"US",
    "sg:address":"1251 Lexington Ave",
    "sg:city":"Mansfield",
    "sg:classifiers":[
        {
            "category":"Wholesale",
            "subcategory":"Office Equipment",
            "type":"Manufacturing & Wholesale Goods"
        }
    ],
    "sg:phone":"+1 419 756 7225",
    "sg:postcode":"44907",
    "sg:province":"OH",
    "wof:name":"Mid Ohio Office Systems",
    "wof:placetype":"venue"
},
  "geometry": {"coordinates":[-82.54111,40.724116],"type":"Point"}
}