{
  "type": "Feature",
  "properties": {
    "addr:full": "125 Wayne Ave Bucyrus OH 44820",
    "addr:housenumber": "125",
    "addr:postcode": "44820",
    "addr:street": "Wayne Ave",
    "iso:country": "US",
    "sg:address": "125 Wayne Ave",
    "sg:city": "Bucyrus",
    "sg:classifiers": [
      {
        "category": "Personal",
        "subcategory": "Beauty Salon",
        "type": "Services"
      }
    ],
    "sg:phone": "+1 419 562 1738",
    "sg:postcode": "44820",
    "sg:province": "OH",
    "wof:name": "Tonya's Hair Fashions",
    "wof:placetype": "venue"
  },
  "geometry": {"coordinates":[-82.956256,40.811146],"type":"Point"}
}
