{
  "type": "Feature",
  "properties": {
    "addr:full": "805 S Main St Englewood OH 45322",
    "addr:housenumber": "805",
    "addr:postcode": "45322",
    "addr:street": "S Main St",
    "iso:country": "US",
    "sg:address": "805 S Main St",
    "sg:city": "Englewood",
    "sg:classifiers": [
      {
        "category": "Sports \u0026 Exercise",
        "subcategory": "Bowling",
        "type": "Entertainment"
      }
    ],
    "sg:phone": "+1 937 836 5177",
    "sg:postcode": "45322",
    "sg:province": "OH",
    "sg:tags": [
      "center"
    ],
    "wof:name": "Thunderbowl Lanes",
    "wof:placetype": "venue"
  },
  "geometry": {"coordinates":[-84.28735,39.864283],"type":"Point"}
}
