{
  "type": "Feature",
  "properties": {
    "iso:country":"US",
    "sg:address":"11250 Chester Rd",
    "sg:city":"Cincinnati",
    "sg:classifiers":[
        {
            "category":"Retail",
            "subcategory":"Auto Rental",
            "type":"Services"
        }
    ],
    "sg:phone":"+1 513 771 3518",
    "sg:postcode":"45246",
    "sg:province":"OH",
    "sg:tags":[
        "renting",
        "automobile"
    ],
    "wof:name":"Hertz Rent A Car",
    "wof:placetype":"venue"
},
  "geometry": {"coordinates":[-84.444203,39.273007],"type":"Point"}
}