{
  "type": "Feature",
  "properties": {
    "addr:full": "3970 State Rte 229 Marengo OH 43334",
    "addr:housenumber": "3970",
    "addr:postcode": "43334",
    "addr:street": "State Rte 229",
    "iso:country": "US",
    "sg:address": "3970 State Rte 229",
    "sg:city": "Marengo",
    "sg:classifiers": [
      {
        "category": "Autos \u0026 Motor Vehicles",
        "subcategory": "Automobile Sales",
        "type": "Retail Goods"
      }
    ],
    "sg:phone": "+1 419 253 2991",
    "sg:postcode": "43334",
    "sg:province": "OH",
    "sg:tags": [
      "sport",
      "trailer",
      "utility"
    ],
    "wof:name": "Hill Equipment",
    "wof:placetype": "venue"
  },
  "geometry": {"coordinates":[-82.828259,40.400748],"type":"Point"}
}
