{
  "type": "Feature",
  "properties": {
    "addr:full":"2902 Cleveland Rd W Huron OH 44839",
    "addr:housenumber":"2902",
    "addr:postcode":"44839",
    "addr:street":"Cleveland Rd W",
    "iso:country":"US",
    "sg:address":"2902 Cleveland Rd W",
    "sg:city":"Huron",
    "sg:classifiers":[
        {
            "category":"Organizations",
            "subcategory":"Community Association",
            "type":"Services"
        }
    ],
    "sg:phone":"+1 419 433 4611",
    "sg:postcode":"44839",
    "sg:province":"OH",
    "sg:tags":[
        "fraternal"
    ],
    "wof:name":"Huron Eagles Club",
    "wof:placetype":"venue"
},
  "geometry": {"coordinates":[-82.587407,41.40832],"type":"Point"}
}