{
  "type": "Feature",
  "properties": {
    "addr:full":"406 Shorb Ave NW Canton OH 44703",
    "addr:housenumber":"406",
    "addr:postcode":"44703",
    "addr:street":"Shorb Ave Nw",
    "iso:country":"US",
    "sg:address":"406 Shorb Ave NW",
    "sg:city":"Canton",
    "sg:classifiers":[
        {
            "category":"Professional",
            "subcategory":"Management & Consulting",
            "type":"Services"
        },
        {
            "category":"Social Services",
            "subcategory":"Job Training",
            "type":"Services"
        }
    ],
    "sg:phone":"+1 330 588 3205",
    "sg:postcode":"44703",
    "sg:province":"OH",
    "sg:tags":[
        "consultant"
    ],
    "wof:name":"Project Rebuild Inc",
    "wof:placetype":"venue"
},
  "geometry": {"coordinates":[-81.380831,40.802058],"type":"Point"}
}