{
  "type": "Feature",
  "properties": {
    "iso:country":"US",
    "sg:address":"1499 Hamilton New London Rd",
    "sg:city":"Hamilton",
    "sg:classifiers":[
        {
            "category":"Professional",
            "subcategory":"Management & Consulting",
            "type":"Services"
        }
    ],
    "sg:phone":"+1 513 896 5998",
    "sg:postcode":"45013",
    "sg:province":"OH",
    "sg:tags":[
        "farm"
    ],
    "wof:name":"Wilson Farm Magement",
    "wof:placetype":"venue"
},
  "geometry": {"coordinates":[-84.62339799999999,39.374996],"type":"Point"}
}