{
  "type": "Feature",
  "properties": {
    "addr:full": "1499 Hamilton New London Rd Hamilton OH 45013",
    "addr:housenumber": "1499",
    "addr:postcode": "45013",
    "addr:street": "New London Rd",
    "iso:country": "US",
    "sg:address": "1499 Hamilton New London Rd",
    "sg:city": "Hamilton",
    "sg:classifiers": [
      {
        "category": "Professional",
        "subcategory": "Management \u0026 Consulting",
        "type": "Services"
      }
    ],
    "sg:phone": "+1 513 896 5998",
    "sg:postcode": "45013",
    "sg:province": "OH",
    "sg:tags": [
      "farm"
    ],
    "wof:name": "Wilson Farm Magement",
    "wof:placetype": "venue"
  },
  "geometry": {"coordinates":[-84.623398,39.374996],"type":"Point"}
}
