{
  "type": "Feature",
  "properties": {
    "addr:full": "16029 Nauvoo Rd Middlefield OH 44062",
    "addr:housenumber": "16029",
    "addr:postcode": "44062",
    "addr:street": "Nauvoo Rd",
    "iso:country": "US",
    "sg:address": "16029 Nauvoo Rd",
    "sg:city": "Middlefield",
    "sg:classifiers": [
      {
        "category": "Shopping",
        "subcategory": "Gifts \u0026 Souvenirs",
        "type": "Retail Goods"
      }
    ],
    "sg:phone": "+1 440 632 0950",
    "sg:postcode": "44062",
    "sg:province": "OH",
    "sg:tags": [
      "basket",
      "parcel"
    ],
    "wof:name": "Granny's Basket \u0026 Boutique",
    "wof:placetype": "venue"
  },
  "geometry": {"coordinates":[-81.057478,41.479148],"type":"Point"}
}
