{
  "type": "Feature",
  "properties": {
    "addr:full": "5561 Merily Way Dayton OH 45424",
    "addr:housenumber": "5561",
    "addr:postcode": "45424",
    "addr:street": "Merily Way",
    "iso:country": "US",
    "sg:address": "5561 Merily Way",
    "sg:city": "Dayton",
    "sg:classifiers": [
      {
        "category": "Ice Cream",
        "type": "Food \u0026 Drink"
      }
    ],
    "sg:menulink": "http://www.allmenus.com/oh/huber-heights/165230-dairy-queen/menu/",
    "sg:phone": "+1 937 237 9407",
    "sg:postcode": "45424",
    "sg:province": "OH",
    "sg:tags": [
      "burger",
      "american"
    ],
    "wof:name": "Dairy Queen",
    "wof:placetype": "venue"
  },
  "geometry": {"coordinates":[-84.136369,39.867183],"type":"Point"}
}
