{
  "type": "Feature",
  "properties": {
    "addr:full": "8500 Co Hwy 373 Big Prairie OH 44611",
    "addr:housenumber": "8500",
    "addr:postcode": "44611",
    "addr:street": "Co Hwy 373",
    "iso:country": "US",
    "sg:address": "8500 Co Hwy 373",
    "sg:city": "Big Prairie",
    "sg:classifiers": [
      {
        "category": "Home \u0026 Garden",
        "subcategory": "Home Furnishings",
        "type": "Retail Goods"
      }
    ],
    "sg:phone": "+1 330 496 2406",
    "sg:postcode": "44611",
    "sg:province": "OH",
    "wof:name": "Holmes County Pottery",
    "wof:placetype": "venue"
  },
  "geometry": {"coordinates":[-82.081746,40.653311],"type":"Point"}
}
