{
  "type": "Feature",
  "properties": {
    "iso:country":"US",
    "sg:address":"1127 Beatty Ave",
    "sg:city":"Cambridge",
    "sg:classifiers":[
        {
            "category":"Social Services",
            "subcategory":"Child Care",
            "type":"Services"
        },
        {
            "category":"Social Services",
            "type":"Services"
        }
    ],
    "sg:phone":"+1 740 439 3493",
    "sg:postcode":"43725",
    "sg:province":"OH",
    "sg:tags":[
        "organization",
        "day",
        "welfare"
    ],
    "wof:name":"Beatty Ave Head Start Center",
    "wof:placetype":"venue"
},
  "geometry": {"coordinates":[-81.584337,40.028688],"type":"Point"}
}