{
  "type": "Feature",
  "properties": {
    "addr:full": "1991 S Baney Rd Ashland OH 44805",
    "addr:housenumber": "1991",
    "addr:postcode": "44805",
    "addr:street": "S Baney Rd",
    "iso:country": "US",
    "sg:address": "1991 S Baney Rd",
    "sg:city": "Ashland",
    "sg:classifiers": [
      {
        "category": "Retail",
        "subcategory": "Portrait Studio",
        "type": "Services"
      }
    ],
    "sg:phone": "+1 419 281 7584",
    "sg:postcode": "44805",
    "sg:province": "OH",
    "sg:tags": [
      "photographer"
    ],
    "wof:name": "Wal-Mart Portrait Studio",
    "wof:placetype": "venue"
  },
  "geometry": {"coordinates":[-82.349056,40.845423],"type":"Point"}
}
