{
  "type": "Feature",
  "properties": {
    "addr:full":"10860 Louisville St NE Louisville OH 44641",
    "addr:housenumber":"10860",
    "addr:postcode":"44641",
    "addr:street":"Louisville St Ne",
    "iso:country":"US",
    "sg:address":"10860 Louisville St NE",
    "sg:city":"Louisville",
    "sg:classifiers":[
        {
            "category":"Building & Trades",
            "subcategory":"Plumbing",
            "type":"Services"
        }
    ],
    "sg:phone":"+1 330 875 1103",
    "sg:postcode":"44641",
    "sg:province":"OH",
    "sg:tags":[
        "contractor"
    ],
    "wof:name":"Barley Eldon",
    "wof:placetype":"venue"
},
  "geometry": {"coordinates":[-81.211643,40.834859],"type":"Point"}
}