{
  "type": "Feature",
  "properties": {
    "addr:full":"22355 Rivergate Dr Rocky River OH 44116",
    "addr:housenumber":"22355",
    "addr:postcode":"44116",
    "addr:street":"Rivergate Dr",
    "iso:country":"US",
    "sg:address":"22355 Rivergate Dr",
    "sg:city":"Rocky River",
    "sg:classifiers":[
        {
            "category":"Freight",
            "type":"Transportation"
        }
    ],
    "sg:phone":"+1 440 356 1400",
    "sg:postcode":"44116",
    "sg:province":"OH",
    "wof:name":"Nyk Logistics Americas Gst Div",
    "wof:placetype":"venue"
},
  "geometry": {"coordinates":[-81.86902600000001,41.450257],"type":"Point"}
}