{
  "type": "Feature",
  "properties": {
    "iso:country":"US",
    "sg:address":"12411 Kinsman Rd",
    "sg:city":"Burton",
    "sg:classifiers":[
        {
            "category":"Autos & Motor Vehicles",
            "subcategory":"Fuel & Gas Station",
            "type":"Retail Goods"
        }
    ],
    "sg:phone":"+1 440 834 4445",
    "sg:postcode":"44021",
    "sg:province":"OH",
    "sg:tags":[
        "oil"
    ],
    "wof:name":"Big Moe's Bp Corp",
    "wof:placetype":"venue"
},
  "geometry": {"coordinates":[-81.190926,41.470761],"type":"Point"}
}