{
  "type": "Feature",
  "properties": {
    "addr:full": "1410 Friar Ln Columbus OH 43221",
    "addr:housenumber": "1410",
    "addr:postcode": "43221",
    "addr:street": "Friar Ln",
    "iso:country": "US",
    "sg:address": "1410 Friar Ln",
    "sg:city": "Columbus",
    "sg:classifiers": [
      {
        "category": "Professional",
        "subcategory": "Management \u0026 Consulting",
        "type": "Services"
      }
    ],
    "sg:phone": "+1 614 459 7790",
    "sg:postcode": "43221",
    "sg:province": "OH",
    "sg:tags": [
      "export"
    ],
    "wof:name": "IMTREX Corp",
    "wof:placetype": "venue"
  },
  "geometry": {"coordinates":[-83.05037,40.026039],"type":"Point"}
}
