{
  "type": "Feature",
  "properties": {
    "iso:country":"US",
    "sg:address":"1410 Friar Ln",
    "sg:city":"Columbus",
    "sg:classifiers":[
        {
            "category":"Professional",
            "subcategory":"Management & Consulting",
            "type":"Services"
        }
    ],
    "sg:phone":"+1 614 459 7790",
    "sg:postcode":"43221",
    "sg:province":"OH",
    "sg:tags":[
        "export"
    ],
    "wof:name":"IMTREX Corp",
    "wof:placetype":"venue"
},
  "geometry": {"coordinates":[-83.05037,40.026039],"type":"Point"}
}