{
  "type": "Feature",
  "properties": {
    "addr:full":"13354 State Rte 108 Wauseon OH 43567",
    "addr:housenumber":"13354",
    "addr:postcode":"43567",
    "addr:street":"State Rte 108",
    "iso:country":"US",
    "sg:address":"13354 State Rte 108",
    "sg:city":"Wauseon",
    "sg:phone":"+1 419 337 8228",
    "sg:postcode":"43567",
    "sg:province":"OH",
    "sg:tags":[
        "farm",
        "repair",
        "corn",
        "soybean"
    ],
    "wof:name":"Bills Repair",
    "wof:placetype":"venue"
},
  "geometry": {"coordinates":[-84.152106,41.662528],"type":"Point"}
}