{
  "type": "Feature",
  "properties": {
    "addr:full":"3939 Swartzel Rd Farmersville OH 45325",
    "addr:housenumber":"3939",
    "addr:postcode":"45325",
    "addr:street":"Swartzel Rd",
    "iso:country":"US",
    "sg:address":"3939 Swartzel Rd",
    "sg:city":"Farmersville",
    "sg:classifiers":[
        {
            "category":"Building & Trades",
            "subcategory":"Construction",
            "type":"Services"
        }
    ],
    "sg:phone":"+1 937 696 2114",
    "sg:postcode":"45325",
    "sg:province":"OH",
    "sg:tags":[
        "masonry",
        "contractor"
    ],
    "wof:name":"Wilder Masonry",
    "wof:placetype":"venue"
},
  "geometry": {"coordinates":[-84.45167499999999,39.678066],"type":"Point"}
}