{
  "type": "Feature",
  "properties": {
    "addr:full": "1230 3rd St NW New Philadelphia OH 44663",
    "addr:housenumber": "1230",
    "addr:postcode": "44663",
    "addr:street": "3Rd St Nw New Philadelphia",
    "iso:country": "US",
    "sg:address": "1230 3rd St NW",
    "sg:city": "New Philadelphia",
    "sg:classifiers": [
      {
        "category": "Building \u0026 Trades",
        "subcategory": "Construction",
        "type": "Services"
      }
    ],
    "sg:phone": "+1 330 364 3200",
    "sg:postcode": "44663",
    "sg:province": "OH",
    "sg:tags": [
      "sign",
      "contractor"
    ],
    "wof:name": "M G Sign",
    "wof:placetype": "venue"
  },
  "geometry": {"coordinates":[-81.450113,40.505812],"type":"Point"}
}
