{
  "type": "Feature",
  "properties": {
    "iso:country":"US",
    "sg:address":"315 Liberty St",
    "sg:city":"West Liberty",
    "sg:classifiers":[
        {
            "category":"Organizations",
            "subcategory":"Religious Organization",
            "type":"Services"
        }
    ],
    "sg:phone":"+1 937 465 5600",
    "sg:postcode":"43357",
    "sg:province":"OH",
    "sg:tags":[
        "church"
    ],
    "wof:name":"First Church Of God",
    "wof:placetype":"venue"
},
  "geometry": {"coordinates":[-83.75185,40.255164],"type":"Point"}
}