{
  "type": "Feature",
  "properties": {
    "addr:full": "22 Milton St Seville OH 44273",
    "addr:housenumber": "22",
    "addr:postcode": "44273",
    "addr:street": "Milton St",
    "iso:country": "US",
    "sg:address": "22 Milton St",
    "sg:city": "Seville",
    "sg:classifiers": [
      {
        "category": "Manufacturing",
        "subcategory": "Tools \u0026 Machinery",
        "type": "Manufacturing \u0026 Wholesale Goods"
      }
    ],
    "sg:phone": "+1 330 769 2071",
    "sg:postcode": "44273",
    "sg:province": "OH",
    "sg:tags": [
      "bearing",
      "ball",
      "roller"
    ],
    "wof:name": "Seville Centrifugal Bronze Inc",
    "wof:placetype": "venue"
  },
  "geometry": {"coordinates":[-81.861152,41.007903],"type":"Point"}
}
