{
  "type": "Feature",
  "properties": {
    "iso:country":"US",
    "sg:address":"927 S Union St",
    "sg:city":"Bryan",
    "sg:classifiers":[
        {
            "category":"Manufacturing",
            "subcategory":"Rubber & Plastics",
            "type":"Manufacturing & Wholesale Goods"
        },
        {
            "category":"Autos & Motor Vehicles",
            "subcategory":"Auto Supplies",
            "type":"Retail Goods"
        }
    ],
    "sg:phone":"+1 419 633 4221",
    "sg:postcode":"43506",
    "sg:province":"OH",
    "sg:tags":[
        "tube",
        "inner",
        "tire"
    ],
    "sg:website":"www.conti-online.com",
    "wof:name":"Continental Tire North America",
    "wof:placetype":"venue"
},
  "geometry": {"coordinates":[-84.536208,41.464461],"type":"Point"}
}