{
  "type": "Feature",
  "properties": {
    "addr:full": "927 S Union St Bryan OH 43506",
    "addr:housenumber": "927",
    "addr:postcode": "43506",
    "addr:street": "S Union St",
    "iso:country": "US",
    "sg:address": "927 S Union St",
    "sg:city": "Bryan",
    "sg:classifiers": [
      {
        "category": "Manufacturing",
        "subcategory": "Rubber \u0026 Plastics",
        "type": "Manufacturing \u0026 Wholesale Goods"
      },
      {
        "category": "Autos \u0026 Motor Vehicles",
        "subcategory": "Auto Supplies",
        "type": "Retail Goods"
      }
    ],
    "sg:phone": "+1 419 633 4221",
    "sg:postcode": "43506",
    "sg:province": "OH",
    "sg:tags": [
      "tube",
      "inner",
      "tire"
    ],
    "sg:website": "www.conti-online.com",
    "wof:name": "Continental Tire North America",
    "wof:placetype": "venue"
  },
  "geometry": {"coordinates":[-84.536208,41.464461],"type":"Point"}
}
