{
  "type": "Feature",
  "properties": {
    "addr:full":"7524 East Pike Norwich OH 43767",
    "addr:housenumber":"7524",
    "addr:postcode":"43767",
    "addr:street":"East Pike",
    "iso:country":"US",
    "sg:address":"7524 East Pike",
    "sg:city":"Norwich",
    "sg:classifiers":[
        {
            "category":"Wholesale",
            "subcategory":"Non-durable Goods",
            "type":"Manufacturing & Wholesale Goods"
        }
    ],
    "sg:phone":"+1 740 844 0300",
    "sg:postcode":"43767",
    "sg:province":"OH",
    "wof:name":"Mid South Distributors",
    "wof:placetype":"venue"
},
  "geometry": {"coordinates":[-81.847587,39.973402],"type":"Point"}
}