{
  "type": "Feature",
  "properties": {
    "addr:full": "11404 US Hwy 250 Milan OH 44846",
    "addr:housenumber": "11404",
    "addr:postcode": "44846",
    "addr:street": "Us Hwy 250",
    "iso:country": "US",
    "sg:address": "11404 US Hwy 250",
    "sg:city": "Milan",
    "sg:classifiers": [
      {
        "category": "Travel",
        "subcategory": "Campground",
        "type": "Entertainment"
      }
    ],
    "sg:phone": "+1 419 499 4627",
    "sg:postcode": "44846",
    "sg:province": "OH",
    "sg:tags": [
      "trailer"
    ],
    "wof:name": "Milan Trav-L-Park",
    "wof:placetype": "venue"
  },
  "geometry": {"coordinates":[-82.609062,41.314302],"type":"Point"}
}
