{
  "type": "Feature",
  "properties": {
    "addr:full": "406 Croghan St Fremont OH 43420",
    "addr:housenumber": "406",
    "addr:postcode": "43420",
    "addr:street": "Croghan St",
    "iso:country": "US",
    "sg:address": "406 Croghan St",
    "sg:city": "Fremont",
    "sg:classifiers": [
      {
        "category": "Professional",
        "subcategory": "Accounting \u0026 Tax Preparation",
        "type": "Services"
      }
    ],
    "sg:phone": "+1 419 334 7988",
    "sg:postcode": "43420",
    "sg:province": "OH",
    "sg:tags": [
      "return",
      "filing"
    ],
    "wof:name": "Keys Tax Svc",
    "wof:placetype": "venue"
  },
  "geometry": {"coordinates":[-83.114753,41.346575],"type":"Point"}
}
