{
  "type": "Feature",
  "properties": {
    "iso:country":"US",
    "sg:address":"406 Croghan St",
    "sg:city":"Fremont",
    "sg:classifiers":[
        {
            "category":"Professional",
            "subcategory":"Accounting & Tax Preparation",
            "type":"Services"
        }
    ],
    "sg:phone":"+1 419 334 7988",
    "sg:postcode":"43420",
    "sg:province":"OH",
    "sg:tags":[
        "return",
        "filing"
    ],
    "wof:name":"Keys Tax Svc",
    "wof:placetype":"venue"
},
  "geometry": {"coordinates":[-83.11475299999999,41.346575],"type":"Point"}
}