{
  "type": "Feature",
  "properties": {
    "addr:full":"1120 Bernath Pkwy Toledo OH 43615",
    "addr:housenumber":"1120",
    "addr:postcode":"43615",
    "addr:street":"Bernath Pkwy",
    "iso:country":"US",
    "sg:address":"1120 Bernath Pkwy",
    "sg:city":"Toledo",
    "sg:classifiers":[
        {
            "category":"Retail",
            "subcategory":"Animal Services",
            "type":"Services"
        }
    ],
    "sg:phone":"+1 419 868 1881",
    "sg:postcode":"43615",
    "sg:province":"OH",
    "wof:name":"S Lahnum",
    "wof:placetype":"venue"
},
  "geometry": {"coordinates":[-83.676129,41.620719],"type":"Point"}
}