{
  "type": "Feature",
  "properties": {
    "addr:full": "2440 Kingston Pike Circleville OH 43113",
    "addr:housenumber": "2440",
    "addr:postcode": "43113",
    "addr:street": "Kingston Pike",
    "iso:country": "US",
    "sg:address": "2440 Kingston Pike",
    "sg:city": "Circleville",
    "sg:classifiers": [
      {
        "category": "Farming",
        "subcategory": "Farm",
        "type": "Manufacturing \u0026 Wholesale Goods"
      }
    ],
    "sg:phone": "+1 740 474 2014",
    "sg:postcode": "43113",
    "sg:province": "OH",
    "sg:tags": [
      "crop",
      "general"
    ],
    "wof:name": "Denny R Hart",
    "wof:placetype": "venue"
  },
  "geometry": {"coordinates":[-82.930731,39.562334],"type":"Point"}
}
