{
  "type": "Feature",
  "properties": {
    "iso:country":"US",
    "sg:address":"109 Village Green Dr",
    "sg:city":"Sidney",
    "sg:classifiers":[
        {
            "category":"Banks & Credit Unions",
            "subcategory":"Investment Brokerage",
            "type":"Services"
        }
    ],
    "sg:phone":"+1 937 498 1874",
    "sg:postcode":"45365",
    "sg:province":"OH",
    "sg:tags":[
        "advisory",
        "financial"
    ],
    "wof:name":"Thompson Financial Svc",
    "wof:placetype":"venue"
},
  "geometry": {"coordinates":[-84.15817,40.309812],"type":"Point"}
}