{
  "type": "Feature",
  "properties": {
    "addr:full": "109 Village Green Dr Sidney OH 45365",
    "addr:housenumber": "109",
    "addr:postcode": "45365",
    "addr:street": "Village Green Dr",
    "iso:country": "US",
    "sg:address": "109 Village Green Dr",
    "sg:city": "Sidney",
    "sg:classifiers": [
      {
        "category": "Banks \u0026 Credit Unions",
        "subcategory": "Investment Brokerage",
        "type": "Services"
      }
    ],
    "sg:phone": "+1 937 498 1874",
    "sg:postcode": "45365",
    "sg:province": "OH",
    "sg:tags": [
      "advisory",
      "financial"
    ],
    "wof:name": "Thompson Financial Svc",
    "wof:placetype": "venue"
  },
  "geometry": {"coordinates":[-84.15817,40.309812],"type":"Point"}
}
