{
  "type": "Feature",
  "properties": {
    "iso:country":"US",
    "sg:address":"2506 Mahoning Ave NW",
    "sg:city":"Warren",
    "sg:classifiers":[
        {
            "category":"Autos & Motor Vehicles",
            "subcategory":"Automobile Sales",
            "type":"Retail Goods"
        }
    ],
    "sg:phone":"+1 330 393 0004",
    "sg:postcode":"44483",
    "sg:province":"OH",
    "sg:tags":[
        "car",
        "dealer"
    ],
    "wof:name":"Falling Rock Motors Exp Inc",
    "wof:placetype":"venue"
},
  "geometry": {"coordinates":[-80.832825,41.258041],"type":"Point"}
}