{
  "type": "Feature",
  "properties": {
    "addr:full": "4154 Fieldsedge Dr Mason OH 45040",
    "addr:postcode": "4154;45040",
    "addr:street": "Fieldsedge Dr",
    "iso:country": "US",
    "sg:address": "4154 Fieldsedge Dr",
    "sg:city": "Mason",
    "sg:classifiers": [
      {
        "category": "Professional",
        "subcategory": "Computer Services",
        "type": "Services"
      }
    ],
    "sg:phone": "+1 513 229 3603",
    "sg:postcode": "45040",
    "sg:province": "OH",
    "sg:tags": [
      "development",
      "software"
    ],
    "wof:name": "Sunstruck Technologies",
    "wof:placetype": "venue"
  },
  "geometry": {"coordinates":[-84.292174,39.343131],"type":"Point"}
}
