{
  "type": "Feature",
  "properties": {
    "addr:full": "3970 N Bend Rd Cincinnati OH 45211",
    "addr:housenumber": "3970",
    "addr:postcode": "45211",
    "addr:street": "N Bend Rd",
    "iso:country": "US",
    "sg:address": "3970 N Bend Rd",
    "sg:city": "Cincinnati",
    "sg:classifiers": [
      {
        "category": "Food \u0026 Beverages",
        "subcategory": "Groceries \u0026 Convenience Stores",
        "type": "Retail Goods"
      }
    ],
    "sg:phone": "+1 513 662 0660",
    "sg:postcode": "45211",
    "sg:province": "OH",
    "sg:tags": [
      "independent"
    ],
    "wof:name": "IGA",
    "wof:placetype": "venue"
  },
  "geometry": {"coordinates":[-84.606113,39.162589],"type":"Point"}
}
