{
  "type": "Feature",
  "properties": {
    "addr:full":"2098 Sypher Rd Akron OH 44306",
    "addr:housenumber":"2098",
    "addr:postcode":"44306",
    "addr:street":"Sypher Rd",
    "iso:country":"US",
    "sg:address":"2098 Sypher Rd",
    "sg:city":"Akron",
    "sg:classifiers":[
        {
            "category":"Manufacturing",
            "subcategory":"Tools & Machinery",
            "type":"Manufacturing & Wholesale Goods"
        }
    ],
    "sg:phone":"+1 330 785 3057",
    "sg:postcode":"44306",
    "sg:province":"OH",
    "sg:tags":[
        "machine",
        "shop"
    ],
    "wof:name":"D & R Manufacturing & Svc",
    "wof:placetype":"venue"
},
  "geometry": {"coordinates":[-81.48969200000001,41.014738],"type":"Point"}
}