{
  "type": "Feature",
  "properties": {
    "addr:full": "3518 Glenmore Ave Cincinnati OH 45211",
    "addr:housenumber": "3518",
    "addr:postcode": "45211",
    "addr:street": "Glenmore Ave",
    "iso:country": "US",
    "sg:address": "3518 Glenmore Ave",
    "sg:city": "Cincinnati",
    "sg:classifiers": [
      {
        "category": "Insurance",
        "subcategory": "Insurance Agent",
        "type": "Services"
      }
    ],
    "sg:phone": "+1 513 662 4300",
    "sg:postcode": "45211",
    "sg:province": "OH",
    "wof:name": "Steven Ulmer Insurance",
    "wof:placetype": "venue"
  },
  "geometry": {"coordinates":[-84.612441,39.151998],"type":"Point"}
}
