{
  "type": "Feature",
  "properties": {
    "addr:full": "1275 Olentangy River Rd Columbus OH 43212",
    "addr:housenumber": "1275",
    "addr:postcode": "43212",
    "addr:street": "Olentangy River Rd",
    "iso:country": "US",
    "sg:address": "1275 Olentangy River Rd",
    "sg:city": "Columbus",
    "sg:classifiers": [
      {
        "category": "Health Services",
        "subcategory": "Health Practitioner",
        "type": "Services"
      }
    ],
    "sg:phone": "+1 614 297 7704",
    "sg:postcode": "43212",
    "sg:province": "OH",
    "sg:tags": [
      "psychologist"
    ],
    "wof:name": "Sleep \u0026 Breathing Institute",
    "wof:placetype": "venue"
  },
  "geometry": {"coordinates":[-83.023455,39.985658],"type":"Point"}
}
