{
  "type": "Feature",
  "properties": {
    "addr:full": "161 E Firestone Blvd Akron OH 44301",
    "addr:housenumber": "161",
    "addr:postcode": "44301",
    "addr:street": "E Firestone Blvd",
    "iso:country": "US",
    "sg:address": "161 E Firestone Blvd",
    "sg:city": "Akron",
    "sg:classifiers": [
      {
        "category": "Banks \u0026 Credit Unions",
        "subcategory": "Financial Services",
        "type": "Services"
      }
    ],
    "sg:phone": "+1 330 724 7077",
    "sg:postcode": "44301",
    "sg:province": "OH",
    "sg:tags": [
      "investor"
    ],
    "wof:name": "Degeorge Investments",
    "wof:placetype": "venue"
  },
  "geometry": {"coordinates":[-81.520308,41.042902],"type":"Point"}
}
