{
  "type": "Feature",
  "properties": {
    "addr:full":"1015 W Washington St Sandusky OH 44870",
    "addr:housenumber":"1015",
    "addr:postcode":"44870",
    "addr:street":"W Washington St",
    "iso:country":"US",
    "sg:address":"1015 W Washington St",
    "sg:city":"Sandusky",
    "sg:classifiers":[
        {
            "category":"Community Center",
            "type":"Public Place"
        }
    ],
    "sg:phone":"+1 419 626 2273",
    "sg:postcode":"44870",
    "sg:province":"OH",
    "sg:tags":[
        "medical"
    ],
    "wof:name":"After Hours Medical Center",
    "wof:placetype":"venue"
},
  "geometry": {"coordinates":[-82.71934400000001,41.452281],"type":"Point"}
}