{
  "type": "Feature",
  "properties": {
    "iso:country":"US",
    "sg:address":"7660 Beechmont Ave",
    "sg:city":"Cincinnati",
    "sg:classifiers":[
        {
            "category":"Restaurant",
            "type":"Food & Drink"
        },
        {
            "category":"Food & Beverages",
            "subcategory":"Groceries & Convenience Stores",
            "type":"Retail Goods"
        }
    ],
    "sg:phone":"+1 513 232 8484",
    "sg:postcode":"45255",
    "sg:province":"OH",
    "sg:tags":[
        "shop",
        "sandwich",
        "house",
        "vegetarian",
        "american",
        "barbecue",
        "steak"
    ],
    "wof:name":"Maloney's Pub East",
    "wof:placetype":"venue"
},
  "geometry": {"coordinates":[-84.34470399999999,39.072601],"type":"Point"}
}