{
  "type": "Feature",
  "properties": {
    "addr:full": "7660 Beechmont Ave Cincinnati OH 45255",
    "addr:postcode": "7660;45255",
    "addr:street": "Beechmont Ave",
    "iso:country": "US",
    "sg:address": "7660 Beechmont Ave",
    "sg:city": "Cincinnati",
    "sg:classifiers": [
      {
        "category": "Restaurant",
        "type": "Food \u0026 Drink"
      },
      {
        "category": "Food \u0026 Beverages",
        "subcategory": "Groceries \u0026 Convenience Stores",
        "type": "Retail Goods"
      }
    ],
    "sg:phone": "+1 513 232 8484",
    "sg:postcode": "45255",
    "sg:province": "OH",
    "sg:tags": [
      "shop",
      "sandwich",
      "house",
      "vegetarian",
      "american",
      "barbecue",
      "steak"
    ],
    "wof:name": "Maloney's Pub East",
    "wof:placetype": "venue"
  },
  "geometry": {"coordinates":[-84.344704,39.072601],"type":"Point"}
}
