{
  "type": "Feature",
  "properties": {
    "addr:full":"721 Peach Orchard Dr Dayton OH 45449",
    "addr:housenumber":"721",
    "addr:postcode":"45449",
    "addr:street":"Peach Orchard Dr",
    "iso:country":"US",
    "sg:address":"721 Peach Orchard Dr",
    "sg:city":"Dayton",
    "sg:classifiers":[
        {
            "category":"Building & Trades",
            "subcategory":"Construction",
            "type":"Services"
        }
    ],
    "sg:phone":"+1 937 847 1879",
    "sg:postcode":"45449",
    "sg:province":"OH",
    "sg:tags":[
        "house"
    ],
    "wof:name":"Marshall Home Remodeling",
    "wof:placetype":"venue"
},
  "geometry": {"coordinates":[-84.256212,39.661041],"type":"Point"}
}