{
  "type": "Feature",
  "properties": {
    "addr:full":"1435 Glendale Milford Rd Cincinnati OH 45215",
    "addr:housenumber":"1435",
    "addr:postcode":"45215",
    "addr:street":"Glendale Milford Rd",
    "iso:country":"US",
    "sg:address":"1435 Glendale Milford Rd",
    "sg:city":"Cincinnati",
    "sg:classifiers":[
        {
            "category":"Wholesale",
            "subcategory":"Painting Supplies",
            "type":"Manufacturing & Wholesale Goods"
        }
    ],
    "sg:phone":"+1 513 771 2060",
    "sg:postcode":"45215",
    "sg:province":"OH",
    "sg:tags":[
        "paint"
    ],
    "wof:name":"Perfect Paint & Wall Coverings",
    "wof:placetype":"venue"
},
  "geometry": {"coordinates":[-84.449879,39.256192],"type":"Point"}
}