{
  "type": "Feature",
  "properties": {
    "addr:full": "4268 Belden Village St NW Canton OH 44718",
    "addr:housenumber": "4268",
    "addr:postcode": "44718",
    "addr:street": "Belden Village St Nw",
    "iso:country": "US",
    "sg:address": "4268 Belden Village St NW",
    "sg:city": "Canton",
    "sg:classifiers": [
      {
        "category": "Restaurant",
        "type": "Food \u0026 Drink"
      }
    ],
    "sg:phone": "+1 330 493 8306",
    "sg:postcode": "44718",
    "sg:province": "OH",
    "wof:name": "Main Street Grill",
    "wof:placetype": "venue"
  },
  "geometry": {"coordinates":[-81.431511,40.856248],"type":"Point"}
}
