{
  "type": "Feature",
  "properties": {
    "addr:full":"3033 Far Hills Ave Dayton OH 45429",
    "addr:housenumber":"3033",
    "addr:postcode":"45429",
    "addr:street":"Far Hills Ave",
    "iso:country":"US",
    "sg:address":"3033 Far Hills Ave",
    "sg:city":"Dayton",
    "sg:classifiers":[
        {
            "category":"Organizations",
            "subcategory":"Religious Organization",
            "type":"Services"
        }
    ],
    "sg:phone":"+1 937 653 3357",
    "sg:postcode":"45429",
    "sg:province":"OH",
    "sg:tags":[
        "church"
    ],
    "wof:name":"Sisters Of Mercy",
    "wof:placetype":"venue"
},
  "geometry": {"coordinates":[-84.170501,39.704281],"type":"Point"}
}