{
  "type": "Feature",
  "properties": {
    "iso:country":"US",
    "sg:address":"1451 Roamont Dr",
    "sg:city":"Dayton",
    "sg:classifiers":[
        {
            "category":"Professional",
            "subcategory":"Management & Consulting",
            "type":"Services"
        }
    ],
    "sg:phone":"+1 937 434 4127",
    "sg:postcode":"45459",
    "sg:province":"OH",
    "sg:tags":[
        "consultant"
    ],
    "wof:name":"NBE Assoc Inc",
    "wof:placetype":"venue"
},
  "geometry": {"coordinates":[-84.194255,39.643887],"type":"Point"}
}