{
  "type": "Feature",
  "properties": {
    "addr:full": "936 Wasson Rd Union City OH 45390",
    "addr:housenumber": "936",
    "addr:postcode": "45390",
    "addr:street": "Wasson Rd",
    "iso:country": "US",
    "sg:address": "936 Wasson Rd",
    "sg:city": "Union City",
    "sg:classifiers": [
      {
        "category": "Recreation",
        "type": "Entertainment"
      }
    ],
    "sg:phone": "+1 937 968 4444",
    "sg:postcode": "45390",
    "sg:province": "OH",
    "sg:tags": [
      "range",
      "practice",
      "golf"
    ],
    "wof:name": "PAR 1",
    "wof:placetype": "venue"
  },
  "geometry": {"coordinates":[-84.772767,40.150457],"type":"Point"}
}
