{
  "type": "Feature",
  "properties": {
    "addr:full": "8108 Blue Ash Rd Cincinnati OH 45236",
    "addr:housenumber": "8108",
    "addr:postcode": "45236",
    "addr:street": "Blue Ash Rd",
    "iso:country": "US",
    "sg:address": "8108 Blue Ash Rd",
    "sg:city": "Cincinnati",
    "sg:classifiers": [
      {
        "category": "Building \u0026 Trades",
        "subcategory": "Plumbing",
        "type": "Services"
      }
    ],
    "sg:phone": "+1 513 793 8334",
    "sg:postcode": "45236",
    "sg:province": "OH",
    "sg:tags": [
      "plumbing",
      "remodeling",
      "renovation",
      "pool"
    ],
    "wof:name": "Dial One Plumbing Inc",
    "wof:placetype": "venue"
  },
  "geometry": {"coordinates":[-84.391484,39.206849],"type":"Point"}
}
