{
  "type": "Feature",
  "properties": {
    "addr:full": "6717 Saint Clair Ave Cleveland OH 44103",
    "addr:housenumber": "6717",
    "addr:postcode": "44103",
    "addr:street": "Saint Clair Ave",
    "iso:country": "US",
    "sg:address": "6717 Saint Clair Ave",
    "sg:city": "Cleveland",
    "sg:classifiers": [
      {
        "category": "Manufacturing",
        "subcategory": "Tools \u0026 Machinery",
        "type": "Manufacturing \u0026 Wholesale Goods"
      }
    ],
    "sg:phone": "+1 216 881 3143",
    "sg:postcode": "44103",
    "sg:province": "OH",
    "sg:tags": [
      "electric",
      "motor"
    ],
    "wof:name": "Electric Control \u0026 Motor Rpr",
    "wof:placetype": "venue"
  },
  "geometry": {"coordinates":[-81.64247,41.5266],"type":"Point"}
}
