{
  "type": "Feature",
  "properties": {
    "addr:full":"9011 Innovation Pl Hamilton OH 45011",
    "addr:postcode":"9011;45011",
    "addr:street":"Innovation Pl",
    "iso:country":"US",
    "sg:address":"9011 Innovation Pl",
    "sg:city":"Hamilton",
    "sg:classifiers":[
        {
            "category":"Building & Trades",
            "subcategory":"Cleaning & Sanitation",
            "type":"Services"
        }
    ],
    "sg:phone":"+1 513 874 1832",
    "sg:postcode":"45011",
    "sg:province":"OH",
    "sg:tags":[
        "janitorial"
    ],
    "wof:name":"Premium Floor Care",
    "wof:placetype":"venue"
},
  "geometry": {"coordinates":[-84.46911299999999,39.331285],"type":"Point"}
}