{
  "type": "Feature",
  "properties": {
    "iso:country":"US",
    "sg:address":"2475 E 22nd St",
    "sg:city":"Cleveland",
    "sg:classifiers":[
        {
            "category":"Museum",
            "type":"Entertainment"
        }
    ],
    "sg:phone":"+1 216 589 9444",
    "sg:postcode":"44115",
    "sg:province":"OH",
    "sg:tags":[
        "organization",
        "arts",
        "information"
    ],
    "sg:website":"www.ingenuitycleveland.com",
    "wof:name":"Ingenuity",
    "wof:placetype":"venue"
},
  "geometry": {"coordinates":[-81.675043,41.493871],"type":"Point"}
}