{
  "type": "Feature",
  "properties": {
    "iso:country":"US",
    "sg:address":"1300 Grandview Ave",
    "sg:city":"Columbus",
    "sg:classifiers":[
        {
            "category":"Shopping",
            "subcategory":"Optical Goods",
            "type":"Retail Goods"
        }
    ],
    "sg:phone":"+1 614 481 9099",
    "sg:postcode":"43212",
    "sg:province":"OH",
    "wof:name":"Eye One Unique Eyewear",
    "wof:placetype":"venue"
},
  "geometry": {"coordinates":[-83.044771,39.983881],"type":"Point"}
}