{
  "type": "Feature",
  "properties": {
    "addr:full":"1135 Leesburg Ave Washington Ct Hs OH 43160",
    "addr:housenumber":"1135",
    "addr:postcode":"43160",
    "addr:street":"Leesburg Ave Washington Ct",
    "iso:country":"US",
    "sg:address":"1135 Leesburg Ave",
    "sg:city":"Washington Ct Hs",
    "sg:classifiers":[
        {
            "category":"Organizations",
            "subcategory":"Religious Organization",
            "type":"Services"
        }
    ],
    "sg:phone":"+1 740 335 6308",
    "sg:postcode":"43160",
    "sg:province":"OH",
    "sg:tags":[
        "church"
    ],
    "wof:name":"Church Of God",
    "wof:placetype":"venue"
},
  "geometry": {"coordinates":[-83.453402,39.527576],"type":"Point"}
}