{
  "type": "Feature",
  "properties": {
    "addr:full":"2529 N Star Rd Columbus OH 43221",
    "addr:housenumber":"2529",
    "addr:postcode":"43221",
    "addr:street":"N Star Rd",
    "iso:country":"US",
    "sg:address":"2529 N Star Rd",
    "sg:city":"Columbus",
    "sg:classifiers":[
        {
            "category":"Shopping",
            "subcategory":"Gifts & Souvenirs",
            "type":"Retail Goods"
        }
    ],
    "sg:phone":"+1 614 486 6120",
    "sg:postcode":"43221",
    "sg:province":"OH",
    "sg:tags":[
        "shop"
    ],
    "wof:name":"Horse'n Around Badlands",
    "wof:placetype":"venue"
},
  "geometry": {"coordinates":[-83.04787,40.009771],"type":"Point"}
}