{
  "type": "Feature",
  "properties": {
    "iso:country":"US",
    "sg:address":"4600 Fulton Dr NW",
    "sg:city":"Canton",
    "sg:classifiers":[
        {
            "category":"Social Services",
            "subcategory":"Child Care",
            "type":"Services"
        }
    ],
    "sg:phone":"+1 330 837 8285",
    "sg:postcode":"44718",
    "sg:province":"OH",
    "wof:name":"Sitter Service Cooperative Inc",
    "wof:placetype":"venue"
},
  "geometry": {"coordinates":[-81.442775,40.848208],"type":"Point"}
}