{
  "type": "Feature",
  "properties": {
    "iso:country":"US",
    "sg:address":"1295 Parsons Ct",
    "sg:city":"Cleveland",
    "sg:classifiers":[
        {
            "category":"Manufacturing",
            "subcategory":"Printing",
            "type":"Manufacturing & Wholesale Goods"
        }
    ],
    "sg:phone":"+1 440 333 5421",
    "sg:postcode":"44116",
    "sg:province":"OH",
    "sg:tags":[
        "printer"
    ],
    "sg:website":"www.scratchoffworks.com",
    "wof:name":"Lake Point Printing",
    "wof:placetype":"venue"
},
  "geometry": {"coordinates":[-81.837492,41.481615],"type":"Point"}
}