{
  "type": "Feature",
  "properties": {
    "addr:full": "1295 Parsons Ct Cleveland OH 44116",
    "addr:housenumber": "1295",
    "addr:postcode": "44116",
    "addr:street": "Parsons Ct",
    "iso:country": "US",
    "sg:address": "1295 Parsons Ct",
    "sg:city": "Cleveland",
    "sg:classifiers": [
      {
        "category": "Manufacturing",
        "subcategory": "Printing",
        "type": "Manufacturing \u0026 Wholesale Goods"
      }
    ],
    "sg:phone": "+1 440 333 5421",
    "sg:postcode": "44116",
    "sg:province": "OH",
    "sg:tags": [
      "printer"
    ],
    "sg:website": "www.scratchoffworks.com",
    "wof:name": "Lake Point Printing",
    "wof:placetype": "venue"
  },
  "geometry": {"coordinates":[-81.837492,41.481615],"type":"Point"}
}
