{
  "type": "Feature",
  "properties": {
    "iso:country":"US",
    "sg:address":"5225 W 140th St",
    "sg:city":"Cleveland",
    "sg:classifiers":[
        {
            "category":"Home & Garden",
            "subcategory":"Home Furnishings",
            "type":"Retail Goods"
        }
    ],
    "sg:phone":"+1 216 898 7777",
    "sg:postcode":"44142",
    "sg:province":"OH",
    "sg:tags":[
        "equipment",
        "lamp",
        "ultra",
        "specialty"
    ],
    "sg:website":"www.uriworld.com",
    "wof:name":"Ultraviolet Resources Intl",
    "wof:placetype":"venue"
},
  "geometry": {"coordinates":[-81.79198,41.417616],"type":"Point"}
}