{
  "type": "Feature",
  "properties": {
    "addr:full":"2433 Crew Cir Dayton OH 45439",
    "addr:housenumber":"2433",
    "addr:postcode":"45439",
    "addr:street":"Crew Cir",
    "iso:country":"US",
    "sg:address":"2433 Crew Cir",
    "sg:city":"Dayton",
    "sg:classifiers":[
        {
            "category":"Shopping",
            "type":"Retail Goods"
        }
    ],
    "sg:phone":"+1 937 718 2353",
    "sg:postcode":"45439",
    "sg:province":"OH",
    "sg:tags":[
        "candle"
    ],
    "wof:name":"Partylite Gifts Sr Unit Leader",
    "wof:placetype":"venue"
},
  "geometry": {"coordinates":[-84.212062,39.673392],"type":"Point"}
}