{
  "type": "Feature",
  "properties": {
    "iso:country":"US",
    "sg:address":"2160 W Case Rd",
    "sg:city":"Columbus",
    "sg:classifiers":[
        {
            "category":"Autos & Motor Vehicles",
            "subcategory":"Automobile Sales",
            "type":"Retail Goods"
        }
    ],
    "sg:phone":"+1 614 442 1820",
    "sg:postcode":"43235",
    "sg:province":"OH",
    "sg:tags":[
        "aircraft"
    ],
    "wof:name":"Aviation Jamm",
    "wof:placetype":"venue"
},
  "geometry": {"coordinates":[-83.071524,40.072903],"type":"Point"}
}