{
  "type": "Feature",
  "properties": {
    "addr:full": "2160 W Case Rd Columbus OH 43235",
    "addr:housenumber": "2160",
    "addr:postcode": "43235",
    "addr:street": "W Case Rd",
    "iso:country": "US",
    "sg:address": "2160 W Case Rd",
    "sg:city": "Columbus",
    "sg:classifiers": [
      {
        "category": "Autos \u0026 Motor Vehicles",
        "subcategory": "Automobile Sales",
        "type": "Retail Goods"
      }
    ],
    "sg:phone": "+1 614 442 1820",
    "sg:postcode": "43235",
    "sg:province": "OH",
    "sg:tags": [
      "aircraft"
    ],
    "wof:name": "Aviation Jamm",
    "wof:placetype": "venue"
  },
  "geometry": {"coordinates":[-83.071524,40.072903],"type":"Point"}
}
