{
  "type": "Feature",
  "properties": {
    "iso:country":"US",
    "sg:address":"11030 Marcy Rd NW",
    "sg:city":"Canal Winchester",
    "sg:classifiers":[
        {
            "category":"Freight",
            "type":"Transportation"
        }
    ],
    "sg:phone":"+1 614 834 0479",
    "sg:postcode":"43110",
    "sg:province":"OH",
    "sg:tags":[
        "operator",
        "local",
        "trucking"
    ],
    "wof:name":"Rascal Trucking",
    "wof:placetype":"venue"
},
  "geometry": {"coordinates":[-82.81489999999999,39.750822],"type":"Point"}
}