{
  "type": "Feature",
  "properties": {
    "addr:full": "11030 Marcy Rd NW Canal Winchester OH 43110",
    "addr:housenumber": "11030",
    "addr:postcode": "43110",
    "addr:street": "Marcy Rd Nw",
    "iso:country": "US",
    "sg:address": "11030 Marcy Rd NW",
    "sg:city": "Canal Winchester",
    "sg:classifiers": [
      {
        "category": "Freight",
        "type": "Transportation"
      }
    ],
    "sg:phone": "+1 614 834 0479",
    "sg:postcode": "43110",
    "sg:province": "OH",
    "sg:tags": [
      "operator",
      "local",
      "trucking"
    ],
    "wof:name": "Rascal Trucking",
    "wof:placetype": "venue"
  },
  "geometry": {"coordinates":[-82.8149,39.750822],"type":"Point"}
}
