{
  "type": "Feature",
  "properties": {
    "addr:full": "7655 Production Dr Cincinnati OH 45237",
    "addr:housenumber": "7655",
    "addr:postcode": "45237",
    "addr:street": "Production Dr",
    "iso:country": "US",
    "sg:address": "7655 Production Dr",
    "sg:city": "Cincinnati",
    "sg:classifiers": [
      {
        "category": "Home \u0026 Garden",
        "subcategory": "Home Furnishings",
        "type": "Retail Goods"
      }
    ],
    "sg:phone": "+1 513 761 7400",
    "sg:postcode": "45237",
    "sg:province": "OH",
    "sg:tags": [
      "linen"
    ],
    "wof:name": "Alsco Inc Progress Linen Div",
    "wof:placetype": "venue"
  },
  "geometry": {"coordinates":[-84.455041,39.199089],"type":"Point"}
}
