{
  "type": "Feature",
  "properties": {
    "iso:country":"US",
    "sg:address":"7655 Production Dr",
    "sg:city":"Cincinnati",
    "sg:classifiers":[
        {
            "category":"Home & Garden",
            "subcategory":"Home Furnishings",
            "type":"Retail Goods"
        }
    ],
    "sg:phone":"+1 513 761 7400",
    "sg:postcode":"45237",
    "sg:province":"OH",
    "sg:tags":[
        "linen"
    ],
    "wof:name":"Alsco Inc Progress Linen Div",
    "wof:placetype":"venue"
},
  "geometry": {"coordinates":[-84.45504099999999,39.199089],"type":"Point"}
}