{
  "type": "Feature",
  "properties": {
    "addr:full": "41 N Perry St Dayton OH 45402",
    "addr:housenumber": "41",
    "addr:postcode": "45402",
    "addr:street": "N Perry St",
    "iso:country": "US",
    "sg:address": "41 N Perry St",
    "sg:city": "Dayton",
    "sg:classifiers": [
      {
        "category": "Government",
        "subcategory": "Office",
        "type": "Public Place"
      }
    ],
    "sg:phone": "+1 937 225 4055",
    "sg:postcode": "45402",
    "sg:province": "OH",
    "wof:name": "Honorable Dennis J Langer",
    "wof:placetype": "venue"
  },
  "geometry": {"coordinates":[-84.19643,39.758827],"type":"Point"}
}
