{
  "type": "Feature",
  "properties": {
    "addr:full": "1340 Clay St Cincinnati OH 45202",
    "addr:housenumber": "1340",
    "addr:postcode": "45202",
    "addr:street": "Clay St",
    "iso:country": "US",
    "sg:address": "1340 Clay St",
    "sg:city": "Cincinnati",
    "sg:classifiers": [
      {
        "category": "Communications",
        "type": "Services"
      }
    ],
    "sg:phone": "+1 513 723 1410",
    "sg:postcode": "45202",
    "sg:province": "OH",
    "wof:name": "Frazier Communications",
    "wof:placetype": "venue"
  },
  "geometry": {"coordinates":[-84.512881,39.110936],"type":"Point"}
}
