{
  "type": "Feature",
  "properties": {
    "addr:full": "200 Pritz Ave Dayton OH 45403",
    "addr:housenumber": "200",
    "addr:postcode": "45403",
    "addr:street": "Pritz Ave",
    "iso:country": "US",
    "sg:address": "200 Pritz Ave",
    "sg:city": "Dayton",
    "sg:classifiers": [
      {
        "category": "Bars \u0026 Pubs",
        "type": "Food \u0026 Drink"
      }
    ],
    "sg:phone": "+1 937 781 0199",
    "sg:postcode": "45403",
    "sg:province": "OH",
    "sg:tags": [
      "drinking"
    ],
    "wof:name": "Dakota's Tavern",
    "wof:placetype": "venue"
  },
  "geometry": {"coordinates":[-84.156624,39.755172],"type":"Point"}
}
