{
  "type": "Feature",
  "properties": {
    "iso:country":"US",
    "sg:address":"200 Pritz Ave",
    "sg:city":"Dayton",
    "sg:classifiers":[
        {
            "category":"Bars & Pubs",
            "type":"Food & Drink"
        }
    ],
    "sg:phone":"+1 937 781 0199",
    "sg:postcode":"45403",
    "sg:province":"OH",
    "sg:tags":[
        "drinking"
    ],
    "wof:name":"Dakota's Tavern",
    "wof:placetype":"venue"
},
  "geometry": {"coordinates":[-84.15662399999999,39.755172],"type":"Point"}
}