{
  "type": "Feature",
  "properties": {
    "addr:full":"6482 W Calla Rd Canfield OH 44406",
    "addr:housenumber":"6482",
    "addr:postcode":"44406",
    "addr:street":"W Calla Rd",
    "iso:country":"US",
    "sg:address":"6482 W Calla Rd",
    "sg:city":"Canfield",
    "sg:classifiers":[
        {
            "category":"Organizations",
            "subcategory":"Religious Organization",
            "type":"Services"
        }
    ],
    "sg:phone":"+1 330 533 6007",
    "sg:postcode":"44406",
    "sg:province":"OH",
    "sg:tags":[
        "church"
    ],
    "wof:name":"Calla Evangelical Community",
    "wof:placetype":"venue"
},
  "geometry": {"coordinates":[-80.792919,40.972865],"type":"Point"}
}