{
  "type": "Feature",
  "properties": {
    "addr:full": "3307 W 3rd St Dayton OH 45417",
    "addr:housenumber": "3307",
    "addr:postcode": "45417",
    "addr:street": "W 3Rd St",
    "iso:country": "US",
    "sg:address": "3307 W 3rd St",
    "sg:city": "Dayton",
    "sg:classifiers": [
      {
        "category": "Personal",
        "subcategory": "Barber",
        "type": "Services"
      }
    ],
    "sg:phone": "+1 937 262 9446",
    "sg:postcode": "45417",
    "sg:province": "OH",
    "wof:name": "Clack's Versatile Hair Care",
    "wof:placetype": "venue"
  },
  "geometry": {"coordinates":[-84.244224,39.750953],"type":"Point"}
}
