{
  "type": "Feature",
  "properties": {
    "iso:country":"US",
    "sg:address":"88 E State St",
    "sg:city":"Athens",
    "sg:classifiers":[
        {
            "category":"Banks & Credit Unions",
            "subcategory":"Bank",
            "type":"Services"
        }
    ],
    "sg:phone":"+1 740 594 8333",
    "sg:postcode":"45701",
    "sg:province":"OH",
    "sg:tags":[
        "depository",
        "banking"
    ],
    "wof:name":"Prokos Check Cashing",
    "wof:placetype":"venue"
},
  "geometry": {"coordinates":[-82.097989,39.332388],"type":"Point"}
}