{
  "type": "Feature",
  "properties": {
    "addr:full":"1426 Sunflower Dr Columbus OH 43204",
    "addr:housenumber":"1426",
    "addr:postcode":"43204",
    "addr:street":"Sunflower Dr",
    "iso:country":"US",
    "sg:address":"1426 Sunflower Dr",
    "sg:city":"Columbus",
    "sg:classifiers":[
        {
            "category":"Real Estate",
            "subcategory":"Real Estate Operator",
            "type":"Services"
        }
    ],
    "sg:phone":"+1 614 275 4747",
    "sg:postcode":"43204",
    "sg:province":"OH",
    "sg:tags":[
        "building",
        "nonresidential"
    ],
    "wof:name":"Jap Properties",
    "wof:placetype":"venue"
},
  "geometry": {"coordinates":[-83.076097,39.925682],"type":"Point"}
}