{
  "type": "Feature",
  "properties": {
    "addr:full": "4223 E Royalton Rd Cleveland OH 44147",
    "addr:housenumber": "4223",
    "addr:postcode": "44147",
    "addr:street": "E Royalton Rd",
    "iso:country": "US",
    "sg:address": "4223 E Royalton Rd",
    "sg:city": "Cleveland",
    "sg:classifiers": [
      {
        "category": "Social Services",
        "subcategory": "Child Care",
        "type": "Services"
      }
    ],
    "sg:phone": "+1 440 526 1622",
    "sg:postcode": "44147",
    "sg:province": "OH",
    "sg:tags": [
      "kindergarten",
      "academic",
      "school"
    ],
    "sg:website": "www.thechildrenshouse.com",
    "wof:name": "Children's House Montessori",
    "wof:placetype": "venue"
  },
  "geometry": {"coordinates":[-81.653642,41.314959],"type":"Point"}
}
