{
  "type": "Feature",
  "properties": {
    "addr:full": "408 N Elm St Ottawa OH 45875",
    "addr:housenumber": "408",
    "addr:postcode": "45875",
    "addr:street": "N Elm St",
    "iso:country": "US",
    "sg:address": "408 N Elm St",
    "sg:city": "Ottawa",
    "sg:classifiers": [
      {
        "category": "Real Estate",
        "subcategory": "Real Estate Agent",
        "type": "Services"
      }
    ],
    "sg:phone": "+1 419 523 5151",
    "sg:postcode": "45875",
    "sg:province": "OH",
    "wof:name": "Irwin Real Estate",
    "wof:placetype": "venue"
  },
  "geometry": {"coordinates":[-84.050147,41.022237],"type":"Point"}
}
