{
  "type": "Feature",
  "properties": {
    "addr:full":"1030 Heath Way Stow OH 44224",
    "addr:housenumber":"1030",
    "addr:postcode":"44224",
    "addr:street":"Heath Way",
    "iso:country":"US",
    "sg:address":"1030 Heath Way",
    "sg:city":"Stow",
    "sg:classifiers":[
        {
            "category":"Professional",
            "type":"Services"
        }
    ],
    "sg:phone":"+1 330 945 5599",
    "sg:postcode":"44224",
    "sg:province":"OH",
    "wof:name":"Alfred B & Bebe Lavin",
    "wof:placetype":"venue"
},
  "geometry": {"coordinates":[-81.46952,41.176887],"type":"Point"}
}