{
  "type": "Feature",
  "properties": {
    "addr:full": "3461 Warrensville Center Rd Beachwood OH 44122",
    "addr:housenumber": "3461",
    "addr:postcode": "44122",
    "addr:street": "Warrensville Center Rd",
    "iso:country": "US",
    "sg:address": "3461 Warrensville Center Rd",
    "sg:city": "Beachwood",
    "sg:classifiers": [
      {
        "category": "Health Services",
        "subcategory": "Clinic",
        "type": "Services"
      },
      {
        "category": "Health Services",
        "subcategory": "Medical Lab",
        "type": "Services"
      }
    ],
    "sg:phone": "+1 866 661 9964",
    "sg:postcode": "44122",
    "sg:province": "OH",
    "sg:tags": [
      "information",
      "aid",
      "welfare"
    ],
    "sg:website": "http://cleveland.citysearch.com/profile/external/603455532/shaker_heights_oh/std_test_express_cleveland.html?publisher=yellowpages\u0026reference_id=1\u0026placement=ypwebsitemip",
    "wof:name": "STD Test Express Cleveland",
    "wof:placetype": "venue"
  },
  "geometry": {"coordinates":[-81.536293,41.46545],"type":"Point"}
}
