{
  "type": "Feature",
  "properties": {
    "iso:country":"US",
    "sg:address":"104 Mount Vernon Ave",
    "sg:city":"Mt Vernon",
    "sg:classifiers":[
        {
            "category":"Building & Trades",
            "subcategory":"Construction",
            "type":"Services"
        }
    ],
    "sg:phone":"+1 740 397 0648",
    "sg:postcode":"43050",
    "sg:province":"OH",
    "sg:tags":[
        "general",
        "contractor"
    ],
    "wof:name":"Stull Painting",
    "wof:placetype":"venue"
},
  "geometry": {"coordinates":[-82.48200300000001,40.384589],"type":"Point"}
}