{
  "type": "Feature",
  "properties": {
    "addr:full": "9482 Fairmount Rd Novelty OH 44072",
    "addr:housenumber": "9482",
    "addr:postcode": "44072",
    "addr:street": "Fairmount Rd",
    "iso:country": "US",
    "sg:address": "9482 Fairmount Rd",
    "sg:city": "Novelty",
    "sg:classifiers": [
      {
        "category": "Health Services",
        "subcategory": "Doctor",
        "type": "Services"
      }
    ],
    "sg:phone": "+1 440 338 4797",
    "sg:postcode": "44072",
    "sg:province": "OH",
    "sg:tags": [
      "physician",
      "surgeon"
    ],
    "wof:name": "Turf Doctor",
    "wof:placetype": "venue"
  },
  "geometry": {"coordinates":[-81.307156,41.490737],"type":"Point"}
}
