{
  "type": "Feature",
  "properties": {
    "iso:country":"US",
    "sg:address":"9482 Fairmount Rd",
    "sg:city":"Novelty",
    "sg:classifiers":[
        {
            "category":"Health Services",
            "subcategory":"Doctor",
            "type":"Services"
        }
    ],
    "sg:phone":"+1 440 338 4797",
    "sg:postcode":"44072",
    "sg:province":"OH",
    "sg:tags":[
        "physician",
        "surgeon"
    ],
    "wof:name":"Turf Doctor",
    "wof:placetype":"venue"
},
  "geometry": {"coordinates":[-81.30715600000001,41.490737],"type":"Point"}
}