{
  "type": "Feature",
  "properties": {
    "addr:full": "94 N South St Wilmington OH 45177",
    "addr:housenumber": "94",
    "addr:postcode": "45177",
    "addr:street": "N South St",
    "iso:country": "US",
    "sg:address": "94 N South St",
    "sg:city": "Wilmington",
    "sg:classifiers": [
      {
        "category": "Organizations",
        "subcategory": "Religious Organization",
        "type": "Services"
      }
    ],
    "sg:phone": "+1 937 383 3399",
    "sg:postcode": "45177",
    "sg:province": "OH",
    "sg:tags": [
      "church"
    ],
    "wof:name": "Logos Community Church",
    "wof:placetype": "venue"
  },
  "geometry": {"coordinates":[-83.828332,39.447588],"type":"Point"}
}
