{
  "type": "Feature",
  "properties": {
    "addr:full":"2875 Medina Rd Medina OH 44256",
    "addr:housenumber":"2875",
    "addr:postcode":"44256",
    "addr:street":"Medina Rd",
    "iso:country":"US",
    "sg:address":"2875 Medina Rd",
    "sg:city":"Medina",
    "sg:classifiers":[
        {
            "category":"Travel",
            "subcategory":"Hotels & Motels",
            "type":"Entertainment"
        }
    ],
    "sg:phone":"+1 330 725 4571",
    "sg:postcode":"44256",
    "sg:province":"OH",
    "sg:website":"www.travelerschoicehotel.com",
    "wof:name":"Travelers Choice",
    "wof:placetype":"venue"
},
  "geometry": {"coordinates":[-81.790841,41.13626],"type":"Point"}
}