{
  "type": "Feature",
  "properties": {
    "addr:full": "820 E Hudson St Columbus OH 43211",
    "addr:housenumber": "820",
    "addr:postcode": "43211",
    "addr:street": "E Hudson St",
    "iso:country": "US",
    "sg:address": "820 E Hudson St",
    "sg:city": "Columbus",
    "sg:classifiers": [
      {
        "category": "Retail",
        "subcategory": "Auto Repair",
        "type": "Services"
      }
    ],
    "sg:phone": "+1 614 784 8030",
    "sg:postcode": "43211",
    "sg:province": "OH",
    "sg:tags": [
      "transmission"
    ],
    "wof:name": "Quality Transmission",
    "wof:placetype": "venue"
  },
  "geometry": {"coordinates":[-82.988264,40.014666],"type":"Point"}
}
