{
  "type": "Feature",
  "properties": {
    "iso:country":"US",
    "sg:address":"401 Wood St",
    "sg:city":"Piqua",
    "sg:classifiers":[
        {
            "category":"Home & Garden",
            "subcategory":"Furniture",
            "type":"Retail Goods"
        }
    ],
    "sg:phone":"+1 937 778 9320",
    "sg:postcode":"45356",
    "sg:province":"OH",
    "wof:name":"Parson Corner Furniture",
    "wof:placetype":"venue"
},
  "geometry": {"coordinates":[-84.244489,40.145194],"type":"Point"}
}