{
  "type": "Feature",
  "properties": {
    "iso:country":"US",
    "sg:address":"315 W Liberty St",
    "sg:city":"Medina",
    "sg:classifiers":[
        {
            "category":"Personal",
            "subcategory":"Beauty Salon",
            "type":"Services"
        }
    ],
    "sg:phone":"+1 330 722 4247",
    "sg:postcode":"44256",
    "sg:province":"OH",
    "wof:name":"Hair Designs By Judy",
    "wof:placetype":"venue"
},
  "geometry": {"coordinates":[-81.86814200000001,41.139215],"type":"Point"}
}