{
  "type": "Feature",
  "properties": {
    "addr:full":"14014 Shaker Blvd Cleveland OH 44120",
    "addr:housenumber":"14014",
    "addr:postcode":"44120",
    "addr:street":"Shaker Blvd",
    "iso:country":"US",
    "sg:address":"14014 Shaker Blvd",
    "sg:city":"Cleveland",
    "sg:classifiers":[
        {
            "category":"Wholesale",
            "subcategory":"Durable Goods & Equipment",
            "type":"Manufacturing & Wholesale Goods"
        }
    ],
    "sg:phone":"+1 216 991 1279",
    "sg:postcode":"44120",
    "sg:province":"OH",
    "wof:name":"Senior Driver",
    "wof:placetype":"venue"
},
  "geometry": {"coordinates":[-81.58418899999999,41.483323],"type":"Point"}
}