{
  "type": "Feature",
  "properties": {
    "addr:full":"206 E Center St Bellevue OH 44811",
    "addr:housenumber":"206",
    "addr:postcode":"44811",
    "addr:street":"E Center St",
    "iso:country":"US",
    "sg:address":"206 E Center St",
    "sg:city":"Bellevue",
    "sg:classifiers":[
        {
            "category":"Personal",
            "subcategory":"Barber",
            "type":"Services"
        }
    ],
    "sg:phone":"+1 419 483 4625",
    "sg:postcode":"44811",
    "sg:province":"OH",
    "wof:name":"Paul's Barber Shop",
    "wof:placetype":"venue"
},
  "geometry": {"coordinates":[-82.83862999999999,41.272286],"type":"Point"}
}