{
  "type": "Feature",
  "properties": {
    "addr:full":"7251 Engle Rd Cleveland OH 44130",
    "addr:housenumber":"7251",
    "addr:postcode":"44130",
    "addr:street":"Engle Rd",
    "iso:country":"US",
    "sg:address":"7251 Engle Rd",
    "sg:city":"Cleveland",
    "sg:classifiers":[
        {
            "category":"Professional",
            "subcategory":"Accounting & Tax Preparation",
            "type":"Services"
        }
    ],
    "sg:phone":"+1 440 243 5075",
    "sg:postcode":"44130",
    "sg:province":"OH",
    "sg:tags":[
        "return",
        "business"
    ],
    "wof:name":"H & R Block",
    "wof:placetype":"venue"
},
  "geometry": {"coordinates":[-81.825074,41.365029],"type":"Point"}
}