{
  "type": "Feature",
  "properties": {
    "iso:country":"US",
    "sg:address":"34997 Royalton Rd",
    "sg:city":"Grafton",
    "sg:classifiers":[
        {
            "category":"Retail",
            "subcategory":"Auto Repair",
            "type":"Services"
        }
    ],
    "sg:phone":"+1 440 748 6409",
    "sg:postcode":"44044",
    "sg:province":"OH",
    "sg:tags":[
        "repairing",
        "automobile"
    ],
    "wof:name":"Ed's Midview Svc",
    "wof:placetype":"venue"
},
  "geometry": {"coordinates":[-81.99089600000001,41.313718],"type":"Point"}
}