{
  "type": "Feature",
  "properties": {
    "iso:country":"US",
    "sg:address":"807 E Washington St",
    "sg:city":"Medina",
    "sg:classifiers":[
        {
            "category":"Professional",
            "subcategory":"Lawyer & Legal Services",
            "type":"Services"
        }
    ],
    "sg:phone":"+1 330 725 5297",
    "sg:postcode":"44256",
    "sg:province":"OH",
    "sg:tags":[
        "attorney"
    ],
    "wof:name":"Marie M Edmonds Co",
    "wof:placetype":"venue"
},
  "geometry": {"coordinates":[-81.85251,41.138158],"type":"Point"}
}