{
  "type": "Feature",
  "properties": {
    "addr:full":"1939 Independence Blvd Lancaster OH 43130",
    "addr:housenumber":"1939",
    "addr:postcode":"43130",
    "addr:street":"Independence Blvd",
    "iso:country":"US",
    "sg:address":"1939 Independence Blvd",
    "sg:city":"Lancaster",
    "sg:classifiers":[
        {
            "category":"Professional",
            "type":"Services"
        }
    ],
    "sg:phone":"+1 740 687 8100",
    "sg:postcode":"43130",
    "sg:province":"OH",
    "wof:name":"Jordan Heiber",
    "wof:placetype":"venue"
},
  "geometry": {"coordinates":[-82.562765,39.751932],"type":"Point"}
}