{
  "type": "Feature",
  "properties": {
    "addr:full":"7048 Worthington Galena Rd Columbus OH 43085",
    "addr:housenumber":"7048",
    "addr:postcode":"43085",
    "addr:street":"Worthington Galena Rd",
    "iso:country":"US",
    "sg:address":"7048 Worthington Galena Rd",
    "sg:city":"Columbus",
    "sg:classifiers":[
        {
            "category":"Professional",
            "type":"Services"
        },
        {
            "category":"Autos & Motor Vehicles",
            "subcategory":"Recreational Vehicle Sales",
            "type":"Retail Goods"
        }
    ],
    "sg:phone":"+1 614 781 0298",
    "sg:postcode":"43085",
    "sg:province":"OH",
    "sg:tags":[
        "establishment"
    ],
    "wof:name":"Mister Linings",
    "wof:placetype":"venue"
},
  "geometry": {"coordinates":[-82.99959,40.107772],"type":"Point"}
}