{
  "type": "Feature",
  "properties": {
    "iso:country":"US",
    "sg:address":"773 Walnut",
    "sg:city":"Marysville",
    "sg:classifiers":[
        {
            "category":"Health Services",
            "subcategory":"Clinic",
            "type":"Services"
        }
    ],
    "sg:phone":"+1 937 578 2860",
    "sg:postcode":"43040",
    "sg:province":"OH",
    "wof:name":"Family Healthcare-Marysville",
    "wof:placetype":"venue"
},
  "geometry": {"coordinates":[-83.365409,40.226994],"type":"Point"}
}