{
  "type": "Feature",
  "properties": {
    "addr:full": "773 Walnut Marysville OH 43040",
    "addr:housenumber": "773",
    "addr:postcode": "43040",
    "addr:street": "Walnut",
    "iso:country": "US",
    "sg:address": "773 Walnut",
    "sg:city": "Marysville",
    "sg:classifiers": [
      {
        "category": "Health Services",
        "subcategory": "Clinic",
        "type": "Services"
      }
    ],
    "sg:phone": "+1 937 578 2860",
    "sg:postcode": "43040",
    "sg:province": "OH",
    "wof:name": "Family Healthcare-Marysville",
    "wof:placetype": "venue"
  },
  "geometry": {"coordinates":[-83.365409,40.226994],"type":"Point"}
}
