{
  "type": "Feature",
  "properties": {
    "iso:country":"US",
    "sg:address":"3115 Luli Rd",
    "sg:city":"Mogadore",
    "sg:classifiers":[
        {
            "category":"Building & Trades",
            "subcategory":"Landscaping Services",
            "type":"Services"
        }
    ],
    "sg:phone":"+1 330 573 2442",
    "sg:postcode":"44260",
    "sg:province":"OH",
    "sg:tags":[
        "landscape",
        "contractor"
    ],
    "wof:name":"AAA Landscaping",
    "wof:placetype":"venue"
},
  "geometry": {"coordinates":[-81.27796499999999,41.040926],"type":"Point"}
}