{
  "type": "Feature",
  "properties": {
    "iso:country":"US",
    "sg:address":"1515 South Ave",
    "sg:city":"Toledo",
    "sg:classifiers":[
        {
            "category":"Shopping",
            "subcategory":"Music",
            "type":"Retail Goods"
        }
    ],
    "sg:phone":"+1 419 343 6448",
    "sg:postcode":"43609",
    "sg:province":"OH",
    "wof:name":"Glass Records",
    "wof:placetype":"venue"
},
  "geometry": {"coordinates":[-83.57906199999999,41.630648],"type":"Point"}
}