{
  "type": "Feature",
  "properties": {
    "addr:full": "14054 Madison Rd Middlefield OH 44062",
    "addr:housenumber": "14054",
    "addr:postcode": "44062",
    "addr:street": "Madison Rd",
    "iso:country": "US",
    "sg:address": "14054 Madison Rd",
    "sg:city": "Middlefield",
    "sg:classifiers": [
      {
        "category": "Wholesale",
        "subcategory": "Farm Supplies",
        "type": "Manufacturing \u0026 Wholesale Goods"
      }
    ],
    "sg:phone": "+1 440 632 0197",
    "sg:postcode": "44062",
    "sg:province": "OH",
    "sg:tags": [
      "feed"
    ],
    "wof:name": "Farmers Port Svc Inc",
    "wof:placetype": "venue"
  },
  "geometry": {"coordinates":[-81.051394,41.486081],"type":"Point"}
}
