{
  "type": "Feature",
  "properties": {
    "addr:full": "10501 New Haven Rd Harrison IN 45030",
    "addr:housenumber": "10501",
    "addr:postcode": "45030",
    "addr:street": "New Haven Rd",
    "iso:country": "US",
    "sg:address": "10501 New Haven Rd",
    "sg:city": "Harrison",
    "sg:classifiers": [
      {
        "category": "Food \u0026 Beverages",
        "subcategory": "Groceries \u0026 Convenience Stores",
        "type": "Retail Goods"
      }
    ],
    "sg:phone": "+1 513 367 2080",
    "sg:postcode": "45030",
    "sg:province": "IN",
    "sg:tags": [
      "department",
      "supermarket"
    ],
    "wof:name": "Biggs Harrison Hypermarket",
    "wof:placetype": "venue"
  },
  "geometry": {"coordinates":[-84.789516,39.261959],"type":"Point"}
}
