{
  "type": "Feature",
  "properties": {
    "iso:country":"US",
    "sg:address":"1330 Scott St",
    "sg:city":"Napoleon",
    "sg:classifiers":[
        {
            "category":"Health Services",
            "subcategory":"Hospital",
            "type":"Services"
        },
        {
            "category":"Health Services",
            "subcategory":"Clinic",
            "type":"Services"
        }
    ],
    "sg:phone":"+1 419 599 1660",
    "sg:postcode":"43545",
    "sg:province":"OH",
    "sg:tags":[
        "crisis",
        "center",
        "mental"
    ],
    "sg:website":"www.firstcallnwo.org",
    "wof:name":"First Call For Help Inc",
    "wof:placetype":"venue"
},
  "geometry": {"coordinates":[-84.131953,41.397559],"type":"Point"}
}