{
  "type": "Feature",
  "properties": {
    "addr:full": "4041 Tamarack Ave Grove City OH 43123",
    "addr:housenumber": "4041",
    "addr:postcode": "43123",
    "addr:street": "Tamarack Ave",
    "iso:country": "US",
    "sg:address": "4041 Tamarack Ave",
    "sg:city": "Grove City",
    "sg:classifiers": [
      {
        "category": "Manufacturing",
        "subcategory": "Rubber \u0026 Plastics",
        "type": "Manufacturing \u0026 Wholesale Goods"
      }
    ],
    "sg:phone": "+1 614 875 9581",
    "sg:postcode": "43123",
    "sg:province": "OH",
    "sg:tags": [
      "product",
      "mfg"
    ],
    "wof:name": "Kirk Enterprises Inc",
    "wof:placetype": "venue"
  },
  "geometry": {"coordinates":[-83.109451,39.894046],"type":"Point"}
}
