{
  "type": "Feature",
  "properties": {
    "iso:country":"US",
    "sg:address":"4041 Tamarack Ave",
    "sg:city":"Grove City",
    "sg:classifiers":[
        {
            "category":"Manufacturing",
            "subcategory":"Rubber & Plastics",
            "type":"Manufacturing & Wholesale Goods"
        }
    ],
    "sg:phone":"+1 614 875 9581",
    "sg:postcode":"43123",
    "sg:province":"OH",
    "sg:tags":[
        "product",
        "mfg"
    ],
    "wof:name":"Kirk Enterprises Inc",
    "wof:placetype":"venue"
},
  "geometry": {"coordinates":[-83.109451,39.894046],"type":"Point"}
}