{
  "type": "Feature",
  "properties": {
    "addr:full": "521 Forest Ave Cincinnati OH 45229",
    "addr:housenumber": "521",
    "addr:postcode": "45229",
    "addr:street": "Forest Ave",
    "iso:country": "US",
    "sg:address": "521 Forest Ave",
    "sg:city": "Cincinnati",
    "sg:classifiers": [
      {
        "category": "Organizations",
        "subcategory": "Religious Organization",
        "type": "Services"
      }
    ],
    "sg:phone": "+1 513 281 2059",
    "sg:postcode": "45229",
    "sg:province": "OH",
    "sg:tags": [
      "church"
    ],
    "wof:name": "Phillips Memorial CME Church",
    "wof:placetype": "venue"
  },
  "geometry": {"coordinates":[-84.495546,39.145831],"type":"Point"}
}
