{
  "type": "Feature",
  "properties": {
    "iso:country":"US",
    "sg:address":"2260 Bailey Rd",
    "sg:city":"Peebles",
    "sg:classifiers":[
        {
            "category":"Wholesale",
            "subcategory":"Plants",
            "type":"Manufacturing & Wholesale Goods"
        }
    ],
    "sg:phone":"+1 937 386 9990",
    "sg:postcode":"45660",
    "sg:province":"OH",
    "sg:tags":[
        "greenhouse"
    ],
    "wof:name":"Hillcrest Farm Greenhouse",
    "wof:placetype":"venue"
},
  "geometry": {"coordinates":[-83.503705,38.913375],"type":"Point"}
}