{
  "type": "Feature",
  "properties": {
    "addr:full":"3580 S Old 3c Hwy Galena OH 43082",
    "addr:housenumber":"3580;3c",
    "addr:postcode":"43082",
    "addr:street":"S Old;Hwy",
    "iso:country":"US",
    "sg:address":"3580 S Old 3c Hwy",
    "sg:city":"Galena",
    "sg:classifiers":[
        {
            "category":"Organizations",
            "subcategory":"Religious Organization",
            "type":"Services"
        }
    ],
    "sg:phone":"+1 740 965 2088",
    "sg:postcode":"43082",
    "sg:province":"OH",
    "sg:tags":[
        "clergy"
    ],
    "wof:name":"James K Stalder",
    "wof:placetype":"venue"
},
  "geometry": {"coordinates":[-82.89532199999999,40.203748],"type":"Point"}
}