{
  "type": "Feature",
  "properties": {
    "iso:country":"US",
    "sg:address":"140 S Main St",
    "sg:city":"Dayton",
    "sg:classifiers":[
        {
            "category":"Education",
            "subcategory":"Dance Studio",
            "type":"Public Place"
        }
    ],
    "sg:phone":"+1 937 223 1542",
    "sg:postcode":"45402",
    "sg:province":"OH",
    "sg:tags":[
        "instruction",
        "dancing"
    ],
    "wof:name":"Dayton Ballet School",
    "wof:placetype":"venue"
},
  "geometry": {"coordinates":[-84.191081,39.757492],"type":"Point"}
}