{
  "type": "Feature",
  "properties": {
    "addr:full":"3708 Rd Q Pandora OH 45877",
    "addr:housenumber":"3708",
    "addr:postcode":"45877",
    "addr:street":"Rd Q",
    "iso:country":"US",
    "sg:address":"3708 Rd Q",
    "sg:city":"Pandora",
    "sg:phone":"+1 419 384 7268",
    "sg:postcode":"45877",
    "sg:province":"OH",
    "sg:tags":[
        "farm",
        "corn",
        "soybean"
    ],
    "wof:name":"Robert Suter",
    "wof:placetype":"venue"
},
  "geometry": {"coordinates":[-83.92895799999999,40.934885],"type":"Point"}
}