{
  "type": "Feature",
  "properties": {
    "iso:country":"US",
    "sg:address":"1225 Merriman Rd",
    "sg:city":"Akron",
    "sg:classifiers":[
        {
            "category":"Real Estate",
            "subcategory":"Architect",
            "type":"Services"
        }
    ],
    "sg:phone":"+1 330 996 4676",
    "sg:postcode":"44313",
    "sg:province":"OH",
    "sg:tags":[
        "architectural"
    ],
    "wof:name":"Frank Horn Architects Inc",
    "wof:placetype":"venue"
},
  "geometry": {"coordinates":[-81.541187,41.126773],"type":"Point"}
}