{
  "type": "Feature",
  "properties": {
    "addr:full":"40373 Slife Rd Lagrange OH 44050",
    "addr:postcode":"40373;44050",
    "addr:street":"Slife Rd",
    "iso:country":"US",
    "sg:address":"40373 Slife Rd",
    "sg:city":"Lagrange",
    "sg:classifiers":[
        {
            "category":"Professional",
            "type":"Services"
        }
    ],
    "sg:phone":"+1 440 458 8952",
    "sg:postcode":"44050",
    "sg:province":"OH",
    "wof:name":"John Marozsin",
    "wof:placetype":"venue"
},
  "geometry": {"coordinates":[-82.10318100000001,41.300222],"type":"Point"}
}