{
  "type": "Feature",
  "properties": {
    "iso:country":"US",
    "sg:address":"4400 Co Rd 183",
    "sg:city":"Clyde",
    "sg:classifiers":[
        {
            "category":"Shopping",
            "type":"Retail Goods"
        }
    ],
    "sg:phone":"+1 419 271 3789",
    "sg:postcode":"43410",
    "sg:province":"OH",
    "sg:tags":[
        "merchandise"
    ],
    "wof:name":"Dagg Wood",
    "wof:placetype":"venue"
},
  "geometry": {"coordinates":[-82.96252,41.27052],"type":"Point"}
}