{
  "type": "Feature",
  "properties": {
    "addr:full": "1377 Goettemoeller Rd Maria Stein OH 45860",
    "addr:housenumber": "1377",
    "addr:postcode": "45860",
    "addr:street": "Goettemoeller Rd",
    "iso:country": "US",
    "sg:address": "1377 Goettemoeller Rd",
    "sg:city": "Maria Stein",
    "sg:classifiers": [
      {
        "category": "Farming",
        "subcategory": "Dairy Farm",
        "type": "Manufacturing \u0026 Wholesale Goods"
      }
    ],
    "sg:phone": "+1 419 925 4102",
    "sg:postcode": "45860",
    "sg:province": "OH",
    "wof:name": "Roger Evers",
    "wof:placetype": "venue"
  },
  "geometry": {"coordinates":[-84.531928,40.38266],"type":"Point"}
}
