{
  "type": "Feature",
  "properties": {
    "iso:country":"US",
    "sg:address":"1377 Goettemoeller Rd",
    "sg:city":"Maria Stein",
    "sg:classifiers":[
        {
            "category":"Farming",
            "subcategory":"Dairy Farm",
            "type":"Manufacturing & Wholesale Goods"
        }
    ],
    "sg:phone":"+1 419 925 4102",
    "sg:postcode":"45860",
    "sg:province":"OH",
    "wof:name":"Roger Evers",
    "wof:placetype":"venue"
},
  "geometry": {"coordinates":[-84.53192799999999,40.38266],"type":"Point"}
}