{
  "type": "Feature",
  "properties": {
    "addr:full": "1179 Twp Rd 93 Glenford OH 43739",
    "addr:housenumber": "1179;93",
    "addr:postcode": "43739",
    "addr:street": "Twp Rd",
    "iso:country": "US",
    "sg:address": "1179 Twp Rd 93",
    "sg:city": "Glenford",
    "sg:phone": "+1 740 743 2076",
    "sg:postcode": "43739",
    "sg:province": "OH",
    "sg:tags": [
      "farm",
      "cash",
      "crop",
      "field",
      "grain",
      "soybean"
    ],
    "wof:name": "B Carpenter Farm",
    "wof:placetype": "venue"
  },
  "geometry": {"coordinates":[-82.262634,39.862657],"type":"Point"}
}
