{
  "type": "Feature",
  "properties": {
    "addr:full": "18 E 6th St Dresden OH 43821",
    "addr:housenumber": "18",
    "addr:postcode": "43821",
    "addr:street": "E 6Th St",
    "iso:country": "US",
    "sg:address": "18 E 6th St",
    "sg:city": "Dresden",
    "sg:classifiers": [
      {
        "category": "Shopping",
        "subcategory": "Gifts \u0026 Souvenirs",
        "type": "Retail Goods"
      }
    ],
    "sg:phone": "+1 740 754 2228",
    "sg:postcode": "43821",
    "sg:province": "OH",
    "sg:tags": [
      "shop"
    ],
    "sg:website": "www.humbleheartdresden.com",
    "wof:name": "Humble Heart",
    "wof:placetype": "venue"
  },
  "geometry": {"coordinates":[-82.010961,40.123606],"type":"Point"}
}
