{
  "type": "Feature",
  "properties": {
    "addr:full": "101 E Main St Jewett OH 43986",
    "addr:housenumber": "101",
    "addr:postcode": "43986",
    "addr:street": "E Main St",
    "iso:country": "US",
    "sg:address": "101 E Main St",
    "sg:city": "Jewett",
    "sg:classifiers": [
      {
        "category": "Home \u0026 Garden",
        "subcategory": "Hardware",
        "type": "Retail Goods"
      }
    ],
    "sg:phone": "+1 740 946 5391",
    "sg:postcode": "43986",
    "sg:province": "OH",
    "wof:name": "Jewett Supply Ctr",
    "wof:placetype": "venue"
  },
  "geometry": {"coordinates":[-81.003438,40.367636],"type":"Point"}
}
