{
  "type": "Feature",
  "properties": {
    "iso:country":"US",
    "sg:address":"101 E Main St",
    "sg:city":"Jewett",
    "sg:classifiers":[
        {
            "category":"Home & Garden",
            "subcategory":"Hardware",
            "type":"Retail Goods"
        }
    ],
    "sg:phone":"+1 740 946 5391",
    "sg:postcode":"43986",
    "sg:province":"OH",
    "wof:name":"Jewett Supply Ctr",
    "wof:placetype":"venue"
},
  "geometry": {"coordinates":[-81.003438,40.367636],"type":"Point"}
}