{
  "type": "Feature",
  "properties": {
    "iso:country":"US",
    "sg:address":"12828 Church Rd",
    "sg:city":"Orrville",
    "sg:classifiers":[
        {
            "category":"Retail",
            "subcategory":"Veterinary Services",
            "type":"Services"
        }
    ],
    "sg:phone":"+1 330 684 1934",
    "sg:postcode":"44667",
    "sg:province":"OH",
    "wof:name":"Melvin D Wenger Dvm",
    "wof:placetype":"venue"
},
  "geometry": {"coordinates":[-81.752033,40.822054],"type":"Point"}
}