{
  "type": "Feature",
  "properties": {
    "iso:country":"US",
    "sg:address":"3446 E 53rd St",
    "sg:city":"Cleveland",
    "sg:classifiers":[
        {
            "category":"Restaurant",
            "type":"Food & Drink"
        }
    ],
    "sg:phone":"+1 216 351 8200",
    "sg:postcode":"44127",
    "sg:province":"OH",
    "wof:name":"Old School Pizza",
    "wof:placetype":"venue"
},
  "geometry": {"coordinates":[-81.653009,41.465307],"type":"Point"}
}