{
  "type": "Feature",
  "properties": {
    "addr:full": "435 Emory St Columbus OH 43230",
    "addr:housenumber": "435",
    "addr:postcode": "43230",
    "addr:street": "Emory St",
    "iso:country": "US",
    "sg:address": "435 Emory St",
    "sg:city": "Columbus",
    "sg:classifiers": [
      {
        "category": "Communications",
        "type": "Services"
      }
    ],
    "sg:phone": "+1 614 337 0509",
    "sg:postcode": "43230",
    "sg:province": "OH",
    "sg:tags": [
      "communication"
    ],
    "wof:name": "Professnl Cmmnctn Intrntn",
    "wof:placetype": "venue"
  },
  "geometry": {"coordinates":[-82.845601,40.006679],"type":"Point"}
}
