{
  "type": "Feature",
  "properties": {
    "addr:full":"1289 Mentor Ave Painesville OH 44077",
    "addr:housenumber":"1289",
    "addr:postcode":"44077",
    "addr:street":"Mentor Ave",
    "iso:country":"US",
    "sg:address":"1289 Mentor Ave",
    "sg:city":"Painesville",
    "sg:classifiers":[
        {
            "category":"Recreation",
            "type":"Entertainment"
        }
    ],
    "sg:phone":"+1 440 357 0600",
    "sg:postcode":"44077",
    "sg:province":"OH",
    "sg:tags":[
        "bingo",
        "game"
    ],
    "wof:name":"Jean Chase Memorial Fund",
    "wof:placetype":"venue"
},
  "geometry": {"coordinates":[-81.27046300000001,41.70491],"type":"Point"}
}