{
  "type": "Feature",
  "properties": {
    "addr:full": "50 S Broadway St Lebanon OH 45036",
    "addr:housenumber": "50",
    "addr:postcode": "45036",
    "addr:street": "S Broadway St",
    "iso:country": "US",
    "sg:address": "50 S Broadway St",
    "sg:city": "Lebanon",
    "sg:classifiers": [
      {
        "category": "Government",
        "subcategory": "Office",
        "type": "Public Place"
      }
    ],
    "sg:phone": "+1 513 932 3060",
    "sg:postcode": "45036",
    "sg:province": "OH",
    "sg:tags": [
      "village"
    ],
    "sg:website": "www.lebanonohio.ws",
    "wof:name": "Lebanon City Building",
    "wof:placetype": "venue"
  },
  "geometry": {"coordinates":[-84.20839,39.433352],"type":"Point"}
}
