{
  "type": "Feature",
  "properties": {
    "iso:country":"US",
    "sg:address":"2095 Valley Greene Dr",
    "sg:city":"Dayton",
    "sg:classifiers":[
        {
            "category":"Real Estate",
            "subcategory":"Real Estate Operator",
            "type":"Services"
        }
    ],
    "sg:phone":"+1 937 434 7242",
    "sg:postcode":"45440",
    "sg:province":"OH",
    "sg:tags":[
        "apartment"
    ],
    "wof:name":"Fox Hunt Apartments",
    "wof:placetype":"venue"
},
  "geometry": {"coordinates":[-84.130552,39.662903],"type":"Point"}
}