{
  "type": "Feature",
  "properties": {
    "addr:full": "2739 Cory Ave Akron OH 44314",
    "addr:housenumber": "2739",
    "addr:postcode": "44314",
    "addr:street": "Cory Ave",
    "iso:country": "US",
    "sg:address": "2739 Cory Ave",
    "sg:city": "Akron",
    "sg:classifiers": [
      {
        "category": "Manufacturing",
        "subcategory": "Pottery",
        "type": "Manufacturing \u0026 Wholesale Goods"
      }
    ],
    "sg:phone": "+1 330 745 2159",
    "sg:postcode": "44314",
    "sg:province": "OH",
    "sg:tags": [
      "porcelain"
    ],
    "sg:website": "www.akronporcelain.com",
    "wof:name": "Akron Porcelain \u0026 Plastics Co",
    "wof:placetype": "venue"
  },
  "geometry": {"coordinates":[-81.566645,41.028965],"type":"Point"}
}
