{
  "type": "Feature",
  "properties": {
    "iso:country":"US",
    "sg:address":"22 N 4th St",
    "sg:city":"Newark",
    "sg:classifiers":[
        {
            "category":"Health Services",
            "subcategory":"Hospital",
            "type":"Services"
        }
    ],
    "sg:phone":"+1 740 345 0020",
    "sg:postcode":"43055",
    "sg:province":"OH",
    "sg:tags":[
        "mental"
    ],
    "wof:name":"Moundbuilders Guidance Ctr",
    "wof:placetype":"venue"
},
  "geometry": {"coordinates":[-82.404894,40.058642],"type":"Point"}
}