{
  "type": "Feature",
  "properties": {
    "iso:country":"US",
    "sg:address":"3707 Kendall Ave",
    "sg:city":"Cincinnati",
    "sg:classifiers":[
        {
            "category":"Retail",
            "subcategory":"Repair Shop",
            "type":"Services"
        }
    ],
    "sg:phone":"+1 513 321 1015",
    "sg:postcode":"45208",
    "sg:province":"OH",
    "sg:tags":[
        "scooter",
        "motorcycle",
        "motor"
    ],
    "wof:name":"Isolati",
    "wof:placetype":"venue"
},
  "geometry": {"coordinates":[-84.450565,39.144349],"type":"Point"}
}