{
  "type": "Feature",
  "properties": {
    "addr:full": "16844 Co Rd 197 Mount Blanchard OH 45867",
    "addr:housenumber": "16844;197",
    "addr:postcode": "45867",
    "addr:street": "Co Rd;Mount Blanchard",
    "iso:country": "US",
    "sg:address": "16844 Co Rd 197",
    "sg:city": "Mount Blanchard",
    "sg:phone": "+1 419 387 7059",
    "sg:postcode": "45867",
    "sg:province": "OH",
    "sg:tags": [
      "farm",
      "corn",
      "wheat",
      "soybean"
    ],
    "wof:name": "Darrel Walter",
    "wof:placetype": "venue"
  },
  "geometry": {"coordinates":[-83.486186,40.920597],"type":"Point"}
}
