{
  "type": "Feature",
  "properties": {
    "addr:full": "8250 State Rte 609 Orangeville OH 44453",
    "addr:housenumber": "8250",
    "addr:postcode": "44453",
    "addr:street": "State Rte 609",
    "iso:country": "US",
    "sg:address": "8250 State Rte 609",
    "sg:city": "Orangeville",
    "sg:classifiers": [
      {
        "category": "Autos \u0026 Motor Vehicles",
        "subcategory": "Boat Sales",
        "type": "Retail Goods"
      }
    ],
    "sg:phone": "+1 330 772 7722",
    "sg:postcode": "44453",
    "sg:province": "OH",
    "sg:tags": [
      "dealer",
      "sales"
    ],
    "wof:name": "Boyd-Resele Marine Inc",
    "wof:placetype": "venue"
  },
  "geometry": {"coordinates":[-80.524106,41.337962],"type":"Point"}
}
