{
  "type": "Feature",
  "properties": {
    "iso:country":"US",
    "sg:address":"4496 Mahoning Ave",
    "sg:city":"Youngstown",
    "sg:classifiers":[
        {
            "category":"Real Estate",
            "subcategory":"Real Estate Agent",
            "type":"Services"
        }
    ],
    "sg:phone":"+1 330 544 4768",
    "sg:postcode":"44515",
    "sg:province":"OH",
    "wof:name":"Mortgage Consulting Assocaites",
    "wof:placetype":"venue"
},
  "geometry": {"coordinates":[-80.73247499999999,41.102074],"type":"Point"}
}