{
  "type": "Feature",
  "properties": {
    "addr:full":"2460 N Reynolds Rd Toledo OH 43615",
    "addr:housenumber":"2460",
    "addr:postcode":"43615",
    "addr:street":"N Reynolds Rd",
    "iso:country":"US",
    "sg:address":"2460 N Reynolds Rd",
    "sg:city":"Toledo",
    "sg:classifiers":[
        {
            "category":"Real Estate",
            "subcategory":"Real Estate Agent",
            "type":"Services"
        }
    ],
    "sg:phone":"+1 419 535 7692",
    "sg:postcode":"43615",
    "sg:province":"OH",
    "wof:name":"Relocation Office",
    "wof:placetype":"venue"
},
  "geometry": {"coordinates":[-83.66789300000001,41.667396],"type":"Point"}
}