{
  "type": "Feature",
  "properties": {
    "addr:full":"100 Techne Center Dr Milford OH 45150",
    "addr:housenumber":"100",
    "addr:postcode":"45150",
    "addr:street":"Techne Center Dr",
    "iso:country":"US",
    "sg:address":"100 Techne Center Dr",
    "sg:city":"Milford",
    "sg:classifiers":[
        {
            "category":"Manufacturing",
            "subcategory":"Rubber & Plastics",
            "type":"Manufacturing & Wholesale Goods"
        }
    ],
    "sg:phone":"+1 513 831 1606",
    "sg:postcode":"45150",
    "sg:province":"OH",
    "sg:tags":[
        "bottles-wholesale",
        "manufacturer"
    ],
    "sg:website":"http://www.saxcointl.com",
    "wof:name":"Saxco Plastics",
    "wof:placetype":"venue"
},
  "geometry": {"coordinates":[-84.25469200000001,39.153549],"type":"Point"}
}