{
  "type": "Feature",
  "properties": {
    "addr:full": "100 Techne Center Dr Milford OH 45150",
    "addr:housenumber": "100",
    "addr:postcode": "45150",
    "addr:street": "Techne Center Dr",
    "iso:country": "US",
    "sg:address": "100 Techne Center Dr",
    "sg:city": "Milford",
    "sg:classifiers": [
      {
        "category": "Manufacturing",
        "subcategory": "Rubber \u0026 Plastics",
        "type": "Manufacturing \u0026 Wholesale Goods"
      }
    ],
    "sg:phone": "+1 513 831 1606",
    "sg:postcode": "45150",
    "sg:province": "OH",
    "sg:tags": [
      "bottles-wholesale",
      "manufacturer"
    ],
    "sg:website": "http://www.saxcointl.com",
    "wof:name": "Saxco Plastics",
    "wof:placetype": "venue"
  },
  "geometry": {"coordinates":[-84.254692,39.153549],"type":"Point"}
}
