{
  "type": "Feature",
  "properties": {
    "addr:full":"4725 Springdale Rd Cincinnati OH 45251",
    "addr:housenumber":"4725",
    "addr:postcode":"45251",
    "addr:street":"Springdale Rd",
    "iso:country":"US",
    "sg:address":"4725 Springdale Rd",
    "sg:city":"Cincinnati",
    "sg:classifiers":[
        {
            "category":"Recreation",
            "type":"Entertainment"
        },
        {
            "category":"Government",
            "subcategory":"Fire Station",
            "type":"Public Place"
        }
    ],
    "sg:phone":"+1 513 385 6743",
    "sg:postcode":"45251",
    "sg:province":"OH",
    "sg:tags":[
        "protection",
        "parks"
    ],
    "sg:website":"www.coleraintwp.org",
    "wof:name":"Colerain Twnshp Parks Dept",
    "wof:placetype":"venue"
},
  "geometry": {"coordinates":[-84.61304699999999,39.243306],"type":"Point"}
}