{
  "type": "Feature",
  "properties": {
    "addr:full": "8866 N Co Rd 25A Piqua OH 45356",
    "addr:housenumber": "8866;25a",
    "addr:postcode": "45356",
    "addr:street": "N Co Rd",
    "iso:country": "US",
    "sg:address": "8866 N Co Rd 25A",
    "sg:city": "Piqua",
    "sg:classifiers": [
      {
        "category": "Manufacturing",
        "subcategory": "Metals",
        "type": "Manufacturing \u0026 Wholesale Goods"
      }
    ],
    "sg:phone": "+1 937 773 6729",
    "sg:postcode": "45356",
    "sg:province": "OH",
    "sg:tags": [
      "steel"
    ],
    "wof:name": "Superior Steel Sales",
    "wof:placetype": "venue"
  },
  "geometry": {"coordinates":[-84.226284,40.16575],"type":"Point"}
}
