{
  "type": "Feature",
  "properties": {
    "addr:full": "2031 N McCord Rd Toledo OH 43615",
    "addr:housenumber": "2031",
    "addr:postcode": "43615",
    "addr:street": "N Mccord Rd",
    "iso:country": "US",
    "sg:address": "2031 N McCord Rd",
    "sg:city": "Toledo",
    "sg:classifiers": [
      {
        "category": "Restaurant",
        "type": "Food \u0026 Drink"
      }
    ],
    "sg:phone": "+1 419 866 7075",
    "sg:postcode": "43615",
    "sg:province": "OH",
    "sg:tags": [
      "parlor",
      "ice",
      "cream"
    ],
    "wof:name": "Mr Freeze",
    "wof:placetype": "venue"
  },
  "geometry": {"coordinates":[-83.702206,41.657374],"type":"Point"}
}
