{
  "type": "Feature",
  "properties": {
    "iso:country":"US",
    "sg:address":"3260 Salt Springs Rd",
    "sg:city":"Warren",
    "sg:classifiers":[
        {
            "category":"Real Estate",
            "subcategory":"Real Estate Operator",
            "type":"Services"
        }
    ],
    "sg:phone":"+1 330 824 3700",
    "sg:postcode":"44481",
    "sg:province":"OH",
    "sg:tags":[
        "mobile",
        "home",
        "community"
    ],
    "wof:name":"GWA Communities",
    "wof:placetype":"venue"
},
  "geometry": {"coordinates":[-80.904877,41.167698],"type":"Point"}
}