{
  "type": "Feature",
  "properties": {
    "addr:full": "114 N 6th St Coshocton OH 43812",
    "addr:housenumber": "114",
    "addr:postcode": "43812",
    "addr:street": "N 6Th St",
    "iso:country": "US",
    "sg:address": "114 N 6th St",
    "sg:city": "Coshocton",
    "sg:classifiers": [
      {
        "category": "Professional",
        "subcategory": "Business Services",
        "type": "Services"
      }
    ],
    "sg:phone": "+1 740 622 2255",
    "sg:postcode": "43812",
    "sg:province": "OH",
    "sg:tags": [
      "information",
      "referral"
    ],
    "wof:name": "WTNS Lottery Info",
    "wof:placetype": "venue"
  },
  "geometry": {"coordinates":[-81.861452,40.274683],"type":"Point"}
}
