{
  "type": "Feature",
  "properties": {
    "addr:full":"3056 W McMicken Ave Cincinnati OH 45225",
    "addr:housenumber":"3056",
    "addr:postcode":"45225",
    "addr:street":"W Mcmicken Ave",
    "iso:country":"US",
    "sg:address":"3056 W McMicken Ave",
    "sg:city":"Cincinnati",
    "sg:classifiers":[
        {
            "category":"Food & Beverages",
            "subcategory":"Groceries & Convenience Stores",
            "type":"Retail Goods"
        }
    ],
    "sg:phone":"+1 513 559 9113",
    "sg:postcode":"45225",
    "sg:province":"OH",
    "wof:name":"Dairy Mart Convenience Store",
    "wof:placetype":"venue"
},
  "geometry": {"coordinates":[-84.531888,39.139648],"type":"Point"}
}