{
  "type": "Feature",
  "properties": {
    "addr:full": "9261 Ravenna Rd Twinsburg OH 44087",
    "addr:housenumber": "9261",
    "addr:postcode": "44087",
    "addr:street": "Ravenna Rd",
    "iso:country": "US",
    "sg:address": "9261 Ravenna Rd",
    "sg:city": "Twinsburg",
    "sg:classifiers": [
      {
        "category": "Insurance",
        "subcategory": "Insurance Agent",
        "type": "Services"
      }
    ],
    "sg:phone": "+1 330 425 9124",
    "sg:postcode": "44087",
    "sg:province": "OH",
    "wof:name": "John Nye Agency Inc",
    "wof:placetype": "venue"
  },
  "geometry": {"coordinates":[-81.423132,41.305116],"type":"Point"}
}
