{
  "type": "Feature",
  "properties": {
    "addr:full": "15271 E US Hwy 224 Findlay OH 45840",
    "addr:housenumber": "15271",
    "addr:postcode": "45840",
    "addr:street": "E Us Hwy 224",
    "iso:country": "US",
    "sg:address": "15271 E US Hwy 224",
    "sg:city": "Findlay",
    "sg:classifiers": [
      {
        "category": "Insurance",
        "subcategory": "Insurance Agent",
        "type": "Services"
      }
    ],
    "sg:phone": "+1 419 420 1900",
    "sg:postcode": "45840",
    "sg:province": "OH",
    "wof:name": "Chris Schiefer Insurance",
    "wof:placetype": "venue"
  },
  "geometry": {"coordinates":[-83.585057,41.056653],"type":"Point"}
}
