{
  "type": "Feature",
  "properties": {
    "iso:country":"US",
    "sg:address":"15271 E US Hwy 224",
    "sg:city":"Findlay",
    "sg:classifiers":[
        {
            "category":"Insurance",
            "subcategory":"Insurance Agent",
            "type":"Services"
        }
    ],
    "sg:phone":"+1 419 420 1900",
    "sg:postcode":"45840",
    "sg:province":"OH",
    "wof:name":"Chris Schiefer Insurance",
    "wof:placetype":"venue"
},
  "geometry": {"coordinates":[-83.58505700000001,41.056653],"type":"Point"}
}