{
  "type": "Feature",
  "properties": {
    "addr:full": "1347 Hubbard Brookfield Rd Hubbard OH 44425",
    "addr:housenumber": "1347",
    "addr:postcode": "44425",
    "addr:street": "Hubbard Brookfield Rd",
    "iso:country": "US",
    "sg:address": "1347 Hubbard Brookfield Rd",
    "sg:city": "Hubbard",
    "sg:classifiers": [
      {
        "category": "Freight",
        "type": "Transportation"
      }
    ],
    "sg:phone": "+1 330 448 2170",
    "sg:postcode": "44425",
    "sg:province": "OH",
    "sg:tags": [
      "trucking"
    ],
    "wof:name": "Tri-County Delivery Inc",
    "wof:placetype": "venue"
  },
  "geometry": {"coordinates":[-80.56864,41.205326],"type":"Point"}
}
