{
  "type": "Feature",
  "properties": {
    "addr:full":"5969 E Livingston Ave Columbus OH 43232",
    "addr:housenumber":"5969",
    "addr:postcode":"43232",
    "addr:street":"E Livingston Ave",
    "iso:country":"US",
    "sg:address":"5969 E Livingston Ave",
    "sg:city":"Columbus",
    "sg:classifiers":[
        {
            "category":"Professional",
            "subcategory":"Lawyer & Legal Services",
            "type":"Services"
        }
    ],
    "sg:phone":"+1 614 577 1330",
    "sg:postcode":"43232",
    "sg:province":"OH",
    "sg:tags":[
        "attorney"
    ],
    "wof:name":"Paley Law Office",
    "wof:placetype":"venue"
},
  "geometry": {"coordinates":[-82.835854,39.942316],"type":"Point"}
}