{
  "type": "Feature",
  "properties": {
    "addr:full": "7499 Van Wagener Rd London OH 43140",
    "addr:housenumber": "7499",
    "addr:postcode": "43140",
    "addr:street": "Van Wagener Rd",
    "iso:country": "US",
    "sg:address": "7499 Van Wagener Rd",
    "sg:city": "London",
    "sg:phone": "+1 740 852 1303",
    "sg:postcode": "43140",
    "sg:province": "OH",
    "sg:tags": [
      "farm",
      "corn",
      "soybean"
    ],
    "wof:name": "Brian Mast",
    "wof:placetype": "venue"
  },
  "geometry": {"coordinates":[-83.38672,39.823248],"type":"Point"}
}
