{
  "type": "Feature",
  "properties": {
    "addr:full":"4369 Westland Mall Columbus OH 43228",
    "addr:housenumber":"4369",
    "addr:postcode":"43228",
    "addr:street":"Westland Mall",
    "iso:country":"US",
    "sg:address":"4369 Westland Mall",
    "sg:city":"Columbus",
    "sg:classifiers":[
        {
            "category":"Food & Beverages",
            "subcategory":"Specialty",
            "type":"Retail Goods"
        }
    ],
    "sg:phone":"+1 614 274 2022",
    "sg:postcode":"43228",
    "sg:province":"OH",
    "wof:name":"GNC",
    "wof:placetype":"venue"
},
  "geometry": {"coordinates":[-83.11514,39.952639],"type":"Point"}
}