{
  "type": "Feature",
  "properties": {
    "iso:country":"US",
    "sg:address":"28 W State Rte 28",
    "sg:city":"Martinsville",
    "sg:classifiers":[
        {
            "category":"Organizations",
            "subcategory":"Religious Organization",
            "type":"Services"
        }
    ],
    "sg:phone":"+1 937 685 3201",
    "sg:postcode":"45146",
    "sg:province":"OH",
    "sg:tags":[
        "church"
    ],
    "wof:name":"Martinsville Church Of Christ",
    "wof:placetype":"venue"
},
  "geometry": {"coordinates":[-83.815506,39.324058],"type":"Point"}
}