{
  "type": "Feature",
  "properties": {
    "addr:full": "1 Shalimar Dr Mount Vernon OH 43050",
    "addr:housenumber": "1",
    "addr:postcode": "43050",
    "addr:street": "Shalimar Dr",
    "iso:country": "US",
    "sg:address": "1 Shalimar Dr",
    "sg:city": "Mount Vernon",
    "sg:classifiers": [
      {
        "category": "Restaurant",
        "type": "Food \u0026 Drink"
      }
    ],
    "sg:phone": "+1 740 392 4242",
    "sg:postcode": "43050",
    "sg:province": "OH",
    "sg:tags": [
      "eating"
    ],
    "wof:name": "Subway",
    "wof:placetype": "venue"
  },
  "geometry": {"coordinates":[-82.460613,40.399608],"type":"Point"}
}
