{
  "type": "Feature",
  "properties": {
    "addr:full":"9405 Kenwood Rd Cincinnati OH 45242",
    "addr:housenumber":"9405",
    "addr:postcode":"45242",
    "addr:street":"Kenwood Rd",
    "iso:country":"US",
    "sg:address":"9405 Kenwood Rd",
    "sg:city":"Cincinnati",
    "sg:classifiers":[
        {
            "category":"Restaurant",
            "type":"Food & Drink"
        }
    ],
    "sg:menulink":"http://www.allmenus.com/oh/blue-ash/69662-donatos-pizza/menu/",
    "sg:phone":"+1 513 792 4040",
    "sg:postcode":"45242",
    "sg:province":"OH",
    "sg:tags":[
        "sandwich",
        "salad",
        "soup",
        "american",
        "wrap",
        "pizza"
    ],
    "wof:name":"Donatos Pizza",
    "wof:placetype":"venue"
},
  "geometry": {"coordinates":[-84.377411,39.227666],"type":"Point"}
}