{
  "type": "Feature",
  "properties": {
    "addr:full": "3286 Lyndon Rd Greenfield OH 45123",
    "addr:housenumber": "3286",
    "addr:postcode": "45123",
    "addr:street": "Lyndon Rd",
    "iso:country": "US",
    "sg:address": "3286 Lyndon Rd",
    "sg:city": "Greenfield",
    "sg:phone": "+1 937 981 3787",
    "sg:postcode": "45123",
    "sg:province": "OH",
    "sg:tags": [
      "farm",
      "corn"
    ],
    "wof:name": "Byron Dawson",
    "wof:placetype": "venue"
  },
  "geometry": {"coordinates":[-83.328084,39.409592],"type":"Point"}
}
