{
  "type": "Feature",
  "properties": {
    "iso:country":"US",
    "sg:address":"751 Miner Dr",
    "sg:city":"Medina",
    "sg:classifiers":[
        {
            "category":"Retail",
            "subcategory":"Car Wash",
            "type":"Services"
        }
    ],
    "sg:phone":"+1 330 721 4812",
    "sg:postcode":"44256",
    "sg:province":"OH",
    "sg:tags":[
        "automobile",
        "detail",
        "clean"
    ],
    "wof:name":"G & S Detailing",
    "wof:placetype":"venue"
},
  "geometry": {"coordinates":[-81.872984,41.146693],"type":"Point"}
}