{
  "type": "Feature",
  "properties": {
    "addr:full": "322 Colony Park Dr Pickerington OH 43147",
    "addr:housenumber": "322",
    "addr:postcode": "43147",
    "addr:street": "Colony Park Dr",
    "iso:country": "US",
    "sg:address": "322 Colony Park Dr",
    "sg:city": "Pickerington",
    "sg:classifiers": [
      {
        "category": "Building \u0026 Trades",
        "subcategory": "Plumbing",
        "type": "Services"
      }
    ],
    "sg:phone": "+1 614 235 1192",
    "sg:postcode": "43147",
    "sg:province": "OH",
    "sg:tags": [
      "contractor"
    ],
    "wof:name": "McDaniel Plbg Co",
    "wof:placetype": "venue"
  },
  "geometry": {"coordinates":[-82.768588,39.889361],"type":"Point"}
}
