{
  "type": "Feature",
  "properties": {
    "addr:full":"1766 E Waterloo Rd Akron OH 44306",
    "addr:housenumber":"1766",
    "addr:postcode":"44306",
    "addr:street":"E Waterloo Rd",
    "iso:country":"US",
    "sg:address":"1766 E Waterloo Rd",
    "sg:city":"Akron",
    "sg:classifiers":[
        {
            "category":"Manufacturing",
            "subcategory":"Motor Vehicles & Parts",
            "type":"Manufacturing & Wholesale Goods"
        }
    ],
    "sg:phone":"+1 330 784 2259",
    "sg:postcode":"44306",
    "sg:province":"OH",
    "sg:tags":[
        "steel",
        "mfg"
    ],
    "wof:name":"Wire Wizards Inc",
    "wof:placetype":"venue"
},
  "geometry": {"coordinates":[-81.454137,41.029795],"type":"Point"}
}