{
  "type": "Feature",
  "properties": {
    "iso:country":"US",
    "sg:address":"217 S Illinois Ave",
    "sg:city":"Wellston",
    "sg:classifiers":[
        {
            "category":"Building & Trades",
            "subcategory":"Electrical",
            "type":"Services"
        }
    ],
    "sg:phone":"+1 740 384 6179",
    "sg:postcode":"45692",
    "sg:province":"OH",
    "sg:tags":[
        "installation"
    ],
    "wof:name":"M & B Installation Svc",
    "wof:placetype":"venue"
},
  "geometry": {"coordinates":[-82.539671,39.121685],"type":"Point"}
}