{
  "type": "Feature",
  "properties": {
    "iso:country":"US",
    "sg:address":"22938 Broadway Rd",
    "sg:city":"Marysville",
    "sg:phone":"+1 937 246 4642",
    "sg:postcode":"43040",
    "sg:province":"OH",
    "sg:tags":[
        "farm",
        "wheat",
        "soybean"
    ],
    "wof:name":"Green Farm",
    "wof:placetype":"venue"
},
  "geometry": {"coordinates":[-83.41352999999999,40.329285],"type":"Point"}
}