{
  "type": "Feature",
  "properties": {
    "addr:full":"74 N Court St Athens OH 45701",
    "addr:housenumber":"74",
    "addr:postcode":"45701",
    "addr:street":"N Court St",
    "iso:country":"US",
    "sg:address":"74 N Court St",
    "sg:city":"Athens",
    "sg:classifiers":[
        {
            "category":"Food & Beverages",
            "subcategory":"Liquor & Beverages",
            "type":"Retail Goods"
        }
    ],
    "sg:phone":"+1 740 592 2064",
    "sg:postcode":"45701",
    "sg:province":"OH",
    "sg:tags":[
        "alcoholic"
    ],
    "wof:name":"Carry Atheneon Out & Deli",
    "wof:placetype":"venue"
},
  "geometry": {"coordinates":[-82.100904,39.332249],"type":"Point"}
}