{
  "type": "Feature",
  "properties": {
    "addr:full":"6130 Dixie Hwy Fairfield OH 45014",
    "addr:housenumber":"6130",
    "addr:postcode":"45014",
    "addr:street":"Dixie Hwy",
    "iso:country":"US",
    "sg:address":"6130 Dixie Hwy",
    "sg:city":"Fairfield",
    "sg:classifiers":[
        {
            "category":"Restaurant",
            "type":"Food & Drink"
        }
    ],
    "sg:phone":"+1 513 829 8118",
    "sg:postcode":"45014",
    "sg:province":"OH",
    "wof:name":"Buffalo Joes",
    "wof:placetype":"venue"
},
  "geometry": {"coordinates":[-84.509451,39.326017],"type":"Point"}
}