{
  "type": "Feature",
  "properties": {
    "addr:full":"602 River Rd Huron OH 44839",
    "addr:housenumber":"602",
    "addr:postcode":"44839",
    "addr:street":"River Rd",
    "iso:country":"US",
    "sg:address":"602 River Rd",
    "sg:city":"Huron",
    "sg:classifiers":[
        {
            "category":"Building & Trades",
            "subcategory":"Landscaping Services",
            "type":"Services"
        }
    ],
    "sg:phone":"+1 419 433 4954",
    "sg:postcode":"44839",
    "sg:province":"OH",
    "sg:tags":[
        "lawn",
        "garden"
    ],
    "wof:name":"A-1 Lawn Care",
    "wof:placetype":"venue"
},
  "geometry": {"coordinates":[-82.549621,41.385107],"type":"Point"}
}