{
  "type": "Feature",
  "properties": {
    "iso:country":"US",
    "sg:address":"2273 State Rte 65",
    "sg:city":"Mc Clure",
    "sg:classifiers":[
        {
            "category":"Freight",
            "type":"Transportation"
        }
    ],
    "sg:phone":"+1 419 832 0423",
    "sg:postcode":"43534",
    "sg:province":"OH",
    "sg:tags":[
        "special",
        "general"
    ],
    "wof:name":"Sunset Storage",
    "wof:placetype":"venue"
},
  "geometry": {"coordinates":[-83.917287,41.415239],"type":"Point"}
}