{
  "type": "Feature",
  "properties": {
    "addr:full": "5269 N Reiman Rd Curtice OH 43412",
    "addr:housenumber": "5269",
    "addr:postcode": "43412",
    "addr:street": "N Reiman Rd",
    "iso:country": "US",
    "sg:address": "5269 N Reiman Rd",
    "sg:city": "Curtice",
    "sg:phone": "+1 419 836 5303",
    "sg:postcode": "43412",
    "sg:province": "OH",
    "sg:tags": [
      "farm",
      "corn",
      "soybean"
    ],
    "wof:name": "Ray Robaszkiewicz",
    "wof:placetype": "venue"
  },
  "geometry": {"coordinates":[-83.377854,41.598149],"type":"Point"}
}
