{
  "type": "Feature",
  "properties": {
    "addr:full":"1500 Polaris Pkwy Columbus OH 43240",
    "addr:housenumber":"1500",
    "addr:postcode":"43240",
    "addr:street":"Polaris Pkwy",
    "iso:country":"US",
    "sg:address":"1500 Polaris Pkwy",
    "sg:city":"Columbus",
    "sg:classifiers":[
        {
            "category":"Shopping",
            "subcategory":"Clothing, Apparel, & Fashions",
            "type":"Retail Goods"
        }
    ],
    "sg:phone":"+1 614 785 1279",
    "sg:postcode":"43240",
    "sg:province":"OH",
    "sg:tags":[
        "sportswear"
    ],
    "wof:name":"Hollister Co",
    "wof:placetype":"venue"
},
  "geometry": {"coordinates":[-82.985922,40.141536],"type":"Point"}
}