{
  "type": "Feature",
  "properties": {
    "iso:country":"US",
    "sg:address":"540 N Warpole St",
    "sg:city":"Upper Sandusky",
    "sg:classifiers":[
        {
            "category":"Shopping",
            "subcategory":"Department Store",
            "type":"Retail Goods"
        }
    ],
    "sg:phone":"+1 419 294 6450",
    "sg:postcode":"43351",
    "sg:province":"OH",
    "wof:name":"Family Dollar Store",
    "wof:placetype":"venue"
},
  "geometry": {"coordinates":[-83.29037099999999,40.83571],"type":"Point"}
}