{
  "type": "Feature",
  "properties": {
    "addr:full": "885 Eastwind Dr Westerville OH 43081",
    "addr:housenumber": "885",
    "addr:postcode": "43081",
    "addr:street": "Eastwind Dr",
    "iso:country": "US",
    "sg:address": "885 Eastwind Dr",
    "sg:city": "Westerville",
    "sg:classifiers": [
      {
        "category": "Health Services",
        "subcategory": "Doctor",
        "type": "Services"
      }
    ],
    "sg:phone": "+1 614 523 1701",
    "sg:postcode": "43081",
    "sg:province": "OH",
    "sg:tags": [
      "physician",
      "surgeon",
      "medical"
    ],
    "wof:name": "Diagnostic Pathology Assoc",
    "wof:placetype": "venue"
  },
  "geometry": {"coordinates":[-82.913994,40.101737],"type":"Point"}
}
