{
  "type": "Feature",
  "properties": {
    "addr:full":"1001 E 2nd St Dayton OH 45402",
    "addr:housenumber":"1001",
    "addr:postcode":"45402",
    "addr:street":"E 2Nd St",
    "iso:country":"US",
    "sg:address":"1001 E 2nd St",
    "sg:city":"Dayton",
    "sg:classifiers":[
        {
            "category":"Communications",
            "subcategory":"Film & Video Production",
            "type":"Services"
        }
    ],
    "sg:phone":"+1 937 222 6002",
    "sg:postcode":"45402",
    "sg:province":"OH",
    "sg:tags":[
        "taping"
    ],
    "wof:name":"Curious Cumulus Productions",
    "wof:placetype":"venue"
},
  "geometry": {"coordinates":[-84.174825,39.76375],"type":"Point"}
}