{
  "type": "Feature",
  "properties": {
    "addr:full": "1906 Scranton Rd Cleveland OH 44113",
    "addr:housenumber": "1906",
    "addr:postcode": "44113",
    "addr:street": "Scranton Rd",
    "iso:country": "US",
    "sg:address": "1906 Scranton Rd",
    "sg:city": "Cleveland",
    "sg:classifiers": [
      {
        "category": "Autos \u0026 Motor Vehicles",
        "subcategory": "Automobile Sales",
        "type": "Retail Goods"
      }
    ],
    "sg:phone": "+1 216 344 3040",
    "sg:postcode": "44113",
    "sg:province": "OH",
    "sg:tags": [
      "dealers-used",
      "car",
      "used",
      "cars-wholesale"
    ],
    "wof:name": "Empire Motors",
    "wof:placetype": "venue"
  },
  "geometry": {"coordinates":[-81.694556,41.491017],"type":"Point"}
}
