{
  "type": "Feature",
  "properties": {
    "iso:country":"US",
    "sg:address":"1906 Scranton Rd",
    "sg:city":"Cleveland",
    "sg:classifiers":[
        {
            "category":"Autos & Motor Vehicles",
            "subcategory":"Automobile Sales",
            "type":"Retail Goods"
        }
    ],
    "sg:phone":"+1 216 344 3040",
    "sg:postcode":"44113",
    "sg:province":"OH",
    "sg:tags":[
        "dealers-used",
        "car",
        "used",
        "cars-wholesale"
    ],
    "wof:name":"Empire Motors",
    "wof:placetype":"venue"
},
  "geometry": {"coordinates":[-81.69455600000001,41.491017],"type":"Point"}
}