{
  "type": "Feature",
  "properties": {
    "iso:country":"US",
    "sg:address":"368 Elberon Ave",
    "sg:city":"Cincinnati",
    "sg:classifiers":[
        {
            "category":"Wholesale",
            "subcategory":"Office Equipment",
            "type":"Manufacturing & Wholesale Goods"
        }
    ],
    "sg:phone":"+1 513 251 1166",
    "sg:postcode":"45205",
    "sg:province":"OH",
    "sg:tags":[
        "register",
        "cash",
        "supply"
    ],
    "wof:name":"Secret Service Co",
    "wof:placetype":"venue"
},
  "geometry": {"coordinates":[-84.56412,39.095915],"type":"Point"}
}