{
  "type": "Feature",
  "properties": {
    "addr:full": "368 Elberon Ave Cincinnati OH 45205",
    "addr:housenumber": "368",
    "addr:postcode": "45205",
    "addr:street": "Elberon Ave",
    "iso:country": "US",
    "sg:address": "368 Elberon Ave",
    "sg:city": "Cincinnati",
    "sg:classifiers": [
      {
        "category": "Wholesale",
        "subcategory": "Office Equipment",
        "type": "Manufacturing \u0026 Wholesale Goods"
      }
    ],
    "sg:phone": "+1 513 251 1166",
    "sg:postcode": "45205",
    "sg:province": "OH",
    "sg:tags": [
      "register",
      "cash",
      "supply"
    ],
    "wof:name": "Secret Service Co",
    "wof:placetype": "venue"
  },
  "geometry": {"coordinates":[-84.56412,39.095915],"type":"Point"}
}
