{
  "type": "Feature",
  "properties": {
    "addr:full": "8902 Mentor Ave Mentor OH 44060",
    "addr:housenumber": "8902",
    "addr:postcode": "44060",
    "addr:street": "Mentor Ave",
    "iso:country": "US",
    "sg:address": "8902 Mentor Ave",
    "sg:city": "Mentor",
    "sg:classifiers": [
      {
        "category": "Personal",
        "subcategory": "Beauty Salon",
        "type": "Services"
      }
    ],
    "sg:phone": "+1 440 255 7733",
    "sg:postcode": "44060",
    "sg:province": "OH",
    "sg:tags": [
      "shop"
    ],
    "wof:name": "Steven Mathew Hairdressers Inc",
    "wof:placetype": "venue"
  },
  "geometry": {"coordinates":[-81.322306,41.674205],"type":"Point"}
}
