{
  "type": "Feature",
  "properties": {
    "addr:full":"2309 Middletown St NW Uniontown OH 44685",
    "addr:housenumber":"2309",
    "addr:postcode":"44685",
    "addr:street":"Middletown St Nw",
    "iso:country":"US",
    "sg:address":"2309 Middletown St NW",
    "sg:city":"Uniontown",
    "sg:classifiers":[
        {
            "category":"Shopping",
            "subcategory":"Hobbies, Toys, & Games",
            "type":"Retail Goods"
        }
    ],
    "sg:phone":"+1 330 699 7037",
    "sg:postcode":"44685",
    "sg:province":"OH",
    "wof:name":"Kems Country Crafts",
    "wof:placetype":"venue"
},
  "geometry": {"coordinates":[-81.385519,40.975715],"type":"Point"}
}