{
  "type": "Feature",
  "properties": {
    "addr:full": "850 US Hwy 50 Milford OH 45150",
    "addr:housenumber": "850",
    "addr:postcode": "45150",
    "addr:street": "Us Hwy 50",
    "iso:country": "US",
    "sg:address": "850 US Hwy 50",
    "sg:city": "Milford",
    "sg:classifiers": [
      {
        "category": "Social Services",
        "subcategory": "Child Care",
        "type": "Services"
      }
    ],
    "sg:phone": "+1 513 576 1133",
    "sg:postcode": "45150",
    "sg:province": "OH",
    "sg:tags": [
      "day"
    ],
    "wof:name": "Jelly Bean Junction Lrng Ctrs",
    "wof:placetype": "venue"
  },
  "geometry": {"coordinates":[-84.256408,39.162439],"type":"Point"}
}
