{
  "type": "Feature",
  "properties": {
    "iso:country":"US",
    "sg:address":"850 US Hwy 50",
    "sg:city":"Milford",
    "sg:classifiers":[
        {
            "category":"Social Services",
            "subcategory":"Child Care",
            "type":"Services"
        }
    ],
    "sg:phone":"+1 513 576 1133",
    "sg:postcode":"45150",
    "sg:province":"OH",
    "sg:tags":[
        "day"
    ],
    "wof:name":"Jelly Bean Junction Lrng Ctrs",
    "wof:placetype":"venue"
},
  "geometry": {"coordinates":[-84.25640799999999,39.162439],"type":"Point"}
}