{
  "type": "Feature",
  "properties": {
    "addr:full":"4310 Ridge Rd Cleveland OH 44144",
    "addr:housenumber":"4310",
    "addr:postcode":"44144",
    "addr:street":"Ridge Rd",
    "iso:country":"US",
    "sg:address":"4310 Ridge Rd",
    "sg:city":"Cleveland",
    "sg:classifiers":[
        {
            "category":"Personal",
            "subcategory":"Beauty Salon",
            "type":"Services"
        }
    ],
    "sg:phone":"+1 216 741 0909",
    "sg:postcode":"44144",
    "sg:province":"OH",
    "wof:name":"Studio Zia",
    "wof:placetype":"venue"
},
  "geometry": {"coordinates":[-81.73536,41.439711],"type":"Point"}
}