{
  "type": "Feature",
  "properties": {
    "addr:full":"6122 Front St New Boston OH 45662",
    "addr:housenumber":"6122",
    "addr:postcode":"45662",
    "addr:street":"Front St",
    "iso:country":"US",
    "sg:address":"6122 Front St",
    "sg:city":"New Boston",
    "sg:classifiers":[
        {
            "category":"Retail",
            "subcategory":"Auto Repair",
            "type":"Services"
        }
    ],
    "sg:phone":"+1 740 776 2331",
    "sg:postcode":"45662",
    "sg:province":"OH",
    "sg:tags":[
        "repairing",
        "transmission",
        "automotive",
        "automobile"
    ],
    "wof:name":"Suburban Transmission",
    "wof:placetype":"venue"
},
  "geometry": {"coordinates":[-82.87664100000001,38.749482],"type":"Point"}
}