{
  "type": "Feature",
  "properties": {
    "addr:full":"500 Defiance Rd St Marys OH 45885",
    "addr:housenumber":"500",
    "addr:postcode":"45885",
    "addr:street":"Defiance Rd",
    "iso:country":"US",
    "sg:address":"500 Defiance Rd",
    "sg:city":"St Marys",
    "sg:classifiers":[
        {
            "category":"Organizations",
            "subcategory":"Religious Organization",
            "type":"Services"
        }
    ],
    "sg:phone":"+1 419 394 7198",
    "sg:postcode":"45885",
    "sg:province":"OH",
    "sg:tags":[
        "church"
    ],
    "wof:name":"First Church Of God",
    "wof:placetype":"venue"
},
  "geometry": {"coordinates":[-84.39652700000001,40.552549],"type":"Point"}
}