{
  "type": "Feature",
  "properties": {
    "addr:full":"990 E Columbus St Kenton OH 43326",
    "addr:housenumber":"990",
    "addr:postcode":"43326",
    "addr:street":"E Columbus St",
    "iso:country":"US",
    "sg:address":"990 E Columbus St",
    "sg:city":"Kenton",
    "sg:classifiers":[
        {
            "category":"Restaurant",
            "type":"Food & Drink"
        }
    ],
    "sg:menulink":"http://www.allmenus.com/oh/pleasant/195530-mcdonalds/menu/",
    "sg:postcode":"43326",
    "sg:province":"OH",
    "sg:tags":[
        "burger",
        "american"
    ],
    "wof:name":"McDonald's",
    "wof:placetype":"venue"
},
  "geometry": {"coordinates":[-83.59524500000001,40.650519],"type":"Point"}
}