{
  "type": "Feature",
  "properties": {
    "addr:full": "107 N Court St Medina OH 44256",
    "addr:housenumber": "107",
    "addr:postcode": "44256",
    "addr:street": "N Court St",
    "iso:country": "US",
    "sg:address": "107 N Court St",
    "sg:city": "Medina",
    "sg:classifiers": [
      {
        "category": "Banks \u0026 Credit Unions",
        "subcategory": "Bank",
        "type": "Services"
      }
    ],
    "sg:phone": "+1 330 723 8800",
    "sg:postcode": "44256",
    "sg:province": "OH",
    "sg:tags": [
      "broker",
      "mortgage"
    ],
    "wof:name": "Diversified Home Mortgage",
    "wof:placetype": "venue"
  },
  "geometry": {"coordinates":[-81.864068,41.139311],"type":"Point"}
}
