{
  "type": "Feature",
  "properties": {
    "iso:country":"US",
    "sg:address":"1901 Arlington Ave",
    "sg:city":"Columbus",
    "sg:classifiers":[
        {
            "category":"Education",
            "subcategory":"Library",
            "type":"Public Place"
        }
    ],
    "sg:phone":"+1 614 488 5710",
    "sg:postcode":"43212",
    "sg:province":"OH",
    "wof:name":"Miller Park Library",
    "wof:placetype":"venue"
},
  "geometry": {"coordinates":[-83.060717,39.996271],"type":"Point"}
}