{
  "type": "Feature",
  "properties": {
    "addr:full":"110 Windsor Dr Cortland OH 44410",
    "addr:housenumber":"110",
    "addr:postcode":"44410",
    "addr:street":"Windsor Dr",
    "iso:country":"US",
    "sg:address":"110 Windsor Dr",
    "sg:city":"Cortland",
    "sg:classifiers":[
        {
            "category":"Insurance",
            "subcategory":"Insurance Agent",
            "type":"Services"
        }
    ],
    "sg:phone":"+1 330 637 0067",
    "sg:postcode":"44410",
    "sg:province":"OH",
    "wof:name":"Allstate Insurance Co",
    "wof:placetype":"venue"
},
  "geometry": {"coordinates":[-80.72944099999999,41.311533],"type":"Point"}
}