{
  "type": "Feature",
  "properties": {
    "iso:country":"US",
    "sg:address":"238 Carthage Ave",
    "sg:city":"Cincinnati",
    "sg:classifiers":[
        {
            "category":"Retail",
            "subcategory":"Auto Repair",
            "type":"Services"
        }
    ],
    "sg:phone":"+1 513 821 4065",
    "sg:postcode":"45215",
    "sg:province":"OH",
    "sg:tags":[
        "repairing",
        "automobile"
    ],
    "wof:name":"Roberts Garage",
    "wof:placetype":"venue"
},
  "geometry": {"coordinates":[-84.453273,39.219],"type":"Point"}
}