{
  "type": "Feature",
  "properties": {
    "addr:full":"11600 Deeter Rd Bradford OH 45308",
    "addr:housenumber":"11600",
    "addr:postcode":"45308",
    "addr:street":"Deeter Rd",
    "iso:country":"US",
    "sg:address":"11600 Deeter Rd",
    "sg:city":"Bradford",
    "sg:phone":"+1 937 947 1259",
    "sg:postcode":"45308",
    "sg:province":"OH",
    "sg:tags":[
        "farm",
        "corn",
        "soybean"
    ],
    "wof:name":"Gerald Davis",
    "wof:placetype":"venue"
},
  "geometry": {"coordinates":[-84.418398,40.065405],"type":"Point"}
}