{
  "type": "Feature",
  "properties": {
    "addr:full": "1310 Lake Ave Ashtabula OH 44004",
    "addr:housenumber": "1310",
    "addr:postcode": "44004",
    "addr:street": "Lake Ave",
    "iso:country": "US",
    "sg:address": "1310 Lake Ave",
    "sg:city": "Ashtabula",
    "sg:classifiers": [
      {
        "category": "Personal",
        "subcategory": "Beauty Salon",
        "type": "Services"
      }
    ],
    "sg:phone": "+1 440 964 0059",
    "sg:postcode": "44004",
    "sg:province": "OH",
    "wof:name": "Avenue Hair Salon",
    "wof:placetype": "venue"
  },
  "geometry": {"coordinates":[-80.80461,41.887685],"type":"Point"}
}
