{
  "type": "Feature",
  "properties": {
    "iso:country":"US",
    "sg:address":"285 Harris St",
    "sg:city":"Newport",
    "sg:classifiers":[
        {
            "category":"Building & Trades",
            "subcategory":"Pest Control",
            "type":"Services"
        }
    ],
    "sg:phone":"+1 740 374 7193",
    "sg:postcode":"45768",
    "sg:province":"OH",
    "wof:name":"Joy Exterminators",
    "wof:placetype":"venue"
},
  "geometry": {"coordinates":[-81.224012,39.389842],"type":"Point"}
}