{
  "type": "Feature",
  "properties": {
    "addr:full":"1925 US Rte 62 Wilmot OH 44689",
    "addr:housenumber":"1925",
    "addr:postcode":"44689",
    "addr:street":"Us Rte 62",
    "iso:country":"US",
    "sg:address":"1925 US Rte 62",
    "sg:city":"Wilmot",
    "sg:classifiers":[
        {
            "category":"Manufacturing",
            "subcategory":"Lumber",
            "type":"Manufacturing & Wholesale Goods"
        }
    ],
    "sg:phone":"+1 330 359 5091",
    "sg:postcode":"44689",
    "sg:province":"OH",
    "sg:tags":[
        "sawmill"
    ],
    "wof:name":"Weaver Lumber Co",
    "wof:placetype":"venue"
},
  "geometry": {"coordinates":[-81.690597,40.6248],"type":"Point"}
}