{
  "type": "Feature",
  "properties": {
    "addr:full": "970 E 250th St Cleveland OH 44132",
    "addr:housenumber": "970",
    "addr:postcode": "44132",
    "addr:street": "E 250Th St",
    "iso:country": "US",
    "sg:address": "970 E 250th St",
    "sg:city": "Cleveland",
    "sg:classifiers": [
      {
        "category": "Organizations",
        "subcategory": "Religious Organization",
        "type": "Services"
      }
    ],
    "sg:phone": "+1 216 289 9383",
    "sg:postcode": "44132",
    "sg:province": "OH",
    "sg:tags": [
      "church"
    ],
    "wof:name": "Living Waters Church Of God",
    "wof:placetype": "venue"
  },
  "geometry": {"coordinates":[-81.509362,41.598128],"type":"Point"}
}
