{
  "type": "Feature",
  "properties": {
    "addr:full": "50 Public Sq Cleveland OH 44113",
    "addr:housenumber": "50",
    "addr:postcode": "44113",
    "addr:street": "Public Sq",
    "iso:country": "US",
    "sg:address": "50 Public Sq",
    "sg:city": "Cleveland",
    "sg:classifiers": [
      {
        "category": "Organizations",
        "subcategory": "Non-profit Organization",
        "type": "Services"
      }
    ],
    "sg:phone": "+1 216 579 9600",
    "sg:postcode": "44113",
    "sg:province": "OH",
    "sg:tags": [
      "social"
    ],
    "wof:name": "A D L",
    "wof:placetype": "venue"
  },
  "geometry": {"coordinates":[-81.694262,41.500327],"type":"Point"}
}
