{
  "type": "Feature",
  "properties": {
    "addr:full": "128 Granville St Columbus OH 43230",
    "addr:housenumber": "128",
    "addr:postcode": "43230",
    "addr:street": "Granville St",
    "iso:country": "US",
    "sg:address": "128 Granville St",
    "sg:city": "Columbus",
    "sg:classifiers": [
      {
        "category": "Organizations",
        "subcategory": "Non-profit Organization",
        "type": "Services"
      }
    ],
    "sg:phone": "+1 614 473 9521",
    "sg:postcode": "43230",
    "sg:province": "OH",
    "wof:name": "Miracles For You Today",
    "wof:placetype": "venue"
  },
  "geometry": {"coordinates":[-82.876175,40.018808],"type":"Point"}
}
