{
  "type": "Feature",
  "properties": {
    "addr:full":"266 Federal Ave NW Massillon OH 44647",
    "addr:housenumber":"266",
    "addr:postcode":"44647",
    "addr:street":"Federal Ave Nw",
    "iso:country":"US",
    "sg:address":"266 Federal Ave NW",
    "sg:city":"Massillon",
    "sg:classifiers":[
        {
            "category":"Food & Beverages",
            "subcategory":"Groceries & Convenience Stores",
            "type":"Retail Goods"
        }
    ],
    "sg:phone":"+1 330 837 2561",
    "sg:postcode":"44647",
    "sg:province":"OH",
    "sg:tags":[
        "grocer"
    ],
    "wof:name":"Save-A-Lot",
    "wof:placetype":"venue"
},
  "geometry": {"coordinates":[-81.526533,40.796544],"type":"Point"}
}