{
  "type": "Feature",
  "properties": {
    "iso:country":"US",
    "sg:address":"6126 Moss Hill Ct",
    "sg:city":"Dayton",
    "sg:classifiers":[
        {
            "category":"Organizations",
            "subcategory":"Labor Organization",
            "type":"Services"
        }
    ],
    "sg:phone":"+1 937 879 2909",
    "sg:postcode":"45424",
    "sg:province":"OH",
    "wof:name":"Internationl Assn Machinsts/Ae",
    "wof:placetype":"venue"
},
  "geometry": {"coordinates":[-84.125742,39.875904],"type":"Point"}
}