{
  "type": "Feature",
  "properties": {
    "addr:full":"21460 Rd 48 Grover Hill OH 45849",
    "addr:postcode":"21460;45849",
    "addr:street":"Rd 48",
    "iso:country":"US",
    "sg:address":"21460 Rd 48",
    "sg:city":"Grover Hill",
    "sg:phone":"+1 419 587 3689",
    "sg:postcode":"45849",
    "sg:province":"OH",
    "sg:tags":[
        "farm",
        "corn",
        "wheat",
        "soybean"
    ],
    "wof:name":"Darwin McClure",
    "wof:placetype":"venue"
},
  "geometry": {"coordinates":[-84.400356,41.033932],"type":"Point"}
}