{
  "type": "Feature",
  "properties": {
    "addr:full": "2941 Baird Ave SE Paris OH 44669",
    "addr:housenumber": "2941",
    "addr:postcode": "44669",
    "addr:street": "Baird Ave Se",
    "iso:country": "US",
    "sg:address": "2941 Baird Ave SE",
    "sg:city": "Paris",
    "sg:classifiers": [
      {
        "category": "Farming",
        "subcategory": "Dairy Farm",
        "type": "Manufacturing \u0026 Wholesale Goods"
      }
    ],
    "sg:phone": "+1 330 862 2369",
    "sg:postcode": "44669",
    "sg:province": "OH",
    "wof:name": "Lee Keith Thomas",
    "wof:placetype": "venue"
  },
  "geometry": {"coordinates":[-81.144343,40.768222],"type":"Point"}
}
