{
  "type": "Feature",
  "properties": {
    "addr:full": "9700 Rockside Rd Cleveland OH 44125",
    "addr:housenumber": "9700",
    "addr:postcode": "44125",
    "addr:street": "Rockside Rd",
    "iso:country": "US",
    "sg:address": "9700 Rockside Rd",
    "sg:city": "Cleveland",
    "sg:classifiers": [
      {
        "category": "Banks \u0026 Credit Unions",
        "subcategory": "Bank",
        "type": "Services"
      }
    ],
    "sg:phone": "+1 216 520 6330",
    "sg:postcode": "44125",
    "sg:province": "OH",
    "sg:tags": [
      "mortgage"
    ],
    "wof:name": "Wholesale Mortgage Group Inc",
    "wof:placetype": "venue"
  },
  "geometry": {"coordinates":[-81.622621,41.393278],"type":"Point"}
}
