{
  "type": "Feature",
  "properties": {
    "addr:full": "1995 Alabama Ave SW Dalton OH 44618",
    "addr:housenumber": "1995",
    "addr:postcode": "44618",
    "addr:street": "Alabama Ave Sw",
    "iso:country": "US",
    "sg:address": "1995 Alabama Ave SW",
    "sg:city": "Dalton",
    "sg:classifiers": [
      {
        "category": "Farming",
        "subcategory": "Farm",
        "type": "Manufacturing \u0026 Wholesale Goods"
      }
    ],
    "sg:phone": "+1 330 837 3197",
    "sg:postcode": "44618",
    "sg:province": "OH",
    "sg:tags": [
      "crop",
      "general"
    ],
    "wof:name": "Middlebrook Farms",
    "wof:placetype": "venue"
  },
  "geometry": {"coordinates":[-81.632578,40.779942],"type":"Point"}
}
