{
  "type": "Feature",
  "properties": {
    "iso:country":"US",
    "sg:address":"1995 Alabama Ave SW",
    "sg:city":"Dalton",
    "sg:classifiers":[
        {
            "category":"Farming",
            "subcategory":"Farm",
            "type":"Manufacturing & Wholesale Goods"
        }
    ],
    "sg:phone":"+1 330 837 3197",
    "sg:postcode":"44618",
    "sg:province":"OH",
    "sg:tags":[
        "crop",
        "general"
    ],
    "wof:name":"Middlebrook Farms",
    "wof:placetype":"venue"
},
  "geometry": {"coordinates":[-81.632578,40.779942],"type":"Point"}
}