{
  "type": "Feature",
  "properties": {
    "addr:full":"1414 Raff Rd SW Canton OH 44710",
    "addr:housenumber":"1414",
    "addr:postcode":"44710",
    "addr:street":"Raff Rd Sw",
    "iso:country":"US",
    "sg:address":"1414 Raff Rd SW",
    "sg:city":"Canton",
    "sg:classifiers":[
        {
            "category":"Freight",
            "type":"Transportation"
        }
    ],
    "sg:phone":"+1 330 477 0070",
    "sg:postcode":"44710",
    "sg:province":"OH",
    "sg:tags":[
        "local",
        "storage",
        "trucking"
    ],
    "wof:name":"Demario Philip J Moving & Stor",
    "wof:placetype":"venue"
},
  "geometry": {"coordinates":[-81.419771,40.784142],"type":"Point"}
}