{
  "type": "Feature",
  "properties": {
    "addr:full": "700 Home Ave Akron OH 44310",
    "addr:housenumber": "700",
    "addr:postcode": "44310",
    "addr:street": "Home Ave",
    "iso:country": "US",
    "sg:address": "700 Home Ave",
    "sg:city": "Akron",
    "sg:classifiers": [
      {
        "category": "Building \u0026 Trades",
        "subcategory": "Construction",
        "type": "Services"
      }
    ],
    "sg:phone": "+1 330 762 9373",
    "sg:postcode": "44310",
    "sg:province": "OH",
    "sg:tags": [
      "highway"
    ],
    "sg:website": "www.kenmorecompanies.com",
    "wof:name": "Kenmore Construction Co",
    "wof:placetype": "venue"
  },
  "geometry": {"coordinates":[-81.489969,41.08774],"type":"Point"}
}
