{
  "type": "Feature",
  "properties": {
    "addr:full": "1410 E Dorothy Ln Dayton OH 45429",
    "addr:housenumber": "1410",
    "addr:postcode": "45429",
    "addr:street": "E Dorothy Ln",
    "iso:country": "US",
    "sg:address": "1410 E Dorothy Ln",
    "sg:city": "Dayton",
    "sg:classifiers": [
      {
        "category": "Shopping",
        "subcategory": "Pharmacy",
        "type": "Retail Goods"
      }
    ],
    "sg:phone": "+1 937 294 0535",
    "sg:postcode": "45429",
    "sg:province": "OH",
    "sg:tags": [
      "drug",
      "store"
    ],
    "wof:name": "CVS",
    "wof:placetype": "venue"
  },
  "geometry": {"coordinates":[-84.139372,39.70352],"type":"Point"}
}
