{
  "type": "Feature",
  "properties": {
    "addr:full": "233 W 6th St Marysville OH 43040",
    "addr:housenumber": "233",
    "addr:postcode": "43040",
    "addr:street": "W 6Th St",
    "iso:country": "US",
    "sg:address": "233 W 6th St",
    "sg:city": "Marysville",
    "sg:classifiers": [
      {
        "category": "Government",
        "subcategory": "Office",
        "type": "Public Place"
      }
    ],
    "sg:phone": "+1 937 645 3003",
    "sg:postcode": "43040",
    "sg:province": "OH",
    "sg:tags": [
      "county",
      "taxation"
    ],
    "sg:website": "www.co.union.oh.us",
    "wof:name": "Union County Auditor",
    "wof:placetype": "venue"
  },
  "geometry": {"coordinates":[-83.370416,40.235443],"type":"Point"}
}
