{
  "type": "Feature",
  "properties": {
    "iso:country":"US",
    "sg:address":"3800 Dayton Park Dr",
    "sg:city":"Dayton",
    "sg:phone":"+1 937 236 0211",
    "sg:postcode":"45414",
    "sg:province":"OH",
    "sg:tags":[
        "bulk",
        "gas"
    ],
    "wof:name":"Linde Gas",
    "wof:placetype":"venue"
},
  "geometry": {"coordinates":[-84.168097,39.802468],"type":"Point"}
}