{
  "type": "Feature",
  "properties": {
    "iso:country":"US",
    "sg:address":"2809 Nationwide Pkwy",
    "sg:city":"Brunswick",
    "sg:classifiers":[
        {
            "category":"Manufacturing",
            "subcategory":"Metals",
            "type":"Manufacturing & Wholesale Goods"
        }
    ],
    "sg:phone":"+1 330 273 6468",
    "sg:postcode":"44212",
    "sg:province":"OH",
    "sg:tags":[
        "shop",
        "die",
        "tool",
        "stamping"
    ],
    "sg:website":"www.ronlen.com",
    "wof:name":"Ronlen Industries Inc",
    "wof:placetype":"venue"
},
  "geometry": {"coordinates":[-81.78762399999999,41.244447],"type":"Point"}
}