{
  "type": "Feature",
  "properties": {
    "addr:full":"761 Eastgate South Dr Cincinnati OH 45245",
    "addr:housenumber":"761",
    "addr:postcode":"45245",
    "addr:street":"Eastgate South Dr",
    "iso:country":"US",
    "sg:address":"761 Eastgate South Dr",
    "sg:city":"Cincinnati",
    "sg:classifiers":[
        {
            "category":"Sports & Exercise",
            "subcategory":"Gym",
            "type":"Entertainment"
        }
    ],
    "sg:phone":"+1 513 752 1200",
    "sg:postcode":"45245",
    "sg:province":"OH",
    "sg:tags":[
        "equipment",
        "fitness"
    ],
    "wof:name":"Home Gym. Fitness Whse.",
    "wof:placetype":"venue"
},
  "geometry": {"coordinates":[-84.27124000000001,39.095903],"type":"Point"}
}