{
  "type": "Feature",
  "properties": {
    "addr:full":"127 N Maysville Ave Zanesville OH 43701",
    "addr:housenumber":"127",
    "addr:postcode":"43701",
    "addr:street":"N Maysville Ave",
    "iso:country":"US",
    "sg:address":"127 N Maysville Ave",
    "sg:city":"Zanesville",
    "sg:classifiers":[
        {
            "category":"Sports & Exercise",
            "subcategory":"Gym",
            "type":"Entertainment"
        }
    ],
    "sg:phone":"+1 740 455 2639",
    "sg:postcode":"43701",
    "sg:province":"OH",
    "sg:tags":[
        "gymnasium"
    ],
    "wof:name":"Southtown Gym",
    "wof:placetype":"venue"
},
  "geometry": {"coordinates":[-82.018806,39.906019],"type":"Point"}
}