{
  "type": "Feature",
  "properties": {
    "iso:country":"US",
    "sg:address":"4059 State Rte 37",
    "sg:city":"Delaware",
    "sg:classifiers":[
        {
            "category":"Health Services",
            "subcategory":"Chiropractor",
            "type":"Services"
        },
        {
            "category":"Health Services",
            "subcategory":"Doctor",
            "type":"Services"
        }
    ],
    "sg:phone":"+1 740 369 7023",
    "sg:postcode":"43015",
    "sg:province":"OH",
    "sg:tags":[
        "physician",
        "surgeon"
    ],
    "wof:name":"Brian G Foltz MD",
    "wof:placetype":"venue"
},
  "geometry": {"coordinates":[-82.99979500000001,40.283537],"type":"Point"}
}