{
  "type": "Feature",
  "properties": {
    "addr:full":"10250 Phillipp Pkwy Streetsboro OH 44241",
    "addr:housenumber":"10250",
    "addr:postcode":"44241",
    "addr:street":"Phillipp Pkwy",
    "iso:country":"US",
    "sg:address":"10250 Phillipp Pkwy",
    "sg:city":"Streetsboro",
    "sg:classifiers":[
        {
            "category":"Home & Garden",
            "subcategory":"Building Materials",
            "type":"Retail Goods"
        }
    ],
    "sg:phone":"+1 330 528 3400",
    "sg:postcode":"44241",
    "sg:province":"OH",
    "sg:tags":[
        "windows"
    ],
    "wof:name":"Soft-Lite",
    "wof:placetype":"venue"
},
  "geometry": {"coordinates":[-81.370633,41.270395],"type":"Point"}
}