{
  "type": "Feature",
  "properties": {
    "addr:full": "151 E Main St Wayne OH 43466",
    "addr:housenumber": "151",
    "addr:postcode": "43466",
    "addr:street": "E Main St",
    "iso:country": "US",
    "sg:address": "151 E Main St",
    "sg:city": "Wayne",
    "sg:classifiers": [
      {
        "category": "Professional",
        "subcategory": "Lawyer \u0026 Legal Services",
        "type": "Services"
      }
    ],
    "sg:phone": "+1 419 288 8787",
    "sg:postcode": "43466",
    "sg:province": "OH",
    "sg:tags": [
      "attorney"
    ],
    "wof:name": "Thomas E Teet",
    "wof:placetype": "venue"
  },
  "geometry": {"coordinates":[-83.473009,41.300824],"type":"Point"}
}
