{
  "type": "Feature",
  "properties": {
    "iso:country":"US",
    "sg:address":"151 E Main St",
    "sg:city":"Wayne",
    "sg:classifiers":[
        {
            "category":"Professional",
            "subcategory":"Lawyer & Legal Services",
            "type":"Services"
        }
    ],
    "sg:phone":"+1 419 288 8787",
    "sg:postcode":"43466",
    "sg:province":"OH",
    "sg:tags":[
        "attorney"
    ],
    "wof:name":"Thomas E Teet",
    "wof:placetype":"venue"
},
  "geometry": {"coordinates":[-83.473009,41.300824],"type":"Point"}
}