{
  "type": "Feature",
  "properties": {
    "addr:full": "145 S State St Westerville OH 43081",
    "addr:housenumber": "145",
    "addr:postcode": "43081",
    "addr:street": "S State St",
    "iso:country": "US",
    "sg:address": "145 S State St",
    "sg:city": "Westerville",
    "sg:classifiers": [
      {
        "category": "Shopping",
        "subcategory": "Pharmacy",
        "type": "Retail Goods"
      }
    ],
    "sg:phone": "+1 614 890 4660",
    "sg:postcode": "43081",
    "sg:province": "OH",
    "wof:name": "CVS Pharmacy",
    "wof:placetype": "venue"
  },
  "geometry": {"coordinates":[-82.930233,40.122013],"type":"Point"}
}
