{
  "type": "Feature",
  "properties": {
    "addr:full": "6272 Misty Cove Ln Columbus OH 43231",
    "addr:housenumber": "6272",
    "addr:postcode": "43231",
    "addr:street": "Misty Cove Ln",
    "iso:country": "US",
    "sg:address": "6272 Misty Cove Ln",
    "sg:city": "Columbus",
    "sg:classifiers": [
      {
        "category": "Arts \u0026 Performance",
        "subcategory": "Theater",
        "type": "Entertainment"
      }
    ],
    "sg:phone": "+1 614 890 1046",
    "sg:postcode": "43231",
    "sg:province": "OH",
    "sg:tags": [
      "live",
      "music"
    ],
    "wof:name": "Sounds Perfect",
    "wof:placetype": "venue"
  },
  "geometry": {"coordinates":[-82.942465,40.098353],"type":"Point"}
}
