{
  "type": "Feature",
  "properties": {
    "addr:full":"1130 Tower Blvd Lorain OH 44052",
    "addr:housenumber":"1130",
    "addr:postcode":"44052",
    "addr:street":"Tower Blvd",
    "iso:country":"US",
    "sg:address":"1130 Tower Blvd",
    "sg:city":"Lorain",
    "sg:classifiers":[
        {
            "category":"Professional",
            "type":"Services"
        }
    ],
    "sg:phone":"+1 440 282 4472",
    "sg:postcode":"44052",
    "sg:province":"OH",
    "wof:name":"T M Godek",
    "wof:placetype":"venue"
},
  "geometry": {"coordinates":[-82.18528999999999,41.433923],"type":"Point"}
}