{
  "type": "Feature",
  "properties": {
    "iso:country":"US",
    "sg:address":"209 Leyland Park Dr",
    "sg:city":"Wilmington",
    "sg:classifiers":[
        {
            "category":"Professional",
            "subcategory":"Lawyer & Legal Services",
            "type":"Services"
        }
    ],
    "sg:phone":"+1 937 382 4454",
    "sg:postcode":"45177",
    "sg:province":"OH",
    "sg:tags":[
        "attorney"
    ],
    "wof:name":"Frederick J Buckley Attorney",
    "wof:placetype":"venue"
},
  "geometry": {"coordinates":[-83.821934,39.457249],"type":"Point"}
}