{
  "type": "Feature",
  "properties": {
    "addr:full":"874 Mahoning Rd NE Canton OH 44705",
    "addr:housenumber":"874",
    "addr:postcode":"44705",
    "addr:street":"Mahoning Rd Ne",
    "iso:country":"US",
    "sg:address":"874 Mahoning Rd NE",
    "sg:city":"Canton",
    "sg:classifiers":[
        {
            "category":"Recreation",
            "type":"Entertainment"
        }
    ],
    "sg:phone":"+1 330 588 9074",
    "sg:postcode":"44705",
    "sg:province":"OH",
    "sg:tags":[
        "club",
        "membership"
    ],
    "wof:name":"Juneites Club",
    "wof:placetype":"venue"
},
  "geometry": {"coordinates":[-81.359386,40.803181],"type":"Point"}
}