{
  "type": "Feature",
  "properties": {
    "addr:full": "26 Wyandotte St Dayton OH 45402",
    "addr:housenumber": "26",
    "addr:postcode": "45402",
    "addr:street": "Wyandotte St",
    "iso:country": "US",
    "sg:address": "26 Wyandotte St",
    "sg:city": "Dayton",
    "sg:classifiers": [
      {
        "category": "Bars \u0026 Pubs",
        "type": "Food \u0026 Drink"
      }
    ],
    "sg:phone": "+1 937 222 8550",
    "sg:postcode": "45402",
    "sg:province": "OH",
    "sg:tags": [
      "club",
      "night"
    ],
    "wof:name": "Foundry",
    "wof:placetype": "venue"
  },
  "geometry": {"coordinates":[-84.186224,39.759311],"type":"Point"}
}
