{
  "type": "Feature",
  "properties": {
    "addr:full": "535 E Main St Greenville OH 45331",
    "addr:housenumber": "535",
    "addr:postcode": "45331",
    "addr:street": "E Main St",
    "iso:country": "US",
    "sg:address": "535 E Main St",
    "sg:city": "Greenville",
    "sg:classifiers": [
      {
        "category": "Real Estate",
        "subcategory": "Real Estate Agent",
        "type": "Services"
      }
    ],
    "sg:phone": "+1 937 548 5750",
    "sg:postcode": "45331",
    "sg:province": "OH",
    "sg:website": "www.leisrealty.com",
    "wof:name": "Leis Realty",
    "wof:placetype": "venue"
  },
  "geometry": {"coordinates":[-84.62736,40.106301],"type":"Point"}
}
