{
  "type": "Feature",
  "properties": {
    "iso:country":"US",
    "sg:address":"218 E Washington St",
    "sg:city":"Sandusky",
    "sg:classifiers":[
        {
            "category":"Restaurant",
            "type":"Food & Drink"
        }
    ],
    "sg:phone":"+1 419 627 2773",
    "sg:postcode":"44870",
    "sg:province":"OH",
    "wof:name":"Tearose Tearoom",
    "wof:placetype":"venue"
},
  "geometry": {"coordinates":[-82.707952,41.455842],"type":"Point"}
}