{
  "type": "Feature",
  "properties": {
    "addr:full": "1190 Three Forks Dr N Westerville OH 43081",
    "addr:housenumber": "1190",
    "addr:postcode": "43081",
    "addr:street": "Three Forks Dr N",
    "iso:country": "US",
    "sg:address": "1190 Three Forks Dr N",
    "sg:city": "Westerville",
    "sg:classifiers": [
      {
        "category": "Professional",
        "type": "Services"
      }
    ],
    "sg:phone": "+1 614 736 6056",
    "sg:postcode": "43081",
    "sg:province": "OH",
    "wof:name": "David M Sweet Organiztn",
    "wof:placetype": "venue"
  },
  "geometry": {"coordinates":[-82.891996,40.105349],"type":"Point"}
}
