{
  "type": "Feature",
  "properties": {
    "iso:country":"US",
    "sg:address":"5100 Post Rd",
    "sg:city":"Dublin",
    "sg:classifiers":[
        {
            "category":"Autos & Motor Vehicles",
            "subcategory":"Automobile Sales",
            "type":"Retail Goods"
        }
    ],
    "sg:phone":"+1 614 799 5000",
    "sg:postcode":"43017",
    "sg:province":"OH",
    "sg:tags":[
        "car",
        "dealer"
    ],
    "sg:website":"www.toybarncars.com",
    "wof:name":"Toy Barn",
    "wof:placetype":"venue"
},
  "geometry": {"coordinates":[-83.12859,40.101138],"type":"Point"}
}