{
  "type": "Feature",
  "properties": {
    "addr:full":"35225 N Turtle Trl Willoughby OH 44094",
    "addr:housenumber":"35225",
    "addr:postcode":"44094",
    "addr:street":"N Turtle Trl",
    "iso:country":"US",
    "sg:address":"35225 N Turtle Trl",
    "sg:city":"Willoughby",
    "sg:classifiers":[
        {
            "category":"Shopping",
            "subcategory":"Shoes",
            "type":"Retail Goods"
        }
    ],
    "sg:phone":"+1 440 946 6759",
    "sg:postcode":"44094",
    "sg:province":"OH",
    "wof:name":"Payless Shoesource",
    "wof:placetype":"venue"
},
  "geometry": {"coordinates":[-81.43679899999999,41.621539],"type":"Point"}
}