{
  "type": "Feature",
  "properties": {
    "addr:full":"3039 E Center St North Kingsville OH 44030",
    "addr:housenumber":"3039",
    "addr:postcode":"44030",
    "addr:street":"E Center St",
    "iso:country":"US",
    "sg:address":"3039 E Center St",
    "sg:city":"North Kingsville",
    "sg:classifiers":[
        {
            "category":"Sports & Exercise",
            "subcategory":"Bowling",
            "type":"Entertainment"
        }
    ],
    "sg:phone":"+1 440 224 2148",
    "sg:postcode":"44030",
    "sg:province":"OH",
    "sg:tags":[
        "center"
    ],
    "wof:name":"Kings Lanes",
    "wof:placetype":"venue"
},
  "geometry": {"coordinates":[-80.67260899999999,41.915169],"type":"Point"}
}