{
  "type": "Feature",
  "properties": {
    "addr:full": "17829 Euclid Ave Cleveland OH 44112",
    "addr:housenumber": "17829",
    "addr:postcode": "44112",
    "addr:street": "Euclid Ave",
    "iso:country": "US",
    "sg:address": "17829 Euclid Ave",
    "sg:city": "Cleveland",
    "sg:classifiers": [
      {
        "category": "Personal",
        "subcategory": "Beauty Salon",
        "type": "Services"
      }
    ],
    "sg:phone": "+1 216 383 1100",
    "sg:postcode": "44112",
    "sg:province": "OH",
    "wof:name": "Trend Beauty Salon",
    "wof:placetype": "venue"
  },
  "geometry": {"coordinates":[-81.554752,41.553726],"type":"Point"}
}
