{
  "type": "Feature",
  "properties": {
    "addr:full": "994 E 13th Ave Columbus OH 43211",
    "addr:housenumber": "994",
    "addr:postcode": "43211",
    "addr:street": "E 13Th Ave",
    "iso:country": "US",
    "sg:address": "994 E 13th Ave",
    "sg:city": "Columbus",
    "sg:classifiers": [
      {
        "category": "Organizations",
        "subcategory": "Religious Organization",
        "type": "Services"
      }
    ],
    "sg:phone": "+1 614 294 8769",
    "sg:postcode": "43211",
    "sg:province": "OH",
    "sg:tags": [
      "church"
    ],
    "wof:name": "Word Of Faith Fellowship",
    "wof:placetype": "venue"
  },
  "geometry": {"coordinates":[-82.981143,39.997169],"type":"Point"}
}
