{
  "type": "Feature",
  "properties": {
    "addr:full":"4841 State Rte 43 Kent OH 44240",
    "addr:housenumber":"4841",
    "addr:postcode":"44240",
    "addr:street":"State Rte 43",
    "iso:country":"US",
    "sg:address":"4841 State Rte 43",
    "sg:city":"Kent",
    "sg:classifiers":[
        {
            "category":"Autos & Motor Vehicles",
            "subcategory":"Automobile Sales",
            "type":"Retail Goods"
        }
    ],
    "sg:phone":"+1 330 673 3133",
    "sg:postcode":"44240",
    "sg:province":"OH",
    "sg:tags":[
        "car",
        "dealer"
    ],
    "wof:name":"Portage Motors",
    "wof:placetype":"venue"
},
  "geometry": {"coordinates":[-81.348024,41.123394],"type":"Point"}
}