{
  "type": "Feature",
  "properties": {
    "addr:full":"20108 Kylemore Dr Strongsville OH 44149",
    "addr:postcode":"20108;44149",
    "addr:street":"Kylemore Dr",
    "iso:country":"US",
    "sg:address":"20108 Kylemore Dr",
    "sg:city":"Strongsville",
    "sg:classifiers":[
        {
            "category":"Professional",
            "type":"Services"
        }
    ],
    "sg:phone":"+1 440 878 1685",
    "sg:postcode":"44149",
    "sg:province":"OH",
    "sg:tags":[
        "establishment"
    ],
    "wof:name":"CTRL Systems",
    "wof:placetype":"venue"
},
  "geometry": {"coordinates":[-81.846982,41.279361],"type":"Point"}
}