{
  "type": "Feature",
  "properties": {
    "addr:full": "9716 Barrows Rd Huron OH 44839",
    "addr:housenumber": "9716",
    "addr:postcode": "44839",
    "addr:street": "Barrows Rd",
    "iso:country": "US",
    "sg:address": "9716 Barrows Rd",
    "sg:city": "Huron",
    "sg:classifiers": [
      {
        "category": "Manufacturing",
        "subcategory": "Building Materials",
        "type": "Manufacturing \u0026 Wholesale Goods"
      }
    ],
    "sg:phone": "+1 419 433 8005",
    "sg:postcode": "44839",
    "sg:province": "OH",
    "sg:tags": [
      "manufacture",
      "wooden",
      "kitchen",
      "custom",
      "cabinet"
    ],
    "wof:name": "Traditional Wood Designs",
    "wof:placetype": "venue"
  },
  "geometry": {"coordinates":[-82.517757,41.348871],"type":"Point"}
}
