{
  "type": "Feature",
  "properties": {
    "addr:full": "573 Williamsburg Ct Cincinnati OH 45244",
    "addr:housenumber": "573",
    "addr:postcode": "45244",
    "addr:street": "Williamsburg Ct",
    "iso:country": "US",
    "sg:address": "573 Williamsburg Ct",
    "sg:city": "Cincinnati",
    "sg:classifiers": [
      {
        "category": "Banks \u0026 Credit Unions",
        "subcategory": "Bank",
        "type": "Services"
      }
    ],
    "sg:phone": "+1 513 528 3051",
    "sg:postcode": "45244",
    "sg:province": "OH",
    "sg:tags": [
      "mortgage"
    ],
    "wof:name": "1st Citi Mortgage Corp",
    "wof:placetype": "venue"
  },
  "geometry": {"coordinates":[-84.292692,39.127239],"type":"Point"}
}
