{
  "type": "Feature",
  "properties": {
    "addr:full":"2024 W Schaaf Rd Cleveland OH 44109",
    "addr:housenumber":"2024",
    "addr:postcode":"44109",
    "addr:street":"W Schaaf Rd",
    "iso:country":"US",
    "sg:address":"2024 W Schaaf Rd",
    "sg:city":"Cleveland",
    "sg:classifiers":[
        {
            "category":"Organizations",
            "subcategory":"Membership Organization",
            "type":"Services"
        }
    ],
    "sg:phone":"+1 216 741 2483",
    "sg:postcode":"44109",
    "sg:province":"OH",
    "sg:tags":[
        "athletic"
    ],
    "wof:name":"Cleveland Lions Afc Inc",
    "wof:placetype":"venue"
},
  "geometry": {"coordinates":[-81.69698099999999,41.429524],"type":"Point"}
}