{
  "type": "Feature",
  "properties": {
    "addr:full":"2414 Locust St S Canal Fulton OH 44614",
    "addr:housenumber":"2414",
    "addr:postcode":"44614",
    "addr:street":"Locust St S",
    "iso:country":"US",
    "sg:address":"2414 Locust St S",
    "sg:city":"Canal Fulton",
    "sg:classifiers":[
        {
            "category":"Banks & Credit Unions",
            "subcategory":"Bank",
            "type":"Services"
        }
    ],
    "sg:phone":"+1 330 854 1022",
    "sg:postcode":"44614",
    "sg:province":"OH",
    "wof:name":"Apple Creek Banking Co the",
    "wof:placetype":"venue"
},
  "geometry": {"coordinates":[-81.570099,40.882301],"type":"Point"}
}