{
  "type": "Feature",
  "properties": {
    "addr:full": "1551 W River Rd N Elyria OH 44035",
    "addr:housenumber": "1551",
    "addr:postcode": "44035",
    "addr:street": "W River Rd N",
    "iso:country": "US",
    "sg:address": "1551 W River Rd N",
    "sg:city": "Elyria",
    "sg:classifiers": [
      {
        "category": "Professional",
        "subcategory": "Lawyer \u0026 Legal Services",
        "type": "Services"
      }
    ],
    "sg:phone": "+1 440 324 5353",
    "sg:postcode": "44035",
    "sg:province": "OH",
    "sg:tags": [
      "attorney"
    ],
    "wof:name": "Spike Meckler \u0026 Brill Illner",
    "wof:placetype": "venue"
  },
  "geometry": {"coordinates":[-82.106595,41.394836],"type":"Point"}
}
