{
  "type": "Feature",
  "properties": {
    "addr:full": "1561 E 40th St Cleveland OH 44103",
    "addr:housenumber": "1561",
    "addr:postcode": "44103",
    "addr:street": "E 40Th St",
    "iso:country": "US",
    "sg:address": "1561 E 40th St",
    "sg:city": "Cleveland",
    "sg:classifiers": [
      {
        "category": "Building \u0026 Trades",
        "subcategory": "Cleaning \u0026 Sanitation",
        "type": "Services"
      }
    ],
    "sg:phone": "+1 216 881 8484",
    "sg:postcode": "44103",
    "sg:province": "OH",
    "sg:tags": [
      "janitor"
    ],
    "wof:name": "Ajax Cleaning Contractors",
    "wof:placetype": "venue"
  },
  "geometry": {"coordinates":[-81.659384,41.510751],"type":"Point"}
}
