{
  "type": "Feature",
  "properties": {
    "addr:full": "1167 Shangrila Dr Cincinnati OH 45230",
    "addr:housenumber": "1167",
    "addr:postcode": "45230",
    "addr:street": "Shangrila Dr",
    "iso:country": "US",
    "sg:address": "1167 Shangrila Dr",
    "sg:city": "Cincinnati",
    "sg:classifiers": [
      {
        "category": "Shopping",
        "subcategory": "Jewelry",
        "type": "Retail Goods"
      }
    ],
    "sg:phone": "+1 513 231 4239",
    "sg:postcode": "45230",
    "sg:province": "OH",
    "wof:name": "Proctor Martha H",
    "wof:placetype": "venue"
  },
  "geometry": {"coordinates":[-84.353493,39.070864],"type":"Point"}
}
