{
  "type": "Feature",
  "properties": {
    "iso:country":"US",
    "sg:address":"487 W Johnstown Rd",
    "sg:city":"Gahanna",
    "sg:classifiers":[
        {
            "category":"Professional",
            "subcategory":"Business Services",
            "type":"Services"
        }
    ],
    "sg:phone":"+1 614 226 3539",
    "sg:postcode":"43230",
    "sg:province":"OH",
    "sg:tags":[
        "interior",
        "consultant",
        "design",
        "decorator"
    ],
    "wof:name":"Sullivan Interiors",
    "wof:placetype":"venue"
},
  "geometry": {"coordinates":[-82.89448299999999,40.014025],"type":"Point"}
}