{
  "type": "Feature",
  "properties": {
    "addr:full":"943 S Clayton Rd New Lebanon OH 45345",
    "addr:housenumber":"943",
    "addr:postcode":"45345",
    "addr:street":"S Clayton Rd",
    "iso:country":"US",
    "sg:address":"943 S Clayton Rd",
    "sg:city":"New Lebanon",
    "sg:classifiers":[
        {
            "category":"Shopping",
            "subcategory":"Beauty & Cosmetics",
            "type":"Retail Goods"
        }
    ],
    "sg:phone":"+1 937 687 3008",
    "sg:postcode":"45345",
    "sg:province":"OH",
    "sg:tags":[
        "merchandise"
    ],
    "wof:name":"Rebecca Cummins",
    "wof:placetype":"venue"
},
  "geometry": {"coordinates":[-84.395188,39.730984],"type":"Point"}
}