{
  "type": "Feature",
  "properties": {
    "addr:full": "5219 Woodville Pike Urbana OH 43078",
    "addr:housenumber": "5219",
    "addr:postcode": "43078",
    "addr:street": "Woodville Pike",
    "iso:country": "US",
    "sg:address": "5219 Woodville Pike",
    "sg:city": "Urbana",
    "sg:classifiers": [
      {
        "category": "Manufacturing",
        "subcategory": "Metals",
        "type": "Manufacturing \u0026 Wholesale Goods"
      }
    ],
    "sg:phone": "+1 937 362 2854",
    "sg:postcode": "43078",
    "sg:province": "OH",
    "sg:tags": [
      "plate",
      "work",
      "fabricated",
      "mfg"
    ],
    "wof:name": "Fine Liners Etc",
    "wof:placetype": "venue"
  },
  "geometry": {"coordinates":[-83.85854,40.176575],"type":"Point"}
}
