{
  "type": "Feature",
  "properties": {
    "addr:full": "4423 Nebo Rd Patriot OH 45658",
    "addr:housenumber": "4423",
    "addr:postcode": "45658",
    "addr:street": "Nebo Rd",
    "iso:country": "US",
    "sg:address": "4423 Nebo Rd",
    "sg:city": "Patriot",
    "sg:classifiers": [
      {
        "category": "Organizations",
        "subcategory": "Religious Organization",
        "type": "Services"
      }
    ],
    "sg:phone": "+1 740 379 2616",
    "sg:postcode": "45658",
    "sg:province": "OH",
    "sg:tags": [
      "church"
    ],
    "wof:name": "Salem Baptist Church",
    "wof:placetype": "venue"
  },
  "geometry": {"coordinates":[-82.407458,38.804423],"type":"Point"}
}
