{
  "type": "Feature",
  "properties": {
    "addr:full":"534 Janet Dr Canfield OH 44406",
    "addr:housenumber":"534",
    "addr:postcode":"44406",
    "addr:street":"Janet Dr",
    "iso:country":"US",
    "sg:address":"534 Janet Dr",
    "sg:city":"Canfield",
    "sg:classifiers":[
        {
            "category":"Building & Trades",
            "subcategory":"Construction",
            "type":"Services"
        }
    ],
    "sg:phone":"+1 330 533 8453",
    "sg:postcode":"44406",
    "sg:province":"OH",
    "sg:tags":[
        "contractor"
    ],
    "wof:name":"Torella Tile Co",
    "wof:placetype":"venue"
},
  "geometry": {"coordinates":[-80.74757099999999,41.019879],"type":"Point"}
}