{
  "type": "Feature",
  "properties": {
    "iso:country":"US",
    "sg:address":"5733 Emporium Sq",
    "sg:city":"Columbus",
    "sg:phone":"+1 614 899 2029",
    "sg:postcode":"43231",
    "sg:province":"OH",
    "sg:website":"http://www.fashionbug.com",
    "wof:name":"Fashion Bug",
    "wof:placetype":"venue"
},
  "geometry": {"coordinates":[-82.94736899999999,40.085649],"type":"Point"}
}