{
  "type": "Feature",
  "properties": {
    "addr:full": "5733 Emporium Sq Columbus OH 43231",
    "addr:postcode": "43231",
    "addr:street": "Sq",
    "iso:country": "US",
    "sg:address": "5733 Emporium Sq",
    "sg:city": "Columbus",
    "sg:phone": "+1 614 899 2029",
    "sg:postcode": "43231",
    "sg:province": "OH",
    "sg:website": "http://www.fashionbug.com",
    "wof:name": "Fashion Bug",
    "wof:placetype": "venue"
  },
  "geometry": {"coordinates":[-82.947369,40.085649],"type":"Point"}
}
