{
  "type": "Feature",
  "properties": {
    "addr:full": "669 Broadway Lorain OH 44052",
    "addr:housenumber": "669",
    "addr:postcode": "44052",
    "addr:street": "Broadway",
    "iso:country": "US",
    "sg:address": "669 Broadway",
    "sg:city": "Lorain",
    "sg:classifiers": [
      {
        "category": "Personal",
        "subcategory": "Beauty Salon",
        "type": "Services"
      }
    ],
    "sg:phone": "+1 440 244 4282",
    "sg:postcode": "44052",
    "sg:province": "OH",
    "sg:tags": [
      "shop",
      "school"
    ],
    "wof:name": "Northern Inst of Cosmetology",
    "wof:placetype": "venue"
  },
  "geometry": {"coordinates":[-82.17489,41.465654],"type":"Point"}
}
