{
  "type": "Feature",
  "properties": {
    "addr:full": "700 Broadway Ave Cleveland OH 44146",
    "addr:housenumber": "700",
    "addr:postcode": "44146",
    "addr:street": "Broadway Ave",
    "iso:country": "US",
    "sg:address": "700 Broadway Ave",
    "sg:city": "Cleveland",
    "sg:classifiers": [
      {
        "category": "Professional",
        "subcategory": "Advertising",
        "type": "Services"
      }
    ],
    "sg:phone": "+1 216 246 2519",
    "sg:postcode": "44146",
    "sg:province": "OH",
    "sg:tags": [
      "guide"
    ],
    "wof:name": "Lorain County Phone Directory",
    "wof:placetype": "venue"
  },
  "geometry": {"coordinates":[-81.534721,41.390804],"type":"Point"}
}
