{
  "type": "Feature",
  "properties": {
    "addr:full":"2102 Garden Dr Wickliffe OH 44092",
    "addr:housenumber":"2102",
    "addr:postcode":"44092",
    "addr:street":"Garden Dr",
    "iso:country":"US",
    "sg:address":"2102 Garden Dr",
    "sg:city":"Wickliffe",
    "sg:classifiers":[
        {
            "category":"Banks & Credit Unions",
            "subcategory":"Financial Services",
            "type":"Services"
        }
    ],
    "sg:phone":"+1 440 944 1359",
    "sg:postcode":"44092",
    "sg:province":"OH",
    "sg:tags":[
        "investor"
    ],
    "wof:name":"Kish Investments LLC",
    "wof:placetype":"venue"
},
  "geometry": {"coordinates":[-81.45564400000001,41.604765],"type":"Point"}
}