{
  "type": "Feature",
  "properties": {
    "addr:full": "124 W Main St Mc Arthur OH 45651",
    "addr:housenumber": "124",
    "addr:postcode": "45651",
    "addr:street": "W Main St",
    "iso:country": "US",
    "sg:address": "124 W Main St",
    "sg:city": "Mc Arthur",
    "sg:classifiers": [
      {
        "category": "Utilities",
        "subcategory": "Water",
        "type": "Services"
      }
    ],
    "sg:phone": "+1 740 596 4060",
    "sg:postcode": "45651",
    "sg:province": "OH",
    "sg:tags": [
      "executive",
      "supply"
    ],
    "wof:name": "Village McArthur Water Dept",
    "wof:placetype": "venue"
  },
  "geometry": {"coordinates":[-82.479288,39.246584],"type":"Point"}
}
