{
  "type": "Feature",
  "properties": {
    "addr:full": "617 W Center St Marion OH 43302",
    "addr:housenumber": "617",
    "addr:postcode": "43302",
    "addr:street": "W Center St",
    "iso:country": "US",
    "sg:address": "617 W Center St",
    "sg:city": "Marion",
    "sg:classifiers": [
      {
        "category": "Freight",
        "type": "Transportation"
      }
    ],
    "sg:phone": "+1 740 223 0822",
    "sg:postcode": "43302",
    "sg:province": "OH",
    "sg:tags": [
      "operator",
      "trucking"
    ],
    "wof:name": "Newman Trucking",
    "wof:placetype": "venue"
  },
  "geometry": {"coordinates":[-83.141877,40.588545],"type":"Point"}
}
