{
  "type": "Feature",
  "properties": {
    "iso:country":"US",
    "sg:address":"1700 Ann St",
    "sg:city":"Columbus",
    "sg:classifiers":[
        {
            "category":"Recreation",
            "type":"Entertainment"
        }
    ],
    "sg:phone":"+1 614 645 3058",
    "sg:postcode":"43207",
    "sg:province":"OH",
    "sg:tags":[
        "pool",
        "swimming"
    ],
    "wof:name":"Lincoln Swimming Pool",
    "wof:placetype":"venue"
},
  "geometry": {"coordinates":[-82.98132,39.928885],"type":"Point"}
}