{
  "type": "Feature",
  "properties": {
    "addr:full":"38296 Colorado Ave Avon OH 44011",
    "addr:housenumber":"38296",
    "addr:postcode":"44011",
    "addr:street":"Colorado Ave",
    "iso:country":"US",
    "sg:address":"38296 Colorado Ave",
    "sg:city":"Avon",
    "sg:classifiers":[
        {
            "category":"Retail",
            "subcategory":"Auto Repair",
            "type":"Services"
        }
    ],
    "sg:phone":"+1 440 934 3807",
    "sg:postcode":"44011",
    "sg:province":"OH",
    "sg:tags":[
        "automobile",
        "lubrication"
    ],
    "wof:name":"Valvoline Instant Oil Change",
    "wof:placetype":"venue"
},
  "geometry": {"coordinates":[-82.04544300000001,41.45974],"type":"Point"}
}