{
  "type": "Feature",
  "properties": {
    "iso:country":"US",
    "sg:address":"39300 Deersville Ridge Rd",
    "sg:city":"Cadiz",
    "sg:classifiers":[
        {
            "category":"Organizations",
            "subcategory":"Religious Organization",
            "type":"Services"
        }
    ],
    "sg:phone":"+1 740 942 2660",
    "sg:postcode":"43907",
    "sg:province":"OH",
    "sg:tags":[
        "church"
    ],
    "wof:name":"Parish Church",
    "wof:placetype":"venue"
},
  "geometry": {"coordinates":[-81.06402799999999,40.28458],"type":"Point"}
}