{
  "type": "Feature",
  "properties": {
    "addr:full": "6645 Western Row Rd Mason OH 45040",
    "addr:housenumber": "6645",
    "addr:postcode": "45040",
    "addr:street": "Western Row Rd",
    "iso:country": "US",
    "sg:address": "6645 Western Row Rd",
    "sg:city": "Mason",
    "sg:classifiers": [
      {
        "category": "Restaurant",
        "type": "Food \u0026 Drink"
      }
    ],
    "sg:phone": "+1 513 573 9003",
    "sg:postcode": "45040",
    "sg:province": "OH",
    "sg:tags": [
      "eating"
    ],
    "sg:website": "www.skyline.com",
    "wof:name": "Skyline Chili Inc",
    "wof:placetype": "venue"
  },
  "geometry": {"coordinates":[-84.33101,39.337279],"type":"Point"}
}
