{
  "type": "Feature",
  "properties": {
    "addr:full": "163 Vesper Dr Akron OH 44310",
    "addr:housenumber": "163",
    "addr:postcode": "44310",
    "addr:street": "Vesper Dr",
    "iso:country": "US",
    "sg:address": "163 Vesper Dr",
    "sg:city": "Akron",
    "sg:classifiers": [
      {
        "category": "Organizations",
        "subcategory": "Religious Organization",
        "type": "Services"
      }
    ],
    "sg:phone": "+1 330 535 6317",
    "sg:postcode": "44310",
    "sg:province": "OH",
    "sg:tags": [
      "clergy"
    ],
    "wof:name": "Norman Holmes",
    "wof:placetype": "venue"
  },
  "geometry": {"coordinates":[-81.521921,41.100474],"type":"Point"}
}
