{
  "type": "Feature",
  "properties": {
    "iso:country":"US",
    "sg:address":"163 Vesper Dr",
    "sg:city":"Akron",
    "sg:classifiers":[
        {
            "category":"Organizations",
            "subcategory":"Religious Organization",
            "type":"Services"
        }
    ],
    "sg:phone":"+1 330 535 6317",
    "sg:postcode":"44310",
    "sg:province":"OH",
    "sg:tags":[
        "clergy"
    ],
    "wof:name":"Norman Holmes",
    "wof:placetype":"venue"
},
  "geometry": {"coordinates":[-81.52192100000001,41.100474],"type":"Point"}
}