{
  "type": "Feature",
  "properties": {
    "addr:full":"2700 E Dublin Granville Rd Columbus OH 43231",
    "addr:housenumber":"2700",
    "addr:postcode":"43231",
    "addr:street":"E Dublin Granville Rd",
    "iso:country":"US",
    "sg:address":"2700 E Dublin Granville Rd",
    "sg:city":"Columbus",
    "sg:classifiers":[
        {
            "category":"Professional",
            "subcategory":"Management & Consulting",
            "type":"Services"
        }
    ],
    "sg:phone":"+1 614 895 3605",
    "sg:postcode":"43231",
    "sg:province":"OH",
    "sg:tags":[
        "consultant",
        "business"
    ],
    "wof:name":"Geo Quip",
    "wof:placetype":"venue"
},
  "geometry": {"coordinates":[-82.948172,40.084612],"type":"Point"}
}