{
  "type": "Feature",
  "properties": {
    "addr:full": "3140 Lick Run Rd Chillicothe OH 45601",
    "addr:postcode": "3140;45601",
    "addr:street": "Lick Run Rd",
    "iso:country": "US",
    "sg:address": "3140 Lick Run Rd",
    "sg:city": "Chillicothe",
    "sg:classifiers": [
      {
        "category": "Government",
        "subcategory": "Fire Station",
        "type": "Public Place"
      }
    ],
    "sg:phone": "+1 740 775 9105",
    "sg:postcode": "45601",
    "sg:province": "OH",
    "sg:tags": [
      "protection"
    ],
    "wof:name": "Fire Dept",
    "wof:placetype": "venue"
  },
  "geometry": {"coordinates":[-82.910123,39.350563],"type":"Point"}
}
