{
  "type": "Feature",
  "properties": {
    "addr:full": "2067 W 41st St Cleveland OH 44113",
    "addr:housenumber": "2067",
    "addr:postcode": "44113",
    "addr:street": "W 41St St",
    "iso:country": "US",
    "sg:address": "2067 W 41st St",
    "sg:city": "Cleveland",
    "sg:classifiers": [
      {
        "category": "Manufacturing",
        "subcategory": "Rubber \u0026 Plastics",
        "type": "Manufacturing \u0026 Wholesale Goods"
      }
    ],
    "sg:phone": "+1 216 651 3330",
    "sg:postcode": "44113",
    "sg:province": "OH",
    "sg:tags": [
      "product",
      "mfg"
    ],
    "wof:name": "Ray-Craft Inc",
    "wof:placetype": "venue"
  },
  "geometry": {"coordinates":[-81.713389,41.477968],"type":"Point"}
}
