{
  "type": "Feature",
  "properties": {
    "addr:full": "9603 Co Rd 89 Alger OH 45812",
    "addr:housenumber": "9603",
    "addr:postcode": "45812",
    "addr:street": "Co Rd 89",
    "iso:country": "US",
    "sg:address": "9603 Co Rd 89",
    "sg:city": "Alger",
    "sg:classifiers": [
      {
        "category": "Freight",
        "type": "Transportation"
      }
    ],
    "sg:phone": "+1 419 675 2655",
    "sg:postcode": "45812",
    "sg:province": "OH",
    "sg:tags": [
      "grain",
      "elevator"
    ],
    "wof:name": "Foraker Elevator",
    "wof:placetype": "venue"
  },
  "geometry": {"coordinates":[-83.74142,40.677691],"type":"Point"}
}
