{
  "type": "Feature",
  "properties": {
    "iso:country":"US",
    "sg:address":"9603 Co Rd 89",
    "sg:city":"Alger",
    "sg:classifiers":[
        {
            "category":"Freight",
            "type":"Transportation"
        }
    ],
    "sg:phone":"+1 419 675 2655",
    "sg:postcode":"45812",
    "sg:province":"OH",
    "sg:tags":[
        "grain",
        "elevator"
    ],
    "wof:name":"Foraker Elevator",
    "wof:placetype":"venue"
},
  "geometry": {"coordinates":[-83.74142000000001,40.677691],"type":"Point"}
}