{
  "type": "Feature",
  "properties": {
    "addr:full": "8 N State St Painesville OH 44077",
    "addr:housenumber": "8",
    "addr:postcode": "44077",
    "addr:street": "N State St",
    "iso:country": "US",
    "sg:address": "8 N State St",
    "sg:city": "Painesville",
    "sg:classifiers": [
      {
        "category": "Insurance",
        "subcategory": "Insurance Agent",
        "type": "Services"
      }
    ],
    "sg:phone": "+1 440 639 1900",
    "sg:postcode": "44077",
    "sg:province": "OH",
    "wof:name": "Allstate",
    "wof:placetype": "venue"
  },
  "geometry": {"coordinates":[-81.242317,41.727773],"type":"Point"}
}
