{
  "type": "Feature",
  "properties": {
    "addr:full":"2354 Wimbledon Park Blvd Toledo OH 43617",
    "addr:housenumber":"2354",
    "addr:postcode":"43617",
    "addr:street":"Wimbledon Park Blvd",
    "iso:country":"US",
    "sg:address":"2354 Wimbledon Park Blvd",
    "sg:city":"Toledo",
    "sg:classifiers":[
        {
            "category":"Professional",
            "subcategory":"Computer Services",
            "type":"Services"
        }
    ],
    "sg:phone":"+1 419 843 3310",
    "sg:postcode":"43617",
    "sg:province":"OH",
    "sg:tags":[
        "consultant",
        "designer"
    ],
    "wof:name":"N 8 Solutions Inc",
    "wof:placetype":"venue"
},
  "geometry": {"coordinates":[-83.71639,41.661885],"type":"Point"}
}