{
  "type": "Feature",
  "properties": {
    "iso:country":"US",
    "sg:address":"3095 Philothea Rd",
    "sg:city":"Coldwater",
    "sg:classifiers":[
        {
            "category":"Professional",
            "type":"Services"
        }
    ],
    "sg:phone":"+1 419 678 8544",
    "sg:postcode":"45828",
    "sg:province":"OH",
    "wof:name":"Roger A Homan",
    "wof:placetype":"venue"
},
  "geometry": {"coordinates":[-84.684465,40.450675],"type":"Point"}
}