{
  "type": "Feature",
  "properties": {
    "addr:full":"1116 Main St Grafton OH 44044",
    "addr:housenumber":"1116",
    "addr:postcode":"44044",
    "addr:street":"Main St",
    "iso:country":"US",
    "sg:address":"1116 Main St",
    "sg:city":"Grafton",
    "sg:classifiers":[
        {
            "category":"Manufacturing",
            "subcategory":"Signs",
            "type":"Manufacturing & Wholesale Goods"
        }
    ],
    "sg:phone":"+1 440 926 3749",
    "sg:postcode":"44044",
    "sg:province":"OH",
    "sg:tags":[
        "advertising",
        "specialty"
    ],
    "wof:name":"All Kinds Of Signs",
    "wof:placetype":"venue"
},
  "geometry": {"coordinates":[-82.05015299999999,41.267873],"type":"Point"}
}