{
  "type": "Feature",
  "properties": {
    "addr:full":"1055 Rombach Ave Wilmington OH 45177",
    "addr:housenumber":"1055",
    "addr:postcode":"45177",
    "addr:street":"Rombach Ave",
    "iso:country":"US",
    "sg:address":"1055 Rombach Ave",
    "sg:city":"Wilmington",
    "sg:classifiers":[
        {
            "category":"Restaurant",
            "type":"Food & Drink"
        }
    ],
    "sg:phone":"+1 937 382 1340",
    "sg:postcode":"45177",
    "sg:province":"OH",
    "sg:tags":[
        "eating"
    ],
    "wof:name":"Wendys",
    "wof:placetype":"venue"
},
  "geometry": {"coordinates":[-83.81057300000001,39.447531],"type":"Point"}
}