{
  "type": "Feature",
  "properties": {
    "addr:full": "11154 Lincoln St SE Canton OH 44670",
    "addr:housenumber": "11154",
    "addr:postcode": "44670",
    "addr:street": "Lincoln St Se",
    "iso:country": "US",
    "sg:address": "11154 Lincoln St SE",
    "sg:city": "Canton",
    "sg:classifiers": [
      {
        "category": "Farming",
        "subcategory": "Nursery",
        "type": "Manufacturing \u0026 Wholesale Goods"
      }
    ],
    "sg:phone": "+1 330 862 2922",
    "sg:postcode": "44670",
    "sg:province": "OH",
    "sg:tags": [
      "greenhouse"
    ],
    "wof:name": "Clapper's Greenhouse",
    "wof:placetype": "venue"
  },
  "geometry": {"coordinates":[-81.193969,40.762558],"type":"Point"}
}
