{
  "type": "Feature",
  "properties": {
    "iso:country":"US",
    "sg:address":"43 Grove Ave",
    "sg:city":"Painesville",
    "sg:classifiers":[
        {
            "category":"Professional",
            "type":"Services"
        }
    ],
    "sg:phone":"+1 440 357 6429",
    "sg:postcode":"44077",
    "sg:province":"OH",
    "wof:name":"Loretta A Bartish",
    "wof:placetype":"venue"
},
  "geometry": {"coordinates":[-81.21227,41.727907],"type":"Point"}
}