{
  "type": "Feature",
  "properties": {
    "addr:full": "3761 Burbank Rd Wooster OH 44691",
    "addr:housenumber": "3761",
    "addr:postcode": "44691",
    "addr:street": "Burbank Rd",
    "iso:country": "US",
    "sg:address": "3761 Burbank Rd",
    "sg:city": "Wooster",
    "sg:classifiers": [
      {
        "category": "Shopping",
        "subcategory": "Stationery \u0026 Office Supplies",
        "type": "Retail Goods"
      }
    ],
    "sg:phone": "+1 330 345 4320",
    "sg:postcode": "44691",
    "sg:province": "OH",
    "wof:name": "Staples The Office Superstore",
    "wof:placetype": "venue"
  },
  "geometry": {"coordinates":[-81.942525,40.84357],"type":"Point"}
}
