{
  "type": "Feature",
  "properties": {
    "addr:full": "130 E Walnut St Westerville OH 43081",
    "addr:housenumber": "130",
    "addr:postcode": "43081",
    "addr:street": "E Walnut St",
    "iso:country": "US",
    "sg:address": "130 E Walnut St",
    "sg:city": "Westerville",
    "sg:classifiers": [
      {
        "category": "Social Services",
        "type": "Services"
      }
    ],
    "sg:phone": "+1 614 882 2697",
    "sg:postcode": "43081",
    "sg:province": "OH",
    "sg:tags": [
      "organization",
      "welfare"
    ],
    "wof:name": "YWCA",
    "wof:placetype": "venue"
  },
  "geometry": {"coordinates":[-82.922125,40.121372],"type":"Point"}
}
