{
  "type": "Feature",
  "properties": {
    "iso:country":"US",
    "sg:address":"130 E Walnut St",
    "sg:city":"Westerville",
    "sg:classifiers":[
        {
            "category":"Social Services",
            "type":"Services"
        }
    ],
    "sg:phone":"+1 614 882 2697",
    "sg:postcode":"43081",
    "sg:province":"OH",
    "sg:tags":[
        "organization",
        "welfare"
    ],
    "wof:name":"YWCA",
    "wof:placetype":"venue"
},
  "geometry": {"coordinates":[-82.92212499999999,40.121372],"type":"Point"}
}