{
  "type": "Feature",
  "properties": {
    "addr:full": "40 E 3rd St Ashland OH 44805",
    "addr:housenumber": "40",
    "addr:postcode": "44805",
    "addr:street": "E 3Rd St",
    "iso:country": "US",
    "sg:address": "40 E 3rd St",
    "sg:city": "Ashland",
    "sg:classifiers": [
      {
        "category": "Social Services",
        "type": "Services"
      }
    ],
    "sg:phone": "+1 419 281 8001",
    "sg:postcode": "44805",
    "sg:province": "OH",
    "sg:tags": [
      "organization",
      "welfare"
    ],
    "sg:website": "www.salvationarmy.org",
    "wof:name": "Salvation Army",
    "wof:placetype": "venue"
  },
  "geometry": {"coordinates":[-82.314902,40.86986],"type":"Point"}
}
