{
  "type": "Feature",
  "properties": {
    "addr:full": "8503 Rockefeller Ln Northfield OH 44067",
    "addr:housenumber": "8503",
    "addr:postcode": "44067",
    "addr:street": "Rockefeller Ln",
    "iso:country": "US",
    "sg:address": "8503 Rockefeller Ln",
    "sg:city": "Northfield",
    "sg:classifiers": [
      {
        "category": "Wholesale",
        "subcategory": "Metals \u0026 Minerals",
        "type": "Manufacturing \u0026 Wholesale Goods"
      }
    ],
    "sg:phone": "+1 330 468 2279",
    "sg:postcode": "44067",
    "sg:province": "OH",
    "sg:tags": [
      "steel",
      "warehouse"
    ],
    "wof:name": "Braline Steel",
    "wof:placetype": "venue"
  },
  "geometry": {"coordinates":[-81.564499,41.342712],"type":"Point"}
}
