{
  "type": "Feature",
  "properties": {
    "addr:full":"25 Public Sq Willoughby OH 44094",
    "addr:housenumber":"25",
    "addr:postcode":"44094",
    "addr:street":"Public Sq",
    "iso:country":"US",
    "sg:address":"25 Public Sq",
    "sg:city":"Willoughby",
    "sg:classifiers":[
        {
            "category":"Education",
            "subcategory":"School",
            "type":"Public Place"
        }
    ],
    "sg:phone":"+1 440 946 7085",
    "sg:postcode":"44094",
    "sg:province":"OH",
    "sg:tags":[
        "high",
        "vocational"
    ],
    "wof:name":"Willoughby Eastlake Tech Bldg",
    "wof:placetype":"venue"
},
  "geometry": {"coordinates":[-81.405424,41.639618],"type":"Point"}
}