{
  "type": "Feature",
  "properties": {
    "addr:full": "13144 Gar Hwy Chardon OH 44024",
    "addr:housenumber": "13144",
    "addr:postcode": "44024",
    "addr:street": "Gar Hwy",
    "iso:country": "US",
    "sg:address": "13144 Gar Hwy",
    "sg:city": "Chardon",
    "sg:classifiers": [
      {
        "category": "Retail",
        "subcategory": "Auto Repair",
        "type": "Services"
      }
    ],
    "sg:phone": "+1 440 285 3755",
    "sg:postcode": "44024",
    "sg:province": "OH",
    "sg:tags": [
      "body",
      "automobile",
      "painting"
    ],
    "wof:name": "Farinacci Auto Body",
    "wof:placetype": "venue"
  },
  "geometry": {"coordinates":[-81.168701,41.594028],"type":"Point"}
}
