{
  "type": "Feature",
  "properties": {
    "addr:full":"11914 Henia Cir Cleveland OH 44125",
    "addr:housenumber":"11914",
    "addr:postcode":"44125",
    "addr:street":"Henia Cir",
    "iso:country":"US",
    "sg:address":"11914 Henia Cir",
    "sg:city":"Cleveland",
    "sg:classifiers":[
        {
            "category":"Building & Trades",
            "subcategory":"Construction",
            "type":"Services"
        }
    ],
    "sg:phone":"+1 216 518 1467",
    "sg:postcode":"44125",
    "sg:province":"OH",
    "sg:tags":[
        "concrete",
        "contractor"
    ],
    "wof:name":"Central Concrete Co",
    "wof:placetype":"venue"
},
  "geometry": {"coordinates":[-81.599475,41.425429],"type":"Point"}
}