{
  "type": "Feature",
  "properties": {
    "iso:country":"US",
    "sg:address":"11435 Cherry Ln",
    "sg:city":"Baltimore",
    "sg:classifiers":[
        {
            "category":"Farming",
            "subcategory":"Livestock Farm",
            "type":"Manufacturing & Wholesale Goods"
        }
    ],
    "sg:phone":"+1 740 862 8165",
    "sg:postcode":"43105",
    "sg:province":"OH",
    "sg:tags":[
        "beef",
        "feedlot",
        "cattle"
    ],
    "wof:name":"Charles McCandlish",
    "wof:placetype":"venue"
},
  "geometry": {"coordinates":[-82.58448,39.889732],"type":"Point"}
}