{
  "type": "Feature",
  "properties": {
    "iso:country":"US",
    "sg:address":"1212 S Front St",
    "sg:city":"Columbus",
    "sg:classifiers":[
        {
            "category":"Professional",
            "subcategory":"Computer Services",
            "type":"Services"
        }
    ],
    "sg:phone":"+1 614 358 9060",
    "sg:postcode":"43206",
    "sg:province":"OH",
    "sg:tags":[
        "home",
        "consulting",
        "page",
        "dev",
        "internet"
    ],
    "wof:name":"Virtual Office Ctr",
    "wof:placetype":"venue"
},
  "geometry": {"coordinates":[-82.997253,39.93553],"type":"Point"}
}