{
  "type": "Feature",
  "properties": {
    "iso:country":"US",
    "sg:address":"504 E Temple St",
    "sg:city":"Washington Ct Hs",
    "sg:classifiers":[
        {
            "category":"Organizations",
            "subcategory":"Religious Organization",
            "type":"Services"
        }
    ],
    "sg:phone":"+1 740 335 3039",
    "sg:postcode":"43160",
    "sg:province":"OH",
    "sg:tags":[
        "church"
    ],
    "wof:name":"Christian Science Society",
    "wof:placetype":"venue"
},
  "geometry": {"coordinates":[-83.438204,39.539851],"type":"Point"}
}