{
  "type": "Feature",
  "properties": {
    "addr:full":"7893 Meadowlark Ln S Reynoldsburg OH 43068",
    "addr:housenumber":"7893",
    "addr:postcode":"43068",
    "addr:street":"Meadowlark Ln S",
    "iso:country":"US",
    "sg:address":"7893 Meadowlark Ln S",
    "sg:city":"Reynoldsburg",
    "sg:classifiers":[
        {
            "category":"Building & Trades",
            "subcategory":"Construction",
            "type":"Services"
        }
    ],
    "sg:phone":"+1 614 864 9540",
    "sg:postcode":"43068",
    "sg:province":"OH",
    "sg:tags":[
        "house"
    ],
    "wof:name":"Hunt JD Builders",
    "wof:placetype":"venue"
},
  "geometry": {"coordinates":[-82.786722,39.940656],"type":"Point"}
}