{
  "type": "Feature",
  "properties": {
    "iso:country":"US",
    "sg:address":"6816 Lauffer Rd",
    "sg:city":"Columbus",
    "sg:classifiers":[
        {
            "category":"Manufacturing",
            "subcategory":"Tools & Machinery",
            "type":"Manufacturing & Wholesale Goods"
        }
    ],
    "sg:phone":"+1 614 848 4890",
    "sg:postcode":"43231",
    "sg:province":"OH",
    "sg:tags":[
        "instrument",
        "surgical"
    ],
    "sg:website":"www.zimmer.com",
    "wof:name":"Zimmer Inc",
    "wof:placetype":"venue"
},
  "geometry": {"coordinates":[-82.94645199999999,40.110357],"type":"Point"}
}