{
  "type": "Feature",
  "properties": {
    "addr:full": "1587 Golden Gate Plz Cleveland OH 44124",
    "addr:housenumber": "1587",
    "addr:postcode": "44124",
    "addr:street": "Golden Gate Plz",
    "iso:country": "US",
    "sg:address": "1587 Golden Gate Plz",
    "sg:city": "Cleveland",
    "sg:classifiers": [
      {
        "category": "Shopping",
        "subcategory": "Computers \u0026 Home Electronics",
        "type": "Retail Goods"
      }
    ],
    "sg:phone": "+1 440 720 1840",
    "sg:postcode": "44124",
    "sg:province": "OH",
    "sg:tags": [
      "software"
    ],
    "wof:name": "Funcoland",
    "wof:placetype": "venue"
  },
  "geometry": {"coordinates":[-81.449073,41.519384],"type":"Point"}
}
