{
  "type": "Feature",
  "properties": {
    "addr:full": "1304 W High St Bryan OH 43506",
    "addr:housenumber": "1304",
    "addr:postcode": "43506",
    "addr:street": "W High St",
    "iso:country": "US",
    "sg:address": "1304 W High St",
    "sg:city": "Bryan",
    "sg:classifiers": [
      {
        "category": "Health Services",
        "subcategory": "Chiropractor",
        "type": "Services"
      }
    ],
    "sg:phone": "+1 419 636 5279",
    "sg:postcode": "43506",
    "sg:province": "OH",
    "wof:name": "Andre Gaulard DC",
    "wof:placetype": "venue"
  },
  "geometry": {"coordinates":[-84.570667,41.474605],"type":"Point"}
}
