{
  "type": "Feature",
  "properties": {
    "iso:country":"US",
    "sg:address":"100 N Miller Rd",
    "sg:city":"Fairlawn",
    "sg:classifiers":[
        {
            "category":"Real Estate",
            "subcategory":"Real Estate Agent",
            "type":"Services"
        }
    ],
    "sg:phone":"+1 330 864 8090",
    "sg:postcode":"44333",
    "sg:province":"OH",
    "sg:tags":[
        "appraiser"
    ],
    "sg:website":"www.b-ankney.com",
    "wof:name":"Barry R Ankney Inc",
    "wof:placetype":"venue"
},
  "geometry": {"coordinates":[-81.60985100000001,41.1288],"type":"Point"}
}