{
  "type": "Feature",
  "properties": {
    "addr:full": "2092 Orr Rd Bloomville OH 44818",
    "addr:housenumber": "2092",
    "addr:postcode": "44818",
    "addr:street": "Orr Rd",
    "iso:country": "US",
    "sg:address": "2092 Orr Rd",
    "sg:city": "Bloomville",
    "sg:classifiers": [
      {
        "category": "Building \u0026 Trades",
        "subcategory": "Electrical",
        "type": "Services"
      }
    ],
    "sg:phone": "+1 419 284 2500",
    "sg:postcode": "44818",
    "sg:province": "OH",
    "sg:tags": [
      "electrical",
      "contractor"
    ],
    "wof:name": "Hieber Electric",
    "wof:placetype": "venue"
  },
  "geometry": {"coordinates":[-83.016495,40.935756],"type":"Point"}
}
