{
  "type": "Feature",
  "properties": {
    "iso:country":"US",
    "sg:address":"2092 Orr Rd",
    "sg:city":"Bloomville",
    "sg:classifiers":[
        {
            "category":"Building & Trades",
            "subcategory":"Electrical",
            "type":"Services"
        }
    ],
    "sg:phone":"+1 419 284 2500",
    "sg:postcode":"44818",
    "sg:province":"OH",
    "sg:tags":[
        "electrical",
        "contractor"
    ],
    "wof:name":"Hieber Electric",
    "wof:placetype":"venue"
},
  "geometry": {"coordinates":[-83.01649500000001,40.935756],"type":"Point"}
}