{
  "type": "Feature",
  "properties": {
    "addr:full": "6088 W 24th St Cleveland OH 44134",
    "addr:housenumber": "6088",
    "addr:postcode": "44134",
    "addr:street": "W 24Th St",
    "iso:country": "US",
    "sg:address": "6088 W 24th St",
    "sg:city": "Cleveland",
    "sg:classifiers": [
      {
        "category": "Building \u0026 Trades",
        "subcategory": "Construction",
        "type": "Services"
      }
    ],
    "sg:phone": "+1 216 351 7646",
    "sg:postcode": "44134",
    "sg:province": "OH",
    "sg:tags": [
      "special",
      "contractor"
    ],
    "wof:name": "Spectrum Painting",
    "wof:placetype": "venue"
  },
  "geometry": {"coordinates":[-81.698128,41.397015],"type":"Point"}
}
