{
  "type": "Feature",
  "properties": {
    "iso:country":"US",
    "sg:address":"7062 Hickory Ridge Rd",
    "sg:city":"Sylvania",
    "sg:classifiers":[
        {
            "category":"Professional",
            "type":"Services"
        }
    ],
    "sg:phone":"+1 419 882 0513",
    "sg:postcode":"43560",
    "sg:province":"OH",
    "wof:name":"Imaging Consultants Inc",
    "wof:placetype":"venue"
},
  "geometry": {"coordinates":[-83.71184,41.714249],"type":"Point"}
}