{
  "type": "Feature",
  "properties": {
    "iso:country":"US",
    "sg:address":"2995 Dresden St",
    "sg:city":"Columbus",
    "sg:classifiers":[
        {
            "category":"Professional",
            "type":"Services"
        }
    ],
    "sg:phone":"+1 614 267 5247",
    "sg:postcode":"43224",
    "sg:province":"OH",
    "wof:name":"Minemall Co",
    "wof:placetype":"venue"
},
  "geometry": {"coordinates":[-82.971093,40.027606],"type":"Point"}
}