{
  "type": "Feature",
  "properties": {
    "addr:full": "9834 Homer Rd Milford Center OH 43045",
    "addr:housenumber": "9834",
    "addr:postcode": "43045",
    "addr:street": "Homer Rd",
    "iso:country": "US",
    "sg:address": "9834 Homer Rd",
    "sg:city": "Milford Center",
    "sg:phone": "+1 937 349 4721",
    "sg:postcode": "43045",
    "sg:province": "OH",
    "sg:tags": [
      "beef",
      "farm",
      "cash",
      "grain",
      "cattle",
      "feedlot"
    ],
    "wof:name": "James Watkins Farm",
    "wof:placetype": "venue"
  },
  "geometry": {"coordinates":[-83.46398,40.147599],"type":"Point"}
}
