{
  "type": "Feature",
  "properties": {
    "iso:country":"US",
    "sg:address":"126 N Main St",
    "sg:city":"Lakeview",
    "sg:classifiers":[
        {
            "category":"Government",
            "subcategory":"Office",
            "type":"Public Place"
        }
    ],
    "sg:phone":"+1 937 843 2851",
    "sg:postcode":"43331",
    "sg:province":"OH",
    "sg:tags":[
        "village"
    ],
    "wof:name":"Lakeview Vlg Water & Light",
    "wof:placetype":"venue"
},
  "geometry": {"coordinates":[-83.924502,40.485008],"type":"Point"}
}