{
  "type": "Feature",
  "properties": {
    "iso:country":"US",
    "sg:address":"423 Marguerite Ave",
    "sg:city":"Cuyahoga Falls",
    "sg:classifiers":[
        {
            "category":"Professional",
            "type":"Services"
        }
    ],
    "sg:phone":"+1 330 928 0749",
    "sg:postcode":"44221",
    "sg:province":"OH",
    "wof:name":"Robin L Carpenter",
    "wof:placetype":"venue"
},
  "geometry": {"coordinates":[-81.474953,41.152699],"type":"Point"}
}