{
  "type": "Feature",
  "properties": {
    "iso:country":"US",
    "sg:address":"172 W High Ave",
    "sg:city":"New Philadelphia",
    "sg:classifiers":[
        {
            "category":"Government",
            "subcategory":"Office",
            "type":"Public Place"
        }
    ],
    "sg:phone":"+1 330 343 8875",
    "sg:postcode":"44663",
    "sg:province":"OH",
    "sg:tags":[
        "educational"
    ],
    "wof:name":"Area Office 7",
    "wof:placetype":"venue"
},
  "geometry": {"coordinates":[-81.44883,40.490066],"type":"Point"}
}