{
  "type": "Feature",
  "properties": {
    "iso:country":"US",
    "sg:address":"6025 Fairfield Rd",
    "sg:city":"Oxford",
    "sg:classifiers":[
        {
            "category":"Recreation",
            "type":"Entertainment"
        }
    ],
    "sg:phone":"+1 513 523 6314",
    "sg:postcode":"45056",
    "sg:province":"IN",
    "sg:tags":[
        "parks"
    ],
    "sg:website":"www.cityofoxford.org",
    "wof:name":"Oxford Recreation Dept",
    "wof:placetype":"venue"
},
  "geometry": {"coordinates":[-84.753264,39.50787],"type":"Point"}
}