{
  "type": "Feature",
  "properties": {
    "iso:country":"US",
    "sg:address":"7540 Lawyer Rd",
    "sg:city":"Cincinnati",
    "sg:classifiers":[
        {
            "category":"Real Estate",
            "subcategory":"Real Estate Agent",
            "type":"Services"
        }
    ],
    "sg:phone":"+1 513 231 2439",
    "sg:postcode":"45244",
    "sg:province":"OH",
    "wof:name":"Donald E Hadley",
    "wof:placetype":"venue"
},
  "geometry": {"coordinates":[-84.345586,39.100017],"type":"Point"}
}