{
  "type": "Feature",
  "properties": {
    "addr:full":"8715 Muirfield Dr Dublin OH 43017",
    "addr:housenumber":"8715",
    "addr:postcode":"43017",
    "addr:street":"Muirfield Dr",
    "iso:country":"US",
    "sg:address":"8715 Muirfield Dr",
    "sg:city":"Dublin",
    "sg:classifiers":[
        {
            "category":"Recreation",
            "type":"Entertainment"
        }
    ],
    "sg:phone":"+1 614 764 1714",
    "sg:postcode":"43017",
    "sg:province":"OH",
    "sg:tags":[
        "club",
        "country"
    ],
    "wof:name":"Country Club The",
    "wof:placetype":"venue"
},
  "geometry": {"coordinates":[-83.15399499999999,40.145632],"type":"Point"}
}