{
  "type": "Feature",
  "properties": {
    "addr:full": "2140 Larkspur Dr Lima OH 45807",
    "addr:housenumber": "2140",
    "addr:postcode": "45807",
    "addr:street": "Larkspur Dr",
    "iso:country": "US",
    "sg:address": "2140 Larkspur Dr",
    "sg:city": "Lima",
    "sg:classifiers": [
      {
        "category": "Building \u0026 Trades",
        "subcategory": "Construction",
        "type": "Services"
      }
    ],
    "sg:phone": "+1 419 339 8780",
    "sg:postcode": "45807",
    "sg:province": "OH",
    "sg:tags": [
      "house"
    ],
    "wof:name": "William B Warner",
    "wof:placetype": "venue"
  },
  "geometry": {"coordinates":[-84.192074,40.778928],"type":"Point"}
}
