{
  "type": "Feature",
  "properties": {
    "addr:full": "23800 Aurora Rd Bedford OH 44146",
    "addr:housenumber": "23800",
    "addr:postcode": "44146",
    "addr:street": "Aurora Rd",
    "iso:country": "US",
    "sg:address": "23800 Aurora Rd",
    "sg:city": "Bedford",
    "sg:classifiers": [
      {
        "category": "Manufacturing",
        "subcategory": "Furniture",
        "type": "Manufacturing \u0026 Wholesale Goods"
      },
      {
        "category": "Manufacturing",
        "subcategory": "Building Materials",
        "type": "Manufacturing \u0026 Wholesale Goods"
      }
    ],
    "sg:phone": "+1 440 439 0908",
    "sg:postcode": "44146",
    "sg:province": "OH",
    "sg:tags": [
      "top",
      "kitchen",
      "sink",
      "cabinet",
      "mfg"
    ],
    "wof:name": "New Image Kitchens \u0026 Baths Inc",
    "wof:placetype": "venue"
  },
  "geometry": {"coordinates":[-81.508328,41.413974],"type":"Point"}
}
