{
  "type": "Feature",
  "properties": {
    "addr:full": "4635 State Rte 286 Mount Orab OH 45154",
    "addr:housenumber": "4635;286",
    "addr:postcode": "45154",
    "addr:street": "State Rte;Mount",
    "iso:country": "US",
    "sg:address": "4635 State Rte 286",
    "sg:city": "Mount Orab",
    "sg:classifiers": [
      {
        "category": "Shopping",
        "subcategory": "Bicycles \u0026 Sporting Goods",
        "type": "Retail Goods"
      }
    ],
    "sg:phone": "+1 937 444 3052",
    "sg:postcode": "45154",
    "sg:province": "OH",
    "sg:tags": [
      "equipment",
      "rodeo",
      "roping"
    ],
    "wof:name": "Lone Star Ranch",
    "wof:placetype": "venue"
  },
  "geometry": {"coordinates":[-83.889318,39.104562],"type":"Point"}
}
