{
  "type": "Feature",
  "properties": {
    "iso:country":"US",
    "sg:address":"453 State Rte 7",
    "sg:city":"Gallipolis",
    "sg:classifiers":[
        {
            "category":"Personal",
            "subcategory":"Beauty Salon",
            "type":"Services"
        }
    ],
    "sg:phone":"+1 740 446 4597",
    "sg:postcode":"45631",
    "sg:province":"OH",
    "wof:name":"Hair Highlights",
    "wof:placetype":"venue"
},
  "geometry": {"coordinates":[-82.148206,38.841359],"type":"Point"}
}