{
  "type": "Feature",
  "properties": {
    "addr:full": "17 River St Chagrin Falls OH 44022",
    "addr:housenumber": "17",
    "addr:postcode": "44022",
    "addr:street": "River St",
    "iso:country": "US",
    "sg:address": "17 River St",
    "sg:city": "Chagrin Falls",
    "sg:classifiers": [
      {
        "category": "Restaurant",
        "type": "Food \u0026 Drink"
      }
    ],
    "sg:phone": "+1 440 893 0797",
    "sg:postcode": "44022",
    "sg:province": "OH",
    "sg:tags": [
      "new",
      "american"
    ],
    "sg:website": "www.jekyllskitchen.com",
    "wof:name": "Jekyll's Kitchen",
    "wof:placetype": "venue"
  },
  "geometry": {"coordinates":[-81.392865,41.431516],"type":"Point"}
}
