{
  "type": "Feature",
  "properties": {
    "addr:full": "30700 Bainbridge Rd Solon OH 44139",
    "addr:housenumber": "30700",
    "addr:postcode": "44139",
    "addr:street": "Bainbridge Rd",
    "iso:country": "US",
    "sg:address": "30700 Bainbridge Rd",
    "sg:city": "Solon",
    "sg:classifiers": [
      {
        "category": "Shopping",
        "subcategory": "Computers \u0026 Home Electronics",
        "type": "Retail Goods"
      }
    ],
    "sg:phone": "+1 440 542 9330",
    "sg:postcode": "44139",
    "sg:province": "OH",
    "wof:name": "Cyber Mag Computers",
    "wof:placetype": "venue"
  },
  "geometry": {"coordinates":[-81.461073,41.400589],"type":"Point"}
}
