{
  "type": "Feature",
  "properties": {
    "addr:full":"338 Co Rd 11 Bellefontaine OH 43311",
    "addr:housenumber":"338;11",
    "addr:postcode":"43311",
    "addr:street":"Co Rd",
    "iso:country":"US",
    "sg:address":"338 Co Rd 11",
    "sg:city":"Bellefontaine",
    "sg:classifiers":[
        {
            "category":"Government",
            "subcategory":"Office",
            "type":"Public Place"
        }
    ],
    "sg:phone":"+1 937 592 8896",
    "sg:postcode":"43311",
    "sg:province":"OH",
    "sg:tags":[
        "use",
        "program",
        "commodity",
        "related",
        "land"
    ],
    "wof:name":"Farm Service Agency",
    "wof:placetype":"venue"
},
  "geometry": {"coordinates":[-83.765557,40.346904],"type":"Point"}
}