{
  "type": "Feature",
  "properties": {
    "iso:country":"US",
    "sg:address":"815 Lawrence St",
    "sg:city":"Lancaster",
    "sg:classifiers":[
        {
            "category":"Manufacturing",
            "subcategory":"Textiles",
            "type":"Manufacturing & Wholesale Goods"
        }
    ],
    "sg:phone":"+1 740 653 1540",
    "sg:postcode":"43130",
    "sg:province":"OH",
    "sg:tags":[
        "coated",
        "fabric",
        "mfg"
    ],
    "wof:name":"Hexcel Advanced Composites",
    "wof:placetype":"venue"
},
  "geometry": {"coordinates":[-82.58751100000001,39.709825],"type":"Point"}
}