{
  "type": "Feature",
  "properties": {
    "addr:full": "210 13th St Malta OH 43758",
    "addr:housenumber": "210",
    "addr:postcode": "43758",
    "addr:street": "13Th St",
    "iso:country": "US",
    "sg:address": "210 13th St",
    "sg:city": "Malta",
    "sg:classifiers": [
      {
        "category": "Wholesale",
        "subcategory": "Scrap",
        "type": "Manufacturing \u0026 Wholesale Goods"
      }
    ],
    "sg:phone": "+1 740 962 3335",
    "sg:postcode": "43758",
    "sg:province": "OH",
    "sg:tags": [
      "recycling",
      "center"
    ],
    "wof:name": "Campbells Scrap Tire",
    "wof:placetype": "venue"
  },
  "geometry": {"coordinates":[-81.86859,39.656614],"type":"Point"}
}
