{
  "type": "Feature",
  "properties": {
    "addr:full": "101 Stonecrest Dr Marietta OH 45750",
    "addr:housenumber": "101",
    "addr:postcode": "45750",
    "addr:street": "Stonecrest Dr",
    "iso:country": "US",
    "sg:address": "101 Stonecrest Dr",
    "sg:city": "Marietta",
    "sg:classifiers": [
      {
        "category": "Insurance",
        "subcategory": "Insurance Agent",
        "type": "Services"
      }
    ],
    "sg:phone": "+1 740 374 7385",
    "sg:postcode": "45750",
    "sg:province": "OH",
    "wof:name": "Martin Insurance Agency Inc",
    "wof:placetype": "venue"
  },
  "geometry": {"coordinates":[-81.448011,39.444002],"type":"Point"}
}
