{
  "type": "Feature",
  "properties": {
    "iso:country":"US",
    "sg:address":"140 Rogers St",
    "sg:city":"Xenia",
    "sg:classifiers":[
        {
            "category":"Health Services",
            "subcategory":"Doctor",
            "type":"Services"
        }
    ],
    "sg:phone":"+1 937 382 6971",
    "sg:postcode":"45385",
    "sg:province":"OH",
    "sg:tags":[
        "dentist"
    ],
    "wof:name":"Hillside Dental",
    "wof:placetype":"venue"
},
  "geometry": {"coordinates":[-83.928082,39.675872],"type":"Point"}
}