{
  "type": "Feature",
  "properties": {
    "addr:full":"4016 Colby Ave Columbus OH 43227",
    "addr:housenumber":"4016",
    "addr:postcode":"43227",
    "addr:street":"Colby Ave",
    "iso:country":"US",
    "sg:address":"4016 Colby Ave",
    "sg:city":"Columbus",
    "sg:classifiers":[
        {
            "category":"Building & Trades",
            "subcategory":"Electrical",
            "type":"Services"
        }
    ],
    "sg:phone":"+1 614 774 9665",
    "sg:postcode":"43227",
    "sg:province":"OH",
    "sg:tags":[
        "electrical",
        "contractor"
    ],
    "wof:name":"New Wave Electric",
    "wof:placetype":"venue"
},
  "geometry": {"coordinates":[-82.88837599999999,39.946447],"type":"Point"}
}