{
  "type": "Feature",
  "properties": {
    "addr:full": "6599 Granger Rd Cleveland OH 44131",
    "addr:housenumber": "6599",
    "addr:postcode": "44131",
    "addr:street": "Granger Rd",
    "iso:country": "US",
    "sg:address": "6599 Granger Rd",
    "sg:city": "Cleveland",
    "sg:classifiers": [
      {
        "category": "Wholesale",
        "subcategory": "Office Equipment",
        "type": "Manufacturing \u0026 Wholesale Goods"
      }
    ],
    "sg:phone": "+1 216 642 9555",
    "sg:postcode": "44131",
    "sg:province": "OH",
    "sg:tags": [
      "machine",
      "duplicating",
      "copying"
    ],
    "sg:website": "www.acecopy.com",
    "wof:name": "Ace American Copy Equipment",
    "wof:placetype": "venue"
  },
  "geometry": {"coordinates":[-81.646963,41.414311],"type":"Point"}
}
