{
  "type": "Feature",
  "properties": {
    "iso:country":"US",
    "sg:address":"212 W Main St",
    "sg:city":"Cortland",
    "sg:classifiers":[
        {
            "category":"Professional",
            "subcategory":"Lawyer & Legal Services",
            "type":"Services"
        }
    ],
    "sg:phone":"+1 330 637 3906",
    "sg:postcode":"44410",
    "sg:province":"OH",
    "sg:tags":[
        "attorney"
    ],
    "wof:name":"Gessner & Platt",
    "wof:placetype":"venue"
},
  "geometry": {"coordinates":[-80.729147,41.330173],"type":"Point"}
}