{
  "type": "Feature",
  "properties": {
    "iso:country":"US",
    "sg:address":"31525 Bishops Gate Cir",
    "sg:city":"Cleveland",
    "sg:classifiers":[
        {
            "category":"Professional",
            "type":"Services"
        }
    ],
    "sg:phone":"+1 440 892 4782",
    "sg:postcode":"44145",
    "sg:province":"OH",
    "wof:name":"L Suter Svc Inc",
    "wof:placetype":"venue"
},
  "geometry": {"coordinates":[-81.96859499999999,41.434652],"type":"Point"}
}