{
  "type": "Feature",
  "properties": {
    "addr:full": "31525 Bishops Gate Cir Cleveland OH 44145",
    "addr:postcode": "31525;44145",
    "addr:street": "Bishops Gate Cir",
    "iso:country": "US",
    "sg:address": "31525 Bishops Gate Cir",
    "sg:city": "Cleveland",
    "sg:classifiers": [
      {
        "category": "Professional",
        "type": "Services"
      }
    ],
    "sg:phone": "+1 440 892 4782",
    "sg:postcode": "44145",
    "sg:province": "OH",
    "wof:name": "L Suter Svc Inc",
    "wof:placetype": "venue"
  },
  "geometry": {"coordinates":[-81.968595,41.434652],"type":"Point"}
}
