{
  "type": "Feature",
  "properties": {
    "iso:country":"US",
    "sg:address":"4243 Derrwood Dr",
    "sg:city":"Akron",
    "sg:classifiers":[
        {
            "category":"Real Estate",
            "subcategory":"Real Estate Agent",
            "type":"Services"
        }
    ],
    "sg:phone":"+1 330 666 3018",
    "sg:postcode":"44333",
    "sg:province":"OH",
    "wof:name":"Cr Real Estate",
    "wof:placetype":"venue"
},
  "geometry": {"coordinates":[-81.661845,41.176508],"type":"Point"}
}