{
  "type": "Feature",
  "properties": {
    "addr:full": "190 New Hudson Rd Aurora OH 44202",
    "addr:housenumber": "190",
    "addr:postcode": "44202",
    "addr:street": "New Hudson Rd",
    "iso:country": "US",
    "sg:address": "190 New Hudson Rd",
    "sg:city": "Aurora",
    "sg:classifiers": [
      {
        "category": "Building \u0026 Trades",
        "subcategory": "Cleaning \u0026 Sanitation",
        "type": "Services"
      }
    ],
    "sg:phone": "+1 330 865 5595",
    "sg:postcode": "44202",
    "sg:province": "OH",
    "sg:tags": [
      "maintenance"
    ],
    "wof:name": "Kap Enterprises Inc",
    "wof:placetype": "venue"
  },
  "geometry": {"coordinates":[-81.336274,41.31094],"type":"Point"}
}
