{
  "type": "Feature",
  "properties": {
    "iso:country":"US",
    "sg:address":"190 New Hudson Rd",
    "sg:city":"Aurora",
    "sg:classifiers":[
        {
            "category":"Building & Trades",
            "subcategory":"Cleaning & Sanitation",
            "type":"Services"
        }
    ],
    "sg:phone":"+1 330 865 5595",
    "sg:postcode":"44202",
    "sg:province":"OH",
    "sg:tags":[
        "maintenance"
    ],
    "wof:name":"Kap Enterprises Inc",
    "wof:placetype":"venue"
},
  "geometry": {"coordinates":[-81.336274,41.31094],"type":"Point"}
}