{
  "type": "Feature",
  "properties": {
    "addr:full": "1601 Glenn Hwy New Concord OH 43762",
    "addr:housenumber": "1601",
    "addr:postcode": "43762",
    "addr:street": "Glenn Hwy",
    "iso:country": "US",
    "sg:address": "1601 Glenn Hwy",
    "sg:city": "New Concord",
    "sg:classifiers": [
      {
        "category": "Mining \u0026 Drilling",
        "type": "Manufacturing \u0026 Wholesale Goods"
      }
    ],
    "sg:phone": "+1 740 826 4786",
    "sg:postcode": "43762",
    "sg:province": "OH",
    "sg:tags": [
      "field",
      "oil"
    ],
    "wof:name": "Mc Cance Welding",
    "wof:placetype": "venue"
  },
  "geometry": {"coordinates":[-81.722709,39.995351],"type":"Point"}
}
