{
  "type": "Feature",
  "properties": {
    "iso:country":"US",
    "sg:address":"1601 Glenn Hwy",
    "sg:city":"New Concord",
    "sg:classifiers":[
        {
            "category":"Mining & Drilling",
            "type":"Manufacturing & Wholesale Goods"
        }
    ],
    "sg:phone":"+1 740 826 4786",
    "sg:postcode":"43762",
    "sg:province":"OH",
    "sg:tags":[
        "field",
        "oil"
    ],
    "wof:name":"Mc Cance Welding",
    "wof:placetype":"venue"
},
  "geometry": {"coordinates":[-81.72270899999999,39.995351],"type":"Point"}
}