{
  "type": "Feature",
  "properties": {
    "addr:full": "1301 W Market St Baltimore OH 43105",
    "addr:housenumber": "1301",
    "addr:postcode": "43105",
    "addr:street": "W Market St",
    "iso:country": "US",
    "sg:address": "1301 W Market St",
    "sg:city": "Baltimore",
    "sg:classifiers": [
      {
        "category": "Banks \u0026 Credit Unions",
        "subcategory": "Bank",
        "type": "Services"
      }
    ],
    "sg:phone": "+1 740 862 4104",
    "sg:postcode": "43105",
    "sg:province": "OH",
    "sg:tags": [
      "national",
      "commercial"
    ],
    "sg:website": "www.fairfieldnationalbank.com",
    "wof:name": "Fairfield National Bank",
    "wof:placetype": "venue"
  },
  "geometry": {"coordinates":[-82.6183,39.845641],"type":"Point"}
}
