{
  "type": "Feature",
  "properties": {
    "iso:country":"US",
    "sg:address":"111 Commerce Ln",
    "sg:city":"Bluffton",
    "sg:classifiers":[
        {
            "category":"Food & Beverages",
            "subcategory":"Groceries & Convenience Stores",
            "type":"Retail Goods"
        }
    ],
    "sg:phone":"+1 419 369 5506",
    "sg:postcode":"45817",
    "sg:province":"OH",
    "wof:name":"Sterling Stores",
    "wof:placetype":"venue"
},
  "geometry": {"coordinates":[-83.8717,40.894069],"type":"Point"}
}