{
  "type": "Feature",
  "properties": {
    "iso:country":"US",
    "sg:address":"11691 State Rte 213",
    "sg:city":"Toronto",
    "sg:classifiers":[
        {
            "category":"Health Services",
            "subcategory":"Clinic",
            "type":"Services"
        }
    ],
    "sg:phone":"+1 740 544 6700",
    "sg:postcode":"43964",
    "sg:province":"OH",
    "sg:tags":[
        "home"
    ],
    "wof:name":"Just To Say Hello",
    "wof:placetype":"venue"
},
  "geometry": {"coordinates":[-80.70427100000001,40.515139],"type":"Point"}
}