{
  "type": "Feature",
  "properties": {
    "addr:full": "7051 E Market St Warren OH 44484",
    "addr:housenumber": "7051",
    "addr:postcode": "44484",
    "addr:street": "E Market St",
    "iso:country": "US",
    "sg:address": "7051 E Market St",
    "sg:city": "Warren",
    "sg:classifiers": [
      {
        "category": "Shopping",
        "subcategory": "Bicycles \u0026 Sporting Goods",
        "type": "Retail Goods"
      }
    ],
    "sg:phone": "+1 330 856 3867",
    "sg:postcode": "44484",
    "sg:province": "OH",
    "wof:name": "Trumbull Outdoor Sports",
    "wof:placetype": "venue"
  },
  "geometry": {"coordinates":[-80.748268,41.238624],"type":"Point"}
}
