{
  "type": "Feature",
  "properties": {
    "addr:full":"6163 Allen Rd West Chester OH 45069",
    "addr:housenumber":"6163",
    "addr:postcode":"45069",
    "addr:street":"Allen Rd",
    "iso:country":"US",
    "sg:address":"6163 Allen Rd",
    "sg:city":"West Chester",
    "sg:classifiers":[
        {
            "category":"Manufacturing",
            "subcategory":"Signs",
            "type":"Manufacturing & Wholesale Goods"
        }
    ],
    "sg:phone":"+1 513 779 3333",
    "sg:postcode":"45069",
    "sg:province":"OH",
    "sg:tags":[
        "manufacture"
    ],
    "wof:name":"Diversified Sign",
    "wof:placetype":"venue"
},
  "geometry": {"coordinates":[-84.426018,39.313436],"type":"Point"}
}