{
  "type": "Feature",
  "properties": {
    "addr:full":"940 Hamilton Cleves Rd Hamilton OH 45013",
    "addr:housenumber":"940",
    "addr:postcode":"45013",
    "addr:street":"Hamilton Cleves Rd",
    "iso:country":"US",
    "sg:address":"940 Hamilton Cleves Rd",
    "sg:city":"Hamilton",
    "sg:classifiers":[
        {
            "category":"Wholesale",
            "subcategory":"Beer",
            "type":"Manufacturing & Wholesale Goods"
        }
    ],
    "sg:phone":"+1 513 893 5000",
    "sg:postcode":"45013",
    "sg:province":"OH",
    "wof:name":"Riverview Drive Thru",
    "wof:placetype":"venue"
},
  "geometry": {"coordinates":[-84.57413,39.387549],"type":"Point"}
}