{
  "type": "Feature",
  "properties": {
    "addr:full":"6670 E Garfield Rd Petersburg OH 44454",
    "addr:housenumber":"6670",
    "addr:postcode":"44454",
    "addr:street":"E Garfield Rd",
    "iso:country":"US",
    "sg:address":"6670 E Garfield Rd",
    "sg:city":"Petersburg",
    "sg:classifiers":[
        {
            "category":"Professional",
            "type":"Services"
        }
    ],
    "sg:phone":"+1 330 542 3826",
    "sg:postcode":"44454",
    "sg:province":"OH",
    "sg:tags":[
        "establishment"
    ],
    "wof:name":"Pennsylvania Turnpike Cmmssn",
    "wof:placetype":"venue"
},
  "geometry": {"coordinates":[-80.525552,40.914734],"type":"Point"}
}