{
  "type": "Feature",
  "properties": {
    "iso:country":"US",
    "sg:address":"29461 Carey Rd",
    "sg:city":"Salem",
    "sg:classifiers":[
        {
            "category":"Real Estate",
            "subcategory":"Real Estate Operator",
            "type":"Services"
        }
    ],
    "sg:phone":"+1 330 537 3652",
    "sg:postcode":"44460",
    "sg:province":"OH",
    "sg:tags":[
        "property",
        "lessor"
    ],
    "wof:name":"Karlen Delmar",
    "wof:placetype":"venue"
},
  "geometry": {"coordinates":[-80.94516400000001,40.864758],"type":"Point"}
}