{
  "type": "Feature",
  "properties": {
    "addr:full":"6770 N High St Worthington OH 43085",
    "addr:housenumber":"6770",
    "addr:postcode":"43085",
    "addr:street":"N High St",
    "iso:country":"US",
    "sg:address":"6770 N High St",
    "sg:city":"Worthington",
    "sg:classifiers":[
        {
            "category":"Organizations",
            "subcategory":"Religious Organization",
            "type":"Services"
        }
    ],
    "sg:phone":"+1 614 885 0112",
    "sg:postcode":"43085",
    "sg:province":"OH",
    "sg:tags":[
        "church"
    ],
    "sg:website":"www.saintsonhigh.org",
    "wof:name":"All Saints Evangelical Luth",
    "wof:placetype":"venue"
},
  "geometry": {"coordinates":[-83.01714699999999,40.103346],"type":"Point"}
}