{
  "type": "Feature",
  "properties": {
    "addr:full": "100 Marwood Cir Youngstown OH 44512",
    "addr:housenumber": "100",
    "addr:postcode": "44512",
    "addr:street": "Marwood Cir",
    "iso:country": "US",
    "sg:address": "100 Marwood Cir",
    "sg:city": "Youngstown",
    "sg:classifiers": [
      {
        "category": "Professional",
        "subcategory": "Lawyer \u0026 Legal Services",
        "type": "Services"
      }
    ],
    "sg:phone": "+1 330 965 8000",
    "sg:postcode": "44512",
    "sg:province": "OH",
    "sg:tags": [
      "attorney"
    ],
    "wof:name": "Osborne Delaurentis \u0026 Sontich",
    "wof:placetype": "venue"
  },
  "geometry": {"coordinates":[-80.661107,40.991799],"type":"Point"}
}
