{
  "type": "Feature",
  "properties": {
    "addr:full":"12481 Pearl Rd Cleveland OH 44136",
    "addr:housenumber":"12481",
    "addr:postcode":"44136",
    "addr:street":"Pearl Rd",
    "iso:country":"US",
    "sg:address":"12481 Pearl Rd",
    "sg:city":"Cleveland",
    "sg:classifiers":[
        {
            "category":"Health Services",
            "subcategory":"Chiropractor",
            "type":"Services"
        }
    ],
    "sg:phone":"+1 440 238 4766",
    "sg:postcode":"44136",
    "sg:province":"OH",
    "wof:name":"Starek Chiropractic Ctr",
    "wof:placetype":"venue"
},
  "geometry": {"coordinates":[-81.83629500000001,41.322356],"type":"Point"}
}