{
  "type": "Feature",
  "properties": {
    "addr:full":"3992 Cozycroft Dr Dayton OH 45424",
    "addr:housenumber":"3992",
    "addr:postcode":"45424",
    "addr:street":"Cozycroft Dr",
    "iso:country":"US",
    "sg:address":"3992 Cozycroft Dr",
    "sg:city":"Dayton",
    "sg:classifiers":[
        {
            "category":"Organizations",
            "subcategory":"Community Association",
            "type":"Services"
        }
    ],
    "sg:phone":"+1 937 235 2252",
    "sg:postcode":"45424",
    "sg:province":"OH",
    "sg:tags":[
        "sorority",
        "fraternity"
    ],
    "wof:name":"Alpha Kappa Alpha Beta Eta",
    "wof:placetype":"venue"
},
  "geometry": {"coordinates":[-84.109917,39.811913],"type":"Point"}
}