{
  "type": "Feature",
  "properties": {
    "addr:full": "103 Kirk St Flushing OH 43977",
    "addr:housenumber": "103",
    "addr:postcode": "43977",
    "addr:street": "Kirk St",
    "iso:country": "US",
    "sg:address": "103 Kirk St",
    "sg:city": "Flushing",
    "sg:classifiers": [
      {
        "category": "Building \u0026 Trades",
        "subcategory": "Construction",
        "type": "Services"
      }
    ],
    "sg:phone": "+1 740 968 1041",
    "sg:postcode": "43977",
    "sg:province": "OH",
    "sg:tags": [
      "house"
    ],
    "wof:name": "Jeffrey A Vale",
    "wof:placetype": "venue"
  },
  "geometry": {"coordinates":[-81.068124,40.147839],"type":"Point"}
}
