{
  "type": "Feature",
  "properties": {
    "addr:full": "5975 Meadowsglen Dr Dublin OH 43017",
    "addr:housenumber": "5975",
    "addr:postcode": "43017",
    "addr:street": "Meadowsglen Dr",
    "iso:country": "US",
    "sg:address": "5975 Meadowsglen Dr",
    "sg:city": "Dublin",
    "sg:classifiers": [
      {
        "category": "Real Estate",
        "subcategory": "Real Estate Operator",
        "type": "Services"
      }
    ],
    "sg:phone": "+1 614 761 8669",
    "sg:postcode": "43017",
    "sg:province": "OH",
    "sg:tags": [
      "property"
    ],
    "wof:name": "Open Vistas Inc",
    "wof:placetype": "venue"
  },
  "geometry": {"coordinates":[-83.100035,40.077139],"type":"Point"}
}
