{
  "type": "Feature",
  "properties": {
    "iso:country":"US",
    "sg:address":"5975 Meadowsglen Dr",
    "sg:city":"Dublin",
    "sg:classifiers":[
        {
            "category":"Real Estate",
            "subcategory":"Real Estate Operator",
            "type":"Services"
        }
    ],
    "sg:phone":"+1 614 761 8669",
    "sg:postcode":"43017",
    "sg:province":"OH",
    "sg:tags":[
        "property"
    ],
    "wof:name":"Open Vistas Inc",
    "wof:placetype":"venue"
},
  "geometry": {"coordinates":[-83.10003500000001,40.077139],"type":"Point"}
}