{
  "type": "Feature",
  "properties": {
    "addr:full": "7 Prestige Plaza Dr Miamisburg OH 45342",
    "addr:housenumber": "7",
    "addr:postcode": "45342",
    "addr:street": "Prestige Plaza Dr",
    "iso:country": "US",
    "sg:address": "7 Prestige Plaza Dr",
    "sg:city": "Miamisburg",
    "sg:classifiers": [
      {
        "category": "Shopping",
        "subcategory": "Clothing, Apparel, \u0026 Fashions",
        "type": "Retail Goods"
      }
    ],
    "sg:phone": "+1 937 434 8501",
    "sg:postcode": "45342",
    "sg:province": "OH",
    "sg:tags": [
      "shop",
      "occasion",
      "bridal",
      "dress",
      "special"
    ],
    "wof:name": "David's Bridal",
    "wof:placetype": "venue"
  },
  "geometry": {"coordinates":[-84.225512,39.635766],"type":"Point"}
}
