{
  "type": "Feature",
  "properties": {
    "iso:country":"US",
    "sg:address":"11416 Montgomery Rd",
    "sg:city":"Cincinnati",
    "sg:classifiers":[
        {
            "category":"Home & Garden",
            "subcategory":"Carpets & Floor Coverings",
            "type":"Retail Goods"
        }
    ],
    "sg:phone":"+1 513 489 4777",
    "sg:postcode":"45249",
    "sg:province":"OH",
    "sg:tags":[
        "dealer",
        "rug"
    ],
    "wof:name":"Rug Emporium",
    "wof:placetype":"venue"
},
  "geometry": {"coordinates":[-84.326764,39.273245],"type":"Point"}
}