{
  "type": "Feature",
  "properties": {
    "addr:full": "11416 Montgomery Rd Cincinnati OH 45249",
    "addr:housenumber": "11416",
    "addr:postcode": "45249",
    "addr:street": "Montgomery Rd",
    "iso:country": "US",
    "sg:address": "11416 Montgomery Rd",
    "sg:city": "Cincinnati",
    "sg:classifiers": [
      {
        "category": "Home \u0026 Garden",
        "subcategory": "Carpets \u0026 Floor Coverings",
        "type": "Retail Goods"
      }
    ],
    "sg:phone": "+1 513 489 4777",
    "sg:postcode": "45249",
    "sg:province": "OH",
    "sg:tags": [
      "dealer",
      "rug"
    ],
    "wof:name": "Rug Emporium",
    "wof:placetype": "venue"
  },
  "geometry": {"coordinates":[-84.326764,39.273245],"type":"Point"}
}
