{
  "type": "Feature",
  "properties": {
    "addr:full": "16 State St Gallipolis OH 45631",
    "addr:housenumber": "16",
    "addr:postcode": "45631",
    "addr:street": "State St",
    "iso:country": "US",
    "sg:address": "16 State St",
    "sg:city": "Gallipolis",
    "sg:classifiers": [
      {
        "category": "Professional",
        "subcategory": "Management \u0026 Consulting",
        "type": "Services"
      }
    ],
    "sg:phone": "+1 740 446 3662",
    "sg:postcode": "45631",
    "sg:province": "OH",
    "sg:tags": [
      "development",
      "economic",
      "agency"
    ],
    "wof:name": "Community Improvement Corp",
    "wof:placetype": "venue"
  },
  "geometry": {"coordinates":[-82.204948,38.807591],"type":"Point"}
}
