{
  "type": "Feature",
  "properties": {
    "addr:full": "3071 Graham Rd Stow OH 44224",
    "addr:housenumber": "3071",
    "addr:postcode": "44224",
    "addr:street": "Graham Rd",
    "iso:country": "US",
    "sg:address": "3071 Graham Rd",
    "sg:city": "Stow",
    "sg:classifiers": [
      {
        "category": "Personal",
        "subcategory": "Beauty Salon",
        "type": "Services"
      }
    ],
    "sg:phone": "+1 330 677 1909",
    "sg:postcode": "44224",
    "sg:province": "OH",
    "sg:tags": [
      "manicuring"
    ],
    "wof:name": "Vimi's Nail Spa",
    "wof:placetype": "venue"
  },
  "geometry": {"coordinates":[-81.400762,41.166467],"type":"Point"}
}
