{
  "type": "Feature",
  "properties": {
    "addr:full": "234 Demorest Rd Columbus OH 43204",
    "addr:housenumber": "234",
    "addr:postcode": "43204",
    "addr:street": "Demorest Rd",
    "iso:country": "US",
    "sg:address": "234 Demorest Rd",
    "sg:city": "Columbus",
    "sg:classifiers": [
      {
        "category": "Freight",
        "type": "Transportation"
      },
      {
        "category": "Wholesale",
        "subcategory": "Furniture",
        "type": "Manufacturing \u0026 Wholesale Goods"
      }
    ],
    "sg:phone": "+1 614 279 0682",
    "sg:postcode": "43204",
    "sg:province": "OH",
    "sg:tags": [
      "operator",
      "contractor",
      "local",
      "trade",
      "trucking"
    ],
    "wof:name": "Office Link",
    "wof:placetype": "venue"
  },
  "geometry": {"coordinates":[-83.090249,39.951275],"type":"Point"}
}
