{
  "type": "Feature",
  "properties": {
    "addr:full": "5509 Berger Rd Groveport OH 43125",
    "addr:housenumber": "5509",
    "addr:postcode": "43125",
    "addr:street": "Berger Rd",
    "iso:country": "US",
    "sg:address": "5509 Berger Rd",
    "sg:city": "Groveport",
    "sg:classifiers": [
      {
        "category": "Utilities",
        "subcategory": "Natural Gas",
        "type": "Services"
      }
    ],
    "sg:phone": "+1 614 837 6881",
    "sg:postcode": "43125",
    "sg:province": "OH",
    "sg:tags": [
      "transmission"
    ],
    "wof:name": "Dominion",
    "wof:placetype": "venue"
  },
  "geometry": {"coordinates":[-82.85331,39.815224],"type":"Point"}
}
