{
  "type": "Feature",
  "properties": {
    "iso:country":"US",
    "sg:address":"9215 Market St",
    "sg:city":"North Lima",
    "sg:classifiers":[
        {
            "category":"Wholesale",
            "subcategory":"Machinery & Supplies",
            "type":"Manufacturing & Wholesale Goods"
        },
        {
            "category":"Retail",
            "subcategory":"Animal Services",
            "type":"Services"
        }
    ],
    "sg:phone":"+1 330 758 4444",
    "sg:postcode":"44452",
    "sg:province":"OH",
    "sg:tags":[
        "pet",
        "equipment",
        "grooming",
        "industrial",
        "washing"
    ],
    "wof:name":"Pet Spa",
    "wof:placetype":"venue"
},
  "geometry": {"coordinates":[-80.662421,40.98353],"type":"Point"}
}