{
  "type": "Feature",
  "properties": {
    "addr:full": "9215 Market St North Lima OH 44452",
    "addr:housenumber": "9215",
    "addr:postcode": "44452",
    "addr:street": "Market St",
    "iso:country": "US",
    "sg:address": "9215 Market St",
    "sg:city": "North Lima",
    "sg:classifiers": [
      {
        "category": "Wholesale",
        "subcategory": "Machinery \u0026 Supplies",
        "type": "Manufacturing \u0026 Wholesale Goods"
      },
      {
        "category": "Retail",
        "subcategory": "Animal Services",
        "type": "Services"
      }
    ],
    "sg:phone": "+1 330 758 4444",
    "sg:postcode": "44452",
    "sg:province": "OH",
    "sg:tags": [
      "pet",
      "equipment",
      "grooming",
      "industrial",
      "washing"
    ],
    "wof:name": "Pet Spa",
    "wof:placetype": "venue"
  },
  "geometry": {"coordinates":[-80.662421,40.98353],"type":"Point"}
}
