{
  "type": "Feature",
  "properties": {
    "addr:full":"333 Lewiston Rd Dayton OH 45429",
    "addr:housenumber":"333",
    "addr:postcode":"45429",
    "addr:street":"Lewiston Rd",
    "iso:country":"US",
    "sg:address":"333 Lewiston Rd",
    "sg:city":"Dayton",
    "sg:classifiers":[
        {
            "category":"Wholesale",
            "subcategory":"Machinery & Supplies",
            "type":"Manufacturing & Wholesale Goods"
        }
    ],
    "sg:phone":"+1 937 299 0529",
    "sg:postcode":"45429",
    "sg:province":"OH",
    "sg:tags":[
        "tool"
    ],
    "wof:name":"2LZ",
    "wof:placetype":"venue"
},
  "geometry": {"coordinates":[-84.165508,39.703066],"type":"Point"}
}