{
  "type": "Feature",
  "properties": {
    "addr:full": "6902 Wooster Pike Cincinnati OH 45227",
    "addr:housenumber": "6902",
    "addr:postcode": "45227",
    "addr:street": "Wooster Pike",
    "iso:country": "US",
    "sg:address": "6902 Wooster Pike",
    "sg:city": "Cincinnati",
    "sg:classifiers": [
      {
        "category": "Banks \u0026 Credit Unions",
        "subcategory": "Bank",
        "type": "Services"
      }
    ],
    "sg:phone": "+1 513 271 0480",
    "sg:postcode": "45227",
    "sg:province": "OH",
    "sg:website": "www.pncbank.com",
    "wof:name": "Pnc Bank",
    "wof:placetype": "venue"
  },
  "geometry": {"coordinates":[-84.372134,39.145184],"type":"Point"}
}
