{
  "type": "Feature",
  "properties": {
    "addr:full": "2720 Van Aken Blvd Cleveland OH 44120",
    "addr:housenumber": "2720",
    "addr:postcode": "44120",
    "addr:street": "Van Aken Blvd",
    "iso:country": "US",
    "sg:address": "2720 Van Aken Blvd",
    "sg:city": "Cleveland",
    "sg:classifiers": [
      {
        "category": "Manufacturing",
        "subcategory": "Furniture",
        "type": "Manufacturing \u0026 Wholesale Goods"
      }
    ],
    "sg:phone": "+1 216 283 2530",
    "sg:postcode": "44120",
    "sg:province": "OH",
    "sg:website": "www.holmeschair.com",
    "wof:name": "Holmes County Chair Co Inc",
    "wof:placetype": "venue"
  },
  "geometry": {"coordinates":[-81.588684,41.482535],"type":"Point"}
}
