{
  "type": "Feature",
  "properties": {
    "addr:full":"10792 Montgomery Rd Cincinnati OH 45242",
    "addr:housenumber":"10792",
    "addr:postcode":"45242",
    "addr:street":"Montgomery Rd",
    "iso:country":"US",
    "sg:address":"10792 Montgomery Rd",
    "sg:city":"Cincinnati",
    "sg:classifiers":[
        {
            "category":"Restaurant",
            "type":"Food & Drink"
        }
    ],
    "sg:menulink":"http://www.allmenus.com/oh/sycamore/122329-quiznos-sub/menu/",
    "sg:phone":"+1 513 469 8284",
    "sg:postcode":"45242",
    "sg:province":"OH",
    "sg:tags":[
        "wrap",
        "american",
        "sandwich"
    ],
    "wof:name":"Quiznos Sub",
    "wof:placetype":"venue"
},
  "geometry": {"coordinates":[-84.340146,39.258588],"type":"Point"}
}