{
  "type": "Feature",
  "properties": {
    "addr:full": "3015 State Rd Ashtabula OH 44004",
    "addr:housenumber": "3015",
    "addr:postcode": "44004",
    "addr:street": "State Rd",
    "iso:country": "US",
    "sg:address": "3015 State Rd",
    "sg:city": "Ashtabula",
    "sg:classifiers": [
      {
        "category": "Professional",
        "subcategory": "Accounting \u0026 Tax Preparation",
        "type": "Services"
      }
    ],
    "sg:phone": "+1 440 992 1338",
    "sg:postcode": "44004",
    "sg:province": "OH",
    "sg:tags": [
      "return",
      "filing"
    ],
    "wof:name": "Ebersole-Niemi Tax \u0026 Acctg Svc",
    "wof:placetype": "venue"
  },
  "geometry": {"coordinates":[-80.772545,41.87941],"type":"Point"}
}
