{
  "type": "Feature",
  "properties": {
    "addr:full": "3528 Monroe St Toledo OH 43606",
    "addr:housenumber": "3528",
    "addr:postcode": "43606",
    "addr:street": "Monroe St",
    "iso:country": "US",
    "sg:address": "3528 Monroe St",
    "sg:city": "Toledo",
    "sg:classifiers": [
      {
        "category": "Social Services",
        "type": "Services"
      }
    ],
    "sg:phone": "+1 419 242 9392",
    "sg:postcode": "43606",
    "sg:province": "OH",
    "sg:tags": [
      "employee",
      "assistance",
      "program"
    ],
    "wof:name": "Arena Of Life Jobs Program",
    "wof:placetype": "venue"
  },
  "geometry": {"coordinates":[-83.581296,41.669797],"type":"Point"}
}
