{
  "type": "Feature",
  "properties": {
    "addr:full":"6000 Wooster Pike Cincinnati OH 45227",
    "addr:housenumber":"6000",
    "addr:postcode":"45227",
    "addr:street":"Wooster Pike",
    "iso:country":"US",
    "sg:address":"6000 Wooster Pike",
    "sg:city":"Cincinnati",
    "sg:classifiers":[
        {
            "category":"Wholesale",
            "subcategory":"Groceries",
            "type":"Manufacturing & Wholesale Goods"
        }
    ],
    "sg:phone":"+1 513 271 3688",
    "sg:postcode":"45227",
    "sg:province":"OH",
    "sg:tags":[
        "confectionery"
    ],
    "wof:name":"Donut Wholesale Co",
    "wof:placetype":"venue"
},
  "geometry": {"coordinates":[-84.388863,39.142877],"type":"Point"}
}