{
  "type": "Feature",
  "properties": {
    "addr:full":"438 S Prospect St Bowling Green OH 43402",
    "addr:housenumber":"438",
    "addr:postcode":"43402",
    "addr:street":"S Prospect St",
    "iso:country":"US",
    "sg:address":"438 S Prospect St",
    "sg:city":"Bowling Green",
    "sg:classifiers":[
        {
            "category":"Professional",
            "subcategory":"Computer Services",
            "type":"Services"
        }
    ],
    "sg:phone":"+1 419 352 6963",
    "sg:postcode":"43402",
    "sg:province":"OH",
    "sg:tags":[
        "internet"
    ],
    "wof:name":"J-B Prospects Corp",
    "wof:placetype":"venue"
},
  "geometry": {"coordinates":[-83.64886199999999,41.368938],"type":"Point"}
}