{
  "type": "Feature",
  "properties": {
    "addr:full": "779 S Ellsworth Ave Salem OH 44460",
    "addr:housenumber": "779",
    "addr:postcode": "44460",
    "addr:street": "S Ellsworth Ave",
    "iso:country": "US",
    "sg:address": "779 S Ellsworth Ave",
    "sg:city": "Salem",
    "sg:classifiers": [
      {
        "category": "Manufacturing",
        "subcategory": "Tools \u0026 Machinery",
        "type": "Manufacturing \u0026 Wholesale Goods"
      }
    ],
    "sg:phone": "+1 330 337 7039",
    "sg:postcode": "44460",
    "sg:province": "OH",
    "sg:tags": [
      "die",
      "maker"
    ],
    "wof:name": "Concept-4 Inc",
    "wof:placetype": "venue"
  },
  "geometry": {"coordinates":[-80.856964,40.894493],"type":"Point"}
}
