{
  "type": "Feature",
  "properties": {
    "addr:full": "121 N Main St Urbana OH 43078",
    "addr:housenumber": "121",
    "addr:postcode": "43078",
    "addr:street": "N Main St",
    "iso:country": "US",
    "sg:address": "121 N Main St",
    "sg:city": "Urbana",
    "sg:classifiers": [
      {
        "category": "Shopping",
        "subcategory": "Florist",
        "type": "Retail Goods"
      }
    ],
    "sg:phone": "+1 937 652 2800",
    "sg:postcode": "43078",
    "sg:province": "OH",
    "wof:name": "Absolute Floral",
    "wof:placetype": "venue"
  },
  "geometry": {"coordinates":[-83.752315,40.10895],"type":"Point"}
}
