{
  "type": "Feature",
  "properties": {
    "addr:full":"290 W Main St Pomeroy OH 45769",
    "addr:housenumber":"290",
    "addr:postcode":"45769",
    "addr:street":"W Main St",
    "iso:country":"US",
    "sg:address":"290 W Main St",
    "sg:city":"Pomeroy",
    "sg:classifiers":[
        {
            "category":"Farming",
            "subcategory":"Farm",
            "type":"Manufacturing & Wholesale Goods"
        }
    ],
    "sg:phone":"+1 740 992 6793",
    "sg:postcode":"45769",
    "sg:province":"OH",
    "sg:tags":[
        "crop",
        "general"
    ],
    "wof:name":"Four Oaks Farms",
    "wof:placetype":"venue"
},
  "geometry": {"coordinates":[-82.040542,39.021996],"type":"Point"}
}