{
  "type": "Feature",
  "properties": {
    "addr:full": "305 Buffalo St Conneaut OH 44030",
    "addr:housenumber": "305",
    "addr:postcode": "44030",
    "addr:street": "Buffalo St",
    "iso:country": "US",
    "sg:address": "305 Buffalo St",
    "sg:city": "Conneaut",
    "sg:classifiers": [
      {
        "category": "Personal",
        "subcategory": "Beauty Salon",
        "type": "Services"
      }
    ],
    "sg:phone": "+1 440 593 3802",
    "sg:postcode": "44030",
    "sg:province": "OH",
    "wof:name": "Carol's Beauty Salon",
    "wof:placetype": "venue"
  },
  "geometry": {"coordinates":[-80.557498,41.945604],"type":"Point"}
}
