{
  "type": "Feature",
  "properties": {
    "iso:country":"US",
    "sg:address":"1528 Market Ave N",
    "sg:city":"Canton",
    "sg:classifiers":[
        {
            "category":"Health Services",
            "subcategory":"Nursing And Care Facility",
            "type":"Services"
        }
    ],
    "sg:phone":"+1 330 453 8456",
    "sg:postcode":"44714",
    "sg:province":"OH",
    "sg:tags":[
        "home",
        "center",
        "rest"
    ],
    "wof:name":"Colonial Nursing Home",
    "wof:placetype":"venue"
},
  "geometry": {"coordinates":[-81.36977,40.814979],"type":"Point"}
}