{
  "type": "Feature",
  "properties": {
    "addr:full": "19084 Lucerne Rd Fredericktown OH 43019",
    "addr:housenumber": "19084",
    "addr:postcode": "43019",
    "addr:street": "Lucerne Rd",
    "iso:country": "US",
    "sg:address": "19084 Lucerne Rd",
    "sg:city": "Fredericktown",
    "sg:classifiers": [
      {
        "category": "Building \u0026 Trades",
        "subcategory": "Construction",
        "type": "Services"
      }
    ],
    "sg:phone": "+1 740 694 4581",
    "sg:postcode": "43019",
    "sg:province": "OH",
    "sg:tags": [
      "excavation",
      "contractor"
    ],
    "wof:name": "Carmon Weller Excavating",
    "wof:placetype": "venue"
  },
  "geometry": {"coordinates":[-82.628855,40.515811],"type":"Point"}
}
