{
  "type": "Feature",
  "properties": {
    "addr:full":"2888 Brice Rd Columbus OH 43232",
    "addr:housenumber":"2888",
    "addr:postcode":"43232",
    "addr:street":"Brice Rd",
    "iso:country":"US",
    "sg:address":"2888 Brice Rd",
    "sg:city":"Columbus",
    "sg:classifiers":[
        {
            "category":"Professional",
            "type":"Services"
        }
    ],
    "sg:phone":"+1 614 501 3106",
    "sg:postcode":"43232",
    "sg:province":"OH",
    "wof:name":"Huffy Service First Inc",
    "wof:placetype":"venue"
},
  "geometry": {"coordinates":[-82.831498,39.921718],"type":"Point"}
}