{
  "type": "Feature",
  "properties": {
    "addr:full":"3850 Morse Rd Columbus OH 43219",
    "addr:housenumber":"3850",
    "addr:postcode":"43219",
    "addr:street":"Morse Rd",
    "iso:country":"US",
    "sg:address":"3850 Morse Rd",
    "sg:city":"Columbus",
    "sg:classifiers":[
        {
            "category":"Shopping",
            "subcategory":"Bicycles & Sporting Goods",
            "type":"Retail Goods"
        }
    ],
    "sg:phone":"+1 614 476 0500",
    "sg:postcode":"43219",
    "sg:province":"OH",
    "wof:name":"Sportmart Inc",
    "wof:placetype":"venue"
},
  "geometry": {"coordinates":[-82.918224,40.057891],"type":"Point"}
}