{
  "type": "Feature",
  "properties": {
    "iso:country":"US",
    "sg:address":"2150 W Central Ave",
    "sg:city":"Toledo",
    "sg:classifiers":[
        {
            "category":"Education",
            "subcategory":"Special Training",
            "type":"Public Place"
        }
    ],
    "sg:phone":"+1 419 291 7888",
    "sg:postcode":"43606",
    "sg:province":"OH",
    "sg:tags":[
        "center"
    ],
    "wof:name":"Children's Center For Learning",
    "wof:placetype":"venue"
},
  "geometry": {"coordinates":[-83.596428,41.677806],"type":"Point"}
}