{
  "type": "Feature",
  "properties": {
    "iso:country":"US",
    "sg:address":"24 S Washington St",
    "sg:city":"Tiffin",
    "sg:classifiers":[
        {
            "category":"Wholesale",
            "subcategory":"Electrical",
            "type":"Manufacturing & Wholesale Goods"
        }
    ],
    "sg:phone":"+1 419 447 3062",
    "sg:postcode":"44883",
    "sg:province":"OH",
    "sg:tags":[
        "alarm",
        "burglar",
        "system"
    ],
    "wof:name":"Electro Alarms Co",
    "wof:placetype":"venue"
},
  "geometry": {"coordinates":[-83.177003,41.116896],"type":"Point"}
}