{
  "type": "Feature",
  "properties": {
    "addr:full": "24 S Washington St Tiffin OH 44883",
    "addr:housenumber": "24",
    "addr:postcode": "44883",
    "addr:street": "S Washington St",
    "iso:country": "US",
    "sg:address": "24 S Washington St",
    "sg:city": "Tiffin",
    "sg:classifiers": [
      {
        "category": "Wholesale",
        "subcategory": "Electrical",
        "type": "Manufacturing \u0026 Wholesale Goods"
      }
    ],
    "sg:phone": "+1 419 447 3062",
    "sg:postcode": "44883",
    "sg:province": "OH",
    "sg:tags": [
      "alarm",
      "burglar",
      "system"
    ],
    "wof:name": "Electro Alarms Co",
    "wof:placetype": "venue"
  },
  "geometry": {"coordinates":[-83.177003,41.116896],"type":"Point"}
}
