{
  "type": "Feature",
  "properties": {
    "addr:full":"12300 Youngstown Salem Rd Salem OH 44460",
    "addr:housenumber":"12300",
    "addr:postcode":"44460",
    "addr:street":"Youngstown Salem Rd",
    "iso:country":"US",
    "sg:address":"12300 Youngstown Salem Rd",
    "sg:city":"Salem",
    "sg:classifiers":[
        {
            "category":"Wholesale",
            "subcategory":"Auto Parts",
            "type":"Manufacturing & Wholesale Goods"
        }
    ],
    "sg:phone":"+1 330 337 3556",
    "sg:postcode":"44460",
    "sg:province":"OH",
    "sg:tags":[
        "automobile",
        "used",
        "wrecking"
    ],
    "wof:name":"Diamond Auto Wrecking Co Inc",
    "wof:placetype":"venue"
},
  "geometry": {"coordinates":[-80.840473,40.93105],"type":"Point"}
}