{
  "type": "Feature",
  "properties": {
    "iso:country":"US",
    "sg:address":"4466 Kinsman Rd",
    "sg:city":"Middlefield",
    "sg:classifiers":[
        {
            "category":"Education",
            "subcategory":"School",
            "type":"Public Place"
        }
    ],
    "sg:phone":"+1 440 693 4127",
    "sg:postcode":"44439",
    "sg:province":"OH",
    "wof:name":"Bloomfield Mespo Local Sd",
    "wof:placetype":"venue"
},
  "geometry": {"coordinates":[-80.95848599999999,41.458436],"type":"Point"}
}