{
  "type": "Feature",
  "properties": {
    "iso:country":"US",
    "sg:address":"2301 Fairwood Ave",
    "sg:city":"Columbus",
    "sg:classifiers":[
        {
            "category":"Manufacturing",
            "subcategory":"Metals",
            "type":"Manufacturing & Wholesale Goods"
        }
    ],
    "sg:phone":"+1 614 444 2181",
    "sg:postcode":"43207",
    "sg:province":"OH",
    "sg:tags":[
        "stamping"
    ],
    "sg:website":"www.superior-dietool.com",
    "wof:name":"Superior Die Tool & Machine",
    "wof:placetype":"venue"
},
  "geometry": {"coordinates":[-82.95609399999999,39.919444],"type":"Point"}
}