{
  "type": "Feature",
  "properties": {
    "addr:full": "2301 Fairwood Ave Columbus OH 43207",
    "addr:housenumber": "2301",
    "addr:postcode": "43207",
    "addr:street": "Fairwood Ave",
    "iso:country": "US",
    "sg:address": "2301 Fairwood Ave",
    "sg:city": "Columbus",
    "sg:classifiers": [
      {
        "category": "Manufacturing",
        "subcategory": "Metals",
        "type": "Manufacturing \u0026 Wholesale Goods"
      }
    ],
    "sg:phone": "+1 614 444 2181",
    "sg:postcode": "43207",
    "sg:province": "OH",
    "sg:tags": [
      "stamping"
    ],
    "sg:website": "www.superior-dietool.com",
    "wof:name": "Superior Die Tool \u0026 Machine",
    "wof:placetype": "venue"
  },
  "geometry": {"coordinates":[-82.956094,39.919444],"type":"Point"}
}
