{
  "type": "Feature",
  "properties": {
    "addr:full":"34 Licking View Dr Heath OH 43056",
    "addr:housenumber":"34",
    "addr:postcode":"43056",
    "addr:street":"Licking View Dr",
    "iso:country":"US",
    "sg:address":"34 Licking View Dr",
    "sg:city":"Heath",
    "sg:classifiers":[
        {
            "category":"Banks & Credit Unions",
            "subcategory":"Bank",
            "type":"Services"
        }
    ],
    "sg:phone":"+1 740 522 5277",
    "sg:postcode":"43056",
    "sg:province":"OH",
    "sg:website":"www.harvestfcu.org",
    "wof:name":"Harvest Federal Credit Union",
    "wof:placetype":"venue"
},
  "geometry": {"coordinates":[-82.44325499999999,40.025306],"type":"Point"}
}