{
  "type": "Feature",
  "properties": {
    "addr:full": "817 Columbia Rd Valley City OH 44280",
    "addr:housenumber": "817",
    "addr:postcode": "44280",
    "addr:street": "Columbia Rd",
    "iso:country": "US",
    "sg:address": "817 Columbia Rd",
    "sg:city": "Valley City",
    "sg:classifiers": [
      {
        "category": "Manufacturing",
        "subcategory": "Printing",
        "type": "Manufacturing \u0026 Wholesale Goods"
      }
    ],
    "sg:phone": "+1 330 483 3348",
    "sg:postcode": "44280",
    "sg:province": "OH",
    "sg:tags": [
      "commercial"
    ],
    "wof:name": "RNR Creations",
    "wof:placetype": "venue"
  },
  "geometry": {"coordinates":[-81.926079,41.252755],"type":"Point"}
}
