{
  "type": "Feature",
  "properties": {
    "iso:country":"US",
    "sg:address":"8820 Mentor Ave",
    "sg:city":"Mentor",
    "sg:classifiers":[
        {
            "category":"Restaurant",
            "type":"Food & Drink"
        }
    ],
    "sg:phone":"+1 440 974 7001",
    "sg:postcode":"44060",
    "sg:province":"OH",
    "wof:name":"Slam Jams",
    "wof:placetype":"venue"
},
  "geometry": {"coordinates":[-81.325924,41.673052],"type":"Point"}
}