{
  "type": "Feature",
  "properties": {
    "iso:country":"US",
    "sg:address":"200 Eaton Lewisburg Rd",
    "sg:city":"Eaton",
    "sg:classifiers":[
        {
            "category":"Health Services",
            "subcategory":"Doctor",
            "type":"Services"
        }
    ],
    "sg:phone":"+1 937 456 4141",
    "sg:postcode":"45320",
    "sg:province":"OH",
    "sg:tags":[
        "dermatology",
        "consultant"
    ],
    "wof:name":"Dermotology Consultants Inc",
    "wof:placetype":"venue"
},
  "geometry": {"coordinates":[-84.634895,39.759906],"type":"Point"}
}