{
  "type": "Feature",
  "properties": {
    "addr:full": "14761 Pearl Rd Cleveland OH 44136",
    "addr:housenumber": "14761",
    "addr:postcode": "44136",
    "addr:street": "Pearl Rd",
    "iso:country": "US",
    "sg:address": "14761 Pearl Rd",
    "sg:city": "Cleveland",
    "sg:classifiers": [
      {
        "category": "Building \u0026 Trades",
        "subcategory": "Electrical",
        "type": "Services"
      },
      {
        "category": "Wholesale",
        "subcategory": "Electrical",
        "type": "Manufacturing \u0026 Wholesale Goods"
      }
    ],
    "sg:phone": "+1 440 237 3950",
    "sg:postcode": "44136",
    "sg:province": "OH",
    "sg:tags": [
      "equipment",
      "lighting",
      "landscape"
    ],
    "wof:name": "Outdoor Lighting Prospectives",
    "wof:placetype": "venue"
  },
  "geometry": {"coordinates":[-81.835135,41.305907],"type":"Point"}
}
