{
  "type": "Feature",
  "properties": {
    "addr:full": "7611 Hamilton Ave Cincinnati OH 45231",
    "addr:housenumber": "7611",
    "addr:postcode": "45231",
    "addr:street": "Hamilton Ave",
    "iso:country": "US",
    "sg:address": "7611 Hamilton Ave",
    "sg:city": "Cincinnati",
    "sg:classifiers": [
      {
        "category": "Building \u0026 Trades",
        "subcategory": "Construction",
        "type": "Services"
      }
    ],
    "sg:phone": "+1 513 522 2333",
    "sg:postcode": "45231",
    "sg:province": "OH",
    "sg:tags": [
      "contractor"
    ],
    "wof:name": "Preferred Building Specialists",
    "wof:placetype": "venue"
  },
  "geometry": {"coordinates":[-84.548186,39.233432],"type":"Point"}
}
