{
  "type": "Feature",
  "properties": {
    "addr:full": "3518 N Main St Dayton OH 45405",
    "addr:housenumber": "3518",
    "addr:postcode": "45405",
    "addr:street": "N Main St",
    "iso:country": "US",
    "sg:address": "3518 N Main St",
    "sg:city": "Dayton",
    "sg:classifiers": [
      {
        "category": "Real Estate",
        "subcategory": "Real Estate Services",
        "type": "Services"
      },
      {
        "category": "Real Estate",
        "subcategory": "Real Estate Agent",
        "type": "Services"
      }
    ],
    "sg:phone": "+1 937 275 0001",
    "sg:postcode": "45405",
    "sg:province": "OH",
    "sg:tags": [
      "buyer",
      "broker"
    ],
    "wof:name": "PepZee Realty",
    "wof:placetype": "venue"
  },
  "geometry": {"coordinates":[-84.217577,39.797798],"type":"Point"}
}
