{
  "type": "Feature",
  "properties": {
    "iso:country":"US",
    "sg:address":"37 White Allen Ave",
    "sg:city":"Dayton",
    "sg:classifiers":[
        {
            "category":"Professional",
            "subcategory":"Credit Reporting & Collection",
            "type":"Services"
        }
    ],
    "sg:phone":"+1 937 228 6124",
    "sg:postcode":"45405",
    "sg:province":"OH",
    "sg:tags":[
        "agency"
    ],
    "sg:website":"www.nacmohio.com",
    "wof:name":"National Association Of Credit",
    "wof:placetype":"venue"
},
  "geometry": {"coordinates":[-84.192408,39.767845],"type":"Point"}
}