{
  "type": "Feature",
  "properties": {
    "addr:full": "600 E Brown Ave Bellefontaine OH 43311",
    "addr:housenumber": "600",
    "addr:postcode": "43311",
    "addr:street": "E Brown Ave",
    "iso:country": "US",
    "sg:address": "600 E Brown Ave",
    "sg:city": "Bellefontaine",
    "sg:classifiers": [
      {
        "category": "Education",
        "subcategory": "School",
        "type": "Public Place"
      }
    ],
    "sg:phone": "+1 937 599 4431",
    "sg:postcode": "43311",
    "sg:province": "OH",
    "wof:name": "Northeastern Elementary School",
    "wof:placetype": "venue"
  },
  "geometry": {"coordinates":[-83.748215,40.36643],"type":"Point"}
}
