{
  "type": "Feature",
  "properties": {
    "iso:country":"US",
    "sg:address":"1931 Windhill Ter",
    "sg:city":"Cincinnati",
    "sg:classifiers":[
        {
            "category":"Health Services",
            "subcategory":"Medical Lab",
            "type":"Services"
        }
    ],
    "sg:phone":"+1 513 984 4742",
    "sg:postcode":"45255",
    "sg:province":"OH",
    "sg:tags":[
        "laboratory"
    ],
    "wof:name":"Simon D De Chatlet",
    "wof:placetype":"venue"
},
  "geometry": {"coordinates":[-84.33548500000001,39.087435],"type":"Point"}
}