{
  "type": "Feature",
  "properties": {
    "addr:full":"17715 Euclid Ave Cleveland OH 44112",
    "addr:housenumber":"17715",
    "addr:postcode":"44112",
    "addr:street":"Euclid Ave",
    "iso:country":"US",
    "sg:address":"17715 Euclid Ave",
    "sg:city":"Cleveland",
    "sg:classifiers":[
        {
            "category":"Organizations",
            "subcategory":"Religious Organization",
            "type":"Services"
        }
    ],
    "sg:phone":"+1 216 481 2668",
    "sg:postcode":"44112",
    "sg:province":"OH",
    "sg:tags":[
        "church"
    ],
    "wof:name":"Greater St Joseph Missionary",
    "wof:placetype":"venue"
},
  "geometry": {"coordinates":[-81.556091,41.552801],"type":"Point"}
}