{
  "type": "Feature",
  "properties": {
    "addr:full": "2720 Airport Dr Columbus OH 43219",
    "addr:housenumber": "2720",
    "addr:postcode": "43219",
    "addr:street": "Airport Dr",
    "iso:country": "US",
    "sg:address": "2720 Airport Dr",
    "sg:city": "Columbus",
    "sg:classifiers": [
      {
        "category": "Airport",
        "type": "Transportation"
      }
    ],
    "sg:phone": "+1 614 418 1725",
    "sg:postcode": "43219",
    "sg:province": "OH",
    "sg:tags": [
      "aircraft",
      "maintenance"
    ],
    "wof:name": "P \u0026 Wc AIRCRAFT Svc Inc",
    "wof:placetype": "venue"
  },
  "geometry": {"coordinates":[-82.933368,39.995824],"type":"Point"}
}
