{
  "type": "Feature",
  "properties": {
    "iso:country":"US",
    "sg:address":"10946 Hamilton Ave",
    "sg:city":"Cincinnati",
    "sg:classifiers":[
        {
            "category":"Restaurant",
            "type":"Food & Drink"
        }
    ],
    "sg:phone":"+1 513 941 9224",
    "sg:postcode":"45231",
    "sg:province":"OH",
    "sg:tags":[
        "eating"
    ],
    "wof:name":"Riverfront Restaurant",
    "wof:placetype":"venue"
},
  "geometry": {"coordinates":[-84.562678,39.275201],"type":"Point"}
}