{
  "type": "Feature",
  "properties": {
    "iso:country":"US",
    "sg:address":"23956 Greenlawn Ave",
    "sg:city":"Cleveland",
    "sg:classifiers":[
        {
            "category":"Building & Trades",
            "subcategory":"Plumbing",
            "type":"Services"
        }
    ],
    "sg:phone":"+1 216 496 7572",
    "sg:postcode":"44122",
    "sg:province":"OH",
    "sg:tags":[
        "contractor"
    ],
    "wof:name":"Newmeyer Plumbing Inc",
    "wof:placetype":"venue"
},
  "geometry": {"coordinates":[-81.509292,41.495361],"type":"Point"}
}