{
  "type": "Feature",
  "properties": {
    "iso:country":"US",
    "sg:address":"1713 Patterson Rd",
    "sg:city":"Dayton",
    "sg:classifiers":[
        {
            "category":"Building & Trades",
            "subcategory":"Construction",
            "type":"Services"
        }
    ],
    "sg:phone":"+1 937 252 9562",
    "sg:postcode":"45420",
    "sg:province":"OH",
    "sg:tags":[
        "painter"
    ],
    "wof:name":"Mc Donough & Foster Inc",
    "wof:placetype":"venue"
},
  "geometry": {"coordinates":[-84.13755,39.723474],"type":"Point"}
}