{
  "type": "Feature",
  "properties": {
    "iso:country":"US",
    "sg:address":"7127 Co Rd 30",
    "sg:city":"Mount Gilead",
    "sg:phone":"+1 419 947 5336",
    "sg:postcode":"43338",
    "sg:province":"OH",
    "sg:tags":[
        "farm",
        "field",
        "soybean",
        "crop"
    ],
    "wof:name":"Val Kunze",
    "wof:placetype":"venue"
},
  "geometry": {"coordinates":[-82.84199,40.610864],"type":"Point"}
}