{
  "type": "Feature",
  "properties": {
    "addr:full":"1624 Mechanicsburg Rd Wooster OH 44691",
    "addr:housenumber":"1624",
    "addr:postcode":"44691",
    "addr:street":"Mechanicsburg Rd",
    "iso:country":"US",
    "sg:address":"1624 Mechanicsburg Rd",
    "sg:city":"Wooster",
    "sg:classifiers":[
        {
            "category":"Wholesale",
            "subcategory":"Vending Machines",
            "type":"Manufacturing & Wholesale Goods"
        }
    ],
    "sg:phone":"+1 330 264 2783",
    "sg:postcode":"44691",
    "sg:province":"OH",
    "wof:name":"Cuyahoga Vending",
    "wof:placetype":"venue"
},
  "geometry": {"coordinates":[-81.962924,40.818161],"type":"Point"}
}