{
  "type": "Feature",
  "properties": {
    "iso:country":"US",
    "sg:address":"5777 E Livingston Ave",
    "sg:city":"Columbus",
    "sg:classifiers":[
        {
            "category":"Autos & Motor Vehicles",
            "subcategory":"Automobile Sales",
            "type":"Retail Goods"
        }
    ],
    "sg:phone":"+1 614 337 8001",
    "sg:postcode":"43232",
    "sg:province":"OH",
    "sg:tags":[
        "car",
        "dealer"
    ],
    "sg:website":"www.miraclemotormart.com",
    "wof:name":"Priced Right Motor Cars Inc",
    "wof:placetype":"venue"
},
  "geometry": {"coordinates":[-82.840166,39.942829],"type":"Point"}
}