{
  "type": "Feature",
  "properties": {
    "iso:country":"US",
    "sg:address":"20514 Stonerock Rd",
    "sg:city":"Circleville",
    "sg:phone":"+1 740 474 2438",
    "sg:postcode":"43113",
    "sg:province":"OH",
    "sg:tags":[
        "farm",
        "corn",
        "soybean"
    ],
    "wof:name":"Ruff Farms",
    "wof:placetype":"venue"
},
  "geometry": {"coordinates":[-83.09267,39.639904],"type":"Point"}
}