{
  "type": "Feature",
  "properties": {
    "addr:full":"12135 Station Rd Columbia Station OH 44028",
    "addr:housenumber":"12135",
    "addr:postcode":"44028",
    "addr:street":"Station Rd",
    "iso:country":"US",
    "sg:address":"12135 Station Rd",
    "sg:city":"Columbia Station",
    "sg:classifiers":[
        {
            "category":"Freight",
            "type":"Transportation"
        }
    ],
    "sg:phone":"+1 440 238 5638",
    "sg:postcode":"44028",
    "sg:province":"OH",
    "sg:tags":[
        "distance",
        "long",
        "trucking"
    ],
    "wof:name":"Mist Trucking Inc",
    "wof:placetype":"venue"
},
  "geometry": {"coordinates":[-81.943241,41.331611],"type":"Point"}
}