{
  "type": "Feature",
  "properties": {
    "addr:full":"1344 Nebraska Ave Toledo OH 43607",
    "addr:housenumber":"1344",
    "addr:postcode":"43607",
    "addr:street":"Nebraska Ave",
    "iso:country":"US",
    "sg:address":"1344 Nebraska Ave",
    "sg:city":"Toledo",
    "sg:classifiers":[
        {
            "category":"Shopping",
            "subcategory":"Clothing, Apparel, & Fashions",
            "type":"Retail Goods"
        }
    ],
    "sg:phone":"+1 419 244 2122",
    "sg:postcode":"43607",
    "sg:province":"OH",
    "sg:tags":[
        "item",
        "boutique"
    ],
    "wof:name":"Gilmore's Fashion Boutique",
    "wof:placetype":"venue"
},
  "geometry": {"coordinates":[-83.575394,41.645613],"type":"Point"}
}