{
  "type": "Feature",
  "properties": {
    "addr:full":"4522 State Rte 516 Dover OH 44622",
    "addr:housenumber":"4522",
    "addr:postcode":"44622",
    "addr:street":"State Rte 516",
    "iso:country":"US",
    "sg:address":"4522 State Rte 516",
    "sg:city":"Dover",
    "sg:classifiers":[
        {
            "category":"Farming",
            "subcategory":"Livestock Farm",
            "type":"Manufacturing & Wholesale Goods"
        }
    ],
    "sg:phone":"+1 330 343 5480",
    "sg:postcode":"44622",
    "sg:province":"OH",
    "sg:tags":[
        "equine"
    ],
    "wof:name":"Dean Auman Farm",
    "wof:placetype":"venue"
},
  "geometry": {"coordinates":[-81.54522900000001,40.543829],"type":"Point"}
}