{
  "type": "Feature",
  "properties": {
    "addr:full":"233 Union St Newark OH 43055",
    "addr:housenumber":"233",
    "addr:postcode":"43055",
    "addr:street":"Union St",
    "iso:country":"US",
    "sg:address":"233 Union St",
    "sg:city":"Newark",
    "sg:classifiers":[
        {
            "category":"Shopping",
            "subcategory":"Bicycles & Sporting Goods",
            "type":"Retail Goods"
        }
    ],
    "sg:phone":"+1 740 349 0992",
    "sg:postcode":"43055",
    "sg:province":"OH",
    "sg:tags":[
        "tackle",
        "fishing"
    ],
    "wof:name":"Bob's Outdoor Supply",
    "wof:placetype":"venue"
},
  "geometry": {"coordinates":[-82.42138199999999,40.047287],"type":"Point"}
}