{
  "type": "Feature",
  "properties": {
    "addr:full":"1193 Debord Rd Chillicothe OH 45601",
    "addr:housenumber":"1193",
    "addr:postcode":"45601",
    "addr:street":"Debord Rd",
    "iso:country":"US",
    "sg:address":"1193 Debord Rd",
    "sg:city":"Chillicothe",
    "sg:classifiers":[
        {
            "category":"Sports & Exercise",
            "subcategory":"Golf",
            "type":"Entertainment"
        }
    ],
    "sg:phone":"+1 740 663 2700",
    "sg:postcode":"45601",
    "sg:province":"OH",
    "sg:tags":[
        "course",
        "public"
    ],
    "wof:name":"Dogwood Hills Golf Course",
    "wof:placetype":"venue"
},
  "geometry": {"coordinates":[-82.99702499999999,39.198283],"type":"Point"}
}