{
  "type": "Feature",
  "properties": {
    "addr:full":"555 Anthony Wayne Trl Waterville OH 43566",
    "addr:housenumber":"555",
    "addr:postcode":"43566",
    "addr:street":"Anthony Wayne Trl",
    "iso:country":"US",
    "sg:address":"555 Anthony Wayne Trl",
    "sg:city":"Waterville",
    "sg:classifiers":[
        {
            "category":"Health Services",
            "subcategory":"Hospital",
            "type":"Services"
        }
    ],
    "sg:phone":"+1 419 878 8279",
    "sg:postcode":"43566",
    "sg:province":"OH",
    "wof:name":"Riverside Mercy Hospital",
    "wof:placetype":"venue"
},
  "geometry": {"coordinates":[-83.728842,41.488914],"type":"Point"}
}