{
  "type": "Feature",
  "properties": {
    "iso:country":"US",
    "sg:address":"13055 Chillicothe Rd",
    "sg:city":"Chesterland",
    "sg:classifiers":[
        {
            "category":"Organizations",
            "subcategory":"Religious Organization",
            "type":"Services"
        }
    ],
    "sg:phone":"+1 440 729 0292",
    "sg:postcode":"44026",
    "sg:province":"OH",
    "sg:tags":[
        "clergy"
    ],
    "wof:name":"St Anselm's Convent",
    "wof:placetype":"venue"
},
  "geometry": {"coordinates":[-81.339046,41.509653],"type":"Point"}
}