{
  "type": "Feature",
  "properties": {
    "addr:full":"3115 Woodbury Rd Cleveland OH 44120",
    "addr:housenumber":"3115",
    "addr:postcode":"44120",
    "addr:street":"Woodbury Rd",
    "iso:country":"US",
    "sg:address":"3115 Woodbury Rd",
    "sg:city":"Cleveland",
    "sg:classifiers":[
        {
            "category":"Social Services",
            "subcategory":"Child Care",
            "type":"Services"
        }
    ],
    "sg:phone":"+1 216 752 3251",
    "sg:postcode":"44120",
    "sg:province":"OH",
    "sg:tags":[
        "kindergarten",
        "academic",
        "school"
    ],
    "wof:name":"Shaker Heights Recreation Care",
    "wof:placetype":"venue"
},
  "geometry": {"coordinates":[-81.574991,41.477418],"type":"Point"}
}