{
  "type": "Feature",
  "properties": {
    "addr:full":"556 Lawnview Ave Painesville OH 44077",
    "addr:housenumber":"556",
    "addr:postcode":"44077",
    "addr:street":"Lawnview Ave",
    "iso:country":"US",
    "sg:address":"556 Lawnview Ave",
    "sg:city":"Painesville",
    "sg:classifiers":[
        {
            "category":"Organizations",
            "subcategory":"Religious Organization",
            "type":"Services"
        }
    ],
    "sg:phone":"+1 440 354 4056",
    "sg:postcode":"44077",
    "sg:province":"OH",
    "sg:tags":[
        "church"
    ],
    "wof:name":"Calvary CME Church",
    "wof:placetype":"venue"
},
  "geometry": {"coordinates":[-81.255698,41.729022],"type":"Point"}
}