{
  "type": "Feature",
  "properties": {
    "addr:full":"10735 Ravenna Rd Twinsburg OH 44087",
    "addr:housenumber":"10735",
    "addr:postcode":"44087",
    "addr:street":"Ravenna Rd",
    "iso:country":"US",
    "sg:address":"10735 Ravenna Rd",
    "sg:city":"Twinsburg",
    "sg:classifiers":[
        {
            "category":"Restaurant",
            "type":"Food & Drink"
        }
    ],
    "sg:phone":"+1 330 963 3888",
    "sg:postcode":"44087",
    "sg:province":"OH",
    "wof:name":"China Moon",
    "wof:placetype":"venue"
},
  "geometry": {"coordinates":[-81.47138699999999,41.33544],"type":"Point"}
}