{
  "type": "Feature",
  "properties": {
    "iso:country":"US",
    "sg:address":"229 W 7th St",
    "sg:city":"Cincinnati",
    "sg:classifiers":[
        {
            "category":"Government",
            "subcategory":"Office",
            "type":"Public Place"
        }
    ],
    "sg:phone":"+1 513 784 5787",
    "sg:postcode":"45202",
    "sg:province":"OH",
    "sg:tags":[
        "space"
    ],
    "wof:name":"Converbys Inc",
    "wof:placetype":"venue"
},
  "geometry": {"coordinates":[-84.516958,39.103129],"type":"Point"}
}