{
  "type": "Feature",
  "properties": {
    "iso:country":"US",
    "sg:address":"304 W 3rd St",
    "sg:city":"Greenville",
    "sg:classifiers":[
        {
            "category":"Travel",
            "subcategory":"Hotels & Motels",
            "type":"Entertainment"
        }
    ],
    "sg:phone":"+1 937 548 3448",
    "sg:postcode":"45331",
    "sg:province":"OH",
    "sg:tags":[
        "breakfast",
        "accommodation",
        "bed"
    ],
    "wof:name":"Waring House",
    "wof:placetype":"venue"
},
  "geometry": {"coordinates":[-84.635074,40.099908],"type":"Point"}
}