{
  "type": "Feature",
  "properties": {
    "addr:full": "14443 Cedar Rd Cleveland OH 44121",
    "addr:housenumber": "14443",
    "addr:postcode": "44121",
    "addr:street": "Cedar Rd",
    "iso:country": "US",
    "sg:address": "14443 Cedar Rd",
    "sg:city": "Cleveland",
    "sg:classifiers": [
      {
        "category": "Health Services",
        "subcategory": "Medical Lab",
        "type": "Services"
      }
    ],
    "sg:phone": "+1 216 382 2121",
    "sg:postcode": "44121",
    "sg:province": "OH",
    "sg:tags": [
      "laboratory",
      "dental"
    ],
    "wof:name": "Mark Kriwinsky DDS",
    "wof:placetype": "venue"
  },
  "geometry": {"coordinates":[-81.520282,41.501432],"type":"Point"}
}
