{
  "type": "Feature",
  "properties": {
    "iso:country":"US",
    "sg:address":"11445 Glynwood Rd",
    "sg:city":"Wapakoneta",
    "sg:phone":"+1 419 738 6332",
    "sg:postcode":"45895",
    "sg:province":"OH",
    "sg:tags":[
        "farm",
        "corn",
        "wheat",
        "soybean"
    ],
    "wof:name":"Dale Altstaetter",
    "wof:placetype":"venue"
},
  "geometry": {"coordinates":[-84.230236,40.585493],"type":"Point"}
}