{
  "type": "Feature",
  "properties": {
    "addr:full": "1791 N US Hwy 68 Wilmington OH 45177",
    "addr:housenumber": "1791",
    "addr:postcode": "45177",
    "addr:street": "N Us Hwy 68",
    "iso:country": "US",
    "sg:address": "1791 N US Hwy 68",
    "sg:city": "Wilmington",
    "sg:classifiers": [
      {
        "category": "Organizations",
        "subcategory": "Religious Organization",
        "type": "Services"
      }
    ],
    "sg:phone": "+1 937 382 5998",
    "sg:postcode": "45177",
    "sg:province": "OH",
    "sg:tags": [
      "church"
    ],
    "wof:name": "Faith Baptist Church",
    "wof:placetype": "venue"
  },
  "geometry": {"coordinates":[-83.838396,39.471364],"type":"Point"}
}
