{
  "type": "Feature",
  "properties": {
    "addr:full": "52 Starling St Columbus OH 43215",
    "addr:housenumber": "52",
    "addr:postcode": "43215",
    "addr:street": "Starling St",
    "iso:country": "US",
    "sg:address": "52 Starling St",
    "sg:city": "Columbus",
    "sg:classifiers": [
      {
        "category": "Professional",
        "type": "Services"
      }
    ],
    "sg:phone": "+1 614 365 6701",
    "sg:postcode": "43215",
    "sg:province": "OH",
    "sg:tags": [
      "establishment"
    ],
    "wof:name": "Central Ohio Regional Teacher",
    "wof:placetype": "venue"
  },
  "geometry": {"coordinates":[-83.009928,39.959326],"type":"Point"}
}
