{
  "type": "Feature",
  "properties": {
    "iso:country":"US",
    "sg:address":"50 Blackberry Dr",
    "sg:city":"Hudson",
    "sg:classifiers":[
        {
            "category":"Wholesale",
            "subcategory":"Machinery & Supplies",
            "type":"Manufacturing & Wholesale Goods"
        }
    ],
    "sg:phone":"+1 330 656 9766",
    "sg:postcode":"44236",
    "sg:province":"OH",
    "sg:tags":[
        "equipment",
        "industrial"
    ],
    "wof:name":"Penetone",
    "wof:placetype":"venue"
},
  "geometry": {"coordinates":[-81.449489,41.250056],"type":"Point"}
}