{
  "type": "Feature",
  "properties": {
    "iso:country":"US",
    "sg:address":"11328 Lagrange Rd",
    "sg:city":"Elyria",
    "sg:classifiers":[
        {
            "category":"Retail",
            "subcategory":"Auto Repair",
            "type":"Services"
        }
    ],
    "sg:phone":"+1 440 458 4111",
    "sg:postcode":"44035",
    "sg:province":"OH",
    "wof:name":"Motor Heads",
    "wof:placetype":"venue"
},
  "geometry": {"coordinates":[-82.117639,41.324798],"type":"Point"}
}