{
  "type": "Feature",
  "properties": {
    "addr:full": "3630 Cinnamon Way Westlake OH 44145",
    "addr:housenumber": "3630",
    "addr:postcode": "44145",
    "addr:street": "Cinnamon Way",
    "iso:country": "US",
    "sg:address": "3630 Cinnamon Way",
    "sg:city": "Westlake",
    "sg:classifiers": [
      {
        "category": "Restaurant",
        "type": "Food \u0026 Drink"
      }
    ],
    "sg:phone": "+1 440 777 2818",
    "sg:postcode": "44145",
    "sg:province": "OH",
    "wof:name": "Martinis",
    "wof:placetype": "venue"
  },
  "geometry": {"coordinates":[-81.910264,41.436999],"type":"Point"}
}
