{
  "type": "Feature",
  "properties": {
    "addr:full":"9109 Montgomery Rd Cincinnati OH 45242",
    "addr:housenumber":"9109",
    "addr:postcode":"45242",
    "addr:street":"Montgomery Rd",
    "iso:country":"US",
    "sg:address":"9109 Montgomery Rd",
    "sg:city":"Cincinnati",
    "sg:classifiers":[
        {
            "category":"Professional",
            "subcategory":"Accounting & Tax Preparation",
            "type":"Services"
        }
    ],
    "sg:phone":"+1 513 984 3971",
    "sg:postcode":"45242",
    "sg:province":"OH",
    "sg:tags":[
        "accountant"
    ],
    "wof:name":"Dolores M Angel CPA",
    "wof:placetype":"venue"
},
  "geometry": {"coordinates":[-84.357266,39.219968],"type":"Point"}
}