{
  "type": "Feature",
  "properties": {
    "addr:full": "8203 W Chester Rd West Chester OH 45069",
    "addr:housenumber": "8203",
    "addr:postcode": "45069",
    "addr:street": "W Chester Rd",
    "iso:country": "US",
    "sg:address": "8203 W Chester Rd",
    "sg:city": "West Chester",
    "sg:classifiers": [
      {
        "category": "Building \u0026 Trades",
        "subcategory": "Construction",
        "type": "Services"
      }
    ],
    "sg:phone": "+1 513 755 9180",
    "sg:postcode": "45069",
    "sg:province": "OH",
    "sg:tags": [
      "handyman"
    ],
    "wof:name": "West Chester Home Improvements",
    "wof:placetype": "venue"
  },
  "geometry": {"coordinates":[-84.356338,39.317539],"type":"Point"}
}
