{
  "type": "Feature",
  "properties": {
    "iso:country":"US",
    "sg:address":"3598 Herr Fieldhouse Rd",
    "sg:city":"Southington",
    "sg:classifiers":[
        {
            "category":"Personal",
            "subcategory":"Beauty Salon",
            "type":"Services"
        }
    ],
    "sg:phone":"+1 330 898 6666",
    "sg:postcode":"44470",
    "sg:province":"OH",
    "wof:name":"Betsy's Beauty World",
    "wof:placetype":"venue"
},
  "geometry": {"coordinates":[-80.930525,41.272072],"type":"Point"}
}