{
  "type": "Feature",
  "properties": {
    "iso:country":"US",
    "sg:address":"145 N South St",
    "sg:city":"Wilmington",
    "sg:classifiers":[
        {
            "category":"Professional",
            "subcategory":"Lawyer & Legal Services",
            "type":"Services"
        }
    ],
    "sg:phone":"+1 937 382 0946",
    "sg:postcode":"45177",
    "sg:province":"OH",
    "sg:tags":[
        "firm",
        "law"
    ],
    "wof:name":"Buckley Miller & Wright",
    "wof:placetype":"venue"
},
  "geometry": {"coordinates":[-83.828526,39.446972],"type":"Point"}
}