{
  "type": "Feature",
  "properties": {
    "addr:full": "145 N South St Wilmington OH 45177",
    "addr:housenumber": "145",
    "addr:postcode": "45177",
    "addr:street": "N South St",
    "iso:country": "US",
    "sg:address": "145 N South St",
    "sg:city": "Wilmington",
    "sg:classifiers": [
      {
        "category": "Professional",
        "subcategory": "Lawyer \u0026 Legal Services",
        "type": "Services"
      }
    ],
    "sg:phone": "+1 937 382 0946",
    "sg:postcode": "45177",
    "sg:province": "OH",
    "sg:tags": [
      "firm",
      "law"
    ],
    "wof:name": "Buckley Miller \u0026 Wright",
    "wof:placetype": "venue"
  },
  "geometry": {"coordinates":[-83.828526,39.446972],"type":"Point"}
}
