{
  "type": "Feature",
  "properties": {
    "addr:full": "2650 Maysville Pike Zanesville OH 43701",
    "addr:postcode": "2650;43701",
    "addr:street": "Maysville Pike",
    "iso:country": "US",
    "sg:address": "2650 Maysville Pike",
    "sg:city": "Zanesville",
    "sg:classifiers": [
      {
        "category": "Autos \u0026 Motor Vehicles",
        "subcategory": "Motorcycle Sales",
        "type": "Retail Goods"
      }
    ],
    "sg:phone": "+1 740 454 0010",
    "sg:postcode": "43701",
    "sg:province": "OH",
    "sg:tags": [
      "automobile",
      "scooter"
    ],
    "wof:name": "Fink's Harley-Davidson",
    "wof:placetype": "venue"
  },
  "geometry": {"coordinates":[-82.042147,39.894423],"type":"Point"}
}
