{
  "type": "Feature",
  "properties": {
    "addr:full":"822 S Metcalf St Lima OH 45804",
    "addr:housenumber":"822",
    "addr:postcode":"45804",
    "addr:street":"S Metcalf St",
    "iso:country":"US",
    "sg:address":"822 S Metcalf St",
    "sg:city":"Lima",
    "sg:classifiers":[
        {
            "category":"Food & Beverages",
            "subcategory":"Bakery",
            "type":"Retail Goods"
        }
    ],
    "sg:phone":"+1 419 222 3121",
    "sg:postcode":"45804",
    "sg:province":"OH",
    "sg:tags":[
        "doughnut"
    ],
    "wof:name":"Mello-Creme Donuts",
    "wof:placetype":"venue"
},
  "geometry": {"coordinates":[-84.11340300000001,40.729077],"type":"Point"}
}