{
  "type": "Feature",
  "properties": {
    "addr:full": "1840 Town Park Blvd Uniontown OH 44685",
    "addr:housenumber": "1840",
    "addr:postcode": "44685",
    "addr:street": "Town Park Blvd",
    "iso:country": "US",
    "sg:address": "1840 Town Park Blvd",
    "sg:city": "Uniontown",
    "sg:classifiers": [
      {
        "category": "Restaurant",
        "type": "Food \u0026 Drink"
      }
    ],
    "sg:menulink": "http://www.allmenus.com/oh/green/79197-pizza-hut/menu/",
    "sg:phone": "+1 330 899 0000",
    "sg:postcode": "44685",
    "sg:province": "OH",
    "sg:tags": [
      "american",
      "pizza"
    ],
    "wof:name": "Pizza Hut",
    "wof:placetype": "venue"
  },
  "geometry": {"coordinates":[-81.466801,40.950574],"type":"Point"}
}
