{
  "type": "Feature",
  "properties": {
    "addr:full": "7545 Winding Way Tipp City OH 45371",
    "addr:housenumber": "7545",
    "addr:postcode": "45371",
    "addr:street": "Winding Way",
    "iso:country": "US",
    "sg:address": "7545 Winding Way",
    "sg:city": "Tipp City",
    "sg:classifiers": [
      {
        "category": "Professional",
        "subcategory": "Lawyer \u0026 Legal Services",
        "type": "Services"
      }
    ],
    "sg:phone": "+1 937 667 5599",
    "sg:postcode": "45371",
    "sg:province": "OH",
    "sg:tags": [
      "attorney"
    ],
    "wof:name": "John R Mohr",
    "wof:placetype": "venue"
  },
  "geometry": {"coordinates":[-84.177433,39.927585],"type":"Point"}
}
