{
  "type": "Feature",
  "properties": {
    "iso:country":"US",
    "sg:address":"7545 Winding Way",
    "sg:city":"Tipp City",
    "sg:classifiers":[
        {
            "category":"Professional",
            "subcategory":"Lawyer & Legal Services",
            "type":"Services"
        }
    ],
    "sg:phone":"+1 937 667 5599",
    "sg:postcode":"45371",
    "sg:province":"OH",
    "sg:tags":[
        "attorney"
    ],
    "wof:name":"John R Mohr",
    "wof:placetype":"venue"
},
  "geometry": {"coordinates":[-84.17743299999999,39.927585],"type":"Point"}
}