{
  "type": "Feature",
  "properties": {
    "addr:full":"135 N Water St Fort Jennings OH 45844",
    "addr:housenumber":"135",
    "addr:postcode":"45844",
    "addr:street":"N Water St",
    "iso:country":"US",
    "sg:address":"135 N Water St",
    "sg:city":"Fort Jennings",
    "sg:classifiers":[
        {
            "category":"Organizations",
            "subcategory":"Religious Organization",
            "type":"Services"
        }
    ],
    "sg:phone":"+1 419 286 2132",
    "sg:postcode":"45844",
    "sg:province":"OH",
    "sg:tags":[
        "church"
    ],
    "sg:website":"www.stjosephfj.com",
    "wof:name":"St Joseph's Catholic Church",
    "wof:placetype":"venue"
},
  "geometry": {"coordinates":[-84.29847599999999,40.903629],"type":"Point"}
}