{
  "type": "Feature",
  "properties": {
    "addr:full":"23293 Commerce Park Rd Cleveland OH 44122",
    "addr:housenumber":"23293",
    "addr:postcode":"44122",
    "addr:street":"Commerce Park Rd",
    "iso:country":"US",
    "sg:address":"23293 Commerce Park Rd",
    "sg:city":"Cleveland",
    "sg:classifiers":[
        {
            "category":"Professional",
            "subcategory":"Research",
            "type":"Services"
        },
        {
            "category":"Manufacturing",
            "subcategory":"Tools & Machinery",
            "type":"Manufacturing & Wholesale Goods"
        }
    ],
    "sg:phone":"+1 216 464 1255",
    "sg:postcode":"44122",
    "sg:province":"OH",
    "sg:tags":[
        "development",
        "oxygen",
        "generator",
        "supply",
        "hospital",
        "equipment"
    ],
    "wof:name":"I G R Enterprises Inc",
    "wof:placetype":"venue"
},
  "geometry": {"coordinates":[-81.506049,41.462109],"type":"Point"}
}