{
  "type": "Feature",
  "properties": {
    "addr:full":"56 Steven Dr Butler OH 44822",
    "addr:housenumber":"56",
    "addr:postcode":"44822",
    "addr:street":"Steven Dr",
    "iso:country":"US",
    "sg:address":"56 Steven Dr",
    "sg:city":"Butler",
    "sg:classifiers":[
        {
            "category":"Building & Trades",
            "subcategory":"Construction",
            "type":"Services"
        }
    ],
    "sg:phone":"+1 419 883 2269",
    "sg:postcode":"44822",
    "sg:province":"OH",
    "sg:tags":[
        "residential"
    ],
    "wof:name":"Bryant Enterprises",
    "wof:placetype":"venue"
},
  "geometry": {"coordinates":[-82.41748699999999,40.58563],"type":"Point"}
}