{
  "type": "Feature",
  "properties": {
    "iso:country":"US",
    "sg:address":"6355 Harrison Ave",
    "sg:city":"Cincinnati",
    "sg:classifiers":[
        {
            "category":"Insurance",
            "subcategory":"Insurance Agent",
            "type":"Services"
        }
    ],
    "sg:phone":"+1 513 598 7200",
    "sg:postcode":"45247",
    "sg:province":"OH",
    "wof:name":"State Farm Insurance",
    "wof:placetype":"venue"
},
  "geometry": {"coordinates":[-84.658905,39.192117],"type":"Point"}
}