{
  "type": "Feature",
  "properties": {
    "addr:full":"8468 Pond Ridge Dr Maineville OH 45039",
    "addr:housenumber":"8468",
    "addr:postcode":"45039",
    "addr:street":"Pond Ridge Dr",
    "iso:country":"US",
    "sg:address":"8468 Pond Ridge Dr",
    "sg:city":"Maineville",
    "sg:classifiers":[
        {
            "category":"Home & Garden",
            "subcategory":"Home Furnishings",
            "type":"Retail Goods"
        }
    ],
    "sg:phone":"+1 513 683 2557",
    "sg:postcode":"45039",
    "sg:province":"OH",
    "wof:name":"Pampered Chef",
    "wof:placetype":"venue"
},
  "geometry": {"coordinates":[-84.26759300000001,39.314004],"type":"Point"}
}