{
  "type": "Feature",
  "properties": {
    "iso:country":"US",
    "sg:address":"18090 Miles Ave",
    "sg:city":"Cleveland",
    "sg:classifiers":[
        {
            "category":"Manufacturing",
            "subcategory":"Building Materials",
            "type":"Manufacturing & Wholesale Goods"
        }
    ],
    "sg:phone":"+1 216 475 5700",
    "sg:postcode":"44128",
    "sg:province":"OH",
    "sg:tags":[
        "steel",
        "door",
        "mfg",
        "garage",
        "wood",
        "overhead"
    ],
    "wof:name":"Anderson Door Co",
    "wof:placetype":"venue"
},
  "geometry": {"coordinates":[-81.551923,41.436607],"type":"Point"}
}