{
  "type": "Feature",
  "properties": {
    "addr:full": "18090 Miles Ave Cleveland OH 44128",
    "addr:housenumber": "18090",
    "addr:postcode": "44128",
    "addr:street": "Miles Ave",
    "iso:country": "US",
    "sg:address": "18090 Miles Ave",
    "sg:city": "Cleveland",
    "sg:classifiers": [
      {
        "category": "Manufacturing",
        "subcategory": "Building Materials",
        "type": "Manufacturing \u0026 Wholesale Goods"
      }
    ],
    "sg:phone": "+1 216 475 5700",
    "sg:postcode": "44128",
    "sg:province": "OH",
    "sg:tags": [
      "steel",
      "door",
      "mfg",
      "garage",
      "wood",
      "overhead"
    ],
    "wof:name": "Anderson Door Co",
    "wof:placetype": "venue"
  },
  "geometry": {"coordinates":[-81.551923,41.436607],"type":"Point"}
}
