{
  "type": "Feature",
  "properties": {
    "iso:country":"US",
    "sg:address":"4010 Alum Creek Dr",
    "sg:city":"Columbus",
    "sg:classifiers":[
        {
            "category":"Banks & Credit Unions",
            "subcategory":"Bank",
            "type":"Services"
        }
    ],
    "sg:phone":"+1 614 497 9322",
    "sg:postcode":"43207",
    "sg:province":"OH",
    "sg:tags":[
        "cashing",
        "check"
    ],
    "wof:name":"Fast Check Cash In Advance",
    "wof:placetype":"venue"
},
  "geometry": {"coordinates":[-82.93044500000001,39.885416],"type":"Point"}
}