{
  "type": "Feature",
  "properties": {
    "addr:full":"19865 Detroit Rd Cleveland OH 44116",
    "addr:housenumber":"19865",
    "addr:postcode":"44116",
    "addr:street":"Detroit Rd",
    "iso:country":"US",
    "sg:address":"19865 Detroit Rd",
    "sg:city":"Cleveland",
    "sg:classifiers":[
        {
            "category":"Bars & Pubs",
            "type":"Food & Drink"
        }
    ],
    "sg:phone":"+1 440 333 1609",
    "sg:postcode":"44116",
    "sg:province":"OH",
    "wof:name":"Linden Tavern",
    "wof:placetype":"venue"
},
  "geometry": {"coordinates":[-81.84241900000001,41.479148],"type":"Point"}
}