{
  "type": "Feature",
  "properties": {
    "iso:country":"US",
    "sg:address":"854 Wilson Ave",
    "sg:city":"Youngstown",
    "sg:classifiers":[
        {
            "category":"Organizations",
            "subcategory":"Religious Organization",
            "type":"Services"
        }
    ],
    "sg:phone":"+1 330 743 1905",
    "sg:postcode":"44506",
    "sg:province":"OH",
    "wof:name":"St Stephen Of Hungary Church",
    "wof:placetype":"venue"
},
  "geometry": {"coordinates":[-80.633115,41.092191],"type":"Point"}
}