{
  "type": "Feature",
  "properties": {
    "addr:full": "834 Ohio Pike Cincinnati OH 45245",
    "addr:housenumber": "834",
    "addr:postcode": "45245",
    "addr:street": "Ohio Pike",
    "iso:country": "US",
    "sg:address": "834 Ohio Pike",
    "sg:city": "Cincinnati",
    "sg:classifiers": [
      {
        "category": "Real Estate",
        "subcategory": "Real Estate Operator",
        "type": "Services"
      }
    ],
    "sg:phone": "+1 513 752 6100",
    "sg:postcode": "45245",
    "sg:province": "OH",
    "sg:tags": [
      "dwelling"
    ],
    "wof:name": "Mc Clorey and Mc Clorey",
    "wof:placetype": "venue"
  },
  "geometry": {"coordinates":[-84.278913,39.064528],"type":"Point"}
}
