{
  "type": "Feature",
  "properties": {
    "iso:country":"US",
    "sg:address":"175 Lyness Ave",
    "sg:city":"Harrison",
    "sg:classifiers":[
        {
            "category":"Health Services",
            "subcategory":"Doctor",
            "type":"Services"
        }
    ],
    "sg:phone":"+1 513 367 2121",
    "sg:postcode":"45030",
    "sg:province":"IN",
    "sg:tags":[
        "dentist"
    ],
    "wof:name":"Nicholas F Staarmann DDS",
    "wof:placetype":"venue"
},
  "geometry": {"coordinates":[-84.797727,39.252186],"type":"Point"}
}