{
  "type": "Feature",
  "properties": {
    "addr:full":"3776 Rocky River Dr Cleveland OH 44111",
    "addr:housenumber":"3776",
    "addr:postcode":"44111",
    "addr:street":"Rocky River Dr",
    "iso:country":"US",
    "sg:address":"3776 Rocky River Dr",
    "sg:city":"Cleveland",
    "sg:classifiers":[
        {
            "category":"Shopping",
            "subcategory":"Clothing, Apparel, & Fashions",
            "type":"Retail Goods"
        }
    ],
    "sg:phone":"+1 216 671 4377",
    "sg:postcode":"44111",
    "sg:province":"OH",
    "sg:tags":[
        "store"
    ],
    "wof:name":"Dots Inc",
    "wof:placetype":"venue"
},
  "geometry": {"coordinates":[-81.816772,41.450634],"type":"Point"}
}