{
  "type": "Feature",
  "properties": {
    "addr:full": "1391 Arrowhead Dr Maumee OH 43537",
    "addr:housenumber": "1391",
    "addr:postcode": "43537",
    "addr:street": "Arrowhead Dr",
    "iso:country": "US",
    "sg:address": "1391 Arrowhead Dr",
    "sg:city": "Maumee",
    "sg:classifiers": [
      {
        "category": "Restaurant",
        "type": "Food \u0026 Drink"
      }
    ],
    "sg:menulink": "http://www.allmenus.com/oh/maumee/10873-max--ermas/menu/",
    "sg:phone": "+1 419 897 7780",
    "sg:postcode": "43537",
    "sg:province": "OH",
    "sg:tags": [
      "american"
    ],
    "wof:name": "Max \u0026 Erma's",
    "wof:placetype": "venue"
  },
  "geometry": {"coordinates":[-83.68583,41.578892],"type":"Point"}
}
