{
  "type": "Feature",
  "properties": {
    "addr:full":"385 Circleville Ave Ashville OH 43103",
    "addr:housenumber":"385",
    "addr:postcode":"43103",
    "addr:street":"Circleville Ave",
    "iso:country":"US",
    "sg:address":"385 Circleville Ave",
    "sg:city":"Ashville",
    "sg:classifiers":[
        {
            "category":"Education",
            "subcategory":"School",
            "type":"Public Place"
        }
    ],
    "sg:phone":"+1 740 983 4111",
    "sg:postcode":"43103",
    "sg:province":"OH",
    "wof:name":"Teays Valley Local Schls Bus",
    "wof:placetype":"venue"
},
  "geometry": {"coordinates":[-82.943653,39.718999],"type":"Point"}
}