{
  "type": "Feature",
  "properties": {
    "addr:full": "1302 Rombach Ave Wilmington OH 45177",
    "addr:housenumber": "1302",
    "addr:postcode": "45177",
    "addr:street": "Rombach Ave",
    "iso:country": "US",
    "sg:address": "1302 Rombach Ave",
    "sg:city": "Wilmington",
    "sg:classifiers": [
      {
        "category": "Shopping",
        "subcategory": "Discount \u0026 Variety Stores",
        "type": "Retail Goods"
      }
    ],
    "sg:phone": "+1 937 382 8863",
    "sg:postcode": "45177",
    "sg:province": "OH",
    "sg:website": "www.biglots.com",
    "wof:name": "Big Lots",
    "wof:placetype": "venue"
  },
  "geometry": {"coordinates":[-83.803461,39.44907],"type":"Point"}
}
