{
  "type": "Feature",
  "properties": {
    "addr:full":"654 Scioto St Urbana OH 43078",
    "addr:housenumber":"654",
    "addr:postcode":"43078",
    "addr:street":"Scioto St",
    "iso:country":"US",
    "sg:address":"654 Scioto St",
    "sg:city":"Urbana",
    "sg:classifiers":[
        {
            "category":"Autos & Motor Vehicles",
            "subcategory":"Auto Supplies",
            "type":"Retail Goods"
        }
    ],
    "sg:phone":"+1 937 652 2789",
    "sg:postcode":"43078",
    "sg:province":"OH",
    "sg:tags":[
        "parts"
    ],
    "wof:name":"Autozone",
    "wof:placetype":"venue"
},
  "geometry": {"coordinates":[-83.738303,40.107295],"type":"Point"}
}