{
  "type": "Feature",
  "properties": {
    "addr:full": "18516 Detroit Ave Cleveland OH 44107",
    "addr:housenumber": "18516",
    "addr:postcode": "44107",
    "addr:street": "Detroit Ave",
    "iso:country": "US",
    "sg:address": "18516 Detroit Ave",
    "sg:city": "Cleveland",
    "sg:classifiers": [
      {
        "category": "Building \u0026 Trades",
        "subcategory": "Construction",
        "type": "Services"
      }
    ],
    "sg:phone": "+1 216 228 7950",
    "sg:postcode": "44107",
    "sg:province": "OH",
    "sg:tags": [
      "general",
      "contractor"
    ],
    "wof:name": "Thompson Builders Inc",
    "wof:placetype": "venue"
  },
  "geometry": {"coordinates":[-81.827373,41.481749],"type":"Point"}
}
