{
  "type": "Feature",
  "properties": {
    "iso:country":"US",
    "sg:address":"300 Overlook Dr",
    "sg:city":"Piketon",
    "sg:classifiers":[
        {
            "category":"Health Services",
            "subcategory":"Nursing And Care Facility",
            "type":"Services"
        }
    ],
    "sg:phone":"+1 740 289 4074",
    "sg:postcode":"45661",
    "sg:province":"OH",
    "sg:tags":[
        "home",
        "convalescent"
    ],
    "wof:name":"Piketon Nursing Ctr",
    "wof:placetype":"venue"
},
  "geometry": {"coordinates":[-82.987279,39.069556],"type":"Point"}
}