{
  "type": "Feature",
  "properties": {
    "iso:country":"US",
    "sg:address":"118 S Washington St",
    "sg:city":"Tiffin",
    "sg:classifiers":[
        {
            "category":"Shopping",
            "subcategory":"Bicycles & Sporting Goods",
            "type":"Retail Goods"
        }
    ],
    "sg:phone":"+1 419 443 8683",
    "sg:postcode":"44883",
    "sg:province":"OH",
    "wof:name":"G T Cycling & Fitness",
    "wof:placetype":"venue"
},
  "geometry": {"coordinates":[-83.176605,41.114275],"type":"Point"}
}