{
  "type": "Feature",
  "properties": {
    "addr:full":"14902 Clifton Blvd Cleveland OH 44107",
    "addr:housenumber":"14902",
    "addr:postcode":"44107",
    "addr:street":"Clifton Blvd",
    "iso:country":"US",
    "sg:address":"14902 Clifton Blvd",
    "sg:city":"Cleveland",
    "sg:classifiers":[
        {
            "category":"Professional",
            "type":"Services"
        }
    ],
    "sg:phone":"+1 216 228 9225",
    "sg:postcode":"44107",
    "sg:province":"OH",
    "sg:tags":[
        "establishment"
    ],
    "wof:name":"AMG",
    "wof:placetype":"venue"
},
  "geometry": {"coordinates":[-81.801435,41.491912],"type":"Point"}
}