{
  "type": "Feature",
  "properties": {
    "addr:full": "3783 N High St Columbus OH 43214",
    "addr:housenumber": "3783",
    "addr:postcode": "43214",
    "addr:street": "N High St",
    "iso:country": "US",
    "sg:address": "3783 N High St",
    "sg:city": "Columbus",
    "sg:classifiers": [
      {
        "category": "Health Services",
        "subcategory": "Doctor",
        "type": "Services"
      }
    ],
    "sg:phone": "+1 614 268 2237",
    "sg:postcode": "43214",
    "sg:province": "OH",
    "sg:tags": [
      "dentist"
    ],
    "wof:name": "Whetstone Dental Group",
    "wof:placetype": "venue"
  },
  "geometry": {"coordinates":[-83.017933,40.03937],"type":"Point"}
}
