{
  "type": "Feature",
  "properties": {
    "iso:country":"US",
    "sg:address":"2220 S Yellow Springs St",
    "sg:city":"Springfield",
    "sg:classifiers":[
        {
            "category":"Autos & Motor Vehicles",
            "subcategory":"Automobile Sales",
            "type":"Retail Goods"
        }
    ],
    "sg:phone":"+1 937 325 3331",
    "sg:postcode":"45506",
    "sg:province":"OH",
    "sg:tags":[
        "used"
    ],
    "wof:name":"Just Wheels Used Cars",
    "wof:placetype":"venue"
},
  "geometry": {"coordinates":[-83.831667,39.89855],"type":"Point"}
}