{
  "type": "Feature",
  "properties": {
    "iso:country":"US",
    "sg:address":"8700 Akins Rd",
    "sg:city":"Cleveland",
    "sg:classifiers":[
        {
            "category":"Retail",
            "subcategory":"Car Wash",
            "type":"Services"
        }
    ],
    "sg:phone":"+1 440 582 5252",
    "sg:postcode":"44133",
    "sg:province":"OH",
    "sg:tags":[
        "automobile",
        "detail",
        "clean"
    ],
    "wof:name":"Artistic Auto",
    "wof:placetype":"venue"
},
  "geometry": {"coordinates":[-81.75253600000001,41.306519],"type":"Point"}
}