{
  "type": "Feature",
  "properties": {
    "addr:full": "1224 N State Rte 133 Blanchester OH 45107",
    "addr:housenumber": "1224",
    "addr:postcode": "45107",
    "addr:street": "N State Rte 133",
    "iso:country": "US",
    "sg:address": "1224 N State Rte 133",
    "sg:city": "Blanchester",
    "sg:classifiers": [
      {
        "category": "Organizations",
        "subcategory": "Religious Organization",
        "type": "Services"
      }
    ],
    "sg:phone": "+1 937 783 2796",
    "sg:postcode": "45107",
    "sg:province": "OH",
    "sg:tags": [
      "church"
    ],
    "wof:name": "Kingdom Hall-Jehovah's Witness",
    "wof:placetype": "venue"
  },
  "geometry": {"coordinates":[-83.986544,39.310213],"type":"Point"}
}
