{
  "type": "Feature",
  "properties": {
    "iso:country":"US",
    "sg:address":"1224 N State Rte 133",
    "sg:city":"Blanchester",
    "sg:classifiers":[
        {
            "category":"Organizations",
            "subcategory":"Religious Organization",
            "type":"Services"
        }
    ],
    "sg:phone":"+1 937 783 2796",
    "sg:postcode":"45107",
    "sg:province":"OH",
    "sg:tags":[
        "church"
    ],
    "wof:name":"Kingdom Hall-Jehovah's Witness",
    "wof:placetype":"venue"
},
  "geometry": {"coordinates":[-83.98654399999999,39.310213],"type":"Point"}
}