{
  "type": "Feature",
  "properties": {
    "iso:country":"US",
    "sg:address":"15602 State Rte 67",
    "sg:city":"Kenton",
    "sg:classifiers":[
        {
            "category":"Manufacturing",
            "subcategory":"Tools & Machinery",
            "type":"Manufacturing & Wholesale Goods"
        }
    ],
    "sg:phone":"+1 419 673 0411",
    "sg:postcode":"43326",
    "sg:province":"OH",
    "sg:tags":[
        "electrical",
        "mfg"
    ],
    "wof:name":"Watts Electric Co",
    "wof:placetype":"venue"
},
  "geometry": {"coordinates":[-83.577021,40.657088],"type":"Point"}
}