{
  "type": "Feature",
  "properties": {
    "iso:country":"US",
    "sg:address":"219 Winfield Dr",
    "sg:city":"Bowling Green",
    "sg:classifiers":[
        {
            "category":"Building & Trades",
            "subcategory":"Construction",
            "type":"Services"
        }
    ],
    "sg:phone":"+1 419 353 3090",
    "sg:postcode":"43402",
    "sg:province":"OH",
    "sg:tags":[
        "contractor"
    ],
    "wof:name":"Romag Construction & Rmdlng",
    "wof:placetype":"venue"
},
  "geometry": {"coordinates":[-83.661025,41.371817],"type":"Point"}
}