{
  "type": "Feature",
  "properties": {
    "addr:full":"3545 S High St Columbus OH 43207",
    "addr:housenumber":"3545",
    "addr:postcode":"43207",
    "addr:street":"S High St",
    "iso:country":"US",
    "sg:address":"3545 S High St",
    "sg:city":"Columbus",
    "sg:classifiers":[
        {
            "category":"Restaurant",
            "type":"Food & Drink"
        }
    ],
    "sg:phone":"+1 614 491 3536",
    "sg:postcode":"43207",
    "sg:province":"OH",
    "sg:website":"www.wendys.com",
    "wof:name":"Wendy's",
    "wof:placetype":"venue"
},
  "geometry": {"coordinates":[-83.00011499999999,39.88419],"type":"Point"}
}