{
  "type": "Feature",
  "properties": {
    "addr:full":"10653 Loveland Madeira Rd Loveland OH 45140",
    "addr:housenumber":"10653",
    "addr:postcode":"45140",
    "addr:street":"Loveland Madeira Rd",
    "iso:country":"US",
    "sg:address":"10653 Loveland Madeira Rd",
    "sg:city":"Loveland",
    "sg:classifiers":[
        {
            "category":"Restaurant",
            "type":"Food & Drink"
        }
    ],
    "sg:phone":"+1 513 583 0200",
    "sg:postcode":"45140",
    "sg:province":"OH",
    "sg:tags":[
        "eating"
    ],
    "wof:name":"Starbucks",
    "wof:placetype":"venue"
},
  "geometry": {"coordinates":[-84.296477,39.251695],"type":"Point"}
}