{
  "type": "Feature",
  "properties": {
    "addr:full": "7229 State Rte 9 Winona OH 44423",
    "addr:housenumber": "7229",
    "addr:postcode": "44423",
    "addr:street": "State Rte 9",
    "iso:country": "US",
    "sg:address": "7229 State Rte 9",
    "sg:city": "Winona",
    "sg:classifiers": [
      {
        "category": "Shopping",
        "subcategory": "Bicycles \u0026 Sporting Goods",
        "type": "Retail Goods"
      }
    ],
    "sg:phone": "+1 330 222 2484",
    "sg:postcode": "44423",
    "sg:province": "OH",
    "wof:name": "Sweat Shop",
    "wof:placetype": "venue"
  },
  "geometry": {"coordinates":[-80.925938,40.795933],"type":"Point"}
}
