{
  "type": "Feature",
  "properties": {
    "addr:full":"5795 Royalton Rd SW Lancaster OH 43130",
    "addr:housenumber":"5795",
    "addr:postcode":"43130",
    "addr:street":"Royalton Rd Sw",
    "iso:country":"US",
    "sg:address":"5795 Royalton Rd SW",
    "sg:city":"Lancaster",
    "sg:classifiers":[
        {
            "category":"Building & Trades",
            "subcategory":"Construction",
            "type":"Services"
        }
    ],
    "sg:phone":"+1 614 443 3638",
    "sg:postcode":"43130",
    "sg:province":"OH",
    "sg:tags":[
        "contractor"
    ],
    "wof:name":"Dorn Construction Co",
    "wof:placetype":"venue"
},
  "geometry": {"coordinates":[-82.71382199999999,39.72808],"type":"Point"}
}