{
  "type": "Feature",
  "properties": {
    "iso:country":"US",
    "sg:address":"2149 Sullivant Ave",
    "sg:city":"Columbus",
    "sg:classifiers":[
        {
            "category":"Shopping",
            "type":"Retail Goods"
        }
    ],
    "sg:phone":"+1 614 272 6222",
    "sg:postcode":"43223",
    "sg:province":"OH",
    "sg:tags":[
        "telephone",
        "cellular"
    ],
    "wof:name":"Wireless For Less",
    "wof:placetype":"venue"
},
  "geometry": {"coordinates":[-83.056084,39.946782],"type":"Point"}
}