{
  "type": "Feature",
  "properties": {
    "addr:full":"10 W Main St Norwalk OH 44857",
    "addr:housenumber":"10",
    "addr:postcode":"44857",
    "addr:street":"W Main St",
    "iso:country":"US",
    "sg:address":"10 W Main St",
    "sg:city":"Norwalk",
    "sg:classifiers":[
        {
            "category":"Social Services",
            "type":"Services"
        }
    ],
    "sg:phone":"+1 419 668 0269",
    "sg:postcode":"44857",
    "sg:province":"OH",
    "sg:tags":[
        "organization",
        "welfare"
    ],
    "wof:name":"United Way",
    "wof:placetype":"venue"
},
  "geometry": {"coordinates":[-82.61590200000001,41.242253],"type":"Point"}
}