{
  "type": "Feature",
  "properties": {
    "iso:country":"US",
    "sg:address":"474 Grant St",
    "sg:city":"Akron",
    "sg:classifiers":[
        {
            "category":"Personal",
            "type":"Services"
        }
    ],
    "sg:phone":"+1 330 376 7706",
    "sg:postcode":"44311",
    "sg:province":"OH",
    "sg:tags":[
        "child",
        "day",
        "care"
    ],
    "sg:website":"www.infolineinc.org",
    "wof:name":"Child Care Connection",
    "wof:placetype":"venue"
},
  "geometry": {"coordinates":[-81.51807100000001,41.070146],"type":"Point"}
}