{
  "type": "Feature",
  "properties": {
    "iso:country":"US",
    "sg:address":"3410 Canfield Rd",
    "sg:city":"Youngstown",
    "sg:classifiers":[
        {
            "category":"Shopping",
            "subcategory":"Clothing, Apparel, & Fashions",
            "type":"Retail Goods"
        }
    ],
    "sg:phone":"+1 330 759 3781",
    "sg:postcode":"44511",
    "sg:province":"OH",
    "wof:name":"Second Fiddle",
    "wof:placetype":"venue"
},
  "geometry": {"coordinates":[-80.708736,41.063298],"type":"Point"}
}