{
  "type": "Feature",
  "properties": {
    "iso:country":"US",
    "sg:address":"1000 Ford Cir",
    "sg:city":"Milford",
    "sg:classifiers":[
        {
            "category":"Professional",
            "subcategory":"Engineering",
            "type":"Services"
        }
    ],
    "sg:phone":"+1 513 248 5200",
    "sg:postcode":"45150",
    "sg:province":"OH",
    "sg:tags":[
        "consulting",
        "mechanical",
        "engineer"
    ],
    "wof:name":"Manta Corporation",
    "wof:placetype":"venue"
},
  "geometry": {"coordinates":[-84.252419,39.156543],"type":"Point"}
}