{
  "type": "Feature",
  "properties": {
    "iso:country":"US",
    "sg:address":"2633 8th St NE",
    "sg:city":"Canton",
    "sg:classifiers":[
        {
            "category":"Wholesale",
            "subcategory":"Machinery & Supplies",
            "type":"Manufacturing & Wholesale Goods"
        }
    ],
    "sg:phone":"+1 330 438 1728",
    "sg:postcode":"44704",
    "sg:province":"OH",
    "wof:name":"Lame & Carlson Machinery Svc",
    "wof:placetype":"venue"
},
  "geometry": {"coordinates":[-81.336471,40.80056],"type":"Point"}
}