{
  "type": "Feature",
  "properties": {
    "iso:country":"US",
    "sg:address":"7663 Fishel Dr S",
    "sg:city":"Dublin",
    "sg:classifiers":[
        {
            "category":"Building & Trades",
            "subcategory":"Construction",
            "type":"Services"
        }
    ],
    "sg:phone":"+1 614 761 7876",
    "sg:postcode":"43016",
    "sg:province":"OH",
    "sg:tags":[
        "contractor"
    ],
    "wof:name":"Huffer Restoration Inc",
    "wof:placetype":"venue"
},
  "geometry": {"coordinates":[-83.192092,40.102628],"type":"Point"}
}