{
  "type": "Feature",
  "properties": {
    "iso:country":"US",
    "sg:address":"7941 State Rte 45",
    "sg:city":"Lisbon",
    "sg:classifiers":[
        {
            "category":"Cinema",
            "subcategory":"Movie Rental",
            "type":"Entertainment"
        }
    ],
    "sg:phone":"+1 330 420 9691",
    "sg:postcode":"44432",
    "sg:province":"OH",
    "sg:tags":[
        "leasing",
        "video",
        "disc",
        "tape"
    ],
    "sg:website":"www.moviegallery.com",
    "wof:name":"Movie Gallery",
    "wof:placetype":"venue"
},
  "geometry": {"coordinates":[-80.773552,40.78437],"type":"Point"}
}