{
  "type": "Feature",
  "properties": {
    "addr:full":"112 N Fulton St Wauseon OH 43567",
    "addr:housenumber":"112",
    "addr:postcode":"43567",
    "addr:street":"N Fulton St",
    "iso:country":"US",
    "sg:address":"112 N Fulton St",
    "sg:city":"Wauseon",
    "sg:classifiers":[
        {
            "category":"Personal",
            "subcategory":"Beauty Salon",
            "type":"Services"
        }
    ],
    "sg:phone":"+1 419 335 6563",
    "sg:postcode":"43567",
    "sg:province":"OH",
    "wof:name":"Felipe Hair Design",
    "wof:placetype":"venue"
},
  "geometry": {"coordinates":[-84.14142,41.549072],"type":"Point"}
}