{
  "type": "Feature",
  "properties": {
    "addr:full": "3938 Bellevue Rd Toledo OH 43613",
    "addr:housenumber": "3938",
    "addr:postcode": "43613",
    "addr:street": "Bellevue Rd",
    "iso:country": "US",
    "sg:address": "3938 Bellevue Rd",
    "sg:city": "Toledo",
    "sg:classifiers": [
      {
        "category": "Organizations",
        "subcategory": "Labor Organization",
        "type": "Services"
      }
    ],
    "sg:phone": "+1 419 472 5736",
    "sg:postcode": "43613",
    "sg:province": "OH",
    "wof:name": "UAW",
    "wof:placetype": "venue"
  },
  "geometry": {"coordinates":[-83.595602,41.690437],"type":"Point"}
}
