{
  "type": "Feature",
  "properties": {
    "iso:country":"US",
    "sg:address":"393 E Town St",
    "sg:city":"Columbus",
    "sg:classifiers":[
        {
            "category":"Health Services",
            "subcategory":"Clinic",
            "type":"Services"
        },
        {
            "category":"Health Services",
            "subcategory":"Doctor",
            "type":"Services"
        }
    ],
    "sg:phone":"+1 614 469 0070",
    "sg:postcode":"43215",
    "sg:province":"OH",
    "sg:tags":[
        "medical",
        "specialty",
        "outpatient"
    ],
    "sg:website":"www.fmcna.com",
    "wof:name":"Grant Park Dialysis Center",
    "wof:placetype":"venue"
},
  "geometry": {"coordinates":[-82.98920200000001,39.959971],"type":"Point"}
}