{
  "type": "Feature",
  "properties": {
    "iso:country":"US",
    "sg:address":"5 W Main St",
    "sg:city":"West Jefferson",
    "sg:classifiers":[
        {
            "category":"Real Estate",
            "subcategory":"Real Estate Operator",
            "type":"Services"
        }
    ],
    "sg:phone":"+1 614 879 7010",
    "sg:postcode":"43162",
    "sg:province":"OH",
    "sg:tags":[
        "building",
        "apartment"
    ],
    "wof:name":"Douglas Properties",
    "wof:placetype":"venue"
},
  "geometry": {"coordinates":[-83.268091,39.944775],"type":"Point"}
}