{
  "type": "Feature",
  "properties": {
    "addr:full": "3470 Warren Meadville Rd Cortland OH 44410",
    "addr:housenumber": "3470",
    "addr:postcode": "44410",
    "addr:street": "Warren Meadville Rd",
    "iso:country": "US",
    "sg:address": "3470 Warren Meadville Rd",
    "sg:city": "Cortland",
    "sg:classifiers": [
      {
        "category": "Professional",
        "type": "Services"
      }
    ],
    "sg:phone": "+1 330 638 0744",
    "sg:postcode": "44410",
    "sg:province": "OH",
    "sg:tags": [
      "establishment"
    ],
    "wof:name": "Specialty Technologies Inc",
    "wof:placetype": "venue"
  },
  "geometry": {"coordinates":[-80.741934,41.310758],"type":"Point"}
}
