{
  "type": "Feature",
  "properties": {
    "addr:full": "1303 Oakwood Ave Napoleon OH 43545",
    "addr:housenumber": "1303",
    "addr:postcode": "43545",
    "addr:street": "Oakwood Ave",
    "iso:country": "US",
    "sg:address": "1303 Oakwood Ave",
    "sg:city": "Napoleon",
    "sg:classifiers": [
      {
        "category": "Manufacturing",
        "subcategory": "Glass \u0026 Minerals",
        "type": "Manufacturing \u0026 Wholesale Goods"
      }
    ],
    "sg:phone": "+1 419 592 2761",
    "sg:postcode": "43545",
    "sg:province": "OH",
    "sg:tags": [
      "concrete",
      "brick",
      "prod",
      "block"
    ],
    "wof:name": "Fred H Gerken Co",
    "wof:placetype": "venue"
  },
  "geometry": {"coordinates":[-84.123239,41.400142],"type":"Point"}
}
