{
  "type": "Feature",
  "properties": {
    "iso:country":"US",
    "sg:address":"1303 Oakwood Ave",
    "sg:city":"Napoleon",
    "sg:classifiers":[
        {
            "category":"Manufacturing",
            "subcategory":"Glass & Minerals",
            "type":"Manufacturing & Wholesale Goods"
        }
    ],
    "sg:phone":"+1 419 592 2761",
    "sg:postcode":"43545",
    "sg:province":"OH",
    "sg:tags":[
        "concrete",
        "brick",
        "prod",
        "block"
    ],
    "wof:name":"Fred H Gerken Co",
    "wof:placetype":"venue"
},
  "geometry": {"coordinates":[-84.123239,41.400142],"type":"Point"}
}