{
  "type": "Feature",
  "properties": {
    "iso:country":"US",
    "sg:address":"12415 Neowash Rd",
    "sg:city":"Whitehouse",
    "sg:classifiers":[
        {
            "category":"Farming",
            "subcategory":"Farm",
            "type":"Manufacturing & Wholesale Goods"
        }
    ],
    "sg:phone":"+1 419 832 1175",
    "sg:postcode":"43571",
    "sg:province":"OH",
    "sg:tags":[
        "crop",
        "general"
    ],
    "wof:name":"Thomas Farms Inc",
    "wof:placetype":"venue"
},
  "geometry": {"coordinates":[-83.836434,41.473506],"type":"Point"}
}