{
  "type": "Feature",
  "properties": {
    "iso:country":"US",
    "sg:address":"3521 State Rte 795",
    "sg:city":"Millbury",
    "sg:classifiers":[
        {
            "category":"Home & Garden",
            "subcategory":"Building Materials",
            "type":"Retail Goods"
        }
    ],
    "sg:phone":"+1 419 836 1767",
    "sg:postcode":"43447",
    "sg:province":"OH",
    "sg:tags":[
        "lumber"
    ],
    "sg:website":"www.carterlumber.com",
    "wof:name":"Carter Lumber",
    "wof:placetype":"venue"
},
  "geometry": {"coordinates":[-83.465656,41.558671],"type":"Point"}
}