{
  "type": "Feature",
  "properties": {
    "addr:full": "569 S High St Cortland OH 44410",
    "addr:housenumber": "569",
    "addr:postcode": "44410",
    "addr:street": "S High St",
    "iso:country": "US",
    "sg:address": "569 S High St",
    "sg:city": "Cortland",
    "sg:classifiers": [
      {
        "category": "Wholesale",
        "subcategory": "Medical Equipment \u0026 Supplies",
        "type": "Manufacturing \u0026 Wholesale Goods"
      },
      {
        "category": "Shopping",
        "subcategory": "Beauty \u0026 Cosmetics",
        "type": "Retail Goods"
      },
      {
        "category": "Food \u0026 Beverages",
        "subcategory": "Specialty",
        "type": "Retail Goods"
      },
      {
        "category": "Shopping",
        "subcategory": "Gifts \u0026 Souvenirs",
        "type": "Retail Goods"
      },
      {
        "category": "Retail",
        "subcategory": "Photofinishing",
        "type": "Services"
      },
      {
        "category": "Shopping",
        "subcategory": "Pharmacy",
        "type": "Retail Goods"
      }
    ],
    "sg:phone": "+1 330 638 8747",
    "sg:postcode": "44410",
    "sg:province": "OH",
    "sg:tags": [
      "product",
      "photo",
      "vitamin",
      "perfume",
      "supplement",
      "health",
      "wellness",
      "aid",
      "finishing",
      "first",
      "card",
      "greeting"
    ],
    "sg:website": "http://www.riteaid.com",
    "wof:name": "Rite Aid",
    "wof:placetype": "venue"
  },
  "geometry": {"coordinates":[-80.731133,41.31963],"type":"Point"}
}
