{
  "type": "Feature",
  "properties": {
    "addr:full":"2553 Indianola Ave Columbus OH 43202",
    "addr:housenumber":"2553",
    "addr:postcode":"43202",
    "addr:street":"Indianola Ave",
    "iso:country":"US",
    "sg:address":"2553 Indianola Ave",
    "sg:city":"Columbus",
    "sg:classifiers":[
        {
            "category":"Recreation",
            "type":"Entertainment"
        }
    ],
    "sg:phone":"+1 614 263 4701",
    "sg:postcode":"43202",
    "sg:province":"OH",
    "sg:tags":[
        "martial",
        "arts",
        "instruction"
    ],
    "wof:name":"Ho-I Tai-Chi & Shuai-Chiao",
    "wof:placetype":"venue"
},
  "geometry": {"coordinates":[-83.002218,40.016211],"type":"Point"}
}