{
  "type": "Feature",
  "properties": {
    "addr:full": "117 S Main St Dayton OH 45402",
    "addr:housenumber": "117",
    "addr:postcode": "45402",
    "addr:street": "S Main St",
    "iso:country": "US",
    "sg:address": "117 S Main St",
    "sg:city": "Dayton",
    "sg:classifiers": [
      {
        "category": "Government",
        "subcategory": "Police Station",
        "type": "Public Place"
      }
    ],
    "sg:phone": "+1 937 225 4420",
    "sg:postcode": "45402",
    "sg:province": "OH",
    "sg:tags": [
      "protection"
    ],
    "wof:name": "Bureau of Vital Stat",
    "wof:placetype": "venue"
  },
  "geometry": {"coordinates":[-84.191154,39.757121],"type":"Point"}
}
