{
  "type": "Feature",
  "properties": {
    "addr:full": "4101 Shuffel Dr NW North Canton OH 44720",
    "addr:housenumber": "4101",
    "addr:postcode": "44720",
    "addr:street": "Shuffel Dr Nw",
    "iso:country": "US",
    "sg:address": "4101 Shuffel Dr NW",
    "sg:city": "North Canton",
    "sg:classifiers": [
      {
        "category": "Professional",
        "subcategory": "Testing Lab",
        "type": "Services"
      }
    ],
    "sg:phone": "+1 330 497 9396",
    "sg:postcode": "44720",
    "sg:province": "OH",
    "sg:tags": [
      "laboratory"
    ],
    "sg:website": "www.stl-inc.com",
    "wof:name": "Severn Trent Labs",
    "wof:placetype": "venue"
  },
  "geometry": {"coordinates":[-81.422964,40.89815],"type":"Point"}
}
