{
  "type": "Feature",
  "properties": {
    "addr:full": "1343 Tallmadge Rd Kent OH 44240",
    "addr:housenumber": "1343",
    "addr:postcode": "44240",
    "addr:street": "Tallmadge Rd",
    "iso:country": "US",
    "sg:address": "1343 Tallmadge Rd",
    "sg:city": "Kent",
    "sg:classifiers": [
      {
        "category": "Food \u0026 Beverages",
        "subcategory": "Dairy",
        "type": "Retail Goods"
      }
    ],
    "sg:phone": "+1 330 678 2508",
    "sg:postcode": "44240",
    "sg:province": "OH",
    "sg:tags": [
      "product"
    ],
    "wof:name": "Dairy Mart Convenience Store",
    "wof:placetype": "venue"
  },
  "geometry": {"coordinates":[-81.34339,41.100047],"type":"Point"}
}
