{
  "type": "Feature",
  "properties": {
    "iso:country":"US",
    "sg:address":"1343 Tallmadge Rd",
    "sg:city":"Kent",
    "sg:classifiers":[
        {
            "category":"Food & Beverages",
            "subcategory":"Dairy",
            "type":"Retail Goods"
        }
    ],
    "sg:phone":"+1 330 678 2508",
    "sg:postcode":"44240",
    "sg:province":"OH",
    "sg:tags":[
        "product"
    ],
    "wof:name":"Dairy Mart Convenience Store",
    "wof:placetype":"venue"
},
  "geometry": {"coordinates":[-81.34339,41.100047],"type":"Point"}
}