{
  "type": "Feature",
  "properties": {
    "addr:full":"1415 Warrensville Center Rd Cleveland OH 44121",
    "addr:housenumber":"1415",
    "addr:postcode":"44121",
    "addr:street":"Warrensville Center Rd",
    "iso:country":"US",
    "sg:address":"1415 Warrensville Center Rd",
    "sg:city":"Cleveland",
    "sg:classifiers":[
        {
            "category":"Freight",
            "type":"Transportation"
        }
    ],
    "sg:phone":"+1 216 382 4200",
    "sg:postcode":"44121",
    "sg:province":"OH",
    "sg:tags":[
        "commercial",
        "storage"
    ],
    "wof:name":"E Z Storage",
    "wof:placetype":"venue"
},
  "geometry": {"coordinates":[-81.53639,41.520739],"type":"Point"}
}