{
  "type": "Feature",
  "properties": {
    "addr:full": "11738 Bank Rd Cincinnati OH 45251",
    "addr:housenumber": "11738",
    "addr:postcode": "45251",
    "addr:street": "Bank Rd",
    "iso:country": "US",
    "sg:address": "11738 Bank Rd",
    "sg:city": "Cincinnati",
    "sg:classifiers": [
      {
        "category": "Retail",
        "subcategory": "Auto Repair",
        "type": "Services"
      }
    ],
    "sg:phone": "+1 513 851 3544",
    "sg:postcode": "45251",
    "sg:province": "OH",
    "sg:tags": [
      "repairing",
      "automobile"
    ],
    "wof:name": "A C Auto Repair",
    "wof:placetype": "venue"
  },
  "geometry": {"coordinates":[-84.593928,39.296658],"type":"Point"}
}
