{
  "type": "Feature",
  "properties": {
    "iso:country":"US",
    "sg:address":"16200 Brookpark Rd",
    "sg:city":"Cleveland",
    "sg:classifiers":[
        {
            "category":"Freight",
            "type":"Transportation"
        }
    ],
    "sg:phone":"+1 216 267 6688",
    "sg:postcode":"44135",
    "sg:province":"OH",
    "sg:tags":[
        "packing",
        "crating"
    ],
    "wof:name":"Crates Are Us",
    "wof:placetype":"venue"
},
  "geometry": {"coordinates":[-81.812986,41.418676],"type":"Point"}
}