{
  "type": "Feature",
  "properties": {
    "addr:full":"6751 Taylor Rd Blacklick OH 43004",
    "addr:housenumber":"6751",
    "addr:postcode":"43004",
    "addr:street":"Taylor Rd",
    "iso:country":"US",
    "sg:address":"6751 Taylor Rd",
    "sg:city":"Blacklick",
    "sg:classifiers":[
        {
            "category":"Utilities",
            "subcategory":"Refuse",
            "type":"Services"
        }
    ],
    "sg:phone":"+1 614 501 7875",
    "sg:postcode":"43004",
    "sg:province":"OH",
    "sg:tags":[
        "system"
    ],
    "wof:name":"Buckeye Valley Waste",
    "wof:placetype":"venue"
},
  "geometry": {"coordinates":[-82.817874,40.000658],"type":"Point"}
}