{
  "type": "Feature",
  "properties": {
    "addr:full":"5800 Burkhardt Rd Dayton OH 45431",
    "addr:postcode":"5800;45431",
    "addr:street":"Burkhardt Rd",
    "iso:country":"US",
    "sg:address":"5800 Burkhardt Rd",
    "sg:city":"Dayton",
    "sg:classifiers":[
        {
            "category":"Education",
            "subcategory":"School",
            "type":"Public Place"
        }
    ],
    "sg:phone":"+1 937 259 6625",
    "sg:postcode":"45431",
    "sg:province":"OH",
    "wof:name":"Seville Elementary School",
    "wof:placetype":"venue"
},
  "geometry": {"coordinates":[-84.10337800000001,39.758331],"type":"Point"}
}