{
  "type": "Feature",
  "properties": {
    "iso:country":"US",
    "sg:address":"5800 Burkhardt Rd",
    "sg:city":"Dayton",
    "sg:classifiers":[
        {
            "category":"Education",
            "subcategory":"School",
            "type":"Public Place"
        }
    ],
    "sg:phone":"+1 937 259 6625",
    "sg:postcode":"45431",
    "sg:province":"OH",
    "wof:name":"Seville Elementary School",
    "wof:placetype":"venue"
},
  "geometry": {"coordinates":[-84.103378,39.758331],"type":"Point"}
}