{
  "type": "Feature",
  "properties": {
    "iso:country":"US",
    "sg:address":"24099 Front St",
    "sg:city":"Grand Rapids",
    "sg:classifiers":[
        {
            "category":"Professional",
            "type":"Services"
        }
    ],
    "sg:phone":"+1 419 832 2222",
    "sg:postcode":"43522",
    "sg:province":"OH",
    "sg:tags":[
        "establishment"
    ],
    "wof:name":"Romantic Elements Candles",
    "wof:placetype":"venue"
},
  "geometry": {"coordinates":[-83.86503399999999,41.412759],"type":"Point"}
}