{
  "type": "Feature",
  "properties": {
    "iso:country":"US",
    "sg:address":"3296 E 93rd St",
    "sg:city":"Cleveland",
    "sg:classifiers":[
        {
            "category":"Organizations",
            "subcategory":"Religious Organization",
            "type":"Services"
        }
    ],
    "sg:phone":"+1 216 271 0823",
    "sg:postcode":"44104",
    "sg:province":"OH",
    "sg:tags":[
        "church"
    ],
    "wof:name":"Love Center Interdenomination",
    "wof:placetype":"venue"
},
  "geometry": {"coordinates":[-81.621558,41.46884],"type":"Point"}
}