{
  "type": "Feature",
  "properties": {
    "addr:full":"340 E Main St Enon OH 45323",
    "addr:housenumber":"340",
    "addr:postcode":"45323",
    "addr:street":"E Main St",
    "iso:country":"US",
    "sg:address":"340 E Main St",
    "sg:city":"Enon",
    "sg:classifiers":[
        {
            "category":"Insurance",
            "subcategory":"Insurance Agent",
            "type":"Services"
        }
    ],
    "sg:phone":"+1 937 864 0273",
    "sg:postcode":"45323",
    "sg:province":"OH",
    "wof:name":"Mariann Mulrooney Agency",
    "wof:placetype":"venue"
},
  "geometry": {"coordinates":[-83.932801,39.880563],"type":"Point"}
}