{
  "type": "Feature",
  "properties": {
    "addr:full": "10116 Gay Ave Cleveland OH 44105",
    "addr:housenumber": "10116",
    "addr:postcode": "44105",
    "addr:street": "Gay Ave",
    "iso:country": "US",
    "sg:address": "10116 Gay Ave",
    "sg:city": "Cleveland",
    "sg:classifiers": [
      {
        "category": "Organizations",
        "subcategory": "Religious Organization",
        "type": "Services"
      }
    ],
    "sg:phone": "+1 216 341 7770",
    "sg:postcode": "44105",
    "sg:province": "OH",
    "sg:tags": [
      "clergy"
    ],
    "wof:name": "Benjamin Richey",
    "wof:placetype": "venue"
  },
  "geometry": {"coordinates":[-81.612931,41.45647],"type":"Point"}
}
