{
  "type": "Feature",
  "properties": {
    "addr:full":"432 Washington St Steubenville OH 43952",
    "addr:housenumber":"432",
    "addr:postcode":"43952",
    "addr:street":"Washington St",
    "iso:country":"US",
    "sg:address":"432 Washington St",
    "sg:city":"Steubenville",
    "sg:classifiers":[
        {
            "category":"Retail",
            "subcategory":"Auto Repair",
            "type":"Services"
        }
    ],
    "sg:phone":"+1 740 283 4648",
    "sg:postcode":"43952",
    "sg:province":"OH",
    "sg:tags":[
        "automotive"
    ],
    "wof:name":"Firestone",
    "wof:placetype":"venue"
},
  "geometry": {"coordinates":[-80.615568,40.362011],"type":"Point"}
}