{
  "type": "Feature",
  "properties": {
    "iso:country":"US",
    "sg:address":"24700 Center Ridge Rd",
    "sg:city":"Cleveland",
    "sg:classifiers":[
        {
            "category":"Real Estate",
            "subcategory":"Real Estate Agent",
            "type":"Services"
        }
    ],
    "sg:phone":"+1 440 835 0180",
    "sg:postcode":"44145",
    "sg:province":"OH",
    "wof:name":"DOT Gonzalez Realty",
    "wof:placetype":"venue"
},
  "geometry": {"coordinates":[-81.895446,41.457522],"type":"Point"}
}