{
  "type": "Feature",
  "properties": {
    "addr:full": "6222 Fireside Dr Mason OH 45040",
    "addr:housenumber": "6222",
    "addr:postcode": "45040",
    "addr:street": "Fireside Dr",
    "iso:country": "US",
    "sg:address": "6222 Fireside Dr",
    "sg:city": "Mason",
    "sg:classifiers": [
      {
        "category": "Building \u0026 Trades",
        "subcategory": "Construction",
        "type": "Services"
      }
    ],
    "sg:phone": "+1 513 459 8922",
    "sg:postcode": "45040",
    "sg:province": "OH",
    "sg:tags": [
      "contractor"
    ],
    "wof:name": "TLB Construction",
    "wof:placetype": "venue"
  },
  "geometry": {"coordinates":[-84.339621,39.349833],"type":"Point"}
}
