{
  "type": "Feature",
  "properties": {
    "addr:full":"2115 Laural Ct Ashtabula OH 44004",
    "addr:housenumber":"2115",
    "addr:postcode":"44004",
    "addr:street":"Laural Ct",
    "iso:country":"US",
    "sg:address":"2115 Laural Ct",
    "sg:city":"Ashtabula",
    "sg:classifiers":[
        {
            "category":"Building & Trades",
            "subcategory":"Construction",
            "type":"Services"
        }
    ],
    "sg:phone":"+1 440 998 4517",
    "sg:postcode":"44004",
    "sg:province":"OH",
    "sg:tags":[
        "repairing",
        "remodeling",
        "contractor"
    ],
    "wof:name":"Patete Brothers Remodeling",
    "wof:placetype":"venue"
},
  "geometry": {"coordinates":[-80.79607900000001,41.885776],"type":"Point"}
}