{
  "type": "Feature",
  "properties": {
    "addr:full":"531 E 120th St Cleveland OH 44108",
    "addr:housenumber":"531",
    "addr:postcode":"44108",
    "addr:street":"E 120Th St",
    "iso:country":"US",
    "sg:address":"531 E 120th St",
    "sg:city":"Cleveland",
    "sg:classifiers":[
        {
            "category":"Shopping",
            "type":"Retail Goods"
        }
    ],
    "sg:phone":"+1 216 761 9934",
    "sg:postcode":"44108",
    "sg:province":"OH",
    "sg:tags":[
        "merchandise"
    ],
    "wof:name":"Williams Fixit Shop",
    "wof:placetype":"venue"
},
  "geometry": {"coordinates":[-81.601962,41.543536],"type":"Point"}
}