{
  "type": "Feature",
  "properties": {
    "iso:country":"US",
    "sg:address":"1634 State Rte 232",
    "sg:city":"New Richmond",
    "sg:classifiers":[
        {
            "category":"Building & Trades",
            "subcategory":"Construction",
            "type":"Services"
        }
    ],
    "sg:phone":"+1 513 553 4925",
    "sg:postcode":"45157",
    "sg:province":"OH",
    "sg:tags":[
        "carpentry",
        "contractor"
    ],
    "wof:name":"Carpentry Co",
    "wof:placetype":"venue"
},
  "geometry": {"coordinates":[-84.205587,38.898489],"type":"Point"}
}