{
  "type": "Feature",
  "properties": {
    "addr:full":"1767 Genessee Ave Columbus OH 43211",
    "addr:housenumber":"1767",
    "addr:postcode":"43211",
    "addr:street":"Genessee Ave",
    "iso:country":"US",
    "sg:address":"1767 Genessee Ave",
    "sg:city":"Columbus",
    "sg:classifiers":[
        {
            "category":"Wholesale",
            "subcategory":"Machinery & Supplies",
            "type":"Manufacturing & Wholesale Goods"
        }
    ],
    "sg:phone":"+1 614 263 6900",
    "sg:postcode":"43211",
    "sg:province":"OH",
    "sg:tags":[
        "equipment",
        "industrial"
    ],
    "sg:website":"www.iamcontrols.com",
    "wof:name":"Innovative American Mfg",
    "wof:placetype":"venue"
},
  "geometry": {"coordinates":[-82.96343,40.018869],"type":"Point"}
}