{
  "type": "Feature",
  "properties": {
    "addr:full": "11508 Rodoan Ct Cincinnati OH 45240",
    "addr:housenumber": "11508",
    "addr:postcode": "45240",
    "addr:street": "Rodoan Ct",
    "iso:country": "US",
    "sg:address": "11508 Rodoan Ct",
    "sg:city": "Cincinnati",
    "sg:classifiers": [
      {
        "category": "Home \u0026 Garden",
        "subcategory": "Building Materials",
        "type": "Retail Goods"
      }
    ],
    "sg:phone": "+1 513 825 5003",
    "sg:postcode": "45240",
    "sg:province": "OH",
    "sg:tags": [
      "equipment",
      "electric",
      "supply"
    ],
    "wof:name": "Robinson Electric Controls Inc",
    "wof:placetype": "venue"
  },
  "geometry": {"coordinates":[-84.558331,39.291278],"type":"Point"}
}
