{
  "type": "Feature",
  "properties": {
    "addr:full":"1209 Stringtown Rd Grove City OH 43123",
    "addr:housenumber":"1209",
    "addr:postcode":"43123",
    "addr:street":"Stringtown Rd",
    "iso:country":"US",
    "sg:address":"1209 Stringtown Rd",
    "sg:city":"Grove City",
    "sg:classifiers":[
        {
            "category":"Building & Trades",
            "subcategory":"Construction",
            "type":"Services"
        }
    ],
    "sg:phone":"+1 614 871 2287",
    "sg:postcode":"43123",
    "sg:province":"OH",
    "sg:tags":[
        "excavation",
        "residential",
        "contractor"
    ],
    "wof:name":"Stanley M Clay Contracting",
    "wof:placetype":"venue"
},
  "geometry": {"coordinates":[-83.029495,39.876351],"type":"Point"}
}