{
  "type": "Feature",
  "properties": {
    "iso:country":"US",
    "sg:address":"10015 Johnsford Rd SW",
    "sg:city":"Beach City",
    "sg:classifiers":[
        {
            "category":"Home & Garden",
            "subcategory":"Furniture",
            "type":"Retail Goods"
        }
    ],
    "sg:phone":"+1 330 756 3084",
    "sg:postcode":"44608",
    "sg:province":"OH",
    "wof:name":"Smoketown Furniture Outlet",
    "wof:placetype":"venue"
},
  "geometry": {"coordinates":[-81.553715,40.660082],"type":"Point"}
}