{
  "type": "Feature",
  "properties": {
    "iso:country":"US",
    "sg:address":"1524 Broadway St",
    "sg:city":"Toledo",
    "sg:classifiers":[
        {
            "category":"Building & Trades",
            "subcategory":"Equipment Rental",
            "type":"Services"
        }
    ],
    "sg:phone":"+1 419 242 0776",
    "sg:postcode":"43609",
    "sg:province":"OH",
    "sg:tags":[
        "yard"
    ],
    "wof:name":"Rent-A-Center",
    "wof:placetype":"venue"
},
  "geometry": {"coordinates":[-83.55637299999999,41.631061],"type":"Point"}
}