{
  "type": "Feature",
  "properties": {
    "addr:full": "1524 Broadway St Toledo OH 43609",
    "addr:housenumber": "1524",
    "addr:postcode": "43609",
    "addr:street": "Broadway St",
    "iso:country": "US",
    "sg:address": "1524 Broadway St",
    "sg:city": "Toledo",
    "sg:classifiers": [
      {
        "category": "Building \u0026 Trades",
        "subcategory": "Equipment Rental",
        "type": "Services"
      }
    ],
    "sg:phone": "+1 419 242 0776",
    "sg:postcode": "43609",
    "sg:province": "OH",
    "sg:tags": [
      "yard"
    ],
    "wof:name": "Rent-A-Center",
    "wof:placetype": "venue"
  },
  "geometry": {"coordinates":[-83.556373,41.631061],"type":"Point"}
}
