{
  "type": "Feature",
  "properties": {
    "addr:full": "7775 Beach Rd Wadsworth OH 44281",
    "addr:housenumber": "7775",
    "addr:postcode": "44281",
    "addr:street": "Beach Rd",
    "iso:country": "US",
    "sg:address": "7775 Beach Rd",
    "sg:city": "Wadsworth",
    "sg:classifiers": [
      {
        "category": "Professional",
        "subcategory": "Engineering",
        "type": "Services"
      }
    ],
    "sg:phone": "+1 330 334 9199",
    "sg:postcode": "44281",
    "sg:province": "OH",
    "sg:tags": [
      "engineer"
    ],
    "wof:name": "Chemron Engineering",
    "wof:placetype": "venue"
  },
  "geometry": {"coordinates":[-81.756519,41.081103],"type":"Point"}
}
