{
  "type": "Feature",
  "properties": {
    "addr:full": "4048 Pathfield Dr Columbus OH 43230",
    "addr:housenumber": "4048",
    "addr:postcode": "43230",
    "addr:street": "Pathfield Dr",
    "iso:country": "US",
    "sg:address": "4048 Pathfield Dr",
    "sg:city": "Columbus",
    "sg:classifiers": [
      {
        "category": "Building \u0026 Trades",
        "subcategory": "Construction",
        "type": "Services"
      }
    ],
    "sg:phone": "+1 614 855 3078",
    "sg:postcode": "43230",
    "sg:province": "OH",
    "sg:tags": [
      "house",
      "builder",
      "home"
    ],
    "wof:name": "Devine Hubbard Cstm Bldrs LTD",
    "wof:placetype": "venue"
  },
  "geometry": {"coordinates":[-82.856655,40.06159],"type":"Point"}
}
