{
  "type": "Feature",
  "properties": {
    "addr:full": "6437 Hamilton Ave Cincinnati OH 45224",
    "addr:housenumber": "6437",
    "addr:postcode": "45224",
    "addr:street": "Hamilton Ave",
    "iso:country": "US",
    "sg:address": "6437 Hamilton Ave",
    "sg:city": "Cincinnati",
    "sg:classifiers": [
      {
        "category": "Building \u0026 Trades",
        "subcategory": "Landscaping Services",
        "type": "Services"
      }
    ],
    "sg:phone": "+1 513 931 5296",
    "sg:postcode": "45224",
    "sg:province": "OH",
    "wof:name": "Avalawn Landscaping Inc",
    "wof:placetype": "venue"
  },
  "geometry": {"coordinates":[-84.547983,39.208329],"type":"Point"}
}
