{
  "type": "Feature",
  "properties": {
    "addr:full": "3471 Beltz Rd Sardinia OH 45171",
    "addr:housenumber": "3471",
    "addr:postcode": "45171",
    "addr:street": "Beltz Rd",
    "iso:country": "US",
    "sg:address": "3471 Beltz Rd",
    "sg:city": "Sardinia",
    "sg:phone": "+1 937 446 2850",
    "sg:postcode": "45171",
    "sg:province": "OH",
    "sg:tags": [
      "farm",
      "corn",
      "wheat",
      "soybean"
    ],
    "wof:name": "Hawk Farms",
    "wof:placetype": "venue"
  },
  "geometry": {"coordinates":[-83.859258,39.095666],"type":"Point"}
}
