{
  "type": "Feature",
  "properties": {
    "addr:full":"920 S Mill St Louisville OH 44641",
    "addr:housenumber":"920",
    "addr:postcode":"44641",
    "addr:street":"S Mill St",
    "iso:country":"US",
    "sg:address":"920 S Mill St",
    "sg:city":"Louisville",
    "sg:classifiers":[
        {
            "category":"Professional",
            "subcategory":"Lawyer & Legal Services",
            "type":"Services"
        }
    ],
    "sg:phone":"+1 330 875 3288",
    "sg:postcode":"44641",
    "sg:province":"OH",
    "sg:tags":[
        "attorney"
    ],
    "wof:name":"Robert J Shockling",
    "wof:placetype":"venue"
},
  "geometry": {"coordinates":[-81.25830499999999,40.832309],"type":"Point"}
}