{
  "type": "Feature",
  "properties": {
    "iso:country":"US",
    "sg:address":"101 W South St",
    "sg:city":"St Marys",
    "sg:classifiers":[
        {
            "category":"Education",
            "subcategory":"School",
            "type":"Public Place"
        }
    ],
    "sg:phone":"+1 419 394 4312",
    "sg:postcode":"45885",
    "sg:province":"OH",
    "sg:tags":[
        "board"
    ],
    "wof:name":"St Marys City School District",
    "wof:placetype":"venue"
},
  "geometry": {"coordinates":[-84.38635499999999,40.542441],"type":"Point"}
}