{
  "type": "Feature",
  "properties": {
    "addr:full": "1234 Retswood Dr Loveland OH 45140",
    "addr:housenumber": "1234",
    "addr:postcode": "45140",
    "addr:street": "Retswood Dr",
    "iso:country": "US",
    "sg:address": "1234 Retswood Dr",
    "sg:city": "Loveland",
    "sg:classifiers": [
      {
        "category": "Professional",
        "type": "Services"
      }
    ],
    "sg:phone": "+1 513 683 8579",
    "sg:postcode": "45140",
    "sg:province": "OH",
    "wof:name": "Thomas G Bomkamp",
    "wof:placetype": "venue"
  },
  "geometry": {"coordinates":[-84.23362,39.257217],"type":"Point"}
}
