{
  "type": "Feature",
  "properties": {
    "addr:full": "3688 Center Rd Brunswick OH 44212",
    "addr:housenumber": "3688",
    "addr:postcode": "44212",
    "addr:street": "Center Rd",
    "iso:country": "US",
    "sg:address": "3688 Center Rd",
    "sg:city": "Brunswick",
    "sg:classifiers": [
      {
        "category": "Food \u0026 Beverages",
        "subcategory": "Bakery",
        "type": "Retail Goods"
      }
    ],
    "sg:phone": "+1 330 273 5777",
    "sg:postcode": "44212",
    "sg:province": "OH",
    "wof:name": "Tops 838 Bakery",
    "wof:placetype": "venue"
  },
  "geometry": {"coordinates":[-81.818132,41.238249],"type":"Point"}
}
