{
  "type": "Feature",
  "properties": {
    "addr:full": "2727 Lantz Rd Beavercreek OH 45434",
    "addr:housenumber": "2727",
    "addr:postcode": "45434",
    "addr:street": "Lantz Rd",
    "iso:country": "US",
    "sg:address": "2727 Lantz Rd",
    "sg:city": "Beavercreek",
    "sg:classifiers": [
      {
        "category": "Manufacturing",
        "subcategory": "Printing",
        "type": "Manufacturing \u0026 Wholesale Goods"
      }
    ],
    "sg:phone": "+1 937 431 1300",
    "sg:postcode": "45434",
    "sg:province": "OH",
    "sg:tags": [
      "newspaper"
    ],
    "wof:name": "Dayton Dartin Assoc",
    "wof:placetype": "venue"
  },
  "geometry": {"coordinates":[-84.035132,39.737079],"type":"Point"}
}
