{
  "type": "Feature",
  "properties": {
    "addr:full": "7748 Washington Park Dr Dayton OH 45459",
    "addr:housenumber": "7748",
    "addr:postcode": "45459",
    "addr:street": "Washington Park Dr",
    "iso:country": "US",
    "sg:address": "7748 Washington Park Dr",
    "sg:city": "Dayton",
    "sg:classifiers": [
      {
        "category": "Banks \u0026 Credit Unions",
        "subcategory": "Investment Brokerage",
        "type": "Services"
      },
      {
        "category": "Insurance",
        "subcategory": "Insurance Agent",
        "type": "Services"
      }
    ],
    "sg:phone": "+1 937 428 3300",
    "sg:postcode": "45459",
    "sg:province": "OH",
    "sg:tags": [
      "consultant",
      "planning",
      "financial"
    ],
    "wof:name": "Quintessential Advisors Inc",
    "wof:placetype": "venue"
  },
  "geometry": {"coordinates":[-84.207879,39.637007],"type":"Point"}
}
