{
  "type": "Feature",
  "properties": {
    "iso:country":"US",
    "sg:address":"7748 Washington Park Dr",
    "sg:city":"Dayton",
    "sg:classifiers":[
        {
            "category":"Banks & Credit Unions",
            "subcategory":"Investment Brokerage",
            "type":"Services"
        },
        {
            "category":"Insurance",
            "subcategory":"Insurance Agent",
            "type":"Services"
        }
    ],
    "sg:phone":"+1 937 428 3300",
    "sg:postcode":"45459",
    "sg:province":"OH",
    "sg:tags":[
        "consultant",
        "planning",
        "financial"
    ],
    "wof:name":"Quintessential Advisors Inc",
    "wof:placetype":"venue"
},
  "geometry": {"coordinates":[-84.207879,39.637007],"type":"Point"}
}