{
  "type": "Feature",
  "properties": {
    "addr:full":"7347 Pickway Dr Cincinnati OH 45233",
    "addr:housenumber":"7347",
    "addr:postcode":"45233",
    "addr:street":"Pickway Dr",
    "iso:country":"US",
    "sg:address":"7347 Pickway Dr",
    "sg:city":"Cincinnati",
    "sg:classifiers":[
        {
            "category":"Building & Trades",
            "subcategory":"Plumbing",
            "type":"Services"
        }
    ],
    "sg:phone":"+1 513 941 3143",
    "sg:postcode":"45233",
    "sg:province":"OH",
    "sg:tags":[
        "plumbing",
        "contractor"
    ],
    "wof:name":"Pohlman Plumbing Company",
    "wof:placetype":"venue"
},
  "geometry": {"coordinates":[-84.69208999999999,39.139898],"type":"Point"}
}