{
  "type": "Feature",
  "properties": {
    "iso:country":"US",
    "sg:address":"3426 Navarre Ave",
    "sg:city":"Oregon",
    "sg:classifiers":[
        {
            "category":"Banks & Credit Unions",
            "subcategory":"Bank",
            "type":"Services"
        }
    ],
    "sg:phone":"+1 419 693 9390",
    "sg:postcode":"43616",
    "sg:province":"OH",
    "sg:tags":[
        "state",
        "commercial"
    ],
    "sg:website":"www.skyfi.com",
    "wof:name":"Sky Bank",
    "wof:placetype":"venue"
},
  "geometry": {"coordinates":[-83.465554,41.637013],"type":"Point"}
}