{
  "type": "Feature",
  "properties": {
    "addr:full": "503 W Park Ave Barberton OH 44203",
    "addr:housenumber": "503",
    "addr:postcode": "44203",
    "addr:street": "W Park Ave",
    "iso:country": "US",
    "sg:address": "503 W Park Ave",
    "sg:city": "Barberton",
    "sg:classifiers": [
      {
        "category": "Professional",
        "subcategory": "Detective \u0026 Security Services",
        "type": "Services"
      }
    ],
    "sg:phone": "+1 330 753 9367",
    "sg:postcode": "44203",
    "sg:province": "OH",
    "sg:tags": [
      "guard",
      "patrol"
    ],
    "wof:name": "Corporate Answers",
    "wof:placetype": "venue"
  },
  "geometry": {"coordinates":[-81.608085,41.013752],"type":"Point"}
}
