{
  "type": "Feature",
  "properties": {
    "addr:full": "2010 N River Rd Fremont OH 43420",
    "addr:housenumber": "2010",
    "addr:postcode": "43420",
    "addr:street": "N River Rd",
    "iso:country": "US",
    "sg:address": "2010 N River Rd",
    "sg:city": "Fremont",
    "sg:classifiers": [
      {
        "category": "Building \u0026 Trades",
        "subcategory": "Construction",
        "type": "Services"
      }
    ],
    "sg:phone": "+1 419 332 5000",
    "sg:postcode": "43420",
    "sg:province": "OH",
    "sg:tags": [
      "roofing",
      "industrial",
      "co",
      "renovation",
      "contractor"
    ],
    "sg:website": "www.damschroderconstruction.com",
    "wof:name": "Damschroder Construction LLC",
    "wof:placetype": "venue"
  },
  "geometry": {"coordinates":[-83.092738,41.369707],"type":"Point"}
}
