{
  "type": "Feature",
  "properties": {
    "iso:country":"US",
    "sg:address":"2010 N River Rd",
    "sg:city":"Fremont",
    "sg:classifiers":[
        {
            "category":"Building & Trades",
            "subcategory":"Construction",
            "type":"Services"
        }
    ],
    "sg:phone":"+1 419 332 5000",
    "sg:postcode":"43420",
    "sg:province":"OH",
    "sg:tags":[
        "roofing",
        "industrial",
        "co",
        "renovation",
        "contractor"
    ],
    "sg:website":"www.damschroderconstruction.com",
    "wof:name":"Damschroder Construction LLC",
    "wof:placetype":"venue"
},
  "geometry": {"coordinates":[-83.092738,41.369707],"type":"Point"}
}