{
  "type": "Feature",
  "properties": {
    "addr:full":"3946 Kul Cir S Hilliard OH 43026",
    "addr:postcode":"3946;43026",
    "addr:street":"Kul Cir S",
    "iso:country":"US",
    "sg:address":"3946 Kul Cir S",
    "sg:city":"Hilliard",
    "sg:classifiers":[
        {
            "category":"Insurance",
            "subcategory":"Insurance Agent",
            "type":"Services"
        }
    ],
    "sg:phone":"+1 614 529 6643",
    "sg:postcode":"43026",
    "sg:province":"OH",
    "wof:name":"Ruckman Consulting Group",
    "wof:placetype":"venue"
},
  "geometry": {"coordinates":[-83.122885,40.055482],"type":"Point"}
}