{
  "type": "Feature",
  "properties": {
    "iso:country":"US",
    "sg:address":"1900 Crown Park Ct",
    "sg:city":"Columbus",
    "sg:classifiers":[
        {
            "category":"Real Estate",
            "subcategory":"Real Estate Operator",
            "type":"Services"
        }
    ],
    "sg:phone":"+1 614 538 2828",
    "sg:postcode":"43235",
    "sg:province":"OH",
    "sg:tags":[
        "property",
        "lessor"
    ],
    "wof:name":"Zrm Property Company",
    "wof:placetype":"venue"
},
  "geometry": {"coordinates":[-83.069787,40.065108],"type":"Point"}
}