{
  "type": "Feature",
  "properties": {
    "addr:full":"11915 Kemper Springs Dr Cincinnati OH 45240",
    "addr:housenumber":"11915",
    "addr:postcode":"45240",
    "addr:street":"Kemper Springs Dr",
    "iso:country":"US",
    "sg:address":"11915 Kemper Springs Dr",
    "sg:city":"Cincinnati",
    "sg:classifiers":[
        {
            "category":"Insurance",
            "subcategory":"Insurance Agent",
            "type":"Services"
        }
    ],
    "sg:phone":"+1 513 851 0600",
    "sg:postcode":"45240",
    "sg:province":"OH",
    "wof:name":"Nationwide Insurance",
    "wof:placetype":"venue"
},
  "geometry": {"coordinates":[-84.533348,39.293823],"type":"Point"}
}