{
  "type": "Feature",
  "properties": {
    "addr:full": "3650 S High St Columbus OH 43207",
    "addr:housenumber": "3650",
    "addr:postcode": "43207",
    "addr:street": "S High St",
    "iso:country": "US",
    "sg:address": "3650 S High St",
    "sg:city": "Columbus",
    "sg:classifiers": [
      {
        "category": "Restaurant",
        "type": "Food \u0026 Drink"
      }
    ],
    "sg:phone": "+1 614 491 8877",
    "sg:postcode": "43207",
    "sg:province": "OH",
    "sg:tags": [
      "eating"
    ],
    "wof:name": "China City Buffet",
    "wof:placetype": "venue"
  },
  "geometry": {"coordinates":[-82.999356,39.885657],"type":"Point"}
}
