{
  "type": "Feature",
  "properties": {
    "addr:full":"11105 Hill Rd Howard OH 43022",
    "addr:housenumber":"11105",
    "addr:postcode":"43022",
    "addr:street":"Hill Rd",
    "iso:country":"US",
    "sg:address":"11105 Hill Rd",
    "sg:city":"Howard",
    "sg:classifiers":[
        {
            "category":"Farming",
            "subcategory":"Farm",
            "type":"Manufacturing & Wholesale Goods"
        }
    ],
    "sg:phone":"+1 740 427 2120",
    "sg:postcode":"43022",
    "sg:province":"OH",
    "sg:tags":[
        "crop",
        "general"
    ],
    "wof:name":"Michael Compton",
    "wof:placetype":"venue"
},
  "geometry": {"coordinates":[-82.310417,40.383828],"type":"Point"}
}