{
  "type": "Feature",
  "properties": {
    "addr:full": "645 Superior Ave Dayton OH 45402",
    "addr:housenumber": "645",
    "addr:postcode": "45402",
    "addr:street": "Superior Ave",
    "iso:country": "US",
    "sg:address": "645 Superior Ave",
    "sg:city": "Dayton",
    "sg:classifiers": [
      {
        "category": "Real Estate",
        "subcategory": "Real Estate Agent",
        "type": "Services"
      }
    ],
    "sg:phone": "+1 937 278 5422",
    "sg:postcode": "45402",
    "sg:province": "OH",
    "sg:tags": [
      "management"
    ],
    "wof:name": "Whitaker Realty",
    "wof:placetype": "venue"
  },
  "geometry": {"coordinates":[-84.211826,39.765671],"type":"Point"}
}
