{
  "type": "Feature",
  "properties": {
    "addr:full": "788 N Orchard Ln Beavercreek OH 45301",
    "addr:housenumber": "788",
    "addr:postcode": "45301",
    "addr:street": "N Orchard Ln",
    "iso:country": "US",
    "sg:address": "788 N Orchard Ln",
    "sg:city": "Beavercreek",
    "sg:classifiers": [
      {
        "category": "Home \u0026 Garden",
        "subcategory": "Carpets \u0026 Floor Coverings",
        "type": "Retail Goods"
      }
    ],
    "sg:phone": "+1 937 312 0124",
    "sg:postcode": "45301",
    "sg:province": "OH",
    "sg:tags": [
      "dealer",
      "rug"
    ],
    "wof:name": "Dayton Installation Svc",
    "wof:placetype": "venue"
  },
  "geometry": {"coordinates":[-84.019289,39.709879],"type":"Point"}
}
