{
  "type": "Feature",
  "properties": {
    "addr:full":"2950 Hayden Run Plz Columbus OH 43235",
    "addr:housenumber":"2950",
    "addr:postcode":"43235",
    "addr:street":"Hayden Run",
    "iso:country":"US",
    "sg:address":"2950 Hayden Run Plz",
    "sg:city":"Columbus",
    "sg:classifiers":[
        {
            "category":"Restaurant",
            "type":"Food & Drink"
        }
    ],
    "sg:phone":"+1 614 799 8655",
    "sg:postcode":"43235",
    "sg:province":"OH",
    "sg:tags":[
        "eating"
    ],
    "wof:name":"Imperial Garden Restaurant",
    "wof:placetype":"venue"
},
  "geometry": {"coordinates":[-83.09608900000001,40.065642],"type":"Point"}
}