{
  "type": "Feature",
  "properties": {
    "addr:full": "2924 Hayden Run Plz Columbus OH 43235",
    "addr:housenumber": "2924",
    "addr:postcode": "43235",
    "addr:street": "Hayden Run",
    "iso:country": "US",
    "sg:address": "2924 Hayden Run Plz",
    "sg:city": "Columbus",
    "sg:classifiers": [
      {
        "category": "Education",
        "subcategory": "Dance Studio",
        "type": "Public Place"
      }
    ],
    "sg:phone": "+1 614 889 0106",
    "sg:postcode": "43235",
    "sg:province": "OH",
    "sg:tags": [
      "instruction",
      "dancing"
    ],
    "wof:name": "Irveline's Ballet School",
    "wof:placetype": "venue"
  },
  "geometry": {"coordinates":[-83.095961,40.065801],"type":"Point"}
}
