{
  "type": "Feature",
  "properties": {
    "addr:full":"20 S 3rd St Columbus OH 43215",
    "addr:housenumber":"20",
    "addr:postcode":"43215",
    "addr:street":"S 3Rd St",
    "iso:country":"US",
    "sg:address":"20 S 3rd St",
    "sg:city":"Columbus",
    "sg:classifiers":[
        {
            "category":"Real Estate",
            "subcategory":"Developer",
            "type":"Services"
        },
        {
            "category":"Banks & Credit Unions",
            "subcategory":"Financial Services",
            "type":"Services"
        }
    ],
    "sg:phone":"+1 614 224 6666",
    "sg:postcode":"43215",
    "sg:province":"OH",
    "sg:tags":[
        "investor"
    ],
    "wof:name":"Thomas H Lurie & Associates",
    "wof:placetype":"venue"
},
  "geometry": {"coordinates":[-82.997868,39.962353],"type":"Point"}
}