{
  "type": "Feature",
  "properties": {
    "addr:full":"1375 Old Logan Rd Lancaster OH 43130",
    "addr:housenumber":"1375",
    "addr:postcode":"43130",
    "addr:street":"Old Logan Rd",
    "iso:country":"US",
    "sg:address":"1375 Old Logan Rd",
    "sg:city":"Lancaster",
    "sg:classifiers":[
        {
            "category":"Shopping",
            "subcategory":"Department Store",
            "type":"Retail Goods"
        }
    ],
    "sg:phone":"+1 740 653 5334",
    "sg:postcode":"43130",
    "sg:province":"OH",
    "wof:name":"Lancaster Sales Inc",
    "wof:placetype":"venue"
},
  "geometry": {"coordinates":[-82.58978399999999,39.69909],"type":"Point"}
}