{
  "type": "Feature",
  "properties": {
    "iso:country":"US",
    "sg:address":"10825 Yankee St",
    "sg:city":"Dayton",
    "sg:classifiers":[
        {
            "category":"Building & Trades",
            "subcategory":"Construction",
            "type":"Services"
        }
    ],
    "sg:phone":"+1 937 885 6960",
    "sg:postcode":"45458",
    "sg:province":"OH",
    "sg:tags":[
        "dry wall",
        "contractor"
    ],
    "wof:name":"Dixie Drywall Co Inc",
    "wof:placetype":"venue"
},
  "geometry": {"coordinates":[-84.201358,39.585275],"type":"Point"}
}