{
  "type": "Feature",
  "properties": {
    "addr:full": "216 S Greenlawn Ave Lima OH 45807",
    "addr:housenumber": "216",
    "addr:postcode": "45807",
    "addr:street": "S Greenlawn Ave",
    "iso:country": "US",
    "sg:address": "216 S Greenlawn Ave",
    "sg:city": "Lima",
    "sg:classifiers": [
      {
        "category": "Manufacturing",
        "subcategory": "Building Materials",
        "type": "Manufacturing \u0026 Wholesale Goods"
      }
    ],
    "sg:phone": "+1 419 339 7600",
    "sg:postcode": "45807",
    "sg:province": "OH",
    "wof:name": "ACA Millworks",
    "wof:placetype": "venue"
  },
  "geometry": {"coordinates":[-84.203727,40.785295],"type":"Point"}
}
