{
  "type": "Feature",
  "properties": {
    "addr:full": "1100 Haskins Rd Bowling Green OH 43402",
    "addr:housenumber": "1100",
    "addr:postcode": "43402",
    "addr:street": "Haskins Rd",
    "iso:country": "US",
    "sg:address": "1100 Haskins Rd",
    "sg:city": "Bowling Green",
    "sg:classifiers": [
      {
        "category": "Manufacturing",
        "subcategory": "Tools \u0026 Machinery",
        "type": "Manufacturing \u0026 Wholesale Goods"
      }
    ],
    "sg:phone": "+1 419 352 7511",
    "sg:postcode": "43402",
    "sg:province": "OH",
    "sg:tags": [
      "industry",
      "mfg"
    ],
    "sg:website": "www.americanlincoln.com",
    "wof:name": "Alto US Inc",
    "wof:placetype": "venue"
  },
  "geometry": {"coordinates":[-83.669844,41.388414],"type":"Point"}
}
