{
  "type": "Feature",
  "properties": {
    "addr:full":"848 Beech Ave Cincinnati OH 45205",
    "addr:housenumber":"848",
    "addr:postcode":"45205",
    "addr:street":"Beech Ave",
    "iso:country":"US",
    "sg:address":"848 Beech Ave",
    "sg:city":"Cincinnati",
    "sg:classifiers":[
        {
            "category":"Professional",
            "type":"Services"
        }
    ],
    "sg:phone":"+1 513 921 8775",
    "sg:postcode":"45205",
    "sg:province":"OH",
    "wof:name":"Rick Hackle Brick Cleanin",
    "wof:placetype":"venue"
},
  "geometry": {"coordinates":[-84.57760399999999,39.109276],"type":"Point"}
}