{
  "type": "Feature",
  "properties": {
    "addr:full":"8060 Forestdale Dr Willoughby OH 44094",
    "addr:housenumber":"8060",
    "addr:postcode":"44094",
    "addr:street":"Forestdale Dr",
    "iso:country":"US",
    "sg:address":"8060 Forestdale Dr",
    "sg:city":"Willoughby",
    "sg:classifiers":[
        {
            "category":"Real Estate",
            "subcategory":"Real Estate Agent",
            "type":"Services"
        }
    ],
    "sg:phone":"+1 440 342 5094",
    "sg:postcode":"44094",
    "sg:province":"OH",
    "wof:name":"Lynda Grimm Realtor",
    "wof:placetype":"venue"
},
  "geometry": {"coordinates":[-81.35083899999999,41.623931],"type":"Point"}
}