{
  "type": "Feature",
  "properties": {
    "iso:country":"US",
    "sg:address":"1 E Broadway St",
    "sg:city":"Jackson",
    "sg:classifiers":[
        {
            "category":"Restaurant",
            "type":"Food & Drink"
        }
    ],
    "sg:phone":"+1 740 286 3817",
    "sg:postcode":"45640",
    "sg:province":"OH",
    "sg:tags":[
        "caterer"
    ],
    "wof:name":"Elegance By Design",
    "wof:placetype":"venue"
},
  "geometry": {"coordinates":[-82.632863,39.054058],"type":"Point"}
}