{
  "type": "Feature",
  "properties": {
    "addr:full":"25 Green Valley Dr Enon OH 45323",
    "addr:housenumber":"25",
    "addr:postcode":"45323",
    "addr:street":"Green Valley Dr",
    "iso:country":"US",
    "sg:address":"25 Green Valley Dr",
    "sg:city":"Enon",
    "sg:classifiers":[
        {
            "category":"Restaurant",
            "type":"Food & Drink"
        }
    ],
    "sg:phone":"+1 937 864 1307",
    "sg:postcode":"45323",
    "sg:province":"OH",
    "wof:name":"Carriage Inn Restaurant",
    "wof:placetype":"venue"
},
  "geometry": {"coordinates":[-83.933401,39.879307],"type":"Point"}
}