{
  "type": "Feature",
  "properties": {
    "addr:full": "5427 N Star Fort Loramie Rd New Weston OH 45348",
    "addr:housenumber": "5427",
    "addr:postcode": "45348",
    "addr:street": "N Star Fort Loramie Rd",
    "iso:country": "US",
    "sg:address": "5427 N Star Fort Loramie Rd",
    "sg:city": "New Weston",
    "sg:classifiers": [
      {
        "category": "Farming",
        "subcategory": "Dairy Farm",
        "type": "Manufacturing \u0026 Wholesale Goods"
      }
    ],
    "sg:phone": "+1 419 336 6131",
    "sg:postcode": "45348",
    "sg:province": "OH",
    "wof:name": "Ron Broering Farms",
    "wof:placetype": "venue"
  },
  "geometry": {"coordinates":[-84.602977,40.322949],"type":"Point"}
}
