{
  "type": "Feature",
  "properties": {
    "addr:full":"568 Oxford State Rd Middletown OH 45044",
    "addr:housenumber":"568",
    "addr:postcode":"45044",
    "addr:street":"State Rd",
    "iso:country":"US",
    "sg:address":"568 Oxford State Rd",
    "sg:city":"Middletown",
    "sg:classifiers":[
        {
            "category":"Retail",
            "subcategory":"Car Wash",
            "type":"Services"
        }
    ],
    "sg:phone":"+1 513 217 5319",
    "sg:postcode":"45044",
    "sg:province":"OH",
    "sg:tags":[
        "polishing",
        "washing"
    ],
    "wof:name":"Tim Donohue MT Carwash",
    "wof:placetype":"venue"
},
  "geometry": {"coordinates":[-84.419236,39.480948],"type":"Point"}
}