{
  "type": "Feature",
  "properties": {
    "iso:country":"US",
    "sg:address":"3141 Asbury Dr",
    "sg:city":"Columbus",
    "sg:classifiers":[
        {
            "category":"Professional",
            "subcategory":"Business Services",
            "type":"Services"
        }
    ],
    "sg:phone":"+1 614 481 7625",
    "sg:postcode":"43221",
    "sg:province":"OH",
    "sg:tags":[
        "event"
    ],
    "wof:name":"Power-A-Rangers LTD",
    "wof:placetype":"venue"
},
  "geometry": {"coordinates":[-83.075971,40.016381],"type":"Point"}
}