{
  "type": "Feature",
  "properties": {
    "iso:country":"US",
    "sg:address":"5185 Ralph Ave",
    "sg:city":"Cincinnati",
    "sg:classifiers":[
        {
            "category":"Building & Trades",
            "subcategory":"Construction",
            "type":"Services"
        }
    ],
    "sg:phone":"+1 513 251 7663",
    "sg:postcode":"45238",
    "sg:province":"OH",
    "sg:tags":[
        "contractor"
    ],
    "wof:name":"Scheper Roofing",
    "wof:placetype":"venue"
},
  "geometry": {"coordinates":[-84.608241,39.120519],"type":"Point"}
}