{
  "type": "Feature",
  "properties": {
    "iso:country":"US",
    "sg:address":"1814 Huffman Ave",
    "sg:city":"Dayton",
    "sg:classifiers":[
        {
            "category":"Building & Trades",
            "subcategory":"Construction",
            "type":"Services"
        }
    ],
    "sg:phone":"+1 937 256 5290",
    "sg:postcode":"45403",
    "sg:province":"OH",
    "sg:tags":[
        "concrete",
        "special",
        "contractor"
    ],
    "wof:name":"Thade Construction Co",
    "wof:placetype":"venue"
},
  "geometry": {"coordinates":[-84.131997,39.757127],"type":"Point"}
}