{
  "type": "Feature",
  "properties": {
    "addr:full":"363 Neighbor St Newcomerstown OH 43832",
    "addr:housenumber":"363",
    "addr:postcode":"43832",
    "addr:street":"Neighbor St",
    "iso:country":"US",
    "sg:address":"363 Neighbor St",
    "sg:city":"Newcomerstown",
    "sg:classifiers":[
        {
            "category":"Organizations",
            "subcategory":"Religious Organization",
            "type":"Services"
        }
    ],
    "sg:phone":"+1 740 498 7588",
    "sg:postcode":"43832",
    "sg:province":"OH",
    "sg:tags":[
        "church"
    ],
    "wof:name":"Church Of The Nazarene",
    "wof:placetype":"venue"
},
  "geometry": {"coordinates":[-81.61036,40.27632],"type":"Point"}
}