{
  "type": "Feature",
  "properties": {
    "addr:full":"4095 Colorado Ave Sheffield Vlg OH 44054",
    "addr:housenumber":"4095",
    "addr:postcode":"44054",
    "addr:street":"Colorado Ave",
    "iso:country":"US",
    "sg:address":"4095 Colorado Ave",
    "sg:city":"Sheffield Vlg",
    "sg:classifiers":[
        {
            "category":"Retail",
            "subcategory":"Auto Repair",
            "type":"Services"
        }
    ],
    "sg:phone":"+1 440 949 2862",
    "sg:postcode":"44054",
    "sg:province":"OH",
    "sg:tags":[
        "repairing",
        "automobile"
    ],
    "wof:name":"Sheffield Dyna-Gard",
    "wof:placetype":"venue"
},
  "geometry": {"coordinates":[-82.11778099999999,41.461659],"type":"Point"}
}