{
  "type": "Feature",
  "properties": {
    "iso:country":"US",
    "sg:address":"802 4th St",
    "sg:city":"Belpre",
    "sg:classifiers":[
        {
            "category":"Organizations",
            "subcategory":"Religious Organization",
            "type":"Services"
        }
    ],
    "sg:phone":"+1 740 423 5724",
    "sg:postcode":"45714",
    "sg:province":"OH",
    "sg:tags":[
        "church"
    ],
    "wof:name":"First Baptist Chr - Belpre",
    "wof:placetype":"venue"
},
  "geometry": {"coordinates":[-81.580365,39.276443],"type":"Point"}
}