{
  "type": "Feature",
  "properties": {
    "addr:full": "6161 Oak Tree Blvd Cleveland OH 44131",
    "addr:housenumber": "6161",
    "addr:postcode": "44131",
    "addr:street": "Oak Tree Blvd",
    "iso:country": "US",
    "sg:address": "6161 Oak Tree Blvd",
    "sg:city": "Cleveland",
    "sg:classifiers": [
      {
        "category": "Insurance",
        "subcategory": "Insurance Agent",
        "type": "Services"
      }
    ],
    "sg:phone": "+1 216 328 1600",
    "sg:postcode": "44131",
    "sg:province": "OH",
    "sg:tags": [
      "administrative",
      "pension",
      "plan"
    ],
    "wof:name": "Qualified Pension Prft Shrng",
    "wof:placetype": "venue"
  },
  "geometry": {"coordinates":[-81.660118,41.395652],"type":"Point"}
}
