{
  "type": "Feature",
  "properties": {
    "iso:country":"US",
    "sg:address":"444 N Front St",
    "sg:city":"Columbus",
    "sg:classifiers":[
        {
            "category":"Professional",
            "subcategory":"Lawyer & Legal Services",
            "type":"Services"
        }
    ],
    "sg:phone":"+1 614 220 5611",
    "sg:postcode":"43215",
    "sg:province":"OH",
    "sg:tags":[
        "law"
    ],
    "wof:name":"Manley Deas & Kochalski LLC",
    "wof:placetype":"venue"
},
  "geometry": {"coordinates":[-83.004409,39.971149],"type":"Point"}
}