{
  "type": "Feature",
  "properties": {
    "addr:full": "444 N Front St Columbus OH 43215",
    "addr:housenumber": "444",
    "addr:postcode": "43215",
    "addr:street": "N Front St",
    "iso:country": "US",
    "sg:address": "444 N Front St",
    "sg:city": "Columbus",
    "sg:classifiers": [
      {
        "category": "Professional",
        "subcategory": "Lawyer \u0026 Legal Services",
        "type": "Services"
      }
    ],
    "sg:phone": "+1 614 220 5611",
    "sg:postcode": "43215",
    "sg:province": "OH",
    "sg:tags": [
      "law"
    ],
    "wof:name": "Manley Deas \u0026 Kochalski LLC",
    "wof:placetype": "venue"
  },
  "geometry": {"coordinates":[-83.004409,39.971149],"type":"Point"}
}
