{
  "type": "Feature",
  "properties": {
    "addr:full":"355 N Main St Munroe Falls OH 44262",
    "addr:housenumber":"355",
    "addr:postcode":"44262",
    "addr:street":"N Main St",
    "iso:country":"US",
    "sg:address":"355 N Main St",
    "sg:city":"Munroe Falls",
    "sg:classifiers":[
        {
            "category":"Real Estate",
            "subcategory":"Real Estate Agent",
            "type":"Services"
        }
    ],
    "sg:phone":"+1 330 686 8200",
    "sg:postcode":"44262",
    "sg:province":"OH",
    "sg:website":"www.harvesthomerealty.com",
    "wof:name":"Harvest Home Realty Corp",
    "wof:placetype":"venue"
},
  "geometry": {"coordinates":[-81.440489,41.149322],"type":"Point"}
}