{
  "type": "Feature",
  "properties": {
    "iso:country":"US",
    "sg:address":"65 E Wilson Bridge Rd",
    "sg:city":"Worthington",
    "sg:classifiers":[
        {
            "category":"Real Estate",
            "subcategory":"Real Estate Services",
            "type":"Services"
        }
    ],
    "sg:phone":"+1 614 781 9770",
    "sg:postcode":"43085",
    "sg:province":"OH",
    "sg:tags":[
        "company",
        "title"
    ],
    "wof:name":"Mac Title",
    "wof:placetype":"venue"
},
  "geometry": {"coordinates":[-83.014611,40.10712],"type":"Point"}
}