{
  "type": "Feature",
  "properties": {
    "iso:country":"US",
    "sg:address":"10059 Aldridge Dr",
    "sg:city":"Columbia Station",
    "sg:classifiers":[
        {
            "category":"Professional",
            "type":"Services"
        }
    ],
    "sg:phone":"+1 440 236 3163",
    "sg:postcode":"44028",
    "sg:province":"OH",
    "wof:name":"Ohio Valley Railcars Inc",
    "wof:placetype":"venue"
},
  "geometry": {"coordinates":[-81.886809,41.347012],"type":"Point"}
}