{
  "type": "Feature",
  "properties": {
    "iso:country":"US",
    "sg:address":"206 W Main St",
    "sg:city":"Wilmington",
    "sg:classifiers":[
        {
            "category":"Personal",
            "subcategory":"Beauty Salon",
            "type":"Services"
        }
    ],
    "sg:phone":"+1 937 382 2129",
    "sg:postcode":"45177",
    "sg:province":"OH",
    "wof:name":"New Pauline's Hair Stylist",
    "wof:placetype":"venue"
},
  "geometry": {"coordinates":[-83.83243899999999,39.445488],"type":"Point"}
}