{
  "type": "Feature",
  "properties": {
    "addr:full": "2618 Lefevre Rd Troy OH 45373",
    "addr:postcode": "2618;45373",
    "addr:street": "Lefevre Rd",
    "iso:country": "US",
    "sg:address": "2618 Lefevre Rd",
    "sg:city": "Troy",
    "sg:classifiers": [
      {
        "category": "Organizations",
        "subcategory": "Community Association",
        "type": "Services"
      }
    ],
    "sg:phone": "+1 937 339 1875",
    "sg:postcode": "45373",
    "sg:province": "OH",
    "sg:tags": [
      "club"
    ],
    "wof:name": "Troy Fish \u0026 Game Club",
    "wof:placetype": "venue"
  },
  "geometry": {"coordinates":[-84.160741,40.037279],"type":"Point"}
}
