{
  "type": "Feature",
  "properties": {
    "iso:country":"US",
    "sg:address":"2618 Lefevre Rd",
    "sg:city":"Troy",
    "sg:classifiers":[
        {
            "category":"Organizations",
            "subcategory":"Community Association",
            "type":"Services"
        }
    ],
    "sg:phone":"+1 937 339 1875",
    "sg:postcode":"45373",
    "sg:province":"OH",
    "sg:tags":[
        "club"
    ],
    "wof:name":"Troy Fish & Game Club",
    "wof:placetype":"venue"
},
  "geometry": {"coordinates":[-84.160741,40.037279],"type":"Point"}
}