{
  "type": "Feature",
  "properties": {
    "iso:country":"US",
    "sg:address":"778 N Court St",
    "sg:city":"Circleville",
    "sg:classifiers":[
        {
            "category":"Health Services",
            "subcategory":"Chiropractor",
            "type":"Services"
        }
    ],
    "sg:phone":"+1 740 474 5352",
    "sg:postcode":"43113",
    "sg:province":"OH",
    "wof:name":"Pickaway Chiropractic Ctr",
    "wof:placetype":"venue"
},
  "geometry": {"coordinates":[-82.940794,39.61166],"type":"Point"}
}