{
  "type": "Feature",
  "properties": {
    "addr:full":"1902 Woodcrest Ave Youngstown OH 44505",
    "addr:housenumber":"1902",
    "addr:postcode":"44505",
    "addr:street":"Woodcrest Ave",
    "iso:country":"US",
    "sg:address":"1902 Woodcrest Ave",
    "sg:city":"Youngstown",
    "sg:classifiers":[
        {
            "category":"Organizations",
            "subcategory":"Religious Organization",
            "type":"Services"
        }
    ],
    "sg:phone":"+1 330 743 0297",
    "sg:postcode":"44505",
    "sg:province":"OH",
    "sg:tags":[
        "church"
    ],
    "wof:name":"Good Shepherd Ministry Inc",
    "wof:placetype":"venue"
},
  "geometry": {"coordinates":[-80.613434,41.108818],"type":"Point"}
}