{
  "type": "Feature",
  "properties": {
    "addr:full":"1950 Radcliff Dr Cincinnati OH 45204",
    "addr:housenumber":"1950",
    "addr:postcode":"45204",
    "addr:street":"Radcliff Dr",
    "iso:country":"US",
    "sg:address":"1950 Radcliff Dr",
    "sg:city":"Cincinnati",
    "sg:classifiers":[
        {
            "category":"Manufacturing",
            "subcategory":"Retail Goods",
            "type":"Manufacturing & Wholesale Goods"
        }
    ],
    "sg:phone":"+1 513 244 2400",
    "sg:postcode":"45204",
    "sg:province":"OH",
    "sg:tags":[
        "manufacturer"
    ],
    "wof:name":"Slush Puppie Corp",
    "wof:placetype":"venue"
},
  "geometry": {"coordinates":[-84.547622,39.122605],"type":"Point"}
}