{
  "type": "Feature",
  "properties": {
    "addr:full": "3867 Medina Rd Akron OH 44333",
    "addr:housenumber": "3867",
    "addr:postcode": "44333",
    "addr:street": "Medina Rd",
    "iso:country": "US",
    "sg:address": "3867 Medina Rd",
    "sg:city": "Akron",
    "sg:classifiers": [
      {
        "category": "Retail",
        "subcategory": "Laundry \u0026 Dry Cleaning",
        "type": "Services"
      }
    ],
    "sg:phone": "+1 330 336 9166",
    "sg:postcode": "44333",
    "sg:province": "OH",
    "sg:tags": [
      "cleaners"
    ],
    "wof:name": "Esprit Cleaners",
    "wof:placetype": "venue"
  },
  "geometry": {"coordinates":[-81.638759,41.135927],"type":"Point"}
}
