{
  "type": "Feature",
  "properties": {
    "iso:country":"US",
    "sg:address":"3867 Medina Rd",
    "sg:city":"Akron",
    "sg:classifiers":[
        {
            "category":"Retail",
            "subcategory":"Laundry & Dry Cleaning",
            "type":"Services"
        }
    ],
    "sg:phone":"+1 330 336 9166",
    "sg:postcode":"44333",
    "sg:province":"OH",
    "sg:tags":[
        "cleaners"
    ],
    "wof:name":"Esprit Cleaners",
    "wof:placetype":"venue"
},
  "geometry": {"coordinates":[-81.638759,41.135927],"type":"Point"}
}