{
  "type": "Feature",
  "properties": {
    "addr:full":"5656 Mayfield Rd Cleveland OH 44124",
    "addr:housenumber":"5656",
    "addr:postcode":"44124",
    "addr:street":"Mayfield Rd",
    "iso:country":"US",
    "sg:address":"5656 Mayfield Rd",
    "sg:city":"Cleveland",
    "sg:classifiers":[
        {
            "category":"Retail",
            "subcategory":"Auto Rental",
            "type":"Services"
        }
    ],
    "sg:phone":"+1 440 473 1500",
    "sg:postcode":"44124",
    "sg:province":"OH",
    "sg:tags":[
        "renting",
        "automobile",
        "passenger",
        "car"
    ],
    "wof:name":"Enterprise Rent A Car",
    "wof:placetype":"venue"
},
  "geometry": {"coordinates":[-81.475701,41.519926],"type":"Point"}
}