{
  "type": "Feature",
  "properties": {
    "addr:full":"2432 State Rte 49 Convoy OH 45832",
    "addr:housenumber":"2432",
    "addr:postcode":"45832",
    "addr:street":"State Rte 49",
    "iso:country":"US",
    "sg:address":"2432 State Rte 49",
    "sg:city":"Convoy",
    "sg:phone":"+1 419 749 2633",
    "sg:postcode":"45832",
    "sg:province":"OH",
    "sg:tags":[
        "farm",
        "corn",
        "soybean"
    ],
    "wof:name":"Dennis Cox",
    "wof:placetype":"venue"
},
  "geometry": {"coordinates":[-84.72651999999999,40.968789],"type":"Point"}
}