{
  "type": "Feature",
  "properties": {
    "addr:full":"6232 Ashland Rd Wooster OH 44691",
    "addr:housenumber":"6232",
    "addr:postcode":"44691",
    "addr:street":"Ashland Rd",
    "iso:country":"US",
    "sg:address":"6232 Ashland Rd",
    "sg:city":"Wooster",
    "sg:classifiers":[
        {
            "category":"Freight",
            "type":"Transportation"
        }
    ],
    "sg:phone":"+1 330 624 6945",
    "sg:postcode":"44691",
    "sg:province":"OH",
    "sg:tags":[
        "commercial",
        "storage"
    ],
    "wof:name":"H & D Mini Storage",
    "wof:placetype":"venue"
},
  "geometry": {"coordinates":[-82.04346700000001,40.816516],"type":"Point"}
}