{
  "type": "Feature",
  "properties": {
    "addr:full": "646 N Main St Marion OH 43302",
    "addr:housenumber": "646",
    "addr:postcode": "43302",
    "addr:street": "N Main St",
    "iso:country": "US",
    "sg:address": "646 N Main St",
    "sg:city": "Marion",
    "sg:classifiers": [
      {
        "category": "Banks \u0026 Credit Unions",
        "subcategory": "Bank",
        "type": "Services"
      }
    ],
    "sg:phone": "+1 740 223 3472",
    "sg:postcode": "43302",
    "sg:province": "OH",
    "sg:tags": [
      "loan"
    ],
    "wof:name": "Fast Payday Loans Of Ohio",
    "wof:placetype": "venue"
  },
  "geometry": {"coordinates":[-83.129498,40.599617],"type":"Point"}
}
