{
  "type": "Feature",
  "properties": {
    "addr:full":"8775 Co Hwy 78 Wharton OH 43359",
    "addr:housenumber":"8775",
    "addr:postcode":"43359",
    "addr:street":"Co Hwy 78",
    "iso:country":"US",
    "sg:address":"8775 Co Hwy 78",
    "sg:city":"Wharton",
    "sg:phone":"+1 419 458 5601",
    "sg:postcode":"43359",
    "sg:province":"OH",
    "sg:tags":[
        "farm",
        "corn",
        "soybean"
    ],
    "wof:name":"Bill Kotterman",
    "wof:placetype":"venue"
},
  "geometry": {"coordinates":[-83.505726,40.862482],"type":"Point"}
}