{
  "type": "Feature",
  "properties": {
    "addr:full": "50 E Long St Columbus OH 43215",
    "addr:housenumber": "50",
    "addr:postcode": "43215",
    "addr:street": "E Long St",
    "iso:country": "US",
    "sg:address": "50 E Long St",
    "sg:city": "Columbus",
    "sg:classifiers": [
      {
        "category": "Shopping",
        "subcategory": "Used Merchandise",
        "type": "Retail Goods"
      }
    ],
    "sg:phone": "+1 614 469 4660",
    "sg:postcode": "43215",
    "sg:province": "OH",
    "sg:tags": [
      "pawnbroker"
    ],
    "wof:name": "Lev's Pawn Shop",
    "wof:placetype": "venue"
  },
  "geometry": {"coordinates":[-82.998978,39.965252],"type":"Point"}
}
