{
  "type": "Feature",
  "properties": {
    "addr:full": "233 Erieview Blvd Sheffield Lake OH 44054",
    "addr:housenumber": "233",
    "addr:postcode": "44054",
    "addr:street": "Erieview Blvd",
    "iso:country": "US",
    "sg:address": "233 Erieview Blvd",
    "sg:city": "Sheffield Lake",
    "sg:classifiers": [
      {
        "category": "Professional",
        "type": "Services"
      }
    ],
    "sg:phone": "+1 216 310 1522",
    "sg:postcode": "44054",
    "sg:province": "OH",
    "wof:name": "Mark Wayne Paulk",
    "wof:placetype": "venue"
  },
  "geometry": {"coordinates":[-82.0678,41.494837],"type":"Point"}
}
