{
  "type": "Feature",
  "properties": {
    "iso:country":"US",
    "sg:address":"6745 Houck Rd SE",
    "sg:city":"Lancaster",
    "sg:phone":"+1 740 569 4612",
    "sg:postcode":"43130",
    "sg:province":"OH",
    "sg:tags":[
        "farm",
        "field",
        "corn",
        "crop"
    ],
    "wof:name":"Graham John",
    "wof:placetype":"venue"
},
  "geometry": {"coordinates":[-82.466318,39.707685],"type":"Point"}
}