{
  "type": "Feature",
  "properties": {
    "iso:country":"US",
    "sg:address":"1038 Romanus Dr",
    "sg:city":"Vandalia",
    "sg:classifiers":[
        {
            "category":"Social Services",
            "subcategory":"Child Care",
            "type":"Services"
        }
    ],
    "sg:phone":"+1 937 890 9241",
    "sg:postcode":"45377",
    "sg:province":"OH",
    "wof:name":"Aunt Lisa's Playroom LTD",
    "wof:placetype":"venue"
},
  "geometry": {"coordinates":[-84.219234,39.883932],"type":"Point"}
}