{
  "type": "Feature",
  "properties": {
    "iso:country":"US",
    "sg:address":"28819 Chagrin Blvd",
    "sg:city":"Beachwood",
    "sg:classifiers":[
        {
            "category":"Home & Garden",
            "subcategory":"Home Furnishings",
            "type":"Retail Goods"
        }
    ],
    "sg:phone":"+1 216 378 1800",
    "sg:postcode":"44122",
    "sg:province":"OH",
    "sg:tags":[
        "bath",
        "kitchen",
        "accessory"
    ],
    "wof:name":"Sur La Table",
    "wof:placetype":"venue"
},
  "geometry": {"coordinates":[-81.47499500000001,41.462488],"type":"Point"}
}