{
  "type": "Feature",
  "properties": {
    "addr:full":"2247 Moore-Saur Rd Morrow OH 45152",
    "addr:housenumber":"2247",
    "addr:postcode":"45152",
    "addr:street":"Moore-Saur Rd",
    "iso:country":"US",
    "sg:address":"2247 Moore-Saur Rd",
    "sg:city":"Morrow",
    "sg:classifiers":[
        {
            "category":"Recreation",
            "type":"Entertainment"
        }
    ],
    "sg:phone":"+1 513 899 2166",
    "sg:postcode":"45152",
    "sg:province":"OH",
    "sg:tags":[
        "charter",
        "boat"
    ],
    "wof:name":"Ft Ancient Canoe",
    "wof:placetype":"venue"
},
  "geometry": {"coordinates":[-84.104,39.391432],"type":"Point"}
}