{
  "type": "Feature",
  "properties": {
    "addr:full": "3333 W 63rd St Cleveland OH 44102",
    "addr:housenumber": "3333",
    "addr:postcode": "44102",
    "addr:street": "W 63Rd St",
    "iso:country": "US",
    "sg:address": "3333 W 63rd St",
    "sg:city": "Cleveland",
    "sg:classifiers": [
      {
        "category": "Manufacturing",
        "subcategory": "Tools \u0026 Machinery",
        "type": "Manufacturing \u0026 Wholesale Goods"
      }
    ],
    "sg:phone": "+1 216 281 6455",
    "sg:postcode": "44102",
    "sg:province": "OH",
    "sg:tags": [
      "machine",
      "shop"
    ],
    "wof:name": "National Fabricating \u0026 Machine",
    "wof:placetype": "venue"
  },
  "geometry": {"coordinates":[-81.728753,41.464202],"type":"Point"}
}
