{
  "type": "Feature",
  "properties": {
    "addr:full":"1191 E Main St Dayton OH 45426",
    "addr:housenumber":"1191",
    "addr:postcode":"45426",
    "addr:street":"E Main St",
    "iso:country":"US",
    "sg:address":"1191 E Main St",
    "sg:city":"Dayton",
    "sg:classifiers":[
        {
            "category":"Shopping",
            "subcategory":"Catalog Store",
            "type":"Retail Goods"
        }
    ],
    "sg:phone":"+1 937 854 2065",
    "sg:postcode":"45426",
    "sg:province":"OH",
    "sg:tags":[
        "mail",
        "sewing",
        "house"
    ],
    "wof:name":"Cedar Hill Design",
    "wof:placetype":"venue"
},
  "geometry": {"coordinates":[-84.283338,39.797707],"type":"Point"}
}