{
  "type": "Feature",
  "properties": {
    "addr:full":"1884 E 55th St Cleveland OH 44103",
    "addr:housenumber":"1884",
    "addr:postcode":"44103",
    "addr:street":"E 55Th St",
    "iso:country":"US",
    "sg:address":"1884 E 55th St",
    "sg:city":"Cleveland",
    "sg:classifiers":[
        {
            "category":"Manufacturing",
            "subcategory":"Furniture",
            "type":"Manufacturing & Wholesale Goods"
        }
    ],
    "sg:phone":"+1 216 431 5115",
    "sg:postcode":"44103",
    "sg:province":"OH",
    "sg:tags":[
        "mfr",
        "cabinet"
    ],
    "wof:name":"Acme Showcase & Supply Co",
    "wof:placetype":"venue"
},
  "geometry": {"coordinates":[-81.651917,41.507476],"type":"Point"}
}