{
  "type": "Feature",
  "properties": {
    "addr:full":"163 E Columbus St Columbus OH 43206",
    "addr:housenumber":"163",
    "addr:postcode":"43206",
    "addr:street":"E Columbus St",
    "iso:country":"US",
    "sg:address":"163 E Columbus St",
    "sg:city":"Columbus",
    "sg:classifiers":[
        {
            "category":"Shopping",
            "type":"Retail Goods"
        }
    ],
    "sg:phone":"+1 614 233 8600",
    "sg:postcode":"43206",
    "sg:province":"OH",
    "sg:tags":[
        "equipment",
        "miscellaneous",
        "supply"
    ],
    "wof:name":"T-Mobile USA Inc",
    "wof:placetype":"venue"
},
  "geometry": {"coordinates":[-82.992574,39.946764],"type":"Point"}
}