{
  "type": "Feature",
  "properties": {
    "addr:full":"13735 Caves Rd Novelty OH 44072",
    "addr:housenumber":"13735",
    "addr:postcode":"44072",
    "addr:street":"Caves Rd",
    "iso:country":"US",
    "sg:address":"13735 Caves Rd",
    "sg:city":"Novelty",
    "sg:classifiers":[
        {
            "category":"Insurance",
            "subcategory":"Insurance Agent",
            "type":"Services"
        }
    ],
    "sg:phone":"+1 440 338 1376",
    "sg:postcode":"44072",
    "sg:province":"OH",
    "wof:name":"Aa Auto Insurance Agency",
    "wof:placetype":"venue"
},
  "geometry": {"coordinates":[-81.362183,41.498156],"type":"Point"}
}