{
  "type": "Feature",
  "properties": {
    "iso:country":"US",
    "sg:address":"411 Solida Rd",
    "sg:city":"South Point",
    "sg:classifiers":[
        {
            "category":"Shopping",
            "subcategory":"Department Store",
            "type":"Retail Goods"
        }
    ],
    "sg:phone":"+1 740 377 2080",
    "sg:postcode":"45680",
    "sg:province":"OH",
    "wof:name":"Family Dollar Store",
    "wof:placetype":"venue"
},
  "geometry": {"coordinates":[-82.576452,38.420356],"type":"Point"}
}