{
  "type": "Feature",
  "properties": {
    "addr:full": "1743 W Main St Troy OH 45373",
    "addr:housenumber": "1743",
    "addr:postcode": "45373",
    "addr:street": "W Main St",
    "iso:country": "US",
    "sg:address": "1743 W Main St",
    "sg:city": "Troy",
    "sg:classifiers": [
      {
        "category": "Utilities",
        "subcategory": "Mobile Phone",
        "type": "Services"
      }
    ],
    "sg:phone": "+1 937 339 9141",
    "sg:postcode": "45373",
    "sg:province": "OH",
    "sg:tags": [
      "telephone",
      "cellular"
    ],
    "wof:name": "Yakety Yak Wireless",
    "wof:placetype": "venue"
  },
  "geometry": {"coordinates":[-84.235344,40.053642],"type":"Point"}
}
