{
  "type": "Feature",
  "properties": {
    "addr:full": "3489 S Dixie Hwy Franklin OH 45005",
    "addr:housenumber": "3489",
    "addr:postcode": "45005",
    "addr:street": "S Dixie Hwy",
    "iso:country": "US",
    "sg:address": "3489 S Dixie Hwy",
    "sg:city": "Franklin",
    "sg:classifiers": [
      {
        "category": "Professional",
        "subcategory": "Management \u0026 Consulting",
        "type": "Services"
      },
      {
        "category": "Professional",
        "subcategory": "Employment Agencies",
        "type": "Services"
      }
    ],
    "sg:phone": "+1 513 420 9600",
    "sg:postcode": "45005",
    "sg:province": "OH",
    "sg:tags": [
      "consultant",
      "search",
      "executive",
      "temporary",
      "opportunity"
    ],
    "wof:name": "Cbs Personnel",
    "wof:placetype": "venue"
  },
  "geometry": {"coordinates":[-84.336666,39.494339],"type":"Point"}
}
