{
  "type": "Feature",
  "properties": {
    "iso:country":"US",
    "sg:address":"1257 Hickorylake Dr",
    "sg:city":"Cincinnati",
    "sg:classifiers":[
        {
            "category":"Building & Trades",
            "subcategory":"Construction",
            "type":"Services"
        }
    ],
    "sg:phone":"+1 513 922 5709",
    "sg:postcode":"45233",
    "sg:province":"OH",
    "sg:tags":[
        "resurfacing",
        "refinishing",
        "floor"
    ],
    "wof:name":"Schmutte Custom Floor Co",
    "wof:placetype":"venue"
},
  "geometry": {"coordinates":[-84.647173,39.11915],"type":"Point"}
}