{
  "type": "Feature",
  "properties": {
    "iso:country":"US",
    "sg:address":"4140 Linden Ave",
    "sg:city":"Dayton",
    "sg:classifiers":[
        {
            "category":"Professional",
            "subcategory":"Computer Services",
            "type":"Services"
        }
    ],
    "sg:phone":"+1 937 258 0022",
    "sg:postcode":"45432",
    "sg:province":"OH",
    "sg:tags":[
        "consultant",
        "designer"
    ],
    "sg:website":"www.cdotech.com",
    "wof:name":"CDO Technologies",
    "wof:placetype":"venue"
},
  "geometry": {"coordinates":[-84.12259899999999,39.745311],"type":"Point"}
}