{
  "type": "Feature",
  "properties": {
    "iso:country":"US",
    "sg:address":"10981 5th St",
    "sg:city":"Clarksburg",
    "sg:classifiers":[
        {
            "category":"Building & Trades",
            "subcategory":"Electrical",
            "type":"Services"
        }
    ],
    "sg:phone":"+1 740 993 2624",
    "sg:postcode":"43115",
    "sg:province":"OH",
    "sg:tags":[
        "electric",
        "contractor"
    ],
    "wof:name":"Jones Electric & Plumbing",
    "wof:placetype":"venue"
},
  "geometry": {"coordinates":[-83.15792399999999,39.506635],"type":"Point"}
}