{
  "type": "Feature",
  "properties": {
    "addr:full": "10981 5th St Clarksburg OH 43115",
    "addr:housenumber": "10981",
    "addr:postcode": "43115",
    "addr:street": "5Th St",
    "iso:country": "US",
    "sg:address": "10981 5th St",
    "sg:city": "Clarksburg",
    "sg:classifiers": [
      {
        "category": "Building \u0026 Trades",
        "subcategory": "Electrical",
        "type": "Services"
      }
    ],
    "sg:phone": "+1 740 993 2624",
    "sg:postcode": "43115",
    "sg:province": "OH",
    "sg:tags": [
      "electric",
      "contractor"
    ],
    "wof:name": "Jones Electric \u0026 Plumbing",
    "wof:placetype": "venue"
  },
  "geometry": {"coordinates":[-83.157924,39.506635],"type":"Point"}
}
