{
  "type": "Feature",
  "properties": {
    "addr:full": "4081 Rocky River Dr Cleveland OH 44135",
    "addr:housenumber": "4081",
    "addr:postcode": "44135",
    "addr:street": "Rocky River Dr",
    "iso:country": "US",
    "sg:address": "4081 Rocky River Dr",
    "sg:city": "Cleveland",
    "sg:classifiers": [
      {
        "category": "Restaurant",
        "type": "Food \u0026 Drink"
      }
    ],
    "sg:phone": "+1 216 941 8283",
    "sg:postcode": "44135",
    "sg:province": "OH",
    "sg:tags": [
      "eating"
    ],
    "wof:name": "Dairy Queen",
    "wof:placetype": "venue"
  },
  "geometry": {"coordinates":[-81.818658,41.443669],"type":"Point"}
}
