{
  "type": "Feature",
  "properties": {
    "iso:country":"US",
    "sg:address":"125 W Boyer St",
    "sg:city":"Wadsworth",
    "sg:classifiers":[
        {
            "category":"Health Services",
            "subcategory":"Doctor",
            "type":"Services"
        }
    ],
    "sg:phone":"+1 330 336 2558",
    "sg:postcode":"44281",
    "sg:province":"OH",
    "sg:tags":[
        "dentist"
    ],
    "wof:name":"Ashai & Adenwalla Orthodontics",
    "wof:placetype":"venue"
},
  "geometry": {"coordinates":[-81.73128699999999,41.027935],"type":"Point"}
}