{
  "type": "Feature",
  "properties": {
    "addr:full": "27081 Bagley Rd Cleveland OH 44138",
    "addr:housenumber": "27081",
    "addr:postcode": "44138",
    "addr:street": "Bagley Rd",
    "iso:country": "US",
    "sg:address": "27081 Bagley Rd",
    "sg:city": "Cleveland",
    "sg:classifiers": [
      {
        "category": "Insurance",
        "subcategory": "Insurance Agent",
        "type": "Services"
      }
    ],
    "sg:phone": "+1 440 235 1110",
    "sg:postcode": "44138",
    "sg:province": "OH",
    "wof:name": "Donald P Harnegie Insurance",
    "wof:placetype": "venue"
  },
  "geometry": {"coordinates":[-81.928959,41.372602],"type":"Point"}
}
