{
  "type": "Feature",
  "properties": {
    "addr:full": "200 Plaza Blvd Chillicothe OH 45601",
    "addr:housenumber": "200",
    "addr:postcode": "45601",
    "addr:street": "Plaza Blvd",
    "iso:country": "US",
    "sg:address": "200 Plaza Blvd",
    "sg:city": "Chillicothe",
    "sg:classifiers": [
      {
        "category": "Restaurant",
        "type": "Food \u0026 Drink"
      },
      {
        "category": "Personal",
        "subcategory": "Beauty Salon",
        "type": "Services"
      }
    ],
    "sg:phone": "+1 740 773 2100",
    "sg:postcode": "45601",
    "sg:province": "OH",
    "sg:tags": [
      "shop"
    ],
    "sg:website": "www.nynygrill.com",
    "wof:name": "New York New York Grill",
    "wof:placetype": "venue"
  },
  "geometry": {"coordinates":[-82.979081,39.351246],"type":"Point"}
}
