{
  "type": "Feature",
  "properties": {
    "iso:country":"US",
    "sg:address":"200 Plaza Blvd",
    "sg:city":"Chillicothe",
    "sg:classifiers":[
        {
            "category":"Restaurant",
            "type":"Food & Drink"
        },
        {
            "category":"Personal",
            "subcategory":"Beauty Salon",
            "type":"Services"
        }
    ],
    "sg:phone":"+1 740 773 2100",
    "sg:postcode":"45601",
    "sg:province":"OH",
    "sg:tags":[
        "shop"
    ],
    "sg:website":"www.nynygrill.com",
    "wof:name":"New York New York Grill",
    "wof:placetype":"venue"
},
  "geometry": {"coordinates":[-82.97908099999999,39.351246],"type":"Point"}
}