{
  "type": "Feature",
  "properties": {
    "iso:country":"US",
    "sg:address":"1222 Waynesburg Dr SE",
    "sg:city":"Canton",
    "sg:classifiers":[
        {
            "category":"Freight",
            "type":"Transportation"
        }
    ],
    "sg:phone":"+1 330 456 8648",
    "sg:postcode":"44707",
    "sg:province":"OH",
    "sg:tags":[
        "trucking"
    ],
    "wof:name":"R & J Trucking",
    "wof:placetype":"venue"
},
  "geometry": {"coordinates":[-81.34775,40.785619],"type":"Point"}
}