{
  "type": "Feature",
  "properties": {
    "addr:full": "1222 Waynesburg Dr SE Canton OH 44707",
    "addr:housenumber": "1222",
    "addr:postcode": "44707",
    "addr:street": "Waynesburg Dr Se",
    "iso:country": "US",
    "sg:address": "1222 Waynesburg Dr SE",
    "sg:city": "Canton",
    "sg:classifiers": [
      {
        "category": "Freight",
        "type": "Transportation"
      }
    ],
    "sg:phone": "+1 330 456 8648",
    "sg:postcode": "44707",
    "sg:province": "OH",
    "sg:tags": [
      "trucking"
    ],
    "wof:name": "R \u0026 J Trucking",
    "wof:placetype": "venue"
  },
  "geometry": {"coordinates":[-81.34775,40.785619],"type":"Point"}
}
