{
  "type": "Feature",
  "properties": {
    "addr:full": "8130 W State Rd Elida OH 45807",
    "addr:housenumber": "8130",
    "addr:postcode": "45807",
    "addr:street": "W State Rd",
    "iso:country": "US",
    "sg:address": "8130 W State Rd",
    "sg:city": "Elida",
    "sg:classifiers": [
      {
        "category": "Building \u0026 Trades",
        "subcategory": "Construction",
        "type": "Services"
      }
    ],
    "sg:phone": "+1 419 339 4938",
    "sg:postcode": "45807",
    "sg:province": "OH",
    "sg:tags": [
      "porch",
      "enclosure",
      "patio",
      "deck"
    ],
    "wof:name": "Hohlbein Home Improvements",
    "wof:placetype": "venue"
  },
  "geometry": {"coordinates":[-84.258732,40.816517],"type":"Point"}
}
