{
  "type": "Feature",
  "properties": {
    "iso:country":"US",
    "sg:address":"8130 W State Rd",
    "sg:city":"Elida",
    "sg:classifiers":[
        {
            "category":"Building & Trades",
            "subcategory":"Construction",
            "type":"Services"
        }
    ],
    "sg:phone":"+1 419 339 4938",
    "sg:postcode":"45807",
    "sg:province":"OH",
    "sg:tags":[
        "porch",
        "enclosure",
        "patio",
        "deck"
    ],
    "wof:name":"Hohlbein Home Improvements",
    "wof:placetype":"venue"
},
  "geometry": {"coordinates":[-84.25873199999999,40.816517],"type":"Point"}
}