{
  "type": "Feature",
  "properties": {
    "iso:country":"US",
    "sg:address":"5020 Youngstown Warren Rd",
    "sg:city":"Niles",
    "sg:classifiers":[
        {
            "category":"Autos & Motor Vehicles",
            "subcategory":"Fuel & Gas Station",
            "type":"Retail Goods"
        }
    ],
    "sg:phone":"+1 330 652 4592",
    "sg:postcode":"44446",
    "sg:province":"OH",
    "sg:tags":[
        "oil"
    ],
    "wof:name":"Mc Quaids Svc Ctr",
    "wof:placetype":"venue"
},
  "geometry": {"coordinates":[-80.760768,41.212776],"type":"Point"}
}