{
  "type": "Feature",
  "properties": {
    "iso:country":"US",
    "sg:address":"3019 Chickadee Dr",
    "sg:city":"Hamilton",
    "sg:classifiers":[
        {
            "category":"Building & Trades",
            "subcategory":"Construction",
            "type":"Services"
        }
    ],
    "sg:phone":"+1 513 726 5666",
    "sg:postcode":"45011",
    "sg:province":"OH",
    "sg:tags":[
        "contractor"
    ],
    "wof:name":"Abner Roofing & Gutter",
    "wof:placetype":"venue"
},
  "geometry": {"coordinates":[-84.548839,39.464069],"type":"Point"}
}