{
  "type": "Feature",
  "properties": {
    "addr:full": "3019 Chickadee Dr Hamilton OH 45011",
    "addr:housenumber": "3019",
    "addr:postcode": "45011",
    "addr:street": "Chickadee Dr",
    "iso:country": "US",
    "sg:address": "3019 Chickadee Dr",
    "sg:city": "Hamilton",
    "sg:classifiers": [
      {
        "category": "Building \u0026 Trades",
        "subcategory": "Construction",
        "type": "Services"
      }
    ],
    "sg:phone": "+1 513 726 5666",
    "sg:postcode": "45011",
    "sg:province": "OH",
    "sg:tags": [
      "contractor"
    ],
    "wof:name": "Abner Roofing \u0026 Gutter",
    "wof:placetype": "venue"
  },
  "geometry": {"coordinates":[-84.548839,39.464069],"type":"Point"}
}
