{
  "type": "Feature",
  "properties": {
    "addr:full":"4 N Park Pl Newark OH 43055",
    "addr:housenumber":"4",
    "addr:postcode":"43055",
    "addr:street":"N Park Pl",
    "iso:country":"US",
    "sg:address":"4 N Park Pl",
    "sg:city":"Newark",
    "sg:classifiers":[
        {
            "category":"Shopping",
            "type":"Retail Goods"
        }
    ],
    "sg:phone":"+1 740 349 8710",
    "sg:postcode":"43055",
    "sg:province":"OH",
    "sg:tags":[
        "picture",
        "frame"
    ],
    "wof:name":"Frame Up",
    "wof:placetype":"venue"
},
  "geometry": {"coordinates":[-82.401123,40.058864],"type":"Point"}
}