{
  "type": "Feature",
  "properties": {
    "iso:country":"US",
    "sg:address":"2601 Far Hills Ave",
    "sg:city":"Dayton",
    "sg:classifiers":[
        {
            "category":"Shopping",
            "subcategory":"Optical Goods",
            "type":"Retail Goods"
        },
        {
            "category":"Health Services",
            "subcategory":"Doctor",
            "type":"Services"
        }
    ],
    "sg:phone":"+1 937 298 1703",
    "sg:postcode":"45419",
    "sg:province":"OH",
    "sg:tags":[
        "specializing",
        "ophthalmologist",
        "glaucoma",
        "cataract"
    ],
    "wof:name":"Oakwood Optical",
    "wof:placetype":"venue"
},
  "geometry": {"coordinates":[-84.17068999999999,39.706886],"type":"Point"}
}