{
  "type": "Feature",
  "properties": {
    "addr:full":"2737 Navarre Ave Oregon OH 43616",
    "addr:housenumber":"2737",
    "addr:postcode":"43616",
    "addr:street":"Navarre Ave",
    "iso:country":"US",
    "sg:address":"2737 Navarre Ave",
    "sg:city":"Oregon",
    "sg:classifiers":[
        {
            "category":"Shopping",
            "subcategory":"Optical Goods",
            "type":"Retail Goods"
        }
    ],
    "sg:phone":"+1 419 693 3376",
    "sg:postcode":"43616",
    "sg:province":"OH",
    "sg:tags":[
        "optician"
    ],
    "wof:name":"James Optical Inc",
    "wof:placetype":"venue"
},
  "geometry": {"coordinates":[-83.479315,41.63687],"type":"Point"}
}