{
  "type": "Feature",
  "properties": {
    "addr:full": "3826 Morse Rd Columbus OH 43219",
    "addr:housenumber": "3826",
    "addr:postcode": "43219",
    "addr:street": "Morse Rd",
    "iso:country": "US",
    "sg:address": "3826 Morse Rd",
    "sg:city": "Columbus",
    "sg:classifiers": [
      {
        "category": "Shopping",
        "subcategory": "Stationery \u0026 Office Supplies",
        "type": "Retail Goods"
      }
    ],
    "sg:phone": "+1 614 418 0370",
    "sg:postcode": "43219",
    "sg:province": "OH",
    "sg:tags": [
      "equipment",
      "school"
    ],
    "sg:website": "www.officemax.com",
    "wof:name": "Office Max",
    "wof:placetype": "venue"
  },
  "geometry": {"coordinates":[-82.916279,40.057754],"type":"Point"}
}
