{
  "type": "Feature",
  "properties": {
    "addr:full": "5949 E Law Rd Valley City OH 44280",
    "addr:housenumber": "5949",
    "addr:postcode": "44280",
    "addr:street": "E Law Rd",
    "iso:country": "US",
    "sg:address": "5949 E Law Rd",
    "sg:city": "Valley City",
    "sg:classifiers": [
      {
        "category": "Home \u0026 Garden",
        "subcategory": "Furniture",
        "type": "Retail Goods"
      }
    ],
    "sg:phone": "+1 330 483 3118",
    "sg:postcode": "44280",
    "sg:province": "OH",
    "sg:tags": [
      "cabinet"
    ],
    "wof:name": "Valley Cabinet Inc",
    "wof:placetype": "venue"
  },
  "geometry": {"coordinates":[-81.899517,41.222898],"type":"Point"}
}
