{
  "type": "Feature",
  "properties": {
    "addr:full":"401 Tuscarawas St W Canton OH 44702",
    "addr:housenumber":"401",
    "addr:postcode":"44702",
    "addr:street":"Tuscarawas St W",
    "iso:country":"US",
    "sg:address":"401 Tuscarawas St W",
    "sg:city":"Canton",
    "sg:classifiers":[
        {
            "category":"Professional",
            "subcategory":"Management & Consulting",
            "type":"Services"
        }
    ],
    "sg:phone":"+1 330 438 0100",
    "sg:postcode":"44702",
    "sg:province":"OH",
    "sg:tags":[
        "marketing",
        "consultant"
    ],
    "wof:name":"Strategyone Marketing",
    "wof:placetype":"venue"
},
  "geometry": {"coordinates":[-81.37832400000001,40.799171],"type":"Point"}
}