{
  "type": "Feature",
  "properties": {
    "addr:full": "25911 Detroit Rd Cleveland OH 44145",
    "addr:housenumber": "25911",
    "addr:postcode": "44145",
    "addr:street": "Detroit Rd",
    "iso:country": "US",
    "sg:address": "25911 Detroit Rd",
    "sg:city": "Cleveland",
    "sg:classifiers": [
      {
        "category": "Shopping",
        "subcategory": "Clothing, Apparel, \u0026 Fashions",
        "type": "Retail Goods"
      }
    ],
    "sg:phone": "+1 440 835 3655",
    "sg:postcode": "44145",
    "sg:province": "OH",
    "sg:tags": [
      "shop",
      "bridal"
    ],
    "wof:name": "A Bride's Design",
    "wof:placetype": "venue"
  },
  "geometry": {"coordinates":[-81.907342,41.469415],"type":"Point"}
}
