{
  "type": "Feature",
  "properties": {
    "addr:full":"5675 Hudson Industrial Pkwy Hudson OH 44236",
    "addr:housenumber":"5675",
    "addr:postcode":"44236",
    "addr:street":"Hudson Industrial Pkwy",
    "iso:country":"US",
    "sg:address":"5675 Hudson Industrial Pkwy",
    "sg:city":"Hudson",
    "sg:classifiers":[
        {
            "category":"Manufacturing",
            "subcategory":"Electronics",
            "type":"Manufacturing & Wholesale Goods"
        }
    ],
    "sg:phone":"+1 330 655 9000",
    "sg:postcode":"44236",
    "sg:province":"OH",
    "sg:tags":[
        "boards",
        "mfg",
        "peripheral",
        "computer",
        "printed",
        "circuit",
        "etched"
    ],
    "sg:website":"www.quatech.com",
    "wof:name":"Quatech Inc",
    "wof:placetype":"venue"
},
  "geometry": {"coordinates":[-81.42822700000001,41.216809],"type":"Point"}
}