{
  "type": "Feature",
  "properties": {
    "iso:country":"US",
    "sg:address":"4300 Mechanicsburg Rd",
    "sg:city":"Wooster",
    "sg:classifiers":[
        {
            "category":"Wholesale",
            "subcategory":"Electrical",
            "type":"Manufacturing & Wholesale Goods"
        }
    ],
    "sg:phone":"+1 330 345 3519",
    "sg:postcode":"44691",
    "sg:province":"OH",
    "sg:tags":[
        "meter"
    ],
    "wof:name":"Gatherco",
    "wof:placetype":"venue"
},
  "geometry": {"coordinates":[-81.98091,40.852534],"type":"Point"}
}