{
  "type": "Feature",
  "properties": {
    "addr:full": "4300 Mechanicsburg Rd Wooster OH 44691",
    "addr:postcode": "4300;44691",
    "addr:street": "Mechanicsburg Rd",
    "iso:country": "US",
    "sg:address": "4300 Mechanicsburg Rd",
    "sg:city": "Wooster",
    "sg:classifiers": [
      {
        "category": "Wholesale",
        "subcategory": "Electrical",
        "type": "Manufacturing \u0026 Wholesale Goods"
      }
    ],
    "sg:phone": "+1 330 345 3519",
    "sg:postcode": "44691",
    "sg:province": "OH",
    "sg:tags": [
      "meter"
    ],
    "wof:name": "Gatherco",
    "wof:placetype": "venue"
  },
  "geometry": {"coordinates":[-81.98091,40.852534],"type":"Point"}
}
