{
  "type": "Feature",
  "properties": {
    "addr:full": "22414 Stull Rd Howard OH 43028",
    "addr:postcode": "22414;43028",
    "addr:street": "Stull Rd",
    "iso:country": "US",
    "sg:address": "22414 Stull Rd",
    "sg:city": "Howard",
    "sg:classifiers": [
      {
        "category": "Freight",
        "type": "Transportation"
      }
    ],
    "sg:phone": "+1 740 427 3100",
    "sg:postcode": "43028",
    "sg:province": "OH",
    "wof:name": "East Knox Auto Transport",
    "wof:placetype": "venue"
  },
  "geometry": {"coordinates":[-82.343668,40.390906],"type":"Point"}
}
