{
  "type": "Feature",
  "properties": {
    "iso:country":"US",
    "sg:address":"844 Kerr St",
    "sg:city":"Columbus",
    "sg:classifiers":[
        {
            "category":"Retail",
            "subcategory":"Repair Shop",
            "type":"Services"
        }
    ],
    "sg:phone":"+1 614 291 3115",
    "sg:postcode":"43215",
    "sg:province":"OH",
    "sg:tags":[
        "product",
        "sheet",
        "metal",
        "custom",
        "fabrication",
        "welding"
    ],
    "wof:name":"Blackwood Sheet Metal Inc",
    "wof:placetype":"venue"
},
  "geometry": {"coordinates":[-83.00186600000001,39.979341],"type":"Point"}
}