{
  "type": "Feature",
  "properties": {
    "iso:country":"US",
    "sg:address":"622 E Wheeling St",
    "sg:city":"Lancaster",
    "sg:classifiers":[
        {
            "category":"Personal",
            "subcategory":"Beauty Salon",
            "type":"Services"
        }
    ],
    "sg:phone":"+1 740 654 9987",
    "sg:postcode":"43130",
    "sg:province":"OH",
    "sg:tags":[
        "shop"
    ],
    "wof:name":"Victorian Beauty Parlour",
    "wof:placetype":"venue"
},
  "geometry": {"coordinates":[-82.590451,39.714646],"type":"Point"}
}