{
  "type": "Feature",
  "properties": {
    "iso:country":"US",
    "sg:address":"528 Main St",
    "sg:city":"Coshocton",
    "sg:classifiers":[
        {
            "category":"Shopping",
            "subcategory":"Department Store",
            "type":"Retail Goods"
        }
    ],
    "sg:phone":"+1 740 623 9950",
    "sg:postcode":"43812",
    "sg:province":"OH",
    "wof:name":"Bargain Shack",
    "wof:placetype":"venue"
},
  "geometry": {"coordinates":[-81.862664,40.273596],"type":"Point"}
}