{
  "type": "Feature",
  "properties": {
    "iso:country":"US",
    "sg:address":"6446 Harborview Ave NW",
    "sg:city":"Canton",
    "sg:classifiers":[
        {
            "category":"Real Estate",
            "subcategory":"Real Estate Agent",
            "type":"Services"
        }
    ],
    "sg:phone":"+1 330 966 6944",
    "sg:postcode":"44718",
    "sg:province":"OH",
    "sg:tags":[
        "inspection"
    ],
    "wof:name":"American Property Inspections",
    "wof:placetype":"venue"
},
  "geometry": {"coordinates":[-81.468644,40.874553],"type":"Point"}
}