{
  "type": "Feature",
  "properties": {
    "addr:full": "500 S Main St Findlay OH 45840",
    "addr:housenumber": "500",
    "addr:postcode": "45840",
    "addr:street": "S Main St",
    "iso:country": "US",
    "sg:address": "500 S Main St",
    "sg:city": "Findlay",
    "sg:classifiers": [
      {
        "category": "Banks \u0026 Credit Unions",
        "subcategory": "Investment Brokerage",
        "type": "Services"
      }
    ],
    "sg:phone": "+1 419 424 7315",
    "sg:postcode": "45840",
    "sg:province": "OH",
    "sg:tags": [
      "security"
    ],
    "wof:name": "Cooper Tire \u0026 Rubber Co",
    "wof:placetype": "venue"
  },
  "geometry": {"coordinates":[-83.650272,41.037039],"type":"Point"}
}
