{
  "type": "Feature",
  "properties": {
    "iso:country":"US",
    "sg:address":"500 S Main St",
    "sg:city":"Findlay",
    "sg:classifiers":[
        {
            "category":"Banks & Credit Unions",
            "subcategory":"Investment Brokerage",
            "type":"Services"
        }
    ],
    "sg:phone":"+1 419 424 7315",
    "sg:postcode":"45840",
    "sg:province":"OH",
    "sg:tags":[
        "security"
    ],
    "wof:name":"Cooper Tire & Rubber Co",
    "wof:placetype":"venue"
},
  "geometry": {"coordinates":[-83.650272,41.037039],"type":"Point"}
}