{
  "type": "Feature",
  "properties": {
    "iso:country":"US",
    "sg:address":"7500 Twp Rd 103",
    "sg:city":"Millersburg",
    "sg:classifiers":[
        {
            "category":"Professional",
            "type":"Services"
        }
    ],
    "sg:phone":"+1 330 674 1955",
    "sg:postcode":"44654",
    "sg:province":"OH",
    "sg:tags":[
        "establishment"
    ],
    "wof:name":"Hickory Lake Inc",
    "wof:placetype":"venue"
},
  "geometry": {"coordinates":[-81.903682,40.5019],"type":"Point"}
}