{
  "type": "Feature",
  "properties": {
    "iso:country":"US",
    "sg:address":"363 Marietta Rd",
    "sg:city":"Chillicothe",
    "sg:classifiers":[
        {
            "category":"Professional",
            "type":"Services"
        }
    ],
    "sg:phone":"+1 740 775 4491",
    "sg:postcode":"45601",
    "sg:province":"OH",
    "wof:name":"Frontier Vision",
    "wof:placetype":"venue"
},
  "geometry": {"coordinates":[-82.969774,39.353064],"type":"Point"}
}