{
  "type": "Feature",
  "properties": {
    "iso:country":"US",
    "sg:address":"401 Clay St",
    "sg:city":"Carey",
    "sg:classifiers":[
        {
            "category":"Education",
            "subcategory":"School",
            "type":"Public Place"
        }
    ],
    "sg:phone":"+1 419 396 6166",
    "sg:postcode":"43316",
    "sg:province":"OH",
    "sg:tags":[
        "organization",
        "religious"
    ],
    "sg:website":"www.ourladyofconsolationschool.org",
    "wof:name":"Our Lady Of Consolation School",
    "wof:placetype":"venue"
},
  "geometry": {"coordinates":[-83.389937,40.951158],"type":"Point"}
}