{
  "type": "Feature",
  "properties": {
    "iso:country":"US",
    "sg:address":"165 Thornbury Ln",
    "sg:city":"Powell",
    "sg:classifiers":[
        {
            "category":"Building & Trades",
            "subcategory":"Construction",
            "type":"Services"
        }
    ],
    "sg:phone":"+1 614 847 9110",
    "sg:postcode":"43065",
    "sg:province":"OH",
    "sg:tags":[
        "house",
        "real estate"
    ],
    "wof:name":"Arlington Homes",
    "wof:placetype":"venue"
},
  "geometry": {"coordinates":[-83.05407200000001,40.160538],"type":"Point"}
}