{
  "type": "Feature",
  "properties": {
    "addr:full":"715 W Coshocton St Johnstown OH 43031",
    "addr:housenumber":"715",
    "addr:postcode":"43031",
    "addr:street":"W Coshocton St",
    "iso:country":"US",
    "sg:address":"715 W Coshocton St",
    "sg:city":"Johnstown",
    "sg:classifiers":[
        {
            "category":"Shopping",
            "subcategory":"Used Merchandise",
            "type":"Retail Goods"
        }
    ],
    "sg:phone":"+1 740 967 2926",
    "sg:postcode":"43031",
    "sg:province":"OH",
    "wof:name":"Goodwill Industries Johnstown",
    "wof:placetype":"venue"
},
  "geometry": {"coordinates":[-82.700343,40.147698],"type":"Point"}
}