{
  "type": "Feature",
  "properties": {
    "iso:country":"US",
    "sg:address":"8757 Smoky Row Rd",
    "sg:city":"Powell",
    "sg:classifiers":[
        {
            "category":"Insurance",
            "subcategory":"Insurance Agent",
            "type":"Services"
        }
    ],
    "sg:phone":"+1 614 793 0905",
    "sg:postcode":"43065",
    "sg:province":"OH",
    "wof:name":"State Farm Insurance",
    "wof:placetype":"venue"
},
  "geometry": {"coordinates":[-83.070983,40.133351],"type":"Point"}
}