{
  "type": "Feature",
  "properties": {
    "addr:full": "900 Eulalia Ave Upper Sandusky OH 43351",
    "addr:housenumber": "900",
    "addr:postcode": "43351",
    "addr:street": "Eulalia Ave",
    "iso:country": "US",
    "sg:address": "900 Eulalia Ave",
    "sg:city": "Upper Sandusky",
    "sg:classifiers": [
      {
        "category": "Real Estate",
        "subcategory": "Real Estate Operator",
        "type": "Services"
      }
    ],
    "sg:phone": "+1 419 294 5327",
    "sg:postcode": "43351",
    "sg:province": "OH",
    "sg:tags": [
      "apartment"
    ],
    "wof:name": "Riddlehaven Apartments",
    "wof:placetype": "venue"
  },
  "geometry": {"coordinates":[-83.286971,40.816049],"type":"Point"}
}
