{
  "type": "Feature",
  "properties": {
    "addr:full":"315 Solon Rd Chagrin Falls OH 44022",
    "addr:housenumber":"315",
    "addr:postcode":"44022",
    "addr:street":"Solon Rd",
    "iso:country":"US",
    "sg:address":"315 Solon Rd",
    "sg:city":"Chagrin Falls",
    "sg:classifiers":[
        {
            "category":"Organizations",
            "subcategory":"Religious Organization",
            "type":"Services"
        }
    ],
    "sg:phone":"+1 440 247 4618",
    "sg:postcode":"44022",
    "sg:province":"OH",
    "sg:tags":[
        "clergy"
    ],
    "wof:name":"R Lehmann",
    "wof:placetype":"venue"
},
  "geometry": {"coordinates":[-81.399399,41.418722],"type":"Point"}
}