{
  "type": "Feature",
  "properties": {
    "addr:full":"8581 Columbia Rd SW Pataskala OH 43062",
    "addr:housenumber":"8581",
    "addr:postcode":"43062",
    "addr:street":"Columbia Rd Sw",
    "iso:country":"US",
    "sg:address":"8581 Columbia Rd SW",
    "sg:city":"Pataskala",
    "sg:classifiers":[
        {
            "category":"Building & Trades",
            "subcategory":"Construction",
            "type":"Services"
        }
    ],
    "sg:phone":"+1 740 964 0881",
    "sg:postcode":"43062",
    "sg:province":"OH",
    "sg:tags":[
        "house"
    ],
    "wof:name":"Const Johnson & Roofing",
    "wof:placetype":"venue"
},
  "geometry": {"coordinates":[-82.694103,39.96969],"type":"Point"}
}