{
  "type": "Feature",
  "properties": {
    "addr:full":"507 Lansing Rd Akron OH 44312",
    "addr:housenumber":"507",
    "addr:postcode":"44312",
    "addr:street":"Lansing Rd",
    "iso:country":"US",
    "sg:address":"507 Lansing Rd",
    "sg:city":"Akron",
    "sg:classifiers":[
        {
            "category":"Restaurant",
            "type":"Food & Drink"
        }
    ],
    "sg:phone":"+1 330 724 6101",
    "sg:postcode":"44312",
    "sg:province":"OH",
    "sg:tags":[
        "eating"
    ],
    "wof:name":"B-K Root Beer Drive Inc",
    "wof:placetype":"venue"
},
  "geometry": {"coordinates":[-81.454877,41.048334],"type":"Point"}
}