{
  "type": "Feature",
  "properties": {
    "addr:full": "21315 Kenyon Dr Cleveland OH 44137",
    "addr:housenumber": "21315",
    "addr:postcode": "44137",
    "addr:street": "Kenyon Dr",
    "iso:country": "US",
    "sg:address": "21315 Kenyon Dr",
    "sg:city": "Cleveland",
    "sg:classifiers": [
      {
        "category": "Professional",
        "subcategory": "Advertising",
        "type": "Services"
      }
    ],
    "sg:phone": "+1 216 475 1250",
    "sg:postcode": "44137",
    "sg:province": "OH",
    "sg:website": "www.promotionspecialists.com",
    "wof:name": "Promotion Specialists Inc",
    "wof:placetype": "venue"
  },
  "geometry": {"coordinates":[-81.528178,41.418618],"type":"Point"}
}
