{
  "type": "Feature",
  "properties": {
    "addr:full": "8651 Abbot Cove Ave Galloway OH 43119",
    "addr:housenumber": "8651",
    "addr:postcode": "43119",
    "addr:street": "Abbot Cove Ave",
    "iso:country": "US",
    "sg:address": "8651 Abbot Cove Ave",
    "sg:city": "Galloway",
    "sg:classifiers": [
      {
        "category": "Building \u0026 Trades",
        "subcategory": "Construction",
        "type": "Services"
      }
    ],
    "sg:phone": "+1 614 946 8034",
    "sg:postcode": "43119",
    "sg:province": "OH",
    "sg:tags": [
      "home",
      "improvement"
    ],
    "wof:name": "Levitt Construction",
    "wof:placetype": "venue"
  },
  "geometry": {"coordinates":[-83.230369,39.950866],"type":"Point"}
}
