{
  "type": "Feature",
  "properties": {
    "iso:country":"US",
    "sg:address":"6785 W 130th St",
    "sg:city":"Cleveland",
    "sg:classifiers":[
        {
            "category":"Health Services",
            "subcategory":"Health Practitioner",
            "type":"Services"
        }
    ],
    "sg:phone":"+1 440 843 8854",
    "sg:postcode":"44130",
    "sg:province":"OH",
    "sg:tags":[
        "nurse",
        "registry"
    ],
    "wof:name":"Quality Care",
    "wof:placetype":"venue"
},
  "geometry": {"coordinates":[-81.784724,41.375191],"type":"Point"}
}