{
  "type": "Feature",
  "properties": {
    "addr:full":"10700 Stratton Rd Salem OH 44460",
    "addr:housenumber":"10700",
    "addr:postcode":"44460",
    "addr:street":"Stratton Rd",
    "iso:country":"US",
    "sg:address":"10700 Stratton Rd",
    "sg:city":"Salem",
    "sg:classifiers":[
        {
            "category":"Freight",
            "type":"Transportation"
        }
    ],
    "sg:phone":"+1 330 337 6361",
    "sg:postcode":"44460",
    "sg:province":"OH",
    "sg:tags":[
        "operator",
        "local",
        "trucking"
    ],
    "wof:name":"Esterle Trucking",
    "wof:placetype":"venue"
},
  "geometry": {"coordinates":[-80.88593400000001,40.959888],"type":"Point"}
}