{
  "type": "Feature",
  "properties": {
    "addr:full": "26611 Dixie Hwy Perrysburg OH 43551",
    "addr:housenumber": "26611",
    "addr:postcode": "43551",
    "addr:street": "Dixie Hwy",
    "iso:country": "US",
    "sg:address": "26611 Dixie Hwy",
    "sg:city": "Perrysburg",
    "sg:classifiers": [
      {
        "category": "Recreation",
        "type": "Entertainment"
      }
    ],
    "sg:phone": "+1 419 872 0373",
    "sg:postcode": "43551",
    "sg:province": "OH",
    "sg:tags": [
      "club",
      "membership"
    ],
    "wof:name": "AAA Toledo Automobile",
    "wof:placetype": "venue"
  },
  "geometry": {"coordinates":[-83.6346,41.541166],"type":"Point"}
}
