{
  "type": "Feature",
  "properties": {
    "iso:country":"US",
    "sg:address":"26611 Dixie Hwy",
    "sg:city":"Perrysburg",
    "sg:classifiers":[
        {
            "category":"Recreation",
            "type":"Entertainment"
        }
    ],
    "sg:phone":"+1 419 872 0373",
    "sg:postcode":"43551",
    "sg:province":"OH",
    "sg:tags":[
        "club",
        "membership"
    ],
    "wof:name":"AAA Toledo Automobile",
    "wof:placetype":"venue"
},
  "geometry": {"coordinates":[-83.63460000000001,41.541166],"type":"Point"}
}