{
  "type": "Feature",
  "properties": {
    "iso:country":"US",
    "sg:address":"403 Tenney Ave",
    "sg:city":"Campbell",
    "sg:classifiers":[
        {
            "category":"Banks & Credit Unions",
            "subcategory":"Bank",
            "type":"Services"
        }
    ],
    "sg:phone":"+1 330 742 4433",
    "sg:postcode":"44405",
    "sg:province":"OH",
    "sg:tags":[
        "commercial",
        "national",
        "saving"
    ],
    "sg:website":"https://www.nationalcity.com",
    "wof:name":"National City Bank",
    "wof:placetype":"venue"
},
  "geometry": {"coordinates":[-80.593526,41.075568],"type":"Point"}
}