{
  "type": "Feature",
  "properties": {
    "iso:country":"US",
    "sg:address":"3793 State Rte 13",
    "sg:city":"New Lexington",
    "sg:classifiers":[
        {
            "category":"Autos & Motor Vehicles",
            "subcategory":"Fuel & Gas Station",
            "type":"Retail Goods"
        }
    ],
    "sg:phone":"+1 740 342 4543",
    "sg:postcode":"43764",
    "sg:province":"OH",
    "sg:tags":[
        "oil"
    ],
    "sg:website":"www.certifiedoil.com",
    "wof:name":"Certified Oil Co",
    "wof:placetype":"venue"
},
  "geometry": {"coordinates":[-82.233372,39.744795],"type":"Point"}
}