{
  "type": "Feature",
  "properties": {
    "addr:full": "3793 State Rte 13 New Lexington OH 43764",
    "addr:housenumber": "3793",
    "addr:postcode": "43764",
    "addr:street": "State Rte 13",
    "iso:country": "US",
    "sg:address": "3793 State Rte 13",
    "sg:city": "New Lexington",
    "sg:classifiers": [
      {
        "category": "Autos \u0026 Motor Vehicles",
        "subcategory": "Fuel \u0026 Gas Station",
        "type": "Retail Goods"
      }
    ],
    "sg:phone": "+1 740 342 4543",
    "sg:postcode": "43764",
    "sg:province": "OH",
    "sg:tags": [
      "oil"
    ],
    "sg:website": "www.certifiedoil.com",
    "wof:name": "Certified Oil Co",
    "wof:placetype": "venue"
  },
  "geometry": {"coordinates":[-82.233372,39.744795],"type":"Point"}
}
