{
  "type": "Feature",
  "properties": {
    "iso:country":"US",
    "sg:address":"6148 W Central Ave",
    "sg:city":"Toledo",
    "sg:classifiers":[
        {
            "category":"Retail",
            "subcategory":"Auto Repair",
            "type":"Services"
        }
    ],
    "sg:phone":"+1 419 842 1682",
    "sg:postcode":"43615",
    "sg:province":"OH",
    "sg:tags":[
        "repairing",
        "automobile"
    ],
    "wof:name":"Dent Wizard",
    "wof:placetype":"venue"
},
  "geometry": {"coordinates":[-83.690043,41.67599],"type":"Point"}
}