{
  "type": "Feature",
  "properties": {
    "addr:full":"11154 Luschek Dr Cincinnati OH 45241",
    "addr:housenumber":"11154",
    "addr:postcode":"45241",
    "addr:street":"Luschek Dr",
    "iso:country":"US",
    "sg:address":"11154 Luschek Dr",
    "sg:city":"Cincinnati",
    "sg:classifiers":[
        {
            "category":"Wholesale",
            "subcategory":"Office Equipment",
            "type":"Manufacturing & Wholesale Goods"
        }
    ],
    "sg:phone":"+1 513 791 1994",
    "sg:postcode":"45241",
    "sg:province":"OH",
    "sg:tags":[
        "machine",
        "duplicating",
        "copying"
    ],
    "wof:name":"Document Solutions",
    "wof:placetype":"venue"
},
  "geometry": {"coordinates":[-84.380174,39.269602],"type":"Point"}
}