{
  "type": "Feature",
  "properties": {
    "addr:full":"4895 Edsal Dr Cleveland OH 44124",
    "addr:housenumber":"4895",
    "addr:postcode":"44124",
    "addr:street":"Edsal Dr",
    "iso:country":"US",
    "sg:address":"4895 Edsal Dr",
    "sg:city":"Cleveland",
    "sg:classifiers":[
        {
            "category":"Government",
            "subcategory":"Office",
            "type":"Public Place"
        }
    ],
    "sg:phone":"+1 216 381 7132",
    "sg:postcode":"44124",
    "sg:province":"OH",
    "sg:tags":[
        "national",
        "security"
    ],
    "wof:name":"Civil Air Patrol Inc",
    "wof:placetype":"venue"
},
  "geometry": {"coordinates":[-81.50238,41.525858],"type":"Point"}
}