{
  "type": "Feature",
  "properties": {
    "addr:full": "3766 Paxton Ave Cincinnati OH 45209",
    "addr:housenumber": "3766",
    "addr:postcode": "45209",
    "addr:street": "Paxton Ave",
    "iso:country": "US",
    "sg:address": "3766 Paxton Ave",
    "sg:city": "Cincinnati",
    "sg:classifiers": [
      {
        "category": "Personal",
        "subcategory": "Tanning Parlor",
        "type": "Services"
      },
      {
        "category": "Personal",
        "type": "Services"
      }
    ],
    "sg:phone": "+1 513 321 8444",
    "sg:postcode": "45209",
    "sg:province": "OH",
    "sg:tags": [
      "salon"
    ],
    "wof:name": "Palm Beach Tan Inc",
    "wof:placetype": "venue"
  },
  "geometry": {"coordinates":[-84.430378,39.145764],"type":"Point"}
}
