{
  "type": "Feature",
  "properties": {
    "addr:full":"4130 Linden Ave Dayton OH 45432",
    "addr:housenumber":"4130",
    "addr:postcode":"45432",
    "addr:street":"Linden Ave",
    "iso:country":"US",
    "sg:address":"4130 Linden Ave",
    "sg:city":"Dayton",
    "sg:classifiers":[
        {
            "category":"Shopping",
            "subcategory":"Computers & Home Electronics",
            "type":"Retail Goods"
        }
    ],
    "sg:phone":"+1 937 258 0173",
    "sg:postcode":"45432",
    "sg:province":"OH",
    "sg:tags":[
        "software"
    ],
    "wof:name":"Weblink Consulting LLC",
    "wof:placetype":"venue"
},
  "geometry": {"coordinates":[-84.12248599999999,39.745184],"type":"Point"}
}