{
  "type": "Feature",
  "properties": {
    "iso:country":"US",
    "sg:address":"8505 S River Rd",
    "sg:city":"Waterville",
    "sg:classifiers":[
        {
            "category":"Professional",
            "type":"Services"
        }
    ],
    "sg:phone":"+1 419 878 2592",
    "sg:postcode":"43566",
    "sg:province":"OH",
    "sg:tags":[
        "establishment"
    ],
    "wof:name":"Farnsworth Metropark",
    "wof:placetype":"venue"
},
  "geometry": {"coordinates":[-83.75333500000001,41.474014],"type":"Point"}
}