{
  "type": "Feature",
  "properties": {
    "addr:full":"149 Johnson Dr Delaware OH 43015",
    "addr:housenumber":"149",
    "addr:postcode":"43015",
    "addr:street":"Johnson Dr",
    "iso:country":"US",
    "sg:address":"149 Johnson Dr",
    "sg:city":"Delaware",
    "sg:classifiers":[
        {
            "category":"Wholesale",
            "subcategory":"Furniture",
            "type":"Manufacturing & Wholesale Goods"
        }
    ],
    "sg:phone":"+1 740 363 1765",
    "sg:postcode":"43015",
    "sg:province":"OH",
    "wof:name":"Office City Express",
    "wof:placetype":"venue"
},
  "geometry": {"coordinates":[-83.091947,40.281502],"type":"Point"}
}