{
  "type": "Feature",
  "properties": {
    "addr:full":"4040 Embassy Pkwy Akron OH 44333",
    "addr:housenumber":"4040",
    "addr:postcode":"44333",
    "addr:street":"Embassy Pkwy",
    "iso:country":"US",
    "sg:address":"4040 Embassy Pkwy",
    "sg:city":"Akron",
    "sg:classifiers":[
        {
            "category":"Wholesale",
            "subcategory":"Machinery & Supplies",
            "type":"Manufacturing & Wholesale Goods"
        }
    ],
    "sg:phone":"+1 330 668 4880",
    "sg:postcode":"44333",
    "sg:province":"OH",
    "sg:tags":[
        "industrial"
    ],
    "wof:name":"Honeywell",
    "wof:placetype":"venue"
},
  "geometry": {"coordinates":[-81.65454800000001,41.137891],"type":"Point"}
}