{
  "type": "Feature",
  "properties": {
    "iso:country":"US",
    "sg:address":"7500 Slate Ridge Blvd",
    "sg:city":"Reynoldsburg",
    "sg:classifiers":[
        {
            "category":"Professional",
            "subcategory":"Lawyer & Legal Services",
            "type":"Services"
        }
    ],
    "sg:phone":"+1 614 866 9524",
    "sg:postcode":"43068",
    "sg:province":"OH",
    "wof:name":"Griffith & Worth Attorneys",
    "wof:placetype":"venue"
},
  "geometry": {"coordinates":[-82.791038,39.944773],"type":"Point"}
}