{
  "type": "Feature",
  "properties": {
    "addr:full": "7500 Slate Ridge Blvd Reynoldsburg OH 43068",
    "addr:housenumber": "7500",
    "addr:postcode": "43068",
    "addr:street": "Slate Ridge Blvd",
    "iso:country": "US",
    "sg:address": "7500 Slate Ridge Blvd",
    "sg:city": "Reynoldsburg",
    "sg:classifiers": [
      {
        "category": "Professional",
        "subcategory": "Lawyer \u0026 Legal Services",
        "type": "Services"
      }
    ],
    "sg:phone": "+1 614 866 9524",
    "sg:postcode": "43068",
    "sg:province": "OH",
    "wof:name": "Griffith \u0026 Worth Attorneys",
    "wof:placetype": "venue"
  },
  "geometry": {"coordinates":[-82.791038,39.944773],"type":"Point"}
}
