{
  "type": "Feature",
  "properties": {
    "iso:country":"US",
    "sg:address":"6787 Rd 144",
    "sg:city":"Antwerp",
    "sg:classifiers":[
        {
            "category":"Farming",
            "subcategory":"Dairy Farm",
            "type":"Manufacturing & Wholesale Goods"
        }
    ],
    "sg:phone":"+1 419 258 1633",
    "sg:postcode":"45813",
    "sg:province":"OH",
    "wof:name":"Nine Morning Dairies LTD",
    "wof:placetype":"venue"
},
  "geometry": {"coordinates":[-84.692725,41.150408],"type":"Point"}
}