{
  "type": "Feature",
  "properties": {
    "addr:full": "6787 Rd 144 Antwerp OH 45813",
    "addr:housenumber": "6787",
    "addr:postcode": "45813",
    "addr:street": "Rd 144",
    "iso:country": "US",
    "sg:address": "6787 Rd 144",
    "sg:city": "Antwerp",
    "sg:classifiers": [
      {
        "category": "Farming",
        "subcategory": "Dairy Farm",
        "type": "Manufacturing \u0026 Wholesale Goods"
      }
    ],
    "sg:phone": "+1 419 258 1633",
    "sg:postcode": "45813",
    "sg:province": "OH",
    "wof:name": "Nine Morning Dairies LTD",
    "wof:placetype": "venue"
  },
  "geometry": {"coordinates":[-84.692725,41.150408],"type":"Point"}
}
