{
  "type": "Feature",
  "properties": {
    "addr:full": "3497 Villa-Casa Ct Brunswick OH 44212",
    "addr:housenumber": "3497",
    "addr:postcode": "44212",
    "addr:street": "Villa-Casa Ct",
    "iso:country": "US",
    "sg:address": "3497 Villa-Casa Ct",
    "sg:city": "Brunswick",
    "sg:classifiers": [
      {
        "category": "Professional",
        "subcategory": "Business Services",
        "type": "Services"
      }
    ],
    "sg:phone": "+1 330 325 9797",
    "sg:postcode": "44212",
    "sg:province": "OH",
    "sg:tags": [
      "interior",
      "consultant",
      "design",
      "decorator"
    ],
    "wof:name": "Ultimate Interiors",
    "wof:placetype": "venue"
  },
  "geometry": {"coordinates":[-81.811058,41.227704],"type":"Point"}
}
