{
  "type": "Feature",
  "properties": {
    "iso:country":"US",
    "sg:address":"217 12th St NE",
    "sg:city":"Strasburg",
    "sg:classifiers":[
        {
            "category":"Professional",
            "subcategory":"Employment Agencies",
            "type":"Services"
        }
    ],
    "sg:phone":"+1 330 878 5567",
    "sg:postcode":"44680",
    "sg:province":"OH",
    "sg:tags":[
        "help",
        "supply"
    ],
    "wof:name":"Staffing Group",
    "wof:placetype":"venue"
},
  "geometry": {"coordinates":[-81.533294,40.611416],"type":"Point"}
}