{
  "type": "Feature",
  "properties": {
    "iso:country":"US",
    "sg:address":"10237 Maple Branch Trl",
    "sg:city":"Strongsville",
    "sg:classifiers":[
        {
            "category":"Wholesale",
            "subcategory":"Machinery & Supplies",
            "type":"Manufacturing & Wholesale Goods"
        }
    ],
    "sg:phone":"+1 440 238 2112",
    "sg:postcode":"44149",
    "sg:province":"OH",
    "sg:tags":[
        "tank"
    ],
    "wof:name":"JV3 Ind Sales",
    "wof:placetype":"venue"
},
  "geometry": {"coordinates":[-81.865044,41.336491],"type":"Point"}
}