{
  "type": "Feature",
  "properties": {
    "addr:full": "10237 Maple Branch Trl Strongsville OH 44149",
    "addr:housenumber": "10237",
    "addr:postcode": "44149",
    "addr:street": "Maple Branch Trl",
    "iso:country": "US",
    "sg:address": "10237 Maple Branch Trl",
    "sg:city": "Strongsville",
    "sg:classifiers": [
      {
        "category": "Wholesale",
        "subcategory": "Machinery \u0026 Supplies",
        "type": "Manufacturing \u0026 Wholesale Goods"
      }
    ],
    "sg:phone": "+1 440 238 2112",
    "sg:postcode": "44149",
    "sg:province": "OH",
    "sg:tags": [
      "tank"
    ],
    "wof:name": "JV3 Ind Sales",
    "wof:placetype": "venue"
  },
  "geometry": {"coordinates":[-81.865044,41.336491],"type":"Point"}
}
