{
  "type": "Feature",
  "properties": {
    "iso:country":"US",
    "sg:address":"17 N River Rd NE Suite A",
    "sg:city":"Warren",
    "sg:classifiers":[
        {
            "category":"Banks & Credit Unions",
            "subcategory":"Investment Brokerage",
            "type":"Services"
        }
    ],
    "sg:phone":"+1 330 872 1771",
    "sg:postcode":"44483",
    "sg:province":"OH",
    "sg:tags":[
        "tape",
        "video",
        "sale",
        "dvds-rental"
    ],
    "wof:name":"Movie Gallery",
    "wof:placetype":"venue"
},
  "geometry": {"coordinates":[-80.81293700000001,41.265518],"type":"Point"}
}