{
  "type": "Feature",
  "properties": {
    "addr:full": "17 N River Rd NE Suite A Warren OH 44483",
    "addr:housenumber": "17",
    "addr:postcode": "44483",
    "addr:street": "N River Rd Ne Suite A",
    "iso:country": "US",
    "sg:address": "17 N River Rd NE Suite A",
    "sg:city": "Warren",
    "sg:classifiers": [
      {
        "category": "Banks \u0026 Credit Unions",
        "subcategory": "Investment Brokerage",
        "type": "Services"
      }
    ],
    "sg:phone": "+1 330 872 1771",
    "sg:postcode": "44483",
    "sg:province": "OH",
    "sg:tags": [
      "tape",
      "video",
      "sale",
      "dvds-rental"
    ],
    "wof:name": "Movie Gallery",
    "wof:placetype": "venue"
  },
  "geometry": {"coordinates":[-80.812937,41.265518],"type":"Point"}
}
