{
  "type": "Feature",
  "properties": {
    "addr:full":"9 W 130th St Hinckley OH 44233",
    "addr:housenumber":"9",
    "addr:postcode":"44233",
    "addr:street":"W 130Th St",
    "iso:country":"US",
    "sg:address":"9 W 130th St",
    "sg:city":"Hinckley",
    "sg:classifiers":[
        {
            "category":"Shopping",
            "subcategory":"Pharmacy",
            "type":"Retail Goods"
        }
    ],
    "sg:phone":"+1 330 225 8458",
    "sg:postcode":"44233",
    "sg:province":"OH",
    "wof:name":"CVS Pharmacy",
    "wof:placetype":"venue"
},
  "geometry": {"coordinates":[-81.78500099999999,41.273946],"type":"Point"}
}