{
  "type": "Feature",
  "properties": {
    "addr:full": "1934 Martinsburg Rd Utica OH 43080",
    "addr:housenumber": "1934",
    "addr:postcode": "43080",
    "addr:street": "Martinsburg Rd",
    "iso:country": "US",
    "sg:address": "1934 Martinsburg Rd",
    "sg:city": "Utica",
    "sg:classifiers": [
      {
        "category": "Manufacturing",
        "subcategory": "Glass \u0026 Minerals",
        "type": "Manufacturing \u0026 Wholesale Goods"
      }
    ],
    "sg:phone": "+1 740 668 5451",
    "sg:postcode": "43080",
    "sg:province": "OH",
    "sg:tags": [
      "stone",
      "cut",
      "product"
    ],
    "wof:name": "Quality Cement Products",
    "wof:placetype": "venue"
  },
  "geometry": {"coordinates":[-82.338432,40.256642],"type":"Point"}
}
