{
  "type": "Feature",
  "properties": {
    "iso:country":"US",
    "sg:address":"1934 Martinsburg Rd",
    "sg:city":"Utica",
    "sg:classifiers":[
        {
            "category":"Manufacturing",
            "subcategory":"Glass & Minerals",
            "type":"Manufacturing & Wholesale Goods"
        }
    ],
    "sg:phone":"+1 740 668 5451",
    "sg:postcode":"43080",
    "sg:province":"OH",
    "sg:tags":[
        "stone",
        "cut",
        "product"
    ],
    "wof:name":"Quality Cement Products",
    "wof:placetype":"venue"
},
  "geometry": {"coordinates":[-82.338432,40.256642],"type":"Point"}
}