{
  "type": "Feature",
  "properties": {
    "addr:full": "3331 Fredericksburg Rd Wooster OH 44691",
    "addr:housenumber": "3331",
    "addr:postcode": "44691",
    "addr:street": "Fredericksburg Rd",
    "iso:country": "US",
    "sg:address": "3331 Fredericksburg Rd",
    "sg:city": "Wooster",
    "sg:phone": "+1 330 264 1809",
    "sg:postcode": "44691",
    "sg:province": "OH",
    "sg:tags": [
      "farm"
    ],
    "wof:name": "Bauerle Farms",
    "wof:placetype": "venue"
  },
  "geometry": {"coordinates":[-81.895937,40.759141],"type":"Point"}
}
