{
  "type": "Feature",
  "properties": {
    "addr:full": "33382 Walker Rd Avon Lake OH 44012",
    "addr:housenumber": "33382",
    "addr:postcode": "44012",
    "addr:street": "Walker Rd",
    "iso:country": "US",
    "sg:address": "33382 Walker Rd",
    "sg:city": "Avon Lake",
    "sg:classifiers": [
      {
        "category": "Manufacturing",
        "subcategory": "Metals",
        "type": "Manufacturing \u0026 Wholesale Goods"
      }
    ],
    "sg:phone": "+1 440 933 2902",
    "sg:postcode": "44012",
    "sg:province": "OH",
    "sg:tags": [
      "engraver"
    ],
    "wof:name": "P-M Engravers",
    "wof:placetype": "venue"
  },
  "geometry": {"coordinates":[-82.046229,41.493414],"type":"Point"}
}
