{
  "type": "Feature",
  "properties": {
    "iso:country":"US",
    "sg:address":"33382 Walker Rd",
    "sg:city":"Avon Lake",
    "sg:classifiers":[
        {
            "category":"Manufacturing",
            "subcategory":"Metals",
            "type":"Manufacturing & Wholesale Goods"
        }
    ],
    "sg:phone":"+1 440 933 2902",
    "sg:postcode":"44012",
    "sg:province":"OH",
    "sg:tags":[
        "engraver"
    ],
    "wof:name":"P-M Engravers",
    "wof:placetype":"venue"
},
  "geometry": {"coordinates":[-82.046229,41.493414],"type":"Point"}
}