{
  "type": "Feature",
  "properties": {
    "addr:full": "3551 Poole Rd Cincinnati OH 45251",
    "addr:housenumber": "3551",
    "addr:postcode": "45251",
    "addr:street": "Poole Rd",
    "iso:country": "US",
    "sg:address": "3551 Poole Rd",
    "sg:city": "Cincinnati",
    "sg:classifiers": [
      {
        "category": "Organizations",
        "subcategory": "Religious Organization",
        "type": "Services"
      }
    ],
    "sg:phone": "+1 513 385 7323",
    "sg:postcode": "45251",
    "sg:province": "OH",
    "sg:tags": [
      "church"
    ],
    "wof:name": "First Baptist Church-Groesbeck",
    "wof:placetype": "venue"
  },
  "geometry": {"coordinates":[-84.598281,39.235164],"type":"Point"}
}
