{
  "type": "Feature",
  "properties": {
    "addr:full":"347 Knollwood Trl Cleveland OH 44143",
    "addr:housenumber":"347",
    "addr:postcode":"44143",
    "addr:street":"Knollwood Trl",
    "iso:country":"US",
    "sg:address":"347 Knollwood Trl",
    "sg:city":"Cleveland",
    "sg:classifiers":[
        {
            "category":"Real Estate",
            "subcategory":"Real Estate Operator",
            "type":"Services"
        }
    ],
    "sg:phone":"+1 216 731 6758",
    "sg:postcode":"44143",
    "sg:province":"OH",
    "sg:tags":[
        "building",
        "apartment"
    ],
    "wof:name":"Ram West End Place LLC",
    "wof:placetype":"venue"
},
  "geometry": {"coordinates":[-81.503247,41.566404],"type":"Point"}
}