{
  "type": "Feature",
  "properties": {
    "iso:country":"US",
    "sg:address":"3561 W 105th St",
    "sg:city":"Cleveland",
    "sg:classifiers":[
        {
            "category":"Manufacturing",
            "subcategory":"Chemicals & Compounds",
            "type":"Manufacturing & Wholesale Goods"
        },
        {
            "category":"Building & Trades",
            "subcategory":"Pest Control",
            "type":"Services"
        }
    ],
    "sg:phone":"+1 216 252 7140",
    "sg:postcode":"44111",
    "sg:province":"OH",
    "sg:tags":[
        "equipment",
        "insecticide",
        "supply"
    ],
    "sg:website":"http://www.susanproducts.com",
    "wof:name":"Susan Products",
    "wof:placetype":"venue"
},
  "geometry": {"coordinates":[-81.758886,41.455464],"type":"Point"}
}