{
  "type": "Feature",
  "properties": {
    "iso:country":"US",
    "sg:address":"2311 Sandman Dr",
    "sg:city":"Columbus",
    "sg:classifiers":[
        {
            "category":"Professional",
            "subcategory":"Business Services",
            "type":"Services"
        }
    ],
    "sg:phone":"+1 614 538 1664",
    "sg:postcode":"43235",
    "sg:province":"OH",
    "sg:tags":[
        "development"
    ],
    "wof:name":"Action International",
    "wof:placetype":"venue"
},
  "geometry": {"coordinates":[-83.079156,40.072303],"type":"Point"}
}