{
  "type": "Feature",
  "properties": {
    "addr:full": "3011 Harrisburg Rd NE Canton OH 44705",
    "addr:housenumber": "3011",
    "addr:postcode": "44705",
    "addr:street": "Harrisburg Rd Ne",
    "iso:country": "US",
    "sg:address": "3011 Harrisburg Rd NE",
    "sg:city": "Canton",
    "sg:classifiers": [
      {
        "category": "Home \u0026 Garden",
        "subcategory": "Carpets \u0026 Floor Coverings",
        "type": "Retail Goods"
      }
    ],
    "sg:phone": "+1 330 452 7190",
    "sg:postcode": "44705",
    "sg:province": "OH",
    "sg:tags": [
      "dealer",
      "rug"
    ],
    "wof:name": "Phil's Carpet Svc",
    "wof:placetype": "venue"
  },
  "geometry": {"coordinates":[-81.347958,40.830031],"type":"Point"}
}
