{
  "type": "Feature",
  "properties": {
    "iso:country":"US",
    "sg:address":"8320 W Chester Rd",
    "sg:city":"West Chester",
    "sg:classifiers":[
        {
            "category":"Professional",
            "subcategory":"Engineering",
            "type":"Services"
        }
    ],
    "sg:phone":"+1 513 777 2893",
    "sg:postcode":"45069",
    "sg:province":"OH",
    "sg:tags":[
        "engineer"
    ],
    "wof:name":"Smart Science LTD",
    "wof:placetype":"venue"
},
  "geometry": {"coordinates":[-84.353228,39.317694],"type":"Point"}
}