{
  "type": "Feature",
  "properties": {
    "addr:full": "8320 W Chester Rd West Chester OH 45069",
    "addr:housenumber": "8320",
    "addr:postcode": "45069",
    "addr:street": "W Chester Rd",
    "iso:country": "US",
    "sg:address": "8320 W Chester Rd",
    "sg:city": "West Chester",
    "sg:classifiers": [
      {
        "category": "Professional",
        "subcategory": "Engineering",
        "type": "Services"
      }
    ],
    "sg:phone": "+1 513 777 2893",
    "sg:postcode": "45069",
    "sg:province": "OH",
    "sg:tags": [
      "engineer"
    ],
    "wof:name": "Smart Science LTD",
    "wof:placetype": "venue"
  },
  "geometry": {"coordinates":[-84.353228,39.317694],"type":"Point"}
}
