{
  "type": "Feature",
  "properties": {
    "iso:country":"US",
    "sg:address":"112 Grimes St",
    "sg:city":"Dayton",
    "sg:classifiers":[
        {
            "category":"Professional",
            "subcategory":"Advertising",
            "type":"Services"
        }
    ],
    "sg:phone":"+1 937 228 9143",
    "sg:postcode":"45402",
    "sg:province":"OH",
    "sg:website":"www.lamar.com",
    "wof:name":"Lamar Outdoor Advertising",
    "wof:placetype":"venue"
},
  "geometry": {"coordinates":[-84.208092,39.758489],"type":"Point"}
}