{
  "type": "Feature",
  "properties": {
    "iso:country":"US",
    "sg:address":"19612 Battersea Blvd",
    "sg:city":"Cleveland",
    "sg:classifiers":[
        {
            "category":"Shopping",
            "subcategory":"Gifts & Souvenirs",
            "type":"Retail Goods"
        }
    ],
    "sg:phone":"+1 440 331 4406",
    "sg:postcode":"44116",
    "sg:province":"OH",
    "sg:tags":[
        "basket",
        "parcel"
    ],
    "wof:name":"Lucy T Keogh Gift Baskets",
    "wof:placetype":"venue"
},
  "geometry": {"coordinates":[-81.840926,41.484603],"type":"Point"}
}