{
  "type": "Feature",
  "properties": {
    "iso:country":"US",
    "sg:address":"18391 Ringgold Southern Rd",
    "sg:city":"Circleville",
    "sg:classifiers":[
        {
            "category":"Building & Trades",
            "subcategory":"Construction",
            "type":"Services"
        }
    ],
    "sg:phone":"+1 740 474 4160",
    "sg:postcode":"43113",
    "sg:province":"OH",
    "sg:tags":[
        "painter"
    ],
    "wof:name":"All-A-Round Painting",
    "wof:placetype":"venue"
},
  "geometry": {"coordinates":[-82.86032,39.661755],"type":"Point"}
}