{
  "type": "Feature",
  "properties": {
    "iso:country":"US",
    "sg:address":"498 Pike St",
    "sg:city":"Marietta",
    "sg:classifiers":[
        {
            "category":"Autos & Motor Vehicles",
            "subcategory":"Fuel & Gas Station",
            "type":"Retail Goods"
        }
    ],
    "sg:phone":"+1 740 374 8463",
    "sg:postcode":"45750",
    "sg:province":"OH",
    "sg:tags":[
        "station",
        "gasoline"
    ],
    "wof:name":"Hendershots Marathon",
    "wof:placetype":"venue"
},
  "geometry": {"coordinates":[-81.43091099999999,39.410806],"type":"Point"}
}