{
  "type": "Feature",
  "properties": {
    "addr:full": "498 Pike St Marietta OH 45750",
    "addr:housenumber": "498",
    "addr:postcode": "45750",
    "addr:street": "Pike St",
    "iso:country": "US",
    "sg:address": "498 Pike St",
    "sg:city": "Marietta",
    "sg:classifiers": [
      {
        "category": "Autos \u0026 Motor Vehicles",
        "subcategory": "Fuel \u0026 Gas Station",
        "type": "Retail Goods"
      }
    ],
    "sg:phone": "+1 740 374 8463",
    "sg:postcode": "45750",
    "sg:province": "OH",
    "sg:tags": [
      "station",
      "gasoline"
    ],
    "wof:name": "Hendershots Marathon",
    "wof:placetype": "venue"
  },
  "geometry": {"coordinates":[-81.430911,39.410806],"type":"Point"}
}
