{
  "type": "Feature",
  "properties": {
    "addr:full":"673 Clotts Rd Columbus OH 43230",
    "addr:housenumber":"673",
    "addr:postcode":"43230",
    "addr:street":"Clotts Rd",
    "iso:country":"US",
    "sg:address":"673 Clotts Rd",
    "sg:city":"Columbus",
    "sg:classifiers":[
        {
            "category":"Banks & Credit Unions",
            "subcategory":"Financial Services",
            "type":"Services"
        }
    ],
    "sg:phone":"+1 614 228 6959",
    "sg:postcode":"43230",
    "sg:province":"OH",
    "sg:tags":[
        "investor"
    ],
    "wof:name":"Mdm Properties LLC",
    "wof:placetype":"venue"
},
  "geometry": {"coordinates":[-82.858594,40.036024],"type":"Point"}
}