{
  "type": "Feature",
  "properties": {
    "addr:full":"828 Cedarhill Dr Cincinnati OH 45240",
    "addr:housenumber":"828",
    "addr:postcode":"45240",
    "addr:street":"Cedarhill Dr",
    "iso:country":"US",
    "sg:address":"828 Cedarhill Dr",
    "sg:city":"Cincinnati",
    "sg:classifiers":[
        {
            "category":"Shopping",
            "subcategory":"Clothing, Apparel, & Fashions",
            "type":"Retail Goods"
        }
    ],
    "sg:phone":"+1 513 225 9029",
    "sg:postcode":"45240",
    "sg:province":"OH",
    "wof:name":"G J's Fashion & Apparel",
    "wof:placetype":"venue"
},
  "geometry": {"coordinates":[-84.508014,39.302314],"type":"Point"}
}