{
  "type": "Feature",
  "properties": {
    "iso:country":"US",
    "sg:address":"800 E Cooke Rd",
    "sg:city":"Columbus",
    "sg:classifiers":[
        {
            "category":"Wholesale",
            "subcategory":"Poultry",
            "type":"Manufacturing & Wholesale Goods"
        }
    ],
    "sg:phone":"+1 614 261 8001",
    "sg:postcode":"43214",
    "sg:province":"OH",
    "wof:name":"Ohio Valley Poultry Inc",
    "wof:placetype":"venue"
},
  "geometry": {"coordinates":[-82.99832600000001,40.048346],"type":"Point"}
}