{
  "type": "Feature",
  "properties": {
    "addr:full": "800 E Cooke Rd Columbus OH 43214",
    "addr:housenumber": "800",
    "addr:postcode": "43214",
    "addr:street": "E Cooke Rd",
    "iso:country": "US",
    "sg:address": "800 E Cooke Rd",
    "sg:city": "Columbus",
    "sg:classifiers": [
      {
        "category": "Wholesale",
        "subcategory": "Poultry",
        "type": "Manufacturing \u0026 Wholesale Goods"
      }
    ],
    "sg:phone": "+1 614 261 8001",
    "sg:postcode": "43214",
    "sg:province": "OH",
    "wof:name": "Ohio Valley Poultry Inc",
    "wof:placetype": "venue"
  },
  "geometry": {"coordinates":[-82.998326,40.048346],"type":"Point"}
}
