{
  "type": "Feature",
  "properties": {
    "addr:full": "100 Seneca Ave Elyria OH 44035",
    "addr:housenumber": "100",
    "addr:postcode": "44035",
    "addr:street": "Seneca Ave",
    "iso:country": "US",
    "sg:address": "100 Seneca Ave",
    "sg:city": "Elyria",
    "sg:classifiers": [
      {
        "category": "Building \u0026 Trades",
        "subcategory": "Construction",
        "type": "Services"
      },
      {
        "category": "Real Estate",
        "subcategory": "Real Estate Operator",
        "type": "Services"
      }
    ],
    "sg:phone": "+1 440 366 1533",
    "sg:postcode": "44035",
    "sg:province": "OH",
    "sg:tags": [
      "home",
      "builder",
      "apartment"
    ],
    "wof:name": "Hunters Crossing Apartments",
    "wof:placetype": "venue"
  },
  "geometry": {"coordinates":[-82.129268,41.378507],"type":"Point"}
}
