{
  "type": "Feature",
  "properties": {
    "iso:country":"US",
    "sg:address":"5352 Secrest Rd",
    "sg:city":"Wooster",
    "sg:classifiers":[
        {
            "category":"Building & Trades",
            "subcategory":"Construction",
            "type":"Services"
        }
    ],
    "sg:phone":"+1 330 264 3738",
    "sg:postcode":"44691",
    "sg:province":"OH",
    "sg:tags":[
        "house"
    ],
    "wof:name":"Koon Orvie Contractors",
    "wof:placetype":"venue"
},
  "geometry": {"coordinates":[-81.87111400000001,40.788596],"type":"Point"}
}