{
  "type": "Feature",
  "properties": {
    "addr:full": "5352 Secrest Rd Wooster OH 44691",
    "addr:housenumber": "5352",
    "addr:postcode": "44691",
    "addr:street": "Secrest Rd",
    "iso:country": "US",
    "sg:address": "5352 Secrest Rd",
    "sg:city": "Wooster",
    "sg:classifiers": [
      {
        "category": "Building \u0026 Trades",
        "subcategory": "Construction",
        "type": "Services"
      }
    ],
    "sg:phone": "+1 330 264 3738",
    "sg:postcode": "44691",
    "sg:province": "OH",
    "sg:tags": [
      "house"
    ],
    "wof:name": "Koon Orvie Contractors",
    "wof:placetype": "venue"
  },
  "geometry": {"coordinates":[-81.871114,40.788596],"type":"Point"}
}
