{
  "type": "Feature",
  "properties": {
    "addr:full":"5083 Glencrossing Way Cincinnati OH 45238",
    "addr:housenumber":"5083",
    "addr:postcode":"45238",
    "addr:street":"Glencrossing Way",
    "iso:country":"US",
    "sg:address":"5083 Glencrossing Way",
    "sg:city":"Cincinnati",
    "sg:classifiers":[
        {
            "category":"Banks & Credit Unions",
            "subcategory":"Bank",
            "type":"Services"
        }
    ],
    "sg:phone":"+1 513 347 9868",
    "sg:postcode":"45238",
    "sg:province":"OH",
    "sg:tags":[
        "loan",
        "financing",
        "real estate"
    ],
    "wof:name":"Wells Fargo Financial Accptnce",
    "wof:placetype":"venue"
},
  "geometry": {"coordinates":[-84.612601,39.129845],"type":"Point"}
}