{
  "type": "Feature",
  "properties": {
    "iso:country":"US",
    "sg:address":"18 Darlyn Dr",
    "sg:city":"Bowling Green",
    "sg:classifiers":[
        {
            "category":"Wholesale",
            "subcategory":"Groceries",
            "type":"Manufacturing & Wholesale Goods"
        }
    ],
    "sg:phone":"+1 419 352 5873",
    "sg:postcode":"43402",
    "sg:province":"OH",
    "sg:tags":[
        "product",
        "confectionery"
    ],
    "wof:name":"Crawfords Quality Snack Foods",
    "wof:placetype":"venue"
},
  "geometry": {"coordinates":[-83.658507,41.385609],"type":"Point"}
}