{
  "type": "Feature",
  "properties": {
    "addr:full":"980 E 2nd St Franklin OH 45005",
    "addr:housenumber":"980",
    "addr:postcode":"45005",
    "addr:street":"E 2Nd St",
    "iso:country":"US",
    "sg:address":"980 E 2nd St",
    "sg:city":"Franklin",
    "sg:classifiers":[
        {
            "category":"Professional",
            "type":"Services"
        }
    ],
    "sg:phone":"+1 937 704 0645",
    "sg:postcode":"45005",
    "sg:province":"OH",
    "wof:name":"Oreioles Ticket Booth",
    "wof:placetype":"venue"
},
  "geometry": {"coordinates":[-84.285591,39.564197],"type":"Point"}
}