{
  "type": "Feature",
  "properties": {
    "addr:full":"13821 Strathmore Ave Cleveland OH 44112",
    "addr:housenumber":"13821",
    "addr:postcode":"44112",
    "addr:street":"Strathmore Ave",
    "iso:country":"US",
    "sg:address":"13821 Strathmore Ave",
    "sg:city":"Cleveland",
    "sg:classifiers":[
        {
            "category":"Social Services",
            "subcategory":"Child Care",
            "type":"Services"
        }
    ],
    "sg:phone":"+1 216 761 8128",
    "sg:postcode":"44112",
    "sg:province":"OH",
    "wof:name":"Ronni's Day Care",
    "wof:placetype":"venue"
},
  "geometry": {"coordinates":[-81.58274299999999,41.538369],"type":"Point"}
}