{
  "type": "Feature",
  "properties": {
    "addr:full":"880 Steel Dr Valley City OH 44280",
    "addr:housenumber":"880",
    "addr:postcode":"44280",
    "addr:street":"Steel Dr",
    "iso:country":"US",
    "sg:address":"880 Steel Dr",
    "sg:city":"Valley City",
    "sg:classifiers":[
        {
            "category":"Manufacturing",
            "subcategory":"Metals",
            "type":"Manufacturing & Wholesale Goods"
        }
    ],
    "sg:phone":"+1 330 558 2600",
    "sg:postcode":"44280",
    "sg:province":"OH",
    "sg:tags":[
        "steel",
        "processing"
    ],
    "sg:website":"www.shiloh.com",
    "wof:name":"Liverpool Coil Processing Div",
    "wof:placetype":"venue"
},
  "geometry": {"coordinates":[-81.88812299999999,41.251346],"type":"Point"}
}