{
  "type": "Feature",
  "properties": {
    "iso:country":"US",
    "sg:address":"8905 State Rte 121",
    "sg:city":"Bradford",
    "sg:classifiers":[
        {
            "category":"Farming",
            "subcategory":"Farm",
            "type":"Manufacturing & Wholesale Goods"
        }
    ],
    "sg:phone":"+1 937 448 2269",
    "sg:postcode":"45308",
    "sg:province":"OH",
    "sg:tags":[
        "crop",
        "general"
    ],
    "wof:name":"Bowman Enterprises",
    "wof:placetype":"venue"
},
  "geometry": {"coordinates":[-84.52374500000001,40.17583],"type":"Point"}
}