{
  "type": "Feature",
  "properties": {
    "addr:full": "403 Grant St Fairborn OH 45324",
    "addr:housenumber": "403",
    "addr:postcode": "45324",
    "addr:street": "Grant St",
    "iso:country": "US",
    "sg:address": "403 Grant St",
    "sg:city": "Fairborn",
    "sg:classifiers": [
      {
        "category": "Wholesale",
        "subcategory": "Beer",
        "type": "Manufacturing \u0026 Wholesale Goods"
      }
    ],
    "sg:phone": "+1 937 878 0596",
    "sg:postcode": "45324",
    "sg:province": "OH",
    "sg:tags": [
      "product",
      "mfg",
      "plastic"
    ],
    "wof:name": "Bob Hall \u0026 Associate",
    "wof:placetype": "venue"
  },
  "geometry": {"coordinates":[-84.011409,39.82899],"type":"Point"}
}
