{
  "type": "Feature",
  "properties": {
    "iso:country":"US",
    "sg:address":"1941 Cleveland Rd",
    "sg:city":"Wooster",
    "sg:classifiers":[
        {
            "category":"Restaurant",
            "type":"Food & Drink"
        }
    ],
    "sg:phone":"+1 330 264 8413",
    "sg:postcode":"44691",
    "sg:province":"OH",
    "wof:name":"Amish Door Xpress",
    "wof:placetype":"venue"
},
  "geometry": {"coordinates":[-81.934094,40.823216],"type":"Point"}
}