{
  "type": "Feature",
  "properties": {
    "addr:full": "1941 Cleveland Rd Wooster OH 44691",
    "addr:housenumber": "1941",
    "addr:postcode": "44691",
    "addr:street": "Cleveland Rd",
    "iso:country": "US",
    "sg:address": "1941 Cleveland Rd",
    "sg:city": "Wooster",
    "sg:classifiers": [
      {
        "category": "Restaurant",
        "type": "Food \u0026 Drink"
      }
    ],
    "sg:phone": "+1 330 264 8413",
    "sg:postcode": "44691",
    "sg:province": "OH",
    "wof:name": "Amish Door Xpress",
    "wof:placetype": "venue"
  },
  "geometry": {"coordinates":[-81.934094,40.823216],"type":"Point"}
}
