{
  "type": "Feature",
  "properties": {
    "addr:full": "5300 Riverside Dr Cleveland Cleveland OH 44135",
    "addr:housenumber": "5300",
    "addr:postcode": "44135",
    "addr:street": "Riverside Dr",
    "iso:country": "US",
    "sg:address": "5300 Riverside Dr Cleveland",
    "sg:city": "Cleveland",
    "sg:classifiers": [
      {
        "category": "Travel",
        "subcategory": "Hotels \u0026 Motels",
        "type": "Entertainment"
      },
      {
        "category": "Travel",
        "subcategory": "Resort",
        "type": "Entertainment"
      },
      {
        "category": "Sports \u0026 Exercise",
        "subcategory": "Ski Resort",
        "type": "Entertainment"
      }
    ],
    "sg:phone": "+1 888 625 5144",
    "sg:postcode": "44135",
    "sg:province": "OH",
    "sg:tags": [
      "corporate",
      "lodging"
    ],
    "sg:website": "http://clk.atdmt.com/NYC/go/249187170/direct/01/",
    "wof:name": "Sheraton Cleveland Airport",
    "wof:placetype": "venue"
  },
  "geometry": {"coordinates":[-81.85041,41.40049],"type":"Point"}
}
