{
  "type": "Feature",
  "properties": {
    "addr:full":"1845 Harsh Ave SE Massillon OH 44646",
    "addr:housenumber":"1845",
    "addr:postcode":"44646",
    "addr:street":"Harsh Ave Se",
    "iso:country":"US",
    "sg:address":"1845 Harsh Ave SE",
    "sg:city":"Massillon",
    "sg:classifiers":[
        {
            "category":"Professional",
            "subcategory":"Testing Lab",
            "type":"Services"
        }
    ],
    "sg:phone":"+1 330 833 8548",
    "sg:postcode":"44646",
    "sg:province":"OH",
    "sg:tags":[
        "laboratory"
    ],
    "sg:website":"www.stllabs.com",
    "wof:name":"Standards Testing Labs Inc",
    "wof:placetype":"venue"
},
  "geometry": {"coordinates":[-81.497332,40.791107],"type":"Point"}
}