{
  "type": "Feature",
  "properties": {
    "iso:country":"US",
    "sg:address":"3060 Scioto Darby Executive Ct",
    "sg:city":"Hilliard",
    "sg:classifiers":[
        {
            "category":"Professional",
            "subcategory":"Advertising",
            "type":"Services"
        }
    ],
    "sg:phone":"+1 614 777 8010",
    "sg:postcode":"43026",
    "sg:province":"OH",
    "sg:tags":[
        "mailing",
        "shipping"
    ],
    "wof:name":"RTM Enterprises Inc",
    "wof:placetype":"venue"
},
  "geometry": {"coordinates":[-83.115691,40.015527],"type":"Point"}
}