{
  "type": "Feature",
  "properties": {
    "addr:full": "6825 State Rte 722 Ithaca OH 45304",
    "addr:housenumber": "6825",
    "addr:postcode": "45304",
    "addr:street": "State Rte 722",
    "iso:country": "US",
    "sg:address": "6825 State Rte 722",
    "sg:city": "Ithaca",
    "sg:classifiers": [
      {
        "category": "Organizations",
        "subcategory": "Religious Organization",
        "type": "Services"
      }
    ],
    "sg:phone": "+1 937 678 8584",
    "sg:postcode": "45304",
    "sg:province": "OH",
    "sg:tags": [
      "church"
    ],
    "wof:name": "St Matthew's Lutheran Church",
    "wof:placetype": "venue"
  },
  "geometry": {"coordinates":[-84.55183,39.936243],"type":"Point"}
}
