{
  "type": "Feature",
  "properties": {
    "addr:full":"626 N Countyline St Fostoria OH 44830",
    "addr:housenumber":"626",
    "addr:postcode":"44830",
    "addr:street":"N Countyline St",
    "iso:country":"US",
    "sg:address":"626 N Countyline St",
    "sg:city":"Fostoria",
    "sg:classifiers":[
        {
            "category":"Restaurant",
            "type":"Food & Drink"
        }
    ],
    "sg:menulink":"http://www.allmenus.com/oh/washington/195389-mcdonalds/menu/",
    "sg:postcode":"44830",
    "sg:province":"OH",
    "sg:tags":[
        "burger",
        "american"
    ],
    "wof:name":"McDonald's",
    "wof:placetype":"venue"
},
  "geometry": {"coordinates":[-83.421133,41.164366],"type":"Point"}
}