{
  "type": "Feature",
  "properties": {
    "addr:full": "5182 Brookstone St NW Canton OH 44720",
    "addr:housenumber": "5182",
    "addr:postcode": "44720",
    "addr:street": "Brookstone St Nw",
    "iso:country": "US",
    "sg:address": "5182 Brookstone St NW",
    "sg:city": "Canton",
    "sg:classifiers": [
      {
        "category": "Shopping",
        "subcategory": "Clothing, Apparel, \u0026 Fashions",
        "type": "Retail Goods"
      }
    ],
    "sg:phone": "+1 330 305 0274",
    "sg:postcode": "44720",
    "sg:province": "OH",
    "wof:name": "Katys Closet",
    "wof:placetype": "venue"
  },
  "geometry": {"coordinates":[-81.444527,40.876293],"type":"Point"}
}
