{
  "type": "Feature",
  "properties": {
    "iso:country":"US",
    "sg:address":"438 Carnahan Ave",
    "sg:city":"Findlay",
    "sg:classifiers":[
        {
            "category":"Social Services",
            "subcategory":"Adult Care",
            "type":"Services"
        }
    ],
    "sg:phone":"+1 419 427 1954",
    "sg:postcode":"45840",
    "sg:province":"OH",
    "sg:tags":[
        "residential"
    ],
    "wof:name":"Beacon Foster Care",
    "wof:placetype":"venue"
},
  "geometry": {"coordinates":[-83.634416,41.04682],"type":"Point"}
}