{
  "type": "Feature",
  "properties": {
    "addr:full": "596 Yale Dr Mansfield OH 44907",
    "addr:housenumber": "596",
    "addr:postcode": "44907",
    "addr:street": "Yale Dr",
    "iso:country": "US",
    "sg:address": "596 Yale Dr",
    "sg:city": "Mansfield",
    "sg:classifiers": [
      {
        "category": "Professional",
        "type": "Services"
      }
    ],
    "sg:phone": "+1 419 756 8699",
    "sg:postcode": "44907",
    "sg:province": "OH",
    "wof:name": "Jonelles Junk",
    "wof:placetype": "venue"
  },
  "geometry": {"coordinates":[-82.539098,40.733737],"type":"Point"}
}
