{
  "type": "Feature",
  "properties": {
    "addr:full":"7829 Huntington Cir Boardman OH 44512",
    "addr:housenumber":"7829",
    "addr:postcode":"44512",
    "addr:street":"Huntington Cir",
    "iso:country":"US",
    "sg:address":"7829 Huntington Cir",
    "sg:city":"Boardman",
    "sg:classifiers":[
        {
            "category":"Insurance",
            "subcategory":"Insurance Agent",
            "type":"Services"
        }
    ],
    "sg:phone":"+1 330 758 8915",
    "sg:postcode":"44512",
    "sg:province":"OH",
    "wof:name":"Mutual Of Omaha Insurance Co",
    "wof:placetype":"venue"
},
  "geometry": {"coordinates":[-80.70590199999999,41.011947],"type":"Point"}
}