{
  "type": "Feature",
  "properties": {
    "addr:full":"35401 Euclid Ave Willoughby OH 44094",
    "addr:housenumber":"35401",
    "addr:postcode":"44094",
    "addr:street":"Euclid Ave",
    "iso:country":"US",
    "sg:address":"35401 Euclid Ave",
    "sg:city":"Willoughby",
    "sg:classifiers":[
        {
            "category":"Insurance",
            "subcategory":"Insurance Agent",
            "type":"Services"
        }
    ],
    "sg:phone":"+1 440 953 1441",
    "sg:postcode":"44094",
    "sg:province":"OH",
    "wof:name":"Bryan Noda Agency",
    "wof:placetype":"venue"
},
  "geometry": {"coordinates":[-81.43252099999999,41.626544],"type":"Point"}
}