{
  "type": "Feature",
  "properties": {
    "addr:full":"300 Melmore St Tiffin OH 44883",
    "addr:housenumber":"300",
    "addr:postcode":"44883",
    "addr:street":"Melmore St",
    "iso:country":"US",
    "sg:address":"300 Melmore St",
    "sg:city":"Tiffin",
    "sg:classifiers":[
        {
            "category":"Social Services",
            "type":"Services"
        }
    ],
    "sg:phone":"+1 419 447 8111",
    "sg:postcode":"44883",
    "sg:province":"OH",
    "sg:tags":[
        "professional",
        "counselor"
    ],
    "wof:name":"Christian Counseling Ctr",
    "wof:placetype":"venue"
},
  "geometry": {"coordinates":[-83.16888899999999,41.102662],"type":"Point"}
}