{
  "type": "Feature",
  "properties": {
    "addr:full": "5929 Mayfield Rd Cleveland OH 44124",
    "addr:housenumber": "5929",
    "addr:postcode": "44124",
    "addr:street": "Mayfield Rd",
    "iso:country": "US",
    "sg:address": "5929 Mayfield Rd",
    "sg:city": "Cleveland",
    "sg:classifiers": [
      {
        "category": "Manufacturing",
        "subcategory": "Leather Goods",
        "type": "Manufacturing \u0026 Wholesale Goods"
      }
    ],
    "sg:phone": "+1 440 442 1443",
    "sg:postcode": "44124",
    "sg:province": "OH",
    "sg:tags": [
      "footwear",
      "mfg"
    ],
    "wof:name": "MSA Shoe and Orthepedics",
    "wof:placetype": "venue"
  },
  "geometry": {"coordinates":[-81.464008,41.520136],"type":"Point"}
}
