{
  "type": "Feature",
  "properties": {
    "addr:full":"29825 Bolingbrook Rd Cleveland OH 44124",
    "addr:postcode":"29825;44124",
    "addr:street":"Bolingbrook Rd",
    "iso:country":"US",
    "sg:address":"29825 Bolingbrook Rd",
    "sg:city":"Cleveland",
    "sg:classifiers":[
        {
            "category":"Utilities",
            "subcategory":"Mobile Phone",
            "type":"Services"
        }
    ],
    "sg:phone":"+1 216 831 2577",
    "sg:postcode":"44124",
    "sg:province":"OH",
    "sg:tags":[
        "communication",
        "radiotelephone"
    ],
    "wof:name":"Pagerone Inc",
    "wof:placetype":"venue"
},
  "geometry": {"coordinates":[-81.46578599999999,41.471127],"type":"Point"}
}