{
  "type": "Feature",
  "properties": {
    "iso:country":"US",
    "sg:address":"821 S Main St",
    "sg:city":"Canton",
    "sg:classifiers":[
        {
            "category":"Real Estate",
            "subcategory":"Real Estate Agent",
            "type":"Services"
        }
    ],
    "sg:phone":"+1 330 499 8153",
    "sg:postcode":"44720",
    "sg:province":"OH",
    "sg:tags":[
        "commercial",
        "subdivider"
    ],
    "wof:name":"Prudential",
    "wof:placetype":"venue"
},
  "geometry": {"coordinates":[-81.400037,40.870798],"type":"Point"}
}