{
  "type": "Feature",
  "properties": {
    "addr:full": "2310 Kennedy Dr Salem OH 44460",
    "addr:housenumber": "2310",
    "addr:postcode": "44460",
    "addr:street": "Kennedy Dr",
    "iso:country": "US",
    "sg:address": "2310 Kennedy Dr",
    "sg:city": "Salem",
    "sg:classifiers": [
      {
        "category": "Organizations",
        "subcategory": "Religious Organization",
        "type": "Services"
      }
    ],
    "sg:phone": "+1 330 337 6585",
    "sg:postcode": "44460",
    "sg:province": "OH",
    "sg:tags": [
      "church"
    ],
    "wof:name": "Church Of The Nazarene",
    "wof:placetype": "venue"
  },
  "geometry": {"coordinates":[-80.828614,40.895482],"type":"Point"}
}
