{
  "type": "Feature",
  "properties": {
    "addr:full":"275 Wilson Rd Wadsworth OH 44281",
    "addr:housenumber":"275",
    "addr:postcode":"44281",
    "addr:street":"Wilson Rd",
    "iso:country":"US",
    "sg:address":"275 Wilson Rd",
    "sg:city":"Wadsworth",
    "sg:classifiers":[
        {
            "category":"Building & Trades",
            "subcategory":"Electrical",
            "type":"Services"
        }
    ],
    "sg:phone":"+1 330 334 1222",
    "sg:postcode":"44281",
    "sg:province":"OH",
    "sg:tags":[
        "electrical",
        "contractor"
    ],
    "wof:name":"Smiseck Electric",
    "wof:placetype":"venue"
},
  "geometry": {"coordinates":[-81.700029,41.029047],"type":"Point"}
}