{
  "type": "Feature",
  "properties": {
    "addr:full":"2536 Cleveland Ave SW Canton OH 44707",
    "addr:housenumber":"2536",
    "addr:postcode":"44707",
    "addr:street":"Cleveland Ave Sw",
    "iso:country":"US",
    "sg:address":"2536 Cleveland Ave SW",
    "sg:city":"Canton",
    "sg:classifiers":[
        {
            "category":"Autos & Motor Vehicles",
            "subcategory":"Fuel & Gas Station",
            "type":"Retail Goods"
        }
    ],
    "sg:phone":"+1 330 484 5060",
    "sg:postcode":"44707",
    "sg:province":"OH",
    "sg:tags":[
        "truck",
        "station",
        "rental"
    ],
    "wof:name":"Amoco",
    "wof:placetype":"venue"
},
  "geometry": {"coordinates":[-81.384024,40.768676],"type":"Point"}
}