{
  "type": "Feature",
  "properties": {
    "addr:full": "5797 Calico Ln Canfield OH 44406",
    "addr:housenumber": "5797",
    "addr:postcode": "44406",
    "addr:street": "Calico Ln",
    "iso:country": "US",
    "sg:address": "5797 Calico Ln",
    "sg:city": "Canfield",
    "sg:classifiers": [
      {
        "category": "Shopping",
        "type": "Retail Goods"
      }
    ],
    "sg:phone": "+1 330 533 9229",
    "sg:postcode": "44406",
    "sg:province": "OH",
    "sg:tags": [
      "repair",
      "tea",
      "register",
      "cash",
      "also",
      "spice"
    ],
    "wof:name": "Ohio Spice \u0026 Tea",
    "wof:placetype": "venue"
  },
  "geometry": {"coordinates":[-80.799093,41.031561],"type":"Point"}
}
