{
  "type": "Feature",
  "properties": {
    "iso:country":"US",
    "sg:address":"5797 Calico Ln",
    "sg:city":"Canfield",
    "sg:classifiers":[
        {
            "category":"Shopping",
            "type":"Retail Goods"
        }
    ],
    "sg:phone":"+1 330 533 9229",
    "sg:postcode":"44406",
    "sg:province":"OH",
    "sg:tags":[
        "repair",
        "tea",
        "register",
        "cash",
        "also",
        "spice"
    ],
    "wof:name":"Ohio Spice & Tea",
    "wof:placetype":"venue"
},
  "geometry": {"coordinates":[-80.799093,41.031561],"type":"Point"}
}