{
  "type": "Feature",
  "properties": {
    "addr:full": "110 Arco Dr Toledo OH 43607",
    "addr:housenumber": "110",
    "addr:postcode": "43607",
    "addr:street": "Arco Dr",
    "iso:country": "US",
    "sg:address": "110 Arco Dr",
    "sg:city": "Toledo",
    "sg:classifiers": [
      {
        "category": "Professional",
        "subcategory": "Engineering",
        "type": "Services"
      }
    ],
    "sg:phone": "+1 419 535 1015",
    "sg:postcode": "43607",
    "sg:province": "OH",
    "sg:tags": [
      "engineer"
    ],
    "sg:website": "www.dgl-ltd.com",
    "wof:name": "Dansard Grohnke \u0026 Long Ltd LLC",
    "wof:placetype": "venue"
  },
  "geometry": {"coordinates":[-83.622275,41.636138],"type":"Point"}
}
