{
  "type": "Feature",
  "properties": {
    "addr:full": "2091 Elmore Rd Pemberville OH 43450",
    "addr:housenumber": "2091",
    "addr:postcode": "43450",
    "addr:street": "Elmore Rd",
    "iso:country": "US",
    "sg:address": "2091 Elmore Rd",
    "sg:city": "Pemberville",
    "sg:phone": "+1 419 287 4977",
    "sg:postcode": "43450",
    "sg:province": "OH",
    "sg:tags": [
      "farm",
      "corn"
    ],
    "wof:name": "Eric Schuerman",
    "wof:placetype": "venue"
  },
  "geometry": {"coordinates":[-83.436906,41.412525],"type":"Point"}
}
