{
  "type": "Feature",
  "properties": {
    "iso:country":"US",
    "sg:address":"2091 Elmore Rd",
    "sg:city":"Pemberville",
    "sg:phone":"+1 419 287 4977",
    "sg:postcode":"43450",
    "sg:province":"OH",
    "sg:tags":[
        "farm",
        "corn"
    ],
    "wof:name":"Eric Schuerman",
    "wof:placetype":"venue"
},
  "geometry": {"coordinates":[-83.43690599999999,41.412525],"type":"Point"}
}