{
  "type": "Feature",
  "properties": {
    "addr:full":"2802 Henninger Rd Cleveland OH 44109",
    "addr:housenumber":"2802",
    "addr:postcode":"44109",
    "addr:street":"Henninger Rd",
    "iso:country":"US",
    "sg:address":"2802 Henninger Rd",
    "sg:city":"Cleveland",
    "sg:classifiers":[
        {
            "category":"Retail",
            "subcategory":"Auto Repair",
            "type":"Services"
        }
    ],
    "sg:phone":"+1 216 351 0070",
    "sg:postcode":"44109",
    "sg:province":"OH",
    "sg:tags":[
        "body",
        "automobile",
        "painting"
    ],
    "wof:name":"Gold Coast Auto Body",
    "wof:placetype":"venue"
},
  "geometry": {"coordinates":[-81.703132,41.442565],"type":"Point"}
}