{
  "type": "Feature",
  "properties": {
    "addr:full": "1406 Co Rd 250 Edgerton OH 43517",
    "addr:housenumber": "1406;250",
    "addr:postcode": "43517",
    "addr:street": "Co Rd",
    "iso:country": "US",
    "sg:address": "1406 Co Rd 250",
    "sg:city": "Edgerton",
    "sg:classifiers": [
      {
        "category": "Building \u0026 Trades",
        "subcategory": "Construction",
        "type": "Services"
      }
    ],
    "sg:phone": "+1 419 298 3452",
    "sg:postcode": "43517",
    "sg:province": "OH",
    "sg:tags": [
      "concrete",
      "contractor"
    ],
    "wof:name": "Dynacrete",
    "wof:placetype": "venue"
  },
  "geometry": {"coordinates":[-84.797372,41.425954],"type":"Point"}
}
