{
  "type": "Feature",
  "properties": {
    "iso:country":"US",
    "sg:address":"145 S Fulton St",
    "sg:city":"Wauseon",
    "sg:classifiers":[
        {
            "category":"Manufacturing",
            "subcategory":"Printing",
            "type":"Manufacturing & Wholesale Goods"
        }
    ],
    "sg:phone":"+1 419 337 7780",
    "sg:postcode":"43567",
    "sg:province":"OH",
    "sg:tags":[
        "newspaper"
    ],
    "sg:website":"www.toledoblade.com",
    "wof:name":"Toledo Blade Co",
    "wof:placetype":"venue"
},
  "geometry": {"coordinates":[-84.140872,41.547117],"type":"Point"}
}