{
  "type": "Feature",
  "properties": {
    "addr:full":"5433 Lockwood Rd Madison OH 44057",
    "addr:housenumber":"5433",
    "addr:postcode":"44057",
    "addr:street":"Lockwood Rd",
    "iso:country":"US",
    "sg:address":"5433 Lockwood Rd",
    "sg:city":"Madison",
    "sg:classifiers":[
        {
            "category":"Building & Trades",
            "subcategory":"Construction",
            "type":"Services"
        }
    ],
    "sg:phone":"+1 440 428 3666",
    "sg:postcode":"44057",
    "sg:province":"OH",
    "sg:tags":[
        "excavating",
        "contractor"
    ],
    "wof:name":"Beach Bros Excavating",
    "wof:placetype":"venue"
},
  "geometry": {"coordinates":[-81.102514,41.811006],"type":"Point"}
}