{
  "type": "Feature",
  "properties": {
    "addr:full": "1837 Woodman Center Dr Kettering OH 45420",
    "addr:housenumber": "1837",
    "addr:postcode": "45420",
    "addr:street": "Woodman Center Dr",
    "iso:country": "US",
    "sg:address": "1837 Woodman Center Dr",
    "sg:city": "Kettering",
    "sg:classifiers": [
      {
        "category": "Education",
        "subcategory": "Vocational School",
        "type": "Public Place"
      }
    ],
    "sg:phone": "+1 937 299 9450",
    "sg:postcode": "45420",
    "sg:province": "OH",
    "sg:tags": [
      "secretarial"
    ],
    "wof:name": "National College Of Business",
    "wof:placetype": "venue"
  },
  "geometry": {"coordinates":[-84.128629,39.700341],"type":"Point"}
}
