{
  "type": "Feature",
  "properties": {
    "addr:full":"424 E Stroop Rd Dayton OH 45429",
    "addr:housenumber":"424",
    "addr:postcode":"45429",
    "addr:street":"E Stroop Rd",
    "iso:country":"US",
    "sg:address":"424 E Stroop Rd",
    "sg:city":"Dayton",
    "sg:classifiers":[
        {
            "category":"Restaurant",
            "type":"Food & Drink"
        }
    ],
    "sg:menulink":"http://www.allmenus.com/oh/kettering/19315-figlio/menu/",
    "sg:phone":"+1 937 534 0494",
    "sg:postcode":"45429",
    "sg:province":"OH",
    "sg:tags":[
        "italian"
    ],
    "wof:name":"Figlio",
    "wof:placetype":"venue"
},
  "geometry": {"coordinates":[-84.164131,39.689404],"type":"Point"}
}