{
  "type": "Feature",
  "properties": {
    "addr:full": "8105 Blackrun Rd Nashport OH 43830",
    "addr:housenumber": "8105",
    "addr:postcode": "43830",
    "addr:street": "Blackrun Rd",
    "iso:country": "US",
    "sg:address": "8105 Blackrun Rd",
    "sg:city": "Nashport",
    "sg:classifiers": [
      {
        "category": "Mining \u0026 Drilling",
        "type": "Manufacturing \u0026 Wholesale Goods"
      }
    ],
    "sg:phone": "+1 740 828 3453",
    "sg:postcode": "43830",
    "sg:province": "OH",
    "sg:tags": [
      "crude",
      "production",
      "gas"
    ],
    "wof:name": "King Petroleum",
    "wof:placetype": "venue"
  },
  "geometry": {"coordinates":[-82.158936,40.076336],"type":"Point"}
}
