{
  "type": "Feature",
  "properties": {
    "iso:country":"US",
    "sg:address":"8105 Blackrun Rd",
    "sg:city":"Nashport",
    "sg:classifiers":[
        {
            "category":"Mining & Drilling",
            "type":"Manufacturing & Wholesale Goods"
        }
    ],
    "sg:phone":"+1 740 828 3453",
    "sg:postcode":"43830",
    "sg:province":"OH",
    "sg:tags":[
        "crude",
        "production",
        "gas"
    ],
    "wof:name":"King Petroleum",
    "wof:placetype":"venue"
},
  "geometry": {"coordinates":[-82.158936,40.076336],"type":"Point"}
}