{
  "type": "Feature",
  "properties": {
    "addr:full":"4550 Belden Village St NW Canton OH 44718",
    "addr:housenumber":"4550",
    "addr:postcode":"44718",
    "addr:street":"Belden Village St Nw",
    "iso:country":"US",
    "sg:address":"4550 Belden Village St NW",
    "sg:city":"Canton",
    "sg:classifiers":[
        {
            "category":"Home & Garden",
            "subcategory":"Home Furnishings",
            "type":"Retail Goods"
        }
    ],
    "sg:phone":"+1 330 492 8808",
    "sg:postcode":"44718",
    "sg:province":"OH",
    "sg:tags":[
        "lighting",
        "fixture"
    ],
    "sg:website":"www.blc.com",
    "wof:name":"Belden Village Lighting Center",
    "wof:placetype":"venue"
},
  "geometry": {"coordinates":[-81.435395,40.856412],"type":"Point"}
}