{
  "type": "Feature",
  "properties": {
    "addr:full": "1073 Richter Rd Columbus OH 43223",
    "addr:housenumber": "1073",
    "addr:postcode": "43223",
    "addr:street": "Richter Rd",
    "iso:country": "US",
    "sg:address": "1073 Richter Rd",
    "sg:city": "Columbus",
    "sg:classifiers": [
      {
        "category": "Shopping",
        "subcategory": "Bicycles \u0026 Sporting Goods",
        "type": "Retail Goods"
      }
    ],
    "sg:phone": "+1 614 272 8294",
    "sg:postcode": "43223",
    "sg:province": "OH",
    "wof:name": "Gun Room",
    "wof:placetype": "venue"
  },
  "geometry": {"coordinates":[-83.035727,39.925345],"type":"Point"}
}
