{
  "type": "Feature",
  "properties": {
    "addr:full":"1105 Hebron Rd Heath OH 43056",
    "addr:housenumber":"1105",
    "addr:postcode":"43056",
    "addr:street":"Hebron Rd",
    "iso:country":"US",
    "sg:address":"1105 Hebron Rd",
    "sg:city":"Heath",
    "sg:classifiers":[
        {
            "category":"Wholesale",
            "subcategory":"Machinery & Supplies",
            "type":"Manufacturing & Wholesale Goods"
        }
    ],
    "sg:phone":"+1 740 522 8548",
    "sg:postcode":"43056",
    "sg:province":"OH",
    "sg:tags":[
        "janitor",
        "establishment",
        "equipment"
    ],
    "wof:name":"Columbus Janitor Supply Co",
    "wof:placetype":"venue"
},
  "geometry": {"coordinates":[-82.449089,40.020991],"type":"Point"}
}