{
  "type": "Feature",
  "properties": {
    "addr:full": "802 Hanson Dr Cincinnati OH 45240",
    "addr:housenumber": "802",
    "addr:postcode": "45240",
    "addr:street": "Hanson Dr",
    "iso:country": "US",
    "sg:address": "802 Hanson Dr",
    "sg:city": "Cincinnati",
    "sg:classifiers": [
      {
        "category": "Building \u0026 Trades",
        "subcategory": "Cleaning \u0026 Sanitation",
        "type": "Services"
      }
    ],
    "sg:phone": "+1 513 851 7896",
    "sg:postcode": "45240",
    "sg:province": "OH",
    "sg:tags": [
      "janitor"
    ],
    "wof:name": "Gabriel Maintenance Svc",
    "wof:placetype": "venue"
  },
  "geometry": {"coordinates":[-84.508387,39.293956],"type":"Point"}
}
