{
  "type": "Feature",
  "properties": {
    "iso:country":"US",
    "sg:address":"323 E 200th St",
    "sg:city":"Cleveland",
    "sg:classifiers":[
        {
            "category":"Personal",
            "subcategory":"Beauty Salon",
            "type":"Services"
        }
    ],
    "sg:phone":"+1 216 481 5066",
    "sg:postcode":"44119",
    "sg:province":"OH",
    "wof:name":"Esteem Beauty Salon Inc",
    "wof:placetype":"venue"
},
  "geometry": {"coordinates":[-81.54019,41.597307],"type":"Point"}
}