{
  "type": "Feature",
  "properties": {
    "iso:country":"US",
    "sg:address":"13 Renick Ave",
    "sg:city":"Chillicothe",
    "sg:classifiers":[
        {
            "category":"Wholesale",
            "subcategory":"Electrical",
            "type":"Manufacturing & Wholesale Goods"
        }
    ],
    "sg:phone":"+1 740 774 1107",
    "sg:postcode":"45601",
    "sg:province":"OH",
    "sg:tags":[
        "equipment",
        "electric",
        "supply"
    ],
    "wof:name":"State Electric Supply Inc",
    "wof:placetype":"venue"
},
  "geometry": {"coordinates":[-82.95122,39.340396],"type":"Point"}
}