{
  "type": "Feature",
  "properties": {
    "iso:country":"US",
    "sg:address":"6620 W Central Ave",
    "sg:city":"Toledo",
    "sg:classifiers":[
        {
            "category":"Health Services",
            "subcategory":"Health Practitioner",
            "type":"Services"
        }
    ],
    "sg:phone":"+1 419 882 5678",
    "sg:postcode":"43617",
    "sg:province":"OH",
    "sg:tags":[
        "psychologist"
    ],
    "wof:name":"Central Behavioral Healthcare",
    "wof:placetype":"venue"
},
  "geometry": {"coordinates":[-83.701029,41.675451],"type":"Point"}
}