{
  "type": "Feature",
  "properties": {
    "addr:full": "30179 Detroit Rd Cleveland OH 44145",
    "addr:postcode": "30179;44145",
    "addr:street": "Detroit Rd",
    "iso:country": "US",
    "sg:address": "30179 Detroit Rd",
    "sg:city": "Cleveland",
    "sg:classifiers": [
      {
        "category": "Shopping",
        "subcategory": "Clothing, Apparel, \u0026 Fashions",
        "type": "Retail Goods"
      }
    ],
    "sg:phone": "+1 440 899 0050",
    "sg:postcode": "44145",
    "sg:province": "OH",
    "sg:website": "www.carasboutique.com",
    "wof:name": "Cara's Boutique",
    "wof:placetype": "venue"
  },
  "geometry": {"coordinates":[-81.952131,41.463633],"type":"Point"}
}
