{
  "type": "Feature",
  "properties": {
    "iso:country":"US",
    "sg:address":"962 Kenmore Blvd",
    "sg:city":"Akron",
    "sg:classifiers":[
        {
            "category":"Professional",
            "type":"Services"
        }
    ],
    "sg:phone":"+1 330 861 0325",
    "sg:postcode":"44314",
    "sg:province":"OH",
    "wof:name":"J R Baker",
    "wof:placetype":"venue"
},
  "geometry": {"coordinates":[-81.55738,41.04369],"type":"Point"}
}