{
  "type": "Feature",
  "properties": {
    "addr:full": "3255 Daleford Rd Cleveland OH 44120",
    "addr:housenumber": "3255",
    "addr:postcode": "44120",
    "addr:street": "Daleford Rd",
    "iso:country": "US",
    "sg:address": "3255 Daleford Rd",
    "sg:city": "Cleveland",
    "sg:classifiers": [
      {
        "category": "Shopping",
        "subcategory": "Stationery \u0026 Office Supplies",
        "type": "Retail Goods"
      }
    ],
    "sg:phone": "+1 216 531 4300",
    "sg:postcode": "44120",
    "sg:province": "OH",
    "sg:tags": [
      "accessory"
    ],
    "wof:name": "Writing Room The",
    "wof:placetype": "venue"
  },
  "geometry": {"coordinates":[-81.560748,41.468013],"type":"Point"}
}
