{
  "type": "Feature",
  "properties": {
    "iso:country":"US",
    "sg:address":"723 S Byrne Rd",
    "sg:city":"Toledo",
    "sg:classifiers":[
        {
            "category":"Food & Beverages",
            "subcategory":"Groceries & Convenience Stores",
            "type":"Retail Goods"
        }
    ],
    "sg:phone":"+1 419 382 5735",
    "sg:postcode":"43609",
    "sg:province":"OH",
    "wof:name":"Julian's Mart",
    "wof:placetype":"venue"
},
  "geometry": {"coordinates":[-83.6258,41.624591],"type":"Point"}
}