{
  "type": "Feature",
  "properties": {
    "addr:full":"1095 Pennsylvania Ave Columbus OH 43201",
    "addr:housenumber":"1095",
    "addr:postcode":"43201",
    "addr:street":"Pennsylvania Ave",
    "iso:country":"US",
    "sg:address":"1095 Pennsylvania Ave",
    "sg:city":"Columbus",
    "sg:classifiers":[
        {
            "category":"Real Estate",
            "subcategory":"Real Estate Agent",
            "type":"Services"
        }
    ],
    "sg:phone":"+1 614 294 5815",
    "sg:postcode":"43201",
    "sg:province":"OH",
    "wof:name":"Allen Miller & Zeno",
    "wof:placetype":"venue"
},
  "geometry": {"coordinates":[-83.01564,39.982502],"type":"Point"}
}