{
  "type": "Feature",
  "properties": {
    "addr:full": "1155 Old State Rte 74 Batavia OH 45103",
    "addr:housenumber": "1155",
    "addr:postcode": "45103",
    "addr:street": "Old State Rte 74",
    "iso:country": "US",
    "sg:address": "1155 Old State Rte 74",
    "sg:city": "Batavia",
    "sg:classifiers": [
      {
        "category": "Food \u0026 Beverages",
        "subcategory": "Liquor \u0026 Beverages",
        "type": "Retail Goods"
      }
    ],
    "sg:phone": "+1 513 752 1350",
    "sg:postcode": "45103",
    "sg:province": "OH",
    "sg:tags": [
      "beer",
      "ale"
    ],
    "wof:name": "Clermont Distributing Co",
    "wof:placetype": "venue"
  },
  "geometry": {"coordinates":[-84.248122,39.094036],"type":"Point"}
}
