{
  "type": "Feature",
  "properties": {
    "addr:full":"1443 Old Hickory Dr Columbus OH 43223",
    "addr:housenumber":"1443",
    "addr:postcode":"43223",
    "addr:street":"Old Hickory Dr",
    "iso:country":"US",
    "sg:address":"1443 Old Hickory Dr",
    "sg:city":"Columbus",
    "sg:classifiers":[
        {
            "category":"Retail",
            "subcategory":"Auto Repair",
            "type":"Services"
        }
    ],
    "sg:phone":"+1 614 312 3118",
    "sg:postcode":"43223",
    "sg:province":"OH",
    "sg:tags":[
        "wrecker"
    ],
    "wof:name":"Kennedy's Towing",
    "wof:placetype":"venue"
},
  "geometry": {"coordinates":[-83.03495599999999,39.929921],"type":"Point"}
}