{
  "type": "Feature",
  "properties": {
    "addr:full":"469 Bailey Rd Beaver OH 45613",
    "addr:housenumber":"469",
    "addr:postcode":"45613",
    "addr:street":"Bailey Rd",
    "iso:country":"US",
    "sg:address":"469 Bailey Rd",
    "sg:city":"Beaver",
    "sg:classifiers":[
        {
            "category":"Manufacturing",
            "subcategory":"Printing",
            "type":"Manufacturing & Wholesale Goods"
        }
    ],
    "sg:phone":"+1 740 820 8845",
    "sg:postcode":"45613",
    "sg:province":"OH",
    "sg:tags":[
        "commercial"
    ],
    "wof:name":"DArtco",
    "wof:placetype":"venue"
},
  "geometry": {"coordinates":[-82.840656,38.999605],"type":"Point"}
}