{
  "type": "Feature",
  "properties": {
    "addr:full": "19080 Bagley Rd Cleveland OH 44130",
    "addr:housenumber": "19080",
    "addr:postcode": "44130",
    "addr:street": "Bagley Rd",
    "iso:country": "US",
    "sg:address": "19080 Bagley Rd",
    "sg:city": "Cleveland",
    "sg:classifiers": [
      {
        "category": "Social Services",
        "subcategory": "Job Training",
        "type": "Services"
      }
    ],
    "sg:phone": "+1 440 891 8444",
    "sg:postcode": "44130",
    "sg:province": "OH",
    "sg:tags": [
      "retardation",
      "disabled",
      "mental",
      "dev"
    ],
    "wof:name": "Northeast Care Ctr Inc",
    "wof:placetype": "venue"
  },
  "geometry": {"coordinates":[-81.836229,41.372258],"type":"Point"}
}
