{
  "type": "Feature",
  "properties": {
    "iso:country":"US",
    "sg:address":"6142 Dunham Rd",
    "sg:city":"Cleveland",
    "sg:classifiers":[
        {
            "category":"Professional",
            "subcategory":"Accounting & Tax Preparation",
            "type":"Services"
        }
    ],
    "sg:phone":"+1 216 581 0346",
    "sg:postcode":"44137",
    "sg:province":"OH",
    "sg:tags":[
        "return",
        "filing"
    ],
    "wof:name":"H & R Block Tax Svc",
    "wof:placetype":"venue"
},
  "geometry": {"coordinates":[-81.575152,41.392111],"type":"Point"}
}