{
  "type": "Feature",
  "properties": {
    "iso:country":"US",
    "sg:address":"23830 State Rte 56",
    "sg:city":"South Bloomingville",
    "sg:classifiers":[
        {
            "category":"Building & Trades",
            "subcategory":"Construction",
            "type":"Services"
        }
    ],
    "sg:phone":"+1 740 332 3506",
    "sg:postcode":"43152",
    "sg:province":"OH",
    "sg:tags":[
        "contractor"
    ],
    "wof:name":"Daves Fencing",
    "wof:placetype":"venue"
},
  "geometry": {"coordinates":[-82.592289,39.414262],"type":"Point"}
}