{
  "type": "Feature",
  "properties": {
    "addr:full": "1601 S State St Girard OH 44420",
    "addr:housenumber": "1601",
    "addr:postcode": "44420",
    "addr:street": "S State St",
    "iso:country": "US",
    "sg:address": "1601 S State St",
    "sg:city": "Girard",
    "sg:classifiers": [
      {
        "category": "Restaurant",
        "type": "Food \u0026 Drink"
      },
      {
        "category": "Food \u0026 Beverages",
        "subcategory": "Liquor \u0026 Beverages",
        "type": "Retail Goods"
      },
      {
        "category": "Wholesale",
        "subcategory": "Wine \u0026 Distilled Alcoholic Beverages",
        "type": "Manufacturing \u0026 Wholesale Goods"
      }
    ],
    "sg:phone": "+1 330 545 0825",
    "sg:postcode": "44420",
    "sg:province": "OH",
    "sg:tags": [
      "beer",
      "ale",
      "broker",
      "store"
    ],
    "wof:name": "Jr's Drive Thru",
    "wof:placetype": "venue"
  },
  "geometry": {"coordinates":[-80.687668,41.13689],"type":"Point"}
}
