{
  "type": "Feature",
  "properties": {
    "addr:full":"1601 S State St Girard OH 44420",
    "addr:housenumber":"1601",
    "addr:postcode":"44420",
    "addr:street":"S State St",
    "iso:country":"US",
    "sg:address":"1601 S State St",
    "sg:city":"Girard",
    "sg:classifiers":[
        {
            "category":"Restaurant",
            "type":"Food & Drink"
        },
        {
            "category":"Food & Beverages",
            "subcategory":"Liquor & Beverages",
            "type":"Retail Goods"
        },
        {
            "category":"Wholesale",
            "subcategory":"Wine & Distilled Alcoholic Beverages",
            "type":"Manufacturing & Wholesale Goods"
        }
    ],
    "sg:phone":"+1 330 545 0825",
    "sg:postcode":"44420",
    "sg:province":"OH",
    "sg:tags":[
        "beer",
        "ale",
        "broker",
        "store"
    ],
    "wof:name":"Jr's Drive Thru",
    "wof:placetype":"venue"
},
  "geometry": {"coordinates":[-80.687668,41.13689],"type":"Point"}
}