{
  "type": "Feature",
  "properties": {
    "addr:full": "950 Oakland Park Ave Columbus OH 43224",
    "addr:housenumber": "950",
    "addr:postcode": "43224",
    "addr:street": "Oakland Park Ave",
    "iso:country": "US",
    "sg:address": "950 Oakland Park Ave",
    "sg:city": "Columbus",
    "sg:classifiers": [
      {
        "category": "Manufacturing",
        "subcategory": "Printing",
        "type": "Manufacturing \u0026 Wholesale Goods"
      }
    ],
    "sg:phone": "+1 614 263 4433",
    "sg:postcode": "43224",
    "sg:province": "OH",
    "sg:tags": [
      "screen"
    ],
    "wof:name": "Concept Wear",
    "wof:placetype": "venue"
  },
  "geometry": {"coordinates":[-82.988723,40.032573],"type":"Point"}
}
