{
  "type": "Feature",
  "properties": {
    "addr:full": "4110 Tuller Rd Dublin OH 43017",
    "addr:housenumber": "4110",
    "addr:postcode": "43017",
    "addr:street": "Tuller Rd",
    "iso:country": "US",
    "sg:address": "4110 Tuller Rd",
    "sg:city": "Dublin",
    "sg:classifiers": [
      {
        "category": "Real Estate",
        "subcategory": "Real Estate Operator",
        "type": "Services"
      }
    ],
    "sg:phone": "+1 614 798 5200",
    "sg:postcode": "43017",
    "sg:province": "OH",
    "sg:tags": [
      "apartment"
    ],
    "wof:name": "Bridge Street Accommodations",
    "wof:placetype": "venue"
  },
  "geometry": {"coordinates":[-83.09267,40.107428],"type":"Point"}
}
