{
  "type": "Feature",
  "properties": {
    "iso:country":"US",
    "sg:address":"5401 Brookpark Rd",
    "sg:city":"Cleveland",
    "sg:classifiers":[
        {
            "category":"Retail",
            "subcategory":"Car Wash",
            "type":"Services"
        }
    ],
    "sg:phone":"+1 216 661 4666",
    "sg:postcode":"44129",
    "sg:province":"OH",
    "sg:tags":[
        "automobile",
        "detail",
        "clean"
    ],
    "wof:name":"Ramzi Auto Appearance Spec",
    "wof:placetype":"venue"
},
  "geometry": {"coordinates":[-81.726621,41.418723],"type":"Point"}
}