{
  "type": "Feature",
  "properties": {
    "addr:full": "5605 Naomi Dr Milford OH 45150",
    "addr:housenumber": "5605",
    "addr:postcode": "45150",
    "addr:street": "Naomi Dr",
    "iso:country": "US",
    "sg:address": "5605 Naomi Dr",
    "sg:city": "Milford",
    "sg:classifiers": [
      {
        "category": "Building \u0026 Trades",
        "subcategory": "Plumbing",
        "type": "Services"
      }
    ],
    "sg:phone": "+1 513 248 1255",
    "sg:postcode": "45150",
    "sg:province": "OH",
    "sg:tags": [
      "contractor"
    ],
    "wof:name": "Mike Butler Plumbing",
    "wof:placetype": "venue"
  },
  "geometry": {"coordinates":[-84.230027,39.175633],"type":"Point"}
}
