{
  "type": "Feature",
  "properties": {
    "iso:country":"US",
    "sg:address":"5605 Naomi Dr",
    "sg:city":"Milford",
    "sg:classifiers":[
        {
            "category":"Building & Trades",
            "subcategory":"Plumbing",
            "type":"Services"
        }
    ],
    "sg:phone":"+1 513 248 1255",
    "sg:postcode":"45150",
    "sg:province":"OH",
    "sg:tags":[
        "contractor"
    ],
    "wof:name":"Mike Butler Plumbing",
    "wof:placetype":"venue"
},
  "geometry": {"coordinates":[-84.23002700000001,39.175633],"type":"Point"}
}