{
  "type": "Feature",
  "properties": {
    "iso:country":"US",
    "sg:address":"132 N Main St",
    "sg:city":"Minster",
    "sg:classifiers":[
        {
            "category":"Professional",
            "subcategory":"Advertising",
            "type":"Services"
        }
    ],
    "sg:phone":"+1 419 628 3344",
    "sg:postcode":"45865",
    "sg:province":"OH",
    "sg:tags":[
        "counselor"
    ],
    "wof:name":"Ranly Ad & Tech Art Studios",
    "wof:placetype":"venue"
},
  "geometry": {"coordinates":[-84.376672,40.396146],"type":"Point"}
}