{
  "type": "Feature",
  "properties": {
    "addr:full": "132 N Main St Minster OH 45865",
    "addr:housenumber": "132",
    "addr:postcode": "45865",
    "addr:street": "N Main St",
    "iso:country": "US",
    "sg:address": "132 N Main St",
    "sg:city": "Minster",
    "sg:classifiers": [
      {
        "category": "Professional",
        "subcategory": "Advertising",
        "type": "Services"
      }
    ],
    "sg:phone": "+1 419 628 3344",
    "sg:postcode": "45865",
    "sg:province": "OH",
    "sg:tags": [
      "counselor"
    ],
    "wof:name": "Ranly Ad \u0026 Tech Art Studios",
    "wof:placetype": "venue"
  },
  "geometry": {"coordinates":[-84.376672,40.396146],"type":"Point"}
}
