{
  "type": "Feature",
  "properties": {
    "addr:full": "403 Ohio Ave Mc Donald OH 44437",
    "addr:housenumber": "403",
    "addr:postcode": "44437",
    "addr:street": "Ohio Ave Mc",
    "iso:country": "US",
    "sg:address": "403 Ohio Ave",
    "sg:city": "Mc Donald",
    "sg:classifiers": [
      {
        "category": "Shopping",
        "subcategory": "Discount \u0026 Variety Stores",
        "type": "Retail Goods"
      }
    ],
    "sg:phone": "+1 330 530 2635",
    "sg:postcode": "44437",
    "sg:province": "OH",
    "wof:name": "Dollar General",
    "wof:placetype": "venue"
  },
  "geometry": {"coordinates":[-80.724277,41.165099],"type":"Point"}
}
