{
  "type": "Feature",
  "properties": {
    "iso:country":"US",
    "sg:address":"4741 E 355th St",
    "sg:city":"Willoughby",
    "sg:classifiers":[
        {
            "category":"Manufacturing",
            "subcategory":"Metals",
            "type":"Manufacturing & Wholesale Goods"
        }
    ],
    "sg:phone":"+1 440 946 5101",
    "sg:postcode":"44094",
    "sg:province":"OH",
    "sg:tags":[
        "treating",
        "heat"
    ],
    "wof:name":"BOS Svc",
    "wof:placetype":"venue"
},
  "geometry": {"coordinates":[-81.434893,41.630777],"type":"Point"}
}