{
  "type": "Feature",
  "properties": {
    "addr:full": "4741 E 355th St Willoughby OH 44094",
    "addr:housenumber": "4741",
    "addr:postcode": "44094",
    "addr:street": "E 355Th St",
    "iso:country": "US",
    "sg:address": "4741 E 355th St",
    "sg:city": "Willoughby",
    "sg:classifiers": [
      {
        "category": "Manufacturing",
        "subcategory": "Metals",
        "type": "Manufacturing \u0026 Wholesale Goods"
      }
    ],
    "sg:phone": "+1 440 946 5101",
    "sg:postcode": "44094",
    "sg:province": "OH",
    "sg:tags": [
      "treating",
      "heat"
    ],
    "wof:name": "BOS Svc",
    "wof:placetype": "venue"
  },
  "geometry": {"coordinates":[-81.434893,41.630777],"type":"Point"}
}
