{
  "type": "Feature",
  "properties": {
    "iso:country":"US",
    "sg:address":"1361 Worthington Center Dr",
    "sg:city":"Worthington",
    "sg:classifiers":[
        {
            "category":"Retail",
            "subcategory":"Laundry & Dry Cleaning",
            "type":"Services"
        }
    ],
    "sg:phone":"+1 614 848 3900",
    "sg:postcode":"43085",
    "sg:province":"OH",
    "sg:tags":[
        "cleaners"
    ],
    "wof:name":"Swan Cleaners",
    "wof:placetype":"venue"
},
  "geometry": {"coordinates":[-82.980981,40.123504],"type":"Point"}
}