{
  "type": "Feature",
  "properties": {
    "addr:full":"105 Marc Dr Cuyahoga Falls OH 44223",
    "addr:housenumber":"105",
    "addr:postcode":"44223",
    "addr:street":"Marc Dr",
    "iso:country":"US",
    "sg:address":"105 Marc Dr",
    "sg:city":"Cuyahoga Falls",
    "sg:classifiers":[
        {
            "category":"Manufacturing",
            "subcategory":"Tools & Machinery",
            "type":"Manufacturing & Wholesale Goods"
        }
    ],
    "sg:phone":"+1 330 920 8160",
    "sg:postcode":"44223",
    "sg:province":"OH",
    "sg:tags":[
        "mold",
        "special"
    ],
    "sg:website":"www.pdq-marlin.com",
    "wof:name":"Marlin Tool Inc",
    "wof:placetype":"venue"
},
  "geometry": {"coordinates":[-81.503908,41.170915],"type":"Point"}
}