{
  "type": "Feature",
  "properties": {
    "iso:country":"US",
    "sg:address":"10730 Main St",
    "sg:city":"Mantua",
    "sg:classifiers":[
        {
            "category":"Health Services",
            "subcategory":"Optometrist",
            "type":"Services"
        }
    ],
    "sg:phone":"+1 330 274 0502",
    "sg:postcode":"44231",
    "sg:province":"OH",
    "wof:name":"Mantua Eye Ctr",
    "wof:placetype":"venue"
},
  "geometry": {"coordinates":[-81.098687,41.285369],"type":"Point"}
}