{
  "type": "Feature",
  "properties": {
    "addr:full":"1246 Brittain Rd Akron OH 44310",
    "addr:housenumber":"1246",
    "addr:postcode":"44310",
    "addr:street":"Brittain Rd",
    "iso:country":"US",
    "sg:address":"1246 Brittain Rd",
    "sg:city":"Akron",
    "sg:classifiers":[
        {
            "category":"Retail",
            "subcategory":"Auto Repair",
            "type":"Services"
        }
    ],
    "sg:phone":"+1 330 633 1201",
    "sg:postcode":"44310",
    "sg:province":"OH",
    "sg:tags":[
        "repairing",
        "automobile"
    ],
    "wof:name":"G & L Auto & Truck Svc",
    "wof:placetype":"venue"
},
  "geometry": {"coordinates":[-81.466593,41.095558],"type":"Point"}
}