{
  "type": "Feature",
  "properties": {
    "addr:full": "6920 Hall St Holland OH 43528",
    "addr:housenumber": "6920",
    "addr:postcode": "43528",
    "addr:street": "Hall St",
    "iso:country": "US",
    "sg:address": "6920 Hall St",
    "sg:city": "Holland",
    "sg:classifiers": [
      {
        "category": "Manufacturing",
        "subcategory": "Chemicals \u0026 Compounds",
        "type": "Manufacturing \u0026 Wholesale Goods"
      }
    ],
    "sg:phone": "+1 419 865 7788",
    "sg:postcode": "43528",
    "sg:province": "OH",
    "sg:tags": [
      "prep",
      "perfume"
    ],
    "wof:name": "Steiner Co",
    "wof:placetype": "venue"
  },
  "geometry": {"coordinates":[-83.704,41.617125],"type":"Point"}
}
