{
  "type": "Feature",
  "properties": {
    "iso:country":"US",
    "sg:address":"6920 Hall St",
    "sg:city":"Holland",
    "sg:classifiers":[
        {
            "category":"Manufacturing",
            "subcategory":"Chemicals & Compounds",
            "type":"Manufacturing & Wholesale Goods"
        }
    ],
    "sg:phone":"+1 419 865 7788",
    "sg:postcode":"43528",
    "sg:province":"OH",
    "sg:tags":[
        "prep",
        "perfume"
    ],
    "wof:name":"Steiner Co",
    "wof:placetype":"venue"
},
  "geometry": {"coordinates":[-83.70399999999999,41.617125],"type":"Point"}
}