{
  "type": "Feature",
  "properties": {
    "addr:full":"2666 Sharf Rd Delphos OH 45887",
    "addr:housenumber":"2666",
    "addr:postcode":"45887",
    "addr:street":"Sharf Rd",
    "iso:country":"US",
    "sg:address":"2666 Sharf Rd",
    "sg:city":"Delphos",
    "sg:classifiers":[
        {
            "category":"Building & Trades",
            "subcategory":"Construction",
            "type":"Services"
        }
    ],
    "sg:phone":"+1 419 695 6358",
    "sg:postcode":"45887",
    "sg:province":"OH",
    "sg:tags":[
        "house"
    ],
    "wof:name":"Tom Wurst Contracting",
    "wof:placetype":"venue"
},
  "geometry": {"coordinates":[-84.379148,40.77413],"type":"Point"}
}