{
  "type": "Feature",
  "properties": {
    "iso:country":"US",
    "sg:address":"4562 E Bayshore Rd",
    "sg:city":"Port Clinton",
    "sg:phone":"+1 419 734 4272",
    "sg:postcode":"43452",
    "sg:province":"OH",
    "sg:tags":[
        "farm",
        "fruit",
        "tree",
        "soybean",
        "orchard"
    ],
    "wof:name":"Bergman Orchards",
    "wof:placetype":"venue"
},
  "geometry": {"coordinates":[-82.838435,41.504802],"type":"Point"}
}