{
  "type": "Feature",
  "properties": {
    "addr:full": "4562 E Bayshore Rd Port Clinton OH 43452",
    "addr:housenumber": "4562",
    "addr:postcode": "43452",
    "addr:street": "E Bayshore Rd",
    "iso:country": "US",
    "sg:address": "4562 E Bayshore Rd",
    "sg:city": "Port Clinton",
    "sg:phone": "+1 419 734 4272",
    "sg:postcode": "43452",
    "sg:province": "OH",
    "sg:tags": [
      "farm",
      "fruit",
      "tree",
      "soybean",
      "orchard"
    ],
    "wof:name": "Bergman Orchards",
    "wof:placetype": "venue"
  },
  "geometry": {"coordinates":[-82.838435,41.504802],"type":"Point"}
}
