{
  "type": "Feature",
  "properties": {
    "addr:full": "220 3rd St NW Barberton OH 44203",
    "addr:housenumber": "220",
    "addr:postcode": "44203",
    "addr:street": "3Rd St Nw",
    "iso:country": "US",
    "sg:address": "220 3rd St NW",
    "sg:city": "Barberton",
    "sg:classifiers": [
      {
        "category": "Health Services",
        "subcategory": "Nursing And Care Facility",
        "type": "Services"
      }
    ],
    "sg:phone": "+1 330 848 5028",
    "sg:postcode": "44203",
    "sg:province": "OH",
    "sg:tags": [
      "intermediate"
    ],
    "wof:name": "Pleasant Pinte Assisted Living",
    "wof:placetype": "venue"
  },
  "geometry": {"coordinates":[-81.608576,41.017118],"type":"Point"}
}
