{
  "type": "Feature",
  "properties": {
    "addr:full":"9900 Princeton Glendale Rd Cincinnati OH 45246",
    "addr:housenumber":"9900",
    "addr:postcode":"45246",
    "addr:street":"Princeton Glendale Rd",
    "iso:country":"US",
    "sg:address":"9900 Princeton Glendale Rd",
    "sg:city":"Cincinnati",
    "sg:classifiers":[
        {
            "category":"Real Estate",
            "subcategory":"Real Estate Agent",
            "type":"Services"
        }
    ],
    "sg:phone":"+1 513 870 0770",
    "sg:postcode":"45246",
    "sg:province":"OH",
    "wof:name":"Murray Realty & Assoc",
    "wof:placetype":"venue"
},
  "geometry": {"coordinates":[-84.46466700000001,39.312174],"type":"Point"}
}