{
  "type": "Feature",
  "properties": {
    "addr:full": "1494 W Mount Pleasant Rd Wilmington OH 45177",
    "addr:housenumber": "1494",
    "addr:postcode": "45177",
    "addr:street": "W Mount Pleasant Rd",
    "iso:country": "US",
    "sg:address": "1494 W Mount Pleasant Rd",
    "sg:city": "Wilmington",
    "sg:classifiers": [
      {
        "category": "Farming",
        "subcategory": "Farm",
        "type": "Manufacturing \u0026 Wholesale Goods"
      }
    ],
    "sg:phone": "+1 937 382 4447",
    "sg:postcode": "45177",
    "sg:province": "OH",
    "sg:tags": [
      "crop",
      "general"
    ],
    "wof:name": "Lester Jenks",
    "wof:placetype": "venue"
  },
  "geometry": {"coordinates":[-83.848803,39.534296],"type":"Point"}
}
