{
  "type": "Feature",
  "properties": {
    "iso:country":"US",
    "sg:address":"4220 Dillon Hills Dr",
    "sg:city":"Nashport",
    "sg:classifiers":[
        {
            "category":"Insurance",
            "subcategory":"Insurance Agent",
            "type":"Services"
        }
    ],
    "sg:phone":"+1 740 450 8318",
    "sg:postcode":"43830",
    "sg:province":"OH",
    "sg:tags":[
        "consultant"
    ],
    "wof:name":"Paulson & Assoc",
    "wof:placetype":"venue"
},
  "geometry": {"coordinates":[-82.096584,40.010698],"type":"Point"}
}