{
  "type": "Feature",
  "properties": {
    "iso:country":"US",
    "sg:address":"923 N Main St",
    "sg:city":"Lima",
    "sg:classifiers":[
        {
            "category":"Utilities",
            "type":"Services"
        }
    ],
    "sg:phone":"+1 419 222 7382",
    "sg:postcode":"45801",
    "sg:province":"OH",
    "sg:tags":[
        "sanitary"
    ],
    "wof:name":"American Eagle Environmental S",
    "wof:placetype":"venue"
},
  "geometry": {"coordinates":[-84.105022,40.754238],"type":"Point"}
}