{
  "type": "Feature",
  "properties": {
    "addr:full":"3841 N Santom Rd Stow OH 44224",
    "addr:housenumber":"3841",
    "addr:postcode":"44224",
    "addr:street":"N Santom Rd",
    "iso:country":"US",
    "sg:address":"3841 N Santom Rd",
    "sg:city":"Stow",
    "sg:classifiers":[
        {
            "category":"Shopping",
            "subcategory":"Computers & Home Electronics",
            "type":"Retail Goods"
        }
    ],
    "sg:phone":"+1 330 686 0404",
    "sg:postcode":"44224",
    "sg:province":"OH",
    "sg:tags":[
        "satellite",
        "antenna"
    ],
    "wof:name":"Ripple Enterprises Inc",
    "wof:placetype":"venue"
},
  "geometry": {"coordinates":[-81.425988,41.165543],"type":"Point"}
}