{
  "type": "Feature",
  "properties": {
    "iso:country":"US",
    "sg:address":"10 E Locust St",
    "sg:city":"Newark",
    "sg:classifiers":[
        {
            "category":"Building & Trades",
            "subcategory":"Construction",
            "type":"Services"
        }
    ],
    "sg:phone":"+1 740 345 4111",
    "sg:postcode":"43055",
    "sg:province":"OH",
    "sg:tags":[
        "house"
    ],
    "wof:name":"Nelson Homes Inc",
    "wof:placetype":"venue"
},
  "geometry": {"coordinates":[-82.40357299999999,40.060541],"type":"Point"}
}