{
  "type": "Feature",
  "properties": {
    "addr:full": "10 E Locust St Newark OH 43055",
    "addr:housenumber": "10",
    "addr:postcode": "43055",
    "addr:street": "E Locust St",
    "iso:country": "US",
    "sg:address": "10 E Locust St",
    "sg:city": "Newark",
    "sg:classifiers": [
      {
        "category": "Building \u0026 Trades",
        "subcategory": "Construction",
        "type": "Services"
      }
    ],
    "sg:phone": "+1 740 345 4111",
    "sg:postcode": "43055",
    "sg:province": "OH",
    "sg:tags": [
      "house"
    ],
    "wof:name": "Nelson Homes Inc",
    "wof:placetype": "venue"
  },
  "geometry": {"coordinates":[-82.403573,40.060541],"type":"Point"}
}
