{
  "type": "Feature",
  "properties": {
    "iso:country":"US",
    "sg:address":"410 Golfview Dr",
    "sg:city":"Chillicothe",
    "sg:classifiers":[
        {
            "category":"Building & Trades",
            "subcategory":"Construction",
            "type":"Services"
        }
    ],
    "sg:phone":"+1 740 703 1721",
    "sg:postcode":"45601",
    "sg:province":"OH",
    "sg:tags":[
        "roofing",
        "contractor"
    ],
    "wof:name":"Martin Roofing",
    "wof:placetype":"venue"
},
  "geometry": {"coordinates":[-83.064198,39.363566],"type":"Point"}
}