{
  "type": "Feature",
  "properties": {
    "iso:country":"US",
    "sg:address":"24055 Chagrin Blvd",
    "sg:city":"Cleveland",
    "sg:classifiers":[
        {
            "category":"Restaurant",
            "type":"Food & Drink"
        }
    ],
    "sg:phone":"+1 216 292 4446",
    "sg:postcode":"44122",
    "sg:province":"OH",
    "sg:tags":[
        "chinese"
    ],
    "wof:name":"Szechwan House Inc",
    "wof:placetype":"venue"
},
  "geometry": {"coordinates":[-81.49940599999999,41.464515],"type":"Point"}
}