{
  "type": "Feature",
  "properties": {
    "addr:full":"507 Cranston Dr Berea OH 44017",
    "addr:housenumber":"507",
    "addr:postcode":"44017",
    "addr:street":"Cranston Dr",
    "iso:country":"US",
    "sg:address":"507 Cranston Dr",
    "sg:city":"Berea",
    "sg:classifiers":[
        {
            "category":"Real Estate",
            "subcategory":"Real Estate Operator",
            "type":"Services"
        }
    ],
    "sg:phone":"+1 440 234 2319",
    "sg:postcode":"44017",
    "sg:province":"OH",
    "sg:tags":[
        "building",
        "ope",
        "apartment",
        "nonresidential"
    ],
    "wof:name":"Hatco Properties Co",
    "wof:placetype":"venue"
},
  "geometry": {"coordinates":[-81.877546,41.358829],"type":"Point"}
}