{
  "type": "Feature",
  "properties": {
    "iso:country":"US",
    "sg:address":"15995 Mishey Rd",
    "sg:city":"Fredericktown",
    "sg:classifiers":[
        {
            "category":"Building & Trades",
            "subcategory":"Construction",
            "type":"Services"
        }
    ],
    "sg:phone":"+1 740 694 6536",
    "sg:postcode":"43019",
    "sg:province":"OH",
    "sg:tags":[
        "excavation",
        "contractor"
    ],
    "wof:name":"Roger Syler Excavating",
    "wof:placetype":"venue"
},
  "geometry": {"coordinates":[-82.462362,40.539744],"type":"Point"}
}