{
  "type": "Feature",
  "properties": {
    "addr:full": "24801 Brookpark Rd North Olmsted OH 44070",
    "addr:housenumber": "24801",
    "addr:postcode": "44070",
    "addr:street": "Brookpark Rd",
    "iso:country": "US",
    "sg:address": "24801 Brookpark Rd",
    "sg:city": "North Olmsted",
    "sg:classifiers": [
      {
        "category": "Restaurant",
        "type": "Food \u0026 Drink"
      }
    ],
    "sg:menulink": "http://www.allmenus.com/oh/north-olmsted/195105-mcdonalds/menu/",
    "sg:postcode": "44070",
    "sg:province": "OH",
    "sg:tags": [
      "burger",
      "american"
    ],
    "wof:name": "McDonald's",
    "wof:placetype": "venue"
  },
  "geometry": {"coordinates":[-81.897601,41.41754],"type":"Point"}
}
