{
  "type": "Feature",
  "properties": {
    "iso:country":"US",
    "sg:address":"24801 Brookpark Rd",
    "sg:city":"North Olmsted",
    "sg:classifiers":[
        {
            "category":"Restaurant",
            "type":"Food & Drink"
        }
    ],
    "sg:menulink":"http://www.allmenus.com/oh/north-olmsted/195105-mcdonalds/menu/",
    "sg:postcode":"44070",
    "sg:province":"OH",
    "sg:tags":[
        "burger",
        "american"
    ],
    "wof:name":"McDonald's",
    "wof:placetype":"venue"
},
  "geometry": {"coordinates":[-81.89760099999999,41.41754],"type":"Point"}
}