{
  "type": "Feature",
  "properties": {
    "iso:country":"US",
    "sg:address":"766 Scioto St",
    "sg:city":"Urbana",
    "sg:classifiers":[
        {
            "category":"Restaurant",
            "type":"Food & Drink"
        }
    ],
    "sg:menulink":"http://www.allmenus.com/oh/urbana/78444-dominos-pizza/menu/",
    "sg:phone":"+1 937 652 2155",
    "sg:postcode":"43078",
    "sg:province":"OH",
    "sg:tags":[
        "american",
        "wing",
        "pizza"
    ],
    "wof:name":"Domino's Pizza",
    "wof:placetype":"venue"
},
  "geometry": {"coordinates":[-83.73504,40.107032],"type":"Point"}
}