{
  "type": "Feature",
  "properties": {
    "addr:full": "10400 Reading Rd Cincinnati OH 45241",
    "addr:housenumber": "10400",
    "addr:postcode": "45241",
    "addr:street": "Reading Rd",
    "iso:country": "US",
    "sg:address": "10400 Reading Rd",
    "sg:city": "Cincinnati",
    "sg:classifiers": [
      {
        "category": "Shopping",
        "subcategory": "Crafts \u0026 Fabrics",
        "type": "Retail Goods"
      }
    ],
    "sg:phone": "+1 513 733 8501",
    "sg:postcode": "45241",
    "sg:province": "OH",
    "sg:tags": [
      "sewing"
    ],
    "wof:name": "Jo-Ann Fabrics \u0026 Crafts",
    "wof:placetype": "venue"
  },
  "geometry": {"coordinates":[-84.423569,39.252475],"type":"Point"}
}
