{
  "type": "Feature",
  "properties": {
    "iso:country":"US",
    "sg:address":"10400 Reading Rd",
    "sg:city":"Cincinnati",
    "sg:classifiers":[
        {
            "category":"Shopping",
            "subcategory":"Crafts & Fabrics",
            "type":"Retail Goods"
        }
    ],
    "sg:phone":"+1 513 733 8501",
    "sg:postcode":"45241",
    "sg:province":"OH",
    "sg:tags":[
        "sewing"
    ],
    "wof:name":"Jo-Ann Fabrics & Crafts",
    "wof:placetype":"venue"
},
  "geometry": {"coordinates":[-84.423569,39.252475],"type":"Point"}
}