{
  "type": "Feature",
  "properties": {
    "addr:full": "40769 Paine Rd Beallsville OH 43716",
    "addr:housenumber": "40769",
    "addr:postcode": "43716",
    "addr:street": "Paine Rd",
    "iso:country": "US",
    "sg:address": "40769 Paine Rd",
    "sg:city": "Beallsville",
    "sg:classifiers": [
      {
        "category": "Farming",
        "subcategory": "Livestock Farm",
        "type": "Manufacturing \u0026 Wholesale Goods"
      }
    ],
    "sg:phone": "+1 740 926 1613",
    "sg:postcode": "43716",
    "sg:province": "OH",
    "sg:tags": [
      "beef",
      "feedlot",
      "cattle"
    ],
    "wof:name": "Carl Kinzy",
    "wof:placetype": "venue"
  },
  "geometry": {"coordinates":[-81.081637,39.837017],"type":"Point"}
}
