{
  "type": "Feature",
  "properties": {
    "iso:country":"US",
    "sg:address":"4747 Spring Grove Ave",
    "sg:city":"Cincinnati",
    "sg:classifiers":[
        {
            "category":"Government",
            "subcategory":"Office",
            "type":"Public Place"
        }
    ],
    "sg:phone":"+1 513 591 7700",
    "sg:postcode":"45232",
    "sg:province":"OH",
    "sg:tags":[
        "water",
        "supply"
    ],
    "wof:name":"Water Works Dept",
    "wof:placetype":"venue"
},
  "geometry": {"coordinates":[-84.513717,39.16646],"type":"Point"}
}