{
  "type": "Feature",
  "properties": {
    "iso:country":"US",
    "sg:address":"4796 Cross Roads Rd NE",
    "sg:city":"Magnolia",
    "sg:classifiers":[
        {
            "category":"Food & Beverages",
            "subcategory":"Groceries & Convenience Stores",
            "type":"Retail Goods"
        }
    ],
    "sg:phone":"+1 330 866 9329",
    "sg:postcode":"44671",
    "sg:province":"OH",
    "sg:tags":[
        "grocer"
    ],
    "wof:name":"Gene's Crossroad Market",
    "wof:placetype":"venue"
},
  "geometry": {"coordinates":[-81.360865,40.639649],"type":"Point"}
}