{
  "type": "Feature",
  "properties": {
    "addr:full": "4796 Cross Roads Rd NE Magnolia OH 44671",
    "addr:housenumber": "4796",
    "addr:postcode": "44671",
    "addr:street": "Cross Roads Rd Ne",
    "iso:country": "US",
    "sg:address": "4796 Cross Roads Rd NE",
    "sg:city": "Magnolia",
    "sg:classifiers": [
      {
        "category": "Food \u0026 Beverages",
        "subcategory": "Groceries \u0026 Convenience Stores",
        "type": "Retail Goods"
      }
    ],
    "sg:phone": "+1 330 866 9329",
    "sg:postcode": "44671",
    "sg:province": "OH",
    "sg:tags": [
      "grocer"
    ],
    "wof:name": "Gene's Crossroad Market",
    "wof:placetype": "venue"
  },
  "geometry": {"coordinates":[-81.360865,40.639649],"type":"Point"}
}
