{
  "type": "Feature",
  "properties": {
    "iso:country":"US",
    "sg:address":"106 S Main St",
    "sg:city":"London",
    "sg:classifiers":[
        {
            "category":"Shopping",
            "type":"Retail Goods"
        }
    ],
    "sg:phone":"+1 740 852 7168",
    "sg:postcode":"43140",
    "sg:province":"OH",
    "sg:tags":[
        "merchandise"
    ],
    "wof:name":"Door Store",
    "wof:placetype":"venue"
},
  "geometry": {"coordinates":[-83.446729,39.884824],"type":"Point"}
}