{
  "type": "Feature",
  "properties": {
    "addr:full": "75 E Cherry St Sunbury OH 43074",
    "addr:housenumber": "75",
    "addr:postcode": "43074",
    "addr:street": "E Cherry St",
    "iso:country": "US",
    "sg:address": "75 E Cherry St",
    "sg:city": "Sunbury",
    "sg:classifiers": [
      {
        "category": "Shopping",
        "subcategory": "Bicycles \u0026 Sporting Goods",
        "type": "Retail Goods"
      }
    ],
    "sg:phone": "+1 740 965 5202",
    "sg:postcode": "43074",
    "sg:province": "OH",
    "sg:tags": [
      "gun",
      "gunsmith"
    ],
    "wof:name": "Grumpy's Guns \u0026 Gear",
    "wof:placetype": "venue"
  },
  "geometry": {"coordinates":[-82.859919,40.242933],"type":"Point"}
}
