{
  "type": "Feature",
  "properties": {
    "iso:country":"US",
    "sg:address":"75 E Cherry St",
    "sg:city":"Sunbury",
    "sg:classifiers":[
        {
            "category":"Shopping",
            "subcategory":"Bicycles & Sporting Goods",
            "type":"Retail Goods"
        }
    ],
    "sg:phone":"+1 740 965 5202",
    "sg:postcode":"43074",
    "sg:province":"OH",
    "sg:tags":[
        "gun",
        "gunsmith"
    ],
    "wof:name":"Grumpy's Guns & Gear",
    "wof:placetype":"venue"
},
  "geometry": {"coordinates":[-82.859919,40.242933],"type":"Point"}
}