{
  "type": "Feature",
  "properties": {
    "addr:full": "2155 Strathshire Hall Ln Powell OH 43065",
    "addr:housenumber": "2155",
    "addr:postcode": "43065",
    "addr:street": "Strathshire Hall Ln",
    "iso:country": "US",
    "sg:address": "2155 Strathshire Hall Ln",
    "sg:city": "Powell",
    "sg:classifiers": [
      {
        "category": "Restaurant",
        "type": "Food \u0026 Drink"
      }
    ],
    "sg:phone": "+1 614 888 3733",
    "sg:postcode": "43065",
    "sg:province": "OH",
    "sg:tags": [
      "shop",
      "submarine",
      "sandwich"
    ],
    "wof:name": "Subway",
    "wof:placetype": "venue"
  },
  "geometry": {"coordinates":[-83.055299,40.140368],"type":"Point"}
}
