{
  "type": "Feature",
  "properties": {
    "iso:country":"US",
    "sg:address":"2155 Strathshire Hall Ln",
    "sg:city":"Powell",
    "sg:classifiers":[
        {
            "category":"Restaurant",
            "type":"Food & Drink"
        }
    ],
    "sg:phone":"+1 614 888 3733",
    "sg:postcode":"43065",
    "sg:province":"OH",
    "sg:tags":[
        "shop",
        "submarine",
        "sandwich"
    ],
    "wof:name":"Subway",
    "wof:placetype":"venue"
},
  "geometry": {"coordinates":[-83.05529900000001,40.140368],"type":"Point"}
}