{
  "type": "Feature",
  "properties": {
    "iso:country":"US",
    "sg:address":"1492 Westwood Ave",
    "sg:city":"Columbus",
    "sg:classifiers":[
        {
            "category":"Building & Trades",
            "subcategory":"Construction",
            "type":"Services"
        }
    ],
    "sg:phone":"+1 614 989 5393",
    "sg:postcode":"43212",
    "sg:province":"OH",
    "sg:tags":[
        "paving",
        "contractor"
    ],
    "wof:name":"Columbus Paving",
    "wof:placetype":"venue"
},
  "geometry": {"coordinates":[-83.052781,39.987533],"type":"Point"}
}