{
  "type": "Feature",
  "properties": {
    "addr:full": "34303 Bramble Ln Cleveland OH 44139",
    "addr:housenumber": "34303",
    "addr:postcode": "44139",
    "addr:street": "Bramble Ln",
    "iso:country": "US",
    "sg:address": "34303 Bramble Ln",
    "sg:city": "Cleveland",
    "sg:classifiers": [
      {
        "category": "Real Estate",
        "subcategory": "Real Estate Agent",
        "type": "Services"
      }
    ],
    "sg:phone": "+1 440 349 4281",
    "sg:postcode": "44139",
    "sg:province": "OH",
    "wof:name": "Shaste Inc",
    "wof:placetype": "venue"
  },
  "geometry": {"coordinates":[-81.435156,41.363571],"type":"Point"}
}
