{
  "type": "Feature",
  "properties": {
    "addr:full": "11276 US Hwy 62 Orient OH 43146",
    "addr:housenumber": "11276",
    "addr:postcode": "43146",
    "addr:street": "Us Hwy 62",
    "iso:country": "US",
    "sg:address": "11276 US Hwy 62",
    "sg:city": "Orient",
    "sg:classifiers": [
      {
        "category": "Restaurant",
        "type": "Food \u0026 Drink"
      }
    ],
    "sg:phone": "+1 614 877 3282",
    "sg:postcode": "43146",
    "sg:province": "OH",
    "wof:name": "Deer Trail Pizza",
    "wof:placetype": "venue"
  },
  "geometry": {"coordinates":[-83.210026,39.777624],"type":"Point"}
}
