{
  "type": "Feature",
  "properties": {
    "iso:country":"US",
    "sg:address":"13835 Fairgrounds Rd",
    "sg:city":"Croton",
    "sg:classifiers":[
        {
            "category":"Farming",
            "subcategory":"Farm",
            "type":"Manufacturing & Wholesale Goods"
        }
    ],
    "sg:phone":"+1 740 893 4799",
    "sg:postcode":"43013",
    "sg:province":"OH",
    "sg:tags":[
        "crop",
        "general"
    ],
    "wof:name":"Joe Dible Farms",
    "wof:placetype":"venue"
},
  "geometry": {"coordinates":[-82.681032,40.250598],"type":"Point"}
}