{
  "type": "Feature",
  "properties": {
    "addr:full": "4988 Stewart Rd Lima OH 45801",
    "addr:housenumber": "4988",
    "addr:postcode": "45801",
    "addr:street": "Stewart Rd",
    "iso:country": "US",
    "sg:address": "4988 Stewart Rd",
    "sg:city": "Lima",
    "sg:classifiers": [
      {
        "category": "Retail",
        "subcategory": "Animal Services",
        "type": "Services"
      }
    ],
    "sg:phone": "+1 419 228 4065",
    "sg:postcode": "45801",
    "sg:province": "OH",
    "sg:tags": [
      "pet",
      "grooming",
      "washing"
    ],
    "wof:name": "Kathy's Pet Grooming",
    "wof:placetype": "venue"
  },
  "geometry": {"coordinates":[-84.070983,40.816332],"type":"Point"}
}
