{
  "type": "Feature",
  "properties": {
    "iso:country":"US",
    "sg:address":"1860 N High St",
    "sg:city":"Columbus",
    "sg:classifiers":[
        {
            "category":"Banks & Credit Unions",
            "subcategory":"Financial Services",
            "type":"Services"
        }
    ],
    "sg:phone":"+1 614 291 7751",
    "sg:postcode":"43201",
    "sg:province":"OH",
    "sg:tags":[
        "franchise",
        "seller"
    ],
    "wof:name":"Brenens",
    "wof:placetype":"venue"
},
  "geometry": {"coordinates":[-83.00811299999999,40.000685],"type":"Point"}
}