{
  "type": "Feature",
  "properties": {
    "addr:full": "8568 Hayesville Rd Kingston OH 45644",
    "addr:housenumber": "8568",
    "addr:postcode": "45644",
    "addr:street": "Hayesville Rd",
    "iso:country": "US",
    "sg:address": "8568 Hayesville Rd",
    "sg:city": "Kingston",
    "sg:classifiers": [
      {
        "category": "Real Estate",
        "subcategory": "Real Estate Operator",
        "type": "Services"
      }
    ],
    "sg:phone": "+1 740 474 2416",
    "sg:postcode": "45644",
    "sg:province": "OH",
    "sg:tags": [
      "property",
      "lessor"
    ],
    "wof:name": "June McAfee",
    "wof:placetype": "venue"
  },
  "geometry": {"coordinates":[-82.876007,39.503236],"type":"Point"}
}
