{
  "type": "Feature",
  "properties": {
    "addr:full":"10984 Frederick Pike Vandalia OH 45377",
    "addr:housenumber":"10984",
    "addr:postcode":"45377",
    "addr:street":"Frederick Pike",
    "iso:country":"US",
    "sg:address":"10984 Frederick Pike",
    "sg:city":"Vandalia",
    "sg:classifiers":[
        {
            "category":"Professional",
            "subcategory":"Engineering",
            "type":"Services"
        }
    ],
    "sg:phone":"+1 937 898 6778",
    "sg:postcode":"45377",
    "sg:province":"OH",
    "sg:tags":[
        "house",
        "construction"
    ],
    "wof:name":"Around Town Maintenance Inc",
    "wof:placetype":"venue"
},
  "geometry": {"coordinates":[-84.27454299999999,39.909064],"type":"Point"}
}