{
  "type": "Feature",
  "properties": {
    "addr:full": "2115 Hampstead Rd Cleveland OH 44118",
    "addr:housenumber": "2115",
    "addr:postcode": "44118",
    "addr:street": "Hampstead Rd",
    "iso:country": "US",
    "sg:address": "2115 Hampstead Rd",
    "sg:city": "Cleveland",
    "sg:classifiers": [
      {
        "category": "Professional",
        "type": "Services"
      }
    ],
    "sg:phone": "+1 216 371 1181",
    "sg:postcode": "44118",
    "sg:province": "OH",
    "wof:name": "Buccia",
    "wof:placetype": "venue"
  },
  "geometry": {"coordinates":[-81.557094,41.502468],"type":"Point"}
}
