{
  "type": "Feature",
  "properties": {
    "addr:full":"131 Woodlawn Ave Norwalk OH 44857",
    "addr:housenumber":"131",
    "addr:postcode":"44857",
    "addr:street":"Woodlawn Ave",
    "iso:country":"US",
    "sg:address":"131 Woodlawn Ave",
    "sg:city":"Norwalk",
    "sg:classifiers":[
        {
            "category":"Building & Trades",
            "subcategory":"Construction",
            "type":"Services"
        }
    ],
    "sg:phone":"+1 419 668 9616",
    "sg:postcode":"44857",
    "sg:province":"OH",
    "sg:tags":[
        "concrete",
        "contractor"
    ],
    "wof:name":"Schloesser Concrete",
    "wof:placetype":"venue"
},
  "geometry": {"coordinates":[-82.598545,41.240814],"type":"Point"}
}