{
  "type": "Feature",
  "properties": {
    "addr:full":"9430 Colerain Ave Cincinnati OH 45251",
    "addr:postcode":"9430;45251",
    "addr:street":"Colerain Ave",
    "iso:country":"US",
    "sg:address":"9430 Colerain Ave",
    "sg:city":"Cincinnati",
    "sg:classifiers":[
        {
            "category":"Shopping",
            "type":"Retail Goods"
        }
    ],
    "sg:phone":"+1 513 923 1172",
    "sg:postcode":"45251",
    "sg:province":"OH",
    "sg:tags":[
        "merchandise"
    ],
    "wof:name":"T-Mobile USA Inc",
    "wof:placetype":"venue"
},
  "geometry": {"coordinates":[-84.59360100000001,39.240007],"type":"Point"}
}