{
  "type": "Feature",
  "properties": {
    "addr:full": "50 Reynoldsburg-New Albany Rd N Blacklick OH 43004",
    "addr:housenumber": "50",
    "addr:postcode": "43004",
    "addr:street": "Reynoldsburg-New Albany Rd N",
    "iso:country": "US",
    "sg:address": "50 Reynoldsburg-New Albany Rd N",
    "sg:city": "Blacklick",
    "sg:classifiers": [
      {
        "category": "Restaurant",
        "type": "Food \u0026 Drink"
      }
    ],
    "sg:menulink": "http://www.allmenus.com/oh/columbus/42839-bob-evans/menu/",
    "sg:phone": "+1 614 861 9920",
    "sg:postcode": "43004",
    "sg:province": "OH",
    "sg:tags": [
      "american"
    ],
    "wof:name": "Bob Evans",
    "wof:placetype": "venue"
  },
  "geometry": {"coordinates":[-82.814495,39.983936],"type":"Point"}
}
