{
  "type": "Feature",
  "properties": {
    "iso:country":"US",
    "sg:address":"10224 Alliance Rd",
    "sg:city":"Cincinnati",
    "sg:classifiers":[
        {
            "category":"Utilities",
            "subcategory":"Mobile Phone",
            "type":"Services"
        }
    ],
    "sg:phone":"+1 513 794 7400",
    "sg:postcode":"45242",
    "sg:province":"OH",
    "sg:tags":[
        "wireless",
        "communication"
    ],
    "wof:name":"Nextel",
    "wof:placetype":"venue"
},
  "geometry": {"coordinates":[-84.38017600000001,39.246604],"type":"Point"}
}