{
  "type": "Feature",
  "properties": {
    "addr:full":"7875 Winding Way S Tipp City OH 45371",
    "addr:housenumber":"7875",
    "addr:postcode":"45371",
    "addr:street":"Winding Way S Tipp",
    "iso:country":"US",
    "sg:address":"7875 Winding Way S",
    "sg:city":"Tipp City",
    "sg:classifiers":[
        {
            "category":"Building & Trades",
            "subcategory":"Plumbing",
            "type":"Services"
        }
    ],
    "sg:phone":"+1 937 435 5747",
    "sg:postcode":"45371",
    "sg:province":"OH",
    "sg:tags":[
        "contractor"
    ],
    "wof:name":"Climate Master",
    "wof:placetype":"venue"
},
  "geometry": {"coordinates":[-84.185355,39.923567],"type":"Point"}
}