{
  "type": "Feature",
  "properties": {
    "addr:full":"7717 Dalton-Fox Lake Rd North Lawrence OH 44666",
    "addr:housenumber":"7717",
    "addr:postcode":"44666",
    "addr:street":"Dalton-Fox Lake Rd",
    "iso:country":"US",
    "sg:address":"7717 Dalton-Fox Lake Rd",
    "sg:city":"North Lawrence",
    "sg:classifiers":[
        {
            "category":"Home & Garden",
            "subcategory":"Garden Supply",
            "type":"Retail Goods"
        }
    ],
    "sg:phone":"+1 330 855 3452",
    "sg:postcode":"44666",
    "sg:province":"OH",
    "wof:name":"Topes Peat Moss",
    "wof:placetype":"venue"
},
  "geometry": {"coordinates":[-81.67665599999999,40.890078],"type":"Point"}
}