{
  "type": "Feature",
  "properties": {
    "addr:full": "1221 Temple Trl Stow OH 44224",
    "addr:housenumber": "1221",
    "addr:postcode": "44224",
    "addr:street": "Temple Trl",
    "iso:country": "US",
    "sg:address": "1221 Temple Trl",
    "sg:city": "Stow",
    "sg:classifiers": [
      {
        "category": "Wholesale",
        "subcategory": "Electrical",
        "type": "Manufacturing \u0026 Wholesale Goods"
      }
    ],
    "sg:phone": "+1 330 686 1965",
    "sg:postcode": "44224",
    "sg:province": "OH",
    "sg:tags": [
      "electronic"
    ],
    "wof:name": "Lehner JW Co",
    "wof:placetype": "venue"
  },
  "geometry": {"coordinates":[-81.463022,41.17951],"type":"Point"}
}
