{
  "type": "Feature",
  "properties": {
    "iso:country":"US",
    "sg:address":"8979 Mentor Ave",
    "sg:city":"Mentor",
    "sg:classifiers":[
        {
            "category":"Education",
            "subcategory":"School",
            "type":"Public Place"
        }
    ],
    "sg:phone":"+1 440 974 2250",
    "sg:postcode":"44060",
    "sg:province":"OH",
    "wof:name":"Memorial Junior High School",
    "wof:placetype":"venue"
},
  "geometry": {"coordinates":[-81.320374,41.674715],"type":"Point"}
}