{
  "type": "Feature",
  "properties": {
    "iso:country":"US",
    "sg:address":"216 E Wayne St",
    "sg:city":"Lima",
    "sg:classifiers":[
        {
            "category":"Organizations",
            "subcategory":"Religious Organization",
            "type":"Services"
        }
    ],
    "sg:phone":"+1 419 224 6961",
    "sg:postcode":"45801",
    "sg:province":"OH",
    "sg:tags":[
        "campground",
        "rescue",
        "mission"
    ],
    "wof:name":"Lima Rescue Home",
    "wof:placetype":"venue"
},
  "geometry": {"coordinates":[-84.102791,40.743949],"type":"Point"}
}