{
  "type": "Feature",
  "properties": {
    "addr:full": "2190 Brookpark Rd Cleveland OH 44134",
    "addr:housenumber": "2190",
    "addr:postcode": "44134",
    "addr:street": "Brookpark Rd",
    "iso:country": "US",
    "sg:address": "2190 Brookpark Rd",
    "sg:city": "Cleveland",
    "sg:classifiers": [
      {
        "category": "Restaurant",
        "type": "Food \u0026 Drink"
      }
    ],
    "sg:menulink": "http://www.allmenus.com/oh/cleveland/38120-china-jade/menu/",
    "sg:phone": "+1 216 749 4720",
    "sg:postcode": "44134",
    "sg:province": "OH",
    "sg:tags": [
      "asian",
      "chinese"
    ],
    "wof:name": "China Jade",
    "wof:placetype": "venue"
  },
  "geometry": {"coordinates":[-81.696876,41.419178],"type":"Point"}
}
