{
  "type": "Feature",
  "properties": {
    "iso:country":"US",
    "sg:address":"2190 Brookpark Rd",
    "sg:city":"Cleveland",
    "sg:classifiers":[
        {
            "category":"Restaurant",
            "type":"Food & Drink"
        }
    ],
    "sg:menulink":"http://www.allmenus.com/oh/cleveland/38120-china-jade/menu/",
    "sg:phone":"+1 216 749 4720",
    "sg:postcode":"44134",
    "sg:province":"OH",
    "sg:tags":[
        "asian",
        "chinese"
    ],
    "wof:name":"China Jade",
    "wof:placetype":"venue"
},
  "geometry": {"coordinates":[-81.696876,41.419178],"type":"Point"}
}