{
  "type": "Feature",
  "properties": {
    "addr:full": "5852 Middle Ridge Rd Madison OH 44057",
    "addr:housenumber": "5852",
    "addr:postcode": "44057",
    "addr:street": "Middle Ridge Rd",
    "iso:country": "US",
    "sg:address": "5852 Middle Ridge Rd",
    "sg:city": "Madison",
    "sg:classifiers": [
      {
        "category": "Farming",
        "subcategory": "Farm",
        "type": "Manufacturing \u0026 Wholesale Goods"
      }
    ],
    "sg:phone": "+1 440 428 4074",
    "sg:postcode": "44057",
    "sg:province": "OH",
    "sg:tags": [
      "crop",
      "general"
    ],
    "wof:name": "Hejduk Hobart",
    "wof:placetype": "venue"
  },
  "geometry": {"coordinates":[-81.085501,41.783908],"type":"Point"}
}
