{
  "type": "Feature",
  "properties": {
    "addr:full":"1120 N Main St Bellefontaine OH 43311",
    "addr:housenumber":"1120",
    "addr:postcode":"43311",
    "addr:street":"N Main St",
    "iso:country":"US",
    "sg:address":"1120 N Main St",
    "sg:city":"Bellefontaine",
    "sg:classifiers":[
        {
            "category":"Banks & Credit Unions",
            "subcategory":"Bank",
            "type":"Services"
        }
    ],
    "sg:phone":"+1 937 592 5688",
    "sg:postcode":"43311",
    "sg:province":"OH",
    "sg:website":"www.lnbbank.com",
    "wof:name":"Liberty National Bank",
    "wof:placetype":"venue"
},
  "geometry": {"coordinates":[-83.755482,40.378584],"type":"Point"}
}