{
  "type": "Feature",
  "properties": {
    "addr:full": "26301 Curtiss Wright Pkwy Cleveland OH 44143",
    "addr:postcode": "26301;44143",
    "addr:street": "Wright Pkwy",
    "iso:country": "US",
    "sg:address": "26301 Curtiss Wright Pkwy",
    "sg:city": "Cleveland",
    "sg:classifiers": [
      {
        "category": "Manufacturing",
        "subcategory": "Printing",
        "type": "Manufacturing \u0026 Wholesale Goods"
      }
    ],
    "sg:phone": "+1 216 468 0187",
    "sg:postcode": "44143",
    "sg:province": "OH",
    "sg:tags": [
      "periodical"
    ],
    "wof:name": "Trader Publishing Company",
    "wof:placetype": "venue"
  },
  "geometry": {"coordinates":[-81.493706,41.565367],"type":"Point"}
}
