{
  "type": "Feature",
  "properties": {
    "addr:full": "12194 US Hwy 127 Paulding OH 45879",
    "addr:housenumber": "12194",
    "addr:postcode": "45879",
    "addr:street": "Us Hwy 127",
    "iso:country": "US",
    "sg:address": "12194 US Hwy 127",
    "sg:city": "Paulding",
    "sg:classifiers": [
      {
        "category": "Cinema",
        "subcategory": "Movie Rental",
        "type": "Entertainment"
      }
    ],
    "sg:phone": "+1 419 399 3455",
    "sg:postcode": "45879",
    "sg:province": "OH",
    "sg:tags": [
      "video",
      "tape"
    ],
    "wof:name": "Movie Gallery",
    "wof:placetype": "venue"
  },
  "geometry": {"coordinates":[-84.580866,41.154143],"type":"Point"}
}
