{
  "type": "Feature",
  "properties": {
    "addr:full": "10435 Palmer Dr Hopewell OH 43746",
    "addr:housenumber": "10435",
    "addr:postcode": "43746",
    "addr:street": "Palmer Dr",
    "iso:country": "US",
    "sg:address": "10435 Palmer Dr",
    "sg:city": "Hopewell",
    "sg:classifiers": [
      {
        "category": "Professional",
        "subcategory": "Art Services",
        "type": "Services"
      }
    ],
    "sg:phone": "+1 740 787 2102",
    "sg:postcode": "43746",
    "sg:province": "OH",
    "sg:tags": [
      "graphic",
      "designer"
    ],
    "wof:name": "Coast 2 Coast Graphics",
    "wof:placetype": "venue"
  },
  "geometry": {"coordinates":[-82.185965,39.941397],"type":"Point"}
}
