{
  "type": "Feature",
  "properties": {
    "iso:country":"US",
    "sg:address":"214 N Dawson St",
    "sg:city":"Uhrichsville",
    "sg:classifiers":[
        {
            "category":"Retail",
            "subcategory":"Car Wash",
            "type":"Services"
        }
    ],
    "sg:phone":"+1 740 922 5708",
    "sg:postcode":"44683",
    "sg:province":"OH",
    "sg:tags":[
        "polishing",
        "washing"
    ],
    "wof:name":"Classic Care Care",
    "wof:placetype":"venue"
},
  "geometry": {"coordinates":[-81.342049,40.390987],"type":"Point"}
}