{
  "type": "Feature",
  "properties": {
    "addr:full": "5553 Attica Ave Cincinnati OH 45212",
    "addr:housenumber": "5553",
    "addr:postcode": "45212",
    "addr:street": "Attica Ave",
    "iso:country": "US",
    "sg:address": "5553 Attica Ave",
    "sg:city": "Cincinnati",
    "sg:classifiers": [
      {
        "category": "Retail",
        "subcategory": "Repair Shop",
        "type": "Services"
      }
    ],
    "sg:phone": "+1 513 531 0056",
    "sg:postcode": "45212",
    "sg:province": "OH",
    "wof:name": "Andrew J Dresser",
    "wof:placetype": "venue"
  },
  "geometry": {"coordinates":[-84.43999,39.174463],"type":"Point"}
}
