{
  "type": "Feature",
  "properties": {
    "addr:full": "6422 E Main St Reynoldsburg OH 43068",
    "addr:housenumber": "6422",
    "addr:postcode": "43068",
    "addr:street": "E Main St",
    "iso:country": "US",
    "sg:address": "6422 E Main St",
    "sg:city": "Reynoldsburg",
    "sg:classifiers": [
      {
        "category": "Health Services",
        "subcategory": "Health Practitioner",
        "type": "Services"
      }
    ],
    "sg:phone": "+1 614 864 6620",
    "sg:postcode": "43068",
    "sg:province": "OH",
    "sg:tags": [
      "pathologist",
      "speech"
    ],
    "wof:name": "Northrup \u0026 Associates",
    "wof:placetype": "venue"
  },
  "geometry": {"coordinates":[-82.821802,39.954989],"type":"Point"}
}
