{
  "type": "Feature",
  "properties": {
    "iso:country":"US",
    "sg:address":"245 Oakham Ct",
    "sg:city":"Powell",
    "sg:classifiers":[
        {
            "category":"Arts & Performance",
            "subcategory":"Theater",
            "type":"Entertainment"
        }
    ],
    "sg:phone":"+1 614 436 4856",
    "sg:postcode":"43065",
    "sg:province":"OH",
    "sg:tags":[
        "magician"
    ],
    "wof:name":"Afterimage Productions",
    "wof:placetype":"venue"
},
  "geometry": {"coordinates":[-83.068971,40.151105],"type":"Point"}
}