{
  "type": "Feature",
  "properties": {
    "addr:full": "1509 E Main St Columbus OH 43205",
    "addr:housenumber": "1509",
    "addr:postcode": "43205",
    "addr:street": "E Main St",
    "iso:country": "US",
    "sg:address": "1509 E Main St",
    "sg:city": "Columbus",
    "sg:classifiers": [
      {
        "category": "Real Estate",
        "subcategory": "Real Estate Agent",
        "type": "Services"
      }
    ],
    "sg:phone": "+1 614 252 1973",
    "sg:postcode": "43205",
    "sg:province": "OH",
    "wof:name": "Crescent Realty Inc",
    "wof:placetype": "venue"
  },
  "geometry": {"coordinates":[-82.958685,39.95755],"type":"Point"}
}
