{
  "type": "Feature",
  "properties": {
    "addr:full": "4683 N Ridge Rd Perry OH 44081",
    "addr:housenumber": "4683",
    "addr:postcode": "44081",
    "addr:street": "N Ridge Rd",
    "iso:country": "US",
    "sg:address": "4683 N Ridge Rd",
    "sg:city": "Perry",
    "sg:classifiers": [
      {
        "category": "Retail",
        "subcategory": "Auto Repair",
        "type": "Services"
      }
    ],
    "sg:phone": "+1 440 259 0061",
    "sg:postcode": "44081",
    "sg:province": "OH",
    "sg:tags": [
      "repairing",
      "automobile"
    ],
    "wof:name": "Antioch Auto Svc",
    "wof:placetype": "venue"
  },
  "geometry": {"coordinates":[-81.12893,41.786154],"type":"Point"}
}
