{
  "type": "Feature",
  "properties": {
    "iso:country":"US",
    "sg:address":"117 S Main St",
    "sg:city":"Fostoria",
    "sg:classifiers":[
        {
            "category":"Shopping",
            "subcategory":"Computers & Home Electronics",
            "type":"Retail Goods"
        }
    ],
    "sg:phone":"+1 419 436 2355",
    "sg:postcode":"44830",
    "sg:province":"OH",
    "sg:tags":[
        "equipment",
        "satellite",
        "system"
    ],
    "wof:name":"Wireless Store",
    "wof:placetype":"venue"
},
  "geometry": {"coordinates":[-83.414146,41.157405],"type":"Point"}
}