{
  "type": "Feature",
  "properties": {
    "addr:full":"24320 Woodstock Rd Milford Center OH 43045",
    "addr:housenumber":"24320",
    "addr:postcode":"43045",
    "addr:street":"Woodstock Rd",
    "iso:country":"US",
    "sg:address":"24320 Woodstock Rd",
    "sg:city":"Milford Center",
    "sg:classifiers":[
        {
            "category":"Professional",
            "subcategory":"Management & Consulting",
            "type":"Services"
        }
    ],
    "sg:phone":"+1 937 826 3003",
    "sg:postcode":"43045",
    "sg:province":"OH",
    "sg:tags":[
        "agricultural",
        "consultant"
    ],
    "sg:website":"www.integratedag.net",
    "wof:name":"Integrated AG Svc",
    "wof:placetype":"venue"
},
  "geometry": {"coordinates":[-83.497608,40.173012],"type":"Point"}
}