{
  "type": "Feature",
  "properties": {
    "addr:full": "1359 S Byrne Rd Toledo OH 43614",
    "addr:housenumber": "1359",
    "addr:postcode": "43614",
    "addr:street": "S Byrne Rd",
    "iso:country": "US",
    "sg:address": "1359 S Byrne Rd",
    "sg:city": "Toledo",
    "sg:classifiers": [
      {
        "category": "Shopping",
        "subcategory": "Gifts \u0026 Souvenirs",
        "type": "Retail Goods"
      }
    ],
    "sg:phone": "+1 419 380 9455",
    "sg:postcode": "43614",
    "sg:province": "OH",
    "sg:tags": [
      "shop"
    ],
    "wof:name": "Amy's Hallmark",
    "wof:placetype": "venue"
  },
  "geometry": {"coordinates":[-83.625871,41.614731],"type":"Point"}
}
