{
  "type": "Feature",
  "properties": {
    "iso:country":"US",
    "sg:address":"1359 S Byrne Rd",
    "sg:city":"Toledo",
    "sg:classifiers":[
        {
            "category":"Shopping",
            "subcategory":"Gifts & Souvenirs",
            "type":"Retail Goods"
        }
    ],
    "sg:phone":"+1 419 380 9455",
    "sg:postcode":"43614",
    "sg:province":"OH",
    "sg:tags":[
        "shop"
    ],
    "wof:name":"Amy's Hallmark",
    "wof:placetype":"venue"
},
  "geometry": {"coordinates":[-83.625871,41.614731],"type":"Point"}
}