{
  "type": "Feature",
  "properties": {
    "addr:full":"2721 Laurel-Point Isabel Rd Moscow OH 45153",
    "addr:housenumber":"2721",
    "addr:postcode":"45153",
    "addr:street":"Laurel-Point Isabel Rd",
    "iso:country":"US",
    "sg:address":"2721 Laurel-Point Isabel Rd",
    "sg:city":"Moscow",
    "sg:classifiers":[
        {
            "category":"Wholesale",
            "subcategory":"Auto Parts",
            "type":"Manufacturing & Wholesale Goods"
        }
    ],
    "sg:phone":"+1 513 876 9028",
    "sg:postcode":"45153",
    "sg:province":"OH",
    "sg:tags":[
        "automobile",
        "rebuilt"
    ],
    "wof:name":"Nicholsville Auto Parts",
    "wof:placetype":"venue"
},
  "geometry": {"coordinates":[-84.13302299999999,38.898633],"type":"Point"}
}