{
  "type": "Feature",
  "properties": {
    "addr:full": "1 Lakeside Ave E Cleveland OH 44113",
    "addr:housenumber": "1",
    "addr:postcode": "44113",
    "addr:street": "Lakeside Ave E",
    "iso:country": "US",
    "sg:address": "1 Lakeside Ave E",
    "sg:city": "Cleveland",
    "sg:classifiers": [
      {
        "category": "Personal",
        "type": "Services"
      }
    ],
    "sg:phone": "+1 216 443 8920",
    "sg:postcode": "44113",
    "sg:province": "OH",
    "sg:tags": [
      "marriage",
      "bureau",
      "license"
    ],
    "wof:name": "Marriage License Bureau",
    "wof:placetype": "venue"
  },
  "geometry": {"coordinates":[-81.695315,41.503613],"type":"Point"}
}
