{
  "type": "Feature",
  "properties": {
    "iso:country":"US",
    "sg:address":"1 Lakeside Ave E",
    "sg:city":"Cleveland",
    "sg:classifiers":[
        {
            "category":"Personal",
            "type":"Services"
        }
    ],
    "sg:phone":"+1 216 443 8920",
    "sg:postcode":"44113",
    "sg:province":"OH",
    "sg:tags":[
        "marriage",
        "bureau",
        "license"
    ],
    "wof:name":"Marriage License Bureau",
    "wof:placetype":"venue"
},
  "geometry": {"coordinates":[-81.69531499999999,41.503613],"type":"Point"}
}