{
  "type": "Feature",
  "properties": {
    "addr:full":"33596 State Rte 82 Columbia Station OH 44028",
    "addr:housenumber":"33596",
    "addr:postcode":"44028",
    "addr:street":"State Rte 82",
    "iso:country":"US",
    "sg:address":"33596 State Rte 82",
    "sg:city":"Columbia Station",
    "sg:classifiers":[
        {
            "category":"Building & Trades",
            "subcategory":"Landscaping Services",
            "type":"Services"
        }
    ],
    "sg:phone":"+1 440 748 2500",
    "sg:postcode":"44028",
    "sg:province":"OH",
    "sg:tags":[
        "landscape",
        "contractor"
    ],
    "wof:name":"Land Creations Landscaping Inc",
    "wof:placetype":"venue"
},
  "geometry": {"coordinates":[-81.972577,41.313394],"type":"Point"}
}