{
  "type": "Feature",
  "properties": {
    "iso:country":"US",
    "sg:address":"2316 N 3 Bs and K Rd",
    "sg:city":"Sunbury",
    "sg:classifiers":[
        {
            "category":"Building & Trades",
            "subcategory":"Plumbing",
            "type":"Services"
        }
    ],
    "sg:phone":"+1 740 524 2316",
    "sg:postcode":"43074",
    "sg:province":"OH",
    "sg:tags":[
        "tank",
        "septic"
    ],
    "wof:name":"Graves & Sons Inc",
    "wof:placetype":"venue"
},
  "geometry": {"coordinates":[-82.93420999999999,40.300542],"type":"Point"}
}