{
  "type": "Feature",
  "properties": {
    "addr:full": "4256 Dartmouth Dr Cincinnati OH 45217",
    "addr:housenumber": "4256",
    "addr:postcode": "45217",
    "addr:street": "Dartmouth Dr",
    "iso:country": "US",
    "sg:address": "4256 Dartmouth Dr",
    "sg:city": "Cincinnati",
    "sg:classifiers": [
      {
        "category": "Building \u0026 Trades",
        "subcategory": "Electrical",
        "type": "Services"
      }
    ],
    "sg:phone": "+1 513 751 2700",
    "sg:postcode": "45217",
    "sg:province": "OH",
    "sg:tags": [
      "electric",
      "contractor"
    ],
    "wof:name": "Special Electric Svc",
    "wof:placetype": "venue"
  },
  "geometry": {"coordinates":[-84.49197,39.161649],"type":"Point"}
}
