{
  "type": "Feature",
  "properties": {
    "addr:full":"19428 Cadiz Rd Quaker City OH 43773",
    "addr:housenumber":"19428",
    "addr:postcode":"43773",
    "addr:street":"Cadiz Rd",
    "iso:country":"US",
    "sg:address":"19428 Cadiz Rd",
    "sg:city":"Quaker City",
    "sg:classifiers":[
        {
            "category":"Farming",
            "subcategory":"Livestock Farm",
            "type":"Manufacturing & Wholesale Goods"
        }
    ],
    "sg:phone":"+1 740 489 5774",
    "sg:postcode":"43773",
    "sg:province":"OH",
    "sg:tags":[
        "beef",
        "feedlot",
        "cattle"
    ],
    "wof:name":"Paul Dunlap",
    "wof:placetype":"venue"
},
  "geometry": {"coordinates":[-81.36772000000001,40.111781],"type":"Point"}
}