{
  "type": "Feature",
  "properties": {
    "addr:full":"7830 Cleveland Rd Wooster OH 44691",
    "addr:housenumber":"7830",
    "addr:postcode":"44691",
    "addr:street":"Cleveland Rd",
    "iso:country":"US",
    "sg:address":"7830 Cleveland Rd",
    "sg:city":"Wooster",
    "sg:classifiers":[
        {
            "category":"Utilities",
            "subcategory":"Telephone",
            "type":"Services"
        }
    ],
    "sg:phone":"+1 330 345 7097",
    "sg:postcode":"44691",
    "sg:province":"OH",
    "sg:tags":[
        "telecommunication"
    ],
    "wof:name":"RJE Telecom LLC",
    "wof:placetype":"venue"
},
  "geometry": {"coordinates":[-81.915054,40.89868],"type":"Point"}
}