{
  "type": "Feature",
  "properties": {
    "addr:full": "266 Muskingum Dr Marietta OH 45750",
    "addr:housenumber": "266",
    "addr:postcode": "45750",
    "addr:street": "Muskingum Dr",
    "iso:country": "US",
    "sg:address": "266 Muskingum Dr",
    "sg:city": "Marietta",
    "sg:classifiers": [
      {
        "category": "Personal",
        "subcategory": "Barber",
        "type": "Services"
      }
    ],
    "sg:phone": "+1 740 374 5894",
    "sg:postcode": "45750",
    "sg:province": "OH",
    "wof:name": "Muskingum Barbershop",
    "wof:placetype": "venue"
  },
  "geometry": {"coordinates":[-81.464547,39.435328],"type":"Point"}
}
