{
  "type": "Feature",
  "properties": {
    "addr:full":"2202 Corporate Dr Troy OH 45373",
    "addr:housenumber":"2202",
    "addr:postcode":"45373",
    "addr:street":"Corporate Dr",
    "iso:country":"US",
    "sg:address":"2202 Corporate Dr",
    "sg:city":"Troy",
    "sg:classifiers":[
        {
            "category":"Manufacturing",
            "subcategory":"Motor Vehicles & Parts",
            "type":"Manufacturing & Wholesale Goods"
        }
    ],
    "sg:phone":"+1 937 335 4426",
    "sg:postcode":"45373",
    "sg:province":"OH",
    "sg:tags":[
        "automotive",
        "mfg",
        "system",
        "exhaust"
    ],
    "wof:name":"Troy West",
    "wof:placetype":"venue"
},
  "geometry": {"coordinates":[-84.246861,40.065602],"type":"Point"}
}