{
  "type": "Feature",
  "properties": {
    "addr:full": "2485 Linebaugh Rd Xenia OH 45385",
    "addr:postcode": "2485;45385",
    "addr:street": "Linebaugh Rd",
    "iso:country": "US",
    "sg:address": "2485 Linebaugh Rd",
    "sg:city": "Xenia",
    "sg:classifiers": [
      {
        "category": "Manufacturing",
        "subcategory": "Printing",
        "type": "Manufacturing \u0026 Wholesale Goods"
      }
    ],
    "sg:phone": "+1 937 372 1217",
    "sg:postcode": "45385",
    "sg:province": "OH",
    "sg:tags": [
      "publishing"
    ],
    "wof:name": "Rolling Fork Publishing",
    "wof:placetype": "venue"
  },
  "geometry": {"coordinates":[-83.975043,39.757916],"type":"Point"}
}
