{
  "type": "Feature",
  "properties": {
    "iso:country":"US",
    "sg:address":"25 S Columbus St",
    "sg:city":"Sunbury",
    "sg:classifiers":[
        {
            "category":"Professional",
            "subcategory":"Accounting & Tax Preparation",
            "type":"Services"
        }
    ],
    "sg:phone":"+1 740 965 1588",
    "sg:postcode":"43074",
    "sg:province":"OH",
    "sg:tags":[
        "accountant"
    ],
    "wof:name":"Wandle & Assoc Inc",
    "wof:placetype":"venue"
},
  "geometry": {"coordinates":[-82.859876,40.242513],"type":"Point"}
}