{
  "type": "Feature",
  "properties": {
    "addr:full": "25 S Columbus St Sunbury OH 43074",
    "addr:housenumber": "25",
    "addr:postcode": "43074",
    "addr:street": "S Columbus St",
    "iso:country": "US",
    "sg:address": "25 S Columbus St",
    "sg:city": "Sunbury",
    "sg:classifiers": [
      {
        "category": "Professional",
        "subcategory": "Accounting \u0026 Tax Preparation",
        "type": "Services"
      }
    ],
    "sg:phone": "+1 740 965 1588",
    "sg:postcode": "43074",
    "sg:province": "OH",
    "sg:tags": [
      "accountant"
    ],
    "wof:name": "Wandle \u0026 Assoc Inc",
    "wof:placetype": "venue"
  },
  "geometry": {"coordinates":[-82.859876,40.242513],"type":"Point"}
}
