{
  "type": "Feature",
  "properties": {
    "iso:country":"US",
    "sg:address":"2424 Stanley Ave",
    "sg:city":"Dayton",
    "sg:classifiers":[
        {
            "category":"Wholesale",
            "subcategory":"Machinery & Supplies",
            "type":"Manufacturing & Wholesale Goods"
        }
    ],
    "sg:phone":"+1 937 227 3530",
    "sg:postcode":"45404",
    "sg:province":"OH",
    "sg:tags":[
        "equipment",
        "establishment",
        "car"
    ],
    "wof:name":"Complete Car Wash Sales & Serv",
    "wof:placetype":"venue"
},
  "geometry": {"coordinates":[-84.173125,39.787573],"type":"Point"}
}