{
  "type": "Feature",
  "properties": {
    "addr:full": "7774 State Rd 32 Union City OH 47390",
    "addr:housenumber": "7774;32",
    "addr:postcode": "47390",
    "addr:street": "State Rd",
    "iso:country": "US",
    "sg:address": "7774 State Rd 32",
    "sg:city": "Union City",
    "sg:classifiers": [
      {
        "category": "Building \u0026 Trades",
        "subcategory": "Construction",
        "type": "Services"
      }
    ],
    "sg:phone": "+1 765 584 8648",
    "sg:postcode": "47390",
    "sg:province": "OH",
    "sg:tags": [
      "water",
      "well",
      "drilling"
    ],
    "wof:name": "Wiley Well Drilling",
    "wof:placetype": "venue"
  },
  "geometry": {"coordinates":[-84.829021,40.180595],"type":"Point"}
}
