{
  "type": "Feature",
  "properties": {
    "iso:country":"US",
    "sg:address":"7774 State Rd 32",
    "sg:city":"Union City",
    "sg:classifiers":[
        {
            "category":"Building & Trades",
            "subcategory":"Construction",
            "type":"Services"
        }
    ],
    "sg:phone":"+1 765 584 8648",
    "sg:postcode":"47390",
    "sg:province":"OH",
    "sg:tags":[
        "water",
        "well",
        "drilling"
    ],
    "wof:name":"Wiley Well Drilling",
    "wof:placetype":"venue"
},
  "geometry": {"coordinates":[-84.829021,40.180595],"type":"Point"}
}