{
  "type": "Feature",
  "properties": {
    "addr:full": "8695 W Deadfall Rd Hillsboro OH 45133",
    "addr:housenumber": "8695",
    "addr:postcode": "45133",
    "addr:street": "W Deadfall Rd",
    "iso:country": "US",
    "sg:address": "8695 W Deadfall Rd",
    "sg:city": "Hillsboro",
    "sg:classifiers": [
      {
        "category": "Farming",
        "subcategory": "Nursery",
        "type": "Manufacturing \u0026 Wholesale Goods"
      }
    ],
    "sg:phone": "+1 937 393 4866",
    "sg:postcode": "45133",
    "sg:province": "OH",
    "sg:tags": [
      "ornamental"
    ],
    "wof:name": "Brunck \u0026 Sons Greenhouse",
    "wof:placetype": "venue"
  },
  "geometry": {"coordinates":[-83.565841,39.096593],"type":"Point"}
}
