{
  "type": "Feature",
  "properties": {
    "addr:full": "11997 Runyan Dr Cincinnati OH 45241",
    "addr:housenumber": "11997",
    "addr:postcode": "45241",
    "addr:street": "Runyan Dr",
    "iso:country": "US",
    "sg:address": "11997 Runyan Dr",
    "sg:city": "Cincinnati",
    "sg:classifiers": [
      {
        "category": "Building \u0026 Trades",
        "subcategory": "Construction",
        "type": "Services"
      }
    ],
    "sg:phone": "+1 513 769 0020",
    "sg:postcode": "45241",
    "sg:province": "OH",
    "sg:tags": [
      "general",
      "contractor"
    ],
    "sg:website": "www.mvmincorporated.com",
    "wof:name": "MVM Inc",
    "wof:placetype": "venue"
  },
  "geometry": {"coordinates":[-84.40231,39.291001],"type":"Point"}
}
