{
  "type": "Feature",
  "properties": {
    "iso:country":"US",
    "sg:address":"151 Keep Ct",
    "sg:city":"Elyria",
    "sg:classifiers":[
        {
            "category":"Building & Trades",
            "subcategory":"Landscaping Services",
            "type":"Services"
        }
    ],
    "sg:phone":"+1 440 324 7211",
    "sg:postcode":"44035",
    "sg:province":"OH",
    "sg:tags":[
        "lawn",
        "maintenance",
        "grounds"
    ],
    "wof:name":"Barefoot Grass",
    "wof:placetype":"venue"
},
  "geometry": {"coordinates":[-82.12472200000001,41.406511],"type":"Point"}
}