{
  "type": "Feature",
  "properties": {
    "addr:full": "151 Keep Ct Elyria OH 44035",
    "addr:housenumber": "151",
    "addr:postcode": "44035",
    "addr:street": "Keep Ct",
    "iso:country": "US",
    "sg:address": "151 Keep Ct",
    "sg:city": "Elyria",
    "sg:classifiers": [
      {
        "category": "Building \u0026 Trades",
        "subcategory": "Landscaping Services",
        "type": "Services"
      }
    ],
    "sg:phone": "+1 440 324 7211",
    "sg:postcode": "44035",
    "sg:province": "OH",
    "sg:tags": [
      "lawn",
      "maintenance",
      "grounds"
    ],
    "wof:name": "Barefoot Grass",
    "wof:placetype": "venue"
  },
  "geometry": {"coordinates":[-82.124722,41.406511],"type":"Point"}
}
