{
  "type": "Feature",
  "properties": {
    "iso:country":"US",
    "sg:address":"373 S High St",
    "sg:city":"Columbus",
    "sg:classifiers":[
        {
            "category":"Real Estate",
            "subcategory":"Real Estate Services",
            "type":"Services"
        }
    ],
    "sg:phone":"+1 614 224 6860",
    "sg:postcode":"43215",
    "sg:province":"OH",
    "sg:tags":[
        "company",
        "title"
    ],
    "wof:name":"Reliable Research",
    "wof:placetype":"venue"
},
  "geometry": {"coordinates":[-82.99908,39.953836],"type":"Point"}
}