{
  "type": "Feature",
  "properties": {
    "addr:full":"1401 Oakwood Ave Napoleon OH 43545",
    "addr:housenumber":"1401",
    "addr:postcode":"43545",
    "addr:street":"Oakwood Ave",
    "iso:country":"US",
    "sg:address":"1401 Oakwood Ave",
    "sg:city":"Napoleon",
    "sg:classifiers":[
        {
            "category":"Personal",
            "subcategory":"Beauty Salon",
            "type":"Services"
        }
    ],
    "sg:phone":"+1 419 592 3881",
    "sg:postcode":"43545",
    "sg:province":"OH",
    "wof:name":"Michaels Hair Designers",
    "wof:placetype":"venue"
},
  "geometry": {"coordinates":[-84.122624,41.401787],"type":"Point"}
}