{
  "type": "Feature",
  "properties": {
    "iso:country":"US",
    "sg:address":"177 W Longview Ave",
    "sg:city":"Mansfield",
    "sg:classifiers":[
        {
            "category":"Freight",
            "type":"Transportation"
        }
    ],
    "sg:phone":"+1 419 525 1355",
    "sg:postcode":"44903",
    "sg:province":"OH",
    "sg:tags":[
        "trucking"
    ],
    "wof:name":"D Plus S Distribution Inc",
    "wof:placetype":"venue"
},
  "geometry": {"coordinates":[-82.519652,40.776916],"type":"Point"}
}