{
  "type": "Feature",
  "properties": {
    "addr:full": "611 W Logan St Celina OH 45822",
    "addr:housenumber": "611",
    "addr:postcode": "45822",
    "addr:street": "W Logan St",
    "iso:country": "US",
    "sg:address": "611 W Logan St",
    "sg:city": "Celina",
    "sg:classifiers": [
      {
        "category": "Retail",
        "subcategory": "Photofinishing",
        "type": "Services"
      }
    ],
    "sg:phone": "+1 419 586 8900",
    "sg:postcode": "45822",
    "sg:province": "OH",
    "sg:tags": [
      "photo",
      "processing",
      "digital"
    ],
    "wof:name": "Pixelations Digital Photo",
    "wof:placetype": "venue"
  },
  "geometry": {"coordinates":[-84.579467,40.545719],"type":"Point"}
}
