{
  "type": "Feature",
  "properties": {
    "addr:full": "1974 N Fairfield Rd Dayton OH 45432",
    "addr:housenumber": "1974",
    "addr:postcode": "45432",
    "addr:street": "N Fairfield Rd",
    "iso:country": "US",
    "sg:address": "1974 N Fairfield Rd",
    "sg:city": "Dayton",
    "sg:classifiers": [
      {
        "category": "Health Services",
        "subcategory": "Nursing And Care Facility",
        "type": "Services"
      }
    ],
    "sg:phone": "+1 937 429 1106",
    "sg:postcode": "45432",
    "sg:province": "OH",
    "sg:tags": [
      "skilled"
    ],
    "wof:name": "Heartland - Beavercreek",
    "wof:placetype": "venue"
  },
  "geometry": {"coordinates":[-84.056833,39.743106],"type":"Point"}
}
