{
  "type": "Feature",
  "properties": {
    "addr:full": "1965 New Milford Rd Atwater OH 44201",
    "addr:housenumber": "1965",
    "addr:postcode": "44201",
    "addr:street": "New Milford Rd",
    "iso:country": "US",
    "sg:address": "1965 New Milford Rd",
    "sg:city": "Atwater",
    "sg:classifiers": [
      {
        "category": "Real Estate",
        "subcategory": "Architect",
        "type": "Services"
      }
    ],
    "sg:phone": "+1 330 325 9570",
    "sg:postcode": "44201",
    "sg:province": "OH",
    "wof:name": "Frank S Pavliga Architects",
    "wof:placetype": "venue"
  },
  "geometry": {"coordinates":[-81.21592,41.041005],"type":"Point"}
}
