{
  "type": "Feature",
  "properties": {
    "iso:country":"US",
    "sg:address":"1811 Hambletonian Ct",
    "sg:city":"Miamisburg",
    "sg:classifiers":[
        {
            "category":"Health Services",
            "subcategory":"Clinic",
            "type":"Services"
        }
    ],
    "sg:phone":"+1 937 865 6546",
    "sg:postcode":"45342",
    "sg:province":"OH",
    "wof:name":"United Healthcare Svc",
    "wof:placetype":"venue"
},
  "geometry": {"coordinates":[-84.26084299999999,39.619508],"type":"Point"}
}