{
  "type": "Feature",
  "properties": {
    "addr:full": "1811 Hambletonian Ct Miamisburg OH 45342",
    "addr:housenumber": "1811",
    "addr:postcode": "45342",
    "addr:street": "Hambletonian Ct",
    "iso:country": "US",
    "sg:address": "1811 Hambletonian Ct",
    "sg:city": "Miamisburg",
    "sg:classifiers": [
      {
        "category": "Health Services",
        "subcategory": "Clinic",
        "type": "Services"
      }
    ],
    "sg:phone": "+1 937 865 6546",
    "sg:postcode": "45342",
    "sg:province": "OH",
    "wof:name": "United Healthcare Svc",
    "wof:placetype": "venue"
  },
  "geometry": {"coordinates":[-84.260843,39.619508],"type":"Point"}
}
