{
  "type": "Feature",
  "properties": {
    "iso:country":"US",
    "sg:address":"198 Shull Ave",
    "sg:city":"Columbus",
    "sg:classifiers":[
        {
            "category":"Shopping",
            "subcategory":"Discount & Variety Stores",
            "type":"Retail Goods"
        }
    ],
    "sg:phone":"+1 614 476 4646",
    "sg:postcode":"43230",
    "sg:province":"OH",
    "sg:tags":[
        "salvage",
        "surplus"
    ],
    "wof:name":"Tk Airparts",
    "wof:placetype":"venue"
},
  "geometry": {"coordinates":[-82.87487299999999,40.022152],"type":"Point"}
}