{
  "type": "Feature",
  "properties": {
    "addr:full": "198 Shull Ave Columbus OH 43230",
    "addr:housenumber": "198",
    "addr:postcode": "43230",
    "addr:street": "Shull Ave",
    "iso:country": "US",
    "sg:address": "198 Shull Ave",
    "sg:city": "Columbus",
    "sg:classifiers": [
      {
        "category": "Shopping",
        "subcategory": "Discount \u0026 Variety Stores",
        "type": "Retail Goods"
      }
    ],
    "sg:phone": "+1 614 476 4646",
    "sg:postcode": "43230",
    "sg:province": "OH",
    "sg:tags": [
      "salvage",
      "surplus"
    ],
    "wof:name": "Tk Airparts",
    "wof:placetype": "venue"
  },
  "geometry": {"coordinates":[-82.874873,40.022152],"type":"Point"}
}
