{
  "type": "Feature",
  "properties": {
    "addr:full":"9886 Mink St SW Reynoldsburg OH 43068",
    "addr:housenumber":"9886",
    "addr:postcode":"43068",
    "addr:street":"Mink St Sw",
    "iso:country":"US",
    "sg:address":"9886 Mink St SW",
    "sg:city":"Reynoldsburg",
    "sg:classifiers":[
        {
            "category":"Building & Trades",
            "subcategory":"Landscaping Services",
            "type":"Services"
        }
    ],
    "sg:phone":"+1 740 964 2915",
    "sg:postcode":"43068",
    "sg:province":"OH",
    "sg:tags":[
        "landscape",
        "maintenance"
    ],
    "wof:name":"Five Seasons Landscape Mgmt",
    "wof:placetype":"venue"
},
  "geometry": {"coordinates":[-82.73017299999999,39.950422],"type":"Point"}
}