{
  "type": "Feature",
  "properties": {
    "iso:country":"US",
    "sg:address":"1250 N Vandemark Rd",
    "sg:city":"Sidney",
    "sg:classifiers":[
        {
            "category":"Real Estate",
            "subcategory":"Developer",
            "type":"Services"
        }
    ],
    "sg:phone":"+1 937 498 1164",
    "sg:postcode":"45365",
    "sg:province":"OH",
    "wof:name":"Bensar Developments",
    "wof:placetype":"venue"
},
  "geometry": {"coordinates":[-84.184977,40.297318],"type":"Point"}
}