{
  "type": "Feature",
  "properties": {
    "addr:full": "8493 Deer Path West Chester OH 45069",
    "addr:housenumber": "8493",
    "addr:postcode": "45069",
    "addr:street": "Deer Path",
    "iso:country": "US",
    "sg:address": "8493 Deer Path",
    "sg:city": "West Chester",
    "sg:classifiers": [
      {
        "category": "Professional",
        "type": "Services"
      }
    ],
    "sg:phone": "+1 513 860 5993",
    "sg:postcode": "45069",
    "sg:province": "OH",
    "wof:name": "Joseph G Vandal",
    "wof:placetype": "venue"
  },
  "geometry": {"coordinates":[-84.43819,39.343654],"type":"Point"}
}
