{
  "type": "Feature",
  "properties": {
    "iso:country":"US",
    "sg:address":"7079 Steiner Rd",
    "sg:city":"Sterling",
    "sg:classifiers":[
        {
            "category":"Building & Trades",
            "subcategory":"Plumbing",
            "type":"Services"
        }
    ],
    "sg:phone":"+1 330 939 3290",
    "sg:postcode":"44276",
    "sg:province":"OH",
    "sg:tags":[
        "plumbing",
        "contractor"
    ],
    "wof:name":"Ralph Plumbing",
    "wof:placetype":"venue"
},
  "geometry": {"coordinates":[-81.843495,40.930852],"type":"Point"}
}