{
  "type": "Feature",
  "properties": {
    "iso:country":"US",
    "sg:address":"9394 Montgomery Rd",
    "sg:city":"Cincinnati",
    "sg:classifiers":[
        {
            "category":"Real Estate",
            "subcategory":"Architect",
            "type":"Services"
        }
    ],
    "sg:phone":"+1 513 984 8143",
    "sg:postcode":"45242",
    "sg:province":"OH",
    "wof:name":"Creative Shelter Architect",
    "wof:placetype":"venue"
},
  "geometry": {"coordinates":[-84.354696,39.226693],"type":"Point"}
}