{
  "type": "Feature",
  "properties": {
    "addr:full":"18592 Edwards Rd Doylestown OH 44230",
    "addr:housenumber":"18592",
    "addr:postcode":"44230",
    "addr:street":"Edwards Rd",
    "iso:country":"US",
    "sg:address":"18592 Edwards Rd",
    "sg:city":"Doylestown",
    "sg:classifiers":[
        {
            "category":"Home & Garden",
            "subcategory":"Mobile Homes",
            "type":"Retail Goods"
        },
        {
            "category":"Real Estate",
            "subcategory":"Real Estate Operator",
            "type":"Services"
        }
    ],
    "sg:phone":"+1 330 658 6470",
    "sg:postcode":"44230",
    "sg:province":"OH",
    "sg:tags":[
        "community"
    ],
    "wof:name":"Westview Mobile Home Pk & Sls",
    "wof:placetype":"venue"
},
  "geometry": {"coordinates":[-81.659252,40.96026],"type":"Point"}
}