{
  "type": "Feature",
  "properties": {
    "addr:full": "511 Jackie Ln Cincinnati OH 45244",
    "addr:housenumber": "511",
    "addr:postcode": "45244",
    "addr:street": "Jackie Ln",
    "iso:country": "US",
    "sg:address": "511 Jackie Ln",
    "sg:city": "Cincinnati",
    "sg:classifiers": [
      {
        "category": "Building \u0026 Trades",
        "subcategory": "Construction",
        "type": "Services"
      }
    ],
    "sg:phone": "+1 513 528 2112",
    "sg:postcode": "45244",
    "sg:province": "OH",
    "sg:tags": [
      "hanging",
      "painter",
      "contractor"
    ],
    "wof:name": "Stephan Painting and Dctg",
    "wof:placetype": "venue"
  },
  "geometry": {"coordinates":[-84.301212,39.10312],"type":"Point"}
}
