{
  "type": "Feature",
  "properties": {
    "iso:country":"US",
    "sg:address":"511 Jackie Ln",
    "sg:city":"Cincinnati",
    "sg:classifiers":[
        {
            "category":"Building & Trades",
            "subcategory":"Construction",
            "type":"Services"
        }
    ],
    "sg:phone":"+1 513 528 2112",
    "sg:postcode":"45244",
    "sg:province":"OH",
    "sg:tags":[
        "hanging",
        "painter",
        "contractor"
    ],
    "wof:name":"Stephan Painting and Dctg",
    "wof:placetype":"venue"
},
  "geometry": {"coordinates":[-84.30121200000001,39.10312],"type":"Point"}
}