{
  "type": "Feature",
  "properties": {
    "addr:full": "197 Denham Rd Manchester OH 45144",
    "addr:housenumber": "197",
    "addr:postcode": "45144",
    "addr:street": "Denham Rd",
    "iso:country": "US",
    "sg:address": "197 Denham Rd",
    "sg:city": "Manchester",
    "sg:phone": "+1 937 549 4327",
    "sg:postcode": "45144",
    "sg:province": "OH",
    "sg:tags": [
      "farm",
      "corn",
      "tobacco"
    ],
    "wof:name": "Combs Greenhouse",
    "wof:placetype": "venue"
  },
  "geometry": {"coordinates":[-83.648262,38.743714],"type":"Point"}
}
