{
  "type": "Feature",
  "properties": {
    "iso:country":"US",
    "sg:address":"815 N Main St",
    "sg:city":"Canton",
    "sg:classifiers":[
        {
            "category":"Food & Beverages",
            "subcategory":"Candy",
            "type":"Retail Goods"
        }
    ],
    "sg:phone":"+1 330 966 3866",
    "sg:postcode":"44720",
    "sg:province":"OH",
    "sg:tags":[
        "confectionery"
    ],
    "wof:name":"Laura's Candy Nuts & Ice Cream",
    "wof:placetype":"venue"
},
  "geometry": {"coordinates":[-81.403712,40.883799],"type":"Point"}
}