{
  "type": "Feature",
  "properties": {
    "addr:full": "2241 Waynesville Jamestown Rd Xenia OH 45385",
    "addr:housenumber": "2241",
    "addr:postcode": "45385",
    "addr:street": "Jamestown Rd",
    "iso:country": "US",
    "sg:address": "2241 Waynesville Jamestown Rd",
    "sg:city": "Xenia",
    "sg:phone": "+1 937 374 2142",
    "sg:postcode": "45385",
    "sg:province": "OH",
    "sg:tags": [
      "farm",
      "corn",
      "soybean"
    ],
    "wof:name": "Dan Webster Farm",
    "wof:placetype": "venue"
  },
  "geometry": {"coordinates":[-83.846894,39.617709],"type":"Point"}
}
