{
  "type": "Feature",
  "properties": {
    "iso:country":"US",
    "sg:address":"2241 Waynesville Jamestown Rd",
    "sg:city":"Xenia",
    "sg:phone":"+1 937 374 2142",
    "sg:postcode":"45385",
    "sg:province":"OH",
    "sg:tags":[
        "farm",
        "corn",
        "soybean"
    ],
    "wof:name":"Dan Webster Farm",
    "wof:placetype":"venue"
},
  "geometry": {"coordinates":[-83.84689400000001,39.617709],"type":"Point"}
}