{
  "type": "Feature",
  "properties": {
    "addr:full":"16 N Main St Frankfort OH 45628",
    "addr:housenumber":"16",
    "addr:postcode":"45628",
    "addr:street":"N Main St",
    "iso:country":"US",
    "sg:address":"16 N Main St",
    "sg:city":"Frankfort",
    "sg:classifiers":[
        {
            "category":"Real Estate",
            "subcategory":"Real Estate Agent",
            "type":"Services"
        }
    ],
    "sg:phone":"+1 740 998 4021",
    "sg:postcode":"45628",
    "sg:province":"OH",
    "wof:name":"Coldwell Banker",
    "wof:placetype":"venue"
},
  "geometry": {"coordinates":[-83.177437,39.404769],"type":"Point"}
}