{
  "type": "Feature",
  "properties": {
    "addr:full":"869 16th St NE Massillon OH 44646",
    "addr:housenumber":"869",
    "addr:postcode":"44646",
    "addr:street":"16Th St Ne",
    "iso:country":"US",
    "sg:address":"869 16th St NE",
    "sg:city":"Massillon",
    "sg:classifiers":[
        {
            "category":"Building & Trades",
            "subcategory":"Construction",
            "type":"Services"
        }
    ],
    "sg:phone":"+1 330 833 3477",
    "sg:postcode":"44646",
    "sg:province":"OH",
    "sg:tags":[
        "contractor"
    ],
    "wof:name":"Fenton Construction",
    "wof:placetype":"venue"
},
  "geometry": {"coordinates":[-81.50401599999999,40.806406],"type":"Point"}
}