{
  "type": "Feature",
  "properties": {
    "iso:country":"US",
    "sg:address":"3971 State Rte 63",
    "sg:city":"Lebanon",
    "sg:classifiers":[
        {
            "category":"Professional",
            "type":"Services"
        }
    ],
    "sg:phone":"+1 513 932 2852",
    "sg:postcode":"45036",
    "sg:province":"OH",
    "sg:tags":[
        "establishment"
    ],
    "wof:name":"Lebanon Correctional",
    "wof:placetype":"venue"
},
  "geometry": {"coordinates":[-84.29969800000001,39.439159],"type":"Point"}
}