{
  "type": "Feature",
  "properties": {
    "addr:full": "3971 State Rte 63 Lebanon OH 45036",
    "addr:housenumber": "3971",
    "addr:postcode": "45036",
    "addr:street": "State Rte 63",
    "iso:country": "US",
    "sg:address": "3971 State Rte 63",
    "sg:city": "Lebanon",
    "sg:classifiers": [
      {
        "category": "Professional",
        "type": "Services"
      }
    ],
    "sg:phone": "+1 513 932 2852",
    "sg:postcode": "45036",
    "sg:province": "OH",
    "sg:tags": [
      "establishment"
    ],
    "wof:name": "Lebanon Correctional",
    "wof:placetype": "venue"
  },
  "geometry": {"coordinates":[-84.299698,39.439159],"type":"Point"}
}
