{
  "type": "Feature",
  "properties": {
    "addr:full":"3015 Lithopolis Rd NW Lancaster OH 43130",
    "addr:housenumber":"3015",
    "addr:postcode":"43130",
    "addr:street":"Lithopolis Rd Nw",
    "iso:country":"US",
    "sg:address":"3015 Lithopolis Rd NW",
    "sg:city":"Lancaster",
    "sg:classifiers":[
        {
            "category":"Retail",
            "subcategory":"Auto Repair",
            "type":"Services"
        }
    ],
    "sg:phone":"+1 740 652 9063",
    "sg:postcode":"43130",
    "sg:province":"OH",
    "sg:tags":[
        "repairing",
        "automobile"
    ],
    "wof:name":"33 Garage",
    "wof:placetype":"venue"
},
  "geometry": {"coordinates":[-82.657794,39.747571],"type":"Point"}
}