{
  "type": "Feature",
  "properties": {
    "addr:full":"107 N Main St Botkins OH 45306",
    "addr:housenumber":"107",
    "addr:postcode":"45306",
    "addr:street":"N Main St",
    "iso:country":"US",
    "sg:address":"107 N Main St",
    "sg:city":"Botkins",
    "sg:classifiers":[
        {
            "category":"Manufacturing",
            "subcategory":"Metals",
            "type":"Manufacturing & Wholesale Goods"
        }
    ],
    "sg:phone":"+1 937 693 3783",
    "sg:postcode":"45306",
    "sg:province":"OH",
    "sg:tags":[
        "coating"
    ],
    "wof:name":"T & K Laser Works Inc",
    "wof:placetype":"venue"
},
  "geometry": {"coordinates":[-84.182261,40.468581],"type":"Point"}
}