{
  "type": "Feature",
  "properties": {
    "addr:full":"3879 E 93rd St Cleveland OH 44105",
    "addr:housenumber":"3879",
    "addr:postcode":"44105",
    "addr:street":"E 93Rd St",
    "iso:country":"US",
    "sg:address":"3879 E 93rd St",
    "sg:city":"Cleveland",
    "sg:classifiers":[
        {
            "category":"Restaurant",
            "type":"Food & Drink"
        }
    ],
    "sg:phone":"+1 216 641 7428",
    "sg:postcode":"44105",
    "sg:province":"OH",
    "sg:tags":[
        "out"
    ],
    "wof:name":"Mom's Carryout",
    "wof:placetype":"venue"
},
  "geometry": {"coordinates":[-81.621308,41.453245],"type":"Point"}
}