{
  "type": "Feature",
  "properties": {
    "iso:country":"US",
    "sg:address":"1674 Sycamore Line",
    "sg:city":"Sandusky",
    "sg:classifiers":[
        {
            "category":"Health Services",
            "subcategory":"Doctor",
            "type":"Services"
        }
    ],
    "sg:phone":"+1 419 626 9090",
    "sg:postcode":"44870",
    "sg:province":"OH",
    "sg:tags":[
        "physician",
        "surgeon"
    ],
    "sg:website":"www.ncc.com",
    "wof:name":"North Coast Cancer Care",
    "wof:placetype":"venue"
},
  "geometry": {"coordinates":[-82.697167,41.442279],"type":"Point"}
}