{
  "type": "Feature",
  "properties": {
    "addr:full":"2747 Crawfis Blvd Akron OH 44333",
    "addr:housenumber":"2747",
    "addr:postcode":"44333",
    "addr:street":"Crawfis Blvd",
    "iso:country":"US",
    "sg:address":"2747 Crawfis Blvd",
    "sg:city":"Akron",
    "sg:classifiers":[
        {
            "category":"Real Estate",
            "subcategory":"Real Estate Operator",
            "type":"Services"
        }
    ],
    "sg:phone":"+1 330 836 4030",
    "sg:postcode":"44333",
    "sg:province":"OH",
    "sg:tags":[
        "shopping",
        "center"
    ],
    "wof:name":"Crawfis Square",
    "wof:placetype":"venue"
},
  "geometry": {"coordinates":[-81.611335,41.131485],"type":"Point"}
}