{
  "type": "Feature",
  "properties": {
    "iso:country":"US",
    "sg:address":"4619 Everhard Rd NW",
    "sg:city":"Canton",
    "sg:classifiers":[
        {
            "category":"Personal",
            "subcategory":"Beauty Salon",
            "type":"Services"
        }
    ],
    "sg:phone":"+1 330 499 5444",
    "sg:postcode":"44718",
    "sg:province":"OH",
    "wof:name":"Patrick Alan",
    "wof:placetype":"venue"
},
  "geometry": {"coordinates":[-81.439134,40.853217],"type":"Point"}
}