{
  "type": "Feature",
  "properties": {
    "iso:country":"US",
    "sg:address":"11627 Hanover Rd",
    "sg:city":"Cincinnati",
    "sg:classifiers":[
        {
            "category":"Organizations",
            "subcategory":"Religious Organization",
            "type":"Services"
        }
    ],
    "sg:phone":"+1 513 742 0042",
    "sg:postcode":"45240",
    "sg:province":"OH",
    "sg:tags":[
        "church"
    ],
    "wof:name":"Life Changing Ministries",
    "wof:placetype":"venue"
},
  "geometry": {"coordinates":[-84.511339,39.290626],"type":"Point"}
}