{
  "type": "Feature",
  "properties": {
    "iso:country":"US",
    "sg:address":"5640 Frantz Rd",
    "sg:city":"Dublin",
    "sg:classifiers":[
        {
            "category":"Wholesale",
            "subcategory":"Office Equipment",
            "type":"Manufacturing & Wholesale Goods"
        }
    ],
    "sg:phone":"+1 614 885 3772",
    "sg:postcode":"43017",
    "sg:province":"OH",
    "sg:tags":[
        "scanning",
        "code",
        "bar"
    ],
    "sg:website":"www.trackingsolutionsinc.com",
    "wof:name":"Tracking Solutions",
    "wof:placetype":"venue"
},
  "geometry": {"coordinates":[-83.122202,40.082941],"type":"Point"}
}