{
  "type": "Feature",
  "properties": {
    "iso:country":"US",
    "sg:address":"6131 N Spring St",
    "sg:city":"Ravenna",
    "sg:classifiers":[
        {
            "category":"Government",
            "subcategory":"Office",
            "type":"Public Place"
        }
    ],
    "sg:phone":"+1 330 296 9616",
    "sg:postcode":"44266",
    "sg:province":"OH",
    "sg:tags":[
        "city",
        "planning",
        "dev"
    ],
    "wof:name":"Ravenna Twp Zoning Dept",
    "wof:placetype":"venue"
},
  "geometry": {"coordinates":[-81.271242,41.156564],"type":"Point"}
}