{
  "type": "Feature",
  "properties": {
    "addr:full": "3545 Mechanicsburg Rd Springfield OH 45502",
    "addr:postcode": "3545;45502",
    "addr:street": "Mechanicsburg Rd",
    "iso:country": "US",
    "sg:address": "3545 Mechanicsburg Rd",
    "sg:city": "Springfield",
    "sg:classifiers": [
      {
        "category": "Shopping",
        "subcategory": "Gifts \u0026 Souvenirs",
        "type": "Retail Goods"
      }
    ],
    "sg:phone": "+1 937 399 3312",
    "sg:postcode": "45502",
    "sg:province": "OH",
    "wof:name": "Balloons and Stuff",
    "wof:placetype": "venue"
  },
  "geometry": {"coordinates":[-83.750933,39.973737],"type":"Point"}
}
