{
  "type": "Feature",
  "properties": {
    "iso:country":"US",
    "sg:address":"925 Eastland Ave SE",
    "sg:city":"Warren",
    "sg:classifiers":[
        {
            "category":"Bars & Pubs",
            "type":"Food & Drink"
        }
    ],
    "sg:phone":"+1 330 394 7200",
    "sg:postcode":"44484",
    "sg:province":"OH",
    "wof:name":"Town Tavern",
    "wof:placetype":"venue"
},
  "geometry": {"coordinates":[-80.778154,41.225141],"type":"Point"}
}