{
  "type": "Feature",
  "properties": {
    "addr:full": "925 Eastland Ave SE Warren OH 44484",
    "addr:housenumber": "925",
    "addr:postcode": "44484",
    "addr:street": "Eastland Ave Se",
    "iso:country": "US",
    "sg:address": "925 Eastland Ave SE",
    "sg:city": "Warren",
    "sg:classifiers": [
      {
        "category": "Bars \u0026 Pubs",
        "type": "Food \u0026 Drink"
      }
    ],
    "sg:phone": "+1 330 394 7200",
    "sg:postcode": "44484",
    "sg:province": "OH",
    "wof:name": "Town Tavern",
    "wof:placetype": "venue"
  },
  "geometry": {"coordinates":[-80.778154,41.225141],"type":"Point"}
}
