{
  "type": "Feature",
  "properties": {
    "addr:full":"4168 S Arlington Rd Uniontown OH 44685",
    "addr:housenumber":"4168",
    "addr:postcode":"44685",
    "addr:street":"S Arlington Rd",
    "iso:country":"US",
    "sg:address":"4168 S Arlington Rd",
    "sg:city":"Uniontown",
    "sg:phone":"+1 330 896 1814",
    "sg:postcode":"44685",
    "sg:province":"OH",
    "sg:tags":[
        "wheat",
        "farm",
        "corn",
        "cash",
        "crop",
        "field",
        "grain"
    ],
    "wof:name":"James Stiffler",
    "wof:placetype":"venue"
},
  "geometry": {"coordinates":[-81.49437399999999,40.956669],"type":"Point"}
}