{
  "type": "Feature",
  "properties": {
    "iso:country":"US",
    "sg:address":"6406 Kinsman Nickerson Rd",
    "sg:city":"Kinsman",
    "sg:classifiers":[
        {
            "category":"Shopping",
            "subcategory":"Department Store",
            "type":"Retail Goods"
        }
    ],
    "sg:phone":"+1 330 876 3178",
    "sg:postcode":"44428",
    "sg:province":"OH",
    "wof:name":"Market Square",
    "wof:placetype":"venue"
},
  "geometry": {"coordinates":[-80.588434,41.443991],"type":"Point"}
}