{
  "type": "Feature",
  "properties": {
    "addr:full":"230 Airport Pkwy Heath OH 43056",
    "addr:housenumber":"230",
    "addr:postcode":"43056",
    "addr:street":"Airport Pkwy",
    "iso:country":"US",
    "sg:address":"230 Airport Pkwy",
    "sg:city":"Heath",
    "sg:classifiers":[
        {
            "category":"Shopping",
            "subcategory":"Hobbies, Toys, & Games",
            "type":"Retail Goods"
        }
    ],
    "sg:phone":"+1 740 788 8161",
    "sg:postcode":"43056",
    "sg:province":"OH",
    "sg:tags":[
        "craft",
        "supply"
    ],
    "sg:website":"www.hobbylobby.com",
    "wof:name":"Hobby Lobby Creative Ctr",
    "wof:placetype":"venue"
},
  "geometry": {"coordinates":[-82.450885,40.029553],"type":"Point"}
}