{
  "type": "Feature",
  "properties": {
    "iso:country":"US",
    "sg:address":"8323 E Market St",
    "sg:city":"Warren",
    "sg:classifiers":[
        {
            "category":"Personal",
            "subcategory":"Beauty Salon",
            "type":"Services"
        }
    ],
    "sg:phone":"+1 330 856 1511",
    "sg:postcode":"44484",
    "sg:province":"OH",
    "sg:tags":[
        "shop"
    ],
    "wof:name":"Attitudes, New Inc",
    "wof:placetype":"venue"
},
  "geometry": {"coordinates":[-80.741641,41.238289],"type":"Point"}
}