{
  "type": "Feature",
  "properties": {
    "addr:full": "1301 E 9th St Cleveland OH 44114",
    "addr:housenumber": "1301",
    "addr:postcode": "44114",
    "addr:street": "E 9Th St",
    "iso:country": "US",
    "sg:address": "1301 E 9th St",
    "sg:city": "Cleveland",
    "sg:classifiers": [
      {
        "category": "Shopping",
        "subcategory": "Computers \u0026 Home Electronics",
        "type": "Retail Goods"
      }
    ],
    "sg:phone": "+1 216 575 0063",
    "sg:postcode": "44114",
    "sg:province": "OH",
    "sg:tags": [
      "game",
      "video",
      "software"
    ],
    "wof:name": "Electronics Boutique",
    "wof:placetype": "venue"
  },
  "geometry": {"coordinates":[-81.689572,41.503429],"type":"Point"}
}
