{
  "type": "Feature",
  "properties": {
    "iso:country":"US",
    "sg:address":"1301 E 9th St",
    "sg:city":"Cleveland",
    "sg:classifiers":[
        {
            "category":"Shopping",
            "subcategory":"Computers & Home Electronics",
            "type":"Retail Goods"
        }
    ],
    "sg:phone":"+1 216 575 0063",
    "sg:postcode":"44114",
    "sg:province":"OH",
    "sg:tags":[
        "game",
        "video",
        "software"
    ],
    "wof:name":"Electronics Boutique",
    "wof:placetype":"venue"
},
  "geometry": {"coordinates":[-81.689572,41.503429],"type":"Point"}
}