{
  "type": "Feature",
  "properties": {
    "iso:country":"US",
    "sg:address":"720 N Lexington Springmill Rd",
    "sg:city":"Mansfield",
    "sg:classifiers":[
        {
            "category":"Restaurant",
            "type":"Food & Drink"
        }
    ],
    "sg:menulink":"http://www.allmenus.com/oh/five-corners/11372-dennys/menu/",
    "sg:phone":"+1 419 529 6467",
    "sg:postcode":"44906",
    "sg:province":"OH",
    "sg:tags":[
        "american",
        "diner"
    ],
    "wof:name":"Denny's",
    "wof:placetype":"venue"
},
  "geometry": {"coordinates":[-82.590377,40.769246],"type":"Point"}
}