{
  "type": "Feature",
  "properties": {
    "addr:full": "720 N Lexington Springmill Rd Mansfield OH 44906",
    "addr:housenumber": "720",
    "addr:postcode": "44906",
    "addr:street": "N;Springmill Rd",
    "iso:country": "US",
    "sg:address": "720 N Lexington Springmill Rd",
    "sg:city": "Mansfield",
    "sg:classifiers": [
      {
        "category": "Restaurant",
        "type": "Food \u0026 Drink"
      }
    ],
    "sg:menulink": "http://www.allmenus.com/oh/five-corners/11372-dennys/menu/",
    "sg:phone": "+1 419 529 6467",
    "sg:postcode": "44906",
    "sg:province": "OH",
    "sg:tags": [
      "american",
      "diner"
    ],
    "wof:name": "Denny's",
    "wof:placetype": "venue"
  },
  "geometry": {"coordinates":[-82.590377,40.769246],"type":"Point"}
}
