{
  "type": "Feature",
  "properties": {
    "iso:country":"US",
    "sg:address":"8468 Fairbrook Ave",
    "sg:city":"Galloway",
    "sg:classifiers":[
        {
            "category":"Building & Trades",
            "subcategory":"Construction",
            "type":"Services"
        }
    ],
    "sg:phone":"+1 614 878 4289",
    "sg:postcode":"43119",
    "sg:province":"OH",
    "sg:tags":[
        "hanging",
        "painter",
        "contractor"
    ],
    "wof:name":"Dennis' Painting",
    "wof:placetype":"venue"
},
  "geometry": {"coordinates":[-83.22977,39.955842],"type":"Point"}
}