{
  "type": "Feature",
  "properties": {
    "addr:full": "24673 Cedar Rd Cleveland OH 44124",
    "addr:housenumber": "24673",
    "addr:postcode": "44124",
    "addr:street": "Cedar Rd",
    "iso:country": "US",
    "sg:address": "24673 Cedar Rd",
    "sg:city": "Cleveland",
    "sg:classifiers": [
      {
        "category": "Wholesale",
        "subcategory": "Electrical",
        "type": "Manufacturing \u0026 Wholesale Goods"
      },
      {
        "category": "Shopping",
        "subcategory": "Computers \u0026 Home Electronics",
        "type": "Retail Goods"
      },
      {
        "category": "Communications",
        "type": "Services"
      }
    ],
    "sg:phone": "+1 216 367 9466",
    "sg:postcode": "44124",
    "sg:province": "OH",
    "sg:tags": [
      "sound",
      "television",
      "theater",
      "equipment-wholesale",
      "stereo",
      "system",
      "high",
      "equipment",
      "stereophonic",
      "video",
      "equipment-dealers",
      "radio",
      "fidelity",
      "audio",
      "consumer",
      "store",
      "manufacturer"
    ],
    "sg:website": "http://cleveland.citysearch.com/profile/external/46282579/lyndhurst_oh/bose.html?publisher=yellowpages\u0026reference_id=1\u0026placement=ypwebsitemip",
    "wof:name": "Bose",
    "wof:placetype": "venue"
  },
  "geometry": {"coordinates":[-81.449722,41.500959],"type":"Point"}
}
