{
  "type": "Feature",
  "properties": {
    "iso:country":"US",
    "sg:address":"431 Broad Blvd",
    "sg:city":"Cuyahoga Falls",
    "sg:classifiers":[
        {
            "category":"Health Services",
            "subcategory":"Doctor",
            "type":"Services"
        }
    ],
    "sg:phone":"+1 330 923 5287",
    "sg:postcode":"44221",
    "sg:province":"OH",
    "sg:tags":[
        "dentist"
    ],
    "wof:name":"Richard O Mc Nary Inc",
    "wof:placetype":"venue"
},
  "geometry": {"coordinates":[-81.488581,41.134509],"type":"Point"}
}