{
  "type": "Feature",
  "properties": {
    "addr:full": "2216 Norwood Ave Cincinnati OH 45212",
    "addr:housenumber": "2216",
    "addr:postcode": "45212",
    "addr:street": "Norwood Ave",
    "iso:country": "US",
    "sg:address": "2216 Norwood Ave",
    "sg:city": "Cincinnati",
    "sg:classifiers": [
      {
        "category": "Government",
        "subcategory": "Fire Station",
        "type": "Public Place"
      },
      {
        "category": "Professional",
        "subcategory": "Detective \u0026 Security Services",
        "type": "Services"
      },
      {
        "category": "Shopping",
        "subcategory": "Computers \u0026 Home Electronics",
        "type": "Retail Goods"
      }
    ],
    "sg:phone": "+1 877 519 9692",
    "sg:postcode": "45212",
    "sg:province": "OH",
    "sg:tags": [
      "control",
      "monitoring",
      "supply",
      "consultant",
      "system",
      "surveillance",
      "equipment",
      "protection"
    ],
    "sg:website": "http://www.homesecurityteam.com/?tfid=y",
    "wof:name": "Advanced Direct Security - ADT Authorized Company",
    "wof:placetype": "venue"
  },
  "geometry": {"coordinates":[-84.453041,39.16456],"type":"Point"}
}
