{
  "type": "Feature",
  "properties": {
    "addr:full": "908 High St Minford OH 45653",
    "addr:housenumber": "908",
    "addr:postcode": "45653",
    "addr:street": "High St",
    "iso:country": "US",
    "sg:address": "908 High St",
    "sg:city": "Minford",
    "sg:classifiers": [
      {
        "category": "Personal",
        "subcategory": "Beauty Salon",
        "type": "Services"
      }
    ],
    "sg:phone": "+1 740 820 3318",
    "sg:postcode": "45653",
    "sg:province": "OH",
    "wof:name": "Mary Helen's Beauty Shoppe",
    "wof:placetype": "venue"
  },
  "geometry": {"coordinates":[-82.862566,38.859883],"type":"Point"}
}
