{
  "type": "Feature",
  "properties": {
    "iso:country":"US",
    "sg:address":"107 Park Row",
    "sg:city":"New Lexington",
    "sg:classifiers":[
        {
            "category":"Manufacturing",
            "subcategory":"Retail Goods",
            "type":"Manufacturing & Wholesale Goods"
        }
    ],
    "sg:phone":"+1 740 342 2012",
    "sg:postcode":"43764",
    "sg:province":"OH",
    "sg:tags":[
        "product",
        "mfg"
    ],
    "wof:name":"Rose Holden",
    "wof:placetype":"venue"
},
  "geometry": {"coordinates":[-82.204818,39.715315],"type":"Point"}
}