{
  "type": "Feature",
  "properties": {
    "addr:full":"812 E Erie Ave Lorain OH 44052",
    "addr:housenumber":"812",
    "addr:postcode":"44052",
    "addr:street":"E Erie Ave",
    "iso:country":"US",
    "sg:address":"812 E Erie Ave",
    "sg:city":"Lorain",
    "sg:classifiers":[
        {
            "category":"Shopping",
            "type":"Retail Goods"
        }
    ],
    "sg:phone":"+1 440 288 3838",
    "sg:postcode":"44052",
    "sg:province":"OH",
    "sg:tags":[
        "merchandise"
    ],
    "wof:name":"Creativ 4 Life",
    "wof:placetype":"venue"
},
  "geometry": {"coordinates":[-82.166016,41.473147],"type":"Point"}
}