{
  "type": "Feature",
  "properties": {
    "addr:full":"1507 Boettler Rd Uniontown OH 44685",
    "addr:housenumber":"1507",
    "addr:postcode":"44685",
    "addr:street":"Boettler Rd",
    "iso:country":"US",
    "sg:address":"1507 Boettler Rd",
    "sg:city":"Uniontown",
    "sg:classifiers":[
        {
            "category":"Banks & Credit Unions",
            "subcategory":"Investment Brokerage",
            "type":"Services"
        }
    ],
    "sg:phone":"+1 330 896 6250",
    "sg:postcode":"44685",
    "sg:province":"OH",
    "sg:tags":[
        "advisory",
        "financial"
    ],
    "sg:website":"www.ccadvisors.com",
    "wof:name":"Cornerstone Capital Advisors",
    "wof:placetype":"venue"
},
  "geometry": {"coordinates":[-81.47577,40.959617],"type":"Point"}
}