{
  "type": "Feature",
  "properties": {
    "addr:full": "65 W Columbus St Nelsonville OH 45764",
    "addr:housenumber": "65",
    "addr:postcode": "45764",
    "addr:street": "W Columbus St",
    "iso:country": "US",
    "sg:address": "65 W Columbus St",
    "sg:city": "Nelsonville",
    "sg:classifiers": [
      {
        "category": "Shopping",
        "subcategory": "Discount \u0026 Variety Stores",
        "type": "Retail Goods"
      }
    ],
    "sg:phone": "+1 740 753 4158",
    "sg:postcode": "45764",
    "sg:province": "OH",
    "sg:tags": [
      "gen",
      "merchandise"
    ],
    "wof:name": "Variety Wholesalers Inc",
    "wof:placetype": "venue"
  },
  "geometry": {"coordinates":[-82.233643,39.460018],"type":"Point"}
}
