{
  "type": "Feature",
  "properties": {
    "iso:country":"US",
    "sg:address":"214 S Munson Rd",
    "sg:city":"Swanton",
    "sg:classifiers":[
        {
            "category":"Health Services",
            "subcategory":"Nursing And Care Facility",
            "type":"Services"
        }
    ],
    "sg:phone":"+1 419 825 1145",
    "sg:postcode":"43558",
    "sg:province":"OH",
    "sg:tags":[
        "home",
        "convalescent"
    ],
    "wof:name":"Swanton Health Care Ctr",
    "wof:placetype":"venue"
},
  "geometry": {"coordinates":[-83.901905,41.584555],"type":"Point"}
}