{
  "type": "Feature",
  "properties": {
    "iso:country":"US",
    "sg:address":"250 Hopetown Rd",
    "sg:city":"Chillicothe",
    "sg:classifiers":[
        {
            "category":"Wholesale",
            "subcategory":"Hardware",
            "type":"Manufacturing & Wholesale Goods"
        }
    ],
    "sg:phone":"+1 740 702 0295",
    "sg:postcode":"45601",
    "sg:province":"OH",
    "sg:tags":[
        "equipment",
        "heating",
        "system"
    ],
    "wof:name":"Habegger Corp",
    "wof:placetype":"venue"
},
  "geometry": {"coordinates":[-82.96773399999999,39.38251],"type":"Point"}
}