{
  "type": "Feature",
  "properties": {
    "addr:full": "237 College Ave Fostoria OH 44830",
    "addr:housenumber": "237",
    "addr:postcode": "44830",
    "addr:street": "College Ave",
    "iso:country": "US",
    "sg:address": "237 College Ave",
    "sg:city": "Fostoria",
    "sg:classifiers": [
      {
        "category": "Professional",
        "subcategory": "Business Services",
        "type": "Services"
      }
    ],
    "sg:phone": "+1 419 435 8302",
    "sg:postcode": "44830",
    "sg:province": "OH",
    "wof:name": "Daughters of Isabella",
    "wof:placetype": "venue"
  },
  "geometry": {"coordinates":[-83.416833,41.159364],"type":"Point"}
}
