{
  "type": "Feature",
  "properties": {
    "addr:full": "1702 US Hwy 22 NW Washington Ct Hs OH 43160",
    "addr:housenumber": "1702",
    "addr:postcode": "43160",
    "addr:street": "Us Hwy 22 Nw",
    "iso:country": "US",
    "sg:address": "1702 US Hwy 22 NW",
    "sg:city": "Washington Ct Hs",
    "sg:classifiers": [
      {
        "category": "Organizations",
        "subcategory": "Religious Organization",
        "type": "Services"
      }
    ],
    "sg:phone": "+1 740 335 9219",
    "sg:postcode": "43160",
    "sg:province": "OH",
    "sg:tags": [
      "church"
    ],
    "wof:name": "Jehovah's Witnesses",
    "wof:placetype": "venue"
  },
  "geometry": {"coordinates":[-83.46543,39.528431],"type":"Point"}
}
