{
  "type": "Feature",
  "properties": {
    "addr:full":"340 S Market St Wooster OH 44691",
    "addr:housenumber":"340",
    "addr:postcode":"44691",
    "addr:street":"S Market St",
    "iso:country":"US",
    "sg:address":"340 S Market St",
    "sg:city":"Wooster",
    "sg:classifiers":[
        {
            "category":"Education",
            "subcategory":"Special Training",
            "type":"Public Place"
        }
    ],
    "sg:phone":"+1 330 674 2897",
    "sg:postcode":"44691",
    "sg:province":"OH",
    "sg:tags":[
        "instruction",
        "driving"
    ],
    "wof:name":"State Highway Patrol Exam Sta",
    "wof:placetype":"venue"
},
  "geometry": {"coordinates":[-81.939082,40.795361],"type":"Point"}
}