{
  "type": "Feature",
  "properties": {
    "addr:full":"3002 Clark Ave Cleveland OH 44109",
    "addr:housenumber":"3002",
    "addr:postcode":"44109",
    "addr:street":"Clark Ave",
    "iso:country":"US",
    "sg:address":"3002 Clark Ave",
    "sg:city":"Cleveland",
    "sg:classifiers":[
        {
            "category":"Autos & Motor Vehicles",
            "subcategory":"Auto Supplies",
            "type":"Retail Goods"
        },
        {
            "category":"Wholesale",
            "subcategory":"Electrical",
            "type":"Manufacturing & Wholesale Goods"
        }
    ],
    "sg:phone":"+1 216 961 4682",
    "sg:postcode":"44109",
    "sg:province":"OH",
    "sg:tags":[
        "battery",
        "automobile",
        "part",
        "batteries-storage",
        "accessory"
    ],
    "sg:website":"http://www.autozone.com",
    "wof:name":"AutoZone",
    "wof:placetype":"venue"
},
  "geometry": {"coordinates":[-81.701848,41.469879],"type":"Point"}
}