{
  "type": "Feature",
  "properties": {
    "addr:full": "384 W Johnstown Rd Columbus OH 43230",
    "addr:housenumber": "384",
    "addr:postcode": "43230",
    "addr:street": "W Johnstown Rd",
    "iso:country": "US",
    "sg:address": "384 W Johnstown Rd",
    "sg:city": "Columbus",
    "sg:classifiers": [
      {
        "category": "Professional",
        "subcategory": "Art Services",
        "type": "Services"
      }
    ],
    "sg:phone": "+1 614 337 2229",
    "sg:postcode": "43230",
    "sg:province": "OH",
    "sg:tags": [
      "commercial",
      "graphic",
      "design",
      "designer"
    ],
    "wof:name": "Rickabaugh Graphics",
    "wof:placetype": "venue"
  },
  "geometry": {"coordinates":[-82.891052,40.015792],"type":"Point"}
}
