{
  "type": "Feature",
  "properties": {
    "addr:full": "179 Pheasant Run Cleveland OH 44124",
    "addr:housenumber": "179",
    "addr:postcode": "44124",
    "addr:street": "Pheasant Run",
    "iso:country": "US",
    "sg:address": "179 Pheasant Run",
    "sg:city": "Cleveland",
    "sg:classifiers": [
      {
        "category": "Professional",
        "type": "Services"
      }
    ],
    "sg:phone": "+1 440 449 3212",
    "sg:postcode": "44124",
    "sg:province": "OH",
    "wof:name": "Edith Silverman",
    "wof:placetype": "venue"
  },
  "geometry": {"coordinates":[-81.451814,41.510151],"type":"Point"}
}
