{
  "type": "Feature",
  "properties": {
    "addr:full":"307 Pike St Marietta OH 45750",
    "addr:housenumber":"307",
    "addr:postcode":"45750",
    "addr:street":"Pike St",
    "iso:country":"US",
    "sg:address":"307 Pike St",
    "sg:city":"Marietta",
    "sg:classifiers":[
        {
            "category":"Autos & Motor Vehicles",
            "subcategory":"Auto Supplies",
            "type":"Retail Goods"
        }
    ],
    "sg:phone":"+1 740 373 0500",
    "sg:postcode":"45750",
    "sg:province":"OH",
    "sg:tags":[
        "lube",
        "oil"
    ],
    "wof:name":"Motorcare Oil & Lubrication Center",
    "wof:placetype":"venue"
},
  "geometry": {"coordinates":[-81.437449,39.413184],"type":"Point"}
}