{
  "type": "Feature",
  "properties": {
    "addr:full": "4942 Dixie Hwy Fairfield OH 45014",
    "addr:housenumber": "4942",
    "addr:postcode": "45014",
    "addr:street": "Dixie Hwy",
    "iso:country": "US",
    "sg:address": "4942 Dixie Hwy",
    "sg:city": "Fairfield",
    "sg:classifiers": [
      {
        "category": "Shopping",
        "subcategory": "Hobbies, Toys, \u0026 Games",
        "type": "Retail Goods"
      }
    ],
    "sg:phone": "+1 513 892 2723",
    "sg:postcode": "45014",
    "sg:province": "OH",
    "sg:tags": [
      "coin",
      "supply"
    ],
    "sg:website": "http://www.mainstreetcoin.com",
    "wof:name": "Cincinnati Rare Coin Gallery",
    "wof:placetype": "venue"
  },
  "geometry": {"coordinates":[-84.537354,39.342911],"type":"Point"}
}
