{
  "type": "Feature",
  "properties": {
    "iso:country":"US",
    "sg:address":"4942 Dixie Hwy",
    "sg:city":"Fairfield",
    "sg:classifiers":[
        {
            "category":"Shopping",
            "subcategory":"Hobbies, Toys, & Games",
            "type":"Retail Goods"
        }
    ],
    "sg:phone":"+1 513 892 2723",
    "sg:postcode":"45014",
    "sg:province":"OH",
    "sg:tags":[
        "coin",
        "supply"
    ],
    "sg:website":"http://www.mainstreetcoin.com",
    "wof:name":"Cincinnati Rare Coin Gallery",
    "wof:placetype":"venue"
},
  "geometry": {"coordinates":[-84.53735399999999,39.342911],"type":"Point"}
}