{
  "type": "Feature",
  "properties": {
    "iso:country":"US",
    "sg:address":"4060 Sullivant Ave",
    "sg:city":"Columbus",
    "sg:classifiers":[
        {
            "category":"Freight",
            "type":"Transportation"
        }
    ],
    "sg:phone":"+1 614 279 5448",
    "sg:postcode":"43228",
    "sg:province":"OH",
    "sg:tags":[
        "operator",
        "trucking"
    ],
    "wof:name":"Crete Carrier Corporation",
    "wof:placetype":"venue"
},
  "geometry": {"coordinates":[-83.105431,39.942104],"type":"Point"}
}