{
  "type": "Feature",
  "properties": {
    "addr:full": "5505 Keiffer Ave SW Canton OH 44706",
    "addr:housenumber": "5505",
    "addr:postcode": "44706",
    "addr:street": "Keiffer Ave Sw",
    "iso:country": "US",
    "sg:address": "5505 Keiffer Ave SW",
    "sg:city": "Canton",
    "sg:classifiers": [
      {
        "category": "Autos \u0026 Motor Vehicles",
        "subcategory": "Automobile Sales",
        "type": "Retail Goods"
      }
    ],
    "sg:phone": "+1 330 833 1811",
    "sg:postcode": "44706",
    "sg:province": "OH",
    "sg:tags": [
      "sport",
      "trailer",
      "utility"
    ],
    "wof:name": "Trailer Place",
    "wof:placetype": "venue"
  },
  "geometry": {"coordinates":[-81.418707,40.731576],"type":"Point"}
}
