{
  "type": "Feature",
  "properties": {
    "addr:full": "1327 S Wheeling St Oregon OH 43616",
    "addr:housenumber": "1327",
    "addr:postcode": "43616",
    "addr:street": "S Wheeling St",
    "iso:country": "US",
    "sg:address": "1327 S Wheeling St",
    "sg:city": "Oregon",
    "sg:classifiers": [
      {
        "category": "Food \u0026 Beverages",
        "subcategory": "Fruits \u0026 Vegetables",
        "type": "Retail Goods"
      }
    ],
    "sg:phone": "+1 419 693 6739",
    "sg:postcode": "43616",
    "sg:province": "OH",
    "sg:tags": [
      "farm",
      "market"
    ],
    "wof:name": "Sprague's Farm Market",
    "wof:placetype": "venue"
  },
  "geometry": {"coordinates":[-83.486041,41.6244],"type":"Point"}
}
