{
  "type": "Feature",
  "properties": {
    "iso:country":"US",
    "sg:address":"110 E Main St",
    "sg:city":"Mason",
    "sg:classifiers":[
        {
            "category":"Banks & Credit Unions",
            "subcategory":"Financial Services",
            "type":"Services"
        }
    ],
    "sg:phone":"+1 513 398 3332",
    "sg:postcode":"45040",
    "sg:province":"OH",
    "sg:tags":[
        "equipment",
        "company",
        "establishment",
        "holding"
    ],
    "wof:name":"Main Street Salon",
    "wof:placetype":"venue"
},
  "geometry": {"coordinates":[-84.30801599999999,39.360693],"type":"Point"}
}