{
  "type": "Feature",
  "properties": {
    "addr:full": "2500 W State St Alliance OH 44601",
    "addr:housenumber": "2500",
    "addr:postcode": "44601",
    "addr:street": "W State St",
    "iso:country": "US",
    "sg:address": "2500 W State St",
    "sg:city": "Alliance",
    "sg:classifiers": [
      {
        "category": "Education",
        "subcategory": "Library",
        "type": "Public Place"
      }
    ],
    "sg:phone": "+1 330 821 1313",
    "sg:postcode": "44601",
    "sg:province": "OH",
    "sg:website": "www.rodmanlibrary.com",
    "wof:name": "Rodman Public Library",
    "wof:placetype": "venue"
  },
  "geometry": {"coordinates":[-81.157723,40.901955],"type":"Point"}
}
