{
  "type": "Feature",
  "properties": {
    "iso:country":"US",
    "sg:address":"645 Wooster St",
    "sg:city":"Lodi",
    "sg:classifiers":[
        {
            "category":"Professional",
            "subcategory":"Accounting & Tax Preparation",
            "type":"Services"
        }
    ],
    "sg:phone":"+1 330 948 5252",
    "sg:postcode":"44254",
    "sg:province":"OH",
    "sg:tags":[
        "return",
        "filing"
    ],
    "wof:name":"Jackson Hewitt Tax Svc",
    "wof:placetype":"venue"
},
  "geometry": {"coordinates":[-82.004334,41.02993],"type":"Point"}
}