{
  "type": "Feature",
  "properties": {
    "addr:full": "235 W North Bend Rd Cincinnati OH 45216",
    "addr:housenumber": "235",
    "addr:postcode": "45216",
    "addr:street": "W North Bend Rd",
    "iso:country": "US",
    "sg:address": "235 W North Bend Rd",
    "sg:city": "Cincinnati",
    "sg:classifiers": [
      {
        "category": "Building \u0026 Trades",
        "subcategory": "Electrical",
        "type": "Services"
      }
    ],
    "sg:phone": "+1 513 821 1173",
    "sg:postcode": "45216",
    "sg:province": "OH",
    "sg:tags": [
      "electric",
      "contractor"
    ],
    "wof:name": "Total Systems Svc Inc",
    "wof:placetype": "venue"
  },
  "geometry": {"coordinates":[-84.484422,39.198358],"type":"Point"}
}
