{
  "type": "Feature",
  "properties": {
    "addr:full":"4299 Northfield Rd Cleveland OH 44128",
    "addr:housenumber":"4299",
    "addr:postcode":"44128",
    "addr:street":"Northfield Rd",
    "iso:country":"US",
    "sg:address":"4299 Northfield Rd",
    "sg:city":"Cleveland",
    "sg:classifiers":[
        {
            "category":"Food & Beverages",
            "subcategory":"Groceries & Convenience Stores",
            "type":"Retail Goods"
        }
    ],
    "sg:phone":"+1 216 831 2622",
    "sg:postcode":"44128",
    "sg:province":"OH",
    "sg:tags":[
        "grocer"
    ],
    "wof:name":"Dairy Mart",
    "wof:placetype":"venue"
},
  "geometry": {"coordinates":[-81.530731,41.44477],"type":"Point"}
}