{
  "type": "Feature",
  "properties": {
    "addr:full": "5501 Viewpoint Dr Dayton OH 45459",
    "addr:housenumber": "5501",
    "addr:postcode": "45459",
    "addr:street": "Viewpoint Dr",
    "iso:country": "US",
    "sg:address": "5501 Viewpoint Dr",
    "sg:city": "Dayton",
    "sg:classifiers": [
      {
        "category": "Banks \u0026 Credit Unions",
        "subcategory": "Bank",
        "type": "Services"
      }
    ],
    "sg:phone": "+1 937 439 0077",
    "sg:postcode": "45459",
    "sg:province": "OH",
    "sg:tags": [
      "broker",
      "mortgage"
    ],
    "wof:name": "Mayflower Mortgage Company LLC",
    "wof:placetype": "venue"
  },
  "geometry": {"coordinates":[-84.188355,39.667244],"type":"Point"}
}
