{
  "type": "Feature",
  "properties": {
    "addr:full":"5500 S Marginal Rd Cleveland OH 44103",
    "addr:housenumber":"5500",
    "addr:postcode":"44103",
    "addr:street":"S Marginal Rd",
    "iso:country":"US",
    "sg:address":"5500 S Marginal Rd",
    "sg:city":"Cleveland",
    "sg:classifiers":[
        {
            "category":"Wholesale",
            "subcategory":"Machinery & Supplies",
            "type":"Manufacturing & Wholesale Goods"
        }
    ],
    "sg:phone":"+1 216 391 5570",
    "sg:postcode":"44103",
    "sg:province":"OH",
    "sg:tags":[
        "equipment",
        "tool",
        "industrial"
    ],
    "wof:name":"M S C Industrial Supply",
    "wof:placetype":"venue"
},
  "geometry": {"coordinates":[-81.64846199999999,41.531808],"type":"Point"}
}