{
  "type": "Feature",
  "properties": {
    "iso:country":"US",
    "sg:address":"4472 W 8th St",
    "sg:city":"Cincinnati",
    "sg:classifiers":[
        {
            "category":"Insurance",
            "subcategory":"Insurance Agent",
            "type":"Services"
        },
        {
            "category":"Insurance",
            "subcategory":"Hazard Insurance",
            "type":"Services"
        },
        {
            "category":"Insurance",
            "subcategory":"Title Insurance",
            "type":"Services"
        },
        {
            "category":"Insurance",
            "subcategory":"Health Insurance",
            "type":"Services"
        },
        {
            "category":"Insurance",
            "subcategory":"Life Insurance",
            "type":"Services"
        }
    ],
    "sg:phone":"+1 513 251 0112",
    "sg:postcode":"45238",
    "sg:province":"OH",
    "sg:tags":[
        "business",
        "consultant",
        "commercial",
        "homeowner",
        "benefit",
        "auto",
        "employee",
        "analyst"
    ],
    "sg:website":"http://www.amfam.com",
    "wof:name":"American Family Insurance- Frey, Charles",
    "wof:placetype":"venue"
},
  "geometry": {"coordinates":[-84.59833999999999,39.108944],"type":"Point"}
}