{
  "type": "Feature",
  "properties": {
    "addr:full": "4311 Grand Ave Middletown OH 45044",
    "addr:housenumber": "4311",
    "addr:postcode": "45044",
    "addr:street": "Grand Ave",
    "iso:country": "US",
    "sg:address": "4311 Grand Ave",
    "sg:city": "Middletown",
    "sg:classifiers": [
      {
        "category": "Autos \u0026 Motor Vehicles",
        "subcategory": "Fuel \u0026 Gas Station",
        "type": "Retail Goods"
      }
    ],
    "sg:phone": "+1 513 423 4492",
    "sg:postcode": "45044",
    "sg:province": "OH",
    "sg:tags": [
      "grocery",
      "station",
      "gasoline"
    ],
    "wof:name": "BP",
    "wof:placetype": "venue"
  },
  "geometry": {"coordinates":[-84.35551,39.503646],"type":"Point"}
}
