{
  "type": "Feature",
  "properties": {
    "addr:full":"4275 State Rte 376 Mc Connelsville OH 43756",
    "addr:housenumber":"4275",
    "addr:postcode":"43756",
    "addr:street":"State Rte 376",
    "iso:country":"US",
    "sg:address":"4275 State Rte 376",
    "sg:city":"Mc Connelsville",
    "sg:classifiers":[
        {
            "category":"Government",
            "subcategory":"Office",
            "type":"Public Place"
        }
    ],
    "sg:phone":"+1 740 962 4572",
    "sg:postcode":"43756",
    "sg:province":"OH",
    "sg:tags":[
        "administrative",
        "program",
        "health"
    ],
    "wof:name":"Morgan County Health Dept",
    "wof:placetype":"venue"
},
  "geometry": {"coordinates":[-81.85999099999999,39.664775],"type":"Point"}
}