{
  "type": "Feature",
  "properties": {
    "addr:full":"8235 Leatherman Rd Wadsworth OH 44281",
    "addr:housenumber":"8235",
    "addr:postcode":"44281",
    "addr:street":"Leatherman Rd",
    "iso:country":"US",
    "sg:address":"8235 Leatherman Rd",
    "sg:city":"Wadsworth",
    "sg:classifiers":[
        {
            "category":"Building & Trades",
            "subcategory":"Construction",
            "type":"Services"
        }
    ],
    "sg:phone":"+1 330 334 1457",
    "sg:postcode":"44281",
    "sg:province":"OH",
    "sg:tags":[
        "carpentry",
        "contractor"
    ],
    "wof:name":"DMT Construction",
    "wof:placetype":"venue"
},
  "geometry": {"coordinates":[-81.74960799999999,41.048206],"type":"Point"}
}