{
  "type": "Feature",
  "properties": {
    "addr:full":"5720 Frantz Rd Dublin OH 43016",
    "addr:housenumber":"5720",
    "addr:postcode":"43016",
    "addr:street":"Frantz Rd",
    "iso:country":"US",
    "sg:address":"5720 Frantz Rd",
    "sg:city":"Dublin",
    "sg:classifiers":[
        {
            "category":"Restaurant",
            "type":"Food & Drink"
        }
    ],
    "sg:menulink":"http://www.allmenus.com/oh/columbus/282949-indian-palace-restaurant/menu/",
    "sg:phone":"+1 614 889 6654",
    "sg:postcode":"43016",
    "sg:province":"OH",
    "sg:tags":[
        "indian",
        "asian"
    ],
    "wof:name":"Indian Palace Restaurant",
    "wof:placetype":"venue"
},
  "geometry": {"coordinates":[-83.118741,40.069844],"type":"Point"}
}