{
  "type": "Feature",
  "properties": {
    "addr:full": "6370 Som Center Rd Ste 201 Solon OH 44139",
    "addr:postcode": "6370;44139",
    "addr:street": "Som Center Rd Ste 201",
    "iso:country": "US",
    "sg:address": "6370 Som Center Rd Ste 201",
    "sg:city": "Solon",
    "sg:classifiers": [
      {
        "category": "Professional",
        "subcategory": "Accounting \u0026 Tax Preparation",
        "type": "Services"
      }
    ],
    "sg:phone": "+1 440 349 3350",
    "sg:postcode": "44139",
    "sg:province": "OH",
    "sg:tags": [
      "accountant"
    ],
    "wof:name": "Johnson Neil D CPA",
    "wof:placetype": "venue"
  },
  "geometry": {"coordinates":[-81.437798,41.386398],"type":"Point"}
}
