{
  "type": "Feature",
  "properties": {
    "iso:country":"US",
    "sg:address":"88 W Mound St",
    "sg:city":"Columbus",
    "sg:classifiers":[
        {
            "category":"Banks & Credit Unions",
            "subcategory":"Investment Brokerage",
            "type":"Services"
        }
    ],
    "sg:phone":"+1 614 224 2678",
    "sg:postcode":"43215",
    "sg:province":"OH",
    "sg:tags":[
        "advisory"
    ],
    "wof:name":"2411 Harrison Road Investors",
    "wof:placetype":"venue"
},
  "geometry": {"coordinates":[-83.001536,39.95455],"type":"Point"}
}