{
  "type": "Feature",
  "properties": {
    "addr:full":"11847 Downing Rd Croton OH 43013",
    "addr:housenumber":"11847",
    "addr:postcode":"43013",
    "addr:street":"Downing Rd",
    "iso:country":"US",
    "sg:address":"11847 Downing Rd",
    "sg:city":"Croton",
    "sg:phone":"+1 740 893 2790",
    "sg:postcode":"43013",
    "sg:province":"OH",
    "sg:tags":[
        "farm",
        "corn",
        "wheat",
        "soybean"
    ],
    "wof:name":"James Cramer",
    "wof:placetype":"venue"
},
  "geometry": {"coordinates":[-82.738986,40.220973],"type":"Point"}
}