{
  "type": "Feature",
  "properties": {
    "iso:country":"US",
    "sg:address":"210 Retreat Ln",
    "sg:city":"Westerville",
    "sg:classifiers":[
        {
            "category":"Real Estate",
            "subcategory":"Real Estate Operator",
            "type":"Services"
        },
        {
            "category":"Building & Trades",
            "subcategory":"Construction",
            "type":"Services"
        }
    ],
    "sg:phone":"+1 614 882 8005",
    "sg:postcode":"43082",
    "sg:province":"OH",
    "sg:tags":[
        "new",
        "apartment",
        "home"
    ],
    "wof:name":"Retreat At Windemere",
    "wof:placetype":"venue"
},
  "geometry": {"coordinates":[-82.924053,40.134643],"type":"Point"}
}