{
  "type": "Feature",
  "properties": {
    "addr:full": "210 Retreat Ln Westerville OH 43082",
    "addr:housenumber": "210",
    "addr:postcode": "43082",
    "addr:street": "Retreat Ln",
    "iso:country": "US",
    "sg:address": "210 Retreat Ln",
    "sg:city": "Westerville",
    "sg:classifiers": [
      {
        "category": "Real Estate",
        "subcategory": "Real Estate Operator",
        "type": "Services"
      },
      {
        "category": "Building \u0026 Trades",
        "subcategory": "Construction",
        "type": "Services"
      }
    ],
    "sg:phone": "+1 614 882 8005",
    "sg:postcode": "43082",
    "sg:province": "OH",
    "sg:tags": [
      "new",
      "apartment",
      "home"
    ],
    "wof:name": "Retreat At Windemere",
    "wof:placetype": "venue"
  },
  "geometry": {"coordinates":[-82.924053,40.134643],"type":"Point"}
}
