{
  "type": "Feature",
  "properties": {
    "iso:country":"US",
    "sg:address":"2215 Glouchester Dr",
    "sg:city":"Cleveland",
    "sg:classifiers":[
        {
            "category":"Building & Trades",
            "subcategory":"Landscaping Services",
            "type":"Services"
        }
    ],
    "sg:phone":"+1 440 729 7209",
    "sg:postcode":"44124",
    "sg:province":"OH",
    "sg:tags":[
        "landscape"
    ],
    "wof:name":"Carlo Landscaping Inc",
    "wof:placetype":"venue"
},
  "geometry": {"coordinates":[-81.473896,41.502485],"type":"Point"}
}