{
  "type": "Feature",
  "properties": {
    "iso:country":"US",
    "sg:address":"1431 Crest Ave",
    "sg:city":"Cuyahoga Falls",
    "sg:classifiers":[
        {
            "category":"Wholesale",
            "subcategory":"Electrical",
            "type":"Manufacturing & Wholesale Goods"
        }
    ],
    "sg:phone":"+1 330 920 4271",
    "sg:postcode":"44223",
    "sg:province":"OH",
    "sg:tags":[
        "electronic"
    ],
    "wof:name":"R Moser",
    "wof:placetype":"venue"
},
  "geometry": {"coordinates":[-81.50007100000001,41.143235],"type":"Point"}
}