{
  "type": "Feature",
  "properties": {
    "addr:full": "3949 E 71st St Cleveland OH 44105",
    "addr:housenumber": "3949",
    "addr:postcode": "44105",
    "addr:street": "E 71St St",
    "iso:country": "US",
    "sg:address": "3949 E 71st St",
    "sg:city": "Cleveland",
    "sg:classifiers": [
      {
        "category": "Health Services",
        "subcategory": "Doctor",
        "type": "Services"
      }
    ],
    "sg:phone": "+1 216 883 4800",
    "sg:postcode": "44105",
    "sg:province": "OH",
    "sg:tags": [
      "dentist"
    ],
    "wof:name": "Dale Brainard DDS",
    "wof:placetype": "venue"
  },
  "geometry": {"coordinates":[-81.638798,41.451361],"type":"Point"}
}
