{
  "type": "Feature",
  "properties": {
    "addr:full":"610 Northridge Rd Circleville OH 43113",
    "addr:housenumber":"610",
    "addr:postcode":"43113",
    "addr:street":"Northridge Rd",
    "iso:country":"US",
    "sg:address":"610 Northridge Rd",
    "sg:city":"Circleville",
    "sg:classifiers":[
        {
            "category":"Health Services",
            "subcategory":"Medical Lab",
            "type":"Services"
        }
    ],
    "sg:phone":"+1 740 477 9847",
    "sg:postcode":"43113",
    "sg:province":"OH",
    "sg:tags":[
        "laboratory"
    ],
    "wof:name":"Laboratory Corp Of America",
    "wof:placetype":"venue"
},
  "geometry": {"coordinates":[-82.926677,39.616703],"type":"Point"}
}