{
  "type": "Feature",
  "properties": {
    "iso:country":"US",
    "sg:address":"9292 Cincinnati Columbus Rd",
    "sg:city":"Cincinnati",
    "sg:classifiers":[
        {
            "category":"Home & Garden",
            "subcategory":"Building Materials",
            "type":"Retail Goods"
        }
    ],
    "sg:phone":"+1 513 699 1010",
    "sg:postcode":"45241",
    "sg:province":"OH",
    "sg:tags":[
        "windows"
    ],
    "wof:name":"Creative Improvement Spec",
    "wof:placetype":"venue"
},
  "geometry": {"coordinates":[-84.37069700000001,39.31712],"type":"Point"}
}