{
  "type": "Feature",
  "properties": {
    "addr:full": "9292 Cincinnati Columbus Rd Cincinnati OH 45241",
    "addr:housenumber": "9292",
    "addr:postcode": "45241",
    "addr:street": "Cincinnati Columbus Rd",
    "iso:country": "US",
    "sg:address": "9292 Cincinnati Columbus Rd",
    "sg:city": "Cincinnati",
    "sg:classifiers": [
      {
        "category": "Home \u0026 Garden",
        "subcategory": "Building Materials",
        "type": "Retail Goods"
      }
    ],
    "sg:phone": "+1 513 699 1010",
    "sg:postcode": "45241",
    "sg:province": "OH",
    "sg:tags": [
      "windows"
    ],
    "wof:name": "Creative Improvement Spec",
    "wof:placetype": "venue"
  },
  "geometry": {"coordinates":[-84.370697,39.31712],"type":"Point"}
}
