{
  "type": "Feature",
  "properties": {
    "iso:country":"US",
    "sg:address":"4038 Twp Hwy 99",
    "sg:city":"Mount Gilead",
    "sg:classifiers":[
        {
            "category":"Building & Trades",
            "subcategory":"Landscaping Services",
            "type":"Services"
        }
    ],
    "sg:phone":"+1 419 947 9637",
    "sg:postcode":"43338",
    "sg:province":"OH",
    "wof:name":"Clydes Tree Service",
    "wof:placetype":"venue"
},
  "geometry": {"coordinates":[-82.822625,40.57876],"type":"Point"}
}