{
  "type": "Feature",
  "properties": {
    "addr:full": "1510 W Choctaw Dr London OH 43140",
    "addr:housenumber": "1510",
    "addr:postcode": "43140",
    "addr:street": "W Choctaw Dr",
    "iso:country": "US",
    "sg:address": "1510 W Choctaw Dr",
    "sg:city": "London",
    "sg:classifiers": [
      {
        "category": "Building \u0026 Trades",
        "subcategory": "Construction",
        "type": "Services"
      }
    ],
    "sg:phone": "+1 740 852 1598",
    "sg:postcode": "43140",
    "sg:province": "OH",
    "sg:tags": [
      "house"
    ],
    "wof:name": "BSD Maintenance \u0026 Construction",
    "wof:placetype": "venue"
  },
  "geometry": {"coordinates":[-83.49464,39.957157],"type":"Point"}
}
