{
  "type": "Feature",
  "properties": {
    "addr:full": "6038 E Dakar Rd Westerville OH 43081",
    "addr:housenumber": "6038",
    "addr:postcode": "43081",
    "addr:street": "E Dakar Rd",
    "iso:country": "US",
    "sg:address": "6038 E Dakar Rd",
    "sg:city": "Westerville",
    "sg:classifiers": [
      {
        "category": "Building \u0026 Trades",
        "subcategory": "Pest Control",
        "type": "Services"
      },
      {
        "category": "Recreation",
        "type": "Entertainment"
      }
    ],
    "sg:phone": "+1 614 523 3406",
    "sg:postcode": "43081",
    "sg:province": "OH",
    "sg:tags": [
      "trapper",
      "parks",
      "animal"
    ],
    "wof:name": "Duck Duck Goose Wildlife Anml",
    "wof:placetype": "venue"
  },
  "geometry": {"coordinates":[-82.921874,40.093331],"type":"Point"}
}
