{
  "type": "Feature",
  "properties": {
    "addr:full": "13402 Saybrook Ave Cleveland OH 44105",
    "addr:housenumber": "13402",
    "addr:postcode": "44105",
    "addr:street": "Saybrook Ave",
    "iso:country": "US",
    "sg:address": "13402 Saybrook Ave",
    "sg:city": "Cleveland",
    "sg:classifiers": [
      {
        "category": "Building \u0026 Trades",
        "subcategory": "Construction",
        "type": "Services"
      }
    ],
    "sg:phone": "+1 216 587 5955",
    "sg:postcode": "44105",
    "sg:province": "OH",
    "sg:tags": [
      "new",
      "home"
    ],
    "wof:name": "Young Homes",
    "wof:placetype": "venue"
  },
  "geometry": {"coordinates":[-81.589516,41.435681],"type":"Point"}
}
