{
  "type": "Feature",
  "properties": {
    "iso:country":"US",
    "sg:address":"709 Mount Moriah Dr",
    "sg:city":"Cincinnati",
    "sg:classifiers":[
        {
            "category":"Building & Trades",
            "subcategory":"Construction",
            "type":"Services"
        }
    ],
    "sg:phone":"+1 513 752 2777",
    "sg:postcode":"45245",
    "sg:province":"OH",
    "sg:tags":[
        "repairing",
        "remodeling",
        "contractor"
    ],
    "wof:name":"Van Stein Construction Inc",
    "wof:placetype":"venue"
},
  "geometry": {"coordinates":[-84.28904300000001,39.066195],"type":"Point"}
}