{
  "type": "Feature",
  "properties": {
    "addr:full":"2 N Reynolds Rd Toledo OH 43615",
    "addr:housenumber":"2",
    "addr:postcode":"43615",
    "addr:street":"N Reynolds Rd",
    "iso:country":"US",
    "sg:address":"2 N Reynolds Rd",
    "sg:city":"Toledo",
    "sg:classifiers":[
        {
            "category":"Autos & Motor Vehicles",
            "subcategory":"Fuel & Gas Station",
            "type":"Retail Goods"
        }
    ],
    "sg:phone":"+1 419 531 9124",
    "sg:postcode":"43615",
    "sg:province":"OH",
    "sg:tags":[
        "oil"
    ],
    "wof:name":"BP",
    "wof:placetype":"venue"
},
  "geometry": {"coordinates":[-83.664542,41.638673],"type":"Point"}
}