{
  "type": "Feature",
  "properties": {
    "iso:country":"US",
    "sg:address":"3415 Burnet Ave",
    "sg:city":"Cincinnati",
    "sg:classifiers":[
        {
            "category":"Retail",
            "subcategory":"Auto Rental",
            "type":"Services"
        }
    ],
    "sg:phone":"+1 513 281 6619",
    "sg:postcode":"45229",
    "sg:province":"OH",
    "sg:tags":[
        "renting",
        "truck",
        "leasing"
    ],
    "wof:name":"J & J U-Haul Co",
    "wof:placetype":"venue"
},
  "geometry": {"coordinates":[-84.500305,39.142309],"type":"Point"}
}