{
  "type": "Feature",
  "properties": {
    "addr:full": "1523 Broad Ave Findlay OH 45840",
    "addr:housenumber": "1523",
    "addr:postcode": "45840",
    "addr:street": "Broad Ave",
    "iso:country": "US",
    "sg:address": "1523 Broad Ave",
    "sg:city": "Findlay",
    "sg:classifiers": [
      {
        "category": "Fast Food",
        "type": "Food \u0026 Drink"
      },
      {
        "category": "Restaurant",
        "type": "Food \u0026 Drink"
      },
      {
        "category": "Food \u0026 Beverages",
        "subcategory": "Groceries \u0026 Convenience Stores",
        "type": "Retail Goods"
      }
    ],
    "sg:phone": "+1 419 423 1403",
    "sg:postcode": "45840",
    "sg:province": "OH",
    "sg:tags": [
      "shop",
      "style",
      "sandwich",
      "hamburger",
      "family",
      "dog",
      "hot",
      "american",
      "italian"
    ],
    "sg:website": "http://www.bigboy.com",
    "wof:name": "Ralphie's Family Sports Eatery",
    "wof:placetype": "venue"
  },
  "geometry": {"coordinates":[-83.664511,41.058915],"type":"Point"}
}
