{
  "type": "Feature",
  "properties": {
    "addr:full":"1792 W 5th Ave Columbus OH 43212",
    "addr:housenumber":"1792",
    "addr:postcode":"43212",
    "addr:street":"W 5Th Ave",
    "iso:country":"US",
    "sg:address":"1792 W 5th Ave",
    "sg:city":"Columbus",
    "sg:classifiers":[
        {
            "category":"Recreation",
            "type":"Entertainment"
        }
    ],
    "sg:phone":"+1 614 488 6392",
    "sg:postcode":"43212",
    "sg:province":"OH",
    "sg:tags":[
        "martial",
        "arts",
        "instruction"
    ],
    "wof:name":"Arlington Kung Fu & Tai Chi",
    "wof:placetype":"venue"
},
  "geometry": {"coordinates":[-83.054292,39.989296],"type":"Point"}
}