{
  "type": "Feature",
  "properties": {
    "addr:full":"4977 Hazel Brush Rd Shelby OH 44875",
    "addr:housenumber":"4977",
    "addr:postcode":"44875",
    "addr:street":"Hazel Brush Rd",
    "iso:country":"US",
    "sg:address":"4977 Hazel Brush Rd",
    "sg:city":"Shelby",
    "sg:classifiers":[
        {
            "category":"Home & Garden",
            "subcategory":"Garden Supply",
            "type":"Retail Goods"
        }
    ],
    "sg:phone":"+1 419 342 6414",
    "sg:postcode":"44875",
    "sg:province":"OH",
    "sg:tags":[
        "equipment",
        "industrial"
    ],
    "wof:name":"Hazelbrush Lawn & Garden",
    "wof:placetype":"venue"
},
  "geometry": {"coordinates":[-82.694028,40.930155],"type":"Point"}
}