{
  "type": "Feature",
  "properties": {
    "addr:full": "328 E Patterson Ave Bellefontaine OH 43311",
    "addr:housenumber": "328",
    "addr:postcode": "43311",
    "addr:street": "E Patterson Ave",
    "iso:country": "US",
    "sg:address": "328 E Patterson Ave",
    "sg:city": "Bellefontaine",
    "sg:classifiers": [
      {
        "category": "Organizations",
        "subcategory": "Religious Organization",
        "type": "Services"
      }
    ],
    "sg:phone": "+1 937 592 1656",
    "sg:postcode": "43311",
    "sg:province": "OH",
    "sg:tags": [
      "church"
    ],
    "wof:name": "St Patricks Church",
    "wof:placetype": "venue"
  },
  "geometry": {"coordinates":[-83.756105,40.356795],"type":"Point"}
}
