{
  "type": "Feature",
  "properties": {
    "iso:country":"US",
    "sg:address":"4400 Moline Martin Rd",
    "sg:city":"Millbury",
    "sg:classifiers":[
        {
            "category":"Manufacturing",
            "subcategory":"Signs",
            "type":"Manufacturing & Wholesale Goods"
        }
    ],
    "sg:phone":"+1 419 255 4275",
    "sg:postcode":"43447",
    "sg:province":"OH",
    "sg:tags":[
        "flat",
        "neon",
        "panel"
    ],
    "wof:name":"Omnion Technologies",
    "wof:placetype":"venue"
},
  "geometry": {"coordinates":[-83.476617,41.558763],"type":"Point"}
}