{
  "type": "Feature",
  "properties": {
    "iso:country":"US",
    "sg:address":"1832 Westwood Ave",
    "sg:city":"Cincinnati",
    "sg:classifiers":[
        {
            "category":"Manufacturing",
            "subcategory":"Printing",
            "type":"Manufacturing & Wholesale Goods"
        }
    ],
    "sg:phone":"+1 513 723 9600",
    "sg:postcode":"45214",
    "sg:province":"OH",
    "sg:tags":[
        "commercial"
    ],
    "wof:name":"Dulle Printing",
    "wof:placetype":"venue"
},
  "geometry": {"coordinates":[-84.56095500000001,39.125775],"type":"Point"}
}