{
  "type": "Feature",
  "properties": {
    "addr:full": "1832 Westwood Ave Cincinnati OH 45214",
    "addr:housenumber": "1832",
    "addr:postcode": "45214",
    "addr:street": "Westwood Ave",
    "iso:country": "US",
    "sg:address": "1832 Westwood Ave",
    "sg:city": "Cincinnati",
    "sg:classifiers": [
      {
        "category": "Manufacturing",
        "subcategory": "Printing",
        "type": "Manufacturing \u0026 Wholesale Goods"
      }
    ],
    "sg:phone": "+1 513 723 9600",
    "sg:postcode": "45214",
    "sg:province": "OH",
    "sg:tags": [
      "commercial"
    ],
    "wof:name": "Dulle Printing",
    "wof:placetype": "venue"
  },
  "geometry": {"coordinates":[-84.560955,39.125775],"type":"Point"}
}
