{
  "type": "Feature",
  "properties": {
    "addr:full": "399 E Hopocan Ave Barberton OH 44203",
    "addr:housenumber": "399",
    "addr:postcode": "44203",
    "addr:street": "E Hopocan Ave",
    "iso:country": "US",
    "sg:address": "399 E Hopocan Ave",
    "sg:city": "Barberton",
    "sg:classifiers": [
      {
        "category": "Building \u0026 Trades",
        "subcategory": "Construction",
        "type": "Services"
      }
    ],
    "sg:phone": "+1 330 745 5966",
    "sg:postcode": "44203",
    "sg:province": "OH",
    "sg:tags": [
      "house"
    ],
    "wof:name": "Clifford E Berkley",
    "wof:placetype": "venue"
  },
  "geometry": {"coordinates":[-81.59044,41.017286],"type":"Point"}
}
