{
  "type": "Feature",
  "properties": {
    "addr:full": "9360 Mentor Ave Mentor OH 44060",
    "addr:housenumber": "9360",
    "addr:postcode": "44060",
    "addr:street": "Mentor Ave",
    "iso:country": "US",
    "sg:address": "9360 Mentor Ave",
    "sg:city": "Mentor",
    "sg:classifiers": [
      {
        "category": "Banks \u0026 Credit Unions",
        "subcategory": "Bank",
        "type": "Services"
      }
    ],
    "sg:phone": "+1 440 205 0650",
    "sg:postcode": "44060",
    "sg:province": "OH",
    "sg:tags": [
      "cashing",
      "personal",
      "check",
      "institution"
    ],
    "sg:website": "www.advanceamerica.com",
    "wof:name": "Advance America",
    "wof:placetype": "venue"
  },
  "geometry": {"coordinates":[-81.306987,41.678042],"type":"Point"}
}
