{
  "type": "Feature",
  "properties": {
    "addr:full": "2322 Half Hill Rd Bethel OH 45106",
    "addr:housenumber": "2322",
    "addr:postcode": "45106",
    "addr:street": "Half Hill Rd",
    "iso:country": "US",
    "sg:address": "2322 Half Hill Rd",
    "sg:city": "Bethel",
    "sg:classifiers": [
      {
        "category": "Professional",
        "subcategory": "Employment Agencies",
        "type": "Services"
      }
    ],
    "sg:phone": "+1 513 734 1428",
    "sg:postcode": "45106",
    "sg:province": "OH",
    "sg:tags": [
      "opportunity"
    ],
    "wof:name": "Bedbugs \u0026 Tattletales Elite",
    "wof:placetype": "venue"
  },
  "geometry": {"coordinates":[-84.15954,38.978306],"type":"Point"}
}
