{
  "type": "Feature",
  "properties": {
    "addr:full": "11501 Northlake Dr Cincinnati OH 45249",
    "addr:housenumber": "11501",
    "addr:postcode": "45249",
    "addr:street": "Northlake Dr",
    "iso:country": "US",
    "sg:address": "11501 Northlake Dr",
    "sg:city": "Cincinnati",
    "sg:classifiers": [
      {
        "category": "Professional",
        "subcategory": "Computer Services",
        "type": "Services"
      }
    ],
    "sg:phone": "+1 513 605 5800",
    "sg:postcode": "45249",
    "sg:province": "OH",
    "sg:tags": [
      "consultant"
    ],
    "wof:name": "Belcan Information Technology",
    "wof:placetype": "venue"
  },
  "geometry": {"coordinates":[-84.347356,39.276193],"type":"Point"}
}
