{
  "type": "Feature",
  "properties": {
    "addr:full":"4801 Gateway Blvd Springfield OH 45502",
    "addr:housenumber":"4801",
    "addr:postcode":"45502",
    "addr:street":"Gateway Blvd",
    "iso:country":"US",
    "sg:address":"4801 Gateway Blvd",
    "sg:city":"Springfield",
    "sg:classifiers":[
        {
            "category":"Freight",
            "type":"Transportation"
        }
    ],
    "sg:phone":"+1 937 325 9404",
    "sg:postcode":"45502",
    "sg:province":"OH",
    "sg:tags":[
        "arrangement"
    ],
    "wof:name":"K B T Inc",
    "wof:placetype":"venue"
},
  "geometry": {"coordinates":[-83.71561199999999,39.906673],"type":"Point"}
}