{
  "type": "Feature",
  "properties": {
    "addr:full": "6231 Montgomery Rd Cincinnati OH 45213",
    "addr:housenumber": "6231",
    "addr:postcode": "45213",
    "addr:street": "Montgomery Rd",
    "iso:country": "US",
    "sg:address": "6231 Montgomery Rd",
    "sg:city": "Cincinnati",
    "sg:classifiers": [
      {
        "category": "Retail",
        "subcategory": "Animal Services",
        "type": "Services"
      }
    ],
    "sg:phone": "+1 513 351 4776",
    "sg:postcode": "45213",
    "sg:province": "OH",
    "wof:name": "Groom Room",
    "wof:placetype": "venue"
  },
  "geometry": {"coordinates":[-84.423239,39.184394],"type":"Point"}
}
