{
  "type": "Feature",
  "properties": {
    "addr:full": "18001 Detroit Ave Cleveland OH 44107",
    "addr:housenumber": "18001",
    "addr:postcode": "44107",
    "addr:street": "Detroit Ave",
    "iso:country": "US",
    "sg:address": "18001 Detroit Ave",
    "sg:city": "Cleveland",
    "sg:classifiers": [
      {
        "category": "Social Services",
        "subcategory": "Child Care",
        "type": "Services"
      }
    ],
    "sg:phone": "+1 216 226 2840",
    "sg:postcode": "44107",
    "sg:province": "OH",
    "wof:name": "St Peter's Child Care Ctr",
    "wof:placetype": "venue"
  },
  "geometry": {"coordinates":[-81.822486,41.484149],"type":"Point"}
}
