{
  "type": "Feature",
  "properties": {
    "addr:full": "303 S Main St Bryan OH 43506",
    "addr:housenumber": "303",
    "addr:postcode": "43506",
    "addr:street": "S Main St",
    "iso:country": "US",
    "sg:address": "303 S Main St",
    "sg:city": "Bryan",
    "sg:classifiers": [
      {
        "category": "Autos \u0026 Motor Vehicles",
        "subcategory": "Fuel \u0026 Gas Station",
        "type": "Retail Goods"
      }
    ],
    "sg:phone": "+1 419 633 0833",
    "sg:postcode": "43506",
    "sg:province": "OH",
    "sg:tags": [
      "oil"
    ],
    "wof:name": "American Petroleum",
    "wof:placetype": "venue"
  },
  "geometry": {"coordinates":[-84.550953,41.47199],"type":"Point"}
}
