{
  "type": "Feature",
  "properties": {
    "iso:country":"US",
    "sg:address":"2420 W 14th St",
    "sg:city":"Cleveland",
    "sg:classifiers":[
        {
            "category":"Organizations",
            "subcategory":"Religious Organization",
            "type":"Services"
        }
    ],
    "sg:phone":"+1 216 861 2177",
    "sg:postcode":"44113",
    "sg:province":"OH",
    "sg:tags":[
        "church"
    ],
    "wof:name":"Holy Ghost Byzantine Catholic",
    "wof:placetype":"venue"
},
  "geometry": {"coordinates":[-81.69141500000001,41.478857],"type":"Point"}
}