{
  "type": "Feature",
  "properties": {
    "addr:full": "2420 W 14th St Cleveland OH 44113",
    "addr:housenumber": "2420",
    "addr:postcode": "44113",
    "addr:street": "W 14Th St",
    "iso:country": "US",
    "sg:address": "2420 W 14th St",
    "sg:city": "Cleveland",
    "sg:classifiers": [
      {
        "category": "Organizations",
        "subcategory": "Religious Organization",
        "type": "Services"
      }
    ],
    "sg:phone": "+1 216 861 2177",
    "sg:postcode": "44113",
    "sg:province": "OH",
    "sg:tags": [
      "church"
    ],
    "wof:name": "Holy Ghost Byzantine Catholic",
    "wof:placetype": "venue"
  },
  "geometry": {"coordinates":[-81.691415,41.478857],"type":"Point"}
}
