{
  "type": "Feature",
  "properties": {
    "addr:full": "839 E 5th St Marysville OH 43040",
    "addr:housenumber": "839",
    "addr:postcode": "43040",
    "addr:street": "E 5Th St",
    "iso:country": "US",
    "sg:address": "839 E 5th St",
    "sg:city": "Marysville",
    "sg:classifiers": [
      {
        "category": "Shopping",
        "subcategory": "Computers \u0026 Home Electronics",
        "type": "Retail Goods"
      }
    ],
    "sg:phone": "+1 937 642 7585",
    "sg:postcode": "43040",
    "sg:province": "OH",
    "wof:name": "Marysville Supply",
    "wof:placetype": "venue"
  },
  "geometry": {"coordinates":[-83.355802,40.235606],"type":"Point"}
}
