{
  "type": "Feature",
  "properties": {
    "addr:full":"4849 N Twp Rd 175 Republic OH 44867",
    "addr:housenumber":"4849;175",
    "addr:postcode":"44867",
    "addr:street":"N Twp Rd",
    "iso:country":"US",
    "sg:address":"4849 N Twp Rd 175",
    "sg:city":"Republic",
    "sg:phone":"+1 419 639 2146",
    "sg:postcode":"44867",
    "sg:province":"OH",
    "sg:tags":[
        "hog",
        "wheat",
        "farm",
        "corn",
        "soybean",
        "or",
        "feedlot"
    ],
    "wof:name":"Beckman Farms",
    "wof:placetype":"venue"
},
  "geometry": {"coordinates":[-83.033901,41.196056],"type":"Point"}
}