{
  "type": "Feature",
  "properties": {
    "iso:country":"US",
    "sg:address":"1620 Stringtown Rd",
    "sg:city":"Grove City",
    "sg:classifiers":[
        {
            "category":"Restaurant",
            "type":"Food & Drink"
        }
    ],
    "sg:phone":"+1 614 871 2546",
    "sg:postcode":"43123",
    "sg:province":"OH",
    "sg:tags":[
        "eating"
    ],
    "wof:name":"White Castle",
    "wof:placetype":"venue"
},
  "geometry": {"coordinates":[-83.03783,39.878145],"type":"Point"}
}