{
  "type": "Feature",
  "properties": {
    "addr:full": "1620 Stringtown Rd Grove City OH 43123",
    "addr:housenumber": "1620",
    "addr:postcode": "43123",
    "addr:street": "Stringtown Rd",
    "iso:country": "US",
    "sg:address": "1620 Stringtown Rd",
    "sg:city": "Grove City",
    "sg:classifiers": [
      {
        "category": "Restaurant",
        "type": "Food \u0026 Drink"
      }
    ],
    "sg:phone": "+1 614 871 2546",
    "sg:postcode": "43123",
    "sg:province": "OH",
    "sg:tags": [
      "eating"
    ],
    "wof:name": "White Castle",
    "wof:placetype": "venue"
  },
  "geometry": {"coordinates":[-83.03783,39.878145],"type":"Point"}
}
