{
  "type": "Feature",
  "properties": {
    "addr:full": "3812 Pearl Rd Medina OH 44256",
    "addr:housenumber": "3812",
    "addr:postcode": "44256",
    "addr:street": "Pearl Rd",
    "iso:country": "US",
    "sg:address": "3812 Pearl Rd",
    "sg:city": "Medina",
    "sg:classifiers": [
      {
        "category": "Professional",
        "type": "Services"
      }
    ],
    "sg:phone": "+1 330 723 8044",
    "sg:postcode": "44256",
    "sg:province": "OH",
    "sg:tags": [
      "establishment"
    ],
    "wof:name": "Maven Marketing",
    "wof:placetype": "venue"
  },
  "geometry": {"coordinates":[-81.859017,41.172732],"type":"Point"}
}
