{
  "type": "Feature",
  "properties": {
    "iso:country":"US",
    "sg:address":"3812 Pearl Rd",
    "sg:city":"Medina",
    "sg:classifiers":[
        {
            "category":"Professional",
            "type":"Services"
        }
    ],
    "sg:phone":"+1 330 723 8044",
    "sg:postcode":"44256",
    "sg:province":"OH",
    "sg:tags":[
        "establishment"
    ],
    "wof:name":"Maven Marketing",
    "wof:placetype":"venue"
},
  "geometry": {"coordinates":[-81.859017,41.172732],"type":"Point"}
}