{
  "type": "Feature",
  "properties": {
    "addr:full":"604 Dixie Hwy Rossford OH 43460",
    "addr:housenumber":"604",
    "addr:postcode":"43460",
    "addr:street":"Dixie Hwy",
    "iso:country":"US",
    "sg:address":"604 Dixie Hwy",
    "sg:city":"Rossford",
    "sg:classifiers":[
        {
            "category":"Organizations",
            "subcategory":"Religious Organization",
            "type":"Services"
        }
    ],
    "sg:phone":"+1 419 661 2772",
    "sg:postcode":"43460",
    "sg:province":"OH",
    "sg:tags":[
        "church"
    ],
    "wof:name":"Victory Baptist Church",
    "wof:placetype":"venue"
},
  "geometry": {"coordinates":[-83.55811199999999,41.610668],"type":"Point"}
}