{
  "type": "Feature",
  "properties": {
    "addr:full":"2400 Port Clinton Rd Fremont OH 43420",
    "addr:housenumber":"2400",
    "addr:postcode":"43420",
    "addr:street":"Port Clinton Rd",
    "iso:country":"US",
    "sg:address":"2400 Port Clinton Rd",
    "sg:city":"Fremont",
    "sg:classifiers":[
        {
            "category":"Real Estate",
            "subcategory":"Real Estate Operator",
            "type":"Services"
        }
    ],
    "sg:phone":"+1 419 332 1920",
    "sg:postcode":"43420",
    "sg:province":"OH",
    "sg:tags":[
        "mobile",
        "home",
        "park"
    ],
    "wof:name":"Riviera Mobile Manor",
    "wof:placetype":"venue"
},
  "geometry": {"coordinates":[-83.105574,41.379406],"type":"Point"}
}