{
  "type": "Feature",
  "properties": {
    "addr:full": "1150 W 8th St Ste 110 Cincinnati OH 45203",
    "addr:housenumber": "1150",
    "addr:postcode": "45203",
    "addr:street": "W 8Th St Ste 110",
    "iso:country": "US",
    "sg:address": "1150 W 8th St Ste 110",
    "sg:city": "Cincinnati",
    "sg:classifiers": [
      {
        "category": "Transit Center",
        "subcategory": "Freight",
        "type": "Transportation"
      },
      {
        "category": "Freight",
        "type": "Transportation"
      },
      {
        "category": "Government",
        "subcategory": "Post Office",
        "type": "Public Place"
      }
    ],
    "sg:phone": "+1 513 961 2444",
    "sg:postcode": "45203",
    "sg:province": "OH",
    "sg:tags": [
      "delivery",
      "local",
      "trucking-motor",
      "courier",
      "trucking"
    ],
    "wof:name": "United Couriers Inc",
    "wof:placetype": "venue"
  },
  "geometry": {"coordinates":[-84.535898,39.104141],"type":"Point"}
}
