{
  "type": "Feature",
  "properties": {
    "addr:full": "1455 Industrial Pkwy Akron OH 44310",
    "addr:housenumber": "1455",
    "addr:postcode": "44310",
    "addr:street": "Industrial Pkwy",
    "iso:country": "US",
    "sg:address": "1455 Industrial Pkwy",
    "sg:city": "Akron",
    "sg:classifiers": [
      {
        "category": "Retail",
        "subcategory": "Auto Repair",
        "type": "Services"
      }
    ],
    "sg:phone": "+1 330 633 2113",
    "sg:postcode": "44310",
    "sg:province": "OH",
    "sg:tags": [
      "repairing",
      "automobile"
    ],
    "wof:name": "Bent Wrench Auto Svc",
    "wof:placetype": "venue"
  },
  "geometry": {"coordinates":[-81.480229,41.10605],"type":"Point"}
}
