{
  "type": "Feature",
  "properties": {
    "iso:country":"US",
    "sg:address":"1455 Industrial Pkwy",
    "sg:city":"Akron",
    "sg:classifiers":[
        {
            "category":"Retail",
            "subcategory":"Auto Repair",
            "type":"Services"
        }
    ],
    "sg:phone":"+1 330 633 2113",
    "sg:postcode":"44310",
    "sg:province":"OH",
    "sg:tags":[
        "repairing",
        "automobile"
    ],
    "wof:name":"Bent Wrench Auto Svc",
    "wof:placetype":"venue"
},
  "geometry": {"coordinates":[-81.48022899999999,41.10605],"type":"Point"}
}