{
  "type": "Feature",
  "properties": {
    "iso:country":"US",
    "sg:address":"3415 E US Rte 36",
    "sg:city":"Piqua",
    "sg:classifiers":[
        {
            "category":"Manufacturing",
            "subcategory":"Tools & Machinery",
            "type":"Manufacturing & Wholesale Goods"
        }
    ],
    "sg:phone":"+1 937 368 2391",
    "sg:postcode":"45356",
    "sg:province":"OH",
    "sg:tags":[
        "machine",
        "shop",
        "job"
    ],
    "wof:name":"Clark Machine & Tool Co",
    "wof:placetype":"venue"
},
  "geometry": {"coordinates":[-84.139593,40.14659],"type":"Point"}
}