{
  "type": "Feature",
  "properties": {
    "addr:full": "3415 E US Rte 36 Piqua OH 45356",
    "addr:housenumber": "3415",
    "addr:postcode": "45356",
    "addr:street": "E Us Rte 36",
    "iso:country": "US",
    "sg:address": "3415 E US Rte 36",
    "sg:city": "Piqua",
    "sg:classifiers": [
      {
        "category": "Manufacturing",
        "subcategory": "Tools \u0026 Machinery",
        "type": "Manufacturing \u0026 Wholesale Goods"
      }
    ],
    "sg:phone": "+1 937 368 2391",
    "sg:postcode": "45356",
    "sg:province": "OH",
    "sg:tags": [
      "machine",
      "shop",
      "job"
    ],
    "wof:name": "Clark Machine \u0026 Tool Co",
    "wof:placetype": "venue"
  },
  "geometry": {"coordinates":[-84.139593,40.14659],"type":"Point"}
}
