{
  "type": "Feature",
  "properties": {
    "addr:full": "250 E 5th St Cincinnati OH 45202",
    "addr:housenumber": "250",
    "addr:postcode": "45202",
    "addr:street": "E 5Th St",
    "iso:country": "US",
    "sg:address": "250 E 5th St",
    "sg:city": "Cincinnati",
    "sg:classifiers": [
      {
        "category": "Building \u0026 Trades",
        "subcategory": "Cleaning \u0026 Sanitation",
        "type": "Services"
      }
    ],
    "sg:phone": "+1 513 241 4068",
    "sg:postcode": "45202",
    "sg:province": "OH",
    "sg:tags": [
      "janitor"
    ],
    "wof:name": "Unicco",
    "wof:placetype": "venue"
  },
  "geometry": {"coordinates":[-84.508324,39.101923],"type":"Point"}
}
