{
  "type": "Feature",
  "properties": {
    "addr:full": "608 Co Rd 78 Mount Cory OH 45868",
    "addr:housenumber": "608;78",
    "addr:postcode": "45868",
    "addr:street": "Co Rd;Mount",
    "iso:country": "US",
    "sg:address": "608 Co Rd 78",
    "sg:city": "Mount Cory",
    "sg:phone": "+1 419 859 3579",
    "sg:postcode": "45868",
    "sg:province": "OH",
    "sg:tags": [
      "farm",
      "soybean"
    ],
    "wof:name": "Carl Lieb",
    "wof:placetype": "venue"
  },
  "geometry": {"coordinates":[-83.873143,40.993266],"type":"Point"}
}
