{
  "type": "Feature",
  "properties": {
    "iso:country":"US",
    "sg:address":"158 N Broadway St",
    "sg:city":"New Philadelphia",
    "sg:classifiers":[
        {
            "category":"Real Estate",
            "subcategory":"Real Estate Services",
            "type":"Services"
        }
    ],
    "sg:phone":"+1 330 343 9870",
    "sg:postcode":"44663",
    "sg:province":"OH",
    "sg:tags":[
        "company",
        "title"
    ],
    "wof:name":"Alpha Land Title Agency",
    "wof:placetype":"venue"
},
  "geometry": {"coordinates":[-81.44517399999999,40.491159],"type":"Point"}
}