{
  "type": "Feature",
  "properties": {
    "addr:full": "158 N Broadway St New Philadelphia OH 44663",
    "addr:housenumber": "158",
    "addr:postcode": "44663",
    "addr:street": "N Broadway St",
    "iso:country": "US",
    "sg:address": "158 N Broadway St",
    "sg:city": "New Philadelphia",
    "sg:classifiers": [
      {
        "category": "Real Estate",
        "subcategory": "Real Estate Services",
        "type": "Services"
      }
    ],
    "sg:phone": "+1 330 343 9870",
    "sg:postcode": "44663",
    "sg:province": "OH",
    "sg:tags": [
      "company",
      "title"
    ],
    "wof:name": "Alpha Land Title Agency",
    "wof:placetype": "venue"
  },
  "geometry": {"coordinates":[-81.445174,40.491159],"type":"Point"}
}
