{
  "type": "Feature",
  "properties": {
    "addr:full": "501 N Main St Findlay OH 45840",
    "addr:housenumber": "501",
    "addr:postcode": "45840",
    "addr:street": "N Main St",
    "iso:country": "US",
    "sg:address": "501 N Main St",
    "sg:city": "Findlay",
    "sg:classifiers": [
      {
        "category": "Health Services",
        "subcategory": "Doctor",
        "type": "Services"
      }
    ],
    "sg:phone": "+1 419 422 6635",
    "sg:postcode": "45840",
    "sg:province": "OH",
    "sg:tags": [
      "medical"
    ],
    "wof:name": "Findlay Radiology Associates",
    "wof:placetype": "venue"
  },
  "geometry": {"coordinates":[-83.650123,41.048078],"type":"Point"}
}
