{
  "type": "Feature",
  "properties": {
    "addr:full": "356 Cheryl Ln Marion OH 43302",
    "addr:housenumber": "356",
    "addr:postcode": "43302",
    "addr:street": "Cheryl Ln",
    "iso:country": "US",
    "sg:address": "356 Cheryl Ln",
    "sg:city": "Marion",
    "sg:classifiers": [
      {
        "category": "Home \u0026 Garden",
        "subcategory": "Building Materials",
        "type": "Retail Goods"
      }
    ],
    "sg:phone": "+1 740 389 6688",
    "sg:postcode": "43302",
    "sg:province": "OH",
    "sg:tags": [
      "equipment",
      "electric",
      "supply"
    ],
    "wof:name": "Emerson Electric Co",
    "wof:placetype": "venue"
  },
  "geometry": {"coordinates":[-83.06953,40.587909],"type":"Point"}
}
