{
  "type": "Feature",
  "properties": {
    "addr:full": "6322 Century City S Reynoldsburg OH 43068",
    "addr:housenumber": "6322",
    "addr:postcode": "43068",
    "addr:street": "Century;S",
    "iso:country": "US",
    "sg:address": "6322 Century City S",
    "sg:city": "Reynoldsburg",
    "sg:classifiers": [
      {
        "category": "Home \u0026 Garden",
        "subcategory": "Hardware",
        "type": "Retail Goods"
      }
    ],
    "sg:phone": "+1 614 864 3944",
    "sg:postcode": "43068",
    "sg:province": "OH",
    "wof:name": "Value Marketing",
    "wof:placetype": "venue"
  },
  "geometry": {"coordinates":[-82.829672,39.94437],"type":"Point"}
}
