{
  "type": "Feature",
  "properties": {
    "addr:full": "68 S Main St Mansfield OH 44902",
    "addr:housenumber": "68",
    "addr:postcode": "44902",
    "addr:street": "S Main St",
    "iso:country": "US",
    "sg:address": "68 S Main St",
    "sg:city": "Mansfield",
    "sg:classifiers": [
      {
        "category": "Government",
        "subcategory": "Office",
        "type": "Public Place"
      }
    ],
    "sg:phone": "+1 419 774 5822",
    "sg:postcode": "44902",
    "sg:province": "OH",
    "sg:tags": [
      "executive"
    ],
    "wof:name": "Richland County Veterans Svc",
    "wof:placetype": "venue"
  },
  "geometry": {"coordinates":[-82.515829,40.756372],"type":"Point"}
}
