{
  "type": "Feature",
  "properties": {
    "iso:country":"US",
    "sg:address":"105 Hoffman Ave",
    "sg:city":"Lebanon",
    "sg:classifiers":[
        {
            "category":"Building & Trades",
            "subcategory":"Construction",
            "type":"Services"
        }
    ],
    "sg:phone":"+1 513 932 6620",
    "sg:postcode":"45036",
    "sg:province":"OH",
    "sg:tags":[
        "house"
    ],
    "wof:name":"Roy Turner Construction",
    "wof:placetype":"venue"
},
  "geometry": {"coordinates":[-84.199135,39.475161],"type":"Point"}
}