{
  "type": "Feature",
  "properties": {
    "addr:full": "731 E Broad St Columbus OH 43205",
    "addr:housenumber": "731",
    "addr:postcode": "43205",
    "addr:street": "E Broad St",
    "iso:country": "US",
    "sg:address": "731 E Broad St",
    "sg:city": "Columbus",
    "sg:classifiers": [
      {
        "category": "Social Services",
        "type": "Services"
      }
    ],
    "sg:phone": "+1 614 239 7788",
    "sg:postcode": "43205",
    "sg:province": "OH",
    "sg:tags": [
      "organization",
      "welfare"
    ],
    "wof:name": "TEACH",
    "wof:placetype": "venue"
  },
  "geometry": {"coordinates":[-82.980533,39.964444],"type":"Point"}
}
