{
  "type": "Feature",
  "properties": {
    "addr:full": "2750 Mahoning Ave NW Warren OH 44483",
    "addr:housenumber": "2750",
    "addr:postcode": "44483",
    "addr:street": "Mahoning Ave Nw",
    "iso:country": "US",
    "sg:address": "2750 Mahoning Ave NW",
    "sg:city": "Warren",
    "sg:classifiers": [
      {
        "category": "Banks \u0026 Credit Unions",
        "subcategory": "Bank",
        "type": "Services"
      }
    ],
    "sg:phone": "+1 330 399 2050",
    "sg:postcode": "44483",
    "sg:province": "OH",
    "sg:tags": [
      "cashing",
      "personal",
      "check",
      "institution"
    ],
    "wof:name": "Advance America",
    "wof:placetype": "venue"
  },
  "geometry": {"coordinates":[-80.833514,41.259757],"type":"Point"}
}
