{
  "type": "Feature",
  "properties": {
    "iso:country":"US",
    "sg:address":"2750 Mahoning Ave NW",
    "sg:city":"Warren",
    "sg:classifiers":[
        {
            "category":"Banks & Credit Unions",
            "subcategory":"Bank",
            "type":"Services"
        }
    ],
    "sg:phone":"+1 330 399 2050",
    "sg:postcode":"44483",
    "sg:province":"OH",
    "sg:tags":[
        "cashing",
        "personal",
        "check",
        "institution"
    ],
    "wof:name":"Advance America",
    "wof:placetype":"venue"
},
  "geometry": {"coordinates":[-80.83351399999999,41.259757],"type":"Point"}
}