{
  "type": "Feature",
  "properties": {
    "addr:full": "5080 Sour Run Rd Wellston OH 45692",
    "addr:housenumber": "5080",
    "addr:postcode": "45692",
    "addr:street": "Sour Run Rd",
    "iso:country": "US",
    "sg:address": "5080 Sour Run Rd",
    "sg:city": "Wellston",
    "sg:classifiers": [
      {
        "category": "Taxi",
        "type": "Transportation"
      }
    ],
    "sg:phone": "+1 740 288 1325",
    "sg:postcode": "45692",
    "sg:province": "OH",
    "sg:tags": [
      "taxicab"
    ],
    "wof:name": "Kinser Taxidermy",
    "wof:placetype": "venue"
  },
  "geometry": {"coordinates":[-82.637296,39.127603],"type":"Point"}
}
