{
  "type": "Feature",
  "properties": {
    "iso:country":"US",
    "sg:address":"960 Graham Rd",
    "sg:city":"Cuyahoga Falls",
    "sg:classifiers":[
        {
            "category":"Health Services",
            "subcategory":"Doctor",
            "type":"Services"
        }
    ],
    "sg:phone":"+1 330 923 0408",
    "sg:postcode":"44221",
    "sg:province":"OH",
    "sg:tags":[
        "physician",
        "surgeon"
    ],
    "wof:name":"Elizabeth Snoderly DO",
    "wof:placetype":"venue"
},
  "geometry": {"coordinates":[-81.47808999999999,41.163588],"type":"Point"}
}