{
  "type": "Feature",
  "properties": {
    "iso:country":"US",
    "sg:address":"1026 Franklin Ave",
    "sg:city":"Salem",
    "sg:classifiers":[
        {
            "category":"Professional",
            "type":"Services"
        }
    ],
    "sg:phone":"+1 330 332 4660",
    "sg:postcode":"44460",
    "sg:province":"OH",
    "sg:tags":[
        "establishment"
    ],
    "wof:name":"Herron Transfer Co",
    "wof:placetype":"venue"
},
  "geometry": {"coordinates":[-80.84305999999999,40.892817],"type":"Point"}
}