{
  "type": "Feature",
  "properties": {
    "iso:country":"US",
    "sg:address":"222 E Park Dr",
    "sg:city":"Greenville",
    "sg:classifiers":[
        {
            "category":"Real Estate",
            "subcategory":"Real Estate Agent",
            "type":"Services"
        }
    ],
    "sg:phone":"+1 937 548 5026",
    "sg:postcode":"45331",
    "sg:province":"OH",
    "wof:name":"John Myers Realty",
    "wof:placetype":"venue"
},
  "geometry": {"coordinates":[-84.63574,40.110468],"type":"Point"}
}