{
  "type": "Feature",
  "properties": {
    "addr:full":"1503 W Broad St Columbus OH 43222",
    "addr:housenumber":"1503",
    "addr:postcode":"43222",
    "addr:street":"W Broad St",
    "iso:country":"US",
    "sg:address":"1503 W Broad St",
    "sg:city":"Columbus",
    "sg:classifiers":[
        {
            "category":"Restaurant",
            "type":"Food & Drink"
        }
    ],
    "sg:menulink":"http://www.allmenus.com/oh/columbus/134172-subway/menu/",
    "sg:phone":"+1 614 484 0051",
    "sg:postcode":"43222",
    "sg:province":"OH",
    "sg:tags":[
        "american",
        "sandwich"
    ],
    "wof:name":"Subway",
    "wof:placetype":"venue"
},
  "geometry": {"coordinates":[-83.04005600000001,39.956809],"type":"Point"}
}