{
  "type": "Feature",
  "properties": {
    "addr:full":"611 Front St Rockford OH 45882",
    "addr:housenumber":"611",
    "addr:postcode":"45882",
    "addr:street":"Front St",
    "iso:country":"US",
    "sg:address":"611 Front St",
    "sg:city":"Rockford",
    "sg:classifiers":[
        {
            "category":"Organizations",
            "subcategory":"Professional Association",
            "type":"Services"
        }
    ],
    "sg:phone":"+1 419 363 2002",
    "sg:postcode":"45882",
    "sg:province":"OH",
    "wof:name":"Rockford Recreational Assn",
    "wof:placetype":"venue"
},
  "geometry": {"coordinates":[-84.653187,40.693606],"type":"Point"}
}