{
  "type": "Feature",
  "properties": {
    "addr:full": "3081 Cross Rd Winchester OH 45697",
    "addr:housenumber": "3081",
    "addr:postcode": "45697",
    "addr:street": "Cross Rd",
    "iso:country": "US",
    "sg:address": "3081 Cross Rd",
    "sg:city": "Winchester",
    "sg:classifiers": [
      {
        "category": "Farming",
        "subcategory": "Livestock Farm",
        "type": "Manufacturing \u0026 Wholesale Goods"
      }
    ],
    "sg:phone": "+1 937 544 5362",
    "sg:postcode": "45697",
    "sg:province": "OH",
    "sg:tags": [
      "horse",
      "other",
      "equine"
    ],
    "wof:name": "Runway Stables",
    "wof:placetype": "venue"
  },
  "geometry": {"coordinates":[-83.566055,38.854975],"type":"Point"}
}
