{
  "type": "Feature",
  "properties": {
    "iso:country":"US",
    "sg:address":"317 Pleasant St",
    "sg:city":"Ashland",
    "sg:classifiers":[
        {
            "category":"Banks & Credit Unions",
            "subcategory":"Investment Brokerage",
            "type":"Services"
        }
    ],
    "sg:phone":"+1 419 207 1779",
    "sg:postcode":"44805",
    "sg:province":"OH",
    "sg:tags":[
        "advisory"
    ],
    "wof:name":"Financial Educational LLC",
    "wof:placetype":"venue"
},
  "geometry": {"coordinates":[-82.320241,40.872555],"type":"Point"}
}