{
  "type": "Feature",
  "properties": {
    "addr:full": "317 Pleasant St Ashland OH 44805",
    "addr:housenumber": "317",
    "addr:postcode": "44805",
    "addr:street": "Pleasant St",
    "iso:country": "US",
    "sg:address": "317 Pleasant St",
    "sg:city": "Ashland",
    "sg:classifiers": [
      {
        "category": "Banks \u0026 Credit Unions",
        "subcategory": "Investment Brokerage",
        "type": "Services"
      }
    ],
    "sg:phone": "+1 419 207 1779",
    "sg:postcode": "44805",
    "sg:province": "OH",
    "sg:tags": [
      "advisory"
    ],
    "wof:name": "Financial Educational LLC",
    "wof:placetype": "venue"
  },
  "geometry": {"coordinates":[-82.320241,40.872555],"type":"Point"}
}
