{
  "type": "Feature",
  "properties": {
    "iso:country":"US",
    "sg:address":"930 Trailwood Dr",
    "sg:city":"Boardman",
    "sg:classifiers":[
        {
            "category":"Banks & Credit Unions",
            "subcategory":"Investment Brokerage",
            "type":"Services"
        }
    ],
    "sg:phone":"+1 330 758 5626",
    "sg:postcode":"44512",
    "sg:province":"OH",
    "sg:tags":[
        "advisory",
        "financial"
    ],
    "wof:name":"Adelphia Financial",
    "wof:placetype":"venue"
},
  "geometry": {"coordinates":[-80.642764,41.027499],"type":"Point"}
}