{
  "type": "Feature",
  "properties": {
    "addr:full":"1771 Coventry Rd Cleveland OH 44118",
    "addr:housenumber":"1771",
    "addr:postcode":"44118",
    "addr:street":"Coventry Rd",
    "iso:country":"US",
    "sg:address":"1771 Coventry Rd",
    "sg:city":"Cleveland",
    "sg:classifiers":[
        {
            "category":"Shopping",
            "subcategory":"Used Merchandise",
            "type":"Retail Goods"
        }
    ],
    "sg:phone":"+1 216 321 2515",
    "sg:postcode":"44118",
    "sg:province":"OH",
    "sg:tags":[
        "antique",
        "book"
    ],
    "wof:name":"Attenson Antiques and Books",
    "wof:placetype":"venue"
},
  "geometry": {"coordinates":[-81.579903,41.511239],"type":"Point"}
}