{
  "type": "Feature",
  "properties": {
    "iso:country":"US",
    "sg:address":"1607 Cherrybend Rd",
    "sg:city":"Wilmington",
    "sg:classifiers":[
        {
            "category":"Farming",
            "subcategory":"Farm",
            "type":"Manufacturing & Wholesale Goods"
        }
    ],
    "sg:phone":"+1 937 584 2636",
    "sg:postcode":"45177",
    "sg:province":"OH",
    "sg:tags":[
        "crop",
        "general"
    ],
    "wof:name":"Wayne R Ellis",
    "wof:placetype":"venue"
},
  "geometry": {"coordinates":[-83.712319,39.451105],"type":"Point"}
}