{
  "type": "Feature",
  "properties": {
    "iso:country":"US",
    "sg:address":"6310 Este Ave",
    "sg:city":"Cincinnati",
    "sg:classifiers":[
        {
            "category":"Manufacturing",
            "subcategory":"Printing",
            "type":"Manufacturing & Wholesale Goods"
        }
    ],
    "sg:phone":"+1 513 563 1112",
    "sg:postcode":"45232",
    "sg:province":"OH",
    "sg:tags":[
        "packaging",
        "commercial",
        "mfg"
    ],
    "wof:name":"Zech Printing Industries Inc",
    "wof:placetype":"venue"
},
  "geometry": {"coordinates":[-84.492626,39.192138],"type":"Point"}
}