{
  "type": "Feature",
  "properties": {
    "addr:full":"1000 Market St Cincinnati OH 45215",
    "addr:housenumber":"1000",
    "addr:postcode":"45215",
    "addr:street":"Market St",
    "iso:country":"US",
    "sg:address":"1000 Market St",
    "sg:city":"Cincinnati",
    "sg:classifiers":[
        {
            "category":"Government",
            "subcategory":"Fire Station",
            "type":"Public Place"
        },
        {
            "category":"Government",
            "subcategory":"Office",
            "type":"Public Place"
        }
    ],
    "sg:phone":"+1 513 733 4044",
    "sg:postcode":"45215",
    "sg:province":"OH",
    "sg:tags":[
        "department",
        "township",
        "protection",
        "government-city",
        "village"
    ],
    "sg:website":"http://www.readingohio.org",
    "wof:name":"Reading Ohio City",
    "wof:placetype":"venue"
},
  "geometry": {"coordinates":[-84.44193300000001,39.223789],"type":"Point"}
}