{
  "type": "Feature",
  "properties": {
    "addr:full":"2413 Gilbert Ave Cincinnati OH 45206",
    "addr:housenumber":"2413",
    "addr:postcode":"45206",
    "addr:street":"Gilbert Ave",
    "iso:country":"US",
    "sg:address":"2413 Gilbert Ave",
    "sg:city":"Cincinnati",
    "sg:classifiers":[
        {
            "category":"Personal",
            "subcategory":"Beauty Salon",
            "type":"Services"
        }
    ],
    "sg:phone":"+1 513 721 6648",
    "sg:postcode":"45206",
    "sg:province":"OH",
    "wof:name":"Dot's Beauty Salon",
    "wof:placetype":"venue"
},
  "geometry": {"coordinates":[-84.49103599999999,39.124808],"type":"Point"}
}