{
  "type": "Feature",
  "properties": {
    "addr:full":"8989 Co Rd 84 Findlay OH 45840",
    "addr:housenumber":"8989;84",
    "addr:postcode":"45840",
    "addr:street":"Co Rd",
    "iso:country":"US",
    "sg:address":"8989 Co Rd 84",
    "sg:city":"Findlay",
    "sg:classifiers":[
        {
            "category":"Home & Garden",
            "subcategory":"Garden Supply",
            "type":"Retail Goods"
        }
    ],
    "sg:phone":"+1 419 859 2133",
    "sg:postcode":"45840",
    "sg:province":"OH",
    "sg:tags":[
        "bulb",
        "seed"
    ],
    "sg:website":"www.roysterclark.com",
    "wof:name":"ROYSTER Clark Inc",
    "wof:placetype":"venue"
},
  "geometry": {"coordinates":[-83.711561,41.007992],"type":"Point"}
}