{
  "type": "Feature",
  "properties": {
    "iso:country":"US",
    "sg:address":"1664 N Main St",
    "sg:city":"Canton",
    "sg:classifiers":[
        {
            "category":"Banks & Credit Unions",
            "subcategory":"Bank",
            "type":"Services"
        }
    ],
    "sg:phone":"+1 330 966 9170",
    "sg:postcode":"44720",
    "sg:province":"OH",
    "sg:tags":[
        "personal",
        "institution"
    ],
    "wof:name":"Beneficial",
    "wof:placetype":"venue"
},
  "geometry": {"coordinates":[-81.406145,40.897654],"type":"Point"}
}