{
  "type": "Feature",
  "properties": {
    "addr:full": "1664 N Main St Canton OH 44720",
    "addr:housenumber": "1664",
    "addr:postcode": "44720",
    "addr:street": "N Main St",
    "iso:country": "US",
    "sg:address": "1664 N Main St",
    "sg:city": "Canton",
    "sg:classifiers": [
      {
        "category": "Banks \u0026 Credit Unions",
        "subcategory": "Bank",
        "type": "Services"
      }
    ],
    "sg:phone": "+1 330 966 9170",
    "sg:postcode": "44720",
    "sg:province": "OH",
    "sg:tags": [
      "personal",
      "institution"
    ],
    "wof:name": "Beneficial",
    "wof:placetype": "venue"
  },
  "geometry": {"coordinates":[-81.406145,40.897654],"type":"Point"}
}
