{
  "type": "Feature",
  "properties": {
    "addr:full":"100 N Main St Mt Vernon OH 43050",
    "addr:housenumber":"100",
    "addr:postcode":"43050",
    "addr:street":"N Main St",
    "iso:country":"US",
    "sg:address":"100 N Main St",
    "sg:city":"Mt Vernon",
    "sg:classifiers":[
        {
            "category":"Professional",
            "subcategory":"Lawyer & Legal Services",
            "type":"Services"
        }
    ],
    "sg:phone":"+1 740 393 2788",
    "sg:postcode":"43050",
    "sg:province":"OH",
    "sg:tags":[
        "attorney"
    ],
    "wof:name":"Phillip D Lehmkuhl",
    "wof:placetype":"venue"
},
  "geometry": {"coordinates":[-82.485297,40.395303],"type":"Point"}
}