{
  "type": "Feature",
  "properties": {
    "iso:country":"US",
    "sg:address":"909 Morse Rd",
    "sg:city":"Columbus",
    "sg:classifiers":[
        {
            "category":"Professional",
            "subcategory":"Research",
            "type":"Services"
        }
    ],
    "sg:phone":"+1 614 261 0470",
    "sg:postcode":"43229",
    "sg:province":"OH",
    "sg:tags":[
        "medical"
    ],
    "wof:name":"Premier Medical Care",
    "wof:placetype":"venue"
},
  "geometry": {"coordinates":[-82.995294,40.061423],"type":"Point"}
}