{
  "type": "Feature",
  "properties": {
    "addr:full": "1980 Britains Ln Columbus OH 43224",
    "addr:housenumber": "1980",
    "addr:postcode": "43224",
    "addr:street": "Britains Ln",
    "iso:country": "US",
    "sg:address": "1980 Britains Ln",
    "sg:city": "Columbus",
    "sg:classifiers": [
      {
        "category": "Home \u0026 Garden",
        "subcategory": "Building Materials",
        "type": "Retail Goods"
      }
    ],
    "sg:phone": "+1 614 263 6007",
    "sg:postcode": "43224",
    "sg:province": "OH",
    "wof:name": "Don Gearon Countertops \u0026 Decor",
    "wof:placetype": "venue"
  },
  "geometry": {"coordinates":[-82.961676,40.034518],"type":"Point"}
}
