{
  "type": "Feature",
  "properties": {
    "addr:full": "2300 Old State Rte 32 Batavia OH 45103",
    "addr:housenumber": "2300",
    "addr:postcode": "45103",
    "addr:street": "Old State Rte 32",
    "iso:country": "US",
    "sg:address": "2300 Old State Rte 32",
    "sg:city": "Batavia",
    "sg:classifiers": [
      {
        "category": "Organizations",
        "subcategory": "Religious Organization",
        "type": "Services"
      }
    ],
    "sg:phone": "+1 513 735 4228",
    "sg:postcode": "45103",
    "sg:province": "OH",
    "sg:tags": [
      "church"
    ],
    "wof:name": "Real Life Assembly Of God",
    "wof:placetype": "venue"
  },
  "geometry": {"coordinates":[-84.143781,39.075858],"type":"Point"}
}
