{
  "type": "Feature",
  "properties": {
    "iso:country":"US",
    "sg:address":"17 E Tulane Rd",
    "sg:city":"Columbus",
    "sg:classifiers":[
        {
            "category":"Manufacturing",
            "subcategory":"Printing",
            "type":"Manufacturing & Wholesale Goods"
        }
    ],
    "sg:phone":"+1 614 268 0181",
    "sg:postcode":"43202",
    "sg:province":"OH",
    "sg:tags":[
        "lithographic",
        "printer",
        "commercial"
    ],
    "wof:name":"Reinhart Printing Company",
    "wof:placetype":"venue"
},
  "geometry": {"coordinates":[-83.011854,40.023164],"type":"Point"}
}