{
  "type": "Feature",
  "properties": {
    "iso:country":"US",
    "sg:address":"30 E Apple St",
    "sg:city":"Dayton",
    "sg:classifiers":[
        {
            "category":"Health Services",
            "subcategory":"Doctor",
            "type":"Services"
        }
    ],
    "sg:phone":"+1 937 208 2540",
    "sg:postcode":"45409",
    "sg:province":"OH",
    "sg:tags":[
        "physician",
        "surgeon"
    ],
    "wof:name":"Urology Associates",
    "wof:placetype":"venue"
},
  "geometry": {"coordinates":[-84.187198,39.746301],"type":"Point"}
}