{
  "type": "Feature",
  "properties": {
    "addr:full": "8837 Glen Abbey Ct Springboro OH 45066",
    "addr:housenumber": "8837",
    "addr:postcode": "45066",
    "addr:street": "Glen Abbey Ct",
    "iso:country": "US",
    "sg:address": "8837 Glen Abbey Ct",
    "sg:city": "Springboro",
    "sg:classifiers": [
      {
        "category": "Shopping",
        "subcategory": "Computers \u0026 Home Electronics",
        "type": "Retail Goods"
      }
    ],
    "sg:phone": "+1 937 748 0390",
    "sg:postcode": "45066",
    "sg:province": "OH",
    "sg:tags": [
      "software"
    ],
    "wof:name": "Harvard Softworks",
    "wof:placetype": "venue"
  },
  "geometry": {"coordinates":[-84.216609,39.570648],"type":"Point"}
}
