{
  "type": "Feature",
  "properties": {
    "iso:country":"US",
    "sg:address":"7710 Montgomery Rd",
    "sg:city":"Cincinnati",
    "sg:classifiers":[
        {
            "category":"Shopping",
            "subcategory":"Optical Goods",
            "type":"Retail Goods"
        }
    ],
    "sg:phone":"+1 513 791 5911",
    "sg:postcode":"45236",
    "sg:province":"OH",
    "sg:website":"www.svsvision.com",
    "wof:name":"SVS Vision",
    "wof:placetype":"venue"
},
  "geometry": {"coordinates":[-84.382149,39.198318],"type":"Point"}
}