{
  "type": "Feature",
  "properties": {
    "addr:full":"2421 Gideon Dr Middletown OH 45044",
    "addr:housenumber":"2421",
    "addr:postcode":"45044",
    "addr:street":"Gideon Dr",
    "iso:country":"US",
    "sg:address":"2421 Gideon Dr",
    "sg:city":"Middletown",
    "sg:classifiers":[
        {
            "category":"Building & Trades",
            "subcategory":"Plumbing",
            "type":"Services"
        }
    ],
    "sg:phone":"+1 513 423 3485",
    "sg:postcode":"45044",
    "sg:province":"OH",
    "sg:tags":[
        "plumbing",
        "on",
        "contractor",
        "site",
        "welding"
    ],
    "wof:name":"Sportelli Enterprises",
    "wof:placetype":"venue"
},
  "geometry": {"coordinates":[-84.327842,39.479162],"type":"Point"}
}