{
  "type": "Feature",
  "properties": {
    "iso:country":"US",
    "sg:address":"24000 Mercantile Rd",
    "sg:city":"Cleveland",
    "sg:classifiers":[
        {
            "category":"Education",
            "subcategory":"Dance Studio",
            "type":"Public Place"
        }
    ],
    "sg:phone":"+1 216 464 5959",
    "sg:postcode":"44122",
    "sg:province":"OH",
    "sg:tags":[
        "instruction",
        "dancing"
    ],
    "wof:name":"Morgenstern Dance Studios",
    "wof:placetype":"venue"
},
  "geometry": {"coordinates":[-81.504758,41.464476],"type":"Point"}
}