{
  "type": "Feature",
  "properties": {
    "iso:country":"US",
    "sg:address":"3313 Eldean Rd",
    "sg:city":"Covington",
    "sg:classifiers":[
        {
            "category":"Shopping",
            "subcategory":"Bicycles & Sporting Goods",
            "type":"Retail Goods"
        }
    ],
    "sg:phone":"+1 937 332 1939",
    "sg:postcode":"45318",
    "sg:province":"OH",
    "wof:name":"Family Bike Shop Inc",
    "wof:placetype":"venue"
},
  "geometry": {"coordinates":[-84.274418,40.075643],"type":"Point"}
}