{
  "type": "Feature",
  "properties": {
    "iso:country":"US",
    "sg:address":"525 Center Rd",
    "sg:city":"Cleveland",
    "sg:classifiers":[
        {
            "category":"Retail",
            "subcategory":"Repair Shop",
            "type":"Services"
        }
    ],
    "sg:phone":"+1 440 930 5117",
    "sg:postcode":"44146",
    "sg:province":"OH",
    "sg:tags":[
        "equipment",
        "printing"
    ],
    "wof:name":"North Coast Computers",
    "wof:placetype":"venue"
},
  "geometry": {"coordinates":[-81.5373,41.408615],"type":"Point"}
}