{
  "type": "Feature",
  "properties": {
    "iso:country":"US",
    "sg:address":"101 N Detroit St",
    "sg:city":"Xenia",
    "sg:classifiers":[
        {
            "category":"Government",
            "subcategory":"Office",
            "type":"Public Place"
        }
    ],
    "sg:phone":"+1 937 376 7305",
    "sg:postcode":"45385",
    "sg:province":"OH",
    "sg:tags":[
        "village"
    ],
    "wof:name":"Xenia City Solicitor",
    "wof:placetype":"venue"
},
  "geometry": {"coordinates":[-83.929536,39.686473],"type":"Point"}
}