{
  "type": "Feature",
  "properties": {
    "addr:full":"5646 Colgate Ave Youngstown OH 44515",
    "addr:housenumber":"5646",
    "addr:postcode":"44515",
    "addr:street":"Colgate Ave",
    "iso:country":"US",
    "sg:address":"5646 Colgate Ave",
    "sg:city":"Youngstown",
    "sg:classifiers":[
        {
            "category":"Professional",
            "subcategory":"Management & Consulting",
            "type":"Services"
        }
    ],
    "sg:phone":"+1 330 792 8242",
    "sg:postcode":"44515",
    "sg:province":"OH",
    "sg:tags":[
        "retail",
        "direct",
        "sales"
    ],
    "wof:name":"Always A Lady",
    "wof:placetype":"venue"
},
  "geometry": {"coordinates":[-80.769248,41.093433],"type":"Point"}
}