{
  "type": "Feature",
  "properties": {
    "iso:country":"US",
    "sg:address":"6835 Cochran Rd",
    "sg:city":"Cleveland",
    "sg:classifiers":[
        {
            "category":"Shopping",
            "subcategory":"Discount & Variety Stores",
            "type":"Retail Goods"
        }
    ],
    "sg:phone":"+1 440 519 0709",
    "sg:postcode":"44139",
    "sg:province":"OH",
    "sg:tags":[
        "merchandise",
        "general"
    ],
    "wof:name":"Chad Supply",
    "wof:placetype":"venue"
},
  "geometry": {"coordinates":[-81.469245,41.377051],"type":"Point"}
}