{
  "type": "Feature",
  "properties": {
    "iso:country":"US",
    "sg:address":"13975 Twp Rd 135",
    "sg:city":"Kenton",
    "sg:classifiers":[
        {
            "category":"Airport",
            "type":"Transportation"
        }
    ],
    "sg:phone":"+1 419 673 9542",
    "sg:postcode":"43326",
    "sg:province":"OH",
    "wof:name":"Hardin County Airport",
    "wof:placetype":"venue"
},
  "geometry": {"coordinates":[-83.651705,40.619424],"type":"Point"}
}