{
  "type": "Feature",
  "properties": {
    "iso:country":"US",
    "sg:address":"458 Glacierview Dr",
    "sg:city":"Youngstown",
    "sg:classifiers":[
        {
            "category":"Education",
            "subcategory":"Special Training",
            "type":"Public Place"
        }
    ],
    "sg:phone":"+1 330 779 3801",
    "sg:postcode":"44509",
    "sg:province":"OH",
    "sg:tags":[
        "instruction",
        "driving"
    ],
    "wof:name":"Step Ahead",
    "wof:placetype":"venue"
},
  "geometry": {"coordinates":[-80.679706,41.092755],"type":"Point"}
}