{
  "type": "Feature",
  "properties": {
    "addr:full":"116 Marion Rd Cincinnati OH 45215",
    "addr:housenumber":"116",
    "addr:postcode":"45215",
    "addr:street":"Marion Rd",
    "iso:country":"US",
    "sg:address":"116 Marion Rd",
    "sg:city":"Cincinnati",
    "sg:classifiers":[
        {
            "category":"Shopping",
            "subcategory":"Gifts & Souvenirs",
            "type":"Retail Goods"
        },
        {
            "category":"Building & Trades",
            "subcategory":"Equipment Rental",
            "type":"Services"
        }
    ],
    "sg:phone":"+1 513 772 1929",
    "sg:postcode":"45215",
    "sg:province":"OH",
    "sg:tags":[
        "party",
        "supply"
    ],
    "sg:website":"www.academyrentalsinc.com",
    "wof:name":"Academy Rentals Inc",
    "wof:placetype":"venue"
},
  "geometry": {"coordinates":[-84.46853,39.251912],"type":"Point"}
}