{
  "type": "Feature",
  "properties": {
    "addr:full":"13426 Foundation Rd Croton OH 43013",
    "addr:housenumber":"13426",
    "addr:postcode":"43013",
    "addr:street":"Foundation Rd",
    "iso:country":"US",
    "sg:address":"13426 Foundation Rd",
    "sg:city":"Croton",
    "sg:classifiers":[
        {
            "category":"Real Estate",
            "subcategory":"Real Estate Operator",
            "type":"Services"
        }
    ],
    "sg:phone":"+1 740 893 2426",
    "sg:postcode":"43013",
    "sg:province":"OH",
    "sg:tags":[
        "property",
        "lessor"
    ],
    "wof:name":"Gordon Potter",
    "wof:placetype":"venue"
},
  "geometry": {"coordinates":[-82.741322,40.245931],"type":"Point"}
}