{
  "type": "Feature",
  "properties": {
    "addr:full": "31809 Vine St Willowick OH 44095",
    "addr:housenumber": "31809",
    "addr:postcode": "44095",
    "addr:street": "Vine St",
    "iso:country": "US",
    "sg:address": "31809 Vine St",
    "sg:city": "Willowick",
    "sg:classifiers": [
      {
        "category": "Professional",
        "subcategory": "Lawyer \u0026 Legal Services",
        "type": "Services"
      }
    ],
    "sg:phone": "+1 440 585 1441",
    "sg:postcode": "44095",
    "sg:province": "OH",
    "sg:tags": [
      "attorney"
    ],
    "wof:name": "Stephen Komarjanski",
    "wof:placetype": "venue"
  },
  "geometry": {"coordinates":[-81.463788,41.642596],"type":"Point"}
}
