{
  "type": "Feature",
  "properties": {
    "addr:full": "17524 Harvard Ave E Cleveland OH 44128",
    "addr:housenumber": "17524",
    "addr:postcode": "44128",
    "addr:street": "Harvard Ave E",
    "iso:country": "US",
    "sg:address": "17524 Harvard Ave E",
    "sg:city": "Cleveland",
    "sg:classifiers": [
      {
        "category": "Personal",
        "subcategory": "Barber",
        "type": "Services"
      }
    ],
    "sg:phone": "+1 216 991 2071",
    "sg:postcode": "44128",
    "sg:province": "OH",
    "wof:name": "Lady C Barber Shop",
    "wof:placetype": "venue"
  },
  "geometry": {"coordinates":[-81.556884,41.449743],"type":"Point"}
}
