{
  "type": "Feature",
  "properties": {
    "iso:country":"US",
    "sg:address":"8127 Donovan Rd",
    "sg:city":"Ostrander",
    "sg:phone":"+1 740 595 3420",
    "sg:postcode":"43061",
    "sg:province":"OH",
    "sg:tags":[
        "farm",
        "corn",
        "wheat",
        "soybean"
    ],
    "wof:name":"Kenneth Cole",
    "wof:placetype":"venue"
},
  "geometry": {"coordinates":[-83.194363,40.361243],"type":"Point"}
}