{
  "type": "Feature",
  "properties": {
    "iso:country":"US",
    "sg:address":"542 E 12th St",
    "sg:city":"Cincinnati",
    "sg:classifiers":[
        {
            "category":"Manufacturing",
            "subcategory":"Printing",
            "type":"Manufacturing & Wholesale Goods"
        }
    ],
    "sg:phone":"+1 513 381 3221",
    "sg:postcode":"45202",
    "sg:province":"OH",
    "sg:tags":[
        "publishing"
    ],
    "wof:name":"Gallaher Multimedia Studio",
    "wof:placetype":"venue"
},
  "geometry": {"coordinates":[-84.50558100000001,39.110102],"type":"Point"}
}