{
  "type": "Feature",
  "properties": {
    "addr:full":"35 4th St Perrysburg OH 43551",
    "addr:housenumber":"35",
    "addr:postcode":"43551",
    "addr:street":"4Th St",
    "iso:country":"US",
    "sg:address":"35 4th St",
    "sg:city":"Perrysburg",
    "sg:classifiers":[
        {
            "category":"Retail",
            "subcategory":"Auto Repair",
            "type":"Services"
        }
    ],
    "sg:phone":"+1 419 666 0053",
    "sg:postcode":"43551",
    "sg:province":"OH",
    "sg:tags":[
        "truck"
    ],
    "wof:name":"Seagate Truck Equipment & Rpr",
    "wof:placetype":"venue"
},
  "geometry": {"coordinates":[-83.544434,41.581154],"type":"Point"}
}