{
  "type": "Feature",
  "properties": {
    "addr:full":"167 James Way Marion OH 43302",
    "addr:housenumber":"167",
    "addr:postcode":"43302",
    "addr:street":"James Way",
    "iso:country":"US",
    "sg:address":"167 James Way",
    "sg:city":"Marion",
    "sg:classifiers":[
        {
            "category":"Professional",
            "subcategory":"Accounting & Tax Preparation",
            "type":"Services"
        }
    ],
    "sg:phone":"+1 740 386 6575",
    "sg:postcode":"43302",
    "sg:province":"OH",
    "sg:tags":[
        "return",
        "filing"
    ],
    "wof:name":"Jackson Hewitt Tax Svc",
    "wof:placetype":"venue"
},
  "geometry": {"coordinates":[-83.079178,40.580252],"type":"Point"}
}