{
  "type": "Feature",
  "properties": {
    "addr:full":"27589 Chardon Rd Wickliffe OH 44092",
    "addr:housenumber":"27589",
    "addr:postcode":"44092",
    "addr:street":"Chardon Rd",
    "iso:country":"US",
    "sg:address":"27589 Chardon Rd",
    "sg:city":"Wickliffe",
    "sg:classifiers":[
        {
            "category":"Restaurant",
            "type":"Food & Drink"
        }
    ],
    "sg:phone":"+1 440 585 1177",
    "sg:postcode":"44092",
    "sg:province":"OH",
    "sg:tags":[
        "delicatessen"
    ],
    "sg:website":"www.manhattandeli.com",
    "wof:name":"Manhattan Deli & Restaurant",
    "wof:placetype":"venue"
},
  "geometry": {"coordinates":[-81.486059,41.582806],"type":"Point"}
}