{
  "type": "Feature",
  "properties": {
    "addr:full": "5427 Pearl Rd Cleveland OH 44129",
    "addr:housenumber": "5427",
    "addr:postcode": "44129",
    "addr:street": "Pearl Rd",
    "iso:country": "US",
    "sg:address": "5427 Pearl Rd",
    "sg:city": "Cleveland",
    "sg:classifiers": [
      {
        "category": "Shopping",
        "type": "Retail Goods"
      },
      {
        "category": "Manufacturing",
        "subcategory": "Printing",
        "type": "Manufacturing \u0026 Wholesale Goods"
      }
    ],
    "sg:phone": "+1 440 886 3006",
    "sg:postcode": "44129",
    "sg:province": "OH",
    "sg:tags": [
      "trophy",
      "engraver",
      "wood"
    ],
    "wof:name": "A \u0026 J Trophies \u0026 Engraving Co",
    "wof:placetype": "venue"
  },
  "geometry": {"coordinates":[-81.73414,41.413428],"type":"Point"}
}
