{
  "type": "Feature",
  "properties": {
    "iso:country":"US",
    "sg:address":"220 N 4th St",
    "sg:city":"Steubenville",
    "sg:classifiers":[
        {
            "category":"Organizations",
            "subcategory":"Religious Organization",
            "type":"Services"
        }
    ],
    "sg:phone":"+1 740 282 7542",
    "sg:postcode":"43952",
    "sg:province":"OH",
    "sg:tags":[
        "church"
    ],
    "wof:name":"First Christian Church",
    "wof:placetype":"venue"
},
  "geometry": {"coordinates":[-80.61348599999999,40.363016],"type":"Point"}
}