{
  "type": "Feature",
  "properties": {
    "iso:country":"US",
    "sg:address":"2042 Stratford Ct",
    "sg:city":"Loveland",
    "sg:classifiers":[
        {
            "category":"Social Services",
            "type":"Services"
        }
    ],
    "sg:phone":"+1 513 677 3025",
    "sg:postcode":"45140",
    "sg:province":"OH",
    "sg:tags":[
        "counseling"
    ],
    "wof:name":"Christian Professional Cnslng",
    "wof:placetype":"venue"
},
  "geometry": {"coordinates":[-84.304009,39.275421],"type":"Point"}
}