{
  "type": "Feature",
  "properties": {
    "iso:country":"US",
    "sg:address":"1563 Covington Ave",
    "sg:city":"Piqua",
    "sg:classifiers":[
        {
            "category":"Shopping",
            "type":"Retail Goods"
        }
    ],
    "sg:phone":"+1 937 778 9495",
    "sg:postcode":"45356",
    "sg:province":"OH",
    "sg:tags":[
        "telephone",
        "cellular"
    ],
    "wof:name":"Towne Wireless",
    "wof:placetype":"venue"
},
  "geometry": {"coordinates":[-84.26681600000001,40.141335],"type":"Point"}
}