{
  "type": "Feature",
  "properties": {
    "addr:full": "1563 Covington Ave Piqua OH 45356",
    "addr:housenumber": "1563",
    "addr:postcode": "45356",
    "addr:street": "Covington Ave",
    "iso:country": "US",
    "sg:address": "1563 Covington Ave",
    "sg:city": "Piqua",
    "sg:classifiers": [
      {
        "category": "Shopping",
        "type": "Retail Goods"
      }
    ],
    "sg:phone": "+1 937 778 9495",
    "sg:postcode": "45356",
    "sg:province": "OH",
    "sg:tags": [
      "telephone",
      "cellular"
    ],
    "wof:name": "Towne Wireless",
    "wof:placetype": "venue"
  },
  "geometry": {"coordinates":[-84.266816,40.141335],"type":"Point"}
}
