{
  "type": "Feature",
  "properties": {
    "addr:full":"1801 Tiffin Ave Findlay OH 45840",
    "addr:housenumber":"1801",
    "addr:postcode":"45840",
    "addr:street":"Tiffin Ave",
    "iso:country":"US",
    "sg:address":"1801 Tiffin Ave",
    "sg:city":"Findlay",
    "sg:classifiers":[
        {
            "category":"Restaurant",
            "type":"Food & Drink"
        }
    ],
    "sg:phone":"+1 419 425 5450",
    "sg:postcode":"45840",
    "sg:province":"OH",
    "wof:name":"Paradise Pizza & Subs",
    "wof:placetype":"venue"
},
  "geometry": {"coordinates":[-83.612799,41.053095],"type":"Point"}
}