{
  "type": "Feature",
  "properties": {
    "addr:full":"12 W Vine St Mt Vernon OH 43050",
    "addr:housenumber":"12",
    "addr:postcode":"43050",
    "addr:street":"W Vine St",
    "iso:country":"US",
    "sg:address":"12 W Vine St",
    "sg:city":"Mt Vernon",
    "sg:classifiers":[
        {
            "category":"Home & Garden",
            "subcategory":"Household Appliances",
            "type":"Retail Goods"
        }
    ],
    "sg:phone":"+1 740 392 8726",
    "sg:postcode":"43050",
    "sg:province":"OH",
    "sg:tags":[
        "machine",
        "sewing"
    ],
    "wof:name":"Gardner's Singer-Oreck",
    "wof:placetype":"venue"
},
  "geometry": {"coordinates":[-82.486046,40.392606],"type":"Point"}
}