{
  "type": "Feature",
  "properties": {
    "iso:country":"US",
    "sg:address":"10784 Reading Rd",
    "sg:city":"Cincinnati",
    "sg:classifiers":[
        {
            "category":"Shopping",
            "subcategory":"Hobbies, Toys, & Games",
            "type":"Retail Goods"
        }
    ],
    "sg:phone":"+1 513 948 8378",
    "sg:postcode":"45241",
    "sg:province":"OH",
    "sg:tags":[
        "supply"
    ],
    "wof:name":"Steel Tip In Cinti & Ky",
    "wof:placetype":"venue"
},
  "geometry": {"coordinates":[-84.415897,39.263101],"type":"Point"}
}