{
  "type": "Feature",
  "properties": {
    "addr:full": "10784 Reading Rd Cincinnati OH 45241",
    "addr:housenumber": "10784",
    "addr:postcode": "45241",
    "addr:street": "Reading Rd",
    "iso:country": "US",
    "sg:address": "10784 Reading Rd",
    "sg:city": "Cincinnati",
    "sg:classifiers": [
      {
        "category": "Shopping",
        "subcategory": "Hobbies, Toys, \u0026 Games",
        "type": "Retail Goods"
      }
    ],
    "sg:phone": "+1 513 948 8378",
    "sg:postcode": "45241",
    "sg:province": "OH",
    "sg:tags": [
      "supply"
    ],
    "wof:name": "Steel Tip In Cinti \u0026 Ky",
    "wof:placetype": "venue"
  },
  "geometry": {"coordinates":[-84.415897,39.263101],"type":"Point"}
}
