{
  "type": "Feature",
  "properties": {
    "iso:country":"US",
    "sg:address":"35 S Park Pl",
    "sg:city":"Newark",
    "sg:classifiers":[
        {
            "category":"Professional",
            "subcategory":"Lawyer & Legal Services",
            "type":"Services"
        }
    ],
    "sg:phone":"+1 740 349 2775",
    "sg:postcode":"43055",
    "sg:province":"OH",
    "sg:tags":[
        "attorney"
    ],
    "wof:name":"Jennifer Amos Law Offices",
    "wof:placetype":"venue"
},
  "geometry": {"coordinates":[-82.40107399999999,40.057501],"type":"Point"}
}