{
  "type": "Feature",
  "properties": {
    "addr:full": "412 W Prospect St Painesville OH 44077",
    "addr:housenumber": "412",
    "addr:postcode": "44077",
    "addr:street": "W Prospect St",
    "iso:country": "US",
    "sg:address": "412 W Prospect St",
    "sg:city": "Painesville",
    "sg:classifiers": [
      {
        "category": "Manufacturing",
        "subcategory": "Glass \u0026 Minerals",
        "type": "Manufacturing \u0026 Wholesale Goods"
      },
      {
        "category": "Manufacturing",
        "subcategory": "Electronics",
        "type": "Manufacturing \u0026 Wholesale Goods"
      }
    ],
    "sg:phone": "+1 440 358 0460",
    "sg:postcode": "44077",
    "sg:province": "OH",
    "sg:tags": [
      "product",
      "quartz",
      "nonmetallic",
      "mfg"
    ],
    "wof:name": "Great Lakes Glass Werks Inc",
    "wof:placetype": "venue"
  },
  "geometry": {"coordinates":[-81.254735,41.725423],"type":"Point"}
}
