{
  "type": "Feature",
  "properties": {
    "addr:full":"2547 Mayfair Rd Akron OH 44312",
    "addr:housenumber":"2547",
    "addr:postcode":"44312",
    "addr:street":"Mayfair Rd",
    "iso:country":"US",
    "sg:address":"2547 Mayfair Rd",
    "sg:city":"Akron",
    "sg:classifiers":[
        {
            "category":"Building & Trades",
            "subcategory":"Plumbing",
            "type":"Services"
        }
    ],
    "sg:phone":"+1 330 645 6816",
    "sg:postcode":"44312",
    "sg:province":"OH",
    "sg:tags":[
        "conditioning",
        "air",
        "system",
        "contractor"
    ],
    "wof:name":"Dave's Heating & Cooling",
    "wof:placetype":"venue"
},
  "geometry": {"coordinates":[-81.46100199999999,40.993831],"type":"Point"}
}