{
  "type": "Feature",
  "properties": {
    "iso:country":"US",
    "sg:address":"7515 Pearl Rd",
    "sg:city":"Cleveland",
    "sg:classifiers":[
        {
            "category":"Insurance",
            "subcategory":"Insurance Agent",
            "type":"Services"
        }
    ],
    "sg:phone":"+1 440 891 0476",
    "sg:postcode":"44130",
    "sg:province":"OH",
    "sg:tags":[
        "accident"
    ],
    "wof:name":"Buckeye Care",
    "wof:placetype":"venue"
},
  "geometry": {"coordinates":[-81.813101,41.361163],"type":"Point"}
}