{
  "type": "Feature",
  "properties": {
    "iso:country":"US",
    "sg:address":"1611 S Green Rd",
    "sg:city":"Cleveland",
    "sg:classifiers":[
        {
            "category":"Restaurant",
            "type":"Food & Drink"
        }
    ],
    "sg:phone":"+1 216 382 7455",
    "sg:postcode":"44121",
    "sg:province":"OH",
    "sg:tags":[
        "caterer"
    ],
    "wof:name":"Atrium Cafe",
    "wof:placetype":"venue"
},
  "geometry": {"coordinates":[-81.519367,41.514873],"type":"Point"}
}