{
  "type": "Feature",
  "properties": {
    "addr:full": "2582 E River Rd Dayton OH 45439",
    "addr:housenumber": "2582",
    "addr:postcode": "45439",
    "addr:street": "E River Rd",
    "iso:country": "US",
    "sg:address": "2582 E River Rd",
    "sg:city": "Dayton",
    "sg:classifiers": [
      {
        "category": "Professional",
        "subcategory": "Testing Lab",
        "type": "Services"
      }
    ],
    "sg:phone": "+1 937 356 5109",
    "sg:postcode": "45439",
    "sg:province": "OH",
    "sg:tags": [
      "prototype",
      "build",
      "center"
    ],
    "wof:name": "Delphi",
    "wof:placetype": "venue"
  },
  "geometry": {"coordinates":[-84.225147,39.718152],"type":"Point"}
}
