{
  "type": "Feature",
  "properties": {
    "iso:country":"US",
    "sg:address":"145 N Vine St",
    "sg:city":"Orrville",
    "sg:classifiers":[
        {
            "category":"Government",
            "subcategory":"Post Office",
            "type":"Public Place"
        }
    ],
    "sg:phone":"+1 330 682 7831",
    "sg:postcode":"44667",
    "sg:province":"OH",
    "sg:tags":[
        "postal",
        "us"
    ],
    "sg:website":"www.usps.com",
    "wof:name":"US Post Office",
    "wof:placetype":"venue"
},
  "geometry": {"coordinates":[-81.76566699999999,40.841118],"type":"Point"}
}