{
  "type": "Feature",
  "properties": {
    "addr:full":"17381 W Hausencomb Rd Graytown OH 43432",
    "addr:housenumber":"17381",
    "addr:postcode":"43432",
    "addr:street":"W Hausencomb Rd",
    "iso:country":"US",
    "sg:address":"17381 W Hausencomb Rd",
    "sg:city":"Graytown",
    "sg:classifiers":[
        {
            "category":"Farming",
            "subcategory":"Livestock Farm",
            "type":"Manufacturing & Wholesale Goods"
        }
    ],
    "sg:phone":"+1 419 862 3198",
    "sg:postcode":"43432",
    "sg:province":"OH",
    "sg:tags":[
        "hog",
        "f",
        "corn",
        "crop",
        "field",
        "soybean",
        "or",
        "feedlot"
    ],
    "wof:name":"Timothy Tank",
    "wof:placetype":"venue"
},
  "geometry": {"coordinates":[-83.262658,41.582154],"type":"Point"}
}