{
  "type": "Feature",
  "properties": {
    "addr:full": "3710 E 91st St Cleveland OH 44105",
    "addr:housenumber": "3710",
    "addr:postcode": "44105",
    "addr:street": "E 91St St",
    "iso:country": "US",
    "sg:address": "3710 E 91st St",
    "sg:city": "Cleveland",
    "sg:classifiers": [
      {
        "category": "Wholesale",
        "subcategory": "Construction Materials",
        "type": "Manufacturing \u0026 Wholesale Goods"
      }
    ],
    "sg:phone": "+1 216 641 3811",
    "sg:postcode": "44105",
    "sg:province": "OH",
    "wof:name": "Woodstock Products Inc",
    "wof:placetype": "venue"
  },
  "geometry": {"coordinates":[-81.623544,41.457574],"type":"Point"}
}
