{
  "type": "Feature",
  "properties": {
    "addr:full": "1725 Blue Rock St Cincinnati OH 45223",
    "addr:housenumber": "1725",
    "addr:postcode": "45223",
    "addr:street": "Blue Rock St",
    "iso:country": "US",
    "sg:address": "1725 Blue Rock St",
    "sg:city": "Cincinnati",
    "sg:classifiers": [
      {
        "category": "Wholesale",
        "subcategory": "Beer",
        "type": "Manufacturing \u0026 Wholesale Goods"
      }
    ],
    "sg:phone": "+1 513 541 7922",
    "sg:postcode": "45223",
    "sg:province": "OH",
    "wof:name": "Stor Dor Beverage Service",
    "wof:placetype": "venue"
  },
  "geometry": {"coordinates":[-84.5461,39.161283],"type":"Point"}
}
