{
  "type": "Feature",
  "properties": {
    "addr:full": "4956 Monroe St Toledo OH 43623",
    "addr:housenumber": "4956",
    "addr:postcode": "43623",
    "addr:street": "Monroe St",
    "iso:country": "US",
    "sg:address": "4956 Monroe St",
    "sg:city": "Toledo",
    "sg:classifiers": [
      {
        "category": "Personal",
        "subcategory": "Beauty Salon",
        "type": "Services"
      }
    ],
    "sg:phone": "+1 419 480 8000",
    "sg:postcode": "43623",
    "sg:province": "OH",
    "sg:tags": [
      "manicuring"
    ],
    "wof:name": "J J Nails Pedicure \u0026 Tanning",
    "wof:placetype": "venue"
  },
  "geometry": {"coordinates":[-83.643245,41.698488],"type":"Point"}
}
