{
  "type": "Feature",
  "properties": {
    "iso:country":"US",
    "sg:address":"4956 Monroe St",
    "sg:city":"Toledo",
    "sg:classifiers":[
        {
            "category":"Personal",
            "subcategory":"Beauty Salon",
            "type":"Services"
        }
    ],
    "sg:phone":"+1 419 480 8000",
    "sg:postcode":"43623",
    "sg:province":"OH",
    "sg:tags":[
        "manicuring"
    ],
    "wof:name":"J J Nails Pedicure & Tanning",
    "wof:placetype":"venue"
},
  "geometry": {"coordinates":[-83.64324499999999,41.698488],"type":"Point"}
}