{
  "type": "Feature",
  "properties": {
    "iso:country":"US",
    "sg:address":"616 S Collett St",
    "sg:city":"Lima",
    "sg:classifiers":[
        {
            "category":"Organizations",
            "subcategory":"Professional Association",
            "type":"Services"
        }
    ],
    "sg:phone":"+1 419 225 8860",
    "sg:postcode":"45805",
    "sg:province":"OH",
    "wof:name":"American Cancer Society",
    "wof:placetype":"venue"
},
  "geometry": {"coordinates":[-84.119213,40.733067],"type":"Point"}
}