{
  "type": "Feature",
  "properties": {
    "addr:full": "7291 Lilac Ct North Olmsted OH 44070",
    "addr:housenumber": "7291",
    "addr:postcode": "44070",
    "addr:street": "Lilac Ct",
    "iso:country": "US",
    "sg:address": "7291 Lilac Ct",
    "sg:city": "North Olmsted",
    "sg:classifiers": [
      {
        "category": "Professional",
        "subcategory": "Management \u0026 Consulting",
        "type": "Services"
      }
    ],
    "sg:phone": "+1 440 427 1922",
    "sg:postcode": "44070",
    "sg:province": "OH",
    "sg:tags": [
      "consultant"
    ],
    "wof:name": "Gocek Consulting Svc",
    "wof:placetype": "venue"
  },
  "geometry": {"coordinates":[-81.964462,41.386221],"type":"Point"}
}
