{
  "type": "Feature",
  "properties": {
    "addr:full": "841 Boardman Canfield Rd Youngstown OH 44512",
    "addr:housenumber": "841",
    "addr:postcode": "44512",
    "addr:street": "Boardman Canfield Rd",
    "iso:country": "US",
    "sg:address": "841 Boardman Canfield Rd",
    "sg:city": "Youngstown",
    "sg:classifiers": [
      {
        "category": "Insurance",
        "subcategory": "Insurance Agent",
        "type": "Services"
      }
    ],
    "sg:phone": "+1 330 726 5502",
    "sg:postcode": "44512",
    "sg:province": "OH",
    "wof:name": "Ashton Insurance",
    "wof:placetype": "venue"
  },
  "geometry": {"coordinates":[-80.688723,41.024471],"type":"Point"}
}
