{
  "type": "Feature",
  "properties": {
    "addr:full":"3 Laurelwood Dr Milford OH 45150",
    "addr:housenumber":"3",
    "addr:postcode":"45150",
    "addr:street":"Laurelwood Dr",
    "iso:country":"US",
    "sg:address":"3 Laurelwood Dr",
    "sg:city":"Milford",
    "sg:classifiers":[
        {
            "category":"Manufacturing",
            "subcategory":"Rubber & Plastics",
            "type":"Manufacturing & Wholesale Goods"
        }
    ],
    "sg:phone":"+1 513 248 1995",
    "sg:postcode":"45150",
    "sg:province":"OH",
    "sg:tags":[
        "casting",
        "liquid",
        "polyurethane",
        "mfg"
    ],
    "wof:name":"Polytech",
    "wof:placetype":"venue"
},
  "geometry": {"coordinates":[-84.221019,39.136837],"type":"Point"}
}