{
  "type": "Feature",
  "properties": {
    "addr:full": "4301 Stoner Dr Grove City OH 43123",
    "addr:housenumber": "4301",
    "addr:postcode": "43123",
    "addr:street": "Stoner Dr",
    "iso:country": "US",
    "sg:address": "4301 Stoner Dr",
    "sg:city": "Grove City",
    "sg:classifiers": [
      {
        "category": "Real Estate",
        "subcategory": "Real Estate Operator",
        "type": "Services"
      }
    ],
    "sg:phone": "+1 614 539 1022",
    "sg:postcode": "43123",
    "sg:province": "OH",
    "sg:tags": [
      "building",
      "apartment"
    ],
    "wof:name": "Grovewood Place",
    "wof:placetype": "venue"
  },
  "geometry": {"coordinates":[-83.082199,39.874306],"type":"Point"}
}
