{
  "type": "Feature",
  "properties": {
    "addr:full": "585 Three Chimneys Ln Loveland OH 45140",
    "addr:housenumber": "585",
    "addr:postcode": "45140",
    "addr:street": "Three Chimneys Ln",
    "iso:country": "US",
    "sg:address": "585 Three Chimneys Ln",
    "sg:city": "Loveland",
    "sg:classifiers": [
      {
        "category": "Professional",
        "type": "Services"
      }
    ],
    "sg:phone": "+1 513 677 9161",
    "sg:postcode": "45140",
    "sg:province": "OH",
    "sg:tags": [
      "establishment"
    ],
    "wof:name": "Big Red Rooster Cnti",
    "wof:placetype": "venue"
  },
  "geometry": {"coordinates":[-84.273797,39.235819],"type":"Point"}
}
