{
  "type": "Feature",
  "properties": {
    "addr:full":"7632 Tyler Blvd Mentor OH 44060",
    "addr:housenumber":"7632",
    "addr:postcode":"44060",
    "addr:street":"Tyler Blvd",
    "iso:country":"US",
    "sg:address":"7632 Tyler Blvd",
    "sg:city":"Mentor",
    "sg:classifiers":[
        {
            "category":"Building & Trades",
            "subcategory":"Electrical",
            "type":"Services"
        }
    ],
    "sg:phone":"+1 440 975 9200",
    "sg:postcode":"44060",
    "sg:province":"OH",
    "sg:tags":[
        "home",
        "system",
        "automation"
    ],
    "wof:name":"DPS Maintenance Management",
    "wof:placetype":"venue"
},
  "geometry": {"coordinates":[-81.36046399999999,41.677867],"type":"Point"}
}