{
  "type": "Feature",
  "properties": {
    "addr:full": "1 Gleneagle Ct Piqua OH 45356",
    "addr:housenumber": "1",
    "addr:postcode": "45356",
    "addr:street": "Gleneagle Ct",
    "iso:country": "US",
    "sg:address": "1 Gleneagle Ct",
    "sg:city": "Piqua",
    "sg:classifiers": [
      {
        "category": "Professional",
        "subcategory": "Business Services",
        "type": "Services"
      }
    ],
    "sg:phone": "+1 937 778 8017",
    "sg:postcode": "45356",
    "sg:province": "OH",
    "wof:name": "Bayman Auction Service Inc",
    "wof:placetype": "venue"
  },
  "geometry": {"coordinates":[-84.270866,40.157879],"type":"Point"}
}
