{
  "type": "Feature",
  "properties": {
    "iso:country":"US",
    "sg:address":"121 Center Rd",
    "sg:city":"Bedford",
    "sg:classifiers":[
        {
            "category":"Social Services",
            "type":"Services"
        }
    ],
    "sg:phone":"+1 440 232 9310",
    "sg:postcode":"44146",
    "sg:province":"OH",
    "sg:tags":[
        "profit",
        "residential",
        "treatment",
        "facility"
    ],
    "wof:name":"Safely Home Inc",
    "wof:placetype":"venue"
},
  "geometry": {"coordinates":[-81.53711,41.396406],"type":"Point"}
}