{
  "type": "Feature",
  "properties": {
    "addr:full": "3667 Georgia Ave Columbus OH 43219",
    "addr:housenumber": "3667",
    "addr:postcode": "43219",
    "addr:street": "Georgia Ave",
    "iso:country": "US",
    "sg:address": "3667 Georgia Ave",
    "sg:city": "Columbus",
    "sg:classifiers": [
      {
        "category": "Organizations",
        "subcategory": "Religious Organization",
        "type": "Services"
      }
    ],
    "sg:phone": "+1 614 478 5343",
    "sg:postcode": "43219",
    "sg:province": "OH",
    "sg:tags": [
      "church"
    ],
    "wof:name": "Apostolic Church Of Faith",
    "wof:placetype": "venue"
  },
  "geometry": {"coordinates":[-82.90734,40.013424],"type":"Point"}
}
