{
  "type": "Feature",
  "properties": {
    "addr:full":"858 Distribution Dr Columbus OH 43228",
    "addr:housenumber":"858",
    "addr:postcode":"43228",
    "addr:street":"Distribution Dr",
    "iso:country":"US",
    "sg:address":"858 Distribution Dr",
    "sg:city":"Columbus",
    "sg:classifiers":[
        {
            "category":"Building & Trades",
            "subcategory":"Electrical",
            "type":"Services"
        }
    ],
    "sg:phone":"+1 614 299 4445",
    "sg:postcode":"43228",
    "sg:province":"OH",
    "sg:tags":[
        "electrical",
        "contractor"
    ],
    "sg:website":"www.knightelectric.com",
    "wof:name":"Knight Electric Inc",
    "wof:placetype":"venue"
},
  "geometry": {"coordinates":[-83.10866,39.97095],"type":"Point"}
}