{
  "type": "Feature",
  "properties": {
    "iso:country":"US",
    "sg:address":"430 W Rahn Rd",
    "sg:city":"Dayton",
    "sg:classifiers":[
        {
            "category":"Shopping",
            "subcategory":"Computers & Home Electronics",
            "type":"Retail Goods"
        }
    ],
    "sg:phone":"+1 800 325 1312",
    "sg:postcode":"45429",
    "sg:province":"OH",
    "sg:tags":[
        "rental",
        "phone",
        "video",
        "tape",
        "cellular"
    ],
    "wof:name":"Accent Wireless",
    "wof:placetype":"venue"
},
  "geometry": {"coordinates":[-84.17305,39.668716],"type":"Point"}
}