{
  "type": "Feature",
  "properties": {
    "addr:full": "430 W Rahn Rd Dayton OH 45429",
    "addr:housenumber": "430",
    "addr:postcode": "45429",
    "addr:street": "W Rahn Rd",
    "iso:country": "US",
    "sg:address": "430 W Rahn Rd",
    "sg:city": "Dayton",
    "sg:classifiers": [
      {
        "category": "Shopping",
        "subcategory": "Computers \u0026 Home Electronics",
        "type": "Retail Goods"
      }
    ],
    "sg:phone": "+1 800 325 1312",
    "sg:postcode": "45429",
    "sg:province": "OH",
    "sg:tags": [
      "rental",
      "phone",
      "video",
      "tape",
      "cellular"
    ],
    "wof:name": "Accent Wireless",
    "wof:placetype": "venue"
  },
  "geometry": {"coordinates":[-84.17305,39.668716],"type":"Point"}
}
