{
  "type": "Feature",
  "properties": {
    "iso:country":"US",
    "sg:address":"312 Elm St",
    "sg:city":"Cincinnati",
    "sg:classifiers":[
        {
            "category":"Manufacturing",
            "subcategory":"Printing",
            "type":"Manufacturing & Wholesale Goods"
        }
    ],
    "sg:phone":"+1 513 768 6006",
    "sg:postcode":"45202",
    "sg:province":"OH",
    "sg:tags":[
        "periodical"
    ],
    "wof:name":"Design Magazine",
    "wof:placetype":"venue"
},
  "geometry": {"coordinates":[-84.515769,39.098996],"type":"Point"}
}