{
  "type": "Feature",
  "properties": {
    "addr:full":"6807 Boneta Rd Medina OH 44256",
    "addr:housenumber":"6807",
    "addr:postcode":"44256",
    "addr:street":"Boneta Rd",
    "iso:country":"US",
    "sg:address":"6807 Boneta Rd",
    "sg:city":"Medina",
    "sg:classifiers":[
        {
            "category":"Museum",
            "type":"Entertainment"
        }
    ],
    "sg:phone":"+1 330 336 7657",
    "sg:postcode":"44256",
    "sg:province":"OH",
    "sg:tags":[
        "gallery"
    ],
    "wof:name":"Norhteast Ohio Museum",
    "wof:placetype":"venue"
},
  "geometry": {"coordinates":[-81.775842,41.0969],"type":"Point"}
}