{
  "type": "Feature",
  "properties": {
    "addr:full":"205 W Liberty St Geneva OH 44041",
    "addr:housenumber":"205",
    "addr:postcode":"44041",
    "addr:street":"W Liberty St",
    "iso:country":"US",
    "sg:address":"205 W Liberty St",
    "sg:city":"Geneva",
    "sg:classifiers":[
        {
            "category":"Organizations",
            "subcategory":"Religious Organization",
            "type":"Services"
        }
    ],
    "sg:phone":"+1 440 466 6093",
    "sg:postcode":"44041",
    "sg:province":"OH",
    "wof:name":"New Life Assembly Of God",
    "wof:placetype":"venue"
},
  "geometry": {"coordinates":[-80.954356,41.799228],"type":"Point"}
}