{
  "type": "Feature",
  "properties": {
    "addr:full": "6224 Montgomery Rd Cincinnati OH 45213",
    "addr:housenumber": "6224",
    "addr:postcode": "45213",
    "addr:street": "Montgomery Rd",
    "iso:country": "US",
    "sg:address": "6224 Montgomery Rd",
    "sg:city": "Cincinnati",
    "sg:classifiers": [
      {
        "category": "Food \u0026 Beverages",
        "subcategory": "Groceries \u0026 Convenience Stores",
        "type": "Retail Goods"
      },
      {
        "category": "Autos \u0026 Motor Vehicles",
        "subcategory": "Fuel \u0026 Gas Station",
        "type": "Retail Goods"
      }
    ],
    "sg:phone": "+1 513 531 3412",
    "sg:postcode": "45213",
    "sg:province": "OH",
    "sg:tags": [
      "oil"
    ],
    "wof:name": "Reese Sunoco Food Mart LLC",
    "wof:placetype": "venue"
  },
  "geometry": {"coordinates":[-84.423364,39.184122],"type":"Point"}
}
