{
  "type": "Feature",
  "properties": {
    "iso:country":"US",
    "sg:address":"6224 Montgomery Rd",
    "sg:city":"Cincinnati",
    "sg:classifiers":[
        {
            "category":"Food & Beverages",
            "subcategory":"Groceries & Convenience Stores",
            "type":"Retail Goods"
        },
        {
            "category":"Autos & Motor Vehicles",
            "subcategory":"Fuel & Gas Station",
            "type":"Retail Goods"
        }
    ],
    "sg:phone":"+1 513 531 3412",
    "sg:postcode":"45213",
    "sg:province":"OH",
    "sg:tags":[
        "oil"
    ],
    "wof:name":"Reese Sunoco Food Mart LLC",
    "wof:placetype":"venue"
},
  "geometry": {"coordinates":[-84.423364,39.184122],"type":"Point"}
}