{
  "type": "Feature",
  "properties": {
    "iso:country":"US",
    "sg:address":"344 Day St",
    "sg:city":"Ravenna",
    "sg:classifiers":[
        {
            "category":"Food & Beverages",
            "subcategory":"Meat & Fish",
            "type":"Retail Goods"
        }
    ],
    "sg:phone":"+1 330 296 5216",
    "sg:postcode":"44266",
    "sg:province":"OH",
    "sg:tags":[
        "personal",
        "ware",
        "refrigeration"
    ],
    "wof:name":"Portage Frosted Foods Inc",
    "wof:placetype":"venue"
},
  "geometry": {"coordinates":[-81.245422,41.162086],"type":"Point"}
}