{
  "type": "Feature",
  "properties": {
    "addr:full": "344 Day St Ravenna OH 44266",
    "addr:housenumber": "344",
    "addr:postcode": "44266",
    "addr:street": "Day St",
    "iso:country": "US",
    "sg:address": "344 Day St",
    "sg:city": "Ravenna",
    "sg:classifiers": [
      {
        "category": "Food \u0026 Beverages",
        "subcategory": "Meat \u0026 Fish",
        "type": "Retail Goods"
      }
    ],
    "sg:phone": "+1 330 296 5216",
    "sg:postcode": "44266",
    "sg:province": "OH",
    "sg:tags": [
      "personal",
      "ware",
      "refrigeration"
    ],
    "wof:name": "Portage Frosted Foods Inc",
    "wof:placetype": "venue"
  },
  "geometry": {"coordinates":[-81.245422,41.162086],"type":"Point"}
}
