{
  "type": "Feature",
  "properties": {
    "addr:full": "1243 State Rte 66 Archbold OH 43502",
    "addr:housenumber": "1243",
    "addr:postcode": "43502",
    "addr:street": "State Rte 66",
    "iso:country": "US",
    "sg:address": "1243 State Rte 66",
    "sg:city": "Archbold",
    "sg:classifiers": [
      {
        "category": "Wholesale",
        "subcategory": "Electrical",
        "type": "Manufacturing \u0026 Wholesale Goods"
      }
    ],
    "sg:phone": "+1 419 445 5921",
    "sg:postcode": "43502",
    "sg:province": "OH",
    "sg:tags": [
      "electric",
      "motor"
    ],
    "wof:name": "Wyse Electric Motor Repair",
    "wof:placetype": "venue"
  },
  "geometry": {"coordinates":[-84.306607,41.535989],"type":"Point"}
}
