{
  "type": "Feature",
  "properties": {
    "iso:country":"US",
    "sg:address":"2300 Hubbard Rd",
    "sg:city":"Madison",
    "sg:classifiers":[
        {
            "category":"Organizations",
            "subcategory":"Religious Organization",
            "type":"Services"
        }
    ],
    "sg:phone":"+1 440 428 6868",
    "sg:postcode":"44057",
    "sg:province":"OH",
    "sg:website":"www.cornerstonefriends.org",
    "wof:name":"Cornerstone Friends Church",
    "wof:placetype":"venue"
},
  "geometry": {"coordinates":[-81.048615,41.812103],"type":"Point"}
}