{
  "type": "Feature",
  "properties": {
    "iso:country":"US",
    "sg:address":"766 S Broadway St",
    "sg:city":"Geneva",
    "sg:classifiers":[
        {
            "category":"Education",
            "subcategory":"Vocational School",
            "type":"Public Place"
        }
    ],
    "sg:phone":"+1 440 466 6008",
    "sg:postcode":"44041",
    "sg:province":"OH",
    "sg:tags":[
        "secretarial"
    ],
    "wof:name":"H & R Block Tax Svc",
    "wof:placetype":"venue"
},
  "geometry": {"coordinates":[-80.947395,41.793792],"type":"Point"}
}