{
  "type": "Feature",
  "properties": {
    "addr:full": "62 Stonington Cir Newark OH 43055",
    "addr:housenumber": "62",
    "addr:postcode": "43055",
    "addr:street": "Stonington Cir",
    "iso:country": "US",
    "sg:address": "62 Stonington Cir",
    "sg:city": "Newark",
    "sg:classifiers": [
      {
        "category": "Mining \u0026 Drilling",
        "type": "Manufacturing \u0026 Wholesale Goods"
      }
    ],
    "sg:phone": "+1 740 522 1811",
    "sg:postcode": "43055",
    "sg:province": "OH",
    "sg:tags": [
      "crude",
      "production",
      "gas"
    ],
    "wof:name": "Amac Inc",
    "wof:placetype": "venue"
  },
  "geometry": {"coordinates":[-82.458644,40.04306],"type":"Point"}
}
