{
  "type": "Feature",
  "properties": {
    "addr:full":"3041 Austinburg Rd Ashtabula OH 44004",
    "addr:housenumber":"3041",
    "addr:postcode":"44004",
    "addr:street":"Austinburg Rd",
    "iso:country":"US",
    "sg:address":"3041 Austinburg Rd",
    "sg:city":"Ashtabula",
    "sg:classifiers":[
        {
            "category":"Manufacturing",
            "subcategory":"Tools & Machinery",
            "type":"Manufacturing & Wholesale Goods"
        }
    ],
    "sg:phone":"+1 440 998 1038",
    "sg:postcode":"44004",
    "sg:province":"OH",
    "sg:tags":[
        "industrial",
        "mfg"
    ],
    "wof:name":"Lewis Machine Company",
    "wof:placetype":"venue"
},
  "geometry": {"coordinates":[-80.82034899999999,41.811545],"type":"Point"}
}