{
  "type": "Feature",
  "properties": {
    "addr:full": "2209 Grant Ave Cincinnati OH 45231",
    "addr:housenumber": "2209",
    "addr:postcode": "45231",
    "addr:street": "Grant Ave",
    "iso:country": "US",
    "sg:address": "2209 Grant Ave",
    "sg:city": "Cincinnati",
    "sg:classifiers": [
      {
        "category": "Wholesale",
        "subcategory": "Dairy",
        "type": "Manufacturing \u0026 Wholesale Goods"
      }
    ],
    "sg:phone": "+1 513 851 6806",
    "sg:postcode": "45231",
    "sg:province": "OH",
    "sg:tags": [
      "frozen",
      "dessert",
      "ice",
      "cream"
    ],
    "wof:name": "Mcperry Ice Cream",
    "wof:placetype": "venue"
  },
  "geometry": {"coordinates":[-84.563773,39.274287],"type":"Point"}
}
