{
  "type": "Feature",
  "properties": {
    "iso:country":"US",
    "sg:address":"22057 Smith Hulse Rd",
    "sg:city":"Circleville",
    "sg:classifiers":[
        {
            "category":"Real Estate",
            "subcategory":"Real Estate Operator",
            "type":"Services"
        }
    ],
    "sg:phone":"+1 740 474 3222",
    "sg:postcode":"43113",
    "sg:province":"OH",
    "sg:tags":[
        "farm",
        "corn",
        "property",
        "lessor"
    ],
    "wof:name":"Chester McCloud",
    "wof:placetype":"venue"
},
  "geometry": {"coordinates":[-83.046782,39.613755],"type":"Point"}
}