{
  "type": "Feature",
  "properties": {
    "iso:country":"US",
    "sg:address":"1 Riverside Plz",
    "sg:city":"Columbus",
    "sg:classifiers":[
        {
            "category":"Professional",
            "subcategory":"Lawyer & Legal Services",
            "type":"Services"
        }
    ],
    "sg:phone":"+1 614 461 7799",
    "sg:postcode":"43215",
    "sg:province":"OH",
    "sg:tags":[
        "attorney"
    ],
    "wof:name":"Simpson Thacher & Bartlett",
    "wof:placetype":"venue"
},
  "geometry": {"coordinates":[-83.005077,39.965077],"type":"Point"}
}