{
  "type": "Feature",
  "properties": {
    "addr:full": "862 Glenrock Dr Brunswick OH 44212",
    "addr:housenumber": "862",
    "addr:postcode": "44212",
    "addr:street": "Glenrock Dr",
    "iso:country": "US",
    "sg:address": "862 Glenrock Dr",
    "sg:city": "Brunswick",
    "sg:classifiers": [
      {
        "category": "Communications",
        "type": "Services"
      }
    ],
    "sg:phone": "+1 330 225 8382",
    "sg:postcode": "44212",
    "sg:province": "OH",
    "wof:name": "Precision Communication Sltns",
    "wof:placetype": "venue"
  },
  "geometry": {"coordinates":[-81.876058,41.252537],"type":"Point"}
}
