{
  "type": "Feature",
  "properties": {
    "addr:full": "6958 Americana Parkway Dr Reynoldsburg OH 43068",
    "addr:housenumber": "6958",
    "addr:postcode": "43068",
    "addr:street": "Americana Parkway Dr",
    "iso:country": "US",
    "sg:address": "6958 Americana Parkway Dr",
    "sg:city": "Reynoldsburg",
    "sg:classifiers": [
      {
        "category": "Professional",
        "subcategory": "Management \u0026 Consulting",
        "type": "Services"
      }
    ],
    "sg:phone": "+1 614 322 1685",
    "sg:postcode": "43068",
    "sg:province": "OH",
    "sg:tags": [
      "consultant",
      "business"
    ],
    "wof:name": "ICBCA Inc",
    "wof:placetype": "venue"
  },
  "geometry": {"coordinates":[-82.815775,39.929974],"type":"Point"}
}
