{
  "type": "Feature",
  "properties": {
    "addr:full":"620 W Main St Bellevue OH 44811",
    "addr:housenumber":"620",
    "addr:postcode":"44811",
    "addr:street":"W Main St",
    "iso:country":"US",
    "sg:address":"620 W Main St",
    "sg:city":"Bellevue",
    "sg:classifiers":[
        {
            "category":"Travel",
            "subcategory":"Hotels & Motels",
            "type":"Entertainment"
        }
    ],
    "sg:phone":"+1 419 483 6630",
    "sg:postcode":"44811",
    "sg:province":"OH",
    "wof:name":"Village Motel",
    "wof:placetype":"venue"
},
  "geometry": {"coordinates":[-82.855356,41.277825],"type":"Point"}
}