{
  "type": "Feature",
  "properties": {
    "addr:full": "311 West Ave Tallmadge OH 44278",
    "addr:housenumber": "311",
    "addr:postcode": "44278",
    "addr:street": "West Ave",
    "iso:country": "US",
    "sg:address": "311 West Ave",
    "sg:city": "Tallmadge",
    "sg:classifiers": [
      {
        "category": "Shopping",
        "subcategory": "Florist",
        "type": "Retail Goods"
      }
    ],
    "sg:phone": "+1 330 633 6563",
    "sg:postcode": "44278",
    "sg:province": "OH",
    "wof:name": "Petitti Floral Shop",
    "wof:placetype": "venue"
  },
  "geometry": {"coordinates":[-81.455495,41.101683],"type":"Point"}
}
