{
  "type": "Feature",
  "properties": {
    "addr:full": "2640 Thoman Pl Toledo OH 43613",
    "addr:postcode": "2640;43613",
    "addr:street": "Thoman Pl",
    "iso:country": "US",
    "sg:address": "2640 Thoman Pl",
    "sg:city": "Toledo",
    "sg:classifiers": [
      {
        "category": "Wholesale",
        "subcategory": "Apparel",
        "type": "Manufacturing \u0026 Wholesale Goods"
      }
    ],
    "sg:phone": "+1 419 450 7646",
    "sg:postcode": "43613",
    "sg:province": "OH",
    "sg:tags": [
      "clothing"
    ],
    "wof:name": "A Little Touch of ME",
    "wof:placetype": "venue"
  },
  "geometry": {"coordinates":[-83.609012,41.695051],"type":"Point"}
}
