{
  "type": "Feature",
  "properties": {
    "addr:full": "9005 Adamsville Otsego Rd Adamsville OH 43802",
    "addr:housenumber": "9005",
    "addr:postcode": "43802",
    "addr:street": "Adamsville Otsego Rd",
    "iso:country": "US",
    "sg:address": "9005 Adamsville Otsego Rd",
    "sg:city": "Adamsville",
    "sg:classifiers": [
      {
        "category": "Farming",
        "subcategory": "Farm \u0026 Veterinary Services",
        "type": "Manufacturing \u0026 Wholesale Goods"
      }
    ],
    "sg:phone": "+1 740 796 3981",
    "sg:postcode": "43802",
    "sg:province": "OH",
    "sg:tags": [
      "livestock"
    ],
    "wof:name": "Ronald W Welsh",
    "wof:placetype": "venue"
  },
  "geometry": {"coordinates":[-81.808153,40.094216],"type":"Point"}
}
