{
  "type": "Feature",
  "properties": {
    "addr:full":"1019 State Rte 28 Milford OH 45150",
    "addr:housenumber":"1019",
    "addr:postcode":"45150",
    "addr:street":"State Rte 28",
    "iso:country":"US",
    "sg:address":"1019 State Rte 28",
    "sg:city":"Milford",
    "sg:classifiers":[
        {
            "category":"Retail",
            "subcategory":"Laundry & Dry Cleaning",
            "type":"Services"
        }
    ],
    "sg:phone":"+1 513 831 1241",
    "sg:postcode":"45150",
    "sg:province":"OH",
    "sg:tags":[
        "cleaners",
        "plant",
        "power",
        "drycleaning"
    ],
    "wof:name":"Griff's Custom Cleaners",
    "wof:placetype":"venue"
},
  "geometry": {"coordinates":[-84.27604100000001,39.180775],"type":"Point"}
}