{
  "type": "Feature",
  "properties": {
    "iso:country":"US",
    "sg:address":"5610 Alan Moss Ct",
    "sg:city":"Dublin",
    "sg:classifiers":[
        {
            "category":"Retail",
            "subcategory":"Veterinary Services",
            "type":"Services"
        }
    ],
    "sg:phone":"+1 614 766 1184",
    "sg:postcode":"43017",
    "sg:province":"OH",
    "sg:tags":[
        "veterinarian"
    ],
    "wof:name":"House Calls",
    "wof:placetype":"venue"
},
  "geometry": {"coordinates":[-83.143069,40.11489],"type":"Point"}
}