{
  "type": "Feature",
  "properties": {
    "iso:country":"US",
    "sg:address":"1001 McKinley Rd",
    "sg:city":"Saint Marys",
    "sg:classifiers":[
        {
            "category":"Manufacturing",
            "subcategory":"Petroleum Products",
            "type":"Manufacturing & Wholesale Goods"
        }
    ],
    "sg:phone":"+1 419 394 1042",
    "sg:postcode":"45885",
    "sg:province":"OH",
    "sg:tags":[
        "asphalt",
        "mfg"
    ],
    "wof:name":"Sealer & Other Stuff",
    "wof:placetype":"venue"
},
  "geometry": {"coordinates":[-84.372319,40.553528],"type":"Point"}
}