{
  "type": "Feature",
  "properties": {
    "addr:full": "1001 McKinley Rd Saint Marys OH 45885",
    "addr:housenumber": "1001",
    "addr:postcode": "45885",
    "addr:street": "Mckinley Rd",
    "iso:country": "US",
    "sg:address": "1001 McKinley Rd",
    "sg:city": "Saint Marys",
    "sg:classifiers": [
      {
        "category": "Manufacturing",
        "subcategory": "Petroleum Products",
        "type": "Manufacturing \u0026 Wholesale Goods"
      }
    ],
    "sg:phone": "+1 419 394 1042",
    "sg:postcode": "45885",
    "sg:province": "OH",
    "sg:tags": [
      "asphalt",
      "mfg"
    ],
    "wof:name": "Sealer \u0026 Other Stuff",
    "wof:placetype": "venue"
  },
  "geometry": {"coordinates":[-84.372319,40.553528],"type":"Point"}
}
