{
  "type": "Feature",
  "properties": {
    "addr:full": "21200 Lorain Rd Cleveland OH 44126",
    "addr:housenumber": "21200",
    "addr:postcode": "44126",
    "addr:street": "Lorain Rd",
    "iso:country": "US",
    "sg:address": "21200 Lorain Rd",
    "sg:city": "Cleveland",
    "sg:classifiers": [
      {
        "category": "Social Services",
        "subcategory": "Child Care",
        "type": "Services"
      }
    ],
    "sg:phone": "+1 440 331 0096",
    "sg:postcode": "44126",
    "sg:province": "OH",
    "sg:tags": [
      "kindergarten",
      "academic",
      "school"
    ],
    "wof:name": "Parkview Playschool",
    "wof:placetype": "venue"
  },
  "geometry": {"coordinates":[-81.857095,41.444387],"type":"Point"}
}
