{
  "type": "Feature",
  "properties": {
    "iso:country":"US",
    "sg:address":"5026 Delhi Ave",
    "sg:city":"Cincinnati",
    "sg:classifiers":[
        {
            "category":"Social Services",
            "subcategory":"Job Training",
            "type":"Services"
        }
    ],
    "sg:phone":"+1 513 922 5600",
    "sg:postcode":"45238",
    "sg:province":"OH",
    "sg:tags":[
        "rehabilitation"
    ],
    "wof:name":"Howell Rehab Ctr",
    "wof:placetype":"venue"
},
  "geometry": {"coordinates":[-84.61091500000001,39.095247],"type":"Point"}
}