{
  "type": "Feature",
  "properties": {
    "iso:country":"US",
    "sg:address":"3900 Morse Rd",
    "sg:city":"Columbus",
    "sg:classifiers":[
        {
            "category":"Manufacturing",
            "subcategory":"Food",
            "type":"Manufacturing & Wholesale Goods"
        },
        {
            "category":"Restaurant",
            "type":"Food & Drink"
        }
    ],
    "sg:phone":"+1 614 418 9665",
    "sg:postcode":"43219",
    "sg:province":"OH",
    "sg:tags":[
        "eating",
        "pretzel",
        "mfg"
    ],
    "wof:name":"We'Re Rolling Pretzel Co",
    "wof:placetype":"venue"
},
  "geometry": {"coordinates":[-82.91045699999999,40.057565],"type":"Point"}
}