{
  "type": "Feature",
  "properties": {
    "addr:full": "44 S Main St Dayton OH 45402",
    "addr:housenumber": "44",
    "addr:postcode": "45402",
    "addr:street": "S Main St",
    "iso:country": "US",
    "sg:address": "44 S Main St",
    "sg:city": "Dayton",
    "sg:classifiers": [
      {
        "category": "Shopping",
        "subcategory": "Clothing, Apparel, \u0026 Fashions",
        "type": "Retail Goods"
      }
    ],
    "sg:phone": "+1 937 461 1105",
    "sg:postcode": "45402",
    "sg:province": "OH",
    "sg:tags": [
      "furnishing"
    ],
    "wof:name": "Jeans Glory",
    "wof:placetype": "venue"
  },
  "geometry": {"coordinates":[-84.191809,39.759537],"type":"Point"}
}
