{
  "type": "Feature",
  "properties": {
    "addr:full": "10508 W Pine Lake Rd Salem OH 44460",
    "addr:housenumber": "10508",
    "addr:postcode": "44460",
    "addr:street": "W Pine Lake Rd",
    "iso:country": "US",
    "sg:address": "10508 W Pine Lake Rd",
    "sg:city": "Salem",
    "sg:classifiers": [
      {
        "category": "Building \u0026 Trades",
        "subcategory": "Electrical",
        "type": "Services"
      }
    ],
    "sg:phone": "+1 330 332 0541",
    "sg:postcode": "44460",
    "sg:province": "OH",
    "sg:tags": [
      "electrical",
      "contractor"
    ],
    "wof:name": "Fender Heating AC Plbg",
    "wof:placetype": "venue"
  },
  "geometry": {"coordinates":[-80.84755,40.929846],"type":"Point"}
}
