{
  "type": "Feature",
  "properties": {
    "iso:country":"US",
    "sg:address":"2340 Lancaster-Newark Rd NE",
    "sg:city":"Lancaster",
    "sg:classifiers":[
        {
            "category":"Autos & Motor Vehicles",
            "subcategory":"Fuel & Gas Station",
            "type":"Retail Goods"
        }
    ],
    "sg:phone":"+1 740 246 6118",
    "sg:postcode":"43130",
    "sg:province":"OH",
    "sg:tags":[
        "grocery",
        "station",
        "gasoline"
    ],
    "wof:name":"Village Pantry",
    "wof:placetype":"venue"
},
  "geometry": {"coordinates":[-82.58235000000001,39.754234],"type":"Point"}
}