{
  "type": "Feature",
  "properties": {
    "iso:country":"US",
    "sg:address":"5909 Stewart Ave",
    "sg:city":"Cincinnati",
    "sg:classifiers":[
        {
            "category":"Wholesale",
            "subcategory":"Durable Goods & Equipment",
            "type":"Manufacturing & Wholesale Goods"
        }
    ],
    "sg:phone":"+1 513 271 0099",
    "sg:postcode":"45227",
    "sg:province":"OH",
    "sg:tags":[
        "representative",
        "manufacturer"
    ],
    "wof:name":"Petrie-Ingram",
    "wof:placetype":"venue"
},
  "geometry": {"coordinates":[-84.397288,39.173544],"type":"Point"}
}