{
  "type": "Feature",
  "properties": {
    "addr:full": "5909 Stewart Ave Cincinnati OH 45227",
    "addr:housenumber": "5909",
    "addr:postcode": "45227",
    "addr:street": "Stewart Ave",
    "iso:country": "US",
    "sg:address": "5909 Stewart Ave",
    "sg:city": "Cincinnati",
    "sg:classifiers": [
      {
        "category": "Wholesale",
        "subcategory": "Durable Goods \u0026 Equipment",
        "type": "Manufacturing \u0026 Wholesale Goods"
      }
    ],
    "sg:phone": "+1 513 271 0099",
    "sg:postcode": "45227",
    "sg:province": "OH",
    "sg:tags": [
      "representative",
      "manufacturer"
    ],
    "wof:name": "Petrie-Ingram",
    "wof:placetype": "venue"
  },
  "geometry": {"coordinates":[-84.397288,39.173544],"type":"Point"}
}
