{
  "type": "Feature",
  "properties": {
    "iso:country":"US",
    "sg:address":"600 S Pearl St",
    "sg:city":"Columbus",
    "sg:classifiers":[
        {
            "category":"Professional",
            "subcategory":"Lawyer & Legal Services",
            "type":"Services"
        }
    ],
    "sg:phone":"+1 614 221 1662",
    "sg:postcode":"43206",
    "sg:province":"OH",
    "sg:tags":[
        "attorney"
    ],
    "wof:name":"Frank & Wooldridge Co Lpa",
    "wof:placetype":"venue"
},
  "geometry": {"coordinates":[-82.997024,39.948669],"type":"Point"}
}