{
  "type": "Feature",
  "properties": {
    "addr:full":"16346 Twp Hwy 166 Arlington OH 45814",
    "addr:postcode":"16346;45814",
    "addr:street":"Twp Hwy 166",
    "iso:country":"US",
    "sg:address":"16346 Twp Hwy 166",
    "sg:city":"Arlington",
    "sg:classifiers":[
        {
            "category":"Organizations",
            "subcategory":"Religious Organization",
            "type":"Services"
        }
    ],
    "sg:phone":"+1 419 424 3188",
    "sg:postcode":"45814",
    "sg:province":"OH",
    "sg:tags":[
        "clergy"
    ],
    "wof:name":"Christopher Cravens",
    "wof:placetype":"venue"
},
  "geometry": {"coordinates":[-83.570609,40.957015],"type":"Point"}
}