{
  "type": "Feature",
  "properties": {
    "addr:full":"8548 Market Ave N Canton OH 44721",
    "addr:housenumber":"8548",
    "addr:postcode":"44721",
    "addr:street":"Market Ave N",
    "iso:country":"US",
    "sg:address":"8548 Market Ave N",
    "sg:city":"Canton",
    "sg:classifiers":[
        {
            "category":"Building & Trades",
            "subcategory":"Construction",
            "type":"Services"
        }
    ],
    "sg:phone":"+1 330 497 7265",
    "sg:postcode":"44721",
    "sg:province":"OH",
    "sg:tags":[
        "house"
    ],
    "wof:name":"Acinom",
    "wof:placetype":"venue"
},
  "geometry": {"coordinates":[-81.362121,40.906261],"type":"Point"}
}