{
  "type": "Feature",
  "properties": {
    "addr:full": "4600 International Gtwy Columbus OH 43219",
    "addr:housenumber": "4600",
    "addr:postcode": "43219",
    "addr:street": "International Gtwy",
    "iso:country": "US",
    "sg:address": "4600 International Gtwy",
    "sg:city": "Columbus",
    "sg:classifiers": [
      {
        "category": "Restaurant",
        "type": "Food \u0026 Drink"
      }
    ],
    "sg:menulink": "http://www.allmenus.com/oh/columbus/95898-charleys-grilled-subs/menu/",
    "sg:phone": "+1 614 238 6615",
    "sg:postcode": "43219",
    "sg:province": "OH",
    "sg:tags": [
      "wrap",
      "american",
      "sandwich"
    ],
    "wof:name": "Charley's Grilled Subs",
    "wof:placetype": "venue"
  },
  "geometry": {"coordinates":[-82.884704,39.99819],"type":"Point"}
}
