{
  "type": "Feature",
  "properties": {
    "addr:full":"3001 Cleveland Ave SW Canton OH 44707",
    "addr:housenumber":"3001",
    "addr:postcode":"44707",
    "addr:street":"Cleveland Ave Sw",
    "iso:country":"US",
    "sg:address":"3001 Cleveland Ave SW",
    "sg:city":"Canton",
    "sg:classifiers":[
        {
            "category":"Banks & Credit Unions",
            "subcategory":"Bank",
            "type":"Services"
        }
    ],
    "sg:phone":"+1 330 484 3954",
    "sg:postcode":"44707",
    "sg:province":"OH",
    "sg:tags":[
        "national",
        "commercial"
    ],
    "wof:name":"Keybank National Association",
    "wof:placetype":"venue"
},
  "geometry": {"coordinates":[-81.380663,40.763023],"type":"Point"}
}