{
  "type": "Feature",
  "properties": {
    "addr:full":"7 Town Sq Lima OH 45801",
    "addr:housenumber":"7",
    "addr:postcode":"45801",
    "addr:street":"Town Sq",
    "iso:country":"US",
    "sg:address":"7 Town Sq",
    "sg:city":"Lima",
    "sg:classifiers":[
        {
            "category":"Personal",
            "type":"Services"
        }
    ],
    "sg:phone":"+1 419 224 5222",
    "sg:postcode":"45801",
    "sg:province":"OH",
    "sg:tags":[
        "group"
    ],
    "wof:name":"Veterans Mem Cvic Cnvntion Ctr",
    "wof:placetype":"venue"
},
  "geometry": {"coordinates":[-84.10533,40.739783],"type":"Point"}
}