{
  "type": "Feature",
  "properties": {
    "addr:full": "1081 Rosemary Blvd Akron OH 44306",
    "addr:housenumber": "1081",
    "addr:postcode": "44306",
    "addr:street": "Rosemary Blvd",
    "iso:country": "US",
    "sg:address": "1081 Rosemary Blvd",
    "sg:city": "Akron",
    "sg:classifiers": [
      {
        "category": "Manufacturing",
        "subcategory": "Petroleum Products",
        "type": "Manufacturing \u0026 Wholesale Goods"
      }
    ],
    "sg:phone": "+1 330 773 7669",
    "sg:postcode": "44306",
    "sg:province": "OH",
    "sg:tags": [
      "lubricating",
      "mfg"
    ],
    "wof:name": "Koki Laboratories",
    "wof:placetype": "venue"
  },
  "geometry": {"coordinates":[-81.485665,41.035445],"type":"Point"}
}
