{
  "type": "Feature",
  "properties": {
    "iso:country":"US",
    "sg:address":"1736 Bailey Rd",
    "sg:city":"Cuyahoga Falls",
    "sg:classifiers":[
        {
            "category":"Organizations",
            "subcategory":"Religious Organization",
            "type":"Services"
        }
    ],
    "sg:phone":"+1 330 945 9325",
    "sg:postcode":"44221",
    "sg:province":"OH",
    "wof:name":"Falls Community Chapel",
    "wof:placetype":"venue"
},
  "geometry": {"coordinates":[-81.465499,41.12819],"type":"Point"}
}