{
  "type": "Feature",
  "properties": {
    "addr:full":"325 N Warpole St Upper Sandusky OH 43351",
    "addr:housenumber":"325",
    "addr:postcode":"43351",
    "addr:street":"N Warpole St",
    "iso:country":"US",
    "sg:address":"325 N Warpole St",
    "sg:city":"Upper Sandusky",
    "sg:classifiers":[
        {
            "category":"Travel",
            "subcategory":"Hotels & Motels",
            "type":"Entertainment"
        }
    ],
    "sg:phone":"+1 419 294 5161",
    "sg:postcode":"43351",
    "sg:province":"OH",
    "wof:name":"Day's Motel/Like Father",
    "wof:placetype":"venue"
},
  "geometry": {"coordinates":[-83.290024,40.831879],"type":"Point"}
}