{
  "type": "Feature",
  "properties": {
    "iso:country":"US",
    "sg:address":"78 Plaza Blvd",
    "sg:city":"Chillicothe",
    "sg:classifiers":[
        {
            "category":"Professional",
            "subcategory":"Accounting & Tax Preparation",
            "type":"Services"
        }
    ],
    "sg:phone":"+1 740 775 8448",
    "sg:postcode":"45601",
    "sg:province":"OH",
    "sg:tags":[
        "accountant"
    ],
    "wof:name":"J L Uhrig & Assoc",
    "wof:placetype":"venue"
},
  "geometry": {"coordinates":[-82.97876599999999,39.350002],"type":"Point"}
}