{
  "type": "Feature",
  "properties": {
    "addr:full": "78 Plaza Blvd Chillicothe OH 45601",
    "addr:housenumber": "78",
    "addr:postcode": "45601",
    "addr:street": "Plaza Blvd",
    "iso:country": "US",
    "sg:address": "78 Plaza Blvd",
    "sg:city": "Chillicothe",
    "sg:classifiers": [
      {
        "category": "Professional",
        "subcategory": "Accounting \u0026 Tax Preparation",
        "type": "Services"
      }
    ],
    "sg:phone": "+1 740 775 8448",
    "sg:postcode": "45601",
    "sg:province": "OH",
    "sg:tags": [
      "accountant"
    ],
    "wof:name": "J L Uhrig \u0026 Assoc",
    "wof:placetype": "venue"
  },
  "geometry": {"coordinates":[-82.978766,39.350002],"type":"Point"}
}
