{
  "type": "Feature",
  "properties": {
    "addr:full":"400 Lookout Ct Avon Lake OH 44012",
    "addr:housenumber":"400",
    "addr:postcode":"44012",
    "addr:street":"Lookout Ct",
    "iso:country":"US",
    "sg:address":"400 Lookout Ct",
    "sg:city":"Avon Lake",
    "sg:classifiers":[
        {
            "category":"Professional",
            "subcategory":"Management & Consulting",
            "type":"Services"
        }
    ],
    "sg:phone":"+1 440 930 4852",
    "sg:postcode":"44012",
    "sg:province":"OH",
    "sg:tags":[
        "consultant",
        "business"
    ],
    "wof:name":"Quality Solutions Inc",
    "wof:placetype":"venue"
},
  "geometry": {"coordinates":[-81.976221,41.496909],"type":"Point"}
}