{
  "type": "Feature",
  "properties": {
    "addr:full": "5471 State Rte 546 Bellville OH 44813",
    "addr:housenumber": "5471",
    "addr:postcode": "44813",
    "addr:street": "State Rte 546",
    "iso:country": "US",
    "sg:address": "5471 State Rte 546",
    "sg:city": "Bellville",
    "sg:classifiers": [
      {
        "category": "Organizations",
        "subcategory": "Religious Organization",
        "type": "Services"
      }
    ],
    "sg:phone": "+1 419 886 2128",
    "sg:postcode": "44813",
    "sg:province": "OH",
    "sg:tags": [
      "church"
    ],
    "wof:name": "Pleasant Grove Community Chr",
    "wof:placetype": "venue"
  },
  "geometry": {"coordinates":[-82.587611,40.608132],"type":"Point"}
}
