{
  "type": "Feature",
  "properties": {
    "addr:full":"9945 Vail Dr Twinsburg OH 44087",
    "addr:housenumber":"9945",
    "addr:postcode":"44087",
    "addr:street":"Vail Dr",
    "iso:country":"US",
    "sg:address":"9945 Vail Dr",
    "sg:city":"Twinsburg",
    "sg:classifiers":[
        {
            "category":"Real Estate",
            "subcategory":"Real Estate Operator",
            "type":"Services"
        }
    ],
    "sg:phone":"+1 330 425 0912",
    "sg:postcode":"44087",
    "sg:province":"OH",
    "sg:tags":[
        "property",
        "lessor"
    ],
    "wof:name":"Two Guys Named Larry LLC",
    "wof:placetype":"venue"
},
  "geometry": {"coordinates":[-81.436616,41.339471],"type":"Point"}
}