{
  "type": "Feature",
  "properties": {
    "addr:full":"1000 W State St Alliance OH 44601",
    "addr:housenumber":"1000",
    "addr:postcode":"44601",
    "addr:street":"W State St",
    "iso:country":"US",
    "sg:address":"1000 W State St",
    "sg:city":"Alliance",
    "sg:classifiers":[
        {
            "category":"Sports & Exercise",
            "subcategory":"Bowling",
            "type":"Entertainment"
        }
    ],
    "sg:phone":"+1 330 821 9200",
    "sg:postcode":"44601",
    "sg:province":"OH",
    "sg:tags":[
        "drinking",
        "center"
    ],
    "wof:name":"Parkway Lanes Inc",
    "wof:placetype":"venue"
},
  "geometry": {"coordinates":[-81.12122100000001,40.901736],"type":"Point"}
}