{
  "type": "Feature",
  "properties": {
    "addr:full": "61 E Noble St Marengo OH 43334",
    "addr:housenumber": "61",
    "addr:postcode": "43334",
    "addr:street": "E Noble St",
    "iso:country": "US",
    "sg:address": "61 E Noble St",
    "sg:city": "Marengo",
    "sg:classifiers": [
      {
        "category": "Manufacturing",
        "subcategory": "Glass \u0026 Minerals",
        "type": "Manufacturing \u0026 Wholesale Goods"
      }
    ],
    "sg:phone": "+1 419 253 2481",
    "sg:postcode": "43334",
    "sg:province": "OH",
    "sg:tags": [
      "concrete",
      "brick"
    ],
    "wof:name": "Snyder's Milling Svc Inc",
    "wof:placetype": "venue"
  },
  "geometry": {"coordinates":[-82.808977,40.402037],"type":"Point"}
}
