{
  "type": "Feature",
  "properties": {
    "iso:country":"US",
    "sg:address":"61 E Noble St",
    "sg:city":"Marengo",
    "sg:classifiers":[
        {
            "category":"Manufacturing",
            "subcategory":"Glass & Minerals",
            "type":"Manufacturing & Wholesale Goods"
        }
    ],
    "sg:phone":"+1 419 253 2481",
    "sg:postcode":"43334",
    "sg:province":"OH",
    "sg:tags":[
        "concrete",
        "brick"
    ],
    "wof:name":"Snyder's Milling Svc Inc",
    "wof:placetype":"venue"
},
  "geometry": {"coordinates":[-82.808977,40.402037],"type":"Point"}
}