{
  "type": "Feature",
  "properties": {
    "addr:full":"11729 Snow Rd Cleveland OH 44130",
    "addr:housenumber":"11729",
    "addr:postcode":"44130",
    "addr:street":"Snow Rd",
    "iso:country":"US",
    "sg:address":"11729 Snow Rd",
    "sg:city":"Cleveland",
    "sg:classifiers":[
        {
            "category":"Organizations",
            "subcategory":"Community Association",
            "type":"Services"
        }
    ],
    "sg:phone":"+1 440 885 7050",
    "sg:postcode":"44130",
    "sg:province":"OH",
    "sg:tags":[
        "fraternal"
    ],
    "sg:website":"www.foe.com",
    "wof:name":"Fraternal Order Of Eagles",
    "wof:placetype":"venue"
},
  "geometry": {"coordinates":[-81.77098599999999,41.404962],"type":"Point"}
}