{
  "type": "Feature",
  "properties": {
    "iso:country":"US",
    "sg:address":"345 N Market St",
    "sg:city":"Wooster",
    "sg:classifiers":[
        {
            "category":"Insurance",
            "subcategory":"Insurance Agent",
            "type":"Services"
        }
    ],
    "sg:phone":"+1 330 263 0622",
    "sg:postcode":"44691",
    "sg:province":"OH",
    "wof:name":"Johnston Miller Campbell",
    "wof:placetype":"venue"
},
  "geometry": {"coordinates":[-81.940801,40.801679],"type":"Point"}
}