{
  "type": "Feature",
  "properties": {
    "iso:country":"US",
    "sg:address":"2495 Lee Blvd",
    "sg:city":"Cleveland",
    "sg:classifiers":[
        {
            "category":"Shopping",
            "subcategory":"Crafts & Fabrics",
            "type":"Retail Goods"
        }
    ],
    "sg:phone":"+1 216 321 2687",
    "sg:postcode":"44118",
    "sg:province":"OH",
    "sg:tags":[
        "sewing"
    ],
    "wof:name":"Susan Yarns",
    "wof:placetype":"venue"
},
  "geometry": {"coordinates":[-81.569302,41.516697],"type":"Point"}
}