{
  "type": "Feature",
  "properties": {
    "iso:country":"US",
    "sg:address":"680 Siebert St",
    "sg:city":"Columbus",
    "sg:classifiers":[
        {
            "category":"Professional",
            "type":"Services"
        }
    ],
    "sg:phone":"+1 614 445 8495",
    "sg:postcode":"43206",
    "sg:province":"OH",
    "wof:name":"Remey Haxel",
    "wof:placetype":"venue"
},
  "geometry": {"coordinates":[-82.978556,39.94223],"type":"Point"}
}