{
  "type": "Feature",
  "properties": {
    "addr:full":"567 Westminster Cir Akron OH 44319",
    "addr:housenumber":"567",
    "addr:postcode":"44319",
    "addr:street":"Westminster Cir",
    "iso:country":"US",
    "sg:address":"567 Westminster Cir",
    "sg:city":"Akron",
    "sg:classifiers":[
        {
            "category":"Health Services",
            "subcategory":"Clinic",
            "type":"Services"
        }
    ],
    "sg:phone":"+1 330 848 9775",
    "sg:postcode":"44319",
    "sg:province":"OH",
    "sg:tags":[
        "home"
    ],
    "wof:name":"DOC Homecare",
    "wof:placetype":"venue"
},
  "geometry": {"coordinates":[-81.507392,41.022023],"type":"Point"}
}