{
  "type": "Feature",
  "properties": {
    "addr:full":"7012 Mill Rd Brecksville OH 44141",
    "addr:housenumber":"7012",
    "addr:postcode":"44141",
    "addr:street":"Mill Rd",
    "iso:country":"US",
    "sg:address":"7012 Mill Rd",
    "sg:city":"Brecksville",
    "sg:classifiers":[
        {
            "category":"Wholesale",
            "subcategory":"Durable Goods & Equipment",
            "type":"Manufacturing & Wholesale Goods"
        }
    ],
    "sg:phone":"+1 440 746 9555",
    "sg:postcode":"44141",
    "sg:province":"OH",
    "wof:name":"Korr Sales Co",
    "wof:placetype":"venue"
},
  "geometry": {"coordinates":[-81.631548,41.326318],"type":"Point"}
}