{
  "type": "Feature",
  "properties": {
    "addr:full":"1343 N Fountain Blvd Springfield OH 45504",
    "addr:housenumber":"1343",
    "addr:postcode":"45504",
    "addr:street":"N Fountain Blvd",
    "iso:country":"US",
    "sg:address":"1343 N Fountain Blvd",
    "sg:city":"Springfield",
    "sg:classifiers":[
        {
            "category":"Wholesale",
            "subcategory":"Medical Equipment & Supplies",
            "type":"Manufacturing & Wholesale Goods"
        }
    ],
    "sg:phone":"+1 937 390 5228",
    "sg:postcode":"45504",
    "sg:province":"OH",
    "sg:tags":[
        "alarm"
    ],
    "wof:name":"Mercy Lifeline",
    "wof:placetype":"venue"
},
  "geometry": {"coordinates":[-83.808924,39.940714],"type":"Point"}
}