{
  "type": "Feature",
  "properties": {
    "addr:full":"112 Yorkshire Ct Elyria OH 44035",
    "addr:housenumber":"112",
    "addr:postcode":"44035",
    "addr:street":"Yorkshire Ct",
    "iso:country":"US",
    "sg:address":"112 Yorkshire Ct",
    "sg:city":"Elyria",
    "sg:classifiers":[
        {
            "category":"Building & Trades",
            "subcategory":"Construction",
            "type":"Services"
        }
    ],
    "sg:phone":"+1 440 365 1937",
    "sg:postcode":"44035",
    "sg:province":"OH",
    "sg:tags":[
        "excavation",
        "contractor"
    ],
    "wof:name":"KASE Excavating",
    "wof:placetype":"venue"
},
  "geometry": {"coordinates":[-82.07851700000001,41.374546],"type":"Point"}
}