{
  "type": "Feature",
  "properties": {
    "iso:country":"US",
    "sg:address":"2975 Janet Cir",
    "sg:city":"Columbus",
    "sg:classifiers":[
        {
            "category":"Real Estate",
            "subcategory":"Real Estate Operator",
            "type":"Services"
        }
    ],
    "sg:phone":"+1 614 235 3334",
    "sg:postcode":"43209",
    "sg:province":"OH",
    "sg:tags":[
        "apartment"
    ],
    "wof:name":"Janet Circle",
    "wof:placetype":"venue"
},
  "geometry": {"coordinates":[-82.923365,39.97853],"type":"Point"}
}