{
  "type": "Feature",
  "properties": {
    "iso:country":"US",
    "sg:address":"6935 E Broad St",
    "sg:city":"Columbus",
    "sg:classifiers":[
        {
            "category":"Bars & Pubs",
            "type":"Food & Drink"
        }
    ],
    "sg:phone":"+1 614 575 9811",
    "sg:postcode":"43213",
    "sg:province":"OH",
    "sg:tags":[
        "drinking"
    ],
    "wof:name":"Donericks Pub House",
    "wof:placetype":"venue"
},
  "geometry": {"coordinates":[-82.81533399999999,39.982493],"type":"Point"}
}