{
  "type": "Feature",
  "properties": {
    "addr:full": "6935 E Broad St Columbus OH 43213",
    "addr:housenumber": "6935",
    "addr:postcode": "43213",
    "addr:street": "E Broad St",
    "iso:country": "US",
    "sg:address": "6935 E Broad St",
    "sg:city": "Columbus",
    "sg:classifiers": [
      {
        "category": "Bars \u0026 Pubs",
        "type": "Food \u0026 Drink"
      }
    ],
    "sg:phone": "+1 614 575 9811",
    "sg:postcode": "43213",
    "sg:province": "OH",
    "sg:tags": [
      "drinking"
    ],
    "wof:name": "Donericks Pub House",
    "wof:placetype": "venue"
  },
  "geometry": {"coordinates":[-82.815334,39.982493],"type":"Point"}
}
