{
  "type": "Feature",
  "properties": {
    "addr:full": "4281 Ingham Ave Columbus OH 43214",
    "addr:housenumber": "4281",
    "addr:postcode": "43214",
    "addr:street": "Ingham Ave",
    "iso:country": "US",
    "sg:address": "4281 Ingham Ave",
    "sg:city": "Columbus",
    "sg:classifiers": [
      {
        "category": "Shopping",
        "subcategory": "Gifts \u0026 Souvenirs",
        "type": "Retail Goods"
      }
    ],
    "sg:phone": "+1 614 263 5796",
    "sg:postcode": "43214",
    "sg:province": "OH",
    "wof:name": "Pepperberry Cottage",
    "wof:placetype": "venue"
  },
  "geometry": {"coordinates":[-83.011876,40.051026],"type":"Point"}
}
