{
  "type": "Feature",
  "properties": {
    "iso:country":"US",
    "sg:address":"11260 Cornell Park Dr",
    "sg:city":"Cincinnati",
    "sg:classifiers":[
        {
            "category":"Wholesale",
            "subcategory":"Hardware",
            "type":"Manufacturing & Wholesale Goods"
        }
    ],
    "sg:phone":"+1 513 489 7111",
    "sg:postcode":"45242",
    "sg:province":"OH",
    "sg:tags":[
        "industrial",
        "e"
    ],
    "wof:name":"Ketchum & Walton Co",
    "wof:placetype":"venue"
},
  "geometry": {"coordinates":[-84.372968,39.27347],"type":"Point"}
}