{
  "type": "Feature",
  "properties": {
    "iso:country":"US",
    "sg:address":"499 W Cambridge St",
    "sg:city":"Alliance",
    "sg:classifiers":[
        {
            "category":"Manufacturing",
            "subcategory":"Retail Goods",
            "type":"Manufacturing & Wholesale Goods"
        }
    ],
    "sg:phone":"+1 330 829 9344",
    "sg:postcode":"44601",
    "sg:province":"OH",
    "sg:tags":[
        "product",
        "mfg"
    ],
    "wof:name":"Out of Barn Primitives",
    "wof:placetype":"venue"
},
  "geometry": {"coordinates":[-81.113103,40.916668],"type":"Point"}
}