{
  "type": "Feature",
  "properties": {
    "iso:country":"US",
    "sg:address":"1005 E Long St",
    "sg:city":"Columbus",
    "sg:classifiers":[
        {
            "category":"Personal",
            "subcategory":"Beauty Salon",
            "type":"Services"
        }
    ],
    "sg:phone":"+1 614 252 4247",
    "sg:postcode":"43203",
    "sg:province":"OH",
    "sg:tags":[
        "shop"
    ],
    "wof:name":"Christophers Hair & Nail Salon",
    "wof:placetype":"venue"
},
  "geometry": {"coordinates":[-82.97505099999999,39.967929],"type":"Point"}
}