{
  "type": "Feature",
  "properties": {
    "addr:full":"8529 Springboro Pike Miamisburg OH 45342",
    "addr:housenumber":"8529",
    "addr:postcode":"45342",
    "addr:street":"Springboro Pike",
    "iso:country":"US",
    "sg:address":"8529 Springboro Pike",
    "sg:city":"Miamisburg",
    "sg:classifiers":[
        {
            "category":"Building & Trades",
            "subcategory":"Plumbing",
            "type":"Services"
        }
    ],
    "sg:phone":"+1 937 435 7750",
    "sg:postcode":"45342",
    "sg:province":"OH",
    "sg:tags":[
        "conditioning",
        "air",
        "system",
        "contractor"
    ],
    "wof:name":"Liberty Heating & Air Cond",
    "wof:placetype":"venue"
},
  "geometry": {"coordinates":[-84.226066,39.628266],"type":"Point"}
}