{
  "type": "Feature",
  "properties": {
    "addr:full":"1638 Wertz Ave SW Canton OH 44706",
    "addr:housenumber":"1638",
    "addr:postcode":"44706",
    "addr:street":"Wertz Ave Sw",
    "iso:country":"US",
    "sg:address":"1638 Wertz Ave SW",
    "sg:city":"Canton",
    "sg:classifiers":[
        {
            "category":"Building & Trades",
            "subcategory":"Construction",
            "type":"Services"
        }
    ],
    "sg:phone":"+1 330 453 0651",
    "sg:postcode":"44706",
    "sg:province":"OH",
    "sg:tags":[
        "sewer",
        "contractor"
    ],
    "wof:name":"Liberty Drain Cleaning",
    "wof:placetype":"venue"
},
  "geometry": {"coordinates":[-81.40839800000001,40.781344],"type":"Point"}
}