{
  "type": "Feature",
  "properties": {
    "iso:country":"US",
    "sg:address":"114 Barrington Town Sq",
    "sg:city":"Aurora",
    "sg:classifiers":[
        {
            "category":"Professional",
            "type":"Services"
        }
    ],
    "sg:phone":"+1 330 528 1559",
    "sg:postcode":"44202",
    "sg:province":"OH",
    "sg:tags":[
        "establishment"
    ],
    "wof:name":"Polyrol",
    "wof:placetype":"venue"
},
  "geometry": {"coordinates":[-81.347663,41.318522],"type":"Point"}
}