{
  "type": "Feature",
  "properties": {
    "addr:full": "1779 Celina Rd St Marys OH 45885",
    "addr:housenumber": "1779",
    "addr:postcode": "45885",
    "addr:street": "Celina Rd",
    "iso:country": "US",
    "sg:address": "1779 Celina Rd",
    "sg:city": "St Marys",
    "sg:classifiers": [
      {
        "category": "Retail",
        "subcategory": "Repair Shop",
        "type": "Services"
      }
    ],
    "sg:phone": "+1 419 394 1823",
    "sg:postcode": "45885",
    "sg:province": "OH",
    "sg:tags": [
      "welding"
    ],
    "wof:name": "Weldtec Inc",
    "wof:placetype": "venue"
  },
  "geometry": {"coordinates":[-84.411803,40.544151],"type":"Point"}
}
