{
  "type": "Feature",
  "properties": {
    "addr:full":"7500 Industrial Pkwy Plain City OH 43064",
    "addr:housenumber":"7500",
    "addr:postcode":"43064",
    "addr:street":"Industrial Pkwy",
    "iso:country":"US",
    "sg:address":"7500 Industrial Pkwy",
    "sg:city":"Plain City",
    "sg:classifiers":[
        {
            "category":"Real Estate",
            "subcategory":"Real Estate Operator",
            "type":"Services"
        }
    ],
    "sg:phone":"+1 614 889 0145",
    "sg:postcode":"43064",
    "sg:province":"OH",
    "sg:tags":[
        "building"
    ],
    "wof:name":"Da Ron Investments",
    "wof:placetype":"venue"
},
  "geometry": {"coordinates":[-83.191576,40.12082],"type":"Point"}
}