{
  "type": "Feature",
  "properties": {
    "addr:full": "396 N 12th St Sebring OH 44672",
    "addr:housenumber": "396",
    "addr:postcode": "44672",
    "addr:street": "N 12Th St",
    "iso:country": "US",
    "sg:address": "396 N 12th St",
    "sg:city": "Sebring",
    "sg:classifiers": [
      {
        "category": "Retail",
        "subcategory": "Auto Repair",
        "type": "Services"
      }
    ],
    "sg:phone": "+1 330 938 6831",
    "sg:postcode": "44672",
    "sg:province": "OH",
    "sg:tags": [
      "body",
      "automobile",
      "painting"
    ],
    "wof:name": "Ohio Ave Garage",
    "wof:placetype": "venue"
  },
  "geometry": {"coordinates":[-81.012619,40.924288],"type":"Point"}
}
