{
  "type": "Feature",
  "properties": {
    "iso:country":"US",
    "sg:address":"4235 Thunderbird Ln",
    "sg:city":"Fairfield",
    "sg:classifiers":[
        {
            "category":"Wholesale",
            "subcategory":"Groceries",
            "type":"Manufacturing & Wholesale Goods"
        }
    ],
    "sg:phone":"+1 513 874 2155",
    "sg:postcode":"45014",
    "sg:province":"OH",
    "sg:tags":[
        "frozen",
        "packaged",
        "general"
    ],
    "sg:website":"www.usfoodservice.com",
    "wof:name":"US Foodservice",
    "wof:placetype":"venue"
},
  "geometry": {"coordinates":[-84.48573,39.329138],"type":"Point"}
}