{
  "type": "Feature",
  "properties": {
    "addr:full":"5155 Warner Rd Cleveland OH 44125",
    "addr:housenumber":"5155",
    "addr:postcode":"44125",
    "addr:street":"Warner Rd",
    "iso:country":"US",
    "sg:address":"5155 Warner Rd",
    "sg:city":"Cleveland",
    "sg:classifiers":[
        {
            "category":"Freight",
            "type":"Transportation"
        }
    ],
    "sg:phone":"+1 216 341 4800",
    "sg:postcode":"44125",
    "sg:province":"OH",
    "sg:tags":[
        "local",
        "general",
        "storage",
        "t",
        "trucking"
    ],
    "wof:name":"Containerport Group Inc",
    "wof:placetype":"venue"
},
  "geometry": {"coordinates":[-81.633416,41.430825],"type":"Point"}
}