{
  "type": "Feature",
  "properties": {
    "addr:full":"4140 Dresden Rd Zanesville OH 43701",
    "addr:housenumber":"4140",
    "addr:postcode":"43701",
    "addr:street":"Dresden Rd",
    "iso:country":"US",
    "sg:address":"4140 Dresden Rd",
    "sg:city":"Zanesville",
    "sg:classifiers":[
        {
            "category":"Building & Trades",
            "subcategory":"Plumbing",
            "type":"Services"
        }
    ],
    "sg:phone":"+1 740 452 7004",
    "sg:postcode":"43701",
    "sg:province":"OH",
    "sg:tags":[
        "contractor"
    ],
    "wof:name":"All Temp Heating & Cooling",
    "wof:placetype":"venue"
},
  "geometry": {"coordinates":[-82.00471400000001,40.007697],"type":"Point"}
}