{
  "type": "Feature",
  "properties": {
    "iso:country":"US",
    "sg:address":"7865 Paragon Rd",
    "sg:city":"Dayton",
    "sg:classifiers":[
        {
            "category":"Real Estate",
            "subcategory":"Real Estate Operator",
            "type":"Services"
        }
    ],
    "sg:phone":"+1 937 435 5166",
    "sg:postcode":"45459",
    "sg:province":"OH",
    "sg:tags":[
        "condominium"
    ],
    "wof:name":"Princeton Management Co",
    "wof:placetype":"venue"
},
  "geometry": {"coordinates":[-84.1789,39.633083],"type":"Point"}
}