{
  "type": "Feature",
  "properties": {
    "addr:full":"7930 Winterberry Pl Cincinnati OH 45241",
    "addr:housenumber":"7930",
    "addr:postcode":"45241",
    "addr:street":"Winterberry Pl",
    "iso:country":"US",
    "sg:address":"7930 Winterberry Pl",
    "sg:city":"Cincinnati",
    "sg:classifiers":[
        {
            "category":"Shopping",
            "subcategory":"Books",
            "type":"Retail Goods"
        }
    ],
    "sg:phone":"+1 513 779 3725",
    "sg:postcode":"45241",
    "sg:province":"OH",
    "wof:name":"Ren Wen Books LLC",
    "wof:placetype":"venue"
},
  "geometry": {"coordinates":[-84.365302,39.307101],"type":"Point"}
}