{
  "type": "Feature",
  "properties": {
    "addr:full": "4467 Gallia Pike Franklin Furnace OH 45629",
    "addr:housenumber": "4467",
    "addr:postcode": "45629",
    "addr:street": "Gallia Pike",
    "iso:country": "US",
    "sg:address": "4467 Gallia Pike",
    "sg:city": "Franklin Furnace",
    "sg:classifiers": [
      {
        "category": "Food \u0026 Beverages",
        "subcategory": "Groceries \u0026 Convenience Stores",
        "type": "Retail Goods"
      }
    ],
    "sg:phone": "+1 740 354 9000",
    "sg:postcode": "45629",
    "sg:province": "OH",
    "sg:tags": [
      "market"
    ],
    "wof:name": "Blanton \u0026 Graff Market",
    "wof:placetype": "venue"
  },
  "geometry": {"coordinates":[-82.843585,38.620886],"type":"Point"}
}
