{
  "type": "Feature",
  "properties": {
    "iso:country":"US",
    "sg:address":"4467 Gallia Pike",
    "sg:city":"Franklin Furnace",
    "sg:classifiers":[
        {
            "category":"Food & Beverages",
            "subcategory":"Groceries & Convenience Stores",
            "type":"Retail Goods"
        }
    ],
    "sg:phone":"+1 740 354 9000",
    "sg:postcode":"45629",
    "sg:province":"OH",
    "sg:tags":[
        "market"
    ],
    "wof:name":"Blanton & Graff Market",
    "wof:placetype":"venue"
},
  "geometry": {"coordinates":[-82.843585,38.620886],"type":"Point"}
}