{
  "type": "Feature",
  "properties": {
    "addr:full":"24537 Canal Rd Circleville OH 43113",
    "addr:housenumber":"24537",
    "addr:postcode":"43113",
    "addr:street":"Canal Rd",
    "iso:country":"US",
    "sg:address":"24537 Canal Rd",
    "sg:city":"Circleville",
    "sg:classifiers":[
        {
            "category":"Wholesale",
            "subcategory":"Construction Materials",
            "type":"Manufacturing & Wholesale Goods"
        }
    ],
    "sg:phone":"+1 740 474 2134",
    "sg:postcode":"43113",
    "sg:province":"OH",
    "sg:tags":[
        "sand",
        "gravel"
    ],
    "wof:name":"Melvin Stone Co",
    "wof:placetype":"venue"
},
  "geometry": {"coordinates":[-82.98715799999999,39.561556],"type":"Point"}
}