{
  "type": "Feature",
  "properties": {
    "addr:full": "24537 Canal Rd Circleville OH 43113",
    "addr:housenumber": "24537",
    "addr:postcode": "43113",
    "addr:street": "Canal Rd",
    "iso:country": "US",
    "sg:address": "24537 Canal Rd",
    "sg:city": "Circleville",
    "sg:classifiers": [
      {
        "category": "Wholesale",
        "subcategory": "Construction Materials",
        "type": "Manufacturing \u0026 Wholesale Goods"
      }
    ],
    "sg:phone": "+1 740 474 2134",
    "sg:postcode": "43113",
    "sg:province": "OH",
    "sg:tags": [
      "sand",
      "gravel"
    ],
    "wof:name": "Melvin Stone Co",
    "wof:placetype": "venue"
  },
  "geometry": {"coordinates":[-82.987158,39.561556],"type":"Point"}
}
