{
  "type": "Feature",
  "properties": {
    "addr:full": "101 N Limestone St Springfield OH 45503",
    "addr:housenumber": "101",
    "addr:postcode": "45503",
    "addr:street": "N Limestone St",
    "iso:country": "US",
    "sg:address": "101 N Limestone St",
    "sg:city": "Springfield",
    "sg:classifiers": [
      {
        "category": "Government",
        "subcategory": "Court House",
        "type": "Public Place"
      }
    ],
    "sg:phone": "+1 937 328 2653",
    "sg:postcode": "45503",
    "sg:province": "OH",
    "wof:name": "2nd District Court of Appeals",
    "wof:placetype": "venue"
  },
  "geometry": {"coordinates":[-83.808233,39.927021],"type":"Point"}
}
