{
  "type": "Feature",
  "properties": {
    "addr:full": "4852 Galion-New Winchester Rd Galion OH 44833",
    "addr:housenumber": "4852",
    "addr:postcode": "44833",
    "addr:street": "Galion-New Winchester Rd",
    "iso:country": "US",
    "sg:address": "4852 Galion-New Winchester Rd",
    "sg:city": "Galion",
    "sg:phone": "+1 419 468 4098",
    "sg:postcode": "44833",
    "sg:province": "OH",
    "sg:tags": [
      "farm"
    ],
    "wof:name": "W Walter Eldon",
    "wof:placetype": "venue"
  },
  "geometry": {"coordinates":[-82.872394,40.733409],"type":"Point"}
}
