{
  "type": "Feature",
  "properties": {
    "iso:country":"US",
    "sg:address":"383 E Woodside Ter",
    "sg:city":"Holland",
    "sg:classifiers":[
        {
            "category":"Freight",
            "type":"Transportation"
        }
    ],
    "sg:phone":"+1 419 467 2932",
    "sg:postcode":"43528",
    "sg:province":"OH",
    "sg:tags":[
        "operator",
        "local",
        "trucking"
    ],
    "wof:name":"Batdorf Trucking",
    "wof:placetype":"venue"
},
  "geometry": {"coordinates":[-83.723229,41.619618],"type":"Point"}
}