{
  "type": "Feature",
  "properties": {
    "iso:country":"US",
    "sg:address":"508 S Hill Park Dr",
    "sg:city":"Holland",
    "sg:classifiers":[
        {
            "category":"Building & Trades",
            "subcategory":"Landscaping Services",
            "type":"Services"
        }
    ],
    "sg:phone":"+1 419 356 1000",
    "sg:postcode":"43528",
    "sg:province":"OH",
    "wof:name":"Toledo City Landscape",
    "wof:placetype":"venue"
},
  "geometry": {"coordinates":[-83.695821,41.630771],"type":"Point"}
}