{
  "type": "Feature",
  "properties": {
    "addr:full":"8995 W Salem Rd West Salem OH 44287",
    "addr:housenumber":"8995",
    "addr:postcode":"44287",
    "addr:street":"W Salem Rd",
    "iso:country":"US",
    "sg:address":"8995 W Salem Rd",
    "sg:city":"West Salem",
    "sg:classifiers":[
        {
            "category":"Freight",
            "type":"Transportation"
        }
    ],
    "sg:phone":"+1 419 853 4555",
    "sg:postcode":"44287",
    "sg:province":"OH",
    "sg:tags":[
        "trucking"
    ],
    "wof:name":"Devore Trucking Inc",
    "wof:placetype":"venue"
},
  "geometry": {"coordinates":[-82.08862499999999,40.98165],"type":"Point"}
}