{
  "type": "Feature",
  "properties": {
    "iso:country":"US",
    "sg:address":"753 McPherson St",
    "sg:city":"Mansfield",
    "sg:classifiers":[
        {
            "category":"Freight",
            "type":"Transportation"
        }
    ],
    "sg:phone":"+1 419 525 2329",
    "sg:postcode":"44903",
    "sg:province":"OH",
    "sg:tags":[
        "operator",
        "local",
        "trucking"
    ],
    "wof:name":"Briggs Trucking Inc",
    "wof:placetype":"venue"
},
  "geometry": {"coordinates":[-82.54198,40.771197],"type":"Point"}
}