{
  "type": "Feature",
  "properties": {
    "addr:full": "3330 S Main St Akron OH 44319",
    "addr:housenumber": "3330",
    "addr:postcode": "44319",
    "addr:street": "S Main St",
    "iso:country": "US",
    "sg:address": "3330 S Main St",
    "sg:city": "Akron",
    "sg:classifiers": [
      {
        "category": "Retail",
        "subcategory": "Repair Shop",
        "type": "Services"
      },
      {
        "category": "Autos \u0026 Motor Vehicles",
        "subcategory": "Recreational Vehicle Sales",
        "type": "Retail Goods"
      }
    ],
    "sg:phone": "+1 330 644 0462",
    "sg:postcode": "44319",
    "sg:province": "OH",
    "sg:tags": [
      "parts",
      "trailer",
      "welding"
    ],
    "wof:name": "Priess Welding \u0026 Summit Trlr",
    "wof:placetype": "venue"
  },
  "geometry": {"coordinates":[-81.522743,40.993816],"type":"Point"}
}
