{
  "type": "Feature",
  "properties": {
    "iso:country":"US",
    "sg:address":"3330 S Main St",
    "sg:city":"Akron",
    "sg:classifiers":[
        {
            "category":"Retail",
            "subcategory":"Repair Shop",
            "type":"Services"
        },
        {
            "category":"Autos & Motor Vehicles",
            "subcategory":"Recreational Vehicle Sales",
            "type":"Retail Goods"
        }
    ],
    "sg:phone":"+1 330 644 0462",
    "sg:postcode":"44319",
    "sg:province":"OH",
    "sg:tags":[
        "parts",
        "trailer",
        "welding"
    ],
    "wof:name":"Priess Welding & Summit Trlr",
    "wof:placetype":"venue"
},
  "geometry": {"coordinates":[-81.522743,40.993816],"type":"Point"}
}