{
  "type": "Feature",
  "properties": {
    "iso:country":"US",
    "sg:address":"624 Fairview Dr",
    "sg:city":"Franklin",
    "sg:classifiers":[
        {
            "category":"Organizations",
            "subcategory":"Non-profit Organization",
            "type":"Services"
        },
        {
            "category":"Social Services",
            "type":"Services"
        }
    ],
    "sg:phone":"+1 937 746 4201",
    "sg:postcode":"45005",
    "sg:province":"OH",
    "sg:tags":[
        "residential",
        "care"
    ],
    "wof:name":"Society For Handicapped Citzns",
    "wof:placetype":"venue"
},
  "geometry": {"coordinates":[-84.318454,39.584801],"type":"Point"}
}