{
  "type": "Feature",
  "properties": {
    "iso:country":"US",
    "sg:address":"3900 N Summit St",
    "sg:city":"Toledo",
    "sg:classifiers":[
        {
            "category":"Government",
            "subcategory":"Office",
            "type":"Public Place"
        }
    ],
    "sg:phone":"+1 419 729 2020",
    "sg:postcode":"43611",
    "sg:province":"OH",
    "sg:tags":[
        "federal",
        "security"
    ],
    "wof:name":"US Coast Guard Search & Rescue",
    "wof:placetype":"venue"
},
  "geometry": {"coordinates":[-83.485135,41.690197],"type":"Point"}
}