{
  "type": "Feature",
  "properties": {
    "iso:country":"US",
    "sg:address":"253 Springboro Pike",
    "sg:city":"Dayton",
    "sg:classifiers":[
        {
            "category":"Banks & Credit Unions",
            "subcategory":"Bank",
            "type":"Services"
        }
    ],
    "sg:phone":"+1 937 436 3100",
    "sg:postcode":"45449",
    "sg:province":"OH",
    "sg:tags":[
        "state",
        "commercial"
    ],
    "wof:name":"Fifth Third Bank",
    "wof:placetype":"venue"
},
  "geometry": {"coordinates":[-84.221081,39.682874],"type":"Point"}
}