{
  "type": "Feature",
  "properties": {
    "iso:country":"US",
    "sg:address":"1589 McKaig Rd",
    "sg:city":"Troy",
    "sg:classifiers":[
        {
            "category":"Retail",
            "subcategory":"Veterinary Services",
            "type":"Services"
        }
    ],
    "sg:phone":"+1 937 339 4582",
    "sg:postcode":"45373",
    "sg:province":"OH",
    "wof:name":"Animal Clinic Of Troy",
    "wof:placetype":"venue"
},
  "geometry": {"coordinates":[-84.231595,40.039591],"type":"Point"}
}