{
  "type": "Feature",
  "properties": {
    "addr:full":"509 E. Tully St. Convoy OH 45832",
    "addr:housenumber":"509",
    "addr:postcode":"45832",
    "addr:street":"E. Tully St.",
    "iso:country":"US",
    "sg:address":"509 E. Tully St.",
    "sg:city":"Convoy",
    "sg:classifiers":[
        {
            "category":"Professional",
            "subcategory":"Computer Services",
            "type":"Services"
        }
    ],
    "sg:phone":"+1 419 518 9605",
    "sg:postcode":"45832",
    "sg:province":"OH",
    "sg:website":"http://www.webmannetwork.net",
    "wof:name":"The WebMan Network",
    "wof:placetype":"venue"
},
  "geometry": {"coordinates":[-84.70251,40.916816],"type":"Point"}
}