{
  "type": "Feature",
  "properties": {
    "iso:country":"US",
    "sg:address":"6104 Ridgeview Blvd",
    "sg:city":"North Ridgeville",
    "sg:classifiers":[
        {
            "category":"Banks & Credit Unions",
            "subcategory":"Bank",
            "type":"Services"
        }
    ],
    "sg:phone":"+1 440 327 2046",
    "sg:postcode":"44039",
    "sg:province":"OH",
    "sg:tags":[
        "mortgage"
    ],
    "wof:name":"New World Mortgage Inc",
    "wof:placetype":"venue"
},
  "geometry": {"coordinates":[-82.01115900000001,41.399676],"type":"Point"}
}