{
  "type": "Feature",
  "properties": {
    "addr:full":"1561 E 30th St Lorain OH 44055",
    "addr:housenumber":"1561",
    "addr:postcode":"44055",
    "addr:street":"E 30Th St",
    "iso:country":"US",
    "sg:address":"1561 E 30th St",
    "sg:city":"Lorain",
    "sg:classifiers":[
        {
            "category":"Real Estate",
            "subcategory":"Real Estate Agent",
            "type":"Services"
        }
    ],
    "sg:phone":"+1 440 477 4430",
    "sg:postcode":"44055",
    "sg:province":"OH",
    "sg:tags":[
        "housing",
        "transitional"
    ],
    "wof:name":"Mary Humility Housing Dev Corp",
    "wof:placetype":"venue"
},
  "geometry": {"coordinates":[-82.146378,41.443337],"type":"Point"}
}