{
  "type": "Feature",
  "properties": {
    "addr:full": "3431 Manchester Rd Akron OH 44319",
    "addr:housenumber": "3431",
    "addr:postcode": "44319",
    "addr:street": "Manchester Rd",
    "iso:country": "US",
    "sg:address": "3431 Manchester Rd",
    "sg:city": "Akron",
    "sg:classifiers": [
      {
        "category": "Manufacturing",
        "subcategory": "Tools \u0026 Machinery",
        "type": "Manufacturing \u0026 Wholesale Goods"
      }
    ],
    "sg:phone": "+1 330 245 1325",
    "sg:postcode": "44319",
    "sg:province": "OH",
    "sg:tags": [
      "industrial",
      "mfg"
    ],
    "wof:name": "C M Tech Specialists Inc",
    "wof:placetype": "venue"
  },
  "geometry": {"coordinates":[-81.555624,41.006123],"type":"Point"}
}
