{
  "type": "Feature",
  "properties": {
    "addr:full":"1505 Corporate Woods Pkwy Uniontown OH 44685",
    "addr:housenumber":"1505",
    "addr:postcode":"44685",
    "addr:street":"Corporate Woods Pkwy",
    "iso:country":"US",
    "sg:address":"1505 Corporate Woods Pkwy",
    "sg:city":"Uniontown",
    "sg:classifiers":[
        {
            "category":"Wholesale",
            "subcategory":"Books, Periodicals, & Newspapers",
            "type":"Manufacturing & Wholesale Goods"
        },
        {
            "category":"Shopping",
            "subcategory":"News",
            "type":"Retail Goods"
        }
    ],
    "sg:phone":"+1 330 899 9125",
    "sg:postcode":"44685",
    "sg:province":"OH",
    "sg:tags":[
        "magazine"
    ],
    "wof:name":"Trader Distribution Co",
    "wof:placetype":"venue"
},
  "geometry": {"coordinates":[-81.471991,40.964315],"type":"Point"}
}