{
  "type": "Feature",
  "properties": {
    "iso:country":"US",
    "sg:address":"2726 Erie Ave",
    "sg:city":"Cincinnati",
    "sg:classifiers":[
        {
            "category":"Shopping",
            "subcategory":"Clothing, Apparel, & Fashions",
            "type":"Retail Goods"
        }
    ],
    "sg:phone":"+1 513 533 9592",
    "sg:postcode":"45208",
    "sg:province":"OH",
    "sg:tags":[
        "intimate",
        "accessory"
    ],
    "wof:name":"Knickers Of Hyde Park",
    "wof:placetype":"venue"
},
  "geometry": {"coordinates":[-84.442042,39.139636],"type":"Point"}
}