{
  "type": "Feature",
  "properties": {
    "addr:full":"3809 Wilmington Pike Kettering OH 45429",
    "addr:housenumber":"3809",
    "addr:postcode":"45429",
    "addr:street":"Wilmington Pike",
    "iso:country":"US",
    "sg:address":"3809 Wilmington Pike",
    "sg:city":"Kettering",
    "sg:classifiers":[
        {
            "category":"Insurance",
            "subcategory":"Insurance Agent",
            "type":"Services"
        }
    ],
    "sg:phone":"+1 937 296 4311",
    "sg:postcode":"45429",
    "sg:province":"OH",
    "wof:name":"Century Standard",
    "wof:placetype":"venue"
},
  "geometry": {"coordinates":[-84.13538200000001,39.691867],"type":"Point"}
}