{
  "type": "Feature",
  "properties": {
    "iso:country":"US",
    "sg:address":"21 W Wenger Rd",
    "sg:city":"Englewood",
    "sg:classifiers":[
        {
            "category":"Insurance",
            "subcategory":"Insurance Agent",
            "type":"Services"
        }
    ],
    "sg:phone":"+1 937 836 5251",
    "sg:postcode":"45322",
    "sg:province":"OH",
    "wof:name":"Buxton Insur Agcy & Fincl Serv",
    "wof:placetype":"venue"
},
  "geometry": {"coordinates":[-84.287421,39.862322],"type":"Point"}
}