{
  "type": "Feature",
  "properties": {
    "addr:full": "21 W Wenger Rd Englewood OH 45322",
    "addr:housenumber": "21",
    "addr:postcode": "45322",
    "addr:street": "W Wenger Rd",
    "iso:country": "US",
    "sg:address": "21 W Wenger Rd",
    "sg:city": "Englewood",
    "sg:classifiers": [
      {
        "category": "Insurance",
        "subcategory": "Insurance Agent",
        "type": "Services"
      }
    ],
    "sg:phone": "+1 937 836 5251",
    "sg:postcode": "45322",
    "sg:province": "OH",
    "wof:name": "Buxton Insur Agcy \u0026 Fincl Serv",
    "wof:placetype": "venue"
  },
  "geometry": {"coordinates":[-84.287421,39.862322],"type":"Point"}
}
