{
  "type": "Feature",
  "properties": {
    "iso:country":"US",
    "sg:address":"215 Ice Ave",
    "sg:city":"Dayton",
    "sg:classifiers":[
        {
            "category":"Real Estate",
            "subcategory":"Real Estate Agent",
            "type":"Services"
        }
    ],
    "sg:phone":"+1 937 224 1234",
    "sg:postcode":"45402",
    "sg:province":"OH",
    "wof:name":"Realty Goup",
    "wof:placetype":"venue"
},
  "geometry": {"coordinates":[-84.188434,39.76236],"type":"Point"}
}