{
  "type": "Feature",
  "properties": {
    "iso:country":"US",
    "sg:address":"69 N South St",
    "sg:city":"Wilmington",
    "sg:classifiers":[
        {
            "category":"Government",
            "subcategory":"Office",
            "type":"Public Place"
        }
    ],
    "sg:phone":"+1 937 382 6528",
    "sg:postcode":"45177",
    "sg:province":"OH",
    "sg:tags":[
        "village"
    ],
    "wof:name":"City Offices Receptionist",
    "wof:placetype":"venue"
},
  "geometry": {"coordinates":[-83.828638,39.445549],"type":"Point"}
}