{
  "type": "Feature",
  "properties": {
    "iso:country":"US",
    "sg:address":"4200 Sharp Ave NW",
    "sg:city":"Canton",
    "sg:classifiers":[
        {
            "category":"Building & Trades",
            "subcategory":"Construction",
            "type":"Services"
        }
    ],
    "sg:phone":"+1 330 492 8023",
    "sg:postcode":"44718",
    "sg:province":"OH",
    "sg:tags":[
        "contractor"
    ],
    "wof:name":"James D Berger",
    "wof:placetype":"venue"
},
  "geometry": {"coordinates":[-81.430138,40.842204],"type":"Point"}
}