{
  "type": "Feature",
  "properties": {
    "addr:full": "4200 Sharp Ave NW Canton OH 44718",
    "addr:housenumber": "4200",
    "addr:postcode": "44718",
    "addr:street": "Sharp Ave Nw",
    "iso:country": "US",
    "sg:address": "4200 Sharp Ave NW",
    "sg:city": "Canton",
    "sg:classifiers": [
      {
        "category": "Building \u0026 Trades",
        "subcategory": "Construction",
        "type": "Services"
      }
    ],
    "sg:phone": "+1 330 492 8023",
    "sg:postcode": "44718",
    "sg:province": "OH",
    "sg:tags": [
      "contractor"
    ],
    "wof:name": "James D Berger",
    "wof:placetype": "venue"
  },
  "geometry": {"coordinates":[-81.430138,40.842204],"type":"Point"}
}
