{
  "type": "Feature",
  "properties": {
    "iso:country":"US",
    "sg:address":"8181 Camargo Rd",
    "sg:city":"Cincinnati",
    "sg:classifiers":[
        {
            "category":"Shopping",
            "subcategory":"Clothing, Apparel, & Fashions",
            "type":"Retail Goods"
        }
    ],
    "sg:phone":"+1 513 271 2689",
    "sg:postcode":"45243",
    "sg:province":"OH",
    "wof:name":"Chez Renee'",
    "wof:placetype":"venue"
},
  "geometry": {"coordinates":[-84.343129,39.196819],"type":"Point"}
}