{
  "type": "Feature",
  "properties": {
    "iso:country":"US",
    "sg:address":"5516 Village Psge",
    "sg:city":"Hilliard",
    "sg:classifiers":[
        {
            "category":"Freight",
            "type":"Transportation"
        }
    ],
    "sg:phone":"+1 614 876 7777",
    "sg:postcode":"43026",
    "sg:province":"OH",
    "sg:tags":[
        "mover"
    ],
    "wof:name":"Hollander Storage & Moving Co",
    "wof:placetype":"venue"
},
  "geometry": {"coordinates":[-83.15685999999999,40.00562],"type":"Point"}
}