{
  "type": "Feature",
  "properties": {
    "addr:full": "4665 N Detroit Ave Toledo OH 43612",
    "addr:housenumber": "4665",
    "addr:postcode": "43612",
    "addr:street": "N Detroit Ave",
    "iso:country": "US",
    "sg:address": "4665 N Detroit Ave",
    "sg:city": "Toledo",
    "sg:classifiers": [
      {
        "category": "Autos \u0026 Motor Vehicles",
        "subcategory": "Auto Supplies",
        "type": "Retail Goods"
      }
    ],
    "sg:phone": "+1 419 478 8540",
    "sg:postcode": "43612",
    "sg:province": "OH",
    "sg:tags": [
      "tire"
    ],
    "wof:name": "Joy's Tire \u0026 Car Ctr",
    "wof:placetype": "venue"
  },
  "geometry": {"coordinates":[-83.546945,41.703159],"type":"Point"}
}
