{
  "type": "Feature",
  "properties": {
    "addr:full":"4115 Hamilton Rd Lebanon OH 45036",
    "addr:housenumber":"4115",
    "addr:postcode":"45036",
    "addr:street":"Hamilton Rd",
    "iso:country":"US",
    "sg:address":"4115 Hamilton Rd",
    "sg:city":"Lebanon",
    "sg:classifiers":[
        {
            "category":"Wholesale",
            "subcategory":"Hardware",
            "type":"Manufacturing & Wholesale Goods"
        }
    ],
    "sg:phone":"+1 513 932 1490",
    "sg:postcode":"45036",
    "sg:province":"OH",
    "sg:tags":[
        "furnace"
    ],
    "wof:name":"T & T Svc",
    "wof:placetype":"venue"
},
  "geometry": {"coordinates":[-84.28592500000001,39.413132],"type":"Point"}
}