{
  "type": "Feature",
  "properties": {
    "addr:full":"1600 Algiers Dr Cleveland OH 44124",
    "addr:housenumber":"1600",
    "addr:postcode":"44124",
    "addr:street":"Algiers Dr",
    "iso:country":"US",
    "sg:address":"1600 Algiers Dr",
    "sg:city":"Cleveland",
    "sg:classifiers":[
        {
            "category":"Freight",
            "type":"Transportation"
        }
    ],
    "sg:phone":"+1 440 461 7652",
    "sg:postcode":"44124",
    "sg:province":"OH",
    "sg:tags":[
        "trucking"
    ],
    "wof:name":"J D Land Development Inc",
    "wof:placetype":"venue"
},
  "geometry": {"coordinates":[-81.461522,41.517148],"type":"Point"}
}