{
  "type": "Feature",
  "properties": {
    "addr:full":"1515 Washington St Toledo OH 43602",
    "addr:housenumber":"1515",
    "addr:postcode":"43602",
    "addr:street":"Washington St",
    "iso:country":"US",
    "sg:address":"1515 Washington St",
    "sg:city":"Toledo",
    "sg:classifiers":[
        {
            "category":"Wholesale",
            "subcategory":"Hardware",
            "type":"Manufacturing & Wholesale Goods"
        },
        {
            "category":"Building & Trades",
            "subcategory":"Plumbing",
            "type":"Services"
        }
    ],
    "sg:phone":"+1 419 243 3005",
    "sg:postcode":"43602",
    "sg:province":"OH",
    "sg:tags":[
        "furnace",
        "contractor"
    ],
    "sg:website":"www.m-mhvac.com",
    "wof:name":"M & M Heating & Cooling Inc",
    "wof:placetype":"venue"
},
  "geometry": {"coordinates":[-83.54871900000001,41.65234],"type":"Point"}
}