{
  "type": "Feature",
  "properties": {
    "addr:full": "224 West Ave Tallmadge OH 44278",
    "addr:housenumber": "224",
    "addr:postcode": "44278",
    "addr:street": "West Ave",
    "iso:country": "US",
    "sg:address": "224 West Ave",
    "sg:city": "Tallmadge",
    "sg:classifiers": [
      {
        "category": "Health Services",
        "subcategory": "Doctor",
        "type": "Services"
      }
    ],
    "sg:phone": "+1 330 633 8341",
    "sg:postcode": "44278",
    "sg:province": "OH",
    "sg:tags": [
      "physician",
      "surgeon"
    ],
    "wof:name": "West Avenue Family Practice",
    "wof:placetype": "venue"
  },
  "geometry": {"coordinates":[-81.451598,41.10168],"type":"Point"}
}
