{
  "type": "Feature",
  "properties": {
    "iso:country":"US",
    "sg:address":"7807 N Dixie Dr",
    "sg:city":"Dayton",
    "sg:classifiers":[
        {
            "category":"Banks & Credit Unions",
            "subcategory":"Bank",
            "type":"Services"
        }
    ],
    "sg:phone":"+1 937 454 1600",
    "sg:postcode":"45414",
    "sg:province":"OH",
    "sg:tags":[
        "loan",
        "real estate"
    ],
    "wof:name":"American Funding Agency Inc",
    "wof:placetype":"venue"
},
  "geometry": {"coordinates":[-84.19881599999999,39.842747],"type":"Point"}
}