{
  "type": "Feature",
  "properties": {
    "addr:full": "7807 N Dixie Dr Dayton OH 45414",
    "addr:housenumber": "7807",
    "addr:postcode": "45414",
    "addr:street": "N Dixie Dr",
    "iso:country": "US",
    "sg:address": "7807 N Dixie Dr",
    "sg:city": "Dayton",
    "sg:classifiers": [
      {
        "category": "Banks \u0026 Credit Unions",
        "subcategory": "Bank",
        "type": "Services"
      }
    ],
    "sg:phone": "+1 937 454 1600",
    "sg:postcode": "45414",
    "sg:province": "OH",
    "sg:tags": [
      "loan",
      "real estate"
    ],
    "wof:name": "American Funding Agency Inc",
    "wof:placetype": "venue"
  },
  "geometry": {"coordinates":[-84.198816,39.842747],"type":"Point"}
}
