{
  "type": "Feature",
  "properties": {
    "iso:country":"US",
    "sg:address":"7212 Marble Rd NE",
    "sg:city":"Kensington",
    "sg:classifiers":[
        {
            "category":"Freight",
            "type":"Transportation"
        }
    ],
    "sg:phone":"+1 330 223 1066",
    "sg:postcode":"44427",
    "sg:province":"OH",
    "sg:tags":[
        "operator",
        "local",
        "trucking"
    ],
    "wof:name":"Frederick S Mix III",
    "wof:placetype":"venue"
},
  "geometry": {"coordinates":[-80.94104900000001,40.721062],"type":"Point"}
}