{
  "type": "Feature",
  "properties": {
    "addr:full": "7212 Marble Rd NE Kensington OH 44427",
    "addr:housenumber": "7212",
    "addr:postcode": "44427",
    "addr:street": "Marble Rd Ne",
    "iso:country": "US",
    "sg:address": "7212 Marble Rd NE",
    "sg:city": "Kensington",
    "sg:classifiers": [
      {
        "category": "Freight",
        "type": "Transportation"
      }
    ],
    "sg:phone": "+1 330 223 1066",
    "sg:postcode": "44427",
    "sg:province": "OH",
    "sg:tags": [
      "operator",
      "local",
      "trucking"
    ],
    "wof:name": "Frederick S Mix III",
    "wof:placetype": "venue"
  },
  "geometry": {"coordinates":[-80.941049,40.721062],"type":"Point"}
}
