{
  "type": "Feature",
  "properties": {
    "addr:full": "299 Samoa Dr Akron OH 44319",
    "addr:housenumber": "299",
    "addr:postcode": "44319",
    "addr:street": "Samoa Dr",
    "iso:country": "US",
    "sg:address": "299 Samoa Dr",
    "sg:city": "Akron",
    "sg:classifiers": [
      {
        "category": "Autos \u0026 Motor Vehicles",
        "subcategory": "Automobile Sales",
        "type": "Retail Goods"
      }
    ],
    "sg:phone": "+1 330 724 3000",
    "sg:postcode": "44319",
    "sg:province": "OH",
    "sg:tags": [
      "car",
      "dealer"
    ],
    "wof:name": "Vehicle Exchange",
    "wof:placetype": "venue"
  },
  "geometry": {"coordinates":[-81.532086,40.966057],"type":"Point"}
}
