{
  "type": "Feature",
  "properties": {
    "iso:country":"US",
    "sg:address":"299 Samoa Dr",
    "sg:city":"Akron",
    "sg:classifiers":[
        {
            "category":"Autos & Motor Vehicles",
            "subcategory":"Automobile Sales",
            "type":"Retail Goods"
        }
    ],
    "sg:phone":"+1 330 724 3000",
    "sg:postcode":"44319",
    "sg:province":"OH",
    "sg:tags":[
        "car",
        "dealer"
    ],
    "wof:name":"Vehicle Exchange",
    "wof:placetype":"venue"
},
  "geometry": {"coordinates":[-81.53208600000001,40.966057],"type":"Point"}
}