{
  "type": "Feature",
  "properties": {
    "iso:country":"US",
    "sg:address":"2640 W Market St",
    "sg:city":"Fairlawn",
    "sg:classifiers":[
        {
            "category":"Health Services",
            "subcategory":"Doctor",
            "type":"Services"
        }
    ],
    "sg:phone":"+1 330 864 1913",
    "sg:postcode":"44333",
    "sg:province":"OH",
    "sg:tags":[
        "physician",
        "surgeon"
    ],
    "wof:name":"Procomp Care Occupational Hlth",
    "wof:placetype":"venue"
},
  "geometry": {"coordinates":[-81.59831200000001,41.122569],"type":"Point"}
}