{
  "type": "Feature",
  "properties": {
    "iso:country":"US",
    "sg:address":"11700 William Penn Ave NE",
    "sg:city":"Hartville",
    "sg:classifiers":[
        {
            "category":"Sports & Exercise",
            "subcategory":"Golf",
            "type":"Entertainment"
        }
    ],
    "sg:phone":"+1 330 877 9303",
    "sg:postcode":"44632",
    "sg:province":"OH",
    "sg:tags":[
        "course"
    ],
    "wof:name":"George R Gran Inc",
    "wof:placetype":"venue"
},
  "geometry": {"coordinates":[-81.31155800000001,40.949004],"type":"Point"}
}