{
  "type": "Feature",
  "properties": {
    "addr:full": "11700 William Penn Ave NE Hartville OH 44632",
    "addr:housenumber": "11700",
    "addr:postcode": "44632",
    "addr:street": "William Penn Ave Ne",
    "iso:country": "US",
    "sg:address": "11700 William Penn Ave NE",
    "sg:city": "Hartville",
    "sg:classifiers": [
      {
        "category": "Sports \u0026 Exercise",
        "subcategory": "Golf",
        "type": "Entertainment"
      }
    ],
    "sg:phone": "+1 330 877 9303",
    "sg:postcode": "44632",
    "sg:province": "OH",
    "sg:tags": [
      "course"
    ],
    "wof:name": "George R Gran Inc",
    "wof:placetype": "venue"
  },
  "geometry": {"coordinates":[-81.311558,40.949004],"type":"Point"}
}
