{
  "type": "Feature",
  "properties": {
    "addr:full": "11925 Pearl Rd Cleveland OH 44136",
    "addr:housenumber": "11925",
    "addr:postcode": "44136",
    "addr:street": "Pearl Rd",
    "iso:country": "US",
    "sg:address": "11925 Pearl Rd",
    "sg:city": "Cleveland",
    "sg:classifiers": [
      {
        "category": "Retail",
        "subcategory": "Laundry \u0026 Dry Cleaning",
        "type": "Services"
      }
    ],
    "sg:phone": "+1 440 878 1100",
    "sg:postcode": "44136",
    "sg:province": "OH",
    "sg:tags": [
      "uniform",
      "supply"
    ],
    "wof:name": "Cintas Corp",
    "wof:placetype": "venue"
  },
  "geometry": {"coordinates":[-81.836904,41.329873],"type":"Point"}
}
