{
  "type": "Feature",
  "properties": {
    "addr:full": "1205 W Perkins Ave Sandusky OH 44870",
    "addr:housenumber": "1205",
    "addr:postcode": "44870",
    "addr:street": "W Perkins Ave",
    "iso:country": "US",
    "sg:address": "1205 W Perkins Ave",
    "sg:city": "Sandusky",
    "sg:classifiers": [
      {
        "category": "Organizations",
        "subcategory": "Labor Organization",
        "type": "Services"
      }
    ],
    "sg:phone": "+1 419 625 8224",
    "sg:postcode": "44870",
    "sg:province": "OH",
    "wof:name": "Painters",
    "wof:placetype": "venue"
  },
  "geometry": {"coordinates":[-82.717217,41.433269],"type":"Point"}
}
