{
  "type": "Feature",
  "properties": {
    "addr:full":"1200 Monroe Rd Lebanon OH 45036",
    "addr:housenumber":"1200",
    "addr:postcode":"45036",
    "addr:street":"Monroe Rd",
    "iso:country":"US",
    "sg:address":"1200 Monroe Rd",
    "sg:city":"Lebanon",
    "sg:classifiers":[
        {
            "category":"Wholesale",
            "subcategory":"Machinery & Supplies",
            "type":"Manufacturing & Wholesale Goods"
        }
    ],
    "sg:phone":"+1 513 932 3816",
    "sg:postcode":"45036",
    "sg:province":"OH",
    "sg:tags":[
        "tractor"
    ],
    "wof:name":"Lebanon Farm Implements Inc",
    "wof:placetype":"venue"
},
  "geometry": {"coordinates":[-84.182828,39.447083],"type":"Point"}
}