{
  "type": "Feature",
  "properties": {
    "addr:full": "5206 Monroe St Toledo OH 43623",
    "addr:housenumber": "5206",
    "addr:postcode": "43623",
    "addr:street": "Monroe St",
    "iso:country": "US",
    "sg:address": "5206 Monroe St",
    "sg:city": "Toledo",
    "sg:classifiers": [
      {
        "category": "Shopping",
        "subcategory": "Music",
        "type": "Retail Goods"
      }
    ],
    "sg:phone": "+1 419 843 7348",
    "sg:postcode": "43623",
    "sg:province": "OH",
    "sg:tags": [
      "compact",
      "record",
      "disc",
      "tape"
    ],
    "wof:name": "CD Warehouse",
    "wof:placetype": "venue"
  },
  "geometry": {"coordinates":[-83.651147,41.700954],"type":"Point"}
}
