{
  "type": "Feature",
  "properties": {
    "addr:full": "127 Public Sq Cleveland OH 44114",
    "addr:housenumber": "127",
    "addr:postcode": "44114",
    "addr:street": "Public Sq",
    "iso:country": "US",
    "sg:address": "127 Public Sq",
    "sg:city": "Cleveland",
    "sg:classifiers": [
      {
        "category": "Shopping",
        "type": "Retail Goods"
      }
    ],
    "sg:phone": "+1 216 443 0430",
    "sg:postcode": "44114",
    "sg:province": "OH",
    "sg:tags": [
      "diabetic",
      "supply"
    ],
    "wof:name": "Mobile Hypebaric Ctr",
    "wof:placetype": "venue"
  },
  "geometry": {"coordinates":[-81.693533,41.500737],"type":"Point"}
}
