{
  "type": "Feature",
  "properties": {
    "addr:full": "3593 Lee Rd Cleveland OH 44120",
    "addr:housenumber": "3593",
    "addr:postcode": "44120",
    "addr:street": "Lee Rd",
    "iso:country": "US",
    "sg:address": "3593 Lee Rd",
    "sg:city": "Cleveland",
    "sg:classifiers": [
      {
        "category": "Personal",
        "subcategory": "Barber",
        "type": "Services"
      }
    ],
    "sg:phone": "+1 216 283 2183",
    "sg:postcode": "44120",
    "sg:province": "OH",
    "wof:name": "Kuts \u0026 Kurls",
    "wof:placetype": "venue"
  },
  "geometry": {"coordinates":[-81.564856,41.462359],"type":"Point"}
}
