{
  "type": "Feature",
  "properties": {
    "iso:country":"US",
    "sg:address":"3593 Lee Rd",
    "sg:city":"Cleveland",
    "sg:classifiers":[
        {
            "category":"Personal",
            "subcategory":"Barber",
            "type":"Services"
        }
    ],
    "sg:phone":"+1 216 283 2183",
    "sg:postcode":"44120",
    "sg:province":"OH",
    "wof:name":"Kuts & Kurls",
    "wof:placetype":"venue"
},
  "geometry": {"coordinates":[-81.56485600000001,41.462359],"type":"Point"}
}