{
  "type": "Feature",
  "properties": {
    "iso:country":"US",
    "sg:address":"31 Iron Gate Park Dr",
    "sg:city":"Dayton",
    "sg:classifiers":[
        {
            "category":"Insurance",
            "subcategory":"Insurance Agent",
            "type":"Services"
        }
    ],
    "sg:phone":"+1 937 439 2990",
    "sg:postcode":"45459",
    "sg:province":"OH",
    "wof:name":"Assured Continuous Svc",
    "wof:placetype":"venue"
},
  "geometry": {"coordinates":[-84.15674799999999,39.631934],"type":"Point"}
}