{
  "type": "Feature",
  "properties": {
    "addr:full":"10340 Memphis Ave Cleveland OH 44144",
    "addr:housenumber":"10340",
    "addr:postcode":"44144",
    "addr:street":"Memphis Ave",
    "iso:country":"US",
    "sg:address":"10340 Memphis Ave",
    "sg:city":"Cleveland",
    "sg:classifiers":[
        {
            "category":"Recreation",
            "subcategory":"Picnic Area",
            "type":"Entertainment"
        }
    ],
    "sg:phone":"+1 216 941 5995",
    "sg:postcode":"44144",
    "sg:province":"OH",
    "sg:tags":[
        "place",
        "arcade",
        "amusement"
    ],
    "sg:website":"http://www.memphiskiddiepark.com",
    "wof:name":"Memphis Kiddie Park",
    "wof:placetype":"venue"
},
  "geometry": {"coordinates":[-81.758045,41.44019],"type":"Point"}
}