{
  "type": "Feature",
  "properties": {
    "addr:full":"4150 Reading Rd Cincinnati OH 45229",
    "addr:housenumber":"4150",
    "addr:postcode":"45229",
    "addr:street":"Reading Rd",
    "iso:country":"US",
    "sg:address":"4150 Reading Rd",
    "sg:city":"Cincinnati",
    "sg:classifiers":[
        {
            "category":"Government",
            "subcategory":"Police Station",
            "type":"Public Place"
        }
    ],
    "sg:phone":"+1 513 352 3576",
    "sg:postcode":"45229",
    "sg:province":"OH",
    "sg:tags":[
        "department"
    ],
    "wof:name":"Cincinnati Police District 4",
    "wof:placetype":"venue"
},
  "geometry": {"coordinates":[-84.47389800000001,39.160492],"type":"Point"}
}