{
  "type": "Feature",
  "properties": {
    "addr:full":"22841 Aurora Rd Bedford OH 44146",
    "addr:housenumber":"22841",
    "addr:postcode":"44146",
    "addr:street":"Aurora Rd",
    "iso:country":"US",
    "sg:address":"22841 Aurora Rd",
    "sg:city":"Bedford",
    "sg:classifiers":[
        {
            "category":"Building & Trades",
            "subcategory":"Electrical",
            "type":"Services"
        }
    ],
    "sg:phone":"+1 216 662 7596",
    "sg:postcode":"44146",
    "sg:province":"OH",
    "sg:tags":[
        "electrical",
        "electric",
        "contractor"
    ],
    "wof:name":"R J Martin Electrical Contg",
    "wof:placetype":"venue"
},
  "geometry": {"coordinates":[-81.52370000000001,41.421588],"type":"Point"}
}