{
  "type": "Feature",
  "properties": {
    "addr:full": "747 State Rte 100 Bucyrus OH 44820",
    "addr:housenumber": "747",
    "addr:postcode": "44820",
    "addr:street": "State Rte 100",
    "iso:country": "US",
    "sg:address": "747 State Rte 100",
    "sg:city": "Bucyrus",
    "sg:phone": "+1 419 985 4887",
    "sg:postcode": "44820",
    "sg:province": "OH",
    "sg:tags": [
      "farm",
      "grain",
      "cash"
    ],
    "wof:name": "Keith Eichhorn",
    "wof:placetype": "venue"
  },
  "geometry": {"coordinates":[-82.966,40.79847],"type":"Point"}
}
