{
  "type": "Feature",
  "properties": {
    "addr:full": "3645 Warrensville Center Rd Cleveland OH 44122",
    "addr:housenumber": "3645",
    "addr:postcode": "44122",
    "addr:street": "Warrensville Center Rd",
    "iso:country": "US",
    "sg:address": "3645 Warrensville Center Rd",
    "sg:city": "Cleveland",
    "sg:classifiers": [
      {
        "category": "Professional",
        "subcategory": "Management \u0026 Consulting",
        "type": "Services"
      }
    ],
    "sg:phone": "+1 216 921 9194",
    "sg:postcode": "44122",
    "sg:province": "OH",
    "sg:tags": [
      "business"
    ],
    "wof:name": "Broma Information Technology",
    "wof:placetype": "venue"
  },
  "geometry": {"coordinates":[-81.535596,41.458352],"type":"Point"}
}
