{
  "type": "Feature",
  "properties": {
    "iso:country":"US",
    "sg:address":"10095 Brick Church Rd",
    "sg:city":"Cambridge",
    "sg:classifiers":[
        {
            "category":"Health Services",
            "subcategory":"Doctor",
            "type":"Services"
        }
    ],
    "sg:phone":"+1 740 439 3901",
    "sg:postcode":"43725",
    "sg:province":"OH",
    "sg:tags":[
        "physician",
        "surgeon"
    ],
    "wof:name":"Darlene Snider DO",
    "wof:placetype":"venue"
},
  "geometry": {"coordinates":[-81.57655699999999,39.980881],"type":"Point"}
}