{
  "type": "Feature",
  "properties": {
    "addr:full":"6455 Pearl Rd Cleveland OH 44130",
    "addr:housenumber":"6455",
    "addr:postcode":"44130",
    "addr:street":"Pearl Rd",
    "iso:country":"US",
    "sg:address":"6455 Pearl Rd",
    "sg:city":"Cleveland",
    "sg:classifiers":[
        {
            "category":"Health Services",
            "subcategory":"Nursing And Care Facility",
            "type":"Services"
        }
    ],
    "sg:phone":"+1 440 888 5900",
    "sg:postcode":"44130",
    "sg:province":"OH",
    "sg:tags":[
        "hospital",
        "skilled",
        "specialty"
    ],
    "wof:name":"Greenbriar Retirement Center",
    "wof:placetype":"venue"
},
  "geometry": {"coordinates":[-81.769407,41.385987],"type":"Point"}
}