{
  "type": "Feature",
  "properties": {
    "addr:full": "512 Lincoln Ave Troy OH 45373",
    "addr:housenumber": "512",
    "addr:postcode": "45373",
    "addr:street": "Lincoln Ave",
    "iso:country": "US",
    "sg:address": "512 Lincoln Ave",
    "sg:city": "Troy",
    "sg:classifiers": [
      {
        "category": "Building \u0026 Trades",
        "subcategory": "Landscaping Services",
        "type": "Services"
      }
    ],
    "sg:phone": "+1 937 332 0418",
    "sg:postcode": "45373",
    "sg:province": "OH",
    "sg:tags": [
      "landscape",
      "contractor"
    ],
    "wof:name": "Greener Pastures Lawn Care \u0026 L",
    "wof:placetype": "venue"
  },
  "geometry": {"coordinates":[-84.211414,40.035796],"type":"Point"}
}
