{
  "type": "Feature",
  "properties": {
    "addr:full": "22455 S Woodland Rd Cleveland OH 44122",
    "addr:housenumber": "22455",
    "addr:postcode": "44122",
    "addr:street": "S Woodland Rd",
    "iso:country": "US",
    "sg:address": "22455 S Woodland Rd",
    "sg:city": "Cleveland",
    "sg:classifiers": [
      {
        "category": "Real Estate",
        "subcategory": "Real Estate Agent",
        "type": "Services"
      }
    ],
    "sg:phone": "+1 216 316 3965",
    "sg:postcode": "44122",
    "sg:province": "OH",
    "wof:name": "S W Noble LTD",
    "wof:placetype": "venue"
  },
  "geometry": {"coordinates":[-81.521572,41.473823],"type":"Point"}
}
