{
  "type": "Feature",
  "properties": {
    "iso:country":"US",
    "sg:address":"3891 Kemp Rd",
    "sg:city":"Dayton",
    "sg:classifiers":[
        {
            "category":"Food & Beverages",
            "subcategory":"Liquor & Beverages",
            "type":"Retail Goods"
        }
    ],
    "sg:phone":"+1 937 429 5502",
    "sg:postcode":"45431",
    "sg:province":"OH",
    "sg:tags":[
        "alcoholic"
    ],
    "wof:name":"Halls Crnr Carryout Drive-Thru",
    "wof:placetype":"venue"
},
  "geometry": {"coordinates":[-84.079865,39.756757],"type":"Point"}
}