{
  "type": "Feature",
  "properties": {
    "iso:country":"US",
    "sg:address":"1638 Nussbaum Pkwy",
    "sg:city":"Mansfield",
    "sg:classifiers":[
        {
            "category":"Professional",
            "type":"Services"
        }
    ],
    "sg:phone":"+1 419 528 3025",
    "sg:postcode":"44906",
    "sg:province":"OH",
    "wof:name":"Frederick L Robertson",
    "wof:placetype":"venue"
},
  "geometry": {"coordinates":[-82.574018,40.765708],"type":"Point"}
}