{
  "type": "Feature",
  "properties": {
    "addr:full": "192 E Ottawa St Richwood OH 43344",
    "addr:housenumber": "192",
    "addr:postcode": "43344",
    "addr:street": "E Ottawa St",
    "iso:country": "US",
    "sg:address": "192 E Ottawa St",
    "sg:city": "Richwood",
    "sg:classifiers": [
      {
        "category": "Education",
        "subcategory": "School",
        "type": "Public Place"
      }
    ],
    "sg:phone": "+1 740 943 3113",
    "sg:postcode": "43344",
    "sg:province": "OH",
    "wof:name": "Clairborne-Richwood Elementary",
    "wof:placetype": "venue"
  },
  "geometry": {"coordinates":[-83.289653,40.426739],"type":"Point"}
}
