{
  "type": "Feature",
  "properties": {
    "addr:full": "6427 Hilltop Ln Maumee OH 43537",
    "addr:housenumber": "6427",
    "addr:postcode": "43537",
    "addr:street": "Hilltop Ln",
    "iso:country": "US",
    "sg:address": "6427 Hilltop Ln",
    "sg:city": "Maumee",
    "sg:classifiers": [
      {
        "category": "Home \u0026 Garden",
        "subcategory": "Home Furnishings",
        "type": "Retail Goods"
      }
    ],
    "sg:phone": "+1 419 893 2385",
    "sg:postcode": "43537",
    "sg:province": "OH",
    "wof:name": "Hilltop Treasures",
    "wof:placetype": "venue"
  },
  "geometry": {"coordinates":[-83.695525,41.545351],"type":"Point"}
}
