{
  "type": "Feature",
  "properties": {
    "addr:full": "110 E 4th St Port Clinton OH 43452",
    "addr:housenumber": "110",
    "addr:postcode": "43452",
    "addr:street": "E 4Th St",
    "iso:country": "US",
    "sg:address": "110 E 4th St",
    "sg:city": "Port Clinton",
    "sg:classifiers": [
      {
        "category": "Social Services",
        "subcategory": "Child Care",
        "type": "Services"
      },
      {
        "category": "Education",
        "subcategory": "School",
        "type": "Public Place"
      }
    ],
    "sg:phone": "+1 419 734 4448",
    "sg:postcode": "43452",
    "sg:province": "OH",
    "sg:tags": [
      "day"
    ],
    "wof:name": "Port Clinton Middle School",
    "wof:placetype": "venue"
  },
  "geometry": {"coordinates":[-82.940943,41.509024],"type":"Point"}
}
