{
  "type": "Feature",
  "properties": {
    "addr:full":"5489 Dixie Hwy Fairfield OH 45014",
    "addr:housenumber":"5489",
    "addr:postcode":"45014",
    "addr:street":"Dixie Hwy",
    "iso:country":"US",
    "sg:address":"5489 Dixie Hwy",
    "sg:city":"Fairfield",
    "sg:classifiers":[
        {
            "category":"Autos & Motor Vehicles",
            "subcategory":"Boat Sales",
            "type":"Retail Goods"
        }
    ],
    "sg:phone":"+1 513 939 1730",
    "sg:postcode":"45014",
    "sg:province":"OH",
    "sg:tags":[
        "dealer",
        "sales"
    ],
    "wof:name":"Sea Ray Of Cincinnati",
    "wof:placetype":"venue"
},
  "geometry": {"coordinates":[-84.525948,39.334826],"type":"Point"}
}