{
  "type": "Feature",
  "properties": {
    "addr:full": "737 Park Ave Newton Falls OH 44444",
    "addr:housenumber": "737",
    "addr:postcode": "44444",
    "addr:street": "Park Ave",
    "iso:country": "US",
    "sg:address": "737 Park Ave",
    "sg:city": "Newton Falls",
    "sg:classifiers": [
      {
        "category": "Building \u0026 Trades",
        "subcategory": "Construction",
        "type": "Services"
      }
    ],
    "sg:phone": "+1 330 872 8320",
    "sg:postcode": "44444",
    "sg:province": "OH",
    "sg:tags": [
      "excavation",
      "excavating",
      "contractor"
    ],
    "wof:name": "Mc Combs Excavating LLC",
    "wof:placetype": "venue"
  },
  "geometry": {"coordinates":[-80.975594,41.197058],"type":"Point"}
}
