{
  "type": "Feature",
  "properties": {
    "addr:full": "5620 Lake O Springs Ave NW Canton OH 44718",
    "addr:housenumber": "5620",
    "addr:postcode": "44718",
    "addr:street": "Lake O Springs Ave Nw",
    "iso:country": "US",
    "sg:address": "5620 Lake O Springs Ave NW",
    "sg:city": "Canton",
    "sg:classifiers": [
      {
        "category": "Retail",
        "subcategory": "Laundry \u0026 Dry Cleaning",
        "type": "Services"
      }
    ],
    "sg:phone": "+1 330 454 3648",
    "sg:postcode": "44718",
    "sg:province": "OH",
    "sg:tags": [
      "cleaners",
      "rug",
      "carpet"
    ],
    "wof:name": "Like New Cleaning",
    "wof:placetype": "venue"
  },
  "geometry": {"coordinates":[-81.460757,40.865839],"type":"Point"}
}
