{
  "type": "Feature",
  "properties": {
    "iso:country":"US",
    "sg:address":"6841 Old Tarlton Pike",
    "sg:city":"Circleville",
    "sg:classifiers":[
        {
            "category":"Building & Trades",
            "subcategory":"Construction",
            "type":"Services"
        }
    ],
    "sg:phone":"+1 740 474 9371",
    "sg:postcode":"43113",
    "sg:province":"OH",
    "sg:tags":[
        "house",
        "contractor",
        "roofing"
    ],
    "wof:name":"Four Brothers Home Improvement",
    "wof:placetype":"venue"
},
  "geometry": {"coordinates":[-82.902534,39.586526],"type":"Point"}
}