{
  "type": "Feature",
  "properties": {
    "addr:full":"673 Spring Ave Steubenville OH 43952",
    "addr:housenumber":"673",
    "addr:postcode":"43952",
    "addr:street":"Spring Ave",
    "iso:country":"US",
    "sg:address":"673 Spring Ave",
    "sg:city":"Steubenville",
    "sg:classifiers":[
        {
            "category":"Banks & Credit Unions",
            "subcategory":"Financial Services",
            "type":"Services"
        }
    ],
    "sg:phone":"+1 740 283 1267",
    "sg:postcode":"43952",
    "sg:province":"OH",
    "sg:tags":[
        "investor"
    ],
    "wof:name":"Hub Investment Properties LLC",
    "wof:placetype":"venue"
},
  "geometry": {"coordinates":[-80.623926,40.355013],"type":"Point"}
}