{
  "type": "Feature",
  "properties": {
    "addr:full": "1355 Evans Ave Akron OH 44305",
    "addr:housenumber": "1355",
    "addr:postcode": "44305",
    "addr:street": "Evans Ave",
    "iso:country": "US",
    "sg:address": "1355 Evans Ave",
    "sg:city": "Akron",
    "sg:classifiers": [
      {
        "category": "Wholesale",
        "subcategory": "Home Furnishings",
        "type": "Manufacturing \u0026 Wholesale Goods"
      }
    ],
    "sg:phone": "+1 330 633 8680",
    "sg:postcode": "44305",
    "sg:province": "OH",
    "sg:tags": [
      "equipment",
      "fireplace"
    ],
    "wof:name": "Thermo-Rite Mfg Corp",
    "wof:placetype": "venue"
  },
  "geometry": {"coordinates":[-81.474995,41.093188],"type":"Point"}
}
