{
  "type": "Feature",
  "properties": {
    "addr:full": "3919 N Bend Rd Cincinnati OH 45211",
    "addr:housenumber": "3919",
    "addr:postcode": "45211",
    "addr:street": "N Bend Rd",
    "iso:country": "US",
    "sg:address": "3919 N Bend Rd",
    "sg:city": "Cincinnati",
    "sg:classifiers": [
      {
        "category": "Professional",
        "type": "Services"
      }
    ],
    "sg:phone": "+1 513 662 2406",
    "sg:postcode": "45211",
    "sg:province": "OH",
    "sg:tags": [
      "establishment"
    ],
    "wof:name": "B Schweikert Agency",
    "wof:placetype": "venue"
  },
  "geometry": {"coordinates":[-84.606126,39.158915],"type":"Point"}
}
