{
  "type": "Feature",
  "properties": {
    "iso:country":"US",
    "sg:address":"333 14th St",
    "sg:city":"Toledo",
    "sg:classifiers":[
        {
            "category":"Home & Garden",
            "subcategory":"Home Furnishings",
            "type":"Retail Goods"
        }
    ],
    "sg:phone":"+1 419 243 2717",
    "sg:postcode":"43604",
    "sg:province":"OH",
    "sg:tags":[
        "beveled",
        "glass",
        "ornamental"
    ],
    "wof:name":"Cristallo Architectural Glass",
    "wof:placetype":"venue"
},
  "geometry": {"coordinates":[-83.543438,41.65601],"type":"Point"}
}