{
  "type": "Feature",
  "properties": {
    "addr:full": "4565 Shriver Rd North Canton OH 44720",
    "addr:housenumber": "4565",
    "addr:postcode": "44720",
    "addr:street": "Shriver Rd",
    "iso:country": "US",
    "sg:address": "4565 Shriver Rd",
    "sg:city": "North Canton",
    "sg:classifiers": [
      {
        "category": "Building \u0026 Trades",
        "subcategory": "Plumbing",
        "type": "Services"
      }
    ],
    "sg:phone": "+1 330 630 2645",
    "sg:postcode": "44720",
    "sg:province": "OH",
    "sg:tags": [
      "conditioning",
      "air",
      "system",
      "contractor"
    ],
    "wof:name": "Forquer Heating/Air Condition",
    "wof:placetype": "venue"
  },
  "geometry": {"coordinates":[-81.474243,40.939224],"type":"Point"}
}
