{
  "type": "Feature",
  "properties": {
    "addr:full":"5400 Foster Ave Columbus OH 43214",
    "addr:housenumber":"5400",
    "addr:postcode":"43214",
    "addr:street":"Foster Ave",
    "iso:country":"US",
    "sg:address":"5400 Foster Ave",
    "sg:city":"Columbus",
    "sg:classifiers":[
        {
            "category":"Education",
            "subcategory":"School",
            "type":"Public Place"
        }
    ],
    "sg:phone":"+1 614 848 5400",
    "sg:postcode":"43214",
    "sg:province":"OH",
    "sg:tags":[
        "profit",
        "k"
    ],
    "wof:name":"Greater Columbus Christn Schl",
    "wof:placetype":"venue"
},
  "geometry": {"coordinates":[-83.01204799999999,40.073486],"type":"Point"}
}