{
  "type": "Feature",
  "properties": {
    "addr:full": "1600 Princeton Dr Dayton OH 45406",
    "addr:housenumber": "1600",
    "addr:postcode": "45406",
    "addr:street": "Princeton Dr",
    "iso:country": "US",
    "sg:address": "1600 Princeton Dr",
    "sg:city": "Dayton",
    "sg:classifiers": [
      {
        "category": "Recreation",
        "type": "Entertainment"
      }
    ],
    "sg:phone": "+1 937 333 3053",
    "sg:postcode": "45406",
    "sg:province": "OH",
    "sg:tags": [
      "pool",
      "swimming"
    ],
    "wof:name": "Dabney Pool",
    "wof:placetype": "venue"
  },
  "geometry": {"coordinates":[-84.229157,39.773023],"type":"Point"}
}
