{
  "type": "Feature",
  "properties": {
    "addr:full": "233 Factory St NE Sugarcreek OH 44681",
    "addr:housenumber": "233",
    "addr:postcode": "44681",
    "addr:street": "Factory St Ne",
    "iso:country": "US",
    "sg:address": "233 Factory St NE",
    "sg:city": "Sugarcreek",
    "sg:classifiers": [
      {
        "category": "Professional",
        "subcategory": "Business Services",
        "type": "Services"
      }
    ],
    "sg:phone": "+1 330 852 4111",
    "sg:postcode": "44681",
    "sg:province": "OH",
    "sg:tags": [
      "auctioneer"
    ],
    "sg:website": "www.kaufmanrealty.com",
    "wof:name": "Dave Kaufman Realty Inc",
    "wof:placetype": "venue"
  },
  "geometry": {"coordinates":[-81.637856,40.504858],"type":"Point"}
}
