{
  "type": "Feature",
  "properties": {
    "addr:full":"1758 Glenmar Dr Lancaster OH 43130",
    "addr:housenumber":"1758",
    "addr:postcode":"43130",
    "addr:street":"Glenmar Dr",
    "iso:country":"US",
    "sg:address":"1758 Glenmar Dr",
    "sg:city":"Lancaster",
    "sg:classifiers":[
        {
            "category":"Organizations",
            "subcategory":"Religious Organization",
            "type":"Services"
        }
    ],
    "sg:phone":"+1 740 653 6468",
    "sg:postcode":"43130",
    "sg:province":"OH",
    "sg:tags":[
        "clergy"
    ],
    "wof:name":"Harold R Sturm",
    "wof:placetype":"venue"
},
  "geometry": {"coordinates":[-82.61344800000001,39.736453],"type":"Point"}
}