{
  "type": "Feature",
  "properties": {
    "addr:full": "1270 Morse Rd Columbus OH 43229",
    "addr:housenumber": "1270",
    "addr:postcode": "43229",
    "addr:street": "Morse Rd",
    "iso:country": "US",
    "sg:address": "1270 Morse Rd",
    "sg:city": "Columbus",
    "sg:classifiers": [
      {
        "category": "Restaurant",
        "type": "Food \u0026 Drink"
      }
    ],
    "sg:phone": "+1 614 848 5016",
    "sg:postcode": "43229",
    "sg:province": "OH",
    "sg:tags": [
      "eating"
    ],
    "wof:name": "LA Playa",
    "wof:placetype": "venue"
  },
  "geometry": {"coordinates":[-82.988048,40.061274],"type":"Point"}
}
