{
  "type": "Feature",
  "properties": {
    "addr:full": "203 S Wittenberg Ave Springfield OH 45506",
    "addr:housenumber": "203",
    "addr:postcode": "45506",
    "addr:street": "S Wittenberg Ave",
    "iso:country": "US",
    "sg:address": "203 S Wittenberg Ave",
    "sg:city": "Springfield",
    "sg:classifiers": [
      {
        "category": "Manufacturing",
        "subcategory": "Tools \u0026 Machinery",
        "type": "Manufacturing \u0026 Wholesale Goods"
      }
    ],
    "sg:phone": "+1 937 322 5768",
    "sg:postcode": "45506",
    "sg:province": "OH",
    "sg:tags": [
      "machine",
      "mfg",
      "accessory"
    ],
    "wof:name": "Tomco Tool Inc",
    "wof:placetype": "venue"
  },
  "geometry": {"coordinates":[-83.814661,39.921657],"type":"Point"}
}
