{
  "type": "Feature",
  "properties": {
    "addr:full": "1919 State Rte 307 Austinburg OH 44010",
    "addr:housenumber": "1919",
    "addr:postcode": "44010",
    "addr:street": "State Rte 307",
    "iso:country": "US",
    "sg:address": "1919 State Rte 307",
    "sg:city": "Austinburg",
    "sg:classifiers": [
      {
        "category": "Wholesale",
        "subcategory": "Plants",
        "type": "Manufacturing \u0026 Wholesale Goods"
      }
    ],
    "sg:phone": "+1 440 275 3332",
    "sg:postcode": "44010",
    "sg:province": "OH",
    "sg:tags": [
      "nursery",
      "tree"
    ],
    "wof:name": "Tree Tyme Nursery",
    "wof:placetype": "venue"
  },
  "geometry": {"coordinates":[-80.828603,41.767012],"type":"Point"}
}
