{
  "type": "Feature",
  "properties": {
    "addr:full": "201 E 5th St Cincinnati OH 45202",
    "addr:housenumber": "201",
    "addr:postcode": "45202",
    "addr:street": "E 5Th St",
    "iso:country": "US",
    "sg:address": "201 E 5th St",
    "sg:city": "Cincinnati",
    "sg:classifiers": [
      {
        "category": "Real Estate",
        "subcategory": "Architect",
        "type": "Services"
      }
    ],
    "sg:phone": "+1 513 263 6300",
    "sg:postcode": "45202",
    "sg:province": "OH",
    "sg:tags": [
      "architectural",
      "engineer"
    ],
    "wof:name": "Harleyellis Corporation",
    "wof:placetype": "venue"
  },
  "geometry": {"coordinates":[-84.508946,39.101765],"type":"Point"}
}
