{
  "type": "Feature",
  "properties": {
    "addr:full": "621 Walsh Dr New Carlisle OH 45344",
    "addr:housenumber": "621",
    "addr:postcode": "45344",
    "addr:street": "Walsh Dr",
    "iso:country": "US",
    "sg:address": "621 Walsh Dr",
    "sg:city": "New Carlisle",
    "sg:classifiers": [
      {
        "category": "Education",
        "subcategory": "School",
        "type": "Public Place"
      }
    ],
    "sg:phone": "+1 937 845 4480",
    "sg:postcode": "45344",
    "sg:province": "OH",
    "sg:tags": [
      "elementary"
    ],
    "wof:name": "Westlake Elementary School",
    "wof:placetype": "venue"
  },
  "geometry": {"coordinates":[-84.035638,39.945674],"type":"Point"}
}
