{
  "type": "Feature",
  "properties": {
    "addr:full":"965 Harbor View Dr Westerville OH 43081",
    "addr:housenumber":"965",
    "addr:postcode":"43081",
    "addr:street":"Harbor View Dr",
    "iso:country":"US",
    "sg:address":"965 Harbor View Dr",
    "sg:city":"Westerville",
    "sg:classifiers":[
        {
            "category":"Manufacturing",
            "subcategory":"Tools & Machinery",
            "type":"Manufacturing & Wholesale Goods"
        }
    ],
    "sg:phone":"+1 614 882 8121",
    "sg:postcode":"43081",
    "sg:province":"OH",
    "sg:tags":[
        "laboratory",
        "scale",
        "balance"
    ],
    "wof:name":"Fuller Weighing Systems",
    "wof:placetype":"venue"
},
  "geometry": {"coordinates":[-82.898596,40.117155],"type":"Point"}
}