{
  "type": "Feature",
  "properties": {
    "addr:full":"4500 Hanley Rd Millbury OH 43447",
    "addr:housenumber":"4500",
    "addr:postcode":"43447",
    "addr:street":"Hanley Rd",
    "iso:country":"US",
    "sg:address":"4500 Hanley Rd",
    "sg:city":"Millbury",
    "sg:classifiers":[
        {
            "category":"Freight",
            "type":"Transportation"
        }
    ],
    "sg:phone":"+1 419 837 2088",
    "sg:postcode":"43447",
    "sg:province":"OH",
    "sg:tags":[
        "local",
        "storage",
        "trucking"
    ],
    "wof:name":"John Shessler Trucking",
    "wof:placetype":"venue"
},
  "geometry": {"coordinates":[-83.482106,41.529407],"type":"Point"}
}