{
  "type": "Feature",
  "properties": {
    "iso:country":"US",
    "sg:address":"5269 State Rte 45",
    "sg:city":"Rome",
    "sg:classifiers":[
        {
            "category":"Building & Trades",
            "subcategory":"Construction",
            "type":"Services"
        }
    ],
    "sg:phone":"+1 440 563 9552",
    "sg:postcode":"44085",
    "sg:province":"OH",
    "sg:tags":[
        "general",
        "contractor"
    ],
    "wof:name":"B & B Improvements",
    "wof:placetype":"venue"
},
  "geometry": {"coordinates":[-80.865054,41.605401],"type":"Point"}
}