{
  "type": "Feature",
  "properties": {
    "iso:country":"US",
    "sg:address":"4949 S Co Rd 25A",
    "sg:city":"Tipp City",
    "sg:classifiers":[
        {
            "category":"Professional",
            "type":"Services"
        }
    ],
    "sg:phone":"+1 937 669 5390",
    "sg:postcode":"45371",
    "sg:province":"OH",
    "sg:tags":[
        "establishment"
    ],
    "wof:name":"Mcivaine Dedicated Logistics",
    "wof:placetype":"venue"
},
  "geometry": {"coordinates":[-84.199618,39.972401],"type":"Point"}
}