{
  "type": "Feature",
  "properties": {
    "addr:full": "3209 Delaney St Kettering OH 45420",
    "addr:housenumber": "3209",
    "addr:postcode": "45420",
    "addr:street": "Delaney St",
    "iso:country": "US",
    "sg:address": "3209 Delaney St",
    "sg:city": "Kettering",
    "sg:classifiers": [
      {
        "category": "Manufacturing",
        "subcategory": "Metals",
        "type": "Manufacturing \u0026 Wholesale Goods"
      }
    ],
    "sg:phone": "+1 937 299 3939",
    "sg:postcode": "45420",
    "sg:province": "OH",
    "sg:tags": [
      "steel"
    ],
    "wof:name": "Gem City Welding",
    "wof:placetype": "venue"
  },
  "geometry": {"coordinates":[-84.11966,39.696746],"type":"Point"}
}
