{
  "type": "Feature",
  "properties": {
    "iso:country":"US",
    "sg:address":"3209 Delaney St",
    "sg:city":"Kettering",
    "sg:classifiers":[
        {
            "category":"Manufacturing",
            "subcategory":"Metals",
            "type":"Manufacturing & Wholesale Goods"
        }
    ],
    "sg:phone":"+1 937 299 3939",
    "sg:postcode":"45420",
    "sg:province":"OH",
    "sg:tags":[
        "steel"
    ],
    "wof:name":"Gem City Welding",
    "wof:placetype":"venue"
},
  "geometry": {"coordinates":[-84.11966,39.696746],"type":"Point"}
}