{
  "type": "Feature",
  "properties": {
    "addr:full": "639 Congress Park Dr Centerville OH 45459",
    "addr:housenumber": "639",
    "addr:postcode": "45459",
    "addr:street": "Congress Park Dr",
    "iso:country": "US",
    "sg:address": "639 Congress Park Dr",
    "sg:city": "Centerville",
    "sg:classifiers": [
      {
        "category": "Shopping",
        "type": "Retail Goods"
      }
    ],
    "sg:phone": "+1 937 435 7041",
    "sg:postcode": "45459",
    "sg:province": "OH",
    "sg:tags": [
      "limb",
      "orthopedic",
      "appliance",
      "artificial",
      "merchandise"
    ],
    "sg:website": "www.fidelityorthopedic.com",
    "wof:name": "Fidelity Orthopedic Inc",
    "wof:placetype": "venue"
  },
  "geometry": {"coordinates":[-84.180603,39.634473],"type":"Point"}
}
