{
  "type": "Feature",
  "properties": {
    "addr:full": "1706 Mario Pl Fremont OH 43420",
    "addr:housenumber": "1706",
    "addr:postcode": "43420",
    "addr:street": "Mario Pl",
    "iso:country": "US",
    "sg:address": "1706 Mario Pl",
    "sg:city": "Fremont",
    "sg:classifiers": [
      {
        "category": "Shopping",
        "subcategory": "Gifts \u0026 Souvenirs",
        "type": "Retail Goods"
      }
    ],
    "sg:phone": "+1 419 334 8835",
    "sg:postcode": "43420",
    "sg:province": "OH",
    "wof:name": "TDH All About Gifts",
    "wof:placetype": "venue"
  },
  "geometry": {"coordinates":[-83.087644,41.335833],"type":"Point"}
}
