{
  "type": "Feature",
  "properties": {
    "iso:country":"US",
    "sg:address":"412 Avon Belden Rd",
    "sg:city":"Avon Lake",
    "sg:classifiers":[
        {
            "category":"Professional",
            "subcategory":"Accounting & Tax Preparation",
            "type":"Services"
        }
    ],
    "sg:phone":"+1 440 930 8949",
    "sg:postcode":"44012",
    "sg:province":"OH",
    "sg:tags":[
        "accountant"
    ],
    "wof:name":"John G Vertal CPA & Assoc",
    "wof:placetype":"venue"
},
  "geometry": {"coordinates":[-82.018866,41.497053],"type":"Point"}
}