{
  "type": "Feature",
  "properties": {
    "addr:full": "387 Griggy Rd Hartville OH 44632",
    "addr:housenumber": "387",
    "addr:postcode": "44632",
    "addr:street": "Griggy Rd",
    "iso:country": "US",
    "sg:address": "387 Griggy Rd",
    "sg:city": "Hartville",
    "sg:phone": "+1 330 877 9224",
    "sg:postcode": "44632",
    "sg:province": "OH",
    "sg:tags": [
      "farm",
      "soybean"
    ],
    "wof:name": "F Pero",
    "wof:placetype": "venue"
  },
  "geometry": {"coordinates":[-81.308382,41.001312],"type":"Point"}
}
