{
  "type": "Feature",
  "properties": {
    "addr:full": "819 McKay Ct Youngstown OH 44512",
    "addr:housenumber": "819",
    "addr:postcode": "44512",
    "addr:street": "Mckay Ct",
    "iso:country": "US",
    "sg:address": "819 McKay Ct",
    "sg:city": "Youngstown",
    "sg:classifiers": [
      {
        "category": "Health Services",
        "subcategory": "Podiatrist",
        "type": "Services"
      }
    ],
    "sg:phone": "+1 330 758 4335",
    "sg:postcode": "44512",
    "sg:province": "OH",
    "wof:name": "Advanced Podiatry",
    "wof:placetype": "venue"
  },
  "geometry": {"coordinates":[-80.637424,41.023315],"type":"Point"}
}
