{
  "type": "Feature",
  "properties": {
    "iso:country":"US",
    "sg:address":"5950 Springdale Rd",
    "sg:city":"Cincinnati",
    "sg:classifiers":[
        {
            "category":"Recreation",
            "type":"Entertainment"
        }
    ],
    "sg:phone":"+1 513 385 3322",
    "sg:postcode":"45247",
    "sg:province":"OH",
    "sg:tags":[
        "concessionaire"
    ],
    "wof:name":"Kissel Food Concession",
    "wof:placetype":"venue"
},
  "geometry": {"coordinates":[-84.638623,39.227779],"type":"Point"}
}