{
  "type": "Feature",
  "properties": {
    "addr:full": "12736 Abbey Rd Cleveland OH 44133",
    "addr:housenumber": "12736",
    "addr:postcode": "44133",
    "addr:street": "Abbey Rd",
    "iso:country": "US",
    "sg:address": "12736 Abbey Rd",
    "sg:city": "Cleveland",
    "sg:classifiers": [
      {
        "category": "Building \u0026 Trades",
        "subcategory": "Construction",
        "type": "Services"
      }
    ],
    "sg:phone": "+1 440 237 6804",
    "sg:postcode": "44133",
    "sg:province": "OH",
    "sg:tags": [
      "hanging",
      "painter",
      "contractor"
    ],
    "wof:name": "A Glow Painting",
    "wof:placetype": "venue"
  },
  "geometry": {"coordinates":[-81.775056,41.323776],"type":"Point"}
}
