{
  "type": "Feature",
  "properties": {
    "iso:country":"US",
    "sg:address":"19800 Center Ridge Rd",
    "sg:city":"Cleveland",
    "sg:classifiers":[
        {
            "category":"Shopping",
            "type":"Retail Goods"
        },
        {
            "category":"Wholesale",
            "subcategory":"Jewelry",
            "type":"Manufacturing & Wholesale Goods"
        }
    ],
    "sg:phone":"+1 440 356 4002",
    "sg:postcode":"44116",
    "sg:province":"OH",
    "sg:tags":[
        "trophy",
        "other",
        "medal",
        "plaque",
        "award"
    ],
    "wof:name":"Forest City Trophy Ctr",
    "wof:placetype":"venue"
},
  "geometry": {"coordinates":[-81.841953,41.464981],"type":"Point"}
}