{
  "type": "Feature",
  "properties": {
    "addr:full": "1110 Pendleton St Cincinnati OH 45202",
    "addr:housenumber": "1110",
    "addr:postcode": "45202",
    "addr:street": "Pendleton St",
    "iso:country": "US",
    "sg:address": "1110 Pendleton St",
    "sg:city": "Cincinnati",
    "sg:classifiers": [
      {
        "category": "Shopping",
        "subcategory": "Clothing, Apparel, \u0026 Fashions",
        "type": "Retail Goods"
      }
    ],
    "sg:phone": "+1 513 784 0888",
    "sg:postcode": "45202",
    "sg:province": "OH",
    "wof:name": "Scapheld Inc",
    "wof:placetype": "venue"
  },
  "geometry": {"coordinates":[-84.506717,39.109891],"type":"Point"}
}
