{
  "type": "Feature",
  "properties": {
    "iso:country":"US",
    "sg:address":"1110 Pendleton St",
    "sg:city":"Cincinnati",
    "sg:classifiers":[
        {
            "category":"Shopping",
            "subcategory":"Clothing, Apparel, & Fashions",
            "type":"Retail Goods"
        }
    ],
    "sg:phone":"+1 513 784 0888",
    "sg:postcode":"45202",
    "sg:province":"OH",
    "wof:name":"Scapheld Inc",
    "wof:placetype":"venue"
},
  "geometry": {"coordinates":[-84.50671699999999,39.109891],"type":"Point"}
}