{
  "type": "Feature",
  "properties": {
    "iso:country":"US",
    "sg:address":"1219 W Trenton Ave",
    "sg:city":"Findlay",
    "sg:classifiers":[
        {
            "category":"Restaurant",
            "type":"Food & Drink"
        }
    ],
    "sg:phone":"+1 419 429 1668",
    "sg:postcode":"45840",
    "sg:province":"OH",
    "sg:tags":[
        "eating"
    ],
    "wof:name":"China Garden",
    "wof:placetype":"venue"
},
  "geometry": {"coordinates":[-83.677109,41.058688],"type":"Point"}
}