{
  "type": "Feature",
  "properties": {
    "addr:full": "5524 Driftwood Rd Columbus OH 43229",
    "addr:housenumber": "5524",
    "addr:postcode": "43229",
    "addr:street": "Driftwood Rd",
    "iso:country": "US",
    "sg:address": "5524 Driftwood Rd",
    "sg:city": "Columbus",
    "sg:classifiers": [
      {
        "category": "Manufacturing",
        "subcategory": "Tools \u0026 Machinery",
        "type": "Manufacturing \u0026 Wholesale Goods"
      }
    ],
    "sg:phone": "+1 614 885 3538",
    "sg:postcode": "43229",
    "sg:province": "OH",
    "sg:tags": [
      "shop",
      "equipment",
      "lighting",
      "beauty",
      "mfg"
    ],
    "wof:name": "Tan Reflection",
    "wof:placetype": "venue"
  },
  "geometry": {"coordinates":[-82.977977,40.078977],"type":"Point"}
}
