{
  "type": "Feature",
  "properties": {
    "addr:full": "63 E Main St Xenia OH 45385",
    "addr:housenumber": "63",
    "addr:postcode": "45385",
    "addr:street": "E Main St",
    "iso:country": "US",
    "sg:address": "63 E Main St",
    "sg:city": "Xenia",
    "sg:classifiers": [
      {
        "category": "Shopping",
        "subcategory": "Used Merchandise",
        "type": "Retail Goods"
      }
    ],
    "sg:phone": "+1 937 374 7476",
    "sg:postcode": "45385",
    "sg:province": "OH",
    "sg:tags": [
      "shop",
      "thrift"
    ],
    "wof:name": "Mary's Odds \u0026 Ends",
    "wof:placetype": "venue"
  },
  "geometry": {"coordinates":[-83.927885,39.685059],"type":"Point"}
}
