{
  "type": "Feature",
  "properties": {
    "addr:full": "190 N Union St Akron OH 44304",
    "addr:housenumber": "190",
    "addr:postcode": "44304",
    "addr:street": "N Union St",
    "iso:country": "US",
    "sg:address": "190 N Union St",
    "sg:city": "Akron",
    "sg:classifiers": [
      {
        "category": "Professional",
        "subcategory": "Lawyer \u0026 Legal Services",
        "type": "Services"
      }
    ],
    "sg:phone": "+1 330 535 9160",
    "sg:postcode": "44304",
    "sg:province": "OH",
    "sg:tags": [
      "attorney"
    ],
    "wof:name": "Warner Mendenhall",
    "wof:placetype": "venue"
  },
  "geometry": {"coordinates":[-81.505321,41.085214],"type":"Point"}
}
