{
  "type": "Feature",
  "properties": {
    "addr:full": "887 Parkwood Dr Cleveland OH 44108",
    "addr:housenumber": "887",
    "addr:postcode": "44108",
    "addr:street": "Parkwood Dr",
    "iso:country": "US",
    "sg:address": "887 Parkwood Dr",
    "sg:city": "Cleveland",
    "sg:classifiers": [
      {
        "category": "Place Of Worship",
        "type": "Public Place"
      },
      {
        "category": "Place Of Worship",
        "subcategory": "Temple",
        "type": "Public Place"
      }
    ],
    "sg:phone": "+1 216 761 5480",
    "sg:postcode": "44108",
    "sg:province": "OH",
    "sg:tags": [
      "church"
    ],
    "wof:name": "Temple Holy",
    "wof:placetype": "venue"
  },
  "geometry": {"coordinates":[-81.610229,41.53371],"type":"Point"}
}
