{
  "type": "Feature",
  "properties": {
    "addr:full": "7937 School Rd Cincinnati OH 45249",
    "addr:housenumber": "7937",
    "addr:postcode": "45249",
    "addr:street": "School Rd",
    "iso:country": "US",
    "sg:address": "7937 School Rd",
    "sg:city": "Cincinnati",
    "sg:classifiers": [
      {
        "category": "Manufacturing",
        "subcategory": "Tools \u0026 Machinery",
        "type": "Manufacturing \u0026 Wholesale Goods"
      }
    ],
    "sg:phone": "+1 513 489 1047",
    "sg:postcode": "45249",
    "sg:province": "OH",
    "sg:tags": [
      "fan"
    ],
    "sg:website": "www.americraftmfg.com",
    "wof:name": "Americraft Mfg Co",
    "wof:placetype": "venue"
  },
  "geometry": {"coordinates":[-84.345912,39.285303],"type":"Point"}
}
