{
  "type": "Feature",
  "properties": {
    "iso:country":"US",
    "sg:address":"7937 School Rd",
    "sg:city":"Cincinnati",
    "sg:classifiers":[
        {
            "category":"Manufacturing",
            "subcategory":"Tools & Machinery",
            "type":"Manufacturing & Wholesale Goods"
        }
    ],
    "sg:phone":"+1 513 489 1047",
    "sg:postcode":"45249",
    "sg:province":"OH",
    "sg:tags":[
        "fan"
    ],
    "sg:website":"www.americraftmfg.com",
    "wof:name":"Americraft Mfg Co",
    "wof:placetype":"venue"
},
  "geometry": {"coordinates":[-84.345912,39.285303],"type":"Point"}
}