{
  "type": "Feature",
  "properties": {
    "addr:full": "113 W Wellock Dr Akron OH 44319",
    "addr:housenumber": "113",
    "addr:postcode": "44319",
    "addr:street": "W Wellock Dr",
    "iso:country": "US",
    "sg:address": "113 W Wellock Dr",
    "sg:city": "Akron",
    "sg:classifiers": [
      {
        "category": "Building \u0026 Trades",
        "subcategory": "Construction",
        "type": "Services"
      }
    ],
    "sg:phone": "+1 330 724 7331",
    "sg:postcode": "44319",
    "sg:province": "OH",
    "sg:tags": [
      "general",
      "contractor"
    ],
    "wof:name": "G T Custom Carpentry",
    "wof:placetype": "venue"
  },
  "geometry": {"coordinates":[-81.527628,41.005151],"type":"Point"}
}
