{
  "type": "Feature",
  "properties": {
    "addr:full": "1116 Esther Ave Wellsville OH 43968",
    "addr:housenumber": "1116",
    "addr:postcode": "43968",
    "addr:street": "Esther Ave",
    "iso:country": "US",
    "sg:address": "1116 Esther Ave",
    "sg:city": "Wellsville",
    "sg:classifiers": [
      {
        "category": "Wholesale",
        "subcategory": "Motor Vehicles",
        "type": "Manufacturing \u0026 Wholesale Goods"
      }
    ],
    "sg:phone": "+1 330 532 3205",
    "sg:postcode": "43968",
    "sg:province": "OH",
    "wof:name": "Benco Auto Brokers",
    "wof:placetype": "venue"
  },
  "geometry": {"coordinates":[-80.653178,40.627665],"type":"Point"}
}
