{
  "type": "Feature",
  "properties": {
    "addr:full":"7001 Denison Ave Cleveland OH 44102",
    "addr:housenumber":"7001",
    "addr:postcode":"44102",
    "addr:street":"Denison Ave",
    "iso:country":"US",
    "sg:address":"7001 Denison Ave",
    "sg:city":"Cleveland",
    "sg:classifiers":[
        {
            "category":"Recreation",
            "type":"Entertainment"
        }
    ],
    "sg:phone":"+1 216 961 9765",
    "sg:postcode":"44102",
    "sg:province":"OH",
    "sg:tags":[
        "hall",
        "auditorium"
    ],
    "wof:name":"Sachsenheim Hall",
    "wof:placetype":"venue"
},
  "geometry": {"coordinates":[-81.737199,41.461934],"type":"Point"}
}