{
  "type": "Feature",
  "properties": {
    "iso:country":"US",
    "sg:address":"187 W Johnstown Rd",
    "sg:city":"Columbus",
    "sg:classifiers":[
        {
            "category":"Retail",
            "subcategory":"Portrait Studio",
            "type":"Services"
        }
    ],
    "sg:phone":"+1 614 475 7122",
    "sg:postcode":"43230",
    "sg:province":"OH",
    "sg:tags":[
        "photo"
    ],
    "wof:name":"Bischel Photographic",
    "wof:placetype":"venue"
},
  "geometry": {"coordinates":[-82.886894,40.017267],"type":"Point"}
}