{
  "type": "Feature",
  "properties": {
    "addr:full": "16119 State Rte 190 Fort Jennings OH 45844",
    "addr:housenumber": "16119",
    "addr:postcode": "45844",
    "addr:street": "State Rte 190 Fort",
    "iso:country": "US",
    "sg:address": "16119 State Rte 190",
    "sg:city": "Fort Jennings",
    "sg:phone": "+1 419 286 2301",
    "sg:postcode": "45844",
    "sg:province": "OH",
    "sg:tags": [
      "farm",
      "corn",
      "wheat",
      "soybean"
    ],
    "wof:name": "Eugene Meyer",
    "wof:placetype": "venue"
  },
  "geometry": {"coordinates":[-84.268337,40.947539],"type":"Point"}
}
