{
  "type": "Feature",
  "properties": {
    "addr:full": "3283 W Siebenthaler Ave Dayton OH 45406",
    "addr:housenumber": "3283",
    "addr:postcode": "45406",
    "addr:street": "W Siebenthaler Ave",
    "iso:country": "US",
    "sg:address": "3283 W Siebenthaler Ave",
    "sg:city": "Dayton",
    "sg:classifiers": [
      {
        "category": "Banks \u0026 Credit Unions",
        "subcategory": "Bank",
        "type": "Services"
      }
    ],
    "sg:phone": "+1 937 278 1170",
    "sg:postcode": "45406",
    "sg:province": "OH",
    "sg:tags": [
      "depository",
      "banking",
      "check",
      "cashing"
    ],
    "wof:name": "Check Into Cash",
    "wof:placetype": "venue"
  },
  "geometry": {"coordinates":[-84.244603,39.79821],"type":"Point"}
}
