{
  "type": "Feature",
  "properties": {
    "iso:country":"US",
    "sg:address":"3283 W Siebenthaler Ave",
    "sg:city":"Dayton",
    "sg:classifiers":[
        {
            "category":"Banks & Credit Unions",
            "subcategory":"Bank",
            "type":"Services"
        }
    ],
    "sg:phone":"+1 937 278 1170",
    "sg:postcode":"45406",
    "sg:province":"OH",
    "sg:tags":[
        "depository",
        "banking",
        "check",
        "cashing"
    ],
    "wof:name":"Check Into Cash",
    "wof:placetype":"venue"
},
  "geometry": {"coordinates":[-84.244603,39.79821],"type":"Point"}
}