{
  "type": "Feature",
  "properties": {
    "iso:country":"US",
    "sg:address":"8757 Co Rd 254",
    "sg:city":"Belle Center",
    "sg:classifiers":[
        {
            "category":"Farming",
            "subcategory":"Livestock Farm",
            "type":"Manufacturing & Wholesale Goods"
        }
    ],
    "sg:phone":"+1 937 686 3191",
    "sg:postcode":"43310",
    "sg:province":"OH",
    "sg:tags":[
        "hog",
        "beef",
        "far",
        "corn",
        "cattle",
        "or",
        "feedlot"
    ],
    "wof:name":"Phelps Farm",
    "wof:placetype":"venue"
},
  "geometry": {"coordinates":[-83.852243,40.493768],"type":"Point"}
}