{
  "type": "Feature",
  "properties": {
    "addr:full": "8757 Co Rd 254 Belle Center OH 43310",
    "addr:housenumber": "8757;254",
    "addr:postcode": "43310",
    "addr:street": "Co Rd",
    "iso:country": "US",
    "sg:address": "8757 Co Rd 254",
    "sg:city": "Belle Center",
    "sg:classifiers": [
      {
        "category": "Farming",
        "subcategory": "Livestock Farm",
        "type": "Manufacturing \u0026 Wholesale Goods"
      }
    ],
    "sg:phone": "+1 937 686 3191",
    "sg:postcode": "43310",
    "sg:province": "OH",
    "sg:tags": [
      "hog",
      "beef",
      "far",
      "corn",
      "cattle",
      "or",
      "feedlot"
    ],
    "wof:name": "Phelps Farm",
    "wof:placetype": "venue"
  },
  "geometry": {"coordinates":[-83.852243,40.493768],"type":"Point"}
}
