{
  "type": "Feature",
  "properties": {
    "addr:full": "1240 W 33rd St Lorain OH 44053",
    "addr:housenumber": "1240",
    "addr:postcode": "44053",
    "addr:street": "W 33Rd St",
    "iso:country": "US",
    "sg:address": "1240 W 33rd St",
    "sg:city": "Lorain",
    "sg:classifiers": [
      {
        "category": "Insurance",
        "subcategory": "Insurance Agent",
        "type": "Services"
      }
    ],
    "sg:phone": "+1 440 282 8774",
    "sg:postcode": "44053",
    "sg:province": "OH",
    "wof:name": "Dunn Insurance",
    "wof:placetype": "venue"
  },
  "geometry": {"coordinates":[-82.189012,41.44074],"type":"Point"}
}
