{
  "type": "Feature",
  "properties": {
    "iso:country":"US",
    "sg:address":"2340 Clermont Center Dr",
    "sg:city":"Batavia",
    "sg:classifiers":[
        {
            "category":"Government",
            "subcategory":"Court House",
            "type":"Public Place"
        }
    ],
    "sg:phone":"+1 513 732 7696",
    "sg:postcode":"45103",
    "sg:province":"OH",
    "wof:name":"Juvenile Court",
    "wof:placetype":"venue"
},
  "geometry": {"coordinates":[-84.144452,39.083993],"type":"Point"}
}