{
  "type": "Feature",
  "properties": {
    "addr:full":"555 W Schrock Rd Westerville OH 43081",
    "addr:housenumber":"555",
    "addr:postcode":"43081",
    "addr:street":"W Schrock Rd",
    "iso:country":"US",
    "sg:address":"555 W Schrock Rd",
    "sg:city":"Westerville",
    "sg:classifiers":[
        {
            "category":"Building & Trades",
            "subcategory":"Construction",
            "type":"Services"
        }
    ],
    "sg:phone":"+1 614 890 1587",
    "sg:postcode":"43081",
    "sg:province":"OH",
    "sg:tags":[
        "home",
        "builder"
    ],
    "sg:website":"www.romanellicustomhomes.com",
    "wof:name":"Romanelli Custom Homes",
    "wof:placetype":"venue"
},
  "geometry": {"coordinates":[-82.94418899999999,40.110723],"type":"Point"}
}