{
  "type": "Feature",
  "properties": {
    "iso:country":"US",
    "sg:address":"2121 Velma Ave",
    "sg:city":"Columbus",
    "sg:classifiers":[
        {
            "category":"Arena",
            "subcategory":"Sports Club",
            "type":"Entertainment"
        }
    ],
    "sg:phone":"+1 614 447 2739",
    "sg:postcode":"43211",
    "sg:province":"OH",
    "sg:tags":[
        "soccer"
    ],
    "wof:name":"Columbus Crew",
    "wof:placetype":"venue"
},
  "geometry": {"coordinates":[-82.989018,40.005323],"type":"Point"}
}