{
  "type": "Feature",
  "properties": {
    "addr:full": "8221 Brecksville Rd Brecksville OH 44141",
    "addr:housenumber": "8221",
    "addr:postcode": "44141",
    "addr:street": "Brecksville Rd",
    "iso:country": "US",
    "sg:address": "8221 Brecksville Rd",
    "sg:city": "Brecksville",
    "sg:classifiers": [
      {
        "category": "Banks \u0026 Credit Unions",
        "subcategory": "Investment Brokerage",
        "type": "Services"
      }
    ],
    "sg:phone": "+1 440 526 3633",
    "sg:postcode": "44141",
    "sg:province": "OH",
    "sg:tags": [
      "exchange"
    ],
    "wof:name": "Free Life Corp",
    "wof:placetype": "venue"
  },
  "geometry": {"coordinates":[-81.627479,41.339274],"type":"Point"}
}
