{
  "type": "Feature",
  "properties": {
    "iso:country":"US",
    "sg:address":"160 E 2nd St",
    "sg:city":"Chillicothe",
    "sg:classifiers":[
        {
            "category":"Retail",
            "subcategory":"Auto Repair",
            "type":"Services"
        }
    ],
    "sg:phone":"+1 740 772 1797",
    "sg:postcode":"45601",
    "sg:province":"OH",
    "sg:tags":[
        "wheel",
        "axle",
        "alignment"
    ],
    "wof:name":"Ray's Alignment Svc",
    "wof:placetype":"venue"
},
  "geometry": {"coordinates":[-82.97803999999999,39.335111],"type":"Point"}
}