{
  "type": "Feature",
  "properties": {
    "addr:full": "160 E 2nd St Chillicothe OH 45601",
    "addr:housenumber": "160",
    "addr:postcode": "45601",
    "addr:street": "E 2Nd St",
    "iso:country": "US",
    "sg:address": "160 E 2nd St",
    "sg:city": "Chillicothe",
    "sg:classifiers": [
      {
        "category": "Retail",
        "subcategory": "Auto Repair",
        "type": "Services"
      }
    ],
    "sg:phone": "+1 740 772 1797",
    "sg:postcode": "45601",
    "sg:province": "OH",
    "sg:tags": [
      "wheel",
      "axle",
      "alignment"
    ],
    "wof:name": "Ray's Alignment Svc",
    "wof:placetype": "venue"
  },
  "geometry": {"coordinates":[-82.97804,39.335111],"type":"Point"}
}
