{
  "type": "Feature",
  "properties": {
    "iso:country":"US",
    "sg:address":"120 S Main St",
    "sg:city":"Ada",
    "sg:classifiers":[
        {
            "category":"Health Services",
            "subcategory":"Doctor",
            "type":"Services"
        }
    ],
    "sg:phone":"+1 419 634 5901",
    "sg:postcode":"45810",
    "sg:province":"OH",
    "sg:tags":[
        "dentist"
    ],
    "wof:name":"Mark B Shull DDS",
    "wof:placetype":"venue"
},
  "geometry": {"coordinates":[-83.823139,40.770273],"type":"Point"}
}