{
  "type": "Feature",
  "properties": {
    "addr:full": "14375 Washington Blvd Cleveland OH 44118",
    "addr:housenumber": "14375",
    "addr:postcode": "44118",
    "addr:street": "Washington Blvd",
    "iso:country": "US",
    "sg:address": "14375 Washington Blvd",
    "sg:city": "Cleveland",
    "sg:classifiers": [
      {
        "category": "Professional",
        "type": "Services"
      }
    ],
    "sg:phone": "+1 216 397 0532",
    "sg:postcode": "44118",
    "sg:province": "OH",
    "wof:name": "Elizabeth K Dreben",
    "wof:placetype": "venue"
  },
  "geometry": {"coordinates":[-81.52137,41.490046],"type":"Point"}
}
