{
  "type": "Feature",
  "properties": {
    "addr:full": "6902 Pearl Rd Cleveland OH 44130",
    "addr:housenumber": "6902",
    "addr:postcode": "44130",
    "addr:street": "Pearl Rd",
    "iso:country": "US",
    "sg:address": "6902 Pearl Rd",
    "sg:city": "Cleveland",
    "sg:classifiers": [
      {
        "category": "Real Estate",
        "subcategory": "Real Estate Agent",
        "type": "Services"
      }
    ],
    "sg:phone": "+1 440 842 1914",
    "sg:postcode": "44130",
    "sg:province": "OH",
    "wof:name": "Coldwell Banker Hunter Realty",
    "wof:placetype": "venue"
  },
  "geometry": {"coordinates":[-81.794968,41.376327],"type":"Point"}
}
