{
  "type": "Feature",
  "properties": {
    "addr:full": "30 Harrington Pt Conneaut OH 44030",
    "addr:housenumber": "30",
    "addr:postcode": "44030",
    "addr:street": "Harrington Pt",
    "iso:country": "US",
    "sg:address": "30 Harrington Pt",
    "sg:city": "Conneaut",
    "sg:classifiers": [
      {
        "category": "Building \u0026 Trades",
        "subcategory": "Construction",
        "type": "Services"
      }
    ],
    "sg:phone": "+1 440 992 1289",
    "sg:postcode": "44030",
    "sg:province": "OH",
    "sg:tags": [
      "contractor"
    ],
    "wof:name": "North Point Environmental",
    "wof:placetype": "venue"
  },
  "geometry": {"coordinates":[-80.59488,41.953329],"type":"Point"}
}
