{
  "type": "Feature",
  "properties": {
    "iso:country":"US",
    "sg:address":"5851 Youngstown Warren Rd",
    "sg:city":"Niles",
    "sg:classifiers":[
        {
            "category":"Home & Garden",
            "subcategory":"Furniture",
            "type":"Retail Goods"
        }
    ],
    "sg:phone":"+1 330 544 5554",
    "sg:postcode":"44446",
    "sg:province":"OH",
    "wof:name":"Budget Discount Furniture",
    "wof:placetype":"venue"
},
  "geometry": {"coordinates":[-80.743034,41.207323],"type":"Point"}
}