{
  "type": "Feature",
  "properties": {
    "iso:country":"US",
    "sg:address":"1161 E Main St",
    "sg:city":"Ashland",
    "sg:classifiers":[
        {
            "category":"Banks & Credit Unions",
            "subcategory":"Bank",
            "type":"Services"
        }
    ],
    "sg:phone":"+1 419 281 1590",
    "sg:postcode":"44805",
    "sg:province":"OH",
    "sg:tags":[
        "commercial"
    ],
    "wof:name":"Farmers Insurance",
    "wof:placetype":"venue"
},
  "geometry": {"coordinates":[-82.294771,40.864945],"type":"Point"}
}