{
  "type": "Feature",
  "properties": {
    "addr:full": "399 W Boundary St Perrysburg OH 43551",
    "addr:housenumber": "399",
    "addr:postcode": "43551",
    "addr:street": "W Boundary St",
    "iso:country": "US",
    "sg:address": "399 W Boundary St",
    "sg:city": "Perrysburg",
    "sg:classifiers": [
      {
        "category": "Retail",
        "subcategory": "Veterinary Services",
        "type": "Services"
      }
    ],
    "sg:phone": "+1 419 352 7579",
    "sg:postcode": "43551",
    "sg:province": "OH",
    "wof:name": "Donald R Knepper Dvm",
    "wof:placetype": "venue"
  },
  "geometry": {"coordinates":[-83.641048,41.554953],"type":"Point"}
}
