{
  "type": "Feature",
  "properties": {
    "addr:full":"1880 Turner Rd Xenia OH 45385",
    "addr:housenumber":"1880",
    "addr:postcode":"45385",
    "addr:street":"Turner Rd",
    "iso:country":"US",
    "sg:address":"1880 Turner Rd",
    "sg:city":"Xenia",
    "sg:classifiers":[
        {
            "category":"Home & Garden",
            "subcategory":"Building Materials",
            "type":"Retail Goods"
        }
    ],
    "sg:phone":"+1 937 376 3833",
    "sg:postcode":"45385",
    "sg:province":"OH",
    "sg:tags":[
        "interior",
        "product",
        "wood"
    ],
    "wof:name":"Advance Stair Parts & Lumber",
    "wof:placetype":"venue"
},
  "geometry": {"coordinates":[-83.851292,39.625697],"type":"Point"}
}