{
  "type": "Feature",
  "properties": {
    "iso:country":"US",
    "sg:address":"8180 Regal Ln",
    "sg:city":"West Chester",
    "sg:classifiers":[
        {
            "category":"Wholesale",
            "subcategory":"Machinery & Supplies",
            "type":"Manufacturing & Wholesale Goods"
        }
    ],
    "sg:phone":"+1 513 755 9100",
    "sg:postcode":"45069",
    "sg:province":"OH",
    "sg:tags":[
        "machine",
        "tool"
    ],
    "wof:name":"Applied Machine Tech Inc",
    "wof:placetype":"venue"
},
  "geometry": {"coordinates":[-84.358694,39.323818],"type":"Point"}
}