{
  "type": "Feature",
  "properties": {
    "addr:full": "8180 Regal Ln West Chester OH 45069",
    "addr:housenumber": "8180",
    "addr:postcode": "45069",
    "addr:street": "Regal Ln",
    "iso:country": "US",
    "sg:address": "8180 Regal Ln",
    "sg:city": "West Chester",
    "sg:classifiers": [
      {
        "category": "Wholesale",
        "subcategory": "Machinery \u0026 Supplies",
        "type": "Manufacturing \u0026 Wholesale Goods"
      }
    ],
    "sg:phone": "+1 513 755 9100",
    "sg:postcode": "45069",
    "sg:province": "OH",
    "sg:tags": [
      "machine",
      "tool"
    ],
    "wof:name": "Applied Machine Tech Inc",
    "wof:placetype": "venue"
  },
  "geometry": {"coordinates":[-84.358694,39.323818],"type":"Point"}
}
