{
  "type": "Feature",
  "properties": {
    "iso:country":"US",
    "sg:address":"6955 Plainfield Rd",
    "sg:city":"Cincinnati",
    "sg:classifiers":[
        {
            "category":"Manufacturing",
            "subcategory":"Food",
            "type":"Manufacturing & Wholesale Goods"
        }
    ],
    "sg:phone":"+1 513 891 2900",
    "sg:postcode":"45236",
    "sg:province":"OH",
    "sg:tags":[
        "brandy",
        "spirits",
        "wine"
    ],
    "sg:website":"www.meierswinecellars.com",
    "wof:name":"Meier's Wine Cellars Inc",
    "wof:placetype":"venue"
},
  "geometry": {"coordinates":[-84.400522,39.194541],"type":"Point"}
}