{
  "type": "Feature",
  "properties": {
    "iso:country":"US",
    "sg:address":"1683 Hillcrest Ave",
    "sg:city":"Obetz",
    "sg:classifiers":[
        {
            "category":"Building & Trades",
            "subcategory":"Construction",
            "type":"Services"
        }
    ],
    "sg:phone":"+1 614 836 2244",
    "sg:postcode":"43207",
    "sg:province":"OH",
    "sg:tags":[
        "maker",
        "cabinet"
    ],
    "wof:name":"Wall Cabinet Co",
    "wof:placetype":"venue"
},
  "geometry": {"coordinates":[-82.955833,39.87792],"type":"Point"}
}