{
  "type": "Feature",
  "properties": {
    "iso:country":"US",
    "sg:address":"121 E South St",
    "sg:city":"Bryan",
    "sg:classifiers":[
        {
            "category":"Health Services",
            "subcategory":"Clinic",
            "type":"Services"
        }
    ],
    "sg:phone":"+1 419 636 2702",
    "sg:postcode":"43506",
    "sg:province":"OH",
    "sg:tags":[
        "home"
    ],
    "wof:name":"Americare Home Health Svc",
    "wof:placetype":"venue"
},
  "geometry": {"coordinates":[-84.550714,41.463679],"type":"Point"}
}