{
  "type": "Feature",
  "properties": {
    "iso:country":"US",
    "sg:address":"120 N Warpole St",
    "sg:city":"Upper Sandusky",
    "sg:classifiers":[
        {
            "category":"Restaurant",
            "type":"Food & Drink"
        }
    ],
    "sg:phone":"+1 419 209 0203",
    "sg:postcode":"43351",
    "sg:province":"OH",
    "sg:tags":[
        "pizza"
    ],
    "wof:name":"Capo's Pizza",
    "wof:placetype":"venue"
},
  "geometry": {"coordinates":[-83.290166,40.828604],"type":"Point"}
}