{
  "type": "Feature",
  "properties": {
    "addr:full": "120 N Warpole St Upper Sandusky OH 43351",
    "addr:housenumber": "120",
    "addr:postcode": "43351",
    "addr:street": "N Warpole St",
    "iso:country": "US",
    "sg:address": "120 N Warpole St",
    "sg:city": "Upper Sandusky",
    "sg:classifiers": [
      {
        "category": "Restaurant",
        "type": "Food \u0026 Drink"
      }
    ],
    "sg:phone": "+1 419 209 0203",
    "sg:postcode": "43351",
    "sg:province": "OH",
    "sg:tags": [
      "pizza"
    ],
    "wof:name": "Capo's Pizza",
    "wof:placetype": "venue"
  },
  "geometry": {"coordinates":[-83.290166,40.828604],"type":"Point"}
}
