{
  "type": "Feature",
  "properties": {
    "addr:full": "3 Baker St Norwalk OH 44857",
    "addr:housenumber": "3",
    "addr:postcode": "44857",
    "addr:street": "Baker St",
    "iso:country": "US",
    "sg:address": "3 Baker St",
    "sg:city": "Norwalk",
    "sg:classifiers": [
      {
        "category": "Manufacturing",
        "subcategory": "Tools \u0026 Machinery",
        "type": "Manufacturing \u0026 Wholesale Goods"
      }
    ],
    "sg:phone": "+1 419 668 8402",
    "sg:postcode": "44857",
    "sg:province": "OH",
    "sg:tags": [
      "equipment",
      "printing"
    ],
    "wof:name": "Nu-Life Systems Intl Inc",
    "wof:placetype": "venue"
  },
  "geometry": {"coordinates":[-82.623245,41.245481],"type":"Point"}
}
