{
  "type": "Feature",
  "properties": {
    "iso:country":"US",
    "sg:address":"3 Baker St",
    "sg:city":"Norwalk",
    "sg:classifiers":[
        {
            "category":"Manufacturing",
            "subcategory":"Tools & Machinery",
            "type":"Manufacturing & Wholesale Goods"
        }
    ],
    "sg:phone":"+1 419 668 8402",
    "sg:postcode":"44857",
    "sg:province":"OH",
    "sg:tags":[
        "equipment",
        "printing"
    ],
    "wof:name":"Nu-Life Systems Intl Inc",
    "wof:placetype":"venue"
},
  "geometry": {"coordinates":[-82.623245,41.245481],"type":"Point"}
}