{
  "type": "Feature",
  "properties": {
    "addr:full": "420 W Main St Mechanicsburg OH 43044",
    "addr:housenumber": "420",
    "addr:postcode": "43044",
    "addr:street": "W Main St",
    "iso:country": "US",
    "sg:address": "420 W Main St",
    "sg:city": "Mechanicsburg",
    "sg:classifiers": [
      {
        "category": "Government",
        "subcategory": "Office",
        "type": "Public Place"
      }
    ],
    "sg:phone": "+1 937 834 1013",
    "sg:postcode": "43044",
    "sg:province": "OH",
    "sg:tags": [
      "village"
    ],
    "wof:name": "Mechanicsburg Water Plant",
    "wof:placetype": "venue"
  },
  "geometry": {"coordinates":[-83.567386,40.075398],"type":"Point"}
}
