{
  "type": "Feature",
  "properties": {
    "addr:full":"120 Middle Ave Elyria OH 44035",
    "addr:housenumber":"120",
    "addr:postcode":"44035",
    "addr:street":"Middle Ave",
    "iso:country":"US",
    "sg:address":"120 Middle Ave",
    "sg:city":"Elyria",
    "sg:classifiers":[
        {
            "category":"Insurance",
            "subcategory":"Insurance Agent",
            "type":"Services"
        }
    ],
    "sg:phone":"+1 440 328 3121",
    "sg:postcode":"44035",
    "sg:province":"OH",
    "wof:name":"Primerica Financial Svc",
    "wof:placetype":"venue"
},
  "geometry": {"coordinates":[-82.106773,41.366797],"type":"Point"}
}