{
  "type": "Feature",
  "properties": {
    "addr:full": "59 Kingsmeadow Ln Blacklick OH 43004",
    "addr:housenumber": "59",
    "addr:postcode": "43004",
    "addr:street": "Kingsmeadow Ln",
    "iso:country": "US",
    "sg:address": "59 Kingsmeadow Ln",
    "sg:city": "Blacklick",
    "sg:classifiers": [
      {
        "category": "Home \u0026 Garden",
        "subcategory": "Home Furnishings",
        "type": "Retail Goods"
      }
    ],
    "sg:phone": "+1 614 577 9606",
    "sg:postcode": "43004",
    "sg:province": "OH",
    "sg:tags": [
      "personal",
      "care",
      "supply"
    ],
    "wof:name": "Luna Aromethology",
    "wof:placetype": "venue"
  },
  "geometry": {"coordinates":[-82.797444,39.984449],"type":"Point"}
}
