{
  "type": "Feature",
  "properties": {
    "addr:full": "1811 Mechanicsville Rd Rock Creek OH 44084",
    "addr:housenumber": "1811",
    "addr:postcode": "44084",
    "addr:street": "Mechanicsville Rd",
    "iso:country": "US",
    "sg:address": "1811 Mechanicsville Rd",
    "sg:city": "Rock Creek",
    "sg:classifiers": [
      {
        "category": "Retail",
        "subcategory": "Auto Repair",
        "type": "Services"
      }
    ],
    "sg:phone": "+1 440 466 3805",
    "sg:postcode": "44084",
    "sg:province": "OH",
    "sg:tags": [
      "interior"
    ],
    "wof:name": "SM Wood Company LLC",
    "wof:placetype": "venue"
  },
  "geometry": {"coordinates":[-80.903882,41.700944],"type":"Point"}
}
