{
  "type": "Feature",
  "properties": {
    "iso:country":"US",
    "sg:address":"2726 Perry Dr NW",
    "sg:city":"Canton",
    "sg:classifiers":[
        {
            "category":"Organizations",
            "subcategory":"Community Association",
            "type":"Services"
        }
    ],
    "sg:phone":"+1 330 477 0283",
    "sg:postcode":"44708",
    "sg:province":"OH",
    "sg:tags":[
        "club"
    ],
    "wof:name":"Brookside Country Club Grounds",
    "wof:placetype":"venue"
},
  "geometry": {"coordinates":[-81.463092,40.822808],"type":"Point"}
}