{
  "type": "Feature",
  "properties": {
    "addr:full": "4937 W Broad St Columbus OH 43228",
    "addr:housenumber": "4937",
    "addr:postcode": "43228",
    "addr:street": "W Broad St",
    "iso:country": "US",
    "sg:address": "4937 W Broad St",
    "sg:city": "Columbus",
    "sg:classifiers": [
      {
        "category": "Professional",
        "type": "Services"
      }
    ],
    "sg:phone": "+1 614 878 7777",
    "sg:postcode": "43228",
    "sg:province": "OH",
    "wof:name": "Charles H Bindig",
    "wof:placetype": "venue"
  },
  "geometry": {"coordinates":[-83.133205,39.951978],"type":"Point"}
}
