{
  "type": "Feature",
  "properties": {
    "iso:country":"US",
    "sg:address":"1906 Bethel Rd",
    "sg:city":"Columbus",
    "sg:classifiers":[
        {
            "category":"Health Services",
            "subcategory":"Optometrist",
            "type":"Services"
        }
    ],
    "sg:phone":"+1 614 457 1159",
    "sg:postcode":"43220",
    "sg:province":"OH",
    "wof:name":"Crown Point Family Eye Care",
    "wof:placetype":"venue"
},
  "geometry": {"coordinates":[-83.071636,40.064285],"type":"Point"}
}