{
  "type": "Feature",
  "properties": {
    "addr:full":"200 E Campus View Blvd Columbus OH 43235",
    "addr:housenumber":"200",
    "addr:postcode":"43235",
    "addr:street":"E Campus View Blvd",
    "iso:country":"US",
    "sg:address":"200 E Campus View Blvd",
    "sg:city":"Columbus",
    "sg:classifiers":[
        {
            "category":"Professional",
            "subcategory":"Lawyer & Legal Services",
            "type":"Services"
        }
    ],
    "sg:phone":"+1 614 985 3651",
    "sg:postcode":"43235",
    "sg:province":"OH",
    "sg:tags":[
        "attorney"
    ],
    "wof:name":"Richard Donovan & Assoc",
    "wof:placetype":"venue"
},
  "geometry": {"coordinates":[-83.01340999999999,40.118272],"type":"Point"}
}