{
  "type": "Feature",
  "properties": {
    "iso:country":"US",
    "sg:address":"1047 Sugar Grove Rd SE",
    "sg:city":"Lancaster",
    "sg:classifiers":[
        {
            "category":"Building & Trades",
            "subcategory":"Electrical",
            "type":"Services"
        }
    ],
    "sg:phone":"+1 740 653 6157",
    "sg:postcode":"43130",
    "sg:province":"OH",
    "sg:tags":[
        "electrical",
        "contractor"
    ],
    "wof:name":"Hutchins Electric",
    "wof:placetype":"venue"
},
  "geometry": {"coordinates":[-82.592192,39.701325],"type":"Point"}
}