{
  "type": "Feature",
  "properties": {
    "addr:full":"268 Saint Leger Ave Akron OH 44305",
    "addr:housenumber":"268",
    "addr:postcode":"44305",
    "addr:street":"Saint Leger Ave",
    "iso:country":"US",
    "sg:address":"268 Saint Leger Ave",
    "sg:city":"Akron",
    "sg:classifiers":[
        {
            "category":"Organizations",
            "subcategory":"Religious Organization",
            "type":"Services"
        }
    ],
    "sg:phone":"+1 330 733 3287",
    "sg:postcode":"44305",
    "sg:province":"OH",
    "sg:tags":[
        "clergy"
    ],
    "wof:name":"Timothy A Roeser",
    "wof:placetype":"venue"
},
  "geometry": {"coordinates":[-81.461342,41.070677],"type":"Point"}
}