{
  "type": "Feature",
  "properties": {
    "addr:full":"198 Mills St Wadsworth OH 44281",
    "addr:housenumber":"198",
    "addr:postcode":"44281",
    "addr:street":"Mills St",
    "iso:country":"US",
    "sg:address":"198 Mills St",
    "sg:city":"Wadsworth",
    "sg:classifiers":[
        {
            "category":"Organizations",
            "subcategory":"Religious Organization",
            "type":"Services"
        }
    ],
    "sg:phone":"+1 330 336 3256",
    "sg:postcode":"44281",
    "sg:province":"OH",
    "sg:tags":[
        "church"
    ],
    "wof:name":"First Baptist Church",
    "wof:placetype":"venue"
},
  "geometry": {"coordinates":[-81.73354999999999,41.024021],"type":"Point"}
}