{
  "type": "Feature",
  "properties": {
    "addr:full": "5479 W Co Rd 38 Tiffin OH 44883",
    "addr:housenumber": "5479;38",
    "addr:postcode": "44883",
    "addr:street": "W Co Rd",
    "iso:country": "US",
    "sg:address": "5479 W Co Rd 38",
    "sg:city": "Tiffin",
    "sg:classifiers": [
      {
        "category": "Shopping",
        "type": "Retail Goods"
      }
    ],
    "sg:phone": "+1 419 585 7002",
    "sg:postcode": "44883",
    "sg:province": "OH",
    "sg:tags": [
      "engine",
      "equipment",
      "motor"
    ],
    "wof:name": "Recreational Power Engineering",
    "wof:placetype": "venue"
  },
  "geometry": {"coordinates":[-83.267207,41.166591],"type":"Point"}
}
