{
  "type": "Feature",
  "properties": {
    "addr:full": "102 Huggins Dr Steubenville OH 43952",
    "addr:housenumber": "102",
    "addr:postcode": "43952",
    "addr:street": "Huggins Dr",
    "iso:country": "US",
    "sg:address": "102 Huggins Dr",
    "sg:city": "Steubenville",
    "sg:classifiers": [
      {
        "category": "Building \u0026 Trades",
        "subcategory": "Construction",
        "type": "Services"
      }
    ],
    "sg:phone": "+1 740 282 6750",
    "sg:postcode": "43952",
    "sg:province": "OH",
    "sg:tags": [
      "paving",
      "contractor"
    ],
    "wof:name": "Huggins Paving",
    "wof:placetype": "venue"
  },
  "geometry": {"coordinates":[-80.648999,40.400918],"type":"Point"}
}
