{
  "type": "Feature",
  "properties": {
    "iso:country":"US",
    "sg:address":"4401 Jonesboro Rd",
    "sg:city":"Midland",
    "sg:phone":"+1 937 685 2462",
    "sg:postcode":"45148",
    "sg:province":"OH",
    "sg:tags":[
        "farm",
        "field",
        "crop"
    ],
    "wof:name":"Robert Huffman",
    "wof:placetype":"venue"
},
  "geometry": {"coordinates":[-83.85644000000001,39.285237],"type":"Point"}
}