{
  "type": "Feature",
  "properties": {
    "addr:full": "4401 Jonesboro Rd Midland OH 45148",
    "addr:housenumber": "4401",
    "addr:postcode": "45148",
    "addr:street": "Jonesboro Rd",
    "iso:country": "US",
    "sg:address": "4401 Jonesboro Rd",
    "sg:city": "Midland",
    "sg:phone": "+1 937 685 2462",
    "sg:postcode": "45148",
    "sg:province": "OH",
    "sg:tags": [
      "farm",
      "field",
      "crop"
    ],
    "wof:name": "Robert Huffman",
    "wof:placetype": "venue"
  },
  "geometry": {"coordinates":[-83.85644,39.285237],"type":"Point"}
}
