{
  "type": "Feature",
  "properties": {
    "iso:country":"US",
    "sg:address":"2660 Bowline Ct",
    "sg:city":"Maineville",
    "sg:classifiers":[
        {
            "category":"Real Estate",
            "subcategory":"Real Estate Operator",
            "type":"Services"
        }
    ],
    "sg:phone":"+1 513 683 0103",
    "sg:postcode":"45039",
    "sg:province":"OH",
    "sg:tags":[
        "apartment"
    ],
    "wof:name":"Harborridge At Landen",
    "wof:placetype":"venue"
},
  "geometry": {"coordinates":[-84.268732,39.316867],"type":"Point"}
}