{
  "type": "Feature",
  "properties": {
    "addr:full":"12713 Kinsman Rd Cleveland OH 44120",
    "addr:housenumber":"12713",
    "addr:postcode":"44120",
    "addr:street":"Kinsman Rd",
    "iso:country":"US",
    "sg:address":"12713 Kinsman Rd",
    "sg:city":"Cleveland",
    "sg:classifiers":[
        {
            "category":"Personal",
            "subcategory":"Barber",
            "type":"Services"
        }
    ],
    "sg:phone":"+1 216 991 7971",
    "sg:postcode":"44120",
    "sg:province":"OH",
    "wof:name":"Warren's Barber Shop",
    "wof:placetype":"venue"
},
  "geometry": {"coordinates":[-81.593788,41.466246],"type":"Point"}
}