{
  "type": "Feature",
  "properties": {
    "addr:full": "6785 W 130th St Cleveland OH 44130",
    "addr:housenumber": "6785",
    "addr:postcode": "44130",
    "addr:street": "W 130Th St",
    "iso:country": "US",
    "sg:address": "6785 W 130th St",
    "sg:city": "Cleveland",
    "sg:classifiers": [
      {
        "category": "Banks \u0026 Credit Unions",
        "subcategory": "Bank",
        "type": "Services"
      }
    ],
    "sg:phone": "+1 440 885 5050",
    "sg:postcode": "44130",
    "sg:province": "OH",
    "sg:tags": [
      "loan",
      "real estate"
    ],
    "wof:name": "Mortgage Processing Svc",
    "wof:placetype": "venue"
  },
  "geometry": {"coordinates":[-81.784724,41.375191],"type":"Point"}
}
