{
  "type": "Feature",
  "properties": {
    "addr:full":"4315 Hamilton Cleves Rd Hamilton OH 45013",
    "addr:housenumber":"4315",
    "addr:postcode":"45013",
    "addr:street":"Cleves Rd",
    "iso:country":"US",
    "sg:address":"4315 Hamilton Cleves Rd",
    "sg:city":"Hamilton",
    "sg:classifiers":[
        {
            "category":"Autos & Motor Vehicles",
            "subcategory":"Automobile Sales",
            "type":"Retail Goods"
        }
    ],
    "sg:phone":"+1 513 738 5888",
    "sg:postcode":"45013",
    "sg:province":"OH",
    "sg:tags":[
        "car",
        "dealer"
    ],
    "wof:name":"Ross Auto Outlet",
    "wof:placetype":"venue"
},
  "geometry": {"coordinates":[-84.652873,39.310467],"type":"Point"}
}