{
  "type": "Feature",
  "properties": {
    "addr:full": "1594 Celina Rd Saint Marys OH 45885",
    "addr:housenumber": "1594",
    "addr:postcode": "45885",
    "addr:street": "Celina Rd",
    "iso:country": "US",
    "sg:address": "1594 Celina Rd",
    "sg:city": "Saint Marys",
    "sg:classifiers": [
      {
        "category": "Restaurant",
        "type": "Food \u0026 Drink"
      }
    ],
    "sg:menulink": "http://www.allmenus.com/oh/st-marys/134195-subway/menu/",
    "sg:phone": "+1 419 394 7982",
    "sg:postcode": "45885",
    "sg:province": "OH",
    "sg:tags": [
      "american",
      "sandwich"
    ],
    "wof:name": "Subway",
    "wof:placetype": "venue"
  },
  "geometry": {"coordinates":[-84.404188,40.544179],"type":"Point"}
}
