{
  "type": "Feature",
  "properties": {
    "addr:full": "1662 E Cherry St Youngstown OH 44506",
    "addr:housenumber": "1662",
    "addr:postcode": "44506",
    "addr:street": "E Cherry St",
    "iso:country": "US",
    "sg:address": "1662 E Cherry St",
    "sg:city": "Youngstown",
    "sg:classifiers": [
      {
        "category": "Professional",
        "type": "Services"
      }
    ],
    "sg:phone": "+1 330 744 2276",
    "sg:postcode": "44506",
    "sg:province": "OH",
    "sg:tags": [
      "establishment"
    ],
    "wof:name": "Florand Co",
    "wof:placetype": "venue"
  },
  "geometry": {"coordinates":[-80.620142,41.08322],"type":"Point"}
}
