{
  "type": "Feature",
  "properties": {
    "iso:country":"US",
    "sg:address":"405 Portage Trl",
    "sg:city":"Cuyahoga Falls",
    "sg:classifiers":[
        {
            "category":"Banks & Credit Unions",
            "subcategory":"Investment Brokerage",
            "type":"Services"
        }
    ],
    "sg:phone":"+1 330 945 7300",
    "sg:postcode":"44221",
    "sg:province":"OH",
    "sg:tags":[
        "security"
    ],
    "wof:name":"Transmerica Fincl Resources",
    "wof:placetype":"venue"
},
  "geometry": {"coordinates":[-81.48780600000001,41.137148],"type":"Point"}
}