{
  "type": "Feature",
  "properties": {
    "iso:country":"US",
    "sg:address":"136 E Main St",
    "sg:city":"Lancaster",
    "sg:classifiers":[
        {
            "category":"Real Estate",
            "subcategory":"Real Estate Services",
            "type":"Services"
        }
    ],
    "sg:phone":"+1 740 687 5803",
    "sg:postcode":"43130",
    "sg:province":"OH",
    "sg:tags":[
        "agency",
        "insurance",
        "title"
    ],
    "wof:name":"Edwards & Edwards",
    "wof:placetype":"venue"
},
  "geometry": {"coordinates":[-82.601077,39.71363],"type":"Point"}
}