{
  "type": "Feature",
  "properties": {
    "addr:full": "136 E Main St Lancaster OH 43130",
    "addr:housenumber": "136",
    "addr:postcode": "43130",
    "addr:street": "E Main St",
    "iso:country": "US",
    "sg:address": "136 E Main St",
    "sg:city": "Lancaster",
    "sg:classifiers": [
      {
        "category": "Real Estate",
        "subcategory": "Real Estate Services",
        "type": "Services"
      }
    ],
    "sg:phone": "+1 740 687 5803",
    "sg:postcode": "43130",
    "sg:province": "OH",
    "sg:tags": [
      "agency",
      "insurance",
      "title"
    ],
    "wof:name": "Edwards \u0026 Edwards",
    "wof:placetype": "venue"
  },
  "geometry": {"coordinates":[-82.601077,39.71363],"type":"Point"}
}
