{
  "type": "Feature",
  "properties": {
    "addr:full": "1377 Genessee Ave Columbus OH 43211",
    "addr:housenumber": "1377",
    "addr:postcode": "43211",
    "addr:street": "Genessee Ave",
    "iso:country": "US",
    "sg:address": "1377 Genessee Ave",
    "sg:city": "Columbus",
    "sg:classifiers": [
      {
        "category": "Social Services",
        "subcategory": "Child Care",
        "type": "Services"
      }
    ],
    "sg:phone": "+1 614 262 0798",
    "sg:postcode": "43211",
    "sg:province": "OH",
    "wof:name": "Dede's Daycare",
    "wof:placetype": "venue"
  },
  "geometry": {"coordinates":[-82.972156,40.018914],"type":"Point"}
}
