{
  "type": "Feature",
  "properties": {
    "addr:full":"160 Emmaus Rd Marysville OH 43040",
    "addr:housenumber":"160",
    "addr:postcode":"43040",
    "addr:street":"Emmaus Rd",
    "iso:country":"US",
    "sg:address":"160 Emmaus Rd",
    "sg:city":"Marysville",
    "sg:classifiers":[
        {
            "category":"Restaurant",
            "type":"Food & Drink"
        }
    ],
    "sg:phone":"+1 937 644 0110",
    "sg:postcode":"43040",
    "sg:province":"OH",
    "sg:tags":[
        "eating"
    ],
    "wof:name":"Jerry's House Of Hunan",
    "wof:placetype":"venue"
},
  "geometry": {"coordinates":[-83.383523,40.237951],"type":"Point"}
}