{
  "type": "Feature",
  "properties": {
    "addr:full": "30 Greenback Rd Fort Loramie OH 45845",
    "addr:housenumber": "30",
    "addr:postcode": "45845",
    "addr:street": "Greenback Rd",
    "iso:country": "US",
    "sg:address": "30 Greenback Rd",
    "sg:city": "Fort Loramie",
    "sg:classifiers": [
      {
        "category": "Shopping",
        "type": "Retail Goods"
      }
    ],
    "sg:phone": "+1 937 295 2142",
    "sg:postcode": "45845",
    "sg:province": "OH",
    "sg:tags": [
      "wedding",
      "supply"
    ],
    "wof:name": "Renee's Wrapper's LTD",
    "wof:placetype": "venue"
  },
  "geometry": {"coordinates":[-84.372984,40.343138],"type":"Point"}
}
