{
  "type": "Feature",
  "properties": {
    "iso:country":"US",
    "sg:address":"724 Montgomery Rd NE",
    "sg:city":"Newark",
    "sg:classifiers":[
        {
            "category":"Building & Trades",
            "subcategory":"Plumbing",
            "type":"Services"
        }
    ],
    "sg:phone":"+1 740 763 3961",
    "sg:postcode":"43055",
    "sg:province":"OH",
    "sg:tags":[
        "plumbing",
        "contractor"
    ],
    "wof:name":"Houston Plumbing & Heating Inc",
    "wof:placetype":"venue"
},
  "geometry": {"coordinates":[-82.310506,40.068446],"type":"Point"}
}