{
  "type": "Feature",
  "properties": {
    "iso:country":"US",
    "sg:address":"1500 Polaris Pkwy",
    "sg:city":"Columbus",
    "sg:classifiers":[
        {
            "category":"Coffee & Tea",
            "type":"Food & Drink"
        }
    ],
    "sg:menulink":"http://www.allmenus.com/oh/columbus-city/124805-starbucks-coffee/menu/",
    "sg:phone":"+1 614 885 3366",
    "sg:postcode":"43240",
    "sg:province":"OH",
    "sg:tags":[
        "american"
    ],
    "wof:name":"Starbucks Coffee",
    "wof:placetype":"venue"
},
  "geometry": {"coordinates":[-82.980637,40.145446],"type":"Point"}
}