{
  "type": "Feature",
  "properties": {
    "addr:full": "4391 Gary Way Hilliard OH 43026",
    "addr:housenumber": "4391",
    "addr:postcode": "43026",
    "addr:street": "Gary Way",
    "iso:country": "US",
    "sg:address": "4391 Gary Way",
    "sg:city": "Hilliard",
    "sg:classifiers": [
      {
        "category": "Professional",
        "type": "Services"
      }
    ],
    "sg:phone": "+1 614 527 4633",
    "sg:postcode": "43026",
    "sg:province": "OH",
    "wof:name": "Hemitech Inc",
    "wof:placetype": "venue"
  },
  "geometry": {"coordinates":[-83.175635,40.041196],"type":"Point"}
}
