{
  "type": "Feature",
  "properties": {
    "addr:full":"6420 State Rte 119 Maria Stein OH 45860",
    "addr:housenumber":"6420",
    "addr:postcode":"45860",
    "addr:street":"State Rte 119 Maria",
    "iso:country":"US",
    "sg:address":"6420 State Rte 119",
    "sg:city":"Maria Stein",
    "sg:classifiers":[
        {
            "category":"Insurance",
            "subcategory":"Insurance Agent",
            "type":"Services"
        }
    ],
    "sg:phone":"+1 419 925 4567",
    "sg:postcode":"45860",
    "sg:province":"OH",
    "wof:name":"Homan's Insurance",
    "wof:placetype":"venue"
},
  "geometry": {"coordinates":[-84.557619,40.407411],"type":"Point"}
}