{
  "type": "Feature",
  "properties": {
    "addr:full":"4200 Surface Rd Columbus OH 43228",
    "addr:postcode":"4200;43228",
    "addr:street":"Surface Rd",
    "iso:country":"US",
    "sg:address":"4200 Surface Rd",
    "sg:city":"Columbus",
    "sg:classifiers":[
        {
            "category":"Government",
            "subcategory":"Office",
            "type":"Public Place"
        }
    ],
    "sg:phone":"+1 614 644 5559",
    "sg:postcode":"43228",
    "sg:province":"OH",
    "wof:name":"Fixed Asset Management",
    "wof:placetype":"venue"
},
  "geometry": {"coordinates":[-83.11455599999999,39.955442],"type":"Point"}
}