{
  "type": "Feature",
  "properties": {
    "addr:full":"101 S Miami St Quincy OH 43343",
    "addr:housenumber":"101",
    "addr:postcode":"43343",
    "addr:street":"S Miami St",
    "iso:country":"US",
    "sg:address":"101 S Miami St",
    "sg:city":"Quincy",
    "sg:classifiers":[
        {
            "category":"Banks & Credit Unions",
            "subcategory":"Bank",
            "type":"Services"
        }
    ],
    "sg:phone":"+1 937 585 4268",
    "sg:postcode":"43343",
    "sg:province":"OH",
    "wof:name":"Miami Valley Bank",
    "wof:placetype":"venue"
},
  "geometry": {"coordinates":[-83.96861199999999,40.298162],"type":"Point"}
}