{
  "type": "Feature",
  "properties": {
    "iso:country":"US",
    "sg:address":"2509 E 126th St",
    "sg:city":"Cleveland",
    "sg:classifiers":[
        {
            "category":"Shopping",
            "subcategory":"Computers & Home Electronics",
            "type":"Retail Goods"
        }
    ],
    "sg:phone":"+1 216 229 2292",
    "sg:postcode":"44120",
    "sg:province":"OH",
    "sg:tags":[
        "software"
    ],
    "wof:name":"Utopia Technologies LTD",
    "wof:placetype":"venue"
},
  "geometry": {"coordinates":[-81.59517200000001,41.490357],"type":"Point"}
}