{
  "type": "Feature",
  "properties": {
    "addr:full": "2509 E 126th St Cleveland OH 44120",
    "addr:housenumber": "2509",
    "addr:postcode": "44120",
    "addr:street": "E 126Th St",
    "iso:country": "US",
    "sg:address": "2509 E 126th St",
    "sg:city": "Cleveland",
    "sg:classifiers": [
      {
        "category": "Shopping",
        "subcategory": "Computers \u0026 Home Electronics",
        "type": "Retail Goods"
      }
    ],
    "sg:phone": "+1 216 229 2292",
    "sg:postcode": "44120",
    "sg:province": "OH",
    "sg:tags": [
      "software"
    ],
    "wof:name": "Utopia Technologies LTD",
    "wof:placetype": "venue"
  },
  "geometry": {"coordinates":[-81.595172,41.490357],"type":"Point"}
}
