{
  "type": "Feature",
  "properties": {
    "addr:full":"533 Batavia Pike Cincinnati OH 45244",
    "addr:housenumber":"533",
    "addr:postcode":"45244",
    "addr:street":"Batavia Pike",
    "iso:country":"US",
    "sg:address":"533 Batavia Pike",
    "sg:city":"Cincinnati",
    "sg:classifiers":[
        {
            "category":"Recreation",
            "type":"Entertainment"
        }
    ],
    "sg:phone":"+1 513 688 1501",
    "sg:postcode":"45244",
    "sg:province":"OH",
    "sg:tags":[
        "martial",
        "arts",
        "instruction"
    ],
    "wof:name":"Eastgate Martial Arts Club",
    "wof:placetype":"venue"
},
  "geometry": {"coordinates":[-84.300837,39.105092],"type":"Point"}
}