{
  "type": "Feature",
  "properties": {
    "iso:country":"US",
    "sg:address":"5701 N High St",
    "sg:city":"Columbus",
    "sg:classifiers":[
        {
            "category":"Health Services",
            "subcategory":"Clinic",
            "type":"Services"
        },
        {
            "category":"Social Services",
            "type":"Services"
        }
    ],
    "sg:phone":"+1 614 847 6133",
    "sg:postcode":"43085",
    "sg:province":"OH",
    "sg:tags":[
        "professional",
        "counselor",
        "specialty",
        "outpatient"
    ],
    "wof:name":"Mary Moore-Farell",
    "wof:placetype":"venue"
},
  "geometry": {"coordinates":[-83.018747,40.078147],"type":"Point"}
}