{
  "type": "Feature",
  "properties": {
    "addr:full": "1610 W Lane Ave Columbus OH 43221",
    "addr:housenumber": "1610",
    "addr:postcode": "43221",
    "addr:street": "W Lane Ave",
    "iso:country": "US",
    "sg:address": "1610 W Lane Ave",
    "sg:city": "Columbus",
    "sg:classifiers": [
      {
        "category": "Social Services",
        "subcategory": "Child Care",
        "type": "Services"
      }
    ],
    "sg:phone": "+1 614 486 5567",
    "sg:postcode": "43221",
    "sg:province": "OH",
    "sg:tags": [
      "day"
    ],
    "wof:name": "Labc Child Nurturing Center",
    "wof:placetype": "venue"
  },
  "geometry": {"coordinates":[-83.053049,40.007221],"type":"Point"}
}
