{
  "type": "Feature",
  "properties": {
    "addr:full": "505 Espyville Rd S Marion OH 43302",
    "addr:housenumber": "505",
    "addr:postcode": "43302",
    "addr:street": "Espyville Rd S",
    "iso:country": "US",
    "sg:address": "505 Espyville Rd S",
    "sg:city": "Marion",
    "sg:classifiers": [
      {
        "category": "Building \u0026 Trades",
        "subcategory": "Plumbing",
        "type": "Services"
      }
    ],
    "sg:phone": "+1 740 382 1565",
    "sg:postcode": "43302",
    "sg:province": "OH",
    "sg:tags": [
      "plumbing",
      "contractor"
    ],
    "wof:name": "B \u0026 K Plumbing \u0026 Heating",
    "wof:placetype": "venue"
  },
  "geometry": {"coordinates":[-83.255838,40.575524],"type":"Point"}
}
