{
  "type": "Feature",
  "properties": {
    "iso:country":"US",
    "sg:address":"505 Espyville Rd S",
    "sg:city":"Marion",
    "sg:classifiers":[
        {
            "category":"Building & Trades",
            "subcategory":"Plumbing",
            "type":"Services"
        }
    ],
    "sg:phone":"+1 740 382 1565",
    "sg:postcode":"43302",
    "sg:province":"OH",
    "sg:tags":[
        "plumbing",
        "contractor"
    ],
    "wof:name":"B & K Plumbing & Heating",
    "wof:placetype":"venue"
},
  "geometry": {"coordinates":[-83.255838,40.575524],"type":"Point"}
}