{
  "type": "Feature",
  "properties": {
    "addr:full": "505 W Main St Loudonville OH 44842",
    "addr:housenumber": "505",
    "addr:postcode": "44842",
    "addr:street": "W Main St",
    "iso:country": "US",
    "sg:address": "505 W Main St",
    "sg:city": "Loudonville",
    "sg:classifiers": [
      {
        "category": "Autos \u0026 Motor Vehicles",
        "subcategory": "Fuel \u0026 Gas Station",
        "type": "Retail Goods"
      }
    ],
    "sg:phone": "+1 419 994 4660",
    "sg:postcode": "44842",
    "sg:province": "OH",
    "sg:tags": [
      "oil"
    ],
    "wof:name": "Bp Oil",
    "wof:placetype": "venue"
  },
  "geometry": {"coordinates":[-82.24029,40.635696],"type":"Point"}
}
