{
  "type": "Feature",
  "properties": {
    "iso:country":"US",
    "sg:address":"505 W Main St",
    "sg:city":"Loudonville",
    "sg:classifiers":[
        {
            "category":"Autos & Motor Vehicles",
            "subcategory":"Fuel & Gas Station",
            "type":"Retail Goods"
        }
    ],
    "sg:phone":"+1 419 994 4660",
    "sg:postcode":"44842",
    "sg:province":"OH",
    "sg:tags":[
        "oil"
    ],
    "wof:name":"Bp Oil",
    "wof:placetype":"venue"
},
  "geometry": {"coordinates":[-82.24029,40.635696],"type":"Point"}
}