{
  "type": "Feature",
  "properties": {
    "addr:full":"1471 Lear Industrial Pkwy Avon OH 44011",
    "addr:housenumber":"1471",
    "addr:postcode":"44011",
    "addr:street":"Lear Industrial Pkwy",
    "iso:country":"US",
    "sg:address":"1471 Lear Industrial Pkwy",
    "sg:city":"Avon",
    "sg:classifiers":[
        {
            "category":"Shopping",
            "subcategory":"Clothing, Apparel, & Fashions",
            "type":"Retail Goods"
        }
    ],
    "sg:phone":"+1 440 934 1415",
    "sg:postcode":"44011",
    "sg:province":"OH",
    "wof:name":"Buckle",
    "wof:placetype":"venue"
},
  "geometry": {"coordinates":[-81.99006199999999,41.473652],"type":"Point"}
}