{
  "type": "Feature",
  "properties": {
    "addr:full":"9386 National Rd Brookville OH 45309",
    "addr:housenumber":"9386",
    "addr:postcode":"45309",
    "addr:street":"National Rd",
    "iso:country":"US",
    "sg:address":"9386 National Rd",
    "sg:city":"Brookville",
    "sg:classifiers":[
        {
            "category":"Airport",
            "type":"Transportation"
        }
    ],
    "sg:phone":"+1 937 833 0843",
    "sg:postcode":"45309",
    "sg:province":"OH",
    "sg:tags":[
        "engine",
        "aircraft",
        "maintenance"
    ],
    "wof:name":"Phils Cylinder Svc",
    "wof:placetype":"venue"
},
  "geometry": {"coordinates":[-84.438569,39.86485],"type":"Point"}
}