{
  "type": "Feature",
  "properties": {
    "addr:full": "12502 Kinsman Rd Cleveland OH 44120",
    "addr:housenumber": "12502",
    "addr:postcode": "44120",
    "addr:street": "Kinsman Rd",
    "iso:country": "US",
    "sg:address": "12502 Kinsman Rd",
    "sg:city": "Cleveland",
    "sg:classifiers": [
      {
        "category": "Food \u0026 Beverages",
        "subcategory": "Groceries \u0026 Convenience Stores",
        "type": "Retail Goods"
      }
    ],
    "sg:phone": "+1 216 921 6288",
    "sg:postcode": "44120",
    "sg:province": "OH",
    "sg:tags": [
      "grocer"
    ],
    "wof:name": "Kinsman Food Deal",
    "wof:placetype": "venue"
  },
  "geometry": {"coordinates":[-81.594563,41.466235],"type":"Point"}
}
