{
  "type": "Feature",
  "properties": {
    "iso:country":"US",
    "sg:address":"1096 Co Hwy 3275",
    "sg:city":"Perrysville",
    "sg:phone":"+1 419 938 8622",
    "sg:postcode":"44864",
    "sg:province":"OH",
    "sg:tags":[
        "farm",
        "field",
        "crop"
    ],
    "wof:name":"Hay John",
    "wof:placetype":"venue"
},
  "geometry": {"coordinates":[-82.337538,40.584657],"type":"Point"}
}