{
  "type": "Feature",
  "properties": {
    "addr:full": "1560 Harrisburg Pike Columbus OH 43223",
    "addr:housenumber": "1560",
    "addr:postcode": "43223",
    "addr:street": "Harrisburg Pike",
    "iso:country": "US",
    "sg:address": "1560 Harrisburg Pike",
    "sg:city": "Columbus",
    "sg:classifiers": [
      {
        "category": "Real Estate",
        "subcategory": "Real Estate Agent",
        "type": "Services"
      }
    ],
    "sg:phone": "+1 614 278 4629",
    "sg:postcode": "43223",
    "sg:province": "OH",
    "wof:name": "TTG Properties",
    "wof:placetype": "venue"
  },
  "geometry": {"coordinates":[-83.057434,39.925849],"type":"Point"}
}
