{
  "type": "Feature",
  "properties": {
    "iso:country":"US",
    "sg:address":"1118 Cottonwood Dr",
    "sg:city":"Loveland",
    "sg:classifiers":[
        {
            "category":"Restaurant",
            "type":"Food & Drink"
        }
    ],
    "sg:menulink":"http://www.allmenus.com/oh/loveland/90133-penn-station/menu/",
    "sg:phone":"+1 513 583 5311",
    "sg:postcode":"45140",
    "sg:province":"OH",
    "sg:tags":[
        "wrap",
        "american",
        "sandwich"
    ],
    "wof:name":"Penn Station",
    "wof:placetype":"venue"
},
  "geometry": {"coordinates":[-84.29509899999999,39.255727],"type":"Point"}
}