{
  "type": "Feature",
  "properties": {
    "addr:full": "3142 Shasta Ave Columbus OH 43231",
    "addr:housenumber": "3142",
    "addr:postcode": "43231",
    "addr:street": "Shasta Ave",
    "iso:country": "US",
    "sg:address": "3142 Shasta Ave",
    "sg:city": "Columbus",
    "sg:classifiers": [
      {
        "category": "Building \u0026 Trades",
        "subcategory": "Construction",
        "type": "Services"
      }
    ],
    "sg:phone": "+1 614 898 1990",
    "sg:postcode": "43231",
    "sg:province": "OH",
    "sg:tags": [
      "hanging",
      "contractor"
    ],
    "wof:name": "Myers Painting Co",
    "wof:placetype": "venue"
  },
  "geometry": {"coordinates":[-82.934443,40.084245],"type":"Point"}
}
