{
  "type": "Feature",
  "properties": {
    "addr:full": "1751 Wilbur Ave Fairborn OH 45324",
    "addr:housenumber": "1751",
    "addr:postcode": "45324",
    "addr:street": "Wilbur Ave",
    "iso:country": "US",
    "sg:address": "1751 Wilbur Ave",
    "sg:city": "Fairborn",
    "sg:classifiers": [
      {
        "category": "Organizations",
        "subcategory": "Religious Organization",
        "type": "Services"
      }
    ],
    "sg:phone": "+1 937 878 6790",
    "sg:postcode": "45324",
    "sg:province": "OH",
    "sg:tags": [
      "church"
    ],
    "wof:name": "First Assemblies Of God",
    "wof:placetype": "venue"
  },
  "geometry": {"coordinates":[-84.039009,39.794884],"type":"Point"}
}
