{
  "type": "Feature",
  "properties": {
    "addr:full":"610 N Miami Ave Dayton OH 45449",
    "addr:housenumber":"610",
    "addr:postcode":"45449",
    "addr:street":"N Miami Ave",
    "iso:country":"US",
    "sg:address":"610 N Miami Ave",
    "sg:city":"Dayton",
    "sg:classifiers":[
        {
            "category":"Building & Trades",
            "subcategory":"Construction",
            "type":"Services"
        }
    ],
    "sg:phone":"+1 937 859 4668",
    "sg:postcode":"45449",
    "sg:province":"OH",
    "sg:tags":[
        "body",
        "house",
        "auto"
    ],
    "wof:name":"El Jays Mobile Home Service",
    "wof:placetype":"venue"
},
  "geometry": {"coordinates":[-84.26092,39.676236],"type":"Point"}
}