{
  "type": "Feature",
  "properties": {
    "addr:full": "4328 Hoover Ave Dayton OH 45417",
    "addr:housenumber": "4328",
    "addr:postcode": "45417",
    "addr:street": "Hoover Ave",
    "iso:country": "US",
    "sg:address": "4328 Hoover Ave",
    "sg:city": "Dayton",
    "sg:classifiers": [
      {
        "category": "Organizations",
        "subcategory": "Religious Organization",
        "type": "Services"
      }
    ],
    "sg:phone": "+1 937 263 5463",
    "sg:postcode": "45417",
    "sg:province": "OH",
    "wof:name": "Residence Park Church Of Chrst",
    "wof:placetype": "venue"
  },
  "geometry": {"coordinates":[-84.257128,39.761314],"type":"Point"}
}
