{
  "type": "Feature",
  "properties": {
    "addr:full":"3040 Topping Ln Chagrin Falls OH 44022",
    "addr:housenumber":"3040",
    "addr:postcode":"44022",
    "addr:street":"Topping Ln",
    "iso:country":"US",
    "sg:address":"3040 Topping Ln",
    "sg:city":"Chagrin Falls",
    "sg:classifiers":[
        {
            "category":"Insurance",
            "subcategory":"Insurance Agent",
            "type":"Services"
        }
    ],
    "sg:phone":"+1 440 893 9622",
    "sg:postcode":"44022",
    "sg:province":"OH",
    "wof:name":"Marc S Byrnes & Assoc AGC",
    "wof:placetype":"venue"
},
  "geometry": {"coordinates":[-81.432856,41.475644],"type":"Point"}
}