{
  "type": "Feature",
  "properties": {
    "addr:full":"1725 Carll St Cincinnati OH 45225",
    "addr:housenumber":"1725",
    "addr:postcode":"45225",
    "addr:street":"Carll St",
    "iso:country":"US",
    "sg:address":"1725 Carll St",
    "sg:city":"Cincinnati",
    "sg:classifiers":[
        {
            "category":"Organizations",
            "subcategory":"Religious Organization",
            "type":"Services"
        }
    ],
    "sg:phone":"+1 513 471 6509",
    "sg:postcode":"45225",
    "sg:province":"OH",
    "sg:tags":[
        "church"
    ],
    "wof:name":"Pleasant Grove Missionary Bapt",
    "wof:placetype":"venue"
},
  "geometry": {"coordinates":[-84.553299,39.134819],"type":"Point"}
}