{
  "type": "Feature",
  "properties": {
    "addr:full":"12427 Cedar Rd Cleveland OH 44106",
    "addr:housenumber":"12427",
    "addr:postcode":"44106",
    "addr:street":"Cedar Rd",
    "iso:country":"US",
    "sg:address":"12427 Cedar Rd",
    "sg:city":"Cleveland",
    "sg:classifiers":[
        {
            "category":"Travel",
            "subcategory":"Travel Agent",
            "type":"Entertainment"
        }
    ],
    "sg:phone":"+1 216 795 7676",
    "sg:postcode":"44106",
    "sg:province":"OH",
    "sg:tags":[
        "agency",
        "bureau"
    ],
    "wof:name":"Cedar Hill Travel",
    "wof:placetype":"venue"
},
  "geometry": {"coordinates":[-81.592507,41.501131],"type":"Point"}
}