{
  "type": "Feature",
  "properties": {
    "iso:country":"US",
    "sg:address":"733 Vaughn Ridge Rd",
    "sg:city":"West Union",
    "sg:classifiers":[
        {
            "category":"Home & Garden",
            "subcategory":"Building Materials",
            "type":"Retail Goods"
        }
    ],
    "sg:phone":"+1 937 544 2968",
    "sg:postcode":"45693",
    "sg:province":"OH",
    "sg:tags":[
        "lumber"
    ],
    "wof:name":"Mc Coy Lumber Co",
    "wof:placetype":"venue"
},
  "geometry": {"coordinates":[-83.494646,38.805684],"type":"Point"}
}