{
  "type": "Feature",
  "properties": {
    "addr:full": "3733 Glenmore Ave Cincinnati OH 45211",
    "addr:housenumber": "3733",
    "addr:postcode": "45211",
    "addr:street": "Glenmore Ave",
    "iso:country": "US",
    "sg:address": "3733 Glenmore Ave",
    "sg:city": "Cincinnati",
    "sg:classifiers": [
      {
        "category": "Social Services",
        "subcategory": "Child Care",
        "type": "Services"
      }
    ],
    "sg:phone": "+1 513 662 6111",
    "sg:postcode": "45211",
    "sg:province": "OH",
    "wof:name": "Aunt Julie's Daycare",
    "wof:placetype": "venue"
  },
  "geometry": {"coordinates":[-84.611194,39.156218],"type":"Point"}
}
