{
  "type": "Feature",
  "properties": {
    "addr:full":"3307 State Rte 534 Southington OH 44470",
    "addr:housenumber":"3307",
    "addr:postcode":"44470",
    "addr:street":"State Rte 534",
    "iso:country":"US",
    "sg:address":"3307 State Rte 534",
    "sg:city":"Southington",
    "sg:classifiers":[
        {
            "category":"Government",
            "subcategory":"Post Office",
            "type":"Public Place"
        }
    ],
    "sg:phone":"+1 330 898 6788",
    "sg:postcode":"44470",
    "sg:province":"OH",
    "sg:tags":[
        "postal",
        "us"
    ],
    "wof:name":"US Post Office",
    "wof:placetype":"venue"
},
  "geometry": {"coordinates":[-80.955904,41.308575],"type":"Point"}
}