{
  "type": "Feature",
  "properties": {
    "iso:country":"US",
    "sg:address":"10583 Tanagerhills Dr",
    "sg:city":"Cincinnati",
    "sg:classifiers":[
        {
            "category":"Professional",
            "subcategory":"Business Services",
            "type":"Services"
        }
    ],
    "sg:phone":"+1 513 677 5338",
    "sg:postcode":"45249",
    "sg:province":"OH",
    "sg:tags":[
        "translator",
        "interpreter"
    ],
    "sg:website":"www.vice-versa.com",
    "wof:name":"Vice Versa Translation Svc",
    "wof:placetype":"venue"
},
  "geometry": {"coordinates":[-84.30843400000001,39.252328],"type":"Point"}
}