{
  "type": "Feature",
  "properties": {
    "addr:full": "2600 Brentwood Rd Cleveland OH 44122",
    "addr:housenumber": "2600",
    "addr:postcode": "44122",
    "addr:street": "Brentwood Rd",
    "iso:country": "US",
    "sg:address": "2600 Brentwood Rd",
    "sg:city": "Cleveland",
    "sg:classifiers": [
      {
        "category": "Manufacturing",
        "subcategory": "Metals",
        "type": "Manufacturing \u0026 Wholesale Goods"
      }
    ],
    "sg:phone": "+1 216 464 2268",
    "sg:postcode": "44122",
    "sg:province": "OH",
    "sg:tags": [
      "steel"
    ],
    "wof:name": "M L Fried \u0026 Assoc",
    "wof:placetype": "venue"
  },
  "geometry": {"coordinates":[-81.513678,41.490857],"type":"Point"}
}
