{
  "type": "Feature",
  "properties": {
    "iso:country":"US",
    "sg:address":"213 E Spring St",
    "sg:city":"St Marys",
    "sg:classifiers":[
        {
            "category":"Bars & Pubs",
            "type":"Food & Drink"
        }
    ],
    "sg:phone":"+1 419 394 3975",
    "sg:postcode":"45885",
    "sg:province":"OH",
    "wof:name":"C & C Loft & Lounge",
    "wof:placetype":"venue"
},
  "geometry": {"coordinates":[-84.38549,40.544211],"type":"Point"}
}