{
  "type": "Feature",
  "properties": {
    "addr:full":"308 Bank St Painesville OH 44077",
    "addr:housenumber":"308",
    "addr:postcode":"44077",
    "addr:street":"Bank St",
    "iso:country":"US",
    "sg:address":"308 Bank St",
    "sg:city":"Painesville",
    "sg:classifiers":[
        {
            "category":"Shopping",
            "subcategory":"Used Merchandise",
            "type":"Retail Goods"
        }
    ],
    "sg:phone":"+1 440 639 8661",
    "sg:postcode":"44077",
    "sg:province":"OH",
    "wof:name":"Bank Street Trader",
    "wof:placetype":"venue"
},
  "geometry": {"coordinates":[-81.233424,41.719878],"type":"Point"}
}