{
  "type": "Feature",
  "properties": {
    "iso:country":"US",
    "sg:address":"15401 Akron Canfield Rd",
    "sg:city":"Berlin Center",
    "sg:classifiers":[
        {
            "category":"Government",
            "subcategory":"Post Office",
            "type":"Public Place"
        }
    ],
    "sg:phone":"+1 330 547 2351",
    "sg:postcode":"44401",
    "sg:province":"OH",
    "wof:name":"US Post Office",
    "wof:placetype":"venue"
},
  "geometry": {"coordinates":[-80.940505,41.024452],"type":"Point"}
}