{
  "type": "Feature",
  "properties": {
    "addr:full":"8650 Beatty St NW Massillon OH 44646",
    "addr:housenumber":"8650",
    "addr:postcode":"44646",
    "addr:street":"Beatty St Nw",
    "iso:country":"US",
    "sg:address":"8650 Beatty St NW",
    "sg:city":"Massillon",
    "sg:classifiers":[
        {
            "category":"Organizations",
            "subcategory":"Religious Organization",
            "type":"Services"
        }
    ],
    "sg:phone":"+1 330 833 9650",
    "sg:postcode":"44646",
    "sg:province":"OH",
    "wof:name":"Amherst Community Brethren In Christ Church",
    "wof:placetype":"venue"
},
  "geometry": {"coordinates":[-81.511703,40.850899],"type":"Point"}
}