{
  "type": "Feature",
  "properties": {
    "addr:full": "309 E 156th St Cleveland OH 44110",
    "addr:housenumber": "309",
    "addr:postcode": "44110",
    "addr:street": "E 156Th St",
    "iso:country": "US",
    "sg:address": "309 E 156th St",
    "sg:city": "Cleveland",
    "sg:classifiers": [
      {
        "category": "Organizations",
        "subcategory": "Religious Organization",
        "type": "Services"
      }
    ],
    "sg:phone": "+1 216 531 3343",
    "sg:postcode": "44110",
    "sg:province": "OH",
    "sg:tags": [
      "church"
    ],
    "wof:name": "Church Morning Glory",
    "wof:placetype": "venue"
  },
  "geometry": {"coordinates":[-81.571896,41.57467],"type":"Point"}
}
