{
  "type": "Feature",
  "properties": {
    "addr:full":"5755 Grant Ave Cleveland OH 44105",
    "addr:housenumber":"5755",
    "addr:postcode":"44105",
    "addr:street":"Grant Ave",
    "iso:country":"US",
    "sg:address":"5755 Grant Ave",
    "sg:city":"Cleveland",
    "sg:classifiers":[
        {
            "category":"Manufacturing",
            "subcategory":"Metals",
            "type":"Manufacturing & Wholesale Goods"
        }
    ],
    "sg:phone":"+1 216 883 8100",
    "sg:postcode":"44105",
    "sg:province":"OH",
    "wof:name":"Copper & Brass Sales Inc",
    "wof:placetype":"venue"
},
  "geometry": {"coordinates":[-81.64670700000001,41.43903],"type":"Point"}
}