{
  "type": "Feature",
  "properties": {
    "addr:full":"5674 Dover Rd Apple Creek OH 44606",
    "addr:housenumber":"5674",
    "addr:postcode":"44606",
    "addr:street":"Dover Rd",
    "iso:country":"US",
    "sg:address":"5674 Dover Rd",
    "sg:city":"Apple Creek",
    "sg:classifiers":[
        {
            "category":"Food & Beverages",
            "subcategory":"Fruits & Vegetables",
            "type":"Retail Goods"
        }
    ],
    "sg:phone":"+1 330 698 0404",
    "sg:postcode":"44606",
    "sg:province":"OH",
    "wof:name":"Bauerle Pumpkin Raspberry Frm",
    "wof:placetype":"venue"
},
  "geometry": {"coordinates":[-81.865318,40.756765],"type":"Point"}
}