{
  "type": "Feature",
  "properties": {
    "iso:country":"US",
    "sg:address":"6802 Miami Ave",
    "sg:city":"Cincinnati",
    "sg:classifiers":[
        {
            "category":"Building & Trades",
            "subcategory":"Plumbing",
            "type":"Services"
        }
    ],
    "sg:phone":"+1 513 271 1615",
    "sg:postcode":"45243",
    "sg:province":"OH",
    "sg:tags":[
        "balancing",
        "air"
    ],
    "sg:website":"www.melinkcorp.com",
    "wof:name":"Melink Corp.",
    "wof:placetype":"venue"
},
  "geometry": {"coordinates":[-84.363556,39.18573],"type":"Point"}
}