{
  "type": "Feature",
  "properties": {
    "addr:full":"103 E 5th St Cincinnati OH 45202",
    "addr:housenumber":"103",
    "addr:postcode":"45202",
    "addr:street":"E 5Th St",
    "iso:country":"US",
    "sg:address":"103 E 5th St",
    "sg:city":"Cincinnati",
    "sg:classifiers":[
        {
            "category":"Restaurant",
            "type":"Food & Drink"
        }
    ],
    "sg:phone":"+1 513 621 5868",
    "sg:postcode":"45202",
    "sg:province":"OH",
    "sg:tags":[
        "grocery",
        "eating"
    ],
    "wof:name":"California Orange Bars",
    "wof:placetype":"venue"
},
  "geometry": {"coordinates":[-84.509727,39.101512],"type":"Point"}
}