{
  "type": "Feature",
  "properties": {
    "iso:country":"US",
    "sg:address":"1655 Tiffin Ave",
    "sg:city":"Findlay",
    "sg:classifiers":[
        {
            "category":"Recreation",
            "type":"Entertainment"
        }
    ],
    "sg:phone":"+1 419 423 2628",
    "sg:postcode":"45840",
    "sg:province":"OH",
    "wof:name":"Blanchard Vlly Acdmy Mssg",
    "wof:placetype":"venue"
},
  "geometry": {"coordinates":[-83.61657099999999,41.05257],"type":"Point"}
}