{
  "type": "Feature",
  "properties": {
    "addr:full":"2467 Lightsville Broadway Rd Rossburg OH 45362",
    "addr:housenumber":"2467",
    "addr:postcode":"45362",
    "addr:street":"Lightsville Broadway Rd",
    "iso:country":"US",
    "sg:address":"2467 Lightsville Broadway Rd",
    "sg:city":"Rossburg",
    "sg:phone":"+1 937 338 4311",
    "sg:postcode":"45362",
    "sg:province":"OH",
    "sg:tags":[
        "farm",
        "grain",
        "cash"
    ],
    "wof:name":"E&M Carrico",
    "wof:placetype":"venue"
},
  "geometry": {"coordinates":[-84.711248,40.285714],"type":"Point"}
}