{
  "type": "Feature",
  "properties": {
    "iso:country":"US",
    "sg:address":"8223 Simpson Creek Way",
    "sg:city":"Mason",
    "sg:classifiers":[
        {
            "category":"Building & Trades",
            "subcategory":"Construction",
            "type":"Services"
        }
    ],
    "sg:phone":"+1 513 336 8112",
    "sg:postcode":"45040",
    "sg:province":"OH",
    "sg:tags":[
        "house"
    ],
    "wof:name":"Simpson Creek",
    "wof:placetype":"venue"
},
  "geometry": {"coordinates":[-84.328371,39.319389],"type":"Point"}
}