{
  "type": "Feature",
  "properties": {
    "addr:full":"8330 Mayfield Rd Chesterland OH 44026",
    "addr:housenumber":"8330",
    "addr:postcode":"44026",
    "addr:street":"Mayfield Rd",
    "iso:country":"US",
    "sg:address":"8330 Mayfield Rd",
    "sg:city":"Chesterland",
    "sg:classifiers":[
        {
            "category":"Shopping",
            "subcategory":"Bicycles & Sporting Goods",
            "type":"Retail Goods"
        }
    ],
    "sg:phone":"+1 440 729 9472",
    "sg:postcode":"44026",
    "sg:province":"OH",
    "sg:tags":[
        "equipment",
        "skiing"
    ],
    "sg:website":"www.ferdlaster.com",
    "wof:name":"Ferdl Aster Ski Shop",
    "wof:placetype":"venue"
},
  "geometry": {"coordinates":[-81.345508,41.522314],"type":"Point"}
}