{
  "type": "Feature",
  "properties": {
    "addr:full": "2250 Central Point Pkwy Lima OH 45804",
    "addr:housenumber": "2250",
    "addr:postcode": "45804",
    "addr:street": "Central Point Pkwy",
    "iso:country": "US",
    "sg:address": "2250 Central Point Pkwy",
    "sg:city": "Lima",
    "sg:classifiers": [
      {
        "category": "Professional",
        "type": "Services"
      }
    ],
    "sg:phone": "+1 419 221 0781",
    "sg:postcode": "45804",
    "sg:province": "OH",
    "sg:tags": [
      "establishment"
    ],
    "wof:name": "Reichhold",
    "wof:placetype": "venue"
  },
  "geometry": {"coordinates":[-84.091315,40.707754],"type":"Point"}
}
