{
  "type": "Feature",
  "properties": {
    "iso:country":"US",
    "sg:address":"550 Blackhawk Trl",
    "sg:city":"Loveland",
    "sg:classifiers":[
        {
            "category":"Autos & Motor Vehicles",
            "subcategory":"Fuel & Gas Station",
            "type":"Retail Goods"
        }
    ],
    "sg:phone":"+1 513 683 4763",
    "sg:postcode":"45140",
    "sg:province":"OH",
    "sg:tags":[
        "oil"
    ],
    "wof:name":"Exxon Mobil Corp",
    "wof:placetype":"venue"
},
  "geometry": {"coordinates":[-84.275502,39.230936],"type":"Point"}
}