{
  "type": "Feature",
  "properties": {
    "addr:full": "550 Blackhawk Trl Loveland OH 45140",
    "addr:housenumber": "550",
    "addr:postcode": "45140",
    "addr:street": "Blackhawk Trl",
    "iso:country": "US",
    "sg:address": "550 Blackhawk Trl",
    "sg:city": "Loveland",
    "sg:classifiers": [
      {
        "category": "Autos \u0026 Motor Vehicles",
        "subcategory": "Fuel \u0026 Gas Station",
        "type": "Retail Goods"
      }
    ],
    "sg:phone": "+1 513 683 4763",
    "sg:postcode": "45140",
    "sg:province": "OH",
    "sg:tags": [
      "oil"
    ],
    "wof:name": "Exxon Mobil Corp",
    "wof:placetype": "venue"
  },
  "geometry": {"coordinates":[-84.275502,39.230936],"type":"Point"}
}
