{
  "type": "Feature",
  "properties": {
    "addr:full": "311 Sandusky St Plymouth OH 44865",
    "addr:housenumber": "311",
    "addr:postcode": "44865",
    "addr:street": "Sandusky St",
    "iso:country": "US",
    "sg:address": "311 Sandusky St",
    "sg:city": "Plymouth",
    "sg:classifiers": [
      {
        "category": "Insurance",
        "subcategory": "Insurance Agent",
        "type": "Services"
      }
    ],
    "sg:phone": "+1 419 687 4032",
    "sg:postcode": "44865",
    "sg:province": "OH",
    "wof:name": "Auto Owners Insurance",
    "wof:placetype": "venue"
  },
  "geometry": {"coordinates":[-82.670407,41.005225],"type":"Point"}
}
