{
  "type": "Feature",
  "properties": {
    "addr:full": "8606 Hemlock Ridge Dr Willoughby OH 44094",
    "addr:housenumber": "8606",
    "addr:postcode": "44094",
    "addr:street": "Hemlock Ridge Dr",
    "iso:country": "US",
    "sg:address": "8606 Hemlock Ridge Dr",
    "sg:city": "Willoughby",
    "sg:classifiers": [
      {
        "category": "Social Services",
        "subcategory": "Child Care",
        "type": "Services"
      }
    ],
    "sg:phone": "+1 440 256 3129",
    "sg:postcode": "44094",
    "sg:province": "OH",
    "sg:tags": [
      "day"
    ],
    "wof:name": "After Schl Enrchment Programms",
    "wof:placetype": "venue"
  },
  "geometry": {"coordinates":[-81.335631,41.621864],"type":"Point"}
}
