{
  "type": "Feature",
  "properties": {
    "addr:full": "6363 US Hwy 50 Hillsboro OH 45133",
    "addr:housenumber": "6363",
    "addr:postcode": "45133",
    "addr:street": "Us Hwy 50",
    "iso:country": "US",
    "sg:address": "6363 US Hwy 50",
    "sg:city": "Hillsboro",
    "sg:classifiers": [
      {
        "category": "Autos \u0026 Motor Vehicles",
        "subcategory": "Automobile Sales",
        "type": "Retail Goods"
      }
    ],
    "sg:phone": "+1 937 840 9163",
    "sg:postcode": "45133",
    "sg:province": "OH",
    "sg:tags": [
      "car",
      "dealer"
    ],
    "wof:name": "Performance Motors",
    "wof:placetype": "venue"
  },
  "geometry": {"coordinates":[-83.651859,39.204409],"type":"Point"}
}
