{
  "type": "Feature",
  "properties": {
    "iso:country":"US",
    "sg:address":"14901 Glen Valley Dr",
    "sg:city":"Middlefield",
    "sg:classifiers":[
        {
            "category":"Travel",
            "subcategory":"Travel Agent",
            "type":"Entertainment"
        }
    ],
    "sg:phone":"+1 440 632 1000",
    "sg:postcode":"44062",
    "sg:province":"OH",
    "sg:tags":[
        "agency"
    ],
    "wof:name":"Shamrock Travel",
    "wof:placetype":"venue"
},
  "geometry": {"coordinates":[-81.058365,41.461036],"type":"Point"}
}