{
  "type": "Feature",
  "properties": {
    "addr:full":"34610 Lake Shore Blvd Willoughby OH 44095",
    "addr:housenumber":"34610",
    "addr:postcode":"44095",
    "addr:street":"Lake Shore Blvd",
    "iso:country":"US",
    "sg:address":"34610 Lake Shore Blvd",
    "sg:city":"Willoughby",
    "sg:classifiers":[
        {
            "category":"Restaurant",
            "type":"Food & Drink"
        }
    ],
    "sg:phone":"+1 440 942 3770",
    "sg:postcode":"44095",
    "sg:province":"OH",
    "sg:tags":[
        "eating"
    ],
    "wof:name":"Timberlake Family Restaurant",
    "wof:placetype":"venue"
},
  "geometry": {"coordinates":[-81.447686,41.663385],"type":"Point"}
}