{
  "type": "Feature",
  "properties": {
    "iso:country":"US",
    "sg:address":"101 Shinkle St",
    "sg:city":"Findlay",
    "sg:classifiers":[
        {
            "category":"Real Estate",
            "subcategory":"Real Estate Operator",
            "type":"Services"
        }
    ],
    "sg:phone":"+1 419 423 3846",
    "sg:postcode":"45840",
    "sg:province":"OH",
    "sg:tags":[
        "building",
        "apartment"
    ],
    "wof:name":"Shinkle Properties III",
    "wof:placetype":"venue"
},
  "geometry": {"coordinates":[-83.661357,41.043968],"type":"Point"}
}