{
  "type": "Feature",
  "properties": {
    "addr:full": "77 S Main St Utica OH 43080",
    "addr:housenumber": "77",
    "addr:postcode": "43080",
    "addr:street": "S Main St",
    "iso:country": "US",
    "sg:address": "77 S Main St",
    "sg:city": "Utica",
    "sg:classifiers": [
      {
        "category": "Restaurant",
        "type": "Food \u0026 Drink"
      }
    ],
    "sg:phone": "+1 740 892 3017",
    "sg:postcode": "43080",
    "sg:province": "OH",
    "wof:name": "Watts Restaurant",
    "wof:placetype": "venue"
  },
  "geometry": {"coordinates":[-82.452858,40.232981],"type":"Point"}
}
