{
  "type": "Feature",
  "properties": {
    "iso:country":"US",
    "sg:address":"77 S Main St",
    "sg:city":"Utica",
    "sg:classifiers":[
        {
            "category":"Restaurant",
            "type":"Food & Drink"
        }
    ],
    "sg:phone":"+1 740 892 3017",
    "sg:postcode":"43080",
    "sg:province":"OH",
    "wof:name":"Watts Restaurant",
    "wof:placetype":"venue"
},
  "geometry": {"coordinates":[-82.45285800000001,40.232981],"type":"Point"}
}