{
  "type": "Feature",
  "properties": {
    "iso:country":"US",
    "sg:address":"11119 Wilkins Run Rd NE",
    "sg:city":"Newark",
    "sg:classifiers":[
        {
            "category":"Building & Trades",
            "subcategory":"Construction",
            "type":"Services"
        }
    ],
    "sg:phone":"+1 740 345 2971",
    "sg:postcode":"43055",
    "sg:province":"OH",
    "sg:tags":[
        "contractor"
    ],
    "wof:name":"Philip L Baughman",
    "wof:placetype":"venue"
},
  "geometry": {"coordinates":[-82.335697,40.128018],"type":"Point"}
}