{
  "type": "Feature",
  "properties": {
    "addr:full": "2700 E Kemper Rd Cincinnati OH 45241",
    "addr:housenumber": "2700",
    "addr:postcode": "45241",
    "addr:street": "E Kemper Rd",
    "iso:country": "US",
    "sg:address": "2700 E Kemper Rd",
    "sg:city": "Cincinnati",
    "sg:classifiers": [
      {
        "category": "Insurance",
        "subcategory": "Insurance Agent",
        "type": "Services"
      }
    ],
    "sg:phone": "+1 513 772 2300",
    "sg:postcode": "45241",
    "sg:province": "OH",
    "wof:name": "State Farm Insurance",
    "wof:placetype": "venue"
  },
  "geometry": {"coordinates":[-84.421636,39.283822],"type":"Point"}
}
