{
  "type": "Feature",
  "properties": {
    "iso:country":"US",
    "sg:address":"100 Milton Carlisle Rd",
    "sg:city":"New Carlisle",
    "sg:classifiers":[
        {
            "category":"Manufacturing",
            "subcategory":"Retail Goods",
            "type":"Manufacturing & Wholesale Goods"
        }
    ],
    "sg:phone":"+1 937 882 6948",
    "sg:postcode":"45344",
    "sg:province":"OH",
    "sg:tags":[
        "product",
        "mfg"
    ],
    "wof:name":"Lhs Mfg Services Ltd",
    "wof:placetype":"venue"
},
  "geometry": {"coordinates":[-83.93176800000001,39.925565],"type":"Point"}
}