{
  "type": "Feature",
  "properties": {
    "addr:full": "100 Milton Carlisle Rd New Carlisle OH 45344",
    "addr:housenumber": "100",
    "addr:postcode": "45344",
    "addr:street": "Milton Carlisle Rd",
    "iso:country": "US",
    "sg:address": "100 Milton Carlisle Rd",
    "sg:city": "New Carlisle",
    "sg:classifiers": [
      {
        "category": "Manufacturing",
        "subcategory": "Retail Goods",
        "type": "Manufacturing \u0026 Wholesale Goods"
      }
    ],
    "sg:phone": "+1 937 882 6948",
    "sg:postcode": "45344",
    "sg:province": "OH",
    "sg:tags": [
      "product",
      "mfg"
    ],
    "wof:name": "Lhs Mfg Services Ltd",
    "wof:placetype": "venue"
  },
  "geometry": {"coordinates":[-83.931768,39.925565],"type":"Point"}
}
