{
  "type": "Feature",
  "properties": {
    "iso:country":"US",
    "sg:address":"335 N 6th St",
    "sg:city":"Zanesville",
    "sg:classifiers":[
        {
            "category":"Manufacturing",
            "subcategory":"Food",
            "type":"Manufacturing & Wholesale Goods"
        }
    ],
    "sg:phone":"+1 740 452 2721",
    "sg:postcode":"43701",
    "sg:province":"OH",
    "sg:tags":[
        "bottler"
    ],
    "wof:name":"Pepsi-Cola Bottling Co",
    "wof:placetype":"venue"
},
  "geometry": {"coordinates":[-82.00497,39.944248],"type":"Point"}
}