{
  "type": "Feature",
  "properties": {
    "addr:full":"12711 Royalton Rd North Royalton OH 44133",
    "addr:housenumber":"12711",
    "addr:postcode":"44133",
    "addr:street":"Royalton Rd",
    "iso:country":"US",
    "sg:address":"12711 Royalton Rd",
    "sg:city":"North Royalton",
    "sg:classifiers":[
        {
            "category":"Manufacturing",
            "subcategory":"Textiles",
            "type":"Manufacturing & Wholesale Goods"
        }
    ],
    "sg:phone":"+1 440 237 6893",
    "sg:postcode":"44133",
    "sg:province":"OH",
    "sg:tags":[
        "print",
        "matt",
        "artwork",
        "frame",
        "custom"
    ],
    "wof:name":"Kens Renditions",
    "wof:placetype":"venue"
},
  "geometry": {"coordinates":[-81.78289700000001,41.315247],"type":"Point"}
}