{
  "type": "Feature",
  "properties": {
    "iso:country":"US",
    "sg:address":"5211 Park Dr",
    "sg:city":"Medina",
    "sg:classifiers":[
        {
            "category":"Insurance",
            "subcategory":"Life Insurance",
            "type":"Services"
        }
    ],
    "sg:phone":"+1 330 764 4540",
    "sg:postcode":"44256",
    "sg:province":"OH",
    "sg:tags":[
        "financial"
    ],
    "wof:name":"Rjg Agency Inc",
    "wof:placetype":"venue"
},
  "geometry": {"coordinates":[-81.802657,41.130148],"type":"Point"}
}