{
  "type": "Feature",
  "properties": {
    "addr:full":"1209 E Main St Ashland OH 44805",
    "addr:housenumber":"1209",
    "addr:postcode":"44805",
    "addr:street":"E Main St",
    "iso:country":"US",
    "sg:address":"1209 E Main St",
    "sg:city":"Ashland",
    "sg:classifiers":[
        {
            "category":"Government",
            "subcategory":"Office",
            "type":"Public Place"
        }
    ],
    "sg:phone":"+1 419 289 8137",
    "sg:postcode":"44805",
    "sg:province":"OH",
    "sg:tags":[
        "village"
    ],
    "wof:name":"Ashland Municipal Clerk Of Ct",
    "wof:placetype":"venue"
},
  "geometry": {"coordinates":[-82.29095700000001,40.864062],"type":"Point"}
}