{
  "type": "Feature",
  "properties": {
    "addr:full": "1721 Duck Creek Rd Cincinnati OH 45207",
    "addr:housenumber": "1721",
    "addr:postcode": "45207",
    "addr:street": "Duck Creek Rd",
    "iso:country": "US",
    "sg:address": "1721 Duck Creek Rd",
    "sg:city": "Cincinnati",
    "sg:classifiers": [
      {
        "category": "Real Estate",
        "subcategory": "Developer",
        "type": "Services"
      }
    ],
    "sg:phone": "+1 513 961 2179",
    "sg:postcode": "45207",
    "sg:province": "OH",
    "sg:tags": [
      "cemetery"
    ],
    "wof:name": "Catholic Calvary Cemetery Assn",
    "wof:placetype": "venue"
  },
  "geometry": {"coordinates":[-84.470291,39.14164],"type":"Point"}
}
