{
  "type": "Feature",
  "properties": {
    "addr:full": "880 Kidron Rd Orrville OH 44667",
    "addr:housenumber": "880",
    "addr:postcode": "44667",
    "addr:street": "Kidron Rd",
    "iso:country": "US",
    "sg:address": "880 Kidron Rd",
    "sg:city": "Orrville",
    "sg:classifiers": [
      {
        "category": "Building \u0026 Trades",
        "subcategory": "Construction",
        "type": "Services"
      }
    ],
    "sg:phone": "+1 330 857 1861",
    "sg:postcode": "44667",
    "sg:province": "OH",
    "sg:tags": [
      "contractor"
    ],
    "wof:name": "Steiner Fencing",
    "wof:placetype": "venue"
  },
  "geometry": {"coordinates":[-81.745319,40.788751],"type":"Point"}
}
