{
  "type": "Feature",
  "properties": {
    "iso:country":"US",
    "sg:address":"880 Kidron Rd",
    "sg:city":"Orrville",
    "sg:classifiers":[
        {
            "category":"Building & Trades",
            "subcategory":"Construction",
            "type":"Services"
        }
    ],
    "sg:phone":"+1 330 857 1861",
    "sg:postcode":"44667",
    "sg:province":"OH",
    "sg:tags":[
        "contractor"
    ],
    "wof:name":"Steiner Fencing",
    "wof:placetype":"venue"
},
  "geometry": {"coordinates":[-81.74531899999999,40.788751],"type":"Point"}
}