{
  "type": "Feature",
  "properties": {
    "iso:country":"US",
    "sg:address":"8180 Corporate Park Dr",
    "sg:city":"Cincinnati",
    "sg:classifiers":[
        {
            "category":"Professional",
            "subcategory":"Computer Services",
            "type":"Services"
        }
    ],
    "sg:phone":"+1 513 719 9100",
    "sg:postcode":"45242",
    "sg:province":"OH",
    "sg:tags":[
        "consultant"
    ],
    "sg:website":"www.dsc-online.com",
    "wof:name":"Definitive Solutions",
    "wof:placetype":"venue"
},
  "geometry": {"coordinates":[-84.339083,39.25997],"type":"Point"}
}