{
  "type": "Feature",
  "properties": {
    "addr:full": "5573 Spellmire Dr Cincinnati OH 45246",
    "addr:housenumber": "5573",
    "addr:postcode": "45246",
    "addr:street": "Spellmire Dr",
    "iso:country": "US",
    "sg:address": "5573 Spellmire Dr",
    "sg:city": "Cincinnati",
    "sg:classifiers": [
      {
        "category": "Shopping",
        "type": "Retail Goods"
      }
    ],
    "sg:phone": "+1 513 942 5328",
    "sg:postcode": "45246",
    "sg:province": "OH",
    "sg:tags": [
      "factory",
      "outlet"
    ],
    "wof:name": "Crable Factory Outlet",
    "wof:placetype": "venue"
  },
  "geometry": {"coordinates":[-84.44314,39.302131],"type":"Point"}
}
