{
  "type": "Feature",
  "properties": {
    "addr:full": "7140 State Rte 37 New Lexington OH 43764",
    "addr:housenumber": "7140",
    "addr:postcode": "43764",
    "addr:street": "State Rte 37",
    "iso:country": "US",
    "sg:address": "7140 State Rte 37",
    "sg:city": "New Lexington",
    "sg:classifiers": [
      {
        "category": "Farming",
        "subcategory": "Livestock Farm",
        "type": "Manufacturing \u0026 Wholesale Goods"
      }
    ],
    "sg:phone": "+1 740 342 2213",
    "sg:postcode": "43764",
    "sg:province": "OH",
    "sg:tags": [
      "beef",
      "feedlot",
      "cattle"
    ],
    "wof:name": "Ned Underwood",
    "wof:placetype": "venue"
  },
  "geometry": {"coordinates":[-82.184101,39.706873],"type":"Point"}
}
