{
  "type": "Feature",
  "properties": {
    "iso:country":"US",
    "sg:address":"4865 Wales Ave NW",
    "sg:city":"Massillon",
    "sg:classifiers":[
        {
            "category":"Sports & Exercise",
            "subcategory":"Golf",
            "type":"Entertainment"
        }
    ],
    "sg:phone":"+1 330 832 1581",
    "sg:postcode":"44646",
    "sg:province":"OH",
    "wof:name":"Shady Hollow Country Club Co",
    "wof:placetype":"venue"
},
  "geometry": {"coordinates":[-81.49659699999999,40.845402],"type":"Point"}
}