{
  "type": "Feature",
  "properties": {
    "addr:full": "4865 Wales Ave NW Massillon OH 44646",
    "addr:housenumber": "4865",
    "addr:postcode": "44646",
    "addr:street": "Wales Ave Nw",
    "iso:country": "US",
    "sg:address": "4865 Wales Ave NW",
    "sg:city": "Massillon",
    "sg:classifiers": [
      {
        "category": "Sports \u0026 Exercise",
        "subcategory": "Golf",
        "type": "Entertainment"
      }
    ],
    "sg:phone": "+1 330 832 1581",
    "sg:postcode": "44646",
    "sg:province": "OH",
    "wof:name": "Shady Hollow Country Club Co",
    "wof:placetype": "venue"
  },
  "geometry": {"coordinates":[-81.496597,40.845402],"type":"Point"}
}
