{
  "type": "Feature",
  "properties": {
    "addr:full": "921 Giant Oaks Mill Rd Wheelersburg OH 45694",
    "addr:housenumber": "921",
    "addr:postcode": "45694",
    "addr:street": "Giant Oaks Mill Rd",
    "iso:country": "US",
    "sg:address": "921 Giant Oaks Mill Rd",
    "sg:city": "Wheelersburg",
    "sg:classifiers": [
      {
        "category": "Farming",
        "subcategory": "Livestock Farm",
        "type": "Manufacturing \u0026 Wholesale Goods"
      }
    ],
    "sg:phone": "+1 740 574 5272",
    "sg:postcode": "45694",
    "sg:province": "OH",
    "sg:tags": [
      "beef",
      "feedlot",
      "cattle"
    ],
    "wof:name": "Dyers Farm",
    "wof:placetype": "venue"
  },
  "geometry": {"coordinates":[-82.834644,38.694012],"type":"Point"}
}
