{
  "type": "Feature",
  "properties": {
    "addr:full": "2000 Apollo Dr Cleveland OH 44142",
    "addr:housenumber": "2000",
    "addr:postcode": "44142",
    "addr:street": "Apollo Dr",
    "iso:country": "US",
    "sg:address": "2000 Apollo Dr",
    "sg:city": "Cleveland",
    "sg:classifiers": [
      {
        "category": "Banks \u0026 Credit Unions",
        "subcategory": "Investment Brokerage",
        "type": "Services"
      }
    ],
    "sg:phone": "+1 216 416 2500",
    "sg:postcode": "44142",
    "sg:province": "OH",
    "sg:tags": [
      "advisory",
      "financial"
    ],
    "sg:website": "www.eaton.com",
    "wof:name": "Eaton Corp",
    "wof:placetype": "venue"
  },
  "geometry": {"coordinates":[-81.874554,41.403656],"type":"Point"}
}
