{
  "type": "Feature",
  "properties": {
    "addr:full": "525 N Cleveland Massillon Rd Akron OH 44333",
    "addr:housenumber": "525",
    "addr:postcode": "44333",
    "addr:street": "N Cleveland Massillon Rd",
    "iso:country": "US",
    "sg:address": "525 N Cleveland Massillon Rd",
    "sg:city": "Akron",
    "sg:classifiers": [
      {
        "category": "Insurance",
        "subcategory": "Insurance Agent",
        "type": "Services"
      }
    ],
    "sg:phone": "+1 330 666 6371",
    "sg:postcode": "44333",
    "sg:province": "OH",
    "wof:name": "Allstate Insurance Co",
    "wof:placetype": "venue"
  },
  "geometry": {"coordinates":[-81.637008,41.150332],"type":"Point"}
}
