{
  "type": "Feature",
  "properties": {
    "iso:country":"US",
    "sg:address":"19094 State Rte 141",
    "sg:city":"Patriot",
    "sg:classifiers":[
        {
            "category":"Manufacturing",
            "subcategory":"Lumber",
            "type":"Manufacturing & Wholesale Goods"
        }
    ],
    "sg:phone":"+1 740 379 2909",
    "sg:postcode":"45658",
    "sg:province":"OH",
    "sg:tags":[
        "grocery",
        "logging"
    ],
    "wof:name":"Ingles Logging",
    "wof:placetype":"venue"
},
  "geometry": {"coordinates":[-82.43992,38.747827],"type":"Point"}
}