{
  "type": "Feature",
  "properties": {
    "iso:country":"US",
    "sg:address":"386 Broadway Ave",
    "sg:city":"Cleveland",
    "sg:classifiers":[
        {
            "category":"Professional",
            "subcategory":"Business Services",
            "type":"Services"
        }
    ],
    "sg:phone":"+1 440 786 1156",
    "sg:postcode":"44146",
    "sg:province":"OH",
    "sg:tags":[
        "embroidery"
    ],
    "wof:name":"Lynn's Logos",
    "wof:placetype":"venue"
},
  "geometry": {"coordinates":[-81.543838,41.398374],"type":"Point"}
}