{
  "type": "Feature",
  "properties": {
    "addr:full": "29900 Solon Industrial Pkwy Solon OH 44139",
    "addr:postcode": "29900;44139",
    "addr:street": "Industrial Pkwy",
    "iso:country": "US",
    "sg:address": "29900 Solon Industrial Pkwy",
    "sg:city": "Solon",
    "sg:classifiers": [
      {
        "category": "Manufacturing",
        "subcategory": "Tools \u0026 Machinery",
        "type": "Manufacturing \u0026 Wholesale Goods"
      }
    ],
    "sg:phone": "+1 440 349 5660",
    "sg:postcode": "44139",
    "sg:province": "OH",
    "sg:tags": [
      "machine",
      "mfg",
      "accessory"
    ],
    "wof:name": "Toner Co Inc",
    "wof:placetype": "venue"
  },
  "geometry": {"coordinates":[-81.463062,41.372904],"type":"Point"}
}
