{
  "type": "Feature",
  "properties": {
    "addr:full": "231 W Washington Row Sandusky OH 44870",
    "addr:housenumber": "231",
    "addr:postcode": "44870",
    "addr:street": "W Washington Row",
    "iso:country": "US",
    "sg:address": "231 W Washington Row",
    "sg:city": "Sandusky",
    "sg:classifiers": [
      {
        "category": "Professional",
        "subcategory": "Lawyer \u0026 Legal Services",
        "type": "Services"
      }
    ],
    "sg:phone": "+1 419 609 5000",
    "sg:postcode": "44870",
    "sg:province": "OH",
    "sg:tags": [
      "personal",
      "attorney",
      "injury"
    ],
    "wof:name": "Gross \u0026 Gross",
    "wof:placetype": "venue"
  },
  "geometry": {"coordinates":[-82.712196,41.454899],"type":"Point"}
}
