{
  "type": "Feature",
  "properties": {
    "iso:country":"US",
    "sg:address":"231 W Washington Row",
    "sg:city":"Sandusky",
    "sg:classifiers":[
        {
            "category":"Professional",
            "subcategory":"Lawyer & Legal Services",
            "type":"Services"
        }
    ],
    "sg:phone":"+1 419 609 5000",
    "sg:postcode":"44870",
    "sg:province":"OH",
    "sg:tags":[
        "personal",
        "attorney",
        "injury"
    ],
    "wof:name":"Gross & Gross",
    "wof:placetype":"venue"
},
  "geometry": {"coordinates":[-82.71219600000001,41.454899],"type":"Point"}
}