{
  "type": "Feature",
  "properties": {
    "addr:full": "717 E David Rd Dayton OH 45429",
    "addr:housenumber": "717",
    "addr:postcode": "45429",
    "addr:street": "E David Rd",
    "iso:country": "US",
    "sg:address": "717 E David Rd",
    "sg:city": "Dayton",
    "sg:classifiers": [
      {
        "category": "Communications",
        "subcategory": "Radio Station",
        "type": "Services"
      }
    ],
    "sg:phone": "+1 937 294 5858",
    "sg:postcode": "45429",
    "sg:province": "OH",
    "sg:tags": [
      "company",
      "broadcasting"
    ],
    "sg:website": "www.hot1029.com",
    "wof:name": "WDHT",
    "wof:placetype": "venue"
  },
  "geometry": {"coordinates":[-84.158266,39.680929],"type":"Point"}
}
