{
  "type": "Feature",
  "properties": {
    "addr:full": "950 Miamisburg Centerville Rd Washington Twp OH 45459",
    "addr:housenumber": "950",
    "addr:postcode": "45459",
    "addr:street": "Miamisburg Centerville Rd",
    "iso:country": "US",
    "sg:address": "950 Miamisburg Centerville Rd",
    "sg:city": "Washington Twp",
    "sg:classifiers": [
      {
        "category": "Social Services",
        "type": "Services"
      }
    ],
    "sg:phone": "+1 937 434 5335",
    "sg:postcode": "45459",
    "sg:province": "OH",
    "sg:tags": [
      "organization",
      "welfare"
    ],
    "sg:website": "www.goodwill.org",
    "wof:name": "Goodwill Industries",
    "wof:placetype": "venue"
  },
  "geometry": {"coordinates":[-84.188334,39.627796],"type":"Point"}
}
