{
  "type": "Feature",
  "properties": {
    "iso:country":"US",
    "sg:address":"7205 Chagrin Rd",
    "sg:city":"Chagrin Falls",
    "sg:classifiers":[
        {
            "category":"Shopping",
            "type":"Retail Goods"
        }
    ],
    "sg:phone":"+1 440 247 2073",
    "sg:postcode":"44023",
    "sg:province":"OH",
    "sg:tags":[
        "art",
        "gallery",
        "dealer"
    ],
    "wof:name":"Framart Galleries",
    "wof:placetype":"venue"
},
  "geometry": {"coordinates":[-81.385865,41.422454],"type":"Point"}
}