{
  "type": "Feature",
  "properties": {
    "iso:country":"US",
    "sg:address":"6611 Madison Rd",
    "sg:city":"Cincinnati",
    "sg:classifiers":[
        {
            "category":"Retail",
            "subcategory":"Auto Repair",
            "type":"Services"
        }
    ],
    "sg:phone":"+1 513 271 0040",
    "sg:postcode":"45227",
    "sg:province":"OH",
    "sg:tags":[
        "repairing",
        "automobile"
    ],
    "wof:name":"Cincinnati Motor Car",
    "wof:placetype":"venue"
},
  "geometry": {"coordinates":[-84.382797,39.159813],"type":"Point"}
}