{
  "type": "Feature",
  "properties": {
    "addr:full":"119 New Garden Rd New Paris OH 45347",
    "addr:housenumber":"119",
    "addr:postcode":"45347",
    "addr:street":"New Garden Rd",
    "iso:country":"US",
    "sg:address":"119 New Garden Rd",
    "sg:city":"New Paris",
    "sg:phone":"+1 937 997 3781",
    "sg:postcode":"45347",
    "sg:province":"OH",
    "sg:tags":[
        "farm",
        "corn",
        "soybean"
    ],
    "wof:name":"Marty Munchel",
    "wof:placetype":"venue"
},
  "geometry": {"coordinates":[-84.80776299999999,39.939041],"type":"Point"}
}