{
  "type": "Feature",
  "properties": {
    "iso:country":"US",
    "sg:address":"1971 W 5th Ave",
    "sg:city":"Columbus",
    "sg:classifiers":[
        {
            "category":"Health Services",
            "subcategory":"Health Practitioner",
            "type":"Services"
        }
    ],
    "sg:phone":"+1 614 488 6285",
    "sg:postcode":"43212",
    "sg:province":"OH",
    "sg:tags":[
        "psychologist"
    ],
    "wof:name":"John M Showalter",
    "wof:placetype":"venue"
},
  "geometry": {"coordinates":[-83.05995299999999,39.989362],"type":"Point"}
}