{
  "type": "Feature",
  "properties": {
    "addr:full":"727 Fox Rd Van Wert OH 45891",
    "addr:housenumber":"727",
    "addr:postcode":"45891",
    "addr:street":"Fox Rd",
    "iso:country":"US",
    "sg:address":"727 Fox Rd",
    "sg:city":"Van Wert",
    "sg:classifiers":[
        {
            "category":"Banks & Credit Unions",
            "subcategory":"Bank",
            "type":"Services"
        }
    ],
    "sg:phone":"+1 419 238 5725",
    "sg:postcode":"45891",
    "sg:province":"OH",
    "sg:tags":[
        "financing"
    ],
    "wof:name":"Beneficial Mortgage Co Of Ohio",
    "wof:placetype":"venue"
},
  "geometry": {"coordinates":[-84.596647,40.851684],"type":"Point"}
}