{
  "type": "Feature",
  "properties": {
    "addr:full": "7808 Cooper Rd Cincinnati OH 45242",
    "addr:housenumber": "7808",
    "addr:postcode": "45242",
    "addr:street": "Cooper Rd",
    "iso:country": "US",
    "sg:address": "7808 Cooper Rd",
    "sg:city": "Cincinnati",
    "sg:classifiers": [
      {
        "category": "Personal",
        "subcategory": "Beauty Salon",
        "type": "Services"
      }
    ],
    "sg:phone": "+1 513 791 4141",
    "sg:postcode": "45242",
    "sg:province": "OH",
    "wof:name": "Le Salon",
    "wof:placetype": "venue"
  },
  "geometry": {"coordinates":[-84.355173,39.226651],"type":"Point"}
}
