{
  "type": "Feature",
  "properties": {
    "addr:full": "711 State Rte 503 Arcanum OH 45304",
    "addr:housenumber": "711",
    "addr:postcode": "45304",
    "addr:street": "State Rte 503",
    "iso:country": "US",
    "sg:address": "711 State Rte 503",
    "sg:city": "Arcanum",
    "sg:classifiers": [
      {
        "category": "Real Estate",
        "subcategory": "Developer",
        "type": "Services"
      }
    ],
    "sg:phone": "+1 937 678 6773",
    "sg:postcode": "45304",
    "sg:province": "OH",
    "sg:tags": [
      "cemetery"
    ],
    "wof:name": "Ithaca Cemetery",
    "wof:placetype": "venue"
  },
  "geometry": {"coordinates":[-84.555788,39.940781],"type":"Point"}
}
