{
  "type": "Feature",
  "properties": {
    "addr:full":"8096 Market St Youngstown OH 44512",
    "addr:housenumber":"8096",
    "addr:postcode":"44512",
    "addr:street":"Market St",
    "iso:country":"US",
    "sg:address":"8096 Market St",
    "sg:city":"Youngstown",
    "sg:classifiers":[
        {
            "category":"Professional",
            "subcategory":"Accounting & Tax Preparation",
            "type":"Services"
        }
    ],
    "sg:phone":"+1 330 729 1068",
    "sg:postcode":"44512",
    "sg:province":"OH",
    "sg:tags":[
        "return",
        "filing"
    ],
    "wof:name":"Aaron David Tax Solutions",
    "wof:placetype":"venue"
},
  "geometry": {"coordinates":[-80.662812,41.001202],"type":"Point"}
}