{
  "type": "Feature",
  "properties": {
    "iso:country":"US",
    "sg:address":"146 W 5th St",
    "sg:city":"East Liverpool",
    "sg:classifiers":[
        {
            "category":"Health Services",
            "subcategory":"Doctor",
            "type":"Services"
        }
    ],
    "sg:phone":"+1 330 385 9496",
    "sg:postcode":"43920",
    "sg:province":"OH",
    "sg:tags":[
        "dentist"
    ],
    "wof:name":"Jeffrey S Caldwell DDS",
    "wof:placetype":"venue"
},
  "geometry": {"coordinates":[-80.581042,40.61963],"type":"Point"}
}