{
  "type": "Feature",
  "properties": {
    "iso:country":"US",
    "sg:address":"195 N Grant Ave",
    "sg:city":"Columbus",
    "sg:classifiers":[
        {
            "category":"Social Services",
            "type":"Services"
        }
    ],
    "sg:phone":"+1 614 221 6766",
    "sg:postcode":"43215",
    "sg:province":"OH",
    "sg:tags":[
        "organization",
        "welfare"
    ],
    "sg:website":"www.firstlink.org",
    "wof:name":"Firstlink",
    "wof:placetype":"venue"
},
  "geometry": {"coordinates":[-82.991936,39.967443],"type":"Point"}
}