{
  "type": "Feature",
  "properties": {
    "iso:country":"US",
    "sg:address":"2733 E Tower Dr",
    "sg:city":"Cincinnati",
    "sg:classifiers":[
        {
            "category":"Organizations",
            "subcategory":"Religious Organization",
            "type":"Services"
        }
    ],
    "sg:phone":"+1 513 761 4895",
    "sg:postcode":"45238",
    "sg:province":"OH",
    "sg:tags":[
        "clergy"
    ],
    "wof:name":"Alfred Nickles",
    "wof:placetype":"venue"
},
  "geometry": {"coordinates":[-84.594669,39.132299],"type":"Point"}
}