{
  "type": "Feature",
  "properties": {
    "addr:full": "4487 Stitt Rd Mason OH 45040",
    "addr:housenumber": "4487",
    "addr:postcode": "45040",
    "addr:street": "Stitt Rd",
    "iso:country": "US",
    "sg:address": "4487 Stitt Rd",
    "sg:city": "Mason",
    "sg:classifiers": [
      {
        "category": "Restaurant",
        "type": "Food \u0026 Drink"
      }
    ],
    "sg:phone": "+1 513 459 9966",
    "sg:postcode": "45040",
    "sg:province": "OH",
    "wof:name": "Buffet Pizza",
    "wof:placetype": "venue"
  },
  "geometry": {"coordinates":[-84.291754,39.341927],"type":"Point"}
}
