{
  "type": "Feature",
  "properties": {
    "iso:country":"US",
    "sg:address":"4487 Stitt Rd",
    "sg:city":"Mason",
    "sg:classifiers":[
        {
            "category":"Restaurant",
            "type":"Food & Drink"
        }
    ],
    "sg:phone":"+1 513 459 9966",
    "sg:postcode":"45040",
    "sg:province":"OH",
    "wof:name":"Buffet Pizza",
    "wof:placetype":"venue"
},
  "geometry": {"coordinates":[-84.291754,39.341927],"type":"Point"}
}