{
  "type": "Feature",
  "properties": {
    "addr:full": "333 W Town St Columbus OH 43215",
    "addr:housenumber": "333",
    "addr:postcode": "43215",
    "addr:street": "W Town St",
    "iso:country": "US",
    "sg:address": "333 W Town St",
    "sg:city": "Columbus",
    "sg:classifiers": [
      {
        "category": "Health Services",
        "subcategory": "Nursing And Care Facility",
        "type": "Services"
      }
    ],
    "sg:phone": "+1 614 645 6471",
    "sg:postcode": "43215",
    "sg:province": "OH",
    "sg:tags": [
      "home",
      "skilled",
      "public",
      "he"
    ],
    "wof:name": "Health Dept Columbus",
    "wof:placetype": "venue"
  },
  "geometry": {"coordinates":[-83.009709,39.9577],"type":"Point"}
}
