{
  "type": "Feature",
  "properties": {
    "addr:full":"320 S State St Westerville OH 43081",
    "addr:housenumber":"320",
    "addr:postcode":"43081",
    "addr:street":"S State St",
    "iso:country":"US",
    "sg:address":"320 S State St",
    "sg:city":"Westerville",
    "sg:classifiers":[
        {
            "category":"Shopping",
            "type":"Retail Goods"
        }
    ],
    "sg:phone":"+1 614 891 6560",
    "sg:postcode":"43081",
    "sg:province":"OH",
    "sg:tags":[
        "pet",
        "shop"
    ],
    "wof:name":"Fish Junction",
    "wof:placetype":"venue"
},
  "geometry": {"coordinates":[-82.928725,40.118126],"type":"Point"}
}