{
  "type": "Feature",
  "properties": {
    "addr:full":"1722 Brookwood Dr Akron OH 44313",
    "addr:housenumber":"1722",
    "addr:postcode":"44313",
    "addr:street":"Brookwood Dr",
    "iso:country":"US",
    "sg:address":"1722 Brookwood Dr",
    "sg:city":"Akron",
    "sg:classifiers":[
        {
            "category":"Home & Garden",
            "subcategory":"Furniture",
            "type":"Retail Goods"
        }
    ],
    "sg:phone":"+1 330 864 0984",
    "sg:postcode":"44313",
    "sg:province":"OH",
    "wof:name":"Business Furniture",
    "wof:placetype":"venue"
},
  "geometry": {"coordinates":[-81.575996,41.142831],"type":"Point"}
}