{
  "type": "Feature",
  "properties": {
    "addr:full": "610 S Main St Ada OH 45810",
    "addr:housenumber": "610",
    "addr:postcode": "45810",
    "addr:street": "S Main St",
    "iso:country": "US",
    "sg:address": "610 S Main St",
    "sg:city": "Ada",
    "sg:classifiers": [
      {
        "category": "Restaurant",
        "type": "Food \u0026 Drink"
      }
    ],
    "sg:phone": "+1 419 634 9188",
    "sg:postcode": "45810",
    "sg:province": "OH",
    "sg:tags": [
      "eating"
    ],
    "wof:name": "Hardees",
    "wof:placetype": "venue"
  },
  "geometry": {"coordinates":[-83.823127,40.765186],"type":"Point"}
}
