{
  "type": "Feature",
  "properties": {
    "iso:country":"US",
    "sg:address":"610 S Main St",
    "sg:city":"Ada",
    "sg:classifiers":[
        {
            "category":"Restaurant",
            "type":"Food & Drink"
        }
    ],
    "sg:phone":"+1 419 634 9188",
    "sg:postcode":"45810",
    "sg:province":"OH",
    "sg:tags":[
        "eating"
    ],
    "wof:name":"Hardees",
    "wof:placetype":"venue"
},
  "geometry": {"coordinates":[-83.823127,40.765186],"type":"Point"}
}