{
  "type": "Feature",
  "properties": {
    "iso:country":"US",
    "sg:address":"628 Smith St",
    "sg:city":"Ansonia",
    "sg:classifiers":[
        {
            "category":"Restaurant",
            "type":"Food & Drink"
        },
        {
            "category":"Professional",
            "subcategory":"Management & Consulting",
            "type":"Services"
        }
    ],
    "sg:phone":"+1 937 337 3084",
    "sg:postcode":"45303",
    "sg:province":"OH",
    "sg:tags":[
        "direct",
        "ice",
        "sales",
        "parlor",
        "retail",
        "cream"
    ],
    "wof:name":"James H Riffle Distributor",
    "wof:placetype":"venue"
},
  "geometry": {"coordinates":[-84.63572600000001,40.208957],"type":"Point"}
}