{
  "type": "Feature",
  "properties": {
    "addr:full": "1485 Cuba Rd Wilmington OH 45177",
    "addr:housenumber": "1485",
    "addr:postcode": "45177",
    "addr:street": "Cuba Rd",
    "iso:country": "US",
    "sg:address": "1485 Cuba Rd",
    "sg:city": "Wilmington",
    "sg:classifiers": [
      {
        "category": "Building \u0026 Trades",
        "subcategory": "Construction",
        "type": "Services"
      }
    ],
    "sg:phone": "+1 937 382 6158",
    "sg:postcode": "45177",
    "sg:province": "OH",
    "sg:tags": [
      "house"
    ],
    "wof:name": "Spencer Builders",
    "wof:placetype": "venue"
  },
  "geometry": {"coordinates":[-83.838785,39.411498],"type":"Point"}
}
