{
  "type": "Feature",
  "properties": {
    "addr:full":"4812 Overlook Dr Geneva OH 44041",
    "addr:housenumber":"4812",
    "addr:postcode":"44041",
    "addr:street":"Overlook Dr",
    "iso:country":"US",
    "sg:address":"4812 Overlook Dr",
    "sg:city":"Geneva",
    "sg:classifiers":[
        {
            "category":"Professional",
            "type":"Services"
        }
    ],
    "sg:phone":"+1 440 466 0765",
    "sg:postcode":"44041",
    "sg:province":"OH",
    "wof:name":"S Hagler",
    "wof:placetype":"venue"
},
  "geometry": {"coordinates":[-80.926761,41.861581],"type":"Point"}
}