{
  "type": "Feature",
  "properties": {
    "addr:full":"130 New Towne Square Dr Toledo OH 43612",
    "addr:housenumber":"130",
    "addr:postcode":"43612",
    "addr:street":"New Towne Square Dr",
    "iso:country":"US",
    "sg:address":"130 New Towne Square Dr",
    "sg:city":"Toledo",
    "sg:classifiers":[
        {
            "category":"Food & Beverages",
            "subcategory":"Groceries & Convenience Stores",
            "type":"Retail Goods"
        }
    ],
    "sg:phone":"+1 419 000 1111",
    "sg:postcode":"43612",
    "sg:province":"OH",
    "sg:tags":[
        "grocer"
    ],
    "wof:name":"Aldi",
    "wof:placetype":"venue"
},
  "geometry": {"coordinates":[-83.542224,41.723226],"type":"Point"}
}