{
  "type": "Feature",
  "properties": {
    "addr:full":"3807 E 93rd St Cleveland OH 44105",
    "addr:housenumber":"3807",
    "addr:postcode":"44105",
    "addr:street":"E 93Rd St",
    "iso:country":"US",
    "sg:address":"3807 E 93rd St",
    "sg:city":"Cleveland",
    "sg:classifiers":[
        {
            "category":"Retail",
            "subcategory":"Auto Rental",
            "type":"Services"
        }
    ],
    "sg:phone":"+1 216 271 9639",
    "sg:postcode":"44105",
    "sg:province":"OH",
    "sg:tags":[
        "renting",
        "truck",
        "leasing"
    ],
    "wof:name":"U-Haul Co",
    "wof:placetype":"venue"
},
  "geometry": {"coordinates":[-81.621381,41.455782],"type":"Point"}
}