{
  "type": "Feature",
  "properties": {
    "addr:full":"2514 Cleveland Rd E Huron OH 44839",
    "addr:housenumber":"2514",
    "addr:postcode":"44839",
    "addr:street":"Cleveland Rd E",
    "iso:country":"US",
    "sg:address":"2514 Cleveland Rd E",
    "sg:city":"Huron",
    "sg:classifiers":[
        {
            "category":"Travel",
            "subcategory":"Campground",
            "type":"Entertainment"
        }
    ],
    "sg:phone":"+1 614 265 6377",
    "sg:postcode":"44839",
    "sg:province":"OH",
    "sg:tags":[
        "trailer"
    ],
    "wof:name":"State of Ohio Agency",
    "wof:placetype":"venue"
},
  "geometry": {"coordinates":[-82.514762,41.382716],"type":"Point"}
}