{
  "type": "Feature",
  "properties": {
    "addr:full":"549 S Chillicothe Rd Aurora OH 44202",
    "addr:housenumber":"549",
    "addr:postcode":"44202",
    "addr:street":"S Chillicothe Rd",
    "iso:country":"US",
    "sg:address":"549 S Chillicothe Rd",
    "sg:city":"Aurora",
    "sg:classifiers":[
        {
            "category":"Shopping",
            "subcategory":"Department Store",
            "type":"Retail Goods"
        }
    ],
    "sg:phone":"+1 330 562 1730",
    "sg:postcode":"44202",
    "sg:province":"OH",
    "sg:website":"www.eddiebauer.com",
    "wof:name":"Eddie Bauer",
    "wof:placetype":"venue"
},
  "geometry": {"coordinates":[-81.345608,41.300461],"type":"Point"}
}