{
  "type": "Feature",
  "properties": {
    "iso:country":"US",
    "sg:address":"3737 Upper Bellbrook Rd",
    "sg:city":"Bellbrook",
    "sg:classifiers":[
        {
            "category":"Education",
            "subcategory":"School",
            "type":"Public Place"
        }
    ],
    "sg:phone":"+1 937 848 3737",
    "sg:postcode":"45305",
    "sg:province":"OH",
    "wof:name":"Sugar Creek High School",
    "wof:placetype":"venue"
},
  "geometry": {"coordinates":[-84.069519,39.651516],"type":"Point"}
}