{
  "type": "Feature",
  "properties": {
    "addr:full": "240 S Liberty St Powell OH 43065",
    "addr:housenumber": "240",
    "addr:postcode": "43065",
    "addr:street": "S Liberty St",
    "iso:country": "US",
    "sg:address": "240 S Liberty St",
    "sg:city": "Powell",
    "sg:classifiers": [
      {
        "category": "Military Area",
        "type": "Public Place"
      },
      {
        "category": "Government",
        "subcategory": "Office",
        "type": "Public Place"
      }
    ],
    "sg:phone": "+1 614 336 6000",
    "sg:postcode": "43065",
    "sg:province": "OH",
    "sg:tags": [
      "government-state",
      "force",
      "armed",
      "recruiting"
    ],
    "sg:website": "http://www.arng.army.mil",
    "wof:name": "National Guard, Ohio",
    "wof:placetype": "venue"
  },
  "geometry": {"coordinates":[-83.073826,40.149405],"type":"Point"}
}
