{
  "type": "Feature",
  "properties": {
    "iso:country":"US",
    "sg:address":"3966 Hummel Rd",
    "sg:city":"Shelby",
    "sg:classifiers":[
        {
            "category":"Manufacturing",
            "subcategory":"Lumber",
            "type":"Manufacturing & Wholesale Goods"
        }
    ],
    "sg:phone":"+1 419 342 5851",
    "sg:postcode":"44875",
    "sg:province":"OH",
    "sg:tags":[
        "mill"
    ],
    "wof:name":"Swisher Wood Products",
    "wof:placetype":"venue"
},
  "geometry": {"coordinates":[-82.677075,40.862787],"type":"Point"}
}