{
  "type": "Feature",
  "properties": {
    "addr:full": "3966 Hummel Rd Shelby OH 44875",
    "addr:housenumber": "3966",
    "addr:postcode": "44875",
    "addr:street": "Hummel Rd",
    "iso:country": "US",
    "sg:address": "3966 Hummel Rd",
    "sg:city": "Shelby",
    "sg:classifiers": [
      {
        "category": "Manufacturing",
        "subcategory": "Lumber",
        "type": "Manufacturing \u0026 Wholesale Goods"
      }
    ],
    "sg:phone": "+1 419 342 5851",
    "sg:postcode": "44875",
    "sg:province": "OH",
    "sg:tags": [
      "mill"
    ],
    "wof:name": "Swisher Wood Products",
    "wof:placetype": "venue"
  },
  "geometry": {"coordinates":[-82.677075,40.862787],"type":"Point"}
}
