{
  "type": "Feature",
  "properties": {
    "addr:full": "5561 Ottawa River Rd Toledo OH 43611",
    "addr:housenumber": "5561",
    "addr:postcode": "43611",
    "addr:street": "Ottawa River Rd",
    "iso:country": "US",
    "sg:address": "5561 Ottawa River Rd",
    "sg:city": "Toledo",
    "sg:classifiers": [
      {
        "category": "Building \u0026 Trades",
        "subcategory": "Construction",
        "type": "Services"
      }
    ],
    "sg:phone": "+1 419 466 5279",
    "sg:postcode": "43611",
    "sg:province": "OH",
    "sg:tags": [
      "general",
      "contractor"
    ],
    "wof:name": "Gary Hahn Builders",
    "wof:placetype": "venue"
  },
  "geometry": {"coordinates":[-83.480851,41.721008],"type":"Point"}
}
