{
  "type": "Feature",
  "properties": {
    "addr:full":"3567 Blue Rock Rd Cincinnati OH 45247",
    "addr:housenumber":"3567",
    "addr:postcode":"45247",
    "addr:street":"Blue Rock Rd",
    "iso:country":"US",
    "sg:address":"3567 Blue Rock Rd",
    "sg:city":"Cincinnati",
    "sg:classifiers":[
        {
            "category":"Professional",
            "subcategory":"Testing Lab",
            "type":"Services"
        },
        {
            "category":"Professional",
            "subcategory":"Research",
            "type":"Services"
        }
    ],
    "sg:phone":"+1 513 385 0500",
    "sg:postcode":"45247",
    "sg:province":"OH",
    "sg:tags":[
        "laboratory",
        "bio",
        "facility"
    ],
    "wof:name":"National Research Labs LLC",
    "wof:placetype":"venue"
},
  "geometry": {"coordinates":[-84.599698,39.212472],"type":"Point"}
}