{
  "type": "Feature",
  "properties": {
    "addr:full": "23486 Buckland Holden Rd Waynesfield OH 45896",
    "addr:housenumber": "23486",
    "addr:postcode": "45896",
    "addr:street": "Buckland Holden Rd",
    "iso:country": "US",
    "sg:address": "23486 Buckland Holden Rd",
    "sg:city": "Waynesfield",
    "sg:phone": "+1 419 568 1752",
    "sg:postcode": "45896",
    "sg:province": "OH",
    "sg:tags": [
      "farm",
      "corn",
      "soybean"
    ],
    "wof:name": "Waitman Farms",
    "wof:placetype": "venue"
  },
  "geometry": {"coordinates":[-84.003857,40.629556],"type":"Point"}
}
