{
  "type": "Feature",
  "properties": {
    "addr:full": "2505 Antioch Rd Perry OH 44081",
    "addr:housenumber": "2505",
    "addr:postcode": "44081",
    "addr:street": "Antioch Rd",
    "iso:country": "US",
    "sg:address": "2505 Antioch Rd",
    "sg:city": "Perry",
    "sg:classifiers": [
      {
        "category": "Professional",
        "subcategory": "Management \u0026 Consulting",
        "type": "Services"
      }
    ],
    "sg:phone": "+1 440 259 4812",
    "sg:postcode": "44081",
    "sg:province": "OH",
    "sg:tags": [
      "consultant",
      "security",
      "system"
    ],
    "sg:website": "www.checkpointsystems.com",
    "wof:name": "Checkpoint Systems Inc",
    "wof:placetype": "venue"
  },
  "geometry": {"coordinates":[-81.121357,41.810954],"type":"Point"}
}
