{
  "type": "Feature",
  "properties": {
    "addr:full":"542 S Highland Ave Columbus OH 43223",
    "addr:housenumber":"542",
    "addr:postcode":"43223",
    "addr:street":"S Highland Ave",
    "iso:country":"US",
    "sg:address":"542 S Highland Ave",
    "sg:city":"Columbus",
    "sg:classifiers":[
        {
            "category":"Insurance",
            "subcategory":"Insurance Agent",
            "type":"Services"
        }
    ],
    "sg:phone":"+1 614 279 7783",
    "sg:postcode":"43223",
    "sg:province":"OH",
    "wof:name":"Millers Fincl Consulting Svcs",
    "wof:placetype":"venue"
},
  "geometry": {"coordinates":[-83.059628,39.944633],"type":"Point"}
}