{
  "type": "Feature",
  "properties": {
    "addr:full": "58 Center Rd Akron OH 44319",
    "addr:housenumber": "58",
    "addr:postcode": "44319",
    "addr:street": "Center Rd",
    "iso:country": "US",
    "sg:address": "58 Center Rd",
    "sg:city": "Akron",
    "sg:classifiers": [
      {
        "category": "Building \u0026 Trades",
        "subcategory": "Plumbing",
        "type": "Services"
      }
    ],
    "sg:phone": "+1 330 714 6685",
    "sg:postcode": "44319",
    "sg:province": "OH",
    "sg:tags": [
      "contractor"
    ],
    "wof:name": "Engineered Heating \u0026 Cooling",
    "wof:placetype": "venue"
  },
  "geometry": {"coordinates":[-81.534748,40.948661],"type":"Point"}
}
