{
  "type": "Feature",
  "properties": {
    "iso:country":"US",
    "sg:address":"58 Center Rd",
    "sg:city":"Akron",
    "sg:classifiers":[
        {
            "category":"Building & Trades",
            "subcategory":"Plumbing",
            "type":"Services"
        }
    ],
    "sg:phone":"+1 330 714 6685",
    "sg:postcode":"44319",
    "sg:province":"OH",
    "sg:tags":[
        "contractor"
    ],
    "wof:name":"Engineered Heating & Cooling",
    "wof:placetype":"venue"
},
  "geometry": {"coordinates":[-81.53474799999999,40.948661],"type":"Point"}
}