{
  "type": "Feature",
  "properties": {
    "addr:full": "16675 Chagrin Blvd Cleveland OH 44120",
    "addr:housenumber": "16675",
    "addr:postcode": "44120",
    "addr:street": "Chagrin Blvd",
    "iso:country": "US",
    "sg:address": "16675 Chagrin Blvd",
    "sg:city": "Cleveland",
    "sg:classifiers": [
      {
        "category": "Shopping",
        "subcategory": "Shoes",
        "type": "Retail Goods"
      }
    ],
    "sg:phone": "+1 216 561 0849",
    "sg:postcode": "44120",
    "sg:province": "OH",
    "wof:name": "Payless Shoe Source",
    "wof:placetype": "venue"
  },
  "geometry": {"coordinates":[-81.559798,41.464574],"type":"Point"}
}
