{
  "type": "Feature",
  "properties": {
    "iso:country":"US",
    "sg:address":"16675 Chagrin Blvd",
    "sg:city":"Cleveland",
    "sg:classifiers":[
        {
            "category":"Shopping",
            "subcategory":"Shoes",
            "type":"Retail Goods"
        }
    ],
    "sg:phone":"+1 216 561 0849",
    "sg:postcode":"44120",
    "sg:province":"OH",
    "wof:name":"Payless Shoe Source",
    "wof:placetype":"venue"
},
  "geometry": {"coordinates":[-81.559798,41.464574],"type":"Point"}
}