{
  "type": "Feature",
  "properties": {
    "iso:country":"US",
    "sg:address":"8701 Troy Pike",
    "sg:city":"Dayton",
    "sg:classifiers":[
        {
            "category":"Health Services",
            "subcategory":"Doctor",
            "type":"Services"
        }
    ],
    "sg:phone":"+1 937 233 7146",
    "sg:postcode":"45424",
    "sg:province":"OH",
    "sg:tags":[
        "physician",
        "surgeon"
    ],
    "wof:name":"Northeast Family Practice",
    "wof:placetype":"venue"
},
  "geometry": {"coordinates":[-84.136624,39.880292],"type":"Point"}
}