{
  "type": "Feature",
  "properties": {
    "addr:full": "2285 Fenner Rd Troy OH 45373",
    "addr:housenumber": "2285",
    "addr:postcode": "45373",
    "addr:street": "Fenner Rd",
    "iso:country": "US",
    "sg:address": "2285 Fenner Rd",
    "sg:city": "Troy",
    "sg:classifiers": [
      {
        "category": "Building \u0026 Trades",
        "subcategory": "Cleaning \u0026 Sanitation",
        "type": "Services"
      }
    ],
    "sg:phone": "+1 937 335 8800",
    "sg:postcode": "45373",
    "sg:province": "OH",
    "sg:tags": [
      "maintenance"
    ],
    "wof:name": "Dust Catchers Inc",
    "wof:placetype": "venue"
  },
  "geometry": {"coordinates":[-84.243828,40.024436],"type":"Point"}
}
