{
  "type": "Feature",
  "properties": {
    "addr:full": "125 Murwood Dr Chagrin Falls OH 44022",
    "addr:housenumber": "125",
    "addr:postcode": "44022",
    "addr:street": "Murwood Dr",
    "iso:country": "US",
    "sg:address": "125 Murwood Dr",
    "sg:city": "Chagrin Falls",
    "sg:classifiers": [
      {
        "category": "Professional",
        "subcategory": "Business Services",
        "type": "Services"
      }
    ],
    "sg:phone": "+1 440 247 3200",
    "sg:postcode": "44022",
    "sg:province": "OH",
    "sg:tags": [
      "drafting"
    ],
    "wof:name": "Universal Design Svc",
    "wof:placetype": "venue"
  },
  "geometry": {"coordinates":[-81.429173,41.451467],"type":"Point"}
}
