{
  "type": "Feature",
  "properties": {
    "iso:country":"US",
    "sg:address":"198 S Walnut St",
    "sg:city":"Wilmington",
    "sg:classifiers":[
        {
            "category":"Organizations",
            "subcategory":"Religious Organization",
            "type":"Services"
        }
    ],
    "sg:phone":"+1 937 383 4288",
    "sg:postcode":"45177",
    "sg:province":"OH",
    "sg:tags":[
        "church"
    ],
    "wof:name":"First Evangelist Missionary",
    "wof:placetype":"venue"
},
  "geometry": {"coordinates":[-83.827236,39.442534],"type":"Point"}
}