{
  "type": "Feature",
  "properties": {
    "addr:full": "250 Jefferson Ave Cleveland OH 44113",
    "addr:housenumber": "250",
    "addr:postcode": "44113",
    "addr:street": "Jefferson Ave",
    "iso:country": "US",
    "sg:address": "250 Jefferson Ave",
    "sg:city": "Cleveland",
    "sg:classifiers": [
      {
        "category": "Manufacturing",
        "subcategory": "Glass \u0026 Minerals",
        "type": "Manufacturing \u0026 Wholesale Goods"
      }
    ],
    "sg:phone": "+1 216 579 1911",
    "sg:postcode": "44113",
    "sg:province": "OH",
    "sg:tags": [
      "cement"
    ],
    "wof:name": "St Marys Cement Co",
    "wof:placetype": "venue"
  },
  "geometry": {"coordinates":[-81.679666,41.482333],"type":"Point"}
}
