{
  "type": "Feature",
  "properties": {
    "addr:full":"301 State Rte 613 Continental OH 45831",
    "addr:housenumber":"301",
    "addr:postcode":"45831",
    "addr:street":"State Rte 613",
    "iso:country":"US",
    "sg:address":"301 State Rte 613",
    "sg:city":"Continental",
    "sg:classifiers":[
        {
            "category":"Utilities",
            "subcategory":"Refuse",
            "type":"Services"
        }
    ],
    "sg:phone":"+1 419 596 3805",
    "sg:postcode":"45831",
    "sg:province":"OH",
    "sg:tags":[
        "garbage",
        "collection"
    ],
    "wof:name":"S & S Sanitation",
    "wof:placetype":"venue"
},
  "geometry": {"coordinates":[-84.26214299999999,41.092969],"type":"Point"}
}