{
  "type": "Feature",
  "properties": {
    "addr:full":"200 Clay St Bradford OH 45308",
    "addr:housenumber":"200",
    "addr:postcode":"45308",
    "addr:street":"Clay St",
    "iso:country":"US",
    "sg:address":"200 Clay St",
    "sg:city":"Bradford",
    "sg:classifiers":[
        {
            "category":"Organizations",
            "subcategory":"Religious Organization",
            "type":"Services"
        }
    ],
    "sg:phone":"+1 937 448 6400",
    "sg:postcode":"45308",
    "sg:province":"OH",
    "sg:tags":[
        "church"
    ],
    "wof:name":"Immaculate Conception Church",
    "wof:placetype":"venue"
},
  "geometry": {"coordinates":[-84.429356,40.133027],"type":"Point"}
}