{
  "type": "Feature",
  "properties": {
    "addr:full": "7211 Broadway Ave Cleveland OH 44105",
    "addr:housenumber": "7211",
    "addr:postcode": "44105",
    "addr:street": "Broadway Ave",
    "iso:country": "US",
    "sg:address": "7211 Broadway Ave",
    "sg:city": "Cleveland",
    "sg:classifiers": [
      {
        "category": "Shopping",
        "subcategory": "Optical Goods",
        "type": "Retail Goods"
      },
      {
        "category": "Health Services",
        "subcategory": "Optometrist",
        "type": "Services"
      }
    ],
    "sg:phone": "+1 216 641 0055",
    "sg:postcode": "44105",
    "sg:province": "OH",
    "wof:name": "Broadway Optical Svc",
    "wof:placetype": "venue"
  },
  "geometry": {"coordinates":[-81.637761,41.457609],"type":"Point"}
}
