{
  "type": "Feature",
  "properties": {
    "addr:full": "53 W Central Ave Camden IN 45311",
    "addr:housenumber": "53",
    "addr:postcode": "45311",
    "addr:street": "W Central Ave",
    "iso:country": "US",
    "sg:address": "53 W Central Ave",
    "sg:city": "Camden",
    "sg:classifiers": [
      {
        "category": "Restaurant",
        "type": "Food \u0026 Drink"
      }
    ],
    "sg:phone": "+1 937 452 3201",
    "sg:postcode": "45311",
    "sg:province": "IN",
    "sg:tags": [
      "pizza"
    ],
    "wof:name": "Ron's Pizza",
    "wof:placetype": "venue"
  },
  "geometry": {"coordinates":[-84.649114,39.629166],"type":"Point"}
}
