{
  "type": "Feature",
  "properties": {
    "addr:full":"6001 Lower Valley Pike Springfield OH 45502",
    "addr:housenumber":"6001",
    "addr:postcode":"45502",
    "addr:street":"Lower Valley Pike",
    "iso:country":"US",
    "sg:address":"6001 Lower Valley Pike",
    "sg:city":"Springfield",
    "sg:classifiers":[
        {
            "category":"Organizations",
            "subcategory":"Community Association",
            "type":"Services"
        }
    ],
    "sg:phone":"+1 937 882 6412",
    "sg:postcode":"45502",
    "sg:province":"OH",
    "sg:tags":[
        "club"
    ],
    "wof:name":"Amvets",
    "wof:placetype":"venue"
},
  "geometry": {"coordinates":[-83.91293400000001,39.906566],"type":"Point"}
}