{
  "type": "Feature",
  "properties": {
    "iso:country":"US",
    "sg:address":"4626 Mahoning Ave",
    "sg:city":"Youngstown",
    "sg:classifiers":[
        {
            "category":"Restaurant",
            "type":"Food & Drink"
        }
    ],
    "sg:phone":"+1 330 799 6500",
    "sg:postcode":"44515",
    "sg:province":"OH",
    "sg:tags":[
        "mexican"
    ],
    "wof:name":"Don Victor's",
    "wof:placetype":"venue"
},
  "geometry": {"coordinates":[-80.73877299999999,41.101215],"type":"Point"}
}