{
  "type": "Feature",
  "properties": {
    "addr:full":"3601 Greenview Dr Middletown OH 45044",
    "addr:housenumber":"3601",
    "addr:postcode":"45044",
    "addr:street":"Greenview Dr",
    "iso:country":"US",
    "sg:address":"3601 Greenview Dr",
    "sg:city":"Middletown",
    "sg:classifiers":[
        {
            "category":"Building & Trades",
            "subcategory":"Plumbing",
            "type":"Services"
        }
    ],
    "sg:phone":"+1 513 423 5599",
    "sg:postcode":"45044",
    "sg:province":"OH",
    "sg:tags":[
        "plumbing",
        "contractor"
    ],
    "wof:name":"Bruce Plumbing Sewer & Drain",
    "wof:placetype":"venue"
},
  "geometry": {"coordinates":[-84.365494,39.498277],"type":"Point"}
}