{
  "type": "Feature",
  "properties": {
    "addr:full":"5555 Angola Rd Toledo OH 43615",
    "addr:housenumber":"5555",
    "addr:postcode":"43615",
    "addr:street":"Angola Rd",
    "iso:country":"US",
    "sg:address":"5555 Angola Rd",
    "sg:city":"Toledo",
    "sg:classifiers":[
        {
            "category":"Wholesale",
            "subcategory":"Dairy",
            "type":"Manufacturing & Wholesale Goods"
        }
    ],
    "sg:phone":"+1 419 865 7655",
    "sg:postcode":"43615",
    "sg:province":"OH",
    "sg:tags":[
        "leasing",
        "driver",
        "ice",
        "without",
        "truck",
        "cream"
    ],
    "wof:name":"Mister Frosty Inc",
    "wof:placetype":"venue"
},
  "geometry": {"coordinates":[-83.67428099999999,41.623891],"type":"Point"}
}