{
  "type": "Feature",
  "properties": {
    "addr:full": "8460 Kenwood Rd Cincinnati OH 45236",
    "addr:housenumber": "8460",
    "addr:postcode": "45236",
    "addr:street": "Kenwood Rd",
    "iso:country": "US",
    "sg:address": "8460 Kenwood Rd",
    "sg:city": "Cincinnati",
    "sg:classifiers": [
      {
        "category": "Manufacturing",
        "subcategory": "Retail Goods",
        "type": "Manufacturing \u0026 Wholesale Goods"
      }
    ],
    "sg:phone": "+1 513 554 1444",
    "sg:postcode": "45236",
    "sg:province": "OH",
    "sg:tags": [
      "manufacturer"
    ],
    "wof:name": "Westlock Controls",
    "wof:placetype": "venue"
  },
  "geometry": {"coordinates":[-84.379003,39.211877],"type":"Point"}
}
