{
  "type": "Feature",
  "properties": {
    "addr:full": "1 E Campus View Blvd Columbus OH 43235",
    "addr:housenumber": "1",
    "addr:postcode": "43235",
    "addr:street": "View Blvd",
    "iso:country": "US",
    "sg:address": "1 E Campus View Blvd",
    "sg:city": "Columbus",
    "sg:classifiers": [
      {
        "category": "Insurance",
        "subcategory": "Insurance Agent",
        "type": "Services"
      }
    ],
    "sg:phone": "+1 614 885 7323",
    "sg:postcode": "43235",
    "sg:province": "OH",
    "wof:name": "SLF Insurance Agency Inc",
    "wof:placetype": "venue"
  },
  "geometry": {"coordinates":[-83.013534,40.118275],"type":"Point"}
}
