{
  "type": "Feature",
  "properties": {
    "iso:country":"US",
    "sg:address":"304 Cherry St",
    "sg:city":"Findlay",
    "sg:classifiers":[
        {
            "category":"Building & Trades",
            "subcategory":"Plumbing",
            "type":"Services"
        }
    ],
    "sg:phone":"+1 419 422 3801",
    "sg:postcode":"45840",
    "sg:province":"OH",
    "sg:tags":[
        "plumbing",
        "contractor"
    ],
    "wof:name":"Putman Sewer Svc",
    "wof:placetype":"venue"
},
  "geometry": {"coordinates":[-83.64652,41.045508],"type":"Point"}
}