{
  "type": "Feature",
  "properties": {
    "iso:country":"US",
    "sg:address":"13068 Springfield Rd",
    "sg:city":"New Springfield",
    "sg:classifiers":[
        {
            "category":"Building & Trades",
            "subcategory":"Construction",
            "type":"Services"
        }
    ],
    "sg:phone":"+1 330 549 5146",
    "sg:postcode":"44443",
    "sg:province":"OH",
    "sg:tags":[
        "contractor"
    ],
    "wof:name":"Moschella Bros Roofing Inc",
    "wof:placetype":"venue"
},
  "geometry": {"coordinates":[-80.614771,40.925935],"type":"Point"}
}