{
  "type": "Feature",
  "properties": {
    "addr:full": "13068 Springfield Rd New Springfield OH 44443",
    "addr:housenumber": "13068",
    "addr:postcode": "44443",
    "addr:street": "Springfield Rd",
    "iso:country": "US",
    "sg:address": "13068 Springfield Rd",
    "sg:city": "New Springfield",
    "sg:classifiers": [
      {
        "category": "Building \u0026 Trades",
        "subcategory": "Construction",
        "type": "Services"
      }
    ],
    "sg:phone": "+1 330 549 5146",
    "sg:postcode": "44443",
    "sg:province": "OH",
    "sg:tags": [
      "contractor"
    ],
    "wof:name": "Moschella Bros Roofing Inc",
    "wof:placetype": "venue"
  },
  "geometry": {"coordinates":[-80.614771,40.925935],"type":"Point"}
}
