{
  "type": "Feature",
  "properties": {
    "addr:full":"4223 Monroe St Toledo OH 43606",
    "addr:housenumber":"4223",
    "addr:postcode":"43606",
    "addr:street":"Monroe St",
    "iso:country":"US",
    "sg:address":"4223 Monroe St",
    "sg:city":"Toledo",
    "sg:classifiers":[
        {
            "category":"Education",
            "subcategory":"Dance Studio",
            "type":"Public Place"
        }
    ],
    "sg:phone":"+1 419 471 0171",
    "sg:postcode":"43606",
    "sg:province":"OH",
    "sg:tags":[
        "instruction",
        "dancing"
    ],
    "wof:name":"D & D Dance Studio",
    "wof:placetype":"venue"
},
  "geometry": {"coordinates":[-83.606826,41.681837],"type":"Point"}
}