{
  "type": "Feature",
  "properties": {
    "iso:country":"US",
    "sg:address":"8451 Scenicridge Ave NW",
    "sg:city":"Clinton",
    "sg:classifiers":[
        {
            "category":"Professional",
            "subcategory":"Engineering",
            "type":"Services"
        }
    ],
    "sg:phone":"+1 330 854 4808",
    "sg:postcode":"44216",
    "sg:province":"OH",
    "sg:tags":[
        "engineer"
    ],
    "wof:name":"American Engineering Inc",
    "wof:placetype":"venue"
},
  "geometry": {"coordinates":[-81.52325999999999,40.905927],"type":"Point"}
}