{
  "type": "Feature",
  "properties": {
    "addr:full":"323 E Woodrow Ave Columbus OH 43207",
    "addr:housenumber":"323",
    "addr:postcode":"43207",
    "addr:street":"E Woodrow Ave",
    "iso:country":"US",
    "sg:address":"323 E Woodrow Ave",
    "sg:city":"Columbus",
    "sg:classifiers":[
        {
            "category":"Recreation",
            "type":"Entertainment"
        }
    ],
    "sg:phone":"+1 614 449 9321",
    "sg:postcode":"43207",
    "sg:province":"OH",
    "sg:tags":[
        "club",
        "membership"
    ],
    "wof:name":"Cols Assoc Deaf Inc",
    "wof:placetype":"venue"
},
  "geometry": {"coordinates":[-82.986695,39.927219],"type":"Point"}
}