{
  "type": "Feature",
  "properties": {
    "iso:country":"US",
    "sg:address":"7262 Brundage Rd",
    "sg:city":"Waldo",
    "sg:classifiers":[
        {
            "category":"Building & Trades",
            "subcategory":"Construction",
            "type":"Services"
        }
    ],
    "sg:phone":"+1 740 726 2151",
    "sg:postcode":"43356",
    "sg:province":"OH",
    "sg:tags":[
        "general",
        "contractor"
    ],
    "wof:name":"Logan Construction Co",
    "wof:placetype":"venue"
},
  "geometry": {"coordinates":[-83.074134,40.444176],"type":"Point"}
}