{
  "type": "Feature",
  "properties": {
    "addr:full": "5810 Co Rd 29 Mount Gilead OH 43338",
    "addr:housenumber": "5810;29",
    "addr:postcode": "43338",
    "addr:street": "Co Rd;Mount",
    "iso:country": "US",
    "sg:address": "5810 Co Rd 29",
    "sg:city": "Mount Gilead",
    "sg:classifiers": [
      {
        "category": "Government",
        "subcategory": "Office",
        "type": "Public Place"
      }
    ],
    "sg:phone": "+1 419 362 2281",
    "sg:postcode": "43338",
    "sg:province": "OH",
    "sg:tags": [
      "management"
    ],
    "wof:name": "Steinhlfers Aration Wastewater",
    "wof:placetype": "venue"
  },
  "geometry": {"coordinates":[-82.737248,40.638809],"type":"Point"}
}
