{
  "type": "Feature",
  "properties": {
    "addr:full":"6931 Ryan Rd Medina OH 44256",
    "addr:housenumber":"6931",
    "addr:postcode":"44256",
    "addr:street":"Ryan Rd",
    "iso:country":"US",
    "sg:address":"6931 Ryan Rd",
    "sg:city":"Medina",
    "sg:classifiers":[
        {
            "category":"Professional",
            "type":"Services"
        }
    ],
    "sg:phone":"+1 330 722 1650",
    "sg:postcode":"44256",
    "sg:province":"OH",
    "wof:name":"Wingfield Co",
    "wof:placetype":"venue"
},
  "geometry": {"coordinates":[-81.884041,41.085333],"type":"Point"}
}