{
  "type": "Feature",
  "properties": {
    "iso:country":"US",
    "sg:address":"33 Baker Blvd",
    "sg:city":"Fairlawn",
    "sg:classifiers":[
        {
            "category":"Banks & Credit Unions",
            "subcategory":"Investment Brokerage",
            "type":"Services"
        }
    ],
    "sg:phone":"+1 330 864 4549",
    "sg:postcode":"44333",
    "sg:province":"OH",
    "sg:tags":[
        "stock",
        "bond"
    ],
    "wof:name":"Raymond James Financial Svc",
    "wof:placetype":"venue"
},
  "geometry": {"coordinates":[-81.61109999999999,41.130576],"type":"Point"}
}