{
  "type": "Feature",
  "properties": {
    "addr:full": "33 Baker Blvd Fairlawn OH 44333",
    "addr:housenumber": "33",
    "addr:postcode": "44333",
    "addr:street": "Baker Blvd",
    "iso:country": "US",
    "sg:address": "33 Baker Blvd",
    "sg:city": "Fairlawn",
    "sg:classifiers": [
      {
        "category": "Banks \u0026 Credit Unions",
        "subcategory": "Investment Brokerage",
        "type": "Services"
      }
    ],
    "sg:phone": "+1 330 864 4549",
    "sg:postcode": "44333",
    "sg:province": "OH",
    "sg:tags": [
      "stock",
      "bond"
    ],
    "wof:name": "Raymond James Financial Svc",
    "wof:placetype": "venue"
  },
  "geometry": {"coordinates":[-81.6111,41.130576],"type":"Point"}
}
