{
  "type": "Feature",
  "properties": {
    "iso:country":"US",
    "sg:address":"3650 Stonebridge Dr",
    "sg:city":"Cincinnati",
    "sg:classifiers":[
        {
            "category":"Real Estate",
            "subcategory":"Real Estate Operator",
            "type":"Services"
        }
    ],
    "sg:phone":"+1 513 321 0678",
    "sg:postcode":"45209",
    "sg:province":"OH",
    "sg:tags":[
        "apartment"
    ],
    "wof:name":"Windsor At Brookstone Village",
    "wof:placetype":"venue"
},
  "geometry": {"coordinates":[-84.41616999999999,39.156447],"type":"Point"}
}