{
  "type": "Feature",
  "properties": {
    "iso:country":"US",
    "sg:address":"9595 Hamilton Ave",
    "sg:city":"Cincinnati",
    "sg:classifiers":[
        {
            "category":"Manufacturing",
            "subcategory":"Printing",
            "type":"Manufacturing & Wholesale Goods"
        }
    ],
    "sg:phone":"+1 513 728 3344",
    "sg:postcode":"45231",
    "sg:province":"OH",
    "sg:tags":[
        "printer"
    ],
    "sg:website":"www.expressgraph.com",
    "wof:name":"Express Graphics",
    "wof:placetype":"venue"
},
  "geometry": {"coordinates":[-84.5472,39.244788],"type":"Point"}
}