{
  "type": "Feature",
  "properties": {
    "addr:full": "1 W 4th St Cincinnati OH 45202",
    "addr:housenumber": "1",
    "addr:postcode": "45202",
    "addr:street": "W 4Th St",
    "iso:country": "US",
    "sg:address": "1 W 4th St",
    "sg:city": "Cincinnati",
    "sg:classifiers": [
      {
        "category": "Professional",
        "subcategory": "Lawyer \u0026 Legal Services",
        "type": "Services"
      }
    ],
    "sg:phone": "+1 513 352 0509",
    "sg:postcode": "45202",
    "sg:province": "OH",
    "wof:name": "Teletronics Accufix",
    "wof:placetype": "venue"
  },
  "geometry": {"coordinates":[-84.514286,39.099714],"type":"Point"}
}
