{
  "type": "Feature",
  "properties": {
    "iso:country":"US",
    "sg:address":"27093 Bagley Rd",
    "sg:city":"Cleveland",
    "sg:classifiers":[
        {
            "category":"Sports & Exercise",
            "subcategory":"Gym",
            "type":"Entertainment"
        }
    ],
    "sg:phone":"+1 440 235 0482",
    "sg:postcode":"44138",
    "sg:province":"OH",
    "sg:tags":[
        "facility",
        "club",
        "gymnasium",
        "health",
        "fitness",
        "studio",
        "physical"
    ],
    "wof:name":"Workout Express",
    "wof:placetype":"venue"
},
  "geometry": {"coordinates":[-81.923231,41.372678],"type":"Point"}
}