{
  "type": "Feature",
  "properties": {
    "addr:full": "209 Broadway St Quaker City OH 43773",
    "addr:housenumber": "209",
    "addr:postcode": "43773",
    "addr:street": "Broadway St",
    "iso:country": "US",
    "sg:address": "209 Broadway St",
    "sg:city": "Quaker City",
    "sg:classifiers": [
      {
        "category": "Banks \u0026 Credit Unions",
        "subcategory": "Bank",
        "type": "Services"
      }
    ],
    "sg:phone": "+1 740 679 2222",
    "sg:postcode": "43773",
    "sg:province": "OH",
    "sg:tags": [
      "commercial"
    ],
    "wof:name": "Peoples Bank",
    "wof:placetype": "venue"
  },
  "geometry": {"coordinates":[-81.298008,39.97034],"type":"Point"}
}
