{
  "type": "Feature",
  "properties": {
    "iso:country":"US",
    "sg:address":"209 Broadway St",
    "sg:city":"Quaker City",
    "sg:classifiers":[
        {
            "category":"Banks & Credit Unions",
            "subcategory":"Bank",
            "type":"Services"
        }
    ],
    "sg:phone":"+1 740 679 2222",
    "sg:postcode":"43773",
    "sg:province":"OH",
    "sg:tags":[
        "commercial"
    ],
    "wof:name":"Peoples Bank",
    "wof:placetype":"venue"
},
  "geometry": {"coordinates":[-81.298008,39.97034],"type":"Point"}
}