{
  "type": "Feature",
  "properties": {
    "iso:country":"US",
    "sg:address":"5105 Som Center Rd",
    "sg:city":"Solon",
    "sg:classifiers":[
        {
            "category":"Government",
            "subcategory":"Office",
            "type":"Public Place"
        }
    ],
    "sg:phone":"+1 216 795 6275",
    "sg:postcode":"44139",
    "sg:province":"OH",
    "sg:tags":[
        "administrative",
        "program",
        "health"
    ],
    "wof:name":"Kaiser Med Mental Health Dept",
    "wof:placetype":"venue"
},
  "geometry": {"coordinates":[-81.44269799999999,41.418238],"type":"Point"}
}