{
  "type": "Feature",
  "properties": {
    "iso:country":"US",
    "sg:address":"8870 Darrow Rd",
    "sg:city":"Twinsburg",
    "sg:classifiers":[
        {
            "category":"Restaurant",
            "type":"Food & Drink"
        }
    ],
    "sg:phone":"+1 330 487 0400",
    "sg:postcode":"44087",
    "sg:province":"OH",
    "wof:name":"Austins Smokin Steakhouse",
    "wof:placetype":"venue"
},
  "geometry": {"coordinates":[-81.44027800000001,41.306847],"type":"Point"}
}