{
  "type": "Feature",
  "properties": {
    "addr:full": "245 Senate St Marion OH 43302",
    "addr:housenumber": "245",
    "addr:postcode": "43302",
    "addr:street": "Senate St",
    "iso:country": "US",
    "sg:address": "245 Senate St",
    "sg:city": "Marion",
    "sg:classifiers": [
      {
        "category": "Travel",
        "subcategory": "Hotels \u0026 Motels",
        "type": "Entertainment"
      }
    ],
    "sg:phone": "+1 740 382 2402",
    "sg:postcode": "43302",
    "sg:province": "OH",
    "sg:tags": [
      "breakfast",
      "accommodation",
      "bed"
    ],
    "wof:name": "Olde Towne Manor B \u0026 B",
    "wof:placetype": "venue"
  },
  "geometry": {"coordinates":[-83.145181,40.591515],"type":"Point"}
}
