{
  "type": "Feature",
  "properties": {
    "iso:country":"US",
    "sg:address":"296 Tauber Dr",
    "sg:city":"Dayton",
    "sg:classifiers":[
        {
            "category":"Shopping",
            "subcategory":"Catalog Store",
            "type":"Retail Goods"
        }
    ],
    "sg:phone":"+1 937 435 7197",
    "sg:postcode":"45458",
    "sg:province":"OH",
    "sg:tags":[
        "internet"
    ],
    "wof:name":"Betty J Kirchmer Mail Order",
    "wof:placetype":"venue"
},
  "geometry": {"coordinates":[-84.167838,39.622306],"type":"Point"}
}