{
  "type": "Feature",
  "properties": {
    "addr:full":"13497 Crooked St Mount Vernon OH 43050",
    "addr:housenumber":"13497",
    "addr:postcode":"43050",
    "addr:street":"Crooked St",
    "iso:country":"US",
    "sg:address":"13497 Crooked St",
    "sg:city":"Mount Vernon",
    "sg:phone":"+1 740 397 7964",
    "sg:postcode":"43050",
    "sg:province":"OH",
    "sg:tags":[
        "farm",
        "corn",
        "soybean"
    ],
    "wof:name":"Charles Bevington",
    "wof:placetype":"venue"
},
  "geometry": {"coordinates":[-82.50371699999999,40.439737],"type":"Point"}
}