{
  "type": "Feature",
  "properties": {
    "addr:full": "124 Dayton St Yellow Springs OH 45387",
    "addr:housenumber": "124",
    "addr:postcode": "45387",
    "addr:street": "Dayton St",
    "iso:country": "US",
    "sg:address": "124 Dayton St",
    "sg:city": "Yellow Springs",
    "sg:classifiers": [
      {
        "category": "Shopping",
        "subcategory": "Tobacco",
        "type": "Retail Goods"
      },
      {
        "category": "Shopping",
        "subcategory": "Clothing, Apparel, \u0026 Fashions",
        "type": "Retail Goods"
      }
    ],
    "sg:phone": "+1 937 767 9499",
    "sg:postcode": "45387",
    "sg:province": "OH",
    "sg:tags": [
      "shop",
      "smoke",
      "supply"
    ],
    "wof:name": "Import House The",
    "wof:placetype": "venue"
  },
  "geometry": {"coordinates":[-83.888397,39.807546],"type":"Point"}
}
