{
  "type": "Feature",
  "properties": {
    "addr:full":"6730 Roosevelt Ave Franklin OH 45005",
    "addr:housenumber":"6730",
    "addr:postcode":"45005",
    "addr:street":"Roosevelt Ave",
    "iso:country":"US",
    "sg:address":"6730 Roosevelt Ave",
    "sg:city":"Franklin",
    "sg:classifiers":[
        {
            "category":"Organizations",
            "subcategory":"Non-profit Organization",
            "type":"Services"
        },
        {
            "category":"Professional",
            "subcategory":"Management & Consulting",
            "type":"Services"
        }
    ],
    "sg:phone":"+1 513 422 0063",
    "sg:postcode":"45005",
    "sg:province":"OH",
    "sg:tags":[
        "consultant",
        "medical"
    ],
    "sg:website":"www.hsr.com",
    "wof:name":"Health Service Review of Ohio",
    "wof:placetype":"venue"
},
  "geometry": {"coordinates":[-84.335561,39.493401],"type":"Point"}
}