{
  "type": "Feature",
  "properties": {
    "addr:full":"4720 Mahoning Ave Youngstown OH 44515",
    "addr:housenumber":"4720",
    "addr:postcode":"44515",
    "addr:street":"Mahoning Ave",
    "iso:country":"US",
    "sg:address":"4720 Mahoning Ave",
    "sg:city":"Youngstown",
    "sg:classifiers":[
        {
            "category":"Utilities",
            "subcategory":"Cable",
            "type":"Services"
        }
    ],
    "sg:phone":"+1 330 792 9577",
    "sg:postcode":"44515",
    "sg:province":"OH",
    "sg:tags":[
        "television"
    ],
    "wof:name":"Star Cable Co",
    "wof:placetype":"venue"
},
  "geometry": {"coordinates":[-80.74229200000001,41.100951],"type":"Point"}
}