{
  "type": "Feature",
  "properties": {
    "addr:full":"2192 Scranton Rd Cleveland OH 44113",
    "addr:housenumber":"2192",
    "addr:postcode":"44113",
    "addr:street":"Scranton Rd",
    "iso:country":"US",
    "sg:address":"2192 Scranton Rd",
    "sg:city":"Cleveland",
    "sg:classifiers":[
        {
            "category":"Manufacturing",
            "subcategory":"Metals",
            "type":"Manufacturing & Wholesale Goods"
        },
        {
            "category":"Wholesale",
            "subcategory":"Durable Goods & Equipment",
            "type":"Manufacturing & Wholesale Goods"
        }
    ],
    "sg:phone":"+1 216 861 5002",
    "sg:postcode":"44113",
    "sg:province":"OH",
    "sg:tags":[
        "for",
        "industry",
        "grinding",
        "production",
        "slating",
        "retail",
        "tooling"
    ],
    "wof:name":"North Coast Grinding Inc",
    "wof:placetype":"venue"
},
  "geometry": {"coordinates":[-81.69481,41.483515],"type":"Point"}
}