{
  "type": "Feature",
  "properties": {
    "addr:full": "4970 Village Mdw Westerville OH 43081",
    "addr:housenumber": "4970",
    "addr:postcode": "westerville oh 43081",
    "addr:street": "Village Mdw",
    "iso:country": "US",
    "sg:address": "4970 Village Mdw",
    "sg:city": "Westerville",
    "sg:classifiers": [
      {
        "category": "Restaurant",
        "type": "Food \u0026 Drink"
      }
    ],
    "sg:phone": "+1 614 890 7956",
    "sg:postcode": "43081",
    "sg:province": "OH",
    "sg:tags": [
      "eating"
    ],
    "wof:name": "Gameday Grille At Rush Cr",
    "wof:placetype": "venue"
  },
  "geometry": {"coordinates":[-82.867865,40.078433],"type":"Point"}
}
