{
  "type": "Feature",
  "properties": {
    "addr:full": "3606 Venice Rd Sandusky OH 44870",
    "addr:housenumber": "3606",
    "addr:postcode": "44870",
    "addr:street": "Venice Rd",
    "iso:country": "US",
    "sg:address": "3606 Venice Rd",
    "sg:city": "Sandusky",
    "sg:classifiers": [
      {
        "category": "Professional",
        "subcategory": "Testing Lab",
        "type": "Services"
      }
    ],
    "sg:phone": "+1 419 627 1976",
    "sg:postcode": "44870",
    "sg:province": "OH",
    "sg:tags": [
      "asbestos",
      "laboratory",
      "removal",
      "contractor"
    ],
    "wof:name": "Affiliated Environmental Svcs",
    "wof:placetype": "venue"
  },
  "geometry": {"coordinates":[-82.747167,41.441163],"type":"Point"}
}
