{
  "type": "Feature",
  "properties": {
    "addr:full":"2655 Cleveland Rd Wooster OH 44691",
    "addr:housenumber":"2655",
    "addr:postcode":"44691",
    "addr:street":"Cleveland Rd",
    "iso:country":"US",
    "sg:address":"2655 Cleveland Rd",
    "sg:city":"Wooster",
    "sg:classifiers":[
        {
            "category":"Building & Trades",
            "subcategory":"Landscaping Services",
            "type":"Services"
        }
    ],
    "sg:phone":"+1 330 345 5244",
    "sg:postcode":"44691",
    "sg:province":"OH",
    "sg:tags":[
        "landscape",
        "contractor"
    ],
    "wof:name":"Foliage Franks & Landscape",
    "wof:placetype":"venue"
},
  "geometry": {"coordinates":[-81.93021400000001,40.831773],"type":"Point"}
}