{
  "type": "Feature",
  "properties": {
    "iso:country":"US",
    "sg:address":"7 S Ohio Ave",
    "sg:city":"Wellston",
    "sg:classifiers":[
        {
            "category":"Shopping",
            "type":"Retail Goods"
        }
    ],
    "sg:phone":"+1 740 384 5324",
    "sg:postcode":"45692",
    "sg:province":"OH",
    "sg:tags":[
        "trophy",
        "medal",
        "award"
    ],
    "wof:name":"Brodigan's Sports & Trophies",
    "wof:placetype":"venue"
},
  "geometry": {"coordinates":[-82.534254,39.123497],"type":"Point"}
}