{
  "type": "Feature",
  "properties": {
    "addr:full": "325 Venture Dr Westerville OH 43081",
    "addr:housenumber": "325",
    "addr:postcode": "43081",
    "addr:street": "Venture Dr",
    "iso:country": "US",
    "sg:address": "325 Venture Dr",
    "sg:city": "Westerville",
    "sg:classifiers": [
      {
        "category": "Farming",
        "subcategory": "Farm \u0026 Veterinary Services",
        "type": "Manufacturing \u0026 Wholesale Goods"
      }
    ],
    "sg:phone": "+1 614 888 1663",
    "sg:postcode": "43081",
    "sg:province": "OH",
    "sg:tags": [
      "soil",
      "testing"
    ],
    "wof:name": "C L C Labs",
    "wof:placetype": "venue"
  },
  "geometry": {"coordinates":[-83.010684,40.154262],"type":"Point"}
}
