{
  "type": "Feature",
  "properties": {
    "iso:country":"US",
    "sg:address":"12671 Market Ave N",
    "sg:city":"Hartville",
    "sg:classifiers":[
        {
            "category":"Shopping",
            "subcategory":"Gifts & Souvenirs",
            "type":"Retail Goods"
        }
    ],
    "sg:phone":"+1 330 877 9840",
    "sg:postcode":"44632",
    "sg:province":"OH",
    "sg:tags":[
        "shop"
    ],
    "wof:name":"Pine Cone Gift Shoppe",
    "wof:placetype":"venue"
},
  "geometry": {"coordinates":[-81.359225,40.958242],"type":"Point"}
}