{
  "type": "Feature",
  "properties": {
    "addr:full": "150 Wyandotte St Dayton OH 45402",
    "addr:housenumber": "150",
    "addr:postcode": "45402",
    "addr:street": "Wyandotte St",
    "iso:country": "US",
    "sg:address": "150 Wyandotte St",
    "sg:city": "Dayton",
    "sg:classifiers": [
      {
        "category": "Professional",
        "subcategory": "Art Services",
        "type": "Services"
      },
      {
        "category": "Manufacturing",
        "subcategory": "Printing",
        "type": "Manufacturing \u0026 Wholesale Goods"
      }
    ],
    "sg:phone": "+1 937 223 4265",
    "sg:postcode": "45402",
    "sg:province": "OH",
    "sg:tags": [
      "graphic",
      "publishing",
      "designer"
    ],
    "wof:name": "Xtra Pro Print \u0026 Graphics",
    "wof:placetype": "venue"
  },
  "geometry": {"coordinates":[-84.186667,39.75788],"type":"Point"}
}
