{
  "type": "Feature",
  "properties": {
    "addr:full":"68 Crescent Dr Struthers OH 44471",
    "addr:housenumber":"68",
    "addr:postcode":"44471",
    "addr:street":"Crescent Dr",
    "iso:country":"US",
    "sg:address":"68 Crescent Dr",
    "sg:city":"Struthers",
    "sg:classifiers":[
        {
            "category":"Food & Beverages",
            "subcategory":"Liquor & Beverages",
            "type":"Retail Goods"
        }
    ],
    "sg:phone":"+1 330 755 2728",
    "sg:postcode":"44471",
    "sg:province":"OH",
    "sg:tags":[
        "alcoholic"
    ],
    "wof:name":"Toms Drive Thru",
    "wof:placetype":"venue"
},
  "geometry": {"coordinates":[-80.614975,41.059805],"type":"Point"}
}