{
  "type": "Feature",
  "properties": {
    "addr:full":"5066 Sherlin Ave NW Massillon OH 44646",
    "addr:housenumber":"5066",
    "addr:postcode":"44646",
    "addr:street":"Sherlin Ave Nw",
    "iso:country":"US",
    "sg:address":"5066 Sherlin Ave NW",
    "sg:city":"Massillon",
    "sg:classifiers":[
        {
            "category":"Restaurant",
            "type":"Food & Drink"
        }
    ],
    "sg:phone":"+1 330 497 7900",
    "sg:postcode":"44646",
    "sg:province":"OH",
    "sg:tags":[
        "eating"
    ],
    "wof:name":"Pluto S Pizza",
    "wof:placetype":"venue"
},
  "geometry": {"coordinates":[-81.508245,40.853832],"type":"Point"}
}