{
  "type": "Feature",
  "properties": {
    "addr:full": "1614 Lancaster Ave Reynoldsburg OH 43068",
    "addr:housenumber": "1614",
    "addr:postcode": "43068",
    "addr:street": "Lancaster Ave",
    "iso:country": "US",
    "sg:address": "1614 Lancaster Ave",
    "sg:city": "Reynoldsburg",
    "sg:classifiers": [
      {
        "category": "Professional",
        "subcategory": "Employment Agencies",
        "type": "Services"
      }
    ],
    "sg:phone": "+1 614 861 4400",
    "sg:postcode": "43068",
    "sg:province": "OH",
    "wof:name": "Barleycorn Renard \u0026 Associates",
    "wof:placetype": "venue"
  },
  "geometry": {"coordinates":[-82.799614,39.951046],"type":"Point"}
}
