{
  "type": "Feature",
  "properties": {
    "iso:country":"US",
    "sg:address":"1614 Lancaster Ave",
    "sg:city":"Reynoldsburg",
    "sg:classifiers":[
        {
            "category":"Professional",
            "subcategory":"Employment Agencies",
            "type":"Services"
        }
    ],
    "sg:phone":"+1 614 861 4400",
    "sg:postcode":"43068",
    "sg:province":"OH",
    "wof:name":"Barleycorn Renard & Associates",
    "wof:placetype":"venue"
},
  "geometry": {"coordinates":[-82.79961400000001,39.951046],"type":"Point"}
}