{
  "type": "Feature",
  "properties": {
    "addr:full": "32100 Solon Rd Cleveland OH 44139",
    "addr:postcode": "32100;44139",
    "addr:street": "Solon Rd",
    "iso:country": "US",
    "sg:address": "32100 Solon Rd",
    "sg:city": "Cleveland",
    "sg:classifiers": [
      {
        "category": "Professional",
        "type": "Services"
      },
      {
        "category": "Professional",
        "subcategory": "Computer Services",
        "type": "Services"
      }
    ],
    "sg:phone": "+1 440 914 0100",
    "sg:postcode": "44139",
    "sg:province": "OH",
    "sg:tags": [
      "consultant",
      "designer"
    ],
    "wof:name": "Middletech Corp",
    "wof:placetype": "venue"
  },
  "geometry": {"coordinates":[-81.45112,41.387167],"type":"Point"}
}
