{
  "type": "Feature",
  "properties": {
    "addr:full": "7004 Haggerty Rd Hillsboro OH 45133",
    "addr:housenumber": "7004",
    "addr:postcode": "45133",
    "addr:street": "Haggerty Rd",
    "iso:country": "US",
    "sg:address": "7004 Haggerty Rd",
    "sg:city": "Hillsboro",
    "sg:classifiers": [
      {
        "category": "Building \u0026 Trades",
        "subcategory": "Plumbing",
        "type": "Services"
      }
    ],
    "sg:phone": "+1 937 840 9132",
    "sg:postcode": "45133",
    "sg:province": "OH",
    "sg:tags": [
      "heating",
      "contractor"
    ],
    "wof:name": "Butler Service Co",
    "wof:placetype": "venue"
  },
  "geometry": {"coordinates":[-83.559369,39.200245],"type":"Point"}
}
