{
  "type": "Feature",
  "properties": {
    "addr:full": "101 N Park Way Ravenna OH 44266",
    "addr:housenumber": "101",
    "addr:postcode": "44266",
    "addr:street": "N Park Way",
    "iso:country": "US",
    "sg:address": "101 N Park Way",
    "sg:city": "Ravenna",
    "sg:classifiers": [
      {
        "category": "Real Estate",
        "subcategory": "Architect",
        "type": "Services"
      }
    ],
    "sg:phone": "+1 330 296 5200",
    "sg:postcode": "44266",
    "sg:province": "OH",
    "wof:name": "Theodore G Manfrass",
    "wof:placetype": "venue"
  },
  "geometry": {"coordinates":[-81.243912,41.158387],"type":"Point"}
}
