{
  "type": "Feature",
  "properties": {
    "addr:full": "20701 State Rte 697 Delphos OH 45833",
    "addr:housenumber": "20701",
    "addr:postcode": "45833",
    "addr:street": "State Rte 697",
    "iso:country": "US",
    "sg:address": "20701 State Rte 697",
    "sg:city": "Delphos",
    "sg:classifiers": [
      {
        "category": "Farming",
        "subcategory": "Livestock Farm",
        "type": "Manufacturing \u0026 Wholesale Goods"
      }
    ],
    "sg:phone": "+1 419 692 1279",
    "sg:postcode": "45833",
    "sg:province": "OH",
    "sg:tags": [
      "hog",
      "wheat",
      "corn",
      "soybean",
      "or",
      "feedlot"
    ],
    "wof:name": "Friedrich Farms Inc",
    "wof:placetype": "venue"
  },
  "geometry": {"coordinates":[-84.422063,40.837625],"type":"Point"}
}
