{
  "type": "Feature",
  "properties": {
    "addr:full": "20 N 2nd Ave Middleport OH 45760",
    "addr:housenumber": "20",
    "addr:postcode": "45760",
    "addr:street": "N 2Nd Ave",
    "iso:country": "US",
    "sg:address": "20 N 2nd Ave",
    "sg:city": "Middleport",
    "sg:classifiers": [
      {
        "category": "Wholesale",
        "subcategory": "Drugs",
        "type": "Manufacturing \u0026 Wholesale Goods"
      }
    ],
    "sg:phone": "+1 740 992 7039",
    "sg:postcode": "45760",
    "sg:province": "OH",
    "wof:name": "Sandy Iannarelli",
    "wof:placetype": "venue"
  },
  "geometry": {"coordinates":[-82.048253,39.002274],"type":"Point"}
}
