{
  "type": "Feature",
  "properties": {
    "iso:country":"US",
    "sg:address":"20 N 2nd Ave",
    "sg:city":"Middleport",
    "sg:classifiers":[
        {
            "category":"Wholesale",
            "subcategory":"Drugs",
            "type":"Manufacturing & Wholesale Goods"
        }
    ],
    "sg:phone":"+1 740 992 7039",
    "sg:postcode":"45760",
    "sg:province":"OH",
    "wof:name":"Sandy Iannarelli",
    "wof:placetype":"venue"
},
  "geometry": {"coordinates":[-82.048253,39.002274],"type":"Point"}
}