{
  "type": "Feature",
  "properties": {
    "addr:full":"3200 Easton Rd Norton OH 44203",
    "addr:housenumber":"3200",
    "addr:postcode":"44203",
    "addr:street":"Easton Rd",
    "iso:country":"US",
    "sg:address":"3200 Easton Rd",
    "sg:city":"Norton",
    "sg:classifiers":[
        {
            "category":"Organizations",
            "subcategory":"Religious Organization",
            "type":"Services"
        }
    ],
    "sg:phone":"+1 330 706 1009",
    "sg:postcode":"44203",
    "sg:province":"OH",
    "sg:tags":[
        "church"
    ],
    "wof:name":"Church Winning Side Baptist",
    "wof:placetype":"venue"
},
  "geometry": {"coordinates":[-81.647875,41.046029],"type":"Point"}
}