{
  "type": "Feature",
  "properties": {
    "iso:country":"US",
    "sg:address":"105 Cleveland Rd",
    "sg:city":"Norwalk",
    "sg:classifiers":[
        {
            "category":"Professional",
            "subcategory":"Accounting & Tax Preparation",
            "type":"Services"
        }
    ],
    "sg:phone":"+1 419 668 2967",
    "sg:postcode":"44857",
    "sg:province":"OH",
    "sg:tags":[
        "accountant"
    ],
    "sg:website":"www.mvmcpa.com",
    "wof:name":"Mc Laughlin Vandootingh Mosher",
    "wof:placetype":"venue"
},
  "geometry": {"coordinates":[-82.603082,41.247741],"type":"Point"}
}