{
  "type": "Feature",
  "properties": {
    "iso:country":"US",
    "sg:address":"3427 Egypt Rd",
    "sg:city":"Willard",
    "sg:classifiers":[
        {
            "category":"Building & Trades",
            "subcategory":"Landscaping Services",
            "type":"Services"
        }
    ],
    "sg:phone":"+1 419 933 7704",
    "sg:postcode":"44890",
    "sg:province":"OH",
    "sg:tags":[
        "landscape"
    ],
    "wof:name":"Willard Landscaping",
    "wof:placetype":"venue"
},
  "geometry": {"coordinates":[-82.71656900000001,41.079243],"type":"Point"}
}