{
  "type": "Feature",
  "properties": {
    "addr:full": "3427 Egypt Rd Willard OH 44890",
    "addr:housenumber": "3427",
    "addr:postcode": "44890",
    "addr:street": "Egypt Rd",
    "iso:country": "US",
    "sg:address": "3427 Egypt Rd",
    "sg:city": "Willard",
    "sg:classifiers": [
      {
        "category": "Building \u0026 Trades",
        "subcategory": "Landscaping Services",
        "type": "Services"
      }
    ],
    "sg:phone": "+1 419 933 7704",
    "sg:postcode": "44890",
    "sg:province": "OH",
    "sg:tags": [
      "landscape"
    ],
    "wof:name": "Willard Landscaping",
    "wof:placetype": "venue"
  },
  "geometry": {"coordinates":[-82.716569,41.079243],"type":"Point"}
}
