{
  "type": "Feature",
  "properties": {
    "addr:full": "726 Rice St Newark OH 43055",
    "addr:housenumber": "726",
    "addr:postcode": "43055",
    "addr:street": "Rice St",
    "iso:country": "US",
    "sg:address": "726 Rice St",
    "sg:city": "Newark",
    "sg:classifiers": [
      {
        "category": "Retail",
        "subcategory": "Animal Services",
        "type": "Services"
      }
    ],
    "sg:phone": "+1 740 344 4057",
    "sg:postcode": "43055",
    "sg:province": "OH",
    "sg:tags": [
      "pet",
      "grooming",
      "washing"
    ],
    "wof:name": "J \u0026 J Grooming Boutique",
    "wof:placetype": "venue"
  },
  "geometry": {"coordinates":[-82.430429,40.0483],"type":"Point"}
}
