{
  "type": "Feature",
  "properties": {
    "addr:full": "217 S Dixie Dr Vandalia OH 45377",
    "addr:housenumber": "217",
    "addr:postcode": "45377",
    "addr:street": "S Dixie Dr",
    "iso:country": "US",
    "sg:address": "217 S Dixie Dr",
    "sg:city": "Vandalia",
    "sg:classifiers": [
      {
        "category": "Insurance",
        "subcategory": "Insurance Agent",
        "type": "Services"
      }
    ],
    "sg:phone": "+1 937 890 8467",
    "sg:postcode": "45377",
    "sg:province": "OH",
    "wof:name": "American National Insurance Co",
    "wof:placetype": "venue"
  },
  "geometry": {"coordinates":[-84.198998,39.888226],"type":"Point"}
}
