{
  "type": "Feature",
  "properties": {
    "iso:country":"US",
    "sg:address":"1419 South Ave",
    "sg:city":"Toledo",
    "sg:classifiers":[
        {
            "category":"Restaurant",
            "type":"Food & Drink"
        }
    ],
    "sg:menulink":"http://www.allmenus.com/oh/toledo/68819-marcos-pizza/menu/",
    "sg:phone":"+1 419 385 6463",
    "sg:postcode":"43609",
    "sg:province":"OH",
    "sg:tags":[
        "american",
        "pizza"
    ],
    "wof:name":"Marco's Pizza",
    "wof:placetype":"venue"
},
  "geometry": {"coordinates":[-83.575344,41.63057],"type":"Point"}
}