{
  "type": "Feature",
  "properties": {
    "addr:full":"2025 Corvair Ave Columbus OH 43207",
    "addr:housenumber":"2025",
    "addr:postcode":"43207",
    "addr:street":"Corvair Ave",
    "iso:country":"US",
    "sg:address":"2025 Corvair Ave",
    "sg:city":"Columbus",
    "sg:classifiers":[
        {
            "category":"Wholesale",
            "subcategory":"Non-durable Goods",
            "type":"Manufacturing & Wholesale Goods"
        }
    ],
    "sg:phone":"+1 614 449 6100",
    "sg:postcode":"43207",
    "sg:province":"OH",
    "sg:tags":[
        "importer",
        "merchandise",
        "general"
    ],
    "wof:name":"Value City",
    "wof:placetype":"venue"
},
  "geometry": {"coordinates":[-82.942032,39.928417],"type":"Point"}
}