{
  "type": "Feature",
  "properties": {
    "addr:full":"2000 Noble Dr Wooster OH 44691",
    "addr:housenumber":"2000",
    "addr:postcode":"44691",
    "addr:street":"Noble Dr",
    "iso:country":"US",
    "sg:address":"2000 Noble Dr",
    "sg:city":"Wooster",
    "sg:classifiers":[
        {
            "category":"Professional",
            "subcategory":"Computer Services",
            "type":"Services"
        }
    ],
    "sg:phone":"+1 330 263 6222",
    "sg:postcode":"44691",
    "sg:province":"OH",
    "sg:tags":[
        "consultant",
        "designer"
    ],
    "sg:website":"www.tgstech.com",
    "wof:name":"Techni Graphics",
    "wof:placetype":"venue"
},
  "geometry": {"coordinates":[-81.90070799999999,40.82415],"type":"Point"}
}