{
  "type": "Feature",
  "properties": {
    "iso:country":"US",
    "sg:address":"7452 Fulton Dr NW",
    "sg:city":"Massillon",
    "sg:classifiers":[
        {
            "category":"Health Services",
            "subcategory":"Doctor",
            "type":"Services"
        }
    ],
    "sg:phone":"+1 330 837 9249",
    "sg:postcode":"44646",
    "sg:province":"OH",
    "sg:tags":[
        "physician",
        "surgeon"
    ],
    "wof:name":"Mercy Sports Medicine",
    "wof:placetype":"venue"
},
  "geometry": {"coordinates":[-81.488998,40.860704],"type":"Point"}
}