{
  "type": "Feature",
  "properties": {
    "iso:country":"US",
    "sg:address":"9523 State Rte 14",
    "sg:city":"Streetsboro",
    "sg:classifiers":[
        {
            "category":"Shopping",
            "subcategory":"Florist",
            "type":"Retail Goods"
        }
    ],
    "sg:phone":"+1 330 626 4644",
    "sg:postcode":"44241",
    "sg:province":"OH",
    "wof:name":"A & F Garden Gate Florist Inc",
    "wof:placetype":"venue"
},
  "geometry": {"coordinates":[-81.356213,41.244326],"type":"Point"}
}