{
  "type": "Feature",
  "properties": {
    "iso:country":"US",
    "sg:address":"4378 W 191st St",
    "sg:city":"Cleveland",
    "sg:classifiers":[
        {
            "category":"Retail",
            "subcategory":"Auto Repair",
            "type":"Services"
        }
    ],
    "sg:phone":"+1 216 267 7004",
    "sg:postcode":"44135",
    "sg:province":"OH",
    "sg:tags":[
        "wrecker"
    ],
    "wof:name":"Checkers Towing",
    "wof:placetype":"venue"
},
  "geometry": {"coordinates":[-81.83193,41.435096],"type":"Point"}
}