{
  "type": "Feature",
  "properties": {
    "addr:full":"118 Martin Ave Sandusky OH 44870",
    "addr:housenumber":"118",
    "addr:postcode":"44870",
    "addr:street":"Martin Ave",
    "iso:country":"US",
    "sg:address":"118 Martin Ave",
    "sg:city":"Sandusky",
    "sg:classifiers":[
        {
            "category":"Personal",
            "subcategory":"Beauty Salon",
            "type":"Services"
        }
    ],
    "sg:phone":"+1 419 684 5728",
    "sg:postcode":"44870",
    "sg:province":"OH",
    "wof:name":"Jen's KRAY Z Kuts",
    "wof:placetype":"venue"
},
  "geometry": {"coordinates":[-82.843215,41.446889],"type":"Point"}
}