{
  "type": "Feature",
  "properties": {
    "iso:country":"US",
    "sg:address":"1400 Hill Rd N",
    "sg:city":"Pickerington",
    "sg:classifiers":[
        {
            "category":"Retail",
            "subcategory":"Car Wash",
            "type":"Services"
        },
        {
            "category":"Autos & Motor Vehicles",
            "subcategory":"Fuel & Gas Station",
            "type":"Retail Goods"
        }
    ],
    "sg:phone":"+1 614 864 2128",
    "sg:postcode":"43147",
    "sg:province":"OH",
    "sg:tags":[
        "polishing",
        "oil",
        "washing"
    ],
    "wof:name":"Exxon Go Kleen Car Wash",
    "wof:placetype":"venue"
},
  "geometry": {"coordinates":[-82.780317,39.916415],"type":"Point"}
}