{
  "type": "Feature",
  "properties": {
    "iso:country":"US",
    "sg:address":"4535 Smeltzer Rd",
    "sg:city":"Marion",
    "sg:classifiers":[
        {
            "category":"Organizations",
            "subcategory":"Religious Organization",
            "type":"Services"
        }
    ],
    "sg:phone":"+1 740 389 1714",
    "sg:postcode":"43302",
    "sg:province":"OH",
    "sg:tags":[
        "church"
    ],
    "wof:name":"Trinity Lutheran Church",
    "wof:placetype":"venue"
},
  "geometry": {"coordinates":[-83.131424,40.499826],"type":"Point"}
}