{
  "type": "Feature",
  "properties": {
    "addr:full": "2020 Brice Rd Reynoldsburg OH 43068",
    "addr:housenumber": "2020",
    "addr:postcode": "43068",
    "addr:street": "Brice Rd",
    "iso:country": "US",
    "sg:address": "2020 Brice Rd",
    "sg:city": "Reynoldsburg",
    "sg:classifiers": [
      {
        "category": "Insurance",
        "subcategory": "Insurance Agent",
        "type": "Services"
      }
    ],
    "sg:phone": "+1 614 868 8227",
    "sg:postcode": "43068",
    "sg:province": "OH",
    "wof:name": "Al Russo Insurance",
    "wof:placetype": "venue"
  },
  "geometry": {"coordinates":[-82.830113,39.938967],"type":"Point"}
}
