{
  "type": "Feature",
  "properties": {
    "iso:country":"US",
    "sg:address":"8009 Coletown-Lightsville Rd",
    "sg:city":"Greenville",
    "sg:classifiers":[
        {
            "category":"Retail",
            "subcategory":"Repair Shop",
            "type":"Services"
        }
    ],
    "sg:phone":"+1 937 548 7274",
    "sg:postcode":"45331",
    "sg:province":"OH",
    "sg:tags":[
        "equipment",
        "industrial"
    ],
    "wof:name":"Montgomery Indicator Service",
    "wof:placetype":"venue"
},
  "geometry": {"coordinates":[-84.707955,40.150479],"type":"Point"}
}