{
  "type": "Feature",
  "properties": {
    "iso:country":"US",
    "sg:address":"401 Market Ave N",
    "sg:city":"Canton",
    "sg:classifiers":[
        {
            "category":"Building & Trades",
            "subcategory":"Construction",
            "type":"Services"
        }
    ],
    "sg:phone":"+1 330 455 9126",
    "sg:postcode":"44702",
    "sg:province":"OH",
    "sg:tags":[
        "industrial",
        "commercial",
        "contractor"
    ],
    "wof:name":"Bernie Jenkins Inc",
    "wof:placetype":"venue"
},
  "geometry": {"coordinates":[-81.373751,40.801238],"type":"Point"}
}