{
  "type": "Feature",
  "properties": {
    "iso:country":"US",
    "sg:address":"868 Wasson Rd",
    "sg:city":"Union City",
    "sg:classifiers":[
        {
            "category":"Sports & Exercise",
            "subcategory":"Golf",
            "type":"Entertainment"
        }
    ],
    "sg:phone":"+1 937 968 6518",
    "sg:postcode":"45390",
    "sg:province":"OH",
    "sg:tags":[
        "course"
    ],
    "wof:name":"Union City Country Club Inc",
    "wof:placetype":"venue"
},
  "geometry": {"coordinates":[-84.77534799999999,40.150486],"type":"Point"}
}