{
  "type": "Feature",
  "properties": {
    "addr:full": "868 Wasson Rd Union City OH 45390",
    "addr:housenumber": "868",
    "addr:postcode": "45390",
    "addr:street": "Wasson Rd",
    "iso:country": "US",
    "sg:address": "868 Wasson Rd",
    "sg:city": "Union City",
    "sg:classifiers": [
      {
        "category": "Sports \u0026 Exercise",
        "subcategory": "Golf",
        "type": "Entertainment"
      }
    ],
    "sg:phone": "+1 937 968 6518",
    "sg:postcode": "45390",
    "sg:province": "OH",
    "sg:tags": [
      "course"
    ],
    "wof:name": "Union City Country Club Inc",
    "wof:placetype": "venue"
  },
  "geometry": {"coordinates":[-84.775348,40.150486],"type":"Point"}
}
