{
  "type": "Feature",
  "properties": {
    "addr:full": "9360 Ravenna Rd Twinsburg OH 44087",
    "addr:housenumber": "9360",
    "addr:postcode": "44087",
    "addr:street": "Ravenna Rd",
    "iso:country": "US",
    "sg:address": "9360 Ravenna Rd",
    "sg:city": "Twinsburg",
    "sg:classifiers": [
      {
        "category": "Manufacturing",
        "subcategory": "Chemicals \u0026 Compounds",
        "type": "Manufacturing \u0026 Wholesale Goods"
      }
    ],
    "sg:phone": "+1 330 425 7676",
    "sg:postcode": "44087",
    "sg:province": "OH",
    "sg:tags": [
      "preparation",
      "plate",
      "work",
      "fabricated",
      "mfg"
    ],
    "wof:name": "Nationwide Gas Tank \u0026 Service",
    "wof:placetype": "venue"
  },
  "geometry": {"coordinates":[-81.429196,41.307883],"type":"Point"}
}
