{
  "type": "Feature",
  "properties": {
    "iso:country":"US",
    "sg:address":"4557 Bethany Rd",
    "sg:city":"Mason",
    "sg:classifiers":[
        {
            "category":"Professional",
            "subcategory":"Management & Consulting",
            "type":"Services"
        }
    ],
    "sg:phone":"+1 513 459 1114",
    "sg:postcode":"45040",
    "sg:province":"OH",
    "sg:tags":[
        "marketing",
        "consultant"
    ],
    "wof:name":"Trovato Inc",
    "wof:placetype":"venue"
},
  "geometry": {"coordinates":[-84.300166,39.378187],"type":"Point"}
}