{
  "type": "Feature",
  "properties": {
    "addr:full":"302 N Byrne Rd Toledo OH 43607",
    "addr:housenumber":"302",
    "addr:postcode":"43607",
    "addr:street":"N Byrne Rd",
    "iso:country":"US",
    "sg:address":"302 N Byrne Rd",
    "sg:city":"Toledo",
    "sg:classifiers":[
        {
            "category":"Freight",
            "type":"Transportation"
        }
    ],
    "sg:phone":"+1 419 531 3505",
    "sg:postcode":"43607",
    "sg:province":"OH",
    "sg:tags":[
        "commercial",
        "storage"
    ],
    "wof:name":"Stop 'n Lock Self Storage",
    "wof:placetype":"venue"
},
  "geometry": {"coordinates":[-83.625893,41.640122],"type":"Point"}
}