{
  "type": "Feature",
  "properties": {
    "addr:full": "3320 Creek Rd Ste 1 Cincinnati OH 45241",
    "addr:housenumber": "3320",
    "addr:postcode": "45241",
    "addr:street": "Creek Rd Ste 1",
    "iso:country": "US",
    "sg:address": "3320 Creek Rd Ste 1",
    "sg:city": "Cincinnati",
    "sg:classifiers": [
      {
        "category": "Arts \u0026 Performance",
        "subcategory": "Art Gallery",
        "type": "Entertainment"
      },
      {
        "category": "Professional",
        "subcategory": "Art Services",
        "type": "Services"
      }
    ],
    "sg:phone": "+1 513 386 8432",
    "sg:postcode": "45241",
    "sg:province": "OH",
    "sg:tags": [
      "artist",
      "consultant",
      "galleries",
      "conservation",
      "fine",
      "restoration"
    ],
    "sg:website": "http://www.giclee42.com",
    "wof:name": "Giclee 42",
    "wof:placetype": "venue"
  },
  "geometry": {"coordinates":[-84.412706,39.270259],"type":"Point"}
}
