{
  "type": "Feature",
  "properties": {
    "iso:country":"US",
    "sg:address":"3320 Creek Rd Ste 1",
    "sg:city":"Cincinnati",
    "sg:classifiers":[
        {
            "category":"Arts & Performance",
            "subcategory":"Art Gallery",
            "type":"Entertainment"
        },
        {
            "category":"Professional",
            "subcategory":"Art Services",
            "type":"Services"
        }
    ],
    "sg:phone":"+1 513 386 8432",
    "sg:postcode":"45241",
    "sg:province":"OH",
    "sg:tags":[
        "artist",
        "consultant",
        "galleries",
        "conservation",
        "fine",
        "restoration"
    ],
    "sg:website":"http://www.giclee42.com",
    "wof:name":"Giclee 42",
    "wof:placetype":"venue"
},
  "geometry": {"coordinates":[-84.412706,39.270259],"type":"Point"}
}