{
  "type": "Feature",
  "properties": {
    "addr:full": "1209 Coventry Rd Barberton OH 44203",
    "addr:housenumber": "1209",
    "addr:postcode": "44203",
    "addr:street": "Coventry Rd",
    "iso:country": "US",
    "sg:address": "1209 Coventry Rd",
    "sg:city": "Barberton",
    "sg:classifiers": [
      {
        "category": "Home \u0026 Garden",
        "subcategory": "Building Materials",
        "type": "Retail Goods"
      },
      {
        "category": "Building \u0026 Trades",
        "subcategory": "Construction",
        "type": "Services"
      },
      {
        "category": "Military Area",
        "subcategory": "Armory",
        "type": "Public Place"
      }
    ],
    "sg:phone": "+1 330 753 4555",
    "sg:postcode": "44203",
    "sg:province": "OH",
    "sg:tags": [
      "repair",
      "fence-sales",
      "fence",
      "contractor"
    ],
    "wof:name": "Kustom Fencing",
    "wof:placetype": "venue"
  },
  "geometry": {"coordinates":[-81.58062,41.032873],"type":"Point"}
}
