{
  "type": "Feature",
  "properties": {
    "addr:full": "3750 Schirtzinger Rd Hilliard OH 43026",
    "addr:housenumber": "3750",
    "addr:postcode": "43026",
    "addr:street": "Schirtzinger Rd",
    "iso:country": "US",
    "sg:address": "3750 Schirtzinger Rd",
    "sg:city": "Hilliard",
    "sg:classifiers": [
      {
        "category": "Professional",
        "type": "Services"
      }
    ],
    "sg:phone": "+1 614 771 9564",
    "sg:postcode": "43026",
    "sg:province": "OH",
    "wof:name": "Louis Pemjean",
    "wof:placetype": "venue"
  },
  "geometry": {"coordinates":[-83.106164,40.042405],"type":"Point"}
}
