{
  "type": "Feature",
  "properties": {
    "addr:full": "1294 Frederick St Lancaster OH 43130",
    "addr:housenumber": "1294",
    "addr:postcode": "43130",
    "addr:street": "Frederick St",
    "iso:country": "US",
    "sg:address": "1294 Frederick St",
    "sg:city": "Lancaster",
    "sg:classifiers": [
      {
        "category": "Home \u0026 Garden",
        "subcategory": "Building Materials",
        "type": "Retail Goods"
      }
    ],
    "sg:phone": "+1 740 689 8671",
    "sg:postcode": "43130",
    "sg:province": "OH",
    "sg:tags": [
      "glass",
      "leaded"
    ],
    "wof:name": "Black Jewel Art Glass Stuido",
    "wof:placetype": "venue"
  },
  "geometry": {"coordinates":[-82.575803,39.722228],"type":"Point"}
}
