{
  "type": "Feature",
  "properties": {
    "addr:full": "104 E Midlothian Blvd Youngstown OH 44507",
    "addr:housenumber": "104",
    "addr:postcode": "44507",
    "addr:street": "E Midlothian Blvd",
    "iso:country": "US",
    "sg:address": "104 E Midlothian Blvd",
    "sg:city": "Youngstown",
    "sg:classifiers": [
      {
        "category": "Shopping",
        "subcategory": "Used Merchandise",
        "type": "Retail Goods"
      }
    ],
    "sg:phone": "+1 330 783 1140",
    "sg:postcode": "44507",
    "sg:province": "OH",
    "sg:tags": [
      "antique",
      "collectible"
    ],
    "wof:name": "Antique Alley",
    "wof:placetype": "venue"
  },
  "geometry": {"coordinates":[-80.657517,41.06089],"type":"Point"}
}
