{
  "type": "Feature",
  "properties": {
    "iso:country":"US",
    "sg:address":"1890 Hubbard Rd",
    "sg:city":"Madison",
    "sg:classifiers":[
        {
            "category":"Organizations",
            "subcategory":"Non-profit Organization",
            "type":"Services"
        }
    ],
    "sg:phone":"+1 440 428 3966",
    "sg:postcode":"44057",
    "sg:province":"OH",
    "wof:name":"David G Leach Research Station",
    "wof:placetype":"venue"
},
  "geometry": {"coordinates":[-81.04864000000001,41.822555],"type":"Point"}
}