{
  "type": "Feature",
  "properties": {
    "addr:full": "1375 Union St Troy OH 45373",
    "addr:housenumber": "1375",
    "addr:postcode": "45373",
    "addr:street": "Union St",
    "iso:country": "US",
    "sg:address": "1375 Union St",
    "sg:city": "Troy",
    "sg:classifiers": [
      {
        "category": "Retail",
        "subcategory": "Repair Shop",
        "type": "Services"
      },
      {
        "category": "Manufacturing",
        "subcategory": "Wood Products",
        "type": "Manufacturing \u0026 Wholesale Goods"
      }
    ],
    "sg:phone": "+1 937 335 1581",
    "sg:postcode": "45373",
    "sg:province": "OH",
    "sg:tags": [
      "pallet",
      "recycling",
      "local",
      "skid",
      "trucking"
    ],
    "wof:name": "Miami Valley Wood Recycling",
    "wof:placetype": "venue"
  },
  "geometry": {"coordinates":[-84.20106,40.026978],"type":"Point"}
}
