{
  "type": "Feature",
  "properties": {
    "iso:country":"US",
    "sg:address":"2339 Beaver Valley Rd",
    "sg:city":"Fairborn",
    "sg:classifiers":[
        {
            "category":"Building & Trades",
            "subcategory":"Construction",
            "type":"Services"
        }
    ],
    "sg:phone":"+1 937 878 4102",
    "sg:postcode":"45324",
    "sg:province":"OH",
    "sg:tags":[
        "contractor"
    ],
    "wof:name":"Accurate Drywall",
    "wof:placetype":"venue"
},
  "geometry": {"coordinates":[-84.02192,39.779485],"type":"Point"}
}