{
  "type": "Feature",
  "properties": {
    "addr:full": "1300 Gulf Rd Elyria OH 44035",
    "addr:housenumber": "1300",
    "addr:postcode": "44035",
    "addr:street": "Gulf Rd",
    "iso:country": "US",
    "sg:address": "1300 Gulf Rd",
    "sg:city": "Elyria",
    "sg:classifiers": [
      {
        "category": "Education",
        "subcategory": "School",
        "type": "Public Place"
      }
    ],
    "sg:phone": "+1 440 284 8120",
    "sg:postcode": "44035",
    "sg:province": "OH",
    "wof:name": "Hilltop Academy",
    "wof:placetype": "venue"
  },
  "geometry": {"coordinates":[-82.085264,41.410246],"type":"Point"}
}
