{
  "type": "Feature",
  "properties": {
    "addr:full": "23773 Sprague Rd Columbia Station OH 44028",
    "addr:postcode": "23773;44028",
    "addr:street": "Sprague Rd",
    "iso:country": "US",
    "sg:address": "23773 Sprague Rd",
    "sg:city": "Columbia Station",
    "sg:classifiers": [
      {
        "category": "Food \u0026 Beverages",
        "subcategory": "Specialty",
        "type": "Retail Goods"
      },
      {
        "category": "Restaurant",
        "type": "Food \u0026 Drink"
      }
    ],
    "sg:phone": "+1 440 243 0210",
    "sg:postcode": "44028",
    "sg:province": "OH",
    "sg:tags": [
      "grocery",
      "delicatessen"
    ],
    "wof:name": "Sammy's Deli",
    "wof:placetype": "venue"
  },
  "geometry": {"coordinates":[-81.890381,41.350677],"type":"Point"}
}
