{
  "type": "Feature",
  "properties": {
    "addr:full": "1 Singer Dr Streetsboro OH 44241",
    "addr:housenumber": "1",
    "addr:postcode": "44241",
    "addr:street": "Singer Dr",
    "iso:country": "US",
    "sg:address": "1 Singer Dr",
    "sg:city": "Streetsboro",
    "sg:classifiers": [
      {
        "category": "Wholesale",
        "subcategory": "Metals \u0026 Minerals",
        "type": "Manufacturing \u0026 Wholesale Goods"
      }
    ],
    "sg:phone": "+1 330 562 7200",
    "sg:postcode": "44241",
    "sg:province": "OH",
    "sg:tags": [
      "steel",
      "warehouse"
    ],
    "wof:name": "Singer Steel",
    "wof:placetype": "venue"
  },
  "geometry": {"coordinates":[-81.3376,41.273787],"type":"Point"}
}
