{
  "type": "Feature",
  "properties": {
    "addr:full": "755 Bechtle Ave Springfield OH 45504",
    "addr:housenumber": "755",
    "addr:postcode": "45504",
    "addr:street": "Bechtle Ave",
    "iso:country": "US",
    "sg:address": "755 Bechtle Ave",
    "sg:city": "Springfield",
    "sg:classifiers": [
      {
        "category": "Insurance",
        "subcategory": "Insurance Agent",
        "type": "Services"
      }
    ],
    "sg:phone": "+1 937 323 8773",
    "sg:postcode": "45504",
    "sg:province": "OH",
    "wof:name": "AAA Miami Valley",
    "wof:placetype": "venue"
  },
  "geometry": {"coordinates":[-83.834298,39.934734],"type":"Point"}
}
