{
  "type": "Feature",
  "properties": {
    "addr:full": "509 N Main St Findlay OH 45840",
    "addr:housenumber": "509",
    "addr:postcode": "45840",
    "addr:street": "N Main St",
    "iso:country": "US",
    "sg:address": "509 N Main St",
    "sg:city": "Findlay",
    "sg:classifiers": [
      {
        "category": "Social Services",
        "type": "Services"
      }
    ],
    "sg:phone": "+1 419 424 0311",
    "sg:postcode": "45840",
    "sg:province": "OH",
    "sg:tags": [
      "organization",
      "welfare"
    ],
    "wof:name": "Salvation Army",
    "wof:placetype": "venue"
  },
  "geometry": {"coordinates":[-83.650049,41.047971],"type":"Point"}
}
