{
  "type": "Feature",
  "properties": {
    "iso:country":"US",
    "sg:address":"1151 Stone Dr",
    "sg:city":"Harrison",
    "sg:classifiers":[
        {
            "category":"Shopping",
            "subcategory":"Musical Instruments",
            "type":"Retail Goods"
        }
    ],
    "sg:phone":"+1 513 367 0090",
    "sg:postcode":"45030",
    "sg:province":"OH",
    "wof:name":"Gordon and Brians Music Shoppe",
    "wof:placetype":"venue"
},
  "geometry": {"coordinates":[-84.795816,39.253728],"type":"Point"}
}