{
  "type": "Feature",
  "properties": {
    "iso:country":"US",
    "sg:address":"235 S Garber Dr",
    "sg:city":"Tipp City",
    "sg:classifiers":[
        {
            "category":"Health Services",
            "subcategory":"Doctor",
            "type":"Services"
        }
    ],
    "sg:phone":"+1 937 667 8157",
    "sg:postcode":"45371",
    "sg:province":"OH",
    "wof:name":"Coleman Paula DDS",
    "wof:placetype":"venue"
},
  "geometry": {"coordinates":[-84.187819,39.95885],"type":"Point"}
}