{
  "type": "Feature",
  "properties": {
    "iso:country":"US",
    "sg:address":"3913 Brookside Ln",
    "sg:city":"Huron",
    "sg:classifiers":[
        {
            "category":"Freight",
            "type":"Transportation"
        }
    ],
    "sg:phone":"+1 419 433 9000",
    "sg:postcode":"44839",
    "sg:province":"OH",
    "sg:tags":[
        "local",
        "storage",
        "trucking"
    ],
    "wof:name":"Jabs Co",
    "wof:placetype":"venue"
},
  "geometry": {"coordinates":[-82.64180500000001,41.409448],"type":"Point"}
}