{
  "type": "Feature",
  "properties": {
    "iso:country":"US",
    "sg:address":"199 E Mohawk Dr",
    "sg:city":"Malvern",
    "sg:classifiers":[
        {
            "category":"Building & Trades",
            "subcategory":"Construction",
            "type":"Services"
        }
    ],
    "sg:phone":"+1 330 863 2288",
    "sg:postcode":"44644",
    "sg:province":"OH",
    "sg:tags":[
        "excavation",
        "excavating",
        "contractor"
    ],
    "wof:name":"Ark Excavating & Construction",
    "wof:placetype":"venue"
},
  "geometry": {"coordinates":[-81.182408,40.670318],"type":"Point"}
}