{
  "type": "Feature",
  "properties": {
    "addr:full": "199 E Mohawk Dr Malvern OH 44644",
    "addr:housenumber": "199",
    "addr:postcode": "44644",
    "addr:street": "E Mohawk Dr",
    "iso:country": "US",
    "sg:address": "199 E Mohawk Dr",
    "sg:city": "Malvern",
    "sg:classifiers": [
      {
        "category": "Building \u0026 Trades",
        "subcategory": "Construction",
        "type": "Services"
      }
    ],
    "sg:phone": "+1 330 863 2288",
    "sg:postcode": "44644",
    "sg:province": "OH",
    "sg:tags": [
      "excavation",
      "excavating",
      "contractor"
    ],
    "wof:name": "Ark Excavating \u0026 Construction",
    "wof:placetype": "venue"
  },
  "geometry": {"coordinates":[-81.182408,40.670318],"type":"Point"}
}
