{
  "type": "Feature",
  "properties": {
    "addr:full":"10509 Co Rd 1 Chesapeake OH 45619",
    "addr:housenumber":"10509",
    "addr:postcode":"45619",
    "addr:street":"Co Rd 1",
    "iso:country":"US",
    "sg:address":"10509 Co Rd 1",
    "sg:city":"Chesapeake",
    "sg:classifiers":[
        {
            "category":"Organizations",
            "subcategory":"Religious Organization",
            "type":"Services"
        }
    ],
    "sg:phone":"+1 740 867 8109",
    "sg:postcode":"45619",
    "sg:province":"OH",
    "sg:tags":[
        "church"
    ],
    "wof:name":"Jehovah's Witnesses",
    "wof:placetype":"venue"
},
  "geometry": {"coordinates":[-82.47830500000001,38.423236],"type":"Point"}
}