{
  "type": "Feature",
  "properties": {
    "addr:full": "1800 Cleveland Ave NW Canton OH 44709",
    "addr:housenumber": "1800",
    "addr:postcode": "44709",
    "addr:street": "Cleveland Ave Nw",
    "iso:country": "US",
    "sg:address": "1800 Cleveland Ave NW",
    "sg:city": "Canton",
    "sg:classifiers": [
      {
        "category": "Organizations",
        "subcategory": "Non-profit Organization",
        "type": "Services"
      }
    ],
    "sg:phone": "+1 330 456 7792",
    "sg:postcode": "44709",
    "sg:province": "OH",
    "sg:tags": [
      "social"
    ],
    "wof:name": "Comnty Wellness Center",
    "wof:placetype": "venue"
  },
  "geometry": {"coordinates":[-81.380967,40.81854],"type":"Point"}
}
