{
  "type": "Feature",
  "properties": {
    "iso:country":"US",
    "sg:address":"13579 Elton St SW",
    "sg:city":"Navarre",
    "sg:classifiers":[
        {
            "category":"Manufacturing",
            "subcategory":"Building Materials",
            "type":"Manufacturing & Wholesale Goods"
        }
    ],
    "sg:phone":"+1 330 767 0038",
    "sg:postcode":"44662",
    "sg:province":"OH",
    "sg:tags":[
        "mfg",
        "wood",
        "refrigeration",
        "kitchen",
        "cabinet"
    ],
    "wof:name":"Kitchen Repair Systems",
    "wof:placetype":"venue"
},
  "geometry": {"coordinates":[-81.622031,40.728916],"type":"Point"}
}