{
  "type": "Feature",
  "properties": {
    "addr:full": "13579 Elton St SW Navarre OH 44662",
    "addr:housenumber": "13579",
    "addr:postcode": "44662",
    "addr:street": "Elton St Sw",
    "iso:country": "US",
    "sg:address": "13579 Elton St SW",
    "sg:city": "Navarre",
    "sg:classifiers": [
      {
        "category": "Manufacturing",
        "subcategory": "Building Materials",
        "type": "Manufacturing \u0026 Wholesale Goods"
      }
    ],
    "sg:phone": "+1 330 767 0038",
    "sg:postcode": "44662",
    "sg:province": "OH",
    "sg:tags": [
      "mfg",
      "wood",
      "refrigeration",
      "kitchen",
      "cabinet"
    ],
    "wof:name": "Kitchen Repair Systems",
    "wof:placetype": "venue"
  },
  "geometry": {"coordinates":[-81.622031,40.728916],"type":"Point"}
}
