{
  "type": "Feature",
  "properties": {
    "addr:full": "18 N Main St Englewood OH 45322",
    "addr:housenumber": "18",
    "addr:postcode": "45322",
    "addr:street": "N Main St",
    "iso:country": "US",
    "sg:address": "18 N Main St",
    "sg:city": "Englewood",
    "sg:classifiers": [
      {
        "category": "Insurance",
        "subcategory": "Insurance Agent",
        "type": "Services"
      }
    ],
    "sg:phone": "+1 937 832 0011",
    "sg:postcode": "45322",
    "sg:province": "OH",
    "wof:name": "Jack Landis \u0026 Assoc Insurance",
    "wof:placetype": "venue"
  },
  "geometry": {"coordinates":[-84.302204,39.878039],"type":"Point"}
}
