{
  "type": "Feature",
  "properties": {
    "iso:country":"US",
    "sg:address":"18 N Main St",
    "sg:city":"Englewood",
    "sg:classifiers":[
        {
            "category":"Insurance",
            "subcategory":"Insurance Agent",
            "type":"Services"
        }
    ],
    "sg:phone":"+1 937 832 0011",
    "sg:postcode":"45322",
    "sg:province":"OH",
    "wof:name":"Jack Landis & Assoc Insurance",
    "wof:placetype":"venue"
},
  "geometry": {"coordinates":[-84.302204,39.878039],"type":"Point"}
}