{
  "type": "Feature",
  "properties": {
    "addr:full":"3266 Oberlin Pl Columbus OH 43221",
    "addr:housenumber":"3266",
    "addr:postcode":"43221",
    "addr:street":"Oberlin Pl",
    "iso:country":"US",
    "sg:address":"3266 Oberlin Pl",
    "sg:city":"Columbus",
    "sg:classifiers":[
        {
            "category":"Building & Trades",
            "subcategory":"Construction",
            "type":"Services"
        }
    ],
    "sg:phone":"+1 614 451 1194",
    "sg:postcode":"43221",
    "sg:province":"OH",
    "sg:tags":[
        "concrete",
        "contractor"
    ],
    "wof:name":"Tarini Cement Contracting",
    "wof:placetype":"venue"
},
  "geometry": {"coordinates":[-83.040015,40.024944],"type":"Point"}
}