{
  "type": "Feature",
  "properties": {
    "iso:country":"US",
    "sg:address":"207 N Main St",
    "sg:city":"Findlay",
    "sg:classifiers":[
        {
            "category":"Building & Trades",
            "subcategory":"Plumbing",
            "type":"Services"
        }
    ],
    "sg:phone":"+1 419 422 7313",
    "sg:postcode":"45840",
    "sg:province":"OH",
    "sg:tags":[
        "plumbing",
        "air",
        "heating",
        "conditioning",
        "contractor"
    ],
    "wof:name":"Jacks Heating AC & Plbg",
    "wof:placetype":"venue"
},
  "geometry": {"coordinates":[-83.650108,41.043106],"type":"Point"}
}