{
  "type": "Feature",
  "properties": {
    "iso:country":"US",
    "sg:address":"1460 Wheeler Rd",
    "sg:city":"Zanesville",
    "sg:classifiers":[
        {
            "category":"Organizations",
            "subcategory":"Religious Organization",
            "type":"Services"
        }
    ],
    "sg:phone":"+1 740 453 6598",
    "sg:postcode":"43701",
    "sg:province":"OH",
    "sg:tags":[
        "clergy"
    ],
    "wof:name":"Virginia Martindale",
    "wof:placetype":"venue"
},
  "geometry": {"coordinates":[-81.988356,39.932525],"type":"Point"}
}