{
  "type": "Feature",
  "properties": {
    "addr:full": "1300 Norton Rd Columbus OH 43228",
    "addr:housenumber": "1300",
    "addr:postcode": "43228",
    "addr:street": "Norton Rd",
    "iso:country": "US",
    "sg:address": "1300 Norton Rd",
    "sg:city": "Columbus",
    "sg:classifiers": [
      {
        "category": "Wholesale",
        "subcategory": "Scrap",
        "type": "Manufacturing \u0026 Wholesale Goods"
      }
    ],
    "sg:phone": "+1 614 851 4714",
    "sg:postcode": "43228",
    "sg:province": "OH",
    "sg:tags": [
      "recycling",
      "center"
    ],
    "wof:name": "Royal Paper Stock",
    "wof:placetype": "venue"
  },
  "geometry": {"coordinates":[-83.144092,39.925709],"type":"Point"}
}
