{
  "type": "Feature",
  "properties": {
    "iso:country":"US",
    "sg:address":"2615 Fairfax Ct NW",
    "sg:city":"Canton",
    "sg:classifiers":[
        {
            "category":"Food & Beverages",
            "subcategory":"Groceries & Convenience Stores",
            "type":"Retail Goods"
        }
    ],
    "sg:phone":"+1 330 477 9111",
    "sg:postcode":"44708",
    "sg:province":"OH",
    "wof:name":"Finer Things Images",
    "wof:placetype":"venue"
},
  "geometry": {"coordinates":[-81.43677099999999,40.826716],"type":"Point"}
}