{
  "type": "Feature",
  "properties": {
    "addr:full":"2719 Fulton Dr NW Canton OH 44718",
    "addr:housenumber":"2719",
    "addr:postcode":"44718",
    "addr:street":"Fulton Dr Nw",
    "iso:country":"US",
    "sg:address":"2719 Fulton Dr NW",
    "sg:city":"Canton",
    "sg:classifiers":[
        {
            "category":"Government",
            "subcategory":"Office",
            "type":"Public Place"
        }
    ],
    "sg:phone":"+1 330 580 2380",
    "sg:postcode":"44718",
    "sg:province":"OH",
    "sg:tags":[
        "state",
        "program",
        "health"
    ],
    "wof:name":"Austin-Bailey Health & Wellnes",
    "wof:placetype":"venue"
},
  "geometry": {"coordinates":[-81.402283,40.826777],"type":"Point"}
}