{
  "type": "Feature",
  "properties": {
    "addr:full": "100 S Madriver St Bellefontaine OH 43311",
    "addr:housenumber": "100",
    "addr:postcode": "43311",
    "addr:street": "S Madriver St",
    "iso:country": "US",
    "sg:address": "100 S Madriver St",
    "sg:city": "Bellefontaine",
    "sg:classifiers": [
      {
        "category": "Government",
        "subcategory": "Office",
        "type": "Public Place"
      }
    ],
    "sg:phone": "+1 937 599 7201",
    "sg:postcode": "43311",
    "sg:province": "OH",
    "sg:tags": [
      "general"
    ],
    "wof:name": "Logan County Recorder's Office",
    "wof:placetype": "venue"
  },
  "geometry": {"coordinates":[-83.757837,40.361042],"type":"Point"}
}
