{
  "type": "Feature",
  "properties": {
    "iso:country":"US",
    "sg:address":"100 S Madriver St",
    "sg:city":"Bellefontaine",
    "sg:classifiers":[
        {
            "category":"Government",
            "subcategory":"Office",
            "type":"Public Place"
        }
    ],
    "sg:phone":"+1 937 599 7201",
    "sg:postcode":"43311",
    "sg:province":"OH",
    "sg:tags":[
        "general"
    ],
    "wof:name":"Logan County Recorder's Office",
    "wof:placetype":"venue"
},
  "geometry": {"coordinates":[-83.75783699999999,40.361042],"type":"Point"}
}