{
  "type": "Feature",
  "properties": {
    "addr:full": "595 Circlewood Dr Aurora OH 44202",
    "addr:housenumber": "595",
    "addr:postcode": "44202",
    "addr:street": "Circlewood Dr",
    "iso:country": "US",
    "sg:address": "595 Circlewood Dr",
    "sg:city": "Aurora",
    "sg:classifiers": [
      {
        "category": "Communications",
        "subcategory": "Film \u0026 Video Production",
        "type": "Services"
      }
    ],
    "sg:phone": "+1 330 562 8983",
    "sg:postcode": "44202",
    "sg:province": "OH",
    "sg:tags": [
      "duplication",
      "tape"
    ],
    "wof:name": "Advancement International",
    "wof:placetype": "venue"
  },
  "geometry": {"coordinates":[-81.322763,41.327332],"type":"Point"}
}
