{
  "type": "Feature",
  "properties": {
    "iso:country":"US",
    "sg:address":"595 Circlewood Dr",
    "sg:city":"Aurora",
    "sg:classifiers":[
        {
            "category":"Communications",
            "subcategory":"Film & Video Production",
            "type":"Services"
        }
    ],
    "sg:phone":"+1 330 562 8983",
    "sg:postcode":"44202",
    "sg:province":"OH",
    "sg:tags":[
        "duplication",
        "tape"
    ],
    "wof:name":"Advancement International",
    "wof:placetype":"venue"
},
  "geometry": {"coordinates":[-81.32276299999999,41.327332],"type":"Point"}
}