{
  "type": "Feature",
  "properties": {
    "iso:country":"US",
    "sg:address":"23900 Mercantile Rd",
    "sg:city":"Cleveland",
    "sg:classifiers":[
        {
            "category":"Real Estate",
            "subcategory":"Real Estate Agent",
            "type":"Services"
        }
    ],
    "sg:phone":"+1 216 292 7447",
    "sg:postcode":"44122",
    "sg:province":"OH",
    "wof:name":"Laureno Properties LLC",
    "wof:placetype":"venue"
},
  "geometry": {"coordinates":[-81.505289,41.459983],"type":"Point"}
}