{
  "type": "Feature",
  "properties": {
    "iso:country":"US",
    "sg:address":"7391 Redwood Dr",
    "sg:city":"Hubbard",
    "sg:classifiers":[
        {
            "category":"Building & Trades",
            "subcategory":"Construction",
            "type":"Services"
        }
    ],
    "sg:phone":"+1 330 534 9107",
    "sg:postcode":"44425",
    "sg:province":"OH",
    "sg:tags":[
        "nonresidential"
    ],
    "wof:name":"Di Tommaso & Son Construction",
    "wof:placetype":"venue"
},
  "geometry": {"coordinates":[-80.55364899999999,41.150358],"type":"Point"}
}