{
  "type": "Feature",
  "properties": {
    "iso:country":"US",
    "sg:address":"2707 Paxton Ave",
    "sg:city":"Akron",
    "sg:classifiers":[
        {
            "category":"Building & Trades",
            "subcategory":"Construction",
            "type":"Services"
        }
    ],
    "sg:phone":"+1 330 784 1464",
    "sg:postcode":"44312",
    "sg:province":"OH",
    "sg:tags":[
        "general",
        "contractor"
    ],
    "wof:name":"Shiplett Construction",
    "wof:placetype":"venue"
},
  "geometry": {"coordinates":[-81.43288,41.054921],"type":"Point"}
}