{
  "type": "Feature",
  "properties": {
    "addr:full":"1204 Idaho St Toledo OH 43605",
    "addr:housenumber":"1204",
    "addr:postcode":"43605",
    "addr:street":"Idaho St",
    "iso:country":"US",
    "sg:address":"1204 Idaho St",
    "sg:city":"Toledo",
    "sg:classifiers":[
        {
            "category":"Professional",
            "type":"Services"
        }
    ],
    "sg:phone":"+1 419 698 7689",
    "sg:postcode":"43605",
    "sg:province":"OH",
    "wof:name":"Mrs Popes",
    "wof:placetype":"venue"
},
  "geometry": {"coordinates":[-83.512163,41.638071],"type":"Point"}
}