{
  "type": "Feature",
  "properties": {
    "iso:country":"US",
    "sg:address":"4076 Fisher Rd",
    "sg:city":"Columbus",
    "sg:classifiers":[
        {
            "category":"Wholesale",
            "subcategory":"Painting Supplies",
            "type":"Manufacturing & Wholesale Goods"
        }
    ],
    "sg:phone":"+1 614 351 9328",
    "sg:postcode":"43228",
    "sg:province":"OH",
    "sg:tags":[
        "paint"
    ],
    "wof:name":"Jamestown Powder Coating Inc",
    "wof:placetype":"venue"
},
  "geometry": {"coordinates":[-83.106747,39.968589],"type":"Point"}
}