{
  "type": "Feature",
  "properties": {
    "addr:full": "3050 State Rd Ashtabula OH 44004",
    "addr:housenumber": "3050",
    "addr:postcode": "44004",
    "addr:street": "State Rd",
    "iso:country": "US",
    "sg:address": "3050 State Rd",
    "sg:city": "Ashtabula",
    "sg:classifiers": [
      {
        "category": "Autos \u0026 Motor Vehicles",
        "subcategory": "Auto Supplies",
        "type": "Retail Goods"
      }
    ],
    "sg:phone": "+1 440 993 1311",
    "sg:postcode": "44004",
    "sg:province": "OH",
    "sg:tags": [
      "automobile",
      "parts"
    ],
    "wof:name": "Lake Shore Auto Parts",
    "wof:placetype": "venue"
  },
  "geometry": {"coordinates":[-80.772394,41.878736],"type":"Point"}
}
