{
  "type": "Feature",
  "properties": {
    "addr:full": "9884 Tall Timber Dr Cincinnati OH 45241",
    "addr:housenumber": "9884",
    "addr:postcode": "45241",
    "addr:street": "Tall Timber Dr",
    "iso:country": "US",
    "sg:address": "9884 Tall Timber Dr",
    "sg:city": "Cincinnati",
    "sg:classifiers": [
      {
        "category": "Banks \u0026 Credit Unions",
        "subcategory": "Bank",
        "type": "Services"
      }
    ],
    "sg:phone": "+1 513 563 3005",
    "sg:postcode": "45241",
    "sg:province": "OH",
    "sg:tags": [
      "loan",
      "real estate"
    ],
    "wof:name": "Franklin Mortgage",
    "wof:placetype": "venue"
  },
  "geometry": {"coordinates":[-84.381764,39.306222],"type":"Point"}
}
