{
  "type": "Feature",
  "properties": {
    "addr:full": "505 Briarwood Dr Coldwater OH 45828",
    "addr:housenumber": "505",
    "addr:postcode": "45828",
    "addr:street": "Briarwood Dr",
    "iso:country": "US",
    "sg:address": "505 Briarwood Dr",
    "sg:city": "Coldwater",
    "sg:classifiers": [
      {
        "category": "Farming",
        "subcategory": "Dairy Farm",
        "type": "Manufacturing \u0026 Wholesale Goods"
      }
    ],
    "sg:phone": "+1 419 678 4645",
    "sg:postcode": "45828",
    "sg:province": "OH",
    "wof:name": "Crockett Farms Holsteins",
    "wof:placetype": "venue"
  },
  "geometry": {"coordinates":[-84.64092,40.485786],"type":"Point"}
}
