{
  "type": "Feature",
  "properties": {
    "iso:country":"US",
    "sg:address":"505 Briarwood Dr",
    "sg:city":"Coldwater",
    "sg:classifiers":[
        {
            "category":"Farming",
            "subcategory":"Dairy Farm",
            "type":"Manufacturing & Wholesale Goods"
        }
    ],
    "sg:phone":"+1 419 678 4645",
    "sg:postcode":"45828",
    "sg:province":"OH",
    "wof:name":"Crockett Farms Holsteins",
    "wof:placetype":"venue"
},
  "geometry": {"coordinates":[-84.64091999999999,40.485786],"type":"Point"}
}