{
  "type": "Feature",
  "properties": {
    "addr:full": "7399 State Rd Cleveland OH 44134",
    "addr:housenumber": "7399",
    "addr:postcode": "44134",
    "addr:street": "State Rd",
    "iso:country": "US",
    "sg:address": "7399 State Rd",
    "sg:city": "Cleveland",
    "sg:classifiers": [
      {
        "category": "Professional",
        "subcategory": "Accounting \u0026 Tax Preparation",
        "type": "Services"
      }
    ],
    "sg:phone": "+1 440 842 9577",
    "sg:postcode": "44134",
    "sg:province": "OH",
    "sg:tags": [
      "return",
      "filing"
    ],
    "wof:name": "Fast Cash Express Tax Place",
    "wof:placetype": "venue"
  },
  "geometry": {"coordinates":[-81.716506,41.366506],"type":"Point"}
}
