{
  "type": "Feature",
  "properties": {
    "addr:full": "34394 State Rte 7 Sardis OH 43946",
    "addr:housenumber": "34394",
    "addr:postcode": "43946",
    "addr:street": "State Rte 7",
    "iso:country": "US",
    "sg:address": "34394 State Rte 7",
    "sg:city": "Sardis",
    "sg:classifiers": [
      {
        "category": "Freight",
        "type": "Transportation"
      }
    ],
    "sg:phone": "+1 740 865 3322",
    "sg:postcode": "43946",
    "sg:province": "OH",
    "sg:tags": [
      "dry",
      "bulk",
      "trucking"
    ],
    "wof:name": "M C Tank Transport",
    "wof:placetype": "venue"
  },
  "geometry": {"coordinates":[-80.985758,39.586404],"type":"Point"}
}
