{
  "type": "Feature",
  "properties": {
    "addr:full": "650 Salisbury Rd Columbus OH 43204",
    "addr:housenumber": "650",
    "addr:postcode": "43204",
    "addr:street": "Salisbury Rd",
    "iso:country": "US",
    "sg:address": "650 Salisbury Rd",
    "sg:city": "Columbus",
    "sg:classifiers": [
      {
        "category": "Insurance",
        "subcategory": "Insurance Agent",
        "type": "Services"
      }
    ],
    "sg:phone": "+1 614 274 8916",
    "sg:postcode": "43204",
    "sg:province": "OH",
    "wof:name": "Ward North American Inc",
    "wof:placetype": "venue"
  },
  "geometry": {"coordinates":[-83.079191,39.94161],"type":"Point"}
}
