{
  "type": "Feature",
  "properties": {
    "addr:full": "7601 Spencer Rd Homerville OH 44235",
    "addr:housenumber": "7601",
    "addr:postcode": "44235",
    "addr:street": "Spencer Rd",
    "iso:country": "US",
    "sg:address": "7601 Spencer Rd",
    "sg:city": "Homerville",
    "sg:classifiers": [
      {
        "category": "Building \u0026 Trades",
        "subcategory": "Construction",
        "type": "Services"
      }
    ],
    "sg:phone": "+1 330 648 1070",
    "sg:postcode": "44235",
    "sg:province": "OH",
    "sg:tags": [
      "contractor"
    ],
    "wof:name": "Buddy Gutter Ltd",
    "wof:placetype": "venue"
  },
  "geometry": {"coordinates":[-82.123812,41.06794],"type":"Point"}
}
