{
  "type": "Feature",
  "properties": {
    "addr:full": "106 W Rambo St Danville OH 43014",
    "addr:housenumber": "106",
    "addr:postcode": "43014",
    "addr:street": "W Rambo St",
    "iso:country": "US",
    "sg:address": "106 W Rambo St",
    "sg:city": "Danville",
    "sg:classifiers": [
      {
        "category": "Retail",
        "subcategory": "Car Wash",
        "type": "Services"
      }
    ],
    "sg:phone": "+1 740 599 9955",
    "sg:postcode": "43014",
    "sg:province": "OH",
    "sg:tags": [
      "polishing",
      "washing"
    ],
    "wof:name": "Three Micks Inc",
    "wof:placetype": "venue"
  },
  "geometry": {"coordinates":[-82.262791,40.447787],"type":"Point"}
}
