{
  "type": "Feature",
  "properties": {
    "iso:country":"US",
    "sg:address":"4676 W 130th St",
    "sg:city":"Cleveland",
    "sg:classifiers":[
        {
            "category":"Organizations",
            "subcategory":"Religious Organization",
            "type":"Services"
        }
    ],
    "sg:phone":"+1 216 941 6710",
    "sg:postcode":"44135",
    "sg:province":"OH",
    "sg:tags":[
        "church"
    ],
    "wof:name":"Grace Chapel",
    "wof:placetype":"venue"
},
  "geometry": {"coordinates":[-81.780206,41.427384],"type":"Point"}
}