{
  "type": "Feature",
  "properties": {
    "addr:full":"15037 Pearl Rd Cleveland OH 44136",
    "addr:housenumber":"15037",
    "addr:postcode":"44136",
    "addr:street":"Pearl Rd",
    "iso:country":"US",
    "sg:address":"15037 Pearl Rd",
    "sg:city":"Cleveland",
    "sg:classifiers":[
        {
            "category":"Restaurant",
            "type":"Food & Drink"
        }
    ],
    "sg:phone":"+1 440 238 5010",
    "sg:postcode":"44136",
    "sg:province":"OH",
    "sg:tags":[
        "pizza"
    ],
    "wof:name":"Georgios Oven Fresh Pizza Co",
    "wof:placetype":"venue"
},
  "geometry": {"coordinates":[-81.835148,41.30791],"type":"Point"}
}