{
  "type": "Feature",
  "properties": {
    "addr:full": "2010 E 5th St Dayton OH 45403",
    "addr:housenumber": "2010",
    "addr:postcode": "45403",
    "addr:street": "E 5Th St",
    "iso:country": "US",
    "sg:address": "2010 E 5th St",
    "sg:city": "Dayton",
    "sg:classifiers": [
      {
        "category": "Professional",
        "subcategory": "Testing Lab",
        "type": "Services"
      }
    ],
    "sg:phone": "+1 937 255 5508",
    "sg:postcode": "45403",
    "sg:province": "OH",
    "sg:tags": [
      "laboratory"
    ],
    "wof:name": "US Dept of the Air Force",
    "wof:placetype": "venue"
  },
  "geometry": {"coordinates":[-84.167125,39.759512],"type":"Point"}
}
