{
  "type": "Feature",
  "properties": {
    "addr:full":"1163 Hayden Ave Cleveland OH 44110",
    "addr:housenumber":"1163",
    "addr:postcode":"44110",
    "addr:street":"Hayden Ave",
    "iso:country":"US",
    "sg:address":"1163 Hayden Ave",
    "sg:city":"Cleveland",
    "sg:classifiers":[
        {
            "category":"Personal",
            "subcategory":"Beauty Salon",
            "type":"Services"
        }
    ],
    "sg:phone":"+1 216 451 6207",
    "sg:postcode":"44110",
    "sg:province":"OH",
    "wof:name":"Carlass Hair & Nail Salon",
    "wof:placetype":"venue"
},
  "geometry": {"coordinates":[-81.586569,41.547334],"type":"Point"}
}