{
  "type": "Feature",
  "properties": {
    "addr:full": "1436 S Cleveland Massillon Rd Copley OH 44321",
    "addr:housenumber": "1436",
    "addr:postcode": "44321",
    "addr:street": "S Cleveland Massillon Rd",
    "iso:country": "US",
    "sg:address": "1436 S Cleveland Massillon Rd",
    "sg:city": "Copley",
    "sg:classifiers": [
      {
        "category": "Retail",
        "subcategory": "Repair Shop",
        "type": "Services"
      }
    ],
    "sg:phone": "+1 330 666 3312",
    "sg:postcode": "44321",
    "sg:province": "OH",
    "sg:tags": [
      "lock",
      "locksmith"
    ],
    "wof:name": "Jim's Locksmith",
    "wof:placetype": "venue"
  },
  "geometry": {"coordinates":[-81.644695,41.097691],"type":"Point"}
}
