{
  "type": "Feature",
  "properties": {
    "addr:full":"18330 Twp Rd 22 Mt Blanchard OH 45867",
    "addr:housenumber":"22",
    "addr:postcode":"18330;45867",
    "addr:street":"Twp Rd;Mt Blanchard",
    "iso:country":"US",
    "sg:address":"18330 Twp Rd 22",
    "sg:city":"Mt Blanchard",
    "sg:classifiers":[
        {
            "category":"Wholesale",
            "subcategory":"Farm Supplies",
            "type":"Manufacturing & Wholesale Goods"
        }
    ],
    "sg:phone":"+1 419 694 2700",
    "sg:postcode":"45867",
    "sg:province":"OH",
    "sg:tags":[
        "buyer",
        "livestock"
    ],
    "wof:name":"Ibp Inc",
    "wof:placetype":"venue"
},
  "geometry": {"coordinates":[-83.561627,40.901427],"type":"Point"}
}