{
  "type": "Feature",
  "properties": {
    "addr:full":"4676 Erie Ave SW Navarre OH 44662",
    "addr:housenumber":"4676",
    "addr:postcode":"44662",
    "addr:street":"Erie Ave Sw",
    "iso:country":"US",
    "sg:address":"4676 Erie Ave SW",
    "sg:city":"Navarre",
    "sg:classifiers":[
        {
            "category":"Professional",
            "subcategory":"Management & Consulting",
            "type":"Services"
        }
    ],
    "sg:phone":"+1 330 879 5396",
    "sg:postcode":"44662",
    "sg:province":"OH",
    "sg:tags":[
        "fuel"
    ],
    "wof:name":"Massillon Management",
    "wof:placetype":"venue"
},
  "geometry": {"coordinates":[-81.51828500000001,40.735762],"type":"Point"}
}