{
  "type": "Feature",
  "properties": {
    "addr:full": "851 N Canfield Niles Rd Youngstown OH 44515",
    "addr:housenumber": "851",
    "addr:postcode": "44515",
    "addr:street": "N Canfield Niles Rd",
    "iso:country": "US",
    "sg:address": "851 N Canfield Niles Rd",
    "sg:city": "Youngstown",
    "sg:classifiers": [
      {
        "category": "Coffee \u0026 Tea",
        "type": "Food \u0026 Drink"
      }
    ],
    "sg:phone": "+1 330 544 1431",
    "sg:postcode": "44515",
    "sg:province": "OH",
    "sg:tags": [
      "espresso",
      "restaurant"
    ],
    "sg:website": "http://www.starbuckscoffee.com",
    "wof:name": "Starbucks Coffee",
    "wof:placetype": "venue"
  },
  "geometry": {"coordinates":[-80.768173,41.121658],"type":"Point"}
}
