{
  "type": "Feature",
  "properties": {
    "addr:full": "2818 Fisher Rd Columbus OH 43204",
    "addr:housenumber": "2818",
    "addr:postcode": "43204",
    "addr:street": "Fisher Rd",
    "iso:country": "US",
    "sg:address": "2818 Fisher Rd",
    "sg:city": "Columbus",
    "sg:classifiers": [
      {
        "category": "Wholesale",
        "subcategory": "Metals \u0026 Minerals",
        "type": "Manufacturing \u0026 Wholesale Goods"
      }
    ],
    "sg:phone": "+1 614 272 7644",
    "sg:postcode": "43204",
    "sg:province": "OH",
    "sg:tags": [
      "specialty"
    ],
    "wof:name": "Regal Technology Corp",
    "wof:placetype": "venue"
  },
  "geometry": {"coordinates":[-83.079397,39.972328],"type":"Point"}
}
