{
  "type": "Feature",
  "properties": {
    "iso:country":"US",
    "sg:address":"2818 Fisher Rd",
    "sg:city":"Columbus",
    "sg:classifiers":[
        {
            "category":"Wholesale",
            "subcategory":"Metals & Minerals",
            "type":"Manufacturing & Wholesale Goods"
        }
    ],
    "sg:phone":"+1 614 272 7644",
    "sg:postcode":"43204",
    "sg:province":"OH",
    "sg:tags":[
        "specialty"
    ],
    "wof:name":"Regal Technology Corp",
    "wof:placetype":"venue"
},
  "geometry": {"coordinates":[-83.079397,39.972328],"type":"Point"}
}