{
  "type": "Feature",
  "properties": {
    "addr:full":"28867 Chagrin Blvd Cleveland OH 44122",
    "addr:housenumber":"28867",
    "addr:postcode":"44122",
    "addr:street":"Chagrin Blvd",
    "iso:country":"US",
    "sg:address":"28867 Chagrin Blvd",
    "sg:city":"Cleveland",
    "sg:classifiers":[
        {
            "category":"Real Estate",
            "subcategory":"Real Estate Agent",
            "type":"Services"
        }
    ],
    "sg:phone":"+1 216 378 1524",
    "sg:postcode":"44122",
    "sg:province":"OH",
    "sg:website":"www.realtyone.com",
    "wof:name":"Realty One",
    "wof:placetype":"venue"
},
  "geometry": {"coordinates":[-81.47478099999999,41.462429],"type":"Point"}
}