{
  "type": "Feature",
  "properties": {
    "iso:country":"US",
    "sg:address":"7670 1st Pl",
    "sg:city":"Cleveland",
    "sg:classifiers":[
        {
            "category":"Real Estate",
            "subcategory":"Real Estate Operator",
            "type":"Services"
        }
    ],
    "sg:phone":"+1 440 439 9090",
    "sg:postcode":"44146",
    "sg:province":"OH",
    "sg:tags":[
        "building",
        "parks"
    ],
    "wof:name":"Access Point",
    "wof:placetype":"venue"
},
  "geometry": {"coordinates":[-81.511267,41.375525],"type":"Point"}
}