{
  "type": "Feature",
  "properties": {
    "addr:full":"3131 S 3rd St Ironton OH 45638",
    "addr:housenumber":"3131",
    "addr:postcode":"45638",
    "addr:street":"S 3Rd St",
    "iso:country":"US",
    "sg:address":"3131 S 3rd St",
    "sg:city":"Ironton",
    "sg:classifiers":[
        {
            "category":"Autos & Motor Vehicles",
            "subcategory":"Auto Supplies",
            "type":"Retail Goods"
        }
    ],
    "sg:phone":"+1 740 533 2666",
    "sg:postcode":"45638",
    "sg:province":"OH",
    "sg:tags":[
        "tire"
    ],
    "wof:name":"Discount Tire Svc",
    "wof:placetype":"venue"
},
  "geometry": {"coordinates":[-82.66222500000001,38.507478],"type":"Point"}
}