{
  "type": "Feature",
  "properties": {
    "addr:full": "4456 Bellville North Rd Bellville OH 44813",
    "addr:housenumber": "4456",
    "addr:postcode": "44813",
    "addr:street": "Bellville North Rd",
    "iso:country": "US",
    "sg:address": "4456 Bellville North Rd",
    "sg:city": "Bellville",
    "sg:classifiers": [
      {
        "category": "Manufacturing",
        "subcategory": "Wood Products",
        "type": "Manufacturing \u0026 Wholesale Goods"
      }
    ],
    "sg:phone": "+1 419 886 2151",
    "sg:postcode": "44813",
    "sg:province": "OH",
    "sg:tags": [
      "container",
      "mfg"
    ],
    "wof:name": "James E Hope",
    "wof:placetype": "venue"
  },
  "geometry": {"coordinates":[-82.512339,40.631987],"type":"Point"}
}
