{
  "type": "Feature",
  "properties": {
    "iso:country":"US",
    "sg:address":"4456 Bellville North Rd",
    "sg:city":"Bellville",
    "sg:classifiers":[
        {
            "category":"Manufacturing",
            "subcategory":"Wood Products",
            "type":"Manufacturing & Wholesale Goods"
        }
    ],
    "sg:phone":"+1 419 886 2151",
    "sg:postcode":"44813",
    "sg:province":"OH",
    "sg:tags":[
        "container",
        "mfg"
    ],
    "wof:name":"James E Hope",
    "wof:placetype":"venue"
},
  "geometry": {"coordinates":[-82.512339,40.631987],"type":"Point"}
}