{
  "type": "Feature",
  "properties": {
    "addr:full": "7315 E Main St Reynoldsburg OH 43068",
    "addr:housenumber": "7315",
    "addr:postcode": "43068",
    "addr:street": "E Main St",
    "iso:country": "US",
    "sg:address": "7315 E Main St",
    "sg:city": "Reynoldsburg",
    "sg:classifiers": [
      {
        "category": "Insurance",
        "subcategory": "Insurance Agent",
        "type": "Services"
      }
    ],
    "sg:phone": "+1 614 863 5433",
    "sg:postcode": "43068",
    "sg:province": "OH",
    "wof:name": "Thomas Parobek Insurance",
    "wof:placetype": "venue"
  },
  "geometry": {"coordinates":[-82.802369,39.955265],"type":"Point"}
}
