{
  "type": "Feature",
  "properties": {
    "addr:full": "137 Ruth Ann Dr Lucasville OH 45648",
    "addr:housenumber": "137",
    "addr:postcode": "45648",
    "addr:street": "Ruth Ann Dr",
    "iso:country": "US",
    "sg:address": "137 Ruth Ann Dr",
    "sg:city": "Lucasville",
    "sg:classifiers": [
      {
        "category": "Organizations",
        "subcategory": "Religious Organization",
        "type": "Services"
      }
    ],
    "sg:phone": "+1 740 259 2176",
    "sg:postcode": "45648",
    "sg:province": "OH",
    "sg:tags": [
      "clergy"
    ],
    "wof:name": "David Cottrell",
    "wof:placetype": "venue"
  },
  "geometry": {"coordinates":[-82.972243,38.88773],"type":"Point"}
}
