{
  "type": "Feature",
  "properties": {
    "iso:country":"US",
    "sg:address":"137 Ruth Ann Dr",
    "sg:city":"Lucasville",
    "sg:classifiers":[
        {
            "category":"Organizations",
            "subcategory":"Religious Organization",
            "type":"Services"
        }
    ],
    "sg:phone":"+1 740 259 2176",
    "sg:postcode":"45648",
    "sg:province":"OH",
    "sg:tags":[
        "clergy"
    ],
    "wof:name":"David Cottrell",
    "wof:placetype":"venue"
},
  "geometry": {"coordinates":[-82.97224300000001,38.88773],"type":"Point"}
}