{
  "type": "Feature",
  "properties": {
    "addr:full":"1430 Collins Rd NW Lancaster OH 43130",
    "addr:housenumber":"1430",
    "addr:postcode":"43130",
    "addr:street":"Collins Rd Nw",
    "iso:country":"US",
    "sg:address":"1430 Collins Rd NW",
    "sg:city":"Lancaster",
    "sg:classifiers":[
        {
            "category":"Real Estate",
            "subcategory":"Developer",
            "type":"Services"
        }
    ],
    "sg:phone":"+1 740 653 8822",
    "sg:postcode":"43130",
    "sg:province":"OH",
    "wof:name":"Windsor Companies",
    "wof:placetype":"venue"
},
  "geometry": {"coordinates":[-82.657405,39.747364],"type":"Point"}
}