{
  "type": "Feature",
  "properties": {
    "addr:full": "2602 N Main St Findlay OH 45840",
    "addr:housenumber": "2602",
    "addr:postcode": "45840",
    "addr:street": "N Main St",
    "iso:country": "US",
    "sg:address": "2602 N Main St",
    "sg:city": "Findlay",
    "sg:classifiers": [
      {
        "category": "Personal",
        "subcategory": "Barber",
        "type": "Services"
      }
    ],
    "sg:phone": "+1 419 423 8622",
    "sg:postcode": "45840",
    "sg:province": "OH",
    "wof:name": "Mike's Barber Shop",
    "wof:placetype": "venue"
  },
  "geometry": {"coordinates":[-83.649945,41.069717],"type":"Point"}
}
