{
  "type": "Feature",
  "properties": {
    "addr:full": "10265 Spartan Dr Cincinnati OH 45215",
    "addr:housenumber": "10265",
    "addr:postcode": "45215",
    "addr:street": "Spartan Dr",
    "iso:country": "US",
    "sg:address": "10265 Spartan Dr",
    "sg:city": "Cincinnati",
    "sg:classifiers": [
      {
        "category": "Wholesale",
        "subcategory": "Stationery",
        "type": "Manufacturing \u0026 Wholesale Goods"
      },
      {
        "category": "Manufacturing",
        "subcategory": "Tools \u0026 Machinery",
        "type": "Manufacturing \u0026 Wholesale Goods"
      }
    ],
    "sg:phone": "+1 513 241 8484",
    "sg:postcode": "45215",
    "sg:province": "OH",
    "sg:tags": [
      "ind",
      "paper",
      "general"
    ],
    "wof:name": "Glennon Group",
    "wof:placetype": "venue"
  },
  "geometry": {"coordinates":[-84.44981,39.254704],"type":"Point"}
}
