{
  "type": "Feature",
  "properties": {
    "iso:country":"US",
    "sg:address":"9440 Amish Pike",
    "sg:city":"Plain City",
    "sg:phone":"+1 614 873 5589",
    "sg:postcode":"43064",
    "sg:province":"OH",
    "sg:tags":[
        "farm",
        "corn",
        "soybean"
    ],
    "wof:name":"Marvin Kurtz",
    "wof:placetype":"venue"
},
  "geometry": {"coordinates":[-83.338757,40.076814],"type":"Point"}
}