{
  "type": "Feature",
  "properties": {
    "addr:full": "7603 1st Pl Cleveland OH 44146",
    "addr:housenumber": "7603",
    "addr:postcode": "44146",
    "addr:street": "1St Pl",
    "iso:country": "US",
    "sg:address": "7603 1st Pl",
    "sg:city": "Cleveland",
    "sg:classifiers": [
      {
        "category": "Manufacturing",
        "subcategory": "Apparel",
        "type": "Manufacturing \u0026 Wholesale Goods"
      }
    ],
    "sg:phone": "+1 440 232 1555",
    "sg:postcode": "44146",
    "sg:province": "OH",
    "sg:tags": [
      "drapery",
      "contractor"
    ],
    "wof:name": "Herman \u0026 Herman Draperies",
    "wof:placetype": "venue"
  },
  "geometry": {"coordinates":[-81.511056,41.376343],"type":"Point"}
}
