{
  "type": "Feature",
  "properties": {
    "iso:country":"US",
    "sg:address":"1250 Washington Rd",
    "sg:city":"Norwalk",
    "sg:classifiers":[
        {
            "category":"Manufacturing",
            "subcategory":"Lumber",
            "type":"Manufacturing & Wholesale Goods"
        }
    ],
    "sg:phone":"+1 419 668 4218",
    "sg:postcode":"44857",
    "sg:province":"OH",
    "sg:tags":[
        "logging"
    ],
    "wof:name":"Jim Sitterly Logging",
    "wof:placetype":"venue"
},
  "geometry": {"coordinates":[-82.636054,41.249873],"type":"Point"}
}