{
  "type": "Feature",
  "properties": {
    "iso:country":"US",
    "sg:address":"1311 Harrisburg Rd",
    "sg:city":"Alliance",
    "sg:classifiers":[
        {
            "category":"Building & Trades",
            "subcategory":"Construction",
            "type":"Services"
        }
    ],
    "sg:phone":"+1 330 823 0996",
    "sg:postcode":"44601",
    "sg:province":"OH",
    "sg:tags":[
        "painter"
    ],
    "wof:name":"Stanley Painting",
    "wof:placetype":"venue"
},
  "geometry": {"coordinates":[-81.12397300000001,40.923522],"type":"Point"}
}