{
  "type": "Feature",
  "properties": {
    "iso:country":"US",
    "sg:address":"6160 Seeds Rd",
    "sg:city":"Grove City",
    "sg:classifiers":[
        {
            "category":"Wholesale",
            "subcategory":"Electrical",
            "type":"Manufacturing & Wholesale Goods"
        }
    ],
    "sg:phone":"+1 614 539 3222",
    "sg:postcode":"43123",
    "sg:province":"OH",
    "sg:tags":[
        "equipment",
        "ultrasonic",
        "supply"
    ],
    "sg:website":"www.tooltex.com",
    "wof:name":"Tool Tex Inc",
    "wof:placetype":"venue"
},
  "geometry": {"coordinates":[-83.085413,39.83897],"type":"Point"}
}