{
  "type": "Feature",
  "properties": {
    "addr:full": "664 Sugar Ln Elyria OH 44035",
    "addr:housenumber": "664",
    "addr:postcode": "44035",
    "addr:street": "Sugar Ln",
    "iso:country": "US",
    "sg:address": "664 Sugar Ln",
    "sg:city": "Elyria",
    "sg:classifiers": [
      {
        "category": "Manufacturing",
        "subcategory": "Glass \u0026 Minerals",
        "type": "Manufacturing \u0026 Wholesale Goods"
      }
    ],
    "sg:phone": "+1 440 365 0253",
    "sg:postcode": "44035",
    "sg:province": "OH",
    "sg:tags": [
      "product",
      "mfg"
    ],
    "wof:name": "J \u0026 N Glass",
    "wof:placetype": "venue"
  },
  "geometry": {"coordinates":[-82.072912,41.36203],"type":"Point"}
}
