{
  "type": "Feature",
  "properties": {
    "iso:country":"US",
    "sg:address":"664 Sugar Ln",
    "sg:city":"Elyria",
    "sg:classifiers":[
        {
            "category":"Manufacturing",
            "subcategory":"Glass & Minerals",
            "type":"Manufacturing & Wholesale Goods"
        }
    ],
    "sg:phone":"+1 440 365 0253",
    "sg:postcode":"44035",
    "sg:province":"OH",
    "sg:tags":[
        "product",
        "mfg"
    ],
    "wof:name":"J & N Glass",
    "wof:placetype":"venue"
},
  "geometry": {"coordinates":[-82.072912,41.36203],"type":"Point"}
}