{
  "type": "Feature",
  "properties": {
    "addr:full": "3031 W Streetsboro Rd Richfield OH 44286",
    "addr:housenumber": "3031",
    "addr:postcode": "44286",
    "addr:street": "W Streetsboro Rd",
    "iso:country": "US",
    "sg:address": "3031 W Streetsboro Rd",
    "sg:city": "Richfield",
    "sg:classifiers": [
      {
        "category": "Home \u0026 Garden",
        "subcategory": "Garden Supply",
        "type": "Retail Goods"
      }
    ],
    "sg:phone": "+1 330 659 9700",
    "sg:postcode": "44286",
    "sg:province": "OH",
    "sg:tags": [
      "equipment",
      "lawn",
      "mower"
    ],
    "wof:name": "Emmet Equipment Co Inc",
    "wof:placetype": "venue"
  },
  "geometry": {"coordinates":[-81.606859,41.243876],"type":"Point"}
}
