{
  "type": "Feature",
  "properties": {
    "addr:full":"4532 Maize Rd Columbus OH 43224",
    "addr:housenumber":"4532",
    "addr:postcode":"43224",
    "addr:street":"Maize Rd",
    "iso:country":"US",
    "sg:address":"4532 Maize Rd",
    "sg:city":"Columbus",
    "sg:classifiers":[
        {
            "category":"Manufacturing",
            "subcategory":"Rubber & Plastics",
            "type":"Manufacturing & Wholesale Goods"
        }
    ],
    "sg:phone":"+1 614 263 1087",
    "sg:postcode":"43224",
    "sg:province":"OH",
    "sg:tags":[
        "mfg"
    ],
    "wof:name":"KMC Enterprises",
    "wof:placetype":"venue"
},
  "geometry": {"coordinates":[-82.98728800000001,40.06116],"type":"Point"}
}