{
  "type": "Feature",
  "properties": {
    "addr:full":"510 Sand Broad Ct Westerville OH 43081",
    "addr:housenumber":"510",
    "addr:postcode":"43081",
    "addr:street":"Sand Broad Ct",
    "iso:country":"US",
    "sg:address":"510 Sand Broad Ct",
    "sg:city":"Westerville",
    "sg:classifiers":[
        {
            "category":"Building & Trades",
            "subcategory":"Construction",
            "type":"Services"
        }
    ],
    "sg:phone":"+1 614 844 5329",
    "sg:postcode":"43081",
    "sg:province":"OH",
    "sg:tags":[
        "resurfacing",
        "laying",
        "refinishing",
        "floor"
    ],
    "wof:name":"Floor Cleaning Specialists Inc",
    "wof:placetype":"venue"
},
  "geometry": {"coordinates":[-83.004366,40.134713],"type":"Point"}
}