{
  "type": "Feature",
  "properties": {
    "addr:full": "1027 Lander Rd Cleveland OH 44143",
    "addr:housenumber": "1027",
    "addr:postcode": "44143",
    "addr:street": "Lander Rd",
    "iso:country": "US",
    "sg:address": "1027 Lander Rd",
    "sg:city": "Cleveland",
    "sg:classifiers": [
      {
        "category": "Shopping",
        "subcategory": "Clothing, Apparel, \u0026 Fashions",
        "type": "Retail Goods"
      }
    ],
    "sg:phone": "+1 440 442 1903",
    "sg:postcode": "44143",
    "sg:province": "OH",
    "sg:tags": [
      "tailor"
    ],
    "wof:name": "Transform Tailoring",
    "wof:placetype": "venue"
  },
  "geometry": {"coordinates":[-81.463156,41.536982],"type":"Point"}
}
