{
  "type": "Feature",
  "properties": {
    "addr:full": "6061 Harrison Ave Cincinnati OH 45247",
    "addr:housenumber": "6061",
    "addr:postcode": "45247",
    "addr:street": "Harrison Ave",
    "iso:country": "US",
    "sg:address": "6061 Harrison Ave",
    "sg:city": "Cincinnati",
    "sg:classifiers": [
      {
        "category": "Food \u0026 Beverages",
        "subcategory": "Groceries \u0026 Convenience Stores",
        "type": "Retail Goods"
      }
    ],
    "sg:phone": "+1 513 721 9333",
    "sg:postcode": "45247",
    "sg:province": "OH",
    "wof:name": "Mount Auburn Corner Market",
    "wof:placetype": "venue"
  },
  "geometry": {"coordinates":[-84.647971,39.181876],"type":"Point"}
}
