{
  "type": "Feature",
  "properties": {
    "iso:country":"US",
    "sg:address":"6061 Harrison Ave",
    "sg:city":"Cincinnati",
    "sg:classifiers":[
        {
            "category":"Food & Beverages",
            "subcategory":"Groceries & Convenience Stores",
            "type":"Retail Goods"
        }
    ],
    "sg:phone":"+1 513 721 9333",
    "sg:postcode":"45247",
    "sg:province":"OH",
    "wof:name":"Mount Auburn Corner Market",
    "wof:placetype":"venue"
},
  "geometry": {"coordinates":[-84.647971,39.181876],"type":"Point"}
}