{
  "type": "Feature",
  "properties": {
    "addr:full": "5901 Dixie Hwy Fairfield OH 45014",
    "addr:housenumber": "5901",
    "addr:postcode": "45014",
    "addr:street": "Dixie Hwy",
    "iso:country": "US",
    "sg:address": "5901 Dixie Hwy",
    "sg:city": "Fairfield",
    "sg:classifiers": [
      {
        "category": "Wholesale",
        "subcategory": "Dairy",
        "type": "Manufacturing \u0026 Wholesale Goods"
      }
    ],
    "sg:phone": "+1 513 874 5579",
    "sg:postcode": "45014",
    "sg:province": "OH",
    "sg:tags": [
      "frozen",
      "dessert",
      "ice",
      "cream"
    ],
    "wof:name": "Velvet Ice Cream Co",
    "wof:placetype": "venue"
  },
  "geometry": {"coordinates":[-84.514842,39.328775],"type":"Point"}
}
