{
  "type": "Feature",
  "properties": {
    "iso:country":"US",
    "sg:address":"5901 Dixie Hwy",
    "sg:city":"Fairfield",
    "sg:classifiers":[
        {
            "category":"Wholesale",
            "subcategory":"Dairy",
            "type":"Manufacturing & Wholesale Goods"
        }
    ],
    "sg:phone":"+1 513 874 5579",
    "sg:postcode":"45014",
    "sg:province":"OH",
    "sg:tags":[
        "frozen",
        "dessert",
        "ice",
        "cream"
    ],
    "wof:name":"Velvet Ice Cream Co",
    "wof:placetype":"venue"
},
  "geometry": {"coordinates":[-84.514842,39.328775],"type":"Point"}
}