{
  "type": "Feature",
  "properties": {
    "addr:full":"3686 Shangri la Ave E Ontario OH 44903",
    "addr:housenumber":"3686",
    "addr:postcode":"44903",
    "addr:street":"Shangri La Ave E",
    "iso:country":"US",
    "sg:address":"3686 Shangri la Ave E",
    "sg:city":"Ontario",
    "sg:classifiers":[
        {
            "category":"Building & Trades",
            "subcategory":"Plumbing",
            "type":"Services"
        }
    ],
    "sg:phone":"+1 419 528 1782",
    "sg:postcode":"44903",
    "sg:province":"OH",
    "sg:tags":[
        "system",
        "contractor",
        "air conditioning"
    ],
    "wof:name":"Daves Heating & Cooling",
    "wof:placetype":"venue"
},
  "geometry": {"coordinates":[-82.650111,40.755979],"type":"Point"}
}