{
  "type": "Feature",
  "properties": {
    "iso:country":"US",
    "sg:address":"50 Public Sq",
    "sg:city":"Cleveland",
    "sg:classifiers":[
        {
            "category":"Professional",
            "subcategory":"Lawyer & Legal Services",
            "type":"Services"
        }
    ],
    "sg:phone":"+1 216 241 0300",
    "sg:postcode":"44113",
    "sg:province":"OH",
    "sg:tags":[
        "attorney"
    ],
    "wof:name":"Dubyak Goldense & Wolf",
    "wof:placetype":"venue"
},
  "geometry": {"coordinates":[-81.69426199999999,41.500327],"type":"Point"}
}