{
  "type": "Feature",
  "properties": {
    "iso:country":"US",
    "sg:address":"6795 Wonder Way",
    "sg:city":"Tipp City",
    "sg:classifiers":[
        {
            "category":"Manufacturing",
            "subcategory":"Printing",
            "type":"Manufacturing & Wholesale Goods"
        }
    ],
    "sg:phone":"+1 937 846 0862",
    "sg:postcode":"45371",
    "sg:province":"OH",
    "sg:tags":[
        "commercial"
    ],
    "wof:name":"State of Art",
    "wof:placetype":"venue"
},
  "geometry": {"coordinates":[-84.090628,39.905404],"type":"Point"}
}