{
  "type": "Feature",
  "properties": {
    "addr:full": "6795 Wonder Way Tipp City OH 45371",
    "addr:housenumber": "6795",
    "addr:postcode": "45371",
    "addr:street": "Wonder Way",
    "iso:country": "US",
    "sg:address": "6795 Wonder Way",
    "sg:city": "Tipp City",
    "sg:classifiers": [
      {
        "category": "Manufacturing",
        "subcategory": "Printing",
        "type": "Manufacturing \u0026 Wholesale Goods"
      }
    ],
    "sg:phone": "+1 937 846 0862",
    "sg:postcode": "45371",
    "sg:province": "OH",
    "sg:tags": [
      "commercial"
    ],
    "wof:name": "State of Art",
    "wof:placetype": "venue"
  },
  "geometry": {"coordinates":[-84.090628,39.905404],"type":"Point"}
}
