{
  "type": "Feature",
  "properties": {
    "addr:full":"900 Pearl St Martins Ferry OH 43935",
    "addr:housenumber":"900",
    "addr:postcode":"43935",
    "addr:street":"Pearl St Martins Ferry",
    "iso:country":"US",
    "sg:address":"900 Pearl St",
    "sg:city":"Martins Ferry",
    "sg:classifiers":[
        {
            "category":"Wholesale",
            "subcategory":"Non-durable Goods",
            "type":"Manufacturing & Wholesale Goods"
        }
    ],
    "sg:phone":"+1 740 633 1810",
    "sg:postcode":"43935",
    "sg:province":"OH",
    "wof:name":"Larrys Party Center",
    "wof:placetype":"venue"
},
  "geometry": {"coordinates":[-80.732574,40.089766],"type":"Point"}
}