{
  "type": "Feature",
  "properties": {
    "addr:full": "5580 Co Rd 24 Payne OH 45880",
    "addr:housenumber": "5580;24",
    "addr:postcode": "45880",
    "addr:street": "Co Rd",
    "iso:country": "US",
    "sg:address": "5580 Co Rd 24",
    "sg:city": "Payne",
    "sg:classifiers": [
      {
        "category": "Farming",
        "subcategory": "Farm",
        "type": "Manufacturing \u0026 Wholesale Goods"
      }
    ],
    "sg:phone": "+1 419 263 3421",
    "sg:postcode": "45880",
    "sg:province": "OH",
    "sg:tags": [
      "crop",
      "general"
    ],
    "wof:name": "Troy E Greulach",
    "wof:placetype": "venue"
  },
  "geometry": {"coordinates":[-84.715327,41.004112],"type":"Point"}
}
