{
  "type": "Feature",
  "properties": {
    "addr:full":"828 Hall Ave Dayton OH 45404",
    "addr:housenumber":"828",
    "addr:postcode":"45404",
    "addr:street":"Hall Ave",
    "iso:country":"US",
    "sg:address":"828 Hall Ave",
    "sg:city":"Dayton",
    "sg:classifiers":[
        {
            "category":"Manufacturing",
            "subcategory":"Metals",
            "type":"Manufacturing & Wholesale Goods"
        }
    ],
    "sg:phone":"+1 937 222 7077",
    "sg:postcode":"45404",
    "sg:province":"OH",
    "sg:tags":[
        "plating",
        "formed",
        "chromium",
        "product",
        "for"
    ],
    "wof:name":"Custom Chrome Plating Inc",
    "wof:placetype":"venue"
},
  "geometry": {"coordinates":[-84.185886,39.783843],"type":"Point"}
}