{
  "type": "Feature",
  "properties": {
    "iso:country":"US",
    "sg:address":"8021 E Market St",
    "sg:city":"Warren",
    "sg:classifiers":[
        {
            "category":"Banks & Credit Unions",
            "subcategory":"Bank",
            "type":"Services"
        }
    ],
    "sg:phone":"+1 330 609 8666",
    "sg:postcode":"44484",
    "sg:province":"OH",
    "sg:tags":[
        "loan"
    ],
    "wof:name":"Tammac Corp",
    "wof:placetype":"venue"
},
  "geometry": {"coordinates":[-80.747861,41.238618],"type":"Point"}
}