{
  "type": "Feature",
  "properties": {
    "addr:full": "299 E Livingston Ave Columbus OH 43215",
    "addr:housenumber": "299",
    "addr:postcode": "43215",
    "addr:street": "E Livingston Ave",
    "iso:country": "US",
    "sg:address": "299 E Livingston Ave",
    "sg:city": "Columbus",
    "sg:classifiers": [
      {
        "category": "Banks \u0026 Credit Unions",
        "subcategory": "Bank",
        "type": "Services"
      }
    ],
    "sg:phone": "+1 614 775 0556",
    "sg:postcode": "43215",
    "sg:province": "OH",
    "sg:tags": [
      "mortgage"
    ],
    "wof:name": "Df Heritage",
    "wof:placetype": "venue"
  },
  "geometry": {"coordinates":[-82.989166,39.95239],"type":"Point"}
}
