{
  "type": "Feature",
  "properties": {
    "iso:country":"US",
    "sg:address":"5243 Fairgreen Dr",
    "sg:city":"Toledo",
    "sg:classifiers":[
        {
            "category":"Retail",
            "subcategory":"Animal Services",
            "type":"Services"
        }
    ],
    "sg:phone":"+1 419 474 1581",
    "sg:postcode":"43613",
    "sg:province":"OH",
    "wof:name":"Key To Sea Poodle Club",
    "wof:placetype":"venue"
},
  "geometry": {"coordinates":[-83.621437,41.707868],"type":"Point"}
}