{
  "type": "Feature",
  "properties": {
    "addr:full": "306 Betty Ln Port Clinton OH 43452",
    "addr:housenumber": "306",
    "addr:postcode": "43452",
    "addr:street": "Betty Ln",
    "iso:country": "US",
    "sg:address": "306 Betty Ln",
    "sg:city": "Port Clinton",
    "sg:classifiers": [
      {
        "category": "Real Estate",
        "subcategory": "Real Estate Agent",
        "type": "Services"
      }
    ],
    "sg:phone": "+1 419 734 3442",
    "sg:postcode": "43452",
    "sg:province": "OH",
    "wof:name": "Appraisal Concepts Inc",
    "wof:placetype": "venue"
  },
  "geometry": {"coordinates":[-82.911034,41.509334],"type":"Point"}
}
