{
  "type": "Feature",
  "properties": {
    "addr:full":"103 N Main St Youngstown OH 44514",
    "addr:housenumber":"103",
    "addr:postcode":"44514",
    "addr:street":"N Main St",
    "iso:country":"US",
    "sg:address":"103 N Main St",
    "sg:city":"Youngstown",
    "sg:classifiers":[
        {
            "category":"Shopping",
            "subcategory":"Catalog Store",
            "type":"Retail Goods"
        }
    ],
    "sg:phone":"+1 330 757 3334",
    "sg:postcode":"44514",
    "sg:province":"OH",
    "sg:tags":[
        "mail",
        "parts",
        "order"
    ],
    "wof:name":"Mad 4wd",
    "wof:placetype":"venue"
},
  "geometry": {"coordinates":[-80.615644,41.028065],"type":"Point"}
}