{
  "type": "Feature",
  "properties": {
    "addr:full":"2258 Innis Rd Columbus OH 43224",
    "addr:housenumber":"2258",
    "addr:postcode":"43224",
    "addr:street":"Innis Rd",
    "iso:country":"US",
    "sg:address":"2258 Innis Rd",
    "sg:city":"Columbus",
    "sg:classifiers":[
        {
            "category":"Retail",
            "subcategory":"Auto Repair",
            "type":"Services"
        }
    ],
    "sg:phone":"+1 614 471 4774",
    "sg:postcode":"43224",
    "sg:province":"OH",
    "sg:tags":[
        "repairing",
        "automobile"
    ],
    "wof:name":"C & D Automotive Repair",
    "wof:placetype":"venue"
},
  "geometry": {"coordinates":[-82.953085,40.037256],"type":"Point"}
}