{
  "type": "Feature",
  "properties": {
    "iso:country":"US",
    "sg:address":"1051 Mill Rd",
    "sg:city":"Bellville",
    "sg:classifiers":[
        {
            "category":"Retail",
            "subcategory":"Auto Repair",
            "type":"Services"
        }
    ],
    "sg:phone":"+1 419 886 6000",
    "sg:postcode":"44813",
    "sg:province":"OH",
    "sg:tags":[
        "repairing",
        "automobile"
    ],
    "wof:name":"Bellville Auto Svc Ctr",
    "wof:placetype":"venue"
},
  "geometry": {"coordinates":[-82.473311,40.609491],"type":"Point"}
}