{
  "type": "Feature",
  "properties": {
    "iso:country":"US",
    "sg:address":"4460 Bascule Bridge Dr",
    "sg:city":"Dayton",
    "sg:classifiers":[
        {
            "category":"Autos & Motor Vehicles",
            "subcategory":"Auto Supplies",
            "type":"Retail Goods"
        }
    ],
    "sg:phone":"+1 937 232 8119",
    "sg:postcode":"45440",
    "sg:province":"OH",
    "wof:name":"Auto Trendz",
    "wof:placetype":"venue"
},
  "geometry": {"coordinates":[-84.101058,39.691185],"type":"Point"}
}