{
  "type": "Feature",
  "properties": {
    "addr:full": "4460 Bascule Bridge Dr Dayton OH 45440",
    "addr:postcode": "4460;45440",
    "addr:street": "Bascule Bridge Dr",
    "iso:country": "US",
    "sg:address": "4460 Bascule Bridge Dr",
    "sg:city": "Dayton",
    "sg:classifiers": [
      {
        "category": "Autos \u0026 Motor Vehicles",
        "subcategory": "Auto Supplies",
        "type": "Retail Goods"
      }
    ],
    "sg:phone": "+1 937 232 8119",
    "sg:postcode": "45440",
    "sg:province": "OH",
    "wof:name": "Auto Trendz",
    "wof:placetype": "venue"
  },
  "geometry": {"coordinates":[-84.101058,39.691185],"type":"Point"}
}
