{
  "type": "Feature",
  "properties": {
    "addr:full":"4900 Midway Mall Elyria OH 44035",
    "addr:housenumber":"4900",
    "addr:postcode":"44035",
    "addr:street":"Midway Mall",
    "iso:country":"US",
    "sg:address":"4900 Midway Mall",
    "sg:city":"Elyria",
    "sg:classifiers":[
        {
            "category":"Professional",
            "subcategory":"Accounting & Tax Preparation",
            "type":"Services"
        }
    ],
    "sg:phone":"+1 440 324 5626",
    "sg:postcode":"44035",
    "sg:province":"OH",
    "sg:tags":[
        "return",
        "filing"
    ],
    "wof:name":"H & R Block Tax Svc",
    "wof:placetype":"venue"
},
  "geometry": {"coordinates":[-82.11374499999999,41.39876],"type":"Point"}
}