{
  "type": "Feature",
  "properties": {
    "addr:full":"2720 Towne Dr Beavercreek OH 45431",
    "addr:housenumber":"2720",
    "addr:postcode":"45431",
    "addr:street":"Towne Dr",
    "iso:country":"US",
    "sg:address":"2720 Towne Dr",
    "sg:city":"Beavercreek",
    "sg:classifiers":[
        {
            "category":"Home & Garden",
            "subcategory":"Home Furnishings",
            "type":"Retail Goods"
        }
    ],
    "sg:phone":"+1 937 431 5260",
    "sg:postcode":"45431",
    "sg:province":"OH",
    "sg:tags":[
        "housewares"
    ],
    "wof:name":"Bed Bath & Beyond",
    "wof:placetype":"venue"
},
  "geometry": {"coordinates":[-84.05040700000001,39.768457],"type":"Point"}
}