{
  "type": "Feature",
  "properties": {
    "addr:full": "3443 Edwards Rd Cincinnati OH 45208",
    "addr:housenumber": "3443",
    "addr:postcode": "45208",
    "addr:street": "Edwards Rd",
    "iso:country": "US",
    "sg:address": "3443 Edwards Rd",
    "sg:city": "Cincinnati",
    "sg:classifiers": [
      {
        "category": "Personal",
        "subcategory": "Beauty Salon",
        "type": "Services"
      }
    ],
    "sg:phone": "+1 513 871 2999",
    "sg:postcode": "45208",
    "sg:province": "OH",
    "wof:name": "Richards Hair \u0026 Skin Care",
    "wof:placetype": "venue"
  },
  "geometry": {"coordinates":[-84.443481,39.138671],"type":"Point"}
}
