{
  "type": "Feature",
  "properties": {
    "iso:country":"US",
    "sg:address":"3443 Edwards Rd",
    "sg:city":"Cincinnati",
    "sg:classifiers":[
        {
            "category":"Personal",
            "subcategory":"Beauty Salon",
            "type":"Services"
        }
    ],
    "sg:phone":"+1 513 871 2999",
    "sg:postcode":"45208",
    "sg:province":"OH",
    "wof:name":"Richards Hair & Skin Care",
    "wof:placetype":"venue"
},
  "geometry": {"coordinates":[-84.44348100000001,39.138671],"type":"Point"}
}