{
  "type": "Feature",
  "properties": {
    "iso:country":"US",
    "sg:address":"405 Niles Cortland Rd SE",
    "sg:city":"Warren",
    "sg:classifiers":[
        {
            "category":"Health Services",
            "subcategory":"Doctor",
            "type":"Services"
        }
    ],
    "sg:phone":"+1 330 372 2121",
    "sg:postcode":"44484",
    "sg:province":"OH",
    "sg:tags":[
        "physician",
        "surgeon"
    ],
    "wof:name":"Richard L Weitzel Jr MD",
    "wof:placetype":"venue"
},
  "geometry": {"coordinates":[-80.74042799999999,41.234363],"type":"Point"}
}