{
  "type": "Feature",
  "properties": {
    "iso:country":"US",
    "sg:address":"878 Austin Ave",
    "sg:city":"Akron",
    "sg:classifiers":[
        {
            "category":"Professional",
            "subcategory":"Management & Consulting",
            "type":"Services"
        }
    ],
    "sg:phone":"+1 330 773 6678",
    "sg:postcode":"44306",
    "sg:province":"OH",
    "sg:tags":[
        "construction"
    ],
    "wof:name":"C & D Excavating & Constr",
    "wof:placetype":"venue"
},
  "geometry": {"coordinates":[-81.49521799999999,41.045105],"type":"Point"}
}