{
  "type": "Feature",
  "properties": {
    "addr:full": "878 Austin Ave Akron OH 44306",
    "addr:housenumber": "878",
    "addr:postcode": "44306",
    "addr:street": "Austin Ave",
    "iso:country": "US",
    "sg:address": "878 Austin Ave",
    "sg:city": "Akron",
    "sg:classifiers": [
      {
        "category": "Professional",
        "subcategory": "Management \u0026 Consulting",
        "type": "Services"
      }
    ],
    "sg:phone": "+1 330 773 6678",
    "sg:postcode": "44306",
    "sg:province": "OH",
    "sg:tags": [
      "construction"
    ],
    "wof:name": "C \u0026 D Excavating \u0026 Constr",
    "wof:placetype": "venue"
  },
  "geometry": {"coordinates":[-81.495218,41.045105],"type":"Point"}
}
