{
  "type": "Feature",
  "properties": {
    "iso:country":"US",
    "sg:address":"113 Karl Brown Way",
    "sg:city":"Loveland",
    "sg:classifiers":[
        {
            "category":"Freight",
            "type":"Transportation"
        }
    ],
    "sg:phone":"+1 513 683 2233",
    "sg:postcode":"45140",
    "sg:province":"OH",
    "sg:tags":[
        "warehouse",
        "facility"
    ],
    "wof:name":"Bon Furniture Galleries",
    "wof:placetype":"venue"
},
  "geometry": {"coordinates":[-84.259224,39.26795],"type":"Point"}
}