{
  "type": "Feature",
  "properties": {
    "addr:full":"12301 Bennington Ave Cleveland OH 44135",
    "addr:housenumber":"12301",
    "addr:postcode":"44135",
    "addr:street":"Bennington Ave",
    "iso:country":"US",
    "sg:address":"12301 Bennington Ave",
    "sg:city":"Cleveland",
    "sg:classifiers":[
        {
            "category":"Manufacturing",
            "subcategory":"Printing",
            "type":"Manufacturing & Wholesale Goods"
        }
    ],
    "sg:phone":"+1 216 941 0800",
    "sg:postcode":"44135",
    "sg:province":"OH",
    "sg:tags":[
        "commercial",
        "mfg"
    ],
    "wof:name":"William Exline Inc",
    "wof:placetype":"venue"
},
  "geometry": {"coordinates":[-81.77373299999999,41.426649],"type":"Point"}
}