{
  "type": "Feature",
  "properties": {
    "addr:full": "6800 S Marginal Rd Cleveland OH 44103",
    "addr:housenumber": "6800",
    "addr:postcode": "44103",
    "addr:street": "S Marginal Rd",
    "iso:country": "US",
    "sg:address": "6800 S Marginal Rd",
    "sg:city": "Cleveland",
    "sg:classifiers": [
      {
        "category": "Utilities",
        "subcategory": "Electric",
        "type": "Services"
      }
    ],
    "sg:phone": "+1 216 432 6330",
    "sg:postcode": "44103",
    "sg:province": "OH",
    "wof:name": "Firstenergy",
    "wof:placetype": "venue"
  },
  "geometry": {"coordinates":[-81.651701,41.529171],"type":"Point"}
}
