{
  "type": "Feature",
  "properties": {
    "iso:country":"US",
    "sg:address":"8265 Winton Rd",
    "sg:city":"Cincinnati",
    "sg:classifiers":[
        {
            "category":"Organizations",
            "subcategory":"Religious Organization",
            "type":"Services"
        }
    ],
    "sg:phone":"+1 513 931 6100",
    "sg:postcode":"45231",
    "sg:province":"OH",
    "wof:name":"Faith Lutheran Church",
    "wof:placetype":"venue"
},
  "geometry": {"coordinates":[-84.518348,39.21669],"type":"Point"}
}