{
  "type": "Feature",
  "properties": {
    "addr:full": "5647 Buckeye Rd Georgetown OH 45121",
    "addr:housenumber": "5647",
    "addr:postcode": "45121",
    "addr:street": "Buckeye Rd",
    "iso:country": "US",
    "sg:address": "5647 Buckeye Rd",
    "sg:city": "Georgetown",
    "sg:classifiers": [
      {
        "category": "Building \u0026 Trades",
        "subcategory": "Construction",
        "type": "Services"
      }
    ],
    "sg:phone": "+1 937 375 4213",
    "sg:postcode": "45121",
    "sg:province": "OH",
    "sg:tags": [
      "house"
    ],
    "wof:name": "Brian Costa",
    "wof:placetype": "venue"
  },
  "geometry": {"coordinates":[-84.039498,38.795319],"type":"Point"}
}
