{
  "type": "Feature",
  "properties": {
    "iso:country":"US",
    "sg:address":"24371 Lorain Ave",
    "sg:city":"North Olmsted",
    "sg:classifiers":[
        {
            "category":"Real Estate",
            "subcategory":"Real Estate Agent",
            "type":"Services"
        }
    ],
    "sg:phone":"+1 440 552 6639",
    "sg:postcode":"44070",
    "sg:province":"OH",
    "sg:tags":[
        "management"
    ],
    "wof:name":"Dewolf Enterprises",
    "wof:placetype":"venue"
},
  "geometry": {"coordinates":[-81.87830700000001,41.441766],"type":"Point"}
}