{
  "type": "Feature",
  "properties": {
    "addr:full": "10475 Eaton Pike New Lebanon OH 45345",
    "addr:housenumber": "10475",
    "addr:postcode": "45345",
    "addr:street": "Eaton Pike",
    "iso:country": "US",
    "sg:address": "10475 Eaton Pike",
    "sg:city": "New Lebanon",
    "sg:classifiers": [
      {
        "category": "Restaurant",
        "type": "Food \u0026 Drink"
      }
    ],
    "sg:phone": "+1 937 687 3758",
    "sg:postcode": "45345",
    "sg:province": "OH",
    "wof:name": "Willows",
    "wof:placetype": "venue"
  },
  "geometry": {"coordinates":[-84.375888,39.745781],"type":"Point"}
}
