{
  "type": "Feature",
  "properties": {
    "iso:country":"US",
    "sg:address":"10475 Eaton Pike",
    "sg:city":"New Lebanon",
    "sg:classifiers":[
        {
            "category":"Restaurant",
            "type":"Food & Drink"
        }
    ],
    "sg:phone":"+1 937 687 3758",
    "sg:postcode":"45345",
    "sg:province":"OH",
    "wof:name":"Willows",
    "wof:placetype":"venue"
},
  "geometry": {"coordinates":[-84.375888,39.745781],"type":"Point"}
}