{
  "type": "Feature",
  "properties": {
    "addr:full": "3381 Waterloo Rd Mogadore OH 44260",
    "addr:housenumber": "3381",
    "addr:postcode": "44260",
    "addr:street": "Waterloo Rd",
    "iso:country": "US",
    "sg:address": "3381 Waterloo Rd",
    "sg:city": "Mogadore",
    "sg:classifiers": [
      {
        "category": "Freight",
        "type": "Transportation"
      }
    ],
    "sg:phone": "+1 330 628 9175",
    "sg:postcode": "44260",
    "sg:province": "OH",
    "sg:tags": [
      "hauling",
      "trucking"
    ],
    "wof:name": "Kungle Trucking Co",
    "wof:placetype": "venue"
  },
  "geometry": {"coordinates":[-81.269817,41.033339],"type":"Point"}
}
