{
  "type": "Feature",
  "properties": {
    "addr:full":"3111 Serfass Rd Clinton OH 44216",
    "addr:housenumber":"3111",
    "addr:postcode":"44216",
    "addr:street":"Serfass Rd",
    "iso:country":"US",
    "sg:address":"3111 Serfass Rd",
    "sg:city":"Clinton",
    "sg:classifiers":[
        {
            "category":"Wholesale",
            "subcategory":"Stationery",
            "type":"Manufacturing & Wholesale Goods"
        },
        {
            "category":"Shopping",
            "subcategory":"Computers & Home Electronics",
            "type":"Retail Goods"
        }
    ],
    "sg:phone":"+1 330 882 2253",
    "sg:postcode":"44216",
    "sg:province":"OH",
    "sg:tags":[
        "parts",
        "supply"
    ],
    "wof:name":"Clinton Computer Sales Co",
    "wof:placetype":"venue"
},
  "geometry": {"coordinates":[-81.633044,40.943174],"type":"Point"}
}