{
  "type": "Feature",
  "properties": {
    "addr:full":"20 Mount Vernon Ave Mt Vernon OH 43050",
    "addr:housenumber":"20",
    "addr:postcode":"43050",
    "addr:street":"Mount Vernon Ave",
    "iso:country":"US",
    "sg:address":"20 Mount Vernon Ave",
    "sg:city":"Mt Vernon",
    "sg:classifiers":[
        {
            "category":"Social Services",
            "subcategory":"Child Care",
            "type":"Services"
        }
    ],
    "sg:phone":"+1 740 397 3454",
    "sg:postcode":"43050",
    "sg:province":"OH",
    "sg:tags":[
        "kindergarten",
        "academic",
        "school"
    ],
    "wof:name":"KNOX County Head Start",
    "wof:placetype":"venue"
},
  "geometry": {"coordinates":[-82.483149,40.384651],"type":"Point"}
}