{
  "type": "Feature",
  "properties": {
    "addr:full": "3255 S High St Columbus OH 43207",
    "addr:housenumber": "3255",
    "addr:postcode": "43207",
    "addr:street": "S High St",
    "iso:country": "US",
    "sg:address": "3255 S High St",
    "sg:city": "Columbus",
    "sg:classifiers": [
      {
        "category": "Wholesale",
        "subcategory": "Auto Parts",
        "type": "Manufacturing \u0026 Wholesale Goods"
      }
    ],
    "sg:phone": "+1 614 497 1900",
    "sg:postcode": "43207",
    "sg:province": "OH",
    "sg:tags": [
      "supply"
    ],
    "wof:name": "NAPA Auto Parts",
    "wof:placetype": "venue"
  },
  "geometry": {"coordinates":[-82.995399,39.900382],"type":"Point"}
}
