{
  "type": "Feature",
  "properties": {
    "iso:country":"US",
    "sg:address":"3255 S High St",
    "sg:city":"Columbus",
    "sg:classifiers":[
        {
            "category":"Wholesale",
            "subcategory":"Auto Parts",
            "type":"Manufacturing & Wholesale Goods"
        }
    ],
    "sg:phone":"+1 614 497 1900",
    "sg:postcode":"43207",
    "sg:province":"OH",
    "sg:tags":[
        "supply"
    ],
    "wof:name":"NAPA Auto Parts",
    "wof:placetype":"venue"
},
  "geometry": {"coordinates":[-82.99539900000001,39.900382],"type":"Point"}
}