{
  "type": "Feature",
  "properties": {
    "iso:country":"US",
    "sg:address":"351 Beall Ave",
    "sg:city":"Wooster",
    "sg:classifiers":[
        {
            "category":"Autos & Motor Vehicles",
            "subcategory":"Auto Supplies",
            "type":"Retail Goods"
        }
    ],
    "sg:phone":"+1 330 262 2007",
    "sg:postcode":"44691",
    "sg:province":"OH",
    "sg:tags":[
        "automobile",
        "parts"
    ],
    "sg:website":"www.autozone.com",
    "wof:name":"Autozone",
    "wof:placetype":"venue"
},
  "geometry": {"coordinates":[-81.93438399999999,40.802738],"type":"Point"}
}