{
  "type": "Feature",
  "properties": {
    "addr:full": "7892 Eaglecrest Ct Mason OH 45040",
    "addr:housenumber": "7892",
    "addr:postcode": "45040",
    "addr:street": "Eaglecrest Ct",
    "iso:country": "US",
    "sg:address": "7892 Eaglecrest Ct",
    "sg:city": "Mason",
    "sg:classifiers": [
      {
        "category": "Building \u0026 Trades",
        "subcategory": "Construction",
        "type": "Services"
      }
    ],
    "sg:phone": "+1 513 336 7590",
    "sg:postcode": "45040",
    "sg:province": "OH",
    "sg:tags": [
      "repairing",
      "remodeling",
      "contractor"
    ],
    "wof:name": "Residential Revival",
    "wof:placetype": "venue"
  },
  "geometry": {"coordinates":[-84.294171,39.323595],"type":"Point"}
}
