{
  "type": "Feature",
  "properties": {
    "addr:full": "8725 Swigert Rd Loveland OH 45140",
    "addr:postcode": "8725;45140",
    "addr:street": "Swigert Rd",
    "iso:country": "US",
    "sg:address": "8725 Swigert Rd",
    "sg:city": "Loveland",
    "sg:phone": "+1 513 899 2447",
    "sg:postcode": "45140",
    "sg:province": "OH",
    "sg:tags": [
      "farm",
      "grain",
      "cash"
    ],
    "wof:name": "Todd Nahhrup",
    "wof:placetype": "venue"
  },
  "geometry": {"coordinates":[-84.180263,39.302455],"type":"Point"}
}
