{
  "type": "Feature",
  "properties": {
    "addr:full": "9900 E Harbor Rd Lakeside Marblhd OH 43440",
    "addr:housenumber": "9900 e",
    "addr:postcode": "43440",
    "addr:street": "Harbor Rd",
    "iso:country": "US",
    "sg:address": "9900 E Harbor Rd",
    "sg:city": "Lakeside Marblhd",
    "sg:classifiers": [
      {
        "category": "Retail",
        "subcategory": "Auto Repair",
        "type": "Services"
      }
    ],
    "sg:phone": "+1 419 798 4695",
    "sg:postcode": "43440",
    "sg:province": "OH",
    "sg:tags": [
      "body",
      "automobile",
      "painting"
    ],
    "wof:name": "Don's Body Shop",
    "wof:placetype": "venue"
  },
  "geometry": {"coordinates":[-82.741877,41.539325],"type":"Point"}
}
