{
  "type": "Feature",
  "properties": {
    "addr:full": "7984 State St Garrettsville OH 44231",
    "addr:housenumber": "7984",
    "addr:postcode": "44231",
    "addr:street": "State St",
    "iso:country": "US",
    "sg:address": "7984 State St",
    "sg:city": "Garrettsville",
    "sg:classifiers": [
      {
        "category": "Building \u0026 Trades",
        "subcategory": "Construction",
        "type": "Services"
      }
    ],
    "sg:phone": "+1 330 527 0026",
    "sg:postcode": "44231",
    "sg:province": "OH",
    "sg:tags": [
      "house"
    ],
    "wof:name": "Alcraft III",
    "wof:placetype": "venue"
  },
  "geometry": {"coordinates":[-81.107022,41.290225],"type":"Point"}
}
