{
  "type": "Feature",
  "properties": {
    "addr:full":"820 Freeway Dr S Columbus OH 43229",
    "addr:housenumber":"820",
    "addr:postcode":"43229",
    "addr:street":"Freeway Dr S",
    "iso:country":"US",
    "sg:address":"820 Freeway Dr S",
    "sg:city":"Columbus",
    "sg:classifiers":[
        {
            "category":"Wholesale",
            "subcategory":"Meat",
            "type":"Manufacturing & Wholesale Goods"
        }
    ],
    "sg:phone":"+1 614 847 0510",
    "sg:postcode":"43229",
    "sg:province":"OH",
    "sg:tags":[
        "columbus",
        "for",
        "manufactured",
        "sales",
        "p",
        "processed"
    ],
    "wof:name":"I B P",
    "wof:placetype":"venue"
},
  "geometry": {"coordinates":[-82.996285,40.065926],"type":"Point"}
}