{
  "type": "Feature",
  "properties": {
    "iso:country":"US",
    "sg:address":"223 Ardmore Blvd",
    "sg:city":"Painesville",
    "sg:classifiers":[
        {
            "category":"Retail",
            "subcategory":"Animal Services",
            "type":"Services"
        }
    ],
    "sg:phone":"+1 440 796 9594",
    "sg:postcode":"44077",
    "sg:province":"OH",
    "sg:tags":[
        "pet",
        "training"
    ],
    "wof:name":"Best Friends Dog Training",
    "wof:placetype":"venue"
},
  "geometry": {"coordinates":[-81.252933,41.713082],"type":"Point"}
}