{
  "type": "Feature",
  "properties": {
    "addr:full": "1350 Englebeck Rd Lakeside Marblehead OH 43440",
    "addr:housenumber": "1350",
    "addr:postcode": "43440",
    "addr:street": "Englebeck Rd",
    "iso:country": "US",
    "sg:address": "1350 Englebeck Rd",
    "sg:city": "Lakeside Marblehead",
    "sg:classifiers": [
      {
        "category": "Wholesale",
        "subcategory": "Durable Goods \u0026 Equipment",
        "type": "Manufacturing \u0026 Wholesale Goods"
      }
    ],
    "sg:phone": "+1 419 734 5716",
    "sg:postcode": "43440",
    "sg:province": "OH",
    "wof:name": "Tietjen Antiques",
    "wof:placetype": "venue"
  },
  "geometry": {"coordinates":[-82.781251,41.519922],"type":"Point"}
}
