{
  "type": "Feature",
  "properties": {
    "iso:country":"US",
    "sg:address":"1350 Englebeck Rd",
    "sg:city":"Lakeside Marblehead",
    "sg:classifiers":[
        {
            "category":"Wholesale",
            "subcategory":"Durable Goods & Equipment",
            "type":"Manufacturing & Wholesale Goods"
        }
    ],
    "sg:phone":"+1 419 734 5716",
    "sg:postcode":"43440",
    "sg:province":"OH",
    "wof:name":"Tietjen Antiques",
    "wof:placetype":"venue"
},
  "geometry": {"coordinates":[-82.781251,41.519922],"type":"Point"}
}