{
  "type": "Feature",
  "properties": {
    "addr:full": "404 Steven Blvd Cleveland OH 44143",
    "addr:housenumber": "404",
    "addr:postcode": "44143",
    "addr:street": "Steven Blvd",
    "iso:country": "US",
    "sg:address": "404 Steven Blvd",
    "sg:city": "Cleveland",
    "sg:classifiers": [
      {
        "category": "Shopping",
        "subcategory": "Hobbies, Toys, \u0026 Games",
        "type": "Retail Goods"
      }
    ],
    "sg:phone": "+1 440 449 1458",
    "sg:postcode": "44143",
    "sg:province": "OH",
    "sg:tags": [
      "craft"
    ],
    "wof:name": "Ashley's Creations",
    "wof:placetype": "venue"
  },
  "geometry": {"coordinates":[-81.503544,41.553767],"type":"Point"}
}
