{
  "type": "Feature",
  "properties": {
    "addr:full": "7001 Kinsman Rd Cleveland OH 44104",
    "addr:housenumber": "7001",
    "addr:postcode": "44104",
    "addr:street": "Kinsman Rd",
    "iso:country": "US",
    "sg:address": "7001 Kinsman Rd",
    "sg:city": "Cleveland",
    "sg:classifiers": [
      {
        "category": "Restaurant",
        "type": "Food \u0026 Drink"
      }
    ],
    "sg:phone": "+1 216 441 5566",
    "sg:postcode": "44104",
    "sg:province": "OH",
    "sg:tags": [
      "delicatessen"
    ],
    "wof:name": "New York Deli",
    "wof:placetype": "venue"
  },
  "geometry": {"coordinates":[-81.639016,41.480032],"type":"Point"}
}
