{
  "type": "Feature",
  "properties": {
    "iso:country":"US",
    "sg:address":"7001 Kinsman Rd",
    "sg:city":"Cleveland",
    "sg:classifiers":[
        {
            "category":"Restaurant",
            "type":"Food & Drink"
        }
    ],
    "sg:phone":"+1 216 441 5566",
    "sg:postcode":"44104",
    "sg:province":"OH",
    "sg:tags":[
        "delicatessen"
    ],
    "wof:name":"New York Deli",
    "wof:placetype":"venue"
},
  "geometry": {"coordinates":[-81.639016,41.480032],"type":"Point"}
}