{
  "type": "Feature",
  "properties": {
    "addr:full":"213 N Defiance St Archbold OH 43502",
    "addr:housenumber":"213",
    "addr:postcode":"43502",
    "addr:street":"N Defiance St",
    "iso:country":"US",
    "sg:address":"213 N Defiance St",
    "sg:city":"Archbold",
    "sg:classifiers":[
        {
            "category":"Restaurant",
            "type":"Food & Drink"
        }
    ],
    "sg:phone":"+1 419 445 7376",
    "sg:postcode":"43502",
    "sg:province":"OH",
    "sg:tags":[
        "eating"
    ],
    "wof:name":"Archbold Pizza Oven Inc",
    "wof:placetype":"venue"
},
  "geometry": {"coordinates":[-84.306421,41.523434],"type":"Point"}
}