{
  "type": "Feature",
  "properties": {
    "addr:full": "1 Brittain Rd Akron OH 44305",
    "addr:housenumber": "1",
    "addr:postcode": "44305",
    "addr:street": "Brittain Rd",
    "iso:country": "US",
    "sg:address": "1 Brittain Rd",
    "sg:city": "Akron",
    "sg:classifiers": [
      {
        "category": "Autos \u0026 Motor Vehicles",
        "subcategory": "Auto Supplies",
        "type": "Retail Goods"
      }
    ],
    "sg:phone": "+1 330 733 5247",
    "sg:postcode": "44305",
    "sg:province": "OH",
    "sg:tags": [
      "automobile",
      "cap",
      "hub"
    ],
    "wof:name": "Hubcap Shop",
    "wof:placetype": "venue"
  },
  "geometry": {"coordinates":[-81.466659,41.062624],"type":"Point"}
}
