{
  "type": "Feature",
  "properties": {
    "iso:country":"US",
    "sg:address":"1 Brittain Rd",
    "sg:city":"Akron",
    "sg:classifiers":[
        {
            "category":"Autos & Motor Vehicles",
            "subcategory":"Auto Supplies",
            "type":"Retail Goods"
        }
    ],
    "sg:phone":"+1 330 733 5247",
    "sg:postcode":"44305",
    "sg:province":"OH",
    "sg:tags":[
        "automobile",
        "cap",
        "hub"
    ],
    "wof:name":"Hubcap Shop",
    "wof:placetype":"venue"
},
  "geometry": {"coordinates":[-81.46665900000001,41.062624],"type":"Point"}
}