{
  "type": "Feature",
  "properties": {
    "addr:full":"3459 S High St Columbus OH 43207",
    "addr:housenumber":"3459",
    "addr:postcode":"43207",
    "addr:street":"S High St",
    "iso:country":"US",
    "sg:address":"3459 S High St",
    "sg:city":"Columbus",
    "sg:classifiers":[
        {
            "category":"Shopping",
            "subcategory":"Hobbies, Toys, & Games",
            "type":"Retail Goods"
        },
        {
            "category":"Banks & Credit Unions",
            "subcategory":"Investment Brokerage",
            "type":"Services"
        }
    ],
    "sg:phone":"+1 614 218 1122",
    "sg:postcode":"43207",
    "sg:province":"OH",
    "sg:tags":[
        "games-wholesale",
        "sale",
        "dvds-rental",
        "tape",
        "video",
        "supplies-wholesale",
        "manufacturer"
    ],
    "wof:name":"Video Game Action",
    "wof:placetype":"venue"
},
  "geometry": {"coordinates":[-82.996861,39.891132],"type":"Point"}
}