{
  "type": "Feature",
  "properties": {
    "iso:country":"US",
    "sg:address":"3250 W Market St",
    "sg:city":"Fairlawn",
    "sg:classifiers":[
        {
            "category":"Banks & Credit Unions",
            "subcategory":"Investment Brokerage",
            "type":"Services"
        }
    ],
    "sg:phone":"+1 330 867 7023",
    "sg:postcode":"44333",
    "sg:province":"OH",
    "sg:tags":[
        "funds",
        "mutual"
    ],
    "sg:website":"www.agedwards.com",
    "wof:name":"A G Edwards & Sons Inc",
    "wof:placetype":"venue"
},
  "geometry": {"coordinates":[-81.619372,41.132607],"type":"Point"}
}