{
  "type": "Feature",
  "properties": {
    "addr:full": "29183 Anderson Rd Wickliffe OH 44092",
    "addr:housenumber": "29183",
    "addr:postcode": "44092",
    "addr:street": "Anderson Rd",
    "iso:country": "US",
    "sg:address": "29183 Anderson Rd",
    "sg:city": "Wickliffe",
    "sg:classifiers": [
      {
        "category": "Wholesale",
        "subcategory": "Hardware",
        "type": "Manufacturing \u0026 Wholesale Goods"
      }
    ],
    "sg:phone": "+1 440 943 7050",
    "sg:postcode": "44092",
    "sg:province": "OH",
    "sg:tags": [
      "tool"
    ],
    "wof:name": "Wel Dan Co Inc",
    "wof:placetype": "venue"
  },
  "geometry": {"coordinates":[-81.481073,41.605058],"type":"Point"}
}
