{
  "type": "Feature",
  "properties": {
    "addr:full":"970 Hickory Grove Ave Medina OH 44256",
    "addr:housenumber":"970",
    "addr:postcode":"44256",
    "addr:street":"Hickory Grove Ave",
    "iso:country":"US",
    "sg:address":"970 Hickory Grove Ave",
    "sg:city":"Medina",
    "sg:classifiers":[
        {
            "category":"Recreation",
            "type":"Entertainment"
        }
    ],
    "sg:phone":"+1 330 723 8141",
    "sg:postcode":"44256",
    "sg:province":"OH",
    "wof:name":"Chippewa Yacht Club SW",
    "wof:placetype":"venue"
},
  "geometry": {"coordinates":[-81.853206,41.152504],"type":"Point"}
}