{
  "type": "Feature",
  "properties": {
    "addr:full": "5013 East Rd Lima OH 45807",
    "addr:housenumber": "5013",
    "addr:postcode": "45807",
    "addr:street": "East Rd",
    "iso:country": "US",
    "sg:address": "5013 East Rd",
    "sg:city": "Lima",
    "sg:classifiers": [
      {
        "category": "Building \u0026 Trades",
        "subcategory": "Construction",
        "type": "Services"
      }
    ],
    "sg:phone": "+1 419 339 8992",
    "sg:postcode": "45807",
    "sg:province": "OH",
    "sg:tags": [
      "house"
    ],
    "wof:name": "Bower Home Improvement",
    "wof:placetype": "venue"
  },
  "geometry": {"coordinates":[-84.196601,40.772805],"type":"Point"}
}
