{
  "type": "Feature",
  "properties": {
    "addr:full": "333 Mc Cormick Blvd Columbus OH 43213",
    "addr:housenumber": "333",
    "addr:postcode": "43213",
    "addr:street": "Mc Cormick Blvd",
    "iso:country": "US",
    "sg:address": "333 Mc Cormick Blvd",
    "sg:city": "Columbus",
    "sg:classifiers": [
      {
        "category": "Wholesale",
        "subcategory": "Machinery \u0026 Supplies",
        "type": "Manufacturing \u0026 Wholesale Goods"
      }
    ],
    "sg:phone": "+1 614 846 8503",
    "sg:postcode": "43213",
    "sg:province": "OH",
    "sg:tags": [
      "industrial",
      "business"
    ],
    "wof:name": "A P V Crepaco",
    "wof:placetype": "venue"
  },
  "geometry": {"coordinates":[-82.825955,39.990069],"type":"Point"}
}
