{
  "type": "Feature",
  "properties": {
    "iso:country":"US",
    "sg:address":"333 Mc Cormick Blvd",
    "sg:city":"Columbus",
    "sg:classifiers":[
        {
            "category":"Wholesale",
            "subcategory":"Machinery & Supplies",
            "type":"Manufacturing & Wholesale Goods"
        }
    ],
    "sg:phone":"+1 614 846 8503",
    "sg:postcode":"43213",
    "sg:province":"OH",
    "sg:tags":[
        "industrial",
        "business"
    ],
    "wof:name":"A P V Crepaco",
    "wof:placetype":"venue"
},
  "geometry": {"coordinates":[-82.82595499999999,39.990069],"type":"Point"}
}