{
  "type": "Feature",
  "properties": {
    "addr:full": "6965 McCartney Rd Lowellville OH 44436",
    "addr:housenumber": "6965",
    "addr:postcode": "44436",
    "addr:street": "Mccartney Rd",
    "iso:country": "US",
    "sg:address": "6965 McCartney Rd",
    "sg:city": "Lowellville",
    "sg:classifiers": [
      {
        "category": "Travel",
        "subcategory": "Hotels \u0026 Motels",
        "type": "Entertainment"
      }
    ],
    "sg:phone": "+1 330 536 6273",
    "sg:postcode": "44436",
    "sg:province": "OH",
    "sg:tags": [
      "operation"
    ],
    "wof:name": "King's Motel",
    "wof:placetype": "venue"
  },
  "geometry": {"coordinates":[-80.523852,41.090584],"type":"Point"}
}
