{
  "type": "Feature",
  "properties": {
    "iso:country":"US",
    "sg:address":"6965 McCartney Rd",
    "sg:city":"Lowellville",
    "sg:classifiers":[
        {
            "category":"Travel",
            "subcategory":"Hotels & Motels",
            "type":"Entertainment"
        }
    ],
    "sg:phone":"+1 330 536 6273",
    "sg:postcode":"44436",
    "sg:province":"OH",
    "sg:tags":[
        "operation"
    ],
    "wof:name":"King's Motel",
    "wof:placetype":"venue"
},
  "geometry": {"coordinates":[-80.52385200000001,41.090584],"type":"Point"}
}