{
  "type": "Feature",
  "properties": {
    "iso:country":"US",
    "sg:address":"880 S 5th St",
    "sg:city":"Columbus",
    "sg:classifiers":[
        {
            "category":"Manufacturing",
            "subcategory":"Printing",
            "type":"Manufacturing & Wholesale Goods"
        }
    ],
    "sg:phone":"+1 614 445 4949",
    "sg:postcode":"43206",
    "sg:province":"OH",
    "sg:tags":[
        "publisher"
    ],
    "sg:website":"www.parkviewpub.com",
    "wof:name":"Parkview Publishing",
    "wof:placetype":"venue"
},
  "geometry": {"coordinates":[-82.991309,39.944984],"type":"Point"}
}