{
  "type": "Feature",
  "properties": {
    "addr:full":"1330 Corporate Dr Hudson OH 44236",
    "addr:housenumber":"1330",
    "addr:postcode":"44236",
    "addr:street":"Corporate Dr",
    "iso:country":"US",
    "sg:address":"1330 Corporate Dr",
    "sg:city":"Hudson",
    "sg:classifiers":[
        {
            "category":"Social Services",
            "subcategory":"Job Training",
            "type":"Services"
        }
    ],
    "sg:phone":"+1 330 342 0926",
    "sg:postcode":"44236",
    "sg:province":"OH",
    "sg:tags":[
        "rehabilitation"
    ],
    "wof:name":"Remed Recovery Care",
    "wof:placetype":"venue"
},
  "geometry": {"coordinates":[-81.443822,41.214525],"type":"Point"}
}