{
  "type": "Feature",
  "properties": {
    "addr:full": "15611 W High St Middlefield OH 44062",
    "addr:housenumber": "15611",
    "addr:postcode": "44062",
    "addr:street": "W High St",
    "iso:country": "US",
    "sg:address": "15611 W High St",
    "sg:city": "Middlefield",
    "sg:classifiers": [
      {
        "category": "Utilities",
        "subcategory": "Mobile Phone",
        "type": "Services"
      }
    ],
    "sg:phone": "+1 440 632 9761",
    "sg:postcode": "44062",
    "sg:province": "OH",
    "sg:tags": [
      "communication",
      "radiotelephone"
    ],
    "wof:name": "Air Time Cellular",
    "wof:placetype": "venue"
  },
  "geometry": {"coordinates":[-81.089967,41.463169],"type":"Point"}
}
