{
  "type": "Feature",
  "properties": {
    "iso:country":"US",
    "sg:address":"30 N Diamond St",
    "sg:city":"Mansfield",
    "sg:classifiers":[
        {
            "category":"Government",
            "subcategory":"Office",
            "type":"Public Place"
        }
    ],
    "sg:phone":"+1 419 755 9775",
    "sg:postcode":"44902",
    "sg:province":"OH",
    "sg:tags":[
        "policy",
        "department",
        "finance"
    ],
    "wof:name":"Financial Department",
    "wof:placetype":"venue"
},
  "geometry": {"coordinates":[-82.51392300000001,40.759533],"type":"Point"}
}