{
  "type": "Feature",
  "properties": {
    "addr:full":"700 W Breese Rd Lima OH 45806",
    "addr:housenumber":"700",
    "addr:postcode":"45806",
    "addr:street":"W Breese Rd",
    "iso:country":"US",
    "sg:address":"700 W Breese Rd",
    "sg:city":"Lima",
    "sg:classifiers":[
        {
            "category":"Retail",
            "subcategory":"Animal Services",
            "type":"Services"
        }
    ],
    "sg:phone":"+1 419 222 5511",
    "sg:postcode":"45806",
    "sg:province":"OH",
    "sg:tags":[
        "breeder",
        "horse"
    ],
    "wof:name":"TCH Arabians",
    "wof:placetype":"venue"
},
  "geometry": {"coordinates":[-84.115909,40.68671],"type":"Point"}
}