{
  "type": "Feature",
  "properties": {
    "addr:full":"910 State Rte 98 Bucyrus OH 44820",
    "addr:housenumber":"910",
    "addr:postcode":"44820",
    "addr:street":"State Rte 98",
    "iso:country":"US",
    "sg:address":"910 State Rte 98",
    "sg:city":"Bucyrus",
    "sg:classifiers":[
        {
            "category":"Professional",
            "subcategory":"Management & Consulting",
            "type":"Services"
        }
    ],
    "sg:phone":"+1 419 562 9885",
    "sg:postcode":"44820",
    "sg:province":"OH",
    "sg:tags":[
        "consultant"
    ],
    "wof:name":"Hord Livestock",
    "wof:placetype":"venue"
},
  "geometry": {"coordinates":[-82.99506599999999,40.735198],"type":"Point"}
}