{
  "type": "Feature",
  "properties": {
    "addr:full":"425 Walnut St Cincinnati OH 45202",
    "addr:housenumber":"425",
    "addr:postcode":"45202",
    "addr:street":"Walnut St",
    "iso:country":"US",
    "sg:address":"425 Walnut St",
    "sg:city":"Cincinnati",
    "sg:classifiers":[
        {
            "category":"Professional",
            "subcategory":"Management & Consulting",
            "type":"Services"
        },
        {
            "category":"Professional",
            "subcategory":"Computer Services",
            "type":"Services"
        }
    ],
    "sg:phone":"+1 513 345 6670",
    "sg:postcode":"45202",
    "sg:province":"OH",
    "sg:tags":[
        "consultant",
        "datum",
        "business"
    ],
    "sg:website":"www.applobj.com",
    "wof:name":"Application Objects Inc",
    "wof:placetype":"venue"
},
  "geometry": {"coordinates":[-84.51137300000001,39.100998],"type":"Point"}
}