{
  "type": "Feature",
  "properties": {
    "addr:full": "209 Great Oaks Trl Wadsworth OH 44281",
    "addr:housenumber": "209",
    "addr:postcode": "44281",
    "addr:street": "Great Oaks Trl",
    "iso:country": "US",
    "sg:address": "209 Great Oaks Trl",
    "sg:city": "Wadsworth",
    "sg:classifiers": [
      {
        "category": "Real Estate",
        "subcategory": "Real Estate Agent",
        "type": "Services"
      }
    ],
    "sg:phone": "+1 330 335 2560",
    "sg:postcode": "44281",
    "sg:province": "OH",
    "sg:website": "www.smythecramer.com",
    "wof:name": "Cramer Smythe Co",
    "wof:placetype": "venue"
  },
  "geometry": {"coordinates":[-81.732862,41.048917],"type":"Point"}
}
