{
  "type": "Feature",
  "properties": {
    "addr:full": "41 Edgecombe Dr Milford OH 45150",
    "addr:housenumber": "41",
    "addr:postcode": "45150",
    "addr:street": "Edgecombe Dr",
    "iso:country": "US",
    "sg:address": "41 Edgecombe Dr",
    "sg:city": "Milford",
    "sg:classifiers": [
      {
        "category": "Building \u0026 Trades",
        "subcategory": "Construction",
        "type": "Services"
      }
    ],
    "sg:phone": "+1 513 831 7356",
    "sg:postcode": "45150",
    "sg:province": "OH",
    "sg:tags": [
      "house"
    ],
    "wof:name": "BCT Home Improvement",
    "wof:placetype": "venue"
  },
  "geometry": {"coordinates":[-84.271496,39.181435],"type":"Point"}
}
