{
  "type": "Feature",
  "properties": {
    "iso:country":"US",
    "sg:address":"5206 Heatherton Dr",
    "sg:city":"Trotwood",
    "sg:classifiers":[
        {
            "category":"Organizations",
            "subcategory":"Religious Organization",
            "type":"Services"
        }
    ],
    "sg:phone":"+1 937 837 3607",
    "sg:postcode":"45426",
    "sg:province":"OH",
    "sg:tags":[
        "clergy"
    ],
    "wof:name":"Ernest Scales",
    "wof:placetype":"venue"
},
  "geometry": {"coordinates":[-84.27822,39.805395],"type":"Point"}
}