{
  "type": "Feature",
  "properties": {
    "iso:country":"US",
    "sg:address":"1103 Riva Ridge Blvd",
    "sg:city":"Columbus",
    "sg:classifiers":[
        {
            "category":"Real Estate",
            "subcategory":"Architect",
            "type":"Services"
        }
    ],
    "sg:phone":"+1 614 899 4830",
    "sg:postcode":"43230",
    "sg:province":"OH",
    "wof:name":"Trinity Health Group",
    "wof:placetype":"venue"
},
  "geometry": {"coordinates":[-82.84792,40.046695],"type":"Point"}
}