{
  "type": "Feature",
  "properties": {
    "iso:country":"US",
    "sg:address":"2521 E Main St",
    "sg:city":"Columbus",
    "sg:classifiers":[
        {
            "category":"Organizations",
            "subcategory":"Community Association",
            "type":"Services"
        }
    ],
    "sg:phone":"+1 614 231 7359",
    "sg:postcode":"43209",
    "sg:province":"OH",
    "sg:tags":[
        "fraternal"
    ],
    "wof:name":"Bexley Lodge No 704 F & AM",
    "wof:placetype":"venue"
},
  "geometry": {"coordinates":[-82.931346,39.956942],"type":"Point"}
}