{
  "type": "Feature",
  "properties": {
    "addr:full": "2521 E Main St Columbus OH 43209",
    "addr:housenumber": "2521",
    "addr:postcode": "43209",
    "addr:street": "E Main St",
    "iso:country": "US",
    "sg:address": "2521 E Main St",
    "sg:city": "Columbus",
    "sg:classifiers": [
      {
        "category": "Organizations",
        "subcategory": "Community Association",
        "type": "Services"
      }
    ],
    "sg:phone": "+1 614 231 7359",
    "sg:postcode": "43209",
    "sg:province": "OH",
    "sg:tags": [
      "fraternal"
    ],
    "wof:name": "Bexley Lodge No 704 F \u0026 AM",
    "wof:placetype": "venue"
  },
  "geometry": {"coordinates":[-82.931346,39.956942],"type":"Point"}
}
