{
  "type": "Feature",
  "properties": {
    "addr:full":"1827 North Blvd Fairborn OH 45324",
    "addr:housenumber":"1827",
    "addr:postcode":"45324",
    "addr:street":"North Blvd",
    "iso:country":"US",
    "sg:address":"1827 North Blvd",
    "sg:city":"Fairborn",
    "sg:classifiers":[
        {
            "category":"Building & Trades",
            "subcategory":"Construction",
            "type":"Services"
        }
    ],
    "sg:phone":"+1 937 754 9005",
    "sg:postcode":"45324",
    "sg:province":"OH",
    "sg:tags":[
        "house"
    ],
    "wof:name":"Willetts Home Improvement",
    "wof:placetype":"venue"
},
  "geometry": {"coordinates":[-84.041287,39.793567],"type":"Point"}
}