{
  "type": "Feature",
  "properties": {
    "iso:country":"US",
    "sg:address":"110 S Main St",
    "sg:city":"Celina",
    "sg:classifiers":[
        {
            "category":"Shopping",
            "subcategory":"Used Merchandise",
            "type":"Retail Goods"
        }
    ],
    "sg:phone":"+1 419 586 2979",
    "sg:postcode":"45822",
    "sg:province":"OH",
    "wof:name":"Things From Heart Thrift Store",
    "wof:placetype":"venue"
},
  "geometry": {"coordinates":[-84.570722,40.548905],"type":"Point"}
}