{
  "type": "Feature",
  "properties": {
    "iso:country":"US",
    "sg:address":"12024 Shaker Blvd",
    "sg:city":"Cleveland",
    "sg:classifiers":[
        {
            "category":"Professional",
            "type":"Services"
        }
    ],
    "sg:phone":"+1 216 795 6853",
    "sg:postcode":"44120",
    "sg:province":"OH",
    "sg:tags":[
        "establishment"
    ],
    "wof:name":"LA Ronde Resident Counsel",
    "wof:placetype":"venue"
},
  "geometry": {"coordinates":[-81.60123900000001,41.484161],"type":"Point"}
}