{
  "type": "Feature",
  "properties": {
    "addr:full": "13070 Durkee Rd Grafton OH 44044",
    "addr:postcode": "13070;44044",
    "addr:street": "Durkee Rd",
    "iso:country": "US",
    "sg:address": "13070 Durkee Rd",
    "sg:city": "Grafton",
    "sg:classifiers": [
      {
        "category": "Education",
        "subcategory": "School",
        "type": "Public Place"
      }
    ],
    "sg:phone": "+1 440 926 3828",
    "sg:postcode": "44044",
    "sg:province": "OH",
    "sg:website": "www.midviewk12.org",
    "wof:name": "Grafton Elementary School",
    "wof:placetype": "venue"
  },
  "geometry": {"coordinates":[-82.051071,41.29735],"type":"Point"}
}
