{
  "type": "Feature",
  "properties": {
    "addr:full": "5123 Ryan Rd Toledo OH 43614",
    "addr:housenumber": "5123",
    "addr:postcode": "43614",
    "addr:street": "Ryan Rd",
    "iso:country": "US",
    "sg:address": "5123 Ryan Rd",
    "sg:city": "Toledo",
    "sg:classifiers": [
      {
        "category": "Real Estate",
        "subcategory": "Real Estate Operator",
        "type": "Services"
      }
    ],
    "sg:phone": "+1 419 385 7977",
    "sg:postcode": "43614",
    "sg:province": "OH",
    "sg:tags": [
      "apartment"
    ],
    "wof:name": "Sandpiper",
    "wof:placetype": "venue"
  },
  "geometry": {"coordinates":[-83.663343,41.601822],"type":"Point"}
}
