{
  "type": "Feature",
  "properties": {
    "addr:full":"5740 Woodville Rd Northwood OH 43619",
    "addr:housenumber":"5740",
    "addr:postcode":"43619",
    "addr:street":"Woodville Rd",
    "iso:country":"US",
    "sg:address":"5740 Woodville Rd",
    "sg:city":"Northwood",
    "sg:classifiers":[
        {
            "category":"Manufacturing",
            "subcategory":"Tools & Machinery",
            "type":"Manufacturing & Wholesale Goods"
        }
    ],
    "sg:phone":"+1 419 836 7781",
    "sg:postcode":"43619",
    "sg:province":"OH",
    "sg:tags":[
        "machine",
        "shop",
        "general"
    ],
    "wof:name":"Royal Tool and Machine Co",
    "wof:placetype":"venue"
},
  "geometry": {"coordinates":[-83.43484599999999,41.581908],"type":"Point"}
}