{
  "type": "Feature",
  "properties": {
    "addr:full": "5740 Woodville Rd Northwood OH 43619",
    "addr:housenumber": "5740",
    "addr:postcode": "43619",
    "addr:street": "Woodville Rd",
    "iso:country": "US",
    "sg:address": "5740 Woodville Rd",
    "sg:city": "Northwood",
    "sg:classifiers": [
      {
        "category": "Manufacturing",
        "subcategory": "Tools \u0026 Machinery",
        "type": "Manufacturing \u0026 Wholesale Goods"
      }
    ],
    "sg:phone": "+1 419 836 7781",
    "sg:postcode": "43619",
    "sg:province": "OH",
    "sg:tags": [
      "machine",
      "shop",
      "general"
    ],
    "wof:name": "Royal Tool and Machine Co",
    "wof:placetype": "venue"
  },
  "geometry": {"coordinates":[-83.434846,41.581908],"type":"Point"}
}
