{
  "type": "Feature",
  "properties": {
    "addr:full": "8260 Beechmont Ave Cincinnati OH 45255",
    "addr:housenumber": "8260",
    "addr:postcode": "45255",
    "addr:street": "Beechmont Ave",
    "iso:country": "US",
    "sg:address": "8260 Beechmont Ave",
    "sg:city": "Cincinnati",
    "sg:classifiers": [
      {
        "category": "Retail",
        "subcategory": "Auto Repair",
        "type": "Services"
      }
    ],
    "sg:phone": "+1 513 474 4480",
    "sg:postcode": "45255",
    "sg:province": "OH",
    "wof:name": "Meineke Car Care Centers Inc",
    "wof:placetype": "venue"
  },
  "geometry": {"coordinates":[-84.323601,39.072399],"type":"Point"}
}
