{
  "type": "Feature",
  "properties": {
    "addr:full": "811 Sharon Dr Westlake OH 44145",
    "addr:housenumber": "811",
    "addr:postcode": "44145",
    "addr:street": "Sharon Dr",
    "iso:country": "US",
    "sg:address": "811 Sharon Dr",
    "sg:city": "Westlake",
    "sg:classifiers": [
      {
        "category": "Manufacturing",
        "subcategory": "Chemicals \u0026 Compounds",
        "type": "Manufacturing \u0026 Wholesale Goods"
      }
    ],
    "sg:phone": "+1 440 899 2950",
    "sg:postcode": "44145",
    "sg:province": "OH",
    "sg:tags": [
      "p",
      "chem",
      "organic",
      "mfg"
    ],
    "wof:name": "Omg Americas Inc",
    "wof:placetype": "venue"
  },
  "geometry": {"coordinates":[-81.890994,41.473265],"type":"Point"}
}
