{
  "type": "Feature",
  "properties": {
    "addr:full":"15701 Broadway Ave Cleveland OH 44137",
    "addr:housenumber":"15701",
    "addr:postcode":"44137",
    "addr:street":"Broadway Ave",
    "iso:country":"US",
    "sg:address":"15701 Broadway Ave",
    "sg:city":"Cleveland",
    "sg:classifiers":[
        {
            "category":"Banks & Credit Unions",
            "subcategory":"Bank",
            "type":"Services"
        }
    ],
    "sg:phone":"+1 216 581 5892",
    "sg:postcode":"44137",
    "sg:province":"OH",
    "sg:tags":[
        "cashing",
        "check"
    ],
    "sg:website":"www.acecashexpress.com",
    "wof:name":"ACE Cash Express",
    "wof:placetype":"venue"
},
  "geometry": {"coordinates":[-81.570227,41.415642],"type":"Point"}
}