{
  "type": "Feature",
  "properties": {
    "addr:full": "6037 Cleveland Ave Columbus OH 43231",
    "addr:housenumber": "6037",
    "addr:postcode": "43231",
    "addr:street": "Cleveland Ave",
    "iso:country": "US",
    "sg:address": "6037 Cleveland Ave",
    "sg:city": "Columbus",
    "sg:classifiers": [
      {
        "category": "Banks \u0026 Credit Unions",
        "subcategory": "Bank",
        "type": "Services"
      }
    ],
    "sg:phone": "+1 614 884 1900",
    "sg:postcode": "43231",
    "sg:province": "OH",
    "sg:tags": [
      "loan",
      "mortgage",
      "real estate"
    ],
    "wof:name": "Union Capital Mortgage Corp",
    "wof:placetype": "venue"
  },
  "geometry": {"coordinates":[-82.950094,40.096858],"type":"Point"}
}
