{
  "type": "Feature",
  "properties": {
    "addr:full": "1999 Section Rd Cincinnati OH 45237",
    "addr:housenumber": "1999",
    "addr:postcode": "45237",
    "addr:street": "Section Rd",
    "iso:country": "US",
    "sg:address": "1999 Section Rd",
    "sg:city": "Cincinnati",
    "sg:classifiers": [
      {
        "category": "Food \u0026 Beverages",
        "subcategory": "Specialty",
        "type": "Retail Goods"
      },
      {
        "category": "Food \u0026 Beverages",
        "subcategory": "Supermarket",
        "type": "Retail Goods"
      },
      {
        "category": "Food \u0026 Beverages",
        "subcategory": "Meat \u0026 Fish",
        "type": "Retail Goods"
      }
    ],
    "sg:phone": "+1 513 772 3535",
    "sg:postcode": "45237",
    "sg:province": "OH",
    "sg:tags": [
      "store",
      "super",
      "grocers-specialty",
      "market"
    ],
    "wof:name": "Atlantic International Corp",
    "wof:placetype": "venue"
  },
  "geometry": {"coordinates":[-84.452393,39.19706],"type":"Point"}
}
