{
  "type": "Feature",
  "properties": {
    "addr:full": "11721 Lorain Ave Cleveland OH 44111",
    "addr:housenumber": "11721",
    "addr:postcode": "44111",
    "addr:street": "Lorain Ave",
    "iso:country": "US",
    "sg:address": "11721 Lorain Ave",
    "sg:city": "Cleveland",
    "sg:classifiers": [
      {
        "category": "Home \u0026 Garden",
        "subcategory": "Carpets \u0026 Floor Coverings",
        "type": "Retail Goods"
      }
    ],
    "sg:phone": "+1 216 941 0786",
    "sg:postcode": "44111",
    "sg:province": "OH",
    "sg:tags": [
      "linoleum"
    ],
    "wof:name": "Carpet Bargain Outlet Inc",
    "wof:placetype": "venue"
  },
  "geometry": {"coordinates":[-81.769388,41.461651],"type":"Point"}
}
