{
  "type": "Feature",
  "properties": {
    "iso:country":"US",
    "sg:address":"2862 W Johnstown Rd",
    "sg:city":"Columbus",
    "sg:classifiers":[
        {
            "category":"Professional",
            "subcategory":"Secretarial Services",
            "type":"Services"
        }
    ],
    "sg:phone":"+1 614 470 9050",
    "sg:postcode":"43219",
    "sg:province":"OH",
    "sg:tags":[
        "resume"
    ],
    "wof:name":"R Burns & Assoc",
    "wof:placetype":"venue"
},
  "geometry": {"coordinates":[-82.91245499999999,40.005894],"type":"Point"}
}