{
  "type": "Feature",
  "properties": {
    "addr:full":"7795 Cooper Rd Cincinnati OH 45242",
    "addr:housenumber":"7795",
    "addr:postcode":"45242",
    "addr:street":"Cooper Rd",
    "iso:country":"US",
    "sg:address":"7795 Cooper Rd",
    "sg:city":"Cincinnati",
    "sg:classifiers":[
        {
            "category":"Professional",
            "subcategory":"Management & Consulting",
            "type":"Services"
        }
    ],
    "sg:phone":"+1 513 793 6876",
    "sg:postcode":"45242",
    "sg:province":"OH",
    "sg:tags":[
        "consultant",
        "business"
    ],
    "wof:name":"Meridian Group",
    "wof:placetype":"venue"
},
  "geometry": {"coordinates":[-84.35512300000001,39.226498],"type":"Point"}
}