{
  "type": "Feature",
  "properties": {
    "iso:country":"US",
    "sg:address":"131 S Prospect St",
    "sg:city":"Marion",
    "sg:classifiers":[
        {
            "category":"Banks & Credit Unions",
            "subcategory":"Bank",
            "type":"Services"
        }
    ],
    "sg:phone":"+1 740 223 0850",
    "sg:postcode":"43302",
    "sg:province":"OH",
    "sg:tags":[
        "loan",
        "mortgage",
        "real estate"
    ],
    "wof:name":"Common Sense Mortgage Services",
    "wof:placetype":"venue"
},
  "geometry": {"coordinates":[-83.130394,40.587948],"type":"Point"}
}