{
  "type": "Feature",
  "properties": {
    "iso:country":"US",
    "sg:address":"22972 Lorain Rd",
    "sg:city":"Cleveland",
    "sg:classifiers":[
        {
            "category":"Professional",
            "subcategory":"Detective & Security Services",
            "type":"Services"
        },
        {
            "category":"Wholesale",
            "subcategory":"Electrical",
            "type":"Manufacturing & Wholesale Goods"
        }
    ],
    "sg:phone":"+1 440 979 9000",
    "sg:postcode":"44126",
    "sg:province":"OH",
    "sg:tags":[
        "alarm",
        "burglar",
        "system"
    ],
    "wof:name":"New Age Security Inc",
    "wof:placetype":"venue"
},
  "geometry": {"coordinates":[-81.874266,41.437639],"type":"Point"}
}