{
  "type": "Feature",
  "properties": {
    "addr:full":"756 N Market St Shreve OH 44676",
    "addr:housenumber":"756",
    "addr:postcode":"44676",
    "addr:street":"N Market St",
    "iso:country":"US",
    "sg:address":"756 N Market St",
    "sg:city":"Shreve",
    "sg:classifiers":[
        {
            "category":"Farming",
            "subcategory":"Dairy Farm",
            "type":"Manufacturing & Wholesale Goods"
        }
    ],
    "sg:phone":"+1 330 567 3741",
    "sg:postcode":"44676",
    "sg:province":"OH",
    "wof:name":"Gentle View Dairy Farm",
    "wof:placetype":"venue"
},
  "geometry": {"coordinates":[-82.022228,40.688468],"type":"Point"}
}