{
  "type": "Feature",
  "properties": {
    "addr:full":"221 Woodland Ave Swanton OH 43558",
    "addr:housenumber":"221",
    "addr:postcode":"43558",
    "addr:street":"Woodland Ave",
    "iso:country":"US",
    "sg:address":"221 Woodland Ave",
    "sg:city":"Swanton",
    "sg:classifiers":[
        {
            "category":"Wholesale",
            "subcategory":"Machinery & Supplies",
            "type":"Manufacturing & Wholesale Goods"
        }
    ],
    "sg:phone":"+1 419 826 8999",
    "sg:postcode":"43558",
    "sg:province":"OH",
    "sg:tags":[
        "equipment",
        "industrial"
    ],
    "wof:name":"Reynolds Inc",
    "wof:placetype":"venue"
},
  "geometry": {"coordinates":[-83.890792,41.592218],"type":"Point"}
}