{
  "type": "Feature",
  "properties": {
    "addr:full": "8845 Governors Hill Dr Cincinnati OH 45249",
    "addr:housenumber": "8845",
    "addr:postcode": "45249",
    "addr:street": "Governors Hill Dr",
    "iso:country": "US",
    "sg:address": "8845 Governors Hill Dr",
    "sg:city": "Cincinnati",
    "sg:classifiers": [
      {
        "category": "Shopping",
        "subcategory": "Catalog Store",
        "type": "Retail Goods"
      }
    ],
    "sg:phone": "+1 513 336 3350",
    "sg:postcode": "45249",
    "sg:province": "OH",
    "sg:tags": [
      "mail",
      "order",
      "pharmaceutical"
    ],
    "wof:name": "Anthem Prescription MGT LLC",
    "wof:placetype": "venue"
  },
  "geometry": {"coordinates":[-84.319586,39.288517],"type":"Point"}
}
