{
  "type": "Feature",
  "properties": {
    "addr:full": "564 Old State Rte 74 Cincinnati OH 45244",
    "addr:housenumber": "564",
    "addr:postcode": "45244",
    "addr:street": "Old State Rte 74",
    "iso:country": "US",
    "sg:address": "564 Old State Rte 74",
    "sg:city": "Cincinnati",
    "sg:classifiers": [
      {
        "category": "Wholesale",
        "subcategory": "Machinery \u0026 Supplies",
        "type": "Manufacturing \u0026 Wholesale Goods"
      }
    ],
    "sg:phone": "+1 513 528 7000",
    "sg:postcode": "45244",
    "sg:province": "OH",
    "sg:tags": [
      "pump",
      "equipment",
      "mfr",
      "pumping",
      "rep"
    ],
    "wof:name": "M\u0026E Pump \u0026 Equipmt",
    "wof:placetype": "venue"
  },
  "geometry": {"coordinates":[-84.296103,39.104282],"type":"Point"}
}
