{
  "type": "Feature",
  "properties": {
    "addr:full":"15 American Way Monroe OH 45050",
    "addr:housenumber":"15",
    "addr:postcode":"45050",
    "addr:street":"American Way",
    "iso:country":"US",
    "sg:address":"15 American Way",
    "sg:city":"Monroe",
    "sg:classifiers":[
        {
            "category":"Personal",
            "subcategory":"Tattoo Parlor",
            "type":"Services"
        }
    ],
    "sg:phone":"+1 513 539 9987",
    "sg:postcode":"45050",
    "sg:province":"OH",
    "sg:tags":[
        "tattooing"
    ],
    "wof:name":"Tattoo City",
    "wof:placetype":"venue"
},
  "geometry": {"coordinates":[-84.345226,39.439401],"type":"Point"}
}