{
  "type": "Feature",
  "properties": {
    "addr:full": "179 Green Springs Dr Columbus OH 43235",
    "addr:housenumber": "179",
    "addr:postcode": "43235",
    "addr:street": "Green Springs Dr",
    "iso:country": "US",
    "sg:address": "179 Green Springs Dr",
    "sg:city": "Columbus",
    "sg:classifiers": [
      {
        "category": "Real Estate",
        "subcategory": "Real Estate Agent",
        "type": "Services"
      }
    ],
    "sg:phone": "+1 614 846 2228",
    "sg:postcode": "43235",
    "sg:province": "OH",
    "wof:name": "W Jack Bettsy",
    "wof:placetype": "venue"
  },
  "geometry": {"coordinates":[-83.012448,40.132438],"type":"Point"}
}
