{
  "type": "Feature",
  "properties": {
    "iso:country":"US",
    "sg:address":"3381 Bloomfield Rd",
    "sg:city":"Cambridge",
    "sg:classifiers":[
        {
            "category":"Building & Trades",
            "subcategory":"Construction",
            "type":"Services"
        }
    ],
    "sg:phone":"+1 740 432 3815",
    "sg:postcode":"43725",
    "sg:province":"OH",
    "sg:tags":[
        "water",
        "well",
        "drilling"
    ],
    "wof:name":"J R Wells",
    "wof:placetype":"venue"
},
  "geometry": {"coordinates":[-81.684019,40.057909],"type":"Point"}
}