{
  "type": "Feature",
  "properties": {
    "addr:full": "3381 Bloomfield Rd Cambridge OH 43725",
    "addr:housenumber": "3381",
    "addr:postcode": "43725",
    "addr:street": "Bloomfield Rd",
    "iso:country": "US",
    "sg:address": "3381 Bloomfield Rd",
    "sg:city": "Cambridge",
    "sg:classifiers": [
      {
        "category": "Building \u0026 Trades",
        "subcategory": "Construction",
        "type": "Services"
      }
    ],
    "sg:phone": "+1 740 432 3815",
    "sg:postcode": "43725",
    "sg:province": "OH",
    "sg:tags": [
      "water",
      "well",
      "drilling"
    ],
    "wof:name": "J R Wells",
    "wof:placetype": "venue"
  },
  "geometry": {"coordinates":[-81.684019,40.057909],"type":"Point"}
}
