{
  "type": "Feature",
  "properties": {
    "addr:full":"2726 Fulton Dr NW Canton OH 44718",
    "addr:housenumber":"2726",
    "addr:postcode":"44718",
    "addr:street":"Fulton Dr Nw",
    "iso:country":"US",
    "sg:address":"2726 Fulton Dr NW",
    "sg:city":"Canton",
    "sg:classifiers":[
        {
            "category":"Health Services",
            "subcategory":"Doctor",
            "type":"Services"
        }
    ],
    "sg:phone":"+1 330 455 5011",
    "sg:postcode":"44718",
    "sg:province":"OH",
    "sg:tags":[
        "physician",
        "surgeon",
        "medical"
    ],
    "wof:name":"Gastroenterology Specialists",
    "wof:placetype":"venue"
},
  "geometry": {"coordinates":[-81.402203,40.826571],"type":"Point"}
}