{
  "type": "Feature",
  "properties": {
    "iso:country":"US",
    "sg:address":"827 Scioto St",
    "sg:city":"Urbana",
    "sg:classifiers":[
        {
            "category":"Personal",
            "subcategory":"Tanning Parlor",
            "type":"Services"
        }
    ],
    "sg:phone":"+1 937 484 7353",
    "sg:postcode":"43078",
    "sg:province":"OH",
    "sg:tags":[
        "salon"
    ],
    "wof:name":"Martani's Tanning",
    "wof:placetype":"venue"
},
  "geometry": {"coordinates":[-83.733727,40.106872],"type":"Point"}
}