{
  "type": "Feature",
  "properties": {
    "addr:full": "6142 Cleves Warsaw Pike Cincinnati OH 45233",
    "addr:housenumber": "6142",
    "addr:postcode": "45233",
    "addr:street": "Cleves Warsaw Pike",
    "iso:country": "US",
    "sg:address": "6142 Cleves Warsaw Pike",
    "sg:city": "Cincinnati",
    "sg:classifiers": [
      {
        "category": "Building \u0026 Trades",
        "subcategory": "Landscaping Services",
        "type": "Services"
      }
    ],
    "sg:phone": "+1 513 941 2147",
    "sg:postcode": "45233",
    "sg:province": "OH",
    "wof:name": "Lawncare Schultz \u0026 Landscaping",
    "wof:placetype": "venue"
  },
  "geometry": {"coordinates":[-84.657567,39.120325],"type":"Point"}
}
