{
  "type": "Feature",
  "properties": {
    "addr:full": "222 W 3rd St Port Clinton OH 43452",
    "addr:housenumber": "222",
    "addr:postcode": "43452",
    "addr:street": "W 3Rd St",
    "iso:country": "US",
    "sg:address": "222 W 3rd St",
    "sg:city": "Port Clinton",
    "sg:classifiers": [
      {
        "category": "Recreation",
        "subcategory": "Marina",
        "type": "Entertainment"
      }
    ],
    "sg:phone": "+1 419 734 1819",
    "sg:postcode": "43452",
    "sg:province": "OH",
    "sg:tags": [
      "repairing",
      "boat"
    ],
    "wof:name": "D's Marine",
    "wof:placetype": "venue"
  },
  "geometry": {"coordinates":[-82.944456,41.510572],"type":"Point"}
}
