{
  "type": "Feature",
  "properties": {
    "addr:full":"54 E Aurora Rd Northfield OH 44067",
    "addr:housenumber":"54",
    "addr:postcode":"44067",
    "addr:street":"E Aurora Rd",
    "iso:country":"US",
    "sg:address":"54 E Aurora Rd",
    "sg:city":"Northfield",
    "sg:classifiers":[
        {
            "category":"Building & Trades",
            "subcategory":"Construction",
            "type":"Services"
        }
    ],
    "sg:phone":"+1 330 468 1505",
    "sg:postcode":"44067",
    "sg:province":"OH",
    "sg:tags":[
        "door",
        "window",
        "installation",
        "siding",
        "contractor"
    ],
    "wof:name":"Home Exteriors",
    "wof:placetype":"venue"
},
  "geometry": {"coordinates":[-81.53830600000001,41.31415],"type":"Point"}
}