{
  "type": "Feature",
  "properties": {
    "addr:full":"2101 Grandin Rd Cincinnati OH 45208",
    "addr:housenumber":"2101",
    "addr:postcode":"45208",
    "addr:street":"Grandin Rd",
    "iso:country":"US",
    "sg:address":"2101 Grandin Rd",
    "sg:city":"Cincinnati",
    "sg:classifiers":[
        {
            "category":"Banks & Credit Unions",
            "subcategory":"Investment Brokerage",
            "type":"Services"
        }
    ],
    "sg:phone":"+1 513 321 6386",
    "sg:postcode":"45208",
    "sg:province":"OH",
    "sg:tags":[
        "security"
    ],
    "wof:name":"Cyrus Phillip Kahl",
    "wof:placetype":"venue"
},
  "geometry": {"coordinates":[-84.460195,39.131879],"type":"Point"}
}