{
  "type": "Feature",
  "properties": {
    "addr:full":"16281 Glynn Rd Cleveland OH 44112",
    "addr:housenumber":"16281",
    "addr:postcode":"44112",
    "addr:street":"Glynn Rd",
    "iso:country":"US",
    "sg:address":"16281 Glynn Rd",
    "sg:city":"Cleveland",
    "sg:classifiers":[
        {
            "category":"Insurance",
            "subcategory":"Insurance Agent",
            "type":"Services"
        }
    ],
    "sg:phone":"+1 216 541 0076",
    "sg:postcode":"44112",
    "sg:province":"OH",
    "wof:name":"Washington Insurance",
    "wof:placetype":"venue"
},
  "geometry": {"coordinates":[-81.56317300000001,41.529554],"type":"Point"}
}