{
  "type": "Feature",
  "properties": {
    "addr:full": "575 White Pond Dr Akron OH 44320",
    "addr:housenumber": "575",
    "addr:postcode": "44320",
    "addr:street": "White Pond Dr",
    "iso:country": "US",
    "sg:address": "575 White Pond Dr",
    "sg:city": "Akron",
    "sg:classifiers": [
      {
        "category": "Professional",
        "subcategory": "Business Services",
        "type": "Services"
      }
    ],
    "sg:phone": "+1 330 865 1350",
    "sg:postcode": "44320",
    "sg:province": "OH",
    "wof:name": "American Express",
    "wof:placetype": "venue"
  },
  "geometry": {"coordinates":[-81.586213,41.101625],"type":"Point"}
}
