{
  "type": "Feature",
  "properties": {
    "iso:country":"US",
    "sg:address":"7711 Brookpark Rd",
    "sg:city":"Cleveland",
    "sg:classifiers":[
        {
            "category":"Wholesale",
            "subcategory":"Hardware",
            "type":"Manufacturing & Wholesale Goods"
        }
    ],
    "sg:phone":"+1 216 335 9740",
    "sg:postcode":"44129",
    "sg:province":"OH",
    "sg:tags":[
        "equipment",
        "locksmith",
        "supply"
    ],
    "wof:name":"IDN Hardware Sales Inc",
    "wof:placetype":"venue"
},
  "geometry": {"coordinates":[-81.752186,41.418495],"type":"Point"}
}