{
  "type": "Feature",
  "properties": {
    "addr:full": "5929 Broadview Rd Cleveland OH 44134",
    "addr:housenumber": "5929",
    "addr:postcode": "44134",
    "addr:street": "Broadview Rd",
    "iso:country": "US",
    "sg:address": "5929 Broadview Rd",
    "sg:city": "Cleveland",
    "sg:classifiers": [
      {
        "category": "Building \u0026 Trades",
        "subcategory": "Cleaning \u0026 Sanitation",
        "type": "Services"
      }
    ],
    "sg:phone": "+1 216 398 0444",
    "sg:postcode": "44134",
    "sg:province": "OH",
    "sg:tags": [
      "window"
    ],
    "wof:name": "Always Brite Window Cleaning",
    "wof:placetype": "venue"
  },
  "geometry": {"coordinates":[-81.689472,41.401969],"type":"Point"}
}
