{
  "type": "Feature",
  "properties": {
    "iso:country":"US",
    "sg:address":"5929 Broadview Rd",
    "sg:city":"Cleveland",
    "sg:classifiers":[
        {
            "category":"Building & Trades",
            "subcategory":"Cleaning & Sanitation",
            "type":"Services"
        }
    ],
    "sg:phone":"+1 216 398 0444",
    "sg:postcode":"44134",
    "sg:province":"OH",
    "sg:tags":[
        "window"
    ],
    "wof:name":"Always Brite Window Cleaning",
    "wof:placetype":"venue"
},
  "geometry": {"coordinates":[-81.68947199999999,41.401969],"type":"Point"}
}