{
  "type": "Feature",
  "properties": {
    "iso:country":"US",
    "sg:address":"2125 E Dorothy Ln",
    "sg:city":"Dayton",
    "sg:classifiers":[
        {
            "category":"Shopping",
            "subcategory":"Florist",
            "type":"Retail Goods"
        }
    ],
    "sg:phone":"+1 937 298 5744",
    "sg:postcode":"45420",
    "sg:province":"OH",
    "wof:name":"Throckmorton's Flowers & Gifts",
    "wof:placetype":"venue"
},
  "geometry": {"coordinates":[-84.12343300000001,39.702744],"type":"Point"}
}