{
  "type": "Feature",
  "properties": {
    "addr:full": "2125 E Dorothy Ln Dayton OH 45420",
    "addr:housenumber": "2125",
    "addr:postcode": "45420",
    "addr:street": "E Dorothy Ln",
    "iso:country": "US",
    "sg:address": "2125 E Dorothy Ln",
    "sg:city": "Dayton",
    "sg:classifiers": [
      {
        "category": "Shopping",
        "subcategory": "Florist",
        "type": "Retail Goods"
      }
    ],
    "sg:phone": "+1 937 298 5744",
    "sg:postcode": "45420",
    "sg:province": "OH",
    "wof:name": "Throckmorton's Flowers \u0026 Gifts",
    "wof:placetype": "venue"
  },
  "geometry": {"coordinates":[-84.123433,39.702744],"type":"Point"}
}
