{
  "type": "Feature",
  "properties": {
    "addr:full": "201 Great Oaks Trl Wadsworth OH 44281",
    "addr:housenumber": "201",
    "addr:postcode": "44281",
    "addr:street": "Great Oaks Trl",
    "iso:country": "US",
    "sg:address": "201 Great Oaks Trl",
    "sg:city": "Wadsworth",
    "sg:classifiers": [
      {
        "category": "Recreation",
        "type": "Entertainment"
      }
    ],
    "sg:phone": "+1 330 334 3200",
    "sg:postcode": "44281",
    "sg:province": "OH",
    "sg:tags": [
      "instruction",
      "gymnastic"
    ],
    "wof:name": "Tumblebee's",
    "wof:placetype": "venue"
  },
  "geometry": {"coordinates":[-81.732683,41.048991],"type":"Point"}
}
