{
  "type": "Feature",
  "properties": {
    "addr:full":"11780 Headapohl Rd Wapakoneta OH 45895",
    "addr:housenumber":"11780",
    "addr:postcode":"45895",
    "addr:street":"Headapohl Rd",
    "iso:country":"US",
    "sg:address":"11780 Headapohl Rd",
    "sg:city":"Wapakoneta",
    "sg:classifiers":[
        {
            "category":"Professional",
            "type":"Services"
        }
    ],
    "sg:phone":"+1 419 753 2788",
    "sg:postcode":"45895",
    "sg:province":"OH",
    "sg:tags":[
        "establishment"
    ],
    "sg:website":"www.tipllc.com",
    "wof:name":"Technology Integration",
    "wof:placetype":"venue"
},
  "geometry": {"coordinates":[-84.245175,40.50396],"type":"Point"}
}