{
  "type": "Feature",
  "properties": {
    "addr:full":"1703 Toll Gate Dr Maumee OH 43537",
    "addr:housenumber":"1703",
    "addr:postcode":"43537",
    "addr:street":"Toll Gate Dr",
    "iso:country":"US",
    "sg:address":"1703 Toll Gate Dr",
    "sg:city":"Maumee",
    "sg:classifiers":[
        {
            "category":"Personal",
            "subcategory":"Tanning Parlor",
            "type":"Services"
        }
    ],
    "sg:phone":"+1 419 893 3038",
    "sg:postcode":"43537",
    "sg:province":"OH",
    "sg:tags":[
        "salon"
    ],
    "sg:website":"www.360fitness.com",
    "wof:name":"Jamaican Tanning Resort",
    "wof:placetype":"venue"
},
  "geometry": {"coordinates":[-83.666661,41.58838],"type":"Point"}
}