{
  "type": "Feature",
  "properties": {
    "addr:full": "661 Williams Ave Hamilton OH 45015",
    "addr:housenumber": "661",
    "addr:postcode": "45015",
    "addr:street": "Williams Ave",
    "iso:country": "US",
    "sg:address": "661 Williams Ave",
    "sg:city": "Hamilton",
    "sg:classifiers": [
      {
        "category": "Manufacturing",
        "subcategory": "Rubber \u0026 Plastics",
        "type": "Manufacturing \u0026 Wholesale Goods"
      }
    ],
    "sg:phone": "+1 513 868 8890",
    "sg:postcode": "45015",
    "sg:province": "OH",
    "sg:tags": [
      "conductive",
      "product",
      "wiring",
      "devices",
      "mfg"
    ],
    "sg:website": "www.kathom.com",
    "wof:name": "Kathom Manufacturing Co Inc",
    "wof:placetype": "venue"
  },
  "geometry": {"coordinates":[-84.556413,39.373365],"type":"Point"}
}
