{
  "type": "Feature",
  "properties": {
    "addr:full": "9545 Midwest Ave Cleveland OH 44125",
    "addr:housenumber": "9545",
    "addr:postcode": "44125",
    "addr:street": "Midwest Ave",
    "iso:country": "US",
    "sg:address": "9545 Midwest Ave",
    "sg:city": "Cleveland",
    "sg:classifiers": [
      {
        "category": "Building \u0026 Trades",
        "subcategory": "Construction",
        "type": "Services"
      }
    ],
    "sg:phone": "+1 216 823 0064",
    "sg:postcode": "44125",
    "sg:province": "OH",
    "sg:tags": [
      "painter"
    ],
    "wof:name": "Certa Pro Painters",
    "wof:placetype": "venue"
  },
  "geometry": {"coordinates":[-81.619471,41.419653],"type":"Point"}
}
