{
  "type": "Feature",
  "properties": {
    "addr:full": "897 W Broad St Columbus OH 43222",
    "addr:housenumber": "897",
    "addr:postcode": "43222",
    "addr:street": "W Broad St",
    "iso:country": "US",
    "sg:address": "897 W Broad St",
    "sg:city": "Columbus",
    "sg:classifiers": [
      {
        "category": "Wholesale",
        "subcategory": "Medical Equipment \u0026 Supplies",
        "type": "Manufacturing \u0026 Wholesale Goods"
      }
    ],
    "sg:phone": "+1 614 237 8017",
    "sg:postcode": "43222",
    "sg:province": "OH",
    "sg:tags": [
      "physician",
      "surgeon"
    ],
    "wof:name": "Diversified Medical Svc Inc",
    "wof:placetype": "venue"
  },
  "geometry": {"coordinates":[-83.024102,39.959296],"type":"Point"}
}
