{
  "type": "Feature",
  "properties": {
    "addr:full": "101 N Whitewoman St Coshocton OH 43812",
    "addr:housenumber": "101",
    "addr:postcode": "43812",
    "addr:street": "N Whitewoman St",
    "iso:country": "US",
    "sg:address": "101 N Whitewoman St",
    "sg:city": "Coshocton",
    "sg:classifiers": [
      {
        "category": "Government",
        "subcategory": "Office",
        "type": "Public Place"
      },
      {
        "category": "Social Services",
        "type": "Services"
      }
    ],
    "sg:phone": "+1 740 622 7005",
    "sg:postcode": "43812",
    "sg:province": "OH",
    "sg:tags": [
      "city",
      "program",
      "worker"
    ],
    "wof:name": "Coshocton Port Authority",
    "wof:placetype": "venue"
  },
  "geometry": {"coordinates":[-81.876416,40.27917],"type":"Point"}
}
