{
  "type": "Feature",
  "properties": {
    "addr:full":"95 Edgebrook Dr Springboro OH 45066",
    "addr:housenumber":"95",
    "addr:postcode":"45066",
    "addr:street":"Edgebrook Dr",
    "iso:country":"US",
    "sg:address":"95 Edgebrook Dr",
    "sg:city":"Springboro",
    "sg:classifiers":[
        {
            "category":"Professional",
            "subcategory":"Lawyer & Legal Services",
            "type":"Services"
        }
    ],
    "sg:phone":"+1 937 748 6700",
    "sg:postcode":"45066",
    "sg:province":"OH",
    "sg:tags":[
        "attorney"
    ],
    "wof:name":"Stanley E Kolb",
    "wof:placetype":"venue"
},
  "geometry": {"coordinates":[-84.236401,39.557951],"type":"Point"}
}