{
  "type": "Feature",
  "properties": {
    "iso:country":"US",
    "sg:address":"16240 Dresden Ave",
    "sg:city":"East Liverpool",
    "sg:classifiers":[
        {
            "category":"Restaurant",
            "type":"Food & Drink"
        }
    ],
    "sg:phone":"+1 330 385 4200",
    "sg:postcode":"43920",
    "sg:province":"OH",
    "sg:tags":[
        "eating"
    ],
    "wof:name":"Hungry Howies Pizza",
    "wof:placetype":"venue"
},
  "geometry": {"coordinates":[-80.588115,40.659295],"type":"Point"}
}