{
  "type": "Feature",
  "properties": {
    "addr:full":"8001 S Suburban Rd Dayton OH 45458",
    "addr:housenumber":"8001",
    "addr:postcode":"45458",
    "addr:street":"S Suburban Rd",
    "iso:country":"US",
    "sg:address":"8001 S Suburban Rd",
    "sg:city":"Dayton",
    "sg:classifiers":[
        {
            "category":"Professional",
            "subcategory":"Business Services",
            "type":"Services"
        }
    ],
    "sg:phone":"+1 937 438 0141",
    "sg:postcode":"45458",
    "sg:province":"OH",
    "sg:tags":[
        "paper"
    ],
    "wof:name":"Cintas Document Management",
    "wof:placetype":"venue"
},
  "geometry": {"coordinates":[-84.141364,39.624999],"type":"Point"}
}