{
  "type": "Feature",
  "properties": {
    "addr:full": "1602 S Raccoon Rd Youngstown OH 44515",
    "addr:housenumber": "1602",
    "addr:postcode": "44515",
    "addr:street": "S Raccoon Rd",
    "iso:country": "US",
    "sg:address": "1602 S Raccoon Rd",
    "sg:city": "Youngstown",
    "sg:classifiers": [
      {
        "category": "Restaurant",
        "type": "Food \u0026 Drink"
      }
    ],
    "sg:phone": "+1 330 779 3166",
    "sg:postcode": "44515",
    "sg:province": "OH",
    "sg:tags": [
      "american",
      "italian"
    ],
    "wof:name": "Antonios",
    "wof:placetype": "venue"
  },
  "geometry": {"coordinates":[-80.732395,41.08605],"type":"Point"}
}
