{
  "type": "Feature",
  "properties": {
    "iso:country":"US",
    "sg:address":"1316 Mudbrook Rd",
    "sg:city":"Huron",
    "sg:classifiers":[
        {
            "category":"Sports & Exercise",
            "subcategory":"Golf",
            "type":"Entertainment"
        }
    ],
    "sg:phone":"+1 419 433 4552",
    "sg:postcode":"44839",
    "sg:province":"OH",
    "sg:tags":[
        "p",
        "sporting",
        "eating",
        "public",
        "course"
    ],
    "wof:name":"Thunderbird Hills Golf Club",
    "wof:placetype":"venue"
},
  "geometry": {"coordinates":[-82.56617,41.380951],"type":"Point"}
}