{
  "type": "Feature",
  "properties": {
    "addr:full": "4776 Albany Park Dr New Albany OH 43054",
    "addr:housenumber": "4776",
    "addr:postcode": "43054",
    "addr:street": "Albany Park Dr",
    "iso:country": "US",
    "sg:address": "4776 Albany Park Dr",
    "sg:city": "New Albany",
    "sg:classifiers": [
      {
        "category": "Building \u0026 Trades",
        "subcategory": "Construction",
        "type": "Services"
      }
    ],
    "sg:phone": "+1 614 939 9700",
    "sg:postcode": "43054",
    "sg:province": "OH",
    "sg:tags": [
      "home",
      "builder"
    ],
    "wof:name": "Dominion Homes Inc",
    "wof:placetype": "venue"
  },
  "geometry": {"coordinates":[-82.848002,40.078422],"type":"Point"}
}
