{
  "type": "Feature",
  "properties": {
    "addr:full": "2352 Kajean Ave Dayton OH 45439",
    "addr:housenumber": "2352",
    "addr:postcode": "45439",
    "addr:street": "Kajean Ave",
    "iso:country": "US",
    "sg:address": "2352 Kajean Ave",
    "sg:city": "Dayton",
    "sg:classifiers": [
      {
        "category": "Shopping",
        "subcategory": "Bicycles \u0026 Sporting Goods",
        "type": "Retail Goods"
      }
    ],
    "sg:phone": "+1 937 293 6255",
    "sg:postcode": "45439",
    "sg:province": "OH",
    "wof:name": "Deatons Sports Shop",
    "wof:placetype": "venue"
  },
  "geometry": {"coordinates":[-84.210465,39.688103],"type":"Point"}
}
