{
  "type": "Feature",
  "properties": {
    "addr:full": "3548 Vista Ave Apt 2 Cincinnati OH 45208",
    "addr:housenumber": "3548;2",
    "addr:postcode": "45208",
    "addr:street": "Vista Ave Apt",
    "iso:country": "US",
    "sg:address": "3548 Vista Ave Apt 2",
    "sg:city": "Cincinnati",
    "sg:classifiers": [
      {
        "category": "Shopping",
        "subcategory": "Books",
        "type": "Retail Goods"
      },
      {
        "category": "Wholesale",
        "subcategory": "Books, Periodicals, \u0026 Newspapers",
        "type": "Manufacturing \u0026 Wholesale Goods"
      }
    ],
    "sg:phone": "+1 513 305 0026",
    "sg:postcode": "45208",
    "sg:province": "OH",
    "sg:tags": [
      "books-wholesale",
      "store",
      "manufacturer"
    ],
    "wof:name": "Dusk Books",
    "wof:placetype": "venue"
  },
  "geometry": {"coordinates":[-84.456747,39.141986],"type":"Point"}
}
