{
  "type": "Feature",
  "properties": {
    "addr:full":"38669 Mentor Ave Willoughby OH 44094",
    "addr:postcode":"38669;44094",
    "addr:street":"Mentor Ave",
    "iso:country":"US",
    "sg:address":"38669 Mentor Ave",
    "sg:city":"Willoughby",
    "sg:classifiers":[
        {
            "category":"Retail",
            "subcategory":"Self-service Laundry",
            "type":"Services"
        }
    ],
    "sg:phone":"+1 440 602 9592",
    "sg:postcode":"44094",
    "sg:province":"OH",
    "wof:name":"Juniors Coin Laundry & Tanning",
    "wof:placetype":"venue"
},
  "geometry": {"coordinates":[-81.396168,41.643552],"type":"Point"}
}