{
  "type": "Feature",
  "properties": {
    "iso:country":"US",
    "sg:address":"441 E State Line Rd",
    "sg:city":"Toledo",
    "sg:classifiers":[
        {
            "category":"Building & Trades",
            "subcategory":"Construction",
            "type":"Services"
        }
    ],
    "sg:phone":"+1 419 478 9535",
    "sg:postcode":"43612",
    "sg:province":"OH",
    "sg:tags":[
        "concrete",
        "contractor"
    ],
    "sg:website":"www.meridieth.com",
    "wof:name":"Meridieth Construction Inc",
    "wof:placetype":"venue"
},
  "geometry": {"coordinates":[-83.53448400000001,41.729038],"type":"Point"}
}