{
  "type": "Feature",
  "properties": {
    "iso:country":"US",
    "sg:address":"3015 Glendale Ave",
    "sg:city":"Toledo",
    "sg:classifiers":[
        {
            "category":"Shopping",
            "subcategory":"Clothing, Apparel, & Fashions",
            "type":"Retail Goods"
        }
    ],
    "sg:phone":"+1 419 382 0166",
    "sg:postcode":"43614",
    "sg:province":"OH",
    "wof:name":"Dots Fashions",
    "wof:placetype":"venue"
},
  "geometry": {"coordinates":[-83.617909,41.612251],"type":"Point"}
}