{
  "type": "Feature",
  "properties": {
    "iso:country":"US",
    "sg:address":"2500 Corporate Exchange Dr",
    "sg:city":"Columbus",
    "sg:classifiers":[
        {
            "category":"Banks & Credit Unions",
            "subcategory":"Bank",
            "type":"Services"
        }
    ],
    "sg:phone":"+1 614 901 8440",
    "sg:postcode":"43231",
    "sg:province":"OH",
    "sg:tags":[
        "loan",
        "real estate"
    ],
    "wof:name":"Opetion One Mortgage",
    "wof:placetype":"venue"
},
  "geometry": {"coordinates":[-82.942744,40.101687],"type":"Point"}
}