{
  "type": "Feature",
  "properties": {
    "addr:full": "1184 E 61st St Cleveland OH 44103",
    "addr:housenumber": "1184",
    "addr:postcode": "44103",
    "addr:street": "E 61St St",
    "iso:country": "US",
    "sg:address": "1184 E 61st St",
    "sg:city": "Cleveland",
    "sg:classifiers": [
      {
        "category": "Professional",
        "subcategory": "Business Services",
        "type": "Services"
      }
    ],
    "sg:phone": "+1 216 426 0025",
    "sg:postcode": "44103",
    "sg:province": "OH",
    "sg:tags": [
      "diver"
    ],
    "wof:name": "South Shore Diving \u0026 Harbor",
    "wof:placetype": "venue"
  },
  "geometry": {"coordinates":[-81.647927,41.522152],"type":"Point"}
}
