{
  "type": "Feature",
  "properties": {
    "addr:full":"4024 Plainville Rd Cincinnati OH 45227",
    "addr:housenumber":"4024",
    "addr:postcode":"45227",
    "addr:street":"Plainville Rd",
    "iso:country":"US",
    "sg:address":"4024 Plainville Rd",
    "sg:city":"Cincinnati",
    "sg:classifiers":[
        {
            "category":"Retail",
            "subcategory":"Auto Repair",
            "type":"Services"
        }
    ],
    "sg:phone":"+1 513 271 7003",
    "sg:postcode":"45227",
    "sg:province":"OH",
    "sg:tags":[
        "repairing",
        "automobile"
    ],
    "wof:name":"Dav's Complete Auto Repair",
    "wof:placetype":"venue"
},
  "geometry": {"coordinates":[-84.37916300000001,39.148757],"type":"Point"}
}