{
  "type": "Feature",
  "properties": {
    "iso:country":"US",
    "sg:address":"770 Lakeshore Blvd",
    "sg:city":"Painesville",
    "sg:classifiers":[
        {
            "category":"Recreation",
            "subcategory":"Marina",
            "type":"Entertainment"
        }
    ],
    "sg:phone":"+1 440 354 8100",
    "sg:postcode":"44077",
    "sg:province":"OH",
    "sg:tags":[
        "operation",
        "station",
        "gasoline",
        "boat"
    ],
    "wof:name":"Boating Headquarters Inc",
    "wof:placetype":"venue"
},
  "geometry": {"coordinates":[-81.291445,41.729428],"type":"Point"}
}