{
  "type": "Feature",
  "properties": {
    "addr:full":"12 W Park Pl Oxford OH 45056",
    "addr:housenumber":"12",
    "addr:postcode":"45056",
    "addr:street":"W Park Pl",
    "iso:country":"US",
    "sg:address":"12 W Park Pl",
    "sg:city":"Oxford",
    "sg:classifiers":[
        {
            "category":"Real Estate",
            "subcategory":"Real Estate Operator",
            "type":"Services"
        }
    ],
    "sg:phone":"+1 513 523 2015",
    "sg:postcode":"45056",
    "sg:province":"OH",
    "sg:tags":[
        "building",
        "apartment"
    ],
    "wof:name":"Contreras Park",
    "wof:placetype":"venue"
},
  "geometry": {"coordinates":[-84.742497,39.511047],"type":"Point"}
}