{
  "type": "Feature",
  "properties": {
    "addr:full": "162 Chestnut St Painesville OH 44077",
    "addr:housenumber": "162",
    "addr:postcode": "44077",
    "addr:street": "Chestnut St",
    "iso:country": "US",
    "sg:address": "162 Chestnut St",
    "sg:city": "Painesville",
    "sg:classifiers": [
      {
        "category": "Food \u0026 Beverages",
        "subcategory": "Liquor \u0026 Beverages",
        "type": "Retail Goods"
      }
    ],
    "sg:phone": "+1 440 357 7368",
    "sg:postcode": "44077",
    "sg:province": "OH",
    "sg:tags": [
      "beer",
      "ale"
    ],
    "wof:name": "Lina's Beverage \u0026 Cigarette",
    "wof:placetype": "venue"
  },
  "geometry": {"coordinates":[-81.258835,41.709765],"type":"Point"}
}
