{
  "type": "Feature",
  "properties": {
    "iso:country":"US",
    "sg:address":"162 Chestnut St",
    "sg:city":"Painesville",
    "sg:classifiers":[
        {
            "category":"Food & Beverages",
            "subcategory":"Liquor & Beverages",
            "type":"Retail Goods"
        }
    ],
    "sg:phone":"+1 440 357 7368",
    "sg:postcode":"44077",
    "sg:province":"OH",
    "sg:tags":[
        "beer",
        "ale"
    ],
    "wof:name":"Lina's Beverage & Cigarette",
    "wof:placetype":"venue"
},
  "geometry": {"coordinates":[-81.258835,41.709765],"type":"Point"}
}