{
  "type": "Feature",
  "properties": {
    "addr:full": "224 N Market St Loudonville OH 44842",
    "addr:housenumber": "224",
    "addr:postcode": "44842",
    "addr:street": "N Market St",
    "iso:country": "US",
    "sg:address": "224 N Market St",
    "sg:city": "Loudonville",
    "sg:classifiers": [
      {
        "category": "Building \u0026 Trades",
        "subcategory": "Construction",
        "type": "Services"
      }
    ],
    "sg:phone": "+1 419 994 5400",
    "sg:postcode": "44842",
    "sg:province": "OH",
    "sg:tags": [
      "house",
      "nonresidential"
    ],
    "sg:website": "www.websterbuild.com",
    "wof:name": "Webster Building \u0026 Design",
    "wof:placetype": "venue"
  },
  "geometry": {"coordinates":[-82.23329,40.636958],"type":"Point"}
}
