{
  "type": "Feature",
  "properties": {
    "addr:full":"503 Co Rd 24 S De Graff OH 43318",
    "addr:housenumber":"503;24",
    "addr:postcode":"43318",
    "addr:street":"Co Rd;S",
    "iso:country":"US",
    "sg:address":"503 Co Rd 24 S",
    "sg:city":"De Graff",
    "sg:classifiers":[
        {
            "category":"Farming",
            "subcategory":"Livestock Farm",
            "type":"Manufacturing & Wholesale Goods"
        }
    ],
    "sg:phone":"+1 937 585 6130",
    "sg:postcode":"43318",
    "sg:province":"OH",
    "sg:tags":[
        "beef",
        "feedlot",
        "cattle"
    ],
    "wof:name":"David Knight",
    "wof:placetype":"venue"
},
  "geometry": {"coordinates":[-83.925132,40.339118],"type":"Point"}
}