{
  "type": "Feature",
  "properties": {
    "iso:country":"US",
    "sg:address":"505 W Market St",
    "sg:city":"Lima",
    "sg:classifiers":[
        {
            "category":"Shopping",
            "subcategory":"Pharmacy",
            "type":"Retail Goods"
        }
    ],
    "sg:phone":"+1 419 222 7797",
    "sg:postcode":"45801",
    "sg:province":"OH",
    "sg:tags":[
        "drug",
        "store"
    ],
    "wof:name":"Rite Aid",
    "wof:placetype":"venue"
},
  "geometry": {"coordinates":[-84.110755,40.739915],"type":"Point"}
}