{
  "type": "Feature",
  "properties": {
    "iso:country":"US",
    "sg:address":"208 S Summit St",
    "sg:city":"Toledo",
    "sg:classifiers":[
        {
            "category":"Food & Beverages",
            "subcategory":"Groceries & Convenience Stores",
            "type":"Retail Goods"
        }
    ],
    "sg:phone":"+1 419 255 0544",
    "sg:postcode":"43602",
    "sg:province":"OH",
    "wof:name":"Snappy Mart",
    "wof:placetype":"venue"
},
  "geometry": {"coordinates":[-83.541739,41.641669],"type":"Point"}
}