{
  "type": "Feature",
  "properties": {
    "addr:full": "208 S Summit St Toledo OH 43602",
    "addr:housenumber": "208",
    "addr:postcode": "43602",
    "addr:street": "S Summit St",
    "iso:country": "US",
    "sg:address": "208 S Summit St",
    "sg:city": "Toledo",
    "sg:classifiers": [
      {
        "category": "Food \u0026 Beverages",
        "subcategory": "Groceries \u0026 Convenience Stores",
        "type": "Retail Goods"
      }
    ],
    "sg:phone": "+1 419 255 0544",
    "sg:postcode": "43602",
    "sg:province": "OH",
    "wof:name": "Snappy Mart",
    "wof:placetype": "venue"
  },
  "geometry": {"coordinates":[-83.541739,41.641669],"type":"Point"}
}
