{
  "type": "Feature",
  "properties": {
    "addr:full":"1230 Cranford Ave Lakewood OH 44107",
    "addr:housenumber":"1230",
    "addr:postcode":"44107",
    "addr:street":"Cranford Ave",
    "iso:country":"US",
    "sg:address":"1230 Cranford Ave",
    "sg:city":"Lakewood",
    "sg:classifiers":[
        {
            "category":"Shopping",
            "subcategory":"Bicycles & Sporting Goods",
            "type":"Retail Goods"
        }
    ],
    "sg:phone":"+1 216 221 3264",
    "sg:postcode":"44107",
    "sg:province":"OH",
    "wof:name":"Custom Golf Shop",
    "wof:placetype":"venue"
},
  "geometry": {"coordinates":[-81.80981,41.489504],"type":"Point"}
}