{
  "type": "Feature",
  "properties": {
    "iso:country":"US",
    "sg:address":"45 Ludlow St",
    "sg:city":"Hamilton",
    "sg:classifiers":[
        {
            "category":"Wholesale",
            "subcategory":"Stationery",
            "type":"Manufacturing & Wholesale Goods"
        }
    ],
    "sg:phone":"+1 513 863 3400",
    "sg:postcode":"45011",
    "sg:province":"OH",
    "sg:tags":[
        "business",
        "form",
        "system"
    ],
    "wof:name":"ACS Printer Supplies & Svc",
    "wof:placetype":"venue"
},
  "geometry": {"coordinates":[-84.564849,39.398328],"type":"Point"}
}