{
  "type": "Feature",
  "properties": {
    "addr:full":"4249 Colerain Ave Cincinnati OH 45223",
    "addr:housenumber":"4249",
    "addr:postcode":"45223",
    "addr:street":"Colerain Ave",
    "iso:country":"US",
    "sg:address":"4249 Colerain Ave",
    "sg:city":"Cincinnati",
    "sg:classifiers":[
        {
            "category":"Building & Trades",
            "subcategory":"Construction",
            "type":"Services"
        }
    ],
    "sg:phone":"+1 513 681 4618",
    "sg:postcode":"45223",
    "sg:province":"OH",
    "sg:tags":[
        "contractor"
    ],
    "wof:name":"Modesto Masonry",
    "wof:placetype":"venue"
},
  "geometry": {"coordinates":[-84.549268,39.162673],"type":"Point"}
}