{
  "type": "Feature",
  "properties": {
    "addr:full":"4822 Gilead St Mt Gilead OH 43338",
    "addr:housenumber":"4822",
    "addr:postcode":"43338",
    "addr:street":"Gilead St",
    "iso:country":"US",
    "sg:address":"4822 Gilead St",
    "sg:city":"Mt Gilead",
    "sg:classifiers":[
        {
            "category":"Building & Trades",
            "subcategory":"Plumbing",
            "type":"Services"
        }
    ],
    "sg:phone":"+1 419 946 6833",
    "sg:postcode":"43338",
    "sg:province":"OH",
    "sg:tags":[
        "tank",
        "septic"
    ],
    "wof:name":"Howell's Septic Tank Cleaning",
    "wof:placetype":"venue"
},
  "geometry": {"coordinates":[-82.83685800000001,40.516532],"type":"Point"}
}