{
  "type": "Feature",
  "properties": {
    "addr:full":"3003 Observatory Ave Cincinnati OH 45208",
    "addr:housenumber":"3003",
    "addr:postcode":"45208",
    "addr:street":"Observatory Ave",
    "iso:country":"US",
    "sg:address":"3003 Observatory Ave",
    "sg:city":"Cincinnati",
    "sg:classifiers":[
        {
            "category":"Professional",
            "type":"Services"
        }
    ],
    "sg:phone":"+1 513 623 4027",
    "sg:postcode":"45208",
    "sg:province":"OH",
    "wof:name":"Victor A Walton Jr",
    "wof:placetype":"venue"
},
  "geometry": {"coordinates":[-84.432091,39.136857],"type":"Point"}
}