{
  "type": "Feature",
  "properties": {
    "addr:full":"116 W Herrick Ave Wellington OH 44090",
    "addr:housenumber":"116",
    "addr:postcode":"44090",
    "addr:street":"W Herrick Ave",
    "iso:country":"US",
    "sg:address":"116 W Herrick Ave",
    "sg:city":"Wellington",
    "sg:classifiers":[
        {
            "category":"Home & Garden",
            "subcategory":"Carpets & Floor Coverings",
            "type":"Retail Goods"
        }
    ],
    "sg:phone":"+1 440 647 3490",
    "sg:postcode":"44090",
    "sg:province":"OH",
    "sg:tags":[
        "dealer",
        "rug"
    ],
    "wof:name":"Improvements By Corner Stone",
    "wof:placetype":"venue"
},
  "geometry": {"coordinates":[-82.218052,41.168648],"type":"Point"}
}