{
  "type": "Feature",
  "properties": {
    "addr:full":"3970 Catawba St Toledo OH 43612",
    "addr:housenumber":"3970",
    "addr:postcode":"43612",
    "addr:street":"Catawba St",
    "iso:country":"US",
    "sg:address":"3970 Catawba St",
    "sg:city":"Toledo",
    "sg:classifiers":[
        {
            "category":"Manufacturing",
            "subcategory":"Food",
            "type":"Manufacturing & Wholesale Goods"
        }
    ],
    "sg:phone":"+1 419 476 6622",
    "sg:postcode":"43612",
    "sg:province":"OH",
    "sg:tags":[
        "bottler"
    ],
    "wof:name":"Coca-Cola Bottling Co",
    "wof:placetype":"venue"
},
  "geometry": {"coordinates":[-83.549621,41.691394],"type":"Point"}
}