{
  "type": "Feature",
  "properties": {
    "addr:full":"29449 Edgedale Rd Cleveland OH 44124",
    "addr:postcode":"29449;44124",
    "addr:street":"Edgedale Rd",
    "iso:country":"US",
    "sg:address":"29449 Edgedale Rd",
    "sg:city":"Cleveland",
    "sg:classifiers":[
        {
            "category":"Banks & Credit Unions",
            "subcategory":"Financial Services",
            "type":"Services"
        }
    ],
    "sg:phone":"+1 216 360 8860",
    "sg:postcode":"44124",
    "sg:province":"OH",
    "sg:tags":[
        "company",
        "holding"
    ],
    "wof:name":"Magnate Holdings",
    "wof:placetype":"venue"
},
  "geometry": {"coordinates":[-81.474727,41.482114],"type":"Point"}
}