{
  "type": "Feature",
  "properties": {
    "addr:full":"800 Kent Rd Batavia OH 45103",
    "addr:housenumber":"800",
    "addr:postcode":"45103",
    "addr:street":"Kent Rd",
    "iso:country":"US",
    "sg:address":"800 Kent Rd",
    "sg:city":"Batavia",
    "sg:classifiers":[
        {
            "category":"Manufacturing",
            "subcategory":"Tools & Machinery",
            "type":"Manufacturing & Wholesale Goods"
        }
    ],
    "sg:phone":"+1 513 732 2200",
    "sg:postcode":"45103",
    "sg:province":"OH",
    "sg:tags":[
        "conveying",
        "industrial",
        "mfg",
        "i",
        "conveyor",
        "equipment"
    ],
    "sg:website":"www.scott-randallsystems.com",
    "wof:name":"Scott-Randall Systems Inc",
    "wof:placetype":"venue"
},
  "geometry": {"coordinates":[-84.19244500000001,39.084695],"type":"Point"}
}