{
  "type": "Feature",
  "properties": {
    "addr:full":"5407 Turney Rd Cleveland OH 44125",
    "addr:housenumber":"5407",
    "addr:postcode":"44125",
    "addr:street":"Turney Rd",
    "iso:country":"US",
    "sg:address":"5407 Turney Rd",
    "sg:city":"Cleveland",
    "sg:classifiers":[
        {
            "category":"Government",
            "subcategory":"Office",
            "type":"Public Place"
        }
    ],
    "sg:phone":"+1 216 475 1100",
    "sg:postcode":"44125",
    "sg:province":"OH",
    "sg:tags":[
        "city"
    ],
    "sg:website":"www.garfieldhts.org",
    "wof:name":"Garfield Heights City Hall",
    "wof:placetype":"venue"
},
  "geometry": {"coordinates":[-81.605,41.415546],"type":"Point"}
}