{
  "type": "Feature",
  "properties": {
    "iso:country":"US",
    "sg:address":"7585 Race Rd",
    "sg:city":"North Ridgeville",
    "sg:classifiers":[
        {
            "category":"Building & Trades",
            "subcategory":"Construction",
            "type":"Services"
        }
    ],
    "sg:phone":"+1 440 322 3088",
    "sg:postcode":"44039",
    "sg:province":"OH",
    "sg:tags":[
        "waterproofing",
        "contractor"
    ],
    "wof:name":"Elyria Pressure Seal",
    "wof:placetype":"venue"
},
  "geometry": {"coordinates":[-82.044293,41.381194],"type":"Point"}
}