{
  "type": "Feature",
  "properties": {
    "addr:full":"671 Alpha Rd Dayton OH 45434",
    "addr:housenumber":"671",
    "addr:postcode":"45434",
    "addr:street":"Alpha Rd",
    "iso:country":"US",
    "sg:address":"671 Alpha Rd",
    "sg:city":"Dayton",
    "sg:classifiers":[
        {
            "category":"Banks & Credit Unions",
            "subcategory":"Bank",
            "type":"Services"
        }
    ],
    "sg:phone":"+1 937 320 0512",
    "sg:postcode":"45434",
    "sg:province":"OH",
    "sg:tags":[
        "loan",
        "real estate"
    ],
    "wof:name":"CTX",
    "wof:placetype":"venue"
},
  "geometry": {"coordinates":[-84.026483,39.707333],"type":"Point"}
}