{
  "type": "Feature",
  "properties": {
    "addr:full": "6182 Chambersburg Rd Dayton OH 45424",
    "addr:postcode": "6182;45424",
    "addr:street": "Chambersburg Rd",
    "iso:country": "US",
    "sg:address": "6182 Chambersburg Rd",
    "sg:city": "Dayton",
    "sg:classifiers": [
      {
        "category": "Professional",
        "subcategory": "Business Services",
        "type": "Services"
      }
    ],
    "sg:phone": "+1 937 235 0441",
    "sg:postcode": "45424",
    "sg:province": "OH",
    "sg:tags": [
      "equipment",
      "industrial"
    ],
    "wof:name": "Embroidery Creations Inc",
    "wof:placetype": "venue"
  },
  "geometry": {"coordinates":[-84.119373,39.847144],"type":"Point"}
}
