{
  "type": "Feature",
  "properties": {
    "iso:country":"US",
    "sg:address":"6812 Middle Ridge Rd",
    "sg:city":"Madison",
    "sg:classifiers":[
        {
            "category":"Freight",
            "type":"Transportation"
        }
    ],
    "sg:phone":"+1 440 428 6602",
    "sg:postcode":"44057",
    "sg:province":"OH",
    "sg:tags":[
        "operator",
        "local",
        "trucking"
    ],
    "wof:name":"Double D Delivery Inc",
    "wof:placetype":"venue"
},
  "geometry": {"coordinates":[-81.034071,41.789536],"type":"Point"}
}