{
  "type": "Feature",
  "properties": {
    "addr:full": "200 Techne Center Dr Milford OH 45150",
    "addr:housenumber": "200",
    "addr:postcode": "45150",
    "addr:street": "Techne Center Dr",
    "iso:country": "US",
    "sg:address": "200 Techne Center Dr",
    "sg:city": "Milford",
    "sg:classifiers": [
      {
        "category": "Professional",
        "subcategory": "Computer Services",
        "type": "Services"
      }
    ],
    "sg:phone": "+1 513 831 8973",
    "sg:postcode": "45150",
    "sg:province": "OH",
    "sg:tags": [
      "system",
      "cad"
    ],
    "sg:website": "www.techcad.com",
    "wof:name": "Tech CAD",
    "wof:placetype": "venue"
  },
  "geometry": {"coordinates":[-84.254457,39.153493],"type":"Point"}
}
