{
  "type": "Feature",
  "properties": {
    "addr:full":"2965 Columbus St Grove City OH 43123",
    "addr:housenumber":"2965",
    "addr:postcode":"43123",
    "addr:street":"Columbus St",
    "iso:country":"US",
    "sg:address":"2965 Columbus St",
    "sg:city":"Grove City",
    "sg:classifiers":[
        {
            "category":"Health Services",
            "subcategory":"Doctor",
            "type":"Services"
        }
    ],
    "sg:phone":"+1 614 875 4222",
    "sg:postcode":"43123",
    "sg:province":"OH",
    "sg:tags":[
        "dentist"
    ],
    "wof:name":"Michael J Freeman Associates",
    "wof:placetype":"venue"
},
  "geometry": {"coordinates":[-83.08392000000001,39.881496],"type":"Point"}
}