{
  "type": "Feature",
  "properties": {
    "iso:country":"US",
    "sg:address":"160 W Main St",
    "sg:city":"Lancaster",
    "sg:classifiers":[
        {
            "category":"Shopping",
            "subcategory":"Jewelry",
            "type":"Retail Goods"
        }
    ],
    "sg:phone":"+1 740 653 1593",
    "sg:postcode":"43130",
    "sg:province":"OH",
    "sg:tags":[
        "jeweler"
    ],
    "wof:name":"Burtic Jewelers Inc",
    "wof:placetype":"venue"
},
  "geometry": {"coordinates":[-82.603228,39.7137],"type":"Point"}
}