{
  "type": "Feature",
  "properties": {
    "iso:country":"US",
    "sg:address":"5529 W Middletown Rd",
    "sg:city":"Canfield",
    "sg:classifiers":[
        {
            "category":"Wholesale",
            "subcategory":"Dairy",
            "type":"Manufacturing & Wholesale Goods"
        }
    ],
    "sg:phone":"+1 330 533 2309",
    "sg:postcode":"44406",
    "sg:province":"OH",
    "sg:tags":[
        "product"
    ],
    "wof:name":"Esposito Foods Inc",
    "wof:placetype":"venue"
},
  "geometry": {"coordinates":[-80.754046,40.958053],"type":"Point"}
}