{
  "type": "Feature",
  "properties": {
    "addr:full": "535 S Reynolds Rd Toledo OH 43615",
    "addr:housenumber": "535",
    "addr:postcode": "43615",
    "addr:street": "S Reynolds Rd",
    "iso:country": "US",
    "sg:address": "535 S Reynolds Rd",
    "sg:city": "Toledo",
    "sg:classifiers": [
      {
        "category": "Shopping",
        "subcategory": "Department Store",
        "type": "Retail Goods"
      }
    ],
    "sg:phone": "+1 419 536 0710",
    "sg:postcode": "43615",
    "sg:province": "OH",
    "wof:name": "Dollar Daze",
    "wof:placetype": "venue"
  },
  "geometry": {"coordinates":[-83.664434,41.627583],"type":"Point"}
}
