{
  "type": "Feature",
  "properties": {
    "addr:full": "4500 Salem Ave Dayton OH 45416",
    "addr:housenumber": "4500",
    "addr:postcode": "45416",
    "addr:street": "Salem Ave",
    "iso:country": "US",
    "sg:address": "4500 Salem Ave",
    "sg:city": "Dayton",
    "sg:classifiers": [
      {
        "category": "Personal",
        "subcategory": "Beauty Salon",
        "type": "Services"
      }
    ],
    "sg:phone": "+1 937 279 6336",
    "sg:postcode": "45416",
    "sg:province": "OH",
    "sg:tags": [
      "manicuring"
    ],
    "wof:name": "Unique Nailz R Us",
    "wof:placetype": "venue"
  },
  "geometry": {"coordinates":[-84.26421,39.809945],"type":"Point"}
}
