{
  "type": "Feature",
  "properties": {
    "addr:full": "3409 Liberty Ave Vermilion OH 44089",
    "addr:housenumber": "3409",
    "addr:postcode": "44089",
    "addr:street": "Liberty Ave",
    "iso:country": "US",
    "sg:address": "3409 Liberty Ave",
    "sg:city": "Vermilion",
    "sg:classifiers": [
      {
        "category": "Personal",
        "type": "Services"
      }
    ],
    "sg:phone": "+1 440 967 0828",
    "sg:postcode": "44089",
    "sg:province": "OH",
    "sg:tags": [
      "electrolysis"
    ],
    "wof:name": "Tama S Binkley",
    "wof:placetype": "venue"
  },
  "geometry": {"coordinates":[-82.313193,41.424762],"type":"Point"}
}
