{
  "type": "Feature",
  "properties": {
    "addr:full":"4211 Crawford Ave Cincinnati OH 45223",
    "addr:housenumber":"4211",
    "addr:postcode":"45223",
    "addr:street":"Crawford Ave",
    "iso:country":"US",
    "sg:address":"4211 Crawford Ave",
    "sg:city":"Cincinnati",
    "sg:classifiers":[
        {
            "category":"Professional",
            "subcategory":"Advertising",
            "type":"Services"
        }
    ],
    "sg:phone":"+1 513 542 5425",
    "sg:postcode":"45223",
    "sg:province":"OH",
    "sg:tags":[
        "counselor"
    ],
    "sg:website":"www.phcgroupinc.com",
    "wof:name":"PHC Group",
    "wof:placetype":"venue"
},
  "geometry": {"coordinates":[-84.530085,39.163979],"type":"Point"}
}