{
  "type": "Feature",
  "properties": {
    "addr:full":"400 S Westwood Ave Toledo OH 43609",
    "addr:housenumber":"400",
    "addr:postcode":"43609",
    "addr:street":"S Westwood Ave",
    "iso:country":"US",
    "sg:address":"400 S Westwood Ave",
    "sg:city":"Toledo",
    "sg:classifiers":[
        {
            "category":"Real Estate",
            "subcategory":"Real Estate Operator",
            "type":"Services"
        }
    ],
    "sg:phone":"+1 419 385 7294",
    "sg:postcode":"43609",
    "sg:province":"OH",
    "sg:tags":[
        "property",
        "lessor"
    ],
    "wof:name":"Shamrock Assoc",
    "wof:placetype":"venue"
},
  "geometry": {"coordinates":[-83.606678,41.632382],"type":"Point"}
}