{
  "type": "Feature",
  "properties": {
    "addr:full":"4624 Southway St SW Canton OH 44706",
    "addr:housenumber":"4624",
    "addr:postcode":"44706",
    "addr:street":"Southway St Sw",
    "iso:country":"US",
    "sg:address":"4624 Southway St SW",
    "sg:city":"Canton",
    "sg:classifiers":[
        {
            "category":"Building & Trades",
            "subcategory":"Equipment Rental",
            "type":"Services"
        }
    ],
    "sg:phone":"+1 330 478 4157",
    "sg:postcode":"44706",
    "sg:province":"OH",
    "sg:tags":[
        "heavy",
        "construction",
        "rent"
    ],
    "wof:name":"Tractor Parts Inc",
    "wof:placetype":"venue"
},
  "geometry": {"coordinates":[-81.43419299999999,40.781539],"type":"Point"}
}