{
  "type": "Feature",
  "properties": {
    "iso:country":"US",
    "sg:address":"951 Lila Ave",
    "sg:city":"Milford",
    "sg:classifiers":[
        {
            "category":"Home & Garden",
            "subcategory":"Building Materials",
            "type":"Retail Goods"
        }
    ],
    "sg:phone":"+1 513 965 0100",
    "sg:postcode":"45150",
    "sg:province":"OH",
    "wof:name":"Wallpaper Outlet",
    "wof:placetype":"venue"
},
  "geometry": {"coordinates":[-84.273306,39.172451],"type":"Point"}
}