{
  "type": "Feature",
  "properties": {
    "addr:full": "1212 E Stroop Rd Dayton OH 45429",
    "addr:housenumber": "1212",
    "addr:postcode": "45429",
    "addr:street": "E Stroop Rd",
    "iso:country": "US",
    "sg:address": "1212 E Stroop Rd",
    "sg:city": "Dayton",
    "sg:classifiers": [
      {
        "category": "Recreation",
        "type": "Entertainment"
      },
      {
        "category": "Shopping",
        "subcategory": "Bicycles \u0026 Sporting Goods",
        "type": "Retail Goods"
      }
    ],
    "sg:phone": "+1 937 298 2999",
    "sg:postcode": "45429",
    "sg:province": "OH",
    "sg:tags": [
      "equipment",
      "diver",
      "supply"
    ],
    "sg:website": "www.sodadivers.com",
    "wof:name": "Southern Ohio Diving Academy",
    "wof:placetype": "venue"
  },
  "geometry": {"coordinates":[-84.144607,39.688653],"type":"Point"}
}
