{
  "type": "Feature",
  "properties": {
    "iso:country":"US",
    "sg:address":"1212 E Stroop Rd",
    "sg:city":"Dayton",
    "sg:classifiers":[
        {
            "category":"Recreation",
            "type":"Entertainment"
        },
        {
            "category":"Shopping",
            "subcategory":"Bicycles & Sporting Goods",
            "type":"Retail Goods"
        }
    ],
    "sg:phone":"+1 937 298 2999",
    "sg:postcode":"45429",
    "sg:province":"OH",
    "sg:tags":[
        "equipment",
        "diver",
        "supply"
    ],
    "sg:website":"www.sodadivers.com",
    "wof:name":"Southern Ohio Diving Academy",
    "wof:placetype":"venue"
},
  "geometry": {"coordinates":[-84.14460699999999,39.688653],"type":"Point"}
}