{
  "type": "Feature",
  "properties": {
    "iso:country":"US",
    "sg:address":"1320 E Main St",
    "sg:city":"Versailles",
    "sg:classifiers":[
        {
            "category":"Utilities",
            "subcategory":"Refuse",
            "type":"Services"
        }
    ],
    "sg:phone":"+1 937 526 3361",
    "sg:postcode":"45380",
    "sg:province":"OH",
    "sg:tags":[
        "recycling",
        "plastic"
    ],
    "wof:name":"Plastic Recycling Tech Inc",
    "wof:placetype":"venue"
},
  "geometry": {"coordinates":[-84.47083499999999,40.223438],"type":"Point"}
}