{
  "type": "Feature",
  "properties": {
    "iso:country":"US",
    "sg:address":"8040 Reading Rd",
    "sg:city":"Cincinnati",
    "sg:classifiers":[
        {
            "category":"Restaurant",
            "type":"Food & Drink"
        }
    ],
    "sg:phone":"+1 513 821 9500",
    "sg:postcode":"45237",
    "sg:province":"OH",
    "sg:tags":[
        "eating"
    ],
    "wof:name":"Pizza Hut",
    "wof:placetype":"venue"
},
  "geometry": {"coordinates":[-84.45244,39.205697],"type":"Point"}
}