{
  "type": "Feature",
  "properties": {
    "addr:full": "5835 Darrow Rd Hudson OH 44236",
    "addr:housenumber": "5835",
    "addr:postcode": "44236",
    "addr:street": "Darrow Rd",
    "iso:country": "US",
    "sg:address": "5835 Darrow Rd",
    "sg:city": "Hudson",
    "sg:classifiers": [
      {
        "category": "Restaurant",
        "type": "Food \u0026 Drink"
      }
    ],
    "sg:phone": "+1 330 342 0888",
    "sg:postcode": "44236",
    "sg:province": "OH",
    "sg:tags": [
      "eating"
    ],
    "wof:name": "Tai Wah Chinese Restaurant",
    "wof:placetype": "venue"
  },
  "geometry": {"coordinates":[-81.440323,41.227716],"type":"Point"}
}
