{
  "type": "Feature",
  "properties": {
    "addr:full":"5441 Wesley Way Hamilton OH 45011",
    "addr:housenumber":"5441",
    "addr:postcode":"45011",
    "addr:street":"Wesley Way",
    "iso:country":"US",
    "sg:address":"5441 Wesley Way",
    "sg:city":"Hamilton",
    "sg:classifiers":[
        {
            "category":"Manufacturing",
            "subcategory":"Wood Products",
            "type":"Manufacturing & Wholesale Goods"
        },
        {
            "category":"Building & Trades",
            "subcategory":"Construction",
            "type":"Services"
        }
    ],
    "sg:phone":"+1 513 844 8985",
    "sg:postcode":"45011",
    "sg:province":"OH",
    "sg:tags":[
        "mfg",
        "woodworker"
    ],
    "wof:name":"Lacher Custom Woodworking",
    "wof:placetype":"venue"
},
  "geometry": {"coordinates":[-84.47733700000001,39.417995],"type":"Point"}
}