{
  "type": "Feature",
  "properties": {
    "iso:country":"US",
    "sg:address":"436 W Center St",
    "sg:city":"Marion",
    "sg:classifiers":[
        {
            "category":"Professional",
            "subcategory":"Advertising",
            "type":"Services"
        }
    ],
    "sg:phone":"+1 740 383 2141",
    "sg:postcode":"43302",
    "sg:province":"OH",
    "sg:tags":[
        "announcement",
        "temp"
    ],
    "wof:name":"Time & Temperature Rhodes",
    "wof:placetype":"venue"
},
  "geometry": {"coordinates":[-83.137681,40.588533],"type":"Point"}
}