{
  "type": "Feature",
  "properties": {
    "addr:full":"884 Windbourne St Gahanna OH 43230",
    "addr:housenumber":"884",
    "addr:postcode":"43230",
    "addr:street":"Windbourne St",
    "iso:country":"US",
    "sg:address":"884 Windbourne St",
    "sg:city":"Gahanna",
    "sg:classifiers":[
        {
            "category":"Professional",
            "subcategory":"Engineering",
            "type":"Services"
        }
    ],
    "sg:phone":"+1 614 428 1366",
    "sg:postcode":"43230",
    "sg:province":"OH",
    "sg:tags":[
        "engineer"
    ],
    "wof:name":"Synergetic Design Inc",
    "wof:placetype":"venue"
},
  "geometry": {"coordinates":[-82.892386,40.042354],"type":"Point"}
}