{
  "type": "Feature",
  "properties": {
    "iso:country":"US",
    "sg:address":"12 Eagle Dr",
    "sg:city":"Minster",
    "sg:classifiers":[
        {
            "category":"Professional",
            "subcategory":"Lawyer & Legal Services",
            "type":"Services"
        }
    ],
    "sg:phone":"+1 419 628 3232",
    "sg:postcode":"45865",
    "sg:province":"OH",
    "sg:tags":[
        "attorney"
    ],
    "wof:name":"James A Bernhold",
    "wof:placetype":"venue"
},
  "geometry": {"coordinates":[-84.374815,40.402109],"type":"Point"}
}