{
  "type": "Feature",
  "properties": {
    "addr:full":"6949 E Main St Reynoldsburg OH 43068",
    "addr:housenumber":"6949",
    "addr:postcode":"43068",
    "addr:street":"E Main St",
    "iso:country":"US",
    "sg:address":"6949 E Main St",
    "sg:city":"Reynoldsburg",
    "sg:classifiers":[
        {
            "category":"Ice Cream",
            "type":"Food & Drink"
        }
    ],
    "sg:menulink":"http://www.allmenus.com/oh/truro/165279-dairy-queen/menu/",
    "sg:phone":"+1 614 863 8553",
    "sg:postcode":"43068",
    "sg:province":"OH",
    "sg:tags":[
        "burger",
        "american"
    ],
    "wof:name":"Dairy Queen",
    "wof:placetype":"venue"
},
  "geometry": {"coordinates":[-82.81233899999999,39.954844],"type":"Point"}
}