{
  "type": "Feature",
  "properties": {
    "addr:full": "8230 Expansion Way Dayton OH 45424",
    "addr:postcode": "8230;45424",
    "addr:street": "Expansion Way",
    "iso:country": "US",
    "sg:address": "8230 Expansion Way",
    "sg:city": "Dayton",
    "sg:classifiers": [
      {
        "category": "Manufacturing",
        "subcategory": "Building Materials",
        "type": "Manufacturing \u0026 Wholesale Goods"
      }
    ],
    "sg:phone": "+1 937 879 2000",
    "sg:postcode": "45424",
    "sg:province": "OH",
    "sg:tags": [
      "mfg",
      "carpentry",
      "m",
      "contractor"
    ],
    "wof:name": "Appalachian Mllwk \u0026 Lbr Co Inc",
    "wof:placetype": "venue"
  },
  "geometry": {"coordinates":[-84.058821,39.874125],"type":"Point"}
}
