{
  "type": "Feature",
  "properties": {
    "iso:country":"US",
    "sg:address":"1950 Old US Rte 35 E",
    "sg:city":"Xenia",
    "sg:classifiers":[
        {
            "category":"Building & Trades",
            "subcategory":"Landscaping Services",
            "type":"Services"
        }
    ],
    "sg:phone":"+1 937 374 0276",
    "sg:postcode":"45385",
    "sg:province":"OH",
    "wof:name":"Country Garden Landscaping",
    "wof:placetype":"venue"
},
  "geometry": {"coordinates":[-83.860071,39.698857],"type":"Point"}
}