{
  "type": "Feature",
  "properties": {
    "iso:country":"US",
    "sg:address":"5333 Monroe St",
    "sg:city":"Toledo",
    "sg:phone":"+1 419 843 8785",
    "sg:postcode":"43623",
    "sg:province":"OH",
    "sg:website":"http://www.cicispizza.com",
    "wof:name":"CiCi's Pizza",
    "wof:placetype":"venue"
},
  "geometry": {"coordinates":[-83.656779,41.703337],"type":"Point"}
}