{
  "type": "Feature",
  "properties": {
    "addr:full": "8005 Euclid Ave Cleveland OH 44103",
    "addr:housenumber": "8005",
    "addr:postcode": "44103",
    "addr:street": "Euclid Ave",
    "iso:country": "US",
    "sg:address": "8005 Euclid Ave",
    "sg:city": "Cleveland",
    "sg:classifiers": [
      {
        "category": "Shopping",
        "subcategory": "Gifts \u0026 Souvenirs",
        "type": "Retail Goods"
      }
    ],
    "sg:phone": "+1 216 231 7275",
    "sg:postcode": "44103",
    "sg:province": "OH",
    "sg:tags": [
      "shop"
    ],
    "wof:name": "Rose",
    "wof:placetype": "venue"
  },
  "geometry": {"coordinates":[-81.632658,41.503847],"type":"Point"}
}
