{
  "type": "Feature",
  "properties": {
    "iso:country":"US",
    "sg:address":"9099 Apollo Rd NE",
    "sg:city":"Kensington",
    "sg:classifiers":[
        {
            "category":"Retail",
            "subcategory":"Repair Shop",
            "type":"Services"
        }
    ],
    "sg:phone":"+1 330 223 1480",
    "sg:postcode":"44427",
    "sg:province":"OH",
    "sg:tags":[
        "farm",
        "mfg"
    ],
    "wof:name":"Shipley Tractor Equipment",
    "wof:placetype":"venue"
},
  "geometry": {"coordinates":[-80.93959099999999,40.714909],"type":"Point"}
}