{
  "type": "Feature",
  "properties": {
    "addr:full": "9099 Apollo Rd NE Kensington OH 44427",
    "addr:housenumber": "9099",
    "addr:postcode": "44427",
    "addr:street": "Apollo Rd Ne",
    "iso:country": "US",
    "sg:address": "9099 Apollo Rd NE",
    "sg:city": "Kensington",
    "sg:classifiers": [
      {
        "category": "Retail",
        "subcategory": "Repair Shop",
        "type": "Services"
      }
    ],
    "sg:phone": "+1 330 223 1480",
    "sg:postcode": "44427",
    "sg:province": "OH",
    "sg:tags": [
      "farm",
      "mfg"
    ],
    "wof:name": "Shipley Tractor Equipment",
    "wof:placetype": "venue"
  },
  "geometry": {"coordinates":[-80.939591,40.714909],"type":"Point"}
}
