{
  "type": "Feature",
  "properties": {
    "addr:full": "7520 Clover Ave Mentor OH 44060",
    "addr:housenumber": "7520",
    "addr:postcode": "44060",
    "addr:street": "Clover Ave",
    "iso:country": "US",
    "sg:address": "7520 Clover Ave",
    "sg:city": "Mentor",
    "sg:classifiers": [
      {
        "category": "Wholesale",
        "subcategory": "Machinery \u0026 Supplies",
        "type": "Manufacturing \u0026 Wholesale Goods"
      }
    ],
    "sg:phone": "+1 440 951 9519",
    "sg:postcode": "44060",
    "sg:province": "OH",
    "sg:tags": [
      "equipment",
      "material",
      "handling"
    ],
    "wof:name": "Towlift Inc",
    "wof:placetype": "venue"
  },
  "geometry": {"coordinates":[-81.375666,41.663847],"type":"Point"}
}
