{
  "type": "Feature",
  "properties": {
    "addr:full": "24800 Chagrin Blvd Cleveland OH 44122",
    "addr:housenumber": "24800",
    "addr:postcode": "44122",
    "addr:street": "Chagrin Blvd",
    "iso:country": "US",
    "sg:address": "24800 Chagrin Blvd",
    "sg:city": "Cleveland",
    "sg:classifiers": [
      {
        "category": "Wholesale",
        "subcategory": "Electrical",
        "type": "Manufacturing \u0026 Wholesale Goods"
      }
    ],
    "sg:phone": "+1 216 831 1464",
    "sg:postcode": "44122",
    "sg:province": "OH",
    "sg:tags": [
      "equipment",
      "electronic",
      "supply"
    ],
    "sg:website": "www.huntercomponents.com",
    "wof:name": "E C Hunter",
    "wof:placetype": "venue"
  },
  "geometry": {"coordinates":[-81.498421,41.464356],"type":"Point"}
}
