{
  "type": "Feature",
  "properties": {
    "addr:full":"4055 Belmont Ave Youngstown OH 44505",
    "addr:housenumber":"4055",
    "addr:postcode":"44505",
    "addr:street":"Belmont Ave",
    "iso:country":"US",
    "sg:address":"4055 Belmont Ave",
    "sg:city":"Youngstown",
    "sg:classifiers":[
        {
            "category":"Travel",
            "subcategory":"Hotels & Motels",
            "type":"Entertainment"
        }
    ],
    "sg:phone":"+1 330 759 3180",
    "sg:postcode":"44505",
    "sg:province":"OH",
    "wof:name":"Quality Inn",
    "wof:placetype":"venue"
},
  "geometry": {"coordinates":[-80.664866,41.156126],"type":"Point"}
}