{
  "type": "Feature",
  "properties": {
    "iso:country":"US",
    "sg:address":"3588 Harding Hwy E",
    "sg:city":"Marion",
    "sg:classifiers":[
        {
            "category":"Home & Garden",
            "subcategory":"Building Materials",
            "type":"Retail Goods"
        },
        {
            "category":"Building & Trades",
            "subcategory":"Construction",
            "type":"Services"
        }
    ],
    "sg:phone":"+1 740 383 3636",
    "sg:postcode":"43302",
    "sg:province":"OH",
    "sg:tags":[
        "glass",
        "window",
        "glazing",
        "plate"
    ],
    "wof:name":"ACR Glassworks Inc",
    "wof:placetype":"venue"
},
  "geometry": {"coordinates":[-83.033293,40.614055],"type":"Point"}
}