{
  "type": "Feature",
  "properties": {
    "addr:full": "3588 Harding Hwy E Marion OH 43302",
    "addr:housenumber": "3588",
    "addr:postcode": "43302",
    "addr:street": "Harding Hwy E",
    "iso:country": "US",
    "sg:address": "3588 Harding Hwy E",
    "sg:city": "Marion",
    "sg:classifiers": [
      {
        "category": "Home \u0026 Garden",
        "subcategory": "Building Materials",
        "type": "Retail Goods"
      },
      {
        "category": "Building \u0026 Trades",
        "subcategory": "Construction",
        "type": "Services"
      }
    ],
    "sg:phone": "+1 740 383 3636",
    "sg:postcode": "43302",
    "sg:province": "OH",
    "sg:tags": [
      "glass",
      "window",
      "glazing",
      "plate"
    ],
    "wof:name": "ACR Glassworks Inc",
    "wof:placetype": "venue"
  },
  "geometry": {"coordinates":[-83.033293,40.614055],"type":"Point"}
}
