{
  "type": "Feature",
  "properties": {
    "addr:full":"1022 Carlisle Ave Cambridge OH 43725",
    "addr:housenumber":"1022",
    "addr:postcode":"43725",
    "addr:street":"Carlisle Ave",
    "iso:country":"US",
    "sg:address":"1022 Carlisle Ave",
    "sg:city":"Cambridge",
    "sg:classifiers":[
        {
            "category":"Health Services",
            "subcategory":"Clinic",
            "type":"Services"
        }
    ],
    "sg:phone":"+1 740 432 6617",
    "sg:postcode":"43725",
    "sg:province":"OH",
    "sg:tags":[
        "home"
    ],
    "wof:name":"Home Health Care",
    "wof:placetype":"venue"
},
  "geometry": {"coordinates":[-81.586254,40.022659],"type":"Point"}
}