{
  "type": "Feature",
  "properties": {
    "addr:full": "1 W Lakeside Ave Cleveland OH 44113",
    "addr:housenumber": "1",
    "addr:postcode": "44113",
    "addr:street": "W Lakeside Ave",
    "iso:country": "US",
    "sg:address": "1 W Lakeside Ave",
    "sg:city": "Cleveland",
    "sg:classifiers": [
      {
        "category": "Government",
        "subcategory": "Court House",
        "type": "Public Place"
      },
      {
        "category": "Government",
        "subcategory": "Office",
        "type": "Public Place"
      }
    ],
    "sg:phone": "+1 216 443 2050",
    "sg:postcode": "44113",
    "sg:province": "OH",
    "sg:tags": [
      "justice",
      "parish",
      "government-county"
    ],
    "wof:name": "Cuyahoga County",
    "wof:placetype": "venue"
  },
  "geometry": {"coordinates":[-81.696609,41.50296],"type":"Point"}
}
