{
  "type": "Feature",
  "properties": {
    "iso:country":"US",
    "sg:address":"1 W Lakeside Ave",
    "sg:city":"Cleveland",
    "sg:classifiers":[
        {
            "category":"Government",
            "subcategory":"Court House",
            "type":"Public Place"
        },
        {
            "category":"Government",
            "subcategory":"Office",
            "type":"Public Place"
        }
    ],
    "sg:phone":"+1 216 443 2050",
    "sg:postcode":"44113",
    "sg:province":"OH",
    "sg:tags":[
        "justice",
        "parish",
        "government-county"
    ],
    "wof:name":"Cuyahoga County",
    "wof:placetype":"venue"
},
  "geometry": {"coordinates":[-81.696609,41.50296],"type":"Point"}
}