{
  "type": "Feature",
  "properties": {
    "addr:full":"2 Otterbein Ave Dayton OH 45406",
    "addr:housenumber":"2",
    "addr:postcode":"45406",
    "addr:street":"Otterbein Ave",
    "iso:country":"US",
    "sg:address":"2 Otterbein Ave",
    "sg:city":"Dayton",
    "sg:classifiers":[
        {
            "category":"Social Services",
            "subcategory":"Child Care",
            "type":"Services"
        }
    ],
    "sg:phone":"+1 937 274 2357",
    "sg:postcode":"45406",
    "sg:province":"OH",
    "wof:name":"D L Stewart Home Improvement",
    "wof:placetype":"venue"
},
  "geometry": {"coordinates":[-84.22439799999999,39.78122],"type":"Point"}
}