{
  "type": "Feature",
  "properties": {
    "addr:full": "892 S Cable Rd Lima OH 45805",
    "addr:housenumber": "892",
    "addr:postcode": "45805",
    "addr:street": "S Cable Rd",
    "iso:country": "US",
    "sg:address": "892 S Cable Rd",
    "sg:city": "Lima",
    "sg:classifiers": [
      {
        "category": "Health Services",
        "subcategory": "Clinic",
        "type": "Services"
      }
    ],
    "sg:phone": "+1 419 222 9410",
    "sg:postcode": "45805",
    "sg:province": "OH",
    "sg:tags": [
      "home"
    ],
    "wof:name": "Divine Home Care Of Ohio LLC",
    "wof:placetype": "venue"
  },
  "geometry": {"coordinates":[-84.146581,40.728657],"type":"Point"}
}
