{
  "type": "Feature",
  "properties": {
    "addr:full":"4556 Crossfields Rd Toledo OH 43623",
    "addr:housenumber":"4556",
    "addr:postcode":"43623",
    "addr:street":"Crossfields Rd",
    "iso:country":"US",
    "sg:address":"4556 Crossfields Rd",
    "sg:city":"Toledo",
    "sg:classifiers":[
        {
            "category":"Banks & Credit Unions",
            "subcategory":"Bank",
            "type":"Services"
        }
    ],
    "sg:phone":"+1 419 885 5678",
    "sg:postcode":"43623",
    "sg:province":"OH",
    "sg:tags":[
        "national",
        "commercial"
    ],
    "wof:name":"Gar Nat Lab Inc",
    "wof:placetype":"venue"
},
  "geometry": {"coordinates":[-83.677032,41.699435],"type":"Point"}
}