{
  "type": "Feature",
  "properties": {
    "addr:full":"520 Marlena Dr Wilmington OH 45177",
    "addr:housenumber":"520",
    "addr:postcode":"45177",
    "addr:street":"Marlena Dr",
    "iso:country":"US",
    "sg:address":"520 Marlena Dr",
    "sg:city":"Wilmington",
    "sg:classifiers":[
        {
            "category":"Organizations",
            "subcategory":"Religious Organization",
            "type":"Services"
        }
    ],
    "sg:phone":"+1 937 382 5626",
    "sg:postcode":"45177",
    "sg:province":"OH",
    "sg:tags":[
        "clergy"
    ],
    "wof:name":"Larry Harris",
    "wof:placetype":"venue"
},
  "geometry": {"coordinates":[-83.82035,39.43912],"type":"Point"}
}