{
  "type": "Feature",
  "properties": {
    "addr:full":"3862 Morse Rd Columbus OH 43231",
    "addr:housenumber":"3862",
    "addr:postcode":"43231",
    "addr:street":"Morse Rd",
    "iso:country":"US",
    "sg:address":"3862 Morse Rd",
    "sg:city":"Columbus",
    "sg:classifiers":[
        {
            "category":"Shopping",
            "subcategory":"Clothing, Apparel, & Fashions",
            "type":"Retail Goods"
        }
    ],
    "sg:phone":"+1 614 475 5580",
    "sg:postcode":"43231",
    "sg:province":"OH",
    "sg:tags":[
        "s",
        "furnishing",
        "man"
    ],
    "sg:website":"www.menswearhouse.com",
    "wof:name":"Men's Wearhouse",
    "wof:placetype":"venue"
},
  "geometry": {"coordinates":[-82.918224,40.057891],"type":"Point"}
}