{
  "type": "Feature",
  "properties": {
    "addr:full": "10129 E Twp Rd 106 Attica OH 44807",
    "addr:housenumber": "10129",
    "addr:postcode": "44807",
    "addr:street": "E Twp Rd 106",
    "iso:country": "US",
    "sg:address": "10129 E Twp Rd 106",
    "sg:city": "Attica",
    "sg:phone": "+1 419 585 7212",
    "sg:postcode": "44807",
    "sg:province": "OH",
    "sg:tags": [
      "farm",
      "corn",
      "soybean"
    ],
    "wof:name": "Stahl Joseph- Tennant",
    "wof:placetype": "venue"
  },
  "geometry": {"coordinates":[-82.97431,41.095812],"type":"Point"}
}
