{
  "type": "Feature",
  "properties": {
    "addr:full": "12059 Concord Hambden Rd Painesville OH 44077",
    "addr:housenumber": "12059",
    "addr:postcode": "44077",
    "addr:street": "Concord Hambden Rd",
    "iso:country": "US",
    "sg:address": "12059 Concord Hambden Rd",
    "sg:city": "Painesville",
    "sg:classifiers": [
      {
        "category": "Wholesale",
        "subcategory": "Electrical",
        "type": "Manufacturing \u0026 Wholesale Goods"
      }
    ],
    "sg:phone": "+1 440 354 4724",
    "sg:postcode": "44077",
    "sg:province": "OH",
    "sg:tags": [
      "distributor",
      "electronics"
    ],
    "wof:name": "North Coast Enterprises",
    "wof:placetype": "venue"
  },
  "geometry": {"coordinates":[-81.213423,41.672311],"type":"Point"}
}
