{
  "type": "Feature",
  "properties": {
    "iso:country":"US",
    "sg:address":"111 Champion Ln",
    "sg:city":"Chagrin Falls",
    "sg:classifiers":[
        {
            "category":"Banks & Credit Unions",
            "subcategory":"Bank",
            "type":"Services"
        }
    ],
    "sg:phone":"+1 440 338 4333",
    "sg:postcode":"44022",
    "sg:province":"OH",
    "sg:tags":[
        "financing"
    ],
    "wof:name":"Redwood Financial",
    "wof:placetype":"venue"
},
  "geometry": {"coordinates":[-81.312553,41.428021],"type":"Point"}
}