{
  "type": "Feature",
  "properties": {
    "addr:full": "322 3rd St Marietta OH 45750",
    "addr:housenumber": "322",
    "addr:postcode": "45750",
    "addr:street": "3Rd St",
    "iso:country": "US",
    "sg:address": "322 3rd St",
    "sg:city": "Marietta",
    "sg:classifiers": [
      {
        "category": "Professional",
        "subcategory": "Lawyer \u0026 Legal Services",
        "type": "Services"
      }
    ],
    "sg:phone": "+1 740 373 3219",
    "sg:postcode": "45750",
    "sg:province": "OH",
    "wof:name": "Buell Michael D",
    "wof:placetype": "venue"
  },
  "geometry": {"coordinates":[-81.454916,39.41776],"type":"Point"}
}
