{
  "type": "Feature",
  "properties": {
    "addr:full": "595 E Broad St Columbus OH 43215",
    "addr:housenumber": "595",
    "addr:postcode": "43215",
    "addr:street": "E Broad St",
    "iso:country": "US",
    "sg:address": "595 E Broad St",
    "sg:city": "Columbus",
    "sg:classifiers": [
      {
        "category": "Insurance",
        "subcategory": "Insurance Agent",
        "type": "Services"
      }
    ],
    "sg:phone": "+1 614 221 3114",
    "sg:postcode": "43215",
    "sg:province": "OH",
    "wof:name": "AFLAC",
    "wof:placetype": "venue"
  },
  "geometry": {"coordinates":[-82.984886,39.96393],"type":"Point"}
}
