{
  "type": "Feature",
  "properties": {
    "iso:country":"US",
    "sg:address":"595 E Broad St",
    "sg:city":"Columbus",
    "sg:classifiers":[
        {
            "category":"Insurance",
            "subcategory":"Insurance Agent",
            "type":"Services"
        }
    ],
    "sg:phone":"+1 614 221 3114",
    "sg:postcode":"43215",
    "sg:province":"OH",
    "wof:name":"AFLAC",
    "wof:placetype":"venue"
},
  "geometry": {"coordinates":[-82.984886,39.96393],"type":"Point"}
}