{
  "type": "Feature",
  "properties": {
    "addr:full": "2400 E Edgerton Rd Cleveland OH 44141",
    "addr:housenumber": "2400",
    "addr:postcode": "44141",
    "addr:street": "E Edgerton Rd",
    "iso:country": "US",
    "sg:address": "2400 E Edgerton Rd",
    "sg:city": "Cleveland",
    "sg:classifiers": [
      {
        "category": "Building \u0026 Trades",
        "subcategory": "Construction",
        "type": "Services"
      }
    ],
    "sg:phone": "+1 440 526 4600",
    "sg:postcode": "44141",
    "sg:province": "OH",
    "sg:tags": [
      "excavating",
      "contractor"
    ],
    "wof:name": "Frank Salvatore Excavating Inc",
    "wof:placetype": "venue"
  },
  "geometry": {"coordinates":[-81.668296,41.295544],"type":"Point"}
}
