{
  "type": "Feature",
  "properties": {
    "addr:full": "100 Southpark Center Strongsville OH 44136",
    "addr:housenumber": "100",
    "addr:postcode": "44136",
    "addr:street": "Southpark Center",
    "iso:country": "US",
    "sg:address": "100 Southpark Center",
    "sg:city": "Strongsville",
    "sg:classifiers": [
      {
        "category": "Shopping",
        "subcategory": "Clothing, Apparel, \u0026 Fashions",
        "type": "Retail Goods"
      }
    ],
    "sg:phone": "+1 440 238 3561",
    "sg:postcode": "44136",
    "sg:province": "OH",
    "wof:name": "Deb Shops",
    "wof:placetype": "venue"
  },
  "geometry": {"coordinates":[-81.820449,41.310925],"type":"Point"}
}
