{
  "type": "Feature",
  "properties": {
    "addr:full":"4897 Karl Rd Columbus OH 43229",
    "addr:housenumber":"4897",
    "addr:postcode":"43229",
    "addr:street":"Karl Rd",
    "iso:country":"US",
    "sg:address":"4897 Karl Rd",
    "sg:city":"Columbus",
    "sg:classifiers":[
        {
            "category":"Health Services",
            "subcategory":"Clinic",
            "type":"Services"
        }
    ],
    "sg:phone":"+1 614 846 2588",
    "sg:postcode":"43229",
    "sg:province":"OH",
    "sg:tags":[
        "outpatient",
        "mental"
    ],
    "wof:name":"North Community Counseling Ctr",
    "wof:placetype":"venue"
},
  "geometry": {"coordinates":[-82.97694,40.066397],"type":"Point"}
}