{
  "type": "Feature",
  "properties": {
    "addr:full": "6050 Milo Rd Dayton OH 45414",
    "addr:housenumber": "6050",
    "addr:postcode": "45414",
    "addr:street": "Milo Rd",
    "iso:country": "US",
    "sg:address": "6050 Milo Rd",
    "sg:city": "Dayton",
    "sg:classifiers": [
      {
        "category": "Building \u0026 Trades",
        "subcategory": "Plumbing",
        "type": "Services"
      }
    ],
    "sg:phone": "+1 937 275 0645",
    "sg:postcode": "45414",
    "sg:province": "OH",
    "sg:tags": [
      "conditioning",
      "air",
      "system",
      "contractor"
    ],
    "sg:website": "www.carrier-commercial.com",
    "wof:name": "Carrier Corp",
    "wof:placetype": "venue"
  },
  "geometry": {"coordinates":[-84.183521,39.828597],"type":"Point"}
}
