{
  "type": "Feature",
  "properties": {
    "iso:country":"US",
    "sg:address":"801 W 8th St",
    "sg:city":"Cincinnati",
    "sg:classifiers":[
        {
            "category":"Professional",
            "subcategory":"Business Services",
            "type":"Services"
        }
    ],
    "sg:phone":"+1 513 721 2378",
    "sg:postcode":"45203",
    "sg:province":"OH",
    "sg:tags":[
        "fund",
        "promotion",
        "raising"
    ],
    "wof:name":"Cosmic Concepts LTD",
    "wof:placetype":"venue"
},
  "geometry": {"coordinates":[-84.533086,39.103729],"type":"Point"}
}