{
  "type": "Feature",
  "properties": {
    "iso:country":"US",
    "sg:address":"533 8th St",
    "sg:city":"Struthers",
    "sg:classifiers":[
        {
            "category":"Organizations",
            "subcategory":"Labor Organization",
            "type":"Services"
        }
    ],
    "sg:phone":"+1 330 755 1531",
    "sg:postcode":"44471",
    "sg:province":"OH",
    "wof:name":"Stage Employees Local",
    "wof:placetype":"venue"
},
  "geometry": {"coordinates":[-80.60769999999999,41.057633],"type":"Point"}
}