{
  "type": "Feature",
  "properties": {
    "addr:full": "486 Victor Dr Circleville OH 43113",
    "addr:housenumber": "486",
    "addr:postcode": "43113",
    "addr:street": "Victor Dr",
    "iso:country": "US",
    "sg:address": "486 Victor Dr",
    "sg:city": "Circleville",
    "sg:classifiers": [
      {
        "category": "Building \u0026 Trades",
        "subcategory": "Construction",
        "type": "Services"
      }
    ],
    "sg:phone": "+1 740 477 1833",
    "sg:postcode": "43113",
    "sg:province": "OH",
    "sg:tags": [
      "contractor"
    ],
    "wof:name": "Eh Painting",
    "wof:placetype": "venue"
  },
  "geometry": {"coordinates":[-82.927939,39.627563],"type":"Point"}
}
