{
  "type": "Feature",
  "properties": {
    "iso:country":"US",
    "sg:address":"486 Victor Dr",
    "sg:city":"Circleville",
    "sg:classifiers":[
        {
            "category":"Building & Trades",
            "subcategory":"Construction",
            "type":"Services"
        }
    ],
    "sg:phone":"+1 740 477 1833",
    "sg:postcode":"43113",
    "sg:province":"OH",
    "sg:tags":[
        "contractor"
    ],
    "wof:name":"Eh Painting",
    "wof:placetype":"venue"
},
  "geometry": {"coordinates":[-82.92793899999999,39.627563],"type":"Point"}
}