{
  "type": "Feature",
  "properties": {
    "addr:full":"331 W High St Orrville OH 44667",
    "addr:housenumber":"331",
    "addr:postcode":"44667",
    "addr:street":"W High St",
    "iso:country":"US",
    "sg:address":"331 W High St",
    "sg:city":"Orrville",
    "sg:classifiers":[
        {
            "category":"Food & Beverages",
            "subcategory":"Liquor & Beverages",
            "type":"Retail Goods"
        }
    ],
    "sg:phone":"+1 330 683 1528",
    "sg:postcode":"44667",
    "sg:province":"OH",
    "sg:tags":[
        "beer",
        "ale"
    ],
    "wof:name":"Gary's Drive-Thru",
    "wof:placetype":"venue"
},
  "geometry": {"coordinates":[-81.76734,40.843619],"type":"Point"}
}