{
  "type": "Feature",
  "properties": {
    "addr:full":"111 W Market St Akron OH 44303",
    "addr:housenumber":"111",
    "addr:postcode":"44303",
    "addr:street":"W Market St",
    "iso:country":"US",
    "sg:address":"111 W Market St",
    "sg:city":"Akron",
    "sg:classifiers":[
        {
            "category":"Retail",
            "subcategory":"Auto Rental",
            "type":"Services"
        }
    ],
    "sg:phone":"+1 330 434 2525",
    "sg:postcode":"44303",
    "sg:province":"OH",
    "sg:tags":[
        "renting",
        "automobile"
    ],
    "wof:name":"Enterprise Rent A Car",
    "wof:placetype":"venue"
},
  "geometry": {"coordinates":[-81.520747,41.086675],"type":"Point"}
}