{
  "type": "Feature",
  "properties": {
    "addr:full":"13346 Ravenna Rd Chardon OH 44024",
    "addr:housenumber":"13346",
    "addr:postcode":"44024",
    "addr:street":"Ravenna Rd",
    "iso:country":"US",
    "sg:address":"13346 Ravenna Rd",
    "sg:city":"Chardon",
    "sg:classifiers":[
        {
            "category":"Health Services",
            "subcategory":"Doctor",
            "type":"Services"
        }
    ],
    "sg:phone":"+1 440 285 2304",
    "sg:postcode":"44024",
    "sg:province":"OH",
    "sg:tags":[
        "physician",
        "surgeon"
    ],
    "wof:name":"A J Castrovinci Inc",
    "wof:placetype":"venue"
},
  "geometry": {"coordinates":[-81.193663,41.505928],"type":"Point"}
}