{
  "type": "Feature",
  "properties": {
    "addr:full":"4353 Dressler Rd NW Canton OH 44720",
    "addr:postcode":"4353;44720",
    "addr:street":"Dressler Rd Nw",
    "iso:country":"US",
    "sg:address":"4353 Dressler Rd NW",
    "sg:city":"Canton",
    "sg:classifiers":[
        {
            "category":"Personal",
            "subcategory":"Beauty Salon",
            "type":"Services"
        }
    ],
    "sg:phone":"+1 330 649 9886",
    "sg:postcode":"44720",
    "sg:province":"OH",
    "wof:name":"Vogue Hair Design",
    "wof:placetype":"venue"
},
  "geometry": {"coordinates":[-81.434909,40.843968],"type":"Point"}
}