{
  "type": "Feature",
  "properties": {
    "addr:full": "6331 E Livingston Ave Reynoldsburg OH 43068",
    "addr:housenumber": "6331",
    "addr:postcode": "43068",
    "addr:street": "E Livingston Ave",
    "iso:country": "US",
    "sg:address": "6331 E Livingston Ave",
    "sg:city": "Reynoldsburg",
    "sg:classifiers": [
      {
        "category": "Insurance",
        "subcategory": "Health Insurance",
        "type": "Services"
      }
    ],
    "sg:phone": "+1 614 863 8780",
    "sg:postcode": "43068",
    "sg:province": "OH",
    "sg:tags": [
      "surgical",
      "hospitalization",
      "plan"
    ],
    "sg:website": "www.bactpa.com",
    "wof:name": "BAC Agency Inc",
    "wof:placetype": "venue"
  },
  "geometry": {"coordinates":[-82.826266,39.94185],"type":"Point"}
}
