{
  "type": "Feature",
  "properties": {
    "addr:full": "125 E 2nd St Ashland OH 44805",
    "addr:housenumber": "125",
    "addr:postcode": "44805",
    "addr:street": "E 2Nd St",
    "iso:country": "US",
    "sg:address": "125 E 2nd St",
    "sg:city": "Ashland",
    "sg:classifiers": [
      {
        "category": "Shopping",
        "subcategory": "Computers \u0026 Home Electronics",
        "type": "Retail Goods"
      }
    ],
    "sg:phone": "+1 419 281 2598",
    "sg:postcode": "44805",
    "sg:province": "OH",
    "sg:tags": [
      "equipment",
      "dealer"
    ],
    "wof:name": "Ashland Computer Engineering",
    "wof:placetype": "venue"
  },
  "geometry": {"coordinates":[-82.313936,40.869149],"type":"Point"}
}
