{
  "type": "Feature",
  "properties": {
    "addr:full": "8300 N Gilmore Rd Hamilton OH 45015",
    "addr:housenumber": "8300",
    "addr:postcode": "45015",
    "addr:street": "N Gilmore Rd",
    "iso:country": "US",
    "sg:address": "8300 N Gilmore Rd",
    "sg:city": "Hamilton",
    "sg:classifiers": [
      {
        "category": "Wholesale",
        "subcategory": "Machinery \u0026 Supplies",
        "type": "Manufacturing \u0026 Wholesale Goods"
      }
    ],
    "sg:phone": "+1 513 874 3372",
    "sg:postcode": "45015",
    "sg:province": "OH",
    "sg:tags": [
      "chemical",
      "pump"
    ],
    "sg:website": "www.beckerequipment.com",
    "wof:name": "Becker Equipment Inc",
    "wof:placetype": "venue"
  },
  "geometry": {"coordinates":[-84.51986,39.348946],"type":"Point"}
}
