{
  "type": "Feature",
  "properties": {
    "addr:full":"8300 N Gilmore Rd Hamilton OH 45015",
    "addr:housenumber":"8300",
    "addr:postcode":"45015",
    "addr:street":"N Gilmore Rd",
    "iso:country":"US",
    "sg:address":"8300 N Gilmore Rd",
    "sg:city":"Hamilton",
    "sg:classifiers":[
        {
            "category":"Wholesale",
            "subcategory":"Machinery & Supplies",
            "type":"Manufacturing & Wholesale Goods"
        }
    ],
    "sg:phone":"+1 513 874 3372",
    "sg:postcode":"45015",
    "sg:province":"OH",
    "sg:tags":[
        "chemical",
        "pump"
    ],
    "sg:website":"www.beckerequipment.com",
    "wof:name":"Becker Equipment Inc",
    "wof:placetype":"venue"
},
  "geometry": {"coordinates":[-84.51985999999999,39.348946],"type":"Point"}
}