{
  "type": "Feature",
  "properties": {
    "addr:full":"14873 Bradford Dr Logan OH 43138",
    "addr:housenumber":"14873",
    "addr:postcode":"43138",
    "addr:street":"Bradford Dr",
    "iso:country":"US",
    "sg:address":"14873 Bradford Dr",
    "sg:city":"Logan",
    "sg:classifiers":[
        {
            "category":"Retail",
            "subcategory":"Laundry & Dry Cleaning",
            "type":"Services"
        }
    ],
    "sg:phone":"+1 740 380 9001",
    "sg:postcode":"43138",
    "sg:province":"OH",
    "sg:tags":[
        "cleaners",
        "rug",
        "carpet"
    ],
    "wof:name":"Carpetman Custom Cleaning",
    "wof:placetype":"venue"
},
  "geometry": {"coordinates":[-82.381269,39.513373],"type":"Point"}
}