{
  "type": "Feature",
  "properties": {
    "addr:full":"5400 Harvard Ave Cleveland OH 44105",
    "addr:housenumber":"5400",
    "addr:postcode":"44105",
    "addr:street":"Harvard Ave",
    "iso:country":"US",
    "sg:address":"5400 Harvard Ave",
    "sg:city":"Cleveland",
    "sg:classifiers":[
        {
            "category":"Freight",
            "type":"Transportation"
        }
    ],
    "sg:phone":"+1 216 883 6363",
    "sg:postcode":"44105",
    "sg:province":"OH",
    "sg:tags":[
        "carrier",
        "general"
    ],
    "wof:name":"Dworkin Trucking",
    "wof:placetype":"venue"
},
  "geometry": {"coordinates":[-81.65095700000001,41.448274],"type":"Point"}
}