{
  "type": "Feature",
  "properties": {
    "addr:full":"12140 Waters Ln New Concord OH 43762",
    "addr:housenumber":"12140",
    "addr:postcode":"43762",
    "addr:street":"Waters Ln",
    "iso:country":"US",
    "sg:address":"12140 Waters Ln",
    "sg:city":"New Concord",
    "sg:classifiers":[
        {
            "category":"Shopping",
            "subcategory":"Gifts & Souvenirs",
            "type":"Retail Goods"
        }
    ],
    "sg:phone":"+1 740 796 5172",
    "sg:postcode":"43762",
    "sg:province":"OH",
    "wof:name":"Woven Woods",
    "wof:placetype":"venue"
},
  "geometry": {"coordinates":[-81.751516,40.12365],"type":"Point"}
}