{
  "type": "Feature",
  "properties": {
    "addr:full": "441 Wolf Ledges Pkwy Akron OH 44311",
    "addr:housenumber": "441",
    "addr:postcode": "44311",
    "addr:street": "Wolf Ledges Pkwy",
    "iso:country": "US",
    "sg:address": "441 Wolf Ledges Pkwy",
    "sg:city": "Akron",
    "sg:classifiers": [
      {
        "category": "Professional",
        "type": "Services"
      }
    ],
    "sg:phone": "+1 330 252 1201",
    "sg:postcode": "44311",
    "sg:province": "OH",
    "sg:tags": [
      "establishment"
    ],
    "wof:name": "Ruhlin Co",
    "wof:placetype": "venue"
  },
  "geometry": {"coordinates":[-81.520369,41.07061],"type":"Point"}
}
