{
  "type": "Feature",
  "properties": {
    "iso:country":"US",
    "sg:address":"4027 Colonel Glenn Hwy",
    "sg:city":"Beavercreek",
    "sg:classifiers":[
        {
            "category":"Professional",
            "subcategory":"Engineering",
            "type":"Services"
        },
        {
            "category":"Professional",
            "subcategory":"Research",
            "type":"Services"
        }
    ],
    "sg:phone":"+1 937 429 9008",
    "sg:postcode":"45431",
    "sg:province":"OH",
    "sg:tags":[
        "a",
        "equipment",
        "engineer",
        "aerospace",
        "military"
    ],
    "sg:website":"www.systranfederal.com",
    "wof:name":"Systran Federal Corp",
    "wof:placetype":"venue"
},
  "geometry": {"coordinates":[-84.084897,39.773747],"type":"Point"}
}