{
  "type": "Feature",
  "properties": {
    "addr:full": "6488 Glenway Ave Cincinnati OH 45211",
    "addr:housenumber": "6488",
    "addr:postcode": "45211",
    "addr:street": "Glenway Ave",
    "iso:country": "US",
    "sg:address": "6488 Glenway Ave",
    "sg:city": "Cincinnati",
    "sg:classifiers": [
      {
        "category": "Home \u0026 Garden",
        "subcategory": "Building Materials",
        "type": "Retail Goods"
      }
    ],
    "sg:phone": "+1 513 661 4900",
    "sg:postcode": "45211",
    "sg:province": "OH",
    "sg:tags": [
      "glass",
      "window",
      "plate"
    ],
    "wof:name": "Glas-Tech Systems",
    "wof:placetype": "venue"
  },
  "geometry": {"coordinates":[-84.627143,39.147964],"type":"Point"}
}
