{
  "type": "Feature",
  "properties": {
    "addr:full": "70440 Pamela Ave St Clairsville OH 43950",
    "addr:housenumber": "70440",
    "addr:postcode": "43950",
    "addr:street": "Pamela Ave",
    "iso:country": "US",
    "sg:address": "70440 Pamela Ave",
    "sg:city": "St Clairsville",
    "sg:classifiers": [
      {
        "category": "Professional",
        "subcategory": "Secretarial Services",
        "type": "Services"
      }
    ],
    "sg:phone": "+1 740 968 4520",
    "sg:postcode": "43950",
    "sg:province": "OH",
    "sg:tags": [
      "resume"
    ],
    "wof:name": "Ohio Valley Resume \u0026 Typing",
    "wof:placetype": "venue"
  },
  "geometry": {"coordinates":[-80.993067,40.111666],"type":"Point"}
}
