{
  "type": "Feature",
  "properties": {
    "iso:country":"US",
    "sg:address":"70440 Pamela Ave",
    "sg:city":"St Clairsville",
    "sg:classifiers":[
        {
            "category":"Professional",
            "subcategory":"Secretarial Services",
            "type":"Services"
        }
    ],
    "sg:phone":"+1 740 968 4520",
    "sg:postcode":"43950",
    "sg:province":"OH",
    "sg:tags":[
        "resume"
    ],
    "wof:name":"Ohio Valley Resume & Typing",
    "wof:placetype":"venue"
},
  "geometry": {"coordinates":[-80.993067,40.111666],"type":"Point"}
}