{
  "type": "Feature",
  "properties": {
    "iso:country":"US",
    "sg:address":"663 Willow St",
    "sg:city":"Williamsburg",
    "sg:classifiers":[
        {
            "category":"Manufacturing",
            "subcategory":"Tools & Machinery",
            "type":"Manufacturing & Wholesale Goods"
        },
        {
            "category":"Building & Trades",
            "subcategory":"Plumbing",
            "type":"Services"
        }
    ],
    "sg:phone":"+1 513 724 1953",
    "sg:postcode":"45176",
    "sg:province":"OH",
    "sg:tags":[
        "machine",
        "shop",
        "machining",
        "design",
        "mechanical"
    ],
    "wof:name":"East Fork Precision Machinery",
    "wof:placetype":"venue"
},
  "geometry": {"coordinates":[-84.06094899999999,39.05401],"type":"Point"}
}