{
  "type": "Feature",
  "properties": {
    "addr:full": "663 Willow St Williamsburg OH 45176",
    "addr:housenumber": "663",
    "addr:postcode": "45176",
    "addr:street": "Willow St",
    "iso:country": "US",
    "sg:address": "663 Willow St",
    "sg:city": "Williamsburg",
    "sg:classifiers": [
      {
        "category": "Manufacturing",
        "subcategory": "Tools \u0026 Machinery",
        "type": "Manufacturing \u0026 Wholesale Goods"
      },
      {
        "category": "Building \u0026 Trades",
        "subcategory": "Plumbing",
        "type": "Services"
      }
    ],
    "sg:phone": "+1 513 724 1953",
    "sg:postcode": "45176",
    "sg:province": "OH",
    "sg:tags": [
      "machine",
      "shop",
      "machining",
      "design",
      "mechanical"
    ],
    "wof:name": "East Fork Precision Machinery",
    "wof:placetype": "venue"
  },
  "geometry": {"coordinates":[-84.060949,39.05401],"type":"Point"}
}
