{
  "type": "Feature",
  "properties": {
    "addr:full": "100 Crystal Ave Findlay OH 45840",
    "addr:housenumber": "100",
    "addr:postcode": "45840",
    "addr:street": "Crystal Ave",
    "iso:country": "US",
    "sg:address": "100 Crystal Ave",
    "sg:city": "Findlay",
    "sg:classifiers": [
      {
        "category": "Shopping",
        "subcategory": "Computers \u0026 Home Electronics",
        "type": "Retail Goods"
      }
    ],
    "sg:phone": "+1 419 423 6663",
    "sg:postcode": "45840",
    "sg:province": "OH",
    "sg:tags": [
      "equipment",
      "dealer"
    ],
    "wof:name": "Mac Store",
    "wof:placetype": "venue"
  },
  "geometry": {"coordinates":[-83.645294,41.048762],"type":"Point"}
}
