{
  "type": "Feature",
  "properties": {
    "iso:country":"US",
    "sg:address":"427 Beall Ave",
    "sg:city":"Wooster",
    "sg:classifiers":[
        {
            "category":"Restaurant",
            "type":"Food & Drink"
        }
    ],
    "sg:phone":"+1 330 264 7050",
    "sg:postcode":"44691",
    "sg:province":"OH",
    "sg:tags":[
        "eating"
    ],
    "wof:name":"Ponderosa Steakhouse",
    "wof:placetype":"venue"
},
  "geometry": {"coordinates":[-81.934324,40.803082],"type":"Point"}
}