{
  "type": "Feature",
  "properties": {
    "addr:full": "505 W Exchange St Akron OH 44302",
    "addr:housenumber": "505",
    "addr:postcode": "44302",
    "addr:street": "W Exchange St",
    "iso:country": "US",
    "sg:address": "505 W Exchange St",
    "sg:city": "Akron",
    "sg:classifiers": [
      {
        "category": "Wholesale",
        "subcategory": "Medical Equipment \u0026 Supplies",
        "type": "Manufacturing \u0026 Wholesale Goods"
      }
    ],
    "sg:phone": "+1 330 376 2135",
    "sg:postcode": "44302",
    "sg:province": "OH",
    "sg:tags": [
      "hospital"
    ],
    "wof:name": "Health Care Solutions At Home",
    "wof:placetype": "venue"
  },
  "geometry": {"coordinates":[-81.536686,41.085429],"type":"Point"}
}
