{
  "type": "Feature",
  "properties": {
    "iso:country":"US",
    "sg:address":"505 W Exchange St",
    "sg:city":"Akron",
    "sg:classifiers":[
        {
            "category":"Wholesale",
            "subcategory":"Medical Equipment & Supplies",
            "type":"Manufacturing & Wholesale Goods"
        }
    ],
    "sg:phone":"+1 330 376 2135",
    "sg:postcode":"44302",
    "sg:province":"OH",
    "sg:tags":[
        "hospital"
    ],
    "wof:name":"Health Care Solutions At Home",
    "wof:placetype":"venue"
},
  "geometry": {"coordinates":[-81.536686,41.085429],"type":"Point"}
}