{
  "type": "Feature",
  "properties": {
    "addr:full":"4812 Cleveland Rd E Huron OH 44839",
    "addr:housenumber":"4812",
    "addr:postcode":"44839",
    "addr:street":"Cleveland Rd E",
    "iso:country":"US",
    "sg:address":"4812 Cleveland Rd E",
    "sg:city":"Huron",
    "sg:classifiers":[
        {
            "category":"Home & Garden",
            "subcategory":"Garden Supply",
            "type":"Retail Goods"
        }
    ],
    "sg:phone":"+1 440 967 3911",
    "sg:postcode":"44839",
    "sg:province":"OH",
    "wof:name":"Willoway Nurseries",
    "wof:placetype":"venue"
},
  "geometry": {"coordinates":[-82.466448,41.382619],"type":"Point"}
}