{
  "type": "Feature",
  "properties": {
    "iso:country":"US",
    "sg:address":"550 Folkerth Ave",
    "sg:city":"Sidney",
    "sg:classifiers":[
        {
            "category":"Utilities",
            "subcategory":"Telephone",
            "type":"Services"
        }
    ],
    "sg:phone":"+1 937 492 6248",
    "sg:postcode":"45365",
    "sg:province":"OH",
    "sg:tags":[
        "telecommunication"
    ],
    "sg:website":"www.mastec.com",
    "wof:name":"Mas Tec",
    "wof:placetype":"venue"
},
  "geometry": {"coordinates":[-84.184831,40.288298],"type":"Point"}
}