{
  "type": "Feature",
  "properties": {
    "addr:full":"3603 Tylersville Rd Hamilton OH 45011",
    "addr:housenumber":"3603",
    "addr:postcode":"45011",
    "addr:street":"Tylersville Rd",
    "iso:country":"US",
    "sg:address":"3603 Tylersville Rd",
    "sg:city":"Hamilton",
    "sg:phone":"+1 513 860 2653",
    "sg:postcode":"45011",
    "sg:province":"OH",
    "sg:tags":[
        "wheat",
        "farm",
        "corn",
        "crop",
        "field",
        "soybean"
    ],
    "wof:name":"Louis Jacquemin",
    "wof:placetype":"venue"
},
  "geometry": {"coordinates":[-84.503454,39.362527],"type":"Point"}
}