{
  "type": "Feature",
  "properties": {
    "addr:full": "10295 Wye Rd Chesterland OH 44026",
    "addr:housenumber": "10295",
    "addr:postcode": "44026",
    "addr:street": "Wye Rd",
    "iso:country": "US",
    "sg:address": "10295 Wye Rd",
    "sg:city": "Chesterland",
    "sg:classifiers": [
      {
        "category": "Professional",
        "subcategory": "Advertising",
        "type": "Services"
      }
    ],
    "sg:phone": "+1 440 286 4278",
    "sg:postcode": "44026",
    "sg:province": "OH",
    "sg:tags": [
      "designer",
      "display",
      "producer"
    ],
    "wof:name": "Design Viewpoints Inc",
    "wof:placetype": "venue"
  },
  "geometry": {"coordinates":[-81.26776,41.517464],"type":"Point"}
}
