{
  "type": "Feature",
  "properties": {
    "addr:full":"468 S Washington St New Bremen OH 45869",
    "addr:housenumber":"468",
    "addr:postcode":"45869",
    "addr:street":"S Washington St",
    "iso:country":"US",
    "sg:address":"468 S Washington St",
    "sg:city":"New Bremen",
    "sg:classifiers":[
        {
            "category":"Recreation",
            "type":"Entertainment"
        }
    ],
    "sg:phone":"+1 419 629 3815",
    "sg:postcode":"45869",
    "sg:province":"OH",
    "sg:tags":[
        "art",
        "mfg",
        "frame",
        "handcraft",
        "custom",
        "including",
        "gallery"
    ],
    "wof:name":"Artists Touch Inc The",
    "wof:placetype":"venue"
},
  "geometry": {"coordinates":[-84.37879700000001,40.427335],"type":"Point"}
}