{
  "type": "Feature",
  "properties": {
    "addr:full":"55 Lisbon St Canfield OH 44406",
    "addr:housenumber":"55",
    "addr:postcode":"44406",
    "addr:street":"Lisbon St",
    "iso:country":"US",
    "sg:address":"55 Lisbon St",
    "sg:city":"Canfield",
    "sg:classifiers":[
        {
            "category":"Building & Trades",
            "subcategory":"Construction",
            "type":"Services"
        },
        {
            "category":"Building & Trades",
            "subcategory":"Electrical",
            "type":"Services"
        },
        {
            "category":"Building & Trades",
            "subcategory":"Plumbing",
            "type":"Services"
        },
        {
            "category":"Wholesale",
            "subcategory":"Machinery & Supplies",
            "type":"Manufacturing & Wholesale Goods"
        },
        {
            "category":"Home & Garden",
            "subcategory":"Building Materials",
            "type":"Retail Goods"
        },
        {
            "category":"Building & Trades",
            "subcategory":"Cleaning & Sanitation",
            "type":"Services"
        }
    ],
    "sg:phone":"+1 330 533 5559",
    "sg:postcode":"44406",
    "sg:province":"OH",
    "sg:tags":[
        "heater",
        "plumber",
        "electrician",
        "system",
        "specialty",
        "cleaner",
        "repairer",
        "bathroom",
        "water",
        "equipment",
        "pump",
        "heating",
        "clean",
        "contractor",
        "remodeling",
        "air conditioning",
        "boilers-repair",
        "sewer"
    ],
    "sg:website":"http://www.neffplumbing.com",
    "wof:name":"Neff Co Inc The",
    "wof:placetype":"venue"
},
  "geometry": {"coordinates":[-80.763802,41.023026],"type":"Point"}
}