{
  "type": "Feature",
  "properties": {
    "iso:country":"US",
    "sg:address":"26390 Putney Ridge Rd",
    "sg:city":"Quaker City",
    "sg:classifiers":[
        {
            "category":"Farming",
            "subcategory":"Livestock Farm",
            "type":"Manufacturing & Wholesale Goods"
        }
    ],
    "sg:phone":"+1 740 679 2803",
    "sg:postcode":"43773",
    "sg:province":"OH",
    "sg:tags":[
        "beef",
        "feedlot",
        "cattle"
    ],
    "wof:name":"Virgil R Watson",
    "wof:placetype":"venue"
},
  "geometry": {"coordinates":[-81.237544,40.001061],"type":"Point"}
}