{
  "type": "Feature",
  "properties": {
    "iso:country":"US",
    "sg:address":"7772 Metric Dr",
    "sg:city":"Mentor",
    "sg:classifiers":[
        {
            "category":"Manufacturing",
            "subcategory":"Rubber & Plastics",
            "type":"Manufacturing & Wholesale Goods"
        },
        {
            "category":"Manufacturing",
            "subcategory":"Tools & Machinery",
            "type":"Manufacturing & Wholesale Goods"
        }
    ],
    "sg:phone":"+1 440 974 8730",
    "sg:postcode":"44060",
    "sg:province":"OH",
    "sg:tags":[
        "building",
        "shop",
        "for",
        "molding",
        "process",
        "pro",
        "mfg",
        "machine",
        "injection"
    ],
    "sg:website":"www.frantzgroup.com",
    "wof:name":"Frantz Tool & Design Inc",
    "wof:placetype":"venue"
},
  "geometry": {"coordinates":[-81.363625,41.671088],"type":"Point"}
}