{
  "type": "Feature",
  "properties": {
    "addr:full": "7772 Metric Dr Mentor OH 44060",
    "addr:housenumber": "7772",
    "addr:postcode": "44060",
    "addr:street": "Metric Dr",
    "iso:country": "US",
    "sg:address": "7772 Metric Dr",
    "sg:city": "Mentor",
    "sg:classifiers": [
      {
        "category": "Manufacturing",
        "subcategory": "Rubber \u0026 Plastics",
        "type": "Manufacturing \u0026 Wholesale Goods"
      },
      {
        "category": "Manufacturing",
        "subcategory": "Tools \u0026 Machinery",
        "type": "Manufacturing \u0026 Wholesale Goods"
      }
    ],
    "sg:phone": "+1 440 974 8730",
    "sg:postcode": "44060",
    "sg:province": "OH",
    "sg:tags": [
      "building",
      "shop",
      "for",
      "molding",
      "process",
      "pro",
      "mfg",
      "machine",
      "injection"
    ],
    "sg:website": "www.frantzgroup.com",
    "wof:name": "Frantz Tool \u0026 Design Inc",
    "wof:placetype": "venue"
  },
  "geometry": {"coordinates":[-81.363625,41.671088],"type":"Point"}
}
