{
  "type": "Feature",
  "properties": {
    "addr:full": "165 Winding Way Dayton OH 45429",
    "addr:housenumber": "165",
    "addr:postcode": "45429",
    "addr:street": "Winding Way",
    "iso:country": "US",
    "sg:address": "165 Winding Way",
    "sg:city": "Dayton",
    "sg:classifiers": [
      {
        "category": "Home \u0026 Garden",
        "subcategory": "Hardware",
        "type": "Retail Goods"
      }
    ],
    "sg:phone": "+1 937 299 0529",
    "sg:postcode": "45429",
    "sg:province": "OH",
    "wof:name": "2 Lz",
    "wof:placetype": "venue"
  },
  "geometry": {"coordinates":[-84.172082,39.698913],"type":"Point"}
}
