{
  "type": "Feature",
  "properties": {
    "iso:country":"US",
    "sg:address":"521 W Chalmers Ave",
    "sg:city":"Youngstown",
    "sg:classifiers":[
        {
            "category":"Shopping",
            "subcategory":"Clothing, Apparel, & Fashions",
            "type":"Retail Goods"
        }
    ],
    "sg:phone":"+1 330 746 5556",
    "sg:postcode":"44511",
    "sg:province":"OH",
    "sg:tags":[
        "family"
    ],
    "wof:name":"California Hip Hop Fashions",
    "wof:placetype":"venue"
},
  "geometry": {"coordinates":[-80.673456,41.085004],"type":"Point"}
}