{
  "type": "Feature",
  "properties": {
    "iso:country":"US",
    "sg:address":"6363 Monroe St",
    "sg:city":"Sylvania",
    "sg:classifiers":[
        {
            "category":"Restaurant",
            "type":"Food & Drink"
        }
    ],
    "sg:menulink":"http://www.allmenus.com/oh/sylvania/86351-little-caesars-pizza/menu/",
    "sg:phone":"+1 419 885 1933",
    "sg:postcode":"43560",
    "sg:province":"OH",
    "sg:tags":[
        "american",
        "pizza"
    ],
    "wof:name":"Little Caesar's Pizza",
    "wof:placetype":"venue"
},
  "geometry": {"coordinates":[-83.694799,41.715347],"type":"Point"}
}