{
  "type": "Feature",
  "properties": {
    "addr:full":"5785 Corduroy Rd Oregon OH 43616",
    "addr:housenumber":"5785",
    "addr:postcode":"43616",
    "addr:street":"Corduroy Rd",
    "iso:country":"US",
    "sg:address":"5785 Corduroy Rd",
    "sg:city":"Oregon",
    "sg:classifiers":[
        {
            "category":"Building & Trades",
            "subcategory":"Plumbing",
            "type":"Services"
        }
    ],
    "sg:phone":"+1 419 698 8926",
    "sg:postcode":"43616",
    "sg:province":"OH",
    "sg:tags":[
        "heating",
        "contractor"
    ],
    "wof:name":"Lewandowski & Sons Heating",
    "wof:placetype":"venue"
},
  "geometry": {"coordinates":[-83.42765300000001,41.659688],"type":"Point"}
}