{
  "type": "Feature",
  "properties": {
    "iso:country":"US",
    "sg:address":"1025 N Main St",
    "sg:city":"Bowling Green",
    "sg:classifiers":[
        {
            "category":"Restaurant",
            "type":"Food & Drink"
        }
    ],
    "sg:phone":"+1 419 353 6011",
    "sg:postcode":"43402",
    "sg:province":"OH",
    "sg:tags":[
        "eating"
    ],
    "wof:name":"China Dragon",
    "wof:placetype":"venue"
},
  "geometry": {"coordinates":[-83.650564,41.386816],"type":"Point"}
}