{
  "type": "Feature",
  "properties": {
    "addr:full": "1473 Clarence Ave Lakewood OH 44107",
    "addr:housenumber": "1473",
    "addr:postcode": "44107",
    "addr:street": "Clarence Ave",
    "iso:country": "US",
    "sg:address": "1473 Clarence Ave",
    "sg:city": "Lakewood",
    "sg:classifiers": [
      {
        "category": "Shopping",
        "subcategory": "Gifts \u0026 Souvenirs",
        "type": "Retail Goods"
      }
    ],
    "sg:phone": "+1 216 228 3837",
    "sg:postcode": "44107",
    "sg:province": "OH",
    "wof:name": "Shadow Box",
    "wof:placetype": "venue"
  },
  "geometry": {"coordinates":[-81.781569,41.482889],"type":"Point"}
}
