{
  "type": "Feature",
  "properties": {
    "iso:country":"US",
    "sg:address":"3567 Shaw Ave",
    "sg:city":"Cincinnati",
    "sg:classifiers":[
        {
            "category":"Professional",
            "type":"Services"
        }
    ],
    "sg:phone":"+1 513 871 4903",
    "sg:postcode":"45208",
    "sg:province":"OH",
    "wof:name":"MJW Corp Inc",
    "wof:placetype":"venue"
},
  "geometry": {"coordinates":[-84.440096,39.14031],"type":"Point"}
}