{
  "type": "Feature",
  "properties": {
    "addr:full":"111 E Court St Sidney OH 45365",
    "addr:housenumber":"111",
    "addr:postcode":"45365",
    "addr:street":"E Court St",
    "iso:country":"US",
    "sg:address":"111 E Court St",
    "sg:city":"Sidney",
    "sg:classifiers":[
        {
            "category":"Professional",
            "subcategory":"Lawyer & Legal Services",
            "type":"Services"
        }
    ],
    "sg:phone":"+1 937 492 6148",
    "sg:postcode":"45365",
    "sg:province":"OH",
    "sg:tags":[
        "attorney"
    ],
    "wof:name":"W Lynn Swinger",
    "wof:placetype":"venue"
},
  "geometry": {"coordinates":[-84.155188,40.284325],"type":"Point"}
}