{
  "type": "Feature",
  "properties": {
    "addr:full":"602 Lincoln Ave Lancaster OH 43130",
    "addr:housenumber":"602",
    "addr:postcode":"43130",
    "addr:street":"Lincoln Ave",
    "iso:country":"US",
    "sg:address":"602 Lincoln Ave",
    "sg:city":"Lancaster",
    "sg:classifiers":[
        {
            "category":"Food & Beverages",
            "subcategory":"Liquor & Beverages",
            "type":"Retail Goods"
        },
        {
            "category":"Autos & Motor Vehicles",
            "subcategory":"Fuel & Gas Station",
            "type":"Retail Goods"
        }
    ],
    "sg:phone":"+1 740 687 0247",
    "sg:postcode":"43130",
    "sg:province":"OH",
    "sg:tags":[
        "ale",
        "beer",
        "station"
    ],
    "wof:name":"22 Drive Thru",
    "wof:placetype":"venue"
},
  "geometry": {"coordinates":[-82.61342,39.711213],"type":"Point"}
}