{
  "type": "Feature",
  "properties": {
    "iso:country":"US",
    "sg:address":"700 W Pete Rose Way",
    "sg:city":"Cincinnati",
    "sg:classifiers":[
        {
            "category":"Professional",
            "subcategory":"Business Services",
            "type":"Services"
        }
    ],
    "sg:phone":"+1 513 381 6277",
    "sg:postcode":"45203",
    "sg:province":"OH",
    "sg:tags":[
        "transcribing",
        "disc"
    ],
    "wof:name":"Longworth Secretarial Svc",
    "wof:placetype":"venue"
},
  "geometry": {"coordinates":[-84.52336,39.095608],"type":"Point"}
}