{
  "type": "Feature",
  "properties": {
    "addr:full":"35 S Main St Hubbard OH 44425",
    "addr:housenumber":"35",
    "addr:postcode":"44425",
    "addr:street":"S Main St",
    "iso:country":"US",
    "sg:address":"35 S Main St",
    "sg:city":"Hubbard",
    "sg:classifiers":[
        {
            "category":"Home & Garden",
            "subcategory":"Hardware",
            "type":"Retail Goods"
        }
    ],
    "sg:phone":"+1 330 534 0704",
    "sg:postcode":"44425",
    "sg:province":"OH",
    "wof:name":"Handyman Of Hubbard",
    "wof:placetype":"venue"
},
  "geometry": {"coordinates":[-80.568822,41.155478],"type":"Point"}
}