{
  "type": "Feature",
  "properties": {
    "addr:full": "2529 Cedarwood Rd Cleveland OH 44124",
    "addr:housenumber": "2529",
    "addr:postcode": "44124",
    "addr:street": "Cedarwood Rd",
    "iso:country": "US",
    "sg:address": "2529 Cedarwood Rd",
    "sg:city": "Cleveland",
    "sg:classifiers": [
      {
        "category": "Health Services",
        "subcategory": "Doctor",
        "type": "Services"
      }
    ],
    "sg:phone": "+1 440 329 5943",
    "sg:postcode": "44124",
    "sg:province": "OH",
    "sg:tags": [
      "physician",
      "surgeon"
    ],
    "wof:name": "Siva S Nair Inc",
    "wof:placetype": "venue"
  },
  "geometry": {"coordinates":[-81.441182,41.49781],"type":"Point"}
}
