{
  "type": "Feature",
  "properties": {
    "addr:full": "6111 Deer Spring Run Canfield OH 44406",
    "addr:housenumber": "6111",
    "addr:postcode": "44406",
    "addr:street": "Deer Spring Run",
    "iso:country": "US",
    "sg:address": "6111 Deer Spring Run",
    "sg:city": "Canfield",
    "sg:classifiers": [
      {
        "category": "Building \u0026 Trades",
        "subcategory": "Construction",
        "type": "Services"
      }
    ],
    "sg:phone": "+1 330 533 3803",
    "sg:postcode": "44406",
    "sg:province": "OH",
    "sg:tags": [
      "residential"
    ],
    "wof:name": "Conti Construction Excavating",
    "wof:placetype": "venue"
  },
  "geometry": {"coordinates":[-80.765929,41.050711],"type":"Point"}
}
