{
  "type": "Feature",
  "properties": {
    "iso:country":"US",
    "sg:address":"1890 Clermontville Laurel Rd",
    "sg:city":"New Richmond",
    "sg:classifiers":[
        {
            "category":"Professional",
            "subcategory":"Advertising",
            "type":"Services"
        }
    ],
    "sg:phone":"+1 513 553 0367",
    "sg:postcode":"45157",
    "sg:province":"OH",
    "sg:tags":[
        "counselor"
    ],
    "wof:name":"Emedia Group Inc",
    "wof:placetype":"venue"
},
  "geometry": {"coordinates":[-84.20286400000001,38.922142],"type":"Point"}
}