{
  "type": "Feature",
  "properties": {
    "addr:full": "1890 Clermontville Laurel Rd New Richmond OH 45157",
    "addr:housenumber": "1890",
    "addr:postcode": "45157",
    "addr:street": "Clermontville Laurel Rd",
    "iso:country": "US",
    "sg:address": "1890 Clermontville Laurel Rd",
    "sg:city": "New Richmond",
    "sg:classifiers": [
      {
        "category": "Professional",
        "subcategory": "Advertising",
        "type": "Services"
      }
    ],
    "sg:phone": "+1 513 553 0367",
    "sg:postcode": "45157",
    "sg:province": "OH",
    "sg:tags": [
      "counselor"
    ],
    "wof:name": "Emedia Group Inc",
    "wof:placetype": "venue"
  },
  "geometry": {"coordinates":[-84.202864,38.922142],"type":"Point"}
}
