{
  "type": "Feature",
  "properties": {
    "addr:full": "1587 Kinney Ave Cincinnati OH 45231",
    "addr:housenumber": "1587",
    "addr:postcode": "45231",
    "addr:street": "Kinney Ave",
    "iso:country": "US",
    "sg:address": "1587 Kinney Ave",
    "sg:city": "Cincinnati",
    "sg:classifiers": [
      {
        "category": "Wholesale",
        "subcategory": "Chemicals \u0026 Plastics",
        "type": "Manufacturing \u0026 Wholesale Goods"
      }
    ],
    "sg:phone": "+1 513 931 2700",
    "sg:postcode": "45231",
    "sg:province": "OH",
    "sg:tags": [
      "oxygen"
    ],
    "wof:name": "Rx O2",
    "wof:placetype": "venue"
  },
  "geometry": {"coordinates":[-84.547823,39.231391],"type":"Point"}
}
