{
  "type": "Feature",
  "properties": {
    "iso:country":"US",
    "sg:address":"7835 Kyles Station Rd",
    "sg:city":"Middletown",
    "sg:classifiers":[
        {
            "category":"Shopping",
            "subcategory":"Gifts & Souvenirs",
            "type":"Retail Goods"
        }
    ],
    "sg:phone":"+1 513 779 7799",
    "sg:postcode":"45044",
    "sg:province":"OH",
    "wof:name":"Garden Cottage",
    "wof:placetype":"venue"
},
  "geometry": {"coordinates":[-84.36657,39.413753],"type":"Point"}
}