{
  "type": "Feature",
  "properties": {
    "addr:full": "7835 Kyles Station Rd Middletown OH 45044",
    "addr:housenumber": "7835",
    "addr:postcode": "45044",
    "addr:street": "Kyles Station Rd",
    "iso:country": "US",
    "sg:address": "7835 Kyles Station Rd",
    "sg:city": "Middletown",
    "sg:classifiers": [
      {
        "category": "Shopping",
        "subcategory": "Gifts \u0026 Souvenirs",
        "type": "Retail Goods"
      }
    ],
    "sg:phone": "+1 513 779 7799",
    "sg:postcode": "45044",
    "sg:province": "OH",
    "wof:name": "Garden Cottage",
    "wof:placetype": "venue"
  },
  "geometry": {"coordinates":[-84.36657,39.413753],"type":"Point"}
}
