{
  "type": "Feature",
  "properties": {
    "addr:full":"5662 Clover Ridge Dr Lima OH 45807",
    "addr:housenumber":"5662",
    "addr:postcode":"45807",
    "addr:street":"Clover Ridge Dr",
    "iso:country":"US",
    "sg:address":"5662 Clover Ridge Dr",
    "sg:city":"Lima",
    "sg:classifiers":[
        {
            "category":"Professional",
            "type":"Services"
        }
    ],
    "sg:phone":"+1 419 339 7949",
    "sg:postcode":"45807",
    "sg:province":"OH",
    "wof:name":"LA Casa Bella Designs",
    "wof:placetype":"venue"
},
  "geometry": {"coordinates":[-84.202359,40.783355],"type":"Point"}
}