{
  "type": "Feature",
  "properties": {
    "addr:full":"142 E Strong Ave Wayne OH 43466",
    "addr:housenumber":"142",
    "addr:postcode":"43466",
    "addr:street":"E Strong Ave",
    "iso:country":"US",
    "sg:address":"142 E Strong Ave",
    "sg:city":"Wayne",
    "sg:classifiers":[
        {
            "category":"Professional",
            "subcategory":"Business Services",
            "type":"Services"
        }
    ],
    "sg:phone":"+1 419 288 3155",
    "sg:postcode":"43466",
    "sg:province":"OH",
    "sg:tags":[
        "auctioneer"
    ],
    "wof:name":"Avina Auction",
    "wof:placetype":"venue"
},
  "geometry": {"coordinates":[-83.470659,41.303575],"type":"Point"}
}