{
  "type": "Feature",
  "properties": {
    "iso:country":"US",
    "sg:address":"614 N Main St",
    "sg:city":"Cadiz",
    "sg:classifiers":[
        {
            "category":"Professional",
            "type":"Services"
        }
    ],
    "sg:phone":"+1 740 942 3307",
    "sg:postcode":"43907",
    "sg:province":"OH",
    "wof:name":"Vicki Daugherty",
    "wof:placetype":"venue"
},
  "geometry": {"coordinates":[-80.992418,40.276737],"type":"Point"}
}