{
  "type": "Feature",
  "properties": {
    "iso:country":"US",
    "sg:address":"2293 Cleveland Ave",
    "sg:city":"Columbus",
    "sg:classifiers":[
        {
            "category":"Personal",
            "subcategory":"Barber",
            "type":"Services"
        }
    ],
    "sg:phone":"+1 614 263 4293",
    "sg:postcode":"43211",
    "sg:province":"OH",
    "wof:name":"Kings Kuts Barber Salon",
    "wof:placetype":"venue"
},
  "geometry": {"coordinates":[-82.966921,40.014551],"type":"Point"}
}