{
  "type": "Feature",
  "properties": {
    "addr:full":"4196 Noble St Bellaire OH 43906",
    "addr:housenumber":"4196",
    "addr:postcode":"43906",
    "addr:street":"Noble St",
    "iso:country":"US",
    "sg:address":"4196 Noble St",
    "sg:city":"Bellaire",
    "sg:classifiers":[
        {
            "category":"Organizations",
            "subcategory":"Religious Organization",
            "type":"Services"
        }
    ],
    "sg:phone":"+1 740 676 2674",
    "sg:postcode":"43906",
    "sg:province":"OH",
    "sg:tags":[
        "church"
    ],
    "wof:name":"Power Of Prayer",
    "wof:placetype":"venue"
},
  "geometry": {"coordinates":[-80.74190299999999,40.022156],"type":"Point"}
}