{
  "type": "Feature",
  "properties": {
    "iso:country":"US",
    "sg:address":"637 N Wayne Ave",
    "sg:city":"Cincinnati",
    "sg:classifiers":[
        {
            "category":"Manufacturing",
            "subcategory":"Metals",
            "type":"Manufacturing & Wholesale Goods"
        }
    ],
    "sg:phone":"+1 513 733 5162",
    "sg:postcode":"45215",
    "sg:province":"OH",
    "sg:tags":[
        "treating",
        "heat"
    ],
    "wof:name":"Ohio Flame Hardening Company",
    "wof:placetype":"venue"
},
  "geometry": {"coordinates":[-84.460238,39.237209],"type":"Point"}
}