{
  "type": "Feature",
  "properties": {
    "addr:full": "637 N Wayne Ave Cincinnati OH 45215",
    "addr:housenumber": "637",
    "addr:postcode": "45215",
    "addr:street": "N Wayne Ave",
    "iso:country": "US",
    "sg:address": "637 N Wayne Ave",
    "sg:city": "Cincinnati",
    "sg:classifiers": [
      {
        "category": "Manufacturing",
        "subcategory": "Metals",
        "type": "Manufacturing \u0026 Wholesale Goods"
      }
    ],
    "sg:phone": "+1 513 733 5162",
    "sg:postcode": "45215",
    "sg:province": "OH",
    "sg:tags": [
      "treating",
      "heat"
    ],
    "wof:name": "Ohio Flame Hardening Company",
    "wof:placetype": "venue"
  },
  "geometry": {"coordinates":[-84.460238,39.237209],"type":"Point"}
}
