{
  "type": "Feature",
  "properties": {
    "iso:country":"US",
    "sg:address":"120 Depot St",
    "sg:city":"Geneva",
    "sg:classifiers":[
        {
            "category":"Organizations",
            "subcategory":"Community Association",
            "type":"Services"
        }
    ],
    "sg:phone":"+1 440 466 4225",
    "sg:postcode":"44041",
    "sg:province":"OH",
    "sg:tags":[
        "fraternal"
    ],
    "sg:website":"www.foe.com",
    "wof:name":"Fraternal Order Of Eagles",
    "wof:placetype":"venue"
},
  "geometry": {"coordinates":[-80.948446,41.805475],"type":"Point"}
}