{
  "type": "Feature",
  "properties": {
    "addr:full":"4086 Co Rd 52 Glenmont OH 44628",
    "addr:housenumber":"4086;52",
    "addr:postcode":"44628",
    "addr:street":"Co Rd",
    "iso:country":"US",
    "sg:address":"4086 Co Rd 52",
    "sg:city":"Glenmont",
    "sg:classifiers":[
        {
            "category":"Wholesale",
            "subcategory":"Auto Parts",
            "type":"Manufacturing & Wholesale Goods"
        }
    ],
    "sg:phone":"+1 330 377 4178",
    "sg:postcode":"44628",
    "sg:province":"OH",
    "sg:tags":[
        "automobile",
        "rebuilt"
    ],
    "wof:name":"Kevin J Hanna Auto Wrecking",
    "wof:placetype":"venue"
},
  "geometry": {"coordinates":[-82.10542,40.531644],"type":"Point"}
}