{
  "type": "Feature",
  "properties": {
    "addr:full": "11807 Royalton Rd Cleveland OH 44133",
    "addr:housenumber": "11807",
    "addr:postcode": "44133",
    "addr:street": "Royalton Rd",
    "iso:country": "US",
    "sg:address": "11807 Royalton Rd",
    "sg:city": "Cleveland",
    "sg:classifiers": [
      {
        "category": "Insurance",
        "subcategory": "Insurance Agent",
        "type": "Services"
      }
    ],
    "sg:phone": "+1 440 237 8484",
    "sg:postcode": "44133",
    "sg:province": "OH",
    "sg:tags": [
      "agency",
      "gen"
    ],
    "wof:name": "Pfister Insurance",
    "wof:placetype": "venue"
  },
  "geometry": {"coordinates":[-81.764507,41.314268],"type":"Point"}
}
