{
  "type": "Feature",
  "properties": {
    "addr:full": "8600 US Rte 224 Van Wert OH 45891",
    "addr:housenumber": "8600",
    "addr:postcode": "45891",
    "addr:street": "Us Rte 224",
    "iso:country": "US",
    "sg:address": "8600 US Rte 224",
    "sg:city": "Van Wert",
    "sg:phone": "+1 419 238 0149",
    "sg:postcode": "45891",
    "sg:province": "OH",
    "sg:tags": [
      "farm",
      "corn",
      "wheat",
      "soybean"
    ],
    "wof:name": "Ralph Schaadt",
    "wof:placetype": "venue"
  },
  "geometry": {"coordinates":[-84.656618,40.851271],"type":"Point"}
}
