{
  "type": "Feature",
  "properties": {
    "addr:full": "149 22nd St SE New Philadelphia OH 44663",
    "addr:housenumber": "149",
    "addr:postcode": "44663",
    "addr:street": "22Nd St Se",
    "iso:country": "US",
    "sg:address": "149 22nd St SE",
    "sg:city": "New Philadelphia",
    "sg:classifiers": [
      {
        "category": "Real Estate",
        "subcategory": "Real Estate Operator",
        "type": "Services"
      }
    ],
    "sg:phone": "+1 330 339 7035",
    "sg:postcode": "44663",
    "sg:province": "OH",
    "sg:tags": [
      "property",
      "lessor"
    ],
    "wof:name": "Horn Richard Ray",
    "wof:placetype": "venue"
  },
  "geometry": {"coordinates":[-81.41041,40.46311],"type":"Point"}
}
