{
  "type": "Feature",
  "properties": {
    "addr:full": "5868 Fulton Dr NW Canton OH 44718",
    "addr:housenumber": "5868",
    "addr:postcode": "44718",
    "addr:street": "Fulton Dr Nw",
    "iso:country": "US",
    "sg:address": "5868 Fulton Dr NW",
    "sg:city": "Canton",
    "sg:classifiers": [
      {
        "category": "Food \u0026 Beverages",
        "subcategory": "Candy",
        "type": "Retail Goods"
      }
    ],
    "sg:phone": "+1 330 244 9185",
    "sg:postcode": "44718",
    "sg:province": "OH",
    "sg:tags": [
      "confectionery"
    ],
    "wof:name": "Fudge Lady",
    "wof:placetype": "venue"
  },
  "geometry": {"coordinates":[-81.453885,40.855865],"type":"Point"}
}
