{
  "type": "Feature",
  "properties": {
    "iso:country":"US",
    "sg:address":"5868 Fulton Dr NW",
    "sg:city":"Canton",
    "sg:classifiers":[
        {
            "category":"Food & Beverages",
            "subcategory":"Candy",
            "type":"Retail Goods"
        }
    ],
    "sg:phone":"+1 330 244 9185",
    "sg:postcode":"44718",
    "sg:province":"OH",
    "sg:tags":[
        "confectionery"
    ],
    "wof:name":"Fudge Lady",
    "wof:placetype":"venue"
},
  "geometry": {"coordinates":[-81.453885,40.855865],"type":"Point"}
}