{
  "type": "Feature",
  "properties": {
    "addr:full":"5803 Wendcliff Dr Columbus OH 43231",
    "addr:housenumber":"5803",
    "addr:postcode":"43231",
    "addr:street":"Wendcliff Dr",
    "iso:country":"US",
    "sg:address":"5803 Wendcliff Dr",
    "sg:city":"Columbus",
    "sg:classifiers":[
        {
            "category":"Professional",
            "type":"Services"
        }
    ],
    "sg:phone":"+1 614 890 4852",
    "sg:postcode":"43231",
    "sg:province":"OH",
    "sg:tags":[
        "establishment"
    ],
    "wof:name":"Additions By Reina",
    "wof:placetype":"venue"
},
  "geometry": {"coordinates":[-82.942329,40.090131],"type":"Point"}
}