{
  "type": "Feature",
  "properties": {
    "iso:country":"US",
    "sg:address":"845 East Ave",
    "sg:city":"Hamilton",
    "sg:classifiers":[
        {
            "category":"Wholesale",
            "subcategory":"Auto Parts",
            "type":"Manufacturing & Wholesale Goods"
        }
    ],
    "sg:phone":"+1 513 896 9667",
    "sg:postcode":"45011",
    "sg:province":"OH",
    "sg:tags":[
        "automobile",
        "supply"
    ],
    "wof:name":"Mighty Auto Parts",
    "wof:placetype":"venue"
},
  "geometry": {"coordinates":[-84.553557,39.386752],"type":"Point"}
}