{
  "type": "Feature",
  "properties": {
    "addr:full":"530 Lockerbie Ln Dayton OH 45429",
    "addr:housenumber":"530",
    "addr:postcode":"45429",
    "addr:street":"Lockerbie Ln",
    "iso:country":"US",
    "sg:address":"530 Lockerbie Ln",
    "sg:city":"Dayton",
    "sg:classifiers":[
        {
            "category":"Professional",
            "type":"Services"
        }
    ],
    "sg:phone":"+1 937 298 8209",
    "sg:postcode":"45429",
    "sg:province":"OH",
    "wof:name":"McCall Family LLC",
    "wof:placetype":"venue"
},
  "geometry": {"coordinates":[-84.179801,39.68759],"type":"Point"}
}