{
  "type": "Feature",
  "properties": {
    "addr:full": "3289 W Siebenthaler Ave Dayton OH 45406",
    "addr:housenumber": "3289",
    "addr:postcode": "45406",
    "addr:street": "W Siebenthaler Ave",
    "iso:country": "US",
    "sg:address": "3289 W Siebenthaler Ave",
    "sg:city": "Dayton",
    "sg:classifiers": [
      {
        "category": "Wholesale",
        "subcategory": "Machinery \u0026 Supplies",
        "type": "Manufacturing \u0026 Wholesale Goods"
      },
      {
        "category": "Shopping",
        "type": "Retail Goods"
      }
    ],
    "sg:phone": "+1 937 274 2211",
    "sg:postcode": "45406",
    "sg:province": "OH",
    "sg:tags": [
      "equipment",
      "establishment",
      "cosmetic",
      "perfume"
    ],
    "wof:name": "Essence Beauty Supply Inc",
    "wof:placetype": "venue"
  },
  "geometry": {"coordinates":[-84.244585,39.798211],"type":"Point"}
}
