{
  "type": "Feature",
  "properties": {
    "addr:full":"125 E Main St Greenville OH 45331",
    "addr:housenumber":"125",
    "addr:postcode":"45331",
    "addr:street":"E Main St",
    "iso:country":"US",
    "sg:address":"125 E Main St",
    "sg:city":"Greenville",
    "sg:classifiers":[
        {
            "category":"Restaurant",
            "type":"Food & Drink"
        }
    ],
    "sg:phone":"+1 937 548 8032",
    "sg:postcode":"45331",
    "sg:province":"OH",
    "wof:name":"Colony Restaurant",
    "wof:placetype":"venue"
},
  "geometry": {"coordinates":[-84.632947,40.102615],"type":"Point"}
}