{
  "type": "Feature",
  "properties": {
    "addr:full": "11 Camargo Pines Cincinnati OH 45243",
    "addr:housenumber": "11",
    "addr:postcode": "45243",
    "addr:street": "Camargo Pines",
    "iso:country": "US",
    "sg:address": "11 Camargo Pines",
    "sg:city": "Cincinnati",
    "sg:classifiers": [
      {
        "category": "Real Estate",
        "subcategory": "Real Estate Agent",
        "type": "Services"
      }
    ],
    "sg:phone": "+1 513 791 1643",
    "sg:postcode": "45243",
    "sg:province": "OH",
    "wof:name": "Indus Realty Co",
    "wof:placetype": "venue"
  },
  "geometry": {"coordinates":[-84.334776,39.202405],"type":"Point"}
}
