{
  "type": "Feature",
  "properties": {
    "iso:country":"US",
    "sg:address":"128 N Dorcas Rd",
    "sg:city":"Toledo",
    "sg:classifiers":[
        {
            "category":"Building & Trades",
            "subcategory":"Construction",
            "type":"Services"
        }
    ],
    "sg:phone":"+1 419 866 5867",
    "sg:postcode":"43615",
    "sg:province":"OH",
    "sg:tags":[
        "house"
    ],
    "wof:name":"Multi Mode Concepts & Cnstr",
    "wof:placetype":"venue"
},
  "geometry": {"coordinates":[-83.701387,41.642568],"type":"Point"}
}