{
  "type": "Feature",
  "properties": {
    "addr:full": "128 N Dorcas Rd Toledo OH 43615",
    "addr:housenumber": "128",
    "addr:postcode": "43615",
    "addr:street": "N Dorcas Rd",
    "iso:country": "US",
    "sg:address": "128 N Dorcas Rd",
    "sg:city": "Toledo",
    "sg:classifiers": [
      {
        "category": "Building \u0026 Trades",
        "subcategory": "Construction",
        "type": "Services"
      }
    ],
    "sg:phone": "+1 419 866 5867",
    "sg:postcode": "43615",
    "sg:province": "OH",
    "sg:tags": [
      "house"
    ],
    "wof:name": "Multi Mode Concepts \u0026 Cnstr",
    "wof:placetype": "venue"
  },
  "geometry": {"coordinates":[-83.701387,41.642568],"type":"Point"}
}
