{
  "type": "Feature",
  "properties": {
    "iso:country":"US",
    "sg:address":"2909 Cleveland Ave NW",
    "sg:city":"Canton",
    "sg:classifiers":[
        {
            "category":"Retail",
            "subcategory":"Auto Repair",
            "type":"Services"
        }
    ],
    "sg:phone":"+1 330 478 1401",
    "sg:postcode":"44709",
    "sg:province":"OH",
    "sg:tags":[
        "body",
        "automobile",
        "painting"
    ],
    "wof:name":"Nick's Body Shop",
    "wof:placetype":"venue"
},
  "geometry": {"coordinates":[-81.387704,40.831569],"type":"Point"}
}