{
  "type": "Feature",
  "properties": {
    "addr:full": "3908 Ridge Rd Cortland OH 44410",
    "addr:housenumber": "3908",
    "addr:postcode": "44410",
    "addr:street": "Ridge Rd",
    "iso:country": "US",
    "sg:address": "3908 Ridge Rd",
    "sg:city": "Cortland",
    "sg:classifiers": [
      {
        "category": "Professional",
        "type": "Services"
      }
    ],
    "sg:phone": "+1 330 637 8377",
    "sg:postcode": "44410",
    "sg:province": "OH",
    "wof:name": "Louis F Omerzo",
    "wof:placetype": "venue"
  },
  "geometry": {"coordinates":[-80.691882,41.32499],"type":"Point"}
}
