{
  "type": "Feature",
  "properties": {
    "iso:country":"US",
    "sg:address":"3908 Ridge Rd",
    "sg:city":"Cortland",
    "sg:classifiers":[
        {
            "category":"Professional",
            "type":"Services"
        }
    ],
    "sg:phone":"+1 330 637 8377",
    "sg:postcode":"44410",
    "sg:province":"OH",
    "wof:name":"Louis F Omerzo",
    "wof:placetype":"venue"
},
  "geometry": {"coordinates":[-80.69188200000001,41.32499],"type":"Point"}
}