{
  "type": "Feature",
  "properties": {
    "addr:full": "9315 Brandywine Rd Northfield OH 44067",
    "addr:housenumber": "9315",
    "addr:postcode": "44067",
    "addr:street": "Brandywine Rd",
    "iso:country": "US",
    "sg:address": "9315 Brandywine Rd",
    "sg:city": "Northfield",
    "sg:classifiers": [
      {
        "category": "Shopping",
        "subcategory": "Bicycles \u0026 Sporting Goods",
        "type": "Retail Goods"
      }
    ],
    "sg:phone": "+1 330 468 3655",
    "sg:postcode": "44067",
    "sg:province": "OH",
    "wof:name": "Rrco Technical Consulting",
    "wof:placetype": "venue"
  },
  "geometry": {"coordinates":[-81.538889,41.304625],"type":"Point"}
}
