{
  "type": "Feature",
  "properties": {
    "iso:country":"US",
    "sg:address":"501 S Main St",
    "sg:city":"Akron",
    "sg:classifiers":[
        {
            "category":"Building & Trades",
            "subcategory":"Construction",
            "type":"Services"
        }
    ],
    "sg:phone":"+1 330 376 2825",
    "sg:postcode":"44308",
    "sg:province":"OH",
    "sg:tags":[
        "residential"
    ],
    "wof:name":"Infinity Construction",
    "wof:placetype":"venue"
},
  "geometry": {"coordinates":[-81.52465599999999,41.072739],"type":"Point"}
}