{
  "type": "Feature",
  "properties": {
    "iso:country":"US",
    "sg:address":"8287 Springboro Pike",
    "sg:city":"Miamisburg",
    "sg:classifiers":[
        {
            "category":"Shopping",
            "subcategory":"Discount & Variety Stores",
            "type":"Retail Goods"
        }
    ],
    "sg:phone":"+1 937 432 0115",
    "sg:postcode":"45342",
    "sg:province":"OH",
    "wof:name":"Dollar Tree",
    "wof:placetype":"venue"
},
  "geometry": {"coordinates":[-84.226051,39.629309],"type":"Point"}
}