{
  "type": "Feature",
  "properties": {
    "addr:full":"129 Marc Dr Cuyahoga Falls OH 44223",
    "addr:housenumber":"129",
    "addr:postcode":"44223",
    "addr:street":"Marc Dr",
    "iso:country":"US",
    "sg:address":"129 Marc Dr",
    "sg:city":"Cuyahoga Falls",
    "sg:classifiers":[
        {
            "category":"Manufacturing",
            "subcategory":"Motor Vehicles & Parts",
            "type":"Manufacturing & Wholesale Goods"
        }
    ],
    "sg:phone":"+1 330 916 8700",
    "sg:postcode":"44223",
    "sg:province":"OH",
    "sg:tags":[
        "automobile",
        "supply"
    ],
    "sg:website":"www.accuridecorp.com",
    "wof:name":"Accuride Corp",
    "wof:placetype":"venue"
},
  "geometry": {"coordinates":[-81.505049,41.170925],"type":"Point"}
}