{
  "type": "Feature",
  "properties": {
    "addr:full": "605 E 5th St Manchester OH 45144",
    "addr:housenumber": "605",
    "addr:postcode": "45144",
    "addr:street": "E 5Th St",
    "iso:country": "US",
    "sg:address": "605 E 5th St",
    "sg:city": "Manchester",
    "sg:classifiers": [
      {
        "category": "Shopping",
        "subcategory": "Florist",
        "type": "Retail Goods"
      }
    ],
    "sg:phone": "+1 937 549 1952",
    "sg:postcode": "45144",
    "sg:province": "OH",
    "wof:name": "Perfect Petals",
    "wof:placetype": "venue"
  },
  "geometry": {"coordinates":[-83.599888,38.691447],"type":"Point"}
}
