{
  "type": "Feature",
  "properties": {
    "addr:full": "2021 E Dublin Granville Rd Columbus OH 43229",
    "addr:housenumber": "2021",
    "addr:postcode": "43229",
    "addr:street": "E Dublin Granville Rd",
    "iso:country": "US",
    "sg:address": "2021 E Dublin Granville Rd",
    "sg:city": "Columbus",
    "sg:classifiers": [
      {
        "category": "Travel",
        "subcategory": "Travel Agent",
        "type": "Entertainment"
      }
    ],
    "sg:phone": "+1 614 430 8668",
    "sg:postcode": "43229",
    "sg:province": "OH",
    "sg:tags": [
      "agency",
      "bureau"
    ],
    "wof:name": "Glory Shipping \u0026 Travel",
    "wof:placetype": "venue"
  },
  "geometry": {"coordinates":[-82.962744,40.086543],"type":"Point"}
}
