{
  "type": "Feature",
  "properties": {
    "addr:full": "8121 Uehling Ln Dayton OH 45424",
    "addr:housenumber": "8121",
    "addr:postcode": "45424",
    "addr:street": "Uehling Ln",
    "iso:country": "US",
    "sg:address": "8121 Uehling Ln",
    "sg:city": "Dayton",
    "sg:classifiers": [
      {
        "category": "Autos \u0026 Motor Vehicles",
        "subcategory": "Fuel \u0026 Gas Station",
        "type": "Retail Goods"
      }
    ],
    "sg:phone": "+1 937 233 6001",
    "sg:postcode": "45424",
    "sg:province": "OH",
    "sg:tags": [
      "oil"
    ],
    "sg:website": "www.truenorth.org",
    "wof:name": "True North Energy",
    "wof:placetype": "venue"
  },
  "geometry": {"coordinates":[-84.129753,39.870667],"type":"Point"}
}
