{
  "type": "Feature",
  "properties": {
    "iso:country":"US",
    "sg:address":"8121 Uehling Ln",
    "sg:city":"Dayton",
    "sg:classifiers":[
        {
            "category":"Autos & Motor Vehicles",
            "subcategory":"Fuel & Gas Station",
            "type":"Retail Goods"
        }
    ],
    "sg:phone":"+1 937 233 6001",
    "sg:postcode":"45424",
    "sg:province":"OH",
    "sg:tags":[
        "oil"
    ],
    "sg:website":"www.truenorth.org",
    "wof:name":"True North Energy",
    "wof:placetype":"venue"
},
  "geometry": {"coordinates":[-84.12975299999999,39.870667],"type":"Point"}
}