{
  "type": "Feature",
  "properties": {
    "addr:full": "2730 McGuffey Rd Youngstown OH 44505",
    "addr:housenumber": "2730",
    "addr:postcode": "44505",
    "addr:street": "Mcguffey Rd",
    "iso:country": "US",
    "sg:address": "2730 McGuffey Rd",
    "sg:city": "Youngstown",
    "sg:classifiers": [
      {
        "category": "Professional",
        "subcategory": "Employment Agencies",
        "type": "Services"
      }
    ],
    "sg:phone": "+1 330 743 2193",
    "sg:postcode": "44505",
    "sg:province": "OH",
    "sg:tags": [
      "opportunity"
    ],
    "wof:name": "Truth Ministry",
    "wof:placetype": "venue"
  },
  "geometry": {"coordinates":[-80.595032,41.115654],"type":"Point"}
}
