{
  "type": "Feature",
  "properties": {
    "addr:full": "4000 Red Bank Rd Cincinnati OH 45227",
    "addr:housenumber": "4000",
    "addr:postcode": "45227",
    "addr:street": "Red Bank Rd",
    "iso:country": "US",
    "sg:address": "4000 Red Bank Rd",
    "sg:city": "Cincinnati",
    "sg:classifiers": [
      {
        "category": "Manufacturing",
        "subcategory": "Tools \u0026 Machinery",
        "type": "Manufacturing \u0026 Wholesale Goods"
      }
    ],
    "sg:phone": "+1 513 271 3950",
    "sg:postcode": "45227",
    "sg:province": "OH",
    "sg:tags": [
      "equipment",
      "system",
      "automation"
    ],
    "wof:name": "Lott Tool Corp",
    "wof:placetype": "venue"
  },
  "geometry": {"coordinates":[-84.404326,39.150144],"type":"Point"}
}
