{
  "type": "Feature",
  "properties": {
    "addr:full": "2940 Groveport Rd Columbus OH 43207",
    "addr:postcode": "2940;43207",
    "addr:street": "Groveport Rd",
    "iso:country": "US",
    "sg:address": "2940 Groveport Rd",
    "sg:city": "Columbus",
    "sg:classifiers": [
      {
        "category": "Shopping",
        "subcategory": "Pharmacy",
        "type": "Retail Goods"
      }
    ],
    "sg:phone": "+1 614 491 3446",
    "sg:postcode": "43207",
    "sg:province": "OH",
    "sg:tags": [
      "drug",
      "store"
    ],
    "wof:name": "Drug Store Pharmacy Inc",
    "wof:placetype": "venue"
  },
  "geometry": {"coordinates":[-82.965662,39.904],"type":"Point"}
}
