{
  "type": "Feature",
  "properties": {
    "iso:country":"US",
    "sg:address":"3140 Kingstree Ct",
    "sg:city":"Dublin",
    "sg:classifiers":[
        {
            "category":"Professional",
            "subcategory":"Management & Consulting",
            "type":"Services"
        }
    ],
    "sg:phone":"+1 614 734 4000",
    "sg:postcode":"43017",
    "sg:province":"OH",
    "sg:tags":[
        "counselor",
        "public",
        "relations"
    ],
    "wof:name":"Franklin & Son",
    "wof:placetype":"venue"
},
  "geometry": {"coordinates":[-83.100984,40.07198],"type":"Point"}
}