{
  "type": "Feature",
  "properties": {
    "addr:full":"6617 S Canterbury Rd Cleveland OH 44129",
    "addr:housenumber":"6617",
    "addr:postcode":"44129",
    "addr:street":"S Canterbury Rd",
    "iso:country":"US",
    "sg:address":"6617 S Canterbury Rd",
    "sg:city":"Cleveland",
    "sg:classifiers":[
        {
            "category":"Social Services",
            "type":"Services"
        }
    ],
    "sg:phone":"+1 440 886 4174",
    "sg:postcode":"44129",
    "sg:province":"OH",
    "sg:tags":[
        "organization",
        "welfare"
    ],
    "wof:name":"Harold Hawkins",
    "wof:placetype":"venue"
},
  "geometry": {"coordinates":[-81.74066000000001,41.384866],"type":"Point"}
}