{
  "type": "Feature",
  "properties": {
    "iso:country":"US",
    "sg:address":"2811 Swiss Chalet Ct",
    "sg:city":"Cincinnati",
    "sg:classifiers":[
        {
            "category":"Organizations",
            "subcategory":"Community Association",
            "type":"Services"
        }
    ],
    "sg:phone":"+1 513 221 4330",
    "sg:postcode":"45220",
    "sg:province":"OH",
    "sg:tags":[
        "fraternal",
        "social"
    ],
    "wof:name":"Sigma Nu Fraternity Inc",
    "wof:placetype":"venue"
},
  "geometry": {"coordinates":[-84.5203,39.133643],"type":"Point"}
}