{
  "type": "Feature",
  "properties": {
    "addr:full":"2500 Clifton Ave Cincinnati OH 45219",
    "addr:housenumber":"2500",
    "addr:postcode":"45219",
    "addr:street":"Clifton Ave",
    "iso:country":"US",
    "sg:address":"2500 Clifton Ave",
    "sg:city":"Cincinnati",
    "sg:classifiers":[
        {
            "category":"Real Estate",
            "subcategory":"Real Estate Operator",
            "type":"Services"
        }
    ],
    "sg:phone":"+1 513 961 5222",
    "sg:postcode":"45219",
    "sg:province":"OH",
    "sg:tags":[
        "apartment"
    ],
    "wof:name":"University Park Apt Leasing",
    "wof:placetype":"venue"
},
  "geometry": {"coordinates":[-84.520743,39.128623],"type":"Point"}
}