{
  "type": "Feature",
  "properties": {
    "iso:country":"US",
    "sg:address":"10147 Royalton Rd",
    "sg:city":"Cleveland",
    "sg:classifiers":[
        {
            "category":"Home & Garden",
            "subcategory":"Furniture",
            "type":"Retail Goods"
        }
    ],
    "sg:phone":"+1 440 582 9903",
    "sg:postcode":"44133",
    "sg:province":"OH",
    "wof:name":"Furniture Nook-North Royalton",
    "wof:placetype":"venue"
},
  "geometry": {"coordinates":[-81.761245,41.313367],"type":"Point"}
}