{
  "type": "Feature",
  "properties": {
    "addr:full": "10147 Royalton Rd Cleveland OH 44133",
    "addr:housenumber": "10147",
    "addr:postcode": "44133",
    "addr:street": "Royalton Rd",
    "iso:country": "US",
    "sg:address": "10147 Royalton Rd",
    "sg:city": "Cleveland",
    "sg:classifiers": [
      {
        "category": "Home \u0026 Garden",
        "subcategory": "Furniture",
        "type": "Retail Goods"
      }
    ],
    "sg:phone": "+1 440 582 9903",
    "sg:postcode": "44133",
    "sg:province": "OH",
    "wof:name": "Furniture Nook-North Royalton",
    "wof:placetype": "venue"
  },
  "geometry": {"coordinates":[-81.761245,41.313367],"type":"Point"}
}
