{
  "type": "Feature",
  "properties": {
    "addr:full":"545 E Cuyahoga Falls Ave Akron OH 44310",
    "addr:housenumber":"545",
    "addr:postcode":"44310",
    "addr:street":"E Cuyahoga Falls Ave",
    "iso:country":"US",
    "sg:address":"545 E Cuyahoga Falls Ave",
    "sg:city":"Akron",
    "sg:classifiers":[
        {
            "category":"Professional",
            "subcategory":"Lawyer & Legal Services",
            "type":"Services"
        }
    ],
    "sg:phone":"+1 330 929 2838",
    "sg:postcode":"44310",
    "sg:province":"OH",
    "sg:tags":[
        "attorney"
    ],
    "wof:name":"Diane M Johnson",
    "wof:placetype":"venue"
},
  "geometry": {"coordinates":[-81.500208,41.113203],"type":"Point"}
}