{
  "type": "Feature",
  "properties": {
    "addr:full": "3570 Warrensville Center Rd Cleveland OH 44122",
    "addr:postcode": "3570;44122",
    "addr:street": "Warrensville Center Rd",
    "iso:country": "US",
    "sg:address": "3570 Warrensville Center Rd",
    "sg:city": "Cleveland",
    "sg:classifiers": [
      {
        "category": "Manufacturing",
        "subcategory": "Chemicals \u0026 Compounds",
        "type": "Manufacturing \u0026 Wholesale Goods"
      }
    ],
    "sg:phone": "+1 216 283 0832",
    "sg:postcode": "44122",
    "sg:province": "OH",
    "wof:name": "Cleveland Polymer Tech LLC",
    "wof:placetype": "venue"
  },
  "geometry": {"coordinates":[-81.536225,41.461465],"type":"Point"}
}
