{
  "type": "Feature",
  "properties": {
    "iso:country":"US",
    "sg:address":"7057 W 130th St",
    "sg:city":"Cleveland",
    "sg:classifiers":[
        {
            "category":"Health Services",
            "subcategory":"Health Practitioner",
            "type":"Services"
        }
    ],
    "sg:phone":"+1 440 842 2222",
    "sg:postcode":"44130",
    "sg:province":"OH",
    "sg:tags":[
        "hypnotist"
    ],
    "wof:name":"Southland Hypnosis",
    "wof:placetype":"venue"
},
  "geometry": {"coordinates":[-81.78478,41.372198],"type":"Point"}
}