{
  "type": "Feature",
  "properties": {
    "addr:full": "403 Vine St Cincinnati OH 45202",
    "addr:housenumber": "403",
    "addr:postcode": "45202",
    "addr:street": "Vine St",
    "iso:country": "US",
    "sg:address": "403 Vine St",
    "sg:city": "Cincinnati",
    "sg:classifiers": [
      {
        "category": "Banks \u0026 Credit Unions",
        "subcategory": "Investment Brokerage",
        "type": "Services"
      }
    ],
    "sg:phone": "+1 513 579 0123",
    "sg:postcode": "45202",
    "sg:province": "OH",
    "sg:tags": [
      "firm"
    ],
    "wof:name": "Madison Markuette Dev Co",
    "wof:placetype": "venue"
  },
  "geometry": {"coordinates":[-84.51284,39.100315],"type":"Point"}
}
