{
  "type": "Feature",
  "properties": {
    "addr:full":"10 Andover Dr Springboro OH 45066",
    "addr:housenumber":"10",
    "addr:postcode":"45066",
    "addr:street":"Andover Dr",
    "iso:country":"US",
    "sg:address":"10 Andover Dr",
    "sg:city":"Springboro",
    "sg:classifiers":[
        {
            "category":"Building & Trades",
            "subcategory":"Construction",
            "type":"Services"
        }
    ],
    "sg:phone":"+1 937 748 2040",
    "sg:postcode":"45066",
    "sg:province":"OH",
    "sg:tags":[
        "builder",
        "operative"
    ],
    "wof:name":"Williamsburg Homes",
    "wof:placetype":"venue"
},
  "geometry": {"coordinates":[-84.224431,39.547938],"type":"Point"}
}