{
  "type": "Feature",
  "properties": {
    "addr:full": "5215 Mulligans Bluff Rd Ney OH 43549",
    "addr:housenumber": "5215",
    "addr:postcode": "43549",
    "addr:street": "Mulligans Bluff Rd",
    "iso:country": "US",
    "sg:address": "5215 Mulligans Bluff Rd",
    "sg:city": "Ney",
    "sg:classifiers": [
      {
        "category": "Building \u0026 Trades",
        "subcategory": "Construction",
        "type": "Services"
      }
    ],
    "sg:phone": "+1 419 658 2754",
    "sg:postcode": "43549",
    "sg:province": "OH",
    "sg:tags": [
      "house"
    ],
    "wof:name": "Salyers Construction LLC",
    "wof:placetype": "venue"
  },
  "geometry": {"coordinates":[-84.49705,41.366278],"type":"Point"}
}
