{
  "type": "Feature",
  "properties": {
    "addr:full": "743 17th St Elyria OH 44035",
    "addr:housenumber": "743",
    "addr:postcode": "44035",
    "addr:street": "17Th St",
    "iso:country": "US",
    "sg:address": "743 17th St",
    "sg:city": "Elyria",
    "sg:classifiers": [
      {
        "category": "Manufacturing",
        "subcategory": "Printing",
        "type": "Manufacturing \u0026 Wholesale Goods"
      }
    ],
    "sg:phone": "+1 440 323 7341",
    "sg:postcode": "44035",
    "sg:province": "OH",
    "sg:tags": [
      "commercial"
    ],
    "wof:name": "Bip Print Desktop Publishing",
    "wof:placetype": "venue"
  },
  "geometry": {"coordinates":[-82.123119,41.350724],"type":"Point"}
}
