{
  "type": "Feature",
  "properties": {
    "addr:full": "8005 Mayfield Rd Chesterland OH 44026",
    "addr:housenumber": "8005",
    "addr:postcode": "44026",
    "addr:street": "Mayfield Rd",
    "iso:country": "US",
    "sg:address": "8005 Mayfield Rd",
    "sg:city": "Chesterland",
    "sg:classifiers": [
      {
        "category": "Restaurant",
        "type": "Food \u0026 Drink"
      }
    ],
    "sg:phone": "+1 440 729 7205",
    "sg:postcode": "44026",
    "sg:province": "OH",
    "sg:tags": [
      "eating"
    ],
    "wof:name": "High Peaks Coffee",
    "wof:placetype": "venue"
  },
  "geometry": {"coordinates":[-81.358568,41.52232],"type":"Point"}
}
