{
  "type": "Feature",
  "properties": {
    "addr:full":"351 Burbank Dr Toledo OH 43607",
    "addr:housenumber":"351",
    "addr:postcode":"43607",
    "addr:street":"Burbank Dr",
    "iso:country":"US",
    "sg:address":"351 Burbank Dr",
    "sg:city":"Toledo",
    "sg:classifiers":[
        {
            "category":"Wholesale",
            "subcategory":"Machinery & Supplies",
            "type":"Manufacturing & Wholesale Goods"
        }
    ],
    "sg:phone":"+1 419 531 1437",
    "sg:postcode":"43607",
    "sg:province":"OH",
    "sg:tags":[
        "tool"
    ],
    "wof:name":"Riggs Tool Co",
    "wof:placetype":"venue"
},
  "geometry": {"coordinates":[-83.609139,41.642606],"type":"Point"}
}