{
  "type": "Feature",
  "properties": {
    "addr:full": "264 N Dixie Dr Vandalia OH 45377",
    "addr:housenumber": "264",
    "addr:postcode": "45377",
    "addr:street": "N Dixie Dr",
    "iso:country": "US",
    "sg:address": "264 N Dixie Dr",
    "sg:city": "Vandalia",
    "sg:classifiers": [
      {
        "category": "Manufacturing",
        "subcategory": "Retail Goods",
        "type": "Manufacturing \u0026 Wholesale Goods"
      }
    ],
    "sg:phone": "+1 937 454 5384",
    "sg:postcode": "45377",
    "sg:province": "OH",
    "sg:tags": [
      "carbon",
      "rep",
      "ribbon",
      "mfg"
    ],
    "wof:name": "A-1 Rechargers",
    "wof:placetype": "venue"
  },
  "geometry": {"coordinates":[-84.198344,39.894807],"type":"Point"}
}
