{
  "type": "Feature",
  "properties": {
    "addr:full":"362 Stetler Ave Akron OH 44312",
    "addr:housenumber":"362",
    "addr:postcode":"44312",
    "addr:street":"Stetler Ave",
    "iso:country":"US",
    "sg:address":"362 Stetler Ave",
    "sg:city":"Akron",
    "sg:classifiers":[
        {
            "category":"Building & Trades",
            "subcategory":"Construction",
            "type":"Services"
        }
    ],
    "sg:phone":"+1 330 733 3656",
    "sg:postcode":"44312",
    "sg:province":"OH",
    "sg:tags":[
        "concrete",
        "contractor"
    ],
    "wof:name":"Tri County Concrete Leveling",
    "wof:placetype":"venue"
},
  "geometry": {"coordinates":[-81.434719,41.049612],"type":"Point"}
}