{
  "type": "Feature",
  "properties": {
    "addr:full": "17070 Pearl Rd Strongsville OH 44136",
    "addr:housenumber": "17070",
    "addr:postcode": "44136",
    "addr:street": "Pearl Rd",
    "iso:country": "US",
    "sg:address": "17070 Pearl Rd",
    "sg:city": "Strongsville",
    "sg:classifiers": [
      {
        "category": "Restaurant",
        "type": "Food \u0026 Drink"
      }
    ],
    "sg:menulink": "http://www.allmenus.com/oh/strongsville/274009-shinto-japanese-steakhouse/menu/",
    "sg:phone": "+1 440 878 0760",
    "sg:postcode": "44136",
    "sg:province": "OH",
    "sg:tags": [
      "japanese",
      "asian"
    ],
    "wof:name": "Shinto Japanese Steakhouse",
    "wof:placetype": "venue"
  },
  "geometry": {"coordinates":[-81.835334,41.293846],"type":"Point"}
}
