{
  "type": "Feature",
  "properties": {
    "addr:full":"11212 Croton Rd Croton OH 43013",
    "addr:housenumber":"11212",
    "addr:postcode":"43013",
    "addr:street":"Croton Rd",
    "iso:country":"US",
    "sg:address":"11212 Croton Rd",
    "sg:city":"Croton",
    "sg:classifiers":[
        {
            "category":"Wholesale",
            "subcategory":"Poultry",
            "type":"Manufacturing & Wholesale Goods"
        }
    ],
    "sg:phone":"+1 740 893 7200",
    "sg:postcode":"43013",
    "sg:province":"OH",
    "sg:tags":[
        "eggs"
    ],
    "wof:name":"Ohio Fresh Eggs",
    "wof:placetype":"venue"
},
  "geometry": {"coordinates":[-82.69061600000001,40.21379],"type":"Point"}
}