{
  "type": "Feature",
  "properties": {
    "iso:country":"US",
    "sg:address":"893 E National Rd",
    "sg:city":"Vandalia",
    "sg:classifiers":[
        {
            "category":"Restaurant",
            "type":"Food & Drink"
        }
    ],
    "sg:phone":"+1 937 890 8899",
    "sg:postcode":"45377",
    "sg:province":"OH",
    "sg:tags":[
        "eating"
    ],
    "wof:name":"Bunkers Bar & Grill",
    "wof:placetype":"venue"
},
  "geometry": {"coordinates":[-84.18156500000001,39.89229],"type":"Point"}
}