{
  "type": "Feature",
  "properties": {
    "addr:full": "893 E National Rd Vandalia OH 45377",
    "addr:housenumber": "893",
    "addr:postcode": "45377",
    "addr:street": "E National Rd",
    "iso:country": "US",
    "sg:address": "893 E National Rd",
    "sg:city": "Vandalia",
    "sg:classifiers": [
      {
        "category": "Restaurant",
        "type": "Food \u0026 Drink"
      }
    ],
    "sg:phone": "+1 937 890 8899",
    "sg:postcode": "45377",
    "sg:province": "OH",
    "sg:tags": [
      "eating"
    ],
    "wof:name": "Bunkers Bar \u0026 Grill",
    "wof:placetype": "venue"
  },
  "geometry": {"coordinates":[-84.181565,39.89229],"type":"Point"}
}
