{
  "type": "Feature",
  "properties": {
    "addr:full": "485 W Market St Tiffin OH 44883",
    "addr:housenumber": "485",
    "addr:postcode": "44883",
    "addr:street": "W Market St",
    "iso:country": "US",
    "sg:address": "485 W Market St",
    "sg:city": "Tiffin",
    "sg:classifiers": [
      {
        "category": "Health Services",
        "subcategory": "Doctor",
        "type": "Services"
      }
    ],
    "sg:phone": "+1 419 448 4553",
    "sg:postcode": "44883",
    "sg:province": "OH",
    "sg:tags": [
      "physician",
      "surgeon"
    ],
    "wof:name": "Punita Kothari MD",
    "wof:placetype": "venue"
  },
  "geometry": {"coordinates":[-83.197055,41.112519],"type":"Point"}
}
