{
  "type": "Feature",
  "properties": {
    "iso:country":"US",
    "sg:address":"6049 Ranlyn Ave",
    "sg:city":"Cincinnati",
    "sg:classifiers":[
        {
            "category":"Manufacturing",
            "subcategory":"Printing",
            "type":"Manufacturing & Wholesale Goods"
        }
    ],
    "sg:phone":"+1 513 741 2722",
    "sg:postcode":"45239",
    "sg:province":"OH",
    "sg:tags":[
        "publisher"
    ],
    "wof:name":"Goodreeder Publications Inc",
    "wof:placetype":"venue"
},
  "geometry": {"coordinates":[-84.583687,39.20194],"type":"Point"}
}