{
  "type": "Feature",
  "properties": {
    "addr:full": "24845 Aurora Rd Cleveland OH 44146",
    "addr:housenumber": "24845",
    "addr:postcode": "44146",
    "addr:street": "Aurora Rd",
    "iso:country": "US",
    "sg:address": "24845 Aurora Rd",
    "sg:city": "Cleveland",
    "sg:classifiers": [
      {
        "category": "Wholesale",
        "subcategory": "Groceries",
        "type": "Manufacturing \u0026 Wholesale Goods"
      }
    ],
    "sg:phone": "+1 440 439 5143",
    "sg:postcode": "44146",
    "sg:province": "OH",
    "sg:tags": [
      "food",
      "broker"
    ],
    "wof:name": "Creative Food Concepts",
    "wof:placetype": "venue"
  },
  "geometry": {"coordinates":[-81.503211,41.411588],"type":"Point"}
}
