{
  "type": "Feature",
  "properties": {
    "iso:country":"US",
    "sg:address":"24845 Aurora Rd",
    "sg:city":"Cleveland",
    "sg:classifiers":[
        {
            "category":"Wholesale",
            "subcategory":"Groceries",
            "type":"Manufacturing & Wholesale Goods"
        }
    ],
    "sg:phone":"+1 440 439 5143",
    "sg:postcode":"44146",
    "sg:province":"OH",
    "sg:tags":[
        "food",
        "broker"
    ],
    "wof:name":"Creative Food Concepts",
    "wof:placetype":"venue"
},
  "geometry": {"coordinates":[-81.50321099999999,41.411588],"type":"Point"}
}