{
  "type": "Feature",
  "properties": {
    "addr:full":"13717 Prospect Rd Strongsville OH 44149",
    "addr:housenumber":"13717",
    "addr:postcode":"44149",
    "addr:street":"Prospect Rd",
    "iso:country":"US",
    "sg:address":"13717 Prospect Rd",
    "sg:city":"Strongsville",
    "sg:classifiers":[
        {
            "category":"Professional",
            "subcategory":"Business Services",
            "type":"Services"
        }
    ],
    "sg:phone":"+1 440 572 2038",
    "sg:postcode":"44149",
    "sg:province":"OH",
    "sg:tags":[
        "recording",
        "studio"
    ],
    "wof:name":"Ms Rock Recording Production",
    "wof:placetype":"venue"
},
  "geometry": {"coordinates":[-81.85772299999999,41.316105],"type":"Point"}
}