{
  "type": "Feature",
  "properties": {
    "addr:full":"2125 Broadview Rd Cleveland OH 44109",
    "addr:housenumber":"2125",
    "addr:postcode":"44109",
    "addr:street":"Broadview Rd",
    "iso:country":"US",
    "sg:address":"2125 Broadview Rd",
    "sg:city":"Cleveland",
    "sg:classifiers":[
        {
            "category":"Restaurant",
            "type":"Food & Drink"
        }
    ],
    "sg:phone":"+1 216 661 6463",
    "sg:postcode":"44109",
    "sg:province":"OH",
    "wof:name":"Cafe Hideaway",
    "wof:placetype":"venue"
},
  "geometry": {"coordinates":[-81.698984,41.437506],"type":"Point"}
}