{
  "type": "Feature",
  "properties": {
    "iso:country":"US",
    "sg:address":"136 High Ave",
    "sg:city":"Lore City",
    "sg:classifiers":[
        {
            "category":"Organizations",
            "subcategory":"Religious Organization",
            "type":"Services"
        }
    ],
    "sg:phone":"+1 740 685 5582",
    "sg:postcode":"43755",
    "sg:province":"OH",
    "sg:tags":[
        "church"
    ],
    "wof:name":"St Peter & Paul Catholic Chr",
    "wof:placetype":"venue"
},
  "geometry": {"coordinates":[-81.45972999999999,39.983229],"type":"Point"}
}