{
  "type": "Feature",
  "properties": {
    "addr:full": "20461 Collier Dr Strongsville OH 44149",
    "addr:housenumber": "20461",
    "addr:postcode": "44149",
    "addr:street": "Collier Dr",
    "iso:country": "US",
    "sg:address": "20461 Collier Dr",
    "sg:city": "Strongsville",
    "sg:classifiers": [
      {
        "category": "Banks \u0026 Credit Unions",
        "subcategory": "Financial Services",
        "type": "Services"
      }
    ],
    "sg:phone": "+1 440 572 7996",
    "sg:postcode": "44149",
    "sg:province": "OH",
    "sg:tags": [
      "investor"
    ],
    "wof:name": "Boundary Investments LLC",
    "wof:placetype": "venue"
  },
  "geometry": {"coordinates":[-81.852806,41.313909],"type":"Point"}
}
