{
  "type": "Feature",
  "properties": {
    "addr:full":"3350 Collingwood Blvd Toledo OH 43610",
    "addr:housenumber":"3350",
    "addr:postcode":"43610",
    "addr:street":"Collingwood Blvd",
    "iso:country":"US",
    "sg:address":"3350 Collingwood Blvd",
    "sg:city":"Toledo",
    "sg:classifiers":[
        {
            "category":"Retail",
            "subcategory":"Laundry & Dry Cleaning",
            "type":"Services"
        }
    ],
    "sg:phone":"+1 419 244 3091",
    "sg:postcode":"43610",
    "sg:province":"OH",
    "sg:tags":[
        "power"
    ],
    "wof:name":"Laundry Dept",
    "wof:placetype":"venue"
},
  "geometry": {"coordinates":[-83.555655,41.684314],"type":"Point"}
}