{
  "type": "Feature",
  "properties": {
    "addr:full": "6279 Shier Rings Rd Dublin OH 43016",
    "addr:housenumber": "6279",
    "addr:postcode": "43016",
    "addr:street": "Shier Rings Rd",
    "iso:country": "US",
    "sg:address": "6279 Shier Rings Rd",
    "sg:city": "Dublin",
    "sg:classifiers": [
      {
        "category": "Government",
        "subcategory": "Fire Station",
        "type": "Public Place"
      }
    ],
    "sg:phone": "+1 614 889 2347",
    "sg:postcode": "43016",
    "sg:province": "OH",
    "sg:tags": [
      "department"
    ],
    "sg:website": "www.wtwp.com",
    "wof:name": "Washington Twp Fire Dept",
    "wof:placetype": "venue"
  },
  "geometry": {"coordinates":[-83.154653,40.095801],"type":"Point"}
}
