{
  "type": "Feature",
  "properties": {
    "iso:country":"US",
    "sg:address":"50 Ehrman Ave",
    "sg:city":"Cincinnati",
    "sg:classifiers":[
        {
            "category":"Real Estate",
            "subcategory":"Real Estate Agent",
            "type":"Services"
        }
    ],
    "sg:phone":"+1 513 543 8838",
    "sg:postcode":"45220",
    "sg:province":"OH",
    "wof:name":"Arthur Caine Properties",
    "wof:placetype":"venue"
},
  "geometry": {"coordinates":[-84.506879,39.149806],"type":"Point"}
}