{
  "type": "Feature",
  "properties": {
    "addr:full": "80 Twin Lakes Dr Fairfield OH 45014",
    "addr:housenumber": "80",
    "addr:postcode": "45014",
    "addr:street": "Twin Lakes Dr",
    "iso:country": "US",
    "sg:address": "80 Twin Lakes Dr",
    "sg:city": "Fairfield",
    "sg:classifiers": [
      {
        "category": "Building \u0026 Trades",
        "subcategory": "Construction",
        "type": "Services"
      }
    ],
    "sg:phone": "+1 513 860 0492",
    "sg:postcode": "45014",
    "sg:province": "OH",
    "sg:tags": [
      "residential",
      "commercial"
    ],
    "wof:name": "Clyburn Construction Services",
    "wof:placetype": "venue"
  },
  "geometry": {"coordinates":[-84.521159,39.315907],"type":"Point"}
}
