{
  "type": "Feature",
  "properties": {
    "iso:country":"US",
    "sg:address":"1761 Prospect-Upper Sandusky Rd S",
    "sg:city":"Marion",
    "sg:phone":"+1 740 382 6448",
    "sg:postcode":"43302",
    "sg:province":"OH",
    "sg:tags":[
        "beef",
        "farm",
        "corn",
        "soybean",
        "cattle",
        "feedlot"
    ],
    "wof:name":"Charles Fogle",
    "wof:placetype":"venue"
},
  "geometry": {"coordinates":[-83.21808299999999,40.555718],"type":"Point"}
}