{
  "type": "Feature",
  "properties": {
    "addr:full": "5001 Mayfield Rd Cleveland OH 44124",
    "addr:housenumber": "5001",
    "addr:postcode": "44124",
    "addr:street": "Mayfield Rd",
    "iso:country": "US",
    "sg:address": "5001 Mayfield Rd",
    "sg:city": "Cleveland",
    "sg:classifiers": [
      {
        "category": "Professional",
        "subcategory": "Accounting \u0026 Tax Preparation",
        "type": "Services"
      }
    ],
    "sg:phone": "+1 216 691 1320",
    "sg:postcode": "44124",
    "sg:province": "OH",
    "sg:tags": [
      "accountant"
    ],
    "wof:name": "Stephen F Hamilton CPA",
    "wof:placetype": "venue"
  },
  "geometry": {"coordinates":[-81.497965,41.519913],"type":"Point"}
}
