{
  "type": "Feature",
  "properties": {
    "iso:country":"US",
    "sg:address":"1221 Blue Valley Rd SE",
    "sg:city":"Lancaster",
    "sg:classifiers":[
        {
            "category":"Building & Trades",
            "subcategory":"Construction",
            "type":"Services"
        }
    ],
    "sg:phone":"+1 740 808 4447",
    "sg:postcode":"43130",
    "sg:province":"OH",
    "sg:tags":[
        "contractor"
    ],
    "wof:name":"R & B Builders LLC",
    "wof:placetype":"venue"
},
  "geometry": {"coordinates":[-82.585449,39.640285],"type":"Point"}
}