{
  "type": "Feature",
  "properties": {
    "addr:full":"231 3rd St Marietta OH 45750",
    "addr:housenumber":"231",
    "addr:postcode":"45750",
    "addr:street":"3Rd St",
    "iso:country":"US",
    "sg:address":"231 3rd St",
    "sg:city":"Marietta",
    "sg:classifiers":[
        {
            "category":"Communications",
            "type":"Services"
        }
    ],
    "sg:phone":"+1 740 376 9286",
    "sg:postcode":"45750",
    "sg:province":"OH",
    "wof:name":"Telepage Communications",
    "wof:placetype":"venue"
},
  "geometry": {"coordinates":[-81.452822,39.415548],"type":"Point"}
}