{
  "type": "Feature",
  "properties": {
    "iso:country":"US",
    "sg:address":"5257 Dayton-Liberty Rd",
    "sg:city":"Dayton",
    "sg:classifiers":[
        {
            "category":"Shopping",
            "subcategory":"Gifts & Souvenirs",
            "type":"Retail Goods"
        }
    ],
    "sg:phone":"+1 937 268 4550",
    "sg:postcode":"45418",
    "sg:province":"OH",
    "wof:name":"D Ash Productions",
    "wof:placetype":"venue"
},
  "geometry": {"coordinates":[-84.27857,39.732012],"type":"Point"}
}