{
  "type": "Feature",
  "properties": {
    "addr:full":"14588 Madison Ave Lakewood OH 44107",
    "addr:housenumber":"14588",
    "addr:postcode":"44107",
    "addr:street":"Madison Ave",
    "iso:country":"US",
    "sg:address":"14588 Madison Ave",
    "sg:city":"Lakewood",
    "sg:classifiers":[
        {
            "category":"Autos & Motor Vehicles",
            "subcategory":"Auto Supplies",
            "type":"Retail Goods"
        }
    ],
    "sg:phone":"+1 216 226 9316",
    "sg:postcode":"44107",
    "sg:province":"OH",
    "wof:name":"Knapp Lake Wood U-Haul",
    "wof:placetype":"venue"
},
  "geometry": {"coordinates":[-81.79878600000001,41.477295],"type":"Point"}
}