{
  "type": "Feature",
  "properties": {
    "addr:full": "1024 Commerce Dr Grafton OH 44044",
    "addr:housenumber": "1024",
    "addr:postcode": "44044",
    "addr:street": "Commerce Dr",
    "iso:country": "US",
    "sg:address": "1024 Commerce Dr",
    "sg:city": "Grafton",
    "sg:classifiers": [
      {
        "category": "Professional",
        "subcategory": "Business Services",
        "type": "Services"
      }
    ],
    "sg:phone": "+1 440 926 1074",
    "sg:postcode": "44044",
    "sg:province": "OH",
    "sg:tags": [
      "packaging"
    ],
    "wof:name": "M P \u0026 A Inc",
    "wof:placetype": "venue"
  },
  "geometry": {"coordinates":[-82.067617,41.285343],"type":"Point"}
}
