{
  "type": "Feature",
  "properties": {
    "iso:country":"US",
    "sg:address":"6335 Perimeter Loop Rd",
    "sg:city":"Dublin",
    "sg:classifiers":[
        {
            "category":"Autos & Motor Vehicles",
            "subcategory":"Automobile Sales",
            "type":"Retail Goods"
        }
    ],
    "sg:phone":"+1 614 889 2571",
    "sg:postcode":"43017",
    "sg:province":"OH",
    "sg:tags":[
        "repair",
        "general"
    ],
    "sg:website":"www.magcars.com",
    "wof:name":"Midwestern Auto Group",
    "wof:placetype":"venue"
},
  "geometry": {"coordinates":[-83.15411,40.099584],"type":"Point"}
}