{
  "type": "Feature",
  "properties": {
    "addr:full": "5852 Havers Rd Newcomerstown OH 43832",
    "addr:housenumber": "5852",
    "addr:postcode": "43832",
    "addr:street": "Havers Rd",
    "iso:country": "US",
    "sg:address": "5852 Havers Rd",
    "sg:city": "Newcomerstown",
    "sg:classifiers": [
      {
        "category": "Farming",
        "subcategory": "Livestock Farm",
        "type": "Manufacturing \u0026 Wholesale Goods"
      }
    ],
    "sg:phone": "+1 330 339 5970",
    "sg:postcode": "43832",
    "sg:province": "OH",
    "sg:tags": [
      "animal",
      "general"
    ],
    "wof:name": "Hilltop Pork",
    "wof:placetype": "venue"
  },
  "geometry": {"coordinates":[-81.575869,40.373273],"type":"Point"}
}
