{
  "type": "Feature",
  "properties": {
    "iso:country":"US",
    "sg:address":"5852 Havers Rd",
    "sg:city":"Newcomerstown",
    "sg:classifiers":[
        {
            "category":"Farming",
            "subcategory":"Livestock Farm",
            "type":"Manufacturing & Wholesale Goods"
        }
    ],
    "sg:phone":"+1 330 339 5970",
    "sg:postcode":"43832",
    "sg:province":"OH",
    "sg:tags":[
        "animal",
        "general"
    ],
    "wof:name":"Hilltop Pork",
    "wof:placetype":"venue"
},
  "geometry": {"coordinates":[-81.575869,40.373273],"type":"Point"}
}