{
  "type": "Feature",
  "properties": {
    "addr:full": "1981 Westbranch Rd Grove City OH 43123",
    "addr:housenumber": "1981",
    "addr:postcode": "43123",
    "addr:street": "Westbranch Rd",
    "iso:country": "US",
    "sg:address": "1981 Westbranch Rd",
    "sg:city": "Grove City",
    "sg:classifiers": [
      {
        "category": "Retail",
        "subcategory": "Car Wash",
        "type": "Services"
      },
      {
        "category": "Building \u0026 Trades",
        "subcategory": "Construction",
        "type": "Services"
      }
    ],
    "sg:phone": "+1 614 871 7775",
    "sg:postcode": "43123",
    "sg:province": "OH",
    "sg:tags": [
      "carwash",
      "restoration",
      "cleaning",
      "patio",
      "deck"
    ],
    "wof:name": "Turner Mobile Power Wash Inc",
    "wof:placetype": "venue"
  },
  "geometry": {"coordinates":[-83.044668,39.90134],"type":"Point"}
}
