{
  "type": "Feature",
  "properties": {
    "addr:full": "3004 Center Rd Youngstown OH 44514",
    "addr:housenumber": "3004",
    "addr:postcode": "44514",
    "addr:street": "Center Rd",
    "iso:country": "US",
    "sg:address": "3004 Center Rd",
    "sg:city": "Youngstown",
    "sg:classifiers": [
      {
        "category": "Personal",
        "subcategory": "Beauty Salon",
        "type": "Services"
      }
    ],
    "sg:phone": "+1 330 757 8536",
    "sg:postcode": "44514",
    "sg:province": "OH",
    "wof:name": "Poland Hairworks",
    "wof:placetype": "venue"
  },
  "geometry": {"coordinates":[-80.591403,41.023808],"type":"Point"}
}
