{
  "type": "Feature",
  "properties": {
    "iso:country":"US",
    "sg:address":"3110 Coral Park Dr",
    "sg:city":"Cincinnati",
    "sg:classifiers":[
        {
            "category":"Professional",
            "subcategory":"Management & Consulting",
            "type":"Services"
        }
    ],
    "sg:phone":"+1 513 661 5655",
    "sg:postcode":"45211",
    "sg:province":"OH",
    "sg:tags":[
        "consultant",
        "educational"
    ],
    "sg:website":"www.childbirthclassesofcincinnati.com",
    "wof:name":"Childbirth Education Assn",
    "wof:placetype":"venue"
},
  "geometry": {"coordinates":[-84.605171,39.143645],"type":"Point"}
}