{
  "type": "Feature",
  "properties": {
    "addr:full":"850 N Bridge St Chillicothe OH 45601",
    "addr:housenumber":"850",
    "addr:postcode":"45601",
    "addr:street":"N Bridge St",
    "iso:country":"US",
    "sg:address":"850 N Bridge St",
    "sg:city":"Chillicothe",
    "sg:classifiers":[
        {
            "category":"Shopping",
            "subcategory":"Pharmacy",
            "type":"Retail Goods"
        }
    ],
    "sg:phone":"+1 740 779 2901",
    "sg:postcode":"45601",
    "sg:province":"OH",
    "sg:website":"www.walgreens.com",
    "wof:name":"Walgreens",
    "wof:placetype":"venue"
},
  "geometry": {"coordinates":[-82.975961,39.341887],"type":"Point"}
}