{
  "type": "Feature",
  "properties": {
    "iso:country":"US",
    "sg:address":"5980 Jassamine Dr",
    "sg:city":"Dayton",
    "sg:classifiers":[
        {
            "category":"Food & Beverages",
            "subcategory":"Specialty",
            "type":"Retail Goods"
        }
    ],
    "sg:phone":"+1 937 435 2155",
    "sg:postcode":"45449",
    "sg:province":"OH",
    "wof:name":"Shaklee Products",
    "wof:placetype":"venue"
},
  "geometry": {"coordinates":[-84.22341299999999,39.667602],"type":"Point"}
}