{
  "type": "Feature",
  "properties": {
    "iso:country":"US",
    "sg:address":"1062 E 185th St",
    "sg:city":"Cleveland",
    "sg:classifiers":[
        {
            "category":"Retail",
            "subcategory":"Auto Repair",
            "type":"Services"
        }
    ],
    "sg:phone":"+1 216 481 2222",
    "sg:postcode":"44119",
    "sg:province":"OH",
    "sg:tags":[
        "alternator",
        "generator"
    ],
    "wof:name":"Euclid Ignition & Cmplt Auto",
    "wof:placetype":"venue"
},
  "geometry": {"coordinates":[-81.54992799999999,41.579042],"type":"Point"}
}