{
  "type": "Feature",
  "properties": {
    "iso:country":"US",
    "sg:address":"692 S Main St",
    "sg:city":"Lima",
    "sg:classifiers":[
        {
            "category":"Organizations",
            "subcategory":"Religious Organization",
            "type":"Services"
        }
    ],
    "sg:phone":"+1 419 227 0184",
    "sg:postcode":"45804",
    "sg:province":"OH",
    "sg:tags":[
        "church"
    ],
    "wof:name":"St Vincent De Paul",
    "wof:placetype":"venue"
},
  "geometry": {"coordinates":[-84.105108,40.730764],"type":"Point"}
}