{
  "type": "Feature",
  "properties": {
    "addr:full": "9412 Botkins Angle Rd New Knoxville OH 45871",
    "addr:housenumber": "9412",
    "addr:postcode": "45871",
    "addr:street": "Botkins Angle Rd",
    "iso:country": "US",
    "sg:address": "9412 Botkins Angle Rd",
    "sg:city": "New Knoxville",
    "sg:classifiers": [
      {
        "category": "Wholesale",
        "subcategory": "Apparel",
        "type": "Manufacturing \u0026 Wholesale Goods"
      }
    ],
    "sg:phone": "+1 419 753 3131",
    "sg:postcode": "45871",
    "sg:province": "OH",
    "sg:tags": [
      "piece"
    ],
    "wof:name": "Jemspec Inc",
    "wof:placetype": "venue"
  },
  "geometry": {"coordinates":[-84.305203,40.486353],"type":"Point"}
}
