{
  "type": "Feature",
  "properties": {
    "iso:country":"US",
    "sg:address":"9412 Botkins Angle Rd",
    "sg:city":"New Knoxville",
    "sg:classifiers":[
        {
            "category":"Wholesale",
            "subcategory":"Apparel",
            "type":"Manufacturing & Wholesale Goods"
        }
    ],
    "sg:phone":"+1 419 753 3131",
    "sg:postcode":"45871",
    "sg:province":"OH",
    "sg:tags":[
        "piece"
    ],
    "wof:name":"Jemspec Inc",
    "wof:placetype":"venue"
},
  "geometry": {"coordinates":[-84.30520300000001,40.486353],"type":"Point"}
}