{
  "type": "Feature",
  "properties": {
    "iso:country":"US",
    "sg:address":"708 E High St",
    "sg:city":"Hicksville",
    "sg:classifiers":[
        {
            "category":"Social Services",
            "type":"Services"
        }
    ],
    "sg:phone":"+1 419 542 5004",
    "sg:postcode":"43526",
    "sg:province":"OH",
    "sg:tags":[
        "counseling",
        "senior",
        "citizen"
    ],
    "wof:name":"Defiance County Senior Ctr",
    "wof:placetype":"venue"
},
  "geometry": {"coordinates":[-84.75502,41.297944],"type":"Point"}
}