{
  "type": "Feature",
  "properties": {
    "addr:full":"2759 Stone Mill Way Hamilton OH 45011",
    "addr:housenumber":"2759",
    "addr:postcode":"45011",
    "addr:street":"Stone Mill Way",
    "iso:country":"US",
    "sg:address":"2759 Stone Mill Way",
    "sg:city":"Hamilton",
    "sg:classifiers":[
        {
            "category":"Banks & Credit Unions",
            "subcategory":"Financial Services",
            "type":"Services"
        }
    ],
    "sg:phone":"+1 513 892 4848",
    "sg:postcode":"45011",
    "sg:province":"OH",
    "sg:tags":[
        "investor"
    ],
    "wof:name":"Sawgrass Investment Co LLC",
    "wof:placetype":"venue"
},
  "geometry": {"coordinates":[-84.52196000000001,39.4001],"type":"Point"}
}