{
  "type": "Feature",
  "properties": {
    "addr:full":"11713 Buckeye Rd Cleveland OH 44120",
    "addr:housenumber":"11713",
    "addr:postcode":"44120",
    "addr:street":"Buckeye Rd",
    "iso:country":"US",
    "sg:address":"11713 Buckeye Rd",
    "sg:city":"Cleveland",
    "sg:classifiers":[
        {
            "category":"Recreation",
            "subcategory":"Picnic Area",
            "type":"Entertainment"
        },
        {
            "category":"Community Center",
            "type":"Public Place"
        }
    ],
    "sg:phone":"+1 216 991 0015",
    "sg:postcode":"44120",
    "sg:province":"OH",
    "sg:tags":[
        "amusement",
        "arcade"
    ],
    "wof:name":"Science Of Mind Center",
    "wof:placetype":"venue"
},
  "geometry": {"coordinates":[-81.601242,41.480834],"type":"Point"}
}