{
  "type": "Feature",
  "properties": {
    "iso:country":"US",
    "sg:address":"805 Iroquois Run",
    "sg:city":"Macedonia",
    "sg:classifiers":[
        {
            "category":"Real Estate",
            "subcategory":"Real Estate Operator",
            "type":"Services"
        }
    ],
    "sg:phone":"+1 330 467 5736",
    "sg:postcode":"44056",
    "sg:province":"OH",
    "sg:tags":[
        "building",
        "nonresidential"
    ],
    "wof:name":"Bhw Holding Co Inc",
    "wof:placetype":"venue"
},
  "geometry": {"coordinates":[-81.499832,41.331023],"type":"Point"}
}