{
  "type": "Feature",
  "properties": {
    "addr:full": "2000 Auburn Dr Cleveland OH 44122",
    "addr:housenumber": "2000",
    "addr:postcode": "44122",
    "addr:street": "Auburn Dr",
    "iso:country": "US",
    "sg:address": "2000 Auburn Dr",
    "sg:city": "Cleveland",
    "sg:classifiers": [
      {
        "category": "Professional",
        "subcategory": "Lawyer \u0026 Legal Services",
        "type": "Services"
      }
    ],
    "sg:phone": "+1 216 514 9999",
    "sg:postcode": "44122",
    "sg:province": "OH",
    "sg:tags": [
      "firm",
      "attorney",
      "law"
    ],
    "wof:name": "Cornrich \u0026 Cornrich Co Lpa",
    "wof:placetype": "venue"
  },
  "geometry": {"coordinates":[-81.494076,41.457198],"type":"Point"}
}
