{
  "type": "Feature",
  "properties": {
    "iso:country":"US",
    "sg:address":"27836 Co Rd T",
    "sg:city":"Fayette",
    "sg:classifiers":[
        {
            "category":"Building & Trades",
            "subcategory":"Plumbing",
            "type":"Services"
        }
    ],
    "sg:phone":"+1 419 237 3002",
    "sg:postcode":"43521",
    "sg:province":"OH",
    "sg:tags":[
        "plumbing",
        "heating",
        "contractor"
    ],
    "wof:name":"Joughin Richard Plbg & Htg Co",
    "wof:placetype":"venue"
},
  "geometry": {"coordinates":[-84.396188,41.695116],"type":"Point"}
}