{
  "type": "Feature",
  "properties": {
    "iso:country":"US",
    "sg:address":"1307 N Gettysburg Ave",
    "sg:city":"Dayton",
    "sg:classifiers":[
        {
            "category":"Home & Garden",
            "subcategory":"Building Materials",
            "type":"Retail Goods"
        }
    ],
    "sg:phone":"+1 937 263 5696",
    "sg:postcode":"45427",
    "sg:province":"OH",
    "wof:name":"Central Oil Asphalt Corp",
    "wof:placetype":"venue"
},
  "geometry": {"coordinates":[-84.25347600000001,39.765417],"type":"Point"}
}