{
  "type": "Feature",
  "properties": {
    "addr:full": "9419 Denison Ave Cleveland OH 44102",
    "addr:housenumber": "9419",
    "addr:postcode": "44102",
    "addr:street": "Denison Ave",
    "iso:country": "US",
    "sg:address": "9419 Denison Ave",
    "sg:city": "Cleveland",
    "sg:classifiers": [
      {
        "category": "Building \u0026 Trades",
        "subcategory": "Construction",
        "type": "Services"
      }
    ],
    "sg:phone": "+1 216 651 1809",
    "sg:postcode": "44102",
    "sg:province": "OH",
    "sg:tags": [
      "contractor"
    ],
    "wof:name": "A\u0026A Roofing \u0026 Tinning Co",
    "wof:placetype": "venue"
  },
  "geometry": {"coordinates":[-81.747737,41.464977],"type":"Point"}
}
