{
  "type": "Feature",
  "properties": {
    "addr:full": "7469 Grubbs-Rex Rd Arcanum OH 45304",
    "addr:housenumber": "7469",
    "addr:postcode": "45304",
    "addr:street": "Grubbs-Rex Rd",
    "iso:country": "US",
    "sg:address": "7469 Grubbs-Rex Rd",
    "sg:city": "Arcanum",
    "sg:phone": "+1 937 692 8380",
    "sg:postcode": "45304",
    "sg:province": "OH",
    "sg:tags": [
      "farm",
      "field",
      "crop"
    ],
    "wof:name": "James Halderman",
    "wof:placetype": "venue"
  },
  "geometry": {"coordinates":[-84.525561,39.961349],"type":"Point"}
}
