{
  "type": "Feature",
  "properties": {
    "iso:country":"US",
    "sg:address":"9117 Co Rd 54",
    "sg:city":"Lewistown",
    "sg:classifiers":[
        {
            "category":"Building & Trades",
            "subcategory":"Construction",
            "type":"Services"
        }
    ],
    "sg:phone":"+1 937 686 5425",
    "sg:postcode":"43333",
    "sg:province":"OH",
    "sg:tags":[
        "house"
    ],
    "wof:name":"Larry Snipes Construction",
    "wof:placetype":"venue"
},
  "geometry": {"coordinates":[-83.909449,40.419432],"type":"Point"}
}