{
  "type": "Feature",
  "properties": {
    "addr:full": "5547 Red Oak Ct Fairfield OH 45014",
    "addr:housenumber": "5547",
    "addr:postcode": "45014",
    "addr:street": "Red Oak Ct",
    "iso:country": "US",
    "sg:address": "5547 Red Oak Ct",
    "sg:city": "Fairfield",
    "sg:classifiers": [
      {
        "category": "Travel",
        "subcategory": "Travel Agent",
        "type": "Entertainment"
      }
    ],
    "sg:phone": "+1 513 829 0200",
    "sg:postcode": "45014",
    "sg:province": "OH",
    "sg:tags": [
      "agency"
    ],
    "wof:name": "Fairfield Travel Inc",
    "wof:placetype": "venue"
  },
  "geometry": {"coordinates":[-84.569124,39.326897],"type":"Point"}
}
