{
  "type": "Feature",
  "properties": {
    "addr:full":"10574 Ravenna Rd Twinsburg OH 44087",
    "addr:housenumber":"10574",
    "addr:postcode":"44087",
    "addr:street":"Ravenna Rd",
    "iso:country":"US",
    "sg:address":"10574 Ravenna Rd",
    "sg:city":"Twinsburg",
    "sg:classifiers":[
        {
            "category":"Banks & Credit Unions",
            "subcategory":"Bank",
            "type":"Services"
        }
    ],
    "sg:phone":"+1 330 405 6130",
    "sg:postcode":"44087",
    "sg:province":"OH",
    "sg:tags":[
        "loan",
        "mortgage",
        "real estate"
    ],
    "wof:name":"Certified Mortgage Company",
    "wof:placetype":"venue"
},
  "geometry": {"coordinates":[-81.464217,41.329896],"type":"Point"}
}