{
  "type": "Feature",
  "properties": {
    "addr:full": "2863 E Sharon Rd Cincinnati OH 45241",
    "addr:housenumber": "2863",
    "addr:postcode": "45241",
    "addr:street": "E Sharon Rd",
    "iso:country": "US",
    "sg:address": "2863 E Sharon Rd",
    "sg:city": "Cincinnati",
    "sg:classifiers": [
      {
        "category": "Manufacturing",
        "subcategory": "Tools \u0026 Machinery",
        "type": "Manufacturing \u0026 Wholesale Goods"
      }
    ],
    "sg:phone": "+1 513 281 9933",
    "sg:postcode": "45241",
    "sg:province": "OH",
    "sg:tags": [
      "photographic",
      "supply"
    ],
    "sg:website": "www.ohioblue.com",
    "wof:name": "Ohio Blue Print Co",
    "wof:placetype": "venue"
  },
  "geometry": {"coordinates":[-84.424739,39.268978],"type":"Point"}
}
