{
  "type": "Feature",
  "properties": {
    "iso:country":"US",
    "sg:address":"4900 Yankee Rd",
    "sg:city":"Middletown",
    "sg:classifiers":[
        {
            "category":"Farming",
            "subcategory":"Poultry Farm",
            "type":"Manufacturing & Wholesale Goods"
        }
    ],
    "sg:phone":"+1 513 779 4546",
    "sg:postcode":"45044",
    "sg:province":"OH",
    "sg:tags":[
        "egg"
    ],
    "wof:name":"Valley View Turkey Farms",
    "wof:placetype":"venue"
},
  "geometry": {"coordinates":[-84.38407599999999,39.429721],"type":"Point"}
}