{
  "type": "Feature",
  "properties": {
    "addr:full": "1101 Millville Ave Hamilton OH 45013",
    "addr:housenumber": "1101",
    "addr:postcode": "45013",
    "addr:street": "Millville Ave",
    "iso:country": "US",
    "sg:address": "1101 Millville Ave",
    "sg:city": "Hamilton",
    "sg:classifiers": [
      {
        "category": "Freight",
        "type": "Transportation"
      }
    ],
    "sg:phone": "+1 513 892 8371",
    "sg:postcode": "45013",
    "sg:province": "OH",
    "sg:tags": [
      "mover"
    ],
    "wof:name": "Gibson's Moving Svc",
    "wof:placetype": "venue"
  },
  "geometry": {"coordinates":[-84.601506,39.406099],"type":"Point"}
}
