{
  "type": "Feature",
  "properties": {
    "addr:full": "31230 Vine St Willoughby OH 44095",
    "addr:housenumber": "31230",
    "addr:postcode": "44095",
    "addr:street": "Vine St",
    "iso:country": "US",
    "sg:address": "31230 Vine St",
    "sg:city": "Willoughby",
    "sg:classifiers": [
      {
        "category": "Government",
        "subcategory": "Office",
        "type": "Public Place"
      }
    ],
    "sg:phone": "+1 440 585 0963",
    "sg:postcode": "44095",
    "sg:province": "OH",
    "sg:tags": [
      "department"
    ],
    "wof:name": "Service and Building Center",
    "wof:placetype": "venue"
  },
  "geometry": {"coordinates":[-81.467772,41.642444],"type":"Point"}
}
