{
  "type": "Feature",
  "properties": {
    "addr:full":"1194 Burkholder Rd Clyde OH 43410",
    "addr:housenumber":"1194",
    "addr:postcode":"43410",
    "addr:street":"Burkholder Rd",
    "iso:country":"US",
    "sg:address":"1194 Burkholder Rd",
    "sg:city":"Clyde",
    "sg:classifiers":[
        {
            "category":"Food & Beverages",
            "subcategory":"Liquor & Beverages",
            "type":"Retail Goods"
        }
    ],
    "sg:phone":"+1 419 547 7395",
    "sg:postcode":"43410",
    "sg:province":"OH",
    "sg:tags":[
        "alcoholic"
    ],
    "wof:name":"Garden of Wine & Roses",
    "wof:placetype":"venue"
},
  "geometry": {"coordinates":[-82.963301,41.312673],"type":"Point"}
}