{
  "type": "Feature",
  "properties": {
    "addr:full":"12903 Madison Ave Cleveland OH 44107",
    "addr:housenumber":"12903",
    "addr:postcode":"44107",
    "addr:street":"Madison Ave",
    "iso:country":"US",
    "sg:address":"12903 Madison Ave",
    "sg:city":"Cleveland",
    "sg:classifiers":[
        {
            "category":"Organizations",
            "subcategory":"Religious Organization",
            "type":"Services"
        }
    ],
    "sg:phone":"+1 216 521 5086",
    "sg:postcode":"44107",
    "sg:province":"OH",
    "sg:tags":[
        "church"
    ],
    "wof:name":"St Hedwig Church",
    "wof:placetype":"venue"
},
  "geometry": {"coordinates":[-81.779036,41.476891],"type":"Point"}
}