{
  "type": "Feature",
  "properties": {
    "addr:full": "434 Ada St Cincinnati OH 45219",
    "addr:housenumber": "434",
    "addr:postcode": "45219",
    "addr:street": "Ada St",
    "iso:country": "US",
    "sg:address": "434 Ada St",
    "sg:city": "Cincinnati",
    "sg:classifiers": [
      {
        "category": "Building \u0026 Trades",
        "subcategory": "Construction",
        "type": "Services"
      }
    ],
    "sg:phone": "+1 513 421 7759",
    "sg:postcode": "45219",
    "sg:province": "OH",
    "sg:tags": [
      "carpentry",
      "contractor"
    ],
    "wof:name": "Donald J Wagner",
    "wof:placetype": "venue"
  },
  "geometry": {"coordinates":[-84.526488,39.126497],"type":"Point"}
}
