{
  "type": "Feature",
  "properties": {
    "addr:full": "3455 Briarfield Blvd Maumee OH 43537",
    "addr:housenumber": "3455",
    "addr:postcode": "43537",
    "addr:street": "Briarfield Blvd",
    "iso:country": "US",
    "sg:address": "3455 Briarfield Blvd",
    "sg:city": "Maumee",
    "sg:classifiers": [
      {
        "category": "Wholesale",
        "subcategory": "Hardware",
        "type": "Manufacturing \u0026 Wholesale Goods"
      }
    ],
    "sg:phone": "+1 419 868 1149",
    "sg:postcode": "43537",
    "sg:province": "OH",
    "sg:tags": [
      "builder"
    ],
    "wof:name": "Otto C Buehler \u0026 Son",
    "wof:placetype": "venue"
  },
  "geometry": {"coordinates":[-83.696809,41.581869],"type":"Point"}
}
