{
  "type": "Feature",
  "properties": {
    "iso:country":"US",
    "sg:address":"3455 Briarfield Blvd",
    "sg:city":"Maumee",
    "sg:classifiers":[
        {
            "category":"Wholesale",
            "subcategory":"Hardware",
            "type":"Manufacturing & Wholesale Goods"
        }
    ],
    "sg:phone":"+1 419 868 1149",
    "sg:postcode":"43537",
    "sg:province":"OH",
    "sg:tags":[
        "builder"
    ],
    "wof:name":"Otto C Buehler & Son",
    "wof:placetype":"venue"
},
  "geometry": {"coordinates":[-83.696809,41.581869],"type":"Point"}
}