{
  "type": "Feature",
  "properties": {
    "addr:full":"2835 Barber Rd Norton OH 44203",
    "addr:housenumber":"2835",
    "addr:postcode":"44203",
    "addr:street":"Barber Rd",
    "iso:country":"US",
    "sg:address":"2835 Barber Rd",
    "sg:city":"Norton",
    "sg:classifiers":[
        {
            "category":"Autos & Motor Vehicles",
            "subcategory":"Automobile Sales",
            "type":"Retail Goods"
        },
        {
            "category":"Autos & Motor Vehicles",
            "subcategory":"Auto Supplies",
            "type":"Retail Goods"
        },
        {
            "category":"Retail",
            "subcategory":"Auto Repair",
            "type":"Services"
        }
    ],
    "sg:phone":"+1 330 754 0869",
    "sg:postcode":"44203",
    "sg:province":"OH",
    "sg:tags":[
        "used",
        "tire",
        "car",
        "recreational",
        "truck",
        "new",
        "campers-repair"
    ],
    "sg:website":"http://www.ganleyford.com",
    "wof:name":"Ganley Ford",
    "wof:placetype":"venue"
},
  "geometry": {"coordinates":[-81.608582,41.050113],"type":"Point"}
}