{
  "type": "Feature",
  "properties": {
    "addr:full":"2124 Needmore Rd Dayton OH 45414",
    "addr:housenumber":"2124",
    "addr:postcode":"45414",
    "addr:street":"Needmore Rd",
    "iso:country":"US",
    "sg:address":"2124 Needmore Rd",
    "sg:city":"Dayton",
    "sg:classifiers":[
        {
            "category":"Building & Trades",
            "subcategory":"Pest Control",
            "type":"Services"
        }
    ],
    "sg:phone":"+1 937 274 0943",
    "sg:postcode":"45414",
    "sg:province":"OH",
    "sg:website":"www.pro-safe.com",
    "wof:name":"Pro-Safe Pest Control",
    "wof:placetype":"venue"
},
  "geometry": {"coordinates":[-84.194457,39.819612],"type":"Point"}
}