{
  "type": "Feature",
  "properties": {
    "iso:country":"US",
    "sg:address":"109 Cambria St",
    "sg:city":"Newark",
    "sg:classifiers":[
        {
            "category":"Wholesale",
            "subcategory":"Non-durable Goods",
            "type":"Manufacturing & Wholesale Goods"
        },
        {
            "category":"Manufacturing",
            "subcategory":"Rubber & Plastics",
            "type":"Manufacturing & Wholesale Goods"
        }
    ],
    "sg:phone":"+1 740 344 9554",
    "sg:postcode":"43055",
    "sg:province":"OH",
    "sg:tags":[
        "sponge",
        "product",
        "foam",
        "mfg"
    ],
    "wof:name":"ISO Technologies Inc",
    "wof:placetype":"venue"
},
  "geometry": {"coordinates":[-82.428271,40.049943],"type":"Point"}
}