{
  "type": "Feature",
  "properties": {
    "addr:full":"400 Conover Dr Franklin OH 45005",
    "addr:housenumber":"400",
    "addr:postcode":"45005",
    "addr:street":"Conover Dr",
    "iso:country":"US",
    "sg:address":"400 Conover Dr",
    "sg:city":"Franklin",
    "sg:classifiers":[
        {
            "category":"Retail",
            "subcategory":"Repair Shop",
            "type":"Services"
        }
    ],
    "sg:phone":"+1 937 704 9595",
    "sg:postcode":"45005",
    "sg:province":"OH",
    "sg:tags":[
        "spa",
        "hot",
        "tub"
    ],
    "wof:name":"Superior Spas",
    "wof:placetype":"venue"
},
  "geometry": {"coordinates":[-84.277591,39.557462],"type":"Point"}
}