{
  "type": "Feature",
  "properties": {
    "addr:full": "15503 Stockbridge Ave Cleveland OH 44128",
    "addr:housenumber": "15503",
    "addr:postcode": "44128",
    "addr:street": "Stockbridge Ave",
    "iso:country": "US",
    "sg:address": "15503 Stockbridge Ave",
    "sg:city": "Cleveland",
    "sg:classifiers": [
      {
        "category": "Organizations",
        "subcategory": "Religious Organization",
        "type": "Services"
      }
    ],
    "sg:phone": "+1 216 283 0420",
    "sg:postcode": "44128",
    "sg:province": "OH",
    "sg:tags": [
      "clergy"
    ],
    "wof:name": "Robert B Williams",
    "wof:placetype": "venue"
  },
  "geometry": {"coordinates":[-81.568525,41.451324],"type":"Point"}
}
