{
  "type": "Feature",
  "properties": {
    "addr:full": "424 W Town St Columbus OH 43215",
    "addr:housenumber": "424",
    "addr:postcode": "43215",
    "addr:street": "W Town St",
    "iso:country": "US",
    "sg:address": "424 W Town St",
    "sg:city": "Columbus",
    "sg:classifiers": [
      {
        "category": "Retail",
        "subcategory": "Repair Shop",
        "type": "Services"
      }
    ],
    "sg:phone": "+1 614 221 4110",
    "sg:postcode": "43215",
    "sg:province": "OH",
    "sg:tags": [
      "welding"
    ],
    "wof:name": "Capital Track Co",
    "wof:placetype": "venue"
  },
  "geometry": {"coordinates":[-83.012604,39.957442],"type":"Point"}
}
