{
  "type": "Feature",
  "properties": {
    "addr:full":"8005 US Hwy 62 Russellville OH 45168",
    "addr:housenumber":"8005",
    "addr:postcode":"45168",
    "addr:street":"Us Hwy 62",
    "iso:country":"US",
    "sg:address":"8005 US Hwy 62",
    "sg:city":"Russellville",
    "sg:phone":"+1 937 377 6051",
    "sg:postcode":"45168",
    "sg:province":"OH",
    "sg:tags":[
        "farm",
        "tobacco"
    ],
    "wof:name":"Randy & Gina Spiller",
    "wof:placetype":"venue"
},
  "geometry": {"coordinates":[-83.787255,38.856502],"type":"Point"}
}