{
  "type": "Feature",
  "properties": {
    "addr:full": "205 S Main St Mt Vernon OH 43050",
    "addr:housenumber": "205",
    "addr:postcode": "43050",
    "addr:street": "S Main St",
    "iso:country": "US",
    "sg:address": "205 S Main St",
    "sg:city": "Mt Vernon",
    "sg:classifiers": [
      {
        "category": "Professional",
        "subcategory": "Business Services",
        "type": "Services"
      }
    ],
    "sg:phone": "+1 740 392 9894",
    "sg:postcode": "43050",
    "sg:province": "OH",
    "sg:tags": [
      "interior",
      "consultant",
      "design",
      "decorator"
    ],
    "wof:name": "Amy Statler Designs",
    "wof:placetype": "venue"
  },
  "geometry": {"coordinates":[-82.485689,40.391696],"type":"Point"}
}
