{
  "type": "Feature",
  "properties": {
    "iso:country":"US",
    "sg:address":"18136 US Hwy 68",
    "sg:city":"Kenton",
    "sg:classifiers":[
        {
            "category":"Real Estate",
            "subcategory":"Real Estate Operator",
            "type":"Services"
        }
    ],
    "sg:phone":"+1 419 675 1706",
    "sg:postcode":"43326",
    "sg:province":"OH",
    "sg:tags":[
        "property",
        "lessor"
    ],
    "wof:name":"Neil Sutherland",
    "wof:placetype":"venue"
},
  "geometry": {"coordinates":[-83.658303,40.563928],"type":"Point"}
}