{
  "type": "Feature",
  "properties": {
    "iso:country":"US",
    "sg:address":"1164 W North St",
    "sg:city":"Lima",
    "sg:classifiers":[
        {
            "category":"Insurance",
            "subcategory":"Insurance Agent",
            "type":"Services"
        }
    ],
    "sg:phone":"+1 419 224 5553",
    "sg:postcode":"45805",
    "sg:province":"OH",
    "wof:name":"Brian Planz",
    "wof:placetype":"venue"
},
  "geometry": {"coordinates":[-84.127611,40.743484],"type":"Point"}
}