{
  "type": "Feature",
  "properties": {
    "addr:full":"17972 Co Rd 214 Findlay OH 44804",
    "addr:housenumber":"17972",
    "addr:postcode":"44804",
    "addr:street":"Co Rd 214",
    "iso:country":"US",
    "sg:address":"17972 Co Rd 214",
    "sg:city":"Findlay",
    "sg:phone":"+1 419 894 6741",
    "sg:postcode":"44804",
    "sg:province":"OH",
    "sg:tags":[
        "farm",
        "grain",
        "cash"
    ],
    "wof:name":"Richard Colman",
    "wof:placetype":"venue"
},
  "geometry": {"coordinates":[-83.537261,41.094234],"type":"Point"}
}