{
  "type": "Feature",
  "properties": {
    "addr:full":"15765 E Liverpool Rd East Liverpool OH 43920",
    "addr:housenumber":"15765",
    "addr:postcode":"43920",
    "addr:street":"E Liverpool Rd",
    "iso:country":"US",
    "sg:address":"15765 E Liverpool Rd",
    "sg:city":"East Liverpool",
    "sg:classifiers":[
        {
            "category":"Wholesale",
            "subcategory":"Hardware",
            "type":"Manufacturing & Wholesale Goods"
        }
    ],
    "sg:phone":"+1 330 386 3930",
    "sg:postcode":"43920",
    "sg:province":"OH",
    "sg:tags":[
        "fastener"
    ],
    "sg:website":"www.fastenal.com",
    "wof:name":"Fastenal Co",
    "wof:placetype":"venue"
},
  "geometry": {"coordinates":[-80.603866,40.673689],"type":"Point"}
}