{
  "type": "Feature",
  "properties": {
    "addr:full": "13225 State Rte 247 Winchester OH 45697",
    "addr:housenumber": "13225",
    "addr:postcode": "45697",
    "addr:street": "State Rte 247",
    "iso:country": "US",
    "sg:address": "13225 State Rte 247",
    "sg:city": "Winchester",
    "sg:phone": "+1 937 386 2268",
    "sg:postcode": "45697",
    "sg:province": "OH",
    "sg:tags": [
      "farm",
      "real",
      "corn",
      "property",
      "lessor"
    ],
    "wof:name": "James Wallace",
    "wof:placetype": "venue"
  },
  "geometry": {"coordinates":[-83.55984,38.875166],"type":"Point"}
}
