{
  "type": "Feature",
  "properties": {
    "addr:full": "9514 Kenwood Rd Cincinnati OH 45242",
    "addr:housenumber": "9514",
    "addr:postcode": "45242",
    "addr:street": "Kenwood Rd",
    "iso:country": "US",
    "sg:address": "9514 Kenwood Rd",
    "sg:city": "Cincinnati",
    "sg:classifiers": [
      {
        "category": "Shopping",
        "type": "Retail Goods"
      }
    ],
    "sg:phone": "+1 513 745 9501",
    "sg:postcode": "45242",
    "sg:province": "OH",
    "sg:tags": [
      "breast",
      "artificial"
    ],
    "wof:name": "Josephine's Post-Mastectomy",
    "wof:placetype": "venue"
  },
  "geometry": {"coordinates":[-84.377044,39.231272],"type":"Point"}
}
