{
  "type": "Feature",
  "properties": {
    "iso:country":"US",
    "sg:address":"3865 Alton Darby Creek Rd",
    "sg:city":"Hilliard",
    "sg:classifiers":[
        {
            "category":"Building & Trades",
            "subcategory":"Landscaping Services",
            "type":"Services"
        }
    ],
    "sg:phone":"+1 614 876 0616",
    "sg:postcode":"43026",
    "sg:province":"OH",
    "sg:tags":[
        "landscape",
        "contractor"
    ],
    "wof:name":"Creative Space Landscape Ltd",
    "wof:placetype":"venue"
},
  "geometry": {"coordinates":[-83.185513,40.025534],"type":"Point"}
}