{
  "type": "Feature",
  "properties": {
    "iso:country":"US",
    "sg:address":"19455 Rockside Rd",
    "sg:city":"Bedford",
    "sg:classifiers":[
        {
            "category":"Social Services",
            "subcategory":"Adult Care",
            "type":"Services"
        }
    ],
    "sg:phone":"+1 440 439 8666",
    "sg:postcode":"44146",
    "sg:province":"OH",
    "sg:tags":[
        "village",
        "home",
        "retirement",
        "residential"
    ],
    "wof:name":"Aspen Woodside Village",
    "wof:placetype":"venue"
},
  "geometry": {"coordinates":[-81.54636499999999,41.405833],"type":"Point"}
}