{
  "type": "Feature",
  "properties": {
    "addr:full": "288 Paris Dr Youngstown OH 44515",
    "addr:housenumber": "288",
    "addr:postcode": "44515",
    "addr:street": "Paris Dr",
    "iso:country": "US",
    "sg:address": "288 Paris Dr",
    "sg:city": "Youngstown",
    "sg:classifiers": [
      {
        "category": "Shopping",
        "subcategory": "Florist",
        "type": "Retail Goods"
      }
    ],
    "sg:phone": "+1 330 792 1503",
    "sg:postcode": "44515",
    "sg:province": "OH",
    "wof:name": "John Depietro Florist",
    "wof:placetype": "venue"
  },
  "geometry": {"coordinates":[-80.770705,41.096244],"type":"Point"}
}
