{
  "type": "Feature",
  "properties": {
    "iso:country":"US",
    "sg:address":"12000 Snow Rd Ste 16",
    "sg:city":"Cleveland",
    "sg:classifiers":[
        {
            "category":"Government",
            "subcategory":"Office",
            "type":"Public Place"
        }
    ],
    "sg:phone":"+1 440 845 2007",
    "sg:postcode":"44130",
    "sg:province":"OH",
    "sg:tags":[
        "government-state"
    ],
    "wof:name":"Regional Reinstatement Center",
    "wof:placetype":"venue"
},
  "geometry": {"coordinates":[-81.77089100000001,41.405055],"type":"Point"}
}