{
  "type": "Feature",
  "properties": {
    "addr:full": "4180 Kiggins Rd Delphos OH 45833",
    "addr:housenumber": "4180",
    "addr:postcode": "45833",
    "addr:street": "Kiggins Rd",
    "iso:country": "US",
    "sg:address": "4180 Kiggins Rd",
    "sg:city": "Delphos",
    "sg:classifiers": [
      {
        "category": "Farming",
        "subcategory": "Livestock Farm",
        "type": "Manufacturing \u0026 Wholesale Goods"
      }
    ],
    "sg:phone": "+1 419 692 7134",
    "sg:postcode": "45833",
    "sg:province": "OH",
    "sg:tags": [
      "beef",
      "feedlot",
      "cattle"
    ],
    "wof:name": "M \u0026 J Cattle Farm",
    "wof:placetype": "venue"
  },
  "geometry": {"coordinates":[-84.318777,40.795914],"type":"Point"}
}
