{
  "type": "Feature",
  "properties": {
    "addr:full":"1162 Old State Rte 74 Batavia OH 45103",
    "addr:housenumber":"1162",
    "addr:postcode":"45103",
    "addr:street":"Old State Rte 74",
    "iso:country":"US",
    "sg:address":"1162 Old State Rte 74",
    "sg:city":"Batavia",
    "sg:classifiers":[
        {
            "category":"Personal",
            "subcategory":"Beauty Salon",
            "type":"Services"
        }
    ],
    "sg:phone":"+1 513 753 3256",
    "sg:postcode":"45103",
    "sg:province":"OH",
    "wof:name":"Shear Reflections",
    "wof:placetype":"venue"
},
  "geometry": {"coordinates":[-84.248853,39.094609],"type":"Point"}
}