{
  "type": "Feature",
  "properties": {
    "addr:full":"420 E 4th St Cincinnati OH 45202",
    "addr:housenumber":"420",
    "addr:postcode":"45202",
    "addr:street":"E 4Th St",
    "iso:country":"US",
    "sg:address":"420 E 4th St",
    "sg:city":"Cincinnati",
    "sg:classifiers":[
        {
            "category":"Banks & Credit Unions",
            "subcategory":"Investment Brokerage",
            "type":"Services"
        }
    ],
    "sg:phone":"+1 513 361 7600",
    "sg:postcode":"45202",
    "sg:province":"OH",
    "sg:tags":[
        "advisory",
        "financial"
    ],
    "sg:website":"www.ftwashington.com",
    "wof:name":"Fort Washington Inv Advisors",
    "wof:placetype":"venue"
},
  "geometry": {"coordinates":[-84.505734,39.101054],"type":"Point"}
}