{
  "type": "Feature",
  "properties": {
    "addr:full":"4620 Bunker Rd Cleveland OH 44133",
    "addr:housenumber":"4620",
    "addr:postcode":"44133",
    "addr:street":"Bunker Rd",
    "iso:country":"US",
    "sg:address":"4620 Bunker Rd",
    "sg:city":"Cleveland",
    "sg:classifiers":[
        {
            "category":"Manufacturing",
            "subcategory":"Signs",
            "type":"Manufacturing & Wholesale Goods"
        }
    ],
    "sg:phone":"+1 440 582 5284",
    "sg:postcode":"44133",
    "sg:province":"OH",
    "sg:tags":[
        "specialty",
        "mfg"
    ],
    "wof:name":"What's Your Sign",
    "wof:placetype":"venue"
},
  "geometry": {"coordinates":[-81.71502599999999,41.345922],"type":"Point"}
}