{
  "type": "Feature",
  "properties": {
    "iso:country":"US",
    "sg:address":"1718 N Co Rd 25A",
    "sg:city":"Troy",
    "sg:classifiers":[
        {
            "category":"Government",
            "subcategory":"Office",
            "type":"Public Place"
        }
    ],
    "sg:phone":"+1 937 339 2801",
    "sg:postcode":"45373",
    "sg:province":"OH",
    "wof:name":"Buckeye House",
    "wof:placetype":"venue"
},
  "geometry": {"coordinates":[-84.215073,40.066096],"type":"Point"}
}