{
  "type": "Feature",
  "properties": {
    "addr:full":"1101 Gilman Ave Marietta OH 45750",
    "addr:housenumber":"1101",
    "addr:postcode":"45750",
    "addr:street":"Gilman Ave",
    "iso:country":"US",
    "sg:address":"1101 Gilman Ave",
    "sg:city":"Marietta",
    "sg:classifiers":[
        {
            "category":"Restaurant",
            "type":"Food & Drink"
        }
    ],
    "sg:menulink":"http://www.allmenus.com/oh/marietta/194871-mcdonalds/menu/",
    "sg:postcode":"45750",
    "sg:province":"OH",
    "sg:tags":[
        "burger",
        "american"
    ],
    "wof:name":"McDonald's",
    "wof:placetype":"venue"
},
  "geometry": {"coordinates":[-81.468085,39.421618],"type":"Point"}
}