{
  "type": "Feature",
  "properties": {
    "iso:country":"US",
    "sg:address":"2051 Dodge St NW",
    "sg:city":"Warren",
    "sg:classifiers":[
        {
            "category":"Organizations",
            "subcategory":"Religious Organization",
            "type":"Services"
        }
    ],
    "sg:phone":"+1 330 898 2657",
    "sg:postcode":"44485",
    "sg:province":"OH",
    "sg:tags":[
        "clergy"
    ],
    "wof:name":"Warren Outhwaite",
    "wof:placetype":"venue"
},
  "geometry": {"coordinates":[-80.849047,41.256274],"type":"Point"}
}