{
  "type": "Feature",
  "properties": {
    "addr:full":"1725 Palomar Dr Mansfield OH 44906",
    "addr:housenumber":"1725",
    "addr:postcode":"44906",
    "addr:street":"Palomar Dr",
    "iso:country":"US",
    "sg:address":"1725 Palomar Dr",
    "sg:city":"Mansfield",
    "sg:classifiers":[
        {
            "category":"Restaurant",
            "type":"Food & Drink"
        }
    ],
    "sg:phone":"+1 419 529 6930",
    "sg:postcode":"44906",
    "sg:province":"OH",
    "sg:tags":[
        "style",
        "family"
    ],
    "wof:name":"Dairy Land Of Mansfield",
    "wof:placetype":"venue"
},
  "geometry": {"coordinates":[-82.574398,40.744221],"type":"Point"}
}