{
  "type": "Feature",
  "properties": {
    "iso:country":"US",
    "sg:address":"2467 Woodville Rd",
    "sg:city":"Oregon",
    "sg:classifiers":[
        {
            "category":"Food & Beverages",
            "subcategory":"Groceries & Convenience Stores",
            "type":"Retail Goods"
        }
    ],
    "sg:phone":"+1 419 691 8084",
    "sg:postcode":"43616",
    "sg:province":"OH",
    "wof:name":"Gallon & Takis",
    "wof:placetype":"venue"
},
  "geometry": {"coordinates":[-83.48982100000001,41.618865],"type":"Point"}
}