{
  "type": "Feature",
  "properties": {
    "addr:full": "2467 Woodville Rd Oregon OH 43616",
    "addr:housenumber": "2467",
    "addr:postcode": "43616",
    "addr:street": "Woodville Rd",
    "iso:country": "US",
    "sg:address": "2467 Woodville Rd",
    "sg:city": "Oregon",
    "sg:classifiers": [
      {
        "category": "Food \u0026 Beverages",
        "subcategory": "Groceries \u0026 Convenience Stores",
        "type": "Retail Goods"
      }
    ],
    "sg:phone": "+1 419 691 8084",
    "sg:postcode": "43616",
    "sg:province": "OH",
    "wof:name": "Gallon \u0026 Takis",
    "wof:placetype": "venue"
  },
  "geometry": {"coordinates":[-83.489821,41.618865],"type":"Point"}
}
