{
  "type": "Feature",
  "properties": {
    "addr:full": "103 S Reed Ave Malvern OH 44644",
    "addr:housenumber": "103",
    "addr:postcode": "44644",
    "addr:street": "S Reed Ave",
    "iso:country": "US",
    "sg:address": "103 S Reed Ave",
    "sg:city": "Malvern",
    "sg:classifiers": [
      {
        "category": "Restaurant",
        "type": "Food \u0026 Drink"
      }
    ],
    "sg:menulink": "http://www.allmenus.com/oh/brown/247509-malvern-pizza-work/menu/",
    "sg:phone": "+1 330 863 1212",
    "sg:postcode": "44644",
    "sg:province": "OH",
    "sg:tags": [
      "american",
      "pizza"
    ],
    "wof:name": "Malvern Pizza Work",
    "wof:placetype": "venue"
  },
  "geometry": {"coordinates":[-81.180873,40.691516],"type":"Point"}
}
