{
  "type": "Feature",
  "properties": {
    "iso:country":"US",
    "sg:address":"4945 Pointe Pkwy",
    "sg:city":"Cleveland",
    "sg:classifiers":[
        {
            "category":"Wholesale",
            "subcategory":"Electrical",
            "type":"Manufacturing & Wholesale Goods"
        }
    ],
    "sg:phone":"+1 216 292 7278",
    "sg:postcode":"44128",
    "sg:province":"OH",
    "sg:tags":[
        "electric",
        "motor"
    ],
    "sg:website":"www.dynamotors.com",
    "wof:name":"Dynamotors' Inc",
    "wof:placetype":"venue"
},
  "geometry": {"coordinates":[-81.505353,41.425586],"type":"Point"}
}