{
  "type": "Feature",
  "properties": {
    "iso:country":"US",
    "sg:address":"124 Gish Rd",
    "sg:city":"Rittman",
    "sg:classifiers":[
        {
            "category":"Professional",
            "type":"Services"
        }
    ],
    "sg:phone":"+1 330 927 9347",
    "sg:postcode":"44270",
    "sg:province":"OH",
    "sg:tags":[
        "establishment"
    ],
    "wof:name":"Osrum Sylvania",
    "wof:placetype":"venue"
},
  "geometry": {"coordinates":[-81.772111,40.988208],"type":"Point"}
}