{
  "type": "Feature",
  "properties": {
    "iso:country":"US",
    "sg:address":"891 Graham Rd",
    "sg:city":"Cuyahoga Falls",
    "sg:classifiers":[
        {
            "category":"Home & Garden",
            "subcategory":"Home Furnishings",
            "type":"Retail Goods"
        }
    ],
    "sg:phone":"+1 330 929 5009",
    "sg:postcode":"44221",
    "sg:province":"OH",
    "sg:tags":[
        "equipment",
        "fireplace"
    ],
    "wof:name":"Homestead Fireplace & Patio",
    "wof:placetype":"venue"
},
  "geometry": {"coordinates":[-81.47997100000001,41.163587],"type":"Point"}
}