{
  "type": "Feature",
  "properties": {
    "addr:full": "891 Graham Rd Cuyahoga Falls OH 44221",
    "addr:housenumber": "891",
    "addr:postcode": "44221",
    "addr:street": "Graham Rd",
    "iso:country": "US",
    "sg:address": "891 Graham Rd",
    "sg:city": "Cuyahoga Falls",
    "sg:classifiers": [
      {
        "category": "Home \u0026 Garden",
        "subcategory": "Home Furnishings",
        "type": "Retail Goods"
      }
    ],
    "sg:phone": "+1 330 929 5009",
    "sg:postcode": "44221",
    "sg:province": "OH",
    "sg:tags": [
      "equipment",
      "fireplace"
    ],
    "wof:name": "Homestead Fireplace \u0026 Patio",
    "wof:placetype": "venue"
  },
  "geometry": {"coordinates":[-81.479971,41.163587],"type":"Point"}
}
