{
  "type": "Feature",
  "properties": {
    "iso:country":"US",
    "sg:address":"125 Dillmont Dr",
    "sg:city":"Columbus",
    "sg:classifiers":[
        {
            "category":"Building & Trades",
            "subcategory":"Plumbing",
            "type":"Services"
        }
    ],
    "sg:phone":"+1 614 786 5257",
    "sg:postcode":"43235",
    "sg:province":"OH",
    "sg:tags":[
        "mechanical",
        "contractor"
    ],
    "wof:name":"Mechanical Contractors",
    "wof:placetype":"venue"
},
  "geometry": {"coordinates":[-83.012254,40.134541],"type":"Point"}
}