{
  "type": "Feature",
  "properties": {
    "addr:full": "125 Dillmont Dr Columbus OH 43235",
    "addr:housenumber": "125",
    "addr:postcode": "43235",
    "addr:street": "Dillmont Dr",
    "iso:country": "US",
    "sg:address": "125 Dillmont Dr",
    "sg:city": "Columbus",
    "sg:classifiers": [
      {
        "category": "Building \u0026 Trades",
        "subcategory": "Plumbing",
        "type": "Services"
      }
    ],
    "sg:phone": "+1 614 786 5257",
    "sg:postcode": "43235",
    "sg:province": "OH",
    "sg:tags": [
      "mechanical",
      "contractor"
    ],
    "wof:name": "Mechanical Contractors",
    "wof:placetype": "venue"
  },
  "geometry": {"coordinates":[-83.012254,40.134541],"type":"Point"}
}
