{
  "type": "Feature",
  "properties": {
    "addr:full":"10321 Jasper Rd Cleveland OH 44111",
    "addr:housenumber":"10321",
    "addr:postcode":"44111",
    "addr:street":"Jasper Rd",
    "iso:country":"US",
    "sg:address":"10321 Jasper Rd",
    "sg:city":"Cleveland",
    "sg:classifiers":[
        {
            "category":"Retail",
            "subcategory":"Laundry & Dry Cleaning",
            "type":"Services"
        }
    ],
    "sg:phone":"+1 216 920 1223",
    "sg:postcode":"44111",
    "sg:province":"OH",
    "sg:tags":[
        "cleaners"
    ],
    "wof:name":"Amy Dry Cleaning Co",
    "wof:placetype":"venue"
},
  "geometry": {"coordinates":[-81.75817600000001,41.45172],"type":"Point"}
}