{
  "type": "Feature",
  "properties": {
    "addr:full": "4019 Prospect Ave Cleveland OH 44103",
    "addr:housenumber": "4019",
    "addr:postcode": "44103",
    "addr:street": "Prospect Ave",
    "iso:country": "US",
    "sg:address": "4019 Prospect Ave",
    "sg:city": "Cleveland",
    "sg:classifiers": [
      {
        "category": "Social Services",
        "type": "Services"
      }
    ],
    "sg:phone": "+1 216 881 7860",
    "sg:postcode": "44103",
    "sg:province": "OH",
    "sg:tags": [
      "organization",
      "welfare"
    ],
    "wof:name": "Voices For Children Of Greater",
    "wof:placetype": "venue"
  },
  "geometry": {"coordinates":[-81.656388,41.502454],"type":"Point"}
}
