{
  "type": "Feature",
  "properties": {
    "addr:full": "22133 US Hwy 224 Fostoria OH 44830",
    "addr:postcode": "22133;44830",
    "addr:street": "Us Hwy 224",
    "iso:country": "US",
    "sg:address": "22133 US Hwy 224",
    "sg:city": "Fostoria",
    "sg:classifiers": [
      {
        "category": "Real Estate",
        "subcategory": "Real Estate Operator",
        "type": "Services"
      }
    ],
    "sg:phone": "+1 419 894 6075",
    "sg:postcode": "44830",
    "sg:province": "OH",
    "sg:tags": [
      "property",
      "lessor"
    ],
    "wof:name": "Mildred Dreisbach",
    "wof:placetype": "venue"
  },
  "geometry": {"coordinates":[-83.456166,41.073885],"type":"Point"}
}
