{
  "type": "Feature",
  "properties": {
    "addr:full":"5548 Colerain Ave Cincinnati OH 45239",
    "addr:housenumber":"5548",
    "addr:postcode":"45239",
    "addr:street":"Colerain Ave",
    "iso:country":"US",
    "sg:address":"5548 Colerain Ave",
    "sg:city":"Cincinnati",
    "sg:classifiers":[
        {
            "category":"Wholesale",
            "subcategory":"Drugs",
            "type":"Manufacturing & Wholesale Goods"
        }
    ],
    "sg:phone":"+1 513 542 3185",
    "sg:postcode":"45239",
    "sg:province":"OH",
    "wof:name":"Porokhane Beauty Supply",
    "wof:placetype":"venue"
},
  "geometry": {"coordinates":[-84.572203,39.192831],"type":"Point"}
}