{
  "type": "Feature",
  "properties": {
    "addr:full":"8159 E Twp Rd 8 Republic OH 44867",
    "addr:housenumber":"8159",
    "addr:postcode":"44867",
    "addr:street":"E Twp Rd 8",
    "iso:country":"US",
    "sg:address":"8159 E Twp Rd 8",
    "sg:city":"Republic",
    "sg:classifiers":[
        {
            "category":"Building & Trades",
            "subcategory":"Construction",
            "type":"Services"
        }
    ],
    "sg:phone":"+1 419 585 3682",
    "sg:postcode":"44867",
    "sg:province":"OH",
    "sg:tags":[
        "house"
    ],
    "wof:name":"Jay W Weller",
    "wof:placetype":"venue"
},
  "geometry": {"coordinates":[-83.01304,41.11026],"type":"Point"}
}