{
  "type": "Feature",
  "properties": {
    "addr:full": "28699 Chagrin Blvd Cleveland OH 44122",
    "addr:housenumber": "28699",
    "addr:postcode": "44122",
    "addr:street": "Chagrin Blvd",
    "iso:country": "US",
    "sg:address": "28699 Chagrin Blvd",
    "sg:city": "Cleveland",
    "sg:classifiers": [
      {
        "category": "Shopping",
        "subcategory": "Clothing, Apparel, \u0026 Fashions",
        "type": "Retail Goods"
      }
    ],
    "sg:phone": "+1 216 831 4250",
    "sg:postcode": "44122",
    "sg:province": "OH",
    "sg:tags": [
      "jewelry",
      "to",
      "handbag",
      "costume",
      "ready",
      "wear"
    ],
    "wof:name": "Claires",
    "wof:placetype": "venue"
  },
  "geometry": {"coordinates":[-81.475928,41.462415],"type":"Point"}
}
