{
  "type": "Feature",
  "properties": {
    "iso:country":"US",
    "sg:address":"228 S Main St",
    "sg:city":"Bryan",
    "sg:classifiers":[
        {
            "category":"Government",
            "subcategory":"Office",
            "type":"Public Place"
        }
    ],
    "sg:phone":"+1 419 636 8812",
    "sg:postcode":"43506",
    "sg:province":"OH",
    "wof:name":"Williams County Veterans Svc",
    "wof:placetype":"venue"
},
  "geometry": {"coordinates":[-84.55111599999999,41.472931],"type":"Point"}
}