{
  "type": "Feature",
  "properties": {
    "iso:country":"US",
    "sg:address":"11561 Grooms Rd",
    "sg:city":"Cincinnati",
    "sg:classifiers":[
        {
            "category":"Home & Garden",
            "subcategory":"Home Furnishings",
            "type":"Retail Goods"
        }
    ],
    "sg:phone":"+1 513 469 8300",
    "sg:postcode":"45242",
    "sg:province":"OH",
    "sg:tags":[
        "beveled",
        "glass",
        "ornamental"
    ],
    "wof:name":"Square Forest",
    "wof:placetype":"venue"
},
  "geometry": {"coordinates":[-84.36691999999999,39.273661],"type":"Point"}
}