{
  "type": "Feature",
  "properties": {
    "addr:full":"3738 Warsaw Ave Cincinnati OH 45205",
    "addr:housenumber":"3738",
    "addr:postcode":"45205",
    "addr:street":"Warsaw Ave",
    "iso:country":"US",
    "sg:address":"3738 Warsaw Ave",
    "sg:city":"Cincinnati",
    "sg:classifiers":[
        {
            "category":"Restaurant",
            "type":"Food & Drink"
        }
    ],
    "sg:menulink":"http://www.allmenus.com/oh/cincinnati/195222-mcdonalds/menu/",
    "sg:postcode":"45205",
    "sg:province":"OH",
    "sg:tags":[
        "burger",
        "american"
    ],
    "wof:name":"McDonald's",
    "wof:placetype":"venue"
},
  "geometry": {"coordinates":[-84.57466100000001,39.112875],"type":"Point"}
}