{
  "type": "Feature",
  "properties": {
    "addr:full": "3794 E 131st St Cleveland OH 44120",
    "addr:housenumber": "3794",
    "addr:postcode": "44120",
    "addr:street": "E 131St St",
    "iso:country": "US",
    "sg:address": "3794 E 131st St",
    "sg:city": "Cleveland",
    "sg:classifiers": [
      {
        "category": "Wholesale",
        "subcategory": "Machinery \u0026 Supplies",
        "type": "Manufacturing \u0026 Wholesale Goods"
      }
    ],
    "sg:phone": "+1 216 991 1123",
    "sg:postcode": "44120",
    "sg:province": "OH",
    "sg:tags": [
      "equipment",
      "barber"
    ],
    "wof:name": "Wholesaler Unlimited",
    "wof:placetype": "venue"
  },
  "geometry": {"coordinates":[-81.591226,41.45538],"type":"Point"}
}
