{
  "type": "Feature",
  "properties": {
    "iso:country":"US",
    "sg:address":"629 Shoestring Ridge Rd",
    "sg:city":"Gallipolis",
    "sg:classifiers":[
        {
            "category":"Shopping",
            "subcategory":"Hobbies, Toys, & Games",
            "type":"Retail Goods"
        }
    ],
    "sg:phone":"+1 740 441 8249",
    "sg:postcode":"45631",
    "sg:province":"OH",
    "wof:name":"Scrappin Mania",
    "wof:placetype":"venue"
},
  "geometry": {"coordinates":[-82.21230300000001,38.752119],"type":"Point"}
}