{
  "type": "Feature",
  "properties": {
    "iso:country":"US",
    "sg:address":"9033 Academy View Ct",
    "sg:city":"Dayton",
    "sg:classifiers":[
        {
            "category":"Wholesale",
            "subcategory":"Non-durable Goods",
            "type":"Manufacturing & Wholesale Goods"
        }
    ],
    "sg:phone":"+1 937 439 4201",
    "sg:postcode":"45458",
    "sg:province":"OH",
    "sg:tags":[
        "advertising"
    ],
    "wof:name":"Proforma Identity",
    "wof:placetype":"venue"
},
  "geometry": {"coordinates":[-84.140092,39.612499],"type":"Point"}
}