{
  "type": "Feature",
  "properties": {
    "iso:country":"US",
    "sg:address":"2618 Gibbs Ave NE",
    "sg:city":"Canton",
    "sg:classifiers":[
        {
            "category":"Shopping",
            "subcategory":"Used Merchandise",
            "type":"Retail Goods"
        }
    ],
    "sg:phone":"+1 330 455 5910",
    "sg:postcode":"44714",
    "sg:province":"OH",
    "sg:tags":[
        "antique"
    ],
    "wof:name":"Hudz Antiques",
    "wof:placetype":"venue"
},
  "geometry": {"coordinates":[-81.361897,40.824762],"type":"Point"}
}