{
  "type": "Feature",
  "properties": {
    "addr:full":"12905 York-Delta Dr Cleveland OH 44133",
    "addr:housenumber":"12905",
    "addr:postcode":"44133",
    "addr:street":"York-Delta Dr",
    "iso:country":"US",
    "sg:address":"12905 York-Delta Dr",
    "sg:city":"Cleveland",
    "sg:classifiers":[
        {
            "category":"Wholesale",
            "subcategory":"Dairy",
            "type":"Manufacturing & Wholesale Goods"
        }
    ],
    "sg:phone":"+1 440 237 4040",
    "sg:postcode":"44133",
    "sg:province":"OH",
    "sg:tags":[
        "frozen",
        "dessert",
        "ice",
        "cream"
    ],
    "sg:website":"www.countryparlour.com",
    "wof:name":"Country Parlour Ice Cream Co",
    "wof:placetype":"venue"
},
  "geometry": {"coordinates":[-81.761415,41.321338],"type":"Point"}
}