{
  "type": "Feature",
  "properties": {
    "iso:country":"US",
    "sg:address":"3975 Embassy Pkwy",
    "sg:city":"Akron",
    "sg:classifiers":[
        {
            "category":"Manufacturing",
            "subcategory":"Tools & Machinery",
            "type":"Manufacturing & Wholesale Goods"
        },
        {
            "category":"Health Services",
            "subcategory":"Doctor",
            "type":"Services"
        }
    ],
    "sg:phone":"+1 330 668 4070",
    "sg:postcode":"44333",
    "sg:province":"OH",
    "sg:tags":[
        "sport",
        "mfg",
        "medical",
        "surgical",
        "medicine",
        "injury"
    ],
    "wof:name":"Yanke Bionics Inc",
    "wof:placetype":"venue"
},
  "geometry": {"coordinates":[-81.64854099999999,41.141319],"type":"Point"}
}