{
  "type": "Feature",
  "properties": {
    "addr:full": "3975 Embassy Pkwy Akron OH 44333",
    "addr:housenumber": "3975",
    "addr:postcode": "44333",
    "addr:street": "Embassy Pkwy",
    "iso:country": "US",
    "sg:address": "3975 Embassy Pkwy",
    "sg:city": "Akron",
    "sg:classifiers": [
      {
        "category": "Manufacturing",
        "subcategory": "Tools \u0026 Machinery",
        "type": "Manufacturing \u0026 Wholesale Goods"
      },
      {
        "category": "Health Services",
        "subcategory": "Doctor",
        "type": "Services"
      }
    ],
    "sg:phone": "+1 330 668 4070",
    "sg:postcode": "44333",
    "sg:province": "OH",
    "sg:tags": [
      "sport",
      "mfg",
      "medical",
      "surgical",
      "medicine",
      "injury"
    ],
    "wof:name": "Yanke Bionics Inc",
    "wof:placetype": "venue"
  },
  "geometry": {"coordinates":[-81.648541,41.141319],"type":"Point"}
}
