{
  "type": "Feature",
  "properties": {
    "addr:full":"1620 Eddington Rd Cleveland OH 44118",
    "addr:housenumber":"1620",
    "addr:postcode":"44118",
    "addr:street":"Eddington Rd",
    "iso:country":"US",
    "sg:address":"1620 Eddington Rd",
    "sg:city":"Cleveland",
    "sg:classifiers":[
        {
            "category":"Insurance",
            "subcategory":"Insurance Agent",
            "type":"Services"
        },
        {
            "category":"Banks & Credit Unions",
            "subcategory":"Financial Services",
            "type":"Services"
        }
    ],
    "sg:phone":"+1 216 812 1971",
    "sg:postcode":"44118",
    "sg:province":"OH",
    "sg:tags":[
        "counseling",
        "debt",
        "adjuster"
    ],
    "wof:name":"Jubilee Services",
    "wof:placetype":"venue"
},
  "geometry": {"coordinates":[-81.57691199999999,41.515202],"type":"Point"}
}