{
  "type": "Feature",
  "properties": {
    "addr:full":"26829 Warren Rd Utica OH 43080",
    "addr:housenumber":"26829",
    "addr:postcode":"43080",
    "addr:street":"Warren Rd",
    "iso:country":"US",
    "sg:address":"26829 Warren Rd",
    "sg:city":"Utica",
    "sg:classifiers":[
        {
            "category":"Farming",
            "subcategory":"Farm",
            "type":"Manufacturing & Wholesale Goods"
        }
    ],
    "sg:phone":"+1 740 668 2579",
    "sg:postcode":"43080",
    "sg:province":"OH",
    "sg:tags":[
        "crop",
        "general"
    ],
    "wof:name":"Wakatomika Tree Farm",
    "wof:placetype":"venue"
},
  "geometry": {"coordinates":[-82.284177,40.246149],"type":"Point"}
}