{
  "type": "Feature",
  "properties": {
    "addr:full":"8387 Tod Ave Boardman OH 44512",
    "addr:housenumber":"8387",
    "addr:postcode":"44512",
    "addr:street":"Tod Ave",
    "iso:country":"US",
    "sg:address":"8387 Tod Ave",
    "sg:city":"Boardman",
    "sg:classifiers":[
        {
            "category":"Organizations",
            "subcategory":"Community Association",
            "type":"Services"
        }
    ],
    "sg:phone":"+1 330 729 0458",
    "sg:postcode":"44512",
    "sg:province":"OH",
    "sg:tags":[
        "fraternal"
    ],
    "wof:name":"Western Star Masonic Lodge",
    "wof:placetype":"venue"
},
  "geometry": {"coordinates":[-80.658958,40.993086],"type":"Point"}
}