{
  "type": "Feature",
  "properties": {
    "iso:country":"US",
    "sg:address":"4621 Central Ave",
    "sg:city":"Cleveland",
    "sg:classifiers":[
        {
            "category":"Food & Beverages",
            "subcategory":"Groceries & Convenience Stores",
            "type":"Retail Goods"
        }
    ],
    "sg:phone":"+1 216 431 7285",
    "sg:postcode":"44104",
    "sg:province":"OH",
    "sg:tags":[
        "grocer"
    ],
    "wof:name":"Pauls Serve Rite Food Market",
    "wof:placetype":"venue"
},
  "geometry": {"coordinates":[-81.65333200000001,41.496369],"type":"Point"}
}