{
  "type": "Feature",
  "properties": {
    "addr:full": "4621 Central Ave Cleveland OH 44104",
    "addr:housenumber": "4621",
    "addr:postcode": "44104",
    "addr:street": "Central Ave",
    "iso:country": "US",
    "sg:address": "4621 Central Ave",
    "sg:city": "Cleveland",
    "sg:classifiers": [
      {
        "category": "Food \u0026 Beverages",
        "subcategory": "Groceries \u0026 Convenience Stores",
        "type": "Retail Goods"
      }
    ],
    "sg:phone": "+1 216 431 7285",
    "sg:postcode": "44104",
    "sg:province": "OH",
    "sg:tags": [
      "grocer"
    ],
    "wof:name": "Pauls Serve Rite Food Market",
    "wof:placetype": "venue"
  },
  "geometry": {"coordinates":[-81.653332,41.496369],"type":"Point"}
}
