{
  "type": "Feature",
  "properties": {
    "iso:country":"US",
    "sg:address":"407 Walnut St",
    "sg:city":"Cincinnati",
    "sg:classifiers":[
        {
            "category":"Organizations",
            "subcategory":"Religious Organization",
            "type":"Services"
        }
    ],
    "sg:phone":"+1 513 641 4723",
    "sg:postcode":"45216",
    "sg:province":"OH",
    "sg:tags":[
        "church"
    ],
    "wof:name":"Grace Fellowship Bapt Church",
    "wof:placetype":"venue"
},
  "geometry": {"coordinates":[-84.489769,39.187471],"type":"Point"}
}