{
  "type": "Feature",
  "properties": {
    "addr:full":"1871 Niles Cortland Rd NE Warren OH 44484",
    "addr:housenumber":"1871",
    "addr:postcode":"44484",
    "addr:street":"Niles Cortland Rd Ne",
    "iso:country":"US",
    "sg:address":"1871 Niles Cortland Rd NE",
    "sg:city":"Warren",
    "sg:classifiers":[
        {
            "category":"Personal",
            "subcategory":"Beauty Salon",
            "type":"Services"
        }
    ],
    "sg:phone":"+1 330 856 1046",
    "sg:postcode":"44484",
    "sg:province":"OH",
    "wof:name":"Salon 46",
    "wof:placetype":"venue"
},
  "geometry": {"coordinates":[-80.74093999999999,41.26118],"type":"Point"}
}