{
  "type": "Feature",
  "properties": {
    "addr:full":"821 W Hunter St Logan OH 43138",
    "addr:housenumber":"821",
    "addr:postcode":"43138",
    "addr:street":"W Hunter St",
    "iso:country":"US",
    "sg:address":"821 W Hunter St",
    "sg:city":"Logan",
    "sg:classifiers":[
        {
            "category":"Sports & Exercise",
            "subcategory":"Gym",
            "type":"Entertainment"
        }
    ],
    "sg:phone":"+1 740 385 6111",
    "sg:postcode":"43138",
    "sg:province":"OH",
    "sg:tags":[
        "club",
        "health",
        "studio",
        "gymnasium"
    ],
    "wof:name":"B Fit",
    "wof:placetype":"venue"
},
  "geometry": {"coordinates":[-82.42086500000001,39.542001],"type":"Point"}
}