{
  "type": "Feature",
  "properties": {
    "addr:full":"35104 Euclid Ave Willoughby OH 44094",
    "addr:housenumber":"35104",
    "addr:postcode":"44094",
    "addr:street":"Euclid Ave",
    "iso:country":"US",
    "sg:address":"35104 Euclid Ave",
    "sg:city":"Willoughby",
    "sg:classifiers":[
        {
            "category":"Professional",
            "subcategory":"Lawyer & Legal Services",
            "type":"Services"
        }
    ],
    "sg:phone":"+1 440 953 1771",
    "sg:postcode":"44094",
    "sg:province":"OH",
    "sg:tags":[
        "attorney"
    ],
    "wof:name":"Mark Glinski",
    "wof:placetype":"venue"
},
  "geometry": {"coordinates":[-81.437479,41.625365],"type":"Point"}
}