{
  "type": "Feature",
  "properties": {
    "addr:full": "5761 Linnville Rd SE Heath OH 43056",
    "addr:housenumber": "5761",
    "addr:postcode": "43056",
    "addr:street": "Linnville Rd Se",
    "iso:country": "US",
    "sg:address": "5761 Linnville Rd SE",
    "sg:city": "Heath",
    "sg:classifiers": [
      {
        "category": "Local Transit",
        "type": "Transportation"
      }
    ],
    "sg:phone": "+1 740 323 2909",
    "sg:postcode": "43056",
    "sg:province": "OH",
    "sg:tags": [
      "passenger",
      "limousine"
    ],
    "wof:name": "Gray Top Limo Inc",
    "wof:placetype": "venue"
  },
  "geometry": {"coordinates":[-82.374183,40.006354],"type":"Point"}
}
