{
  "type": "Feature",
  "properties": {
    "iso:country":"US",
    "sg:address":"3111 Thomas Ave",
    "sg:city":"Grove City",
    "sg:classifiers":[
        {
            "category":"Building & Trades",
            "subcategory":"Construction",
            "type":"Services"
        }
    ],
    "sg:phone":"+1 614 875 1104",
    "sg:postcode":"43123",
    "sg:province":"OH",
    "sg:tags":[
        "home",
        "contractor",
        "remodeling",
        "co",
        "light"
    ],
    "wof:name":"D E Gibboney & Son Inc",
    "wof:placetype":"venue"
},
  "geometry": {"coordinates":[-83.08565299999999,39.889498],"type":"Point"}
}