{
  "type": "Feature",
  "properties": {
    "addr:full":"2142 W 7th St Cleveland OH 44113",
    "addr:housenumber":"2142",
    "addr:postcode":"44113",
    "addr:street":"W 7Th St",
    "iso:country":"US",
    "sg:address":"2142 W 7th St",
    "sg:city":"Cleveland",
    "sg:classifiers":[
        {
            "category":"Building & Trades",
            "subcategory":"Electrical",
            "type":"Services"
        },
        {
            "category":"Manufacturing",
            "subcategory":"Electronics",
            "type":"Manufacturing & Wholesale Goods"
        }
    ],
    "sg:phone":"+1 440 892 1111",
    "sg:postcode":"44113",
    "sg:province":"OH",
    "sg:tags":[
        "home",
        "security",
        "system",
        "automation"
    ],
    "sg:website":"www.newimageinc.com",
    "wof:name":"Digital Convergence Systems",
    "wof:placetype":"venue"
},
  "geometry": {"coordinates":[-81.686268,41.483571],"type":"Point"}
}