{
  "type": "Feature",
  "properties": {
    "iso:country":"US",
    "sg:address":"1990 Graham Rd",
    "sg:city":"Stow",
    "sg:classifiers":[
        {
            "category":"Insurance",
            "subcategory":"Insurance Agent",
            "type":"Services"
        }
    ],
    "sg:phone":"+1 330 688 4222",
    "sg:postcode":"44224",
    "sg:province":"OH",
    "wof:name":"Raymond James Financial Svc",
    "wof:placetype":"venue"
},
  "geometry": {"coordinates":[-81.44394699999999,41.166717],"type":"Point"}
}