{
  "type": "Feature",
  "properties": {
    "iso:country":"US",
    "sg:address":"6957 S Cleveland Massillon Rd",
    "sg:city":"Clinton",
    "sg:classifiers":[
        {
            "category":"Shopping",
            "subcategory":"Computers & Home Electronics",
            "type":"Retail Goods"
        }
    ],
    "sg:phone":"+1 330 825 7966",
    "sg:postcode":"44216",
    "sg:province":"OH",
    "sg:tags":[
        "equipment",
        "dealer"
    ],
    "wof:name":"PC-Systems",
    "wof:placetype":"venue"
},
  "geometry": {"coordinates":[-81.631707,40.956669],"type":"Point"}
}