{
  "type": "Feature",
  "properties": {
    "addr:full": "11135 Whitewood Dr Newbury OH 44065",
    "addr:housenumber": "11135",
    "addr:postcode": "44065",
    "addr:street": "Whitewood Dr",
    "iso:country": "US",
    "sg:address": "11135 Whitewood Dr",
    "sg:city": "Newbury",
    "sg:classifiers": [
      {
        "category": "Home \u0026 Garden",
        "subcategory": "Building Materials",
        "type": "Retail Goods"
      }
    ],
    "sg:phone": "+1 330 478 0770",
    "sg:postcode": "44065",
    "sg:province": "OH",
    "wof:name": "All Star Garage Door",
    "wof:placetype": "venue"
  },
  "geometry": {"coordinates":[-81.242787,41.49736],"type":"Point"}
}
