{
  "type": "Feature",
  "properties": {
    "addr:full": "4365 Old Delphos Rd Lima OH 45807",
    "addr:housenumber": "4365",
    "addr:postcode": "45807",
    "addr:street": "Old Delphos Rd",
    "iso:country": "US",
    "sg:address": "4365 Old Delphos Rd",
    "sg:city": "Lima",
    "sg:phone": "+1 419 339 2121",
    "sg:postcode": "45807",
    "sg:province": "OH",
    "sg:tags": [
      "farm",
      "corn",
      "soybean"
    ],
    "wof:name": "Charles Rossfeld",
    "wof:placetype": "venue"
  },
  "geometry": {"coordinates":[-84.258148,40.796362],"type":"Point"}
}
