{
  "type": "Feature",
  "properties": {
    "iso:country":"US",
    "sg:address":"623 F St",
    "sg:city":"Lorain",
    "sg:classifiers":[
        {
            "category":"Food & Beverages",
            "subcategory":"Groceries & Convenience Stores",
            "type":"Retail Goods"
        }
    ],
    "sg:phone":"+1 440 288 0314",
    "sg:postcode":"44052",
    "sg:province":"OH",
    "wof:name":"Stan S Grocery Deli",
    "wof:placetype":"venue"
},
  "geometry": {"coordinates":[-82.16512299999999,41.467506],"type":"Point"}
}