{
  "type": "Feature",
  "properties": {
    "addr:full": "623 F St Lorain OH 44052",
    "addr:housenumber": "623",
    "addr:postcode": "44052",
    "addr:street": "F St",
    "iso:country": "US",
    "sg:address": "623 F St",
    "sg:city": "Lorain",
    "sg:classifiers": [
      {
        "category": "Food \u0026 Beverages",
        "subcategory": "Groceries \u0026 Convenience Stores",
        "type": "Retail Goods"
      }
    ],
    "sg:phone": "+1 440 288 0314",
    "sg:postcode": "44052",
    "sg:province": "OH",
    "wof:name": "Stan S Grocery Deli",
    "wof:placetype": "venue"
  },
  "geometry": {"coordinates":[-82.165123,41.467506],"type":"Point"}
}
