{
  "type": "Feature",
  "properties": {
    "iso:country":"US",
    "sg:address":"8100 Reading Rd",
    "sg:city":"Cincinnati",
    "sg:classifiers":[
        {
            "category":"Retail",
            "subcategory":"Repair Shop",
            "type":"Services"
        }
    ],
    "sg:phone":"+1 513 821 2632",
    "sg:postcode":"45237",
    "sg:province":"OH",
    "sg:tags":[
        "equipment",
        "photographic"
    ],
    "wof:name":"Bob's Valley Photo & Video",
    "wof:placetype":"venue"
},
  "geometry": {"coordinates":[-84.451274,39.207004],"type":"Point"}
}