{
  "type": "Feature",
  "properties": {
    "iso:country":"US",
    "sg:address":"1504 Grant Ave",
    "sg:city":"Cuyahoga Falls",
    "sg:classifiers":[
        {
            "category":"Health Services",
            "subcategory":"Nursing And Care Facility",
            "type":"Services"
        },
        {
            "category":"Health Services",
            "subcategory":"Health Practitioner",
            "type":"Services"
        }
    ],
    "sg:phone":"+1 330 926 0824",
    "sg:postcode":"44223",
    "sg:province":"OH",
    "sg:tags":[
        "nurse",
        "skilled",
        "employment",
        "agency",
        "registry"
    ],
    "wof:name":"Reliable Nursing Resources LLC",
    "wof:placetype":"venue"
},
  "geometry": {"coordinates":[-81.501318,41.126875],"type":"Point"}
}