{
  "type": "Feature",
  "properties": {
    "iso:country":"US",
    "sg:address":"2660 N Haven Blvd",
    "sg:city":"Cuyahoga Falls",
    "sg:classifiers":[
        {
            "category":"Wholesale",
            "subcategory":"Metals & Minerals",
            "type":"Manufacturing & Wholesale Goods"
        }
    ],
    "sg:phone":"+1 330 794 2500",
    "sg:postcode":"44223",
    "sg:province":"OH",
    "sg:tags":[
        "steel",
        "warehouse"
    ],
    "wof:name":"American Iron & Alloy",
    "wof:placetype":"venue"
},
  "geometry": {"coordinates":[-81.50295699999999,41.145063],"type":"Point"}
}