{
  "type": "Feature",
  "properties": {
    "addr:full": "2660 N Haven Blvd Cuyahoga Falls OH 44223",
    "addr:housenumber": "2660",
    "addr:postcode": "44223",
    "addr:street": "N Haven Blvd",
    "iso:country": "US",
    "sg:address": "2660 N Haven Blvd",
    "sg:city": "Cuyahoga Falls",
    "sg:classifiers": [
      {
        "category": "Wholesale",
        "subcategory": "Metals \u0026 Minerals",
        "type": "Manufacturing \u0026 Wholesale Goods"
      }
    ],
    "sg:phone": "+1 330 794 2500",
    "sg:postcode": "44223",
    "sg:province": "OH",
    "sg:tags": [
      "steel",
      "warehouse"
    ],
    "wof:name": "American Iron \u0026 Alloy",
    "wof:placetype": "venue"
  },
  "geometry": {"coordinates":[-81.502957,41.145063],"type":"Point"}
}
