{
  "type": "Feature",
  "properties": {
    "iso:country":"US",
    "sg:address":"2050 Kenny Rd",
    "sg:city":"Columbus",
    "sg:classifiers":[
        {
            "category":"Health Services",
            "subcategory":"Podiatrist",
            "type":"Services"
        }
    ],
    "sg:phone":"+1 614 293 3668",
    "sg:postcode":"43221",
    "sg:province":"OH",
    "wof:name":"OSU Podiatry",
    "wof:placetype":"venue"
},
  "geometry": {"coordinates":[-83.03443799999999,40.001285],"type":"Point"}
}