{
  "type": "Feature",
  "properties": {
    "addr:full":"11 State Rte 56 NW London OH 43140",
    "addr:housenumber":"11",
    "addr:postcode":"43140",
    "addr:street":"State Rte 56 Nw",
    "iso:country":"US",
    "sg:address":"11 State Rte 56 NW",
    "sg:city":"London",
    "sg:classifiers":[
        {
            "category":"Organizations",
            "subcategory":"Religious Organization",
            "type":"Services"
        }
    ],
    "sg:phone":"+1 740 852 5875",
    "sg:postcode":"43140",
    "sg:province":"OH",
    "sg:tags":[
        "church"
    ],
    "wof:name":"Abundant Love Christian Chrh",
    "wof:placetype":"venue"
},
  "geometry": {"coordinates":[-83.491845,39.934048],"type":"Point"}
}