{
  "type": "Feature",
  "properties": {
    "iso:country":"US",
    "sg:address":"1226 Nevada St",
    "sg:city":"Toledo",
    "sg:classifiers":[
        {
            "category":"Insurance",
            "subcategory":"Insurance Agent",
            "type":"Services"
        }
    ],
    "sg:phone":"+1 419 691 1428",
    "sg:postcode":"43605",
    "sg:province":"OH",
    "wof:name":"Martin & Martin Agency Inc",
    "wof:placetype":"venue"
},
  "geometry": {"coordinates":[-83.512424,41.639857],"type":"Point"}
}