{
  "type": "Feature",
  "properties": {
    "iso:country":"US",
    "sg:address":"4133 Westward Ave",
    "sg:city":"Columbus",
    "sg:classifiers":[
        {
            "category":"Professional",
            "type":"Services"
        }
    ],
    "sg:phone":"+1 614 761 7779",
    "sg:postcode":"43228",
    "sg:province":"OH",
    "sg:tags":[
        "control",
        "consultant",
        "noise"
    ],
    "wof:name":"Mayer Acoustics",
    "wof:placetype":"venue"
},
  "geometry": {"coordinates":[-83.11165699999999,39.969412],"type":"Point"}
}