{
  "type": "Feature",
  "properties": {
    "addr:full": "135 N Detroit St Bellefontaine OH 43311",
    "addr:housenumber": "135",
    "addr:postcode": "43311",
    "addr:street": "N Detroit St",
    "iso:country": "US",
    "sg:address": "135 N Detroit St",
    "sg:city": "Bellefontaine",
    "sg:classifiers": [
      {
        "category": "Recreation",
        "type": "Entertainment"
      }
    ],
    "sg:phone": "+1 937 592 3475",
    "sg:postcode": "43311",
    "sg:province": "OH",
    "sg:tags": [
      "parks"
    ],
    "wof:name": "Bellefontaine Parks \u0026 Rec Dept",
    "wof:placetype": "venue"
  },
  "geometry": {"coordinates":[-83.761539,40.362628],"type":"Point"}
}
