{
  "type": "Feature",
  "properties": {
    "addr:full":"6457 Reflections Dr Dublin OH 43017",
    "addr:housenumber":"6457",
    "addr:postcode":"43017",
    "addr:street":"Reflections Dr",
    "iso:country":"US",
    "sg:address":"6457 Reflections Dr",
    "sg:city":"Dublin",
    "sg:classifiers":[
        {
            "category":"Banks & Credit Unions",
            "subcategory":"Investment Brokerage",
            "type":"Services"
        }
    ],
    "sg:phone":"+1 614 588 0050",
    "sg:postcode":"43017",
    "sg:province":"OH",
    "sg:tags":[
        "consultant",
        "planning",
        "financial"
    ],
    "sg:website":"www.ameriprise.com",
    "wof:name":"Ameriprise Financial",
    "wof:placetype":"venue"
},
  "geometry": {"coordinates":[-83.088166,40.087958],"type":"Point"}
}