{
  "type": "Feature",
  "properties": {
    "addr:full": "5079 Porter Rd North Olmsted OH 44070",
    "addr:housenumber": "5079",
    "addr:postcode": "44070",
    "addr:street": "Porter Rd",
    "iso:country": "US",
    "sg:address": "5079 Porter Rd",
    "sg:city": "North Olmsted",
    "sg:classifiers": [
      {
        "category": "Building \u0026 Trades",
        "subcategory": "Electrical",
        "type": "Services"
      }
    ],
    "sg:phone": "+1 440 734 9098",
    "sg:postcode": "44070",
    "sg:province": "OH",
    "sg:tags": [
      "repair",
      "electrical",
      "contractor"
    ],
    "wof:name": "Donald R Tatro",
    "wof:placetype": "venue"
  },
  "geometry": {"coordinates":[-81.928329,41.415708],"type":"Point"}
}
