{
  "type": "Feature",
  "properties": {
    "addr:full":"21990 Lorain Rd Cleveland OH 44126",
    "addr:housenumber":"21990",
    "addr:postcode":"44126",
    "addr:street":"Lorain Rd",
    "iso:country":"US",
    "sg:address":"21990 Lorain Rd",
    "sg:city":"Cleveland",
    "sg:classifiers":[
        {
            "category":"Wholesale",
            "subcategory":"Durable Goods & Equipment",
            "type":"Manufacturing & Wholesale Goods"
        }
    ],
    "sg:phone":"+1 440 333 9945",
    "sg:postcode":"44126",
    "sg:province":"OH",
    "sg:tags":[
        "representative",
        "manufacturer"
    ],
    "wof:name":"G F Sindelar Co",
    "wof:placetype":"venue"
},
  "geometry": {"coordinates":[-81.863091,41.442224],"type":"Point"}
}