{
  "type": "Feature",
  "properties": {
    "addr:full":"5676 Dixie Hwy Fairfield OH 45014",
    "addr:housenumber":"5676",
    "addr:postcode":"45014",
    "addr:street":"Dixie Hwy",
    "iso:country":"US",
    "sg:address":"5676 Dixie Hwy",
    "sg:city":"Fairfield",
    "sg:classifiers":[
        {
            "category":"Autos & Motor Vehicles",
            "subcategory":"Automobile Sales",
            "type":"Retail Goods"
        },
        {
            "category":"Wholesale",
            "subcategory":"Auto Parts",
            "type":"Manufacturing & Wholesale Goods"
        }
    ],
    "sg:phone":"+1 513 874 8797",
    "sg:postcode":"45014",
    "sg:province":"OH",
    "sg:tags":[
        "car",
        "lube",
        "oil",
        "supply"
    ],
    "sg:website":"http://www.toyota.com",
    "wof:name":"Performance Toyota",
    "wof:placetype":"venue"
},
  "geometry": {"coordinates":[-84.51979300000001,39.331559],"type":"Point"}
}