{
  "type": "Feature",
  "properties": {
    "addr:full":"14950 US Hwy 68 Mount Orab OH 45154",
    "addr:postcode":"14950;45154",
    "addr:street":"Us Hwy 68 Mount",
    "iso:country":"US",
    "sg:address":"14950 US Hwy 68",
    "sg:city":"Mount Orab",
    "sg:classifiers":[
        {
            "category":"Shopping",
            "type":"Retail Goods"
        }
    ],
    "sg:phone":"+1 937 444 2917",
    "sg:postcode":"45154",
    "sg:province":"OH",
    "sg:tags":[
        "to",
        "finished",
        "monument",
        "order",
        "custom"
    ],
    "wof:name":"Hirons Memorial Works Inc",
    "wof:placetype":"venue"
},
  "geometry": {"coordinates":[-83.923468,39.051384],"type":"Point"}
}