{
  "type": "Feature",
  "properties": {
    "iso:country":"US",
    "sg:address":"903 Orchard Dr",
    "sg:city":"Rossford",
    "sg:classifiers":[
        {
            "category":"Restaurant",
            "type":"Food & Drink"
        }
    ],
    "sg:phone":"+1 419 666 7575",
    "sg:postcode":"43460",
    "sg:province":"OH",
    "sg:tags":[
        "eating"
    ],
    "wof:name":"McDonalds",
    "wof:placetype":"venue"
},
  "geometry": {"coordinates":[-83.55362700000001,41.599864],"type":"Point"}
}