{
  "type": "Feature",
  "properties": {
    "iso:country":"US",
    "sg:address":"10801 Briggs Rd",
    "sg:city":"Cleveland",
    "sg:classifiers":[
        {
            "category":"Retail",
            "subcategory":"Repair Shop",
            "type":"Services"
        }
    ],
    "sg:phone":"+1 216 251 3245",
    "sg:postcode":"44111",
    "sg:province":"OH",
    "sg:tags":[
        "welding"
    ],
    "wof:name":"Thomas Welding & Repair",
    "wof:placetype":"venue"
},
  "geometry": {"coordinates":[-81.761777,41.447505],"type":"Point"}
}