{
  "type": "Feature",
  "properties": {
    "iso:country":"US",
    "sg:address":"4161 Caddy Rd SW",
    "sg:city":"Bowerston",
    "sg:classifiers":[
        {
            "category":"Organizations",
            "subcategory":"Religious Organization",
            "type":"Services"
        }
    ],
    "sg:phone":"+1 330 735 3369",
    "sg:postcode":"44695",
    "sg:province":"OH",
    "sg:tags":[
        "church"
    ],
    "wof:name":"Leavittsville Methodist Chr",
    "wof:placetype":"venue"
},
  "geometry": {"coordinates":[-81.19600199999999,40.513391],"type":"Point"}
}