{
  "type": "Feature",
  "properties": {
    "iso:country":"US",
    "sg:address":"6900 S Edgerton Rd",
    "sg:city":"Cleveland",
    "sg:classifiers":[
        {
            "category":"Real Estate",
            "subcategory":"Real Estate Agent",
            "type":"Services"
        }
    ],
    "sg:phone":"+1 440 838 8130",
    "sg:postcode":"44141",
    "sg:province":"OH",
    "sg:tags":[
        "consultant"
    ],
    "wof:name":"Utility Land Co Inc",
    "wof:placetype":"venue"
},
  "geometry": {"coordinates":[-81.64304799999999,41.292964],"type":"Point"}
}