{
  "type": "Feature",
  "properties": {
    "iso:country":"US",
    "sg:address":"1265 Middle Rowsburg Rd",
    "sg:city":"Ashland",
    "sg:classifiers":[
        {
            "category":"Government",
            "subcategory":"Office",
            "type":"Public Place"
        }
    ],
    "sg:phone":"+1 419 281 3001",
    "sg:postcode":"44805",
    "sg:province":"OH",
    "sg:tags":[
        "govt",
        "city"
    ],
    "wof:name":"Ashland Water Works Shop",
    "wof:placetype":"venue"
},
  "geometry": {"coordinates":[-82.29404,40.872297],"type":"Point"}
}