{
  "type": "Feature",
  "properties": {
    "addr:full": "4560 Heatherdowns Blvd Toledo OH 43614",
    "addr:housenumber": "4560",
    "addr:postcode": "43614",
    "addr:street": "Heatherdowns Blvd",
    "iso:country": "US",
    "sg:address": "4560 Heatherdowns Blvd",
    "sg:city": "Toledo",
    "sg:classifiers": [
      {
        "category": "Banks \u0026 Credit Unions",
        "subcategory": "Investment Brokerage",
        "type": "Services"
      }
    ],
    "sg:phone": "+1 419 385 8280",
    "sg:postcode": "43614",
    "sg:province": "OH",
    "sg:tags": [
      "security"
    ],
    "wof:name": "Seiple Financial Group",
    "wof:placetype": "venue"
  },
  "geometry": {"coordinates":[-83.651292,41.59445],"type":"Point"}
}
