{
  "type": "Feature",
  "properties": {
    "addr:full": "9093 Arrowhead Ct Cincinnati OH 45231",
    "addr:housenumber": "9093",
    "addr:postcode": "45231",
    "addr:street": "Arrowhead Ct",
    "iso:country": "US",
    "sg:address": "9093 Arrowhead Ct",
    "sg:city": "Cincinnati",
    "sg:classifiers": [
      {
        "category": "Professional",
        "subcategory": "Business Services",
        "type": "Services"
      }
    ],
    "sg:phone": "+1 513 729 3009",
    "sg:postcode": "45231",
    "sg:province": "OH",
    "sg:tags": [
      "transcribing",
      "disc"
    ],
    "wof:name": "Clerical Plus",
    "wof:placetype": "venue"
  },
  "geometry": {"coordinates":[-84.501797,39.229681],"type":"Point"}
}
