{
  "type": "Feature",
  "properties": {
    "addr:full": "31767 Co Rd 20 Brinkhaven OH 43843",
    "addr:housenumber": "31767;20",
    "addr:postcode": "43843",
    "addr:street": "Co Rd;Brinkhaven",
    "iso:country": "US",
    "sg:address": "31767 Co Rd 20",
    "sg:city": "Brinkhaven",
    "sg:classifiers": [
      {
        "category": "Government",
        "subcategory": "Office",
        "type": "Public Place"
      }
    ],
    "sg:phone": "+1 740 824 3684",
    "sg:postcode": "43843",
    "sg:province": "OH",
    "sg:tags": [
      "village"
    ],
    "wof:name": "Tiverton Township Trustees",
    "wof:placetype": "venue"
  },
  "geometry": {"coordinates":[-82.120458,40.417474],"type":"Point"}
}
