{
  "type": "Feature",
  "properties": {
    "addr:full": "19213 Co Rd T Napoleon OH 43545",
    "addr:housenumber": "19213",
    "addr:postcode": "43545",
    "addr:street": "Co Rd",
    "iso:country": "US",
    "sg:address": "19213 Co Rd T",
    "sg:city": "Napoleon",
    "sg:classifiers": [
      {
        "category": "Manufacturing",
        "subcategory": "Tools \u0026 Machinery",
        "type": "Manufacturing \u0026 Wholesale Goods"
      }
    ],
    "sg:phone": "+1 419 267 3460",
    "sg:postcode": "43545",
    "sg:province": "OH",
    "sg:tags": [
      "shop",
      "repair",
      "industrial",
      "sheet",
      "mfg",
      "metal",
      "machine",
      "welding"
    ],
    "wof:name": "Daves Machine \u0026 Repair",
    "wof:placetype": "venue"
  },
  "geometry": {"coordinates":[-84.232787,41.442266],"type":"Point"}
}
