{
  "type": "Feature",
  "properties": {
    "iso:country":"US",
    "sg:address":"19213 Co Rd T",
    "sg:city":"Napoleon",
    "sg:classifiers":[
        {
            "category":"Manufacturing",
            "subcategory":"Tools & Machinery",
            "type":"Manufacturing & Wholesale Goods"
        }
    ],
    "sg:phone":"+1 419 267 3460",
    "sg:postcode":"43545",
    "sg:province":"OH",
    "sg:tags":[
        "shop",
        "repair",
        "industrial",
        "sheet",
        "mfg",
        "metal",
        "machine",
        "welding"
    ],
    "wof:name":"Daves Machine & Repair",
    "wof:placetype":"venue"
},
  "geometry": {"coordinates":[-84.232787,41.442266],"type":"Point"}
}