{
  "type": "Feature",
  "properties": {
    "iso:country":"US",
    "sg:address":"5201 Northfield Rd",
    "sg:city":"Bedford",
    "sg:classifiers":[
        {
            "category":"Retail",
            "subcategory":"Auto Repair",
            "type":"Services"
        }
    ],
    "sg:phone":"+1 216 475 2222",
    "sg:postcode":"44146",
    "sg:province":"OH",
    "sg:tags":[
        "general"
    ],
    "wof:name":"Midas Muffler",
    "wof:placetype":"venue"
},
  "geometry": {"coordinates":[-81.52729100000001,41.419621],"type":"Point"}
}