{
  "type": "Feature",
  "properties": {
    "addr:full":"105 W Main St Hebron OH 43025",
    "addr:housenumber":"105",
    "addr:postcode":"43025",
    "addr:street":"W Main St",
    "iso:country":"US",
    "sg:address":"105 W Main St",
    "sg:city":"Hebron",
    "sg:classifiers":[
        {
            "category":"Education",
            "subcategory":"Special Training",
            "type":"Public Place"
        }
    ],
    "sg:phone":"+1 740 929 1065",
    "sg:postcode":"43025",
    "sg:province":"OH",
    "sg:tags":[
        "instruction",
        "driving"
    ],
    "wof:name":"Quad County Driving Academy",
    "wof:placetype":"venue"
},
  "geometry": {"coordinates":[-82.500839,39.960101],"type":"Point"}
}