{
  "type": "Feature",
  "properties": {
    "addr:full":"4473 Ackerly Farm Rd New Albany OH 43054",
    "addr:housenumber":"4473",
    "addr:postcode":"43054",
    "addr:street":"Ackerly Farm Rd",
    "iso:country":"US",
    "sg:address":"4473 Ackerly Farm Rd",
    "sg:city":"New Albany",
    "sg:classifiers":[
        {
            "category":"Shopping",
            "subcategory":"Hobbies, Toys, & Games",
            "type":"Retail Goods"
        }
    ],
    "sg:phone":"+1 614 933 9158",
    "sg:postcode":"43054",
    "sg:province":"OH",
    "wof:name":"Grannys Place",
    "wof:placetype":"venue"
},
  "geometry": {"coordinates":[-82.81459599999999,40.075019],"type":"Point"}
}