{
  "type": "Feature",
  "properties": {
    "addr:full": "276 W Bagley Rd Berea OH 44017",
    "addr:housenumber": "276",
    "addr:postcode": "44017",
    "addr:street": "W Bagley Rd",
    "iso:country": "US",
    "sg:address": "276 W Bagley Rd",
    "sg:city": "Berea",
    "sg:classifiers": [
      {
        "category": "Health Services",
        "subcategory": "Doctor",
        "type": "Services"
      }
    ],
    "sg:phone": "+1 440 816 1888",
    "sg:postcode": "44017",
    "sg:province": "OH",
    "sg:tags": [
      "physician",
      "surgeon",
      "medical"
    ],
    "wof:name": "Patient First",
    "wof:placetype": "venue"
  },
  "geometry": {"coordinates":[-81.86492,41.372488],"type":"Point"}
}
