{
  "type": "Feature",
  "properties": {
    "iso:country":"US",
    "sg:address":"315 High St",
    "sg:city":"Hamilton",
    "sg:classifiers":[
        {
            "category":"Government",
            "subcategory":"Office",
            "type":"Public Place"
        }
    ],
    "sg:phone":"+1 513 887 3352",
    "sg:postcode":"45011",
    "sg:province":"OH",
    "wof:name":"Butler County Domestic Vlnce",
    "wof:placetype":"venue"
},
  "geometry": {"coordinates":[-84.558787,39.398861],"type":"Point"}
}