{
  "type": "Feature",
  "properties": {
    "iso:country":"US",
    "sg:address":"236 Front Ave SW",
    "sg:city":"New Philadelphia",
    "sg:classifiers":[
        {
            "category":"Professional",
            "subcategory":"Management & Consulting",
            "type":"Services"
        }
    ],
    "sg:phone":"+1 330 339 8770",
    "sg:postcode":"44663",
    "sg:province":"OH",
    "sg:tags":[
        "consultant",
        "energy",
        "conservation"
    ],
    "wof:name":"Energy Assistance",
    "wof:placetype":"venue"
},
  "geometry": {"coordinates":[-81.45036,40.488516],"type":"Point"}
}