{
  "type": "Feature",
  "properties": {
    "iso:country":"US",
    "sg:address":"418 Howard St",
    "sg:city":"Bridgeport",
    "sg:classifiers":[
        {
            "category":"Communications",
            "subcategory":"Film & Video Production",
            "type":"Services"
        }
    ],
    "sg:phone":"+1 740 633 3045",
    "sg:postcode":"43912",
    "sg:province":"OH",
    "sg:tags":[
        "editing",
        "tape"
    ],
    "wof:name":"Memory Lane Family Tree Video",
    "wof:placetype":"venue"
},
  "geometry": {"coordinates":[-80.745537,40.070082],"type":"Point"}
}