{
  "type": "Feature",
  "properties": {
    "addr:full": "7200 Frash Rd Malta OH 43758",
    "addr:housenumber": "7200",
    "addr:postcode": "43758",
    "addr:street": "Frash Rd",
    "iso:country": "US",
    "sg:address": "7200 Frash Rd",
    "sg:city": "Malta",
    "sg:classifiers": [
      {
        "category": "Freight",
        "type": "Transportation"
      }
    ],
    "sg:phone": "+1 740 962 4120",
    "sg:postcode": "43758",
    "sg:province": "OH",
    "sg:tags": [
      "operator",
      "local",
      "trucking"
    ],
    "wof:name": "Charles E Brown Trucking Inc",
    "wof:placetype": "venue"
  },
  "geometry": {"coordinates":[-81.960293,39.705642],"type":"Point"}
}
