{
  "type": "Feature",
  "properties": {
    "iso:country":"US",
    "sg:address":"1337 Bates Ave",
    "sg:city":"Cincinnati",
    "sg:classifiers":[
        {
            "category":"Manufacturing",
            "subcategory":"Tools & Machinery",
            "type":"Manufacturing & Wholesale Goods"
        }
    ],
    "sg:phone":"+1 513 541 1042",
    "sg:postcode":"45225",
    "sg:province":"OH",
    "sg:tags":[
        "machine",
        "shop"
    ],
    "wof:name":"Lambert Bros Nutangs",
    "wof:placetype":"venue"
},
  "geometry": {"coordinates":[-84.54082099999999,39.140967],"type":"Point"}
}