{
  "type": "Feature",
  "properties": {
    "iso:country":"US",
    "sg:address":"5225 South Ave",
    "sg:city":"Youngstown",
    "sg:classifiers":[
        {
            "category":"Food & Beverages",
            "subcategory":"Specialty",
            "type":"Retail Goods"
        }
    ],
    "sg:phone":"+1 330 781 1990",
    "sg:postcode":"44512",
    "sg:province":"OH",
    "sg:tags":[
        "gourmet",
        "shop"
    ],
    "wof:name":"Peppers Gourmet Foods",
    "wof:placetype":"venue"
},
  "geometry": {"coordinates":[-80.634852,41.04704],"type":"Point"}
}