{
  "type": "Feature",
  "properties": {
    "iso:country":"US",
    "sg:address":"4640 Hinckley Industrial Pkwy",
    "sg:city":"Cleveland",
    "sg:classifiers":[
        {
            "category":"Health Services",
            "subcategory":"Medical Lab",
            "type":"Services"
        }
    ],
    "sg:phone":"+1 216 739 9599",
    "sg:postcode":"44109",
    "sg:province":"OH",
    "sg:tags":[
        "x"
    ],
    "sg:website":"www.merryxray.com",
    "wof:name":"Merry X Ray",
    "wof:placetype":"venue"
},
  "geometry": {"coordinates":[-81.679894,41.42765],"type":"Point"}
}