{
  "type": "Feature",
  "properties": {
    "iso:country":"US",
    "sg:address":"6525 Drake Rd",
    "sg:city":"Cincinnati",
    "sg:classifiers":[
        {
            "category":"Government",
            "subcategory":"Office",
            "type":"Public Place"
        }
    ],
    "sg:phone":"+1 513 561 6500",
    "sg:postcode":"45243",
    "sg:province":"OH",
    "sg:tags":[
        "executive"
    ],
    "wof:name":"Village of Indian Hill",
    "wof:placetype":"venue"
},
  "geometry": {"coordinates":[-84.344891,39.186868],"type":"Point"}
}