{
  "type": "Feature",
  "properties": {
    "addr:full": "5383 Rd 87 Haviland OH 45880",
    "addr:housenumber": "5383",
    "addr:postcode": "45880",
    "addr:street": "Rd 87",
    "iso:country": "US",
    "sg:address": "5383 Rd 87",
    "sg:city": "Haviland",
    "sg:classifiers": [
      {
        "category": "Utilities",
        "subcategory": "Fuel Oil \u0026 Lpg",
        "type": "Services"
      }
    ],
    "sg:phone": "+1 419 399 4590",
    "sg:postcode": "45880",
    "sg:province": "OH",
    "sg:tags": [
      "liquefied",
      "gas",
      "petroleum"
    ],
    "wof:name": "Anchor Propane",
    "wof:placetype": "venue"
  },
  "geometry": {"coordinates":[-84.630811,41.047906],"type":"Point"}
}
