{
  "type": "Feature",
  "properties": {
    "addr:full": "2942 Jonrose Ave Cincinnati OH 45239",
    "addr:housenumber": "2942",
    "addr:postcode": "45239",
    "addr:street": "Jonrose Ave",
    "iso:country": "US",
    "sg:address": "2942 Jonrose Ave",
    "sg:city": "Cincinnati",
    "sg:classifiers": [
      {
        "category": "Building \u0026 Trades",
        "subcategory": "Plumbing",
        "type": "Services"
      }
    ],
    "sg:phone": "+1 513 923 1234",
    "sg:postcode": "45239",
    "sg:province": "OH",
    "sg:tags": [
      "plumbing",
      "contractor"
    ],
    "wof:name": "Jim Eckhoff Plumbing",
    "wof:placetype": "venue"
  },
  "geometry": {"coordinates":[-84.582293,39.21269],"type":"Point"}
}
