{
  "type": "Feature",
  "properties": {
    "iso:country":"US",
    "sg:address":"2942 Jonrose Ave",
    "sg:city":"Cincinnati",
    "sg:classifiers":[
        {
            "category":"Building & Trades",
            "subcategory":"Plumbing",
            "type":"Services"
        }
    ],
    "sg:phone":"+1 513 923 1234",
    "sg:postcode":"45239",
    "sg:province":"OH",
    "sg:tags":[
        "plumbing",
        "contractor"
    ],
    "wof:name":"Jim Eckhoff Plumbing",
    "wof:placetype":"venue"
},
  "geometry": {"coordinates":[-84.58229300000001,39.21269],"type":"Point"}
}