{
  "type": "Feature",
  "properties": {
    "addr:full": "197 Greentree Dr Saint Clairsville OH 43950",
    "addr:housenumber": "197",
    "addr:postcode": "43950",
    "addr:street": "Greentree Dr Saint Clairsville",
    "iso:country": "US",
    "sg:address": "197 Greentree Dr",
    "sg:city": "Saint Clairsville",
    "sg:classifiers": [
      {
        "category": "Shopping",
        "subcategory": "Bicycles \u0026 Sporting Goods",
        "type": "Retail Goods"
      }
    ],
    "sg:phone": "+1 740 695 1255",
    "sg:postcode": "43950",
    "sg:province": "OH",
    "sg:tags": [
      "a",
      "school",
      "driving",
      "operates"
    ],
    "wof:name": "Swan Driving School",
    "wof:placetype": "venue"
  },
  "geometry": {"coordinates":[-80.891326,40.085912],"type":"Point"}
}
