{
  "type": "Feature",
  "properties": {
    "iso:country":"US",
    "sg:address":"313 N State St",
    "sg:city":"Girard",
    "sg:classifiers":[
        {
            "category":"Wholesale",
            "subcategory":"Auto Parts",
            "type":"Manufacturing & Wholesale Goods"
        }
    ],
    "sg:phone":"+1 330 545 9717",
    "sg:postcode":"44420",
    "sg:province":"OH",
    "sg:tags":[
        "equipment",
        "truck"
    ],
    "sg:website":"www.commtruck.com",
    "wof:name":"Commercial Truck & Trailer Inc",
    "wof:placetype":"venue"
},
  "geometry": {"coordinates":[-80.70209199999999,41.157817],"type":"Point"}
}