{
  "type": "Feature",
  "properties": {
    "addr:full": "313 N State St Girard OH 44420",
    "addr:housenumber": "313",
    "addr:postcode": "44420",
    "addr:street": "N State St",
    "iso:country": "US",
    "sg:address": "313 N State St",
    "sg:city": "Girard",
    "sg:classifiers": [
      {
        "category": "Wholesale",
        "subcategory": "Auto Parts",
        "type": "Manufacturing \u0026 Wholesale Goods"
      }
    ],
    "sg:phone": "+1 330 545 9717",
    "sg:postcode": "44420",
    "sg:province": "OH",
    "sg:tags": [
      "equipment",
      "truck"
    ],
    "sg:website": "www.commtruck.com",
    "wof:name": "Commercial Truck \u0026 Trailer Inc",
    "wof:placetype": "venue"
  },
  "geometry": {"coordinates":[-80.702092,41.157817],"type":"Point"}
}
