{
  "type": "Feature",
  "properties": {
    "addr:full": "11396 Locust St S Canal Fulton OH 44614",
    "addr:housenumber": "11396",
    "addr:postcode": "44614",
    "addr:street": "Locust St S",
    "iso:country": "US",
    "sg:address": "11396 Locust St S",
    "sg:city": "Canal Fulton",
    "sg:classifiers": [
      {
        "category": "Autos \u0026 Motor Vehicles",
        "subcategory": "Automobile Sales",
        "type": "Retail Goods"
      }
    ],
    "sg:phone": "+1 330 854 0089",
    "sg:postcode": "44614",
    "sg:province": "OH",
    "sg:tags": [
      "automotive",
      "sales"
    ],
    "wof:name": "Mr Dannys Rentals",
    "wof:placetype": "venue"
  },
  "geometry": {"coordinates":[-81.578881,40.883236],"type":"Point"}
}
