{
  "type": "Feature",
  "properties": {
    "addr:full":"2020 Twp Rd 128 Adena OH 43901",
    "addr:housenumber":"2020;128",
    "addr:postcode":"43901",
    "addr:street":"Twp Rd",
    "iso:country":"US",
    "sg:address":"2020 Twp Rd 128",
    "sg:city":"Adena",
    "sg:classifiers":[
        {
            "category":"Farming",
            "subcategory":"Livestock Farm",
            "type":"Manufacturing & Wholesale Goods"
        }
    ],
    "sg:phone":"+1 740 546 3650",
    "sg:postcode":"43901",
    "sg:province":"OH",
    "sg:tags":[
        "animal",
        "general"
    ],
    "wof:name":"Thomas Lachendro",
    "wof:placetype":"venue"
},
  "geometry": {"coordinates":[-80.87940999999999,40.191061],"type":"Point"}
}