{
  "type": "Feature",
  "properties": {
    "addr:full":"1617 Lake Rockwell Rd Kent OH 44240",
    "addr:housenumber":"1617",
    "addr:postcode":"44240",
    "addr:street":"Lake Rockwell Rd",
    "iso:country":"US",
    "sg:address":"1617 Lake Rockwell Rd",
    "sg:city":"Kent",
    "sg:classifiers":[
        {
            "category":"Manufacturing",
            "subcategory":"Food",
            "type":"Manufacturing & Wholesale Goods"
        }
    ],
    "sg:phone":"+1 330 673 6433",
    "sg:postcode":"44240",
    "sg:province":"OH",
    "sg:tags":[
        "shop",
        "mill",
        "fruit",
        "cider",
        "gift"
    ],
    "wof:name":"Beckwith Orchards Inc",
    "wof:placetype":"venue"
},
  "geometry": {"coordinates":[-81.324118,41.170289],"type":"Point"}
}