{
  "type": "Feature",
  "properties": {
    "iso:country":"US",
    "sg:address":"180 S Stanfield Rd",
    "sg:city":"Troy",
    "sg:classifiers":[
        {
            "category":"Health Services",
            "subcategory":"Doctor",
            "type":"Services"
        }
    ],
    "sg:phone":"+1 937 335 9020",
    "sg:postcode":"45373",
    "sg:province":"OH",
    "sg:tags":[
        "physician",
        "surgeon"
    ],
    "wof:name":"Todd Gould Inc",
    "wof:placetype":"venue"
},
  "geometry": {"coordinates":[-84.240613,40.051466],"type":"Point"}
}