{
  "type": "Feature",
  "properties": {
    "addr:full": "37747 Co Rd 41 Warsaw OH 43844",
    "addr:housenumber": "37747;41",
    "addr:postcode": "43844",
    "addr:street": "Co Rd",
    "iso:country": "US",
    "sg:address": "37747 Co Rd 41",
    "sg:city": "Warsaw",
    "sg:classifiers": [
      {
        "category": "Health Services",
        "subcategory": "Clinic",
        "type": "Services"
      }
    ],
    "sg:phone": "+1 740 824 4693",
    "sg:postcode": "43844",
    "sg:province": "OH",
    "wof:name": "Miracles Inc",
    "wof:placetype": "venue"
  },
  "geometry": {"coordinates":[-82.060032,40.334227],"type":"Point"}
}
