{
  "type": "Feature",
  "properties": {
    "addr:full": "738 Twp Rd 122 SE Junction City OH 43748",
    "addr:housenumber": "738",
    "addr:postcode": "43748",
    "addr:street": "Twp Rd 122 Se",
    "iso:country": "US",
    "sg:address": "738 Twp Rd 122 SE",
    "sg:city": "Junction City",
    "sg:classifiers": [
      {
        "category": "Farming",
        "subcategory": "Livestock Farm",
        "type": "Manufacturing \u0026 Wholesale Goods"
      }
    ],
    "sg:phone": "+1 740 987 5813",
    "sg:postcode": "43748",
    "sg:province": "OH",
    "sg:tags": [
      "beef",
      "feedlot",
      "cattle"
    ],
    "wof:name": "Wyer Farm",
    "wof:placetype": "venue"
  },
  "geometry": {"coordinates":[-82.273016,39.708108],"type":"Point"}
}
