{
  "type": "Feature",
  "properties": {
    "addr:full":"6699 Tri Way Dr Mason OH 45040",
    "addr:housenumber":"6699",
    "addr:postcode":"45040",
    "addr:street":"Tri Way Dr",
    "iso:country":"US",
    "sg:address":"6699 Tri Way Dr",
    "sg:city":"Mason",
    "sg:classifiers":[
        {
            "category":"Health Services",
            "subcategory":"Nursing And Care Facility",
            "type":"Services"
        }
    ],
    "sg:phone":"+1 513 398 8885",
    "sg:postcode":"45040",
    "sg:province":"OH",
    "sg:tags":[
        "home"
    ],
    "wof:name":"Community Concepts & Options",
    "wof:placetype":"venue"
},
  "geometry": {"coordinates":[-84.335161,39.341836],"type":"Point"}
}