{
  "type": "Feature",
  "properties": {
    "addr:full": "963 5th St Struthers OH 44471",
    "addr:housenumber": "963",
    "addr:postcode": "44471",
    "addr:street": "5Th St",
    "iso:country": "US",
    "sg:address": "963 5th St",
    "sg:city": "Struthers",
    "sg:classifiers": [
      {
        "category": "Insurance",
        "subcategory": "Insurance Agent",
        "type": "Services"
      }
    ],
    "sg:phone": "+1 330 755 2955",
    "sg:postcode": "44471",
    "sg:province": "OH",
    "wof:name": "Beas Insurance Agency",
    "wof:placetype": "venue"
  },
  "geometry": {"coordinates":[-80.6035,41.045331],"type":"Point"}
}
