{
  "type": "Feature",
  "properties": {
    "addr:full": "100 N Canton Rd Akron OH 44305",
    "addr:housenumber": "100",
    "addr:postcode": "44305",
    "addr:street": "N Canton Rd",
    "iso:country": "US",
    "sg:address": "100 N Canton Rd",
    "sg:city": "Akron",
    "sg:classifiers": [
      {
        "category": "Retail",
        "subcategory": "Car Wash",
        "type": "Services"
      }
    ],
    "sg:phone": "+1 330 733 1309",
    "sg:postcode": "44305",
    "sg:province": "OH",
    "sg:tags": [
      "automobile",
      "detail",
      "clean"
    ],
    "wof:name": "J M Quality Scrub",
    "wof:placetype": "venue"
  },
  "geometry": {"coordinates":[-81.442253,41.068287],"type":"Point"}
}
