{
  "type": "Feature",
  "properties": {
    "addr:full":"23490 Rd H Continental OH 45831",
    "addr:postcode":"23490;45831",
    "addr:street":"Rd",
    "iso:country":"US",
    "sg:address":"23490 Rd H",
    "sg:city":"Continental",
    "sg:classifiers":[
        {
            "category":"Retail",
            "subcategory":"Laundry & Dry Cleaning",
            "type":"Services"
        }
    ],
    "sg:phone":"+1 419 596 4477",
    "sg:postcode":"45831",
    "sg:province":"OH",
    "sg:tags":[
        "cleaners",
        "rug",
        "carpet"
    ],
    "wof:name":"All Seasons Carpet Cleaners",
    "wof:placetype":"venue"
},
  "geometry": {"coordinates":[-84.322439,41.063684],"type":"Point"}
}