{
  "type": "Feature",
  "properties": {
    "addr:full": "660 N Main St Akron OH 44310",
    "addr:housenumber": "660",
    "addr:postcode": "44310",
    "addr:street": "N Main St",
    "iso:country": "US",
    "sg:address": "660 N Main St",
    "sg:city": "Akron",
    "sg:classifiers": [
      {
        "category": "Wholesale",
        "subcategory": "Electrical",
        "type": "Manufacturing \u0026 Wholesale Goods"
      }
    ],
    "sg:phone": "+1 330 535 7894",
    "sg:postcode": "44310",
    "sg:province": "OH",
    "sg:tags": [
      "household",
      "appliance"
    ],
    "wof:name": "Home Appliance Parts",
    "wof:placetype": "venue"
  },
  "geometry": {"coordinates":[-81.510947,41.103544],"type":"Point"}
}
