{
  "type": "Feature",
  "properties": {
    "iso:country":"US",
    "sg:address":"660 N Main St",
    "sg:city":"Akron",
    "sg:classifiers":[
        {
            "category":"Wholesale",
            "subcategory":"Electrical",
            "type":"Manufacturing & Wholesale Goods"
        }
    ],
    "sg:phone":"+1 330 535 7894",
    "sg:postcode":"44310",
    "sg:province":"OH",
    "sg:tags":[
        "household",
        "appliance"
    ],
    "wof:name":"Home Appliance Parts",
    "wof:placetype":"venue"
},
  "geometry": {"coordinates":[-81.510947,41.103544],"type":"Point"}
}