{
  "type": "Feature",
  "properties": {
    "addr:full": "210 Stolle Ave Sidney OH 45365",
    "addr:housenumber": "210",
    "addr:postcode": "45365",
    "addr:street": "Stolle Ave",
    "iso:country": "US",
    "sg:address": "210 Stolle Ave",
    "sg:city": "Sidney",
    "sg:classifiers": [
      {
        "category": "Freight",
        "type": "Transportation"
      }
    ],
    "sg:phone": "+1 937 492 7225",
    "sg:postcode": "45365",
    "sg:province": "OH",
    "sg:tags": [
      "trucking"
    ],
    "wof:name": "TNT Logistics",
    "wof:placetype": "venue"
  },
  "geometry": {"coordinates":[-84.196358,40.287401],"type":"Point"}
}
