{
  "type": "Feature",
  "properties": {
    "addr:full":"505 E Stroop Rd Dayton OH 45429",
    "addr:housenumber":"505",
    "addr:postcode":"45429",
    "addr:street":"E Stroop Rd",
    "iso:country":"US",
    "sg:address":"505 E Stroop Rd",
    "sg:city":"Dayton",
    "sg:classifiers":[
        {
            "category":"Insurance",
            "subcategory":"Insurance Agent",
            "type":"Services"
        }
    ],
    "sg:phone":"+1 937 229 2299",
    "sg:postcode":"45429",
    "sg:province":"OH",
    "wof:name":"Thomas A Smith CLU Insura",
    "wof:placetype":"venue"
},
  "geometry": {"coordinates":[-84.160903,39.689426],"type":"Point"}
}