{
  "type": "Feature",
  "properties": {
    "addr:full":"100 Memorial Ave Kenton OH 43326",
    "addr:housenumber":"100",
    "addr:postcode":"43326",
    "addr:street":"Memorial Ave",
    "iso:country":"US",
    "sg:address":"100 Memorial Ave",
    "sg:city":"Kenton",
    "sg:classifiers":[
        {
            "category":"Social Services",
            "type":"Services"
        }
    ],
    "sg:phone":"+1 419 673 1482",
    "sg:postcode":"43326",
    "sg:province":"OH",
    "sg:tags":[
        "care",
        "center",
        "day"
    ],
    "wof:name":"Wilkinson-Mcvitty-Berlien",
    "wof:placetype":"venue"
},
  "geometry": {"coordinates":[-83.59657300000001,40.646923],"type":"Point"}
}