{
  "type": "Feature",
  "properties": {
    "addr:full":"115 E Dow St Tipp City OH 45371",
    "addr:housenumber":"115",
    "addr:postcode":"45371",
    "addr:street":"E Dow St",
    "iso:country":"US",
    "sg:address":"115 E Dow St",
    "sg:city":"Tipp City",
    "sg:classifiers":[
        {
            "category":"Food & Beverages",
            "subcategory":"Groceries & Convenience Stores",
            "type":"Retail Goods"
        }
    ],
    "sg:phone":"+1 937 667 1000",
    "sg:postcode":"45371",
    "sg:province":"OH",
    "wof:name":"Town & Country",
    "wof:placetype":"venue"
},
  "geometry": {"coordinates":[-84.168706,39.960341],"type":"Point"}
}