{
  "type": "Feature",
  "properties": {
    "iso:country":"US",
    "sg:address":"1209 Hill Rd N",
    "sg:city":"Pickerington",
    "sg:classifiers":[
        {
            "category":"Real Estate",
            "subcategory":"Real Estate Agent",
            "type":"Services"
        }
    ],
    "sg:phone":"+1 614 322 2715",
    "sg:postcode":"43147",
    "sg:province":"OH",
    "wof:name":"Gary Albosta Real Estate",
    "wof:placetype":"venue"
},
  "geometry": {"coordinates":[-82.779904,39.914166],"type":"Point"}
}