{
  "type": "Feature",
  "properties": {
    "addr:full":"38 E Water St Chillicothe OH 45601",
    "addr:housenumber":"38",
    "addr:postcode":"45601",
    "addr:street":"E Water St",
    "iso:country":"US",
    "sg:address":"38 E Water St",
    "sg:city":"Chillicothe",
    "sg:classifiers":[
        {
            "category":"Restaurant",
            "type":"Food & Drink"
        }
    ],
    "sg:phone":"+1 740 773 6365",
    "sg:postcode":"45601",
    "sg:province":"OH",
    "sg:tags":[
        "property",
        "management",
        "fast"
    ],
    "wof:name":"Burger King",
    "wof:placetype":"venue"
},
  "geometry": {"coordinates":[-82.9807,39.336059],"type":"Point"}
}