{
  "type": "Feature",
  "properties": {
    "iso:country":"US",
    "sg:address":"3928 State Rte 131",
    "sg:city":"Fayetteville",
    "sg:classifiers":[
        {
            "category":"Building & Trades",
            "subcategory":"Landscaping Services",
            "type":"Services"
        }
    ],
    "sg:phone":"+1 513 875 3979",
    "sg:postcode":"45118",
    "sg:province":"OH",
    "sg:tags":[
        "lawn",
        "maintenance",
        "grounds"
    ],
    "wof:name":"Burdette Lawn Maintenance Inc",
    "wof:placetype":"venue"
},
  "geometry": {"coordinates":[-83.919737,39.156837],"type":"Point"}
}