{
  "type": "Feature",
  "properties": {
    "addr:full":"5828 Manchester Ave NW North Lawrence OH 44666",
    "addr:housenumber":"5828",
    "addr:postcode":"44666",
    "addr:street":"Manchester Ave Nw North",
    "iso:country":"US",
    "sg:address":"5828 Manchester Ave NW",
    "sg:city":"North Lawrence",
    "sg:classifiers":[
        {
            "category":"Government",
            "subcategory":"Office",
            "type":"Public Place"
        }
    ],
    "sg:phone":"+1 330 854 3830",
    "sg:postcode":"44666",
    "sg:province":"OH",
    "sg:tags":[
        "village"
    ],
    "wof:name":"Lawrence Twp Trustees Office",
    "wof:placetype":"venue"
},
  "geometry": {"coordinates":[-81.603458,40.861978],"type":"Point"}
}