{
  "type": "Feature",
  "properties": {
    "addr:full": "2258 Leelanau Ave Cincinnati OH 45215",
    "addr:housenumber": "2258",
    "addr:postcode": "45215",
    "addr:street": "Leelanau Ave",
    "iso:country": "US",
    "sg:address": "2258 Leelanau Ave",
    "sg:city": "Cincinnati",
    "sg:classifiers": [
      {
        "category": "Building \u0026 Trades",
        "subcategory": "Construction",
        "type": "Services"
      }
    ],
    "sg:phone": "+1 513 769 3261",
    "sg:postcode": "45215",
    "sg:province": "OH",
    "sg:tags": [
      "concrete",
      "contractor"
    ],
    "sg:website": "http://www.ypad.com/business-profile.cfm/state/OH/city/Reading/ppid/11125",
    "wof:name": "Cincinnati Concrete Solutions",
    "wof:placetype": "venue"
  },
  "geometry": {"coordinates":[-84.424157,39.225103],"type":"Point"}
}
