{
  "type": "Feature",
  "properties": {
    "addr:full": "14585 Rainbow Lake Rd Shade OH 45776",
    "addr:housenumber": "14585",
    "addr:postcode": "45776",
    "addr:street": "Rainbow Lake Rd",
    "iso:country": "US",
    "sg:address": "14585 Rainbow Lake Rd",
    "sg:city": "Shade",
    "sg:classifiers": [
      {
        "category": "Building \u0026 Trades",
        "subcategory": "Landscaping Services",
        "type": "Services"
      }
    ],
    "sg:phone": "+1 740 696 1376",
    "sg:postcode": "45776",
    "sg:province": "OH",
    "wof:name": "Michael ONeil",
    "wof:placetype": "venue"
  },
  "geometry": {"coordinates":[-82.028512,39.193954],"type":"Point"}
}
