{
  "type": "Feature",
  "properties": {
    "iso:country":"US",
    "sg:address":"17800 Chillicothe Rd",
    "sg:city":"Chagrin Falls",
    "sg:classifiers":[
        {
            "category":"Manufacturing",
            "subcategory":"Chemicals & Compounds",
            "type":"Manufacturing & Wholesale Goods"
        },
        {
            "category":"Manufacturing",
            "subcategory":"Tools & Machinery",
            "type":"Manufacturing & Wholesale Goods"
        }
    ],
    "sg:phone":"+1 440 543 1234",
    "sg:postcode":"44023",
    "sg:province":"OH",
    "sg:tags":[
        "treating",
        "industrial",
        "mfg",
        "metal",
        "equipment",
        "heat"
    ],
    "wof:name":"Surface Combustion Inc",
    "wof:placetype":"venue"
},
  "geometry": {"coordinates":[-81.339356,41.381753],"type":"Point"}
}