{
  "type": "Feature",
  "properties": {
    "addr:full": "4766 River Rd Cincinnati OH 45233",
    "addr:housenumber": "4766",
    "addr:postcode": "45233",
    "addr:street": "River Rd",
    "iso:country": "US",
    "sg:address": "4766 River Rd",
    "sg:city": "Cincinnati",
    "sg:classifiers": [
      {
        "category": "Professional",
        "subcategory": "Printing \u0026 Photocopies",
        "type": "Services"
      }
    ],
    "sg:phone": "+1 513 251 2911",
    "sg:postcode": "45233",
    "sg:province": "OH",
    "sg:website": "www.kahny.com",
    "wof:name": "Kahny Printg Inc",
    "wof:placetype": "venue"
  },
  "geometry": {"coordinates":[-84.643402,39.098],"type":"Point"}
}
