{
  "type": "Feature",
  "properties": {
    "addr:full":"2411 Van Buren Ave Springfield OH 45505",
    "addr:housenumber":"2411",
    "addr:postcode":"45505",
    "addr:street":"Van Buren Ave",
    "iso:country":"US",
    "sg:address":"2411 Van Buren Ave",
    "sg:city":"Springfield",
    "sg:classifiers":[
        {
            "category":"Government",
            "subcategory":"Office",
            "type":"Public Place"
        }
    ],
    "sg:phone":"+1 937 328 2675",
    "sg:postcode":"45505",
    "sg:province":"OH",
    "sg:tags":[
        "county"
    ],
    "wof:name":"Clark County Board Mrdd",
    "wof:placetype":"venue"
},
  "geometry": {"coordinates":[-83.772021,39.914348],"type":"Point"}
}