{
  "type": "Feature",
  "properties": {
    "addr:full":"12776 Deshler Rd North Baltimore OH 45872",
    "addr:housenumber":"12776",
    "addr:postcode":"45872",
    "addr:street":"Deshler Rd",
    "iso:country":"US",
    "sg:address":"12776 Deshler Rd",
    "sg:city":"North Baltimore",
    "sg:classifiers":[
        {
            "category":"Restaurant",
            "type":"Food & Drink"
        }
    ],
    "sg:menulink":"http://www.allmenus.com/oh/bloom/194914-mcdonalds/menu/",
    "sg:postcode":"45872",
    "sg:province":"OH",
    "sg:tags":[
        "burger",
        "american"
    ],
    "wof:name":"McDonald's",
    "wof:placetype":"venue"
},
  "geometry": {"coordinates":[-83.63773399999999,41.172619],"type":"Point"}
}