{
  "type": "Feature",
  "properties": {
    "addr:full":"1991 Shatzer Rd Shiloh OH 44878",
    "addr:housenumber":"1991",
    "addr:postcode":"44878",
    "addr:street":"Shatzer Rd",
    "iso:country":"US",
    "sg:address":"1991 Shatzer Rd",
    "sg:city":"Shiloh",
    "sg:classifiers":[
        {
            "category":"Shopping",
            "subcategory":"Crafts & Fabrics",
            "type":"Retail Goods"
        }
    ],
    "sg:phone":"+1 419 896 3785",
    "sg:postcode":"44878",
    "sg:province":"OH",
    "sg:tags":[
        "farm",
        "sewing",
        "animal",
        "general"
    ],
    "wof:name":"Country Fabrics",
    "wof:placetype":"venue"
},
  "geometry": {"coordinates":[-82.592383,40.930746],"type":"Point"}
}