{
  "type": "Feature",
  "properties": {
    "iso:country":"US",
    "sg:address":"324 Hess Rd",
    "sg:city":"Washington Ct Hs",
    "sg:classifiers":[
        {
            "category":"Government",
            "subcategory":"Office",
            "type":"Public Place"
        }
    ],
    "sg:phone":"+1 740 335 7282",
    "sg:postcode":"43160",
    "sg:province":"OH",
    "sg:tags":[
        "county",
        "resource"
    ],
    "wof:name":"Fayette County Comm Action",
    "wof:placetype":"venue"
},
  "geometry": {"coordinates":[-83.334621,39.548702],"type":"Point"}
}