{
  "type": "Feature",
  "properties": {
    "iso:country":"US",
    "sg:address":"1131 Steubenville Ave",
    "sg:city":"Cambridge",
    "sg:classifiers":[
        {
            "category":"Government",
            "subcategory":"Office",
            "type":"Public Place"
        }
    ],
    "sg:phone":"+1 740 432 5039",
    "sg:postcode":"43725",
    "sg:province":"OH",
    "sg:tags":[
        "city",
        "taxation"
    ],
    "sg:website":"www.cambridgeoh.org",
    "wof:name":"Cambridge City Auditor",
    "wof:placetype":"venue"
},
  "geometry": {"coordinates":[-81.583716,40.025957],"type":"Point"}
}