{
  "type": "Feature",
  "properties": {
    "addr:full": "209 E Aurora Rd Northfield OH 44067",
    "addr:housenumber": "209",
    "addr:postcode": "44067",
    "addr:street": "E Aurora Rd",
    "iso:country": "US",
    "sg:address": "209 E Aurora Rd",
    "sg:city": "Northfield",
    "sg:classifiers": [
      {
        "category": "Professional",
        "subcategory": "Computer Services",
        "type": "Services"
      }
    ],
    "sg:phone": "+1 330 468 2585",
    "sg:postcode": "44067",
    "sg:province": "OH",
    "sg:tags": [
      "consultant",
      "designer"
    ],
    "wof:name": "Eikons Consulting Inc",
    "wof:placetype": "venue"
  },
  "geometry": {"coordinates":[-81.53206,41.31424],"type":"Point"}
}
