{
  "type": "Feature",
  "properties": {
    "addr:full":"1080 Nimitzview Dr Cincinnati OH 45230",
    "addr:housenumber":"1080",
    "addr:postcode":"45230",
    "addr:street":"Nimitzview Dr",
    "iso:country":"US",
    "sg:address":"1080 Nimitzview Dr",
    "sg:city":"Cincinnati",
    "sg:classifiers":[
        {
            "category":"Wholesale",
            "subcategory":"Metals & Minerals",
            "type":"Manufacturing & Wholesale Goods"
        }
    ],
    "sg:phone":"+1 513 231 7401",
    "sg:postcode":"45230",
    "sg:province":"OH",
    "wof:name":"Reynolds Consumer Products",
    "wof:placetype":"venue"
},
  "geometry": {"coordinates":[-84.352525,39.069472],"type":"Point"}
}