{
  "type": "Feature",
  "properties": {
    "addr:full": "300 Main St Leetonia OH 44431",
    "addr:housenumber": "300",
    "addr:postcode": "44431",
    "addr:street": "Main St",
    "iso:country": "US",
    "sg:address": "300 Main St",
    "sg:city": "Leetonia",
    "sg:classifiers": [
      {
        "category": "Government",
        "subcategory": "Police Station",
        "type": "Public Place"
      }
    ],
    "sg:phone": "+1 330 427 6731",
    "sg:postcode": "44431",
    "sg:province": "OH",
    "sg:tags": [
      "department"
    ],
    "wof:name": "Leetonia Police Dept",
    "wof:placetype": "venue"
  },
  "geometry": {"coordinates":[-80.755344,40.879029],"type":"Point"}
}
