{
  "type": "Feature",
  "properties": {
    "iso:country":"US",
    "sg:address":"51 Hamilton Ave",
    "sg:city":"Youngstown",
    "sg:classifiers":[
        {
            "category":"Shopping",
            "subcategory":"Gifts & Souvenirs",
            "type":"Retail Goods"
        }
    ],
    "sg:phone":"+1 330 757 0614",
    "sg:postcode":"44514",
    "sg:province":"OH",
    "sg:tags":[
        "collectible"
    ],
    "wof:name":"Roycass Limited",
    "wof:placetype":"venue"
},
  "geometry": {"coordinates":[-80.612808,41.036184],"type":"Point"}
}