{
  "type": "Feature",
  "properties": {
    "iso:country":"US",
    "sg:address":"4400 Daleview Ave",
    "sg:city":"Dayton",
    "sg:classifiers":[
        {
            "category":"Real Estate",
            "subcategory":"Real Estate Agent",
            "type":"Services"
        }
    ],
    "sg:phone":"+1 937 275 9206",
    "sg:postcode":"45405",
    "sg:province":"OH",
    "sg:tags":[
        "property",
        "management"
    ],
    "wof:name":"Sundance Property Mgt Inc",
    "wof:placetype":"venue"
},
  "geometry": {"coordinates":[-84.21560599999999,39.805534],"type":"Point"}
}