{
  "type": "Feature",
  "properties": {
    "iso:country":"US",
    "sg:address":"5820 Sullivant Ave",
    "sg:city":"Galloway",
    "sg:classifiers":[
        {
            "category":"Government",
            "subcategory":"Post Office",
            "type":"Public Place"
        }
    ],
    "sg:phone":"+1 614 000 1111",
    "sg:postcode":"43119",
    "sg:province":"OH",
    "wof:name":"US Post Office",
    "wof:placetype":"venue"
},
  "geometry": {"coordinates":[-83.153633,39.941842],"type":"Point"}
}