{
  "type": "Feature",
  "properties": {
    "addr:full": "14480 Quail Ridge Dr Cleveland OH 44133",
    "addr:housenumber": "14480",
    "addr:postcode": "44133",
    "addr:street": "Quail Ridge Dr",
    "iso:country": "US",
    "sg:address": "14480 Quail Ridge Dr",
    "sg:city": "Cleveland",
    "sg:classifiers": [
      {
        "category": "Real Estate",
        "subcategory": "Real Estate Operator",
        "type": "Services"
      }
    ],
    "sg:phone": "+1 216 408 1725",
    "sg:postcode": "44133",
    "sg:province": "OH",
    "sg:tags": [
      "condominium"
    ],
    "wof:name": "Quail Ridge Condominiums",
    "wof:placetype": "venue"
  },
  "geometry": {"coordinates":[-81.776542,41.307638],"type":"Point"}
}
