{
  "type": "Feature",
  "properties": {
    "iso:country":"US",
    "sg:address":"14480 Quail Ridge Dr",
    "sg:city":"Cleveland",
    "sg:classifiers":[
        {
            "category":"Real Estate",
            "subcategory":"Real Estate Operator",
            "type":"Services"
        }
    ],
    "sg:phone":"+1 216 408 1725",
    "sg:postcode":"44133",
    "sg:province":"OH",
    "sg:tags":[
        "condominium"
    ],
    "wof:name":"Quail Ridge Condominiums",
    "wof:placetype":"venue"
},
  "geometry": {"coordinates":[-81.77654200000001,41.307638],"type":"Point"}
}