{
  "type": "Feature",
  "properties": {
    "addr:full": "9541 Morral Kirkpatrick Rd Galion OH 44833",
    "addr:housenumber": "9541",
    "addr:postcode": "44833",
    "addr:street": "Morral Kirkpatrick Rd",
    "iso:country": "US",
    "sg:address": "9541 Morral Kirkpatrick Rd",
    "sg:city": "Galion",
    "sg:classifiers": [
      {
        "category": "Manufacturing",
        "subcategory": "Wood Products",
        "type": "Manufacturing \u0026 Wholesale Goods"
      }
    ],
    "sg:phone": "+1 419 468 9703",
    "sg:postcode": "44833",
    "sg:province": "OH",
    "sg:tags": [
      "mfg"
    ],
    "wof:name": "Cotton Wood Pallet Co",
    "wof:placetype": "venue"
  },
  "geometry": {"coordinates":[-82.909858,40.708373],"type":"Point"}
}
