{
  "type": "Feature",
  "properties": {
    "addr:full":"747 Indiana Ave Toledo OH 43604",
    "addr:housenumber":"747",
    "addr:postcode":"43604",
    "addr:street":"Indiana Ave",
    "iso:country":"US",
    "sg:address":"747 Indiana Ave",
    "sg:city":"Toledo",
    "sg:classifiers":[
        {
            "category":"Shopping",
            "subcategory":"Florist",
            "type":"Retail Goods"
        }
    ],
    "sg:phone":"+1 419 248 2726",
    "sg:postcode":"43604",
    "sg:province":"OH",
    "wof:name":"Boyds Florist",
    "wof:placetype":"venue"
},
  "geometry": {"coordinates":[-83.561679,41.650293],"type":"Point"}
}