{
  "type": "Feature",
  "properties": {
    "addr:full":"1417 Harrisburg Rd NE Canton OH 44705",
    "addr:housenumber":"1417",
    "addr:postcode":"44705",
    "addr:street":"Harrisburg Rd Ne",
    "iso:country":"US",
    "sg:address":"1417 Harrisburg Rd NE",
    "sg:city":"Canton",
    "sg:classifiers":[
        {
            "category":"Real Estate",
            "subcategory":"Real Estate Agent",
            "type":"Services"
        }
    ],
    "sg:phone":"+1 330 454 4277",
    "sg:postcode":"44705",
    "sg:province":"OH",
    "sg:tags":[
        "property",
        "contractor"
    ],
    "wof:name":"A1 Advanced Property Solutions",
    "wof:placetype":"venue"
},
  "geometry": {"coordinates":[-81.34882899999999,40.811582],"type":"Point"}
}