{
  "type": "Feature",
  "properties": {
    "addr:full": "2883 Forest Lake Dr Cleveland OH 44145",
    "addr:housenumber": "2883",
    "addr:postcode": "44145",
    "addr:street": "Forest Lake Dr",
    "iso:country": "US",
    "sg:address": "2883 Forest Lake Dr",
    "sg:city": "Cleveland",
    "sg:classifiers": [
      {
        "category": "Professional",
        "subcategory": "Business Services",
        "type": "Services"
      }
    ],
    "sg:phone": "+1 440 617 9766",
    "sg:postcode": "44145",
    "sg:province": "OH",
    "sg:tags": [
      "organizing"
    ],
    "wof:name": "Garage Storage Concepts",
    "wof:placetype": "venue"
  },
  "geometry": {"coordinates":[-81.966038,41.447258],"type":"Point"}
}
