{
  "type": "Feature",
  "properties": {
    "iso:country":"US",
    "sg:address":"2883 Forest Lake Dr",
    "sg:city":"Cleveland",
    "sg:classifiers":[
        {
            "category":"Professional",
            "subcategory":"Business Services",
            "type":"Services"
        }
    ],
    "sg:phone":"+1 440 617 9766",
    "sg:postcode":"44145",
    "sg:province":"OH",
    "sg:tags":[
        "organizing"
    ],
    "wof:name":"Garage Storage Concepts",
    "wof:placetype":"venue"
},
  "geometry": {"coordinates":[-81.966038,41.447258],"type":"Point"}
}