{
  "type": "Feature",
  "properties": {
    "addr:full": "232 Morgan St Oak Hill OH 45656",
    "addr:housenumber": "232",
    "addr:postcode": "45656",
    "addr:street": "Morgan St",
    "iso:country": "US",
    "sg:address": "232 Morgan St",
    "sg:city": "Oak Hill",
    "sg:classifiers": [
      {
        "category": "Restaurant",
        "type": "Food \u0026 Drink"
      }
    ],
    "sg:phone": "+1 740 682 7771",
    "sg:postcode": "45656",
    "sg:province": "OH",
    "sg:tags": [
      "eating"
    ],
    "wof:name": "Kalis Pizza",
    "wof:placetype": "venue"
  },
  "geometry": {"coordinates":[-82.572083,38.901472],"type":"Point"}
}
