{
  "type": "Feature",
  "properties": {
    "iso:country":"US",
    "sg:address":"232 Morgan St",
    "sg:city":"Oak Hill",
    "sg:classifiers":[
        {
            "category":"Restaurant",
            "type":"Food & Drink"
        }
    ],
    "sg:phone":"+1 740 682 7771",
    "sg:postcode":"45656",
    "sg:province":"OH",
    "sg:tags":[
        "eating"
    ],
    "wof:name":"Kalis Pizza",
    "wof:placetype":"venue"
},
  "geometry": {"coordinates":[-82.57208300000001,38.901472],"type":"Point"}
}