{
  "type": "Feature",
  "properties": {
    "iso:country":"US",
    "sg:address":"3420 Section Rd",
    "sg:city":"Cincinnati",
    "sg:classifiers":[
        {
            "category":"Professional",
            "subcategory":"Engineering",
            "type":"Services"
        }
    ],
    "sg:phone":"+1 513 731 3415",
    "sg:postcode":"45237",
    "sg:province":"OH",
    "sg:tags":[
        "engineer"
    ],
    "wof:name":"Paul H Bluestein & Co",
    "wof:placetype":"venue"
},
  "geometry": {"coordinates":[-84.417007,39.195002],"type":"Point"}
}