{
  "type": "Feature",
  "properties": {
    "addr:full": "319 W Main St Montpelier OH 43543",
    "addr:housenumber": "319",
    "addr:postcode": "43543",
    "addr:street": "W Main St",
    "iso:country": "US",
    "sg:address": "319 W Main St",
    "sg:city": "Montpelier",
    "sg:classifiers": [
      {
        "category": "Manufacturing",
        "subcategory": "Printing",
        "type": "Manufacturing \u0026 Wholesale Goods"
      }
    ],
    "sg:phone": "+1 419 485 5320",
    "sg:postcode": "43543",
    "sg:province": "OH",
    "sg:tags": [
      "print",
      "lithographic",
      "commercial",
      "typesetting"
    ],
    "wof:name": "Quality Printing",
    "wof:placetype": "venue"
  },
  "geometry": {"coordinates":[-84.61052,41.586538],"type":"Point"}
}
