{
  "type": "Feature",
  "properties": {
    "iso:country":"US",
    "sg:address":"319 W Main St",
    "sg:city":"Montpelier",
    "sg:classifiers":[
        {
            "category":"Manufacturing",
            "subcategory":"Printing",
            "type":"Manufacturing & Wholesale Goods"
        }
    ],
    "sg:phone":"+1 419 485 5320",
    "sg:postcode":"43543",
    "sg:province":"OH",
    "sg:tags":[
        "print",
        "lithographic",
        "commercial",
        "typesetting"
    ],
    "wof:name":"Quality Printing",
    "wof:placetype":"venue"
},
  "geometry": {"coordinates":[-84.61051999999999,41.586538],"type":"Point"}
}