{
  "type": "Feature",
  "properties": {
    "addr:full": "6397 Johnston Rd New Washington OH 44854",
    "addr:housenumber": "6397",
    "addr:postcode": "44854",
    "addr:street": "Johnston Rd",
    "iso:country": "US",
    "sg:address": "6397 Johnston Rd",
    "sg:city": "New Washington",
    "sg:phone": "+1 419 347 2528",
    "sg:postcode": "44854",
    "sg:province": "OH",
    "sg:tags": [
      "farm",
      "wheat"
    ],
    "wof:name": "Kraft Farm",
    "wof:placetype": "venue"
  },
  "geometry": {"coordinates":[-82.807473,40.916686],"type":"Point"}
}
