{
  "type": "Feature",
  "properties": {
    "iso:country":"US",
    "sg:address":"2245 State Rte 59",
    "sg:city":"Kent",
    "sg:classifiers":[
        {
            "category":"Shopping",
            "subcategory":"Bicycles & Sporting Goods",
            "type":"Retail Goods"
        }
    ],
    "sg:phone":"+1 330 678 0180",
    "sg:postcode":"44240",
    "sg:province":"OH",
    "sg:tags":[
        "apparel",
        "bowling",
        "accessory"
    ],
    "wof:name":"Ultimate Bowling II",
    "wof:placetype":"venue"
},
  "geometry": {"coordinates":[-81.314734,41.156354],"type":"Point"}
}