{
  "type": "Feature",
  "properties": {
    "iso:country":"US",
    "sg:address":"108 May Dr",
    "sg:city":"Harrison",
    "sg:classifiers":[
        {
            "category":"Wholesale",
            "subcategory":"Machinery & Supplies",
            "type":"Manufacturing & Wholesale Goods"
        }
    ],
    "sg:phone":"+1 513 367 3800",
    "sg:postcode":"45030",
    "sg:province":"IN",
    "sg:tags":[
        "equipment",
        "industrial",
        "repair"
    ],
    "wof:name":"C R S Service Inc",
    "wof:placetype":"venue"
},
  "geometry": {"coordinates":[-84.78634599999999,39.244404],"type":"Point"}
}