{
  "type": "Feature",
  "properties": {
    "addr:full": "1799 Akron Peninsula Rd Akron OH 44313",
    "addr:housenumber": "1799",
    "addr:postcode": "44313",
    "addr:street": "Akron Peninsula Rd",
    "iso:country": "US",
    "sg:address": "1799 Akron Peninsula Rd",
    "sg:city": "Akron",
    "sg:classifiers": [
      {
        "category": "Professional",
        "subcategory": "Lawyer \u0026 Legal Services",
        "type": "Services"
      }
    ],
    "sg:phone": "+1 330 920 9920",
    "sg:postcode": "44313",
    "sg:province": "OH",
    "sg:tags": [
      "attorney"
    ],
    "wof:name": "Cheryl Fischer Law Offices",
    "wof:placetype": "venue"
  },
  "geometry": {"coordinates":[-81.5546,41.143395],"type":"Point"}
}
