{
  "type": "Feature",
  "properties": {
    "iso:country":"US",
    "sg:address":"46 Marco Ln",
    "sg:city":"Dayton",
    "sg:classifiers":[
        {
            "category":"Manufacturing",
            "subcategory":"Electronics",
            "type":"Manufacturing & Wholesale Goods"
        },
        {
            "category":"Manufacturing",
            "subcategory":"Tools & Machinery",
            "type":"Manufacturing & Wholesale Goods"
        }
    ],
    "sg:phone":"+1 937 438 3567",
    "sg:postcode":"45458",
    "sg:province":"OH",
    "sg:tags":[
        "measuring",
        "supply",
        "devices",
        "equipment",
        "controlling",
        "electronic",
        "manufacturer"
    ],
    "sg:website":"www.msdicontrols.com",
    "wof:name":"Micro Systems Development Inc",
    "wof:placetype":"venue"
},
  "geometry": {"coordinates":[-84.156627,39.607507],"type":"Point"}
}