{
  "type": "Feature",
  "properties": {
    "addr:full": "46 Marco Ln Dayton OH 45458",
    "addr:housenumber": "46",
    "addr:postcode": "45458",
    "addr:street": "Marco Ln",
    "iso:country": "US",
    "sg:address": "46 Marco Ln",
    "sg:city": "Dayton",
    "sg:classifiers": [
      {
        "category": "Manufacturing",
        "subcategory": "Electronics",
        "type": "Manufacturing \u0026 Wholesale Goods"
      },
      {
        "category": "Manufacturing",
        "subcategory": "Tools \u0026 Machinery",
        "type": "Manufacturing \u0026 Wholesale Goods"
      }
    ],
    "sg:phone": "+1 937 438 3567",
    "sg:postcode": "45458",
    "sg:province": "OH",
    "sg:tags": [
      "measuring",
      "supply",
      "devices",
      "equipment",
      "controlling",
      "electronic",
      "manufacturer"
    ],
    "sg:website": "www.msdicontrols.com",
    "wof:name": "Micro Systems Development Inc",
    "wof:placetype": "venue"
  },
  "geometry": {"coordinates":[-84.156627,39.607507],"type":"Point"}
}
