{
  "type": "Feature",
  "properties": {
    "iso:country":"US",
    "sg:address":"156 S Coy Rd",
    "sg:city":"Oregon",
    "sg:classifiers":[
        {
            "category":"Travel",
            "subcategory":"Travel Agent",
            "type":"Entertainment"
        }
    ],
    "sg:phone":"+1 419 691 6564",
    "sg:postcode":"43616",
    "sg:province":"OH",
    "sg:tags":[
        "agency"
    ],
    "wof:name":"Falcon Travel",
    "wof:placetype":"venue"
},
  "geometry": {"coordinates":[-83.467648,41.647922],"type":"Point"}
}