{
  "type": "Feature",
  "properties": {
    "iso:country":"US",
    "sg:address":"1351 Lear Industrial Pkwy",
    "sg:city":"Avon",
    "sg:classifiers":[
        {
            "category":"Building & Trades",
            "subcategory":"Plumbing",
            "type":"Services"
        }
    ],
    "sg:phone":"+1 440 933 2330",
    "sg:postcode":"44011",
    "sg:province":"OH",
    "sg:tags":[
        "plumbing",
        "contractor"
    ],
    "wof:name":"Leonard's Plumbing & Heating",
    "wof:placetype":"venue"
},
  "geometry": {"coordinates":[-81.992508,41.471865],"type":"Point"}
}