{
  "type": "Feature",
  "properties": {
    "iso:country":"US",
    "sg:address":"10002 Montgomery Rd",
    "sg:city":"Cincinnati",
    "sg:classifiers":[
        {
            "category":"Home & Garden",
            "subcategory":"Home Furnishings",
            "type":"Retail Goods"
        }
    ],
    "sg:phone":"+1 513 985 0098",
    "sg:postcode":"45242",
    "sg:province":"OH",
    "wof:name":"House of France Ltd",
    "wof:placetype":"venue"
},
  "geometry": {"coordinates":[-84.3491,39.23867],"type":"Point"}
}