{
  "type": "Feature",
  "properties": {
    "addr:full":"222 Washington St Oak Harbor OH 43449",
    "addr:housenumber":"222",
    "addr:postcode":"43449",
    "addr:street":"Washington St",
    "iso:country":"US",
    "sg:address":"222 Washington St",
    "sg:city":"Oak Harbor",
    "sg:classifiers":[
        {
            "category":"Government",
            "subcategory":"Office",
            "type":"Public Place"
        }
    ],
    "sg:phone":"+1 419 898 9366",
    "sg:postcode":"43449",
    "sg:province":"OH",
    "sg:tags":[
        "village"
    ],
    "wof:name":"Oak Harbor Mid County EMS",
    "wof:placetype":"venue"
},
  "geometry": {"coordinates":[-83.14762399999999,41.514525],"type":"Point"}
}