{
  "type": "Feature",
  "properties": {
    "iso:country":"US",
    "sg:address":"2752 Sullivant Ave",
    "sg:city":"Columbus",
    "sg:classifiers":[
        {
            "category":"Professional",
            "type":"Services"
        }
    ],
    "sg:phone":"+1 614 272 8855",
    "sg:postcode":"43204",
    "sg:province":"OH",
    "wof:name":"Vitos Inferno",
    "wof:placetype":"venue"
},
  "geometry": {"coordinates":[-83.073088,39.943784],"type":"Point"}
}