{
  "type": "Feature",
  "properties": {
    "addr:full": "2752 Sullivant Ave Columbus OH 43204",
    "addr:housenumber": "2752",
    "addr:postcode": "43204",
    "addr:street": "Sullivant Ave",
    "iso:country": "US",
    "sg:address": "2752 Sullivant Ave",
    "sg:city": "Columbus",
    "sg:classifiers": [
      {
        "category": "Professional",
        "type": "Services"
      }
    ],
    "sg:phone": "+1 614 272 8855",
    "sg:postcode": "43204",
    "sg:province": "OH",
    "wof:name": "Vitos Inferno",
    "wof:placetype": "venue"
  },
  "geometry": {"coordinates":[-83.073088,39.943784],"type":"Point"}
}
