{
  "type": "Feature",
  "properties": {
    "addr:full": "33605 Aurora Rd Solon OH 44139",
    "addr:housenumber": "33605",
    "addr:postcode": "44139",
    "addr:street": "Aurora Rd",
    "iso:country": "US",
    "sg:address": "33605 Aurora Rd",
    "sg:city": "Solon",
    "sg:classifiers": [
      {
        "category": "Shopping",
        "subcategory": "Stationery \u0026 Office Supplies",
        "type": "Retail Goods"
      }
    ],
    "sg:phone": "+1 440 349 2071",
    "sg:postcode": "44139",
    "sg:province": "OH",
    "sg:tags": [
      "equipment"
    ],
    "wof:name": "Officemax",
    "wof:placetype": "venue"
  },
  "geometry": {"coordinates":[-81.440903,41.385101],"type":"Point"}
}
