{
  "type": "Feature",
  "properties": {
    "iso:country":"US",
    "sg:address":"25415 Brittany Cir",
    "sg:city":"Cleveland",
    "sg:classifiers":[
        {
            "category":"Food & Beverages",
            "subcategory":"Groceries & Convenience Stores",
            "type":"Retail Goods"
        }
    ],
    "sg:phone":"+1 440 250 9966",
    "sg:postcode":"44145",
    "sg:province":"OH",
    "sg:tags":[
        "grocer"
    ],
    "wof:name":"Herbawi Samy",
    "wof:placetype":"venue"
},
  "geometry": {"coordinates":[-81.89940199999999,41.460782],"type":"Point"}
}