{
  "type": "Feature",
  "properties": {
    "addr:full": "27070 Detroit Rd Cleveland OH 44145",
    "addr:housenumber": "27070",
    "addr:postcode": "44145",
    "addr:street": "Detroit Rd",
    "iso:country": "US",
    "sg:address": "27070 Detroit Rd",
    "sg:city": "Cleveland",
    "sg:classifiers": [
      {
        "category": "Utilities",
        "subcategory": "Mobile Phone",
        "type": "Services"
      }
    ],
    "sg:phone": "+1 440 919 2505",
    "sg:postcode": "44145",
    "sg:province": "OH",
    "sg:tags": [
      "telephone",
      "cellular"
    ],
    "wof:name": "Global Cellular \u0026 Paging",
    "wof:placetype": "venue"
  },
  "geometry": {"coordinates":[-81.915639,41.468456],"type":"Point"}
}
