{
  "type": "Feature",
  "properties": {
    "iso:country":"US",
    "sg:address":"3128 Losantiville Ave",
    "sg:city":"Cincinnati",
    "sg:classifiers":[
        {
            "category":"Professional",
            "subcategory":"Art Services",
            "type":"Services"
        }
    ],
    "sg:phone":"+1 513 731 1859",
    "sg:postcode":"45213",
    "sg:province":"OH",
    "sg:tags":[
        "artist"
    ],
    "wof:name":"Alice Hoover Designs",
    "wof:placetype":"venue"
},
  "geometry": {"coordinates":[-84.429089,39.182404],"type":"Point"}
}