{
  "type": "Feature",
  "properties": {
    "addr:full":"30195 Chagrin Blvd Cleveland OH 44124",
    "addr:housenumber":"30195",
    "addr:postcode":"44124",
    "addr:street":"Chagrin Blvd",
    "iso:country":"US",
    "sg:address":"30195 Chagrin Blvd",
    "sg:city":"Cleveland",
    "sg:classifiers":[
        {
            "category":"Social Services",
            "type":"Services"
        }
    ],
    "sg:phone":"+1 216 755 1005",
    "sg:postcode":"44124",
    "sg:province":"OH",
    "sg:tags":[
        "crisis",
        "intervention"
    ],
    "wof:name":"Suicide Prevention Edu",
    "wof:placetype":"venue"
},
  "geometry": {"coordinates":[-81.456829,41.46021],"type":"Point"}
}