{
  "type": "Feature",
  "properties": {
    "iso:country":"US",
    "sg:address":"1310 Pendleton St",
    "sg:city":"Cincinnati",
    "sg:classifiers":[
        {
            "category":"Professional",
            "subcategory":"Computer Services",
            "type":"Services"
        }
    ],
    "sg:phone":"+1 513 651 9322",
    "sg:postcode":"45202",
    "sg:province":"OH",
    "sg:tags":[
        "website",
        "design"
    ],
    "wof:name":"Pixels & Dots",
    "wof:placetype":"venue"
},
  "geometry": {"coordinates":[-84.50705,39.111187],"type":"Point"}
}