{
  "type": "Feature",
  "properties": {
    "addr:full":"5634 Sunvalley Ln Cincinnati OH 45230",
    "addr:housenumber":"5634",
    "addr:postcode":"45230",
    "addr:street":"Sunvalley Ln",
    "iso:country":"US",
    "sg:address":"5634 Sunvalley Ln",
    "sg:city":"Cincinnati",
    "sg:classifiers":[
        {
            "category":"Personal",
            "type":"Services"
        }
    ],
    "sg:phone":"+1 513 232 5068",
    "sg:postcode":"45230",
    "sg:province":"OH",
    "sg:tags":[
        "specializing",
        "stitching"
    ],
    "wof:name":"ABC Soup",
    "wof:placetype":"venue"
},
  "geometry": {"coordinates":[-84.385097,39.102331],"type":"Point"}
}