{
  "type": "Feature",
  "properties": {
    "addr:full":"9200 Montgomery Rd Cincinnati OH 45242",
    "addr:housenumber":"9200",
    "addr:postcode":"45242",
    "addr:street":"Montgomery Rd",
    "iso:country":"US",
    "sg:address":"9200 Montgomery Rd",
    "sg:city":"Cincinnati",
    "sg:classifiers":[
        {
            "category":"Professional",
            "subcategory":"Accounting & Tax Preparation",
            "type":"Services"
        }
    ],
    "sg:phone":"+1 513 891 3148",
    "sg:postcode":"45242",
    "sg:province":"OH",
    "sg:tags":[
        "accountant"
    ],
    "wof:name":"Logan & Co",
    "wof:placetype":"venue"
},
  "geometry": {"coordinates":[-84.35668699999999,39.221578],"type":"Point"}
}