{
  "type": "Feature",
  "properties": {
    "addr:full": "400 Thurber Dr W Columbus OH 43215",
    "addr:housenumber": "400",
    "addr:postcode": "43215",
    "addr:street": "Thurber Dr W",
    "iso:country": "US",
    "sg:address": "400 Thurber Dr W",
    "sg:city": "Columbus",
    "sg:classifiers": [
      {
        "category": "Shopping",
        "type": "Retail Goods"
      }
    ],
    "sg:phone": "+1 614 461 1466",
    "sg:postcode": "43215",
    "sg:province": "OH",
    "sg:tags": [
      "merchandise"
    ],
    "wof:name": "Donald T Coffman",
    "wof:placetype": "venue"
  },
  "geometry": {"coordinates":[-83.016461,39.976459],"type":"Point"}
}
