{
  "type": "Feature",
  "properties": {
    "iso:country":"US",
    "sg:address":"115 Mistletoe Rd SE",
    "sg:city":"Niles",
    "sg:classifiers":[
        {
            "category":"Insurance",
            "subcategory":"Insurance Agent",
            "type":"Services"
        }
    ],
    "sg:phone":"+1 330 394 8701",
    "sg:postcode":"44446",
    "sg:province":"OH",
    "wof:name":"New York Life Insurance Co",
    "wof:placetype":"venue"
},
  "geometry": {"coordinates":[-80.759792,41.205438],"type":"Point"}
}