{
  "type": "Feature",
  "properties": {
    "iso:country":"US",
    "sg:address":"4301 Kent Rd",
    "sg:city":"Stow",
    "sg:classifiers":[
        {
            "category":"Shopping",
            "subcategory":"Computers & Home Electronics",
            "type":"Retail Goods"
        }
    ],
    "sg:phone":"+1 330 686 0803",
    "sg:postcode":"44224",
    "sg:province":"OH",
    "sg:tags":[
        "game",
        "video"
    ],
    "wof:name":"Game Stop Corp",
    "wof:placetype":"venue"
},
  "geometry": {"coordinates":[-81.410646,41.157556],"type":"Point"}
}