{
  "type": "Feature",
  "properties": {
    "iso:country":"US",
    "sg:address":"13905 Diana Ave",
    "sg:city":"Cleveland",
    "sg:classifiers":[
        {
            "category":"Organizations",
            "subcategory":"Religious Organization",
            "type":"Services"
        }
    ],
    "sg:phone":"+1 216 249 2421",
    "sg:postcode":"44110",
    "sg:province":"OH",
    "sg:tags":[
        "church"
    ],
    "wof:name":"New Life Mission Baptist Chr",
    "wof:placetype":"venue"
},
  "geometry": {"coordinates":[-81.58687399999999,41.563744],"type":"Point"}
}