{
  "type": "Feature",
  "properties": {
    "iso:country":"US",
    "sg:address":"38241 Willoughby Pkwy",
    "sg:city":"Willoughby",
    "sg:classifiers":[
        {
            "category":"Wholesale",
            "subcategory":"Electrical",
            "type":"Manufacturing & Wholesale Goods"
        },
        {
            "category":"Manufacturing",
            "subcategory":"Tools & Machinery",
            "type":"Manufacturing & Wholesale Goods"
        }
    ],
    "sg:phone":"+1 440 918 0505",
    "sg:postcode":"44094",
    "sg:province":"OH",
    "sg:tags":[
        "control",
        "process",
        "mfg",
        "el",
        "instr"
    ],
    "sg:website":"www.budzar.com",
    "wof:name":"Budzar Industries Inc",
    "wof:placetype":"venue"
},
  "geometry": {"coordinates":[-81.40352900000001,41.678001],"type":"Point"}
}