{
  "type": "Feature",
  "properties": {
    "addr:full": "38241 Willoughby Pkwy Willoughby OH 44094",
    "addr:housenumber": "38241",
    "addr:postcode": "44094",
    "addr:street": "Willoughby Pkwy",
    "iso:country": "US",
    "sg:address": "38241 Willoughby Pkwy",
    "sg:city": "Willoughby",
    "sg:classifiers": [
      {
        "category": "Wholesale",
        "subcategory": "Electrical",
        "type": "Manufacturing \u0026 Wholesale Goods"
      },
      {
        "category": "Manufacturing",
        "subcategory": "Tools \u0026 Machinery",
        "type": "Manufacturing \u0026 Wholesale Goods"
      }
    ],
    "sg:phone": "+1 440 918 0505",
    "sg:postcode": "44094",
    "sg:province": "OH",
    "sg:tags": [
      "control",
      "process",
      "mfg",
      "el",
      "instr"
    ],
    "sg:website": "www.budzar.com",
    "wof:name": "Budzar Industries Inc",
    "wof:placetype": "venue"
  },
  "geometry": {"coordinates":[-81.403529,41.678001],"type":"Point"}
}
