{
  "type": "Feature",
  "properties": {
    "addr:full": "3246 Noe Bixby Rd Columbus OH 43232",
    "addr:housenumber": "3246",
    "addr:postcode": "43232",
    "addr:street": "Noe Bixby Rd",
    "iso:country": "US",
    "sg:address": "3246 Noe Bixby Rd",
    "sg:city": "Columbus",
    "sg:classifiers": [
      {
        "category": "Wholesale",
        "subcategory": "Groceries",
        "type": "Manufacturing \u0026 Wholesale Goods"
      }
    ],
    "sg:phone": "+1 614 833 0442",
    "sg:postcode": "43232",
    "sg:province": "OH",
    "sg:tags": [
      "food",
      "broker"
    ],
    "wof:name": "Freedom Food Brokers Inc",
    "wof:placetype": "venue"
  },
  "geometry": {"coordinates":[-82.864773,39.908478],"type":"Point"}
}
