{
  "type": "Feature",
  "properties": {
    "iso:country":"US",
    "sg:address":"3246 Noe Bixby Rd",
    "sg:city":"Columbus",
    "sg:classifiers":[
        {
            "category":"Wholesale",
            "subcategory":"Groceries",
            "type":"Manufacturing & Wholesale Goods"
        }
    ],
    "sg:phone":"+1 614 833 0442",
    "sg:postcode":"43232",
    "sg:province":"OH",
    "sg:tags":[
        "food",
        "broker"
    ],
    "wof:name":"Freedom Food Brokers Inc",
    "wof:placetype":"venue"
},
  "geometry": {"coordinates":[-82.864773,39.908478],"type":"Point"}
}