{
  "type": "Feature",
  "properties": {
    "addr:full": "176 Cato Dr Xenia OH 45385",
    "addr:housenumber": "176",
    "addr:postcode": "45385",
    "addr:street": "Cato Dr",
    "iso:country": "US",
    "sg:address": "176 Cato Dr",
    "sg:city": "Xenia",
    "sg:classifiers": [
      {
        "category": "Building \u0026 Trades",
        "subcategory": "Pest Control",
        "type": "Services"
      }
    ],
    "sg:phone": "+1 937 372 5807",
    "sg:postcode": "45385",
    "sg:province": "OH",
    "wof:name": "Milt's Termite \u0026 Pest Control",
    "wof:placetype": "venue"
  },
  "geometry": {"coordinates":[-83.953568,39.685281],"type":"Point"}
}
