{
  "type": "Feature",
  "properties": {
    "iso:country":"US",
    "sg:address":"176 Cato Dr",
    "sg:city":"Xenia",
    "sg:classifiers":[
        {
            "category":"Building & Trades",
            "subcategory":"Pest Control",
            "type":"Services"
        }
    ],
    "sg:phone":"+1 937 372 5807",
    "sg:postcode":"45385",
    "sg:province":"OH",
    "wof:name":"Milt's Termite & Pest Control",
    "wof:placetype":"venue"
},
  "geometry": {"coordinates":[-83.953568,39.685281],"type":"Point"}
}