{
  "type": "Feature",
  "properties": {
    "iso:country":"US",
    "sg:address":"415 Lancaster Pike",
    "sg:city":"Circleville",
    "sg:classifiers":[
        {
            "category":"Government",
            "subcategory":"Office",
            "type":"Public Place"
        }
    ],
    "sg:phone":"+1 740 474 2085",
    "sg:postcode":"43113",
    "sg:province":"OH",
    "wof:name":"Pickaway County Fair Board",
    "wof:placetype":"venue"
},
  "geometry": {"coordinates":[-82.927065,39.600883],"type":"Point"}
}