{
  "type": "Feature",
  "properties": {
    "addr:full": "941 N Lake St Amherst OH 44001",
    "addr:housenumber": "941",
    "addr:postcode": "44001",
    "addr:street": "N Lake St",
    "iso:country": "US",
    "sg:address": "941 N Lake St",
    "sg:city": "Amherst",
    "sg:classifiers": [
      {
        "category": "Utilities",
        "subcategory": "Electric",
        "type": "Services"
      }
    ],
    "sg:phone": "+1 440 984 2595",
    "sg:postcode": "44001",
    "sg:province": "OH",
    "wof:name": "Electric Department",
    "wof:placetype": "venue"
  },
  "geometry": {"coordinates":[-82.239132,41.404267],"type":"Point"}
}
