{
  "type": "Feature",
  "properties": {
    "iso:country":"US",
    "sg:address":"13401 S Woodland Rd",
    "sg:city":"Cleveland",
    "sg:classifiers":[
        {
            "category":"Professional",
            "subcategory":"Computer Services",
            "type":"Services"
        }
    ],
    "sg:phone":"+1 216 295 1516",
    "sg:postcode":"44120",
    "sg:province":"OH",
    "sg:tags":[
        "processing",
        "datum"
    ],
    "wof:name":"Datascope Inc",
    "wof:placetype":"venue"
},
  "geometry": {"coordinates":[-81.589291,41.479529],"type":"Point"}
}