{
  "type": "Feature",
  "properties": {
    "addr:full": "2010 Co Hwy 144 Sugarcreek OH 44681",
    "addr:housenumber": "2010",
    "addr:postcode": "44681",
    "addr:street": "Co Hwy 144",
    "iso:country": "US",
    "sg:address": "2010 Co Hwy 144",
    "sg:city": "Sugarcreek",
    "sg:classifiers": [
      {
        "category": "Mining \u0026 Drilling",
        "type": "Manufacturing \u0026 Wholesale Goods"
      }
    ],
    "sg:phone": "+1 330 852 3696",
    "sg:postcode": "44681",
    "sg:province": "OH",
    "sg:tags": [
      "coal",
      "company",
      "shale",
      "clay"
    ],
    "wof:name": "L \u0026 M Mineral Co",
    "wof:placetype": "venue"
  },
  "geometry": {"coordinates":[-81.694933,40.532772],"type":"Point"}
}
