{
  "type": "Feature",
  "properties": {
    "addr:full":"2010 Co Hwy 144 Sugarcreek OH 44681",
    "addr:housenumber":"2010",
    "addr:postcode":"44681",
    "addr:street":"Co Hwy 144",
    "iso:country":"US",
    "sg:address":"2010 Co Hwy 144",
    "sg:city":"Sugarcreek",
    "sg:classifiers":[
        {
            "category":"Mining & Drilling",
            "type":"Manufacturing & Wholesale Goods"
        }
    ],
    "sg:phone":"+1 330 852 3696",
    "sg:postcode":"44681",
    "sg:province":"OH",
    "sg:tags":[
        "coal",
        "company",
        "shale",
        "clay"
    ],
    "wof:name":"L & M Mineral Co",
    "wof:placetype":"venue"
},
  "geometry": {"coordinates":[-81.69493300000001,40.532772],"type":"Point"}
}