{
  "type": "Feature",
  "properties": {
    "iso:country":"US",
    "sg:address":"11977 State Rte 49",
    "sg:city":"Edon",
    "sg:classifiers":[
        {
            "category":"Wholesale",
            "subcategory":"Machinery & Supplies",
            "type":"Manufacturing & Wholesale Goods"
        }
    ],
    "sg:phone":"+1 419 272 2680",
    "sg:postcode":"43518",
    "sg:province":"OH",
    "sg:tags":[
        "farm",
        "equipment"
    ],
    "wof:name":"Reitzel Brothers",
    "wof:placetype":"venue"
},
  "geometry": {"coordinates":[-84.769186,41.585158],"type":"Point"}
}