{
  "type": "Feature",
  "properties": {
    "iso:country":"US",
    "sg:address":"3147 Toledo Ave",
    "sg:city":"Lorain",
    "sg:classifiers":[
        {
            "category":"Social Services",
            "subcategory":"Adult Care",
            "type":"Services"
        }
    ],
    "sg:phone":"+1 440 245 1879",
    "sg:postcode":"44055",
    "sg:province":"OH",
    "sg:tags":[
        "home",
        "group"
    ],
    "wof:name":"Nord Center",
    "wof:placetype":"venue"
},
  "geometry": {"coordinates":[-82.158259,41.443042],"type":"Point"}
}