{
  "type": "Feature",
  "properties": {
    "addr:full": "4536 Vine St Cincinnati OH 45217",
    "addr:housenumber": "4536",
    "addr:postcode": "45217",
    "addr:street": "Vine St",
    "iso:country": "US",
    "sg:address": "4536 Vine St",
    "sg:city": "Cincinnati",
    "sg:classifiers": [
      {
        "category": "Organizations",
        "subcategory": "Religious Organization",
        "type": "Services"
      }
    ],
    "sg:phone": "+1 513 641 3176",
    "sg:postcode": "45217",
    "sg:province": "OH",
    "sg:tags": [
      "church"
    ],
    "sg:website": "www.stcschool.org",
    "wof:name": "St Clement",
    "wof:placetype": "venue"
  },
  "geometry": {"coordinates":[-84.501223,39.165175],"type":"Point"}
}
