{
  "type": "Feature",
  "properties": {
    "addr:full": "1900 Mahoning Rd NE Canton OH 44705",
    "addr:housenumber": "1900",
    "addr:postcode": "44705",
    "addr:street": "Mahoning Rd Ne",
    "iso:country": "US",
    "sg:address": "1900 Mahoning Rd NE",
    "sg:city": "Canton",
    "sg:classifiers": [
      {
        "category": "Manufacturing",
        "subcategory": "Metals",
        "type": "Manufacturing \u0026 Wholesale Goods"
      }
    ],
    "sg:phone": "+1 330 455 7091",
    "sg:postcode": "44705",
    "sg:province": "OH",
    "sg:tags": [
      "barrels",
      "drum"
    ],
    "wof:name": "B \u0026 D Barrel Inc",
    "wof:placetype": "venue"
  },
  "geometry": {"coordinates":[-81.350911,40.808692],"type":"Point"}
}
