{
  "type": "Feature",
  "properties": {
    "addr:full": "3723 Heatherglen Dr Columbus OH 43221",
    "addr:housenumber": "3723",
    "addr:postcode": "43221",
    "addr:street": "Heatherglen Dr",
    "iso:country": "US",
    "sg:address": "3723 Heatherglen Dr",
    "sg:city": "Columbus",
    "sg:classifiers": [
      {
        "category": "Local Transit",
        "type": "Transportation"
      }
    ],
    "sg:phone": "+1 614 851 1663",
    "sg:postcode": "43221",
    "sg:province": "OH",
    "sg:tags": [
      "limousine"
    ],
    "wof:name": "Lacey Limousines",
    "wof:placetype": "venue"
  },
  "geometry": {"coordinates":[-83.119704,40.054736],"type":"Point"}
}
