{
  "type": "Feature",
  "properties": {
    "addr:full":"8361 Edison St NE Louisville OH 44641",
    "addr:housenumber":"8361",
    "addr:postcode":"44641",
    "addr:street":"Edison St Ne",
    "iso:country":"US",
    "sg:address":"8361 Edison St NE",
    "sg:city":"Louisville",
    "sg:classifiers":[
        {
            "category":"Shopping",
            "subcategory":"Clothing, Apparel, & Fashions",
            "type":"Retail Goods"
        }
    ],
    "sg:phone":"+1 330 935 2164",
    "sg:postcode":"44641",
    "sg:province":"OH",
    "sg:tags":[
        "alteration"
    ],
    "wof:name":"Plum Tree Alterations",
    "wof:placetype":"venue"
},
  "geometry": {"coordinates":[-81.245133,40.952015],"type":"Point"}
}