{
  "type": "Feature",
  "properties": {
    "addr:full":"17630 S Waterloo Rd Cleveland OH 44119",
    "addr:housenumber":"17630",
    "addr:postcode":"44119",
    "addr:street":"S Waterloo Rd",
    "iso:country":"US",
    "sg:address":"17630 S Waterloo Rd",
    "sg:city":"Cleveland",
    "sg:classifiers":[
        {
            "category":"Retail",
            "subcategory":"Auto Rental",
            "type":"Services"
        }
    ],
    "sg:phone":"+1 216 531 2678",
    "sg:postcode":"44119",
    "sg:province":"OH",
    "sg:tags":[
        "renting",
        "truck",
        "leasing"
    ],
    "wof:name":"U-Haul Co",
    "wof:placetype":"venue"
},
  "geometry": {"coordinates":[-81.57099599999999,41.568723],"type":"Point"}
}