{
  "type": "Feature",
  "properties": {
    "addr:full": "431 W High St Piqua OH 45356",
    "addr:housenumber": "431",
    "addr:postcode": "45356",
    "addr:street": "W High St",
    "iso:country": "US",
    "sg:address": "431 W High St",
    "sg:city": "Piqua",
    "sg:classifiers": [
      {
        "category": "Shopping",
        "type": "Retail Goods"
      }
    ],
    "sg:phone": "+1 937 615 0424",
    "sg:postcode": "45356",
    "sg:province": "OH",
    "sg:tags": [
      "candle",
      "merchandise"
    ],
    "wof:name": "Apple Valley Candles \u0026 Supplie",
    "wof:placetype": "venue"
  },
  "geometry": {"coordinates":[-84.24526,40.148595],"type":"Point"}
}
