{
  "type": "Feature",
  "properties": {
    "iso:country":"US",
    "sg:address":"9589 Loveland Madeira Rd",
    "sg:city":"Loveland",
    "sg:classifiers":[
        {
            "category":"Freight",
            "type":"Transportation"
        }
    ],
    "sg:phone":"+1 513 984 6422",
    "sg:postcode":"45140",
    "sg:province":"OH",
    "sg:tags":[
        "operator",
        "trucking"
    ],
    "wof:name":"Barry Rhodes Trucking",
    "wof:placetype":"venue"
},
  "geometry": {"coordinates":[-84.311313,39.232295],"type":"Point"}
}