{
  "type": "Feature",
  "properties": {
    "addr:full": "6219 Oak Point Ests Lorain OH 44053",
    "addr:housenumber": "6219",
    "addr:postcode": "44053",
    "addr:street": "Oak Point Ests",
    "iso:country": "US",
    "sg:address": "6219 Oak Point Ests",
    "sg:city": "Lorain",
    "sg:classifiers": [
      {
        "category": "Real Estate",
        "subcategory": "Real Estate Agent",
        "type": "Services"
      }
    ],
    "sg:phone": "+1 440 323 6910",
    "sg:postcode": "44053",
    "sg:province": "OH",
    "wof:name": "Bowe Real Estate Assoc",
    "wof:placetype": "venue"
  },
  "geometry": {"coordinates":[-82.244789,41.421154],"type":"Point"}
}
