{
  "type": "Feature",
  "properties": {
    "iso:country":"US",
    "sg:address":"6219 Oak Point Ests",
    "sg:city":"Lorain",
    "sg:classifiers":[
        {
            "category":"Real Estate",
            "subcategory":"Real Estate Agent",
            "type":"Services"
        }
    ],
    "sg:phone":"+1 440 323 6910",
    "sg:postcode":"44053",
    "sg:province":"OH",
    "wof:name":"Bowe Real Estate Assoc",
    "wof:placetype":"venue"
},
  "geometry": {"coordinates":[-82.244789,41.421154],"type":"Point"}
}