{
  "type": "Feature",
  "properties": {
    "iso:country":"US",
    "sg:address":"6046 323rd St",
    "sg:city":"Toledo",
    "sg:classifiers":[
        {
            "category":"Building & Trades",
            "subcategory":"Construction",
            "type":"Services"
        }
    ],
    "sg:phone":"+1 419 729 5530",
    "sg:postcode":"43611",
    "sg:province":"OH",
    "sg:tags":[
        "contractor"
    ],
    "wof:name":"Bulldog Roofing",
    "wof:placetype":"venue"
},
  "geometry": {"coordinates":[-83.45879499999999,41.72882],"type":"Point"}
}