{
  "type": "Feature",
  "properties": {
    "addr:full": "6046 323rd St Toledo OH 43611",
    "addr:housenumber": "6046",
    "addr:postcode": "43611",
    "addr:street": "323Rd St",
    "iso:country": "US",
    "sg:address": "6046 323rd St",
    "sg:city": "Toledo",
    "sg:classifiers": [
      {
        "category": "Building \u0026 Trades",
        "subcategory": "Construction",
        "type": "Services"
      }
    ],
    "sg:phone": "+1 419 729 5530",
    "sg:postcode": "43611",
    "sg:province": "OH",
    "sg:tags": [
      "contractor"
    ],
    "wof:name": "Bulldog Roofing",
    "wof:placetype": "venue"
  },
  "geometry": {"coordinates":[-83.458795,41.72882],"type":"Point"}
}
