{
  "type": "Feature",
  "properties": {
    "iso:country":"US",
    "sg:address":"5602 302nd St",
    "sg:city":"Toledo",
    "sg:classifiers":[
        {
            "category":"Manufacturing",
            "subcategory":"Signs",
            "type":"Manufacturing & Wholesale Goods"
        }
    ],
    "sg:phone":"+1 419 729 9419",
    "sg:postcode":"43611",
    "sg:province":"OH",
    "wof:name":"A 1 Sign & Graphic",
    "wof:placetype":"venue"
},
  "geometry": {"coordinates":[-83.477542,41.721222],"type":"Point"}
}