{
  "type": "Feature",
  "properties": {
    "addr:full": "5602 302nd St Toledo OH 43611",
    "addr:housenumber": "5602",
    "addr:postcode": "43611",
    "addr:street": "302Nd St",
    "iso:country": "US",
    "sg:address": "5602 302nd St",
    "sg:city": "Toledo",
    "sg:classifiers": [
      {
        "category": "Manufacturing",
        "subcategory": "Signs",
        "type": "Manufacturing \u0026 Wholesale Goods"
      }
    ],
    "sg:phone": "+1 419 729 9419",
    "sg:postcode": "43611",
    "sg:province": "OH",
    "wof:name": "A 1 Sign \u0026 Graphic",
    "wof:placetype": "venue"
  },
  "geometry": {"coordinates":[-83.477542,41.721222],"type":"Point"}
}
