{
  "type": "Feature",
  "properties": {
    "addr:full":"5926 Deering Ave Cleveland OH 44130",
    "addr:housenumber":"5926",
    "addr:postcode":"44130",
    "addr:street":"Deering Ave",
    "iso:country":"US",
    "sg:address":"5926 Deering Ave",
    "sg:city":"Cleveland",
    "sg:classifiers":[
        {
            "category":"Food & Beverages",
            "subcategory":"Liquor & Beverages",
            "type":"Retail Goods"
        }
    ],
    "sg:phone":"+1 440 888 1462",
    "sg:postcode":"44130",
    "sg:province":"OH",
    "sg:tags":[
        "alcoholic"
    ],
    "wof:name":"Drive Thru The",
    "wof:placetype":"venue"
},
  "geometry": {"coordinates":[-81.745862,41.401754],"type":"Point"}
}