{
  "type": "Feature",
  "properties": {
    "addr:full": "2428 Whipple Ave NW Canton OH 44708",
    "addr:housenumber": "2428",
    "addr:postcode": "44708",
    "addr:street": "Whipple Ave Nw",
    "iso:country": "US",
    "sg:address": "2428 Whipple Ave NW",
    "sg:city": "Canton",
    "sg:classifiers": [
      {
        "category": "Real Estate",
        "subcategory": "Real Estate Agent",
        "type": "Services"
      }
    ],
    "sg:phone": "+1 330 433 0307",
    "sg:postcode": "44708",
    "sg:province": "OH",
    "sg:website": "www.remax.com",
    "wof:name": "Remax Partners",
    "wof:placetype": "venue"
  },
  "geometry": {"coordinates":[-81.424546,40.825225],"type":"Point"}
}
