{
  "type": "Feature",
  "properties": {
    "addr:full":"1903 Twp Hwy 220 Bloomingdale OH 43910",
    "addr:housenumber":"1903",
    "addr:postcode":"43910",
    "addr:street":"Twp Hwy 220",
    "iso:country":"US",
    "sg:address":"1903 Twp Hwy 220",
    "sg:city":"Bloomingdale",
    "sg:classifiers":[
        {
            "category":"Shopping",
            "type":"Retail Goods"
        }
    ],
    "sg:phone":"+1 740 765 9300",
    "sg:postcode":"43910",
    "sg:province":"OH",
    "sg:tags":[
        "equipment",
        "telephone",
        "supply"
    ],
    "wof:name":"Onecom Telecommunications",
    "wof:placetype":"venue"
},
  "geometry": {"coordinates":[-80.82674,40.431958],"type":"Point"}
}