{
  "type": "Feature",
  "properties": {
    "addr:full":"31025 Carter St Cleveland OH 44139",
    "addr:housenumber":"31025",
    "addr:postcode":"44139",
    "addr:street":"Carter St",
    "iso:country":"US",
    "sg:address":"31025 Carter St",
    "sg:city":"Cleveland",
    "sg:classifiers":[
        {
            "category":"Manufacturing",
            "subcategory":"Petroleum Products",
            "type":"Manufacturing & Wholesale Goods"
        },
        {
            "category":"Manufacturing",
            "subcategory":"Tools & Machinery",
            "type":"Manufacturing & Wholesale Goods"
        }
    ],
    "sg:phone":"+1 440 287 2302",
    "sg:postcode":"44139",
    "sg:province":"OH",
    "sg:tags":[
        "lubricating",
        "industrial",
        "based",
        "mfg",
        "system",
        "devices",
        "compound",
        "lubricant",
        "soap"
    ],
    "sg:website":"www.jtmproductsinc.com",
    "wof:name":"Jtm Products Inc",
    "wof:placetype":"venue"
},
  "geometry": {"coordinates":[-81.45903800000001,41.381135],"type":"Point"}
}