{
  "type": "Feature",
  "properties": {
    "addr:full": "520 S Main St Akron OH 44311",
    "addr:housenumber": "520",
    "addr:postcode": "44311",
    "addr:street": "S Main St",
    "iso:country": "US",
    "sg:address": "520 S Main St",
    "sg:city": "Akron",
    "sg:classifiers": [
      {
        "category": "Banks \u0026 Credit Unions",
        "subcategory": "Bank",
        "type": "Services"
      }
    ],
    "sg:phone": "+1 330 996 4644",
    "sg:postcode": "44311",
    "sg:province": "OH",
    "sg:tags": [
      "loan",
      "real estate"
    ],
    "wof:name": "E-Z Money Mortgage Co",
    "wof:placetype": "venue"
  },
  "geometry": {"coordinates":[-81.524431,41.073244],"type":"Point"}
}
