{
  "type": "Feature",
  "properties": {
    "iso:country":"US",
    "sg:address":"24819 Twp Rd 461",
    "sg:city":"Newcomerstown",
    "sg:classifiers":[
        {
            "category":"Freight",
            "type":"Transportation"
        }
    ],
    "sg:phone":"+1 740 498 9896",
    "sg:postcode":"43832",
    "sg:province":"OH",
    "sg:tags":[
        "operator",
        "trucking"
    ],
    "wof:name":"McMillian Trucking",
    "wof:placetype":"venue"
},
  "geometry": {"coordinates":[-81.62119,40.302777],"type":"Point"}
}