{
  "type": "Feature",
  "properties": {
    "iso:country":"US",
    "sg:address":"15068 Oak St",
    "sg:city":"Wauseon",
    "sg:classifiers":[
        {
            "category":"Manufacturing",
            "subcategory":"Glass & Minerals",
            "type":"Manufacturing & Wholesale Goods"
        }
    ],
    "sg:phone":"+1 419 337 1413",
    "sg:postcode":"43567",
    "sg:province":"OH",
    "sg:tags":[
        "precast",
        "post",
        "mfg",
        "steps",
        "concrete"
    ],
    "wof:name":"Unit Sales & Service",
    "wof:placetype":"venue"
},
  "geometry": {"coordinates":[-84.153769,41.666391],"type":"Point"}
}