{
  "type": "Feature",
  "properties": {
    "addr:full": "15068 Oak St Wauseon OH 43567",
    "addr:housenumber": "15068",
    "addr:postcode": "43567",
    "addr:street": "Oak St",
    "iso:country": "US",
    "sg:address": "15068 Oak St",
    "sg:city": "Wauseon",
    "sg:classifiers": [
      {
        "category": "Manufacturing",
        "subcategory": "Glass \u0026 Minerals",
        "type": "Manufacturing \u0026 Wholesale Goods"
      }
    ],
    "sg:phone": "+1 419 337 1413",
    "sg:postcode": "43567",
    "sg:province": "OH",
    "sg:tags": [
      "precast",
      "post",
      "mfg",
      "steps",
      "concrete"
    ],
    "wof:name": "Unit Sales \u0026 Service",
    "wof:placetype": "venue"
  },
  "geometry": {"coordinates":[-84.153769,41.666391],"type":"Point"}
}
