{
  "type": "Feature",
  "properties": {
    "addr:full":"5346 Race Rd Cincinnati OH 45247",
    "addr:housenumber":"5346",
    "addr:postcode":"45247",
    "addr:street":"Race Rd",
    "iso:country":"US",
    "sg:address":"5346 Race Rd",
    "sg:city":"Cincinnati",
    "sg:classifiers":[
        {
            "category":"Building & Trades",
            "subcategory":"Construction",
            "type":"Services"
        }
    ],
    "sg:phone":"+1 513 574 8345",
    "sg:postcode":"45247",
    "sg:province":"OH",
    "sg:tags":[
        "general",
        "contractor"
    ],
    "wof:name":"R & K Developers Inc",
    "wof:placetype":"venue"
},
  "geometry": {"coordinates":[-84.627702,39.18858],"type":"Point"}
}