{
  "type": "Feature",
  "properties": {
    "iso:country":"US",
    "sg:address":"1119 Lyons Rd",
    "sg:city":"Dayton",
    "sg:classifiers":[
        {
            "category":"Insurance",
            "subcategory":"Insurance Agent",
            "type":"Services"
        }
    ],
    "sg:phone":"+1 937 435 1949",
    "sg:postcode":"45458",
    "sg:province":"OH",
    "wof:name":"Jerry Poff",
    "wof:placetype":"venue"
},
  "geometry": {"coordinates":[-84.193161,39.629214],"type":"Point"}
}