{
  "type": "Feature",
  "properties": {
    "addr:full": "1119 Lyons Rd Dayton OH 45458",
    "addr:housenumber": "1119",
    "addr:postcode": "45458",
    "addr:street": "Lyons Rd",
    "iso:country": "US",
    "sg:address": "1119 Lyons Rd",
    "sg:city": "Dayton",
    "sg:classifiers": [
      {
        "category": "Insurance",
        "subcategory": "Insurance Agent",
        "type": "Services"
      }
    ],
    "sg:phone": "+1 937 435 1949",
    "sg:postcode": "45458",
    "sg:province": "OH",
    "wof:name": "Jerry Poff",
    "wof:placetype": "venue"
  },
  "geometry": {"coordinates":[-84.193161,39.629214],"type":"Point"}
}
