{
  "type": "Feature",
  "properties": {
    "addr:full":"9297 West Rd Cleves OH 45002",
    "addr:housenumber":"9297",
    "addr:postcode":"45002",
    "addr:street":"West Rd",
    "iso:country":"US",
    "sg:address":"9297 West Rd",
    "sg:city":"Cleves",
    "sg:classifiers":[
        {
            "category":"Farming",
            "subcategory":"Livestock Farm",
            "type":"Manufacturing & Wholesale Goods"
        }
    ],
    "sg:phone":"+1 513 353 2899",
    "sg:postcode":"45002",
    "sg:province":"OH",
    "sg:tags":[
        "beef",
        "feedlot",
        "cattle"
    ],
    "wof:name":"A&T Farms",
    "wof:placetype":"venue"
},
  "geometry": {"coordinates":[-84.75089,39.236632],"type":"Point"}
}