{
  "type": "Feature",
  "properties": {
    "iso:country":"US",
    "sg:address":"1151 Oakdale Ave",
    "sg:city":"Wellsville",
    "sg:classifiers":[
        {
            "category":"Restaurant",
            "type":"Food & Drink"
        }
    ],
    "sg:phone":"+1 330 532 0900",
    "sg:postcode":"43968",
    "sg:province":"OH",
    "wof:name":"Dalonzo's Pizza",
    "wof:placetype":"venue"
},
  "geometry": {"coordinates":[-80.653859,40.629773],"type":"Point"}
}