{
  "type": "Feature",
  "properties": {
    "addr:full": "1151 Oakdale Ave Wellsville OH 43968",
    "addr:housenumber": "1151",
    "addr:postcode": "43968",
    "addr:street": "Oakdale Ave",
    "iso:country": "US",
    "sg:address": "1151 Oakdale Ave",
    "sg:city": "Wellsville",
    "sg:classifiers": [
      {
        "category": "Restaurant",
        "type": "Food \u0026 Drink"
      }
    ],
    "sg:phone": "+1 330 532 0900",
    "sg:postcode": "43968",
    "sg:province": "OH",
    "wof:name": "Dalonzo's Pizza",
    "wof:placetype": "venue"
  },
  "geometry": {"coordinates":[-80.653859,40.629773],"type":"Point"}
}
