{
  "type": "Feature",
  "properties": {
    "addr:full":"1045 S Reynolds Rd Toledo OH 43615",
    "addr:housenumber":"1045",
    "addr:postcode":"43615",
    "addr:street":"S Reynolds Rd",
    "iso:country":"US",
    "sg:address":"1045 S Reynolds Rd",
    "sg:city":"Toledo",
    "sg:classifiers":[
        {
            "category":"Restaurant",
            "type":"Food & Drink"
        }
    ],
    "sg:phone":"+1 419 385 2441",
    "sg:postcode":"43615",
    "sg:province":"OH",
    "wof:name":"Dolly & Joe's Restaurant",
    "wof:placetype":"venue"
},
  "geometry": {"coordinates":[-83.66446500000001,41.620763],"type":"Point"}
}