{
  "type": "Feature",
  "properties": {
    "iso:country":"US",
    "sg:address":"5839 State Rte 5",
    "sg:city":"Ravenna",
    "sg:classifiers":[
        {
            "category":"Building & Trades",
            "subcategory":"Construction",
            "type":"Services"
        }
    ],
    "sg:phone":"+1 330 296 7706",
    "sg:postcode":"44266",
    "sg:province":"OH",
    "sg:tags":[
        "excavating",
        "contractor"
    ],
    "wof:name":"Patrick Excavating & Trucking",
    "wof:placetype":"venue"
},
  "geometry": {"coordinates":[-81.17512499999999,41.151452],"type":"Point"}
}