{
  "type": "Feature",
  "properties": {
    "addr:full": "5839 State Rte 5 Ravenna OH 44266",
    "addr:housenumber": "5839",
    "addr:postcode": "44266",
    "addr:street": "State Rte 5",
    "iso:country": "US",
    "sg:address": "5839 State Rte 5",
    "sg:city": "Ravenna",
    "sg:classifiers": [
      {
        "category": "Building \u0026 Trades",
        "subcategory": "Construction",
        "type": "Services"
      }
    ],
    "sg:phone": "+1 330 296 7706",
    "sg:postcode": "44266",
    "sg:province": "OH",
    "sg:tags": [
      "excavating",
      "contractor"
    ],
    "wof:name": "Patrick Excavating \u0026 Trucking",
    "wof:placetype": "venue"
  },
  "geometry": {"coordinates":[-81.175125,41.151452],"type":"Point"}
}
