{
  "type": "Feature",
  "properties": {
    "iso:country":"US",
    "sg:address":"626 Hilbish Ave",
    "sg:city":"Akron",
    "sg:classifiers":[
        {
            "category":"Bars & Pubs",
            "type":"Food & Drink"
        }
    ],
    "sg:phone":"+1 330 644 3461",
    "sg:postcode":"44312",
    "sg:province":"OH",
    "wof:name":"K C's Lakes Lounge",
    "wof:placetype":"venue"
},
  "geometry": {"coordinates":[-81.453893,41.044138],"type":"Point"}
}