{
  "type": "Feature",
  "properties": {
    "addr:full": "626 Hilbish Ave Akron OH 44312",
    "addr:housenumber": "626",
    "addr:postcode": "44312",
    "addr:street": "Hilbish Ave",
    "iso:country": "US",
    "sg:address": "626 Hilbish Ave",
    "sg:city": "Akron",
    "sg:classifiers": [
      {
        "category": "Bars \u0026 Pubs",
        "type": "Food \u0026 Drink"
      }
    ],
    "sg:phone": "+1 330 644 3461",
    "sg:postcode": "44312",
    "sg:province": "OH",
    "wof:name": "K C's Lakes Lounge",
    "wof:placetype": "venue"
  },
  "geometry": {"coordinates":[-81.453893,41.044138],"type":"Point"}
}
