{
  "type": "Feature",
  "properties": {
    "iso:country":"US",
    "sg:address":"10801 Reading Rd",
    "sg:city":"Cincinnati",
    "sg:classifiers":[
        {
            "category":"Home & Garden",
            "subcategory":"Building Materials",
            "type":"Retail Goods"
        }
    ],
    "sg:phone":"+1 513 563 6803",
    "sg:postcode":"45241",
    "sg:province":"OH",
    "wof:name":"Furrow Building Materials",
    "wof:placetype":"venue"
},
  "geometry": {"coordinates":[-84.415007,39.264762],"type":"Point"}
}