{
  "type": "Feature",
  "properties": {
    "addr:full": "10801 Reading Rd Cincinnati OH 45241",
    "addr:housenumber": "10801",
    "addr:postcode": "45241",
    "addr:street": "Reading Rd",
    "iso:country": "US",
    "sg:address": "10801 Reading Rd",
    "sg:city": "Cincinnati",
    "sg:classifiers": [
      {
        "category": "Home \u0026 Garden",
        "subcategory": "Building Materials",
        "type": "Retail Goods"
      }
    ],
    "sg:phone": "+1 513 563 6803",
    "sg:postcode": "45241",
    "sg:province": "OH",
    "wof:name": "Furrow Building Materials",
    "wof:placetype": "venue"
  },
  "geometry": {"coordinates":[-84.415007,39.264762],"type":"Point"}
}
