{
  "type": "Feature",
  "properties": {
    "addr:full": "7185 Ravenna Ave NE Louisville OH 44641",
    "addr:housenumber": "7185",
    "addr:postcode": "44641",
    "addr:street": "Ravenna Ave Ne",
    "iso:country": "US",
    "sg:address": "7185 Ravenna Ave NE",
    "sg:city": "Louisville",
    "sg:classifiers": [
      {
        "category": "Shopping",
        "type": "Retail Goods"
      },
      {
        "category": "Building \u0026 Trades",
        "subcategory": "Construction",
        "type": "Services"
      }
    ],
    "sg:phone": "+1 330 875 1641",
    "sg:postcode": "44641",
    "sg:province": "OH",
    "sg:tags": [
      "designer",
      "merchandise",
      "dealer",
      "pool",
      "swimming"
    ],
    "wof:name": "King's Precision Pools",
    "wof:placetype": "venue"
  },
  "geometry": {"coordinates":[-81.257714,40.873522],"type":"Point"}
}
