{
  "type": "Feature",
  "properties": {
    "iso:country":"US",
    "sg:address":"7185 Ravenna Ave NE",
    "sg:city":"Louisville",
    "sg:classifiers":[
        {
            "category":"Shopping",
            "type":"Retail Goods"
        },
        {
            "category":"Building & Trades",
            "subcategory":"Construction",
            "type":"Services"
        }
    ],
    "sg:phone":"+1 330 875 1641",
    "sg:postcode":"44641",
    "sg:province":"OH",
    "sg:tags":[
        "designer",
        "merchandise",
        "dealer",
        "pool",
        "swimming"
    ],
    "wof:name":"King's Precision Pools",
    "wof:placetype":"venue"
},
  "geometry": {"coordinates":[-81.25771400000001,40.873522],"type":"Point"}
}