{
  "type": "Feature",
  "properties": {
    "addr:full":"4444 Carver Woods Dr Cincinnati OH 45242",
    "addr:housenumber":"4444",
    "addr:postcode":"45242",
    "addr:street":"Carver Woods Dr",
    "iso:country":"US",
    "sg:address":"4444 Carver Woods Dr",
    "sg:city":"Cincinnati",
    "sg:classifiers":[
        {
            "category":"Professional",
            "subcategory":"Accounting & Tax Preparation",
            "type":"Services"
        }
    ],
    "sg:phone":"+1 513 791 8090",
    "sg:postcode":"45242",
    "sg:province":"OH",
    "wof:name":"Kunimura Wayne K",
    "wof:placetype":"venue"
},
  "geometry": {"coordinates":[-84.38595599999999,39.245388],"type":"Point"}
}