{
  "type": "Feature",
  "properties": {
    "addr:full":"14900 Co Rd H Wauseon OH 43567",
    "addr:housenumber":"14900",
    "addr:postcode":"43567",
    "addr:street":"Co Rd H",
    "iso:country":"US",
    "sg:address":"14900 Co Rd H",
    "sg:city":"Wauseon",
    "sg:classifiers":[
        {
            "category":"Real Estate",
            "subcategory":"Real Estate Operator",
            "type":"Services"
        }
    ],
    "sg:phone":"+1 419 335 2558",
    "sg:postcode":"43567",
    "sg:province":"OH",
    "sg:tags":[
        "mobile",
        "home",
        "park",
        "community"
    ],
    "wof:name":"Dover Glen Estates",
    "wof:placetype":"venue"
},
  "geometry": {"coordinates":[-84.153831,41.587576],"type":"Point"}
}