{
  "type": "Feature",
  "properties": {
    "iso:country":"US",
    "sg:address":"4195 Cleveland Ave",
    "sg:city":"Columbus",
    "sg:classifiers":[
        {
            "category":"Shopping",
            "subcategory":"Computers & Home Electronics",
            "type":"Retail Goods"
        }
    ],
    "sg:phone":"+1 614 473 0802",
    "sg:postcode":"43224",
    "sg:province":"OH",
    "sg:tags":[
        "software"
    ],
    "wof:name":"Iftin Computers",
    "wof:placetype":"venue"
},
  "geometry": {"coordinates":[-82.953539,40.053644],"type":"Point"}
}