{
  "type": "Feature",
  "properties": {
    "addr:full":"9390 Stump Rd Minerva OH 44657",
    "addr:housenumber":"9390",
    "addr:postcode":"44657",
    "addr:street":"Stump Rd",
    "iso:country":"US",
    "sg:address":"9390 Stump Rd",
    "sg:city":"Minerva",
    "sg:phone":"+1 330 868 7613",
    "sg:postcode":"44657",
    "sg:province":"OH",
    "sg:tags":[
        "equipment",
        "commercial"
    ],
    "wof:name":"Burnworth Equipment Inc",
    "wof:placetype":"venue"
},
  "geometry": {"coordinates":[-81.08255,40.765581],"type":"Point"}
}