{
  "type": "Feature",
  "properties": {
    "addr:full": "3001 E Kemper Rd Cincinnati OH 45241",
    "addr:housenumber": "3001",
    "addr:postcode": "45241",
    "addr:street": "E Kemper Rd",
    "iso:country": "US",
    "sg:address": "3001 E Kemper Rd",
    "sg:city": "Cincinnati",
    "sg:classifiers": [
      {
        "category": "Wholesale",
        "subcategory": "Construction Materials",
        "type": "Manufacturing \u0026 Wholesale Goods"
      },
      {
        "category": "Manufacturing",
        "subcategory": "Building Materials",
        "type": "Manufacturing \u0026 Wholesale Goods"
      }
    ],
    "sg:phone": "+1 513 772 9090",
    "sg:postcode": "45241",
    "sg:province": "OH",
    "wof:name": "Andersen Logistics Inc",
    "wof:placetype": "venue"
  },
  "geometry": {"coordinates":[-84.419422,39.283538],"type":"Point"}
}
