{
  "type": "Feature",
  "properties": {
    "iso:country":"US",
    "sg:address":"3001 E Kemper Rd",
    "sg:city":"Cincinnati",
    "sg:classifiers":[
        {
            "category":"Wholesale",
            "subcategory":"Construction Materials",
            "type":"Manufacturing & Wholesale Goods"
        },
        {
            "category":"Manufacturing",
            "subcategory":"Building Materials",
            "type":"Manufacturing & Wholesale Goods"
        }
    ],
    "sg:phone":"+1 513 772 9090",
    "sg:postcode":"45241",
    "sg:province":"OH",
    "wof:name":"Andersen Logistics Inc",
    "wof:placetype":"venue"
},
  "geometry": {"coordinates":[-84.419422,39.283538],"type":"Point"}
}