{
  "type": "Feature",
  "properties": {
    "iso:country":"US",
    "sg:address":"6370 Twp Rd 323",
    "sg:city":"Millersburg",
    "sg:classifiers":[
        {
            "category":"Building & Trades",
            "subcategory":"Construction",
            "type":"Services"
        },
        {
            "category":"Wholesale",
            "subcategory":"Durable Goods & Equipment",
            "type":"Manufacturing & Wholesale Goods"
        }
    ],
    "sg:phone":"+1 330 674 1099",
    "sg:postcode":"44654",
    "sg:province":"OH",
    "sg:tags":[
        "fireproofing"
    ],
    "wof:name":"No Burn Fire Resistant Prods",
    "wof:placetype":"venue"
},
  "geometry": {"coordinates":[-81.928151,40.588266],"type":"Point"}
}