{
  "type": "Feature",
  "properties": {
    "addr:full":"11959 Silica Rd North Jackson OH 44451",
    "addr:housenumber":"11959",
    "addr:postcode":"44451",
    "addr:street":"Silica Rd",
    "iso:country":"US",
    "sg:address":"11959 Silica Rd",
    "sg:city":"North Jackson",
    "sg:classifiers":[
        {
            "category":"Arts & Performance",
            "subcategory":"Theater",
            "type":"Entertainment"
        }
    ],
    "sg:phone":"+1 330 538 8863",
    "sg:postcode":"44451",
    "sg:province":"OH",
    "sg:tags":[
        "live",
        "music"
    ],
    "wof:name":"Entertainment Tune-Ite DJ",
    "wof:placetype":"venue"
},
  "geometry": {"coordinates":[-80.87644400000001,41.118038],"type":"Point"}
}