{
  "type": "Feature",
  "properties": {
    "addr:full": "4638 Commodore Dr Stow OH 44224",
    "addr:housenumber": "4638",
    "addr:postcode": "44224",
    "addr:street": "Commodore Dr",
    "iso:country": "US",
    "sg:address": "4638 Commodore Dr",
    "sg:city": "Stow",
    "sg:classifiers": [
      {
        "category": "Professional",
        "type": "Services"
      }
    ],
    "sg:phone": "+1 330 928 3651",
    "sg:postcode": "44224",
    "sg:province": "OH",
    "sg:tags": [
      "establishment"
    ],
    "wof:name": "MRLR",
    "wof:placetype": "venue"
  },
  "geometry": {"coordinates":[-81.48445,41.191637],"type":"Point"}
}
