{
  "type": "Feature",
  "properties": {
    "addr:full":"3889 Marion-Waldo Rd Marion OH 43302",
    "addr:housenumber":"3889",
    "addr:postcode":"43302",
    "addr:street":"Marion-Waldo Rd",
    "iso:country":"US",
    "sg:address":"3889 Marion-Waldo Rd",
    "sg:city":"Marion",
    "sg:classifiers":[
        {
            "category":"Professional",
            "type":"Services"
        }
    ],
    "sg:phone":"+1 740 386 2801",
    "sg:postcode":"43302",
    "sg:province":"OH",
    "wof:name":"Service Records Inc",
    "wof:placetype":"venue"
},
  "geometry": {"coordinates":[-83.097443,40.511989],"type":"Point"}
}