{
  "type": "Feature",
  "properties": {
    "addr:full":"1607 Hayes Ave Sandusky OH 44870",
    "addr:housenumber":"1607",
    "addr:postcode":"44870",
    "addr:street":"Hayes Ave",
    "iso:country":"US",
    "sg:address":"1607 Hayes Ave",
    "sg:city":"Sandusky",
    "sg:classifiers":[
        {
            "category":"Personal",
            "subcategory":"Barber",
            "type":"Services"
        }
    ],
    "sg:phone":"+1 419 627 9254",
    "sg:postcode":"44870",
    "sg:province":"OH",
    "wof:name":"Phil P's Barber Shop",
    "wof:placetype":"venue"
},
  "geometry": {"coordinates":[-82.71109800000001,41.440701],"type":"Point"}
}