{
  "type": "Feature",
  "properties": {
    "iso:country":"US",
    "sg:address":"476 Piper Rd",
    "sg:city":"Mansfield",
    "sg:classifiers":[
        {
            "category":"Retail",
            "subcategory":"Auto Repair",
            "type":"Services"
        }
    ],
    "sg:phone":"+1 419 522 8822",
    "sg:postcode":"44905",
    "sg:province":"OH",
    "sg:tags":[
        "transmission"
    ],
    "wof:name":"Northeast Transmission Parts",
    "wof:placetype":"venue"
},
  "geometry": {"coordinates":[-82.49716100000001,40.799263],"type":"Point"}
}