{
  "type": "Feature",
  "properties": {
    "addr:full": "13401 Chillicothe Rd Chesterland OH 44026",
    "addr:housenumber": "13401",
    "addr:postcode": "44026",
    "addr:street": "Chillicothe Rd",
    "iso:country": "US",
    "sg:address": "13401 Chillicothe Rd",
    "sg:city": "Chesterland",
    "sg:classifiers": [
      {
        "category": "Education",
        "subcategory": "School",
        "type": "Public Place"
      }
    ],
    "sg:phone": "+1 440 729 5974",
    "sg:postcode": "44026",
    "sg:province": "OH",
    "wof:name": "Nutrition Inc",
    "wof:placetype": "venue"
  },
  "geometry": {"coordinates":[-81.339314,41.505947],"type":"Point"}
}
