{
  "type": "Feature",
  "properties": {
    "addr:full":"170 Lincoln Way E Massillon OH 44646",
    "addr:housenumber":"170",
    "addr:postcode":"44646",
    "addr:street":"Lincoln Way E",
    "iso:country":"US",
    "sg:address":"170 Lincoln Way E",
    "sg:city":"Massillon",
    "sg:classifiers":[
        {
            "category":"Organizations",
            "subcategory":"Community Association",
            "type":"Services"
        }
    ],
    "sg:phone":"+1 330 833 3986",
    "sg:postcode":"44646",
    "sg:province":"OH",
    "sg:tags":[
        "club",
        "social"
    ],
    "wof:name":"Massillon Club",
    "wof:placetype":"venue"
},
  "geometry": {"coordinates":[-81.520679,40.797217],"type":"Point"}
}