{
  "type": "Feature",
  "properties": {
    "iso:country":"US",
    "sg:address":"9852 Greenriver Dr",
    "sg:city":"Cincinnati",
    "sg:classifiers":[
        {
            "category":"Professional",
            "type":"Services"
        }
    ],
    "sg:phone":"+1 513 742 5421",
    "sg:postcode":"45231",
    "sg:province":"OH",
    "wof:name":"First Step Pride Inc",
    "wof:placetype":"venue"
},
  "geometry": {"coordinates":[-84.56897600000001,39.25],"type":"Point"}
}