{
  "type": "Feature",
  "properties": {
    "addr:full":"414 S Belmont Ave Springfield OH 45505",
    "addr:housenumber":"414",
    "addr:postcode":"45505",
    "addr:street":"S Belmont Ave",
    "iso:country":"US",
    "sg:address":"414 S Belmont Ave",
    "sg:city":"Springfield",
    "sg:classifiers":[
        {
            "category":"Building & Trades",
            "subcategory":"Cleaning & Sanitation",
            "type":"Services"
        }
    ],
    "sg:phone":"+1 937 324 9328",
    "sg:postcode":"45505",
    "sg:province":"OH",
    "sg:tags":[
        "window"
    ],
    "wof:name":"Perry Window Cleaning",
    "wof:placetype":"venue"
},
  "geometry": {"coordinates":[-83.780304,39.916449],"type":"Point"}
}