{
  "type": "Feature",
  "properties": {
    "addr:full":"502 S Ridge Ave Troy OH 45373",
    "addr:housenumber":"502",
    "addr:postcode":"45373",
    "addr:street":"S Ridge Ave",
    "iso:country":"US",
    "sg:address":"502 S Ridge Ave",
    "sg:city":"Troy",
    "sg:classifiers":[
        {
            "category":"Wholesale",
            "subcategory":"Chemicals & Plastics",
            "type":"Manufacturing & Wholesale Goods"
        }
    ],
    "sg:phone":"+1 937 339 8069",
    "sg:postcode":"45373",
    "sg:province":"OH",
    "wof:name":"Dennis Burt & Associates",
    "wof:placetype":"venue"
},
  "geometry": {"coordinates":[-84.216821,40.036868],"type":"Point"}
}