{
  "type": "Feature",
  "properties": {
    "addr:full": "2261 River Rd Willoughby OH 44094",
    "addr:housenumber": "2261",
    "addr:postcode": "44094",
    "addr:street": "River Rd",
    "iso:country": "US",
    "sg:address": "2261 River Rd",
    "sg:city": "Willoughby",
    "sg:classifiers": [
      {
        "category": "Home \u0026 Garden",
        "subcategory": "Hardware",
        "type": "Retail Goods"
      }
    ],
    "sg:phone": "+1 440 915 7597",
    "sg:postcode": "44094",
    "sg:province": "OH",
    "sg:tags": [
      "tool",
      "rescue"
    ],
    "wof:name": "Midwest Rescue Products",
    "wof:placetype": "venue"
  },
  "geometry": {"coordinates":[-81.412718,41.611901],"type":"Point"}
}
