{
  "type": "Feature",
  "properties": {
    "addr:full":"5564 Wilson Mills Rd Cleveland OH 44143",
    "addr:housenumber":"5564",
    "addr:postcode":"44143",
    "addr:street":"Wilson Mills Rd",
    "iso:country":"US",
    "sg:address":"5564 Wilson Mills Rd",
    "sg:city":"Cleveland",
    "sg:classifiers":[
        {
            "category":"Professional",
            "subcategory":"Accounting & Tax Preparation",
            "type":"Services"
        }
    ],
    "sg:phone":"+1 440 684 0260",
    "sg:postcode":"44143",
    "sg:province":"OH",
    "sg:tags":[
        "return"
    ],
    "wof:name":"H & R Block",
    "wof:placetype":"venue"
},
  "geometry": {"coordinates":[-81.478537,41.538912],"type":"Point"}
}