{
  "type": "Feature",
  "properties": {
    "addr:full":"38 S Main St Monroe OH 45050",
    "addr:housenumber":"38",
    "addr:postcode":"45050",
    "addr:street":"S Main St",
    "iso:country":"US",
    "sg:address":"38 S Main St",
    "sg:city":"Monroe",
    "sg:classifiers":[
        {
            "category":"Building & Trades",
            "subcategory":"Construction",
            "type":"Services"
        }
    ],
    "sg:phone":"+1 513 539 2084",
    "sg:postcode":"45050",
    "sg:province":"OH",
    "sg:tags":[
        "handyman"
    ],
    "wof:name":"Stan The Handyman",
    "wof:placetype":"venue"
},
  "geometry": {"coordinates":[-84.362228,39.442718],"type":"Point"}
}