{
  "type": "Feature",
  "properties": {
    "addr:full":"375 W Elm St Lima OH 45801",
    "addr:housenumber":"375",
    "addr:postcode":"45801",
    "addr:street":"W Elm St",
    "iso:country":"US",
    "sg:address":"375 W Elm St",
    "sg:city":"Lima",
    "sg:classifiers":[
        {
            "category":"Health Services",
            "subcategory":"Chiropractor",
            "type":"Services"
        }
    ],
    "sg:phone":"+1 419 224 5678",
    "sg:postcode":"45801",
    "sg:province":"OH",
    "wof:name":"Rabe Chiropractic Clinic",
    "wof:placetype":"venue"
},
  "geometry": {"coordinates":[-84.109037,40.737219],"type":"Point"}
}