{
  "type": "Feature",
  "properties": {
    "addr:full":"2825 Burnet Ave Cincinnati OH 45219",
    "addr:housenumber":"2825",
    "addr:postcode":"45219",
    "addr:street":"Burnet Ave",
    "iso:country":"US",
    "sg:address":"2825 Burnet Ave",
    "sg:city":"Cincinnati",
    "sg:classifiers":[
        {
            "category":"Real Estate",
            "subcategory":"Real Estate Operator",
            "type":"Services"
        }
    ],
    "sg:phone":"+1 513 751 3129",
    "sg:postcode":"45219",
    "sg:province":"OH",
    "sg:tags":[
        "building",
        "parks"
    ],
    "wof:name":"Burnet Avenue Profesional Bldg",
    "wof:placetype":"venue"
},
  "geometry": {"coordinates":[-84.501434,39.132079],"type":"Point"}
}