{
  "type": "Feature",
  "properties": {
    "addr:full": "8322 E Kemper Rd Cincinnati OH 45249",
    "addr:housenumber": "8322",
    "addr:postcode": "45249",
    "addr:street": "E Kemper Rd",
    "iso:country": "US",
    "sg:address": "8322 E Kemper Rd",
    "sg:city": "Cincinnati",
    "sg:phone": "+1 513 489 7044",
    "sg:postcode": "45249",
    "sg:province": "OH",
    "wof:name": "Silver Spring House",
    "wof:placetype": "venue"
  },
  "geometry": {"coordinates":[-84.334204,39.275387],"type":"Point"}
}
