{
  "type": "Feature",
  "properties": {
    "iso:country":"US",
    "sg:address":"1187 W 8th St",
    "sg:city":"Cincinnati",
    "sg:classifiers":[
        {
            "category":"Building & Trades",
            "subcategory":"Construction",
            "type":"Services"
        }
    ],
    "sg:phone":"+1 513 871 7111",
    "sg:postcode":"45203",
    "sg:province":"OH",
    "sg:tags":[
        "contractor"
    ],
    "wof:name":"D G Frondorf & Associates",
    "wof:placetype":"venue"
},
  "geometry": {"coordinates":[-84.53517600000001,39.103873],"type":"Point"}
}