{
  "type": "Feature",
  "properties": {
    "addr:full": "8906 Co Rd 28 Jenera OH 45841",
    "addr:housenumber": "8906;28",
    "addr:postcode": "45841",
    "addr:street": "Co Rd",
    "iso:country": "US",
    "sg:address": "8906 Co Rd 28",
    "sg:city": "Jenera",
    "sg:phone": "+1 419 326 5541",
    "sg:postcode": "45841",
    "sg:province": "OH",
    "sg:tags": [
      "farm",
      "corn",
      "wheat",
      "soybean"
    ],
    "wof:name": "Carl Wilson",
    "wof:placetype": "venue"
  },
  "geometry": {"coordinates":[-83.721466,40.86317],"type":"Point"}
}
