{
  "type": "Feature",
  "properties": {
    "iso:country":"US",
    "sg:address":"515 E 11th St",
    "sg:city":"Port Clinton",
    "sg:classifiers":[
        {
            "category":"Retail",
            "subcategory":"Laundry & Dry Cleaning",
            "type":"Services"
        }
    ],
    "sg:phone":"+1 419 734 2643",
    "sg:postcode":"43452",
    "sg:province":"OH",
    "sg:tags":[
        "cleaners",
        "rug",
        "carpet"
    ],
    "wof:name":"Certified Cleaning",
    "wof:placetype":"venue"
},
  "geometry": {"coordinates":[-82.933549,41.50144],"type":"Point"}
}