{
  "type": "Feature",
  "properties": {
    "addr:full": "515 E 11th St Port Clinton OH 43452",
    "addr:housenumber": "515",
    "addr:postcode": "43452",
    "addr:street": "E 11Th St",
    "iso:country": "US",
    "sg:address": "515 E 11th St",
    "sg:city": "Port Clinton",
    "sg:classifiers": [
      {
        "category": "Retail",
        "subcategory": "Laundry \u0026 Dry Cleaning",
        "type": "Services"
      }
    ],
    "sg:phone": "+1 419 734 2643",
    "sg:postcode": "43452",
    "sg:province": "OH",
    "sg:tags": [
      "cleaners",
      "rug",
      "carpet"
    ],
    "wof:name": "Certified Cleaning",
    "wof:placetype": "venue"
  },
  "geometry": {"coordinates":[-82.933549,41.50144],"type":"Point"}
}
