{
  "type": "Feature",
  "properties": {
    "addr:full":"6210 Glenway Ave Cincinnati OH 45211",
    "addr:housenumber":"6210",
    "addr:postcode":"45211",
    "addr:street":"Glenway Ave",
    "iso:country":"US",
    "sg:address":"6210 Glenway Ave",
    "sg:city":"Cincinnati",
    "sg:classifiers":[
        {
            "category":"Real Estate",
            "subcategory":"Real Estate Agent",
            "type":"Services"
        }
    ],
    "sg:phone":"+1 513 661 8200",
    "sg:postcode":"45211",
    "sg:province":"OH",
    "wof:name":"Sibcy Cline Realtors",
    "wof:placetype":"venue"
},
  "geometry": {"coordinates":[-84.626963,39.147759],"type":"Point"}
}