{
  "type": "Feature",
  "properties": {
    "addr:full": "2093 Ewalt Ave NE Warren OH 44483",
    "addr:housenumber": "2093",
    "addr:postcode": "44483",
    "addr:street": "Ewalt Ave Ne",
    "iso:country": "US",
    "sg:address": "2093 Ewalt Ave NE",
    "sg:city": "Warren",
    "sg:classifiers": [
      {
        "category": "Organizations",
        "subcategory": "Religious Organization",
        "type": "Services"
      }
    ],
    "sg:phone": "+1 330 372 4801",
    "sg:postcode": "44483",
    "sg:province": "OH",
    "sg:tags": [
      "church"
    ],
    "wof:name": "Warren Baptist Temple",
    "wof:placetype": "venue"
  },
  "geometry": {"coordinates":[-80.79053,41.256307],"type":"Point"}
}
