{
  "type": "Feature",
  "properties": {
    "addr:full": "101 N Sandusky St Delaware OH 43015",
    "addr:housenumber": "101",
    "addr:postcode": "43015",
    "addr:street": "N Sandusky St",
    "iso:country": "US",
    "sg:address": "101 N Sandusky St",
    "sg:city": "Delaware",
    "sg:classifiers": [
      {
        "category": "Government",
        "subcategory": "Office",
        "type": "Public Place"
      }
    ],
    "sg:phone": "+1 740 368 1800",
    "sg:postcode": "43015",
    "sg:province": "OH",
    "sg:tags": [
      "executive"
    ],
    "wof:name": "County Of Delaware",
    "wof:placetype": "venue"
  },
  "geometry": {"coordinates":[-83.067414,40.302944],"type":"Point"}
}
