{
  "type": "Feature",
  "properties": {
    "addr:full":"939 Norton Ave Barberton OH 44203",
    "addr:housenumber":"939",
    "addr:postcode":"44203",
    "addr:street":"Norton Ave",
    "iso:country":"US",
    "sg:address":"939 Norton Ave",
    "sg:city":"Barberton",
    "sg:classifiers":[
        {
            "category":"Organizations",
            "subcategory":"Religious Organization",
            "type":"Services"
        }
    ],
    "sg:phone":"+1 330 753 2019",
    "sg:postcode":"44203",
    "sg:province":"OH",
    "sg:tags":[
        "church"
    ],
    "wof:name":"Summit Mennonite Church",
    "wof:placetype":"venue"
},
  "geometry": {"coordinates":[-81.62156,41.025282],"type":"Point"}
}