{
  "type": "Feature",
  "properties": {
    "addr:full": "1275 Kinnear Rd. Columbus OH 43212",
    "addr:housenumber": "1275",
    "addr:postcode": "43212",
    "addr:street": "Kinnear Rd.",
    "iso:country": "US",
    "sg:address": "1275 Kinnear Rd.",
    "sg:city": "Columbus",
    "sg:classifiers": [
      {
        "category": "Professional",
        "subcategory": "Computer Services",
        "type": "Services"
      }
    ],
    "sg:phone": "+1 800 728 2573",
    "sg:postcode": "43212",
    "sg:province": "OH",
    "sg:tags": [
      "ecommerce",
      "innovative"
    ],
    "sg:website": "http://www.BoundarylessBrands.com",
    "wof:name": "Boundaryless Brands",
    "wof:placetype": "venue"
  },
  "geometry": {"coordinates":[-83.047483,39.998677],"type":"Point"}
}
