{
  "type": "Feature",
  "properties": {
    "addr:full": "5086 Elno Ave Akron OH 44319",
    "addr:housenumber": "5086",
    "addr:postcode": "44319",
    "addr:street": "Elno Ave",
    "iso:country": "US",
    "sg:address": "5086 Elno Ave",
    "sg:city": "Akron",
    "sg:classifiers": [
      {
        "category": "Building \u0026 Trades",
        "subcategory": "Construction",
        "type": "Services"
      }
    ],
    "sg:phone": "+1 330 882 2597",
    "sg:postcode": "44319",
    "sg:province": "OH",
    "sg:tags": [
      "concrete",
      "contractor"
    ],
    "wof:name": "Clark Concrete",
    "wof:placetype": "venue"
  },
  "geometry": {"coordinates":[-81.537592,40.951247],"type":"Point"}
}
