{
  "type": "Feature",
  "properties": {
    "iso:country":"US",
    "sg:address":"7500 Old Oak Blvd",
    "sg:city":"Cleveland",
    "sg:classifiers":[
        {
            "category":"Manufacturing",
            "subcategory":"Printing",
            "type":"Manufacturing & Wholesale Goods"
        }
    ],
    "sg:phone":"+1 440 243 8100",
    "sg:postcode":"44130",
    "sg:province":"OH",
    "sg:tags":[
        "show",
        "marketing",
        "publish",
        "trade",
        "magazine",
        "operates",
        "con"
    ],
    "wof:name":"Advanstar Inc",
    "wof:placetype":"venue"
},
  "geometry": {"coordinates":[-81.833639,41.368771],"type":"Point"}
}