{
  "type": "Feature",
  "properties": {
    "addr:full":"750 S McCord Rd Holland OH 43528",
    "addr:housenumber":"750",
    "addr:postcode":"43528",
    "addr:street":"S Mccord Rd",
    "iso:country":"US",
    "sg:address":"750 S McCord Rd",
    "sg:city":"Holland",
    "sg:classifiers":[
        {
            "category":"Real Estate",
            "subcategory":"Real Estate Operator",
            "type":"Services"
        }
    ],
    "sg:phone":"+1 419 868 3400",
    "sg:postcode":"43528",
    "sg:province":"OH",
    "sg:tags":[
        "apartment"
    ],
    "wof:name":"Buddy Carr Mobile DJ Co",
    "wof:placetype":"venue"
},
  "geometry": {"coordinates":[-83.703428,41.628383],"type":"Point"}
}