{
  "type": "Feature",
  "properties": {
    "addr:full": "6230 Montgomery Rd Cincinnati OH 45213",
    "addr:housenumber": "6230",
    "addr:postcode": "45213",
    "addr:street": "Montgomery Rd",
    "iso:country": "US",
    "sg:address": "6230 Montgomery Rd",
    "sg:city": "Cincinnati",
    "sg:classifiers": [
      {
        "category": "Retail",
        "subcategory": "Auto Repair",
        "type": "Services"
      }
    ],
    "sg:phone": "+1 513 351 6026",
    "sg:postcode": "45213",
    "sg:province": "OH",
    "sg:tags": [
      "wrecker"
    ],
    "wof:name": "Reese Auto Svc \u0026 Towing",
    "wof:placetype": "venue"
  },
  "geometry": {"coordinates":[-84.423433,39.184073],"type":"Point"}
}
