{
  "type": "Feature",
  "properties": {
    "iso:country":"US",
    "sg:address":"921 Steubenville Ave",
    "sg:city":"Cambridge",
    "sg:classifiers":[
        {
            "category":"Professional",
            "type":"Services"
        }
    ],
    "sg:phone":"+1 740 432 1145",
    "sg:postcode":"43725",
    "sg:province":"OH",
    "sg:tags":[
        "establishment"
    ],
    "wof:name":"Ameridial",
    "wof:placetype":"venue"
},
  "geometry": {"coordinates":[-81.587478,40.026131],"type":"Point"}
}