{
  "type": "Feature",
  "properties": {
    "addr:full":"1914 Bailey Rd Cuyahoga Falls OH 44221",
    "addr:housenumber":"1914",
    "addr:postcode":"44221",
    "addr:street":"Bailey Rd",
    "iso:country":"US",
    "sg:address":"1914 Bailey Rd",
    "sg:city":"Cuyahoga Falls",
    "sg:classifiers":[
        {
            "category":"Shopping",
            "subcategory":"Pharmacy",
            "type":"Retail Goods"
        }
    ],
    "sg:phone":"+1 330 922 4466",
    "sg:postcode":"44221",
    "sg:province":"OH",
    "sg:website":"www.riteaid.com",
    "wof:name":"Rite Aid Pharmacy",
    "wof:placetype":"venue"
},
  "geometry": {"coordinates":[-81.466281,41.132991],"type":"Point"}
}