{
  "type": "Feature",
  "properties": {
    "addr:full":"5455 Salem Bend Dr Dayton OH 45426",
    "addr:housenumber":"5455",
    "addr:postcode":"45426",
    "addr:street":"Salem Bend Dr",
    "iso:country":"US",
    "sg:address":"5455 Salem Bend Dr",
    "sg:city":"Dayton",
    "sg:classifiers":[
        {
            "category":"Health Services",
            "subcategory":"Nursing And Care Facility",
            "type":"Services"
        }
    ],
    "sg:phone":"+1 937 854 5151",
    "sg:postcode":"45426",
    "sg:province":"OH",
    "sg:tags":[
        "home",
        "skilled",
        "convalescent"
    ],
    "wof:name":"Echoing Woods Residential Ctr",
    "wof:placetype":"venue"
},
  "geometry": {"coordinates":[-84.28662300000001,39.824771],"type":"Point"}
}