{
  "type": "Feature",
  "properties": {
    "addr:full":"7550 Lucerne Dr Cleveland OH 44130",
    "addr:housenumber":"7550",
    "addr:postcode":"44130",
    "addr:street":"Lucerne Dr",
    "iso:country":"US",
    "sg:address":"7550 Lucerne Dr",
    "sg:city":"Cleveland",
    "sg:classifiers":[
        {
            "category":"Building & Trades",
            "subcategory":"Construction",
            "type":"Services"
        }
    ],
    "sg:phone":"+1 440 826 3200",
    "sg:postcode":"44130",
    "sg:province":"OH",
    "sg:tags":[
        "hanging",
        "contractor"
    ],
    "wof:name":"Northrn OH Pntng & Tpng Contr",
    "wof:placetype":"venue"
},
  "geometry": {"coordinates":[-81.817138,41.357746],"type":"Point"}
}