{
  "type": "Feature",
  "properties": {
    "addr:full":"6511 Inland Shores Dr Mentor OH 44060",
    "addr:housenumber":"6511",
    "addr:postcode":"44060",
    "addr:street":"Inland Shores Dr",
    "iso:country":"US",
    "sg:address":"6511 Inland Shores Dr",
    "sg:city":"Mentor",
    "sg:classifiers":[
        {
            "category":"Building & Trades",
            "subcategory":"Construction",
            "type":"Services"
        }
    ],
    "sg:phone":"+1 440 209 8710",
    "sg:postcode":"44060",
    "sg:province":"OH",
    "sg:tags":[
        "home",
        "builder"
    ],
    "wof:name":"Zack Homes",
    "wof:placetype":"venue"
},
  "geometry": {"coordinates":[-81.370037,41.694627],"type":"Point"}
}