{
  "type": "Feature",
  "properties": {
    "iso:country":"US",
    "sg:address":"1257 Kieswetter Rd",
    "sg:city":"Holland",
    "sg:classifiers":[
        {
            "category":"Real Estate",
            "subcategory":"Real Estate Agent",
            "type":"Services"
        }
    ],
    "sg:phone":"+1 419 654 1926",
    "sg:postcode":"43528",
    "sg:province":"OH",
    "sg:tags":[
        "inspection"
    ],
    "wof:name":"Spring Meadows Home Inspection",
    "wof:placetype":"venue"
},
  "geometry": {"coordinates":[-83.751773,41.618755],"type":"Point"}
}