{
  "type": "Feature",
  "properties": {
    "addr:full": "111 E 2nd St Delphos OH 45833",
    "addr:housenumber": "111",
    "addr:postcode": "45833",
    "addr:street": "E 2Nd St",
    "iso:country": "US",
    "sg:address": "111 E 2nd St",
    "sg:city": "Delphos",
    "sg:classifiers": [
      {
        "category": "Communications",
        "subcategory": "Radio Station",
        "type": "Services"
      }
    ],
    "sg:phone": "+1 419 692 3963",
    "sg:postcode": "45833",
    "sg:province": "OH",
    "sg:tags": [
      "company",
      "broadcasting"
    ],
    "sg:website": "www.wdoh.com",
    "wof:name": "WDOH",
    "wof:placetype": "venue"
  },
  "geometry": {"coordinates":[-84.338545,40.843676],"type":"Point"}
}
