{
  "type": "Feature",
  "properties": {
    "iso:country":"US",
    "sg:address":"112 S Main St",
    "sg:city":"New Madison",
    "sg:classifiers":[
        {
            "category":"Personal",
            "subcategory":"Beauty Salon",
            "type":"Services"
        }
    ],
    "sg:phone":"+1 937 996 8571",
    "sg:postcode":"45346",
    "sg:province":"OH",
    "wof:name":"Main Street Styling Salon",
    "wof:placetype":"venue"
},
  "geometry": {"coordinates":[-84.709885,39.96785],"type":"Point"}
}