{
  "type": "Feature",
  "properties": {
    "iso:country":"US",
    "sg:address":"2338 Harrington Rd",
    "sg:city":"Akron",
    "sg:classifiers":[
        {
            "category":"Wholesale",
            "subcategory":"Non-durable Goods",
            "type":"Manufacturing & Wholesale Goods"
        }
    ],
    "sg:phone":"+1 330 773 1298",
    "sg:postcode":"44319",
    "sg:province":"OH",
    "wof:name":"Ohio Cardinal",
    "wof:placetype":"venue"
},
  "geometry": {"coordinates":[-81.510989,41.015156],"type":"Point"}
}