{
  "type": "Feature",
  "properties": {
    "addr:full": "979 Twp Rd 90 Mc Comb OH 45858",
    "addr:housenumber": "979;90",
    "addr:postcode": "45858",
    "addr:street": "Twp Rd;Mc Comb",
    "iso:country": "US",
    "sg:address": "979 Twp Rd 90",
    "sg:city": "Mc Comb",
    "sg:classifiers": [
      {
        "category": "Organizations",
        "subcategory": "Religious Organization",
        "type": "Services"
      }
    ],
    "sg:phone": "+1 419 293 3748",
    "sg:postcode": "45858",
    "sg:province": "OH",
    "sg:tags": [
      "church"
    ],
    "wof:name": "Pleasant Hill Bible Church",
    "wof:placetype": "venue"
  },
  "geometry": {"coordinates":[-83.864838,41.050983],"type":"Point"}
}
