{
  "type": "Feature",
  "properties": {
    "iso:country":"US",
    "sg:address":"1380 E 110th St",
    "sg:city":"Cleveland",
    "sg:classifiers":[
        {
            "category":"Shopping",
            "type":"Retail Goods"
        }
    ],
    "sg:phone":"+1 216 791 6641",
    "sg:postcode":"44106",
    "sg:province":"OH",
    "sg:tags":[
        "merchandise"
    ],
    "wof:name":"Vannessas Inguana Island",
    "wof:placetype":"venue"
},
  "geometry": {"coordinates":[-81.60941200000001,41.520612],"type":"Point"}
}