{
  "type": "Feature",
  "properties": {
    "iso:country":"US",
    "sg:address":"6465 Monroe St",
    "sg:city":"Sylvania",
    "sg:classifiers":[
        {
            "category":"Building & Trades",
            "subcategory":"Construction",
            "type":"Services"
        }
    ],
    "sg:phone":"+1 419 824 6074",
    "sg:postcode":"43560",
    "sg:province":"OH",
    "sg:tags":[
        "house"
    ],
    "wof:name":"Helm Homes Inc",
    "wof:placetype":"venue"
},
  "geometry": {"coordinates":[-83.702986,41.715531],"type":"Point"}
}