{
  "type": "Feature",
  "properties": {
    "iso:country":"US",
    "sg:address":"2101 River Rd",
    "sg:city":"Maumee",
    "sg:classifiers":[
        {
            "category":"Insurance",
            "subcategory":"Insurance Agent",
            "type":"Services"
        }
    ],
    "sg:phone":"+1 419 893 1995",
    "sg:postcode":"43537",
    "sg:province":"OH",
    "wof:name":"Allstate",
    "wof:placetype":"venue"
},
  "geometry": {"coordinates":[-83.62461399999999,41.574788],"type":"Point"}
}