{
  "type": "Feature",
  "properties": {
    "addr:full":"307 Market St Danville OH 43014",
    "addr:housenumber":"307",
    "addr:postcode":"43014",
    "addr:street":"Market St",
    "iso:country":"US",
    "sg:address":"307 Market St",
    "sg:city":"Danville",
    "sg:classifiers":[
        {
            "category":"Organizations",
            "subcategory":"Religious Organization",
            "type":"Services"
        }
    ],
    "sg:phone":"+1 740 599 6362",
    "sg:postcode":"43014",
    "sg:province":"OH",
    "sg:tags":[
        "church"
    ],
    "wof:name":"St Luke Catholic Church",
    "wof:placetype":"venue"
},
  "geometry": {"coordinates":[-82.260417,40.448421],"type":"Point"}
}