{
  "type": "Feature",
  "properties": {
    "iso:country":"US",
    "sg:address":"225 S Main St",
    "sg:city":"Mt Vernon",
    "sg:classifiers":[
        {
            "category":"Shopping",
            "subcategory":"Crafts & Fabrics",
            "type":"Retail Goods"
        }
    ],
    "sg:phone":"+1 740 393 7463",
    "sg:postcode":"43050",
    "sg:province":"OH",
    "sg:tags":[
        "material",
        "quilting",
        "supply"
    ],
    "sg:website":"www.jordansquilt.com",
    "wof:name":"Jordan's Quilt Shop",
    "wof:placetype":"venue"
},
  "geometry": {"coordinates":[-82.485708,40.391426],"type":"Point"}
}