{
  "type": "Feature",
  "properties": {
    "iso:country":"US",
    "sg:address":"500 Gressel Dr",
    "sg:city":"Delphos",
    "sg:classifiers":[
        {
            "category":"Retail",
            "subcategory":"Auto Repair",
            "type":"Services"
        }
    ],
    "sg:phone":"+1 419 692 2012",
    "sg:postcode":"45833",
    "sg:province":"OH",
    "sg:tags":[
        "truck"
    ],
    "wof:name":"KIRK Nationalease Co",
    "wof:placetype":"venue"
},
  "geometry": {"coordinates":[-84.32249299999999,40.848697],"type":"Point"}
}