{
  "type": "Feature",
  "properties": {
    "addr:full":"4 Arms Blvd Niles OH 44446",
    "addr:housenumber":"4",
    "addr:postcode":"44446",
    "addr:street":"Arms Blvd",
    "iso:country":"US",
    "sg:address":"4 Arms Blvd",
    "sg:city":"Niles",
    "sg:classifiers":[
        {
            "category":"Real Estate",
            "subcategory":"Real Estate Operator",
            "type":"Services"
        }
    ],
    "sg:phone":"+1 330 652 9934",
    "sg:postcode":"44446",
    "sg:province":"OH",
    "sg:tags":[
        "apartment"
    ],
    "wof:name":"Eastwood Arms Apartments",
    "wof:placetype":"venue"
},
  "geometry": {"coordinates":[-80.748964,41.196985],"type":"Point"}
}