{
  "type": "Feature",
  "properties": {
    "iso:country":"US",
    "sg:address":"5737 Dry Fork Rd",
    "sg:city":"Cleves",
    "sg:classifiers":[
        {
            "category":"Building & Trades",
            "subcategory":"Construction",
            "type":"Services"
        }
    ],
    "sg:phone":"+1 513 367 0218",
    "sg:postcode":"45002",
    "sg:province":"OH",
    "sg:tags":[
        "water",
        "line",
        "sewer"
    ],
    "wof:name":"Smith Larry Plumbing",
    "wof:placetype":"venue"
},
  "geometry": {"coordinates":[-84.770285,39.221612],"type":"Point"}
}