{
  "type": "Feature",
  "properties": {
    "addr:full": "5140 Pleasant Ave Fairfield OH 45014",
    "addr:housenumber": "5140",
    "addr:postcode": "45014",
    "addr:street": "Pleasant Ave",
    "iso:country": "US",
    "sg:address": "5140 Pleasant Ave",
    "sg:city": "Fairfield",
    "sg:classifiers": [
      {
        "category": "Shopping",
        "subcategory": "Computers \u0026 Home Electronics",
        "type": "Retail Goods"
      }
    ],
    "sg:phone": "+1 513 863 0092",
    "sg:postcode": "45014",
    "sg:province": "OH",
    "sg:tags": [
      "equipment",
      "dealer"
    ],
    "wof:name": "Count Master",
    "wof:placetype": "venue"
  },
  "geometry": {"coordinates":[-84.560124,39.337733],"type":"Point"}
}
