{
  "type": "Feature",
  "properties": {
    "iso:country":"US",
    "sg:address":"11157 State Rte 41",
    "sg:city":"West Union",
    "sg:classifiers":[
        {
            "category":"Restaurant",
            "type":"Food & Drink"
        }
    ],
    "sg:phone":"+1 937 544 8985",
    "sg:postcode":"45693",
    "sg:province":"OH",
    "wof:name":"Frisch's Big Boy Restaurant",
    "wof:placetype":"venue"
},
  "geometry": {"coordinates":[-83.56527,38.780516],"type":"Point"}
}