{
  "type": "Feature",
  "properties": {
    "iso:country":"US",
    "sg:address":"126 Prospect St",
    "sg:city":"Wellington",
    "sg:classifiers":[
        {
            "category":"Professional",
            "type":"Services"
        }
    ],
    "sg:phone":"+1 440 647 3535",
    "sg:postcode":"44090",
    "sg:province":"OH",
    "wof:name":"Supreme Pythian Sisters",
    "wof:placetype":"venue"
},
  "geometry": {"coordinates":[-82.220502,41.166697],"type":"Point"}
}