{
  "type": "Feature",
  "properties": {
    "addr:full":"18001 Euclid Ave Cleveland OH 44112",
    "addr:housenumber":"18001",
    "addr:postcode":"44112",
    "addr:street":"Euclid Ave",
    "iso:country":"US",
    "sg:address":"18001 Euclid Ave",
    "sg:city":"Cleveland",
    "sg:classifiers":[
        {
            "category":"Retail",
            "subcategory":"Veterinary Services",
            "type":"Services"
        }
    ],
    "sg:phone":"+1 216 531 7766",
    "sg:postcode":"44112",
    "sg:province":"OH",
    "wof:name":"L Messer Dvm",
    "wof:placetype":"venue"
},
  "geometry": {"coordinates":[-81.55271999999999,41.555136],"type":"Point"}
}