{
  "type": "Feature",
  "properties": {
    "iso:country":"US",
    "sg:address":"3104 Leon Ave",
    "sg:city":"Columbus",
    "sg:classifiers":[
        {
            "category":"Professional",
            "type":"Services"
        }
    ],
    "sg:phone":"+1 614 475 7318",
    "sg:postcode":"43219",
    "sg:province":"OH",
    "wof:name":"Tykiah Wright",
    "wof:placetype":"venue"
},
  "geometry": {"coordinates":[-82.92818699999999,40.015937],"type":"Point"}
}