{
  "type": "Feature",
  "properties": {
    "iso:country":"US",
    "sg:address":"4299 Cranwood Pkwy",
    "sg:city":"Cleveland",
    "sg:classifiers":[
        {
            "category":"Building & Trades",
            "subcategory":"Construction",
            "type":"Services"
        }
    ],
    "sg:phone":"+1 216 581 4700",
    "sg:postcode":"44128",
    "sg:province":"OH",
    "sg:tags":[
        "remodeling",
        "new",
        "general",
        "commercial",
        "contractor"
    ],
    "wof:name":"Downing Construction Company",
    "wof:placetype":"venue"
},
  "geometry": {"coordinates":[-81.547484,41.439023],"type":"Point"}
}