{
  "type": "Feature",
  "properties": {
    "addr:full": "4299 Cranwood Pkwy Cleveland OH 44128",
    "addr:housenumber": "4299",
    "addr:postcode": "44128",
    "addr:street": "Cranwood Pkwy",
    "iso:country": "US",
    "sg:address": "4299 Cranwood Pkwy",
    "sg:city": "Cleveland",
    "sg:classifiers": [
      {
        "category": "Building \u0026 Trades",
        "subcategory": "Construction",
        "type": "Services"
      }
    ],
    "sg:phone": "+1 216 581 4700",
    "sg:postcode": "44128",
    "sg:province": "OH",
    "sg:tags": [
      "remodeling",
      "new",
      "general",
      "commercial",
      "contractor"
    ],
    "wof:name": "Downing Construction Company",
    "wof:placetype": "venue"
  },
  "geometry": {"coordinates":[-81.547484,41.439023],"type":"Point"}
}
