{
  "type": "Feature",
  "properties": {
    "addr:full":"3279 W 34th St Cleveland OH 44109",
    "addr:housenumber":"3279",
    "addr:postcode":"44109",
    "addr:street":"W 34Th St",
    "iso:country":"US",
    "sg:address":"3279 W 34th St",
    "sg:city":"Cleveland",
    "sg:classifiers":[
        {
            "category":"Social Services",
            "subcategory":"Child Care",
            "type":"Services"
        }
    ],
    "sg:phone":"+1 216 749 5465",
    "sg:postcode":"44109",
    "sg:province":"OH",
    "wof:name":"J J's Daycare",
    "wof:placetype":"venue"
},
  "geometry": {"coordinates":[-81.70639300000001,41.465435],"type":"Point"}
}