{
  "type": "Feature",
  "properties": {
    "iso:country":"US",
    "sg:address":"600 N Pickaway St",
    "sg:city":"Circleville",
    "sg:classifiers":[
        {
            "category":"Health Services",
            "subcategory":"Hospital",
            "type":"Services"
        }
    ],
    "sg:phone":"+1 740 474 2126",
    "sg:postcode":"43113",
    "sg:province":"OH",
    "sg:website":"www.bergerhealth.com",
    "wof:name":"Berger Health System",
    "wof:placetype":"venue"
},
  "geometry": {"coordinates":[-82.938011,39.609694],"type":"Point"}
}