{
  "type": "Feature",
  "properties": {
    "iso:country":"US",
    "sg:address":"4663 W Bancroft St",
    "sg:city":"Toledo",
    "sg:classifiers":[
        {
            "category":"Social Services",
            "type":"Services"
        }
    ],
    "sg:phone":"+1 419 535 7950",
    "sg:postcode":"43615",
    "sg:province":"OH",
    "sg:tags":[
        "worker"
    ],
    "wof:name":"Patricia Allen Inc",
    "wof:placetype":"venue"
},
  "geometry": {"coordinates":[-83.649635,41.662365],"type":"Point"}
}