{
  "type": "Feature",
  "properties": {
    "addr:full": "1813 Maiden Ln Springfield OH 45504",
    "addr:housenumber": "1813",
    "addr:postcode": "45504",
    "addr:street": "Maiden Ln",
    "iso:country": "US",
    "sg:address": "1813 Maiden Ln",
    "sg:city": "Springfield",
    "sg:classifiers": [
      {
        "category": "Organizations",
        "subcategory": "Religious Organization",
        "type": "Services"
      }
    ],
    "sg:phone": "+1 937 325 0253",
    "sg:postcode": "45504",
    "sg:province": "OH",
    "sg:tags": [
      "clergy"
    ],
    "wof:name": "C Richard Robinson",
    "wof:placetype": "venue"
  },
  "geometry": {"coordinates":[-83.839427,39.929763],"type":"Point"}
}
