{
  "type": "Feature",
  "properties": {
    "addr:full": "7771 Broadway Ave Cleveland OH 44105",
    "addr:housenumber": "7771",
    "addr:postcode": "44105",
    "addr:street": "Broadway Ave",
    "iso:country": "US",
    "sg:address": "7771 Broadway Ave",
    "sg:city": "Cleveland",
    "sg:classifiers": [
      {
        "category": "Bars \u0026 Pubs",
        "type": "Food \u0026 Drink"
      }
    ],
    "sg:phone": "+1 216 341 7778",
    "sg:postcode": "44105",
    "sg:province": "OH",
    "sg:tags": [
      "drinking"
    ],
    "wof:name": "Bum's Saloon",
    "wof:placetype": "venue"
  },
  "geometry": {"coordinates":[-81.633472,41.453928],"type":"Point"}
}
