{
  "type": "Feature",
  "properties": {
    "iso:country":"US",
    "sg:address":"4800 Sinclair Rd",
    "sg:city":"Columbus",
    "sg:classifiers":[
        {
            "category":"Autos & Motor Vehicles",
            "subcategory":"Auto Supplies",
            "type":"Retail Goods"
        }
    ],
    "sg:phone":"+1 614 436 6336",
    "sg:postcode":"43229",
    "sg:province":"OH",
    "sg:website":"www.ntb.com",
    "wof:name":"National Tire & Battery",
    "wof:placetype":"venue"
},
  "geometry": {"coordinates":[-82.998587,40.064457],"type":"Point"}
}