{
  "type": "Feature",
  "properties": {
    "addr:full": "4800 Sinclair Rd Columbus OH 43229",
    "addr:housenumber": "4800",
    "addr:postcode": "43229",
    "addr:street": "Sinclair Rd",
    "iso:country": "US",
    "sg:address": "4800 Sinclair Rd",
    "sg:city": "Columbus",
    "sg:classifiers": [
      {
        "category": "Autos \u0026 Motor Vehicles",
        "subcategory": "Auto Supplies",
        "type": "Retail Goods"
      }
    ],
    "sg:phone": "+1 614 436 6336",
    "sg:postcode": "43229",
    "sg:province": "OH",
    "sg:website": "www.ntb.com",
    "wof:name": "National Tire \u0026 Battery",
    "wof:placetype": "venue"
  },
  "geometry": {"coordinates":[-82.998587,40.064457],"type":"Point"}
}
