{
  "type": "Feature",
  "properties": {
    "addr:full":"200 1st St SE Barberton OH 44203",
    "addr:housenumber":"200",
    "addr:postcode":"44203",
    "addr:street":"1St St Se",
    "iso:country":"US",
    "sg:address":"200 1st St SE",
    "sg:city":"Barberton",
    "sg:classifiers":[
        {
            "category":"Health Services",
            "subcategory":"Doctor",
            "type":"Services"
        }
    ],
    "sg:phone":"+1 330 753 7772",
    "sg:postcode":"44203",
    "sg:province":"OH",
    "sg:tags":[
        "medical"
    ],
    "wof:name":"Dooley J L DPM Inc",
    "wof:placetype":"venue"
},
  "geometry": {"coordinates":[-81.59802999999999,41.002854],"type":"Point"}
}