{
  "type": "Feature",
  "properties": {
    "addr:full": "1165 Sunnyview Ln Wooster OH 44691",
    "addr:housenumber": "1165",
    "addr:postcode": "44691",
    "addr:street": "Sunnyview Ln",
    "iso:country": "US",
    "sg:address": "1165 Sunnyview Ln",
    "sg:city": "Wooster",
    "sg:classifiers": [
      {
        "category": "Real Estate",
        "subcategory": "Real Estate Operator",
        "type": "Services"
      }
    ],
    "sg:phone": "+1 330 262 6909",
    "sg:postcode": "44691",
    "sg:province": "OH",
    "sg:tags": [
      "building",
      "nonresidential"
    ],
    "wof:name": "Raber Properties LLC",
    "wof:placetype": "venue"
  },
  "geometry": {"coordinates":[-81.965185,40.781543],"type":"Point"}
}
