{
  "type": "Feature",
  "properties": {
    "iso:country":"US",
    "sg:address":"124 E Wayne St",
    "sg:city":"Lima",
    "sg:classifiers":[
        {
            "category":"Retail",
            "subcategory":"Auto Repair",
            "type":"Services"
        }
    ],
    "sg:phone":"+1 419 224 3793",
    "sg:postcode":"45801",
    "sg:province":"OH",
    "sg:tags":[
        "body",
        "automobile",
        "painting"
    ],
    "wof:name":"Frame Specialist",
    "wof:placetype":"venue"
},
  "geometry": {"coordinates":[-84.10441400000001,40.743957],"type":"Point"}
}