{
  "type": "Feature",
  "properties": {
    "iso:country":"US",
    "sg:address":"1010 N Union Ave",
    "sg:city":"Alliance",
    "sg:classifiers":[
        {
            "category":"Manufacturing",
            "subcategory":"Chemicals & Compounds",
            "type":"Manufacturing & Wholesale Goods"
        }
    ],
    "sg:phone":"+1 330 821 1050",
    "sg:postcode":"44601",
    "sg:province":"OH",
    "sg:tags":[
        "paint",
        "varnish",
        "allied",
        "product"
    ],
    "wof:name":"Stewart Brothers Paint Co",
    "wof:placetype":"venue"
},
  "geometry": {"coordinates":[-81.105875,40.931653],"type":"Point"}
}