{
  "type": "Feature",
  "properties": {
    "addr:full": "1010 N Union Ave Alliance OH 44601",
    "addr:housenumber": "1010",
    "addr:postcode": "44601",
    "addr:street": "N Union Ave",
    "iso:country": "US",
    "sg:address": "1010 N Union Ave",
    "sg:city": "Alliance",
    "sg:classifiers": [
      {
        "category": "Manufacturing",
        "subcategory": "Chemicals \u0026 Compounds",
        "type": "Manufacturing \u0026 Wholesale Goods"
      }
    ],
    "sg:phone": "+1 330 821 1050",
    "sg:postcode": "44601",
    "sg:province": "OH",
    "sg:tags": [
      "paint",
      "varnish",
      "allied",
      "product"
    ],
    "wof:name": "Stewart Brothers Paint Co",
    "wof:placetype": "venue"
  },
  "geometry": {"coordinates":[-81.105875,40.931653],"type":"Point"}
}
