{
  "type": "Feature",
  "properties": {
    "addr:full": "2516 Winton St NW Canton OH 44709",
    "addr:housenumber": "2516",
    "addr:postcode": "44709",
    "addr:street": "Winton St Nw",
    "iso:country": "US",
    "sg:address": "2516 Winton St NW",
    "sg:city": "Canton",
    "sg:classifiers": [
      {
        "category": "Building \u0026 Trades",
        "subcategory": "Plumbing",
        "type": "Services"
      }
    ],
    "sg:phone": "+1 330 492 2054",
    "sg:postcode": "44709",
    "sg:province": "OH",
    "sg:tags": [
      "contractor"
    ],
    "wof:name": "Economical Mech Maint",
    "wof:placetype": "venue"
  },
  "geometry": {"coordinates":[-81.402114,40.847124],"type":"Point"}
}
