{
  "type": "Feature",
  "properties": {
    "iso:country":"US",
    "sg:address":"8714 Scenicview Dr",
    "sg:city":"Broadview Heights",
    "sg:classifiers":[
        {
            "category":"Real Estate",
            "subcategory":"Real Estate Operator",
            "type":"Services"
        }
    ],
    "sg:phone":"+1 440 582 2989",
    "sg:postcode":"44147",
    "sg:province":"OH",
    "sg:tags":[
        "building",
        "nonresidential"
    ],
    "wof:name":"Niederst Properties",
    "wof:placetype":"venue"
},
  "geometry": {"coordinates":[-81.698927,41.330576],"type":"Point"}
}