{
  "type": "Feature",
  "properties": {
    "iso:country":"US",
    "sg:address":"358 N Parkview Ave",
    "sg:city":"Columbus",
    "sg:classifiers":[
        {
            "category":"Government",
            "subcategory":"Office",
            "type":"Public Place"
        }
    ],
    "sg:phone":"+1 614 644 7644",
    "sg:postcode":"43209",
    "sg:province":"OH",
    "sg:tags":[
        "general"
    ],
    "wof:name":"State Ohio Governors Residence",
    "wof:placetype":"venue"
},
  "geometry": {"coordinates":[-82.940685,39.975989],"type":"Point"}
}