{
  "type": "Feature",
  "properties": {
    "addr:full":"1175 E Wyandot Ave Upper Sandusky OH 43351",
    "addr:housenumber":"1175 e",
    "addr:postcode":"43351",
    "addr:street":"Wyandot Ave",
    "iso:country":"US",
    "sg:address":"1175 E Wyandot Ave",
    "sg:city":"Upper Sandusky",
    "sg:classifiers":[
        {
            "category":"Building & Trades",
            "subcategory":"Equipment Rental",
            "type":"Services"
        }
    ],
    "sg:phone":"+1 419 294 2242",
    "sg:postcode":"43351",
    "sg:province":"OH",
    "sg:tags":[
        "yard"
    ],
    "sg:website":"www.rentway.com",
    "wof:name":"Rent Way",
    "wof:placetype":"venue"
},
  "geometry": {"coordinates":[-83.260564,40.8298],"type":"Point"}
}