{
  "type": "Feature",
  "properties": {
    "addr:full":"2798 Belgrave Rd Cleveland OH 44124",
    "addr:housenumber":"2798",
    "addr:postcode":"44124",
    "addr:street":"Belgrave Rd",
    "iso:country":"US",
    "sg:address":"2798 Belgrave Rd",
    "sg:city":"Cleveland",
    "sg:classifiers":[
        {
            "category":"Professional",
            "type":"Services"
        }
    ],
    "sg:phone":"+1 216 292 5916",
    "sg:postcode":"44124",
    "sg:province":"OH",
    "wof:name":"Betsy K Kohn",
    "wof:placetype":"venue"
},
  "geometry": {"coordinates":[-81.47689200000001,41.489938],"type":"Point"}
}