{
  "type": "Feature",
  "properties": {
    "addr:full":"35 S Paint St Chillicothe OH 45601",
    "addr:housenumber":"35",
    "addr:postcode":"45601",
    "addr:street":"S Paint St",
    "iso:country":"US",
    "sg:address":"35 S Paint St",
    "sg:city":"Chillicothe",
    "sg:classifiers":[
        {
            "category":"Recreation",
            "type":"Entertainment"
        }
    ],
    "sg:phone":"+1 740 772 5626",
    "sg:postcode":"45601",
    "sg:province":"OH",
    "sg:tags":[
        "parks"
    ],
    "wof:name":"Chillicothe Parks & Recreation",
    "wof:placetype":"venue"
},
  "geometry": {"coordinates":[-82.981951,39.332584],"type":"Point"}
}