{
  "type": "Feature",
  "properties": {
    "addr:full": "5501 Dunham Rd Maple Heights OH 44137",
    "addr:housenumber": "5501",
    "addr:postcode": "44137",
    "addr:street": "Dunham Rd",
    "iso:country": "US",
    "sg:address": "5501 Dunham Rd",
    "sg:city": "Maple Heights",
    "sg:classifiers": [
      {
        "category": "Local Transit",
        "type": "Transportation"
      }
    ],
    "sg:phone": "+1 216 662 6075",
    "sg:postcode": "44137",
    "sg:province": "OH",
    "sg:tags": [
      "bus"
    ],
    "wof:name": "Maple Heights Transit Dept",
    "wof:placetype": "venue"
  },
  "geometry": {"coordinates":[-81.575313,41.409158],"type":"Point"}
}
