{
  "type": "Feature",
  "properties": {
    "addr:full": "33200 Bainbridge Rd Cleveland OH 44139",
    "addr:housenumber": "33200",
    "addr:postcode": "44139",
    "addr:street": "Bainbridge Rd",
    "iso:country": "US",
    "sg:address": "33200 Bainbridge Rd",
    "sg:city": "Cleveland",
    "sg:classifiers": [
      {
        "category": "Retail",
        "subcategory": "Repair Shop",
        "type": "Services"
      }
    ],
    "sg:phone": "+1 440 248 8933",
    "sg:postcode": "44139",
    "sg:province": "OH",
    "sg:tags": [
      "television",
      "radio"
    ],
    "wof:name": "Patio TV Of Solon",
    "wof:placetype": "venue"
  },
  "geometry": {"coordinates":[-81.44208,41.38974],"type":"Point"}
}
