{
  "type": "Feature",
  "properties": {
    "addr:full":"1683 Smith Rd Columbus OH 43207",
    "addr:housenumber":"1683",
    "addr:postcode":"43207",
    "addr:street":"Smith Rd",
    "iso:country":"US",
    "sg:address":"1683 Smith Rd",
    "sg:city":"Columbus",
    "sg:classifiers":[
        {
            "category":"Real Estate",
            "subcategory":"Real Estate Services",
            "type":"Services"
        },
        {
            "category":"Real Estate",
            "subcategory":"Real Estate Operator",
            "type":"Services"
        }
    ],
    "sg:phone":"+1 614 443 5650",
    "sg:postcode":"43207",
    "sg:province":"OH",
    "sg:tags":[
        "vacancy",
        "apartment",
        "rental",
        "listing"
    ],
    "wof:name":"Fair Oaks Housing Limited Partnership",
    "wof:placetype":"venue"
},
  "geometry": {"coordinates":[-82.950334,39.927062],"type":"Point"}
}