{
  "type": "Feature",
  "properties": {
    "iso:country":"US",
    "sg:address":"2400 Refugee Rd",
    "sg:city":"Columbus",
    "sg:classifiers":[
        {
            "category":"Building & Trades",
            "subcategory":"Construction",
            "type":"Services"
        }
    ],
    "sg:phone":"+1 614 449 8035",
    "sg:postcode":"43207",
    "sg:province":"OH",
    "wof:name":"Nacom",
    "wof:placetype":"venue"
},
  "geometry": {"coordinates":[-82.933284,39.921507],"type":"Point"}
}