{
  "type": "Feature",
  "properties": {
    "addr:full": "2400 Refugee Rd Columbus OH 43207",
    "addr:housenumber": "2400",
    "addr:postcode": "43207",
    "addr:street": "Refugee Rd",
    "iso:country": "US",
    "sg:address": "2400 Refugee Rd",
    "sg:city": "Columbus",
    "sg:classifiers": [
      {
        "category": "Building \u0026 Trades",
        "subcategory": "Construction",
        "type": "Services"
      }
    ],
    "sg:phone": "+1 614 449 8035",
    "sg:postcode": "43207",
    "sg:province": "OH",
    "wof:name": "Nacom",
    "wof:placetype": "venue"
  },
  "geometry": {"coordinates":[-82.933284,39.921507],"type":"Point"}
}
