{
  "type": "Feature",
  "properties": {
    "addr:full": "349 Country Club Dr Xenia OH 45385",
    "addr:housenumber": "349",
    "addr:postcode": "45385",
    "addr:street": "Country Club Dr",
    "iso:country": "US",
    "sg:address": "349 Country Club Dr",
    "sg:city": "Xenia",
    "sg:classifiers": [
      {
        "category": "Building \u0026 Trades",
        "subcategory": "Plumbing",
        "type": "Services"
      }
    ],
    "sg:phone": "+1 937 372 8240",
    "sg:postcode": "45385",
    "sg:province": "OH",
    "sg:tags": [
      "plumbing",
      "contractor"
    ],
    "wof:name": "Cyphers Plumbing",
    "wof:placetype": "venue"
  },
  "geometry": {"coordinates":[-83.926165,39.703655],"type":"Point"}
}
