{
  "type": "Feature",
  "properties": {
    "iso:country":"US",
    "sg:address":"425 E State St",
    "sg:city":"Fremont",
    "sg:classifiers":[
        {
            "category":"Retail",
            "subcategory":"Funeral Services",
            "type":"Services"
        }
    ],
    "sg:phone":"+1 419 332 6409",
    "sg:postcode":"43420",
    "sg:province":"OH",
    "sg:tags":[
        "mortuary"
    ],
    "sg:website":"www.wonderlyhorvath.com",
    "wof:name":"Wonderly-Horvath Funeral Home",
    "wof:placetype":"venue"
},
  "geometry": {"coordinates":[-83.106987,41.345603],"type":"Point"}
}