{
  "type": "Feature",
  "properties": {
    "addr:full": "4036 Hendrickson Rd Franklin OH 45005",
    "addr:housenumber": "4036",
    "addr:postcode": "45005",
    "addr:street": "Hendrickson Rd",
    "iso:country": "US",
    "sg:address": "4036 Hendrickson Rd",
    "sg:city": "Franklin",
    "sg:classifiers": [
      {
        "category": "Wholesale",
        "subcategory": "Non-durable Goods",
        "type": "Manufacturing \u0026 Wholesale Goods"
      }
    ],
    "sg:phone": "+1 513 424 4965",
    "sg:postcode": "45005",
    "sg:province": "OH",
    "wof:name": "Longaberger Baskets",
    "wof:placetype": "venue"
  },
  "geometry": {"coordinates":[-84.280957,39.477956],"type":"Point"}
}
