{
  "type": "Feature",
  "properties": {
    "addr:full": "11183 Ottawa Dr Ottawa OH 45875",
    "addr:housenumber": "11183",
    "addr:postcode": "45875",
    "addr:street": "Ottawa Dr",
    "iso:country": "US",
    "sg:address": "11183 Ottawa Dr",
    "sg:city": "Ottawa",
    "sg:classifiers": [
      {
        "category": "Building \u0026 Trades",
        "subcategory": "Landscaping Services",
        "type": "Services"
      }
    ],
    "sg:phone": "+1 419 523 4342",
    "sg:postcode": "45875",
    "sg:province": "OH",
    "sg:tags": [
      "lawn",
      "maintenance",
      "grounds"
    ],
    "wof:name": "Morman's Lawncare",
    "wof:placetype": "venue"
  },
  "geometry": {"coordinates":[-84.006385,41.020477],"type":"Point"}
}
