{
  "type": "Feature",
  "properties": {
    "iso:country":"US",
    "sg:address":"113 W Wheeling St",
    "sg:city":"Lancaster",
    "sg:classifiers":[
        {
            "category":"Personal",
            "subcategory":"Beauty Salon",
            "type":"Services"
        }
    ],
    "sg:phone":"+1 740 654 7263",
    "sg:postcode":"43130",
    "sg:province":"OH",
    "sg:tags":[
        "shop"
    ],
    "wof:name":"Julia's Grand Salon & Spa",
    "wof:placetype":"venue"
},
  "geometry": {"coordinates":[-82.60297199999999,39.715065],"type":"Point"}
}