{
  "type": "Feature",
  "properties": {
    "addr:full": "4953 Delhi Ave Cincinnati OH 45238",
    "addr:housenumber": "4953",
    "addr:postcode": "45238",
    "addr:street": "Delhi Ave",
    "iso:country": "US",
    "sg:address": "4953 Delhi Ave",
    "sg:city": "Cincinnati",
    "sg:classifiers": [
      {
        "category": "Insurance",
        "subcategory": "Insurance Agent",
        "type": "Services"
      }
    ],
    "sg:phone": "+1 513 451 5205",
    "sg:postcode": "45238",
    "sg:province": "OH",
    "wof:name": "Richard C Curry Jr Ins",
    "wof:placetype": "venue"
  },
  "geometry": {"coordinates":[-84.607678,39.095249],"type":"Point"}
}
