{
  "type": "Feature",
  "properties": {
    "addr:full":"2274 Kresge Dr Amherst OH 44001",
    "addr:housenumber":"2274",
    "addr:postcode":"44001",
    "addr:street":"Kresge Dr",
    "iso:country":"US",
    "sg:address":"2274 Kresge Dr",
    "sg:city":"Amherst",
    "sg:classifiers":[
        {
            "category":"Health Services",
            "subcategory":"Medical Lab",
            "type":"Services"
        }
    ],
    "sg:phone":"+1 440 282 4055",
    "sg:postcode":"44001",
    "sg:province":"OH",
    "sg:tags":[
        "laboratory"
    ],
    "wof:name":"Miller Dental Laboratory",
    "wof:placetype":"venue"
},
  "geometry": {"coordinates":[-82.207391,41.416681],"type":"Point"}
}