{
  "type": "Feature",
  "properties": {
    "addr:full": "3946 Lansdale Rd Cleveland OH 44118",
    "addr:housenumber": "3946",
    "addr:postcode": "44118",
    "addr:street": "Lansdale Rd",
    "iso:country": "US",
    "sg:address": "3946 Lansdale Rd",
    "sg:city": "Cleveland",
    "sg:classifiers": [
      {
        "category": "Insurance",
        "subcategory": "Insurance Agent",
        "type": "Services"
      }
    ],
    "sg:phone": "+1 216 321 5674",
    "sg:postcode": "44118",
    "sg:province": "OH",
    "sg:tags": [
      "consultant",
      "compensation"
    ],
    "wof:name": "Transitional Work Systems",
    "wof:placetype": "venue"
  },
  "geometry": {"coordinates":[-81.536794,41.499529],"type":"Point"}
}
