{
  "type": "Feature",
  "properties": {
    "addr:full": "4395 Clime Rd Columbus OH 43228",
    "addr:housenumber": "4395",
    "addr:postcode": "43228",
    "addr:street": "Clime Rd",
    "iso:country": "US",
    "sg:address": "4395 Clime Rd",
    "sg:city": "Columbus",
    "sg:classifiers": [
      {
        "category": "Wholesale",
        "subcategory": "Plants",
        "type": "Manufacturing \u0026 Wholesale Goods"
      },
      {
        "category": "Wholesale",
        "subcategory": "Non-durable Goods",
        "type": "Manufacturing \u0026 Wholesale Goods"
      }
    ],
    "sg:phone": "+1 614 275 6220",
    "sg:postcode": "43228",
    "sg:province": "OH",
    "sg:tags": [
      "florist",
      "toy",
      "sup"
    ],
    "wof:name": "Flower Factory Inc",
    "wof:placetype": "venue"
  },
  "geometry": {"coordinates":[-83.112979,39.932242],"type":"Point"}
}
