{
  "type": "Feature",
  "properties": {
    "addr:full": "29149 Euclid Ave Wickliffe OH 44092",
    "addr:housenumber": "29149",
    "addr:postcode": "44092",
    "addr:street": "Euclid Ave",
    "iso:country": "US",
    "sg:address": "29149 Euclid Ave",
    "sg:city": "Wickliffe",
    "sg:classifiers": [
      {
        "category": "Building \u0026 Trades",
        "subcategory": "Cleaning \u0026 Sanitation",
        "type": "Services"
      }
    ],
    "sg:phone": "+1 440 585 1326",
    "sg:postcode": "44092",
    "sg:province": "OH",
    "sg:tags": [
      "snow",
      "removal"
    ],
    "wof:name": "C J's Snow Plowing",
    "wof:placetype": "venue"
  },
  "geometry": {"coordinates":[-81.475376,41.605163],"type":"Point"}
}
