{
  "type": "Feature",
  "properties": {
    "addr:full":"2489 E 79th St Cleveland OH 44104",
    "addr:housenumber":"2489",
    "addr:postcode":"44104",
    "addr:street":"E 79Th St",
    "iso:country":"US",
    "sg:address":"2489 E 79th St",
    "sg:city":"Cleveland",
    "sg:classifiers":[
        {
            "category":"Retail",
            "subcategory":"Car Wash",
            "type":"Services"
        }
    ],
    "sg:phone":"+1 216 721 1545",
    "sg:postcode":"44104",
    "sg:province":"OH",
    "sg:tags":[
        "polishing",
        "washing"
    ],
    "wof:name":"Triple X",
    "wof:placetype":"venue"
},
  "geometry": {"coordinates":[-81.63334,41.490955],"type":"Point"}
}