{
  "type": "Feature",
  "properties": {
    "addr:full": "18046 Chillicothe Rd Chagrin Falls OH 44023",
    "addr:housenumber": "18046",
    "addr:postcode": "44023",
    "addr:street": "Chillicothe Rd",
    "iso:country": "US",
    "sg:address": "18046 Chillicothe Rd",
    "sg:city": "Chagrin Falls",
    "sg:classifiers": [
      {
        "category": "Organizations",
        "subcategory": "Religious Organization",
        "type": "Services"
      }
    ],
    "sg:phone": "+1 440 543 7227",
    "sg:postcode": "44023",
    "sg:province": "OH",
    "sg:tags": [
      "church"
    ],
    "wof:name": "New Life Fellowship",
    "wof:placetype": "venue"
  },
  "geometry": {"coordinates":[-81.339218,41.37942],"type":"Point"}
}
