{
  "type": "Feature",
  "properties": {
    "addr:full":"135 Lincoln Ave Youngstown OH 44503",
    "addr:housenumber":"135",
    "addr:postcode":"44503",
    "addr:street":"Lincoln Ave",
    "iso:country":"US",
    "sg:address":"135 Lincoln Ave",
    "sg:city":"Youngstown",
    "sg:classifiers":[
        {
            "category":"Restaurant",
            "type":"Food & Drink"
        }
    ],
    "sg:phone":"+1 330 744 1211",
    "sg:postcode":"44503",
    "sg:province":"OH",
    "sg:tags":[
        "eating"
    ],
    "wof:name":"Little Jimmy's Pizza",
    "wof:placetype":"venue"
},
  "geometry": {"coordinates":[-80.64922199999999,41.104859],"type":"Point"}
}