{
  "type": "Feature",
  "properties": {
    "addr:full":"5001 South Ave Toledo OH 43615",
    "addr:housenumber":"5001",
    "addr:postcode":"43615",
    "addr:street":"South Ave",
    "iso:country":"US",
    "sg:address":"5001 South Ave",
    "sg:city":"Toledo",
    "sg:classifiers":[
        {
            "category":"Building & Trades",
            "subcategory":"Construction",
            "type":"Services"
        }
    ],
    "sg:phone":"+1 419 535 8722",
    "sg:postcode":"43615",
    "sg:province":"OH",
    "sg:tags":[
        "concrete",
        "contractor"
    ],
    "wof:name":"Borllner Concrete Construction",
    "wof:placetype":"venue"
},
  "geometry": {"coordinates":[-83.65907900000001,41.631119],"type":"Point"}
}