{
  "type": "Feature",
  "properties": {
    "addr:full": "3501 E Royalton Rd Cleveland OH 44147",
    "addr:housenumber": "3501",
    "addr:postcode": "44147",
    "addr:street": "E Royalton Rd",
    "iso:country": "US",
    "sg:address": "3501 E Royalton Rd",
    "sg:city": "Cleveland",
    "sg:classifiers": [
      {
        "category": "Building \u0026 Trades",
        "subcategory": "Cleaning \u0026 Sanitation",
        "type": "Services"
      }
    ],
    "sg:phone": "+1 440 546 9560",
    "sg:postcode": "44147",
    "sg:province": "OH",
    "sg:tags": [
      "house"
    ],
    "wof:name": "Cleaning Authority",
    "wof:placetype": "venue"
  },
  "geometry": {"coordinates":[-81.660201,41.313958],"type":"Point"}
}
