{
  "type": "Feature",
  "properties": {
    "iso:country":"US",
    "sg:address":"16464 McCormick Run Rd",
    "sg:city":"Salineville",
    "sg:classifiers":[
        {
            "category":"Building & Trades",
            "subcategory":"Plumbing",
            "type":"Services"
        }
    ],
    "sg:phone":"+1 330 532 1333",
    "sg:postcode":"43945",
    "sg:province":"OH",
    "sg:tags":[
        "mechanical",
        "contractor"
    ],
    "wof:name":"Worldwide Mechanical Inc",
    "wof:placetype":"venue"
},
  "geometry": {"coordinates":[-80.740883,40.664964],"type":"Point"}
}