{
  "type": "Feature",
  "properties": {
    "iso:country":"US",
    "sg:address":"4673 Kenny Rd",
    "sg:city":"Columbus",
    "sg:classifiers":[
        {
            "category":"Organizations",
            "subcategory":"Community Association",
            "type":"Services"
        }
    ],
    "sg:phone":"+1 614 451 9997",
    "sg:postcode":"43220",
    "sg:province":"OH",
    "sg:tags":[
        "sorority",
        "fraternity"
    ],
    "wof:name":"Omega Tau Sigma",
    "wof:placetype":"venue"
},
  "geometry": {"coordinates":[-83.048263,40.060532],"type":"Point"}
}