{
  "type": "Feature",
  "properties": {
    "iso:country":"US",
    "sg:address":"1000 Dayton Rd",
    "sg:city":"Springfield",
    "sg:classifiers":[
        {
            "category":"Wholesale",
            "subcategory":"Machinery & Supplies",
            "type":"Manufacturing & Wholesale Goods"
        }
    ],
    "sg:phone":"+1 937 322 8428",
    "sg:postcode":"45506",
    "sg:province":"OH",
    "sg:tags":[
        "janitor"
    ],
    "wof:name":"Janeco Cleaning Supply",
    "wof:placetype":"venue"
},
  "geometry": {"coordinates":[-83.844587,39.916183],"type":"Point"}
}