{
  "type": "Feature",
  "properties": {
    "addr:full": "67800 Mall Rd Saint Clairsville OH 43950",
    "addr:housenumber": "67800",
    "addr:postcode": "43950",
    "addr:street": "Mall Rd",
    "iso:country": "US",
    "sg:address": "67800 Mall Rd",
    "sg:city": "Saint Clairsville",
    "sg:classifiers": [
      {
        "category": "Utilities",
        "subcategory": "Mobile Phone",
        "type": "Services"
      }
    ],
    "sg:phone": "+1 740 695 5300",
    "sg:postcode": "43950",
    "sg:province": "OH",
    "sg:tags": [
      "communication",
      "radiotelephone",
      "merchandise"
    ],
    "wof:name": "AT\u0026T",
    "wof:placetype": "venue"
  },
  "geometry": {"coordinates":[-80.864137,40.069942],"type":"Point"}
}
