{
  "type": "Feature",
  "properties": {
    "iso:country":"US",
    "sg:address":"1435 Shaw Rd",
    "sg:city":"Niles",
    "sg:classifiers":[
        {
            "category":"Wholesale",
            "subcategory":"Machinery & Supplies",
            "type":"Manufacturing & Wholesale Goods"
        }
    ],
    "sg:phone":"+1 330 544 4156",
    "sg:postcode":"44446",
    "sg:province":"OH",
    "sg:tags":[
        "equipment",
        "industrial",
        "con"
    ],
    "wof:name":"J RS Pump Sales & Svc",
    "wof:placetype":"venue"
},
  "geometry": {"coordinates":[-80.73846899999999,41.201636],"type":"Point"}
}