{
  "type": "Feature",
  "properties": {
    "addr:full": "1435 Shaw Rd Niles OH 44446",
    "addr:housenumber": "1435",
    "addr:postcode": "44446",
    "addr:street": "Shaw Rd",
    "iso:country": "US",
    "sg:address": "1435 Shaw Rd",
    "sg:city": "Niles",
    "sg:classifiers": [
      {
        "category": "Wholesale",
        "subcategory": "Machinery \u0026 Supplies",
        "type": "Manufacturing \u0026 Wholesale Goods"
      }
    ],
    "sg:phone": "+1 330 544 4156",
    "sg:postcode": "44446",
    "sg:province": "OH",
    "sg:tags": [
      "equipment",
      "industrial",
      "con"
    ],
    "wof:name": "J RS Pump Sales \u0026 Svc",
    "wof:placetype": "venue"
  },
  "geometry": {"coordinates":[-80.738469,41.201636],"type":"Point"}
}
