{
  "type": "Feature",
  "properties": {
    "addr:full": "431 E Broad St Columbus OH 43215",
    "addr:housenumber": "431",
    "addr:postcode": "43215",
    "addr:street": "E Broad St",
    "iso:country": "US",
    "sg:address": "431 E Broad St",
    "sg:city": "Columbus",
    "sg:classifiers": [
      {
        "category": "Professional",
        "subcategory": "Detective \u0026 Security Services",
        "type": "Services"
      }
    ],
    "sg:phone": "+1 614 360 2426",
    "sg:postcode": "43215",
    "sg:province": "OH",
    "sg:tags": [
      "information",
      "bureau"
    ],
    "wof:name": "Paratus Solutions",
    "wof:placetype": "venue"
  },
  "geometry": {"coordinates":[-82.989129,39.963577],"type":"Point"}
}
