{
  "type": "Feature",
  "properties": {
    "addr:full": "5212 Big Bend Dr Dayton OH 45427",
    "addr:housenumber": "5212",
    "addr:postcode": "45427",
    "addr:street": "Big Bend Dr",
    "iso:country": "US",
    "sg:address": "5212 Big Bend Dr",
    "sg:city": "Dayton",
    "sg:classifiers": [
      {
        "category": "Organizations",
        "subcategory": "Religious Organization",
        "type": "Services"
      }
    ],
    "sg:phone": "+1 937 263 5614",
    "sg:postcode": "45427",
    "sg:province": "OH",
    "sg:tags": [
      "clergy"
    ],
    "wof:name": "Good Samaritan Baptist Church",
    "wof:placetype": "venue"
  },
  "geometry": {"coordinates":[-84.273543,39.736005],"type":"Point"}
}
