{
  "type": "Feature",
  "properties": {
    "addr:full":"3170 E 79th St Cleveland OH 44104",
    "addr:housenumber":"3170",
    "addr:postcode":"44104",
    "addr:street":"E 79Th St",
    "iso:country":"US",
    "sg:address":"3170 E 79th St",
    "sg:city":"Cleveland",
    "sg:classifiers":[
        {
            "category":"Retail",
            "subcategory":"Auto Repair",
            "type":"Services"
        }
    ],
    "sg:phone":"+1 216 206 0746",
    "sg:postcode":"44104",
    "sg:province":"OH",
    "sg:tags":[
        "repairing",
        "automobile"
    ],
    "wof:name":"Harper Brothers",
    "wof:placetype":"venue"
},
  "geometry": {"coordinates":[-81.63281000000001,41.469659],"type":"Point"}
}