{
  "type": "Feature",
  "properties": {
    "addr:full":"304 West Ave Elyria OH 44035",
    "addr:housenumber":"304",
    "addr:postcode":"44035",
    "addr:street":"West Ave",
    "iso:country":"US",
    "sg:address":"304 West Ave",
    "sg:city":"Elyria",
    "sg:classifiers":[
        {
            "category":"Banks & Credit Unions",
            "subcategory":"Investment Brokerage",
            "type":"Services"
        }
    ],
    "sg:phone":"+1 440 322 0820",
    "sg:postcode":"44035",
    "sg:province":"OH",
    "wof:name":"John F Smith & Co",
    "wof:placetype":"venue"
},
  "geometry": {"coordinates":[-82.11026699999999,41.365015],"type":"Point"}
}