{
  "type": "Feature",
  "properties": {
    "addr:full":"4920 Milan Rd Sandusky OH 44870",
    "addr:housenumber":"4920",
    "addr:postcode":"44870",
    "addr:street":"Milan Rd",
    "iso:country":"US",
    "sg:address":"4920 Milan Rd",
    "sg:city":"Sandusky",
    "sg:classifiers":[
        {
            "category":"Professional",
            "subcategory":"Advertising",
            "type":"Services"
        }
    ],
    "sg:phone":"+1 419 609 0867",
    "sg:postcode":"44870",
    "sg:province":"OH",
    "sg:tags":[
        "mailing",
        "shipping"
    ],
    "wof:name":"UPS Store",
    "wof:placetype":"venue"
},
  "geometry": {"coordinates":[-82.658081,41.402198],"type":"Point"}
}