{
  "type": "Feature",
  "properties": {
    "addr:full": "2210 Superior Via Cleveland OH 44113",
    "addr:housenumber": "2210",
    "addr:postcode": "44113",
    "addr:street": "Superior Via Cleveland",
    "iso:country": "US",
    "sg:address": "2210 Superior Via",
    "sg:city": "Cleveland",
    "sg:classifiers": [
      {
        "category": "Professional",
        "subcategory": "Art Services",
        "type": "Services"
      }
    ],
    "sg:phone": "+1 216 781 2440",
    "sg:postcode": "44113",
    "sg:province": "OH",
    "sg:tags": [
      "photographer"
    ],
    "wof:name": "Peter Renerts Photographer",
    "wof:placetype": "venue"
  },
  "geometry": {"coordinates":[-81.706123,41.492987],"type":"Point"}
}
