{
  "type": "Feature",
  "properties": {
    "iso:country":"US",
    "sg:address":"2210 Superior Via",
    "sg:city":"Cleveland",
    "sg:classifiers":[
        {
            "category":"Professional",
            "subcategory":"Art Services",
            "type":"Services"
        }
    ],
    "sg:phone":"+1 216 781 2440",
    "sg:postcode":"44113",
    "sg:province":"OH",
    "sg:tags":[
        "photographer"
    ],
    "wof:name":"Peter Renerts Photographer",
    "wof:placetype":"venue"
},
  "geometry": {"coordinates":[-81.70612300000001,41.492987],"type":"Point"}
}