{
  "type": "Feature",
  "properties": {
    "iso:country":"US",
    "sg:address":"159 Adams St",
    "sg:city":"Corning",
    "sg:classifiers":[
        {
            "category":"Organizations",
            "subcategory":"Religious Organization",
            "type":"Services"
        }
    ],
    "sg:phone":"+1 740 347 4415",
    "sg:postcode":"43730",
    "sg:province":"OH",
    "sg:tags":[
        "church"
    ],
    "wof:name":"Bethany United Methodist Chr",
    "wof:placetype":"venue"
},
  "geometry": {"coordinates":[-82.08832099999999,39.60564],"type":"Point"}
}