{
  "type": "Feature",
  "properties": {
    "addr:full": "32 S Shafer St Athens OH 45701",
    "addr:housenumber": "32",
    "addr:postcode": "45701",
    "addr:street": "S Shafer St",
    "iso:country": "US",
    "sg:address": "32 S Shafer St",
    "sg:city": "Athens",
    "sg:classifiers": [
      {
        "category": "Wholesale",
        "subcategory": "Machinery \u0026 Supplies",
        "type": "Manufacturing \u0026 Wholesale Goods"
      }
    ],
    "sg:phone": "+1 740 594 6901",
    "sg:postcode": "45701",
    "sg:province": "OH",
    "sg:tags": [
      "tractor"
    ],
    "wof:name": "Jacobs Tractor Repair",
    "wof:placetype": "venue"
  },
  "geometry": {"coordinates":[-82.110468,39.331459],"type":"Point"}
}
