{
  "type": "Feature",
  "properties": {
    "iso:country":"US",
    "sg:address":"32 S Shafer St",
    "sg:city":"Athens",
    "sg:classifiers":[
        {
            "category":"Wholesale",
            "subcategory":"Machinery & Supplies",
            "type":"Manufacturing & Wholesale Goods"
        }
    ],
    "sg:phone":"+1 740 594 6901",
    "sg:postcode":"45701",
    "sg:province":"OH",
    "sg:tags":[
        "tractor"
    ],
    "wof:name":"Jacobs Tractor Repair",
    "wof:placetype":"venue"
},
  "geometry": {"coordinates":[-82.110468,39.331459],"type":"Point"}
}