{
  "type": "Feature",
  "properties": {
    "iso:country":"US",
    "sg:address":"1500 Bowman St",
    "sg:city":"Mansfield",
    "sg:classifiers":[
        {
            "category":"Wholesale",
            "subcategory":"Scrap",
            "type":"Manufacturing & Wholesale Goods"
        }
    ],
    "sg:phone":"+1 419 747 4733",
    "sg:postcode":"44903",
    "sg:province":"OH",
    "sg:tags":[
        "pr",
        "secondary",
        "material",
        "metal",
        "nonferrous"
    ],
    "wof:name":"Omnisource Corporation",
    "wof:placetype":"venue"
},
  "geometry": {"coordinates":[-82.537766,40.803228],"type":"Point"}
}