{
  "type": "Feature",
  "properties": {
    "addr:full":"309 Ludlow Ave Cincinnati OH 45220",
    "addr:housenumber":"309",
    "addr:postcode":"45220",
    "addr:street":"Ludlow Ave",
    "iso:country":"US",
    "sg:address":"309 Ludlow Ave",
    "sg:city":"Cincinnati",
    "sg:classifiers":[
        {
            "category":"Organizations",
            "subcategory":"Non-profit Organization",
            "type":"Services"
        },
        {
            "category":"Recreation",
            "type":"Entertainment"
        }
    ],
    "sg:phone":"+1 513 861 4001",
    "sg:postcode":"45220",
    "sg:province":"OH",
    "sg:tags":[
        "club",
        "membership"
    ],
    "wof:name":"Sierra Club National",
    "wof:placetype":"venue"
},
  "geometry": {"coordinates":[-84.520302,39.143543],"type":"Point"}
}