{
  "type": "Feature",
  "properties": {
    "iso:country":"US",
    "sg:address":"753 Loveland Miamiville Rd",
    "sg:city":"Loveland",
    "sg:classifiers":[
        {
            "category":"Real Estate",
            "subcategory":"Surveying",
            "type":"Services"
        }
    ],
    "sg:phone":"+1 513 677 1555",
    "sg:postcode":"45140",
    "sg:province":"OH",
    "sg:tags":[
        "surveyor"
    ],
    "wof:name":"Robert W Smith Jr",
    "wof:placetype":"venue"
},
  "geometry": {"coordinates":[-84.25977399999999,39.227396],"type":"Point"}
}