{
  "type": "Feature",
  "properties": {
    "addr:full": "383 N Front St Columbus OH 43215",
    "addr:housenumber": "383",
    "addr:postcode": "43215",
    "addr:street": "N Front St",
    "iso:country": "US",
    "sg:address": "383 N Front St",
    "sg:city": "Columbus",
    "sg:classifiers": [
      {
        "category": "Professional",
        "subcategory": "Accounting \u0026 Tax Preparation",
        "type": "Services"
      }
    ],
    "sg:phone": "+1 614 848 7855",
    "sg:postcode": "43215",
    "sg:province": "OH",
    "wof:name": "Steen \u0026 Co LLC",
    "wof:placetype": "venue"
  },
  "geometry": {"coordinates":[-83.004014,39.969856],"type":"Point"}
}
