{
  "type": "Feature",
  "properties": {
    "iso:country":"US",
    "sg:address":"383 N Front St",
    "sg:city":"Columbus",
    "sg:classifiers":[
        {
            "category":"Professional",
            "subcategory":"Accounting & Tax Preparation",
            "type":"Services"
        }
    ],
    "sg:phone":"+1 614 848 7855",
    "sg:postcode":"43215",
    "sg:province":"OH",
    "wof:name":"Steen & Co LLC",
    "wof:placetype":"venue"
},
  "geometry": {"coordinates":[-83.004014,39.969856],"type":"Point"}
}