{
  "type": "Feature",
  "properties": {
    "addr:full": "4540 W 160th St Cleveland OH 44135",
    "addr:housenumber": "4540",
    "addr:postcode": "44135",
    "addr:street": "W 160Th St",
    "iso:country": "US",
    "sg:address": "4540 W 160th St",
    "sg:city": "Cleveland",
    "sg:classifiers": [
      {
        "category": "Manufacturing",
        "subcategory": "Tools \u0026 Machinery",
        "type": "Manufacturing \u0026 Wholesale Goods"
      }
    ],
    "sg:phone": "+1 216 265 8400",
    "sg:postcode": "44135",
    "sg:province": "OH",
    "sg:tags": [
      "fan"
    ],
    "sg:website": "www.supertrapp.com",
    "wof:name": "Super Trap Industries Inc",
    "wof:placetype": "venue"
  },
  "geometry": {"coordinates":[-81.810548,41.432198],"type":"Point"}
}
