{
  "type": "Feature",
  "properties": {
    "iso:country":"US",
    "sg:address":"1265 Maxwalton Dr",
    "sg:city":"Mansfield",
    "sg:classifiers":[
        {
            "category":"Manufacturing",
            "subcategory":"Tools & Machinery",
            "type":"Manufacturing & Wholesale Goods"
        }
    ],
    "sg:phone":"+1 419 524 4458",
    "sg:postcode":"44903",
    "sg:province":"OH",
    "sg:tags":[
        "mfg",
        "industrial",
        "supply"
    ],
    "wof:name":"Jackson Racing",
    "wof:placetype":"venue"
},
  "geometry": {"coordinates":[-82.469297,40.723943],"type":"Point"}
}