{
  "type": "Feature",
  "properties": {
    "addr:full": "1265 Maxwalton Dr Mansfield OH 44903",
    "addr:housenumber": "1265",
    "addr:postcode": "44903",
    "addr:street": "Maxwalton Dr",
    "iso:country": "US",
    "sg:address": "1265 Maxwalton Dr",
    "sg:city": "Mansfield",
    "sg:classifiers": [
      {
        "category": "Manufacturing",
        "subcategory": "Tools \u0026 Machinery",
        "type": "Manufacturing \u0026 Wholesale Goods"
      }
    ],
    "sg:phone": "+1 419 524 4458",
    "sg:postcode": "44903",
    "sg:province": "OH",
    "sg:tags": [
      "mfg",
      "industrial",
      "supply"
    ],
    "wof:name": "Jackson Racing",
    "wof:placetype": "venue"
  },
  "geometry": {"coordinates":[-82.469297,40.723943],"type":"Point"}
}
