{
  "type": "Feature",
  "properties": {
    "addr:full": "2463 Hamilton Richmond Rd Hamilton OH 45013",
    "addr:housenumber": "2463",
    "addr:postcode": "45013",
    "addr:street": "Hamilton Richmond Rd",
    "iso:country": "US",
    "sg:address": "2463 Hamilton Richmond Rd",
    "sg:city": "Hamilton",
    "sg:classifiers": [
      {
        "category": "Shopping",
        "subcategory": "Hobbies, Toys, \u0026 Games",
        "type": "Retail Goods"
      }
    ],
    "sg:phone": "+1 513 896 9027",
    "sg:postcode": "45013",
    "sg:province": "OH",
    "wof:name": "Handcraft",
    "wof:placetype": "venue"
  },
  "geometry": {"coordinates":[-84.62098,39.450825],"type":"Point"}
}
