{
  "type": "Feature",
  "properties": {
    "iso:country":"US",
    "sg:address":"2463 Hamilton Richmond Rd",
    "sg:city":"Hamilton",
    "sg:classifiers":[
        {
            "category":"Shopping",
            "subcategory":"Hobbies, Toys, & Games",
            "type":"Retail Goods"
        }
    ],
    "sg:phone":"+1 513 896 9027",
    "sg:postcode":"45013",
    "sg:province":"OH",
    "wof:name":"Handcraft",
    "wof:placetype":"venue"
},
  "geometry": {"coordinates":[-84.62098,39.450825],"type":"Point"}
}