{
  "type": "Feature",
  "properties": {
    "addr:full": "14800 Private Dr Cleveland OH 44112",
    "addr:housenumber": "14800",
    "addr:postcode": "44112",
    "addr:street": "Private Dr",
    "iso:country": "US",
    "sg:address": "14800 Private Dr",
    "sg:city": "Cleveland",
    "sg:classifiers": [
      {
        "category": "Social Services",
        "subcategory": "Child Care",
        "type": "Services"
      }
    ],
    "sg:phone": "+1 216 761 6100",
    "sg:postcode": "44112",
    "sg:province": "OH",
    "wof:name": "YWCA Of Cleveland",
    "wof:placetype": "venue"
  },
  "geometry": {"coordinates":[-81.573028,41.530921],"type":"Point"}
}
