{
  "type": "Feature",
  "properties": {
    "iso:country":"US",
    "sg:address":"7118 Union Ave",
    "sg:city":"Cleveland",
    "sg:classifiers":[
        {
            "category":"Food & Beverages",
            "subcategory":"Groceries & Convenience Stores",
            "type":"Retail Goods"
        }
    ],
    "sg:phone":"+1 216 641 8137",
    "sg:postcode":"44105",
    "sg:province":"OH",
    "wof:name":"Convenience One",
    "wof:placetype":"venue"
},
  "geometry": {"coordinates":[-81.637576,41.463268],"type":"Point"}
}