{
  "type": "Feature",
  "properties": {
    "iso:country":"US",
    "sg:address":"776 Center St",
    "sg:city":"Ashtabula",
    "sg:classifiers":[
        {
            "category":"Retail",
            "subcategory":"Auto Repair",
            "type":"Services"
        }
    ],
    "sg:phone":"+1 440 993 0039",
    "sg:postcode":"44004",
    "sg:province":"OH",
    "sg:tags":[
        "repairing",
        "automobile"
    ],
    "wof:name":"Tom's Auto",
    "wof:placetype":"venue"
},
  "geometry": {"coordinates":[-80.790606,41.864927],"type":"Point"}
}