{
  "type": "Feature",
  "properties": {
    "addr:full": "405 S Tarr St North Baltimore OH 45872",
    "addr:housenumber": "405",
    "addr:postcode": "45872",
    "addr:street": "S Tarr St",
    "iso:country": "US",
    "sg:address": "405 S Tarr St",
    "sg:city": "North Baltimore",
    "sg:classifiers": [
      {
        "category": "Communications",
        "type": "Services"
      }
    ],
    "sg:phone": "+1 419 257 1355",
    "sg:postcode": "45872",
    "sg:province": "OH",
    "wof:name": "R \u0026 J Communications",
    "wof:placetype": "venue"
  },
  "geometry": {"coordinates":[-83.676929,41.175492],"type":"Point"}
}
