{
  "type": "Feature",
  "properties": {
    "iso:country":"US",
    "sg:address":"405 S Tarr St",
    "sg:city":"North Baltimore",
    "sg:classifiers":[
        {
            "category":"Communications",
            "type":"Services"
        }
    ],
    "sg:phone":"+1 419 257 1355",
    "sg:postcode":"45872",
    "sg:province":"OH",
    "wof:name":"R & J Communications",
    "wof:placetype":"venue"
},
  "geometry": {"coordinates":[-83.676929,41.175492],"type":"Point"}
}