{
  "type": "Feature",
  "properties": {
    "iso:country":"US",
    "sg:address":"5112 Wesselman Woods Dr",
    "sg:city":"Cleves",
    "sg:classifiers":[
        {
            "category":"Real Estate",
            "subcategory":"Real Estate Agent",
            "type":"Services"
        }
    ],
    "sg:phone":"+1 513 598 9222",
    "sg:postcode":"45002",
    "sg:province":"OH",
    "wof:name":"Cep Realty",
    "wof:placetype":"venue"
},
  "geometry": {"coordinates":[-84.671644,39.183129],"type":"Point"}
}