{
  "type": "Feature",
  "properties": {
    "addr:full":"16937 State Rte 67 Wapakoneta OH 45895",
    "addr:housenumber":"16937",
    "addr:postcode":"45895",
    "addr:street":"State Rte 67",
    "iso:country":"US",
    "sg:address":"16937 State Rte 67",
    "sg:city":"Wapakoneta",
    "sg:phone":"+1 419 738 8398",
    "sg:postcode":"45895",
    "sg:province":"OH",
    "sg:tags":[
        "farm",
        "soybean"
    ],
    "wof:name":"Darryl Kohlrieser",
    "wof:placetype":"venue"
},
  "geometry": {"coordinates":[-84.12929,40.599618],"type":"Point"}
}