{
  "type": "Feature",
  "properties": {
    "addr:full":"3504 River Rock Dr Cuyahoga Falls OH 44223",
    "addr:housenumber":"3504",
    "addr:postcode":"44223",
    "addr:street":"River Rock Dr",
    "iso:country":"US",
    "sg:address":"3504 River Rock Dr",
    "sg:city":"Cuyahoga Falls",
    "sg:classifiers":[
        {
            "category":"Building & Trades",
            "subcategory":"Construction",
            "type":"Services"
        }
    ],
    "sg:phone":"+1 330 929 7550",
    "sg:postcode":"44223",
    "sg:province":"OH",
    "sg:tags":[
        "home",
        "builder"
    ],
    "wof:name":"Design Construction Svc",
    "wof:placetype":"venue"
},
  "geometry": {"coordinates":[-81.498401,41.163191],"type":"Point"}
}