{
  "type": "Feature",
  "properties": {
    "addr:full":"688 Hyde Shaffer Rd NW Bristolville OH 44402",
    "addr:housenumber":"688",
    "addr:postcode":"44402",
    "addr:street":"Hyde Shaffer Rd Nw Bristolville",
    "iso:country":"US",
    "sg:address":"688 Hyde Shaffer Rd NW",
    "sg:city":"Bristolville",
    "sg:classifiers":[
        {
            "category":"Organizations",
            "subcategory":"Community Association",
            "type":"Services"
        }
    ],
    "sg:phone":"+1 330 889 3861",
    "sg:postcode":"44402",
    "sg:province":"OH",
    "wof:name":"Knights of Columbus",
    "wof:placetype":"venue"
},
  "geometry": {"coordinates":[-80.824028,41.371446],"type":"Point"}
}