{
  "type": "Feature",
  "properties": {
    "iso:country":"US",
    "sg:address":"2908 Yankee Rd",
    "sg:city":"Middletown",
    "sg:classifiers":[
        {
            "category":"Personal",
            "subcategory":"Beauty Salon",
            "type":"Services"
        }
    ],
    "sg:phone":"+1 513 422 1988",
    "sg:postcode":"45044",
    "sg:province":"OH",
    "wof:name":"Kelly's Magic Curl",
    "wof:placetype":"venue"
},
  "geometry": {"coordinates":[-84.396152,39.483347],"type":"Point"}
}