{
  "type": "Feature",
  "properties": {
    "addr:full":"7698 Co Rd T Lyons OH 43540",
    "addr:housenumber":"7698",
    "addr:postcode":"43540",
    "addr:street":"Co Rd",
    "iso:country":"US",
    "sg:address":"7698 Co Rd T",
    "sg:city":"Lyons",
    "sg:classifiers":[
        {
            "category":"Autos & Motor Vehicles",
            "subcategory":"Automobile Sales",
            "type":"Retail Goods"
        }
    ],
    "sg:phone":"+1 419 923 6785",
    "sg:postcode":"43540",
    "sg:province":"OH",
    "sg:tags":[
        "car",
        "dealer"
    ],
    "wof:name":"Willie's Garage Inc",
    "wof:placetype":"venue"
},
  "geometry": {"coordinates":[-84.01196,41.700036],"type":"Point"}
}