{
  "type": "Feature",
  "properties": {
    "iso:country":"US",
    "sg:address":"1848 Allen Dr",
    "sg:city":"Salem",
    "sg:classifiers":[
        {
            "category":"Real Estate",
            "subcategory":"Real Estate Agent",
            "type":"Services"
        },
        {
            "category":"Professional",
            "subcategory":"Business Services",
            "type":"Services"
        }
    ],
    "sg:phone":"+1 330 337 6085",
    "sg:postcode":"44460",
    "sg:province":"OH",
    "sg:tags":[
        "auctioneer"
    ],
    "wof:name":"Bowker Auction & Appraisal Svc",
    "wof:placetype":"venue"
},
  "geometry": {"coordinates":[-80.86354,40.877825],"type":"Point"}
}