{
  "type": "Feature",
  "properties": {
    "addr:full":"831 Main St Dresden OH 43821",
    "addr:housenumber":"831",
    "addr:postcode":"43821",
    "addr:street":"Main St",
    "iso:country":"US",
    "sg:address":"831 Main St",
    "sg:city":"Dresden",
    "sg:classifiers":[
        {
            "category":"Restaurant",
            "type":"Food & Drink"
        }
    ],
    "sg:phone":"+1 740 754 2105",
    "sg:postcode":"43821",
    "sg:province":"OH",
    "sg:tags":[
        "eating"
    ],
    "wof:name":"Dresden Family Rest & Pizza",
    "wof:placetype":"venue"
},
  "geometry": {"coordinates":[-82.010921,40.121053],"type":"Point"}
}