{
  "type": "Feature",
  "properties": {
    "addr:full": "2266 Twp Hwy 102 Dillonvale OH 43917",
    "addr:postcode": "2266;43917",
    "addr:street": "Twp Hwy 102",
    "iso:country": "US",
    "sg:address": "2266 Twp Hwy 102",
    "sg:city": "Dillonvale",
    "sg:classifiers": [
      {
        "category": "Building \u0026 Trades",
        "subcategory": "Construction",
        "type": "Services"
      }
    ],
    "sg:phone": "+1 740 769 2648",
    "sg:postcode": "43917",
    "sg:province": "OH",
    "sg:tags": [
      "house"
    ],
    "wof:name": "Hertler Construction Company",
    "wof:placetype": "venue"
  },
  "geometry": {"coordinates":[-80.82655,40.161398],"type":"Point"}
}
