{
  "type": "Feature",
  "properties": {
    "iso:country":"US",
    "sg:address":"650 N Miami St",
    "sg:city":"West Milton",
    "sg:classifiers":[
        {
            "category":"Utilities",
            "subcategory":"Fuel Oil & Lpg",
            "type":"Services"
        }
    ],
    "sg:phone":"+1 937 698 5180",
    "sg:postcode":"45383",
    "sg:province":"OH",
    "sg:tags":[
        "station",
        "gasoline",
        "dealer"
    ],
    "wof:name":"Wilsons Community Oil",
    "wof:placetype":"venue"
},
  "geometry": {"coordinates":[-84.329114,39.967263],"type":"Point"}
}