{
  "type": "Feature",
  "properties": {
    "addr:full":"301 Ohio Ave Trenton OH 45067",
    "addr:housenumber":"301",
    "addr:postcode":"45067",
    "addr:street":"Ohio Ave",
    "iso:country":"US",
    "sg:address":"301 Ohio Ave",
    "sg:city":"Trenton",
    "sg:classifiers":[
        {
            "category":"Food & Beverages",
            "subcategory":"Groceries & Convenience Stores",
            "type":"Retail Goods"
        }
    ],
    "sg:phone":"+1 513 988 6767",
    "sg:postcode":"45067",
    "sg:province":"OH",
    "wof:name":"Randy Marts",
    "wof:placetype":"venue"
},
  "geometry": {"coordinates":[-84.45210299999999,39.478426],"type":"Point"}
}