{
  "type": "Feature",
  "properties": {
    "iso:country":"US",
    "sg:address":"710 S Main St",
    "sg:city":"Mt Vernon",
    "sg:classifiers":[
        {
            "category":"Real Estate",
            "subcategory":"Real Estate Agent",
            "type":"Services"
        }
    ],
    "sg:phone":"+1 740 392 5764",
    "sg:postcode":"43050",
    "sg:province":"OH",
    "wof:name":"Tom Woosley",
    "wof:placetype":"venue"
},
  "geometry": {"coordinates":[-82.486338,40.3825],"type":"Point"}
}