{
  "type": "Feature",
  "properties": {
    "addr:full":"1212 Hull Rd Sandusky OH 44870",
    "addr:housenumber":"1212",
    "addr:postcode":"44870",
    "addr:street":"Hull Rd",
    "iso:country":"US",
    "sg:address":"1212 Hull Rd",
    "sg:city":"Sandusky",
    "sg:classifiers":[
        {
            "category":"Retail",
            "subcategory":"Laundry & Dry Cleaning",
            "type":"Services"
        }
    ],
    "sg:phone":"+1 419 626 5482",
    "sg:postcode":"44870",
    "sg:province":"OH",
    "sg:tags":[
        "cleaners"
    ],
    "wof:name":"French-Tex Cleaners",
    "wof:placetype":"venue"
},
  "geometry": {"coordinates":[-82.66942,41.415069],"type":"Point"}
}