{
  "type": "Feature",
  "properties": {
    "iso:country":"US",
    "sg:address":"831 Charles St",
    "sg:city":"Willoughby",
    "sg:classifiers":[
        {
            "category":"Professional",
            "type":"Services"
        }
    ],
    "sg:phone":"+1 440 944 0608",
    "sg:postcode":"44095",
    "sg:province":"OH",
    "wof:name":"Benjamin H Jones",
    "wof:placetype":"venue"
},
  "geometry": {"coordinates":[-81.45504800000001,41.632576],"type":"Point"}
}