{
  "type": "Feature",
  "properties": {
    "addr:full": "831 Charles St Willoughby OH 44095",
    "addr:housenumber": "831",
    "addr:postcode": "44095",
    "addr:street": "Charles St",
    "iso:country": "US",
    "sg:address": "831 Charles St",
    "sg:city": "Willoughby",
    "sg:classifiers": [
      {
        "category": "Professional",
        "type": "Services"
      }
    ],
    "sg:phone": "+1 440 944 0608",
    "sg:postcode": "44095",
    "sg:province": "OH",
    "wof:name": "Benjamin H Jones",
    "wof:placetype": "venue"
  },
  "geometry": {"coordinates":[-81.455048,41.632576],"type":"Point"}
}
