{
  "type": "Feature",
  "properties": {
    "addr:full": "3071 Clark Pkwy Cleveland OH 44145",
    "addr:housenumber": "3071",
    "addr:postcode": "44145",
    "addr:street": "Clark Pkwy",
    "iso:country": "US",
    "sg:address": "3071 Clark Pkwy",
    "sg:city": "Cleveland",
    "sg:classifiers": [
      {
        "category": "Retail",
        "subcategory": "Auto Repair",
        "type": "Services"
      },
      {
        "category": "Manufacturing",
        "subcategory": "Motor Vehicles \u0026 Parts",
        "type": "Manufacturing \u0026 Wholesale Goods"
      }
    ],
    "sg:phone": "+1 440 899 7553",
    "sg:postcode": "44145",
    "sg:province": "OH",
    "sg:tags": [
      "brake",
      "mfg"
    ],
    "wof:name": "MGM Brakes",
    "wof:placetype": "venue"
  },
  "geometry": {"coordinates":[-81.919046,41.442984],"type":"Point"}
}
