{
  "type": "Feature",
  "properties": {
    "iso:country":"US",
    "sg:address":"8885 N Shiloh Dr",
    "sg:city":"Chesterland",
    "sg:classifiers":[
        {
            "category":"Building & Trades",
            "subcategory":"Construction",
            "type":"Services"
        }
    ],
    "sg:phone":"+1 440 951 6212",
    "sg:postcode":"44026",
    "sg:province":"OH",
    "sg:tags":[
        "waterproofing",
        "contractor"
    ],
    "wof:name":"Orlando Berardinelli Inc",
    "wof:placetype":"venue"
},
  "geometry": {"coordinates":[-81.32412100000001,41.53744],"type":"Point"}
}