{
  "type": "Feature",
  "properties": {
    "addr:full": "8885 N Shiloh Dr Chesterland OH 44026",
    "addr:housenumber": "8885",
    "addr:postcode": "44026",
    "addr:street": "N Shiloh Dr",
    "iso:country": "US",
    "sg:address": "8885 N Shiloh Dr",
    "sg:city": "Chesterland",
    "sg:classifiers": [
      {
        "category": "Building \u0026 Trades",
        "subcategory": "Construction",
        "type": "Services"
      }
    ],
    "sg:phone": "+1 440 951 6212",
    "sg:postcode": "44026",
    "sg:province": "OH",
    "sg:tags": [
      "waterproofing",
      "contractor"
    ],
    "wof:name": "Orlando Berardinelli Inc",
    "wof:placetype": "venue"
  },
  "geometry": {"coordinates":[-81.324121,41.53744],"type":"Point"}
}
