{
  "type": "Feature",
  "properties": {
    "addr:full": "442 5th St Struthers OH 44471",
    "addr:housenumber": "442",
    "addr:postcode": "44471",
    "addr:street": "5Th St",
    "iso:country": "US",
    "sg:address": "442 5th St",
    "sg:city": "Struthers",
    "sg:classifiers": [
      {
        "category": "Building \u0026 Trades",
        "subcategory": "Landscaping Services",
        "type": "Services"
      }
    ],
    "sg:phone": "+1 330 755 5973",
    "sg:postcode": "44471",
    "sg:province": "OH",
    "sg:tags": [
      "tree"
    ],
    "wof:name": "Carmen \u0026 Audrey's Tree Svc",
    "wof:placetype": "venue"
  },
  "geometry": {"coordinates":[-80.603548,41.059827],"type":"Point"}
}
