{
  "type": "Feature",
  "properties": {
    "iso:country":"US",
    "sg:address":"902 Ohio Pike",
    "sg:city":"Cincinnati",
    "sg:classifiers":[
        {
            "category":"Food & Beverages",
            "subcategory":"Groceries & Convenience Stores",
            "type":"Retail Goods"
        }
    ],
    "sg:phone":"+1 513 947 2600",
    "sg:postcode":"45245",
    "sg:province":"OH",
    "sg:website":"www.marathon.com",
    "wof:name":"Withamsville Marathon Convenient Store",
    "wof:placetype":"venue"
},
  "geometry": {"coordinates":[-84.272903,39.061798],"type":"Point"}
}