{
  "type": "Feature",
  "properties": {
    "addr:full": "153 Pine Ave NE Warren OH 44481",
    "addr:housenumber": "153",
    "addr:postcode": "44481",
    "addr:street": "Pine Ave Ne",
    "iso:country": "US",
    "sg:address": "153 Pine Ave NE",
    "sg:city": "Warren",
    "sg:classifiers": [
      {
        "category": "Professional",
        "subcategory": "Secretarial Services",
        "type": "Services"
      }
    ],
    "sg:phone": "+1 330 399 1400",
    "sg:postcode": "44481",
    "sg:province": "OH",
    "sg:tags": [
      "reporting"
    ],
    "wof:name": "Simoni Court Reporting",
    "wof:placetype": "venue"
  },
  "geometry": {"coordinates":[-80.816306,41.236777],"type":"Point"}
}
