{
  "type": "Feature",
  "properties": {
    "addr:full":"455 W Central Ave Delaware OH 43015",
    "addr:housenumber":"455",
    "addr:postcode":"43015",
    "addr:street":"W Central Ave",
    "iso:country":"US",
    "sg:address":"455 W Central Ave",
    "sg:city":"Delaware",
    "sg:classifiers":[
        {
            "category":"Shopping",
            "subcategory":"Gifts & Souvenirs",
            "type":"Retail Goods"
        }
    ],
    "sg:phone":"+1 740 369 3447",
    "sg:postcode":"43015",
    "sg:province":"OH",
    "sg:tags":[
        "shop"
    ],
    "wof:name":"Pamelas",
    "wof:placetype":"venue"
},
  "geometry": {"coordinates":[-83.085667,40.304897],"type":"Point"}
}