{
  "type": "Feature",
  "properties": {
    "addr:full":"6007 Co Rd 41 Helena OH 43435",
    "addr:housenumber":"6007;41",
    "addr:postcode":"43435",
    "addr:street":"Co Rd",
    "iso:country":"US",
    "sg:address":"6007 Co Rd 41",
    "sg:city":"Helena",
    "sg:classifiers":[
        {
            "category":"Building & Trades",
            "subcategory":"Construction",
            "type":"Services"
        }
    ],
    "sg:phone":"+1 419 638 0303",
    "sg:postcode":"43435",
    "sg:province":"OH",
    "sg:tags":[
        "house"
    ],
    "wof:name":"Fairbanks Construction LLC",
    "wof:placetype":"venue"
},
  "geometry": {"coordinates":[-83.355092,41.31312],"type":"Point"}
}