{
  "type": "Feature",
  "properties": {
    "addr:full": "1847 Pike Lake Rd Bainbridge OH 45612",
    "addr:housenumber": "1847",
    "addr:postcode": "45612",
    "addr:street": "Pike Lake Rd",
    "iso:country": "US",
    "sg:address": "1847 Pike Lake Rd",
    "sg:city": "Bainbridge",
    "sg:classifiers": [
      {
        "category": "Recreation",
        "type": "Entertainment"
      }
    ],
    "sg:phone": "+1 740 947 4059",
    "sg:postcode": "45612",
    "sg:province": "OH",
    "sg:tags": [
      "parks"
    ],
    "wof:name": "Parks \u0026 Recreation Dept",
    "wof:placetype": "venue"
  },
  "geometry": {"coordinates":[-83.221421,39.158837],"type":"Point"}
}
