{
  "type": "Feature",
  "properties": {
    "iso:country":"US",
    "sg:address":"1847 Pike Lake Rd",
    "sg:city":"Bainbridge",
    "sg:classifiers":[
        {
            "category":"Recreation",
            "type":"Entertainment"
        }
    ],
    "sg:phone":"+1 740 947 4059",
    "sg:postcode":"45612",
    "sg:province":"OH",
    "sg:tags":[
        "parks"
    ],
    "wof:name":"Parks & Recreation Dept",
    "wof:placetype":"venue"
},
  "geometry": {"coordinates":[-83.22142100000001,39.158837],"type":"Point"}
}