{
  "type": "Feature",
  "properties": {
    "iso:country":"US",
    "sg:address":"86 N High St",
    "sg:city":"La Rue",
    "sg:classifiers":[
        {
            "category":"Education",
            "subcategory":"Library",
            "type":"Public Place"
        }
    ],
    "sg:phone":"+1 740 499 3066",
    "sg:postcode":"43332",
    "sg:province":"OH",
    "wof:name":"Henkle-Holliday Memorial Lbry",
    "wof:placetype":"venue"
},
  "geometry": {"coordinates":[-83.384194,40.576836],"type":"Point"}
}