{
  "type": "Feature",
  "properties": {
    "addr:full":"5370 Swisher Rd Groveport OH 43125",
    "addr:housenumber":"5370",
    "addr:postcode":"43125",
    "addr:street":"Swisher Rd",
    "iso:country":"US",
    "sg:address":"5370 Swisher Rd",
    "sg:city":"Groveport",
    "sg:classifiers":[
        {
            "category":"Shopping",
            "subcategory":"Hobbies, Toys, & Games",
            "type":"Retail Goods"
        }
    ],
    "sg:phone":"+1 740 753 4521",
    "sg:postcode":"43125",
    "sg:province":"OH",
    "sg:tags":[
        "craft"
    ],
    "wof:name":"Blacksmith's Wife",
    "wof:placetype":"venue"
},
  "geometry": {"coordinates":[-82.914973,39.857304],"type":"Point"}
}