{
  "type": "Feature",
  "properties": {
    "iso:country":"US",
    "sg:address":"3080 Tremont Rd",
    "sg:city":"Columbus",
    "sg:classifiers":[
        {
            "category":"Restaurant",
            "type":"Food & Drink"
        }
    ],
    "sg:phone":"+1 614 273 9877",
    "sg:postcode":"43221",
    "sg:province":"OH",
    "sg:tags":[
        "eating"
    ],
    "wof:name":"Zuppa",
    "wof:placetype":"venue"
},
  "geometry": {"coordinates":[-83.062305,40.01956],"type":"Point"}
}