{
  "type": "Feature",
  "properties": {
    "iso:country":"US",
    "sg:address":"755 White Pond Dr",
    "sg:city":"Akron",
    "sg:classifiers":[
        {
            "category":"Professional",
            "subcategory":"Management & Consulting",
            "type":"Services"
        }
    ],
    "sg:phone":"+1 234 542 3004",
    "sg:postcode":"44320",
    "sg:province":"OH",
    "sg:tags":[
        "consultant"
    ],
    "wof:name":"Endurance Capital Advisors LLC",
    "wof:placetype":"venue"
},
  "geometry": {"coordinates":[-81.589152,41.095578],"type":"Point"}
}