{
  "type": "Feature",
  "properties": {
    "iso:country":"US",
    "sg:address":"16345 Doty Rd",
    "sg:city":"Garrettsville",
    "sg:classifiers":[
        {
            "category":"Home & Garden",
            "subcategory":"Furniture",
            "type":"Retail Goods"
        }
    ],
    "sg:phone":"+1 440 548 7011",
    "sg:postcode":"44231",
    "sg:province":"OH",
    "sg:tags":[
        "top",
        "counter"
    ],
    "wof:name":"Dutch Craft Cabinets",
    "wof:placetype":"venue"
},
  "geometry": {"coordinates":[-81.05547199999999,41.357137],"type":"Point"}
}