{
  "type": "Feature",
  "properties": {
    "addr:full": "16345 Doty Rd Garrettsville OH 44231",
    "addr:postcode": "16345;44231",
    "addr:street": "Doty Rd",
    "iso:country": "US",
    "sg:address": "16345 Doty Rd",
    "sg:city": "Garrettsville",
    "sg:classifiers": [
      {
        "category": "Home \u0026 Garden",
        "subcategory": "Furniture",
        "type": "Retail Goods"
      }
    ],
    "sg:phone": "+1 440 548 7011",
    "sg:postcode": "44231",
    "sg:province": "OH",
    "sg:tags": [
      "top",
      "counter"
    ],
    "wof:name": "Dutch Craft Cabinets",
    "wof:placetype": "venue"
  },
  "geometry": {"coordinates":[-81.055472,41.357137],"type":"Point"}
}
