{
  "type": "Feature",
  "properties": {
    "iso:country":"US",
    "sg:address":"148 Graceland Blvd",
    "sg:city":"Columbus",
    "sg:classifiers":[
        {
            "category":"Home & Garden",
            "subcategory":"Furniture",
            "type":"Retail Goods"
        }
    ],
    "sg:phone":"+1 614 848 9760",
    "sg:postcode":"43214",
    "sg:province":"OH",
    "wof:name":"Brand Name Furniture",
    "wof:placetype":"venue"
},
  "geometry": {"coordinates":[-83.021231,40.066043],"type":"Point"}
}