{
  "type": "Feature",
  "properties": {
    "iso:country":"US",
    "sg:address":"5329 Lake Rd W",
    "sg:city":"Ashtabula",
    "sg:classifiers":[
        {
            "category":"Food & Beverages",
            "subcategory":"Liquor & Beverages",
            "type":"Retail Goods"
        }
    ],
    "sg:phone":"+1 440 466 7563",
    "sg:postcode":"44004",
    "sg:province":"OH",
    "sg:tags":[
        "alcoholic"
    ],
    "wof:name":"Lake Package",
    "wof:placetype":"venue"
},
  "geometry": {"coordinates":[-80.861445,41.880347],"type":"Point"}
}