{
  "type": "Feature",
  "properties": {
    "addr:full": "5329 Lake Rd W Ashtabula OH 44004",
    "addr:housenumber": "5329",
    "addr:postcode": "44004",
    "addr:street": "Lake Rd W",
    "iso:country": "US",
    "sg:address": "5329 Lake Rd W",
    "sg:city": "Ashtabula",
    "sg:classifiers": [
      {
        "category": "Food \u0026 Beverages",
        "subcategory": "Liquor \u0026 Beverages",
        "type": "Retail Goods"
      }
    ],
    "sg:phone": "+1 440 466 7563",
    "sg:postcode": "44004",
    "sg:province": "OH",
    "sg:tags": [
      "alcoholic"
    ],
    "wof:name": "Lake Package",
    "wof:placetype": "venue"
  },
  "geometry": {"coordinates":[-80.861445,41.880347],"type":"Point"}
}
