{
  "type": "Feature",
  "properties": {
    "addr:full": "3909 Orange Pl Cleveland OH 44122",
    "addr:housenumber": "3909",
    "addr:postcode": "44122",
    "addr:street": "Orange Pl",
    "iso:country": "US",
    "sg:address": "3909 Orange Pl",
    "sg:city": "Cleveland",
    "sg:classifiers": [
      {
        "category": "Health Services",
        "subcategory": "Hospital",
        "type": "Services"
      }
    ],
    "sg:phone": "+1 216 896 1855",
    "sg:postcode": "44122",
    "sg:province": "OH",
    "sg:tags": [
      "general"
    ],
    "wof:name": "University Hospital Occupation",
    "wof:placetype": "venue"
  },
  "geometry": {"coordinates":[-81.487929,41.460249],"type":"Point"}
}
