{
  "type": "Feature",
  "properties": {
    "iso:country":"US",
    "sg:address":"3909 Orange Pl",
    "sg:city":"Cleveland",
    "sg:classifiers":[
        {
            "category":"Health Services",
            "subcategory":"Hospital",
            "type":"Services"
        }
    ],
    "sg:phone":"+1 216 896 1855",
    "sg:postcode":"44122",
    "sg:province":"OH",
    "sg:tags":[
        "general"
    ],
    "wof:name":"University Hospital Occupation",
    "wof:placetype":"venue"
},
  "geometry": {"coordinates":[-81.48792899999999,41.460249],"type":"Point"}
}