{
  "type": "Feature",
  "properties": {
    "addr:full": "2375 E Main St Columbus OH 43209",
    "addr:housenumber": "2375",
    "addr:postcode": "43209",
    "addr:street": "E Main St",
    "iso:country": "US",
    "sg:address": "2375 E Main St",
    "sg:city": "Columbus",
    "sg:classifiers": [
      {
        "category": "Organizations",
        "subcategory": "Religious Organization",
        "type": "Services"
      }
    ],
    "sg:phone": "+1 614 238 6778",
    "sg:postcode": "43209",
    "sg:province": "OH",
    "sg:tags": [
      "synagogue"
    ],
    "wof:name": "Congregation Torat Emet",
    "wof:placetype": "venue"
  },
  "geometry": {"coordinates":[-82.935969,39.957058],"type":"Point"}
}
