{
  "type": "Feature",
  "properties": {
    "addr:full": "11611 W State Rte 571 Laura OH 45337",
    "addr:housenumber": "11611",
    "addr:postcode": "45337",
    "addr:street": "W State Rte 571",
    "iso:country": "US",
    "sg:address": "11611 W State Rte 571",
    "sg:city": "Laura",
    "sg:classifiers": [
      {
        "category": "Utilities",
        "subcategory": "Fuel Oil \u0026 Lpg",
        "type": "Services"
      }
    ],
    "sg:phone": "+1 937 947 1883",
    "sg:postcode": "45337",
    "sg:province": "OH",
    "sg:tags": [
      "dealer"
    ],
    "wof:name": "Fuel Man The",
    "wof:placetype": "venue"
  },
  "geometry": {"coordinates":[-84.420413,40.006341],"type":"Point"}
}
