{
  "type": "Feature",
  "properties": {
    "addr:full": "768 S Broadway St Geneva OH 44041",
    "addr:housenumber": "768",
    "addr:postcode": "44041",
    "addr:street": "S Broadway St",
    "iso:country": "US",
    "sg:address": "768 S Broadway St",
    "sg:city": "Geneva",
    "sg:classifiers": [
      {
        "category": "Professional",
        "subcategory": "Employment Agencies",
        "type": "Services"
      }
    ],
    "sg:phone": "+1 440 466 2250",
    "sg:postcode": "44041",
    "sg:province": "OH",
    "sg:tags": [
      "help",
      "contractor"
    ],
    "wof:name": "Spherion",
    "wof:placetype": "venue"
  },
  "geometry": {"coordinates":[-80.947394,41.793752],"type":"Point"}
}
