{
  "type": "Feature",
  "properties": {
    "addr:full": "384 Post Rd Fort Recovery OH 45846",
    "addr:housenumber": "384",
    "addr:postcode": "45846",
    "addr:street": "Post Rd",
    "iso:country": "US",
    "sg:address": "384 Post Rd",
    "sg:city": "Fort Recovery",
    "sg:classifiers": [
      {
        "category": "Building \u0026 Trades",
        "subcategory": "Construction",
        "type": "Services"
      }
    ],
    "sg:phone": "+1 419 375 4432",
    "sg:postcode": "45846",
    "sg:province": "OH",
    "sg:tags": [
      "house"
    ],
    "wof:name": "Grube Homes Ltd",
    "wof:placetype": "venue"
  },
  "geometry": {"coordinates":[-84.671641,40.36191],"type":"Point"}
}
