{
  "type": "Feature",
  "properties": {
    "iso:country":"US",
    "sg:address":"384 Post Rd",
    "sg:city":"Fort Recovery",
    "sg:classifiers":[
        {
            "category":"Building & Trades",
            "subcategory":"Construction",
            "type":"Services"
        }
    ],
    "sg:phone":"+1 419 375 4432",
    "sg:postcode":"45846",
    "sg:province":"OH",
    "sg:tags":[
        "house"
    ],
    "wof:name":"Grube Homes Ltd",
    "wof:placetype":"venue"
},
  "geometry": {"coordinates":[-84.67164099999999,40.36191],"type":"Point"}
}