{
  "type": "Feature",
  "properties": {
    "addr:full":"818 Mason St Springfield OH 45503",
    "addr:housenumber":"818",
    "addr:postcode":"45503",
    "addr:street":"Mason St",
    "iso:country":"US",
    "sg:address":"818 Mason St",
    "sg:city":"Springfield",
    "sg:classifiers":[
        {
            "category":"Professional",
            "type":"Services"
        }
    ],
    "sg:phone":"+1 937 322 2946",
    "sg:postcode":"45503",
    "sg:province":"OH",
    "wof:name":"Christina & Shane Nichols",
    "wof:placetype":"venue"
},
  "geometry": {"coordinates":[-83.803715,39.933887],"type":"Point"}
}