{
  "type": "Feature",
  "properties": {
    "addr:full":"605 Orient Ave Cincinnati OH 45232",
    "addr:housenumber":"605",
    "addr:postcode":"45232",
    "addr:street":"Orient Ave",
    "iso:country":"US",
    "sg:address":"605 Orient Ave",
    "sg:city":"Cincinnati",
    "sg:classifiers":[
        {
            "category":"Building & Trades",
            "subcategory":"Construction",
            "type":"Services"
        }
    ],
    "sg:phone":"+1 513 541 1892",
    "sg:postcode":"45232",
    "sg:province":"OH",
    "sg:tags":[
        "contractor"
    ],
    "wof:name":"Fenos Ceramic Tile Co",
    "wof:placetype":"venue"
},
  "geometry": {"coordinates":[-84.513344,39.172517],"type":"Point"}
}