{
  "type": "Feature",
  "properties": {
    "iso:country":"US",
    "sg:address":"332 Trigonia Dr",
    "sg:city":"Akron",
    "sg:classifiers":[
        {
            "category":"Organizations",
            "subcategory":"Religious Organization",
            "type":"Services"
        }
    ],
    "sg:phone":"+1 330 535 1430",
    "sg:postcode":"44302",
    "sg:province":"OH",
    "sg:tags":[
        "church"
    ],
    "wof:name":"Friendship Apostolic Church",
    "wof:placetype":"venue"
},
  "geometry": {"coordinates":[-81.539502,41.085125],"type":"Point"}
}