{
  "type": "Feature",
  "properties": {
    "addr:full": "303 Carroll St Akron OH 44304",
    "addr:housenumber": "303",
    "addr:postcode": "44304",
    "addr:street": "Carroll St",
    "iso:country": "US",
    "sg:address": "303 Carroll St",
    "sg:city": "Akron",
    "sg:classifiers": [
      {
        "category": "Cinema",
        "subcategory": "Movie Theater",
        "type": "Entertainment"
      }
    ],
    "sg:phone": "+1 330 972 6757",
    "sg:postcode": "44304",
    "sg:province": "OH",
    "wof:name": "Gardner Movie Theatre",
    "wof:placetype": "venue"
  },
  "geometry": {"coordinates":[-81.51565,41.075347],"type":"Point"}
}
