{
  "type": "Feature",
  "properties": {
    "addr:full": "102 Meadow Ln Solon OH 44139",
    "addr:housenumber": "102",
    "addr:postcode": "44139",
    "addr:street": "Meadow Ln",
    "iso:country": "US",
    "sg:address": "102 Meadow Ln",
    "sg:city": "Solon",
    "sg:classifiers": [
      {
        "category": "Manufacturing",
        "subcategory": "Tools \u0026 Machinery",
        "type": "Manufacturing \u0026 Wholesale Goods"
      }
    ],
    "sg:phone": "+1 440 248 4728",
    "sg:postcode": "44139",
    "sg:province": "OH",
    "sg:tags": [
      "industry",
      "mfg"
    ],
    "wof:name": "James A West",
    "wof:placetype": "venue"
  },
  "geometry": {"coordinates":[-81.429749,41.414138],"type":"Point"}
}
