{
  "type": "Feature",
  "properties": {
    "addr:full": "460 Lake Rd Medina OH 44256",
    "addr:housenumber": "460",
    "addr:postcode": "44256",
    "addr:street": "Lake Rd",
    "iso:country": "US",
    "sg:address": "460 Lake Rd",
    "sg:city": "Medina",
    "sg:classifiers": [
      {
        "category": "Professional",
        "type": "Services"
      }
    ],
    "sg:phone": "+1 330 725 3706",
    "sg:postcode": "44256",
    "sg:province": "OH",
    "sg:tags": [
      "establishment"
    ],
    "wof:name": "Metal Assembly",
    "wof:placetype": "venue"
  },
  "geometry": {"coordinates":[-81.894668,41.129896],"type":"Point"}
}
