{
  "type": "Feature",
  "properties": {
    "addr:full":"14 N Walnut St Troy OH 45373",
    "addr:housenumber":"14",
    "addr:postcode":"45373",
    "addr:street":"N Walnut St",
    "iso:country":"US",
    "sg:address":"14 N Walnut St",
    "sg:city":"Troy",
    "sg:classifiers":[
        {
            "category":"Professional",
            "subcategory":"Accounting & Tax Preparation",
            "type":"Services"
        }
    ],
    "sg:phone":"+1 937 335 1150",
    "sg:postcode":"45373",
    "sg:province":"OH",
    "sg:tags":[
        "return",
        "filing"
    ],
    "wof:name":"H & R Block Tax Svc",
    "wof:placetype":"venue"
},
  "geometry": {"coordinates":[-84.202226,40.039399],"type":"Point"}
}