{
  "type": "Feature",
  "properties": {
    "iso:country":"US",
    "sg:address":"242 N Detroit St",
    "sg:city":"Xenia",
    "sg:classifiers":[
        {
            "category":"Insurance",
            "subcategory":"Insurance Agent",
            "type":"Services"
        }
    ],
    "sg:phone":"+1 937 372 4491",
    "sg:postcode":"45385",
    "sg:province":"OH",
    "wof:name":"Anderson Williamson Insurance",
    "wof:placetype":"venue"
},
  "geometry": {"coordinates":[-83.930108,39.688375],"type":"Point"}
}