{
  "type": "Feature",
  "properties": {
    "iso:country":"US",
    "sg:address":"7571 Ryan Rd",
    "sg:city":"Medina",
    "sg:phone":"+1 330 769 2245",
    "sg:postcode":"44256",
    "sg:province":"OH",
    "sg:tags":[
        "farm",
        "corn"
    ],
    "wof:name":"Robert Workman",
    "wof:placetype":"venue"
},
  "geometry": {"coordinates":[-81.884547,41.070827],"type":"Point"}
}