{
  "type": "Feature",
  "properties": {
    "iso:country":"US",
    "sg:address":"140 N Verity Pkwy",
    "sg:city":"Middletown",
    "sg:classifiers":[
        {
            "category":"Social Services",
            "type":"Services"
        }
    ],
    "sg:phone":"+1 513 705 9168",
    "sg:postcode":"45042",
    "sg:province":"OH",
    "sg:tags":[
        "organization",
        "welfare"
    ],
    "wof:name":"Alzheimer's Association Butler",
    "wof:placetype":"venue"
},
  "geometry": {"coordinates":[-84.400831,39.517985],"type":"Point"}
}