{
  "type": "Feature",
  "properties": {
    "addr:full": "15707 Detroit Ave Cleveland OH 44107",
    "addr:housenumber": "15707",
    "addr:postcode": "44107",
    "addr:street": "Detroit Ave",
    "iso:country": "US",
    "sg:address": "15707 Detroit Ave",
    "sg:city": "Cleveland",
    "sg:classifiers": [
      {
        "category": "Banks \u0026 Credit Unions",
        "subcategory": "Bank",
        "type": "Services"
      }
    ],
    "sg:phone": "+1 216 227 0190",
    "sg:postcode": "44107",
    "sg:province": "OH",
    "sg:tags": [
      "loan",
      "real estate"
    ],
    "wof:name": "Custom Fit Mortgage Inc",
    "wof:placetype": "venue"
  },
  "geometry": {"coordinates":[-81.808071,41.48508],"type":"Point"}
}
