{
  "type": "Feature",
  "properties": {
    "iso:country":"US",
    "sg:address":"1840 Zollinger Rd",
    "sg:city":"Columbus",
    "sg:classifiers":[
        {
            "category":"Health Services",
            "subcategory":"Doctor",
            "type":"Services"
        }
    ],
    "sg:phone":"+1 614 457 4723",
    "sg:postcode":"43221",
    "sg:province":"OH",
    "sg:tags":[
        "physician",
        "medical",
        "surgeon"
    ],
    "wof:name":"Richard D Carr MD Office",
    "wof:placetype":"venue"
},
  "geometry": {"coordinates":[-83.060791,40.01891],"type":"Point"}
}