{
  "type": "Feature",
  "properties": {
    "addr:full": "2627 State Rte 103 Sycamore OH 44882",
    "addr:housenumber": "2627",
    "addr:postcode": "44882",
    "addr:street": "State Rte 103",
    "iso:country": "US",
    "sg:address": "2627 State Rte 103",
    "sg:city": "Sycamore",
    "sg:classifiers": [
      {
        "category": "Shopping",
        "subcategory": "Hobbies, Toys, \u0026 Games",
        "type": "Retail Goods"
      }
    ],
    "sg:phone": "+1 419 927 2248",
    "sg:postcode": "44882",
    "sg:province": "OH",
    "sg:tags": [
      "craft"
    ],
    "wof:name": "Designs By Mary Jane",
    "wof:placetype": "venue"
  },
  "geometry": {"coordinates":[-83.159523,40.949729],"type":"Point"}
}
