{
  "type": "Feature",
  "properties": {
    "iso:country":"US",
    "sg:address":"2627 State Rte 103",
    "sg:city":"Sycamore",
    "sg:classifiers":[
        {
            "category":"Shopping",
            "subcategory":"Hobbies, Toys, & Games",
            "type":"Retail Goods"
        }
    ],
    "sg:phone":"+1 419 927 2248",
    "sg:postcode":"44882",
    "sg:province":"OH",
    "sg:tags":[
        "craft"
    ],
    "wof:name":"Designs By Mary Jane",
    "wof:placetype":"venue"
},
  "geometry": {"coordinates":[-83.15952299999999,40.949729],"type":"Point"}
}