{
  "type": "Feature",
  "properties": {
    "addr:full":"18975 Villaview Rd Cleveland OH 44119",
    "addr:housenumber":"18975",
    "addr:postcode":"44119",
    "addr:street":"Villaview Rd",
    "iso:country":"US",
    "sg:address":"18975 Villaview Rd",
    "sg:city":"Cleveland",
    "sg:classifiers":[
        {
            "category":"Health Services",
            "subcategory":"Hospital",
            "type":"Services"
        }
    ],
    "sg:phone":"+1 216 898 1633",
    "sg:postcode":"44119",
    "sg:province":"OH",
    "sg:tags":[
        "medical",
        "surgical",
        "hospitalization",
        "plan"
    ],
    "wof:name":"Emerald Billing Inc",
    "wof:placetype":"venue"
},
  "geometry": {"coordinates":[-81.546981,41.579865],"type":"Point"}
}