{
  "type": "Feature",
  "properties": {
    "iso:country":"US",
    "sg:address":"6902 Murray Ave",
    "sg:city":"Cincinnati",
    "sg:classifiers":[
        {
            "category":"Real Estate",
            "subcategory":"Real Estate Agent",
            "type":"Services"
        }
    ],
    "sg:phone":"+1 513 561 5100",
    "sg:postcode":"45227",
    "sg:province":"OH",
    "wof:name":"Dandenmark Ltd",
    "wof:placetype":"venue"
},
  "geometry": {"coordinates":[-84.376257,39.147971],"type":"Point"}
}