{
  "type": "Feature",
  "properties": {
    "addr:full":"1734 State Rte 131 Milford OH 45150",
    "addr:housenumber":"1734",
    "addr:postcode":"45150",
    "addr:street":"State Rte 131",
    "iso:country":"US",
    "sg:address":"1734 State Rte 131",
    "sg:city":"Milford",
    "sg:classifiers":[
        {
            "category":"Farming",
            "subcategory":"Nursery",
            "type":"Manufacturing & Wholesale Goods"
        }
    ],
    "sg:phone":"+1 513 722 1234",
    "sg:postcode":"45150",
    "sg:province":"OH",
    "sg:tags":[
        "turf"
    ],
    "wof:name":"Turf N Scapes",
    "wof:placetype":"venue"
},
  "geometry": {"coordinates":[-84.184742,39.175863],"type":"Point"}
}