{
  "type": "Feature",
  "properties": {
    "iso:country":"US",
    "sg:address":"21800 Chardon Rd",
    "sg:city":"Cleveland",
    "sg:classifiers":[
        {
            "category":"Social Services",
            "subcategory":"Job Training",
            "type":"Services"
        }
    ],
    "sg:phone":"+1 216 481 9159",
    "sg:postcode":"44117",
    "sg:province":"OH",
    "sg:tags":[
        "rehabilitation"
    ],
    "sg:website":"www.kindredhealthcare.com",
    "wof:name":"Kindred 8490 Mt St Joseph",
    "wof:placetype":"venue"
},
  "geometry": {"coordinates":[-81.53253100000001,41.568757],"type":"Point"}
}