{
  "type": "Feature",
  "properties": {
    "addr:full": "10476 Mill St Rockbridge OH 43149",
    "addr:housenumber": "10476",
    "addr:postcode": "43149",
    "addr:street": "Mill St",
    "iso:country": "US",
    "sg:address": "10476 Mill St",
    "sg:city": "Rockbridge",
    "sg:classifiers": [
      {
        "category": "Building \u0026 Trades",
        "subcategory": "Construction",
        "type": "Services"
      }
    ],
    "sg:phone": "+1 740 385 1940",
    "sg:postcode": "43149",
    "sg:province": "OH",
    "sg:tags": [
      "excavation",
      "contractor"
    ],
    "wof:name": "Glen Roop Excavating",
    "wof:placetype": "venue"
  },
  "geometry": {"coordinates":[-82.520776,39.581018],"type":"Point"}
}
