{
  "type": "Feature",
  "properties": {
    "addr:full": "515 Burbank Dr Toledo OH 43607",
    "addr:housenumber": "515",
    "addr:postcode": "43607",
    "addr:street": "Burbank Dr",
    "iso:country": "US",
    "sg:address": "515 Burbank Dr",
    "sg:city": "Toledo",
    "sg:classifiers": [
      {
        "category": "Building \u0026 Trades",
        "subcategory": "Construction",
        "type": "Services"
      },
      {
        "category": "Home \u0026 Garden",
        "subcategory": "Carpets \u0026 Floor Coverings",
        "type": "Retail Goods"
      }
    ],
    "sg:phone": "+1 419 535 1811",
    "sg:postcode": "43607",
    "sg:province": "OH",
    "sg:tags": [
      "material",
      "installation",
      "contractor"
    ],
    "wof:name": "Phalen's Floor Covering",
    "wof:placetype": "venue"
  },
  "geometry": {"coordinates":[-83.609159,41.64456],"type":"Point"}
}
