{
  "type": "Feature",
  "properties": {
    "addr:full": "1170 Alliance Rd NW Minerva OH 44657",
    "addr:housenumber": "1170",
    "addr:postcode": "minerva;44657",
    "addr:street": "Alliance Rd Nw",
    "iso:country": "US",
    "sg:address": "1170 Alliance Rd NW",
    "sg:city": "Minerva",
    "sg:classifiers": [
      {
        "category": "Banks \u0026 Credit Unions",
        "subcategory": "Bank",
        "type": "Services"
      }
    ],
    "sg:phone": "+1 330 868 0886",
    "sg:postcode": "44657",
    "sg:province": "OH",
    "sg:tags": [
      "depository",
      "banking",
      "se",
      "institution",
      "business"
    ],
    "wof:name": "VRS Cash Advance",
    "wof:placetype": "venue"
  },
  "geometry": {"coordinates":[-81.119504,40.717772],"type":"Point"}
}
