{
  "type": "Feature",
  "properties": {
    "iso:country":"US",
    "sg:address":"5598 Fulton Rd",
    "sg:city":"Smithville",
    "sg:classifiers":[
        {
            "category":"Farming",
            "subcategory":"Dairy Farm",
            "type":"Manufacturing & Wholesale Goods"
        }
    ],
    "sg:phone":"+1 330 669 9144",
    "sg:postcode":"44677",
    "sg:province":"OH",
    "wof:name":"Two By Two Farm",
    "wof:placetype":"venue"
},
  "geometry": {"coordinates":[-81.864311,40.90171],"type":"Point"}
}