{
  "type": "Feature",
  "properties": {
    "addr:full":"9797 Springboro Pike Miamisburg OH 45342",
    "addr:housenumber":"9797",
    "addr:postcode":"45342",
    "addr:street":"Springboro Pike",
    "iso:country":"US",
    "sg:address":"9797 Springboro Pike",
    "sg:city":"Miamisburg",
    "sg:classifiers":[
        {
            "category":"Insurance",
            "subcategory":"Insurance Agent",
            "type":"Services"
        }
    ],
    "sg:phone":"+1 937 859 2400",
    "sg:postcode":"45342",
    "sg:province":"OH",
    "wof:name":"Metropolitan Property & Cslty",
    "wof:placetype":"venue"
},
  "geometry": {"coordinates":[-84.228089,39.60778],"type":"Point"}
}