{
  "type": "Feature",
  "properties": {
    "iso:country":"US",
    "sg:address":"775 Eastgate South Dr",
    "sg:city":"Cincinnati",
    "sg:classifiers":[
        {
            "category":"Personal",
            "subcategory":"Nail Salon",
            "type":"Services"
        }
    ],
    "sg:phone":"+1 513 752 2271",
    "sg:postcode":"45245",
    "sg:province":"OH",
    "wof:name":"Diamond Nails",
    "wof:placetype":"venue"
},
  "geometry": {"coordinates":[-84.271005,39.095921],"type":"Point"}
}