{
  "type": "Feature",
  "properties": {
    "iso:country":"US",
    "sg:address":"2007 Taylor Ln",
    "sg:city":"Batavia",
    "sg:classifiers":[
        {
            "category":"Banks & Credit Unions",
            "subcategory":"Investment Brokerage",
            "type":"Services"
        }
    ],
    "sg:phone":"+1 513 625 1100",
    "sg:postcode":"45103",
    "sg:province":"OH",
    "wof:name":"ALC Investment Group LLC",
    "wof:placetype":"venue"
},
  "geometry": {"coordinates":[-84.16249500000001,39.168012],"type":"Point"}
}