{
  "type": "Feature",
  "properties": {
    "addr:full": "2007 Taylor Ln Batavia OH 45103",
    "addr:housenumber": "2007",
    "addr:postcode": "45103",
    "addr:street": "Taylor Ln",
    "iso:country": "US",
    "sg:address": "2007 Taylor Ln",
    "sg:city": "Batavia",
    "sg:classifiers": [
      {
        "category": "Banks \u0026 Credit Unions",
        "subcategory": "Investment Brokerage",
        "type": "Services"
      }
    ],
    "sg:phone": "+1 513 625 1100",
    "sg:postcode": "45103",
    "sg:province": "OH",
    "wof:name": "ALC Investment Group LLC",
    "wof:placetype": "venue"
  },
  "geometry": {"coordinates":[-84.162495,39.168012],"type":"Point"}
}
