{
  "type": "Feature",
  "properties": {
    "iso:country":"US",
    "sg:address":"4111 Oak Crest Rd",
    "sg:city":"Toledo",
    "sg:classifiers":[
        {
            "category":"Real Estate",
            "subcategory":"Real Estate Operator",
            "type":"Services"
        }
    ],
    "sg:phone":"+1 419 474 0646",
    "sg:postcode":"43623",
    "sg:province":"OH",
    "sg:tags":[
        "building",
        "apartment"
    ],
    "wof:name":"David Edward Redlinger",
    "wof:placetype":"venue"
},
  "geometry": {"coordinates":[-83.643304,41.712126],"type":"Point"}
}