{
  "type": "Feature",
  "properties": {
    "iso:country":"US",
    "sg:address":"815 Sicily Rd",
    "sg:city":"Mount Orab",
    "sg:classifiers":[
        {
            "category":"Building & Trades",
            "subcategory":"Construction",
            "type":"Services"
        }
    ],
    "sg:phone":"+1 937 444 9012",
    "sg:postcode":"45154",
    "sg:province":"OH",
    "sg:tags":[
        "contractor"
    ],
    "wof:name":"Adams Masonry",
    "wof:placetype":"venue"
},
  "geometry": {"coordinates":[-83.86725800000001,39.016642],"type":"Point"}
}