{
  "type": "Feature",
  "properties": {
    "addr:full": "815 Sicily Rd Mount Orab OH 45154",
    "addr:housenumber": "815",
    "addr:postcode": "45154",
    "addr:street": "Sicily Rd",
    "iso:country": "US",
    "sg:address": "815 Sicily Rd",
    "sg:city": "Mount Orab",
    "sg:classifiers": [
      {
        "category": "Building \u0026 Trades",
        "subcategory": "Construction",
        "type": "Services"
      }
    ],
    "sg:phone": "+1 937 444 9012",
    "sg:postcode": "45154",
    "sg:province": "OH",
    "sg:tags": [
      "contractor"
    ],
    "wof:name": "Adams Masonry",
    "wof:placetype": "venue"
  },
  "geometry": {"coordinates":[-83.867258,39.016642],"type":"Point"}
}
