{
  "type": "Feature",
  "properties": {
    "iso:country":"US",
    "sg:address":"10015 Lorain Ave",
    "sg:city":"Cleveland",
    "sg:classifiers":[
        {
            "category":"Home & Garden",
            "subcategory":"Carpets & Floor Coverings",
            "type":"Retail Goods"
        }
    ],
    "sg:phone":"+1 216 651 2250",
    "sg:postcode":"44111",
    "sg:province":"OH",
    "sg:tags":[
        "dealer",
        "rug"
    ],
    "wof:name":"Public Home Furnishings",
    "wof:placetype":"venue"
},
  "geometry": {"coordinates":[-81.75354400000001,41.466907],"type":"Point"}
}