{
  "type": "Feature",
  "properties": {
    "addr:full": "10015 Lorain Ave Cleveland OH 44111",
    "addr:housenumber": "10015",
    "addr:postcode": "44111",
    "addr:street": "Lorain Ave",
    "iso:country": "US",
    "sg:address": "10015 Lorain Ave",
    "sg:city": "Cleveland",
    "sg:classifiers": [
      {
        "category": "Home \u0026 Garden",
        "subcategory": "Carpets \u0026 Floor Coverings",
        "type": "Retail Goods"
      }
    ],
    "sg:phone": "+1 216 651 2250",
    "sg:postcode": "44111",
    "sg:province": "OH",
    "sg:tags": [
      "dealer",
      "rug"
    ],
    "wof:name": "Public Home Furnishings",
    "wof:placetype": "venue"
  },
  "geometry": {"coordinates":[-81.753544,41.466907],"type":"Point"}
}
