{
  "type": "Feature",
  "properties": {
    "addr:full":"4755 Northfield Rd Cleveland OH 44128",
    "addr:housenumber":"4755",
    "addr:postcode":"44128",
    "addr:street":"Northfield Rd",
    "iso:country":"US",
    "sg:address":"4755 Northfield Rd",
    "sg:city":"Cleveland",
    "sg:classifiers":[
        {
            "category":"Shopping",
            "subcategory":"Clothing, Apparel, & Fashions",
            "type":"Retail Goods"
        }
    ],
    "sg:phone":"+1 216 475 9124",
    "sg:postcode":"44128",
    "sg:province":"OH",
    "sg:tags":[
        "furnishing"
    ],
    "wof:name":"Casual Male Big & Tall",
    "wof:placetype":"venue"
},
  "geometry": {"coordinates":[-81.52554600000001,41.431393],"type":"Point"}
}