{
  "type": "Feature",
  "properties": {
    "addr:full": "286 Ridgewood Dr Marietta OH 45750",
    "addr:housenumber": "286",
    "addr:postcode": "45750",
    "addr:street": "Ridgewood Dr",
    "iso:country": "US",
    "sg:address": "286 Ridgewood Dr",
    "sg:city": "Marietta",
    "sg:classifiers": [
      {
        "category": "Real Estate",
        "subcategory": "Real Estate Operator",
        "type": "Services"
      }
    ],
    "sg:phone": "+1 740 374 8004",
    "sg:postcode": "45750",
    "sg:province": "OH",
    "sg:tags": [
      "management"
    ],
    "wof:name": "Ridgewood Court Apartments",
    "wof:placetype": "venue"
  },
  "geometry": {"coordinates":[-81.447138,39.428211],"type":"Point"}
}
