{
  "type": "Feature",
  "properties": {
    "addr:full": "4845 Market St Youngstown OH 44512",
    "addr:housenumber": "4845",
    "addr:postcode": "44512",
    "addr:street": "Market St",
    "iso:country": "US",
    "sg:address": "4845 Market St",
    "sg:city": "Youngstown",
    "sg:classifiers": [
      {
        "category": "Banks \u0026 Credit Unions",
        "subcategory": "Bank",
        "type": "Services"
      }
    ],
    "sg:phone": "+1 330 782 3351",
    "sg:postcode": "44512",
    "sg:province": "OH",
    "sg:tags": [
      "financing"
    ],
    "wof:name": "Citi Financial",
    "wof:placetype": "venue"
  },
  "geometry": {"coordinates":[-80.66271,41.050056],"type":"Point"}
}
