{
  "type": "Feature",
  "properties": {
    "addr:full": "7050 Engle Rd Cleveland OH 44130",
    "addr:housenumber": "7050",
    "addr:postcode": "44130",
    "addr:street": "Engle Rd",
    "iso:country": "US",
    "sg:address": "7050 Engle Rd",
    "sg:city": "Cleveland",
    "sg:classifiers": [
      {
        "category": "Professional",
        "subcategory": "Accounting \u0026 Tax Preparation",
        "type": "Services"
      }
    ],
    "sg:phone": "+1 440 243 0806",
    "sg:postcode": "44130",
    "sg:province": "OH",
    "sg:tags": [
      "return",
      "filing"
    ],
    "wof:name": "Galati \u0026 Pyros",
    "wof:placetype": "venue"
  },
  "geometry": {"coordinates":[-81.824792,41.373966],"type":"Point"}
}
