{
  "type": "Feature",
  "properties": {
    "iso:country":"US",
    "sg:address":"1120 State Rte 41 S",
    "sg:city":"Bainbridge",
    "sg:classifiers":[
        {
            "category":"Autos & Motor Vehicles",
            "subcategory":"Automobile Sales",
            "type":"Retail Goods"
        }
    ],
    "sg:phone":"+1 740 634 2739",
    "sg:postcode":"45612",
    "sg:province":"OH",
    "sg:tags":[
        "car",
        "dealer"
    ],
    "wof:name":"D & K Auto Sales",
    "wof:placetype":"venue"
},
  "geometry": {"coordinates":[-83.311622,39.196468],"type":"Point"}
}