{
  "type": "Feature",
  "properties": {
    "iso:country":"US",
    "sg:address":"10151 Maumee Western Rd",
    "sg:city":"Monclova",
    "sg:classifiers":[
        {
            "category":"Restaurant",
            "type":"Food & Drink"
        }
    ],
    "sg:phone":"+1 419 865 8707",
    "sg:postcode":"43542",
    "sg:province":"OH",
    "sg:tags":[
        "eating"
    ],
    "wof:name":"Pig Outs",
    "wof:placetype":"venue"
},
  "geometry": {"coordinates":[-83.781519,41.574155],"type":"Point"}
}