{
  "type": "Feature",
  "properties": {
    "addr:full": "10151 Maumee Western Rd Monclova OH 43542",
    "addr:housenumber": "10151",
    "addr:postcode": "43542",
    "addr:street": "Western Rd",
    "iso:country": "US",
    "sg:address": "10151 Maumee Western Rd",
    "sg:city": "Monclova",
    "sg:classifiers": [
      {
        "category": "Restaurant",
        "type": "Food \u0026 Drink"
      }
    ],
    "sg:phone": "+1 419 865 8707",
    "sg:postcode": "43542",
    "sg:province": "OH",
    "sg:tags": [
      "eating"
    ],
    "wof:name": "Pig Outs",
    "wof:placetype": "venue"
  },
  "geometry": {"coordinates":[-83.781519,41.574155],"type":"Point"}
}
