{
  "type": "Feature",
  "properties": {
    "addr:full": "2612 Greenbrier Dr Dayton OH 45406",
    "addr:housenumber": "2612",
    "addr:postcode": "45406",
    "addr:street": "Greenbrier Dr",
    "iso:country": "US",
    "sg:address": "2612 Greenbrier Dr",
    "sg:city": "Dayton",
    "sg:classifiers": [
      {
        "category": "Recreation",
        "type": "Entertainment"
      }
    ],
    "sg:phone": "+1 937 275 2249",
    "sg:postcode": "45406",
    "sg:province": "OH",
    "sg:tags": [
      "club",
      "membership"
    ],
    "wof:name": "Dayton Mohawk Association",
    "wof:placetype": "venue"
  },
  "geometry": {"coordinates":[-84.261295,39.794395],"type":"Point"}
}
