{
  "type": "Feature",
  "properties": {
    "addr:full":"2600 Morral-Kirkpatrick Rd E Marion OH 43302",
    "addr:housenumber":"2600",
    "addr:postcode":"43302",
    "addr:street":"Morral-Kirkpatrick Rd E",
    "iso:country":"US",
    "sg:address":"2600 Morral-Kirkpatrick Rd E",
    "sg:city":"Marion",
    "sg:classifiers":[
        {
            "category":"Farming",
            "subcategory":"Farm",
            "type":"Manufacturing & Wholesale Goods"
        }
    ],
    "sg:phone":"+1 740 382 8286",
    "sg:postcode":"43302",
    "sg:province":"OH",
    "wof:name":"Crawford Pork Inc",
    "wof:placetype":"venue"
},
  "geometry": {"coordinates":[-83.04216700000001,40.688568],"type":"Point"}
}