{
  "type": "Feature",
  "properties": {
    "addr:full": "7215 Old Oak Blvd Cleveland OH 44130",
    "addr:housenumber": "7215",
    "addr:postcode": "44130",
    "addr:street": "Old Oak Blvd",
    "iso:country": "US",
    "sg:address": "7215 Old Oak Blvd",
    "sg:city": "Cleveland",
    "sg:classifiers": [
      {
        "category": "Health Services",
        "subcategory": "Medical Lab",
        "type": "Services"
      }
    ],
    "sg:phone": "+1 440 260 7672",
    "sg:postcode": "44130",
    "sg:province": "OH",
    "sg:tags": [
      "laboratory"
    ],
    "wof:name": "Quest Diagnostics",
    "wof:placetype": "venue"
  },
  "geometry": {"coordinates":[-81.833335,41.359119],"type":"Point"}
}
