{
  "type": "Feature",
  "properties": {
    "addr:full": "1426 Reserve Dr Akron OH 44333",
    "addr:housenumber": "1426",
    "addr:postcode": "44333",
    "addr:street": "Reserve Dr",
    "iso:country": "US",
    "sg:address": "1426 Reserve Dr",
    "sg:city": "Akron",
    "sg:classifiers": [
      {
        "category": "Building \u0026 Trades",
        "subcategory": "Cleaning \u0026 Sanitation",
        "type": "Services"
      }
    ],
    "sg:phone": "+1 330 666 5779",
    "sg:postcode": "44333",
    "sg:province": "OH",
    "sg:tags": [
      "fireplace",
      "chimney"
    ],
    "wof:name": "Super Sweep Chimneys",
    "wof:placetype": "venue"
  },
  "geometry": {"coordinates":[-81.674704,41.172535],"type":"Point"}
}
