{
  "type": "Feature",
  "properties": {
    "iso:country":"US",
    "sg:address":"1426 Reserve Dr",
    "sg:city":"Akron",
    "sg:classifiers":[
        {
            "category":"Building & Trades",
            "subcategory":"Cleaning & Sanitation",
            "type":"Services"
        }
    ],
    "sg:phone":"+1 330 666 5779",
    "sg:postcode":"44333",
    "sg:province":"OH",
    "sg:tags":[
        "fireplace",
        "chimney"
    ],
    "wof:name":"Super Sweep Chimneys",
    "wof:placetype":"venue"
},
  "geometry": {"coordinates":[-81.67470400000001,41.172535],"type":"Point"}
}