{
  "type": "Feature",
  "properties": {
    "iso:country":"US",
    "sg:address":"3333 W Pleasant Valley Rd",
    "sg:city":"Cleveland",
    "sg:classifiers":[
        {
            "category":"Organizations",
            "subcategory":"Religious Organization",
            "type":"Services"
        }
    ],
    "sg:phone":"+1 440 884 7602",
    "sg:postcode":"44134",
    "sg:province":"OH",
    "sg:tags":[
        "church"
    ],
    "wof:name":"First Ukrainian Evangelico",
    "wof:placetype":"venue"
},
  "geometry": {"coordinates":[-81.705639,41.362027],"type":"Point"}
}