{
  "type": "Feature",
  "properties": {
    "addr:full": "3214 Saint Clair Ave NE Cleveland OH 44114",
    "addr:housenumber": "3214",
    "addr:postcode": "44114",
    "addr:street": "Saint Clair Ave Ne",
    "iso:country": "US",
    "sg:address": "3214 Saint Clair Ave NE",
    "sg:city": "Cleveland",
    "sg:classifiers": [
      {
        "category": "Building \u0026 Trades",
        "subcategory": "Construction",
        "type": "Services"
      }
    ],
    "sg:phone": "+1 216 241 3397",
    "sg:postcode": "44114",
    "sg:province": "OH",
    "sg:tags": [
      "general",
      "contractor"
    ],
    "wof:name": "Neshkin Construction Co",
    "wof:placetype": "venue"
  },
  "geometry": {"coordinates":[-81.66981,41.51371],"type":"Point"}
}
