{
  "type": "Feature",
  "properties": {
    "addr:full":"15 S 3rd St Newark OH 43055",
    "addr:housenumber":"15",
    "addr:postcode":"43055",
    "addr:street":"S 3Rd St",
    "iso:country":"US",
    "sg:address":"15 S 3rd St",
    "sg:city":"Newark",
    "sg:classifiers":[
        {
            "category":"Restaurant",
            "type":"Food & Drink"
        }
    ],
    "sg:menulink":"http://www.allmenus.com/oh/newark/194957-mcdonalds/menu/",
    "sg:postcode":"43055",
    "sg:province":"OH",
    "sg:tags":[
        "burger",
        "american"
    ],
    "wof:name":"McDonald's",
    "wof:placetype":"venue"
},
  "geometry": {"coordinates":[-82.402349,40.057245],"type":"Point"}
}