{
  "type": "Feature",
  "properties": {
    "addr:full": "6867 Pearl Rd Cleveland OH 44130",
    "addr:housenumber": "6867",
    "addr:postcode": "44130",
    "addr:street": "Pearl Rd",
    "iso:country": "US",
    "sg:address": "6867 Pearl Rd",
    "sg:city": "Cleveland",
    "sg:classifiers": [
      {
        "category": "Professional",
        "subcategory": "Accounting \u0026 Tax Preparation",
        "type": "Services"
      }
    ],
    "sg:phone": "+1 440 886 1660",
    "sg:postcode": "44130",
    "sg:province": "OH",
    "sg:tags": [
      "accountant"
    ],
    "wof:name": "Donald G Velcio Inc",
    "wof:placetype": "venue"
  },
  "geometry": {"coordinates":[-81.790173,41.378358],"type":"Point"}
}
