{
  "type": "Feature",
  "properties": {
    "iso:country":"US",
    "sg:address":"5021 State Rd",
    "sg:city":"Ashtabula",
    "sg:classifiers":[
        {
            "category":"Social Services",
            "type":"Services"
        }
    ],
    "sg:phone":"+1 440 998 1453",
    "sg:postcode":"44004",
    "sg:province":"OH",
    "sg:tags":[
        "counseling"
    ],
    "wof:name":"Baire Foundation",
    "wof:placetype":"venue"
},
  "geometry": {"coordinates":[-80.77053100000001,41.861081],"type":"Point"}
}