{
  "type": "Feature",
  "properties": {
    "addr:full": "5021 State Rd Ashtabula OH 44004",
    "addr:housenumber": "5021",
    "addr:postcode": "44004",
    "addr:street": "State Rd",
    "iso:country": "US",
    "sg:address": "5021 State Rd",
    "sg:city": "Ashtabula",
    "sg:classifiers": [
      {
        "category": "Social Services",
        "type": "Services"
      }
    ],
    "sg:phone": "+1 440 998 1453",
    "sg:postcode": "44004",
    "sg:province": "OH",
    "sg:tags": [
      "counseling"
    ],
    "wof:name": "Baire Foundation",
    "wof:placetype": "venue"
  },
  "geometry": {"coordinates":[-80.770531,41.861081],"type":"Point"}
}
