{
  "type": "Feature",
  "properties": {
    "addr:full":"18975 Villaview Rd Cleveland OH 44119",
    "addr:housenumber":"18975",
    "addr:postcode":"44119",
    "addr:street":"Villaview Rd",
    "iso:country":"US",
    "sg:address":"18975 Villaview Rd",
    "sg:city":"Cleveland",
    "sg:classifiers":[
        {
            "category":"Professional",
            "subcategory":"Lawyer & Legal Services",
            "type":"Services"
        }
    ],
    "sg:phone":"+1 216 531 5898",
    "sg:postcode":"44119",
    "sg:province":"OH",
    "sg:tags":[
        "attorney"
    ],
    "wof:name":"Katica Markulin",
    "wof:placetype":"venue"
},
  "geometry": {"coordinates":[-81.547383,41.579853],"type":"Point"}
}