{
  "type": "Feature",
  "properties": {
    "addr:full":"5402 Lake Rd Sheffield Lake OH 44054",
    "addr:housenumber":"5402",
    "addr:postcode":"44054",
    "addr:street":"Lake Rd",
    "iso:country":"US",
    "sg:address":"5402 Lake Rd",
    "sg:city":"Sheffield Lake",
    "sg:classifiers":[
        {
            "category":"Restaurant",
            "type":"Food & Drink"
        }
    ],
    "sg:phone":"+1 440 949 8102",
    "sg:postcode":"44054",
    "sg:province":"OH",
    "sg:tags":[
        "pizza"
    ],
    "wof:name":"Carmino's Pizza",
    "wof:placetype":"venue"
},
  "geometry": {"coordinates":[-82.071061,41.499104],"type":"Point"}
}