{
  "type": "Feature",
  "properties": {
    "addr:full":"6283 Orchard View Dr SE Canton OH 44730",
    "addr:housenumber":"6283",
    "addr:postcode":"44730",
    "addr:street":"Orchard View Dr Se",
    "iso:country":"US",
    "sg:address":"6283 Orchard View Dr SE",
    "sg:city":"Canton",
    "sg:phone":"+1 330 488 2815",
    "sg:postcode":"44730",
    "sg:province":"OH",
    "sg:tags":[
        "hog",
        "farm",
        "corn",
        "soybean",
        "or",
        "feedlot"
    ],
    "wof:name":"Scott Zimmerman",
    "wof:placetype":"venue"
},
  "geometry": {"coordinates":[-81.285329,40.771065],"type":"Point"}
}