{
  "type": "Feature",
  "properties": {
    "addr:full":"580 Park Ave W Mansfield OH 44906",
    "addr:housenumber":"580",
    "addr:postcode":"44906",
    "addr:street":"Park Ave W",
    "iso:country":"US",
    "sg:address":"580 Park Ave W",
    "sg:city":"Mansfield",
    "sg:classifiers":[
        {
            "category":"Banks & Credit Unions",
            "subcategory":"Bank",
            "type":"Services"
        }
    ],
    "sg:phone":"+1 419 589 8076",
    "sg:postcode":"44906",
    "sg:province":"OH",
    "sg:tags":[
        "cashing",
        "check"
    ],
    "wof:name":"Check Into Cash",
    "wof:placetype":"venue"
},
  "geometry": {"coordinates":[-82.535737,40.759048],"type":"Point"}
}