{
  "type": "Feature",
  "properties": {
    "iso:country":"US",
    "sg:address":"10072 Crows Nest Cove",
    "sg:city":"Aurora",
    "sg:classifiers":[
        {
            "category":"Professional",
            "subcategory":"Management & Consulting",
            "type":"Services"
        }
    ],
    "sg:phone":"+1 330 995 4781",
    "sg:postcode":"44202",
    "sg:province":"OH",
    "sg:tags":[
        "business"
    ],
    "wof:name":"Piezo Solutions",
    "wof:placetype":"venue"
},
  "geometry": {"coordinates":[-81.396153,41.331521],"type":"Point"}
}