{
  "type": "Feature",
  "properties": {
    "addr:full":"1277 Evergreen Ave W Mansfield OH 44905",
    "addr:housenumber":"1277",
    "addr:postcode":"44905",
    "addr:street":"Evergreen Ave W",
    "iso:country":"US",
    "sg:address":"1277 Evergreen Ave W",
    "sg:city":"Mansfield",
    "sg:classifiers":[
        {
            "category":"Real Estate",
            "subcategory":"Real Estate Operator",
            "type":"Services"
        }
    ],
    "sg:phone":"+1 419 589 6777",
    "sg:postcode":"44905",
    "sg:province":"OH",
    "sg:tags":[
        "mobile",
        "home",
        "community"
    ],
    "wof:name":"Madison City Mobile Home Park",
    "wof:placetype":"venue"
},
  "geometry": {"coordinates":[-82.468568,40.777212],"type":"Point"}
}