{
  "type": "Feature",
  "properties": {
    "addr:full":"1055 Pinhook Rd West Harrison OH 47060",
    "addr:housenumber":"1055",
    "addr:postcode":"47060",
    "addr:street":"Pinhook Rd",
    "iso:country":"US",
    "sg:address":"1055 Pinhook Rd",
    "sg:city":"West Harrison",
    "sg:classifiers":[
        {
            "category":"Real Estate",
            "subcategory":"Real Estate Agent",
            "type":"Services"
        }
    ],
    "sg:phone":"+1 812 637 3559",
    "sg:postcode":"47060",
    "sg:province":"OH",
    "wof:name":"Sweet Escape",
    "wof:placetype":"venue"
},
  "geometry": {"coordinates":[-84.833814,39.26281],"type":"Point"}
}