{
  "type": "Feature",
  "properties": {
    "addr:full":"2812 US Hwy 40 Tipp City OH 45371",
    "addr:housenumber":"2812",
    "addr:postcode":"45371",
    "addr:street":"Us Hwy 40",
    "iso:country":"US",
    "sg:address":"2812 US Hwy 40",
    "sg:city":"Tipp City",
    "sg:classifiers":[
        {
            "category":"Building & Trades",
            "subcategory":"Construction",
            "type":"Services"
        }
    ],
    "sg:phone":"+1 937 898 0953",
    "sg:postcode":"45371",
    "sg:province":"OH",
    "sg:tags":[
        "general",
        "contractor"
    ],
    "wof:name":"Dalo Construction Co Inc",
    "wof:placetype":"venue"
},
  "geometry": {"coordinates":[-84.148032,39.895713],"type":"Point"}
}