{
  "type": "Feature",
  "properties": {
    "addr:full": "1737 E Ohio Pike Amelia OH 45102",
    "addr:housenumber": "1737",
    "addr:postcode": "45102",
    "addr:street": "E Ohio Pike",
    "iso:country": "US",
    "sg:address": "1737 E Ohio Pike",
    "sg:city": "Amelia",
    "sg:classifiers": [
      {
        "category": "Restaurant",
        "type": "Food \u0026 Drink"
      }
    ],
    "sg:phone": "+1 513 797 7227",
    "sg:postcode": "45102",
    "sg:province": "OH",
    "sg:website": "www.subway.com",
    "wof:name": "Subway Sandwiches \u0026 Salads",
    "wof:placetype": "venue"
  },
  "geometry": {"coordinates":[-84.205811,39.019799],"type":"Point"}
}
