{
  "type": "Feature",
  "properties": {
    "addr:full": "9881 York-Theta Dr Cleveland OH 44133",
    "addr:postcode": "9881;44133",
    "addr:street": "York-Theta Dr",
    "iso:country": "US",
    "sg:address": "9881 York-Theta Dr",
    "sg:city": "Cleveland",
    "sg:classifiers": [
      {
        "category": "Home \u0026 Garden",
        "subcategory": "Furniture",
        "type": "Retail Goods"
      }
    ],
    "sg:phone": "+1 440 237 2990",
    "sg:postcode": "44133",
    "sg:province": "OH",
    "sg:tags": [
      "cabinet"
    ],
    "wof:name": "Mike Custom Made Cabinet",
    "wof:placetype": "venue"
  },
  "geometry": {"coordinates":[-81.763415,41.319482],"type":"Point"}
}
