{
  "type": "Feature",
  "properties": {
    "addr:full": "382 Pearl St Jackson OH 45640",
    "addr:housenumber": "382",
    "addr:postcode": "45640",
    "addr:street": "Pearl St",
    "iso:country": "US",
    "sg:address": "382 Pearl St",
    "sg:city": "Jackson",
    "sg:classifiers": [
      {
        "category": "Professional",
        "subcategory": "Printing \u0026 Photocopies",
        "type": "Services"
      }
    ],
    "sg:phone": "+1 740 288 2400",
    "sg:postcode": "45640",
    "sg:province": "OH",
    "sg:tags": [
      "photocopying"
    ],
    "wof:name": "Wright Company",
    "wof:placetype": "venue"
  },
  "geometry": {"coordinates":[-82.635231,39.048946],"type":"Point"}
}
