{
  "type": "Feature",
  "properties": {
    "iso:country":"US",
    "sg:address":"139 W Washington St",
    "sg:city":"Athens",
    "sg:classifiers":[
        {
            "category":"Professional",
            "subcategory":"Management & Consulting",
            "type":"Services"
        }
    ],
    "sg:phone":"+1 740 592 4552",
    "sg:postcode":"45701",
    "sg:province":"OH",
    "sg:tags":[
        "business"
    ],
    "wof:name":"Mediad",
    "wof:placetype":"venue"
},
  "geometry": {"coordinates":[-82.105903,39.330767],"type":"Point"}
}