{
  "type": "Feature",
  "properties": {
    "addr:full": "1603 Hayes Ave Sandusky OH 44870",
    "addr:housenumber": "1603",
    "addr:postcode": "44870",
    "addr:street": "Hayes Ave",
    "iso:country": "US",
    "sg:address": "1603 Hayes Ave",
    "sg:city": "Sandusky",
    "sg:classifiers": [
      {
        "category": "Shopping",
        "subcategory": "Clothing, Apparel, \u0026 Fashions",
        "type": "Retail Goods"
      }
    ],
    "sg:phone": "+1 419 609 9967",
    "sg:postcode": "44870",
    "sg:province": "OH",
    "wof:name": "Christina Clothing Store",
    "wof:placetype": "venue"
  },
  "geometry": {"coordinates":[-82.711193,41.441256],"type":"Point"}
}
