{
  "type": "Feature",
  "properties": {
    "iso:country":"US",
    "sg:address":"56 Milford Dr",
    "sg:city":"Hudson",
    "sg:classifiers":[
        {
            "category":"Manufacturing",
            "subcategory":"Metals",
            "type":"Manufacturing & Wholesale Goods"
        }
    ],
    "sg:phone":"+1 330 656 2302",
    "sg:postcode":"44236",
    "sg:province":"OH",
    "sg:tags":[
        "mfg",
        "forging"
    ],
    "wof:name":"Philadelphia Gear Corporation",
    "wof:placetype":"venue"
},
  "geometry": {"coordinates":[-81.447992,41.237755],"type":"Point"}
}