{
  "type": "Feature",
  "properties": {
    "addr:full": "414 W 3rd St Defiance OH 43512",
    "addr:housenumber": "414",
    "addr:postcode": "43512",
    "addr:street": "W 3Rd St",
    "iso:country": "US",
    "sg:address": "414 W 3rd St",
    "sg:city": "Defiance",
    "sg:classifiers": [
      {
        "category": "Organizations",
        "subcategory": "Non-profit Organization",
        "type": "Services"
      }
    ],
    "sg:phone": "+1 419 784 0886",
    "sg:postcode": "43512",
    "sg:province": "OH",
    "wof:name": "Champaign Residential Svc",
    "wof:placetype": "venue"
  },
  "geometry": {"coordinates":[-84.360729,41.285123],"type":"Point"}
}
