{
  "type": "Feature",
  "properties": {
    "addr:full": "4650 Lake Rd Sheffield Lake OH 44054",
    "addr:housenumber": "4650",
    "addr:postcode": "44054",
    "addr:street": "Lake Rd",
    "iso:country": "US",
    "sg:address": "4650 Lake Rd",
    "sg:city": "Sheffield Lake",
    "sg:classifiers": [
      {
        "category": "Personal",
        "subcategory": "Beauty Salon",
        "type": "Services"
      }
    ],
    "sg:phone": "+1 440 949 7400",
    "sg:postcode": "44054",
    "sg:province": "OH",
    "wof:name": "Hair-Ways",
    "wof:placetype": "venue"
  },
  "geometry": {"coordinates":[-82.095636,41.493461],"type":"Point"}
}
