{
  "type": "Feature",
  "properties": {
    "addr:full":"153 S Main St Cadiz OH 43907",
    "addr:housenumber":"153",
    "addr:postcode":"43907",
    "addr:street":"S Main St",
    "iso:country":"US",
    "sg:address":"153 S Main St",
    "sg:city":"Cadiz",
    "sg:classifiers":[
        {
            "category":"Retail",
            "subcategory":"Auto Repair",
            "type":"Services"
        }
    ],
    "sg:phone":"+1 740 942 2444",
    "sg:postcode":"43907",
    "sg:province":"OH",
    "sg:tags":[
        "automobile",
        "restoration",
        "classic"
    ],
    "wof:name":"Gary's Body Shop",
    "wof:placetype":"venue"
},
  "geometry": {"coordinates":[-80.997607,40.272479],"type":"Point"}
}