{
  "type": "Feature",
  "properties": {
    "addr:full": "263 W McKinley Way Poland OH 44514",
    "addr:housenumber": "263",
    "addr:postcode": "44514",
    "addr:street": "W Mckinley Way",
    "iso:country": "US",
    "sg:address": "263 W McKinley Way",
    "sg:city": "Poland",
    "sg:classifiers": [
      {
        "category": "Health Services",
        "subcategory": "Doctor",
        "type": "Services"
      }
    ],
    "sg:phone": "+1 330 757 7933",
    "sg:postcode": "44514",
    "sg:province": "OH",
    "sg:tags": [
      "physician",
      "surgeon"
    ],
    "wof:name": "Adie Tamboli MD",
    "wof:placetype": "venue"
  },
  "geometry": {"coordinates":[-80.618327,41.02417],"type":"Point"}
}
