{
  "type": "Feature",
  "properties": {
    "iso:country":"US",
    "sg:address":"523 Windsor Park Dr",
    "sg:city":"Dayton",
    "sg:classifiers":[
        {
            "category":"Wholesale",
            "subcategory":"Electrical",
            "type":"Manufacturing & Wholesale Goods"
        }
    ],
    "sg:phone":"+1 937 434 7500",
    "sg:postcode":"45459",
    "sg:province":"OH",
    "sg:tags":[
        "measuring",
        "instrument"
    ],
    "wof:name":"M I E W K M",
    "wof:placetype":"venue"
},
  "geometry": {"coordinates":[-84.17470400000001,39.630576],"type":"Point"}
}