{
  "type": "Feature",
  "properties": {
    "addr:full": "523 Windsor Park Dr Dayton OH 45459",
    "addr:housenumber": "523",
    "addr:postcode": "45459",
    "addr:street": "Windsor Park Dr",
    "iso:country": "US",
    "sg:address": "523 Windsor Park Dr",
    "sg:city": "Dayton",
    "sg:classifiers": [
      {
        "category": "Wholesale",
        "subcategory": "Electrical",
        "type": "Manufacturing \u0026 Wholesale Goods"
      }
    ],
    "sg:phone": "+1 937 434 7500",
    "sg:postcode": "45459",
    "sg:province": "OH",
    "sg:tags": [
      "measuring",
      "instrument"
    ],
    "wof:name": "M I E W K M",
    "wof:placetype": "venue"
  },
  "geometry": {"coordinates":[-84.174704,39.630576],"type":"Point"}
}
