{
  "type": "Feature",
  "properties": {
    "addr:full": "5723 Main St Sylvania OH 43560",
    "addr:housenumber": "5723",
    "addr:postcode": "43560",
    "addr:street": "Main St",
    "iso:country": "US",
    "sg:address": "5723 Main St",
    "sg:city": "Sylvania",
    "sg:classifiers": [
      {
        "category": "Home \u0026 Garden",
        "subcategory": "Garden Supply",
        "type": "Retail Goods"
      }
    ],
    "sg:phone": "+1 419 885 1565",
    "sg:postcode": "43560",
    "sg:province": "OH",
    "sg:tags": [
      "center"
    ],
    "wof:name": "Garden Delights",
    "wof:placetype": "venue"
  },
  "geometry": {"coordinates":[-83.703309,41.718888],"type":"Point"}
}
