{
  "type": "Feature",
  "properties": {
    "iso:country":"US",
    "sg:address":"2037 Hoge Ave",
    "sg:city":"Zanesville",
    "sg:classifiers":[
        {
            "category":"Manufacturing",
            "subcategory":"Buildings",
            "type":"Manufacturing & Wholesale Goods"
        }
    ],
    "sg:phone":"+1 740 452 1383",
    "sg:postcode":"43701",
    "sg:province":"OH",
    "sg:tags":[
        "mobile",
        "home",
        "mfg"
    ],
    "wof:name":"Krown Park",
    "wof:placetype":"venue"
},
  "geometry": {"coordinates":[-82.000428,39.963126],"type":"Point"}
}