{
  "type": "Feature",
  "properties": {
    "addr:full":"543 W Tuscarawas Ave Barberton OH 44203",
    "addr:housenumber":"543",
    "addr:postcode":"44203",
    "addr:street":"W Tuscarawas Ave",
    "iso:country":"US",
    "sg:address":"543 W Tuscarawas Ave",
    "sg:city":"Barberton",
    "sg:classifiers":[
        {
            "category":"Professional",
            "subcategory":"Management & Consulting",
            "type":"Services"
        }
    ],
    "sg:phone":"+1 330 745 4552",
    "sg:postcode":"44203",
    "sg:province":"OH",
    "sg:tags":[
        "consultant",
        "writing"
    ],
    "wof:name":"Words Count",
    "wof:placetype":"venue"
},
  "geometry": {"coordinates":[-81.609071,41.012942],"type":"Point"}
}