{
  "type": "Feature",
  "properties": {
    "addr:full": "205 E Oregon Ave Sebring OH 44672",
    "addr:housenumber": "205",
    "addr:postcode": "44672",
    "addr:street": "E Oregon Ave",
    "iso:country": "US",
    "sg:address": "205 E Oregon Ave",
    "sg:city": "Sebring",
    "sg:classifiers": [
      {
        "category": "Personal",
        "subcategory": "Beauty Salon",
        "type": "Services"
      }
    ],
    "sg:phone": "+1 330 938 3345",
    "sg:postcode": "44672",
    "sg:province": "OH",
    "sg:tags": [
      "manicuring"
    ],
    "wof:name": "T G Daggers Nail \u0026 Tanning Sln",
    "wof:placetype": "venue"
  },
  "geometry": {"coordinates":[-81.01477,40.922252],"type":"Point"}
}
