{
  "type": "Feature",
  "properties": {
    "iso:country":"US",
    "sg:address":"1010 Brian Ct",
    "sg:city":"Englewood",
    "sg:classifiers":[
        {
            "category":"Wholesale",
            "subcategory":"Machinery & Supplies",
            "type":"Manufacturing & Wholesale Goods"
        },
        {
            "category":"Home & Garden",
            "subcategory":"Hardware",
            "type":"Retail Goods"
        }
    ],
    "sg:phone":"+1 937 832 8228",
    "sg:postcode":"45322",
    "sg:province":"OH",
    "sg:tags":[
        "tool"
    ],
    "wof:name":"Total Tool Engineering Service",
    "wof:placetype":"venue"
},
  "geometry": {"coordinates":[-84.30250599999999,39.860113],"type":"Point"}
}