{
  "type": "Feature",
  "properties": {
    "iso:country":"US",
    "sg:address":"578 Mason Rd",
    "sg:city":"South Lebanon",
    "sg:classifiers":[
        {
            "category":"Organizations",
            "subcategory":"Religious Organization",
            "type":"Services"
        }
    ],
    "sg:phone":"+1 513 494 1886",
    "sg:postcode":"45065",
    "sg:province":"OH",
    "sg:tags":[
        "church"
    ],
    "wof:name":"Church Of The Nazarene",
    "wof:placetype":"venue"
},
  "geometry": {"coordinates":[-84.223473,39.373949],"type":"Point"}
}