{
  "type": "Feature",
  "properties": {
    "iso:country":"US",
    "sg:address":"262 Stoney Run Rd",
    "sg:city":"Portsmouth",
    "sg:classifiers":[
        {
            "category":"Wholesale",
            "subcategory":"Auto Parts",
            "type":"Manufacturing & Wholesale Goods"
        }
    ],
    "sg:phone":"+1 740 858 4818",
    "sg:postcode":"45663",
    "sg:province":"OH",
    "sg:tags":[
        "automobile",
        "rebuilt",
        "used"
    ],
    "wof:name":"Best Buy Auto Salvage",
    "wof:placetype":"venue"
},
  "geometry": {"coordinates":[-83.080696,38.711621],"type":"Point"}
}