{
  "type": "Feature",
  "properties": {
    "addr:full":"735 S Erie Hwy Hamilton OH 45011",
    "addr:housenumber":"735",
    "addr:postcode":"45011",
    "addr:street":"S Erie Hwy",
    "iso:country":"US",
    "sg:address":"735 S Erie Hwy",
    "sg:city":"Hamilton",
    "sg:classifiers":[
        {
            "category":"Retail",
            "subcategory":"Car Wash",
            "type":"Services"
        }
    ],
    "sg:phone":"+1 513 893 2886",
    "sg:postcode":"45011",
    "sg:province":"OH",
    "sg:tags":[
        "automobile",
        "detail",
        "clean"
    ],
    "wof:name":"Xtream",
    "wof:placetype":"venue"
},
  "geometry": {"coordinates":[-84.54942800000001,39.387373],"type":"Point"}
}