{
  "type": "Feature",
  "properties": {
    "addr:full":"1927 W Sylvania Ave Toledo OH 43613",
    "addr:housenumber":"1927",
    "addr:postcode":"43613",
    "addr:street":"W Sylvania Ave",
    "iso:country":"US",
    "sg:address":"1927 W Sylvania Ave",
    "sg:city":"Toledo",
    "sg:classifiers":[
        {
            "category":"Shopping",
            "subcategory":"Music",
            "type":"Retail Goods"
        }
    ],
    "sg:phone":"+1 419 474 0706",
    "sg:postcode":"43613",
    "sg:province":"OH",
    "wof:name":"House Value Buy & Sell U Cds",
    "wof:placetype":"venue"
},
  "geometry": {"coordinates":[-83.59143899999999,41.692193],"type":"Point"}
}