{
  "type": "Feature",
  "properties": {
    "addr:full": "93 Walburn Ave Franklin Furnace OH 45629",
    "addr:housenumber": "93",
    "addr:postcode": "45629",
    "addr:street": "Walburn Ave",
    "iso:country": "US",
    "sg:address": "93 Walburn Ave",
    "sg:city": "Franklin Furnace",
    "sg:classifiers": [
      {
        "category": "Building \u0026 Trades",
        "subcategory": "Construction",
        "type": "Services"
      }
    ],
    "sg:phone": "+1 740 354 9775",
    "sg:postcode": "45629",
    "sg:province": "OH",
    "sg:tags": [
      "carpentry",
      "contractor"
    ],
    "wof:name": "Jeff Gullett",
    "wof:placetype": "venue"
  },
  "geometry": {"coordinates":[-82.851835,38.62348],"type":"Point"}
}
