{
  "type": "Feature",
  "properties": {
    "iso:country":"US",
    "sg:address":"93 Walburn Ave",
    "sg:city":"Franklin Furnace",
    "sg:classifiers":[
        {
            "category":"Building & Trades",
            "subcategory":"Construction",
            "type":"Services"
        }
    ],
    "sg:phone":"+1 740 354 9775",
    "sg:postcode":"45629",
    "sg:province":"OH",
    "sg:tags":[
        "carpentry",
        "contractor"
    ],
    "wof:name":"Jeff Gullett",
    "wof:placetype":"venue"
},
  "geometry": {"coordinates":[-82.85183499999999,38.62348],"type":"Point"}
}