{
  "type": "Feature",
  "properties": {
    "iso:country":"US",
    "sg:address":"500 N Liberty St",
    "sg:city":"Delaware",
    "sg:classifiers":[
        {
            "category":"Government",
            "subcategory":"Office",
            "type":"Public Place"
        }
    ],
    "sg:phone":"+1 740 363 1821",
    "sg:postcode":"43015",
    "sg:province":"OH",
    "sg:tags":[
        "clinic",
        "health",
        "mental"
    ],
    "wof:name":"Central Ohio Mental Health Ctr",
    "wof:placetype":"venue"
},
  "geometry": {"coordinates":[-83.071608,40.314812],"type":"Point"}
}