{
  "type": "Feature",
  "properties": {
    "addr:full":"330 Rosslyn Ave Columbus OH 43214",
    "addr:housenumber":"330",
    "addr:postcode":"43214",
    "addr:street":"Rosslyn Ave",
    "iso:country":"US",
    "sg:address":"330 Rosslyn Ave",
    "sg:city":"Columbus",
    "sg:classifiers":[
        {
            "category":"Farming",
            "subcategory":"Dairy Farm",
            "type":"Manufacturing & Wholesale Goods"
        }
    ],
    "sg:phone":"+1 614 848 8732",
    "sg:postcode":"43214",
    "sg:province":"OH",
    "wof:name":"Where Quality Counts LLC",
    "wof:placetype":"venue"
},
  "geometry": {"coordinates":[-83.025356,40.072361],"type":"Point"}
}