{
  "type": "Feature",
  "properties": {
    "addr:full": "738 E Archwood Ave Akron OH 44306",
    "addr:housenumber": "738",
    "addr:postcode": "44306",
    "addr:street": "E Archwood Ave",
    "iso:country": "US",
    "sg:address": "738 E Archwood Ave",
    "sg:city": "Akron",
    "sg:classifiers": [
      {
        "category": "Food \u0026 Beverages",
        "subcategory": "Groceries \u0026 Convenience Stores",
        "type": "Retail Goods"
      }
    ],
    "sg:phone": "+1 330 785 4020",
    "sg:postcode": "44306",
    "sg:province": "OH",
    "sg:tags": [
      "grocer"
    ],
    "wof:name": "Far East Oriental Market",
    "wof:placetype": "venue"
  },
  "geometry": {"coordinates":[-81.5003,41.046777],"type":"Point"}
}
