{
  "type": "Feature",
  "properties": {
    "addr:full":"4519 Kellogg Ave Cincinnati OH 45226",
    "addr:housenumber":"4519",
    "addr:postcode":"45226",
    "addr:street":"Kellogg Ave",
    "iso:country":"US",
    "sg:address":"4519 Kellogg Ave",
    "sg:city":"Cincinnati",
    "sg:classifiers":[
        {
            "category":"Autos & Motor Vehicles",
            "subcategory":"Automobile Sales",
            "type":"Retail Goods"
        }
    ],
    "sg:phone":"+1 513 533 9660",
    "sg:postcode":"45226",
    "sg:province":"OH",
    "sg:tags":[
        "used"
    ],
    "wof:name":"Hobie Motors",
    "wof:placetype":"venue"
},
  "geometry": {"coordinates":[-84.42894800000001,39.09514],"type":"Point"}
}