{
  "type": "Feature",
  "properties": {
    "iso:country":"US",
    "sg:address":"16942 Kinsman Rd",
    "sg:city":"Middlefield",
    "sg:classifiers":[
        {
            "category":"Manufacturing",
            "subcategory":"Food",
            "type":"Manufacturing & Wholesale Goods"
        }
    ],
    "sg:phone":"+1 440 632 5567",
    "sg:postcode":"44062",
    "sg:province":"OH",
    "sg:tags":[
        "cheese",
        "processor"
    ],
    "wof:name":"Middlefield Original Cheese Co",
    "wof:placetype":"venue"
},
  "geometry": {"coordinates":[-81.023541,41.459051],"type":"Point"}
}