{
  "type": "Feature",
  "properties": {
    "addr:full":"130 Lyons Dr Dayton OH 45459",
    "addr:housenumber":"130",
    "addr:postcode":"45459",
    "addr:street":"Lyons Dr",
    "iso:country":"US",
    "sg:address":"130 Lyons Dr",
    "sg:city":"Dayton",
    "sg:classifiers":[
        {
            "category":"Organizations",
            "subcategory":"Non-profit Organization",
            "type":"Services"
        }
    ],
    "sg:phone":"+1 937 438 9673",
    "sg:postcode":"45459",
    "sg:province":"OH",
    "sg:tags":[
        "charitable",
        "institution"
    ],
    "wof:name":"Brownfield Charities Inc",
    "wof:placetype":"venue"
},
  "geometry": {"coordinates":[-84.160403,39.632137],"type":"Point"}
}