{
  "type": "Feature",
  "properties": {
    "addr:full": "770 Georgesville Rd Columbus OH 43228",
    "addr:housenumber": "770",
    "addr:postcode": "43228",
    "addr:street": "Georgesville Rd",
    "iso:country": "US",
    "sg:address": "770 Georgesville Rd",
    "sg:city": "Columbus",
    "sg:classifiers": [
      {
        "category": "Professional",
        "subcategory": "Business Services",
        "type": "Services"
      },
      {
        "category": "Government",
        "subcategory": "Post Office",
        "type": "Public Place"
      }
    ],
    "sg:phone": "+1 800 275 8777",
    "sg:postcode": "43228",
    "sg:province": "OH",
    "sg:tags": [
      "mail",
      "shipping"
    ],
    "sg:website": "http://www.usps.com",
    "wof:name": "USPS - United States Post Office - Galloway Carrier Unit",
    "wof:placetype": "venue"
  },
  "geometry": {"coordinates":[-83.113611,39.93638],"type":"Point"}
}
