{
  "type": "Feature",
  "properties": {
    "addr:full":"1263 Shannon Ave Barberton OH 44203",
    "addr:housenumber":"1263",
    "addr:postcode":"44203",
    "addr:street":"Shannon Ave",
    "iso:country":"US",
    "sg:address":"1263 Shannon Ave",
    "sg:city":"Barberton",
    "sg:classifiers":[
        {
            "category":"Organizations",
            "subcategory":"Religious Organization",
            "type":"Services"
        }
    ],
    "sg:phone":"+1 330 825 9543",
    "sg:postcode":"44203",
    "sg:province":"OH",
    "sg:tags":[
        "church"
    ],
    "wof:name":"Prince Of Peace Church",
    "wof:placetype":"venue"
},
  "geometry": {"coordinates":[-81.63702499999999,41.015575],"type":"Point"}
}