{
  "type": "Feature",
  "properties": {
    "addr:full":"6840 Wise Ave NW North Canton OH 44720",
    "addr:housenumber":"6840",
    "addr:postcode":"44720",
    "addr:street":"Wise Ave Nw",
    "iso:country":"US",
    "sg:address":"6840 Wise Ave NW",
    "sg:city":"North Canton",
    "sg:classifiers":[
        {
            "category":"Retail",
            "subcategory":"Auto Repair",
            "type":"Services"
        }
    ],
    "sg:phone":"+1 330 494 7048",
    "sg:postcode":"44720",
    "sg:province":"OH",
    "sg:tags":[
        "repairing",
        "automobile"
    ],
    "wof:name":"Blair's Foreign Car Svc",
    "wof:placetype":"venue"
},
  "geometry": {"coordinates":[-81.42167999999999,40.882127],"type":"Point"}
}