{
  "type": "Feature",
  "properties": {
    "addr:full":"843 Dayton St Hamilton OH 45011",
    "addr:housenumber":"843",
    "addr:postcode":"45011",
    "addr:street":"Dayton St",
    "iso:country":"US",
    "sg:address":"843 Dayton St",
    "sg:city":"Hamilton",
    "sg:classifiers":[
        {
            "category":"Professional",
            "subcategory":"Accounting & Tax Preparation",
            "type":"Services"
        }
    ],
    "sg:phone":"+1 513 863 7511",
    "sg:postcode":"45011",
    "sg:province":"OH",
    "sg:tags":[
        "accountant"
    ],
    "wof:name":"Warren J Townsend CPA",
    "wof:placetype":"venue"
},
  "geometry": {"coordinates":[-84.551152,39.39926],"type":"Point"}
}