{
  "type": "Feature",
  "properties": {
    "addr:full":"32 N Columbus St Sunbury OH 43074",
    "addr:housenumber":"32",
    "addr:postcode":"43074",
    "addr:street":"N Columbus St",
    "iso:country":"US",
    "sg:address":"32 N Columbus St",
    "sg:city":"Sunbury",
    "sg:classifiers":[
        {
            "category":"Restaurant",
            "type":"Food & Drink"
        }
    ],
    "sg:phone":"+1 740 965 3112",
    "sg:postcode":"43074",
    "sg:province":"OH",
    "sg:tags":[
        "eating"
    ],
    "wof:name":"Smugglers Cove Pub",
    "wof:placetype":"venue"
},
  "geometry": {"coordinates":[-82.85964800000001,40.243498],"type":"Point"}
}