{
  "type": "Feature",
  "properties": {
    "iso:country":"US",
    "sg:address":"6460 Peach St NE",
    "sg:city":"Louisville",
    "sg:classifiers":[
        {
            "category":"Retail",
            "subcategory":"Repair Shop",
            "type":"Services"
        }
    ],
    "sg:phone":"+1 330 454 4000",
    "sg:postcode":"44641",
    "sg:province":"OH",
    "sg:tags":[
        "plumbing",
        "drain",
        "cleaning",
        "sewer"
    ],
    "wof:name":"Able Cable Sewer & Drain Svc",
    "wof:placetype":"venue"
},
  "geometry": {"coordinates":[-81.278775,40.839303],"type":"Point"}
}