{
  "type": "Feature",
  "properties": {
    "addr:full": "39558 Bradbury Rd Middleport OH 45760",
    "addr:postcode": "39558;45760",
    "addr:street": "Bradbury Rd",
    "iso:country": "US",
    "sg:address": "39558 Bradbury Rd",
    "sg:city": "Middleport",
    "sg:classifiers": [
      {
        "category": "Organizations",
        "subcategory": "Religious Organization",
        "type": "Services"
      }
    ],
    "sg:phone": "+1 740 992 7369",
    "sg:postcode": "45760",
    "sg:province": "OH",
    "sg:tags": [
      "church"
    ],
    "wof:name": "Bradbury Church Of Christ",
    "wof:placetype": "venue"
  },
  "geometry": {"coordinates":[-82.06182,39.01018],"type":"Point"}
}
