{
  "type": "Feature",
  "properties": {
    "addr:full":"24805 Rapp-Dean Rd Raymond OH 43067",
    "addr:postcode":"24805;43067",
    "addr:street":"Rapp-Dean Rd",
    "iso:country":"US",
    "sg:address":"24805 Rapp-Dean Rd",
    "sg:city":"Raymond",
    "sg:classifiers":[
        {
            "category":"Shopping",
            "subcategory":"Computers & Home Electronics",
            "type":"Retail Goods"
        }
    ],
    "sg:phone":"+1 937 246 3312",
    "sg:postcode":"43067",
    "sg:province":"OH",
    "sg:tags":[
        "software"
    ],
    "wof:name":"PCT",
    "wof:placetype":"venue"
},
  "geometry": {"coordinates":[-83.523898,40.331297],"type":"Point"}
}