{
  "type": "Feature",
  "properties": {
    "addr:full": "1555 N 4th St Columbus OH 43201",
    "addr:housenumber": "1555",
    "addr:postcode": "43201",
    "addr:street": "N 4Th St",
    "iso:country": "US",
    "sg:address": "1555 N 4th St",
    "sg:city": "Columbus",
    "sg:classifiers": [
      {
        "category": "Building \u0026 Trades",
        "subcategory": "Plumbing",
        "type": "Services"
      }
    ],
    "sg:phone": "+1 614 299 9943",
    "sg:postcode": "43201",
    "sg:province": "OH",
    "sg:tags": [
      "heating",
      "contractor"
    ],
    "wof:name": "Love Heating \u0026 Cooling",
    "wof:placetype": "venue"
  },
  "geometry": {"coordinates":[-82.999149,39.994756],"type":"Point"}
}
