{
  "type": "Feature",
  "properties": {
    "iso:country":"US",
    "sg:address":"1555 N 4th St",
    "sg:city":"Columbus",
    "sg:classifiers":[
        {
            "category":"Building & Trades",
            "subcategory":"Plumbing",
            "type":"Services"
        }
    ],
    "sg:phone":"+1 614 299 9943",
    "sg:postcode":"43201",
    "sg:province":"OH",
    "sg:tags":[
        "heating",
        "contractor"
    ],
    "wof:name":"Love Heating & Cooling",
    "wof:placetype":"venue"
},
  "geometry": {"coordinates":[-82.999149,39.994756],"type":"Point"}
}