{
  "type": "Feature",
  "properties": {
    "iso:country":"US",
    "sg:address":"7160 Columbia Rd",
    "sg:city":"Cleveland",
    "sg:classifiers":[
        {
            "category":"Autos & Motor Vehicles",
            "subcategory":"Fuel & Gas Station",
            "type":"Retail Goods"
        }
    ],
    "sg:phone":"+1 440 235 3827",
    "sg:postcode":"44138",
    "sg:province":"OH",
    "sg:tags":[
        "station",
        "gasoline",
        "oil"
    ],
    "wof:name":"Olmsted Marathon",
    "wof:placetype":"venue"
},
  "geometry": {"coordinates":[-81.903088,41.38622],"type":"Point"}
}