{
  "type": "Feature",
  "properties": {
    "addr:full": "380 Dresden Adamsville Rd Dresden OH 43821",
    "addr:housenumber": "380",
    "addr:postcode": "43821",
    "addr:street": "Dresden Adamsville Rd",
    "iso:country": "US",
    "sg:address": "380 Dresden Adamsville Rd",
    "sg:city": "Dresden",
    "sg:classifiers": [
      {
        "category": "Farming",
        "subcategory": "Livestock Farm",
        "type": "Manufacturing \u0026 Wholesale Goods"
      }
    ],
    "sg:phone": "+1 740 754 1226",
    "sg:postcode": "43821",
    "sg:province": "OH",
    "sg:tags": [
      "animal",
      "general"
    ],
    "wof:name": "Spiker Farm",
    "wof:placetype": "venue"
  },
  "geometry": {"coordinates":[-81.995027,40.123784],"type":"Point"}
}
