{
  "type": "Feature",
  "properties": {
    "iso:country":"US",
    "sg:address":"40 E Main St",
    "sg:city":"Westerville",
    "sg:classifiers":[
        {
            "category":"Building & Trades",
            "subcategory":"Construction",
            "type":"Services"
        }
    ],
    "sg:phone":"+1 614 523 4288",
    "sg:postcode":"43081",
    "sg:province":"OH",
    "sg:tags":[
        "housing"
    ],
    "wof:name":"Craftmaster",
    "wof:placetype":"venue"
},
  "geometry": {"coordinates":[-82.929287,40.126783],"type":"Point"}
}