{
  "type": "Feature",
  "properties": {
    "iso:country":"US",
    "sg:address":"906 Napoleon Rd",
    "sg:city":"Bowling Green",
    "sg:classifiers":[
        {
            "category":"Retail",
            "subcategory":"Repair Shop",
            "type":"Services"
        }
    ],
    "sg:phone":"+1 419 353 7772",
    "sg:postcode":"43402",
    "sg:province":"OH",
    "sg:tags":[
        "lock",
        "locksmith"
    ],
    "wof:name":"B G Lock & Key",
    "wof:placetype":"venue"
},
  "geometry": {"coordinates":[-83.639128,41.363672],"type":"Point"}
}