{
  "type": "Feature",
  "properties": {
    "iso:country":"US",
    "sg:address":"364 Foundry St",
    "sg:city":"Medina",
    "sg:classifiers":[
        {
            "category":"Organizations",
            "subcategory":"Religious Organization",
            "type":"Services"
        }
    ],
    "sg:phone":"+1 330 725 4520",
    "sg:postcode":"44256",
    "sg:province":"OH",
    "sg:tags":[
        "church"
    ],
    "wof:name":"Church Of God MPGT",
    "wof:placetype":"venue"
},
  "geometry": {"coordinates":[-81.87277899999999,41.14326],"type":"Point"}
}