{
  "type": "Feature",
  "properties": {
    "addr:full": "1351 N Warpole St Upper Sandusky OH 43351",
    "addr:housenumber": "1351",
    "addr:postcode": "43351",
    "addr:street": "N Warpole St",
    "iso:country": "US",
    "sg:address": "1351 N Warpole St",
    "sg:city": "Upper Sandusky",
    "sg:classifiers": [
      {
        "category": "Restaurant",
        "type": "Food \u0026 Drink"
      }
    ],
    "sg:menulink": "http://www.allmenus.com/oh/crane/185032-woodys-restaurant/menu/",
    "sg:phone": "+1 419 294 1434",
    "sg:postcode": "43351",
    "sg:province": "OH",
    "sg:tags": [
      "american"
    ],
    "wof:name": "Woody's Restaurant",
    "wof:placetype": "venue"
  },
  "geometry": {"coordinates":[-83.290095,40.832212],"type":"Point"}
}
