{
  "type": "Feature",
  "properties": {
    "addr:full":"19 Highland Ct Medina OH 44256",
    "addr:housenumber":"19",
    "addr:postcode":"44256",
    "addr:street":"Highland Ct",
    "iso:country":"US",
    "sg:address":"19 Highland Ct",
    "sg:city":"Medina",
    "sg:classifiers":[
        {
            "category":"Shopping",
            "type":"Retail Goods"
        }
    ],
    "sg:phone":"+1 330 725 1060",
    "sg:postcode":"44256",
    "sg:province":"OH",
    "sg:tags":[
        "hearing",
        "equipment",
        "supply",
        "merchandise",
        "impaired"
    ],
    "wof:name":"Medina Hearing Aid Service",
    "wof:placetype":"venue"
},
  "geometry": {"coordinates":[-81.86374000000001,41.148926],"type":"Point"}
}