{
  "type": "Feature",
  "properties": {
    "iso:country":"US",
    "sg:address":"81 E State St",
    "sg:city":"Sharon",
    "sg:classifiers":[
        {
            "category":"Professional",
            "subcategory":"Advertising",
            "type":"Services"
        }
    ],
    "sg:phone":"+1 724 981 1566",
    "sg:postcode":"16146",
    "sg:province":"OH",
    "sg:tags":[
        "marketing",
        "medium",
        "buying"
    ],
    "sg:website":"www.wa2.com",
    "wof:name":"Winner Advertising",
    "wof:placetype":"venue"
},
  "geometry": {"coordinates":[-80.508358,41.232986],"type":"Point"}
}