{
  "type": "Feature",
  "properties": {
    "iso:country":"US",
    "sg:address":"245 New Milford Rd",
    "sg:city":"Ravenna",
    "sg:classifiers":[
        {
            "category":"Health Services",
            "subcategory":"Nursing And Care Facility",
            "type":"Services"
        }
    ],
    "sg:phone":"+1 330 296 6415",
    "sg:postcode":"44266",
    "sg:province":"OH",
    "sg:tags":[
        "home"
    ],
    "wof:name":"Altercare Of Ravenna",
    "wof:placetype":"venue"
},
  "geometry": {"coordinates":[-81.223782,41.156799],"type":"Point"}
}