{
  "type": "Feature",
  "properties": {
    "addr:full": "5522 Turney Rd Cleveland OH 44125",
    "addr:housenumber": "5522",
    "addr:postcode": "44125",
    "addr:street": "Turney Rd",
    "iso:country": "US",
    "sg:address": "5522 Turney Rd",
    "sg:city": "Cleveland",
    "sg:classifiers": [
      {
        "category": "Personal",
        "subcategory": "Beauty Salon",
        "type": "Services"
      }
    ],
    "sg:phone": "+1 216 663 6633",
    "sg:postcode": "44125",
    "sg:province": "OH",
    "sg:tags": [
      "shop"
    ],
    "wof:name": "Odyssey Hair Fashions",
    "wof:placetype": "venue"
  },
  "geometry": {"coordinates":[-81.603092,41.412907],"type":"Point"}
}
