{
  "type": "Feature",
  "properties": {
    "addr:full": "39462 Center Ridge Rd North Ridgeville OH 44039",
    "addr:housenumber": "39462",
    "addr:postcode": "44039",
    "addr:street": "Center Ridge Rd",
    "iso:country": "US",
    "sg:address": "39462 Center Ridge Rd",
    "sg:city": "North Ridgeville",
    "sg:classifiers": [
      {
        "category": "Personal",
        "subcategory": "Beauty Salon",
        "type": "Services"
      }
    ],
    "sg:phone": "+1 440 353 6576",
    "sg:postcode": "44039",
    "sg:province": "OH",
    "wof:name": "Guys N Dolls",
    "wof:placetype": "venue"
  },
  "geometry": {"coordinates":[-82.067667,41.380483],"type":"Point"}
}
