{
  "type": "Feature",
  "properties": {
    "addr:full":"1 Ohio Machinery Blvd Girard OH 44420",
    "addr:housenumber":"1",
    "addr:postcode":"44420",
    "addr:street":"Ohio Machinery Blvd",
    "iso:country":"US",
    "sg:address":"1 Ohio Machinery Blvd",
    "sg:city":"Girard",
    "sg:classifiers":[
        {
            "category":"Retail",
            "subcategory":"Repair Shop",
            "type":"Services"
        }
    ],
    "sg:phone":"+1 330 530 9010",
    "sg:postcode":"44420",
    "sg:province":"OH",
    "sg:tags":[
        "equipment"
    ],
    "wof:name":"Ohio Cat",
    "wof:placetype":"venue"
},
  "geometry": {"coordinates":[-80.72190999999999,41.139779],"type":"Point"}
}