{
  "type": "Feature",
  "properties": {
    "addr:full": "7313 Ravenna Rd Painesville OH 44077",
    "addr:housenumber": "7313",
    "addr:postcode": "44077",
    "addr:street": "Ravenna Rd",
    "iso:country": "US",
    "sg:address": "7313 Ravenna Rd",
    "sg:city": "Painesville",
    "sg:classifiers": [
      {
        "category": "Building \u0026 Trades",
        "subcategory": "Construction",
        "type": "Services"
      }
    ],
    "sg:phone": "+1 440 352 9752",
    "sg:postcode": "44077",
    "sg:province": "OH",
    "sg:tags": [
      "concrete",
      "contractor"
    ],
    "wof:name": "Long Concrete Inc",
    "wof:placetype": "venue"
  },
  "geometry": {"coordinates":[-81.223043,41.672107],"type":"Point"}
}
