{
  "type": "Feature",
  "properties": {
    "addr:full": "4848 Duff Dr Cincinnati OH 45246",
    "addr:housenumber": "4848",
    "addr:postcode": "45246",
    "addr:street": "Duff Dr",
    "iso:country": "US",
    "sg:address": "4848 Duff Dr",
    "sg:city": "Cincinnati",
    "sg:classifiers": [
      {
        "category": "Building \u0026 Trades",
        "subcategory": "Construction",
        "type": "Services"
      }
    ],
    "sg:phone": "+1 513 874 3496",
    "sg:postcode": "45246",
    "sg:province": "OH",
    "sg:tags": [
      "new",
      "industrial",
      "commercial"
    ],
    "wof:name": "Villa Construction",
    "wof:placetype": "venue"
  },
  "geometry": {"coordinates":[-84.46378,39.310384],"type":"Point"}
}
