{
  "type": "Feature",
  "properties": {
    "iso:country":"US",
    "sg:address":"401 Otterbein Ave",
    "sg:city":"Dayton",
    "sg:classifiers":[
        {
            "category":"Building & Trades",
            "subcategory":"Cleaning & Sanitation",
            "type":"Services"
        }
    ],
    "sg:phone":"+1 937 278 1924",
    "sg:postcode":"45406",
    "sg:province":"OH",
    "sg:tags":[
        "car",
        "material",
        "wash",
        "bio"
    ],
    "wof:name":"Gssp Enterprises Inc",
    "wof:placetype":"venue"
},
  "geometry": {"coordinates":[-84.23018999999999,39.780981],"type":"Point"}
}