{
  "type": "Feature",
  "properties": {
    "iso:country":"US",
    "sg:address":"22555 Ascoa Ct",
    "sg:city":"Strongsville",
    "sg:classifiers":[
        {
            "category":"Wholesale",
            "subcategory":"Durable Goods & Equipment",
            "type":"Manufacturing & Wholesale Goods"
        }
    ],
    "sg:phone":"+1 440 878 1111",
    "sg:postcode":"44149",
    "sg:province":"OH",
    "sg:tags":[
        "representative",
        "manufacturer"
    ],
    "wof:name":"Demag Rapistan",
    "wof:placetype":"venue"
},
  "geometry": {"coordinates":[-81.872381,41.301122],"type":"Point"}
}