{
  "type": "Feature",
  "properties": {
    "addr:full": "4524 Este Ave Cincinnati OH 45232",
    "addr:housenumber": "4524",
    "addr:postcode": "45232",
    "addr:street": "Este Ave",
    "iso:country": "US",
    "sg:address": "4524 Este Ave",
    "sg:city": "Cincinnati",
    "sg:classifiers": [
      {
        "category": "Manufacturing",
        "subcategory": "Chemicals \u0026 Compounds",
        "type": "Manufacturing \u0026 Wholesale Goods"
      }
    ],
    "sg:phone": "+1 513 541 5631",
    "sg:postcode": "45232",
    "sg:province": "OH",
    "sg:tags": [
      "emulsifier",
      "mfr"
    ],
    "wof:name": "Berghausen Corporation",
    "wof:placetype": "venue"
  },
  "geometry": {"coordinates":[-84.511977,39.172194],"type":"Point"}
}
