{
  "type": "Feature",
  "properties": {
    "iso:country":"US",
    "sg:address":"410 N Memorial Dr",
    "sg:city":"Lancaster",
    "sg:classifiers":[
        {
            "category":"Autos & Motor Vehicles",
            "subcategory":"Auto Supplies",
            "type":"Retail Goods"
        }
    ],
    "sg:phone":"+1 740 654 9850",
    "sg:postcode":"43130",
    "sg:province":"OH",
    "sg:tags":[
        "tire"
    ],
    "wof:name":"Mr Tire",
    "wof:placetype":"venue"
},
  "geometry": {"coordinates":[-82.606858,39.718114],"type":"Point"}
}