{
  "type": "Feature",
  "properties": {
    "addr:full": "10812 Adeline Ave Cleveland OH 44111",
    "addr:housenumber": "10812",
    "addr:postcode": "44111",
    "addr:street": "Adeline Ave",
    "iso:country": "US",
    "sg:address": "10812 Adeline Ave",
    "sg:city": "Cleveland",
    "sg:classifiers": [
      {
        "category": "Organizations",
        "subcategory": "Religious Organization",
        "type": "Services"
      }
    ],
    "sg:phone": "+1 216 941 6808",
    "sg:postcode": "44111",
    "sg:province": "OH",
    "sg:tags": [
      "church"
    ],
    "wof:name": "Sts Philip \u0026 James Church",
    "wof:placetype": "venue"
  },
  "geometry": {"coordinates":[-81.763128,41.451195],"type":"Point"}
}
