{
  "type": "Feature",
  "properties": {
    "addr:full": "201 W Main St Hillsboro OH 45133",
    "addr:housenumber": "201",
    "addr:postcode": "45133",
    "addr:street": "W Main St",
    "iso:country": "US",
    "sg:address": "201 W Main St",
    "sg:city": "Hillsboro",
    "sg:classifiers": [
      {
        "category": "Travel",
        "subcategory": "Hotels \u0026 Motels",
        "type": "Entertainment"
      }
    ],
    "sg:phone": "+1 937 393 9175",
    "sg:postcode": "45133",
    "sg:province": "OH",
    "wof:name": "Hill City Hotel",
    "wof:placetype": "venue"
  },
  "geometry": {"coordinates":[-83.615639,39.202793],"type":"Point"}
}
