{
  "type": "Feature",
  "properties": {
    "addr:full":"8066 Luckstone Dr Dublin OH 43017",
    "addr:housenumber":"8066",
    "addr:postcode":"43017",
    "addr:street":"Luckstone Dr",
    "iso:country":"US",
    "sg:address":"8066 Luckstone Dr",
    "sg:city":"Dublin",
    "sg:classifiers":[
        {
            "category":"Real Estate",
            "subcategory":"Real Estate Operator",
            "type":"Services"
        }
    ],
    "sg:phone":"+1 614 336 9096",
    "sg:postcode":"43017",
    "sg:province":"OH",
    "sg:tags":[
        "building",
        "nonresidential"
    ],
    "wof:name":"GLC Properties LLC",
    "wof:placetype":"venue"
},
  "geometry": {"coordinates":[-83.14437,40.130198],"type":"Point"}
}