{
  "type": "Feature",
  "properties": {
    "addr:full": "12402 Lancaster St Millersport OH 43046",
    "addr:housenumber": "12402",
    "addr:postcode": "43046",
    "addr:street": "Lancaster St",
    "iso:country": "US",
    "sg:address": "12402 Lancaster St",
    "sg:city": "Millersport",
    "sg:classifiers": [
      {
        "category": "Real Estate",
        "subcategory": "Real Estate Agent",
        "type": "Services"
      }
    ],
    "sg:phone": "+1 740 467 2552",
    "sg:postcode": "43046",
    "sg:province": "OH",
    "wof:name": "Farmers Realty",
    "wof:placetype": "venue"
  },
  "geometry": {"coordinates":[-82.534372,39.904197],"type":"Point"}
}
