{
  "type": "Feature",
  "properties": {
    "addr:full":"24190 Wilderness Trl Olmsted Falls OH 44138",
    "addr:housenumber":"24190",
    "addr:postcode":"44138",
    "addr:street":"Wilderness Trl",
    "iso:country":"US",
    "sg:address":"24190 Wilderness Trl",
    "sg:city":"Olmsted Falls",
    "sg:classifiers":[
        {
            "category":"Shopping",
            "subcategory":"Jewelry",
            "type":"Retail Goods"
        }
    ],
    "sg:phone":"+1 440 891 4437",
    "sg:postcode":"44138",
    "sg:province":"OH",
    "wof:name":"Love Silver Jewelry",
    "wof:placetype":"venue"
},
  "geometry": {"coordinates":[-81.88833099999999,41.364123],"type":"Point"}
}