{
  "type": "Feature",
  "properties": {
    "iso:country":"US",
    "sg:address":"6671 Maple Canyon Ave",
    "sg:city":"Columbus",
    "sg:classifiers":[
        {
            "category":"Real Estate",
            "subcategory":"Real Estate Operator",
            "type":"Services"
        }
    ],
    "sg:phone":"+1 614 431 0503",
    "sg:postcode":"43229",
    "sg:province":"OH",
    "sg:tags":[
        "apartment"
    ],
    "wof:name":"York Terrace",
    "wof:placetype":"venue"
},
  "geometry": {"coordinates":[-82.958304,40.097721],"type":"Point"}
}