{
  "type": "Feature",
  "properties": {
    "addr:full": "424 Earl Ct Elyria OH 44035",
    "addr:housenumber": "424",
    "addr:postcode": "44035",
    "addr:street": "Earl Ct",
    "iso:country": "US",
    "sg:address": "424 Earl Ct",
    "sg:city": "Elyria",
    "sg:classifiers": [
      {
        "category": "Social Services",
        "subcategory": "Child Care",
        "type": "Services"
      }
    ],
    "sg:phone": "+1 440 284 9724",
    "sg:postcode": "44035",
    "sg:province": "OH",
    "sg:website": "www.linden-school.org",
    "wof:name": "Linden School",
    "wof:placetype": "venue"
  },
  "geometry": {"coordinates":[-82.110835,41.361109],"type":"Point"}
}
