{
  "type": "Feature",
  "properties": {
    "addr:full":"7026 Woodthrush Ave Painesville OH 44077",
    "addr:postcode":"7026;44077",
    "addr:street":"Woodthrush Ave",
    "iso:country":"US",
    "sg:address":"7026 Woodthrush Ave",
    "sg:city":"Painesville",
    "sg:classifiers":[
        {
            "category":"Building & Trades",
            "subcategory":"Construction",
            "type":"Services"
        }
    ],
    "sg:phone":"+1 440 352 1938",
    "sg:postcode":"44077",
    "sg:province":"OH",
    "sg:tags":[
        "residential",
        "nonresidential"
    ],
    "wof:name":"Lett Construction",
    "wof:placetype":"venue"
},
  "geometry": {"coordinates":[-81.234146,41.679437],"type":"Point"}
}