{
  "type": "Feature",
  "properties": {
    "addr:full":"301 Main St Toronto OH 43964",
    "addr:housenumber":"301",
    "addr:postcode":"43964",
    "addr:street":"Main St",
    "iso:country":"US",
    "sg:address":"301 Main St",
    "sg:city":"Toronto",
    "sg:classifiers":[
        {
            "category":"Autos & Motor Vehicles",
            "subcategory":"Auto Supplies",
            "type":"Retail Goods"
        }
    ],
    "sg:phone":"+1 740 537 4099",
    "sg:postcode":"43964",
    "sg:province":"OH",
    "sg:tags":[
        "tire"
    ],
    "wof:name":"Hometown Tire & Auto Inc",
    "wof:placetype":"venue"
},
  "geometry": {"coordinates":[-80.601007,40.464439],"type":"Point"}
}