{
  "type": "Feature",
  "properties": {
    "iso:country":"US",
    "sg:address":"27001 Risch Rd",
    "sg:city":"Rockbridge",
    "sg:phone":"+1 740 385 5164",
    "sg:postcode":"43149",
    "sg:province":"OH",
    "sg:tags":[
        "farm",
        "field",
        "crop"
    ],
    "wof:name":"Hal Nihiser",
    "wof:placetype":"venue"
},
  "geometry": {"coordinates":[-82.51926899999999,39.559484],"type":"Point"}
}