{
  "type": "Feature",
  "properties": {
    "addr:full": "27001 Risch Rd Rockbridge OH 43149",
    "addr:postcode": "27001;43149",
    "addr:street": "Risch Rd",
    "iso:country": "US",
    "sg:address": "27001 Risch Rd",
    "sg:city": "Rockbridge",
    "sg:phone": "+1 740 385 5164",
    "sg:postcode": "43149",
    "sg:province": "OH",
    "sg:tags": [
      "farm",
      "field",
      "crop"
    ],
    "wof:name": "Hal Nihiser",
    "wof:placetype": "venue"
  },
  "geometry": {"coordinates":[-82.519269,39.559484],"type":"Point"}
}
