{
  "type": "Feature",
  "properties": {
    "addr:full": "1783 N Hampton Rd New Carlisle OH 45344",
    "addr:housenumber": "1783",
    "addr:postcode": "45344",
    "addr:street": "N Hampton Rd",
    "iso:country": "US",
    "sg:address": "1783 N Hampton Rd",
    "sg:city": "New Carlisle",
    "sg:phone": "+1 937 882 6856",
    "sg:postcode": "45344",
    "sg:province": "OH",
    "sg:tags": [
      "farm",
      "bean",
      "soybean",
      "supply"
    ],
    "wof:name": "Hartman Farm",
    "wof:placetype": "venue"
  },
  "geometry": {"coordinates":[-83.952271,39.946695],"type":"Point"}
}
