{
  "type": "Feature",
  "properties": {
    "iso:country":"US",
    "sg:address":"23 Ridge Rd",
    "sg:city":"Apple Creek",
    "sg:classifiers":[
        {
            "category":"Wholesale",
            "subcategory":"Furniture",
            "type":"Manufacturing & Wholesale Goods"
        }
    ],
    "sg:phone":"+1 330 698 6877",
    "sg:postcode":"44657",
    "sg:province":"OH",
    "wof:name":"Continental Office",
    "wof:placetype":"venue"
},
  "geometry": {"coordinates":[-81.079432,40.727796],"type":"Point"}
}