{
  "type": "Feature",
  "properties": {
    "iso:country":"US",
    "sg:address":"25670 1st St",
    "sg:city":"Cleveland",
    "sg:classifiers":[
        {
            "category":"Wholesale",
            "subcategory":"Durable Goods & Equipment",
            "type":"Manufacturing & Wholesale Goods"
        }
    ],
    "sg:phone":"+1 440 835 8071",
    "sg:postcode":"44145",
    "sg:province":"OH",
    "sg:tags":[
        "representative",
        "manufacturer"
    ],
    "wof:name":"Shoreside",
    "wof:placetype":"venue"
},
  "geometry": {"coordinates":[-81.908838,41.476364],"type":"Point"}
}