{
  "type": "Feature",
  "properties": {
    "addr:full":"630 Harding Way W Galion OH 44833",
    "addr:housenumber":"630",
    "addr:postcode":"44833",
    "addr:street":"Harding Way W",
    "iso:country":"US",
    "sg:address":"630 Harding Way W",
    "sg:city":"Galion",
    "sg:classifiers":[
        {
            "category":"Shopping",
            "subcategory":"Hobbies, Toys, & Games",
            "type":"Retail Goods"
        },
        {
            "category":"Shopping",
            "subcategory":"Crafts & Fabrics",
            "type":"Retail Goods"
        }
    ],
    "sg:phone":"+1 419 468 7830",
    "sg:postcode":"44833",
    "sg:province":"OH",
    "sg:tags":[
        "shop",
        "hobby",
        "model",
        "supply"
    ],
    "wof:name":"Ohio Wood Craft",
    "wof:placetype":"venue"
},
  "geometry": {"coordinates":[-82.798759,40.734028],"type":"Point"}
}