{
  "type": "Feature",
  "properties": {
    "iso:country":"US",
    "sg:address":"2769 State Rte 131",
    "sg:city":"Batavia",
    "sg:classifiers":[
        {
            "category":"Retail",
            "subcategory":"Auto Repair",
            "type":"Services"
        }
    ],
    "sg:phone":"+1 513 625 0016",
    "sg:postcode":"45103",
    "sg:province":"OH",
    "sg:tags":[
        "repairing",
        "automobile"
    ],
    "wof:name":"Joe's Auto Repair",
    "wof:placetype":"venue"
},
  "geometry": {"coordinates":[-84.100714,39.178305],"type":"Point"}
}