{
  "type": "Feature",
  "properties": {
    "addr:full":"108 Pine Ave St Clairsville OH 43950",
    "addr:housenumber":"108",
    "addr:postcode":"43950",
    "addr:street":"Pine Ave",
    "iso:country":"US",
    "sg:address":"108 Pine Ave",
    "sg:city":"St Clairsville",
    "sg:classifiers":[
        {
            "category":"Health Services",
            "subcategory":"Nursing And Care Facility",
            "type":"Services"
        },
        {
            "category":"Real Estate",
            "subcategory":"Real Estate Operator",
            "type":"Services"
        }
    ],
    "sg:phone":"+1 740 695 7275",
    "sg:postcode":"43950",
    "sg:province":"OH",
    "sg:tags":[
        "building",
        "home",
        "apartment",
        "rest"
    ],
    "wof:name":"Mark H Kennedy Retirement Park",
    "wof:placetype":"venue"
},
  "geometry": {"coordinates":[-80.91385099999999,40.080208],"type":"Point"}
}