{
  "type": "Feature",
  "properties": {
    "addr:full":"3217 Waterloo Rd Mogadore OH 44260",
    "addr:housenumber":"3217",
    "addr:postcode":"44260",
    "addr:street":"Waterloo Rd",
    "iso:country":"US",
    "sg:address":"3217 Waterloo Rd",
    "sg:city":"Mogadore",
    "sg:classifiers":[
        {
            "category":"Arts & Performance",
            "subcategory":"Theater",
            "type":"Entertainment"
        }
    ],
    "sg:phone":"+1 330 628 5560",
    "sg:postcode":"44260",
    "sg:province":"OH",
    "sg:tags":[
        "equipment",
        "theatrical",
        "supply"
    ],
    "wof:name":"Akron Theatrical Svc",
    "wof:placetype":"venue"
},
  "geometry": {"coordinates":[-81.272531,41.033179],"type":"Point"}
}