{
  "type": "Feature",
  "properties": {
    "addr:full": "2838 Observatory Ave Cincinnati OH 45208",
    "addr:housenumber": "2838",
    "addr:postcode": "45208",
    "addr:street": "Observatory Ave",
    "iso:country": "US",
    "sg:address": "2838 Observatory Ave",
    "sg:city": "Cincinnati",
    "sg:classifiers": [
      {
        "category": "Shopping",
        "subcategory": "Florist",
        "type": "Retail Goods"
      }
    ],
    "sg:phone": "+1 513 871 8884",
    "sg:postcode": "45208",
    "sg:province": "OH",
    "wof:name": "Adrian Vurban Florist",
    "wof:placetype": "venue"
  },
  "geometry": {"coordinates":[-84.437429,39.137167],"type":"Point"}
}
