{
  "type": "Feature",
  "properties": {
    "addr:full":"739 Ridgewood Dr Coshocton OH 43812",
    "addr:housenumber":"739",
    "addr:postcode":"43812",
    "addr:street":"Ridgewood Dr",
    "iso:country":"US",
    "sg:address":"739 Ridgewood Dr",
    "sg:city":"Coshocton",
    "sg:classifiers":[
        {
            "category":"Organizations",
            "subcategory":"Religious Organization",
            "type":"Services"
        }
    ],
    "sg:phone":"+1 740 622 4662",
    "sg:postcode":"43812",
    "sg:province":"OH",
    "sg:tags":[
        "clergy"
    ],
    "wof:name":"Robert Millspaugh",
    "wof:placetype":"venue"
},
  "geometry": {"coordinates":[-81.83385,40.261588],"type":"Point"}
}