{
  "type": "Feature",
  "properties": {
    "iso:country":"US",
    "sg:address":"10617 Frank Ave",
    "sg:city":"Cleveland",
    "sg:classifiers":[
        {
            "category":"Wholesale",
            "subcategory":"Drugs",
            "type":"Manufacturing & Wholesale Goods"
        }
    ],
    "sg:phone":"+1 216 231 6441",
    "sg:postcode":"44106",
    "sg:province":"OH",
    "sg:tags":[
        "pharmaceutical",
        "product"
    ],
    "wof:name":"Reese Pharmacutical",
    "wof:placetype":"venue"
},
  "geometry": {"coordinates":[-81.611871,41.497896],"type":"Point"}
}