{
  "type": "Feature",
  "properties": {
    "iso:country":"US",
    "sg:address":"715 US Hwy 250 E",
    "sg:city":"Ashland",
    "sg:classifiers":[
        {
            "category":"Professional",
            "type":"Services"
        }
    ],
    "sg:phone":"+1 419 281 1714",
    "sg:postcode":"44805",
    "sg:province":"OH",
    "sg:tags":[
        "establishment"
    ],
    "wof:name":"Dial A Truck",
    "wof:placetype":"venue"
},
  "geometry": {"coordinates":[-82.261332,40.857358],"type":"Point"}
}