{
  "type": "Feature",
  "properties": {
    "iso:country":"US",
    "sg:address":"2900 Glengarry Dr",
    "sg:city":"Dayton",
    "sg:classifiers":[
        {
            "category":"Shopping",
            "subcategory":"Bicycles & Sporting Goods",
            "type":"Retail Goods"
        }
    ],
    "sg:phone":"+1 937 294 2966",
    "sg:postcode":"45420",
    "sg:province":"OH",
    "wof:name":"Hockey World",
    "wof:placetype":"venue"
},
  "geometry": {"coordinates":[-84.112361,39.694873],"type":"Point"}
}