{
  "type": "Feature",
  "properties": {
    "addr:full": "15316 Kinsman Rd Cleveland OH 44120",
    "addr:housenumber": "15316",
    "addr:postcode": "44120",
    "addr:street": "Kinsman Rd",
    "iso:country": "US",
    "sg:address": "15316 Kinsman Rd",
    "sg:city": "Cleveland",
    "sg:classifiers": [
      {
        "category": "Restaurant",
        "type": "Food \u0026 Drink"
      }
    ],
    "sg:phone": "+1 216 991 5402",
    "sg:postcode": "44120",
    "sg:province": "OH",
    "sg:tags": [
      "delicatessen"
    ],
    "wof:name": "Native Son Delicatessen",
    "wof:placetype": "venue"
  },
  "geometry": {"coordinates":[-81.57326,41.464333],"type":"Point"}
}
