{
  "type": "Feature",
  "properties": {
    "iso:country":"US",
    "sg:address":"374 S Main St",
    "sg:city":"Akron",
    "sg:classifiers":[
        {
            "category":"Shopping",
            "type":"Retail Goods"
        }
    ],
    "sg:phone":"+1 330 535 5544",
    "sg:postcode":"44311",
    "sg:province":"OH",
    "sg:tags":[
        "art",
        "gallery",
        "dealer"
    ],
    "wof:name":"In Collaboration",
    "wof:placetype":"venue"
},
  "geometry": {"coordinates":[-81.522541,41.076104],"type":"Point"}
}