{
  "type": "Feature",
  "properties": {
    "iso:country":"US",
    "sg:address":"469 Cherry Wood Cir",
    "sg:city":"Northfield",
    "sg:classifiers":[
        {
            "category":"Retail",
            "subcategory":"Auto Repair",
            "type":"Services"
        }
    ],
    "sg:phone":"+1 330 467 9849",
    "sg:postcode":"44067",
    "sg:province":"OH",
    "sg:tags":[
        "wrecker"
    ],
    "wof:name":"Interstate Wrecker Svc",
    "wof:placetype":"venue"
},
  "geometry": {"coordinates":[-81.545534,41.347789],"type":"Point"}
}