{
  "type": "Feature",
  "properties": {
    "iso:country":"US",
    "sg:address":"3595 Urbancrest Industrial Dr",
    "sg:city":"Grove City",
    "sg:classifiers":[
        {
            "category":"Freight",
            "type":"Transportation"
        }
    ],
    "sg:phone":"+1 614 871 0666",
    "sg:postcode":"43123",
    "sg:province":"OH",
    "sg:tags":[
        "delivery"
    ],
    "wof:name":"Appliance Custom Delivery",
    "wof:placetype":"venue"
},
  "geometry": {"coordinates":[-83.092795,39.903472],"type":"Point"}
}