{
  "type": "Feature",
  "properties": {
    "addr:full":"6091 Mcnaughten Ctr Columbus OH 43232",
    "addr:postcode":"6091;43232",
    "addr:street":"Mcnaughten",
    "iso:country":"US",
    "sg:address":"6091 Mcnaughten Ctr",
    "sg:city":"Columbus",
    "sg:classifiers":[
        {
            "category":"Shopping",
            "subcategory":"Jewelry",
            "type":"Retail Goods"
        },
        {
            "category":"Manufacturing",
            "subcategory":"Jewelry",
            "type":"Manufacturing & Wholesale Goods"
        }
    ],
    "sg:phone":"+1 614 861 1188",
    "sg:postcode":"43232",
    "sg:province":"OH",
    "sg:tags":[
        "designer",
        "jeweler"
    ],
    "wof:name":"Executive Jewelry & Watch Co.",
    "wof:placetype":"venue"
},
  "geometry": {"coordinates":[-82.83832099999999,39.953442],"type":"Point"}
}