{
  "type": "Feature",
  "properties": {
    "addr:full": "5323 State Rd Cleveland OH 44134",
    "addr:housenumber": "5323",
    "addr:postcode": "44134",
    "addr:street": "State Rd",
    "iso:country": "US",
    "sg:address": "5323 State Rd",
    "sg:city": "Cleveland",
    "sg:classifiers": [
      {
        "category": "Health Services",
        "subcategory": "Doctor",
        "type": "Services"
      }
    ],
    "sg:phone": "+1 216 741 6068",
    "sg:postcode": "44134",
    "sg:province": "OH",
    "sg:tags": [
      "dentist"
    ],
    "wof:name": "Kenneth L Baiko DDS",
    "wof:placetype": "venue"
  },
  "geometry": {"coordinates":[-81.710393,41.415033],"type":"Point"}
}
