{
  "type": "Feature",
  "properties": {
    "addr:full":"547 Loveland Madeira Rd Loveland OH 45140",
    "addr:housenumber":"547",
    "addr:postcode":"45140",
    "addr:street":"Loveland Madeira Rd",
    "iso:country":"US",
    "sg:address":"547 Loveland Madeira Rd",
    "sg:city":"Loveland",
    "sg:classifiers":[
        {
            "category":"Shopping",
            "subcategory":"Jewelry",
            "type":"Retail Goods"
        }
    ],
    "sg:phone":"+1 513 683 3379",
    "sg:postcode":"45140",
    "sg:province":"OH",
    "sg:tags":[
        "jeweler"
    ],
    "wof:name":"Watkins Jewelry Plus Inc",
    "wof:placetype":"venue"
},
  "geometry": {"coordinates":[-84.27029400000001,39.26292],"type":"Point"}
}