{
  "type": "Feature",
  "properties": {
    "addr:full": "13231 Salem Church St NE Alliance OH 44601",
    "addr:housenumber": "13231",
    "addr:postcode": "44601",
    "addr:street": "Salem Church St Ne",
    "iso:country": "US",
    "sg:address": "13231 Salem Church St NE",
    "sg:city": "Alliance",
    "sg:classifiers": [
      {
        "category": "Manufacturing",
        "subcategory": "Tools \u0026 Machinery",
        "type": "Manufacturing \u0026 Wholesale Goods"
      }
    ],
    "sg:phone": "+1 330 875 1661",
    "sg:postcode": "44601",
    "sg:province": "OH",
    "sg:tags": [
      "industrial",
      "mfg"
    ],
    "wof:name": "Travis Manufacturing Corp",
    "wof:placetype": "venue"
  },
  "geometry": {"coordinates":[-81.172399,40.850882],"type":"Point"}
}
