{
  "type": "Feature",
  "properties": {
    "iso:country":"US",
    "sg:address":"13231 Salem Church St NE",
    "sg:city":"Alliance",
    "sg:classifiers":[
        {
            "category":"Manufacturing",
            "subcategory":"Tools & Machinery",
            "type":"Manufacturing & Wholesale Goods"
        }
    ],
    "sg:phone":"+1 330 875 1661",
    "sg:postcode":"44601",
    "sg:province":"OH",
    "sg:tags":[
        "industrial",
        "mfg"
    ],
    "wof:name":"Travis Manufacturing Corp",
    "wof:placetype":"venue"
},
  "geometry": {"coordinates":[-81.172399,40.850882],"type":"Point"}
}