{
  "type": "Feature",
  "properties": {
    "iso:country":"US",
    "sg:address":"550 Mirabeau St",
    "sg:city":"Greenfield",
    "sg:classifiers":[
        {
            "category":"Health Services",
            "subcategory":"Podiatrist",
            "type":"Services"
        }
    ],
    "sg:phone":"+1 937 981 9261",
    "sg:postcode":"45123",
    "sg:province":"OH",
    "wof:name":"Bryan D Giesy DPM",
    "wof:placetype":"venue"
},
  "geometry": {"coordinates":[-83.387474,39.349356],"type":"Point"}
}