{
  "type": "Feature",
  "properties": {
    "addr:full": "183 Rue Marseille Dayton OH 45429",
    "addr:housenumber": "183",
    "addr:postcode": "45429",
    "addr:street": "Rue Marseille",
    "iso:country": "US",
    "sg:address": "183 Rue Marseille",
    "sg:city": "Dayton",
    "sg:classifiers": [
      {
        "category": "Shopping",
        "type": "Retail Goods"
      }
    ],
    "sg:phone": "+1 937 296 1000",
    "sg:postcode": "45429",
    "sg:province": "OH",
    "sg:tags": [
      "cosmetic",
      "perfume"
    ],
    "wof:name": "Mary Kay Independent",
    "wof:placetype": "venue"
  },
  "geometry": {"coordinates":[-84.170157,39.682889],"type":"Point"}
}
