{
  "type": "Feature",
  "properties": {
    "addr:full": "2316 Maxine Ave NE Canton OH 44705",
    "addr:housenumber": "2316",
    "addr:postcode": "44705",
    "addr:street": "Maxine Ave Ne",
    "iso:country": "US",
    "sg:address": "2316 Maxine Ave NE",
    "sg:city": "Canton",
    "sg:classifiers": [
      {
        "category": "Building \u0026 Trades",
        "subcategory": "Construction",
        "type": "Services"
      }
    ],
    "sg:phone": "+1 330 455 8248",
    "sg:postcode": "44705",
    "sg:province": "OH",
    "sg:tags": [
      "house"
    ],
    "wof:name": "Jay Evans Construction",
    "wof:placetype": "venue"
  },
  "geometry": {"coordinates":[-81.333685,40.821648],"type":"Point"}
}
