{
  "type": "Feature",
  "properties": {
    "iso:country":"US",
    "sg:address":"6891 Ross Rd",
    "sg:city":"Bloomville",
    "sg:classifiers":[
        {
            "category":"Retail",
            "subcategory":"Repair Shop",
            "type":"Services"
        }
    ],
    "sg:phone":"+1 419 284 0070",
    "sg:postcode":"44818",
    "sg:province":"OH",
    "sg:tags":[
        "taxidermist"
    ],
    "wof:name":"Bloomfield's Taxidermy",
    "wof:placetype":"venue"
},
  "geometry": {"coordinates":[-82.977849,40.95033],"type":"Point"}
}