{
  "type": "Feature",
  "properties": {
    "addr:full":"202 E Summit St Kent OH 44240",
    "addr:housenumber":"202",
    "addr:postcode":"44240",
    "addr:street":"E Summit St",
    "iso:country":"US",
    "sg:address":"202 E Summit St",
    "sg:city":"Kent",
    "sg:classifiers":[
        {
            "category":"Real Estate",
            "subcategory":"Real Estate Operator",
            "type":"Services"
        }
    ],
    "sg:phone":"+1 330 678 3020",
    "sg:postcode":"44240",
    "sg:province":"OH",
    "sg:tags":[
        "building",
        "apartment"
    ],
    "wof:name":"Housing Placement Center",
    "wof:placetype":"venue"
},
  "geometry": {"coordinates":[-81.355245,41.15001],"type":"Point"}
}