{
  "type": "Feature",
  "properties": {
    "addr:full": "15879 Co Rd F Wauseon OH 43567",
    "addr:housenumber": "15879",
    "addr:postcode": "43567",
    "addr:street": "Co Rd",
    "iso:country": "US",
    "sg:address": "15879 Co Rd F",
    "sg:city": "Wauseon",
    "sg:classifiers": [
      {
        "category": "Organizations",
        "subcategory": "Religious Organization",
        "type": "Services"
      }
    ],
    "sg:phone": "+1 419 335 1686",
    "sg:postcode": "43567",
    "sg:province": "OH",
    "sg:tags": [
      "church"
    ],
    "wof:name": "Faith Baptist Church",
    "wof:placetype": "venue"
  },
  "geometry": {"coordinates":[-84.170413,41.558336],"type":"Point"}
}
