{
  "type": "Feature",
  "properties": {
    "addr:full": "5280 Poling Rd Elida OH 45807",
    "addr:housenumber": "5280",
    "addr:postcode": "45807",
    "addr:street": "Poling Rd",
    "iso:country": "US",
    "sg:address": "5280 Poling Rd",
    "sg:city": "Elida",
    "sg:classifiers": [
      {
        "category": "Retail",
        "subcategory": "Repair Shop",
        "type": "Services"
      }
    ],
    "sg:phone": "+1 419 339 3246",
    "sg:postcode": "45807",
    "sg:province": "OH",
    "sg:tags": [
      "repairing",
      "lawn",
      "mower"
    ],
    "wof:name": "Hanes Enterprises",
    "wof:placetype": "venue"
  },
  "geometry": {"coordinates":[-84.195505,40.755071],"type":"Point"}
}
