{
  "type": "Feature",
  "properties": {
    "addr:full":"5830 Western Aly Milford OH 45150",
    "addr:housenumber":"5830",
    "addr:postcode":"45150",
    "addr:street":"Western Aly",
    "iso:country":"US",
    "sg:address":"5830 Western Aly",
    "sg:city":"Milford",
    "sg:classifiers":[
        {
            "category":"Education",
            "subcategory":"Dance Studio",
            "type":"Public Place"
        }
    ],
    "sg:phone":"+1 513 576 1400",
    "sg:postcode":"45150",
    "sg:province":"OH",
    "sg:tags":[
        "instruction",
        "dancing"
    ],
    "wof:name":"Cheer Etc",
    "wof:placetype":"venue"
},
  "geometry": {"coordinates":[-84.247348,39.193698],"type":"Point"}
}