{
  "type": "Feature",
  "properties": {
    "addr:full": "105 Cross St Palestine OH 45352",
    "addr:housenumber": "105",
    "addr:postcode": "45352",
    "addr:street": "Cross St",
    "iso:country": "US",
    "sg:address": "105 Cross St",
    "sg:city": "Palestine",
    "sg:classifiers": [
      {
        "category": "Government",
        "subcategory": "Post Office",
        "type": "Public Place"
      }
    ],
    "sg:phone": "+1 937 547 1188",
    "sg:postcode": "45352",
    "sg:province": "OH",
    "wof:name": "US Post Office",
    "wof:placetype": "venue"
  },
  "geometry": {"coordinates":[-84.744175,40.049775],"type":"Point"}
}
