{
  "type": "Feature",
  "properties": {
    "addr:full": "846 N Market St Lisbon OH 44432",
    "addr:housenumber": "846",
    "addr:postcode": "44432",
    "addr:street": "N Market St",
    "iso:country": "US",
    "sg:address": "846 N Market St",
    "sg:city": "Lisbon",
    "sg:classifiers": [
      {
        "category": "Personal",
        "subcategory": "Beauty Salon",
        "type": "Services"
      }
    ],
    "sg:phone": "+1 330 424 7389",
    "sg:postcode": "44432",
    "sg:province": "OH",
    "wof:name": "Dino's Beauty Salon",
    "wof:placetype": "venue"
  },
  "geometry": {"coordinates":[-80.770723,40.780935],"type":"Point"}
}
