{
  "type": "Feature",
  "properties": {
    "addr:full":"11355 Chester Rd Cincinnati OH 45246",
    "addr:housenumber":"11355",
    "addr:postcode":"45246",
    "addr:street":"Chester Rd",
    "iso:country":"US",
    "sg:address":"11355 Chester Rd",
    "sg:city":"Cincinnati",
    "sg:classifiers":[
        {
            "category":"Professional",
            "subcategory":"Business Services",
            "type":"Services"
        },
        {
            "category":"Restaurant",
            "type":"Food & Drink"
        }
    ],
    "sg:phone":"+1 513 771 7744",
    "sg:postcode":"45246",
    "sg:province":"OH",
    "sg:tags":[
        "operation",
        "banquet",
        "rooms"
    ],
    "sg:website":"www.sharonvilleconventioncenter.com",
    "wof:name":"Sharonville Convention Center",
    "wof:placetype":"venue"
},
  "geometry": {"coordinates":[-84.444524,39.271395],"type":"Point"}
}