{
  "type": "Feature",
  "properties": {
    "iso:country":"US",
    "sg:address":"927 E Columbus St",
    "sg:city":"Kenton",
    "sg:classifiers":[
        {
            "category":"Building & Trades",
            "subcategory":"Landscaping Services",
            "type":"Services"
        }
    ],
    "sg:phone":"+1 419 675 2718",
    "sg:postcode":"43326",
    "sg:province":"OH",
    "sg:tags":[
        "mi",
        "supply"
    ],
    "wof:name":"New Leaf Landscape Garden Ctr",
    "wof:placetype":"venue"
},
  "geometry": {"coordinates":[-83.59154599999999,40.651843],"type":"Point"}
}