{
  "type": "Feature",
  "properties": {
    "iso:country":"US",
    "sg:address":"3037 E Derbyshire Rd",
    "sg:city":"Cleveland",
    "sg:classifiers":[
        {
            "category":"Professional",
            "subcategory":"Research",
            "type":"Services"
        }
    ],
    "sg:phone":"+1 216 321 3107",
    "sg:postcode":"44118",
    "sg:province":"OH",
    "sg:tags":[
        "development",
        "marketing",
        "product"
    ],
    "wof:name":"Art 4 Art Inc",
    "wof:placetype":"venue"
},
  "geometry": {"coordinates":[-81.574697,41.502393],"type":"Point"}
}