{
  "type": "Feature",
  "properties": {
    "addr:full": "3037 E Derbyshire Rd Cleveland OH 44118",
    "addr:housenumber": "3037",
    "addr:postcode": "44118",
    "addr:street": "E Derbyshire Rd",
    "iso:country": "US",
    "sg:address": "3037 E Derbyshire Rd",
    "sg:city": "Cleveland",
    "sg:classifiers": [
      {
        "category": "Professional",
        "subcategory": "Research",
        "type": "Services"
      }
    ],
    "sg:phone": "+1 216 321 3107",
    "sg:postcode": "44118",
    "sg:province": "OH",
    "sg:tags": [
      "development",
      "marketing",
      "product"
    ],
    "wof:name": "Art 4 Art Inc",
    "wof:placetype": "venue"
  },
  "geometry": {"coordinates":[-81.574697,41.502393],"type":"Point"}
}
