{
  "type": "Feature",
  "properties": {
    "addr:full": "2639 US Hwy 20 Swanton OH 43558",
    "addr:housenumber": "2639",
    "addr:postcode": "43558",
    "addr:street": "Us Hwy 20",
    "iso:country": "US",
    "sg:address": "2639 US Hwy 20",
    "sg:city": "Swanton",
    "sg:classifiers": [
      {
        "category": "Education",
        "subcategory": "School",
        "type": "Public Place"
      }
    ],
    "sg:phone": "+1 419 644 3971",
    "sg:postcode": "43558",
    "sg:province": "OH",
    "sg:website": "www.holytrinityschool-swanton.org",
    "wof:name": "Holy Trinity School",
    "wof:placetype": "venue"
  },
  "geometry": {"coordinates":[-83.910485,41.671984],"type":"Point"}
}
