{
  "type": "Feature",
  "properties": {
    "iso:country":"US",
    "sg:address":"2639 US Hwy 20",
    "sg:city":"Swanton",
    "sg:classifiers":[
        {
            "category":"Education",
            "subcategory":"School",
            "type":"Public Place"
        }
    ],
    "sg:phone":"+1 419 644 3971",
    "sg:postcode":"43558",
    "sg:province":"OH",
    "sg:website":"www.holytrinityschool-swanton.org",
    "wof:name":"Holy Trinity School",
    "wof:placetype":"venue"
},
  "geometry": {"coordinates":[-83.91048499999999,41.671984],"type":"Point"}
}