{
  "type": "Feature",
  "properties": {
    "addr:full": "1525 Massillon Rd Akron OH 44306",
    "addr:housenumber": "1525",
    "addr:postcode": "44306",
    "addr:street": "Massillon Rd",
    "iso:country": "US",
    "sg:address": "1525 Massillon Rd",
    "sg:city": "Akron",
    "sg:classifiers": [
      {
        "category": "Building \u0026 Trades",
        "subcategory": "Construction",
        "type": "Services"
      }
    ],
    "sg:phone": "+1 330 922 9910",
    "sg:postcode": "44306",
    "sg:province": "OH",
    "sg:tags": [
      "concrete",
      "contractor"
    ],
    "wof:name": "Zrioka Concrete Construction",
    "wof:placetype": "venue"
  },
  "geometry": {"coordinates":[-81.463366,41.019621],"type":"Point"}
}
