{
  "type": "Feature",
  "properties": {
    "addr:full": "1152 Co Rd 46 Toronto OH 43964",
    "addr:housenumber": "1152;46",
    "addr:postcode": "43964",
    "addr:street": "Co Rd",
    "iso:country": "US",
    "sg:address": "1152 Co Rd 46",
    "sg:city": "Toronto",
    "sg:classifiers": [
      {
        "category": "Building \u0026 Trades",
        "subcategory": "Construction",
        "type": "Services"
      }
    ],
    "sg:phone": "+1 740 544 5825",
    "sg:postcode": "43964",
    "sg:province": "OH",
    "sg:tags": [
      "house"
    ],
    "wof:name": "Terry A Sine Jr",
    "wof:placetype": "venue"
  },
  "geometry": {"coordinates":[-80.639693,40.459529],"type":"Point"}
}
