{
  "type": "Feature",
  "properties": {
    "iso:country":"US",
    "sg:address":"1152 Co Rd 46",
    "sg:city":"Toronto",
    "sg:classifiers":[
        {
            "category":"Building & Trades",
            "subcategory":"Construction",
            "type":"Services"
        }
    ],
    "sg:phone":"+1 740 544 5825",
    "sg:postcode":"43964",
    "sg:province":"OH",
    "sg:tags":[
        "house"
    ],
    "wof:name":"Terry A Sine Jr",
    "wof:placetype":"venue"
},
  "geometry": {"coordinates":[-80.63969299999999,40.459529],"type":"Point"}
}