{
  "type": "Feature",
  "properties": {
    "iso:country":"US",
    "sg:address":"525 W Main St",
    "sg:city":"Plain City",
    "sg:classifiers":[
        {
            "category":"Retail",
            "subcategory":"Auto Rental",
            "type":"Services"
        }
    ],
    "sg:phone":"+1 614 733 0782",
    "sg:postcode":"43064",
    "sg:province":"OH",
    "sg:tags":[
        "renting",
        "truck",
        "leasing"
    ],
    "wof:name":"U-Haul Co",
    "wof:placetype":"venue"
},
  "geometry": {"coordinates":[-83.275086,40.109802],"type":"Point"}
}