{
  "type": "Feature",
  "properties": {
    "addr:full": "687 Lafayette Rd Medina OH 44256",
    "addr:housenumber": "687",
    "addr:postcode": "44256",
    "addr:street": "Rd",
    "iso:country": "US",
    "sg:address": "687 Lafayette Rd",
    "sg:city": "Medina",
    "sg:classifiers": [
      {
        "category": "Manufacturing",
        "subcategory": "Tools \u0026 Machinery",
        "type": "Manufacturing \u0026 Wholesale Goods"
      }
    ],
    "sg:phone": "+1 330 725 5395",
    "sg:postcode": "44256",
    "sg:province": "OH",
    "sg:tags": [
      "mill",
      "paper"
    ],
    "wof:name": "Printing \u0026 Die Cutting Specs",
    "wof:placetype": "venue"
  },
  "geometry": {"coordinates":[-81.877518,41.12961],"type":"Point"}
}
