{
  "type": "Feature",
  "properties": {
    "iso:country":"US",
    "sg:address":"687 Lafayette Rd",
    "sg:city":"Medina",
    "sg:classifiers":[
        {
            "category":"Manufacturing",
            "subcategory":"Tools & Machinery",
            "type":"Manufacturing & Wholesale Goods"
        }
    ],
    "sg:phone":"+1 330 725 5395",
    "sg:postcode":"44256",
    "sg:province":"OH",
    "sg:tags":[
        "mill",
        "paper"
    ],
    "wof:name":"Printing & Die Cutting Specs",
    "wof:placetype":"venue"
},
  "geometry": {"coordinates":[-81.87751799999999,41.12961],"type":"Point"}
}