{
  "type": "Feature",
  "properties": {
    "addr:full":"1869 E Aurora Rd Twinsburg OH 44087",
    "addr:housenumber":"1869",
    "addr:postcode":"44087",
    "addr:street":"E Aurora Rd",
    "iso:country":"US",
    "sg:address":"1869 E Aurora Rd",
    "sg:city":"Twinsburg",
    "sg:classifiers":[
        {
            "category":"Professional",
            "subcategory":"Business Services",
            "type":"Services"
        }
    ],
    "sg:phone":"+1 330 487 1130",
    "sg:postcode":"44087",
    "sg:province":"OH",
    "sg:tags":[
        "broker"
    ],
    "wof:name":"Active Business Brokers",
    "wof:placetype":"venue"
},
  "geometry": {"coordinates":[-81.46316899999999,41.311415],"type":"Point"}
}