{
  "type": "Feature",
  "properties": {
    "iso:country":"US",
    "sg:address":"5775 Summit View Ct",
    "sg:city":"Cincinnati",
    "sg:classifiers":[
        {
            "category":"Manufacturing",
            "subcategory":"Paper Products",
            "type":"Manufacturing & Wholesale Goods"
        }
    ],
    "sg:phone":"+1 513 922 2960",
    "sg:postcode":"45247",
    "sg:province":"OH",
    "sg:tags":[
        "bag"
    ],
    "wof:name":"Bag Productions",
    "wof:placetype":"venue"
},
  "geometry": {"coordinates":[-84.670245,39.200287],"type":"Point"}
}