{
  "type": "Feature",
  "properties": {
    "addr:full":"6562 Mercer Rd Mendon OH 45862",
    "addr:housenumber":"6562",
    "addr:postcode":"45862",
    "addr:street":"Mercer Rd",
    "iso:country":"US",
    "sg:address":"6562 Mercer Rd",
    "sg:city":"Mendon",
    "sg:phone":"+1 419 795 3261",
    "sg:postcode":"45862",
    "sg:province":"OH",
    "sg:tags":[
        "farm",
        "wheat",
        "soybean"
    ],
    "wof:name":"Robert Christian",
    "wof:placetype":"venue"
},
  "geometry": {"coordinates":[-84.54746799999999,40.655066],"type":"Point"}
}