{
  "type": "Feature",
  "properties": {
    "addr:full": "4 High St Mechanicsburg OH 43044",
    "addr:housenumber": "4",
    "addr:postcode": "43044",
    "addr:street": "High St",
    "iso:country": "US",
    "sg:address": "4 High St",
    "sg:city": "Mechanicsburg",
    "sg:classifiers": [
      {
        "category": "Real Estate",
        "subcategory": "Real Estate Agent",
        "type": "Services"
      }
    ],
    "sg:phone": "+1 937 834 4444",
    "sg:postcode": "43044",
    "sg:province": "OH",
    "wof:name": "American Realty Trust",
    "wof:placetype": "venue"
  },
  "geometry": {"coordinates":[-83.559302,40.075065],"type":"Point"}
}
