{
  "type": "Feature",
  "properties": {
    "addr:full": "2815 Frick Dr Zanesville OH 43701",
    "addr:postcode": "2815;43701",
    "addr:street": "Frick Dr",
    "iso:country": "US",
    "sg:address": "2815 Frick Dr",
    "sg:city": "Zanesville",
    "sg:classifiers": [
      {
        "category": "Real Estate",
        "subcategory": "Real Estate Agent",
        "type": "Services"
      }
    ],
    "sg:phone": "+1 740 453 3783",
    "sg:postcode": "43701",
    "sg:province": "OH",
    "wof:name": "Edwards Rentals",
    "wof:placetype": "venue"
  },
  "geometry": {"coordinates":[-81.982944,39.890962],"type":"Point"}
}
