{
  "type": "Feature",
  "properties": {
    "addr:full": "308 Barrington Ridge Rd Painesville OH 44077",
    "addr:housenumber": "308",
    "addr:postcode": "44077",
    "addr:street": "Barrington Ridge Rd",
    "iso:country": "US",
    "sg:address": "308 Barrington Ridge Rd",
    "sg:city": "Painesville",
    "sg:classifiers": [
      {
        "category": "Professional",
        "subcategory": "Lawyer \u0026 Legal Services",
        "type": "Services"
      }
    ],
    "sg:phone": "+1 330 434 1234",
    "sg:postcode": "44077",
    "sg:province": "OH",
    "wof:name": "Biales C Biales Co",
    "wof:placetype": "venue"
  },
  "geometry": {"coordinates":[-81.276757,41.687647],"type":"Point"}
}
