{
  "type": "Feature",
  "properties": {
    "iso:country":"US",
    "sg:address":"12639 Irvington Ave",
    "sg:city":"Cleveland",
    "sg:classifiers":[
        {
            "category":"Freight",
            "type":"Transportation"
        }
    ],
    "sg:phone":"+1 216 374 1923",
    "sg:postcode":"44108",
    "sg:province":"OH",
    "sg:tags":[
        "development",
        "management",
        "business"
    ],
    "wof:name":"Sherkesk Incorporated",
    "wof:placetype":"venue"
},
  "geometry": {"coordinates":[-81.5946,41.533384],"type":"Point"}
}