{
  "type": "Feature",
  "properties": {
    "addr:full": "6340 River Rd Cincinnati OH 45233",
    "addr:housenumber": "6340",
    "addr:postcode": "45233",
    "addr:street": "River Rd",
    "iso:country": "US",
    "sg:address": "6340 River Rd",
    "sg:city": "Cincinnati",
    "sg:classifiers": [
      {
        "category": "Autos \u0026 Motor Vehicles",
        "subcategory": "Fuel \u0026 Gas Station",
        "type": "Retail Goods"
      }
    ],
    "sg:phone": "+1 513 941 0208",
    "sg:postcode": "45233",
    "sg:province": "OH",
    "sg:tags": [
      "grocery",
      "oil"
    ],
    "wof:name": "Saylor Park Express Inc",
    "wof:placetype": "venue"
  },
  "geometry": {"coordinates":[-84.687897,39.106499],"type":"Point"}
}
