{
  "type": "Feature",
  "properties": {
    "iso:country":"US",
    "sg:address":"6340 River Rd",
    "sg:city":"Cincinnati",
    "sg:classifiers":[
        {
            "category":"Autos & Motor Vehicles",
            "subcategory":"Fuel & Gas Station",
            "type":"Retail Goods"
        }
    ],
    "sg:phone":"+1 513 941 0208",
    "sg:postcode":"45233",
    "sg:province":"OH",
    "sg:tags":[
        "grocery",
        "oil"
    ],
    "wof:name":"Saylor Park Express Inc",
    "wof:placetype":"venue"
},
  "geometry": {"coordinates":[-84.68789700000001,39.106499],"type":"Point"}
}