{
  "type": "Feature",
  "properties": {
    "addr:full":"3575 Maple Ave Zanesville OH 43701",
    "addr:housenumber":"3575",
    "addr:postcode":"43701",
    "addr:street":"Maple Ave",
    "iso:country":"US",
    "sg:address":"3575 Maple Ave",
    "sg:city":"Zanesville",
    "sg:classifiers":[
        {
            "category":"Shopping",
            "subcategory":"Crafts & Fabrics",
            "type":"Retail Goods"
        }
    ],
    "sg:phone":"+1 740 452 9034",
    "sg:postcode":"43701",
    "sg:province":"OH",
    "sg:tags":[
        "sewing"
    ],
    "wof:name":"Jo-Ann Fabrics & Crafts",
    "wof:placetype":"venue"
},
  "geometry": {"coordinates":[-82.02225199999999,39.986451],"type":"Point"}
}