{
  "type": "Feature",
  "properties": {
    "addr:full":"438 S Yale Ave Columbus OH 43223",
    "addr:housenumber":"438",
    "addr:postcode":"43223",
    "addr:street":"S Yale Ave",
    "iso:country":"US",
    "sg:address":"438 S Yale Ave",
    "sg:city":"Columbus",
    "sg:classifiers":[
        {
            "category":"Home & Garden",
            "subcategory":"Household Appliances",
            "type":"Retail Goods"
        }
    ],
    "sg:phone":"+1 614 461 1087",
    "sg:postcode":"43223",
    "sg:province":"OH",
    "sg:tags":[
        "refrigerator",
        "freezer"
    ],
    "wof:name":"A-Alert Repair Svc",
    "wof:placetype":"venue"
},
  "geometry": {"coordinates":[-83.029623,39.949472],"type":"Point"}
}