{
  "type": "Feature",
  "properties": {
    "addr:full": "9280 Fessler-Buxton Rd Piqua OH 45356",
    "addr:postcode": "9280;45356",
    "addr:street": "Fessler-Buxton Rd",
    "iso:country": "US",
    "sg:address": "9280 Fessler-Buxton Rd",
    "sg:city": "Piqua",
    "sg:classifiers": [
      {
        "category": "Professional",
        "type": "Services"
      }
    ],
    "sg:phone": "+1 937 778 8754",
    "sg:postcode": "45356",
    "sg:province": "OH",
    "wof:name": "Randy Schwable",
    "wof:placetype": "venue"
  },
  "geometry": {"coordinates":[-84.258809,40.211001],"type":"Point"}
}
