{
  "type": "Feature",
  "properties": {
    "addr:full":"329 Stoneridge Ln Columbus OH 43230",
    "addr:housenumber":"329",
    "addr:postcode":"43230",
    "addr:street":"Stoneridge Ln",
    "iso:country":"US",
    "sg:address":"329 Stoneridge Ln",
    "sg:city":"Columbus",
    "sg:classifiers":[
        {
            "category":"Shopping",
            "type":"Retail Goods"
        }
    ],
    "sg:phone":"+1 614 337 1751",
    "sg:postcode":"43230",
    "sg:province":"OH",
    "sg:tags":[
        "picture",
        "frame",
        "merchandise"
    ],
    "wof:name":"Framemakers",
    "wof:placetype":"venue"
},
  "geometry": {"coordinates":[-82.86407199999999,40.051832],"type":"Point"}
}