{
  "type": "Feature",
  "properties": {
    "addr:full":"6961 Morris Rd Hamilton OH 45011",
    "addr:housenumber":"6961",
    "addr:postcode":"45011",
    "addr:street":"Morris Rd",
    "iso:country":"US",
    "sg:address":"6961 Morris Rd",
    "sg:city":"Hamilton",
    "sg:classifiers":[
        {
            "category":"Building & Trades",
            "subcategory":"Plumbing",
            "type":"Services"
        }
    ],
    "sg:phone":"+1 513 863 3575",
    "sg:postcode":"45011",
    "sg:province":"OH",
    "sg:tags":[
        "conditioning",
        "air",
        "system",
        "contractor"
    ],
    "wof:name":"Cornett's Heating & Air Cond",
    "wof:placetype":"venue"
},
  "geometry": {"coordinates":[-84.496638,39.384582],"type":"Point"}
}