{
  "type": "Feature",
  "properties": {
    "addr:full":"8990 Duke Blvd Mason OH 45040",
    "addr:housenumber":"8990",
    "addr:postcode":"45040",
    "addr:street":"Duke Blvd",
    "iso:country":"US",
    "sg:address":"8990 Duke Blvd",
    "sg:city":"Mason",
    "sg:classifiers":[
        {
            "category":"Shopping",
            "subcategory":"Catalog Store",
            "type":"Retail Goods"
        },
        {
            "category":"Professional",
            "subcategory":"Management & Consulting",
            "type":"Services"
        },
        {
            "category":"Insurance",
            "subcategory":"Insurance Agent",
            "type":"Services"
        }
    ],
    "sg:phone":"+1 513 336 5982",
    "sg:postcode":"45040",
    "sg:province":"OH",
    "sg:tags":[
        "pharmaceutical",
        "program",
        "mail",
        "order",
        "marketing"
    ],
    "sg:website":"www.anthem.com",
    "wof:name":"Anthem Prescription MGT LLC",
    "wof:placetype":"venue"
},
  "geometry": {"coordinates":[-84.303104,39.307535],"type":"Point"}
}