{
  "type": "Feature",
  "properties": {
    "addr:full": "517 Wilson Ave Coshocton OH 43812",
    "addr:housenumber": "517",
    "addr:postcode": "43812",
    "addr:street": "Wilson Ave",
    "iso:country": "US",
    "sg:address": "517 Wilson Ave",
    "sg:city": "Coshocton",
    "sg:classifiers": [
      {
        "category": "Real Estate",
        "subcategory": "Real Estate Agent",
        "type": "Services"
      }
    ],
    "sg:phone": "+1 740 622 7687",
    "sg:postcode": "43812",
    "sg:province": "OH",
    "wof:name": "Terry Mizer",
    "wof:placetype": "venue"
  },
  "geometry": {"coordinates":[-81.853363,40.267866],"type":"Point"}
}
