{
  "type": "Feature",
  "properties": {
    "iso:country":"US",
    "sg:address":"107 Dogwood Dr",
    "sg:city":"Loveland",
    "sg:classifiers":[
        {
            "category":"Building & Trades",
            "subcategory":"Landscaping Services",
            "type":"Services"
        }
    ],
    "sg:phone":"+1 513 583 9366",
    "sg:postcode":"45140",
    "sg:province":"OH",
    "sg:tags":[
        "landscape",
        "contractor"
    ],
    "wof:name":"Flint General Maintenance Inc",
    "wof:placetype":"venue"
},
  "geometry": {"coordinates":[-84.293898,39.25804],"type":"Point"}
}