{
  "type": "Feature",
  "properties": {
    "addr:full":"125 S Walnut St Yellow Springs OH 45387",
    "addr:housenumber":"125",
    "addr:postcode":"45387",
    "addr:street":"S Walnut St",
    "iso:country":"US",
    "sg:address":"125 S Walnut St",
    "sg:city":"Yellow Springs",
    "sg:classifiers":[
        {
            "category":"Manufacturing",
            "subcategory":"Tools & Machinery",
            "type":"Manufacturing & Wholesale Goods"
        }
    ],
    "sg:phone":"+1 937 767 4852",
    "sg:postcode":"45387",
    "sg:province":"OH",
    "sg:tags":[
        "analytical",
        "instrument",
        "mfg"
    ],
    "wof:name":"Laser Linc Inc",
    "wof:placetype":"venue"
},
  "geometry": {"coordinates":[-83.889899,39.80667],"type":"Point"}
}