{
  "type": "Feature",
  "properties": {
    "addr:full":"2180 Alum Creek Dr Columbus OH 43207",
    "addr:housenumber":"2180",
    "addr:postcode":"43207",
    "addr:street":"Alum Creek Dr",
    "iso:country":"US",
    "sg:address":"2180 Alum Creek Dr",
    "sg:city":"Columbus",
    "sg:classifiers":[
        {
            "category":"Freight",
            "type":"Transportation"
        }
    ],
    "sg:phone":"+1 614 449 0020",
    "sg:postcode":"43207",
    "sg:province":"OH",
    "sg:tags":[
        "regional",
        "trucking"
    ],
    "wof:name":"Worthy Cartage Company Inc",
    "wof:placetype":"venue"
},
  "geometry": {"coordinates":[-82.931551,39.920435],"type":"Point"}
}