{
  "type": "Feature",
  "properties": {
    "iso:country":"US",
    "sg:address":"4650 Lake Forest Dr",
    "sg:city":"Cincinnati",
    "sg:classifiers":[
        {
            "category":"Professional",
            "subcategory":"Business Services",
            "type":"Services"
        }
    ],
    "sg:phone":"+1 513 733 0338",
    "sg:postcode":"45242",
    "sg:province":"OH",
    "wof:name":"Medcomm Fulfillment Inc",
    "wof:placetype":"venue"
},
  "geometry": {"coordinates":[-84.378498,39.254818],"type":"Point"}
}