{
  "type": "Feature",
  "properties": {
    "iso:country":"US",
    "sg:address":"3108 N Dixie Dr",
    "sg:city":"Dayton",
    "sg:classifiers":[
        {
            "category":"Bars & Pubs",
            "type":"Food & Drink"
        }
    ],
    "sg:phone":"+1 937 276 9120",
    "sg:postcode":"45414",
    "sg:province":"OH",
    "sg:tags":[
        "drinking"
    ],
    "wof:name":"Dixie Lounge",
    "wof:placetype":"venue"
},
  "geometry": {"coordinates":[-84.190487,39.791544],"type":"Point"}
}