{
  "type": "Feature",
  "properties": {
    "addr:full": "3108 N Dixie Dr Dayton OH 45414",
    "addr:housenumber": "3108",
    "addr:postcode": "45414",
    "addr:street": "N Dixie Dr",
    "iso:country": "US",
    "sg:address": "3108 N Dixie Dr",
    "sg:city": "Dayton",
    "sg:classifiers": [
      {
        "category": "Bars \u0026 Pubs",
        "type": "Food \u0026 Drink"
      }
    ],
    "sg:phone": "+1 937 276 9120",
    "sg:postcode": "45414",
    "sg:province": "OH",
    "sg:tags": [
      "drinking"
    ],
    "wof:name": "Dixie Lounge",
    "wof:placetype": "venue"
  },
  "geometry": {"coordinates":[-84.190487,39.791544],"type":"Point"}
}
