{
  "type": "Feature",
  "properties": {
    "addr:full": "6875 W Chester Rd West Chester OH 45069",
    "addr:housenumber": "6875",
    "addr:postcode": "45069",
    "addr:street": "W Chester Rd",
    "iso:country": "US",
    "sg:address": "6875 W Chester Rd",
    "sg:city": "West Chester",
    "sg:classifiers": [
      {
        "category": "Education",
        "subcategory": "Special Training",
        "type": "Public Place"
      }
    ],
    "sg:phone": "+1 513 779 1103",
    "sg:postcode": "45069",
    "sg:province": "OH",
    "sg:tags": [
      "educational"
    ],
    "wof:name": "Safe Day Education Of Ohio",
    "wof:placetype": "venue"
  },
  "geometry": {"coordinates":[-84.399407,39.324486],"type":"Point"}
}
