{
  "type": "Feature",
  "properties": {
    "addr:full":"6560 N High St Columbus OH 43085",
    "addr:housenumber":"6560",
    "addr:postcode":"43085",
    "addr:street":"N High St",
    "iso:country":"US",
    "sg:address":"6560 N High St",
    "sg:city":"Columbus",
    "sg:classifiers":[
        {
            "category":"Building & Trades",
            "subcategory":"Construction",
            "type":"Services"
        }
    ],
    "sg:phone":"+1 614 428 8888",
    "sg:postcode":"43085",
    "sg:province":"OH",
    "sg:tags":[
        "siding",
        "contractor"
    ],
    "wof:name":"Precision Window & Siding Inc",
    "wof:placetype":"venue"
},
  "geometry": {"coordinates":[-83.017472,40.097067],"type":"Point"}
}