{
  "type": "Feature",
  "properties": {
    "iso:country":"US",
    "sg:address":"26 N Main St",
    "sg:city":"Pleasant Hill",
    "sg:classifiers":[
        {
            "category":"Personal",
            "subcategory":"Beauty Salon",
            "type":"Services"
        }
    ],
    "sg:phone":"+1 937 676 8100",
    "sg:postcode":"45359",
    "sg:province":"OH",
    "wof:name":"Michelangelo Hair Designs",
    "wof:placetype":"venue"
},
  "geometry": {"coordinates":[-84.344277,40.052099],"type":"Point"}
}