{
  "type": "Feature",
  "properties": {
    "addr:full": "400 W Nationwide Blvd Columbus OH 43215",
    "addr:housenumber": "400",
    "addr:postcode": "43215",
    "addr:street": "W Nationwide Blvd",
    "iso:country": "US",
    "sg:address": "400 W Nationwide Blvd",
    "sg:city": "Columbus",
    "sg:classifiers": [
      {
        "category": "Restaurant",
        "type": "Food \u0026 Drink"
      }
    ],
    "sg:phone": "+1 614 280 1919",
    "sg:postcode": "43215",
    "sg:province": "OH",
    "wof:name": "New World Restaurants Inc",
    "wof:placetype": "venue"
  },
  "geometry": {"coordinates":[-83.013203,39.96777],"type":"Point"}
}
