{
  "type": "Feature",
  "properties": {
    "iso:country":"US",
    "sg:address":"1321 Dueber Ave SW",
    "sg:city":"Canton",
    "sg:classifiers":[
        {
            "category":"Retail",
            "subcategory":"Auto Repair",
            "type":"Services"
        }
    ],
    "sg:phone":"+1 330 456 3080",
    "sg:postcode":"44706",
    "sg:province":"OH",
    "sg:tags":[
        "engine"
    ],
    "wof:name":"Perry Diesel Svc",
    "wof:placetype":"venue"
},
  "geometry": {"coordinates":[-81.394578,40.787458],"type":"Point"}
}