{
  "type": "Feature",
  "properties": {
    "addr:full": "4040 E National Rd Springfield OH 45505",
    "addr:housenumber": "4040",
    "addr:postcode": "45505",
    "addr:street": "E National Rd",
    "iso:country": "US",
    "sg:address": "4040 E National Rd",
    "sg:city": "Springfield",
    "sg:classifiers": [
      {
        "category": "Travel",
        "subcategory": "Hotels \u0026 Motels",
        "type": "Entertainment"
      }
    ],
    "sg:phone": "+1 937 325 6991",
    "sg:postcode": "45505",
    "sg:province": "OH",
    "wof:name": "Springfield Motel",
    "wof:placetype": "venue"
  },
  "geometry": {"coordinates":[-83.732434,39.923389],"type":"Point"}
}
