{
  "type": "Feature",
  "properties": {
    "addr:full":"1177 Marquette St Cleveland OH 44114",
    "addr:housenumber":"1177",
    "addr:postcode":"44114",
    "addr:street":"Marquette St",
    "iso:country":"US",
    "sg:address":"1177 Marquette St",
    "sg:city":"Cleveland",
    "sg:classifiers":[
        {
            "category":"Manufacturing",
            "subcategory":"Metals",
            "type":"Manufacturing & Wholesale Goods"
        }
    ],
    "sg:phone":"+1 216 881 8100",
    "sg:postcode":"44114",
    "sg:province":"OH",
    "sg:tags":[
        "treating",
        "repair",
        "blast",
        "heat",
        "furnace",
        "welding"
    ],
    "wof:name":"HI Tecmetal Group Inc",
    "wof:placetype":"venue"
},
  "geometry": {"coordinates":[-81.656409,41.526749],"type":"Point"}
}