{
  "type": "Feature",
  "properties": {
    "iso:country":"US",
    "sg:address":"50 Blaine Ave",
    "sg:city":"Bedford",
    "sg:classifiers":[
        {
            "category":"Health Services",
            "subcategory":"Doctor",
            "type":"Services"
        }
    ],
    "sg:phone":"+1 440 232 5400",
    "sg:postcode":"44146",
    "sg:province":"OH",
    "sg:tags":[
        "physician",
        "pediatrics",
        "family",
        "gynecology",
        "practice",
        "surgeons",
        "obstetrics",
        "medicine",
        "surgeon",
        "sport"
    ],
    "wof:name":"UPCP Bedford Family Medical",
    "wof:placetype":"venue"
},
  "geometry": {"coordinates":[-81.53342600000001,41.395459],"type":"Point"}
}