{
  "type": "Feature",
  "properties": {
    "iso:country":"US",
    "sg:address":"4984 State Rte 93",
    "sg:city":"Oak Hill",
    "sg:classifiers":[
        {
            "category":"Autos & Motor Vehicles",
            "subcategory":"Automobile Sales",
            "type":"Retail Goods"
        }
    ],
    "sg:phone":"+1 740 682 7766",
    "sg:postcode":"45656",
    "sg:province":"OH",
    "sg:tags":[
        "car",
        "dealer"
    ],
    "wof:name":"Northside Quality Auto",
    "wof:placetype":"venue"
},
  "geometry": {"coordinates":[-82.567737,38.913641],"type":"Point"}
}