{
  "type": "Feature",
  "properties": {
    "addr:full": "4984 State Rte 93 Oak Hill OH 45656",
    "addr:housenumber": "4984",
    "addr:postcode": "45656",
    "addr:street": "State Rte 93;Hill",
    "iso:country": "US",
    "sg:address": "4984 State Rte 93",
    "sg:city": "Oak Hill",
    "sg:classifiers": [
      {
        "category": "Autos \u0026 Motor Vehicles",
        "subcategory": "Automobile Sales",
        "type": "Retail Goods"
      }
    ],
    "sg:phone": "+1 740 682 7766",
    "sg:postcode": "45656",
    "sg:province": "OH",
    "sg:tags": [
      "car",
      "dealer"
    ],
    "wof:name": "Northside Quality Auto",
    "wof:placetype": "venue"
  },
  "geometry": {"coordinates":[-82.567737,38.913641],"type":"Point"}
}
