{
  "type": "Feature",
  "properties": {
    "addr:full": "425 4th St Lorain OH 44052",
    "addr:housenumber": "425",
    "addr:postcode": "44052",
    "addr:street": "4Th St",
    "iso:country": "US",
    "sg:address": "425 4th St",
    "sg:city": "Lorain",
    "sg:classifiers": [
      {
        "category": "Professional",
        "type": "Services"
      }
    ],
    "sg:phone": "+1 440 244 2036",
    "sg:postcode": "44052",
    "sg:province": "OH",
    "sg:tags": [
      "establishment"
    ],
    "wof:name": "Jgt Plaza",
    "wof:placetype": "venue"
  },
  "geometry": {"coordinates":[-82.178262,41.467044],"type":"Point"}
}
