{
  "type": "Feature",
  "properties": {
    "iso:country":"US",
    "sg:address":"2000 Warrensville Center Rd",
    "sg:city":"Cleveland",
    "sg:classifiers":[
        {
            "category":"Professional",
            "subcategory":"Credit Reporting & Collection",
            "type":"Services"
        }
    ],
    "sg:phone":"+1 216 381 0013",
    "sg:postcode":"44121",
    "sg:province":"OH",
    "sg:tags":[
        "agency"
    ],
    "wof:name":"Allied Debt Recovery Svc",
    "wof:placetype":"venue"
},
  "geometry": {"coordinates":[-81.536322,41.503842],"type":"Point"}
}