{
  "type": "Feature",
  "properties": {
    "addr:full":"444 Darrow Rd Akron OH 44305",
    "addr:housenumber":"444",
    "addr:postcode":"44305",
    "addr:street":"Darrow Rd",
    "iso:country":"US",
    "sg:address":"444 Darrow Rd",
    "sg:city":"Akron",
    "sg:classifiers":[
        {
            "category":"Education",
            "subcategory":"School",
            "type":"Public Place"
        }
    ],
    "sg:phone":"+1 330 794 4164",
    "sg:postcode":"44305",
    "sg:province":"OH",
    "sg:website":"www.bettyjaneowls.com",
    "wof:name":"Betty Jane Elementary School",
    "wof:placetype":"venue"
},
  "geometry": {"coordinates":[-81.441957,41.076814],"type":"Point"}
}