{
  "type": "Feature",
  "properties": {
    "iso:country":"US",
    "sg:address":"14538 Main Market Rd",
    "sg:city":"Burton",
    "sg:classifiers":[
        {
            "category":"Personal",
            "type":"Services"
        }
    ],
    "sg:phone":"+1 440 834 8990",
    "sg:postcode":"44021",
    "sg:province":"OH",
    "sg:tags":[
        "consultant",
        "program",
        "health",
        "fitness"
    ],
    "sg:website":"www.beecap.com",
    "wof:name":"Nature Cure Of Ohio",
    "wof:placetype":"venue"
},
  "geometry": {"coordinates":[-81.11180299999999,41.37813],"type":"Point"}
}