{
  "type": "Feature",
  "properties": {
    "addr:full":"15625 Detroit Ave Lakewood OH 44107",
    "addr:housenumber":"15625",
    "addr:postcode":"44107",
    "addr:street":"Detroit Ave",
    "iso:country":"US",
    "sg:address":"15625 Detroit Ave",
    "sg:city":"Lakewood",
    "sg:classifiers":[
        {
            "category":"Bars & Pubs",
            "type":"Food & Drink"
        }
    ],
    "sg:phone":"+1 216 226 7050",
    "sg:postcode":"44107",
    "sg:province":"OH",
    "sg:tags":[
        "lounge"
    ],
    "wof:name":"Nikos Restaurant",
    "wof:placetype":"venue"
},
  "geometry": {"coordinates":[-81.80690300000001,41.485059],"type":"Point"}
}