{
  "type": "Feature",
  "properties": {
    "iso:country":"US",
    "sg:address":"5311 N Leavitt Rd",
    "sg:city":"Lorain",
    "sg:classifiers":[
        {
            "category":"Health Services",
            "subcategory":"Doctor",
            "type":"Services"
        }
    ],
    "sg:phone":"+1 440 960 5200",
    "sg:postcode":"44053",
    "sg:province":"OH",
    "wof:name":"Camille Sfeir DDS Inc",
    "wof:placetype":"venue"
},
  "geometry": {"coordinates":[-82.208753,41.421116],"type":"Point"}
}