{
  "type": "Feature",
  "properties": {
    "iso:country":"US",
    "sg:address":"2282 Patterson Rd",
    "sg:city":"Dayton",
    "sg:classifiers":[
        {
            "category":"Building & Trades",
            "subcategory":"Construction",
            "type":"Services"
        },
        {
            "category":"Home & Garden",
            "subcategory":"Carpets & Floor Coverings",
            "type":"Retail Goods"
        }
    ],
    "sg:phone":"+1 937 299 6012",
    "sg:postcode":"45420",
    "sg:province":"OH",
    "sg:tags":[
        "dealer",
        "laying",
        "rug",
        "contractor"
    ],
    "wof:name":"Professional Flooring A-DTR Co",
    "wof:placetype":"venue"
},
  "geometry": {"coordinates":[-84.13059,39.722933],"type":"Point"}
}