{
  "type": "Feature",
  "properties": {
    "addr:full": "138 Sylvester St Barberton OH 44203",
    "addr:housenumber": "138",
    "addr:postcode": "44203",
    "addr:street": "Sylvester St",
    "iso:country": "US",
    "sg:address": "138 Sylvester St",
    "sg:city": "Barberton",
    "sg:classifiers": [
      {
        "category": "Insurance",
        "subcategory": "Life Insurance",
        "type": "Services"
      }
    ],
    "sg:phone": "+1 330 753 3359",
    "sg:postcode": "44203",
    "sg:province": "OH",
    "sg:tags": [
      "society",
      "fraternal"
    ],
    "wof:name": "Barberton Social Club",
    "wof:placetype": "venue"
  },
  "geometry": {"coordinates":[-81.604372,41.019124],"type":"Point"}
}
