{
  "type": "Feature",
  "properties": {
    "addr:full": "1265 Rozelle Ave Cleveland OH 44112",
    "addr:housenumber": "1265",
    "addr:postcode": "44112",
    "addr:street": "Rozelle Ave",
    "iso:country": "US",
    "sg:address": "1265 Rozelle Ave",
    "sg:city": "Cleveland",
    "sg:classifiers": [
      {
        "category": "Local Transit",
        "type": "Transportation"
      }
    ],
    "sg:phone": "+1 216 851 1104",
    "sg:postcode": "44112",
    "sg:province": "OH",
    "sg:tags": [
      "passenger"
    ],
    "wof:name": "Mini Transportation",
    "wof:placetype": "venue"
  },
  "geometry": {"coordinates":[-81.592875,41.523242],"type":"Point"}
}
