{
  "type": "Feature",
  "properties": {
    "addr:full":"3445 Morse Rd Columbus OH 43231",
    "addr:housenumber":"3445",
    "addr:postcode":"43231",
    "addr:street":"Morse Rd",
    "iso:country":"US",
    "sg:address":"3445 Morse Rd",
    "sg:city":"Columbus",
    "sg:classifiers":[
        {
            "category":"Professional",
            "type":"Services"
        }
    ],
    "sg:phone":"+1 614 478 3887",
    "sg:postcode":"43231",
    "sg:province":"OH",
    "wof:name":"Columbus Fyinest Allstar Cheer",
    "wof:placetype":"venue"
},
  "geometry": {"coordinates":[-82.92714599999999,40.058244],"type":"Point"}
}