{
  "type": "Feature",
  "properties": {
    "addr:full": "413 Boardman Poland Rd Youngstown OH 44512",
    "addr:housenumber": "413",
    "addr:postcode": "44512",
    "addr:street": "Boardman Poland Rd",
    "iso:country": "US",
    "sg:address": "413 Boardman Poland Rd",
    "sg:city": "Youngstown",
    "sg:classifiers": [
      {
        "category": "Personal",
        "subcategory": "Beauty Salon",
        "type": "Services"
      }
    ],
    "sg:phone": "+1 330 758 3005",
    "sg:postcode": "44512",
    "sg:province": "OH",
    "wof:name": "Beautyfirst",
    "wof:placetype": "venue"
  },
  "geometry": {"coordinates":[-80.645478,41.024227],"type":"Point"}
}
