{
  "type": "Feature",
  "properties": {
    "iso:country":"US",
    "sg:address":"886 State Rte 7",
    "sg:city":"Coolville",
    "sg:classifiers":[
        {
            "category":"Organizations",
            "subcategory":"Religious Organization",
            "type":"Services"
        }
    ],
    "sg:phone":"+1 740 667 6778",
    "sg:postcode":"45723",
    "sg:province":"OH",
    "sg:tags":[
        "church"
    ],
    "wof:name":"Allegheny Wesleyan Methodist",
    "wof:placetype":"venue"
},
  "geometry": {"coordinates":[-81.83388600000001,39.192623],"type":"Point"}
}