{
  "type": "Feature",
  "properties": {
    "iso:country":"US",
    "sg:address":"662 Dover Center Rd",
    "sg:city":"Bay Village",
    "sg:classifiers":[
        {
            "category":"Real Estate",
            "subcategory":"Real Estate Agent",
            "type":"Services"
        }
    ],
    "sg:phone":"+1 440 835 6500",
    "sg:postcode":"44140",
    "sg:province":"OH",
    "sg:tags":[
        "broker"
    ],
    "wof:name":"Realty One Bay Village",
    "wof:placetype":"venue"
},
  "geometry": {"coordinates":[-81.92112,41.477461],"type":"Point"}
}