{
  "type": "Feature",
  "properties": {
    "addr:full": "1800 Manor Hill Rd Findlay OH 45840",
    "addr:housenumber": "1800",
    "addr:postcode": "45840",
    "addr:street": "Manor Hill Rd",
    "iso:country": "US",
    "sg:address": "1800 Manor Hill Rd",
    "sg:city": "Findlay",
    "sg:classifiers": [
      {
        "category": "Restaurant",
        "type": "Food \u0026 Drink"
      }
    ],
    "sg:phone": "+1 419 422 6950",
    "sg:postcode": "45840",
    "sg:province": "OH",
    "wof:name": "Hacienda Mexican Restaurant",
    "wof:placetype": "venue"
  },
  "geometry": {"coordinates":[-83.606256,41.062767],"type":"Point"}
}
