{
  "type": "Feature",
  "properties": {
    "iso:country":"US",
    "sg:address":"1800 Manor Hill Rd",
    "sg:city":"Findlay",
    "sg:classifiers":[
        {
            "category":"Restaurant",
            "type":"Food & Drink"
        }
    ],
    "sg:phone":"+1 419 422 6950",
    "sg:postcode":"45840",
    "sg:province":"OH",
    "wof:name":"Hacienda Mexican Restaurant",
    "wof:placetype":"venue"
},
  "geometry": {"coordinates":[-83.606256,41.062767],"type":"Point"}
}