{
  "type": "Feature",
  "properties": {
    "addr:full": "3308 Brookside Ln Cuyahoga Falls OH 44223",
    "addr:housenumber": "3308",
    "addr:postcode": "44223",
    "addr:street": "Brookside Ln",
    "iso:country": "US",
    "sg:address": "3308 Brookside Ln",
    "sg:city": "Cuyahoga Falls",
    "sg:classifiers": [
      {
        "category": "Shopping",
        "subcategory": "Used Merchandise",
        "type": "Retail Goods"
      }
    ],
    "sg:phone": "+1 330 923 5369",
    "sg:postcode": "44223",
    "sg:province": "OH",
    "wof:name": "Tiques \u0026 Things",
    "wof:placetype": "venue"
  },
  "geometry": {"coordinates":[-81.501302,41.15985],"type":"Point"}
}
