{
  "type": "Feature",
  "properties": {
    "addr:full": "3319 Regent Rd Cleveland OH 44127",
    "addr:housenumber": "3319",
    "addr:postcode": "44127",
    "addr:street": "Regent Rd",
    "iso:country": "US",
    "sg:address": "3319 Regent Rd",
    "sg:city": "Cleveland",
    "sg:classifiers": [
      {
        "category": "Professional",
        "type": "Services"
      }
    ],
    "sg:phone": "+1 216 341 9900",
    "sg:postcode": "44127",
    "sg:province": "OH",
    "sg:tags": [
      "establishment"
    ],
    "wof:name": "Evan Diversified",
    "wof:placetype": "venue"
  },
  "geometry": {"coordinates":[-81.641938,41.465915],"type":"Point"}
}
