{
  "type": "Feature",
  "properties": {
    "addr:full":"507 London Rd Delaware OH 43015",
    "addr:housenumber":"507",
    "addr:postcode":"43015",
    "addr:street":"London Rd",
    "iso:country":"US",
    "sg:address":"507 London Rd",
    "sg:city":"Delaware",
    "sg:classifiers":[
        {
            "category":"Professional",
            "type":"Services"
        }
    ],
    "sg:phone":"+1 740 363 6400",
    "sg:postcode":"43015",
    "sg:province":"OH",
    "sg:tags":[
        "establishment"
    ],
    "wof:name":"Americana Star Co",
    "wof:placetype":"venue"
},
  "geometry": {"coordinates":[-83.08552899999999,40.28646],"type":"Point"}
}