{
  "type": "Feature",
  "properties": {
    "addr:full": "4600 Carnegie Ave Cleveland OH 44103",
    "addr:housenumber": "4600",
    "addr:postcode": "44103",
    "addr:street": "Carnegie Ave",
    "iso:country": "US",
    "sg:address": "4600 Carnegie Ave",
    "sg:city": "Cleveland",
    "sg:classifiers": [
      {
        "category": "Social Services",
        "subcategory": "Job Training",
        "type": "Services"
      }
    ],
    "sg:phone": "+1 216 881 9000",
    "sg:postcode": "44103",
    "sg:province": "OH",
    "wof:name": "Cleveland Job Corps Center",
    "wof:placetype": "venue"
  },
  "geometry": {"coordinates":[-81.653391,41.50147],"type":"Point"}
}
