{
  "type": "Feature",
  "properties": {
    "iso:country":"US",
    "sg:address":"655 Plum St",
    "sg:city":"Cincinnati",
    "sg:classifiers":[
        {
            "category":"Building & Trades",
            "subcategory":"Construction",
            "type":"Services"
        }
    ],
    "sg:phone":"+1 513 241 1370",
    "sg:postcode":"45202",
    "sg:province":"OH",
    "sg:tags":[
        "concrete",
        "contractor"
    ],
    "wof:name":"Baker Concrete Construction",
    "wof:placetype":"venue"
},
  "geometry": {"coordinates":[-84.518452,39.102598],"type":"Point"}
}