{
  "type": "Feature",
  "properties": {
    "addr:full": "655 Plum St Cincinnati OH 45202",
    "addr:housenumber": "655",
    "addr:postcode": "45202",
    "addr:street": "Plum St",
    "iso:country": "US",
    "sg:address": "655 Plum St",
    "sg:city": "Cincinnati",
    "sg:classifiers": [
      {
        "category": "Building \u0026 Trades",
        "subcategory": "Construction",
        "type": "Services"
      }
    ],
    "sg:phone": "+1 513 241 1370",
    "sg:postcode": "45202",
    "sg:province": "OH",
    "sg:tags": [
      "concrete",
      "contractor"
    ],
    "wof:name": "Baker Concrete Construction",
    "wof:placetype": "venue"
  },
  "geometry": {"coordinates":[-84.518452,39.102598],"type":"Point"}
}
