{
  "type": "Feature",
  "properties": {
    "addr:full": "302 Elm St Celina OH 45822",
    "addr:housenumber": "302",
    "addr:postcode": "45822",
    "addr:street": "Elm St",
    "iso:country": "US",
    "sg:address": "302 Elm St",
    "sg:city": "Celina",
    "sg:classifiers": [
      {
        "category": "Building \u0026 Trades",
        "subcategory": "Construction",
        "type": "Services"
      }
    ],
    "sg:phone": "+1 419 586 2935",
    "sg:postcode": "45822",
    "sg:province": "OH",
    "sg:tags": [
      "concrete",
      "contractor"
    ],
    "wof:name": "D \u0026 G Concrete",
    "wof:placetype": "venue"
  },
  "geometry": {"coordinates":[-84.579673,40.546788],"type":"Point"}
}
