{
  "type": "Feature",
  "properties": {
    "iso:country":"US",
    "sg:address":"302 Elm St",
    "sg:city":"Celina",
    "sg:classifiers":[
        {
            "category":"Building & Trades",
            "subcategory":"Construction",
            "type":"Services"
        }
    ],
    "sg:phone":"+1 419 586 2935",
    "sg:postcode":"45822",
    "sg:province":"OH",
    "sg:tags":[
        "concrete",
        "contractor"
    ],
    "wof:name":"D & G Concrete",
    "wof:placetype":"venue"
},
  "geometry": {"coordinates":[-84.579673,40.546788],"type":"Point"}
}