{
  "type": "Feature",
  "properties": {
    "addr:full": "421 Putnam Ave Zanesville OH 43701",
    "addr:housenumber": "421",
    "addr:postcode": "43701",
    "addr:street": "Putnam Ave",
    "iso:country": "US",
    "sg:address": "421 Putnam Ave",
    "sg:city": "Zanesville",
    "sg:classifiers": [
      {
        "category": "Organizations",
        "subcategory": "Non-profit Organization",
        "type": "Services"
      }
    ],
    "sg:phone": "+1 740 453 5703",
    "sg:postcode": "43701",
    "sg:province": "OH",
    "sg:tags": [
      "public"
    ],
    "wof:name": "Meoag",
    "wof:placetype": "venue"
  },
  "geometry": {"coordinates":[-82.007237,39.93276],"type":"Point"}
}
