{
  "type": "Feature",
  "properties": {
    "iso:country":"US",
    "sg:address":"4021 Hamilton Ave",
    "sg:city":"Cincinnati",
    "sg:classifiers":[
        {
            "category":"Home & Garden",
            "subcategory":"Household Appliances",
            "type":"Retail Goods"
        }
    ],
    "sg:phone":"+1 513 541 8685",
    "sg:postcode":"45223",
    "sg:province":"OH",
    "wof:name":"Quality Appliance Sales & Svc",
    "wof:placetype":"venue"
},
  "geometry": {"coordinates":[-84.539501,39.158842],"type":"Point"}
}