{
  "type": "Feature",
  "properties": {
    "iso:country":"US",
    "sg:address":"833 E Ashton Ave",
    "sg:city":"Lima",
    "sg:classifiers":[
        {
            "category":"Building & Trades",
            "subcategory":"Construction",
            "type":"Services"
        }
    ],
    "sg:phone":"+1 419 227 1453",
    "sg:postcode":"45801",
    "sg:province":"OH",
    "sg:tags":[
        "roofing",
        "contractor"
    ],
    "wof:name":"Reliable Roofing & Home",
    "wof:placetype":"venue"
},
  "geometry": {"coordinates":[-84.093355,40.755933],"type":"Point"}
}