{
  "type": "Feature",
  "properties": {
    "addr:full":"10851 Montgomery Rd Cincinnati OH 45242",
    "addr:housenumber":"10851",
    "addr:postcode":"45242",
    "addr:street":"Montgomery Rd",
    "iso:country":"US",
    "sg:address":"10851 Montgomery Rd",
    "sg:city":"Cincinnati",
    "sg:classifiers":[
        {
            "category":"Banks & Credit Unions",
            "subcategory":"Bank",
            "type":"Services"
        }
    ],
    "sg:phone":"+1 513 387 2109",
    "sg:postcode":"45242",
    "sg:province":"OH",
    "sg:tags":[
        "state"
    ],
    "wof:name":"US Bancorp",
    "wof:placetype":"venue"
},
  "geometry": {"coordinates":[-84.337991,39.261376],"type":"Point"}
}