{
  "type": "Feature",
  "properties": {
    "addr:full":"5252 Alliance Rd NW Malvern OH 44644",
    "addr:housenumber":"5252",
    "addr:postcode":"44644",
    "addr:street":"Alliance Rd Nw",
    "iso:country":"US",
    "sg:address":"5252 Alliance Rd NW",
    "sg:city":"Malvern",
    "sg:classifiers":[
        {
            "category":"Restaurant",
            "type":"Food & Drink"
        }
    ],
    "sg:phone":"+1 330 863 1645",
    "sg:postcode":"44644",
    "sg:province":"OH",
    "sg:tags":[
        "eating"
    ],
    "wof:name":"Little Forest Inn Inc",
    "wof:placetype":"venue"
},
  "geometry": {"coordinates":[-81.193606,40.690243],"type":"Point"}
}