{
  "type": "Feature",
  "properties": {
    "addr:full": "3132 W Central Ave Toledo OH 43606",
    "addr:housenumber": "3132",
    "addr:postcode": "43606",
    "addr:street": "W Central Ave",
    "iso:country": "US",
    "sg:address": "3132 W Central Ave",
    "sg:city": "Toledo",
    "sg:classifiers": [
      {
        "category": "Personal",
        "subcategory": "Beauty Salon",
        "type": "Services"
      }
    ],
    "sg:phone": "+1 419 537 6606",
    "sg:postcode": "43606",
    "sg:province": "OH",
    "wof:name": "Artistic Creations",
    "wof:placetype": "venue"
  },
  "geometry": {"coordinates":[-83.621312,41.67747],"type":"Point"}
}
