{
  "type": "Feature",
  "properties": {
    "addr:full": "285 Miami Ave Columbus OH 43203",
    "addr:housenumber": "285",
    "addr:postcode": "43203",
    "addr:street": "Miami Ave",
    "iso:country": "US",
    "sg:address": "285 Miami Ave",
    "sg:city": "Columbus",
    "sg:classifiers": [
      {
        "category": "Home \u0026 Garden",
        "subcategory": "Hardware",
        "type": "Retail Goods"
      }
    ],
    "sg:phone": "+1 614 258 6852",
    "sg:postcode": "43203",
    "sg:province": "OH",
    "sg:tags": [
      "store"
    ],
    "wof:name": "Wallace Brothers Hardware Inc",
    "wof:placetype": "venue"
  },
  "geometry": {"coordinates":[-82.974677,39.969742],"type":"Point"}
}
