{
  "type": "Feature",
  "properties": {
    "iso:country":"US",
    "sg:address":"285 Miami Ave",
    "sg:city":"Columbus",
    "sg:classifiers":[
        {
            "category":"Home & Garden",
            "subcategory":"Hardware",
            "type":"Retail Goods"
        }
    ],
    "sg:phone":"+1 614 258 6852",
    "sg:postcode":"43203",
    "sg:province":"OH",
    "sg:tags":[
        "store"
    ],
    "wof:name":"Wallace Brothers Hardware Inc",
    "wof:placetype":"venue"
},
  "geometry": {"coordinates":[-82.974677,39.969742],"type":"Point"}
}