{
  "type": "Feature",
  "properties": {
    "iso:country":"US",
    "sg:address":"13737 Middleton Pike",
    "sg:city":"Bowling Green",
    "sg:classifiers":[
        {
            "category":"Education",
            "subcategory":"School",
            "type":"Public Place"
        }
    ],
    "sg:phone":"+1 419 823 4806",
    "sg:postcode":"43402",
    "sg:province":"OH",
    "wof:name":"PENTA-Ag Incubator",
    "wof:placetype":"venue"
},
  "geometry": {"coordinates":[-83.667663,41.458819],"type":"Point"}
}