{
  "type": "Feature",
  "properties": {
    "iso:country":"US",
    "sg:address":"2707 State Rte 307 E",
    "sg:city":"Jefferson",
    "sg:classifiers":[
        {
            "category":"Mining & Drilling",
            "type":"Manufacturing & Wholesale Goods"
        }
    ],
    "sg:phone":"+1 440 858 2471",
    "sg:postcode":"44047",
    "sg:province":"OH",
    "sg:tags":[
        "development",
        "gas",
        "oil",
        "exploration"
    ],
    "wof:name":"Zoran Oil & Gas Co",
    "wof:placetype":"venue"
},
  "geometry": {"coordinates":[-80.68380000000001,41.680998],"type":"Point"}
}