{
  "type": "Feature",
  "properties": {
    "addr:full": "2707 State Rte 307 E Jefferson OH 44047",
    "addr:housenumber": "2707",
    "addr:postcode": "44047",
    "addr:street": "State Rte 307 E",
    "iso:country": "US",
    "sg:address": "2707 State Rte 307 E",
    "sg:city": "Jefferson",
    "sg:classifiers": [
      {
        "category": "Mining \u0026 Drilling",
        "type": "Manufacturing \u0026 Wholesale Goods"
      }
    ],
    "sg:phone": "+1 440 858 2471",
    "sg:postcode": "44047",
    "sg:province": "OH",
    "sg:tags": [
      "development",
      "gas",
      "oil",
      "exploration"
    ],
    "wof:name": "Zoran Oil \u0026 Gas Co",
    "wof:placetype": "venue"
  },
  "geometry": {"coordinates":[-80.6838,41.680998],"type":"Point"}
}
