{
  "type": "Feature",
  "properties": {
    "iso:country":"US",
    "sg:address":"2421 13th St NW",
    "sg:city":"Canton",
    "sg:classifiers":[
        {
            "category":"Social Services",
            "type":"Services"
        }
    ],
    "sg:phone":"+1 330 452 9812",
    "sg:postcode":"44708",
    "sg:province":"OH",
    "sg:tags":[
        "intervention",
        "center",
        "crisis"
    ],
    "wof:name":"Crisis Intvntn Ctr Stark Cnty",
    "wof:placetype":"venue"
},
  "geometry": {"coordinates":[-81.40443500000001,40.811919],"type":"Point"}
}