{
  "type": "Feature",
  "properties": {
    "addr:full":"311 Delta Ave Cincinnati OH 45226",
    "addr:housenumber":"311",
    "addr:postcode":"45226",
    "addr:street":"Delta Ave",
    "iso:country":"US",
    "sg:address":"311 Delta Ave",
    "sg:city":"Cincinnati",
    "sg:classifiers":[
        {
            "category":"Professional",
            "subcategory":"Management & Consulting",
            "type":"Services"
        }
    ],
    "sg:phone":"+1 513 321 8080",
    "sg:postcode":"45226",
    "sg:province":"OH",
    "sg:tags":[
        "business"
    ],
    "wof:name":"Tropicana",
    "wof:placetype":"venue"
},
  "geometry": {"coordinates":[-84.439387,39.117185],"type":"Point"}
}