{
  "type": "Feature",
  "properties": {
    "iso:country":"US",
    "sg:address":"607 S Shawnee St",
    "sg:city":"Lima",
    "sg:classifiers":[
        {
            "category":"Wholesale",
            "subcategory":"Construction Materials",
            "type":"Manufacturing & Wholesale Goods"
        },
        {
            "category":"Building & Trades",
            "subcategory":"Construction",
            "type":"Services"
        }
    ],
    "sg:phone":"+1 419 227 6006",
    "sg:postcode":"45804",
    "sg:province":"OH",
    "sg:tags":[
        "fence",
        "contractor"
    ],
    "wof:name":"Roeder Fence & Supply Company",
    "wof:placetype":"venue"
},
  "geometry": {"coordinates":[-84.08762400000001,40.734561],"type":"Point"}
}