{
  "type": "Feature",
  "properties": {
    "addr:full": "607 S Shawnee St Lima OH 45804",
    "addr:housenumber": "607",
    "addr:postcode": "45804",
    "addr:street": "S Shawnee St",
    "iso:country": "US",
    "sg:address": "607 S Shawnee St",
    "sg:city": "Lima",
    "sg:classifiers": [
      {
        "category": "Wholesale",
        "subcategory": "Construction Materials",
        "type": "Manufacturing \u0026 Wholesale Goods"
      },
      {
        "category": "Building \u0026 Trades",
        "subcategory": "Construction",
        "type": "Services"
      }
    ],
    "sg:phone": "+1 419 227 6006",
    "sg:postcode": "45804",
    "sg:province": "OH",
    "sg:tags": [
      "fence",
      "contractor"
    ],
    "wof:name": "Roeder Fence \u0026 Supply Company",
    "wof:placetype": "venue"
  },
  "geometry": {"coordinates":[-84.087624,40.734561],"type":"Point"}
}
