{
  "type": "Feature",
  "properties": {
    "addr:full":"1840 State Rte 131 Milford OH 45150",
    "addr:housenumber":"1840",
    "addr:postcode":"45150",
    "addr:street":"State Rte 131",
    "iso:country":"US",
    "sg:address":"1840 State Rte 131",
    "sg:city":"Milford",
    "sg:classifiers":[
        {
            "category":"Building & Trades",
            "subcategory":"Construction",
            "type":"Services"
        }
    ],
    "sg:phone":"+1 513 722 1840",
    "sg:postcode":"45150",
    "sg:province":"OH",
    "sg:tags":[
        "house"
    ],
    "wof:name":"Laypool Construction",
    "wof:placetype":"venue"
},
  "geometry": {"coordinates":[-84.173063,39.175729],"type":"Point"}
}