{
  "type": "Feature",
  "properties": {
    "addr:full": "4770 Duke Dr Mason OH 45040",
    "addr:housenumber": "4770",
    "addr:postcode": "45040",
    "addr:street": "Duke Dr",
    "iso:country": "US",
    "sg:address": "4770 Duke Dr",
    "sg:city": "Mason",
    "sg:classifiers": [
      {
        "category": "Organizations",
        "subcategory": "Non-profit Organization",
        "type": "Services"
      }
    ],
    "sg:phone": "+1 513 398 6660",
    "sg:postcode": "45040",
    "sg:province": "OH",
    "sg:tags": [
      "charitable",
      "institution"
    ],
    "wof:name": "Make A Wish Foundation-S Ohio",
    "wof:placetype": "venue"
  },
  "geometry": {"coordinates":[-84.308733,39.302294],"type":"Point"}
}
