{
  "type": "Feature",
  "properties": {
    "addr:full": "36 E 4th St Cincinnati OH 45202",
    "addr:housenumber": "36",
    "addr:postcode": "45202",
    "addr:street": "E 4Th St",
    "iso:country": "US",
    "sg:address": "36 E 4th St",
    "sg:city": "Cincinnati",
    "sg:classifiers": [
      {
        "category": "Professional",
        "subcategory": "Management \u0026 Consulting",
        "type": "Services"
      }
    ],
    "sg:phone": "+1 513 723 2400",
    "sg:postcode": "45202",
    "sg:province": "OH",
    "sg:tags": [
      "consultant",
      "business"
    ],
    "wof:name": "North Star Navigators",
    "wof:placetype": "venue"
  },
  "geometry": {"coordinates":[-84.511207,39.100233],"type":"Point"}
}
