{
  "type": "Feature",
  "properties": {
    "addr:full": "145 W Canal St Newark OH 43055",
    "addr:housenumber": "145",
    "addr:postcode": "43055",
    "addr:street": "W Canal St",
    "iso:country": "US",
    "sg:address": "145 W Canal St",
    "sg:city": "Newark",
    "sg:classifiers": [
      {
        "category": "Building \u0026 Trades",
        "subcategory": "Plumbing",
        "type": "Services"
      }
    ],
    "sg:phone": "+1 740 366 1811",
    "sg:postcode": "43055",
    "sg:province": "OH",
    "sg:tags": [
      "sewer",
      "cleaning",
      "drain"
    ],
    "wof:name": "Affordable Portable Toilets",
    "wof:placetype": "venue"
  },
  "geometry": {"coordinates":[-82.40688,40.055165],"type":"Point"}
}
