{
  "type": "Feature",
  "properties": {
    "iso:country":"US",
    "sg:address":"145 W Canal St",
    "sg:city":"Newark",
    "sg:classifiers":[
        {
            "category":"Building & Trades",
            "subcategory":"Plumbing",
            "type":"Services"
        }
    ],
    "sg:phone":"+1 740 366 1811",
    "sg:postcode":"43055",
    "sg:province":"OH",
    "sg:tags":[
        "sewer",
        "cleaning",
        "drain"
    ],
    "wof:name":"Affordable Portable Toilets",
    "wof:placetype":"venue"
},
  "geometry": {"coordinates":[-82.40688,40.055165],"type":"Point"}
}