{
  "type": "Feature",
  "properties": {
    "addr:full":"3971 Burkettsville-St Henry Rd Coldwater OH 45828",
    "addr:housenumber":"3971",
    "addr:postcode":"45828",
    "addr:street":"Burkettsville-St Henry Rd",
    "iso:country":"US",
    "sg:address":"3971 Burkettsville-St Henry Rd",
    "sg:city":"Coldwater",
    "sg:classifiers":[
        {
            "category":"Home & Garden",
            "subcategory":"Garden Supply",
            "type":"Retail Goods"
        }
    ],
    "sg:phone":"+1 419 678 2267",
    "sg:postcode":"45828",
    "sg:province":"OH",
    "sg:tags":[
        "fertilizer",
        "chemical"
    ],
    "wof:name":"Helena Chemical Company",
    "wof:placetype":"venue"
},
  "geometry": {"coordinates":[-84.647983,40.464788],"type":"Point"}
}