{
  "type": "Feature",
  "properties": {
    "iso:country":"US",
    "sg:address":"15919 Industrial Pkwy",
    "sg:city":"Cleveland",
    "sg:classifiers":[
        {
            "category":"Wholesale",
            "subcategory":"Non-durable Goods",
            "type":"Manufacturing & Wholesale Goods"
        }
    ],
    "sg:phone":"+1 216 267 0610",
    "sg:postcode":"44135",
    "sg:province":"OH",
    "sg:tags":[
        "advertising"
    ],
    "wof:name":"Stuart & Assoc",
    "wof:placetype":"venue"
},
  "geometry": {"coordinates":[-81.811682,41.425346],"type":"Point"}
}