{
  "type": "Feature",
  "properties": {
    "addr:full": "15919 Industrial Pkwy Cleveland OH 44135",
    "addr:housenumber": "15919",
    "addr:postcode": "44135",
    "addr:street": "Industrial Pkwy",
    "iso:country": "US",
    "sg:address": "15919 Industrial Pkwy",
    "sg:city": "Cleveland",
    "sg:classifiers": [
      {
        "category": "Wholesale",
        "subcategory": "Non-durable Goods",
        "type": "Manufacturing \u0026 Wholesale Goods"
      }
    ],
    "sg:phone": "+1 216 267 0610",
    "sg:postcode": "44135",
    "sg:province": "OH",
    "sg:tags": [
      "advertising"
    ],
    "wof:name": "Stuart \u0026 Assoc",
    "wof:placetype": "venue"
  },
  "geometry": {"coordinates":[-81.811682,41.425346],"type":"Point"}
}
