{
  "type": "Feature",
  "properties": {
    "iso:country":"US",
    "sg:address":"72644 Harkins Chapel Rd",
    "sg:city":"Albany",
    "sg:classifiers":[
        {
            "category":"Wholesale",
            "subcategory":"Machinery & Supplies",
            "type":"Manufacturing & Wholesale Goods"
        },
        {
            "category":"Manufacturing",
            "subcategory":"Wood Products",
            "type":"Manufacturing & Wholesale Goods"
        }
    ],
    "sg:phone":"+1 740 596 2484",
    "sg:postcode":"45710",
    "sg:province":"OH",
    "sg:tags":[
        "instrument",
        "surveying",
        "mfg"
    ],
    "wof:name":"Barber's Surveyor Stakes",
    "wof:placetype":"venue"
},
  "geometry": {"coordinates":[-82.325474,39.227568],"type":"Point"}
}