{
  "type": "Feature",
  "properties": {
    "addr:full": "72644 Harkins Chapel Rd Albany OH 45710",
    "addr:postcode": "72644;45710",
    "addr:street": "Chapel Rd",
    "iso:country": "US",
    "sg:address": "72644 Harkins Chapel Rd",
    "sg:city": "Albany",
    "sg:classifiers": [
      {
        "category": "Wholesale",
        "subcategory": "Machinery \u0026 Supplies",
        "type": "Manufacturing \u0026 Wholesale Goods"
      },
      {
        "category": "Manufacturing",
        "subcategory": "Wood Products",
        "type": "Manufacturing \u0026 Wholesale Goods"
      }
    ],
    "sg:phone": "+1 740 596 2484",
    "sg:postcode": "45710",
    "sg:province": "OH",
    "sg:tags": [
      "instrument",
      "surveying",
      "mfg"
    ],
    "wof:name": "Barber's Surveyor Stakes",
    "wof:placetype": "venue"
  },
  "geometry": {"coordinates":[-82.325474,39.227568],"type":"Point"}
}
