{
  "type": "Feature",
  "properties": {
    "addr:full":"42307 N Ridge Rd Elyria OH 44035",
    "addr:housenumber":"42307",
    "addr:postcode":"44035",
    "addr:street":"N Ridge Rd",
    "iso:country":"US",
    "sg:address":"42307 N Ridge Rd",
    "sg:city":"Elyria",
    "sg:classifiers":[
        {
            "category":"Wholesale",
            "subcategory":"Electrical",
            "type":"Manufacturing & Wholesale Goods"
        }
    ],
    "sg:phone":"+1 440 233 6188",
    "sg:postcode":"44035",
    "sg:province":"OH",
    "sg:tags":[
        "equipment"
    ],
    "sg:website":"www.leffelectric.com",
    "wof:name":"H Leff Electric Co",
    "wof:placetype":"venue"
},
  "geometry": {"coordinates":[-82.136808,41.418095],"type":"Point"}
}