{
  "type": "Feature",
  "properties": {
    "addr:full":"9480 Kennard Rd Lodi OH 44254",
    "addr:postcode":"9480;44254",
    "addr:street":"Kennard Rd",
    "iso:country":"US",
    "sg:address":"9480 Kennard Rd",
    "sg:city":"Lodi",
    "sg:classifiers":[
        {
            "category":"Real Estate",
            "subcategory":"Real Estate Operator",
            "type":"Services"
        }
    ],
    "sg:phone":"+1 330 948 2314",
    "sg:postcode":"44254",
    "sg:province":"OH",
    "sg:tags":[
        "apartment"
    ],
    "wof:name":"Crowley Apartments",
    "wof:placetype":"venue"
},
  "geometry": {"coordinates":[-82.031226,41.053513],"type":"Point"}
}