{
  "type": "Feature",
  "properties": {
    "iso:country":"US",
    "sg:address":"768 N Main St",
    "sg:city":"Akron",
    "sg:classifiers":[
        {
            "category":"Retail",
            "subcategory":"Auto Repair",
            "type":"Services"
        }
    ],
    "sg:phone":"+1 330 701 5859",
    "sg:postcode":"44310",
    "sg:province":"OH",
    "sg:tags":[
        "automobile",
        "customizing"
    ],
    "wof:name":"T A Custom Cars",
    "wof:placetype":"venue"
},
  "geometry": {"coordinates":[-81.51091599999999,41.105895],"type":"Point"}
}