{
  "type": "Feature",
  "properties": {
    "addr:full": "768 N Main St Akron OH 44310",
    "addr:housenumber": "768",
    "addr:postcode": "44310",
    "addr:street": "N Main St",
    "iso:country": "US",
    "sg:address": "768 N Main St",
    "sg:city": "Akron",
    "sg:classifiers": [
      {
        "category": "Retail",
        "subcategory": "Auto Repair",
        "type": "Services"
      }
    ],
    "sg:phone": "+1 330 701 5859",
    "sg:postcode": "44310",
    "sg:province": "OH",
    "sg:tags": [
      "automobile",
      "customizing"
    ],
    "wof:name": "T A Custom Cars",
    "wof:placetype": "venue"
  },
  "geometry": {"coordinates":[-81.510916,41.105895],"type":"Point"}
}
