{
  "type": "Feature",
  "properties": {
    "iso:country":"US",
    "sg:address":"126 Marlyn Dr NE",
    "sg:city":"Newark",
    "sg:classifiers":[
        {
            "category":"Building & Trades",
            "subcategory":"Construction",
            "type":"Services"
        }
    ],
    "sg:phone":"+1 740 366 2786",
    "sg:postcode":"43055",
    "sg:province":"OH",
    "sg:tags":[
        "interior",
        "home",
        "finishing",
        "furnishing"
    ],
    "wof:name":"Parker H Barton Construction",
    "wof:placetype":"venue"
},
  "geometry": {"coordinates":[-82.47045,40.09924],"type":"Point"}
}