{
  "type": "Feature",
  "properties": {
    "addr:full": "4568 Mayfield Rd Cleveland OH 44121",
    "addr:housenumber": "4568",
    "addr:postcode": "44121",
    "addr:street": "Mayfield Rd",
    "iso:country": "US",
    "sg:address": "4568 Mayfield Rd",
    "sg:city": "Cleveland",
    "sg:classifiers": [
      {
        "category": "Professional",
        "subcategory": "Accounting \u0026 Tax Preparation",
        "type": "Services"
      }
    ],
    "sg:phone": "+1 216 382 7799",
    "sg:postcode": "44121",
    "sg:province": "OH",
    "sg:tags": [
      "return",
      "filing"
    ],
    "wof:name": "R \u0026 K Tax Svc",
    "wof:placetype": "venue"
  },
  "geometry": {"coordinates":[-81.51543,41.519739],"type":"Point"}
}
