{
  "type": "Feature",
  "properties": {
    "addr:full":"2751 Old Home Rd Akron OH 44312",
    "addr:housenumber":"2751",
    "addr:postcode":"44312",
    "addr:street":"Old Home Rd",
    "iso:country":"US",
    "sg:address":"2751 Old Home Rd",
    "sg:city":"Akron",
    "sg:classifiers":[
        {
            "category":"Shopping",
            "subcategory":"Used Merchandise",
            "type":"Retail Goods"
        }
    ],
    "sg:phone":"+1 330 733 5008",
    "sg:postcode":"44312",
    "sg:province":"OH",
    "sg:tags":[
        "shop",
        "consignment"
    ],
    "wof:name":"Tots To Teens Resale Clothing",
    "wof:placetype":"venue"
},
  "geometry": {"coordinates":[-81.42512000000001,41.032687],"type":"Point"}
}