{
  "type": "Feature",
  "properties": {
    "iso:country":"US",
    "sg:address":"70 Grace Dr",
    "sg:city":"Powell",
    "sg:classifiers":[
        {
            "category":"Building & Trades",
            "subcategory":"Landscaping Services",
            "type":"Services"
        }
    ],
    "sg:phone":"+1 614 888 1155",
    "sg:postcode":"43065",
    "sg:province":"OH",
    "sg:tags":[
        "landscape",
        "contractor"
    ],
    "wof:name":"Yagers Landscaping",
    "wof:placetype":"venue"
},
  "geometry": {"coordinates":[-83.072889,40.158868],"type":"Point"}
}