{
  "type": "Feature",
  "properties": {
    "addr:full": "70 Grace Dr Powell OH 43065",
    "addr:housenumber": "70",
    "addr:postcode": "43065",
    "addr:street": "Grace Dr",
    "iso:country": "US",
    "sg:address": "70 Grace Dr",
    "sg:city": "Powell",
    "sg:classifiers": [
      {
        "category": "Building \u0026 Trades",
        "subcategory": "Landscaping Services",
        "type": "Services"
      }
    ],
    "sg:phone": "+1 614 888 1155",
    "sg:postcode": "43065",
    "sg:province": "OH",
    "sg:tags": [
      "landscape",
      "contractor"
    ],
    "wof:name": "Yagers Landscaping",
    "wof:placetype": "venue"
  },
  "geometry": {"coordinates":[-83.072889,40.158868],"type":"Point"}
}
