{
  "type": "Feature",
  "properties": {
    "iso:country":"US",
    "sg:address":"9300 Co Rd 25A S",
    "sg:city":"Sidney",
    "sg:classifiers":[
        {
            "category":"Manufacturing",
            "subcategory":"Metals",
            "type":"Manufacturing & Wholesale Goods"
        }
    ],
    "sg:phone":"+1 937 492 5000",
    "sg:postcode":"45365",
    "sg:province":"OH",
    "sg:tags":[
        "steel"
    ],
    "wof:name":"Tower Steel Corp",
    "wof:placetype":"venue"
},
  "geometry": {"coordinates":[-84.165711,40.337046],"type":"Point"}
}