{
  "type": "Feature",
  "properties": {
    "addr:full": "9300 Co Rd 25A S Sidney OH 45365",
    "addr:housenumber": "9300;25a",
    "addr:postcode": "45365",
    "addr:street": "Co Rd;S Sidney",
    "iso:country": "US",
    "sg:address": "9300 Co Rd 25A S",
    "sg:city": "Sidney",
    "sg:classifiers": [
      {
        "category": "Manufacturing",
        "subcategory": "Metals",
        "type": "Manufacturing \u0026 Wholesale Goods"
      }
    ],
    "sg:phone": "+1 937 492 5000",
    "sg:postcode": "45365",
    "sg:province": "OH",
    "sg:tags": [
      "steel"
    ],
    "wof:name": "Tower Steel Corp",
    "wof:placetype": "venue"
  },
  "geometry": {"coordinates":[-84.165711,40.337046],"type":"Point"}
}
