{
  "type": "Feature",
  "properties": {
    "addr:full":"6144 Chidester Dr Canfield OH 44406",
    "addr:housenumber":"6144",
    "addr:postcode":"44406",
    "addr:street":"Chidester Dr",
    "iso:country":"US",
    "sg:address":"6144 Chidester Dr",
    "sg:city":"Canfield",
    "sg:classifiers":[
        {
            "category":"Manufacturing",
            "subcategory":"Furniture",
            "type":"Manufacturing & Wholesale Goods"
        },
        {
            "category":"Building & Trades",
            "subcategory":"Construction",
            "type":"Services"
        }
    ],
    "sg:phone":"+1 330 702 1759",
    "sg:postcode":"44406",
    "sg:province":"OH",
    "sg:tags":[
        "painter",
        "mfg"
    ],
    "wof:name":"T & R Refinishing",
    "wof:placetype":"venue"
},
  "geometry": {"coordinates":[-80.790663,41.031552],"type":"Point"}
}