{
  "type": "Feature",
  "properties": {
    "addr:full":"2109 Lowell St Springfield OH 45503",
    "addr:housenumber":"2109",
    "addr:postcode":"45503",
    "addr:street":"Lowell St",
    "iso:country":"US",
    "sg:address":"2109 Lowell St",
    "sg:city":"Springfield",
    "sg:classifiers":[
        {
            "category":"Retail",
            "subcategory":"Auto Repair",
            "type":"Services"
        }
    ],
    "sg:phone":"+1 937 325 7761",
    "sg:postcode":"45503",
    "sg:province":"OH",
    "sg:tags":[
        "repairing",
        "automobile"
    ],
    "wof:name":"C & H Svc Ctr",
    "wof:placetype":"venue"
},
  "geometry": {"coordinates":[-83.77665,39.936824],"type":"Point"}
}