{
  "type": "Feature",
  "properties": {
    "addr:full":"689 N Lexington-Springmill Rd Mansfield OH 44906",
    "addr:housenumber":"689",
    "addr:postcode":"44906",
    "addr:street":"N Lexington-Springmill Rd",
    "iso:country":"US",
    "sg:address":"689 N Lexington-Springmill Rd",
    "sg:city":"Mansfield",
    "sg:classifiers":[
        {
            "category":"Restaurant",
            "type":"Food & Drink"
        }
    ],
    "sg:phone":"+1 419 529 4561",
    "sg:postcode":"44906",
    "sg:province":"OH",
    "wof:name":"RTM Arby's",
    "wof:placetype":"venue"
},
  "geometry": {"coordinates":[-82.590461,40.770987],"type":"Point"}
}