{
  "type": "Feature",
  "properties": {
    "addr:full": "2450 Rathmell Rd Columbus OH 43207",
    "addr:postcode": "2450;43207",
    "addr:street": "Rathmell Rd",
    "iso:country": "US",
    "sg:address": "2450 Rathmell Rd",
    "sg:city": "Columbus",
    "sg:classifiers": [
      {
        "category": "Freight",
        "type": "Transportation"
      }
    ],
    "sg:phone": "+1 614 497 6031",
    "sg:postcode": "43207",
    "sg:province": "OH",
    "sg:tags": [
      "courier"
    ],
    "wof:name": "Unitd Parcel Service Emply Ctr",
    "wof:placetype": "venue"
  },
  "geometry": {"coordinates":[-82.937213,39.863326],"type":"Point"}
}
