{
  "type": "Feature",
  "properties": {
    "addr:full": "4444 Holly Hill Dr Toledo OH 43614",
    "addr:housenumber": "4444",
    "addr:postcode": "43614",
    "addr:street": "Holly Hill Dr",
    "iso:country": "US",
    "sg:address": "4444 Holly Hill Dr",
    "sg:city": "Toledo",
    "sg:classifiers": [
      {
        "category": "Professional",
        "type": "Services"
      }
    ],
    "sg:phone": "+1 419 382 9737",
    "sg:postcode": "43614",
    "sg:province": "OH",
    "wof:name": "Richard J Bage",
    "wof:placetype": "venue"
  },
  "geometry": {"coordinates":[-83.646058,41.608245],"type":"Point"}
}
