{
  "type": "Feature",
  "properties": {
    "iso:country":"US",
    "sg:address":"2721 Federated Blvd",
    "sg:city":"Columbus",
    "sg:classifiers":[
        {
            "category":"Travel",
            "subcategory":"Travel Agent",
            "type":"Entertainment"
        }
    ],
    "sg:phone":"+1 614 764 9844",
    "sg:postcode":"43235",
    "sg:province":"OH",
    "sg:tags":[
        "agency",
        "bureau"
    ],
    "sg:website":"www.carlsonwagonlit.com",
    "wof:name":"Carlson Wagonlit Elite Travel",
    "wof:placetype":"venue"
},
  "geometry": {"coordinates":[-83.091521,40.101875],"type":"Point"}
}