{
  "type": "Feature",
  "properties": {
    "addr:full":"213 Main St Duncan Falls OH 43734",
    "addr:housenumber":"213",
    "addr:postcode":"43734",
    "addr:street":"Main St",
    "iso:country":"US",
    "sg:address":"213 Main St",
    "sg:city":"Duncan Falls",
    "sg:classifiers":[
        {
            "category":"Restaurant",
            "type":"Food & Drink"
        }
    ],
    "sg:phone":"+1 740 674 4334",
    "sg:postcode":"43734",
    "sg:province":"OH",
    "sg:tags":[
        "drinking",
        "eating"
    ],
    "wof:name":"Brannonscafe",
    "wof:placetype":"venue"
},
  "geometry": {"coordinates":[-81.909302,39.871537],"type":"Point"}
}