{
  "type": "Feature",
  "properties": {
    "iso:country":"US",
    "sg:address":"8929 State Rte 43",
    "sg:city":"East Springfield",
    "sg:classifiers":[
        {
            "category":"Real Estate",
            "subcategory":"Real Estate Agent",
            "type":"Services"
        }
    ],
    "sg:phone":"+1 740 543 3311",
    "sg:postcode":"43925",
    "sg:province":"OH",
    "sg:website":"www.garycain.com",
    "wof:name":"Gary W Cain Realtors & Actnrs",
    "wof:placetype":"venue"
},
  "geometry": {"coordinates":[-80.882651,40.44695],"type":"Point"}
}