{
  "type": "Feature",
  "properties": {
    "addr:full":"10699 Campbell Rd Cleves OH 45030",
    "addr:housenumber":"10699",
    "addr:postcode":"45030",
    "addr:street":"Campbell Rd",
    "iso:country":"US",
    "sg:address":"10699 Campbell Rd",
    "sg:city":"Cleves",
    "sg:classifiers":[
        {
            "category":"Home & Garden",
            "subcategory":"Building Materials",
            "type":"Retail Goods"
        }
    ],
    "sg:phone":"+1 513 941 3770",
    "sg:postcode":"45030",
    "sg:province":"OH",
    "sg:tags":[
        "mixed",
        "concrete"
    ],
    "wof:name":"Greens Fuel & Supply Co Inc",
    "wof:placetype":"venue"
},
  "geometry": {"coordinates":[-84.80789799999999,39.247424],"type":"Point"}
}