{
  "type": "Feature",
  "properties": {
    "iso:country":"US",
    "sg:address":"18 N High St",
    "sg:city":"Covington",
    "sg:classifiers":[
        {
            "category":"Personal",
            "subcategory":"Beauty Salon",
            "type":"Services"
        }
    ],
    "sg:phone":"+1 937 473 5365",
    "sg:postcode":"45318",
    "sg:province":"OH",
    "sg:tags":[
        "shop",
        "used",
        "merchandise"
    ],
    "wof:name":"Hair Depot",
    "wof:placetype":"venue"
},
  "geometry": {"coordinates":[-84.354578,40.117638],"type":"Point"}
}