{
  "type": "Feature",
  "properties": {
    "addr:full":"3061 W Alexis Rd Toledo OH 43613",
    "addr:housenumber":"3061",
    "addr:postcode":"43613",
    "addr:street":"W Alexis Rd",
    "iso:country":"US",
    "sg:address":"3061 W Alexis Rd",
    "sg:city":"Toledo",
    "sg:classifiers":[
        {
            "category":"Retail",
            "subcategory":"Self-service Laundry",
            "type":"Services"
        }
    ],
    "sg:phone":"+1 419 472 7772",
    "sg:postcode":"43613",
    "sg:province":"OH",
    "sg:tags":[
        "coin"
    ],
    "wof:name":"Sunshine Laundromat",
    "wof:placetype":"venue"
},
  "geometry": {"coordinates":[-83.619321,41.720838],"type":"Point"}
}