{
  "type": "Feature",
  "properties": {
    "addr:full": "355 E Campus View Blvd Columbus OH 43235",
    "addr:housenumber": "355",
    "addr:postcode": "43235",
    "addr:street": "E Campus View Blvd",
    "iso:country": "US",
    "sg:address": "355 E Campus View Blvd",
    "sg:city": "Columbus",
    "sg:classifiers": [
      {
        "category": "Professional",
        "subcategory": "Computer Services",
        "type": "Services"
      }
    ],
    "sg:phone": "+1 614 854 0020",
    "sg:postcode": "43235",
    "sg:province": "OH",
    "sg:tags": [
      "consultant",
      "designer"
    ],
    "wof:name": "RHI Consulting Inc",
    "wof:placetype": "venue"
  },
  "geometry": {"coordinates":[-83.007275,40.118752],"type":"Point"}
}
