{
  "type": "Feature",
  "properties": {
    "addr:full": "6778 Lexington Park Blvd Mason OH 45040",
    "addr:housenumber": "6778",
    "addr:postcode": "45040",
    "addr:street": "Lexington Park Blvd",
    "iso:country": "US",
    "sg:address": "6778 Lexington Park Blvd",
    "sg:city": "Mason",
    "sg:classifiers": [
      {
        "category": "Shopping",
        "subcategory": "Computers \u0026 Home Electronics",
        "type": "Retail Goods"
      }
    ],
    "sg:phone": "+1 513 398 8790",
    "sg:postcode": "45040",
    "sg:province": "OH",
    "sg:tags": [
      "consulting",
      "software"
    ],
    "wof:name": "Bostonsoft Inc",
    "wof:placetype": "venue"
  },
  "geometry": {"coordinates":[-84.312538,39.341405],"type":"Point"}
}
