{
  "type": "Feature",
  "properties": {
    "addr:full":"13177 Kevin Dr Doylestown OH 44230",
    "addr:housenumber":"13177",
    "addr:postcode":"44230",
    "addr:street":"Kevin Dr",
    "iso:country":"US",
    "sg:address":"13177 Kevin Dr",
    "sg:city":"Doylestown",
    "sg:classifiers":[
        {
            "category":"Building & Trades",
            "subcategory":"Construction",
            "type":"Services"
        }
    ],
    "sg:phone":"+1 330 658 8996",
    "sg:postcode":"44230",
    "sg:province":"OH",
    "sg:tags":[
        "carpentry",
        "carpenter",
        "contractor"
    ],
    "wof:name":"Quality Carpentry Service",
    "wof:placetype":"venue"
},
  "geometry": {"coordinates":[-81.65233499999999,40.960282],"type":"Point"}
}