{
  "type": "Feature",
  "properties": {
    "iso:country":"US",
    "sg:address":"138 N Fulton St",
    "sg:city":"Wauseon",
    "sg:classifiers":[
        {
            "category":"Insurance",
            "subcategory":"Insurance Agent",
            "type":"Services"
        }
    ],
    "sg:phone":"+1 419 335 2941",
    "sg:postcode":"43567",
    "sg:province":"OH",
    "wof:name":"D Scott Bechtel & Ned L B",
    "wof:placetype":"venue"
},
  "geometry": {"coordinates":[-84.14137,41.548802],"type":"Point"}
}