{
  "type": "Feature",
  "properties": {
    "addr:full":"7355 E Kemper Rd Cincinnati OH 45249",
    "addr:housenumber":"7355",
    "addr:postcode":"45249",
    "addr:street":"E Kemper Rd",
    "iso:country":"US",
    "sg:address":"7355 E Kemper Rd",
    "sg:city":"Cincinnati",
    "sg:classifiers":[
        {
            "category":"Building & Trades",
            "subcategory":"Construction",
            "type":"Services"
        }
    ],
    "sg:phone":"+1 513 791 7586",
    "sg:postcode":"45249",
    "sg:province":"OH",
    "sg:tags":[
        "home",
        "builder"
    ],
    "sg:website":"www.pinnaclebuildinggroup.com",
    "wof:name":"Pinnacle Building Group Inc",
    "wof:placetype":"venue"
},
  "geometry": {"coordinates":[-84.359759,39.281189],"type":"Point"}
}