{
  "type": "Feature",
  "properties": {
    "addr:full": "15351 Rd 126 Paulding OH 45879",
    "addr:housenumber": "15351",
    "addr:postcode": "45879",
    "addr:street": "Rd 126",
    "iso:country": "US",
    "sg:address": "15351 Rd 126",
    "sg:city": "Paulding",
    "sg:classifiers": [
      {
        "category": "Shopping",
        "subcategory": "Used Merchandise",
        "type": "Retail Goods"
      }
    ],
    "sg:phone": "+1 419 399 2930",
    "sg:postcode": "45879",
    "sg:province": "OH",
    "sg:tags": [
      "store"
    ],
    "wof:name": "Twin Willows Antiques",
    "wof:placetype": "venue"
  },
  "geometry": {"coordinates":[-84.52109,41.121207],"type":"Point"}
}
