{
  "type": "Feature",
  "properties": {
    "iso:country":"US",
    "sg:address":"520 N Main St",
    "sg:city":"Findlay",
    "sg:classifiers":[
        {
            "category":"Insurance",
            "subcategory":"Insurance Agent",
            "type":"Services"
        }
    ],
    "sg:phone":"+1 419 425 2500",
    "sg:postcode":"45840",
    "sg:province":"OH",
    "wof:name":"Striff Insurance Agency",
    "wof:placetype":"venue"
},
  "geometry": {"coordinates":[-83.650201,41.047814],"type":"Point"}
}