{
  "type": "Feature",
  "properties": {
    "addr:full":"1904 E Main St Springfield OH 45503",
    "addr:housenumber":"1904",
    "addr:postcode":"45503",
    "addr:street":"E Main St",
    "iso:country":"US",
    "sg:address":"1904 E Main St",
    "sg:city":"Springfield",
    "sg:classifiers":[
        {
            "category":"Retail",
            "subcategory":"Auto Repair",
            "type":"Services"
        }
    ],
    "sg:phone":"+1 937 325 0038",
    "sg:postcode":"45503",
    "sg:province":"OH",
    "sg:tags":[
        "muffler",
        "exhaust",
        "system"
    ],
    "wof:name":"Rainbow Muffler & Svc Ctr",
    "wof:placetype":"venue"
},
  "geometry": {"coordinates":[-83.78080199999999,39.923399],"type":"Point"}
}