{
  "type": "Feature",
  "properties": {
    "addr:full":"1315 Boardman Canfield Rd Youngstown OH 44512",
    "addr:housenumber":"1315",
    "addr:postcode":"44512",
    "addr:street":"Boardman Canfield Rd",
    "iso:country":"US",
    "sg:address":"1315 Boardman Canfield Rd",
    "sg:city":"Youngstown",
    "sg:classifiers":[
        {
            "category":"Health Services",
            "subcategory":"Chiropractor",
            "type":"Services"
        }
    ],
    "sg:phone":"+1 330 726 7404",
    "sg:postcode":"44512",
    "sg:province":"OH",
    "sg:tags":[
        "chiropractic"
    ],
    "wof:name":"Advanced Chiropractic",
    "wof:placetype":"venue"
},
  "geometry": {"coordinates":[-80.70425299999999,41.02462],"type":"Point"}
}