{
  "type": "Feature",
  "properties": {
    "iso:country":"US",
    "sg:address":"10637 Purvis Rd NE",
    "sg:city":"Bremen",
    "sg:classifiers":[
        {
            "category":"Wholesale",
            "subcategory":"Auto Parts",
            "type":"Manufacturing & Wholesale Goods"
        }
    ],
    "sg:phone":"+1 740 569 4603",
    "sg:postcode":"43107",
    "sg:province":"OH",
    "sg:tags":[
        "automobile",
        "rebuilt"
    ],
    "wof:name":"Thirty-Seven Auto Parts",
    "wof:placetype":"venue"
},
  "geometry": {"coordinates":[-82.38806599999999,39.728877],"type":"Point"}
}