{
  "type": "Feature",
  "properties": {
    "addr:full":"2301 Middletown Eaton Rd Middletown OH 45042",
    "addr:housenumber":"2301",
    "addr:postcode":"45042",
    "addr:street":"Middletown Eaton Rd",
    "iso:country":"US",
    "sg:address":"2301 Middletown Eaton Rd",
    "sg:city":"Middletown",
    "sg:classifiers":[
        {
            "category":"Personal",
            "subcategory":"Beauty Salon",
            "type":"Services"
        }
    ],
    "sg:phone":"+1 513 420 9205",
    "sg:postcode":"45042",
    "sg:province":"OH",
    "wof:name":"Lou's Styling Station",
    "wof:placetype":"venue"
},
  "geometry": {"coordinates":[-84.4747,39.539017],"type":"Point"}
}