{
  "type": "Feature",
  "properties": {
    "addr:full": "278 E Garfield Rd Aurora OH 44202",
    "addr:housenumber": "278",
    "addr:postcode": "44202",
    "addr:street": "E Garfield Rd",
    "iso:country": "US",
    "sg:address": "278 E Garfield Rd",
    "sg:city": "Aurora",
    "sg:classifiers": [
      {
        "category": "Professional",
        "subcategory": "Art Services",
        "type": "Services"
      }
    ],
    "sg:phone": "+1 330 995 0014",
    "sg:postcode": "44202",
    "sg:province": "OH",
    "sg:tags": [
      "commercial",
      "design"
    ],
    "sg:website": "www.auedesignstudio.com",
    "wof:name": "Aue Design Studio",
    "wof:placetype": "venue"
  },
  "geometry": {"coordinates":[-81.334605,41.31729],"type":"Point"}
}
