{
  "type": "Feature",
  "properties": {
    "addr:full":"22655 Chagrin Blvd Cleveland OH 44122",
    "addr:housenumber":"22655",
    "addr:postcode":"44122",
    "addr:street":"Chagrin Blvd",
    "iso:country":"US",
    "sg:address":"22655 Chagrin Blvd",
    "sg:city":"Cleveland",
    "sg:classifiers":[
        {
            "category":"Wholesale",
            "subcategory":"Non-durable Goods",
            "type":"Manufacturing & Wholesale Goods"
        }
    ],
    "sg:phone":"+1 216 921 6622",
    "sg:postcode":"44122",
    "sg:province":"OH",
    "sg:tags":[
        "advertising"
    ],
    "wof:name":"Bill Mack Specialties",
    "wof:placetype":"venue"
},
  "geometry": {"coordinates":[-81.51902699999999,41.46456],"type":"Point"}
}