{
  "type": "Feature",
  "properties": {
    "iso:country":"US",
    "sg:address":"3520 Heatherdowns Blvd",
    "sg:city":"Toledo",
    "sg:classifiers":[
        {
            "category":"Personal",
            "subcategory":"Barber",
            "type":"Services"
        }
    ],
    "sg:phone":"+1 419 382 3461",
    "sg:postcode":"43614",
    "sg:province":"OH",
    "wof:name":"Heather-Byrne Barber Style",
    "wof:placetype":"venue"
},
  "geometry": {"coordinates":[-83.626924,41.602055],"type":"Point"}
}