{
  "type": "Feature",
  "properties": {
    "iso:country":"US",
    "sg:address":"631 E Temple St",
    "sg:city":"Washington Ct Hs",
    "sg:classifiers":[
        {
            "category":"Shopping",
            "subcategory":"Clothing, Apparel, & Fashions",
            "type":"Retail Goods"
        }
    ],
    "sg:phone":"+1 740 333 5400",
    "sg:postcode":"43160",
    "sg:province":"OH",
    "sg:tags":[
        "theatrical",
        "costume"
    ],
    "wof:name":"Costumes For All Occasions",
    "wof:placetype":"venue"
},
  "geometry": {"coordinates":[-83.435622,39.5417],"type":"Point"}
}