{
  "type": "Feature",
  "properties": {
    "iso:country":"US",
    "sg:address":"6050 Cranberry Ct",
    "sg:city":"Columbus",
    "sg:classifiers":[
        {
            "category":"Education",
            "subcategory":"School",
            "type":"Public Place"
        }
    ],
    "sg:phone":"+1 614 864 0355",
    "sg:postcode":"43213",
    "sg:province":"OH",
    "wof:name":"Preparatory Program For C",
    "wof:placetype":"venue"
},
  "geometry": {"coordinates":[-82.83731899999999,39.961051],"type":"Point"}
}