{
  "type": "Feature",
  "properties": {
    "addr:full": "709 N Main St Bellefontaine OH 43311",
    "addr:housenumber": "709",
    "addr:postcode": "43311",
    "addr:street": "N Main St",
    "iso:country": "US",
    "sg:address": "709 N Main St",
    "sg:city": "Bellefontaine",
    "sg:classifiers": [
      {
        "category": "Professional",
        "subcategory": "Lawyer \u0026 Legal Services",
        "type": "Services"
      }
    ],
    "sg:phone": "+1 937 599 6242",
    "sg:postcode": "43311",
    "sg:province": "OH",
    "sg:tags": [
      "attorney"
    ],
    "wof:name": "Beck Beck \u0026 Hawkins",
    "wof:placetype": "venue"
  },
  "geometry": {"coordinates":[-83.758704,40.371409],"type":"Point"}
}
