{
  "type": "Feature",
  "properties": {
    "addr:full":"5757 Monclova Rd Maumee OH 43537",
    "addr:housenumber":"5757",
    "addr:postcode":"43537",
    "addr:street":"Monclova Rd",
    "iso:country":"US",
    "sg:address":"5757 Monclova Rd",
    "sg:city":"Maumee",
    "sg:classifiers":[
        {
            "category":"Health Services",
            "subcategory":"Doctor",
            "type":"Services"
        }
    ],
    "sg:phone":"+1 419 893 5679",
    "sg:postcode":"43537",
    "sg:province":"OH",
    "sg:tags":[
        "physician",
        "surgeon"
    ],
    "wof:name":"Toledo Neurological Assoc Inc",
    "wof:placetype":"venue"
},
  "geometry": {"coordinates":[-83.679833,41.558659],"type":"Point"}
}