{
  "type": "Feature",
  "properties": {
    "iso:country":"US",
    "sg:address":"889 Williams Ave",
    "sg:city":"Columbus",
    "sg:classifiers":[
        {
            "category":"Shopping",
            "type":"Retail Goods"
        }
    ],
    "sg:phone":"+1 614 291 7455",
    "sg:postcode":"43212",
    "sg:province":"OH",
    "sg:tags":[
        "art",
        "gallery",
        "dealer"
    ],
    "wof:name":"Junctionview Studios LTD",
    "wof:placetype":"venue"
},
  "geometry": {"coordinates":[-83.02960299999999,39.978113],"type":"Point"}
}