{
  "type": "Feature",
  "properties": {
    "iso:country":"US",
    "sg:address":"515 S Abbe Rd",
    "sg:city":"Elyria",
    "sg:classifiers":[
        {
            "category":"Shopping",
            "type":"Retail Goods"
        }
    ],
    "sg:phone":"+1 440 365 1848",
    "sg:postcode":"44035",
    "sg:province":"OH",
    "sg:tags":[
        "merchandise"
    ],
    "wof:name":"Think Wireless",
    "wof:placetype":"venue"
},
  "geometry": {"coordinates":[-82.077804,41.367692],"type":"Point"}
}