{
  "type": "Feature",
  "properties": {
    "addr:full": "4227 Lorain Ave Cleveland OH 44113",
    "addr:housenumber": "4227",
    "addr:postcode": "44113",
    "addr:street": "Lorain Ave",
    "iso:country": "US",
    "sg:address": "4227 Lorain Ave",
    "sg:city": "Cleveland",
    "sg:classifiers": [
      {
        "category": "Autos \u0026 Motor Vehicles",
        "subcategory": "Automobile Sales",
        "type": "Retail Goods"
      }
    ],
    "sg:phone": "+1 216 281 7909",
    "sg:postcode": "44113",
    "sg:province": "OH",
    "sg:tags": [
      "dealers-used",
      "used",
      "cars-wholesale",
      "car"
    ],
    "wof:name": "Brooklyn Motors",
    "wof:placetype": "venue"
  },
  "geometry": {"coordinates":[-81.715256,41.479693],"type":"Point"}
}
