{
  "type": "Feature",
  "properties": {
    "addr:full":"202 W Main St Loudonville OH 44842",
    "addr:housenumber":"202",
    "addr:postcode":"44842",
    "addr:street":"W Main St",
    "iso:country":"US",
    "sg:address":"202 W Main St",
    "sg:city":"Loudonville",
    "sg:classifiers":[
        {
            "category":"Shopping",
            "subcategory":"Pharmacy",
            "type":"Retail Goods"
        }
    ],
    "sg:phone":"+1 419 994 3221",
    "sg:postcode":"44842",
    "sg:province":"OH",
    "sg:tags":[
        "drug",
        "store"
    ],
    "wof:name":"Danners Pharmacy",
    "wof:placetype":"venue"
},
  "geometry": {"coordinates":[-82.235878,40.635808],"type":"Point"}
}