{
  "type": "Feature",
  "properties": {
    "addr:full":"6302 Southington Dr Cleveland OH 44129",
    "addr:housenumber":"6302",
    "addr:postcode":"44129",
    "addr:street":"Southington Dr",
    "iso:country":"US",
    "sg:address":"6302 Southington Dr",
    "sg:city":"Cleveland",
    "sg:classifiers":[
        {
            "category":"Professional",
            "type":"Services"
        }
    ],
    "sg:phone":"+1 440 843 9685",
    "sg:postcode":"44129",
    "sg:province":"OH",
    "wof:name":"Kellisle Ltd",
    "wof:placetype":"venue"
},
  "geometry": {"coordinates":[-81.72873300000001,41.39144],"type":"Point"}
}