{
  "type": "Feature",
  "properties": {
    "addr:full": "446 W Delaware Ave Toledo OH 43610",
    "addr:housenumber": "446",
    "addr:postcode": "43610",
    "addr:street": "W Delaware Ave",
    "iso:country": "US",
    "sg:address": "446 W Delaware Ave",
    "sg:city": "Toledo",
    "sg:classifiers": [
      {
        "category": "Personal",
        "subcategory": "Beauty Salon",
        "type": "Services"
      }
    ],
    "sg:phone": "+1 419 754 1074",
    "sg:postcode": "43610",
    "sg:province": "OH",
    "wof:name": "M \u0026 M Beauty Salon \u0026 Boutique",
    "wof:placetype": "venue"
  },
  "geometry": {"coordinates":[-83.552604,41.671201],"type":"Point"}
}
