{
  "type": "Feature",
  "properties": {
    "iso:country":"US",
    "sg:address":"446 W Delaware Ave",
    "sg:city":"Toledo",
    "sg:classifiers":[
        {
            "category":"Personal",
            "subcategory":"Beauty Salon",
            "type":"Services"
        }
    ],
    "sg:phone":"+1 419 754 1074",
    "sg:postcode":"43610",
    "sg:province":"OH",
    "wof:name":"M & M Beauty Salon & Boutique",
    "wof:placetype":"venue"
},
  "geometry": {"coordinates":[-83.552604,41.671201],"type":"Point"}
}