{
  "type": "Feature",
  "properties": {
    "addr:full":"4000 Hollenback Rd Delaware OH 43035",
    "addr:postcode":"4000;43035",
    "addr:street":"Hollenback Rd",
    "iso:country":"US",
    "sg:address":"4000 Hollenback Rd",
    "sg:city":"Delaware",
    "sg:classifiers":[
        {
            "category":"Professional",
            "type":"Services"
        }
    ],
    "sg:phone":"+1 740 549 4976",
    "sg:postcode":"43035",
    "sg:province":"OH",
    "sg:tags":[
        "establishment"
    ],
    "wof:name":"Sunny 95",
    "wof:placetype":"venue"
},
  "geometry": {"coordinates":[-82.983931,40.216377],"type":"Point"}
}