{
  "type": "Feature",
  "properties": {
    "iso:country":"US",
    "sg:address":"80 Harrington Pt",
    "sg:city":"Conneaut",
    "sg:classifiers":[
        {
            "category":"Professional",
            "subcategory":"Research",
            "type":"Services"
        }
    ],
    "sg:phone":"+1 440 599 9161",
    "sg:postcode":"44030",
    "sg:province":"OH",
    "sg:tags":[
        "environmental",
        "ecological"
    ],
    "wof:name":"North Pointe Environmental Inc",
    "wof:placetype":"venue"
},
  "geometry": {"coordinates":[-80.59454,41.952726],"type":"Point"}
}