{
  "type": "Feature",
  "properties": {
    "addr:full": "2500 Bethel Rd Columbus OH 43220",
    "addr:housenumber": "2500",
    "addr:postcode": "43220",
    "addr:street": "Bethel Rd",
    "iso:country": "US",
    "sg:address": "2500 Bethel Rd",
    "sg:city": "Columbus",
    "sg:classifiers": [
      {
        "category": "Restaurant",
        "type": "Food \u0026 Drink"
      }
    ],
    "sg:phone": "+1 614 442 3375",
    "sg:postcode": "43220",
    "sg:province": "OH",
    "sg:tags": [
      "eating"
    ],
    "wof:name": "Sun Tong Luk Asian Cuisine",
    "wof:placetype": "venue"
  },
  "geometry": {"coordinates":[-83.083495,40.064672],"type":"Point"}
}
