{
  "type": "Feature",
  "properties": {
    "iso:country":"US",
    "sg:address":"2500 Bethel Rd",
    "sg:city":"Columbus",
    "sg:classifiers":[
        {
            "category":"Restaurant",
            "type":"Food & Drink"
        }
    ],
    "sg:phone":"+1 614 442 3375",
    "sg:postcode":"43220",
    "sg:province":"OH",
    "sg:tags":[
        "eating"
    ],
    "wof:name":"Sun Tong Luk Asian Cuisine",
    "wof:placetype":"venue"
},
  "geometry": {"coordinates":[-83.083495,40.064672],"type":"Point"}
}