{
  "type": "Feature",
  "properties": {
    "addr:full": "2254 Cheltenham Rd Toledo OH 43606",
    "addr:housenumber": "2254",
    "addr:postcode": "43606",
    "addr:street": "Cheltenham Rd",
    "iso:country": "US",
    "sg:address": "2254 Cheltenham Rd",
    "sg:city": "Toledo",
    "sg:classifiers": [
      {
        "category": "Manufacturing",
        "subcategory": "Rubber \u0026 Plastics",
        "type": "Manufacturing \u0026 Wholesale Goods"
      }
    ],
    "sg:phone": "+1 419 578 1776",
    "sg:postcode": "43606",
    "sg:province": "OH",
    "sg:tags": [
      "product",
      "mfg"
    ],
    "wof:name": "Adell Plastic",
    "wof:placetype": "venue"
  },
  "geometry": {"coordinates":[-83.611926,41.663859],"type":"Point"}
}
