{
  "type": "Feature",
  "properties": {
    "iso:country":"US",
    "sg:address":"2254 Cheltenham Rd",
    "sg:city":"Toledo",
    "sg:classifiers":[
        {
            "category":"Manufacturing",
            "subcategory":"Rubber & Plastics",
            "type":"Manufacturing & Wholesale Goods"
        }
    ],
    "sg:phone":"+1 419 578 1776",
    "sg:postcode":"43606",
    "sg:province":"OH",
    "sg:tags":[
        "product",
        "mfg"
    ],
    "wof:name":"Adell Plastic",
    "wof:placetype":"venue"
},
  "geometry": {"coordinates":[-83.611926,41.663859],"type":"Point"}
}