{
  "type": "Feature",
  "properties": {
    "iso:country":"US",
    "sg:address":"6645 Glenallen Ave",
    "sg:city":"Solon",
    "sg:classifiers":[
        {
            "category":"Building & Trades",
            "subcategory":"Plumbing",
            "type":"Services"
        }
    ],
    "sg:phone":"+1 440 232 5911",
    "sg:postcode":"44139",
    "sg:province":"OH",
    "sg:tags":[
        "plumbing",
        "contractor"
    ],
    "wof:name":"Murphy Plumbing Inc",
    "wof:placetype":"venue"
},
  "geometry": {"coordinates":[-81.44855200000001,41.374767],"type":"Point"}
}