{
  "type": "Feature",
  "properties": {
    "addr:full": "803 Union St Troy OH 45373",
    "addr:housenumber": "803",
    "addr:postcode": "45373",
    "addr:street": "Union St",
    "iso:country": "US",
    "sg:address": "803 Union St",
    "sg:city": "Troy",
    "sg:classifiers": [
      {
        "category": "Manufacturing",
        "subcategory": "Petroleum Products",
        "type": "Manufacturing \u0026 Wholesale Goods"
      }
    ],
    "sg:phone": "+1 937 339 4013",
    "sg:postcode": "45373",
    "sg:province": "OH",
    "sg:tags": [
      "construction",
      "asphalt",
      "mfg"
    ],
    "wof:name": "Barrett Paving",
    "wof:placetype": "venue"
  },
  "geometry": {"coordinates":[-84.201088,40.029679],"type":"Point"}
}
