{
  "type": "Feature",
  "properties": {
    "addr:full":"49 E Main St Shelby OH 44875",
    "addr:housenumber":"49",
    "addr:postcode":"44875",
    "addr:street":"E Main St",
    "iso:country":"US",
    "sg:address":"49 E Main St",
    "sg:city":"Shelby",
    "sg:classifiers":[
        {
            "category":"Government",
            "subcategory":"Office",
            "type":"Public Place"
        }
    ],
    "sg:phone":"+1 419 347 1240",
    "sg:postcode":"44875",
    "sg:province":"OH",
    "sg:tags":[
        "county"
    ],
    "wof:name":"Richland County Clerk Of Court",
    "wof:placetype":"venue"
},
  "geometry": {"coordinates":[-82.656925,40.88146],"type":"Point"}
}