{
  "type": "Feature",
  "properties": {
    "addr:full": "6587 Havens Rd Blacklick OH 43004",
    "addr:housenumber": "6587",
    "addr:postcode": "43004",
    "addr:street": "Havens Rd",
    "iso:country": "US",
    "sg:address": "6587 Havens Rd",
    "sg:city": "Blacklick",
    "sg:classifiers": [
      {
        "category": "Wholesale",
        "subcategory": "Furniture",
        "type": "Manufacturing \u0026 Wholesale Goods"
      }
    ],
    "sg:phone": "+1 614 855 1211",
    "sg:postcode": "43004",
    "sg:province": "OH",
    "sg:tags": [
      "equipment",
      "school"
    ],
    "wof:name": "Capital Design Group",
    "wof:placetype": "venue"
  },
  "geometry": {"coordinates":[-82.814672,40.029868],"type":"Point"}
}
