{
  "type": "Feature",
  "properties": {
    "addr:full":"38 S Main St Munroe Falls OH 44262",
    "addr:housenumber":"38",
    "addr:postcode":"44262",
    "addr:street":"S Main St",
    "iso:country":"US",
    "sg:address":"38 S Main St",
    "sg:city":"Munroe Falls",
    "sg:classifiers":[
        {
            "category":"Government",
            "subcategory":"Post Office",
            "type":"Public Place"
        }
    ],
    "sg:phone":"+1 330 688 1161",
    "sg:postcode":"44262",
    "sg:province":"OH",
    "wof:name":"US Post Office",
    "wof:placetype":"venue"
},
  "geometry": {"coordinates":[-81.439257,41.138934],"type":"Point"}
}