{
  "type": "Feature",
  "properties": {
    "addr:full": "5833 Timely Ter Cincinnati OH 45233",
    "addr:housenumber": "5833",
    "addr:postcode": "45233",
    "addr:street": "Timely Ter",
    "iso:country": "US",
    "sg:address": "5833 Timely Ter",
    "sg:city": "Cincinnati",
    "sg:classifiers": [
      {
        "category": "Building \u0026 Trades",
        "subcategory": "Locksmith",
        "type": "Services"
      }
    ],
    "sg:phone": "+1 513 322 0044",
    "sg:postcode": "45233",
    "sg:province": "OH",
    "sg:tags": [
      "key"
    ],
    "wof:name": "Locksmith A 24 Hour",
    "wof:placetype": "venue"
  },
  "geometry": {"coordinates":[-84.641781,39.104822],"type":"Point"}
}
