{
  "type": "Feature",
  "properties": {
    "iso:country":"US",
    "sg:address":"5833 Timely Ter",
    "sg:city":"Cincinnati",
    "sg:classifiers":[
        {
            "category":"Building & Trades",
            "subcategory":"Locksmith",
            "type":"Services"
        }
    ],
    "sg:phone":"+1 513 322 0044",
    "sg:postcode":"45233",
    "sg:province":"OH",
    "sg:tags":[
        "key"
    ],
    "wof:name":"Locksmith A 24 Hour",
    "wof:placetype":"venue"
},
  "geometry": {"coordinates":[-84.64178099999999,39.104822],"type":"Point"}
}