{
  "type": "Feature",
  "properties": {
    "addr:full": "8401 Vine St Cincinnati OH 45216",
    "addr:housenumber": "8401",
    "addr:postcode": "45216",
    "addr:street": "Vine St",
    "iso:country": "US",
    "sg:address": "8401 Vine St",
    "sg:city": "Cincinnati",
    "sg:classifiers": [
      {
        "category": "Restaurant",
        "type": "Food \u0026 Drink"
      }
    ],
    "sg:phone": "+1 513 761 4227",
    "sg:postcode": "45216",
    "sg:province": "OH",
    "sg:tags": [
      "barbecue"
    ],
    "wof:name": "Jimmys Bbq",
    "wof:placetype": "venue"
  },
  "geometry": {"coordinates":[-84.473757,39.216426],"type":"Point"}
}
