{
  "type": "Feature",
  "properties": {
    "iso:country":"US",
    "sg:address":"8401 Vine St",
    "sg:city":"Cincinnati",
    "sg:classifiers":[
        {
            "category":"Restaurant",
            "type":"Food & Drink"
        }
    ],
    "sg:phone":"+1 513 761 4227",
    "sg:postcode":"45216",
    "sg:province":"OH",
    "sg:tags":[
        "barbecue"
    ],
    "wof:name":"Jimmys Bbq",
    "wof:placetype":"venue"
},
  "geometry": {"coordinates":[-84.473757,39.216426],"type":"Point"}
}