{
  "type": "Feature",
  "properties": {
    "iso:country":"US",
    "sg:address":"22332 Lake Shore Blvd",
    "sg:city":"Cleveland",
    "sg:classifiers":[
        {
            "category":"Banks & Credit Unions",
            "subcategory":"Bank",
            "type":"Services"
        }
    ],
    "sg:phone":"+1 216 261 0900",
    "sg:postcode":"44123",
    "sg:province":"OH",
    "sg:website":"www.thirdfederal.com",
    "wof:name":"Third Federal Savings & Loan",
    "wof:placetype":"venue"
},
  "geometry": {"coordinates":[-81.52609699999999,41.60974],"type":"Point"}
}