{
  "type": "Feature",
  "properties": {
    "iso:country":"US",
    "sg:address":"1330 N Co Rd 25A",
    "sg:city":"Troy",
    "sg:classifiers":[
        {
            "category":"Government",
            "subcategory":"Office",
            "type":"Public Place"
        }
    ],
    "sg:phone":"+1 937 339 3876",
    "sg:postcode":"45373",
    "sg:province":"OH",
    "wof:name":"Bvr",
    "wof:placetype":"venue"
},
  "geometry": {"coordinates":[-84.21396900000001,40.060888],"type":"Point"}
}