{
  "type": "Feature",
  "properties": {
    "iso:country":"US",
    "sg:address":"8053 Meadowlark Dr",
    "sg:city":"Franklin",
    "sg:classifiers":[
        {
            "category":"Building & Trades",
            "subcategory":"Landscaping Services",
            "type":"Services"
        }
    ],
    "sg:phone":"+1 937 743 9529",
    "sg:postcode":"45005",
    "sg:province":"OH",
    "sg:tags":[
        "landscape"
    ],
    "wof:name":"Masterpiece Landscaping",
    "wof:placetype":"venue"
},
  "geometry": {"coordinates":[-84.326712,39.578403],"type":"Point"}
}