{
  "type": "Feature",
  "properties": {
    "iso:country":"US",
    "sg:address":"1571 State Rte 28",
    "sg:city":"Loveland",
    "sg:classifiers":[
        {
            "category":"Retail",
            "subcategory":"Auto Repair",
            "type":"Services"
        }
    ],
    "sg:phone":"+1 513 575 2100",
    "sg:postcode":"45140",
    "sg:province":"OH",
    "sg:tags":[
        "body",
        "automobile",
        "painting"
    ],
    "wof:name":"Prestige Auto Body",
    "wof:placetype":"venue"
},
  "geometry": {"coordinates":[-84.192424,39.21959],"type":"Point"}
}