{
  "type": "Feature",
  "properties": {
    "addr:full": "2246 Navarre Ave Oregon OH 43616",
    "addr:housenumber": "2246",
    "addr:postcode": "43616",
    "addr:street": "Navarre Ave",
    "iso:country": "US",
    "sg:address": "2246 Navarre Ave",
    "sg:city": "Oregon",
    "sg:classifiers": [
      {
        "category": "Bars \u0026 Pubs",
        "type": "Food \u0026 Drink"
      }
    ],
    "sg:phone": "+1 419 698 9300",
    "sg:postcode": "43616",
    "sg:province": "OH",
    "sg:tags": [
      "drinking"
    ],
    "wof:name": "Rosebuds",
    "wof:placetype": "venue"
  },
  "geometry": {"coordinates":[-83.494164,41.636502],"type":"Point"}
}
