{
  "type": "Feature",
  "properties": {
    "addr:full": "22109 State Rte 62 Alliance OH 44601",
    "addr:housenumber": "22109",
    "addr:postcode": "44601",
    "addr:street": "State Rte 62",
    "iso:country": "US",
    "sg:address": "22109 State Rte 62",
    "sg:city": "Alliance",
    "sg:classifiers": [
      {
        "category": "Manufacturing",
        "subcategory": "Glass \u0026 Minerals",
        "type": "Manufacturing \u0026 Wholesale Goods"
      }
    ],
    "sg:phone": "+1 330 821 4653",
    "sg:postcode": "44601",
    "sg:province": "OH",
    "sg:tags": [
      "refractory",
      "mfg"
    ],
    "wof:name": "Allen Refractories Co",
    "wof:placetype": "venue"
  },
  "geometry": {"coordinates":[-81.072532,40.901643],"type":"Point"}
}
