{
  "type": "Feature",
  "properties": {
    "addr:full":"137 S East St Mc Clure OH 43534",
    "addr:housenumber":"137",
    "addr:postcode":"43534",
    "addr:street":"S East St Mc Clure",
    "iso:country":"US",
    "sg:address":"137 S East St",
    "sg:city":"Mc Clure",
    "sg:classifiers":[
        {
            "category":"Restaurant",
            "type":"Food & Drink"
        }
    ],
    "sg:phone":"+1 419 748 7601",
    "sg:postcode":"43534",
    "sg:province":"OH",
    "sg:tags":[
        "out"
    ],
    "wof:name":"Pop & Son Carry Out LLC",
    "wof:placetype":"venue"
},
  "geometry": {"coordinates":[-83.941328,41.37122],"type":"Point"}
}