{
  "type": "Feature",
  "properties": {
    "addr:full": "126 W Ward St Urbana OH 43078",
    "addr:housenumber": "126",
    "addr:postcode": "43078",
    "addr:street": "W Ward St",
    "iso:country": "US",
    "sg:address": "126 W Ward St",
    "sg:city": "Urbana",
    "sg:classifiers": [
      {
        "category": "Retail",
        "subcategory": "Portrait Studio",
        "type": "Services"
      }
    ],
    "sg:phone": "+1 937 484 4494",
    "sg:postcode": "43078",
    "sg:province": "OH",
    "sg:tags": [
      "photographer"
    ],
    "wof:name": "Artistic Images Photography",
    "wof:placetype": "venue"
  },
  "geometry": {"coordinates":[-83.75334,40.111477],"type":"Point"}
}
