{
  "type": "Feature",
  "properties": {
    "addr:full": "1527 Lake Crest Dr Rock Creek OH 44084",
    "addr:housenumber": "1527",
    "addr:postcode": "44084",
    "addr:street": "Lake Crest Dr",
    "iso:country": "US",
    "sg:address": "1527 Lake Crest Dr",
    "sg:city": "Rock Creek",
    "sg:classifiers": [
      {
        "category": "Real Estate",
        "subcategory": "Real Estate Operator",
        "type": "Services"
      }
    ],
    "sg:phone": "+1 440 563 3590",
    "sg:postcode": "44084",
    "sg:province": "OH",
    "sg:tags": [
      "building",
      "nonresidential"
    ],
    "wof:name": "Frane Properties LLC",
    "wof:placetype": "venue"
  },
  "geometry": {"coordinates":[-80.819919,41.630682],"type":"Point"}
}
