{
  "type": "Feature",
  "properties": {
    "iso:country":"US",
    "sg:address":"408 Nutt Rd",
    "sg:city":"Dayton",
    "sg:classifiers":[
        {
            "category":"Real Estate",
            "subcategory":"Real Estate Operator",
            "type":"Services"
        }
    ],
    "sg:phone":"+1 937 886 9702",
    "sg:postcode":"45458",
    "sg:province":"OH",
    "sg:tags":[
        "building",
        "nonresidential"
    ],
    "wof:name":"R Squared Properties LLC",
    "wof:placetype":"venue"
},
  "geometry": {"coordinates":[-84.152851,39.598717],"type":"Point"}
}