{
  "type": "Feature",
  "properties": {
    "iso:country":"US",
    "sg:address":"421 N Court St",
    "sg:city":"Medina",
    "sg:classifiers":[
        {
            "category":"Retail",
            "subcategory":"Car Wash",
            "type":"Services"
        }
    ],
    "sg:phone":"+1 330 725 5273",
    "sg:postcode":"44256",
    "sg:province":"OH",
    "sg:tags":[
        "polishing",
        "washing"
    ],
    "wof:name":"Susan-Kaye Car Wash",
    "wof:placetype":"venue"
},
  "geometry": {"coordinates":[-81.864071,41.143511],"type":"Point"}
}