{
  "type": "Feature",
  "properties": {
    "iso:country":"US",
    "sg:address":"4767 Creek Rd",
    "sg:city":"Cincinnati",
    "sg:classifiers":[
        {
            "category":"Local Transit",
            "type":"Transportation"
        }
    ],
    "sg:phone":"+1 513 793 0610",
    "sg:postcode":"45242",
    "sg:province":"OH",
    "sg:tags":[
        "limousine"
    ],
    "wof:name":"Cincy Limos",
    "wof:placetype":"venue"
},
  "geometry": {"coordinates":[-84.376735,39.258279],"type":"Point"}
}