{
  "type": "Feature",
  "properties": {
    "addr:full": "2125 E Sand Rd Port Clinton OH 43452",
    "addr:housenumber": "2125",
    "addr:postcode": "43452",
    "addr:street": "E Sand Rd",
    "iso:country": "US",
    "sg:address": "2125 E Sand Rd",
    "sg:city": "Port Clinton",
    "sg:classifiers": [
      {
        "category": "Real Estate",
        "subcategory": "Real Estate Operator",
        "type": "Services"
      }
    ],
    "sg:phone": "+1 419 734 4745",
    "sg:postcode": "43452",
    "sg:province": "OH",
    "sg:tags": [
      "mobile",
      "home",
      "site"
    ],
    "wof:name": "Summer Breeze Assoc Inc",
    "wof:placetype": "venue"
  },
  "geometry": {"coordinates":[-82.899261,41.51747],"type":"Point"}
}
