{
  "type": "Feature",
  "properties": {
    "addr:full": "191 W Bridge St Dublin OH 43017",
    "addr:housenumber": "191",
    "addr:postcode": "43017",
    "addr:street": "W Bridge St",
    "iso:country": "US",
    "sg:address": "191 W Bridge St",
    "sg:city": "Dublin",
    "sg:classifiers": [
      {
        "category": "Autos \u0026 Motor Vehicles",
        "subcategory": "Fuel \u0026 Gas Station",
        "type": "Retail Goods"
      }
    ],
    "sg:phone": "+1 614 889 8635",
    "sg:postcode": "43017",
    "sg:province": "OH",
    "sg:tags": [
      "station",
      "gasoline"
    ],
    "wof:name": "Duke \u0026 Duchess",
    "wof:placetype": "venue"
  },
  "geometry": {"coordinates":[-83.117753,40.099163],"type":"Point"}
}
