{
  "type": "Feature",
  "properties": {
    "iso:country":"US",
    "sg:address":"191 W Bridge St",
    "sg:city":"Dublin",
    "sg:classifiers":[
        {
            "category":"Autos & Motor Vehicles",
            "subcategory":"Fuel & Gas Station",
            "type":"Retail Goods"
        }
    ],
    "sg:phone":"+1 614 889 8635",
    "sg:postcode":"43017",
    "sg:province":"OH",
    "sg:tags":[
        "station",
        "gasoline"
    ],
    "wof:name":"Duke & Duchess",
    "wof:placetype":"venue"
},
  "geometry": {"coordinates":[-83.117753,40.099163],"type":"Point"}
}