{
  "type": "Feature",
  "properties": {
    "addr:full":"7195 Thumbelina Ln Cincinnati OH 45242",
    "addr:housenumber":"7195",
    "addr:postcode":"45242",
    "addr:street":"Thumbelina Ln",
    "iso:country":"US",
    "sg:address":"7195 Thumbelina Ln",
    "sg:city":"Cincinnati",
    "sg:classifiers":[
        {
            "category":"Home & Garden",
            "subcategory":"Home Furnishings",
            "type":"Retail Goods"
        }
    ],
    "sg:phone":"+1 513 891 6425",
    "sg:postcode":"45242",
    "sg:province":"OH",
    "wof:name":"Montgomery Window Fashions",
    "wof:placetype":"venue"
},
  "geometry": {"coordinates":[-84.358723,39.253976],"type":"Point"}
}