{
  "type": "Feature",
  "properties": {
    "iso:country":"US",
    "sg:address":"11535 McGillard St",
    "sg:city":"Cincinnati",
    "sg:classifiers":[
        {
            "category":"Autos & Motor Vehicles",
            "subcategory":"Automobile Sales",
            "type":"Retail Goods"
        }
    ],
    "sg:phone":"+1 513 782 1122",
    "sg:postcode":"45246",
    "sg:province":"OH",
    "sg:website":"www.jakesweeney.com",
    "wof:name":"JAKE Sweeney Bmw",
    "wof:placetype":"venue"
},
  "geometry": {"coordinates":[-84.470109,39.284811],"type":"Point"}
}