{
  "type": "Feature",
  "properties": {
    "addr:full":"3225 Hilliard Rome Rd Hilliard OH 43026",
    "addr:housenumber":"3225",
    "addr:postcode":"43026",
    "addr:street":"Hilliard Rome Rd",
    "iso:country":"US",
    "sg:address":"3225 Hilliard Rome Rd",
    "sg:city":"Hilliard",
    "sg:classifiers":[
        {
            "category":"Health Services",
            "subcategory":"Doctor",
            "type":"Services"
        }
    ],
    "sg:phone":"+1 614 777 5454",
    "sg:postcode":"43026",
    "sg:province":"OH",
    "sg:tags":[
        "dentist"
    ],
    "wof:name":"Lisa Pomarico DDS",
    "wof:placetype":"venue"
},
  "geometry": {"coordinates":[-83.15655599999999,40.016746],"type":"Point"}
}