{
  "type": "Feature",
  "properties": {
    "addr:full": "106 W Perry St Port Clinton OH 43452",
    "addr:housenumber": "106",
    "addr:postcode": "43452",
    "addr:street": "W Perry St",
    "iso:country": "US",
    "sg:address": "106 W Perry St",
    "sg:city": "Port Clinton",
    "sg:classifiers": [
      {
        "category": "Social Services",
        "type": "Services"
      }
    ],
    "sg:phone": "+1 419 734 2652",
    "sg:postcode": "43452",
    "sg:province": "OH",
    "sg:tags": [
      "organization",
      "welfare"
    ],
    "wof:name": "WSOS Child \u0026 Family Devlpmt",
    "wof:placetype": "venue"
  },
  "geometry": {"coordinates":[-82.942693,41.513209],"type":"Point"}
}
