{
  "type": "Feature",
  "properties": {
    "iso:country":"US",
    "sg:address":"106 W Perry St",
    "sg:city":"Port Clinton",
    "sg:classifiers":[
        {
            "category":"Social Services",
            "type":"Services"
        }
    ],
    "sg:phone":"+1 419 734 2652",
    "sg:postcode":"43452",
    "sg:province":"OH",
    "sg:tags":[
        "organization",
        "welfare"
    ],
    "wof:name":"WSOS Child & Family Devlpmt",
    "wof:placetype":"venue"
},
  "geometry": {"coordinates":[-82.94269300000001,41.513209],"type":"Point"}
}