{
  "type": "Feature",
  "properties": {
    "addr:full": "102 W Indiana Ave Perrysburg OH 43551",
    "addr:housenumber": "102",
    "addr:postcode": "43551",
    "addr:street": "W Indiana Ave",
    "iso:country": "US",
    "sg:address": "102 W Indiana Ave",
    "sg:city": "Perrysburg",
    "sg:classifiers": [
      {
        "category": "Personal",
        "subcategory": "Beauty Salon",
        "type": "Services"
      },
      {
        "category": "Personal",
        "subcategory": "Day Spa",
        "type": "Services"
      }
    ],
    "sg:phone": "+1 419 872 9908",
    "sg:postcode": "43551",
    "sg:province": "OH",
    "sg:website": "http://www.shamas.com",
    "wof:name": "Shamas",
    "wof:placetype": "venue"
  },
  "geometry": {"coordinates":[-83.627874,41.557105],"type":"Point"}
}
