{
  "type": "Feature",
  "properties": {
    "addr:full": "4791 Blue Church Rd Sunbury OH 43074",
    "addr:housenumber": "4791",
    "addr:postcode": "43074",
    "addr:street": "Blue Church Rd",
    "iso:country": "US",
    "sg:address": "4791 Blue Church Rd",
    "sg:city": "Sunbury",
    "sg:classifiers": [
      {
        "category": "Building \u0026 Trades",
        "subcategory": "Construction",
        "type": "Services"
      }
    ],
    "sg:phone": "+1 740 965 4641",
    "sg:postcode": "43074",
    "sg:province": "OH",
    "sg:tags": [
      "heavy"
    ],
    "wof:name": "Wandle Construction Inc",
    "wof:placetype": "venue"
  },
  "geometry": {"coordinates":[-82.867177,40.309974],"type":"Point"}
}
