{
  "type": "Feature",
  "properties": {
    "iso:country":"US",
    "sg:address":"4514 Coe Rd",
    "sg:city":"Ravenna",
    "sg:classifiers":[
        {
            "category":"Real Estate",
            "subcategory":"Real Estate Operator",
            "type":"Services"
        }
    ],
    "sg:phone":"+1 330 297 0652",
    "sg:postcode":"44266",
    "sg:province":"OH",
    "sg:tags":[
        "building",
        "apartment"
    ],
    "wof:name":"Portage Terrace Apartments",
    "wof:placetype":"venue"
},
  "geometry": {"coordinates":[-81.22995899999999,41.171298],"type":"Point"}
}