{
  "type": "Feature",
  "properties": {
    "addr:full":"502 Pearl St Lynchburg OH 45142",
    "addr:housenumber":"502",
    "addr:postcode":"45142",
    "addr:street":"Pearl St",
    "iso:country":"US",
    "sg:address":"502 Pearl St",
    "sg:city":"Lynchburg",
    "sg:classifiers":[
        {
            "category":"Organizations",
            "subcategory":"Religious Organization",
            "type":"Services"
        }
    ],
    "sg:phone":"+1 937 364 2379",
    "sg:postcode":"45142",
    "sg:province":"OH",
    "sg:tags":[
        "church"
    ],
    "wof:name":"St Paul Lutheran Church",
    "wof:placetype":"venue"
},
  "geometry": {"coordinates":[-83.78541,39.243767],"type":"Point"}
}