{
  "type": "Feature",
  "properties": {
    "addr:full": "37152 Oneil Dr Cleveland OH 44139",
    "addr:postcode": "37152;44139",
    "addr:street": "Oneil Dr",
    "iso:country": "US",
    "sg:address": "37152 Oneil Dr",
    "sg:city": "Cleveland",
    "sg:classifiers": [
      {
        "category": "Building \u0026 Trades",
        "subcategory": "Construction",
        "type": "Services"
      }
    ],
    "sg:phone": "+1 440 519 9992",
    "sg:postcode": "44139",
    "sg:province": "OH",
    "sg:tags": [
      "general",
      "contractor"
    ],
    "wof:name": "O'Brien Construction Inc",
    "wof:placetype": "venue"
  },
  "geometry": {"coordinates":[-81.414485,41.399034],"type":"Point"}
}
