{
  "type": "Feature",
  "properties": {
    "addr:full": "9118 N Dixie Dr Dayton OH 45414",
    "addr:housenumber": "9118",
    "addr:postcode": "45414",
    "addr:street": "N Dixie Dr",
    "iso:country": "US",
    "sg:address": "9118 N Dixie Dr",
    "sg:city": "Dayton",
    "sg:classifiers": [
      {
        "category": "Food \u0026 Beverages",
        "subcategory": "Liquor \u0026 Beverages",
        "type": "Retail Goods"
      }
    ],
    "sg:phone": "+1 937 454 9030",
    "sg:postcode": "45414",
    "sg:province": "OH",
    "sg:tags": [
      "beer",
      "ale"
    ],
    "wof:name": "Butler Beer Drive-Thru",
    "wof:placetype": "venue"
  },
  "geometry": {"coordinates":[-84.199004,39.863711],"type":"Point"}
}
