{
  "type": "Feature",
  "properties": {
    "iso:country":"US",
    "sg:address":"1580 Miami Conservancy Rd",
    "sg:city":"Sidney",
    "sg:classifiers":[
        {
            "category":"Shopping",
            "subcategory":"Beauty & Cosmetics",
            "type":"Retail Goods"
        }
    ],
    "sg:phone":"+1 937 497 8441",
    "sg:postcode":"45365",
    "sg:province":"OH",
    "sg:tags":[
        "merchandise"
    ],
    "wof:name":"Tracey Vondenhuevel",
    "wof:placetype":"venue"
},
  "geometry": {"coordinates":[-84.233591,40.222432],"type":"Point"}
}