{
  "type": "Feature",
  "properties": {
    "addr:full": "1580 Miami Conservancy Rd Sidney OH 45365",
    "addr:housenumber": "1580",
    "addr:postcode": "45365",
    "addr:street": "Miami Conservancy Rd",
    "iso:country": "US",
    "sg:address": "1580 Miami Conservancy Rd",
    "sg:city": "Sidney",
    "sg:classifiers": [
      {
        "category": "Shopping",
        "subcategory": "Beauty \u0026 Cosmetics",
        "type": "Retail Goods"
      }
    ],
    "sg:phone": "+1 937 497 8441",
    "sg:postcode": "45365",
    "sg:province": "OH",
    "sg:tags": [
      "merchandise"
    ],
    "wof:name": "Tracey Vondenhuevel",
    "wof:placetype": "venue"
  },
  "geometry": {"coordinates":[-84.233591,40.222432],"type":"Point"}
}
