{
  "type": "Feature",
  "properties": {
    "addr:full":"804 Bogart Rd Huron OH 44839",
    "addr:housenumber":"804",
    "addr:postcode":"44839",
    "addr:street":"Bogart Rd",
    "iso:country":"US",
    "sg:address":"804 Bogart Rd",
    "sg:city":"Huron",
    "sg:phone":"+1 419 433 2367",
    "sg:postcode":"44839",
    "sg:province":"OH",
    "sg:tags":[
        "farm",
        "soybean"
    ],
    "wof:name":"Ted Hahn",
    "wof:placetype":"venue"
},
  "geometry": {"coordinates":[-82.578946,41.388912],"type":"Point"}
}