{
  "type": "Feature",
  "properties": {
    "addr:full":"825 S Union St Fostoria OH 44830",
    "addr:housenumber":"825",
    "addr:postcode":"44830",
    "addr:street":"S Union St",
    "iso:country":"US",
    "sg:address":"825 S Union St",
    "sg:city":"Fostoria",
    "sg:classifiers":[
        {
            "category":"Shopping",
            "subcategory":"Florist",
            "type":"Retail Goods"
        },
        {
            "category":"Farming",
            "subcategory":"Nursery",
            "type":"Manufacturing & Wholesale Goods"
        }
    ],
    "sg:phone":"+1 419 435 4324",
    "sg:postcode":"44830",
    "sg:province":"OH",
    "sg:tags":[
        "ornamental"
    ],
    "wof:name":"Payne Brothers Greenhouse",
    "wof:placetype":"venue"
},
  "geometry": {"coordinates":[-83.41891099999999,41.149242],"type":"Point"}
}