{
  "type": "Feature",
  "properties": {
    "addr:full":"3333 Manchester Rd Akron OH 44319",
    "addr:housenumber":"3333",
    "addr:postcode":"44319",
    "addr:street":"Manchester Rd",
    "iso:country":"US",
    "sg:address":"3333 Manchester Rd",
    "sg:city":"Akron",
    "sg:classifiers":[
        {
            "category":"Restaurant",
            "type":"Food & Drink"
        }
    ],
    "sg:menulink":"http://www.allmenus.com/oh/coventry/134460-subway/menu/",
    "sg:phone":"+1 330 644 5220",
    "sg:postcode":"44319",
    "sg:province":"OH",
    "sg:tags":[
        "american",
        "sandwich"
    ],
    "wof:name":"Subway",
    "wof:placetype":"venue"
},
  "geometry": {"coordinates":[-81.554892,41.009146],"type":"Point"}
}