{
  "type": "Feature",
  "properties": {
    "addr:full": "3250 Northwest Blvd Upper Arlington OH 43221",
    "addr:housenumber": "3250",
    "addr:postcode": "43221",
    "addr:street": "Northwest Blvd",
    "iso:country": "US",
    "sg:address": "3250 Northwest Blvd",
    "sg:city": "Upper Arlington",
    "sg:classifiers": [
      {
        "category": "Banks \u0026 Credit Unions",
        "subcategory": "Bank",
        "type": "Services"
      }
    ],
    "sg:phone": "+1 614 545 5626",
    "sg:postcode": "43221",
    "sg:province": "OH",
    "wof:name": "Union Savings Bank",
    "wof:placetype": "venue"
  },
  "geometry": {"coordinates":[-83.057256,40.024672],"type":"Point"}
}
