{
  "type": "Feature",
  "properties": {
    "addr:full": "4307 Delridge Dr Cincinnati OH 45205",
    "addr:housenumber": "4307",
    "addr:postcode": "45205",
    "addr:street": "Delridge Dr",
    "iso:country": "US",
    "sg:address": "4307 Delridge Dr",
    "sg:city": "Cincinnati",
    "sg:classifiers": [
      {
        "category": "Professional",
        "type": "Services"
      }
    ],
    "sg:phone": "+1 513 300 1189",
    "sg:postcode": "45205",
    "sg:province": "OH",
    "wof:name": "Rej and Company",
    "wof:placetype": "venue"
  },
  "geometry": {"coordinates":[-84.591774,39.104521],"type":"Point"}
}
