{
  "type": "Feature",
  "properties": {
    "addr:full": "3167 Cleveland Ave Columbus OH 43224",
    "addr:housenumber": "3167",
    "addr:postcode": "43224",
    "addr:street": "Cleveland Ave",
    "iso:country": "US",
    "sg:address": "3167 Cleveland Ave",
    "sg:city": "Columbus",
    "sg:classifiers": [
      {
        "category": "Professional",
        "subcategory": "Employment Agencies",
        "type": "Services"
      }
    ],
    "sg:phone": "+1 614 784 9331",
    "sg:postcode": "43224",
    "sg:province": "OH",
    "sg:tags": [
      "opportunity"
    ],
    "sg:website": "www.laborready.com",
    "wof:name": "Labor Ready Inc",
    "wof:placetype": "venue"
  },
  "geometry": {"coordinates":[-82.964034,40.0313],"type":"Point"}
}
