{
  "type": "Feature",
  "properties": {
    "iso:country":"US",
    "sg:address":"3167 Cleveland Ave",
    "sg:city":"Columbus",
    "sg:classifiers":[
        {
            "category":"Professional",
            "subcategory":"Employment Agencies",
            "type":"Services"
        }
    ],
    "sg:phone":"+1 614 784 9331",
    "sg:postcode":"43224",
    "sg:province":"OH",
    "sg:tags":[
        "opportunity"
    ],
    "sg:website":"www.laborready.com",
    "wof:name":"Labor Ready Inc",
    "wof:placetype":"venue"
},
  "geometry": {"coordinates":[-82.964034,40.0313],"type":"Point"}
}