{
  "type": "Feature",
  "properties": {
    "addr:full":"613 Chillicothe St Portsmouth OH 45662",
    "addr:housenumber":"613",
    "addr:postcode":"45662",
    "addr:street":"Chillicothe St",
    "iso:country":"US",
    "sg:address":"613 Chillicothe St",
    "sg:city":"Portsmouth",
    "sg:classifiers":[
        {
            "category":"Local Transit",
            "type":"Transportation"
        }
    ],
    "sg:phone":"+1 740 354 4277",
    "sg:postcode":"45662",
    "sg:province":"OH",
    "sg:tags":[
        "passenger"
    ],
    "wof:name":"Lie Ambulance Cpr Classes",
    "wof:placetype":"venue"
},
  "geometry": {"coordinates":[-82.996562,38.735506],"type":"Point"}
}