{
  "type": "Feature",
  "properties": {
    "iso:country":"US",
    "sg:address":"1322 Old River Rd",
    "sg:city":"Cleveland",
    "sg:classifiers":[
        {
            "category":"Organizations",
            "subcategory":"Membership Organization",
            "type":"Services"
        }
    ],
    "sg:phone":"+1 216 685 0880",
    "sg:postcode":"44113",
    "sg:province":"OH",
    "sg:website":"www.madd.org",
    "wof:name":"Mothers Against Drunk Driving",
    "wof:placetype":"venue"
},
  "geometry": {"coordinates":[-81.702975,41.498402],"type":"Point"}
}