{
  "type": "Feature",
  "properties": {
    "addr:full":"1265 N River Rd Warren OH 44430",
    "addr:housenumber":"1265",
    "addr:postcode":"44430",
    "addr:street":"N River Rd",
    "iso:country":"US",
    "sg:address":"1265 N River Rd",
    "sg:city":"Warren",
    "sg:classifiers":[
        {
            "category":"Manufacturing",
            "subcategory":"Motor Vehicles & Parts",
            "type":"Manufacturing & Wholesale Goods"
        }
    ],
    "sg:phone":"+1 330 373 2790",
    "sg:postcode":"44430",
    "sg:province":"OH",
    "sg:tags":[
        "automotive",
        "component",
        "mfg"
    ],
    "wof:name":"Delphi",
    "wof:placetype":"venue"
},
  "geometry": {"coordinates":[-80.868556,41.257708],"type":"Point"}
}