{
  "type": "Feature",
  "properties": {
    "addr:full": "1079 Waycross Rd Cincinnati OH 45240",
    "addr:housenumber": "1079",
    "addr:postcode": "45240",
    "addr:street": "Waycross Rd",
    "iso:country": "US",
    "sg:address": "1079 Waycross Rd",
    "sg:city": "Cincinnati",
    "sg:classifiers": [
      {
        "category": "Shopping",
        "subcategory": "Crafts \u0026 Fabrics",
        "type": "Retail Goods"
      },
      {
        "category": "Professional",
        "subcategory": "Art Services",
        "type": "Services"
      }
    ],
    "sg:phone": "+1 513 825 0099",
    "sg:postcode": "45240",
    "sg:province": "OH",
    "sg:tags": [
      "punching",
      "shop",
      "design",
      "embroidery"
    ],
    "wof:name": "Cincinnati Embroidery",
    "wof:placetype": "venue"
  },
  "geometry": {"coordinates":[-84.518123,39.283818],"type":"Point"}
}
