{
  "type": "Feature",
  "properties": {
    "iso:country":"US",
    "sg:address":"1005 Hart Rd",
    "sg:city":"Columbus",
    "sg:classifiers":[
        {
            "category":"Organizations",
            "subcategory":"Religious Organization",
            "type":"Services"
        }
    ],
    "sg:phone":"+1 614 351 0333",
    "sg:postcode":"43223",
    "sg:province":"OH",
    "sg:tags":[
        "church"
    ],
    "wof:name":"New Life Christian Fellowship",
    "wof:placetype":"venue"
},
  "geometry": {"coordinates":[-83.03191099999999,39.924161],"type":"Point"}
}