{
  "type": "Feature",
  "properties": {
    "addr:full": "213 E 7th St Uhrichsville OH 44683",
    "addr:housenumber": "213",
    "addr:postcode": "44683",
    "addr:street": "E 7Th St",
    "iso:country": "US",
    "sg:address": "213 E 7th St",
    "sg:city": "Uhrichsville",
    "sg:classifiers": [
      {
        "category": "Utilities",
        "subcategory": "Water",
        "type": "Services"
      }
    ],
    "sg:phone": "+1 740 922 9229",
    "sg:postcode": "44683",
    "sg:province": "OH",
    "sg:tags": [
      "supply"
    ],
    "wof:name": "Kevin Staten",
    "wof:placetype": "venue"
  },
  "geometry": {"coordinates":[-81.344557,40.395559],"type":"Point"}
}
