{
  "type": "Feature",
  "properties": {
    "iso:country":"US",
    "sg:address":"139 N Canfield Niles Rd",
    "sg:city":"Youngstown",
    "sg:classifiers":[
        {
            "category":"Food & Beverages",
            "subcategory":"Liquor & Beverages",
            "type":"Retail Goods"
        }
    ],
    "sg:phone":"+1 330 792 8711",
    "sg:postcode":"44515",
    "sg:province":"OH",
    "sg:tags":[
        "beer",
        "ale"
    ],
    "wof:name":"R T 46 Beer & Wine Drive Thru",
    "wof:placetype":"venue"
},
  "geometry": {"coordinates":[-80.76428199999999,41.104628],"type":"Point"}
}