{
  "type": "Feature",
  "properties": {
    "addr:full": "139 N Canfield Niles Rd Youngstown OH 44515",
    "addr:housenumber": "139",
    "addr:postcode": "44515",
    "addr:street": "N Canfield Niles Rd",
    "iso:country": "US",
    "sg:address": "139 N Canfield Niles Rd",
    "sg:city": "Youngstown",
    "sg:classifiers": [
      {
        "category": "Food \u0026 Beverages",
        "subcategory": "Liquor \u0026 Beverages",
        "type": "Retail Goods"
      }
    ],
    "sg:phone": "+1 330 792 8711",
    "sg:postcode": "44515",
    "sg:province": "OH",
    "sg:tags": [
      "beer",
      "ale"
    ],
    "wof:name": "R T 46 Beer \u0026 Wine Drive Thru",
    "wof:placetype": "venue"
  },
  "geometry": {"coordinates":[-80.764282,41.104628],"type":"Point"}
}
