{
  "type": "Feature",
  "properties": {
    "addr:full":"1135 Oak Leaf Rd Sardinia OH 45171",
    "addr:housenumber":"1135",
    "addr:postcode":"45171",
    "addr:street":"Oak Leaf Rd",
    "iso:country":"US",
    "sg:address":"1135 Oak Leaf Rd",
    "sg:city":"Sardinia",
    "sg:phone":"+1 937 446 2579",
    "sg:postcode":"45171",
    "sg:province":"OH",
    "sg:tags":[
        "farm",
        "corn",
        "soybean",
        "tobacco"
    ],
    "wof:name":"Larry Dye",
    "wof:placetype":"venue"
},
  "geometry": {"coordinates":[-83.834621,39.02486],"type":"Point"}
}