{
  "type": "Feature",
  "properties": {
    "addr:full": "38135 Colorado Ave Avon OH 44011",
    "addr:housenumber": "38135",
    "addr:postcode": "44011",
    "addr:street": "Colorado Ave",
    "iso:country": "US",
    "sg:address": "38135 Colorado Ave",
    "sg:city": "Avon",
    "sg:classifiers": [
      {
        "category": "Social Services",
        "subcategory": "Adult Care",
        "type": "Services"
      }
    ],
    "sg:phone": "+1 440 356 2594",
    "sg:postcode": "44011",
    "sg:province": "OH",
    "sg:tags": [
      "a",
      "term",
      "facility",
      "long",
      "operates",
      "as"
    ],
    "wof:name": "Adminstration Office",
    "wof:placetype": "venue"
  },
  "geometry": {"coordinates":[-82.040658,41.457371],"type":"Point"}
}
