{
  "type": "Feature",
  "properties": {
    "addr:full": "3853 Lambton Pl New Albany OH 43054",
    "addr:housenumber": "3853",
    "addr:postcode": "43054",
    "addr:street": "Lambton Pl",
    "iso:country": "US",
    "sg:address": "3853 Lambton Pl",
    "sg:city": "New Albany",
    "sg:classifiers": [
      {
        "category": "Wholesale",
        "subcategory": "Metals \u0026 Minerals",
        "type": "Manufacturing \u0026 Wholesale Goods"
      }
    ],
    "sg:phone": "+1 614 939 9300",
    "sg:postcode": "43054",
    "sg:province": "OH",
    "sg:tags": [
      "steel",
      "warehouse"
    ],
    "wof:name": "Steel Co Of America",
    "wof:placetype": "venue"
  },
  "geometry": {"coordinates":[-82.822942,40.0617],"type":"Point"}
}
