{
  "type": "Feature",
  "properties": {
    "iso:country":"US",
    "sg:address":"3400 Vine St",
    "sg:city":"Cincinnati",
    "sg:classifiers":[
        {
            "category":"Restaurant",
            "type":"Food & Drink"
        }
    ],
    "sg:menulink":"http://www.allmenus.com/oh/cincinnati/163723-skyline-chili/menu/",
    "sg:phone":"+1 513 559 7718",
    "sg:postcode":"45220",
    "sg:province":"OH",
    "sg:tags":[
        "mexican"
    ],
    "wof:name":"Skyline Chili",
    "wof:placetype":"venue"
},
  "geometry": {"coordinates":[-84.509241,39.142636],"type":"Point"}
}