{
  "type": "Feature",
  "properties": {
    "iso:country":"US",
    "sg:address":"3545 Martindale Rd NE",
    "sg:city":"Canton",
    "sg:classifiers":[
        {
            "category":"Organizations",
            "subcategory":"Religious Organization",
            "type":"Services"
        }
    ],
    "sg:phone":"+1 330 455 5010",
    "sg:postcode":"44714",
    "sg:province":"OH",
    "sg:tags":[
        "church"
    ],
    "wof:name":"Martindale Christian Fllwshp",
    "wof:placetype":"venue"
},
  "geometry": {"coordinates":[-81.360893,40.835605],"type":"Point"}
}