{
  "type": "Feature",
  "properties": {
    "iso:country":"US",
    "sg:address":"1945 E 97th St",
    "sg:city":"Cleveland",
    "sg:classifiers":[
        {
            "category":"Shopping",
            "type":"Retail Goods"
        }
    ],
    "sg:phone":"+1 216 231 6812",
    "sg:postcode":"44106",
    "sg:province":"OH",
    "sg:tags":[
        "limb",
        "artificial"
    ],
    "wof:name":"Neuro Control Corp",
    "wof:placetype":"venue"
},
  "geometry": {"coordinates":[-81.619657,41.50418],"type":"Point"}
}