{
  "type": "Feature",
  "properties": {
    "iso:country":"US",
    "sg:address":"27600 Chagrin Blvd",
    "sg:city":"Cleveland",
    "sg:classifiers":[
        {
            "category":"Shopping",
            "subcategory":"Clothing, Apparel, & Fashions",
            "type":"Retail Goods"
        }
    ],
    "sg:phone":"+1 216 514 1000",
    "sg:postcode":"44122",
    "sg:province":"OH",
    "sg:tags":[
        "furnishing"
    ],
    "wof:name":"Diamond's Men's Stores Inc",
    "wof:placetype":"venue"
},
  "geometry": {"coordinates":[-81.48431600000001,41.462259],"type":"Point"}
}