{
  "type": "Feature",
  "properties": {
    "iso:country":"US",
    "sg:address":"874 Oakland Park Ave",
    "sg:city":"Columbus",
    "sg:classifiers":[
        {
            "category":"Restaurant",
            "type":"Food & Drink"
        }
    ],
    "sg:phone":"+1 614 262 7500",
    "sg:postcode":"43224",
    "sg:province":"OH",
    "wof:name":"Fat Daddy's Pizza & Subs",
    "wof:placetype":"venue"
},
  "geometry": {"coordinates":[-82.989777,40.032622],"type":"Point"}
}