{
  "type": "Feature",
  "properties": {
    "addr:full": "874 Oakland Park Ave Columbus OH 43224",
    "addr:housenumber": "874",
    "addr:postcode": "43224",
    "addr:street": "Oakland Park Ave",
    "iso:country": "US",
    "sg:address": "874 Oakland Park Ave",
    "sg:city": "Columbus",
    "sg:classifiers": [
      {
        "category": "Restaurant",
        "type": "Food \u0026 Drink"
      }
    ],
    "sg:phone": "+1 614 262 7500",
    "sg:postcode": "43224",
    "sg:province": "OH",
    "wof:name": "Fat Daddy's Pizza \u0026 Subs",
    "wof:placetype": "venue"
  },
  "geometry": {"coordinates":[-82.989777,40.032622],"type":"Point"}
}
