{
  "type": "Feature",
  "properties": {
    "addr:full": "41 N Foster St Norwalk OH 44857",
    "addr:housenumber": "41",
    "addr:postcode": "44857",
    "addr:street": "N Foster St",
    "iso:country": "US",
    "sg:address": "41 N Foster St",
    "sg:city": "Norwalk",
    "sg:classifiers": [
      {
        "category": "Retail",
        "subcategory": "Car Wash",
        "type": "Services"
      }
    ],
    "sg:phone": "+1 419 663 1881",
    "sg:postcode": "44857",
    "sg:province": "OH",
    "sg:tags": [
      "polishing",
      "washing"
    ],
    "wof:name": "Wash \u0026 Wax",
    "wof:placetype": "venue"
  },
  "geometry": {"coordinates":[-82.614438,41.245689],"type":"Point"}
}
