{
  "type": "Feature",
  "properties": {
    "addr:full": "4385 Creek Rd Cincinnati OH 45241",
    "addr:housenumber": "4385",
    "addr:postcode": "45241",
    "addr:street": "Creek Rd",
    "iso:country": "US",
    "sg:address": "4385 Creek Rd",
    "sg:city": "Cincinnati",
    "sg:classifiers": [
      {
        "category": "Manufacturing",
        "subcategory": "Metals",
        "type": "Manufacturing \u0026 Wholesale Goods"
      }
    ],
    "sg:phone": "+1 513 793 5635",
    "sg:postcode": "45241",
    "sg:province": "OH",
    "sg:tags": [
      "mfr",
      "safe"
    ],
    "wof:name": "Cincy Safe Company",
    "wof:placetype": "venue"
  },
  "geometry": {"coordinates":[-84.388977,39.260473],"type":"Point"}
}
