{
  "type": "Feature",
  "properties": {
    "iso:country":"US",
    "sg:address":"176 N Park Ave",
    "sg:city":"Warren",
    "sg:classifiers":[
        {
            "category":"Restaurant",
            "type":"Food & Drink"
        }
    ],
    "sg:phone":"+1 330 372 4747",
    "sg:postcode":"44481",
    "sg:province":"OH",
    "wof:name":"Blue Iris Cafe",
    "wof:placetype":"venue"
},
  "geometry": {"coordinates":[-80.817931,41.236392],"type":"Point"}
}