{
  "type": "Feature",
  "properties": {
    "iso:country":"US",
    "sg:address":"7038 Blue Ash Rd",
    "sg:city":"Cincinnati",
    "sg:classifiers":[
        {
            "category":"Wholesale",
            "subcategory":"Electrical",
            "type":"Manufacturing & Wholesale Goods"
        }
    ],
    "sg:phone":"+1 513 984 3500",
    "sg:postcode":"45236",
    "sg:province":"OH",
    "sg:tags":[
        "alarm",
        "burglar",
        "system"
    ],
    "sg:website":"www.vectorsecurity.com",
    "wof:name":"Vector Security",
    "wof:placetype":"venue"
},
  "geometry": {"coordinates":[-84.39963400000001,39.197604],"type":"Point"}
}