{
  "type": "Feature",
  "properties": {
    "iso:country":"US",
    "sg:address":"12212 Sprecher Ave",
    "sg:city":"Cleveland",
    "sg:classifiers":[
        {
            "category":"Manufacturing",
            "subcategory":"Tools & Machinery",
            "type":"Manufacturing & Wholesale Goods"
        }
    ],
    "sg:phone":"+1 216 267 4644",
    "sg:postcode":"44135",
    "sg:province":"OH",
    "sg:tags":[
        "machine",
        "shop",
        "job"
    ],
    "wof:name":"Hafco Case Inc",
    "wof:placetype":"venue"
},
  "geometry": {"coordinates":[-81.77601900000001,41.424051],"type":"Point"}
}