{
  "type": "Feature",
  "properties": {
    "addr:full": "304 Donna Dr Camden IN 45311",
    "addr:housenumber": "304",
    "addr:postcode": "45311",
    "addr:street": "Donna Dr",
    "iso:country": "US",
    "sg:address": "304 Donna Dr",
    "sg:city": "Camden",
    "sg:classifiers": [
      {
        "category": "Building \u0026 Trades",
        "subcategory": "Construction",
        "type": "Services"
      }
    ],
    "sg:phone": "+1 937 452 3071",
    "sg:postcode": "45311",
    "sg:province": "IN",
    "sg:tags": [
      "remodeling"
    ],
    "wof:name": "R T Hall Home Improvements",
    "wof:placetype": "venue"
  },
  "geometry": {"coordinates":[-84.645725,39.637928],"type":"Point"}
}
