{
  "type": "Feature",
  "properties": {
    "iso:country":"US",
    "sg:address":"3962 Brown Park Dr",
    "sg:city":"Hilliard",
    "sg:classifiers":[
        {
            "category":"Banks & Credit Unions",
            "subcategory":"Bank",
            "type":"Services"
        }
    ],
    "sg:phone":"+1 614 921 9129",
    "sg:postcode":"43026",
    "sg:province":"OH",
    "sg:tags":[
        "mortgage",
        "loan",
        "broker",
        "real estate"
    ],
    "wof:name":"American Eagle Funding",
    "wof:placetype":"venue"
},
  "geometry": {"coordinates":[-83.136383,40.033128],"type":"Point"}
}