{
  "type": "Feature",
  "properties": {
    "addr:full":"5117 Tuscarawas St W Canton OH 44708",
    "addr:housenumber":"5117",
    "addr:postcode":"44708",
    "addr:street":"Tuscarawas St W",
    "iso:country":"US",
    "sg:address":"5117 Tuscarawas St W",
    "sg:city":"Canton",
    "sg:classifiers":[
        {
            "category":"Food & Beverages",
            "subcategory":"Groceries & Convenience Stores",
            "type":"Retail Goods"
        }
    ],
    "sg:phone":"+1 330 000 1111",
    "sg:postcode":"44708",
    "sg:province":"OH",
    "sg:tags":[
        "grocer"
    ],
    "wof:name":"Aldi",
    "wof:placetype":"venue"
},
  "geometry": {"coordinates":[-81.448173,40.792321],"type":"Point"}
}