{
  "type": "Feature",
  "properties": {
    "addr:full":"1203 S Main St Mt Vernon OH 43050",
    "addr:housenumber":"1203",
    "addr:postcode":"43050",
    "addr:street":"S Main St",
    "iso:country":"US",
    "sg:address":"1203 S Main St",
    "sg:city":"Mt Vernon",
    "sg:classifiers":[
        {
            "category":"Freight",
            "type":"Transportation"
        }
    ],
    "sg:phone":"+1 740 393 0755",
    "sg:postcode":"43050",
    "sg:province":"OH",
    "sg:tags":[
        "commercial",
        "storage",
        "general"
    ],
    "wof:name":"Affordable Mini Storage",
    "wof:placetype":"venue"
},
  "geometry": {"coordinates":[-82.48808,40.37195],"type":"Point"}
}