{
  "type": "Feature",
  "properties": {
    "iso:country":"US",
    "sg:address":"131 N 5th St",
    "sg:city":"Newark",
    "sg:classifiers":[
        {
            "category":"Shopping",
            "subcategory":"Gifts & Souvenirs",
            "type":"Retail Goods"
        }
    ],
    "sg:phone":"+1 740 349 0224",
    "sg:postcode":"43055",
    "sg:province":"OH",
    "wof:name":"Dianes Designs & Gifts",
    "wof:placetype":"venue"
},
  "geometry": {"coordinates":[-82.40728799999999,40.059586],"type":"Point"}
}