{
  "type": "Feature",
  "properties": {
    "addr:full": "6605 River Styx Rd Medina OH 44256",
    "addr:housenumber": "6605",
    "addr:postcode": "44256",
    "addr:street": "River Styx Rd",
    "iso:country": "US",
    "sg:address": "6605 River Styx Rd",
    "sg:city": "Medina",
    "sg:classifiers": [
      {
        "category": "Professional",
        "type": "Services"
      }
    ],
    "sg:phone": "+1 330 725 5456",
    "sg:postcode": "44256",
    "sg:province": "OH",
    "wof:name": "John V Curci \u0026 Deidree An",
    "wof:placetype": "venue"
  },
  "geometry": {"coordinates":[-81.803749,41.094156],"type":"Point"}
}
