{
  "type": "Feature",
  "properties": {
    "iso:country":"US",
    "sg:address":"6605 River Styx Rd",
    "sg:city":"Medina",
    "sg:classifiers":[
        {
            "category":"Professional",
            "type":"Services"
        }
    ],
    "sg:phone":"+1 330 725 5456",
    "sg:postcode":"44256",
    "sg:province":"OH",
    "wof:name":"John V Curci & Deidree An",
    "wof:placetype":"venue"
},
  "geometry": {"coordinates":[-81.803749,41.094156],"type":"Point"}
}