{
  "type": "Feature",
  "properties": {
    "addr:full": "2255 Kimberly Pkwy E Columbus OH 43232",
    "addr:housenumber": "2255",
    "addr:postcode": "43232",
    "addr:street": "Kimberly Pkwy E",
    "iso:country": "US",
    "sg:address": "2255 Kimberly Pkwy E",
    "sg:city": "Columbus",
    "sg:classifiers": [
      {
        "category": "Professional",
        "subcategory": "Lawyer \u0026 Legal Services",
        "type": "Services"
      }
    ],
    "sg:phone": "+1 614 751 9496",
    "sg:postcode": "43232",
    "sg:province": "OH",
    "sg:tags": [
      "planning",
      "estate"
    ],
    "wof:name": "His Legacy Group",
    "wof:placetype": "venue"
  },
  "geometry": {"coordinates":[-82.883225,39.928063],"type":"Point"}
}
