{
  "type": "Feature",
  "properties": {
    "iso:country":"US",
    "sg:address":"4327 Cleveland Ave NW",
    "sg:city":"Canton",
    "sg:classifiers":[
        {
            "category":"Personal",
            "subcategory":"Beauty Salon",
            "type":"Services"
        }
    ],
    "sg:phone":"+1 330 493 1505",
    "sg:postcode":"44709",
    "sg:province":"OH",
    "sg:tags":[
        "shop",
        "merchandise"
    ],
    "wof:name":"Designer Hair Studios",
    "wof:placetype":"venue"
},
  "geometry": {"coordinates":[-81.391836,40.845124],"type":"Point"}
}