{
  "type": "Feature",
  "properties": {
    "iso:country":"US",
    "sg:address":"5409 W 3rd St",
    "sg:city":"Dayton",
    "sg:classifiers":[
        {
            "category":"Shopping",
            "subcategory":"Clothing, Apparel, & Fashions",
            "type":"Retail Goods"
        }
    ],
    "sg:phone":"+1 937 262 9599",
    "sg:postcode":"45427",
    "sg:province":"OH",
    "sg:tags":[
        "jewelry",
        "costume",
        "gold",
        "wear"
    ],
    "wof:name":"Melissas Fashion Fare",
    "wof:placetype":"venue"
},
  "geometry": {"coordinates":[-84.276194,39.746672],"type":"Point"}
}