{
  "type": "Feature",
  "properties": {
    "addr:full": "618 High Ave NW Canton OH 44703",
    "addr:housenumber": "618",
    "addr:postcode": "44703",
    "addr:street": "High Ave Nw",
    "iso:country": "US",
    "sg:address": "618 High Ave NW",
    "sg:city": "Canton",
    "sg:classifiers": [
      {
        "category": "Organizations",
        "subcategory": "Labor Organization",
        "type": "Services"
      }
    ],
    "sg:phone": "+1 330 452 2244",
    "sg:postcode": "44703",
    "sg:province": "OH",
    "sg:tags": [
      "union"
    ],
    "wof:name": "International Brotherhood",
    "wof:placetype": "venue"
  },
  "geometry": {"coordinates":[-81.378812,40.803452],"type":"Point"}
}
