{
  "type": "Feature",
  "properties": {
    "iso:country":"US",
    "sg:address":"2458 Straight St",
    "sg:city":"Batavia",
    "sg:classifiers":[
        {
            "category":"Building & Trades",
            "subcategory":"Construction",
            "type":"Services"
        }
    ],
    "sg:phone":"+1 513 732 3776",
    "sg:postcode":"45103",
    "sg:province":"OH",
    "sg:tags":[
        "concrete",
        "contractor"
    ],
    "wof:name":"AK Concrete Cutng Systems LLC",
    "wof:placetype":"venue"
},
  "geometry": {"coordinates":[-84.220604,39.086823],"type":"Point"}
}