{
  "type": "Feature",
  "properties": {
    "iso:country":"US",
    "sg:address":"3895 Woodridge Blvd",
    "sg:city":"Fairfield",
    "sg:classifiers":[
        {
            "category":"Building & Trades",
            "subcategory":"Construction",
            "type":"Services"
        }
    ],
    "sg:phone":"+1 513 860 2800",
    "sg:postcode":"45014",
    "sg:province":"OH",
    "sg:tags":[
        "house"
    ],
    "wof:name":"Dallis Homes LLC",
    "wof:placetype":"venue"
},
  "geometry": {"coordinates":[-84.490385,39.306827],"type":"Point"}
}