{
  "type": "Feature",
  "properties": {
    "addr:full":"34 S 3rd St Columbus OH 43215",
    "addr:housenumber":"34",
    "addr:postcode":"43215",
    "addr:street":"S 3Rd St",
    "iso:country":"US",
    "sg:address":"34 S 3rd St",
    "sg:city":"Columbus",
    "sg:classifiers":[
        {
            "category":"Education",
            "subcategory":"Library",
            "type":"Public Place"
        }
    ],
    "sg:phone":"+1 614 461 5039",
    "sg:postcode":"43215",
    "sg:province":"OH",
    "sg:tags":[
        "special",
        "interest"
    ],
    "sg:website":"www.dispatch.com",
    "wof:name":"Columbus Dispatch Library",
    "wof:placetype":"venue"
},
  "geometry": {"coordinates":[-82.99752599999999,39.960612],"type":"Point"}
}