{
  "type": "Feature",
  "properties": {
    "iso:country":"US",
    "sg:address":"1898 State Rte 89",
    "sg:city":"Jeromesville",
    "sg:classifiers":[
        {
            "category":"Building & Trades",
            "subcategory":"Construction",
            "type":"Services"
        }
    ],
    "sg:phone":"+1 419 368 1344",
    "sg:postcode":"44840",
    "sg:province":"OH",
    "sg:tags":[
        "house"
    ],
    "wof:name":"Summit Homes",
    "wof:placetype":"venue"
},
  "geometry": {"coordinates":[-82.18485,40.786158],"type":"Point"}
}