{
  "type": "Feature",
  "properties": {
    "iso:country":"US",
    "sg:address":"4794 Madison Rd",
    "sg:city":"Cincinnati",
    "sg:classifiers":[
        {
            "category":"Retail",
            "subcategory":"Auto Repair",
            "type":"Services"
        }
    ],
    "sg:phone":"+1 513 841 1111",
    "sg:postcode":"45227",
    "sg:province":"OH",
    "sg:tags":[
        "repairing",
        "automobile"
    ],
    "wof:name":"R & R Transmissions",
    "wof:placetype":"venue"
},
  "geometry": {"coordinates":[-84.41412699999999,39.161411],"type":"Point"}
}