{
  "type": "Feature",
  "properties": {
    "addr:full": "4794 Madison Rd Cincinnati OH 45227",
    "addr:housenumber": "4794",
    "addr:postcode": "45227",
    "addr:street": "Madison Rd",
    "iso:country": "US",
    "sg:address": "4794 Madison Rd",
    "sg:city": "Cincinnati",
    "sg:classifiers": [
      {
        "category": "Retail",
        "subcategory": "Auto Repair",
        "type": "Services"
      }
    ],
    "sg:phone": "+1 513 841 1111",
    "sg:postcode": "45227",
    "sg:province": "OH",
    "sg:tags": [
      "repairing",
      "automobile"
    ],
    "wof:name": "R \u0026 R Transmissions",
    "wof:placetype": "venue"
  },
  "geometry": {"coordinates":[-84.414127,39.161411],"type":"Point"}
}
