{
  "type": "Feature",
  "properties": {
    "addr:full":"7013 State Rte 199 Upper Sandusky OH 43351",
    "addr:housenumber":"7013",
    "addr:postcode":"43351",
    "addr:street":"State Rte 199 Upper",
    "iso:country":"US",
    "sg:address":"7013 State Rte 199",
    "sg:city":"Upper Sandusky",
    "sg:classifiers":[
        {
            "category":"Manufacturing",
            "subcategory":"Tools & Machinery",
            "type":"Manufacturing & Wholesale Goods"
        }
    ],
    "sg:phone":"+1 419 294 3814",
    "sg:postcode":"43351",
    "sg:province":"OH",
    "sg:tags":[
        "mfg",
        "industrial",
        "mach",
        "welding"
    ],
    "wof:name":"Schmidt Machine Co/AGCO Dealer",
    "wof:placetype":"venue"
},
  "geometry": {"coordinates":[-83.3308,40.890606],"type":"Point"}
}