{
  "type": "Feature",
  "properties": {
    "addr:full":"3905 Alexander Rd Pemberville OH 43450",
    "addr:housenumber":"3905",
    "addr:postcode":"43450",
    "addr:street":"Alexander Rd",
    "iso:country":"US",
    "sg:address":"3905 Alexander Rd",
    "sg:city":"Pemberville",
    "sg:classifiers":[
        {
            "category":"Farming",
            "subcategory":"Livestock Farm",
            "type":"Manufacturing & Wholesale Goods"
        }
    ],
    "sg:phone":"+1 419 287 3831",
    "sg:postcode":"43450",
    "sg:province":"OH",
    "sg:tags":[
        "hog",
        "lot"
    ],
    "wof:name":"David Gerald Bruning",
    "wof:placetype":"venue"
},
  "geometry": {"coordinates":[-83.472291,41.399142],"type":"Point"}
}