{
  "type": "Feature",
  "properties": {
    "addr:full": "9354 Mentor Ave Mentor OH 44060",
    "addr:housenumber": "9354",
    "addr:postcode": "44060",
    "addr:street": "Mentor Ave",
    "iso:country": "US",
    "sg:address": "9354 Mentor Ave",
    "sg:city": "Mentor",
    "sg:classifiers": [
      {
        "category": "Government",
        "subcategory": "Office",
        "type": "Public Place"
      }
    ],
    "sg:phone": "+1 440 974 8506",
    "sg:postcode": "44060",
    "sg:province": "OH",
    "sg:tags": [
      "county"
    ],
    "wof:name": "Lake County Assn Of Realtors",
    "wof:placetype": "venue"
  },
  "geometry": {"coordinates":[-81.306741,41.678167],"type":"Point"}
}
