{
  "type": "Feature",
  "properties": {
    "addr:full":"2750 Enslin St Cincinnati OH 45225",
    "addr:housenumber":"2750",
    "addr:postcode":"45225",
    "addr:street":"Enslin St",
    "iso:country":"US",
    "sg:address":"2750 Enslin St",
    "sg:city":"Cincinnati",
    "sg:classifiers":[
        {
            "category":"Building & Trades",
            "subcategory":"Construction",
            "type":"Services"
        }
    ],
    "sg:phone":"+1 513 751 2408",
    "sg:postcode":"45225",
    "sg:province":"OH",
    "sg:tags":[
        "nonresidential"
    ],
    "wof:name":"Kwb Inc",
    "wof:placetype":"venue"
},
  "geometry": {"coordinates":[-84.52775200000001,39.131486],"type":"Point"}
}