{
  "type": "Feature",
  "properties": {
    "addr:full": "4226 Hazelton Etna Rd Johnstown OH 43031",
    "addr:housenumber": "4226",
    "addr:postcode": "43031",
    "addr:street": "Hazelton Etna Rd",
    "iso:country": "US",
    "sg:address": "4226 Hazelton Etna Rd",
    "sg:city": "Johnstown",
    "sg:classifiers": [
      {
        "category": "Retail",
        "subcategory": "Animal Services",
        "type": "Services"
      }
    ],
    "sg:phone": "+1 740 967 6171",
    "sg:postcode": "43031",
    "sg:province": "OH",
    "wof:name": "Sunny-Hill Pet Care Center",
    "wof:placetype": "venue"
  },
  "geometry": {"coordinates":[-82.661141,40.109825],"type":"Point"}
}
