{
  "type": "Feature",
  "properties": {
    "iso:country":"US",
    "sg:address":"7083 Bittersweet Ln",
    "sg:city":"Okeana",
    "sg:classifiers":[
        {
            "category":"Wholesale",
            "subcategory":"Machinery & Supplies",
            "type":"Manufacturing & Wholesale Goods"
        }
    ],
    "sg:phone":"+1 513 738 4300",
    "sg:postcode":"45053",
    "sg:province":"IN",
    "sg:tags":[
        "equipment",
        "industrial"
    ],
    "wof:name":"Esco",
    "wof:placetype":"venue"
},
  "geometry": {"coordinates":[-84.784299,39.354405],"type":"Point"}
}