{
  "type": "Feature",
  "properties": {
    "iso:country":"US",
    "sg:address":"1425 Mount Vernon Rd",
    "sg:city":"Newark",
    "sg:classifiers":[
        {
            "category":"Autos & Motor Vehicles",
            "subcategory":"Automobile Sales",
            "type":"Retail Goods"
        }
    ],
    "sg:phone":"+1 740 366 7373",
    "sg:postcode":"43055",
    "sg:province":"OH",
    "sg:tags":[
        "car",
        "dealer"
    ],
    "wof:name":"Chesrown Oldsmobile-Cadillac",
    "wof:placetype":"venue"
},
  "geometry": {"coordinates":[-82.422797,40.096485],"type":"Point"}
}