{
  "type": "Feature",
  "properties": {
    "addr:full":"13738 Settlement Acres Dr Cleveland OH 44142",
    "addr:housenumber":"13738",
    "addr:postcode":"44142",
    "addr:street":"Settlement Acres Dr",
    "iso:country":"US",
    "sg:address":"13738 Settlement Acres Dr",
    "sg:city":"Cleveland",
    "sg:classifiers":[
        {
            "category":"Real Estate",
            "subcategory":"Real Estate Agent",
            "type":"Services"
        }
    ],
    "sg:phone":"+1 216 676 8928",
    "sg:postcode":"44142",
    "sg:province":"OH",
    "wof:name":"B Sure",
    "wof:placetype":"venue"
},
  "geometry": {"coordinates":[-81.789963,41.393934],"type":"Point"}
}