{
  "type": "Feature",
  "properties": {
    "iso:country":"US",
    "sg:address":"2010 E 224th St",
    "sg:city":"Euclid",
    "sg:classifiers":[
        {
            "category":"Retail",
            "subcategory":"Laundry & Dry Cleaning",
            "type":"Services"
        }
    ],
    "sg:phone":"+1 216 481 6085",
    "sg:postcode":"44117",
    "sg:province":"OH",
    "sg:tags":[
        "cleaner",
        "rug",
        "carpet"
    ],
    "wof:name":"Rjl Carpet Cleaning",
    "wof:placetype":"venue"
},
  "geometry": {"coordinates":[-81.52568599999999,41.565517],"type":"Point"}
}