{
  "type": "Feature",
  "properties": {
    "addr:full": "94 Beech Ave Northfield OH 44067",
    "addr:housenumber": "94",
    "addr:postcode": "44067",
    "addr:street": "Beech Ave",
    "iso:country": "US",
    "sg:address": "94 Beech Ave",
    "sg:city": "Northfield",
    "sg:classifiers": [
      {
        "category": "Professional",
        "subcategory": "Art Services",
        "type": "Services"
      }
    ],
    "sg:phone": "+1 330 908 0920",
    "sg:postcode": "44067",
    "sg:province": "OH",
    "sg:tags": [
      "graphic",
      "designer"
    ],
    "wof:name": "Moore Graphics \u0026 Design",
    "wof:placetype": "venue"
  },
  "geometry": {"coordinates":[-81.531265,41.342501],"type":"Point"}
}
