{
  "type": "Feature",
  "properties": {
    "iso:country":"US",
    "sg:address":"94 Beech Ave",
    "sg:city":"Northfield",
    "sg:classifiers":[
        {
            "category":"Professional",
            "subcategory":"Art Services",
            "type":"Services"
        }
    ],
    "sg:phone":"+1 330 908 0920",
    "sg:postcode":"44067",
    "sg:province":"OH",
    "sg:tags":[
        "graphic",
        "designer"
    ],
    "wof:name":"Moore Graphics & Design",
    "wof:placetype":"venue"
},
  "geometry": {"coordinates":[-81.531265,41.342501],"type":"Point"}
}