{
  "type": "Feature",
  "properties": {
    "addr:full":"3061 Shadycrest Dr Cincinnati OH 45239",
    "addr:housenumber":"3061",
    "addr:postcode":"45239",
    "addr:street":"Shadycrest Dr",
    "iso:country":"US",
    "sg:address":"3061 Shadycrest Dr",
    "sg:city":"Cincinnati",
    "sg:classifiers":[
        {
            "category":"Professional",
            "subcategory":"Engineering",
            "type":"Services"
        }
    ],
    "sg:phone":"+1 513 931 1500",
    "sg:postcode":"45239",
    "sg:province":"OH",
    "sg:tags":[
        "lighting",
        "engineer"
    ],
    "wof:name":"J K Svc",
    "wof:placetype":"venue"
},
  "geometry": {"coordinates":[-84.584722,39.21777],"type":"Point"}
}