{
  "type": "Feature",
  "properties": {
    "iso:country":"US",
    "sg:address":"600 Bluebonnet Dr",
    "sg:city":"Findlay",
    "sg:classifiers":[
        {
            "category":"Health Services",
            "subcategory":"Health Practitioner",
            "type":"Services"
        }
    ],
    "sg:phone":"+1 419 422 0015",
    "sg:postcode":"45840",
    "sg:province":"OH",
    "sg:tags":[
        "therapist",
        "physical"
    ],
    "wof:name":"Crawford County Physcl Therapy",
    "wof:placetype":"venue"
},
  "geometry": {"coordinates":[-83.655137,41.007145],"type":"Point"}
}