{
  "type": "Feature",
  "properties": {
    "addr:full": "601 Tuxedo Ave Cleveland OH 44131",
    "addr:housenumber": "601",
    "addr:postcode": "44131",
    "addr:street": "Tuxedo Ave",
    "iso:country": "US",
    "sg:address": "601 Tuxedo Ave",
    "sg:city": "Cleveland",
    "sg:classifiers": [
      {
        "category": "Building \u0026 Trades",
        "subcategory": "Plumbing",
        "type": "Services"
      }
    ],
    "sg:phone": "+1 216 398 6180",
    "sg:postcode": "44131",
    "sg:province": "OH",
    "sg:tags": [
      "mechanical",
      "contractor"
    ],
    "wof:name": "Brainmasters Co",
    "wof:placetype": "venue"
  },
  "geometry": {"coordinates":[-81.683844,41.416491],"type":"Point"}
}
