{
  "type": "Feature",
  "properties": {
    "iso:country":"US",
    "sg:address":"601 Tuxedo Ave",
    "sg:city":"Cleveland",
    "sg:classifiers":[
        {
            "category":"Building & Trades",
            "subcategory":"Plumbing",
            "type":"Services"
        }
    ],
    "sg:phone":"+1 216 398 6180",
    "sg:postcode":"44131",
    "sg:province":"OH",
    "sg:tags":[
        "mechanical",
        "contractor"
    ],
    "wof:name":"Brainmasters Co",
    "wof:placetype":"venue"
},
  "geometry": {"coordinates":[-81.68384399999999,41.416491],"type":"Point"}
}