{
  "type": "Feature",
  "properties": {
    "addr:full": "132 Akron Rd Wadsworth OH 44281",
    "addr:housenumber": "132",
    "addr:postcode": "44281",
    "addr:street": "Akron Rd",
    "iso:country": "US",
    "sg:address": "132 Akron Rd",
    "sg:city": "Wadsworth",
    "sg:classifiers": [
      {
        "category": "Restaurant",
        "type": "Food \u0026 Drink"
      }
    ],
    "sg:menulink": "http://www.allmenus.com/oh/wadsworth/83342-papa-johns-pizza/menu/",
    "sg:phone": "+1 330 334 4949",
    "sg:postcode": "44281",
    "sg:province": "OH",
    "sg:tags": [
      "american",
      "pizza"
    ],
    "wof:name": "Papa John's Pizza",
    "wof:placetype": "venue"
  },
  "geometry": {"coordinates":[-81.722938,41.03777],"type":"Point"}
}
