{
  "type": "Feature",
  "properties": {
    "addr:full": "410 N Tuscarawas Ave Dover OH 44622",
    "addr:housenumber": "410",
    "addr:postcode": "44622",
    "addr:street": "N Tuscarawas Ave",
    "iso:country": "US",
    "sg:address": "410 N Tuscarawas Ave",
    "sg:city": "Dover",
    "sg:classifiers": [
      {
        "category": "Wholesale",
        "subcategory": "Machinery \u0026 Supplies",
        "type": "Manufacturing \u0026 Wholesale Goods"
      }
    ],
    "sg:phone": "+1 330 343 6600",
    "sg:postcode": "44622",
    "sg:province": "OH",
    "sg:tags": [
      "equipment",
      "steam",
      "cleaning"
    ],
    "wof:name": "Chempure Products Corp",
    "wof:placetype": "venue"
  },
  "geometry": {"coordinates":[-81.48133,40.521629],"type":"Point"}
}
