{
  "type": "Feature",
  "properties": {
    "addr:full": "786 Battalion Pl Galloway OH 43119",
    "addr:postcode": "43119",
    "addr:street": "Battalion Pl",
    "iso:country": "US",
    "sg:address": "786 Battalion Pl",
    "sg:city": "Galloway",
    "sg:classifiers": [
      {
        "category": "Wholesale",
        "subcategory": "Groceries",
        "type": "Manufacturing \u0026 Wholesale Goods"
      }
    ],
    "sg:phone": "+1 614 878 7370",
    "sg:postcode": "43119",
    "sg:province": "OH",
    "sg:tags": [
      "beverage"
    ],
    "wof:name": "Flow N Go Beverage",
    "wof:placetype": "venue"
  },
  "geometry": {"coordinates":[-83.230383,39.964687],"type":"Point"}
}
