{
  "type": "Feature",
  "properties": {
    "iso:country":"US",
    "sg:address":"600 Wrights Ave",
    "sg:city":"Conneaut",
    "sg:classifiers":[
        {
            "category":"Shopping",
            "type":"Retail Goods"
        }
    ],
    "sg:phone":"+1 440 593 6350",
    "sg:postcode":"44030",
    "sg:province":"OH",
    "sg:tags":[
        "merchandise"
    ],
    "wof:name":"Taylor Resources Ltd",
    "wof:placetype":"venue"
},
  "geometry": {"coordinates":[-80.560693,41.953327],"type":"Point"}
}