{
  "type": "Feature",
  "properties": {
    "iso:country":"US",
    "sg:address":"531 E Indianola Ave",
    "sg:city":"Youngstown",
    "sg:classifiers":[
        {
            "category":"Manufacturing",
            "subcategory":"Food",
            "type":"Manufacturing & Wholesale Goods"
        }
    ],
    "sg:phone":"+1 330 783 1982",
    "sg:postcode":"44502",
    "sg:province":"OH",
    "sg:tags":[
        "bottler"
    ],
    "wof:name":"Coca-Cola Bottling Co",
    "wof:placetype":"venue"
},
  "geometry": {"coordinates":[-80.64458999999999,41.072639],"type":"Point"}
}