{
  "type": "Feature",
  "properties": {
    "addr:full":"1408 Bartley Rd Dayton OH 45414",
    "addr:housenumber":"1408",
    "addr:postcode":"45414",
    "addr:street":"Bartley Rd",
    "iso:country":"US",
    "sg:address":"1408 Bartley Rd",
    "sg:city":"Dayton",
    "sg:classifiers":[
        {
            "category":"Professional",
            "type":"Services"
        }
    ],
    "sg:phone":"+1 937 454 0282",
    "sg:postcode":"45414",
    "sg:province":"OH",
    "wof:name":"Newberry Timothy R and",
    "wof:placetype":"venue"
},
  "geometry": {"coordinates":[-84.206022,39.828598],"type":"Point"}
}