{
  "type": "Feature",
  "properties": {
    "addr:full": "20 S Main St Mansfield OH 44902",
    "addr:housenumber": "20",
    "addr:postcode": "44902",
    "addr:street": "S Main St",
    "iso:country": "US",
    "sg:address": "20 S Main St",
    "sg:city": "Mansfield",
    "sg:classifiers": [
      {
        "category": "Bars \u0026 Pubs",
        "type": "Food \u0026 Drink"
      }
    ],
    "sg:phone": "+1 419 524 8863",
    "sg:postcode": "44902",
    "sg:province": "OH",
    "wof:name": "Jimmy's Lounge",
    "wof:placetype": "venue"
  },
  "geometry": {"coordinates":[-82.515525,40.758128],"type":"Point"}
}
