{
  "type": "Feature",
  "properties": {
    "iso:country":"US",
    "sg:address":"20 S Main St",
    "sg:city":"Mansfield",
    "sg:classifiers":[
        {
            "category":"Bars & Pubs",
            "type":"Food & Drink"
        }
    ],
    "sg:phone":"+1 419 524 8863",
    "sg:postcode":"44902",
    "sg:province":"OH",
    "wof:name":"Jimmy's Lounge",
    "wof:placetype":"venue"
},
  "geometry": {"coordinates":[-82.515525,40.758128],"type":"Point"}
}