{
  "type": "Feature",
  "properties": {
    "addr:full": "1716 Woodman Dr Dayton OH 45420",
    "addr:housenumber": "1716",
    "addr:postcode": "45420",
    "addr:street": "Woodman Dr",
    "iso:country": "US",
    "sg:address": "1716 Woodman Dr",
    "sg:city": "Dayton",
    "sg:classifiers": [
      {
        "category": "Shopping",
        "subcategory": "Discount \u0026 Variety Stores",
        "type": "Retail Goods"
      }
    ],
    "sg:phone": "+1 937 252 4839",
    "sg:postcode": "45420",
    "sg:province": "OH",
    "wof:name": "Dollar General",
    "wof:placetype": "venue"
  },
  "geometry": {"coordinates":[-84.122293,39.727179],"type":"Point"}
}
