{
  "type": "Feature",
  "properties": {
    "addr:full":"215 N Summit St Toledo OH 43604",
    "addr:housenumber":"215",
    "addr:postcode":"43604",
    "addr:street":"N Summit St",
    "iso:country":"US",
    "sg:address":"215 N Summit St",
    "sg:city":"Toledo",
    "sg:classifiers":[
        {
            "category":"Social Services",
            "type":"Services"
        }
    ],
    "sg:phone":"+1 419 259 6432",
    "sg:postcode":"43604",
    "sg:province":"OH",
    "wof:name":"US Probation",
    "wof:placetype":"venue"
},
  "geometry": {"coordinates":[-83.53401100000001,41.650672],"type":"Point"}
}