{
  "type": "Feature",
  "properties": {
    "iso:country":"US",
    "sg:address":"2422 Millborne Rd",
    "sg:city":"Wooster",
    "sg:classifiers":[
        {
            "category":"Shopping",
            "type":"Retail Goods"
        }
    ],
    "sg:phone":"+1 330 683 0775",
    "sg:postcode":"44691",
    "sg:province":"OH",
    "sg:tags":[
        "trophy",
        "medal",
        "merchandise",
        "award"
    ],
    "wof:name":"P S Trophy",
    "wof:placetype":"venue"
},
  "geometry": {"coordinates":[-81.83044099999999,40.831426],"type":"Point"}
}