{
  "type": "Feature",
  "properties": {
    "addr:full": "2422 Millborne Rd Wooster OH 44691",
    "addr:housenumber": "2422",
    "addr:postcode": "44691",
    "addr:street": "Millborne Rd",
    "iso:country": "US",
    "sg:address": "2422 Millborne Rd",
    "sg:city": "Wooster",
    "sg:classifiers": [
      {
        "category": "Shopping",
        "type": "Retail Goods"
      }
    ],
    "sg:phone": "+1 330 683 0775",
    "sg:postcode": "44691",
    "sg:province": "OH",
    "sg:tags": [
      "trophy",
      "medal",
      "merchandise",
      "award"
    ],
    "wof:name": "P S Trophy",
    "wof:placetype": "venue"
  },
  "geometry": {"coordinates":[-81.830441,40.831426],"type":"Point"}
}
