{
  "type": "Feature",
  "properties": {
    "iso:country":"US",
    "sg:address":"1703 Milington Way",
    "sg:city":"Marysville",
    "sg:classifiers":[
        {
            "category":"Building & Trades",
            "subcategory":"Construction",
            "type":"Services"
        }
    ],
    "sg:phone":"+1 937 644 2699",
    "sg:postcode":"43040",
    "sg:province":"OH",
    "sg:tags":[
        "contractor"
    ],
    "wof:name":"Ross Brothers Drywall",
    "wof:placetype":"venue"
},
  "geometry": {"coordinates":[-83.394335,40.214813],"type":"Point"}
}