{
  "type": "Feature",
  "properties": {
    "addr:full": "1703 Milington Way Marysville OH 43040",
    "addr:housenumber": "1703",
    "addr:postcode": "43040",
    "addr:street": "Milington Way",
    "iso:country": "US",
    "sg:address": "1703 Milington Way",
    "sg:city": "Marysville",
    "sg:classifiers": [
      {
        "category": "Building \u0026 Trades",
        "subcategory": "Construction",
        "type": "Services"
      }
    ],
    "sg:phone": "+1 937 644 2699",
    "sg:postcode": "43040",
    "sg:province": "OH",
    "sg:tags": [
      "contractor"
    ],
    "wof:name": "Ross Brothers Drywall",
    "wof:placetype": "venue"
  },
  "geometry": {"coordinates":[-83.394335,40.214813],"type":"Point"}
}
