{
  "type": "Feature",
  "properties": {
    "addr:full": "14665 Gaskill Dr NE Alliance OH 44601",
    "addr:housenumber": "14665",
    "addr:postcode": "44601",
    "addr:street": "Gaskill Dr Ne",
    "iso:country": "US",
    "sg:address": "14665 Gaskill Dr NE",
    "sg:city": "Alliance",
    "sg:classifiers": [
      {
        "category": "Manufacturing",
        "subcategory": "Tools \u0026 Machinery",
        "type": "Manufacturing \u0026 Wholesale Goods"
      }
    ],
    "sg:phone": "+1 330 823 0812",
    "sg:postcode": "44601",
    "sg:province": "OH",
    "sg:tags": [
      "mfg"
    ],
    "wof:name": "Perma Industries",
    "wof:placetype": "venue"
  },
  "geometry": {"coordinates":[-81.116259,40.940402],"type":"Point"}
}
