{
  "type": "Feature",
  "properties": {
    "iso:country":"US",
    "sg:address":"14665 Gaskill Dr NE",
    "sg:city":"Alliance",
    "sg:classifiers":[
        {
            "category":"Manufacturing",
            "subcategory":"Tools & Machinery",
            "type":"Manufacturing & Wholesale Goods"
        }
    ],
    "sg:phone":"+1 330 823 0812",
    "sg:postcode":"44601",
    "sg:province":"OH",
    "sg:tags":[
        "mfg"
    ],
    "wof:name":"Perma Industries",
    "wof:placetype":"venue"
},
  "geometry": {"coordinates":[-81.116259,40.940402],"type":"Point"}
}