{
  "type": "Feature",
  "properties": {
    "addr:full": "9321 Ash Hollow Ln Dayton OH 45458",
    "addr:housenumber": "9321",
    "addr:postcode": "45458",
    "addr:street": "Ash Hollow Ln",
    "iso:country": "US",
    "sg:address": "9321 Ash Hollow Ln",
    "sg:city": "Dayton",
    "sg:classifiers": [
      {
        "category": "Manufacturing",
        "subcategory": "Retail Goods",
        "type": "Manufacturing \u0026 Wholesale Goods"
      }
    ],
    "sg:phone": "+1 937 885 9693",
    "sg:postcode": "45458",
    "sg:province": "OH",
    "sg:tags": [
      "product",
      "mfg"
    ],
    "wof:name": "Baskets Bouquets \u0026 More",
    "wof:placetype": "venue"
  },
  "geometry": {"coordinates":[-84.113081,39.607564],"type":"Point"}
}
