{
  "type": "Feature",
  "properties": {
    "iso:country":"US",
    "sg:address":"9321 Ash Hollow Ln",
    "sg:city":"Dayton",
    "sg:classifiers":[
        {
            "category":"Manufacturing",
            "subcategory":"Retail Goods",
            "type":"Manufacturing & Wholesale Goods"
        }
    ],
    "sg:phone":"+1 937 885 9693",
    "sg:postcode":"45458",
    "sg:province":"OH",
    "sg:tags":[
        "product",
        "mfg"
    ],
    "wof:name":"Baskets Bouquets & More",
    "wof:placetype":"venue"
},
  "geometry": {"coordinates":[-84.11308099999999,39.607564],"type":"Point"}
}