{
  "type": "Feature",
  "properties": {
    "addr:full":"2155 Eakin Rd Columbus OH 43223",
    "addr:housenumber":"2155",
    "addr:postcode":"43223",
    "addr:street":"Eakin Rd",
    "iso:country":"US",
    "sg:address":"2155 Eakin Rd",
    "sg:city":"Columbus",
    "sg:classifiers":[
        {
            "category":"Shopping",
            "subcategory":"Computers & Home Electronics",
            "type":"Retail Goods"
        }
    ],
    "sg:phone":"+1 614 274 3139",
    "sg:postcode":"43223",
    "sg:province":"OH",
    "sg:tags":[
        "equipment",
        "electronic",
        "supply"
    ],
    "wof:name":"Radio Shack",
    "wof:placetype":"venue"
},
  "geometry": {"coordinates":[-83.051856,39.932649],"type":"Point"}
}