{
  "type": "Feature",
  "properties": {
    "addr:full": "9567 Gibson Dr Powell OH 43065",
    "addr:housenumber": "9567",
    "addr:postcode": "43065",
    "addr:street": "Gibson Dr",
    "iso:country": "US",
    "sg:address": "9567 Gibson Dr",
    "sg:city": "Powell",
    "sg:classifiers": [
      {
        "category": "Building \u0026 Trades",
        "subcategory": "Construction",
        "type": "Services"
      }
    ],
    "sg:phone": "+1 614 766 2856",
    "sg:postcode": "43065",
    "sg:province": "OH",
    "sg:tags": [
      "home",
      "builder"
    ],
    "wof:name": "Virginia Homes",
    "wof:placetype": "venue"
  },
  "geometry": {"coordinates":[-83.107959,40.16195],"type":"Point"}
}
