{
  "type": "Feature",
  "properties": {
    "iso:country":"US",
    "sg:address":"8338 Melody Ln",
    "sg:city":"Macedonia",
    "sg:classifiers":[
        {
            "category":"Retail",
            "subcategory":"Animal Services",
            "type":"Services"
        }
    ],
    "sg:phone":"+1 330 467 8262",
    "sg:postcode":"44056",
    "sg:province":"OH",
    "wof:name":"Clip Joint",
    "wof:placetype":"venue"
},
  "geometry": {"coordinates":[-81.518187,41.319036],"type":"Point"}
}