{
  "type": "Feature",
  "properties": {
    "addr:full": "9832 Valley View Rd Macedonia OH 44056",
    "addr:housenumber": "9832",
    "addr:postcode": "44056",
    "addr:street": "Valley View Rd",
    "iso:country": "US",
    "sg:address": "9832 Valley View Rd",
    "sg:city": "Macedonia",
    "sg:classifiers": [
      {
        "category": "Cinema",
        "subcategory": "Movie Rental",
        "type": "Entertainment"
      }
    ],
    "sg:phone": "+1 330 468 3053",
    "sg:postcode": "44056",
    "sg:province": "OH",
    "sg:tags": [
      "leasing",
      "video",
      "disc",
      "tape"
    ],
    "wof:name": "Video Madness",
    "wof:placetype": "venue"
  },
  "geometry": {"coordinates":[-81.506701,41.312074],"type":"Point"}
}
