{
  "type": "Feature",
  "properties": {
    "iso:country":"US",
    "sg:address":"358 Victoria Dr",
    "sg:city":"London",
    "sg:classifiers":[
        {
            "category":"Retail",
            "subcategory":"Laundry & Dry Cleaning",
            "type":"Services"
        }
    ],
    "sg:phone":"+1 614 870 0374",
    "sg:postcode":"43140",
    "sg:province":"OH",
    "sg:tags":[
        "cleaners",
        "rug",
        "carpet"
    ],
    "wof:name":"Dick's Carpet Care",
    "wof:placetype":"venue"
},
  "geometry": {"coordinates":[-83.423558,39.8974],"type":"Point"}
}