{
  "type": "Feature",
  "properties": {
    "addr:full": "358 Victoria Dr London OH 43140",
    "addr:housenumber": "358",
    "addr:postcode": "43140",
    "addr:street": "Victoria Dr",
    "iso:country": "US",
    "sg:address": "358 Victoria Dr",
    "sg:city": "London",
    "sg:classifiers": [
      {
        "category": "Retail",
        "subcategory": "Laundry \u0026 Dry Cleaning",
        "type": "Services"
      }
    ],
    "sg:phone": "+1 614 870 0374",
    "sg:postcode": "43140",
    "sg:province": "OH",
    "sg:tags": [
      "cleaners",
      "rug",
      "carpet"
    ],
    "wof:name": "Dick's Carpet Care",
    "wof:placetype": "venue"
  },
  "geometry": {"coordinates":[-83.423558,39.8974],"type":"Point"}
}
