{
  "type": "Feature",
  "properties": {
    "iso:country":"US",
    "sg:address":"8437 Mayfield Rd",
    "sg:city":"Chesterland",
    "sg:classifiers":[
        {
            "category":"Real Estate",
            "subcategory":"Architect",
            "type":"Services"
        }
    ],
    "sg:phone":"+1 440 729 2110",
    "sg:postcode":"44026",
    "sg:province":"OH",
    "wof:name":"DJS Design",
    "wof:placetype":"venue"
},
  "geometry": {"coordinates":[-81.338965,41.52208],"type":"Point"}
}