{
  "type": "Feature",
  "properties": {
    "addr:full":"7317 Portage St NW Massillon OH 44646",
    "addr:housenumber":"7317",
    "addr:postcode":"44646",
    "addr:street":"Portage St Nw",
    "iso:country":"US",
    "sg:address":"7317 Portage St NW",
    "sg:city":"Massillon",
    "sg:classifiers":[
        {
            "category":"Social Services",
            "type":"Services"
        }
    ],
    "sg:phone":"+1 330 966 1620",
    "sg:postcode":"44646",
    "sg:province":"OH",
    "sg:tags":[
        "counseling"
    ],
    "wof:name":"New Beginnings",
    "wof:placetype":"venue"
},
  "geometry": {"coordinates":[-81.48973700000001,40.879291],"type":"Point"}
}