{
  "type": "Feature",
  "properties": {
    "addr:full":"6353 Som Center Rd Cleveland OH 44139",
    "addr:housenumber":"6353",
    "addr:postcode":"44139",
    "addr:street":"Som Center Rd",
    "iso:country":"US",
    "sg:address":"6353 Som Center Rd",
    "sg:city":"Cleveland",
    "sg:classifiers":[
        {
            "category":"Food & Beverages",
            "subcategory":"Bakery",
            "type":"Retail Goods"
        }
    ],
    "sg:phone":"+1 440 349 4037",
    "sg:postcode":"44139",
    "sg:province":"OH",
    "sg:tags":[
        "doughnut"
    ],
    "wof:name":"Dandi Enterprises Inc",
    "wof:placetype":"venue"
},
  "geometry": {"coordinates":[-81.437676,41.386482],"type":"Point"}
}