{
  "type": "Feature",
  "properties": {
    "iso:country":"US",
    "sg:address":"330 Marseilles-Galion Rd E",
    "sg:city":"Marion",
    "sg:classifiers":[
        {
            "category":"Farming",
            "subcategory":"Farm",
            "type":"Manufacturing & Wholesale Goods"
        }
    ],
    "sg:phone":"+1 740 382 6823",
    "sg:postcode":"43302",
    "sg:province":"OH",
    "sg:tags":[
        "repair",
        "general",
        "automotive",
        "crop",
        "auto"
    ],
    "wof:name":"In Tune Auto Repairs",
    "wof:placetype":"venue"
},
  "geometry": {"coordinates":[-83.138492,40.673684],"type":"Point"}
}