{
  "type": "Feature",
  "properties": {
    "addr:full": "214 High St Waynesville OH 45068",
    "addr:housenumber": "214",
    "addr:postcode": "45068",
    "addr:street": "High St",
    "iso:country": "US",
    "sg:address": "214 High St",
    "sg:city": "Waynesville",
    "sg:classifiers": [
      {
        "category": "Shopping",
        "subcategory": "Used Merchandise",
        "type": "Retail Goods"
      }
    ],
    "sg:phone": "+1 513 897 3858",
    "sg:postcode": "45068",
    "sg:province": "OH",
    "sg:tags": [
      "antique"
    ],
    "wof:name": "Days Gone By Antiques \u0026 Accent",
    "wof:placetype": "venue"
  },
  "geometry": {"coordinates":[-84.087818,39.528699],"type":"Point"}
}
