{
  "type": "Feature",
  "properties": {
    "iso:country":"US",
    "sg:address":"15980 Georgia Rd",
    "sg:city":"Middlefield",
    "sg:classifiers":[
        {
            "category":"Wholesale",
            "subcategory":"Farm Supplies",
            "type":"Manufacturing & Wholesale Goods"
        },
        {
            "category":"Autos & Motor Vehicles",
            "subcategory":"Automobile Sales",
            "type":"Retail Goods"
        },
        {
            "category":"Wholesale",
            "subcategory":"Machinery & Supplies",
            "type":"Manufacturing & Wholesale Goods"
        },
        {
            "category":"Farming",
            "subcategory":"Farm",
            "type":"Manufacturing & Wholesale Goods"
        }
    ],
    "sg:phone":"+1 440 632 5590",
    "sg:postcode":"44062",
    "sg:province":"OH",
    "sg:tags":[
        "equipment",
        "all-terrain",
        "baling"
    ],
    "wof:name":"Middlefield Farm & Garden",
    "wof:placetype":"venue"
},
  "geometry": {"coordinates":[-81.071484,41.449457],"type":"Point"}
}