{
  "type": "Feature",
  "properties": {
    "addr:full": "15980 Georgia Rd Middlefield OH 44062",
    "addr:housenumber": "15980",
    "addr:postcode": "44062",
    "addr:street": "Georgia Rd",
    "iso:country": "US",
    "sg:address": "15980 Georgia Rd",
    "sg:city": "Middlefield",
    "sg:classifiers": [
      {
        "category": "Wholesale",
        "subcategory": "Farm Supplies",
        "type": "Manufacturing \u0026 Wholesale Goods"
      },
      {
        "category": "Autos \u0026 Motor Vehicles",
        "subcategory": "Automobile Sales",
        "type": "Retail Goods"
      },
      {
        "category": "Wholesale",
        "subcategory": "Machinery \u0026 Supplies",
        "type": "Manufacturing \u0026 Wholesale Goods"
      },
      {
        "category": "Farming",
        "subcategory": "Farm",
        "type": "Manufacturing \u0026 Wholesale Goods"
      }
    ],
    "sg:phone": "+1 440 632 5590",
    "sg:postcode": "44062",
    "sg:province": "OH",
    "sg:tags": [
      "equipment",
      "all-terrain",
      "baling"
    ],
    "wof:name": "Middlefield Farm \u0026 Garden",
    "wof:placetype": "venue"
  },
  "geometry": {"coordinates":[-81.071484,41.449457],"type":"Point"}
}
