{
  "type": "Feature",
  "properties": {
    "addr:full":"301 N Mulberry St Tremont City OH 45372",
    "addr:housenumber":"301",
    "addr:postcode":"45372",
    "addr:street":"N Mulberry St",
    "iso:country":"US",
    "sg:address":"301 N Mulberry St",
    "sg:city":"Tremont City",
    "sg:classifiers":[
        {
            "category":"Real Estate",
            "subcategory":"Real Estate Agent",
            "type":"Services"
        }
    ],
    "sg:phone":"+1 937 969 8609",
    "sg:postcode":"45372",
    "sg:province":"OH",
    "wof:name":"Residential Restructuring Co",
    "wof:placetype":"venue"
},
  "geometry": {"coordinates":[-83.835745,40.015329],"type":"Point"}
}