{
  "type": "Feature",
  "properties": {
    "addr:full": "1038 Lebanon St Monroe OH 45050",
    "addr:housenumber": "1038",
    "addr:postcode": "45050",
    "addr:street": "Lebanon St",
    "iso:country": "US",
    "sg:address": "1038 Lebanon St",
    "sg:city": "Monroe",
    "sg:classifiers": [
      {
        "category": "Shopping",
        "subcategory": "News",
        "type": "Retail Goods"
      },
      {
        "category": "Shopping",
        "type": "Retail Goods"
      }
    ],
    "sg:phone": "+1 513 539 6969",
    "sg:postcode": "45050",
    "sg:province": "OH",
    "sg:tags": [
      "store",
      "miscellaneous",
      "gift"
    ],
    "sg:website": "www.hustlerhollywood.com",
    "wof:name": "Hustler Hollywood of Ohio",
    "wof:placetype": "venue"
  },
  "geometry": {"coordinates":[-84.341754,39.439859],"type":"Point"}
}
