{
  "type": "Feature",
  "properties": {
    "iso:country":"US",
    "sg:address":"11060 Deerfield Rd",
    "sg:city":"Cincinnati",
    "sg:classifiers":[
        {
            "category":"Wholesale",
            "subcategory":"Durable Goods & Equipment",
            "type":"Manufacturing & Wholesale Goods"
        }
    ],
    "sg:phone":"+1 513 793 9910",
    "sg:postcode":"45242",
    "sg:province":"OH",
    "sg:tags":[
        "magnet",
        "magnetic",
        "devices"
    ],
    "wof:name":"Irvine Industrial",
    "wof:placetype":"venue"
},
  "geometry": {"coordinates":[-84.36129200000001,39.261431],"type":"Point"}
}