{
  "type": "Feature",
  "properties": {
    "addr:full": "11060 Deerfield Rd Cincinnati OH 45242",
    "addr:housenumber": "11060",
    "addr:postcode": "45242",
    "addr:street": "Deerfield Rd",
    "iso:country": "US",
    "sg:address": "11060 Deerfield Rd",
    "sg:city": "Cincinnati",
    "sg:classifiers": [
      {
        "category": "Wholesale",
        "subcategory": "Durable Goods \u0026 Equipment",
        "type": "Manufacturing \u0026 Wholesale Goods"
      }
    ],
    "sg:phone": "+1 513 793 9910",
    "sg:postcode": "45242",
    "sg:province": "OH",
    "sg:tags": [
      "magnet",
      "magnetic",
      "devices"
    ],
    "wof:name": "Irvine Industrial",
    "wof:placetype": "venue"
  },
  "geometry": {"coordinates":[-84.361292,39.261431],"type":"Point"}
}
