{
  "type": "Feature",
  "properties": {
    "iso:country":"US",
    "sg:address":"6340 Georgetown Rd",
    "sg:city":"Fairfield",
    "sg:classifiers":[
        {
            "category":"Banks & Credit Unions",
            "subcategory":"Financial Services",
            "type":"Services"
        }
    ],
    "sg:phone":"+1 513 858 1141",
    "sg:postcode":"45014",
    "sg:province":"OH",
    "sg:tags":[
        "trust",
        "investment",
        "real estate"
    ],
    "wof:name":"Rcs2 Properties Ltd",
    "wof:placetype":"venue"
},
  "geometry": {"coordinates":[-84.618388,39.311967],"type":"Point"}
}