{
  "type": "Feature",
  "properties": {
    "addr:full": "5580 Newton Falls Rd Ravenna OH 44266",
    "addr:housenumber": "5580",
    "addr:postcode": "44266",
    "addr:street": "Newton Falls Rd",
    "iso:country": "US",
    "sg:address": "5580 Newton Falls Rd",
    "sg:city": "Ravenna",
    "sg:classifiers": [
      {
        "category": "Building \u0026 Trades",
        "subcategory": "Construction",
        "type": "Services"
      }
    ],
    "sg:phone": "+1 330 296 5539",
    "sg:postcode": "44266",
    "sg:province": "OH",
    "sg:tags": [
      "contractor"
    ],
    "wof:name": "Crowe Masonry",
    "wof:placetype": "venue"
  },
  "geometry": {"coordinates":[-81.190354,41.163136],"type":"Point"}
}
