{
  "type": "Feature",
  "properties": {
    "addr:full": "7030 Reading Rd Cincinnati OH 45237",
    "addr:housenumber": "7030",
    "addr:postcode": "45237",
    "addr:street": "Reading Rd",
    "iso:country": "US",
    "sg:address": "7030 Reading Rd",
    "sg:city": "Cincinnati",
    "sg:classifiers": [
      {
        "category": "Building \u0026 Trades",
        "subcategory": "Cleaning \u0026 Sanitation",
        "type": "Services"
      }
    ],
    "sg:phone": "+1 513 841 2424",
    "sg:postcode": "45237",
    "sg:province": "OH",
    "sg:tags": [
      "janitor"
    ],
    "wof:name": "New Concepts Janitorial",
    "wof:placetype": "venue"
  },
  "geometry": {"coordinates":[-84.46402,39.188198],"type":"Point"}
}
