{
  "type": "Feature",
  "properties": {
    "addr:full":"133 N Prospect St Granville OH 43023",
    "addr:housenumber":"133",
    "addr:postcode":"43023",
    "addr:street":"N Prospect St",
    "iso:country":"US",
    "sg:address":"133 N Prospect St",
    "sg:city":"Granville",
    "sg:classifiers":[
        {
            "category":"Government",
            "subcategory":"Fire Station",
            "type":"Public Place"
        }
    ],
    "sg:phone":"+1 740 587 0261",
    "sg:postcode":"43023",
    "sg:province":"OH",
    "sg:tags":[
        "department"
    ],
    "wof:name":"Fire Departments",
    "wof:placetype":"venue"
},
  "geometry": {"coordinates":[-82.518401,40.068705],"type":"Point"}
}