{
  "type": "Feature",
  "properties": {
    "iso:country":"US",
    "sg:address":"6326 E Livingston Ave",
    "sg:city":"Reynoldsburg",
    "sg:classifiers":[
        {
            "category":"Organizations",
            "subcategory":"Religious Organization",
            "type":"Services"
        }
    ],
    "sg:phone":"+1 614 751 0895",
    "sg:postcode":"43068",
    "sg:province":"OH",
    "wof:name":"Vision Ministries Intl",
    "wof:placetype":"venue"
},
  "geometry": {"coordinates":[-82.82584,39.942026],"type":"Point"}
}