{
  "type": "Feature",
  "properties": {
    "addr:full": "4262 Duneden Ave Cincinnati OH 45236",
    "addr:housenumber": "4262",
    "addr:postcode": "45236",
    "addr:street": "Duneden Ave",
    "iso:country": "US",
    "sg:address": "4262 Duneden Ave",
    "sg:city": "Cincinnati",
    "sg:classifiers": [
      {
        "category": "Professional",
        "subcategory": "Engineering",
        "type": "Services"
      }
    ],
    "sg:phone": "+1 513 792 1090",
    "sg:postcode": "45236",
    "sg:province": "OH",
    "sg:tags": [
      "engineer"
    ],
    "wof:name": "Pactech Engineering Inc",
    "wof:placetype": "venue"
  },
  "geometry": {"coordinates":[-84.392622,39.203872],"type":"Point"}
}
