{
  "type": "Feature",
  "properties": {
    "addr:full": "336 Ludlow Ave Cincinnati OH 45220",
    "addr:housenumber": "336",
    "addr:postcode": "45220",
    "addr:street": "Ludlow Ave",
    "iso:country": "US",
    "sg:address": "336 Ludlow Ave",
    "sg:city": "Cincinnati",
    "sg:classifiers": [
      {
        "category": "Personal",
        "subcategory": "Massage",
        "type": "Services"
      },
      {
        "category": "Health Services",
        "subcategory": "Clinic",
        "type": "Services"
      },
      {
        "category": "Health Services",
        "subcategory": "Health Practitioner",
        "type": "Services"
      },
      {
        "category": "Health Services",
        "subcategory": "Chiropractor",
        "type": "Services"
      }
    ],
    "sg:phone": "+1 513 549 5964",
    "sg:postcode": "45220",
    "sg:province": "OH",
    "sg:tags": [
      "information",
      "referral",
      "chiropractic",
      "sport",
      "medicine",
      "therapist",
      "therapy",
      "treatment",
      "nutritionist",
      "injury",
      "physical"
    ],
    "sg:website": "http://www.yext.com/p/superpages/fick-chiropractic-and-orthopedic-clifton-downtown-cincinnati-ohio.html",
    "wof:name": "Fick Chiropractic",
    "wof:placetype": "venue"
  },
  "geometry": {"coordinates":[-84.520576,39.143711],"type":"Point"}
}
