{
  "type": "Feature",
  "properties": {
    "addr:full":"5000 Creek Rd Cincinnati OH 45242",
    "addr:housenumber":"5000",
    "addr:postcode":"45242",
    "addr:street":"Creek Rd",
    "iso:country":"US",
    "sg:address":"5000 Creek Rd",
    "sg:city":"Cincinnati",
    "sg:classifiers":[
        {
            "category":"Communications",
            "subcategory":"Film & Video Production",
            "type":"Services"
        },
        {
            "category":"Building & Trades",
            "subcategory":"Locksmith",
            "type":"Services"
        },
        {
            "category":"Manufacturing",
            "subcategory":"Paper Products",
            "type":"Manufacturing & Wholesale Goods"
        }
    ],
    "sg:phone":"+1 513 891 9544",
    "sg:postcode":"45242",
    "sg:province":"OH",
    "sg:tags":[
        "equipment",
        "die",
        "cutting",
        "supply"
    ],
    "wof:name":"Loroco Industries Inc.",
    "wof:placetype":"venue"
},
  "geometry": {"coordinates":[-84.37342099999999,39.258033],"type":"Point"}
}