{
  "type": "Feature",
  "properties": {
    "iso:country":"US",
    "sg:address":"5957 Boymel Dr",
    "sg:city":"Fairfield",
    "sg:classifiers":[
        {
            "category":"Recreation",
            "type":"Entertainment"
        }
    ],
    "sg:phone":"+1 513 942 3483",
    "sg:postcode":"45014",
    "sg:province":"OH",
    "sg:tags":[
        "repair",
        "instruction",
        "equipment",
        "s",
        "retail",
        "scuba"
    ],
    "wof:name":"Planet Ocean",
    "wof:placetype":"venue"
},
  "geometry": {"coordinates":[-84.49876,39.31912],"type":"Point"}
}