{
  "type": "Feature",
  "properties": {
    "addr:full": "11546 Caves Rd Chesterland OH 44026",
    "addr:housenumber": "11546",
    "addr:postcode": "44026",
    "addr:street": "Caves Rd",
    "iso:country": "US",
    "sg:address": "11546 Caves Rd",
    "sg:city": "Chesterland",
    "sg:classifiers": [
      {
        "category": "Shopping",
        "subcategory": "Bicycles \u0026 Sporting Goods",
        "type": "Retail Goods"
      }
    ],
    "sg:phone": "+1 440 729 8054",
    "sg:postcode": "44026",
    "sg:province": "OH",
    "wof:name": "Tack Shoppe",
    "wof:placetype": "venue"
  },
  "geometry": {"coordinates":[-81.362807,41.563484],"type":"Point"}
}
