{
  "type": "Feature",
  "properties": {
    "iso:country":"US",
    "sg:address":"11546 Caves Rd",
    "sg:city":"Chesterland",
    "sg:classifiers":[
        {
            "category":"Shopping",
            "subcategory":"Bicycles & Sporting Goods",
            "type":"Retail Goods"
        }
    ],
    "sg:phone":"+1 440 729 8054",
    "sg:postcode":"44026",
    "sg:province":"OH",
    "wof:name":"Tack Shoppe",
    "wof:placetype":"venue"
},
  "geometry": {"coordinates":[-81.362807,41.563484],"type":"Point"}
}