{
  "type": "Feature",
  "properties": {
    "iso:country":"US",
    "sg:address":"1012 Commercial Ave SE",
    "sg:city":"New Philadelphia",
    "sg:classifiers":[
        {
            "category":"Autos & Motor Vehicles",
            "subcategory":"Auto Supplies",
            "type":"Retail Goods"
        }
    ],
    "sg:phone":"+1 330 339 8816",
    "sg:postcode":"44663",
    "sg:province":"OH",
    "sg:tags":[
        "new",
        "used",
        "tire"
    ],
    "wof:name":"Outlaw Tire Inc",
    "wof:placetype":"venue"
},
  "geometry": {"coordinates":[-81.442082,40.472598],"type":"Point"}
}