{
  "type": "Feature",
  "properties": {
    "addr:full": "1012 Commercial Ave SE New Philadelphia OH 44663",
    "addr:housenumber": "1012",
    "addr:postcode": "44663",
    "addr:street": "Commercial Ave Se",
    "iso:country": "US",
    "sg:address": "1012 Commercial Ave SE",
    "sg:city": "New Philadelphia",
    "sg:classifiers": [
      {
        "category": "Autos \u0026 Motor Vehicles",
        "subcategory": "Auto Supplies",
        "type": "Retail Goods"
      }
    ],
    "sg:phone": "+1 330 339 8816",
    "sg:postcode": "44663",
    "sg:province": "OH",
    "sg:tags": [
      "new",
      "used",
      "tire"
    ],
    "wof:name": "Outlaw Tire Inc",
    "wof:placetype": "venue"
  },
  "geometry": {"coordinates":[-81.442082,40.472598],"type":"Point"}
}
