{
  "type": "Feature",
  "properties": {
    "addr:full": "6622 Hayes Rd Cincinnati OH 45248",
    "addr:housenumber": "6622",
    "addr:postcode": "45248",
    "addr:street": "Hayes Rd",
    "iso:country": "US",
    "sg:address": "6622 Hayes Rd",
    "sg:city": "Cincinnati",
    "sg:classifiers": [
      {
        "category": "Building \u0026 Trades",
        "subcategory": "Plumbing",
        "type": "Services"
      }
    ],
    "sg:phone": "+1 513 598 8449",
    "sg:postcode": "45248",
    "sg:province": "OH",
    "sg:tags": [
      "air",
      "heating",
      "conditioning",
      "contractor"
    ],
    "wof:name": "Durbin Heating \u0026 Cooling Inc",
    "wof:placetype": "venue"
  },
  "geometry": {"coordinates":[-84.660507,39.172504],"type":"Point"}
}
