{
  "type": "Feature",
  "properties": {
    "iso:country":"US",
    "sg:address":"4905 Whetsel Ave",
    "sg:city":"Cincinnati",
    "sg:classifiers":[
        {
            "category":"Arena",
            "subcategory":"Indoor Arena",
            "type":"Entertainment"
        },
        {
            "category":"Personal",
            "type":"Services"
        },
        {
            "category":"Arts & Performance",
            "subcategory":"Theater",
            "type":"Entertainment"
        },
        {
            "category":"Recreation",
            "subcategory":"Dance Hall",
            "type":"Entertainment"
        }
    ],
    "sg:phone":"+1 513 407 4555",
    "sg:postcode":"45227",
    "sg:province":"OH",
    "sg:tags":[
        "bingo",
        "theatres-concert",
        "ballroom",
        "venue",
        "planning",
        "party",
        "event"
    ],
    "sg:website":"http://Mystiquehall.webs.com",
    "wof:name":"Mystique Event Hall",
    "wof:placetype":"venue"
},
  "geometry": {"coordinates":[-84.393154,39.159883],"type":"Point"}
}