{
  "type": "Feature",
  "properties": {
    "iso:country":"US",
    "sg:address":"7856 Westfall Rd",
    "sg:city":"Frankfort",
    "sg:classifiers":[
        {
            "category":"Manufacturing",
            "subcategory":"Chemicals & Compounds",
            "type":"Manufacturing & Wholesale Goods"
        }
    ],
    "sg:phone":"+1 740 998 5220",
    "sg:postcode":"45628",
    "sg:province":"OH",
    "sg:tags":[
        "preparation",
        "toilet",
        "product",
        "mfg"
    ],
    "wof:name":"Scent From Heaven",
    "wof:placetype":"venue"
},
  "geometry": {"coordinates":[-83.183456,39.395581],"type":"Point"}
}