{
  "type": "Feature",
  "properties": {
    "addr:full": "7856 Westfall Rd Frankfort OH 45628",
    "addr:housenumber": "7856",
    "addr:postcode": "45628",
    "addr:street": "Westfall Rd",
    "iso:country": "US",
    "sg:address": "7856 Westfall Rd",
    "sg:city": "Frankfort",
    "sg:classifiers": [
      {
        "category": "Manufacturing",
        "subcategory": "Chemicals \u0026 Compounds",
        "type": "Manufacturing \u0026 Wholesale Goods"
      }
    ],
    "sg:phone": "+1 740 998 5220",
    "sg:postcode": "45628",
    "sg:province": "OH",
    "sg:tags": [
      "preparation",
      "toilet",
      "product",
      "mfg"
    ],
    "wof:name": "Scent From Heaven",
    "wof:placetype": "venue"
  },
  "geometry": {"coordinates":[-83.183456,39.395581],"type":"Point"}
}
