{
  "type": "Feature",
  "properties": {
    "addr:full":"731 E McMillan St Cincinnati OH 45206",
    "addr:housenumber":"731",
    "addr:postcode":"45206",
    "addr:street":"E Mcmillan St",
    "iso:country":"US",
    "sg:address":"731 E McMillan St",
    "sg:city":"Cincinnati",
    "sg:classifiers":[
        {
            "category":"Food & Beverages",
            "subcategory":"Meat & Fish",
            "type":"Retail Goods"
        }
    ],
    "sg:phone":"+1 513 961 4559",
    "sg:postcode":"45206",
    "sg:province":"OH",
    "sg:tags":[
        "market"
    ],
    "wof:name":"Louis Meats Inc",
    "wof:placetype":"venue"
},
  "geometry": {"coordinates":[-84.493484,39.126066],"type":"Point"}
}