{
  "type": "Feature",
  "properties": {
    "iso:country":"US",
    "sg:address":"7126 Bayard Rd",
    "sg:city":"Minerva",
    "sg:phone":"+1 330 894 2339",
    "sg:postcode":"44657",
    "sg:province":"OH",
    "sg:tags":[
        "farm",
        "corn",
        "dairy"
    ],
    "wof:name":"Hahn Farms",
    "wof:placetype":"venue"
},
  "geometry": {"coordinates":[-81.06572799999999,40.796457],"type":"Point"}
}