{
  "type": "Feature",
  "properties": {
    "addr:full": "7126 Bayard Rd Minerva OH 44657",
    "addr:housenumber": "7126",
    "addr:postcode": "44657",
    "addr:street": "Bayard Rd",
    "iso:country": "US",
    "sg:address": "7126 Bayard Rd",
    "sg:city": "Minerva",
    "sg:phone": "+1 330 894 2339",
    "sg:postcode": "44657",
    "sg:province": "OH",
    "sg:tags": [
      "farm",
      "corn",
      "dairy"
    ],
    "wof:name": "Hahn Farms",
    "wof:placetype": "venue"
  },
  "geometry": {"coordinates":[-81.065728,40.796457],"type":"Point"}
}
