{
  "type": "Feature",
  "properties": {
    "iso:country":"US",
    "sg:address":"569 Twp Hwy 2152",
    "sg:city":"Loudonville",
    "sg:classifiers":[
        {
            "category":"Wholesale",
            "subcategory":"Plants",
            "type":"Manufacturing & Wholesale Goods"
        }
    ],
    "sg:phone":"+1 419 368 3314",
    "sg:postcode":"44842",
    "sg:province":"OH",
    "sg:tags":[
        "nursery",
        "tree"
    ],
    "wof:name":"Hobby & Assoc",
    "wof:placetype":"venue"
},
  "geometry": {"coordinates":[-82.239054,40.747865],"type":"Point"}
}