{
  "type": "Feature",
  "properties": {
    "addr:full":"21640 Main St Raymond OH 43067",
    "addr:housenumber":"21640",
    "addr:postcode":"43067",
    "addr:street":"Main St",
    "iso:country":"US",
    "sg:address":"21640 Main St",
    "sg:city":"Raymond",
    "sg:classifiers":[
        {
            "category":"Autos & Motor Vehicles",
            "subcategory":"Automobile Sales",
            "type":"Retail Goods"
        }
    ],
    "sg:phone":"+1 937 246 2004",
    "sg:postcode":"43067",
    "sg:province":"OH",
    "sg:tags":[
        "car",
        "dealer"
    ],
    "wof:name":"Stephens Auto Sales",
    "wof:placetype":"venue"
},
  "geometry": {"coordinates":[-83.466151,40.334323],"type":"Point"}
}