{
  "type": "Feature",
  "properties": {
    "iso:country":"US",
    "sg:address":"2997 Palmetto St",
    "sg:city":"Columbus",
    "sg:classifiers":[
        {
            "category":"Building & Trades",
            "subcategory":"Construction",
            "type":"Services"
        }
    ],
    "sg:phone":"+1 614 276 4779",
    "sg:postcode":"43204",
    "sg:province":"OH",
    "sg:tags":[
        "house"
    ],
    "wof:name":"Mitchell Montgomery Lyle Inv",
    "wof:placetype":"venue"
},
  "geometry": {"coordinates":[-83.080378,39.949432],"type":"Point"}
}