{
  "type": "Feature",
  "properties": {
    "addr:full":"4329 W 224th St Cleveland OH 44126",
    "addr:housenumber":"4329",
    "addr:postcode":"44126",
    "addr:street":"W 224Th St",
    "iso:country":"US",
    "sg:address":"4329 W 224th St",
    "sg:city":"Cleveland",
    "sg:classifiers":[
        {
            "category":"Building & Trades",
            "subcategory":"Electrical",
            "type":"Services"
        }
    ],
    "sg:phone":"+1 440 716 5417",
    "sg:postcode":"44126",
    "sg:province":"OH",
    "sg:tags":[
        "electrical",
        "contractor"
    ],
    "wof:name":"Buckeye Electric Inc",
    "wof:placetype":"venue"
},
  "geometry": {"coordinates":[-81.868706,41.44248],"type":"Point"}
}