{
  "type": "Feature",
  "properties": {
    "addr:full":"7598 Ashlar Ct Canal Winchester OH 43110",
    "addr:housenumber":"7598",
    "addr:postcode":"43110",
    "addr:street":"Ashlar Ct",
    "iso:country":"US",
    "sg:address":"7598 Ashlar Ct",
    "sg:city":"Canal Winchester",
    "sg:classifiers":[
        {
            "category":"Freight",
            "type":"Transportation"
        }
    ],
    "sg:phone":"+1 614 920 2411",
    "sg:postcode":"43110",
    "sg:province":"OH",
    "sg:tags":[
        "operator",
        "local",
        "trucking"
    ],
    "wof:name":"Evans Larry Delivery Serv",
    "wof:placetype":"venue"
},
  "geometry": {"coordinates":[-82.816975,39.82707],"type":"Point"}
}