{
  "type": "Feature",
  "properties": {
    "addr:full": "5 E Long St Columbus OH 43215",
    "addr:housenumber": "5",
    "addr:postcode": "43215",
    "addr:street": "E Long St",
    "iso:country": "US",
    "sg:address": "5 E Long St",
    "sg:city": "Columbus",
    "sg:classifiers": [
      {
        "category": "Professional",
        "subcategory": "Lawyer \u0026 Legal Services",
        "type": "Services"
      }
    ],
    "sg:phone": "+1 614 221 7381",
    "sg:postcode": "43215",
    "sg:province": "OH",
    "sg:tags": [
      "attorney"
    ],
    "wof:name": "Koltak \u0026 Gibson",
    "wof:placetype": "venue"
  },
  "geometry": {"coordinates":[-83.000366,39.964953],"type":"Point"}
}
