{
  "type": "Feature",
  "properties": {
    "addr:full": "2575 Commerce Blvd Cincinnati OH 45241",
    "addr:housenumber": "2575",
    "addr:postcode": "45241",
    "addr:street": "Commerce Blvd",
    "iso:country": "US",
    "sg:address": "2575 Commerce Blvd",
    "sg:city": "Cincinnati",
    "sg:classifiers": [
      {
        "category": "Restaurant",
        "type": "Food \u0026 Drink"
      }
    ],
    "sg:phone": "+1 513 552 1340",
    "sg:postcode": "45241",
    "sg:province": "OH",
    "sg:tags": [
      "caterer"
    ],
    "wof:name": "Elegant Fare Inc",
    "wof:placetype": "venue"
  },
  "geometry": {"coordinates":[-84.423343,39.290394],"type":"Point"}
}
