{
  "type": "Feature",
  "properties": {
    "iso:country":"US",
    "sg:address":"700 Shiloh Springs Rd",
    "sg:city":"Dayton",
    "sg:classifiers":[
        {
            "category":"Personal",
            "type":"Services"
        }
    ],
    "sg:phone":"+1 937 276 9600",
    "sg:postcode":"45415",
    "sg:province":"OH",
    "sg:tags":[
        "no"
    ],
    "wof:name":"Old Red Barn Inc",
    "wof:placetype":"venue"
},
  "geometry": {"coordinates":[-84.25405499999999,39.819777],"type":"Point"}
}