{
  "type": "Feature",
  "properties": {
    "addr:full":"1505 Enterprise Way Kent OH 44240",
    "addr:housenumber":"1505",
    "addr:postcode":"44240",
    "addr:street":"Enterprise Way",
    "iso:country":"US",
    "sg:address":"1505 Enterprise Way",
    "sg:city":"Kent",
    "sg:classifiers":[
        {
            "category":"Retail",
            "subcategory":"Auto Repair",
            "type":"Services"
        }
    ],
    "sg:phone":"+1 330 677 4004",
    "sg:postcode":"44240",
    "sg:province":"OH",
    "sg:tags":[
        "body",
        "automobile",
        "painting"
    ],
    "wof:name":"Performance Collision Ctr",
    "wof:placetype":"venue"
},
  "geometry": {"coordinates":[-81.376932,41.138264],"type":"Point"}
}