{
  "type": "Feature",
  "properties": {
    "iso:country":"US",
    "sg:address":"17525 Linscott Run Rd",
    "sg:city":"Amesville",
    "sg:classifiers":[
        {
            "category":"Restaurant",
            "type":"Food & Drink"
        }
    ],
    "sg:phone":"+1 740 448 7355",
    "sg:postcode":"45711",
    "sg:province":"OH",
    "sg:tags":[
        "eating"
    ],
    "wof:name":"Burrito Buggy",
    "wof:placetype":"venue"
},
  "geometry": {"coordinates":[-81.943319,39.430507],"type":"Point"}
}