{
  "type": "Feature",
  "properties": {
    "addr:full": "7067 Enfield Dr Mentor OH 44060",
    "addr:housenumber": "7067",
    "addr:postcode": "44060",
    "addr:street": "Enfield Dr",
    "iso:country": "US",
    "sg:address": "7067 Enfield Dr",
    "sg:city": "Mentor",
    "sg:classifiers": [
      {
        "category": "Wholesale",
        "subcategory": "Office Equipment",
        "type": "Manufacturing \u0026 Wholesale Goods"
      }
    ],
    "sg:phone": "+1 440 951 0637",
    "sg:postcode": "44060",
    "sg:province": "OH",
    "sg:tags": [
      "machine",
      "duplicating",
      "copying"
    ],
    "wof:name": "Diversified Office Machines",
    "wof:placetype": "venue"
  },
  "geometry": {"coordinates":[-81.387996,41.670428],"type":"Point"}
}
