{
  "type": "Feature",
  "properties": {
    "iso:country":"US",
    "sg:address":"7067 Enfield Dr",
    "sg:city":"Mentor",
    "sg:classifiers":[
        {
            "category":"Wholesale",
            "subcategory":"Office Equipment",
            "type":"Manufacturing & Wholesale Goods"
        }
    ],
    "sg:phone":"+1 440 951 0637",
    "sg:postcode":"44060",
    "sg:province":"OH",
    "sg:tags":[
        "machine",
        "duplicating",
        "copying"
    ],
    "wof:name":"Diversified Office Machines",
    "wof:placetype":"venue"
},
  "geometry": {"coordinates":[-81.387996,41.670428],"type":"Point"}
}