{
  "type": "Feature",
  "properties": {
    "iso:country":"US",
    "sg:address":"2349 Carousel Ct",
    "sg:city":"Westlake",
    "sg:classifiers":[
        {
            "category":"Restaurant",
            "type":"Food & Drink"
        }
    ],
    "sg:phone":"+1 440 835 0703",
    "sg:postcode":"44145",
    "sg:province":"OH",
    "sg:tags":[
        "eating"
    ],
    "wof:name":"Dogs At Play Inc",
    "wof:placetype":"venue"
},
  "geometry": {"coordinates":[-81.934408,41.454213],"type":"Point"}
}