{
  "type": "Feature",
  "properties": {
    "iso:country":"US",
    "sg:address":"6544 Lake Rd W",
    "sg:city":"Ashtabula",
    "sg:classifiers":[
        {
            "category":"Shopping",
            "subcategory":"Books",
            "type":"Retail Goods"
        }
    ],
    "sg:phone":"+1 440 964 5505",
    "sg:postcode":"44004",
    "sg:province":"OH",
    "wof:name":"Java Books",
    "wof:placetype":"venue"
},
  "geometry": {"coordinates":[-80.889303,41.871864],"type":"Point"}
}