{
  "type": "Feature",
  "properties": {
    "addr:full":"1020 Cleveland Rd E Huron OH 44839",
    "addr:housenumber":"1020",
    "addr:postcode":"44839",
    "addr:street":"Cleveland Rd E",
    "iso:country":"US",
    "sg:address":"1020 Cleveland Rd E",
    "sg:city":"Huron",
    "sg:classifiers":[
        {
            "category":"Wholesale",
            "subcategory":"Apparel",
            "type":"Manufacturing & Wholesale Goods"
        }
    ],
    "sg:phone":"+1 419 433 4043",
    "sg:postcode":"44839",
    "sg:province":"OH",
    "sg:tags":[
        "piece"
    ],
    "wof:name":"Bridal Collection",
    "wof:placetype":"venue"
},
  "geometry": {"coordinates":[-82.534609,41.387731],"type":"Point"}
}