{
  "type": "Feature",
  "properties": {
    "iso:country":"US",
    "sg:address":"6565 E Livingston Ave",
    "sg:city":"Reynoldsburg",
    "sg:classifiers":[
        {
            "category":"Retail",
            "subcategory":"Veterinary Services",
            "type":"Services"
        }
    ],
    "sg:phone":"+1 614 868 0350",
    "sg:postcode":"43068",
    "sg:province":"OH",
    "sg:tags":[
        "specialty"
    ],
    "wof:name":"Blackbick V Center",
    "wof:placetype":"venue"
},
  "geometry": {"coordinates":[-82.81986000000001,39.94311],"type":"Point"}
}