{
  "type": "Feature",
  "properties": {
    "addr:full": "6565 E Livingston Ave Reynoldsburg OH 43068",
    "addr:housenumber": "6565",
    "addr:postcode": "43068",
    "addr:street": "E Livingston Ave",
    "iso:country": "US",
    "sg:address": "6565 E Livingston Ave",
    "sg:city": "Reynoldsburg",
    "sg:classifiers": [
      {
        "category": "Retail",
        "subcategory": "Veterinary Services",
        "type": "Services"
      }
    ],
    "sg:phone": "+1 614 868 0350",
    "sg:postcode": "43068",
    "sg:province": "OH",
    "sg:tags": [
      "specialty"
    ],
    "wof:name": "Blackbick V Center",
    "wof:placetype": "venue"
  },
  "geometry": {"coordinates":[-82.81986,39.94311],"type":"Point"}
}
