{
  "type": "Feature",
  "properties": {
    "addr:full": "13967 Cedar Rd Cleveland OH 44118",
    "addr:housenumber": "13967",
    "addr:postcode": "44118",
    "addr:street": "Cedar Rd",
    "iso:country": "US",
    "sg:address": "13967 Cedar Rd",
    "sg:city": "Cleveland",
    "sg:classifiers": [
      {
        "category": "Insurance",
        "subcategory": "Insurance Agent",
        "type": "Services"
      }
    ],
    "sg:phone": "+1 216 397 5890",
    "sg:postcode": "44118",
    "sg:province": "OH",
    "wof:name": "Kozuch Insurance Services",
    "wof:placetype": "venue"
  },
  "geometry": {"coordinates":[-81.538204,41.501428],"type":"Point"}
}
