{
  "type": "Feature",
  "properties": {
    "iso:country":"US",
    "sg:address":"13967 Cedar Rd",
    "sg:city":"Cleveland",
    "sg:classifiers":[
        {
            "category":"Insurance",
            "subcategory":"Insurance Agent",
            "type":"Services"
        }
    ],
    "sg:phone":"+1 216 397 5890",
    "sg:postcode":"44118",
    "sg:province":"OH",
    "wof:name":"Kozuch Insurance Services",
    "wof:placetype":"venue"
},
  "geometry": {"coordinates":[-81.53820399999999,41.501428],"type":"Point"}
}