{
  "type": "Feature",
  "properties": {
    "addr:full":"444 2nd Ave Gallipolis OH 45631",
    "addr:housenumber":"444",
    "addr:postcode":"45631",
    "addr:street":"2Nd Ave",
    "iso:country":"US",
    "sg:address":"444 2nd Ave",
    "sg:city":"Gallipolis",
    "sg:classifiers":[
        {
            "category":"Professional",
            "subcategory":"Accounting & Tax Preparation",
            "type":"Services"
        }
    ],
    "sg:phone":"+1 740 446 4549",
    "sg:postcode":"45631",
    "sg:province":"OH",
    "sg:tags":[
        "accountant"
    ],
    "wof:name":"Black's Advisory Svc Inc",
    "wof:placetype":"venue"
},
  "geometry": {"coordinates":[-82.204223,38.808722],"type":"Point"}
}