{
  "type": "Feature",
  "properties": {
    "addr:full":"1 Mount Vernon Ave Mt Vernon OH 43050",
    "addr:housenumber":"1",
    "addr:postcode":"43050",
    "addr:street":"Mount Vernon Ave",
    "iso:country":"US",
    "sg:address":"1 Mount Vernon Ave",
    "sg:city":"Mt Vernon",
    "sg:classifiers":[
        {
            "category":"Banks & Credit Unions",
            "subcategory":"Investment Brokerage",
            "type":"Services"
        }
    ],
    "sg:phone":"+1 740 392 7177",
    "sg:postcode":"43050",
    "sg:province":"OH",
    "sg:tags":[
        "consultant",
        "planning",
        "financial"
    ],
    "wof:name":"Money Concepts",
    "wof:placetype":"venue"
},
  "geometry": {"coordinates":[-82.485495,40.384826],"type":"Point"}
}