{
  "type": "Feature",
  "properties": {
    "iso:country":"US",
    "sg:address":"2110 S Main St",
    "sg:city":"Middletown",
    "sg:classifiers":[
        {
            "category":"Insurance",
            "subcategory":"Insurance Agent",
            "type":"Services"
        }
    ],
    "sg:phone":"+1 513 423 5008",
    "sg:postcode":"45044",
    "sg:province":"OH",
    "sg:tags":[
        "business"
    ],
    "wof:name":"Best Bail Bonds",
    "wof:placetype":"venue"
},
  "geometry": {"coordinates":[-84.41874799999999,39.493164],"type":"Point"}
}