{
  "type": "Feature",
  "properties": {
    "addr:full": "130 Smokerise Dr Wadsworth OH 44281",
    "addr:housenumber": "130",
    "addr:postcode": "44281",
    "addr:street": "Smokerise Dr",
    "iso:country": "US",
    "sg:address": "130 Smokerise Dr",
    "sg:city": "Wadsworth",
    "sg:classifiers": [
      {
        "category": "Restaurant",
        "type": "Food \u0026 Drink"
      }
    ],
    "sg:menulink": "http://www.allmenus.com/oh/wadsworth/238954-maries/menu/",
    "sg:phone": "+1 330 334 1030",
    "sg:postcode": "44281",
    "sg:province": "OH",
    "sg:tags": [
      "american"
    ],
    "wof:name": "Marie's",
    "wof:placetype": "venue"
  },
  "geometry": {"coordinates":[-81.730202,41.052068],"type":"Point"}
}
