{
  "type": "Feature",
  "properties": {
    "iso:country":"US",
    "sg:address":"130 Smokerise Dr",
    "sg:city":"Wadsworth",
    "sg:classifiers":[
        {
            "category":"Restaurant",
            "type":"Food & Drink"
        }
    ],
    "sg:menulink":"http://www.allmenus.com/oh/wadsworth/238954-maries/menu/",
    "sg:phone":"+1 330 334 1030",
    "sg:postcode":"44281",
    "sg:province":"OH",
    "sg:tags":[
        "american"
    ],
    "wof:name":"Marie's",
    "wof:placetype":"venue"
},
  "geometry": {"coordinates":[-81.73020200000001,41.052068],"type":"Point"}
}