{
  "type": "Feature",
  "properties": {
    "addr:full": "1911 Kendall Pl Grove City OH 43123",
    "addr:housenumber": "1911",
    "addr:postcode": "43123",
    "addr:street": "Kendall Pl",
    "iso:country": "US",
    "sg:address": "1911 Kendall Pl",
    "sg:city": "Grove City",
    "sg:classifiers": [
      {
        "category": "Real Estate",
        "subcategory": "Real Estate Operator",
        "type": "Services"
      }
    ],
    "sg:phone": "+1 614 871 0071",
    "sg:postcode": "43123",
    "sg:province": "OH",
    "sg:tags": [
      "apartment"
    ],
    "wof:name": "Park Place Of Grove City",
    "wof:placetype": "venue"
  },
  "geometry": {"coordinates":[-83.05404,39.875256],"type":"Point"}
}
