{
  "type": "Feature",
  "properties": {
    "addr:full":"2129 N Michigan St Toledo OH 43611",
    "addr:housenumber":"2129",
    "addr:postcode":"43611",
    "addr:street":"N Michigan St",
    "iso:country":"US",
    "sg:address":"2129 N Michigan St",
    "sg:city":"Toledo",
    "sg:classifiers":[
        {
            "category":"Organizations",
            "subcategory":"Religious Organization",
            "type":"Services"
        }
    ],
    "sg:phone":"+1 419 726 7021",
    "sg:postcode":"43611",
    "sg:province":"OH",
    "sg:tags":[
        "clergy"
    ],
    "wof:name":"Russell Dicken",
    "wof:placetype":"venue"
},
  "geometry": {"coordinates":[-83.509485,41.673831],"type":"Point"}
}