{
  "type": "Feature",
  "properties": {
    "iso:country":"US",
    "sg:address":"44 Twp Rd 1290",
    "sg:city":"Chesapeake",
    "sg:classifiers":[
        {
            "category":"Building & Trades",
            "subcategory":"Equipment Rental",
            "type":"Services"
        }
    ],
    "sg:phone":"+1 740 867 2401",
    "sg:postcode":"45619",
    "sg:province":"OH",
    "sg:tags":[
        "contractor"
    ],
    "wof:name":"TMC Backhoe Rental",
    "wof:placetype":"venue"
},
  "geometry": {"coordinates":[-82.403471,38.448887],"type":"Point"}
}