{
  "type": "Feature",
  "properties": {
    "iso:country":"US",
    "sg:address":"68 N High St",
    "sg:city":"New Albany",
    "sg:classifiers":[
        {
            "category":"Organizations",
            "subcategory":"Religious Organization",
            "type":"Services"
        }
    ],
    "sg:phone":"+1 614 933 9680",
    "sg:postcode":"43054",
    "sg:province":"OH",
    "sg:tags":[
        "church"
    ],
    "wof:name":"New Albany Presbyterian Church",
    "wof:placetype":"venue"
},
  "geometry": {"coordinates":[-82.808661,40.082812],"type":"Point"}
}