{
  "type": "Feature",
  "properties": {
    "iso:country":"US",
    "sg:address":"3230 Venice Rd",
    "sg:city":"Sandusky",
    "sg:classifiers":[
        {
            "category":"Travel",
            "subcategory":"Hotels & Motels",
            "type":"Entertainment"
        }
    ],
    "sg:phone":"+1 419 625 7862",
    "sg:postcode":"44870",
    "sg:province":"OH",
    "wof:name":"Sundown Motel",
    "wof:placetype":"venue"
},
  "geometry": {"coordinates":[-82.744535,41.440933],"type":"Point"}
}