{
  "type": "Feature",
  "properties": {
    "addr:full": "3230 Venice Rd Sandusky OH 44870",
    "addr:housenumber": "3230",
    "addr:postcode": "44870",
    "addr:street": "Venice Rd",
    "iso:country": "US",
    "sg:address": "3230 Venice Rd",
    "sg:city": "Sandusky",
    "sg:classifiers": [
      {
        "category": "Travel",
        "subcategory": "Hotels \u0026 Motels",
        "type": "Entertainment"
      }
    ],
    "sg:phone": "+1 419 625 7862",
    "sg:postcode": "44870",
    "sg:province": "OH",
    "wof:name": "Sundown Motel",
    "wof:placetype": "venue"
  },
  "geometry": {"coordinates":[-82.744535,41.440933],"type":"Point"}
}
