{
  "type": "Feature",
  "properties": {
    "iso:country":"US",
    "sg:address":"19524 Pigeon Roost Rd",
    "sg:city":"Howard",
    "sg:classifiers":[
        {
            "category":"Manufacturing",
            "subcategory":"Lumber",
            "type":"Manufacturing & Wholesale Goods"
        }
    ],
    "sg:phone":"+1 740 599 7301",
    "sg:postcode":"43028",
    "sg:province":"OH",
    "sg:tags":[
        "operation",
        "timber",
        "tract"
    ],
    "wof:name":"Rodney Hayden Farm",
    "wof:placetype":"venue"
},
  "geometry": {"coordinates":[-82.331881,40.514266],"type":"Point"}
}