{
  "type": "Feature",
  "properties": {
    "addr:full": "56 Foss Way Troy OH 45373",
    "addr:housenumber": "56",
    "addr:postcode": "45373",
    "addr:street": "Foss Way",
    "iso:country": "US",
    "sg:address": "56 Foss Way",
    "sg:city": "Troy",
    "sg:classifiers": [
      {
        "category": "Sports \u0026 Exercise",
        "subcategory": "Bowling",
        "type": "Entertainment"
      }
    ],
    "sg:phone": "+1 937 339 1601",
    "sg:postcode": "45373",
    "sg:province": "OH",
    "sg:tags": [
      "center"
    ],
    "wof:name": "Sherwood Lanes Inc",
    "wof:placetype": "venue"
  },
  "geometry": {"coordinates":[-84.194961,40.050101],"type":"Point"}
}
