{
  "type": "Feature",
  "properties": {
    "iso:country":"US",
    "sg:address":"56 Foss Way",
    "sg:city":"Troy",
    "sg:classifiers":[
        {
            "category":"Sports & Exercise",
            "subcategory":"Bowling",
            "type":"Entertainment"
        }
    ],
    "sg:phone":"+1 937 339 1601",
    "sg:postcode":"45373",
    "sg:province":"OH",
    "sg:tags":[
        "center"
    ],
    "wof:name":"Sherwood Lanes Inc",
    "wof:placetype":"venue"
},
  "geometry": {"coordinates":[-84.19496100000001,40.050101],"type":"Point"}
}