{
  "type": "Feature",
  "properties": {
    "addr:full":"5209 Prospect Ave Cleveland OH 44103",
    "addr:housenumber":"5209",
    "addr:postcode":"44103",
    "addr:street":"Prospect Ave",
    "iso:country":"US",
    "sg:address":"5209 Prospect Ave",
    "sg:city":"Cleveland",
    "sg:phone":"+1 216 431 6202",
    "sg:postcode":"44103",
    "sg:province":"OH",
    "sg:tags":[
        "equipment",
        "supply"
    ],
    "wof:name":"China Mist Iced Tea",
    "wof:placetype":"venue"
},
  "geometry": {"coordinates":[-81.65348400000001,41.502734],"type":"Point"}
}