{
  "type": "Feature",
  "properties": {
    "addr:full": "10177 International Blvd Cincinnati OH 45246",
    "addr:housenumber": "10177",
    "addr:postcode": "45246",
    "addr:street": "International Blvd",
    "iso:country": "US",
    "sg:address": "10177 International Blvd",
    "sg:city": "Cincinnati",
    "sg:classifiers": [
      {
        "category": "Real Estate",
        "subcategory": "Architect",
        "type": "Services"
      }
    ],
    "sg:phone": "+1 513 618 6050",
    "sg:postcode": "45246",
    "sg:province": "OH",
    "sg:tags": [
      "building",
      "construction"
    ],
    "wof:name": "Integrity Building Group",
    "wof:placetype": "venue"
  },
  "geometry": {"coordinates":[-84.443523,39.301694],"type":"Point"}
}
