{
  "type": "Feature",
  "properties": {
    "addr:full":"8755 Refugee Rd Pickerington OH 43147",
    "addr:housenumber":"8755",
    "addr:postcode":"43147",
    "addr:street":"Refugee Rd",
    "iso:country":"US",
    "sg:address":"8755 Refugee Rd",
    "sg:city":"Pickerington",
    "sg:classifiers":[
        {
            "category":"Professional",
            "subcategory":"Accounting & Tax Preparation",
            "type":"Services"
        }
    ],
    "sg:phone":"+1 614 837 7928",
    "sg:postcode":"43147",
    "sg:province":"OH",
    "sg:tags":[
        "bookkeeping",
        "general"
    ],
    "wof:name":"E K Williams & Co",
    "wof:placetype":"venue"
},
  "geometry": {"coordinates":[-82.754423,39.90857],"type":"Point"}
}