{
  "type": "Feature",
  "properties": {
    "addr:full":"422 Cleveland Rd E Huron OH 44839",
    "addr:housenumber":"422",
    "addr:postcode":"44839",
    "addr:street":"Cleveland Rd E",
    "iso:country":"US",
    "sg:address":"422 Cleveland Rd E",
    "sg:city":"Huron",
    "sg:classifiers":[
        {
            "category":"Shopping",
            "subcategory":"Used Merchandise",
            "type":"Retail Goods"
        }
    ],
    "sg:phone":"+1 419 433 7542",
    "sg:postcode":"44839",
    "sg:province":"OH",
    "wof:name":"Huron Goodwill Shopp",
    "wof:placetype":"venue"
},
  "geometry": {"coordinates":[-82.540752,41.388674],"type":"Point"}
}