{
  "type": "Feature",
  "properties": {
    "iso:country":"US",
    "sg:address":"3991 Medina Rd",
    "sg:city":"Akron",
    "sg:classifiers":[
        {
            "category":"Shopping",
            "subcategory":"Bicycles & Sporting Goods",
            "type":"Retail Goods"
        }
    ],
    "sg:phone":"+1 330 666 2453",
    "sg:postcode":"44333",
    "sg:province":"OH",
    "sg:tags":[
        "parts"
    ],
    "wof:name":"Eddys Bike Shop Inc",
    "wof:placetype":"venue"
},
  "geometry": {"coordinates":[-81.640355,41.135946],"type":"Point"}
}