{
  "type": "Feature",
  "properties": {
    "addr:full": "3991 Medina Rd Akron OH 44333",
    "addr:housenumber": "3991",
    "addr:postcode": "44333",
    "addr:street": "Medina Rd",
    "iso:country": "US",
    "sg:address": "3991 Medina Rd",
    "sg:city": "Akron",
    "sg:classifiers": [
      {
        "category": "Shopping",
        "subcategory": "Bicycles \u0026 Sporting Goods",
        "type": "Retail Goods"
      }
    ],
    "sg:phone": "+1 330 666 2453",
    "sg:postcode": "44333",
    "sg:province": "OH",
    "sg:tags": [
      "parts"
    ],
    "wof:name": "Eddys Bike Shop Inc",
    "wof:placetype": "venue"
  },
  "geometry": {"coordinates":[-81.640355,41.135946],"type":"Point"}
}
