{
  "type": "Feature",
  "properties": {
    "addr:full": "2955 Charter St Columbus OH 43228",
    "addr:housenumber": "2955",
    "addr:postcode": "43228",
    "addr:street": "Charter St",
    "iso:country": "US",
    "sg:address": "2955 Charter St",
    "sg:city": "Columbus",
    "sg:classifiers": [
      {
        "category": "Freight",
        "type": "Transportation"
      }
    ],
    "sg:phone": "+1 614 771 0224",
    "sg:postcode": "43228",
    "sg:province": "OH",
    "sg:tags": [
      "warehouse"
    ],
    "wof:name": "McLane",
    "wof:placetype": "venue"
  },
  "geometry": {"coordinates":[-83.134492,40.007359],"type":"Point"}
}
