{
  "type": "Feature",
  "properties": {
    "addr:full":"5070 Canfield Rd Canfield OH 44406",
    "addr:housenumber":"5070",
    "addr:postcode":"44406",
    "addr:street":"Canfield Rd",
    "iso:country":"US",
    "sg:address":"5070 Canfield Rd",
    "sg:city":"Canfield",
    "sg:classifiers":[
        {
            "category":"Freight",
            "type":"Transportation"
        }
    ],
    "sg:phone":"+1 330 793 8120",
    "sg:postcode":"44406",
    "sg:province":"OH",
    "sg:tags":[
        "commercial",
        "storage"
    ],
    "wof:name":"R T 45 Storage Solutions",
    "wof:placetype":"venue"
},
  "geometry": {"coordinates":[-80.734413,41.045988],"type":"Point"}
}