{
  "type": "Feature",
  "properties": {
    "addr:full": "16863 Boundry Rd Wapakoneta OH 45895",
    "addr:postcode": "16863;45895",
    "addr:street": "Boundry Rd",
    "iso:country": "US",
    "sg:address": "16863 Boundry Rd",
    "sg:city": "Wapakoneta",
    "sg:classifiers": [
      {
        "category": "Farming",
        "subcategory": "Livestock Farm",
        "type": "Manufacturing \u0026 Wholesale Goods"
      }
    ],
    "sg:phone": "+1 419 568 9400",
    "sg:postcode": "45895",
    "sg:province": "OH",
    "sg:tags": [
      "kennel"
    ],
    "wof:name": "Van Der Haus Kennel",
    "wof:placetype": "venue"
  },
  "geometry": {"coordinates":[-84.046178,40.599873],"type":"Point"}
}
