{
  "type": "Feature",
  "properties": {
    "addr:full":"153 Center St Seville OH 44273",
    "addr:housenumber":"153",
    "addr:postcode":"44273",
    "addr:street":"Center St",
    "iso:country":"US",
    "sg:address":"153 Center St",
    "sg:city":"Seville",
    "sg:classifiers":[
        {
            "category":"Building & Trades",
            "subcategory":"Construction",
            "type":"Services"
        }
    ],
    "sg:phone":"+1 330 769 8029",
    "sg:postcode":"44273",
    "sg:province":"OH",
    "sg:tags":[
        "hanging",
        "contractor"
    ],
    "wof:name":"Rescue Painting",
    "wof:placetype":"venue"
},
  "geometry": {"coordinates":[-81.86188900000001,41.018717],"type":"Point"}
}