{
  "type": "Feature",
  "properties": {
    "addr:full":"11228 Detroit Ave Cleveland OH 44102",
    "addr:housenumber":"11228",
    "addr:postcode":"44102",
    "addr:street":"Detroit Ave",
    "iso:country":"US",
    "sg:address":"11228 Detroit Ave",
    "sg:city":"Cleveland",
    "sg:classifiers":[
        {
            "category":"Organizations",
            "subcategory":"Religious Organization",
            "type":"Services"
        }
    ],
    "sg:phone":"+1 216 228 2273",
    "sg:postcode":"44102",
    "sg:province":"OH",
    "sg:tags":[
        "church"
    ],
    "wof:name":"Our Father's House",
    "wof:placetype":"venue"
},
  "geometry": {"coordinates":[-81.76600500000001,41.48298],"type":"Point"}
}