{
  "type": "Feature",
  "properties": {
    "iso:country":"US",
    "sg:address":"309 E Stroop Rd",
    "sg:city":"Dayton",
    "sg:classifiers":[
        {
            "category":"Health Services",
            "subcategory":"Doctor",
            "type":"Services"
        }
    ],
    "sg:phone":"+1 937 294 4343",
    "sg:postcode":"45429",
    "sg:province":"OH",
    "sg:tags":[
        "dentist"
    ],
    "wof:name":"William D Borchers DDS",
    "wof:placetype":"venue"
},
  "geometry": {"coordinates":[-84.163465,39.689516],"type":"Point"}
}