{
  "type": "Feature",
  "properties": {
    "iso:country":"US",
    "sg:address":"4892 Pearl Rd",
    "sg:city":"Cleveland",
    "sg:classifiers":[
        {
            "category":"Shopping",
            "subcategory":"Florist",
            "type":"Retail Goods"
        }
    ],
    "sg:phone":"+1 216 398 5400",
    "sg:postcode":"44109",
    "sg:province":"OH",
    "wof:name":"Cantius Flowers",
    "wof:placetype":"venue"
},
  "geometry": {"coordinates":[-81.72162299999999,41.42443],"type":"Point"}
}