{
  "type": "Feature",
  "properties": {
    "addr:full":"4540 Heatherdowns Blvd Toledo OH 43614",
    "addr:housenumber":"4540",
    "addr:postcode":"43614",
    "addr:street":"Heatherdowns Blvd",
    "iso:country":"US",
    "sg:address":"4540 Heatherdowns Blvd",
    "sg:city":"Toledo",
    "sg:classifiers":[
        {
            "category":"Professional",
            "subcategory":"Lawyer & Legal Services",
            "type":"Services"
        }
    ],
    "sg:phone":"+1 419 891 8884",
    "sg:postcode":"43614",
    "sg:province":"OH",
    "sg:tags":[
        "attorney"
    ],
    "wof:name":"Bayer Papay & Steiner",
    "wof:placetype":"venue"
},
  "geometry": {"coordinates":[-83.64676900000001,41.594352],"type":"Point"}
}