{
  "type": "Feature",
  "properties": {
    "addr:full":"400 Decatur St Kenton OH 43326",
    "addr:housenumber":"400",
    "addr:postcode":"43326",
    "addr:street":"Decatur St",
    "iso:country":"US",
    "sg:address":"400 Decatur St",
    "sg:city":"Kenton",
    "sg:classifiers":[
        {
            "category":"Education",
            "subcategory":"School",
            "type":"Public Place"
        }
    ],
    "sg:phone":"+1 419 673 0775",
    "sg:postcode":"43326",
    "sg:province":"OH",
    "sg:website":"www.kenton.k12.oh.us",
    "wof:name":"Kenton Board Of Education",
    "wof:placetype":"venue"
},
  "geometry": {"coordinates":[-83.603437,40.643656],"type":"Point"}
}