{
  "type": "Feature",
  "properties": {
    "addr:full": "3355 Westgate Cleveland OH 44126",
    "addr:housenumber": "3355",
    "addr:postcode": "44126",
    "addr:street": "Westgate",
    "iso:country": "US",
    "sg:address": "3355 Westgate",
    "sg:city": "Cleveland",
    "sg:classifiers": [
      {
        "category": "Shopping",
        "subcategory": "Jewelry",
        "type": "Retail Goods"
      }
    ],
    "sg:phone": "+1 440 331 2865",
    "sg:postcode": "44126",
    "sg:province": "OH",
    "sg:tags": [
      "jeweler"
    ],
    "wof:name": "Rogers Jewelers",
    "wof:placetype": "venue"
  },
  "geometry": {"coordinates":[-81.852795,41.458355],"type":"Point"}
}
