{
  "type": "Feature",
  "properties": {
    "addr:full": "8500 Eagle Rd Willoughby OH 44094",
    "addr:housenumber": "8500",
    "addr:postcode": "44094",
    "addr:street": "Eagle Rd",
    "iso:country": "US",
    "sg:address": "8500 Eagle Rd",
    "sg:city": "Willoughby",
    "sg:classifiers": [
      {
        "category": "Health Services",
        "subcategory": "Clinic",
        "type": "Services"
      }
    ],
    "sg:phone": "+1 440 256 2273",
    "sg:postcode": "44094",
    "sg:province": "OH",
    "sg:tags": [
      "holistic",
      "practitioner"
    ],
    "wof:name": "Prisma Center",
    "wof:placetype": "venue"
  },
  "geometry": {"coordinates":[-81.335038,41.604543],"type":"Point"}
}
