{
  "type": "Feature",
  "properties": {
    "iso:country":"US",
    "sg:address":"7787 Mentor Ave",
    "sg:city":"Mentor",
    "sg:classifiers":[
        {
            "category":"Shopping",
            "subcategory":"Optical Goods",
            "type":"Retail Goods"
        }
    ],
    "sg:phone":"+1 440 942 7714",
    "sg:postcode":"44060",
    "sg:province":"OH",
    "wof:name":"Union Eye Care",
    "wof:placetype":"venue"
},
  "geometry": {"coordinates":[-81.359221,41.661553],"type":"Point"}
}