{
  "type": "Feature",
  "properties": {
    "addr:full":"940 Rome Greenwich Rd New London OH 44851",
    "addr:housenumber":"940",
    "addr:postcode":"44851",
    "addr:street":"Rome Greenwich Rd",
    "iso:country":"US",
    "sg:address":"940 Rome Greenwich Rd",
    "sg:city":"New London",
    "sg:phone":"+1 419 929 3883",
    "sg:postcode":"44851",
    "sg:province":"OH",
    "sg:tags":[
        "farm",
        "corn",
        "soybean"
    ],
    "wof:name":"Herman Crecelius",
    "wof:placetype":"venue"
},
  "geometry": {"coordinates":[-82.513904,41.11391],"type":"Point"}
}