{
  "type": "Feature",
  "properties": {
    "addr:full":"941 Westport Dr Youngstown OH 44511",
    "addr:housenumber":"941",
    "addr:postcode":"44511",
    "addr:street":"Westport Dr",
    "iso:country":"US",
    "sg:address":"941 Westport Dr",
    "sg:city":"Youngstown",
    "sg:classifiers":[
        {
            "category":"Real Estate",
            "subcategory":"Real Estate Services",
            "type":"Services"
        },
        {
            "category":"Real Estate",
            "subcategory":"Real Estate Agent",
            "type":"Services"
        }
    ],
    "sg:phone":"+1 330 783 1869",
    "sg:postcode":"44511",
    "sg:province":"OH",
    "sg:tags":[
        "buyer",
        "broker"
    ],
    "sg:website":"http://www.beauquest.com",
    "wof:name":"Transpacific International",
    "wof:placetype":"venue"
},
  "geometry": {"coordinates":[-80.690515,41.048413],"type":"Point"}
}