{
  "type": "Feature",
  "properties": {
    "iso:country":"US",
    "sg:address":"1126 E Mcmillan St",
    "sg:city":"Cincinnati",
    "sg:classifiers":[
        {
            "category":"Restaurant",
            "type":"Food & Drink"
        }
    ],
    "sg:menulink":"http://www.allmenus.com/oh/cincinnati/194883-mcdonalds/menu/",
    "sg:postcode":"45206",
    "sg:province":"OH",
    "sg:tags":[
        "burger",
        "american"
    ],
    "wof:name":"McDonald's",
    "wof:placetype":"venue"
},
  "geometry": {"coordinates":[-84.48490099999999,39.125888],"type":"Point"}
}