{
  "type": "Feature",
  "properties": {
    "addr:full": "1310 Pendleton St Cincinnati OH 45202",
    "addr:housenumber": "1310",
    "addr:postcode": "45202",
    "addr:street": "Pendleton St",
    "iso:country": "US",
    "sg:address": "1310 Pendleton St",
    "sg:city": "Cincinnati",
    "sg:classifiers": [
      {
        "category": "Professional",
        "type": "Services"
      }
    ],
    "sg:phone": "+1 513 665 9888",
    "sg:postcode": "45202",
    "sg:province": "OH",
    "sg:tags": [
      "arts",
      "artist"
    ],
    "wof:name": "Christopher Brian's Fine Arts",
    "wof:placetype": "venue"
  },
  "geometry": {"coordinates":[-84.50705,39.111187],"type":"Point"}
}
