{
  "type": "Feature",
  "properties": {
    "iso:country":"US",
    "sg:address":"8103 Cincinnati Dayton Rd",
    "sg:city":"West Chester",
    "sg:classifiers":[
        {
            "category":"Restaurant",
            "type":"Food & Drink"
        }
    ],
    "sg:menulink":"http://www.allmenus.com/oh/west-chester/83345-papa-johns-pizza/menu/",
    "sg:phone":"+1 513 777 4400",
    "sg:postcode":"45069",
    "sg:province":"OH",
    "sg:tags":[
        "american",
        "pizza"
    ],
    "wof:name":"Papa John's Pizza",
    "wof:placetype":"venue"
},
  "geometry": {"coordinates":[-84.395921,39.349537],"type":"Point"}
}