{
  "type": "Feature",
  "properties": {
    "addr:full":"885 S Hamilton Rd Columbus OH 43213",
    "addr:housenumber":"885",
    "addr:postcode":"43213",
    "addr:street":"S Hamilton Rd",
    "iso:country":"US",
    "sg:address":"885 S Hamilton Rd",
    "sg:city":"Columbus",
    "sg:classifiers":[
        {
            "category":"Restaurant",
            "type":"Food & Drink"
        }
    ],
    "sg:phone":"+1 614 231 7357",
    "sg:postcode":"43213",
    "sg:province":"OH",
    "wof:name":"Indochine Cafe",
    "wof:placetype":"venue"
},
  "geometry": {"coordinates":[-82.876811,39.956536],"type":"Point"}
}