{
  "type": "Feature",
  "properties": {
    "addr:full": "4160 Mayfield Rd Cleveland OH 44121",
    "addr:housenumber": "4160",
    "addr:postcode": "44121",
    "addr:street": "Mayfield Rd",
    "iso:country": "US",
    "sg:address": "4160 Mayfield Rd",
    "sg:city": "Cleveland",
    "sg:classifiers": [
      {
        "category": "Personal",
        "subcategory": "Beauty Salon",
        "type": "Services"
      }
    ],
    "sg:phone": "+1 216 381 9639",
    "sg:postcode": "44121",
    "sg:province": "OH",
    "wof:name": "Silhouette's By Ms B",
    "wof:placetype": "venue"
  },
  "geometry": {"coordinates":[-81.530305,41.520676],"type":"Point"}
}
