{
  "type": "Feature",
  "properties": {
    "addr:full": "2122 Brown Rd Cleveland OH 44107",
    "addr:housenumber": "2122",
    "addr:postcode": "44107",
    "addr:street": "Brown Rd",
    "iso:country": "US",
    "sg:address": "2122 Brown Rd",
    "sg:city": "Cleveland",
    "sg:classifiers": [
      {
        "category": "Professional",
        "subcategory": "Advertising",
        "type": "Services"
      }
    ],
    "sg:phone": "+1 216 226 4834",
    "sg:postcode": "44107",
    "sg:province": "OH",
    "sg:tags": [
      "distribution"
    ],
    "wof:name": "M E Sales",
    "wof:placetype": "venue"
  },
  "geometry": {"coordinates":[-81.792111,41.473563],"type":"Point"}
}
