{
  "type": "Feature",
  "properties": {
    "iso:country":"US",
    "sg:address":"2510 Medina Rd",
    "sg:city":"Medina",
    "sg:classifiers":[
        {
            "category":"Freight",
            "type":"Transportation"
        }
    ],
    "sg:phone":"+1 330 723 5700",
    "sg:postcode":"44256",
    "sg:province":"OH",
    "sg:tags":[
        "commercial",
        "storage"
    ],
    "wof:name":"Great Lake Self-Storage",
    "wof:placetype":"venue"
},
  "geometry": {"coordinates":[-81.777186,41.136165],"type":"Point"}
}