{
  "type": "Feature",
  "properties": {
    "addr:full": "2508 Summit St Columbus OH 43202",
    "addr:housenumber": "2508",
    "addr:postcode": "43202",
    "addr:street": "Summit St",
    "iso:country": "US",
    "sg:address": "2508 Summit St",
    "sg:city": "Columbus",
    "sg:classifiers": [
      {
        "category": "Real Estate",
        "subcategory": "Real Estate Agent",
        "type": "Services"
      }
    ],
    "sg:phone": "+1 614 262 5900",
    "sg:postcode": "43202",
    "sg:province": "OH",
    "wof:name": "R J Chappelear \u0026 Co",
    "wof:placetype": "venue"
  },
  "geometry": {"coordinates":[-83.00005,40.014507],"type":"Point"}
}
