{
  "type": "Feature",
  "properties": {
    "addr:full":"10885 Indeco Dr Cincinnati OH 45241",
    "addr:housenumber":"10885",
    "addr:postcode":"45241",
    "addr:street":"Indeco Dr",
    "iso:country":"US",
    "sg:address":"10885 Indeco Dr",
    "sg:city":"Cincinnati",
    "sg:classifiers":[
        {
            "category":"Wholesale",
            "subcategory":"Machinery & Supplies",
            "type":"Manufacturing & Wholesale Goods"
        }
    ],
    "sg:phone":"+1 513 793 8010",
    "sg:postcode":"45241",
    "sg:province":"OH",
    "sg:tags":[
        "industrial"
    ],
    "wof:name":"Buckeye Industrial Supply Co",
    "wof:placetype":"venue"
},
  "geometry": {"coordinates":[-84.388345,39.261754],"type":"Point"}
}