{
  "type": "Feature",
  "properties": {
    "addr:full":"3220 Dixie Hwy Fairfield OH 45014",
    "addr:housenumber":"3220",
    "addr:postcode":"45014",
    "addr:street":"Dixie Hwy",
    "iso:country":"US",
    "sg:address":"3220 Dixie Hwy",
    "sg:city":"Fairfield",
    "sg:classifiers":[
        {
            "category":"Bars & Pubs",
            "type":"Food & Drink"
        }
    ],
    "sg:phone":"+1 513 863 6320",
    "sg:postcode":"45014",
    "sg:province":"OH",
    "sg:tags":[
        "club",
        "night"
    ],
    "wof:name":"Hummer's Night Club",
    "wof:placetype":"venue"
},
  "geometry": {"coordinates":[-84.54326399999999,39.362595],"type":"Point"}
}