{
  "type": "Feature",
  "properties": {
    "addr:full":"2550 Echo Valley Dr Dayton OH 45434",
    "addr:housenumber":"2550",
    "addr:postcode":"45434",
    "addr:street":"Echo Valley Dr",
    "iso:country":"US",
    "sg:address":"2550 Echo Valley Dr",
    "sg:city":"Dayton",
    "sg:classifiers":[
        {
            "category":"Freight",
            "type":"Transportation"
        }
    ],
    "sg:phone":"+1 937 586 9960",
    "sg:postcode":"45434",
    "sg:province":"OH",
    "sg:tags":[
        "delivery"
    ],
    "wof:name":"21st Century Charter Inc",
    "wof:placetype":"venue"
},
  "geometry": {"coordinates":[-84.031195,39.72414],"type":"Point"}
}