{
  "type": "Feature",
  "properties": {
    "addr:full":"203 Potomac Ave Tallmadge OH 44278",
    "addr:housenumber":"203",
    "addr:postcode":"44278",
    "addr:street":"Potomac Ave",
    "iso:country":"US",
    "sg:address":"203 Potomac Ave",
    "sg:city":"Tallmadge",
    "sg:classifiers":[
        {
            "category":"Retail",
            "subcategory":"Auto Repair",
            "type":"Services"
        }
    ],
    "sg:phone":"+1 330 633 0059",
    "sg:postcode":"44278",
    "sg:province":"OH",
    "sg:tags":[
        "repairing",
        "automobile"
    ],
    "wof:name":"Ralph's Auto Care",
    "wof:placetype":"venue"
},
  "geometry": {"coordinates":[-81.461169,41.097329],"type":"Point"}
}