{
  "type": "Feature",
  "properties": {
    "iso:country":"US",
    "sg:address":"216 Runkle St",
    "sg:city":"West Liberty",
    "sg:classifiers":[
        {
            "category":"Retail",
            "subcategory":"Repair Shop",
            "type":"Services"
        },
        {
            "category":"Retail",
            "subcategory":"Auto Repair",
            "type":"Services"
        }
    ],
    "sg:phone":"+1 937 592 4575",
    "sg:postcode":"43357",
    "sg:province":"OH",
    "sg:tags":[
        "industrial",
        "mfg",
        "automobile",
        "general",
        "machine",
        "r",
        "machinery"
    ],
    "wof:name":"Wilguss Automotive Machine",
    "wof:placetype":"venue"
},
  "geometry": {"coordinates":[-83.758618,40.251321],"type":"Point"}
}