{
  "type": "Feature",
  "properties": {
    "addr:full": "1366 Briarcliff Rd Reynoldsburg OH 43068",
    "addr:housenumber": "1366",
    "addr:postcode": "43068",
    "addr:street": "Briarcliff Rd",
    "iso:country": "US",
    "sg:address": "1366 Briarcliff Rd",
    "sg:city": "Reynoldsburg",
    "sg:classifiers": [
      {
        "category": "Real Estate",
        "subcategory": "Real Estate Operator",
        "type": "Services"
      }
    ],
    "sg:phone": "+1 614 861 8897",
    "sg:postcode": "43068",
    "sg:province": "OH",
    "sg:tags": [
      "building",
      "apartment"
    ],
    "wof:name": "Briarcliff Plaza",
    "wof:placetype": "venue"
  },
  "geometry": {"coordinates":[-82.811827,39.954602],"type":"Point"}
}
