{
  "type": "Feature",
  "properties": {
    "iso:country":"US",
    "sg:address":"4001 Rosslyn Dr",
    "sg:city":"Cincinnati",
    "sg:classifiers":[
        {
            "category":"Professional",
            "type":"Services"
        }
    ],
    "sg:phone":"+1 513 527 5732",
    "sg:postcode":"45209",
    "sg:province":"OH",
    "sg:tags":[
        "establishment"
    ],
    "wof:name":"Schierland & Schierland",
    "wof:placetype":"venue"
},
  "geometry": {"coordinates":[-84.40861200000001,39.152367],"type":"Point"}
}