{
  "type": "Feature",
  "properties": {
    "addr:full":"123 S Forge St Akron OH 44308",
    "addr:housenumber":"123",
    "addr:postcode":"44308",
    "addr:street":"S Forge St",
    "iso:country":"US",
    "sg:address":"123 S Forge St",
    "sg:city":"Akron",
    "sg:classifiers":[
        {
            "category":"Education",
            "subcategory":"School",
            "type":"Public Place"
        }
    ],
    "sg:phone":"+1 330 761 1605",
    "sg:postcode":"44308",
    "sg:province":"OH",
    "wof:name":"Central Hower High School",
    "wof:placetype":"venue"
},
  "geometry": {"coordinates":[-81.51168199999999,41.079177],"type":"Point"}
}