{
  "type": "Feature",
  "properties": {
    "addr:full":"5007 State Rte 416 SE New Philadelphia OH 44663",
    "addr:housenumber":"5007",
    "addr:postcode":"44663",
    "addr:street":"State Rte 416 Se",
    "iso:country":"US",
    "sg:address":"5007 State Rte 416 SE",
    "sg:city":"New Philadelphia",
    "sg:classifiers":[
        {
            "category":"Building & Trades",
            "subcategory":"Construction",
            "type":"Services"
        }
    ],
    "sg:phone":"+1 740 922 0986",
    "sg:postcode":"44663",
    "sg:province":"OH",
    "sg:tags":[
        "house"
    ],
    "wof:name":"Randy Tschudy Contracting",
    "wof:placetype":"venue"
},
  "geometry": {"coordinates":[-81.407375,40.407321],"type":"Point"}
}