{
  "type": "Feature",
  "properties": {
    "addr:full": "2225 Montego Blvd Columbus OH 43235",
    "addr:housenumber": "2225",
    "addr:postcode": "43235",
    "addr:street": "Montego Blvd",
    "iso:country": "US",
    "sg:address": "2225 Montego Blvd",
    "sg:city": "Columbus",
    "sg:classifiers": [
      {
        "category": "Real Estate",
        "subcategory": "Real Estate Agent",
        "type": "Services"
      }
    ],
    "sg:phone": "+1 614 457 8919",
    "sg:postcode": "43235",
    "sg:province": "OH",
    "wof:name": "Island Club Apts",
    "wof:placetype": "venue"
  },
  "geometry": {"coordinates":[-83.076938,40.06711],"type":"Point"}
}
