{
  "type": "Feature",
  "properties": {
    "addr:full":"2130 Hayes Ave Sandusky OH 44870",
    "addr:housenumber":"2130",
    "addr:postcode":"44870",
    "addr:street":"Hayes Ave",
    "iso:country":"US",
    "sg:address":"2130 Hayes Ave",
    "sg:city":"Sandusky",
    "sg:classifiers":[
        {
            "category":"Government",
            "subcategory":"Office",
            "type":"Public Place"
        }
    ],
    "sg:phone":"+1 419 625 6019",
    "sg:postcode":"44870",
    "sg:province":"OH",
    "sg:tags":[
        "county"
    ],
    "wof:name":"Erie County Orthopedically Hnd",
    "wof:placetype":"venue"
},
  "geometry": {"coordinates":[-82.713928,41.435066],"type":"Point"}
}