{
  "type": "Feature",
  "properties": {
    "addr:full": "419 Co Rd 18 Napoleon OH 43545",
    "addr:housenumber": "419;18",
    "addr:postcode": "43545",
    "addr:street": "Co Rd",
    "iso:country": "US",
    "sg:address": "419 Co Rd 18",
    "sg:city": "Napoleon",
    "sg:phone": "+1 419 267 3676",
    "sg:postcode": "43545",
    "sg:province": "OH",
    "sg:tags": [
      "farm",
      "corn",
      "wheat",
      "soybean"
    ],
    "wof:name": "Thomas H Eggers",
    "wof:placetype": "venue"
  },
  "geometry": {"coordinates":[-84.208887,41.401344],"type":"Point"}
}
