{
  "type": "Feature",
  "properties": {
    "iso:country":"US",
    "sg:address":"3151 Pond Run Rd",
    "sg:city":"New Richmond",
    "sg:classifiers":[
        {
            "category":"Real Estate",
            "subcategory":"Architect",
            "type":"Services"
        }
    ],
    "sg:phone":"+1 513 553 6464",
    "sg:postcode":"45157",
    "sg:province":"OH",
    "wof:name":"Kuehn Frederick",
    "wof:placetype":"venue"
},
  "geometry": {"coordinates":[-84.26974800000001,39.00012],"type":"Point"}
}