{
  "type": "Feature",
  "properties": {
    "addr:full":"1455 N Columbus St Lancaster OH 43130",
    "addr:housenumber":"1455",
    "addr:postcode":"43130",
    "addr:street":"N Columbus St",
    "iso:country":"US",
    "sg:address":"1455 N Columbus St",
    "sg:city":"Lancaster",
    "sg:classifiers":[
        {
            "category":"Health Services",
            "subcategory":"Clinic",
            "type":"Services"
        }
    ],
    "sg:phone":"+1 740 654 0502",
    "sg:postcode":"43130",
    "sg:province":"OH",
    "sg:tags":[
        "home",
        "care"
    ],
    "wof:name":"Connie Denney",
    "wof:placetype":"venue"
},
  "geometry": {"coordinates":[-82.610316,39.732298],"type":"Point"}
}