{
  "type": "Feature",
  "properties": {
    "iso:country":"US",
    "sg:address":"3893 W Powell Rd",
    "sg:city":"Powell",
    "sg:classifiers":[
        {
            "category":"Personal",
            "subcategory":"Beauty Salon",
            "type":"Services"
        }
    ],
    "sg:phone":"+1 614 798 4800",
    "sg:postcode":"43065",
    "sg:province":"OH",
    "sg:website":"www.fringeeurosalon.com",
    "wof:name":"Fringe",
    "wof:placetype":"venue"
},
  "geometry": {"coordinates":[-83.093887,40.158515],"type":"Point"}
}