{
  "type": "Feature",
  "properties": {
    "iso:country":"US",
    "sg:address":"4660 Fitzgerald Ave",
    "sg:city":"Youngstown",
    "sg:classifiers":[
        {
            "category":"Professional",
            "type":"Services"
        }
    ],
    "sg:phone":"+1 330 799 8172",
    "sg:postcode":"44515",
    "sg:province":"OH",
    "wof:name":"Supreme Grand Commandery",
    "wof:placetype":"venue"
},
  "geometry": {"coordinates":[-80.742235,41.086433],"type":"Point"}
}