{
  "type": "Feature",
  "properties": {
    "addr:full": "5600 Pleasant Valley Rd SE Uhrichsville OH 44683",
    "addr:housenumber": "5600",
    "addr:postcode": "44683",
    "addr:street": "Pleasant Valley Rd Se",
    "iso:country": "US",
    "sg:address": "5600 Pleasant Valley Rd SE",
    "sg:city": "Uhrichsville",
    "sg:classifiers": [
      {
        "category": "Mining \u0026 Drilling",
        "type": "Manufacturing \u0026 Wholesale Goods"
      }
    ],
    "sg:phone": "+1 740 922 2799",
    "sg:postcode": "44683",
    "sg:province": "OH",
    "sg:tags": [
      "coal",
      "shipping"
    ],
    "wof:name": "Tusky Coal LLC",
    "wof:placetype": "venue"
  },
  "geometry": {"coordinates":[-81.296006,40.396754],"type":"Point"}
}
