{
  "type": "Feature",
  "properties": {
    "iso:country":"US",
    "sg:address":"5600 Pleasant Valley Rd SE",
    "sg:city":"Uhrichsville",
    "sg:classifiers":[
        {
            "category":"Mining & Drilling",
            "type":"Manufacturing & Wholesale Goods"
        }
    ],
    "sg:phone":"+1 740 922 2799",
    "sg:postcode":"44683",
    "sg:province":"OH",
    "sg:tags":[
        "coal",
        "shipping"
    ],
    "wof:name":"Tusky Coal LLC",
    "wof:placetype":"venue"
},
  "geometry": {"coordinates":[-81.296006,40.396754],"type":"Point"}
}