{
  "type": "Feature",
  "properties": {
    "addr:full": "346 N Hague Ave Columbus OH 43204",
    "addr:housenumber": "346",
    "addr:postcode": "43204",
    "addr:street": "N Hague Ave",
    "iso:country": "US",
    "sg:address": "346 N Hague Ave",
    "sg:city": "Columbus",
    "sg:classifiers": [
      {
        "category": "Personal",
        "subcategory": "Beauty Salon",
        "type": "Services"
      }
    ],
    "sg:phone": "+1 614 274 1123",
    "sg:postcode": "43204",
    "sg:province": "OH",
    "wof:name": "Enchanted Mirror Beauty Salon",
    "wof:placetype": "venue"
  },
  "geometry": {"coordinates":[-83.075909,39.961466],"type":"Point"}
}
