{
  "type": "Feature",
  "properties": {
    "addr:full": "2952 Likens Rd Marion OH 43302",
    "addr:housenumber": "2952",
    "addr:postcode": "43302",
    "addr:street": "Likens Rd",
    "iso:country": "US",
    "sg:address": "2952 Likens Rd",
    "sg:city": "Marion",
    "sg:classifiers": [
      {
        "category": "Building \u0026 Trades",
        "subcategory": "Construction",
        "type": "Services"
      }
    ],
    "sg:phone": "+1 740 387 4555",
    "sg:postcode": "43302",
    "sg:province": "OH",
    "sg:tags": [
      "house"
    ],
    "wof:name": "James A Gibbs Jr",
    "wof:placetype": "venue"
  },
  "geometry": {"coordinates":[-83.050487,40.630394],"type":"Point"}
}
