{
  "type": "Feature",
  "properties": {
    "iso:country":"US",
    "sg:address":"5714 Signal Hill Ct",
    "sg:city":"Milford",
    "sg:classifiers":[
        {
            "category":"Wholesale",
            "subcategory":"Durable Goods & Equipment",
            "type":"Manufacturing & Wholesale Goods"
        },
        {
            "category":"Manufacturing",
            "subcategory":"Tools & Machinery",
            "type":"Manufacturing & Wholesale Goods"
        }
    ],
    "sg:phone":"+1 513 417 6692",
    "sg:postcode":"45150",
    "sg:province":"OH",
    "sg:tags":[
        "mfg",
        "electrical",
        "representative",
        "manufacturer"
    ],
    "wof:name":"W W Baerbalck & Associates",
    "wof:placetype":"venue"
},
  "geometry": {"coordinates":[-84.26662899999999,39.185966],"type":"Point"}
}