{
  "type": "Feature",
  "properties": {
    "addr:full": "5714 Signal Hill Ct Milford OH 45150",
    "addr:housenumber": "5714",
    "addr:postcode": "45150",
    "addr:street": "Signal Hill Ct",
    "iso:country": "US",
    "sg:address": "5714 Signal Hill Ct",
    "sg:city": "Milford",
    "sg:classifiers": [
      {
        "category": "Wholesale",
        "subcategory": "Durable Goods \u0026 Equipment",
        "type": "Manufacturing \u0026 Wholesale Goods"
      },
      {
        "category": "Manufacturing",
        "subcategory": "Tools \u0026 Machinery",
        "type": "Manufacturing \u0026 Wholesale Goods"
      }
    ],
    "sg:phone": "+1 513 417 6692",
    "sg:postcode": "45150",
    "sg:province": "OH",
    "sg:tags": [
      "mfg",
      "electrical",
      "representative",
      "manufacturer"
    ],
    "wof:name": "W W Baerbalck \u0026 Associates",
    "wof:placetype": "venue"
  },
  "geometry": {"coordinates":[-84.266629,39.185966],"type":"Point"}
}
