{
  "type": "Feature",
  "properties": {
    "addr:full":"42 Grant St Painesville OH 44077",
    "addr:housenumber":"42",
    "addr:postcode":"44077",
    "addr:street":"Grant St",
    "iso:country":"US",
    "sg:address":"42 Grant St",
    "sg:city":"Painesville",
    "sg:classifiers":[
        {
            "category":"Travel",
            "subcategory":"Travel Agent",
            "type":"Entertainment"
        }
    ],
    "sg:phone":"+1 440 357 2236",
    "sg:postcode":"44077",
    "sg:province":"OH",
    "sg:tags":[
        "agency",
        "bureau"
    ],
    "wof:name":"Fairwinds Travel",
    "wof:placetype":"venue"
},
  "geometry": {"coordinates":[-81.258284,41.715966],"type":"Point"}
}