{
  "type": "Feature",
  "properties": {
    "addr:full":"904 SE Catawba Rd Port Clinton OH 43452",
    "addr:housenumber":"904",
    "addr:postcode":"43452",
    "addr:street":"Se Catawba Rd",
    "iso:country":"US",
    "sg:address":"904 SE Catawba Rd",
    "sg:city":"Port Clinton",
    "sg:classifiers":[
        {
            "category":"Autos & Motor Vehicles",
            "subcategory":"Boat Sales",
            "type":"Retail Goods"
        }
    ],
    "sg:phone":"+1 419 734 3796",
    "sg:postcode":"43452",
    "sg:province":"OH",
    "sg:tags":[
        "used",
        "dealer",
        "sales"
    ],
    "wof:name":"Johnson's Best Buy Marine",
    "wof:placetype":"venue"
},
  "geometry": {"coordinates":[-82.859478,41.511836],"type":"Point"}
}