{
  "type": "Feature",
  "properties": {
    "iso:country":"US",
    "sg:address":"2163 Southgate Pkwy",
    "sg:city":"Cambridge",
    "sg:classifiers":[
        {
            "category":"Restaurant",
            "type":"Food & Drink"
        }
    ],
    "sg:phone":"+1 740 439 1336",
    "sg:postcode":"43725",
    "sg:province":"OH",
    "wof:name":"KFC",
    "wof:placetype":"venue"
},
  "geometry": {"coordinates":[-81.57628200000001,40.006407],"type":"Point"}
}