{
  "type": "Feature",
  "properties": {
    "iso:country":"US",
    "sg:address":"391 W Washington St",
    "sg:city":"Painesville",
    "sg:classifiers":[
        {
            "category":"Organizations",
            "subcategory":"Non-profit Organization",
            "type":"Services"
        }
    ],
    "sg:phone":"+1 440 354 4404",
    "sg:postcode":"44077",
    "sg:province":"OH",
    "sg:tags":[
        "human"
    ],
    "wof:name":"Habitat For Humanity",
    "wof:placetype":"venue"
},
  "geometry": {"coordinates":[-81.25175,41.718915],"type":"Point"}
}