{
  "type": "Feature",
  "properties": {
    "addr:full": "8053 Deepwood Dr Sylvania OH 43560",
    "addr:housenumber": "8053",
    "addr:postcode": "43560",
    "addr:street": "Deepwood Dr",
    "iso:country": "US",
    "sg:address": "8053 Deepwood Dr",
    "sg:city": "Sylvania",
    "sg:classifiers": [
      {
        "category": "Professional",
        "type": "Services"
      }
    ],
    "sg:phone": "+1 419 824 4645",
    "sg:postcode": "43560",
    "sg:province": "OH",
    "wof:name": "Concept Services",
    "wof:placetype": "venue"
  },
  "geometry": {"coordinates":[-83.738463,41.723697],"type":"Point"}
}
