{
  "type": "Feature",
  "properties": {
    "addr:full": "2477 State Rte 12 Burgoon OH 43407",
    "addr:housenumber": "2477",
    "addr:postcode": "43407",
    "addr:street": "State Rte 12",
    "iso:country": "US",
    "sg:address": "2477 State Rte 12",
    "sg:city": "Burgoon",
    "sg:phone": "+1 419 986 5612",
    "sg:postcode": "43407",
    "sg:province": "OH",
    "sg:tags": [
      "farm",
      "corn",
      "soybean"
    ],
    "wof:name": "Ronald Willoughby",
    "wof:placetype": "venue"
  },
  "geometry": {"coordinates":[-83.200344,41.272345],"type":"Point"}
}
