{
  "type": "Feature",
  "properties": {
    "addr:full": "6802 Wood St Brookfield OH 44403",
    "addr:housenumber": "6802",
    "addr:postcode": "44403",
    "addr:street": "Wood St",
    "iso:country": "US",
    "sg:address": "6802 Wood St",
    "sg:city": "Brookfield",
    "sg:classifiers": [
      {
        "category": "Building \u0026 Trades",
        "subcategory": "Construction",
        "type": "Services"
      }
    ],
    "sg:phone": "+1 330 448 4441",
    "sg:postcode": "44403",
    "sg:province": "OH",
    "sg:tags": [
      "contractor"
    ],
    "wof:name": "Foam Block Insulators Inc",
    "wof:placetype": "venue"
  },
  "geometry": {"coordinates":[-80.573298,41.231008],"type":"Point"}
}
