{
  "type": "Feature",
  "properties": {
    "addr:full": "6048 Glenway Ave Cincinnati OH 45211",
    "addr:housenumber": "6048",
    "addr:postcode": "45211",
    "addr:street": "Glenway Ave",
    "iso:country": "US",
    "sg:address": "6048 Glenway Ave",
    "sg:city": "Cincinnati",
    "sg:classifiers": [
      {
        "category": "Shopping",
        "subcategory": "Clothing, Apparel, \u0026 Fashions",
        "type": "Retail Goods"
      }
    ],
    "sg:phone": "+1 513 389 9922",
    "sg:postcode": "45211",
    "sg:province": "OH",
    "sg:tags": [
      "furnishing"
    ],
    "sg:website": "www.deveroes.com",
    "wof:name": "Deveroes",
    "wof:placetype": "venue"
  },
  "geometry": {"coordinates":[-84.6186,39.14178],"type":"Point"}
}
