{
  "type": "Feature",
  "properties": {
    "iso:country":"US",
    "sg:address":"6048 Glenway Ave",
    "sg:city":"Cincinnati",
    "sg:classifiers":[
        {
            "category":"Shopping",
            "subcategory":"Clothing, Apparel, & Fashions",
            "type":"Retail Goods"
        }
    ],
    "sg:phone":"+1 513 389 9922",
    "sg:postcode":"45211",
    "sg:province":"OH",
    "sg:tags":[
        "furnishing"
    ],
    "sg:website":"www.deveroes.com",
    "wof:name":"Deveroes",
    "wof:placetype":"venue"
},
  "geometry": {"coordinates":[-84.6186,39.14178],"type":"Point"}
}