{
  "type": "Feature",
  "properties": {
    "iso:country":"US",
    "sg:address":"2916 Smeltzer Rd",
    "sg:city":"Marion",
    "sg:classifiers":[
        {
            "category":"Personal",
            "subcategory":"Tanning Parlor",
            "type":"Services"
        }
    ],
    "sg:phone":"+1 740 383 1440",
    "sg:postcode":"43302",
    "sg:province":"OH",
    "sg:tags":[
        "salon"
    ],
    "wof:name":"Total Image Tanning & Nails",
    "wof:placetype":"venue"
},
  "geometry": {"coordinates":[-83.135988,40.531713],"type":"Point"}
}