{
  "type": "Feature",
  "properties": {
    "iso:country":"US",
    "sg:address":"549 S Chillicothe Rd",
    "sg:city":"Aurora",
    "sg:classifiers":[
        {
            "category":"Shopping",
            "subcategory":"Clothing, Apparel, & Fashions",
            "type":"Retail Goods"
        }
    ],
    "sg:phone":"+1 330 562 9036",
    "sg:postcode":"44202",
    "sg:province":"OH",
    "sg:tags":[
        "wear"
    ],
    "wof:name":"Carters Factory Outlet",
    "wof:placetype":"venue"
},
  "geometry": {"coordinates":[-81.345608,41.300461],"type":"Point"}
}