{
  "type": "Feature",
  "properties": {
    "addr:full": "6930 Serene Pl Huber Heights OH 45424",
    "addr:housenumber": "6930",
    "addr:postcode": "45424",
    "addr:street": "Serene Pl",
    "iso:country": "US",
    "sg:address": "6930 Serene Pl",
    "sg:city": "Huber Heights",
    "sg:classifiers": [
      {
        "category": "Professional",
        "subcategory": "Management \u0026 Consulting",
        "type": "Services"
      }
    ],
    "sg:phone": "+1 937 233 6535",
    "sg:postcode": "45424",
    "sg:province": "OH",
    "sg:tags": [
      "party",
      "planning"
    ],
    "wof:name": "Jolly-O's Entertainment",
    "wof:placetype": "venue"
  },
  "geometry": {"coordinates":[-84.107657,39.862001],"type":"Point"}
}
