{
  "type": "Feature",
  "properties": {
    "addr:full": "4725 E Galbraith Rd Cincinnati OH 45236",
    "addr:housenumber": "4725",
    "addr:postcode": "45236",
    "addr:street": "E Galbraith Rd",
    "iso:country": "US",
    "sg:address": "4725 E Galbraith Rd",
    "sg:city": "Cincinnati",
    "sg:classifiers": [
      {
        "category": "Health Services",
        "subcategory": "Doctor",
        "type": "Services"
      }
    ],
    "sg:phone": "+1 513 793 6052",
    "sg:postcode": "45236",
    "sg:province": "OH",
    "sg:tags": [
      "physician",
      "surgeon"
    ],
    "sg:website": "www.ohcare.com",
    "wof:name": "Oncology Hematology Care Inc",
    "wof:placetype": "venue"
  },
  "geometry": {"coordinates":[-84.38025,39.206727],"type":"Point"}
}
