{
  "type": "Feature",
  "properties": {
    "iso:country":"US",
    "sg:address":"3500 Millikin Ct",
    "sg:city":"Columbus",
    "sg:classifiers":[
        {
            "category":"Professional",
            "subcategory":"Accounting & Tax Preparation",
            "type":"Services"
        }
    ],
    "sg:phone":"+1 614 527 0590",
    "sg:postcode":"43228",
    "sg:province":"OH",
    "sg:tags":[
        "return",
        "filing"
    ],
    "wof:name":"CTA Svc Inc",
    "wof:placetype":"venue"
},
  "geometry": {"coordinates":[-83.102357,40.002176],"type":"Point"}
}