{
  "type": "Feature",
  "properties": {
    "addr:full": "2611 Needmore Rd Dayton OH 45414",
    "addr:housenumber": "2611",
    "addr:postcode": "45414",
    "addr:street": "Needmore Rd",
    "iso:country": "US",
    "sg:address": "2611 Needmore Rd",
    "sg:city": "Dayton",
    "sg:classifiers": [
      {
        "category": "Recreation",
        "type": "Entertainment"
      }
    ],
    "sg:phone": "+1 937 274 1230",
    "sg:postcode": "45414",
    "sg:province": "OH",
    "wof:name": "Airway Billiards Bar \u0026 Grill",
    "wof:placetype": "venue"
  },
  "geometry": {"coordinates":[-84.186174,39.819888],"type":"Point"}
}
