{
  "type": "Feature",
  "properties": {
    "addr:full": "6025 Kruse Dr Cleveland OH 44139",
    "addr:housenumber": "6025",
    "addr:postcode": "44139",
    "addr:street": "Kruse Dr",
    "iso:country": "US",
    "sg:address": "6025 Kruse Dr",
    "sg:city": "Cleveland",
    "sg:classifiers": [
      {
        "category": "Shopping",
        "type": "Retail Goods"
      }
    ],
    "sg:phone": "+1 440 542 0526",
    "sg:postcode": "44139",
    "sg:province": "OH",
    "sg:tags": [
      "cosmetic",
      "perfume"
    ],
    "wof:name": "Sally Beauty Supply",
    "wof:placetype": "venue"
  },
  "geometry": {"coordinates":[-81.444176,41.39265],"type":"Point"}
}
