{
  "type": "Feature",
  "properties": {
    "addr:full": "108 S Main St Bloomdale OH 44817",
    "addr:housenumber": "108",
    "addr:postcode": "44817",
    "addr:street": "S Main St",
    "iso:country": "US",
    "sg:address": "108 S Main St",
    "sg:city": "Bloomdale",
    "sg:classifiers": [
      {
        "category": "Bars \u0026 Pubs",
        "type": "Food \u0026 Drink"
      }
    ],
    "sg:phone": "+1 419 454 5915",
    "sg:postcode": "44817",
    "sg:province": "OH",
    "wof:name": "Abner's Place",
    "wof:placetype": "venue"
  },
  "geometry": {"coordinates":[-83.554261,41.17051],"type":"Point"}
}
