{
  "type": "Feature",
  "properties": {
    "addr:full":"2717 Clifton Ave Cincinnati OH 45220",
    "addr:housenumber":"2717",
    "addr:postcode":"45220",
    "addr:street":"Clifton Ave",
    "iso:country":"US",
    "sg:address":"2717 Clifton Ave",
    "sg:city":"Cincinnati",
    "sg:classifiers":[
        {
            "category":"Organizations",
            "subcategory":"Religious Organization",
            "type":"Services"
        }
    ],
    "sg:phone":"+1 513 861 2929",
    "sg:postcode":"45220",
    "sg:province":"OH",
    "sg:tags":[
        "church"
    ],
    "sg:website":"www.wesleyuc.org",
    "wof:name":"Wesley Foundation",
    "wof:placetype":"venue"
},
  "geometry": {"coordinates":[-84.520382,39.132875],"type":"Point"}
}