{
  "type": "Feature",
  "properties": {
    "iso:country":"US",
    "sg:address":"1279 Rohr Rd",
    "sg:city":"Lockbourne",
    "sg:classifiers":[
        {
            "category":"Food & Beverages",
            "subcategory":"Fruits & Vegetables",
            "type":"Retail Goods"
        }
    ],
    "sg:phone":"+1 614 491 0917",
    "sg:postcode":"43137",
    "sg:province":"OH",
    "wof:name":"Hahns Farm Market & Grnhse",
    "wof:placetype":"venue"
},
  "geometry": {"coordinates":[-82.969517,39.846475],"type":"Point"}
}