{
  "type": "Feature",
  "properties": {
    "addr:full": "1279 Rohr Rd Lockbourne OH 43137",
    "addr:housenumber": "1279",
    "addr:postcode": "43137",
    "addr:street": "Rohr Rd",
    "iso:country": "US",
    "sg:address": "1279 Rohr Rd",
    "sg:city": "Lockbourne",
    "sg:classifiers": [
      {
        "category": "Food \u0026 Beverages",
        "subcategory": "Fruits \u0026 Vegetables",
        "type": "Retail Goods"
      }
    ],
    "sg:phone": "+1 614 491 0917",
    "sg:postcode": "43137",
    "sg:province": "OH",
    "wof:name": "Hahns Farm Market \u0026 Grnhse",
    "wof:placetype": "venue"
  },
  "geometry": {"coordinates":[-82.969517,39.846475],"type":"Point"}
}
