{
  "type": "Feature",
  "properties": {
    "iso:country":"US",
    "sg:address":"2931 Exon Ave",
    "sg:city":"Cincinnati",
    "sg:classifiers":[
        {
            "category":"Wholesale",
            "subcategory":"Machinery & Supplies",
            "type":"Manufacturing & Wholesale Goods"
        }
    ],
    "sg:phone":"+1 513 733 0883",
    "sg:postcode":"45241",
    "sg:province":"OH",
    "sg:tags":[
        "gasket"
    ],
    "sg:website":"www.netherlandrubber.com",
    "wof:name":"Netherland Rubber Co",
    "wof:placetype":"venue"
},
  "geometry": {"coordinates":[-84.41886100000001,39.259715],"type":"Point"}
}