{
  "type": "Feature",
  "properties": {
    "addr:full": "2931 Exon Ave Cincinnati OH 45241",
    "addr:housenumber": "2931",
    "addr:postcode": "45241",
    "addr:street": "Exon Ave",
    "iso:country": "US",
    "sg:address": "2931 Exon Ave",
    "sg:city": "Cincinnati",
    "sg:classifiers": [
      {
        "category": "Wholesale",
        "subcategory": "Machinery \u0026 Supplies",
        "type": "Manufacturing \u0026 Wholesale Goods"
      }
    ],
    "sg:phone": "+1 513 733 0883",
    "sg:postcode": "45241",
    "sg:province": "OH",
    "sg:tags": [
      "gasket"
    ],
    "sg:website": "www.netherlandrubber.com",
    "wof:name": "Netherland Rubber Co",
    "wof:placetype": "venue"
  },
  "geometry": {"coordinates":[-84.418861,39.259715],"type":"Point"}
}
