{
  "type": "Feature",
  "properties": {
    "addr:full":"2908 Springboro Rd Dayton OH 45439",
    "addr:housenumber":"2908",
    "addr:postcode":"45439",
    "addr:street":"Springboro Rd",
    "iso:country":"US",
    "sg:address":"2908 Springboro Rd",
    "sg:city":"Dayton",
    "sg:classifiers":[
        {
            "category":"Building & Trades",
            "subcategory":"Construction",
            "type":"Services"
        }
    ],
    "sg:phone":"+1 937 299 9722",
    "sg:postcode":"45439",
    "sg:province":"OH",
    "sg:tags":[
        "demolition",
        "contractor"
    ],
    "wof:name":"Tri-County Demolition Contrs",
    "wof:placetype":"venue"
},
  "geometry": {"coordinates":[-84.216875,39.710414],"type":"Point"}
}