{
  "type": "Feature",
  "properties": {
    "addr:full": "5791 Youngstown Warren Rd Niles OH 44446",
    "addr:housenumber": "5791",
    "addr:postcode": "44446",
    "addr:street": "Youngstown Warren Rd",
    "iso:country": "US",
    "sg:address": "5791 Youngstown Warren Rd",
    "sg:city": "Niles",
    "sg:classifiers": [
      {
        "category": "Shopping",
        "subcategory": "Department Store",
        "type": "Retail Goods"
      },
      {
        "category": "Shopping",
        "subcategory": "Discount \u0026 Variety Stores",
        "type": "Retail Goods"
      }
    ],
    "sg:phone": "+1 330 544 9370",
    "sg:postcode": "44446",
    "sg:province": "OH",
    "wof:name": "Deals",
    "wof:placetype": "venue"
  },
  "geometry": {"coordinates":[-80.747239,41.209152],"type":"Point"}
}
