{
  "type": "Feature",
  "properties": {
    "iso:country":"US",
    "sg:address":"172 E US Hwy 22 and 3",
    "sg:city":"Maineville",
    "sg:classifiers":[
        {
            "category":"Organizations",
            "subcategory":"Religious Organization",
            "type":"Services"
        }
    ],
    "sg:phone":"+1 513 677 1777",
    "sg:postcode":"45039",
    "sg:province":"OH",
    "sg:tags":[
        "church"
    ],
    "wof:name":"St Mary Magdalene Episcopal",
    "wof:placetype":"venue"
},
  "geometry": {"coordinates":[-84.215344,39.341161],"type":"Point"}
}