{
  "type": "Feature",
  "properties": {
    "addr:full": "172 E US Hwy 22 and 3 Maineville OH 45039",
    "addr:housenumber": "172",
    "addr:postcode": "45039",
    "addr:street": "E Us Hwy 22 And 3",
    "iso:country": "US",
    "sg:address": "172 E US Hwy 22 and 3",
    "sg:city": "Maineville",
    "sg:classifiers": [
      {
        "category": "Organizations",
        "subcategory": "Religious Organization",
        "type": "Services"
      }
    ],
    "sg:phone": "+1 513 677 1777",
    "sg:postcode": "45039",
    "sg:province": "OH",
    "sg:tags": [
      "church"
    ],
    "wof:name": "St Mary Magdalene Episcopal",
    "wof:placetype": "venue"
  },
  "geometry": {"coordinates":[-84.215344,39.341161],"type":"Point"}
}
