{
  "type": "Feature",
  "properties": {
    "iso:country":"US",
    "sg:address":"2773 Salt Springs Rd",
    "sg:city":"Youngstown",
    "sg:classifiers":[
        {
            "category":"Wholesale",
            "subcategory":"Medical Equipment & Supplies",
            "type":"Manufacturing & Wholesale Goods"
        },
        {
            "category":"Wholesale",
            "subcategory":"Machinery & Supplies",
            "type":"Manufacturing & Wholesale Goods"
        },
        {
            "category":"Transit Center",
            "subcategory":"Freight",
            "type":"Transportation"
        },
        {
            "category":"Manufacturing",
            "subcategory":"Tools & Machinery",
            "type":"Manufacturing & Wholesale Goods"
        },
        {
            "category":"Autos & Motor Vehicles",
            "subcategory":"Auto Supplies",
            "type":"Retail Goods"
        },
        {
            "category":"Autos & Motor Vehicles",
            "subcategory":"Automobile Sales",
            "type":"Retail Goods"
        },
        {
            "category":"Professional",
            "subcategory":"Advertising",
            "type":"Services"
        },
        {
            "category":"Building & Trades",
            "subcategory":"Equipment Rental",
            "type":"Services"
        },
        {
            "category":"Wholesale",
            "subcategory":"Auto Parts",
            "type":"Manufacturing & Wholesale Goods"
        }
    ],
    "sg:phone":"+1 800 589 7911",
    "sg:postcode":"44509",
    "sg:province":"OH",
    "sg:tags":[
        "body",
        "loading",
        "yard",
        "trucks-industrial",
        "material",
        "accessory",
        "dock",
        "construction",
        "truck",
        "trucks-rental",
        "forklift",
        "handling",
        "store"
    ],
    "sg:website":"http://www.fallsway.com",
    "wof:name":"Fallsway Equipment Company",
    "wof:placetype":"venue"
},
  "geometry": {"coordinates":[-80.704212,41.128535],"type":"Point"}
}