{
  "type": "Feature",
  "properties": {
    "addr:full": "2773 Salt Springs Rd Youngstown OH 44509",
    "addr:housenumber": "2773",
    "addr:postcode": "44509",
    "addr:street": "Salt Springs Rd",
    "iso:country": "US",
    "sg:address": "2773 Salt Springs Rd",
    "sg:city": "Youngstown",
    "sg:classifiers": [
      {
        "category": "Wholesale",
        "subcategory": "Medical Equipment \u0026 Supplies",
        "type": "Manufacturing \u0026 Wholesale Goods"
      },
      {
        "category": "Wholesale",
        "subcategory": "Machinery \u0026 Supplies",
        "type": "Manufacturing \u0026 Wholesale Goods"
      },
      {
        "category": "Transit Center",
        "subcategory": "Freight",
        "type": "Transportation"
      },
      {
        "category": "Manufacturing",
        "subcategory": "Tools \u0026 Machinery",
        "type": "Manufacturing \u0026 Wholesale Goods"
      },
      {
        "category": "Autos \u0026 Motor Vehicles",
        "subcategory": "Auto Supplies",
        "type": "Retail Goods"
      },
      {
        "category": "Autos \u0026 Motor Vehicles",
        "subcategory": "Automobile Sales",
        "type": "Retail Goods"
      },
      {
        "category": "Professional",
        "subcategory": "Advertising",
        "type": "Services"
      },
      {
        "category": "Building \u0026 Trades",
        "subcategory": "Equipment Rental",
        "type": "Services"
      },
      {
        "category": "Wholesale",
        "subcategory": "Auto Parts",
        "type": "Manufacturing \u0026 Wholesale Goods"
      }
    ],
    "sg:phone": "+1 800 589 7911",
    "sg:postcode": "44509",
    "sg:province": "OH",
    "sg:tags": [
      "body",
      "loading",
      "yard",
      "trucks-industrial",
      "material",
      "accessory",
      "dock",
      "construction",
      "truck",
      "trucks-rental",
      "forklift",
      "handling",
      "store"
    ],
    "sg:website": "http://www.fallsway.com",
    "wof:name": "Fallsway Equipment Company",
    "wof:placetype": "venue"
  },
  "geometry": {"coordinates":[-80.704212,41.128535],"type":"Point"}
}
