{
  "type": "Feature",
  "properties": {
    "addr:full": "311 Reynolds Ct Wooster OH 44691",
    "addr:housenumber": "311",
    "addr:postcode": "44691",
    "addr:street": "Reynolds Ct",
    "iso:country": "US",
    "sg:address": "311 Reynolds Ct",
    "sg:city": "Wooster",
    "sg:classifiers": [
      {
        "category": "Building \u0026 Trades",
        "subcategory": "Landscaping Services",
        "type": "Services"
      }
    ],
    "sg:phone": "+1 330 345 7942",
    "sg:postcode": "44691",
    "sg:province": "OH",
    "sg:tags": [
      "landscape"
    ],
    "wof:name": "Wayne Lawn \u0026 Landscape",
    "wof:placetype": "venue"
  },
  "geometry": {"coordinates":[-81.936735,40.842253],"type":"Point"}
}
