{
  "type": "Feature",
  "properties": {
    "iso:country":"US",
    "sg:address":"4380 N Old State Rd",
    "sg:city":"Delaware",
    "sg:classifiers":[
        {
            "category":"Real Estate",
            "subcategory":"Real Estate Operator",
            "type":"Services"
        }
    ],
    "sg:phone":"+1 740 524 2663",
    "sg:postcode":"43015",
    "sg:province":"OH",
    "sg:tags":[
        "property",
        "lessor"
    ],
    "wof:name":"Sheets Farm",
    "wof:placetype":"venue"
},
  "geometry": {"coordinates":[-82.955376,40.338649],"type":"Point"}
}