{
  "type": "Feature",
  "properties": {
    "iso:country":"US",
    "sg:address":"3180 W Canal St",
    "sg:city":"Port Clinton",
    "sg:classifiers":[
        {
            "category":"Home & Garden",
            "subcategory":"Garden Supply",
            "type":"Retail Goods"
        }
    ],
    "sg:phone":"+1 419 732 1365",
    "sg:postcode":"43452",
    "sg:province":"OH",
    "sg:tags":[
        "sprinkler"
    ],
    "wof:name":"Innovative Irrigation",
    "wof:placetype":"venue"
},
  "geometry": {"coordinates":[-82.993504,41.507612],"type":"Point"}
}