{
  "type": "Feature",
  "properties": {
    "addr:full": "3180 W Canal St Port Clinton OH 43452",
    "addr:housenumber": "3180",
    "addr:postcode": "43452",
    "addr:street": "W Canal St",
    "iso:country": "US",
    "sg:address": "3180 W Canal St",
    "sg:city": "Port Clinton",
    "sg:classifiers": [
      {
        "category": "Home \u0026 Garden",
        "subcategory": "Garden Supply",
        "type": "Retail Goods"
      }
    ],
    "sg:phone": "+1 419 732 1365",
    "sg:postcode": "43452",
    "sg:province": "OH",
    "sg:tags": [
      "sprinkler"
    ],
    "wof:name": "Innovative Irrigation",
    "wof:placetype": "venue"
  },
  "geometry": {"coordinates":[-82.993504,41.507612],"type":"Point"}
}
