{
  "type": "Feature",
  "properties": {
    "iso:country":"US",
    "sg:address":"3640 Hazelhurst Ave",
    "sg:city":"Toledo",
    "sg:classifiers":[
        {
            "category":"Building & Trades",
            "subcategory":"Construction",
            "type":"Services"
        }
    ],
    "sg:phone":"+1 419 478 6880",
    "sg:postcode":"43612",
    "sg:province":"OH",
    "sg:tags":[
        "house"
    ],
    "wof:name":"Class Act Home Remodeling Inc",
    "wof:placetype":"venue"
},
  "geometry": {"coordinates":[-83.575378,41.687157],"type":"Point"}
}