{
  "type": "Feature",
  "properties": {
    "addr:full":"791 Presidential Dr Youngstown OH 44512",
    "addr:housenumber":"791",
    "addr:postcode":"44512",
    "addr:street":"Presidential Dr",
    "iso:country":"US",
    "sg:address":"791 Presidential Dr",
    "sg:city":"Youngstown",
    "sg:classifiers":[
        {
            "category":"Building & Trades",
            "subcategory":"Construction",
            "type":"Services"
        }
    ],
    "sg:phone":"+1 330 758 0660",
    "sg:postcode":"44512",
    "sg:province":"OH",
    "sg:tags":[
        "contractor",
        "painting",
        "painter",
        "hanging"
    ],
    "wof:name":"Valley, Gary & Son Painting",
    "wof:placetype":"venue"
},
  "geometry": {"coordinates":[-80.637169,41.017159],"type":"Point"}
}