{
  "type": "Feature",
  "properties": {
    "addr:full": "525 Vine St Cincinnati OH 45202",
    "addr:housenumber": "525",
    "addr:postcode": "45202",
    "addr:street": "Vine St",
    "iso:country": "US",
    "sg:address": "525 Vine St",
    "sg:city": "Cincinnati",
    "sg:classifiers": [
      {
        "category": "Professional",
        "subcategory": "Lawyer \u0026 Legal Services",
        "type": "Services"
      }
    ],
    "sg:phone": "+1 513 665 9500",
    "sg:postcode": "45202",
    "sg:province": "OH",
    "wof:name": "Klingler Robert A Co Lpa",
    "wof:placetype": "venue"
  },
  "geometry": {"coordinates":[-84.51327,39.102018],"type":"Point"}
}
