{
  "type": "Feature",
  "properties": {
    "addr:full": "221 E Home Rd Springfield OH 45503",
    "addr:housenumber": "221",
    "addr:postcode": "45503",
    "addr:street": "E Home Rd",
    "iso:country": "US",
    "sg:address": "221 E Home Rd",
    "sg:city": "Springfield",
    "sg:classifiers": [
      {
        "category": "Health Services",
        "subcategory": "Doctor",
        "type": "Services"
      }
    ],
    "sg:phone": "+1 937 399 7721",
    "sg:postcode": "45503",
    "sg:province": "OH",
    "sg:tags": [
      "dentist"
    ],
    "wof:name": "Dennis M Casey DDS",
    "wof:placetype": "venue"
  },
  "geometry": {"coordinates":[-83.802531,39.953129],"type":"Point"}
}
