{
  "type": "Feature",
  "properties": {
    "addr:full":"1757 State Rte 46 N Jefferson OH 44047",
    "addr:housenumber":"1757",
    "addr:postcode":"44047",
    "addr:street":"State Rte 46 N",
    "iso:country":"US",
    "sg:address":"1757 State Rte 46 N",
    "sg:city":"Jefferson",
    "sg:classifiers":[
        {
            "category":"Manufacturing",
            "subcategory":"Metals",
            "type":"Manufacturing & Wholesale Goods"
        }
    ],
    "sg:phone":"+1 440 576 9526",
    "sg:postcode":"44047",
    "sg:province":"OH",
    "sg:tags":[
        "tubing",
        "mfg"
    ],
    "wof:name":"Ultraform Inc",
    "wof:placetype":"venue"
},
  "geometry": {"coordinates":[-80.76435600000001,41.773408],"type":"Point"}
}