{
  "type": "Feature",
  "properties": {
    "addr:full":"1518 Saint Paris Pike Springfield OH 45504",
    "addr:housenumber":"1518",
    "addr:postcode":"45504",
    "addr:street":"Saint Paris Pike",
    "iso:country":"US",
    "sg:address":"1518 Saint Paris Pike",
    "sg:city":"Springfield",
    "sg:classifiers":[
        {
            "category":"Wholesale",
            "subcategory":"Auto Parts",
            "type":"Manufacturing & Wholesale Goods"
        }
    ],
    "sg:phone":"+1 937 342 0876",
    "sg:postcode":"45504",
    "sg:province":"OH",
    "wof:name":"Rimman Custom Accessories Inc",
    "wof:placetype":"venue"
},
  "geometry": {"coordinates":[-83.822597,39.947869],"type":"Point"}
}