{
  "type": "Feature",
  "properties": {
    "addr:full":"4049 Woodlane Dr Nelsonville OH 45764",
    "addr:housenumber":"4049",
    "addr:postcode":"45764",
    "addr:street":"Woodlane Dr",
    "iso:country":"US",
    "sg:address":"4049 Woodlane Dr",
    "sg:city":"Nelsonville",
    "sg:classifiers":[
        {
            "category":"Food & Beverages",
            "subcategory":"Groceries & Convenience Stores",
            "type":"Retail Goods"
        }
    ],
    "sg:phone":"+1 740 753 4177",
    "sg:postcode":"45764",
    "sg:province":"OH",
    "wof:name":"Bookman Food Service Inc",
    "wof:placetype":"venue"
},
  "geometry": {"coordinates":[-82.203318,39.463758],"type":"Point"}
}