{
  "type": "Feature",
  "properties": {
    "addr:full": "348 W Main St Conneaut OH 44030",
    "addr:housenumber": "348",
    "addr:postcode": "44030",
    "addr:street": "W Main St",
    "iso:country": "US",
    "sg:address": "348 W Main St",
    "sg:city": "Conneaut",
    "sg:classifiers": [
      {
        "category": "Health Services",
        "subcategory": "Health Practitioner",
        "type": "Services"
      }
    ],
    "sg:phone": "+1 440 593 2804",
    "sg:postcode": "44030",
    "sg:province": "OH",
    "sg:tags": [
      "therapist",
      "physical"
    ],
    "wof:name": "Keystone Rehabilitation Syst",
    "wof:placetype": "venue"
  },
  "geometry": {"coordinates":[-80.601799,41.933405],"type":"Point"}
}
