{
  "type": "Feature",
  "properties": {
    "iso:country":"US",
    "sg:address":"6596 Brecksville Rd",
    "sg:city":"Cleveland",
    "sg:classifiers":[
        {
            "category":"Professional",
            "subcategory":"Accounting & Tax Preparation",
            "type":"Services"
        }
    ],
    "sg:phone":"+1 216 642 9140",
    "sg:postcode":"44131",
    "sg:province":"OH",
    "sg:tags":[
        "accountant"
    ],
    "wof:name":"Seikel Shalek & Co",
    "wof:placetype":"venue"
},
  "geometry": {"coordinates":[-81.641251,41.384775],"type":"Point"}
}