{
  "type": "Feature",
  "properties": {
    "addr:full": "2383 W 23rd St Bellaire OH 43906",
    "addr:housenumber": "2383",
    "addr:postcode": "43906",
    "addr:street": "W 23Rd St",
    "iso:country": "US",
    "sg:address": "2383 W 23rd St",
    "sg:city": "Bellaire",
    "sg:classifiers": [
      {
        "category": "Food \u0026 Beverages",
        "subcategory": "Liquor \u0026 Beverages",
        "type": "Retail Goods"
      }
    ],
    "sg:phone": "+1 740 676 5049",
    "sg:postcode": "43906",
    "sg:province": "OH",
    "sg:tags": [
      "alcoholic"
    ],
    "wof:name": "Carry Moes Out",
    "wof:placetype": "venue"
  },
  "geometry": {"coordinates":[-80.760481,40.007383],"type":"Point"}
}
