{
  "type": "Feature",
  "properties": {
    "iso:country":"US",
    "sg:address":"46601 State Rte 78",
    "sg:city":"Woodsfield",
    "sg:classifiers":[
        {
            "category":"Education",
            "subcategory":"School",
            "type":"Public Place"
        }
    ],
    "sg:phone":"+1 740 472 0722",
    "sg:postcode":"43793",
    "sg:province":"OH",
    "wof:name":"Monroe Central High School",
    "wof:placetype":"venue"
},
  "geometry": {"coordinates":[-80.975427,39.754336],"type":"Point"}
}