{
  "type": "Feature",
  "properties": {
    "iso:country":"US",
    "sg:address":"64 W Main St",
    "sg:city":"New Concord",
    "sg:classifiers":[
        {
            "category":"Personal",
            "subcategory":"Barber",
            "type":"Services"
        }
    ],
    "sg:phone":"+1 740 826 4921",
    "sg:postcode":"43762",
    "sg:province":"OH",
    "wof:name":"John's Barber Shop",
    "wof:placetype":"venue"
},
  "geometry": {"coordinates":[-81.735474,39.993504],"type":"Point"}
}