{
  "type": "Feature",
  "properties": {
    "iso:country":"US",
    "sg:address":"20800 Lake Rd",
    "sg:city":"Cleveland",
    "sg:classifiers":[
        {
            "category":"Wholesale",
            "subcategory":"Metals & Minerals",
            "type":"Manufacturing & Wholesale Goods"
        }
    ],
    "sg:phone":"+1 216 589 4793",
    "sg:postcode":"44116",
    "sg:province":"OH",
    "sg:tags":[
        "coal",
        "coke"
    ],
    "wof:name":"Service Fuels Co",
    "wof:placetype":"venue"
},
  "geometry": {"coordinates":[-81.849861,41.48293],"type":"Point"}
}