{
  "type": "Feature",
  "properties": {
    "iso:country":"US",
    "sg:address":"3757 Swamp St NE",
    "sg:city":"Hartville",
    "sg:classifiers":[
        {
            "category":"Building & Trades",
            "subcategory":"Construction",
            "type":"Services"
        }
    ],
    "sg:phone":"+1 330 877 2968",
    "sg:postcode":"44632",
    "sg:province":"OH",
    "sg:tags":[
        "residential"
    ],
    "wof:name":"Yarchak Construction Inc",
    "wof:placetype":"venue"
},
  "geometry": {"coordinates":[-81.307582,40.969804],"type":"Point"}
}