{
  "type": "Feature",
  "properties": {
    "addr:full":"2121 Tiffin Ave Findlay OH 45840",
    "addr:housenumber":"2121",
    "addr:postcode":"45840",
    "addr:street":"Tiffin Ave",
    "iso:country":"US",
    "sg:address":"2121 Tiffin Ave",
    "sg:city":"Findlay",
    "sg:classifiers":[
        {
            "category":"Restaurant",
            "type":"Food & Drink"
        }
    ],
    "sg:menulink":"http://www.allmenus.com/oh/findlay/121630-fazolis/menu/",
    "sg:phone":"+1 419 420 1644",
    "sg:postcode":"45840",
    "sg:province":"OH",
    "sg:tags":[
        "italian"
    ],
    "wof:name":"Fazoli's",
    "wof:placetype":"venue"
},
  "geometry": {"coordinates":[-83.606802,41.053992],"type":"Point"}
}