{
  "type": "Feature",
  "properties": {
    "addr:full":"735 Springfield Rd Columbiana OH 44408",
    "addr:housenumber":"735",
    "addr:postcode":"44408",
    "addr:street":"Springfield Rd",
    "iso:country":"US",
    "sg:address":"735 Springfield Rd",
    "sg:city":"Columbiana",
    "sg:classifiers":[
        {
            "category":"Wholesale",
            "subcategory":"Plants",
            "type":"Manufacturing & Wholesale Goods"
        }
    ],
    "sg:phone":"+1 330 482 4212",
    "sg:postcode":"44408",
    "sg:province":"OH",
    "sg:tags":[
        "florist",
        "flower"
    ],
    "wof:name":"Columbiana Wholesale Floral Co",
    "wof:placetype":"venue"
},
  "geometry": {"coordinates":[-80.675849,40.890008],"type":"Point"}
}