{
  "type": "Feature",
  "properties": {
    "iso:country":"US",
    "sg:address":"239 W State St",
    "sg:city":"Salem",
    "sg:classifiers":[
        {
            "category":"Home & Garden",
            "subcategory":"Hardware",
            "type":"Retail Goods"
        }
    ],
    "sg:phone":"+1 330 332 1400",
    "sg:postcode":"44460",
    "sg:province":"OH",
    "wof:name":"Metzger's True Value Hardware",
    "wof:placetype":"venue"
},
  "geometry": {"coordinates":[-80.858671,40.900877],"type":"Point"}
}