{
  "type": "Feature",
  "properties": {
    "addr:full": "239 W State St Salem OH 44460",
    "addr:housenumber": "239",
    "addr:postcode": "44460",
    "addr:street": "W State St",
    "iso:country": "US",
    "sg:address": "239 W State St",
    "sg:city": "Salem",
    "sg:classifiers": [
      {
        "category": "Home \u0026 Garden",
        "subcategory": "Hardware",
        "type": "Retail Goods"
      }
    ],
    "sg:phone": "+1 330 332 1400",
    "sg:postcode": "44460",
    "sg:province": "OH",
    "wof:name": "Metzger's True Value Hardware",
    "wof:placetype": "venue"
  },
  "geometry": {"coordinates":[-80.858671,40.900877],"type":"Point"}
}
