{
  "type": "Feature",
  "properties": {
    "addr:full":"4153 Crossgate Ln Cincinnati OH 45236",
    "addr:housenumber":"4153",
    "addr:postcode":"45236",
    "addr:street":"Crossgate Ln",
    "iso:country":"US",
    "sg:address":"4153 Crossgate Ln",
    "sg:city":"Cincinnati",
    "sg:classifiers":[
        {
            "category":"Professional",
            "subcategory":"Lawyer & Legal Services",
            "type":"Services"
        }
    ],
    "sg:phone":"+1 513 793 5560",
    "sg:postcode":"45236",
    "sg:province":"OH",
    "sg:tags":[
        "attorney"
    ],
    "wof:name":"Slutsky & Slutsky Co",
    "wof:placetype":"venue"
},
  "geometry": {"coordinates":[-84.394144,39.224119],"type":"Point"}
}