{
  "type": "Feature",
  "properties": {
    "addr:full":"504 E Main St Bellevue OH 44811",
    "addr:housenumber":"504",
    "addr:postcode":"44811",
    "addr:street":"E Main St",
    "iso:country":"US",
    "sg:address":"504 E Main St",
    "sg:city":"Bellevue",
    "sg:classifiers":[
        {
            "category":"Building & Trades",
            "subcategory":"Construction",
            "type":"Services"
        }
    ],
    "sg:phone":"+1 419 483 0273",
    "sg:postcode":"44811",
    "sg:province":"OH",
    "sg:tags":[
        "hanging",
        "contractor"
    ],
    "wof:name":"McGinn Painting",
    "wof:placetype":"venue"
},
  "geometry": {"coordinates":[-82.83374000000001,41.272685],"type":"Point"}
}