{
  "type": "Feature",
  "properties": {
    "iso:country":"US",
    "sg:address":"2202 Niles Cortland Rd NE",
    "sg:city":"Cortland",
    "sg:classifiers":[
        {
            "category":"Real Estate",
            "subcategory":"Developer",
            "type":"Services"
        },
        {
            "category":"Building & Trades",
            "subcategory":"Construction",
            "type":"Services"
        }
    ],
    "sg:phone":"+1 330 638 8511",
    "sg:postcode":"44410",
    "sg:province":"OH",
    "sg:tags":[
        "specializing",
        "new",
        "general",
        "contractor"
    ],
    "wof:name":"Ross Development Corporation",
    "wof:placetype":"venue"
},
  "geometry": {"coordinates":[-80.737458,41.284023],"type":"Point"}
}