{
  "type": "Feature",
  "properties": {
    "addr:full": "2202 Niles Cortland Rd NE Cortland OH 44410",
    "addr:housenumber": "2202",
    "addr:postcode": "44410",
    "addr:street": "Niles Cortland Rd Ne",
    "iso:country": "US",
    "sg:address": "2202 Niles Cortland Rd NE",
    "sg:city": "Cortland",
    "sg:classifiers": [
      {
        "category": "Real Estate",
        "subcategory": "Developer",
        "type": "Services"
      },
      {
        "category": "Building \u0026 Trades",
        "subcategory": "Construction",
        "type": "Services"
      }
    ],
    "sg:phone": "+1 330 638 8511",
    "sg:postcode": "44410",
    "sg:province": "OH",
    "sg:tags": [
      "specializing",
      "new",
      "general",
      "contractor"
    ],
    "wof:name": "Ross Development Corporation",
    "wof:placetype": "venue"
  },
  "geometry": {"coordinates":[-80.737458,41.284023],"type":"Point"}
}
