{
  "type": "Feature",
  "properties": {
    "addr:full": "10711 Weymouth Ave Powell OH 43065",
    "addr:housenumber": "10711",
    "addr:postcode": "43065",
    "addr:street": "Weymouth Ave",
    "iso:country": "US",
    "sg:address": "10711 Weymouth Ave",
    "sg:city": "Powell",
    "sg:classifiers": [
      {
        "category": "Banks \u0026 Credit Unions",
        "subcategory": "Financial Services",
        "type": "Services"
      }
    ],
    "sg:phone": "+1 614 764 2711",
    "sg:postcode": "43065",
    "sg:province": "OH",
    "sg:tags": [
      "investor"
    ],
    "wof:name": "Willington Investments LLC",
    "wof:placetype": "venue"
  },
  "geometry": {"coordinates":[-83.107802,40.143068],"type":"Point"}
}
