{
  "type": "Feature",
  "properties": {
    "addr:full": "6135 Rings Rd Dublin OH 43016",
    "addr:postcode": "6135;43016",
    "addr:street": "Rings Rd",
    "iso:country": "US",
    "sg:address": "6135 Rings Rd",
    "sg:city": "Dublin",
    "sg:classifiers": [
      {
        "category": "Social Services",
        "subcategory": "Child Care",
        "type": "Services"
      },
      {
        "category": "Organizations",
        "subcategory": "Religious Organization",
        "type": "Services"
      }
    ],
    "sg:phone": "+1 614 889 5893",
    "sg:postcode": "43016",
    "sg:province": "OH",
    "sg:tags": [
      "kindergarten",
      "academic",
      "school",
      "day"
    ],
    "wof:name": "St John's Christian Preschool",
    "wof:placetype": "venue"
  },
  "geometry": {"coordinates":[-83.15628,40.080476],"type":"Point"}
}
