{
  "type": "Feature",
  "properties": {
    "addr:full": "6660 Outville Rd SW Pataskala OH 43062",
    "addr:postcode": "6660;43062",
    "addr:street": "Outville Rd Sw",
    "iso:country": "US",
    "sg:address": "6660 Outville Rd SW",
    "sg:city": "Pataskala",
    "sg:classifiers": [
      {
        "category": "Railroad",
        "type": "Transportation"
      }
    ],
    "sg:phone": "+1 740 927 5043",
    "sg:postcode": "43062",
    "sg:province": "OH",
    "sg:tags": [
      "operator",
      "line"
    ],
    "wof:name": "Columbus \u0026 Ohio River Rail Rd",
    "wof:placetype": "venue"
  },
  "geometry": {"coordinates":[-82.596602,39.994487],"type":"Point"}
}
