{
  "type": "Feature",
  "properties": {
    "iso:country":"US",
    "sg:address":"1710 Stringtown Rd",
    "sg:city":"Grove City",
    "sg:classifiers":[
        {
            "category":"Autos & Motor Vehicles",
            "subcategory":"Auto Supplies",
            "type":"Retail Goods"
        }
    ],
    "sg:phone":"+1 614 871 6016",
    "sg:postcode":"43123",
    "sg:province":"OH",
    "sg:tags":[
        "tire"
    ],
    "sg:website":"www.tires.com",
    "wof:name":"Discount Tire Co",
    "wof:placetype":"venue"
},
  "geometry": {"coordinates":[-83.04423,39.878886],"type":"Point"}
}