{
  "type": "Feature",
  "properties": {
    "addr:full": "9764 Kenwood Rd Cincinnati OH 45242",
    "addr:housenumber": "9764",
    "addr:postcode": "45242",
    "addr:street": "Kenwood Rd",
    "iso:country": "US",
    "sg:address": "9764 Kenwood Rd",
    "sg:city": "Cincinnati",
    "sg:classifiers": [
      {
        "category": "Professional",
        "subcategory": "Lawyer \u0026 Legal Services",
        "type": "Services"
      }
    ],
    "sg:phone": "+1 513 891 5630",
    "sg:postcode": "45242",
    "sg:province": "OH",
    "sg:tags": [
      "attorney"
    ],
    "wof:name": "Eric D Bender Co",
    "wof:placetype": "venue"
  },
  "geometry": {"coordinates":[-84.376586,39.234552],"type":"Point"}
}
