{
  "type": "Feature",
  "properties": {
    "iso:country":"US",
    "sg:address":"604 Home Ave",
    "sg:city":"Akron",
    "sg:classifiers":[
        {
            "category":"Retail",
            "subcategory":"Car Wash",
            "type":"Services"
        }
    ],
    "sg:phone":"+1 330 434 5985",
    "sg:postcode":"44305",
    "sg:province":"OH",
    "sg:tags":[
        "automobile",
        "detail",
        "clean"
    ],
    "wof:name":"Strictly Details & Accessories",
    "wof:placetype":"venue"
},
  "geometry": {"coordinates":[-81.48773,41.09117],"type":"Point"}
}