{
  "type": "Feature",
  "properties": {
    "addr:full": "604 Home Ave Akron OH 44305",
    "addr:housenumber": "604",
    "addr:postcode": "44305",
    "addr:street": "Home Ave",
    "iso:country": "US",
    "sg:address": "604 Home Ave",
    "sg:city": "Akron",
    "sg:classifiers": [
      {
        "category": "Retail",
        "subcategory": "Car Wash",
        "type": "Services"
      }
    ],
    "sg:phone": "+1 330 434 5985",
    "sg:postcode": "44305",
    "sg:province": "OH",
    "sg:tags": [
      "automobile",
      "detail",
      "clean"
    ],
    "wof:name": "Strictly Details \u0026 Accessories",
    "wof:placetype": "venue"
  },
  "geometry": {"coordinates":[-81.48773,41.09117],"type":"Point"}
}
