{
  "type": "Feature",
  "properties": {
    "iso:country":"US",
    "sg:address":"8939 Thomas Rd",
    "sg:city":"Middletown",
    "sg:classifiers":[
        {
            "category":"Building & Trades",
            "subcategory":"Landscaping Services",
            "type":"Services"
        }
    ],
    "sg:phone":"+1 513 422 1756",
    "sg:postcode":"45042",
    "sg:province":"OH",
    "wof:name":"Pro Lawn",
    "wof:placetype":"venue"
},
  "geometry": {"coordinates":[-84.366911,39.562257],"type":"Point"}
}