{
  "type": "Feature",
  "properties": {
    "iso:country":"US",
    "sg:address":"17418 Beech Grove Trl",
    "sg:city":"Chagrin Falls",
    "sg:classifiers":[
        {
            "category":"Professional",
            "subcategory":"Management & Consulting",
            "type":"Services"
        }
    ],
    "sg:phone":"+1 440 543 6431",
    "sg:postcode":"44023",
    "sg:province":"OH",
    "sg:tags":[
        "marketing",
        "program"
    ],
    "wof:name":"Flexible Marketing",
    "wof:placetype":"venue"
},
  "geometry": {"coordinates":[-81.370083,41.394365],"type":"Point"}
}