{
  "type": "Feature",
  "properties": {
    "addr:full": "17418 Beech Grove Trl Chagrin Falls OH 44023",
    "addr:housenumber": "17418",
    "addr:postcode": "44023",
    "addr:street": "Beech Grove Trl",
    "iso:country": "US",
    "sg:address": "17418 Beech Grove Trl",
    "sg:city": "Chagrin Falls",
    "sg:classifiers": [
      {
        "category": "Professional",
        "subcategory": "Management \u0026 Consulting",
        "type": "Services"
      }
    ],
    "sg:phone": "+1 440 543 6431",
    "sg:postcode": "44023",
    "sg:province": "OH",
    "sg:tags": [
      "marketing",
      "program"
    ],
    "wof:name": "Flexible Marketing",
    "wof:placetype": "venue"
  },
  "geometry": {"coordinates":[-81.370083,41.394365],"type":"Point"}
}
