{
  "type": "Feature",
  "properties": {
    "iso:country":"US",
    "sg:address":"251 Milan Ave",
    "sg:city":"Norwalk",
    "sg:classifiers":[
        {
            "category":"Organizations",
            "subcategory":"Religious Organization",
            "type":"Services"
        }
    ],
    "sg:phone":"+1 419 668 3365",
    "sg:postcode":"44857",
    "sg:province":"OH",
    "sg:tags":[
        "church"
    ],
    "wof:name":"Crossroads Community Church",
    "wof:placetype":"venue"
},
  "geometry": {"coordinates":[-82.61191700000001,41.260355],"type":"Point"}
}