{
  "type": "Feature",
  "properties": {
    "addr:full": "1370 Stadelman Ave Akron OH 44320",
    "addr:housenumber": "1370",
    "addr:postcode": "44320",
    "addr:street": "Stadelman Ave",
    "iso:country": "US",
    "sg:address": "1370 Stadelman Ave",
    "sg:city": "Akron",
    "sg:classifiers": [
      {
        "category": "Banks \u0026 Credit Unions",
        "subcategory": "Bank",
        "type": "Services"
      }
    ],
    "sg:phone": "+1 330 475 0718",
    "sg:postcode": "44320",
    "sg:province": "OH",
    "sg:tags": [
      "loan",
      "real estate"
    ],
    "wof:name": "Al Walkin Al Amer Home Lending",
    "wof:placetype": "venue"
  },
  "geometry": {"coordinates":[-81.567002,41.090482],"type":"Point"}
}
