{
  "type": "Feature",
  "properties": {
    "addr:full": "1624 Central Ave Middletown OH 45044",
    "addr:housenumber": "1624",
    "addr:postcode": "45044",
    "addr:street": "Central Ave",
    "iso:country": "US",
    "sg:address": "1624 Central Ave",
    "sg:city": "Middletown",
    "sg:classifiers": [
      {
        "category": "Shopping",
        "subcategory": "Clothing, Apparel, \u0026 Fashions",
        "type": "Retail Goods"
      }
    ],
    "sg:phone": "+1 513 423 2199",
    "sg:postcode": "45044",
    "sg:province": "OH",
    "sg:tags": [
      "alteration"
    ],
    "wof:name": "Classic Stitch Sewing Shop",
    "wof:placetype": "venue"
  },
  "geometry": {"coordinates":[-84.396676,39.514243],"type":"Point"}
}
