{
  "type": "Feature",
  "properties": {
    "addr:full":"12000 Wanda Ave Cleveland OH 44135",
    "addr:housenumber":"12000",
    "addr:postcode":"44135",
    "addr:street":"Wanda Ave",
    "iso:country":"US",
    "sg:address":"12000 Wanda Ave",
    "sg:city":"Cleveland",
    "sg:classifiers":[
        {
            "category":"Social Services",
            "subcategory":"Child Care",
            "type":"Services"
        }
    ],
    "sg:phone":"+1 216 252 7794",
    "sg:postcode":"44135",
    "sg:province":"OH",
    "wof:name":"Lauries Daycare",
    "wof:placetype":"venue"
},
  "geometry": {"coordinates":[-81.77355300000001,41.439948],"type":"Point"}
}