{
  "type": "Feature",
  "properties": {
    "addr:full":"1931 W Market St Warren OH 44485",
    "addr:housenumber":"1931",
    "addr:postcode":"44485",
    "addr:street":"W Market St",
    "iso:country":"US",
    "sg:address":"1931 W Market St",
    "sg:city":"Warren",
    "sg:classifiers":[
        {
            "category":"Retail",
            "subcategory":"Auto Repair",
            "type":"Services"
        }
    ],
    "sg:phone":"+1 330 392 9580",
    "sg:postcode":"44485",
    "sg:province":"OH",
    "sg:tags":[
        "repairing",
        "automobile"
    ],
    "wof:name":"Chris & Sons Automotive Inc",
    "wof:placetype":"venue"
},
  "geometry": {"coordinates":[-80.84356699999999,41.235422],"type":"Point"}
}