{
  "type": "Feature",
  "properties": {
    "iso:country":"US",
    "sg:address":"7057 W Chester Rd",
    "sg:city":"West Chester",
    "sg:classifiers":[
        {
            "category":"Wholesale",
            "subcategory":"Chemicals & Plastics",
            "type":"Manufacturing & Wholesale Goods"
        }
    ],
    "sg:phone":"+1 513 755 0067",
    "sg:postcode":"45069",
    "sg:province":"OH",
    "wof:name":"James P Allshouse",
    "wof:placetype":"venue"
},
  "geometry": {"coordinates":[-84.392954,39.322908],"type":"Point"}
}