{
  "type": "Feature",
  "properties": {
    "addr:full": "7057 W Chester Rd West Chester OH 45069",
    "addr:housenumber": "7057",
    "addr:postcode": "45069",
    "addr:street": "W Chester Rd",
    "iso:country": "US",
    "sg:address": "7057 W Chester Rd",
    "sg:city": "West Chester",
    "sg:classifiers": [
      {
        "category": "Wholesale",
        "subcategory": "Chemicals \u0026 Plastics",
        "type": "Manufacturing \u0026 Wholesale Goods"
      }
    ],
    "sg:phone": "+1 513 755 0067",
    "sg:postcode": "45069",
    "sg:province": "OH",
    "wof:name": "James P Allshouse",
    "wof:placetype": "venue"
  },
  "geometry": {"coordinates":[-84.392954,39.322908],"type":"Point"}
}
