{
  "type": "Feature",
  "properties": {
    "iso:country":"US",
    "sg:address":"1001 Cordova Ave",
    "sg:city":"Akron",
    "sg:classifiers":[
        {
            "category":"Building & Trades",
            "subcategory":"Electrical",
            "type":"Services"
        }
    ],
    "sg:phone":"+1 330 864 7663",
    "sg:postcode":"44320",
    "sg:province":"OH",
    "sg:tags":[
        "electrical",
        "electric",
        "business",
        "contractor"
    ],
    "wof:name":"Home's Electric",
    "wof:placetype":"venue"
},
  "geometry": {"coordinates":[-81.575024,41.080425],"type":"Point"}
}