{
  "type": "Feature",
  "properties": {
    "addr:full": "820 State Rte 316 W Ashville OH 43103",
    "addr:housenumber": "820",
    "addr:postcode": "43103",
    "addr:street": "State Rte 316 W",
    "iso:country": "US",
    "sg:address": "820 State Rte 316 W",
    "sg:city": "Ashville",
    "sg:phone": "+1 740 983 2339",
    "sg:postcode": "43103",
    "sg:province": "OH",
    "sg:tags": [
      "farm",
      "corn",
      "soybean"
    ],
    "wof:name": "Roese Farm",
    "wof:placetype": "venue"
  },
  "geometry": {"coordinates":[-82.979355,39.714314],"type":"Point"}
}
