{
  "type": "Feature",
  "properties": {
    "iso:country":"US",
    "sg:address":"6294 Highgate Pl",
    "sg:city":"Lewis Center",
    "sg:classifiers":[
        {
            "category":"Real Estate",
            "subcategory":"Real Estate Agent",
            "type":"Services"
        }
    ],
    "sg:phone":"+1 614 882 8043",
    "sg:postcode":"43035",
    "sg:province":"OH",
    "wof:name":"G Hadder & Co Realtors",
    "wof:placetype":"venue"
},
  "geometry": {"coordinates":[-82.980802,40.186378],"type":"Point"}
}