{
  "type": "Feature",
  "properties": {
    "addr:full": "6294 Highgate Pl Lewis Center OH 43035",
    "addr:housenumber": "6294",
    "addr:postcode": "43035",
    "addr:street": "Highgate Pl",
    "iso:country": "US",
    "sg:address": "6294 Highgate Pl",
    "sg:city": "Lewis Center",
    "sg:classifiers": [
      {
        "category": "Real Estate",
        "subcategory": "Real Estate Agent",
        "type": "Services"
      }
    ],
    "sg:phone": "+1 614 882 8043",
    "sg:postcode": "43035",
    "sg:province": "OH",
    "wof:name": "G Hadder \u0026 Co Realtors",
    "wof:placetype": "venue"
  },
  "geometry": {"coordinates":[-82.980802,40.186378],"type":"Point"}
}
