{
  "type": "Feature",
  "properties": {
    "addr:full": "819 N Locust St Ottawa OH 45875",
    "addr:housenumber": "819",
    "addr:postcode": "45875",
    "addr:street": "N Locust St",
    "iso:country": "US",
    "sg:address": "819 N Locust St",
    "sg:city": "Ottawa",
    "sg:classifiers": [
      {
        "category": "Insurance",
        "subcategory": "Insurance Agent",
        "type": "Services"
      }
    ],
    "sg:phone": "+1 419 523 4768",
    "sg:postcode": "45875",
    "sg:province": "OH",
    "wof:name": "State Farm Insurance",
    "wof:placetype": "venue"
  },
  "geometry": {"coordinates":[-84.04426,41.025824],"type":"Point"}
}
