{
  "type": "Feature",
  "properties": {
    "addr:full": "308 New Towne Square Dr Toledo OH 43612",
    "addr:housenumber": "308",
    "addr:postcode": "43612",
    "addr:street": "New Towne Square Dr",
    "iso:country": "US",
    "sg:address": "308 New Towne Square Dr",
    "sg:city": "Toledo",
    "sg:classifiers": [
      {
        "category": "Recreation",
        "type": "Entertainment"
      }
    ],
    "sg:phone": "+1 419 470 5665",
    "sg:postcode": "43612",
    "sg:province": "OH",
    "sg:tags": [
      "club",
      "travel"
    ],
    "wof:name": "AAA Northwest Ohio",
    "wof:placetype": "venue"
  },
  "geometry": {"coordinates":[-83.545406,41.723355],"type":"Point"}
}
