{
  "type": "Feature",
  "properties": {
    "iso:country":"US",
    "sg:address":"103 N Union St",
    "sg:city":"Delaware",
    "sg:classifiers":[
        {
            "category":"Real Estate",
            "subcategory":"Real Estate Services",
            "type":"Services"
        }
    ],
    "sg:phone":"+1 740 363 1324",
    "sg:postcode":"43015",
    "sg:province":"OH",
    "sg:tags":[
        "company",
        "title"
    ],
    "wof:name":"Lawyers Title",
    "wof:placetype":"venue"
},
  "geometry": {"coordinates":[-83.065524,40.304797],"type":"Point"}
}