{
  "type": "Feature",
  "properties": {
    "addr:full":"1221 7th Ave Akron OH 44306",
    "addr:housenumber":"1221",
    "addr:postcode":"44306",
    "addr:street":"7Th Ave",
    "iso:country":"US",
    "sg:address":"1221 7th Ave",
    "sg:city":"Akron",
    "sg:classifiers":[
        {
            "category":"Building & Trades",
            "subcategory":"Landscaping Services",
            "type":"Services"
        }
    ],
    "sg:phone":"+1 330 724 4240",
    "sg:postcode":"44306",
    "sg:province":"OH",
    "sg:tags":[
        "lawn",
        "design",
        "maintenance",
        "contractor"
    ],
    "wof:name":"Hydro Laen Landscaping",
    "wof:placetype":"venue"
},
  "geometry": {"coordinates":[-81.484566,41.057455],"type":"Point"}
}