{
  "type": "Feature",
  "properties": {
    "addr:full":"399 S State St Westerville OH 43081",
    "addr:housenumber":"399",
    "addr:postcode":"43081",
    "addr:street":"S State St",
    "iso:country":"US",
    "sg:address":"399 S State St",
    "sg:city":"Westerville",
    "sg:classifiers":[
        {
            "category":"Shopping",
            "subcategory":"Hobbies, Toys, & Games",
            "type":"Retail Goods"
        },
        {
            "category":"Shopping",
            "subcategory":"Jewelry",
            "type":"Retail Goods"
        },
        {
            "category":"Manufacturing",
            "subcategory":"Jewelry",
            "type":"Manufacturing & Wholesale Goods"
        },
        {
            "category":"Professional",
            "subcategory":"Business Services",
            "type":"Services"
        },
        {
            "category":"Shopping",
            "type":"Retail Goods"
        }
    ],
    "sg:phone":"+1 614 882 3937",
    "sg:postcode":"43081",
    "sg:province":"OH",
    "sg:tags":[
        "platinum",
        "collectible",
        "designer",
        "gold",
        "shop",
        "supply",
        "jeweler",
        "buyer",
        "hobby",
        "model",
        "coin",
        "silver",
        "appraiser"
    ],
    "wof:name":"Allen's Coin Shop Inc.",
    "wof:placetype":"venue"
},
  "geometry": {"coordinates":[-82.927734,40.115459],"type":"Point"}
}