{
  "type": "Feature",
  "properties": {
    "iso:country":"US",
    "sg:address":"10101 Alliance Rd",
    "sg:city":"Cincinnati",
    "sg:classifiers":[
        {
            "category":"Insurance",
            "subcategory":"Insurance Agent",
            "type":"Services"
        }
    ],
    "sg:phone":"+1 513 794 1650",
    "sg:postcode":"45242",
    "sg:province":"OH",
    "wof:name":"American Credit Indemnity Co",
    "wof:placetype":"venue"
},
  "geometry": {"coordinates":[-84.38159899999999,39.239823],"type":"Point"}
}