{
  "type": "Feature",
  "properties": {
    "addr:full": "2872 Broxton Rd Cleveland OH 44120",
    "addr:housenumber": "2872",
    "addr:postcode": "44120",
    "addr:street": "Broxton Rd",
    "iso:country": "US",
    "sg:address": "2872 Broxton Rd",
    "sg:city": "Cleveland",
    "sg:classifiers": [
      {
        "category": "Banks \u0026 Credit Unions",
        "subcategory": "Financial Services",
        "type": "Services"
      }
    ],
    "sg:phone": "+1 216 751 5546",
    "sg:postcode": "44120",
    "sg:province": "OH",
    "sg:tags": [
      "trust",
      "nonprofit",
      "management"
    ],
    "wof:name": "Cochran Family Foundation",
    "wof:placetype": "venue"
  },
  "geometry": {"coordinates":[-81.563382,41.477888],"type":"Point"}
}
