{
  "type": "Feature",
  "properties": {
    "iso:country":"US",
    "sg:address":"2872 Broxton Rd",
    "sg:city":"Cleveland",
    "sg:classifiers":[
        {
            "category":"Banks & Credit Unions",
            "subcategory":"Financial Services",
            "type":"Services"
        }
    ],
    "sg:phone":"+1 216 751 5546",
    "sg:postcode":"44120",
    "sg:province":"OH",
    "sg:tags":[
        "trust",
        "nonprofit",
        "management"
    ],
    "wof:name":"Cochran Family Foundation",
    "wof:placetype":"venue"
},
  "geometry": {"coordinates":[-81.563382,41.477888],"type":"Point"}
}