{
  "type": "Feature",
  "properties": {
    "addr:full": "513 S Broadway St Blanchester OH 45107",
    "addr:housenumber": "513",
    "addr:postcode": "45107",
    "addr:street": "S Broadway St",
    "iso:country": "US",
    "sg:address": "513 S Broadway St",
    "sg:city": "Blanchester",
    "sg:classifiers": [
      {
        "category": "Food \u0026 Beverages",
        "subcategory": "Liquor \u0026 Beverages",
        "type": "Retail Goods"
      }
    ],
    "sg:phone": "+1 937 783 4322",
    "sg:postcode": "45107",
    "sg:province": "OH",
    "sg:tags": [
      "alcoholic"
    ],
    "wof:name": "S \u0026 S Market",
    "wof:placetype": "venue"
  },
  "geometry": {"coordinates":[-83.984284,39.289304],"type":"Point"}
}
