{
  "type": "Feature",
  "properties": {
    "iso:country":"US",
    "sg:address":"513 S Broadway St",
    "sg:city":"Blanchester",
    "sg:classifiers":[
        {
            "category":"Food & Beverages",
            "subcategory":"Liquor & Beverages",
            "type":"Retail Goods"
        }
    ],
    "sg:phone":"+1 937 783 4322",
    "sg:postcode":"45107",
    "sg:province":"OH",
    "sg:tags":[
        "alcoholic"
    ],
    "wof:name":"S & S Market",
    "wof:placetype":"venue"
},
  "geometry": {"coordinates":[-83.984284,39.289304],"type":"Point"}
}