{
  "type": "Feature",
  "properties": {
    "addr:full":"4835 Reading Rd Cincinnati OH 45237",
    "addr:housenumber":"4835",
    "addr:postcode":"45237",
    "addr:street":"Reading Rd",
    "iso:country":"US",
    "sg:address":"4835 Reading Rd",
    "sg:city":"Cincinnati",
    "sg:classifiers":[
        {
            "category":"Professional",
            "type":"Services"
        }
    ],
    "sg:phone":"+1 513 242 1138",
    "sg:postcode":"45237",
    "sg:province":"OH",
    "sg:tags":[
        "establishment"
    ],
    "wof:name":"Family Connection",
    "wof:placetype":"venue"
},
  "geometry": {"coordinates":[-84.467231,39.17465],"type":"Point"}
}