{
  "type": "Feature",
  "properties": {
    "addr:full":"3857 Ivanhoe Ave Cincinnati OH 45212",
    "addr:housenumber":"3857",
    "addr:postcode":"45212",
    "addr:street":"Ivanhoe Ave",
    "iso:country":"US",
    "sg:address":"3857 Ivanhoe Ave",
    "sg:city":"Cincinnati",
    "sg:classifiers":[
        {
            "category":"Professional",
            "subcategory":"Research",
            "type":"Services"
        }
    ],
    "sg:phone":"+1 513 631 4266",
    "sg:postcode":"45212",
    "sg:province":"OH",
    "sg:tags":[
        "market"
    ],
    "wof:name":"Clear Chnnel Crtcal Mass Media",
    "wof:placetype":"venue"
},
  "geometry": {"coordinates":[-84.465082,39.149462],"type":"Point"}
}