{
  "type": "Feature",
  "properties": {
    "iso:country":"US",
    "sg:address":"986 Apple Blossom Ln",
    "sg:city":"Milford",
    "sg:classifiers":[
        {
            "category":"Real Estate",
            "subcategory":"Developer",
            "type":"Services"
        }
    ],
    "sg:phone":"+1 513 576 6383",
    "sg:postcode":"45150",
    "sg:province":"OH",
    "wof:name":"Bkg Development Ltd",
    "wof:placetype":"venue"
},
  "geometry": {"coordinates":[-84.24715,39.174294],"type":"Point"}
}