{
  "type": "Feature",
  "properties": {
    "addr:full":"6722 Miller Dr North Ridgeville OH 44039",
    "addr:housenumber":"6722",
    "addr:postcode":"44039",
    "addr:street":"Miller Dr",
    "iso:country":"US",
    "sg:address":"6722 Miller Dr",
    "sg:city":"North Ridgeville",
    "sg:classifiers":[
        {
            "category":"Wholesale",
            "subcategory":"Computers",
            "type":"Manufacturing & Wholesale Goods"
        }
    ],
    "sg:phone":"+1 440 327 5829",
    "sg:postcode":"44039",
    "sg:province":"OH",
    "wof:name":"Total Technical Training",
    "wof:placetype":"venue"
},
  "geometry": {"coordinates":[-81.989783,41.388439],"type":"Point"}
}