{
  "type": "Feature",
  "properties": {
    "addr:full": "701 N James Rd Columbus OH 43219",
    "addr:housenumber": "701",
    "addr:postcode": "43219",
    "addr:street": "N James Rd",
    "iso:country": "US",
    "sg:address": "701 N James Rd",
    "sg:city": "Columbus",
    "sg:classifiers": [
      {
        "category": "Health Services",
        "subcategory": "Clinic",
        "type": "Services"
      }
    ],
    "sg:phone": "+1 614 231 9202",
    "sg:postcode": "43219",
    "sg:province": "OH",
    "sg:tags": [
      "home",
      "care"
    ],
    "wof:name": "Independent Home Care Inc",
    "wof:placetype": "venue"
  },
  "geometry": {"coordinates":[-82.903197,39.988014],"type":"Point"}
}
