{
  "type": "Feature",
  "properties": {
    "addr:full": "5260 Liberty Ave Vermilion OH 44089",
    "addr:housenumber": "5260",
    "addr:postcode": "44089",
    "addr:street": "Liberty Ave",
    "iso:country": "US",
    "sg:address": "5260 Liberty Ave",
    "sg:city": "Vermilion",
    "sg:classifiers": [
      {
        "category": "Autos \u0026 Motor Vehicles",
        "subcategory": "Boat Sales",
        "type": "Retail Goods"
      }
    ],
    "sg:phone": "+1 440 967 0260",
    "sg:postcode": "44089",
    "sg:province": "OH",
    "sg:website": "www.freeman-eckley.com",
    "wof:name": "Freeman Eckley Inc",
    "wof:placetype": "venue"
  },
  "geometry": {"coordinates":[-82.361916,41.422093],"type":"Point"}
}
