{
  "type": "Feature",
  "properties": {
    "iso:country":"US",
    "sg:address":"5260 Liberty Ave",
    "sg:city":"Vermilion",
    "sg:classifiers":[
        {
            "category":"Autos & Motor Vehicles",
            "subcategory":"Boat Sales",
            "type":"Retail Goods"
        }
    ],
    "sg:phone":"+1 440 967 0260",
    "sg:postcode":"44089",
    "sg:province":"OH",
    "sg:website":"www.freeman-eckley.com",
    "wof:name":"Freeman Eckley Inc",
    "wof:placetype":"venue"
},
  "geometry": {"coordinates":[-82.36191599999999,41.422093],"type":"Point"}
}