{
  "type": "Feature",
  "properties": {
    "addr:full":"950 S Sawburg Rd Alliance OH 44601",
    "addr:housenumber":"950",
    "addr:postcode":"44601",
    "addr:street":"S Sawburg Rd",
    "iso:country":"US",
    "sg:address":"950 S Sawburg Rd",
    "sg:city":"Alliance",
    "sg:classifiers":[
        {
            "category":"Professional",
            "subcategory":"Lawyer & Legal Services",
            "type":"Services"
        }
    ],
    "sg:phone":"+1 330 823 7411",
    "sg:postcode":"44601",
    "sg:province":"OH",
    "wof:name":"John E Haupt Jr",
    "wof:placetype":"venue"
},
  "geometry": {"coordinates":[-81.134603,40.912182],"type":"Point"}
}