{
  "type": "Feature",
  "properties": {
    "addr:full":"1225 N Main St North Canton OH 44720",
    "addr:housenumber":"1225",
    "addr:postcode":"44720",
    "addr:street":"N Main St",
    "iso:country":"US",
    "sg:address":"1225 N Main St",
    "sg:city":"North Canton",
    "sg:classifiers":[
        {
            "category":"Organizations",
            "subcategory":"Non-profit Organization",
            "type":"Services"
        }
    ],
    "sg:phone":"+1 330 433 0063",
    "sg:postcode":"44720",
    "sg:province":"OH",
    "wof:name":"Junior Achievement-Stark Cnty",
    "wof:placetype":"venue"
},
  "geometry": {"coordinates":[-81.40518899999999,40.888245],"type":"Point"}
}