{
  "type": "Feature",
  "properties": {
    "addr:full": "321 N Williams St Paulding OH 45879",
    "addr:housenumber": "321",
    "addr:postcode": "45879",
    "addr:street": "N Williams St",
    "iso:country": "US",
    "sg:address": "321 N Williams St",
    "sg:city": "Paulding",
    "sg:classifiers": [
      {
        "category": "Organizations",
        "subcategory": "Religious Organization",
        "type": "Services"
      }
    ],
    "sg:phone": "+1 419 399 3591",
    "sg:postcode": "45879",
    "sg:province": "OH",
    "sg:tags": [
      "church"
    ],
    "wof:name": "Paulding United Methodist Chr",
    "wof:placetype": "venue"
  },
  "geometry": {"coordinates":[-84.580688,41.139948],"type":"Point"}
}
