{
  "type": "Feature",
  "properties": {
    "addr:full":"4661 Sawmill Rd Columbus OH 43220",
    "addr:housenumber":"4661",
    "addr:postcode":"43220",
    "addr:street":"Sawmill Rd",
    "iso:country":"US",
    "sg:address":"4661 Sawmill Rd",
    "sg:city":"Columbus",
    "sg:classifiers":[
        {
            "category":"Professional",
            "type":"Services"
        }
    ],
    "sg:phone":"+1 614 326 0459",
    "sg:postcode":"43220",
    "sg:province":"OH",
    "sg:tags":[
        "establishment"
    ],
    "wof:name":"Dogwood Enterprises LP",
    "wof:placetype":"venue"
},
  "geometry": {"coordinates":[-83.093452,40.062122],"type":"Point"}
}