{
  "type": "Feature",
  "properties": {
    "iso:country":"US",
    "sg:address":"3910 South Ave",
    "sg:city":"Youngstown",
    "sg:classifiers":[
        {
            "category":"Organizations",
            "subcategory":"Professional Association",
            "type":"Services"
        }
    ],
    "sg:phone":"+1 330 783 6290",
    "sg:postcode":"44512",
    "sg:province":"OH",
    "wof:name":"League Of Women Voters-Greater",
    "wof:placetype":"venue"
},
  "geometry": {"coordinates":[-80.639095,41.053608],"type":"Point"}
}