{
  "type": "Feature",
  "properties": {
    "addr:full": "1208 E Hudson St Columbus OH 43211",
    "addr:housenumber": "1208",
    "addr:postcode": "43211",
    "addr:street": "E Hudson St",
    "iso:country": "US",
    "sg:address": "1208 E Hudson St",
    "sg:city": "Columbus",
    "sg:classifiers": [
      {
        "category": "Professional",
        "subcategory": "Business Services",
        "type": "Services"
      }
    ],
    "sg:phone": "+1 614 261 7172",
    "sg:postcode": "43211",
    "sg:province": "OH",
    "sg:tags": [
      "firm",
      "design"
    ],
    "wof:name": "Quality Design Xpress Inc",
    "wof:placetype": "venue"
  },
  "geometry": {"coordinates":[-82.977005,40.014159],"type":"Point"}
}
