{
  "type": "Feature",
  "properties": {
    "iso:country":"US",
    "sg:address":"1208 E Hudson St",
    "sg:city":"Columbus",
    "sg:classifiers":[
        {
            "category":"Professional",
            "subcategory":"Business Services",
            "type":"Services"
        }
    ],
    "sg:phone":"+1 614 261 7172",
    "sg:postcode":"43211",
    "sg:province":"OH",
    "sg:tags":[
        "firm",
        "design"
    ],
    "wof:name":"Quality Design Xpress Inc",
    "wof:placetype":"venue"
},
  "geometry": {"coordinates":[-82.97700500000001,40.014159],"type":"Point"}
}