{
  "type": "Feature",
  "properties": {
    "iso:country":"US",
    "sg:address":"5455 State St",
    "sg:city":"Whipple",
    "sg:classifiers":[
        {
            "category":"Building & Trades",
            "subcategory":"Pest Control",
            "type":"Services"
        }
    ],
    "sg:phone":"+1 740 525 7174",
    "sg:postcode":"45710",
    "sg:province":"OH",
    "sg:tags":[
        "trapper",
        "animal"
    ],
    "wof:name":"Coyote's Wildlife Control",
    "wof:placetype":"venue"
},
  "geometry": {"coordinates":[-82.200086,39.224182],"type":"Point"}
}