{
  "type": "Feature",
  "properties": {
    "iso:country":"US",
    "sg:address":"732 E 6th St",
    "sg:city":"Marysville",
    "sg:classifiers":[
        {
            "category":"Building & Trades",
            "subcategory":"Plumbing",
            "type":"Services"
        }
    ],
    "sg:phone":"+1 937 642 3956",
    "sg:postcode":"43040",
    "sg:province":"OH",
    "sg:tags":[
        "air",
        "heating",
        "conditioning",
        "contractor"
    ],
    "wof:name":"Althouse Heating & Cooling",
    "wof:placetype":"venue"
},
  "geometry": {"coordinates":[-83.357792,40.234796],"type":"Point"}
}