{
  "type": "Feature",
  "properties": {
    "addr:full": "732 E 6th St Marysville OH 43040",
    "addr:housenumber": "732",
    "addr:postcode": "43040",
    "addr:street": "E 6Th St",
    "iso:country": "US",
    "sg:address": "732 E 6th St",
    "sg:city": "Marysville",
    "sg:classifiers": [
      {
        "category": "Building \u0026 Trades",
        "subcategory": "Plumbing",
        "type": "Services"
      }
    ],
    "sg:phone": "+1 937 642 3956",
    "sg:postcode": "43040",
    "sg:province": "OH",
    "sg:tags": [
      "air",
      "heating",
      "conditioning",
      "contractor"
    ],
    "wof:name": "Althouse Heating \u0026 Cooling",
    "wof:placetype": "venue"
  },
  "geometry": {"coordinates":[-83.357792,40.234796],"type":"Point"}
}
