{
  "type": "Feature",
  "properties": {
    "iso:country":"US",
    "sg:address":"1788 Obetz Ave",
    "sg:city":"Obetz",
    "sg:classifiers":[
        {
            "category":"Government",
            "subcategory":"Office",
            "type":"Public Place"
        }
    ],
    "sg:phone":"+1 614 491 0523",
    "sg:postcode":"43207",
    "sg:province":"OH",
    "sg:tags":[
        "village"
    ],
    "wof:name":"Obetz Municipal Office",
    "wof:placetype":"venue"
},
  "geometry": {"coordinates":[-82.953163,39.87864],"type":"Point"}
}