{
  "type": "Feature",
  "properties": {
    "addr:full": "1788 Obetz Ave Obetz OH 43207",
    "addr:housenumber": "1788",
    "addr:postcode": "43207",
    "addr:street": "Obetz Ave",
    "iso:country": "US",
    "sg:address": "1788 Obetz Ave",
    "sg:city": "Obetz",
    "sg:classifiers": [
      {
        "category": "Government",
        "subcategory": "Office",
        "type": "Public Place"
      }
    ],
    "sg:phone": "+1 614 491 0523",
    "sg:postcode": "43207",
    "sg:province": "OH",
    "sg:tags": [
      "village"
    ],
    "wof:name": "Obetz Municipal Office",
    "wof:placetype": "venue"
  },
  "geometry": {"coordinates":[-82.953163,39.87864],"type":"Point"}
}
