{
  "type": "Feature",
  "properties": {
    "addr:full":"2297 Miller Graber Rd Newton Falls OH 44444",
    "addr:housenumber":"2297",
    "addr:postcode":"44444",
    "addr:street":"Miller Graber Rd",
    "iso:country":"US",
    "sg:address":"2297 Miller Graber Rd",
    "sg:city":"Newton Falls",
    "sg:classifiers":[
        {
            "category":"Building & Trades",
            "subcategory":"Plumbing",
            "type":"Services"
        }
    ],
    "sg:phone":"+1 330 219 4321",
    "sg:postcode":"44444",
    "sg:province":"OH",
    "sg:tags":[
        "conditioning",
        "air",
        "system",
        "contractor"
    ],
    "wof:name":"BMC Building & Mechanical",
    "wof:placetype":"venue"
},
  "geometry": {"coordinates":[-80.93511100000001,41.184245],"type":"Point"}
}