{
  "type": "Feature",
  "properties": {
    "addr:full": "6600 W 130th St Cleveland OH 44130",
    "addr:housenumber": "6600",
    "addr:postcode": "44130",
    "addr:street": "W 130Th St",
    "iso:country": "US",
    "sg:address": "6600 W 130th St",
    "sg:city": "Cleveland",
    "sg:classifiers": [
      {
        "category": "Sports \u0026 Exercise",
        "subcategory": "Gym",
        "type": "Entertainment"
      }
    ],
    "sg:phone": "+1 440 886 4545",
    "sg:postcode": "44130",
    "sg:province": "OH",
    "sg:tags": [
      "club",
      "fitness"
    ],
    "wof:name": "Omni Fitness Club Inc",
    "wof:placetype": "venue"
  },
  "geometry": {"coordinates":[-81.784713,41.380491],"type":"Point"}
}
