{
  "type": "Feature",
  "properties": {
    "addr:full":"425 Main St Coshocton OH 43812",
    "addr:housenumber":"425",
    "addr:postcode":"43812",
    "addr:street":"Main St",
    "iso:country":"US",
    "sg:address":"425 Main St",
    "sg:city":"Coshocton",
    "sg:classifiers":[
        {
            "category":"Shopping",
            "subcategory":"Department Store",
            "type":"Retail Goods"
        }
    ],
    "sg:phone":"+1 740 622 1677",
    "sg:postcode":"43812",
    "sg:province":"OH",
    "wof:name":"Stage Specialty",
    "wof:placetype":"venue"
},
  "geometry": {"coordinates":[-81.86496200000001,40.27353],"type":"Point"}
}