{
  "type": "Feature",
  "properties": {
    "addr:full": "401 Rose Ave SE Massillon OH 44646",
    "addr:housenumber": "401",
    "addr:postcode": "44646",
    "addr:street": "Rose Ave Se",
    "iso:country": "US",
    "sg:address": "401 Rose Ave SE",
    "sg:city": "Massillon",
    "sg:classifiers": [
      {
        "category": "Manufacturing",
        "subcategory": "Metals",
        "type": "Manufacturing \u0026 Wholesale Goods"
      }
    ],
    "sg:phone": "+1 330 837 7024",
    "sg:postcode": "44646",
    "sg:province": "OH",
    "sg:tags": [
      "steel",
      "mills"
    ],
    "sg:website": "www.republicengineered.com",
    "wof:name": "Republic Engineered Products",
    "wof:placetype": "venue"
  },
  "geometry": {"coordinates":[-81.515979,40.793378],"type":"Point"}
}
