{
  "type": "Feature",
  "properties": {
    "addr:full": "2537 Three Locks Rd Chillicothe OH 45601",
    "addr:housenumber": "2537",
    "addr:postcode": "45601",
    "addr:street": "Three Locks Rd",
    "iso:country": "US",
    "sg:address": "2537 Three Locks Rd",
    "sg:city": "Chillicothe",
    "sg:phone": "+1 740 663 5205",
    "sg:postcode": "45601",
    "sg:province": "OH",
    "sg:tags": [
      "farm",
      "corn"
    ],
    "wof:name": "Ramey Ermal",
    "wof:placetype": "venue"
  },
  "geometry": {"coordinates":[-82.895265,39.233675],"type":"Point"}
}
