{
  "type": "Feature",
  "properties": {
    "iso:country":"US",
    "sg:address":"2537 Three Locks Rd",
    "sg:city":"Chillicothe",
    "sg:phone":"+1 740 663 5205",
    "sg:postcode":"45601",
    "sg:province":"OH",
    "sg:tags":[
        "farm",
        "corn"
    ],
    "wof:name":"Ramey Ermal",
    "wof:placetype":"venue"
},
  "geometry": {"coordinates":[-82.89526499999999,39.233675],"type":"Point"}
}