{
  "type": "Feature",
  "properties": {
    "addr:full":"6234 Millikin Rd Liberty Twp OH 45011",
    "addr:housenumber":"6234",
    "addr:postcode":"45011",
    "addr:street":"Millikin Rd",
    "iso:country":"US",
    "sg:address":"6234 Millikin Rd",
    "sg:city":"Liberty Twp",
    "sg:classifiers":[
        {
            "category":"Communications",
            "subcategory":"Film & Video Production",
            "type":"Services"
        }
    ],
    "sg:phone":"+1 513 759 0047",
    "sg:postcode":"45011",
    "sg:province":"OH",
    "sg:tags":[
        "taping"
    ],
    "wof:name":"Pyramid Video Production Group",
    "wof:placetype":"venue"
},
  "geometry": {"coordinates":[-84.41543799999999,39.401855],"type":"Point"}
}