{
  "type": "Feature",
  "properties": {
    "addr:full": "10121 Princeton Glendale Rd Cincinnati OH 45246",
    "addr:housenumber": "10121",
    "addr:postcode": "45246",
    "addr:street": "Princeton Glendale Rd",
    "iso:country": "US",
    "sg:address": "10121 Princeton Glendale Rd",
    "sg:city": "Cincinnati",
    "sg:classifiers": [
      {
        "category": "Freight",
        "type": "Transportation"
      }
    ],
    "sg:phone": "+1 513 942 1575",
    "sg:postcode": "45246",
    "sg:province": "OH",
    "sg:tags": [
      "product",
      "warehousing"
    ],
    "wof:name": "Excel Logistics Tropicana",
    "wof:placetype": "venue"
  },
  "geometry": {"coordinates":[-84.465406,39.304567],"type":"Point"}
}
