{
  "type": "Feature",
  "properties": {
    "addr:full":"12909 Angelus Ave Cleveland OH 44105",
    "addr:housenumber":"12909",
    "addr:postcode":"44105",
    "addr:street":"Angelus Ave",
    "iso:country":"US",
    "sg:address":"12909 Angelus Ave",
    "sg:city":"Cleveland",
    "sg:classifiers":[
        {
            "category":"Building & Trades",
            "subcategory":"Construction",
            "type":"Services"
        }
    ],
    "sg:phone":"+1 216 991 0765",
    "sg:postcode":"44105",
    "sg:province":"OH",
    "sg:tags":[
        "house"
    ],
    "wof:name":"Idl Construction Inc",
    "wof:placetype":"venue"
},
  "geometry": {"coordinates":[-81.59236,41.453984],"type":"Point"}
}