{
  "type": "Feature",
  "properties": {
    "addr:full": "6500 Poe Ave Dayton OH 45414",
    "addr:housenumber": "6500",
    "addr:postcode": "45414",
    "addr:street": "Poe Ave",
    "iso:country": "US",
    "sg:address": "6500 Poe Ave",
    "sg:city": "Dayton",
    "sg:classifiers": [
      {
        "category": "Banks \u0026 Credit Unions",
        "subcategory": "Bank",
        "type": "Services"
      }
    ],
    "sg:phone": "+1 937 890 6068",
    "sg:postcode": "45414",
    "sg:province": "OH",
    "sg:tags": [
      "mortgage"
    ],
    "wof:name": "F N M B",
    "wof:placetype": "venue"
  },
  "geometry": {"coordinates":[-84.187874,39.853834],"type":"Point"}
}
