{
  "type": "Feature",
  "properties": {
    "iso:country":"US",
    "sg:address":"2121 Walcutt Rd",
    "sg:city":"Columbus",
    "sg:classifiers":[
        {
            "category":"Wholesale",
            "subcategory":"Machinery & Supplies",
            "type":"Manufacturing & Wholesale Goods"
        }
    ],
    "sg:phone":"+1 614 876 1141",
    "sg:postcode":"43026",
    "sg:province":"OH",
    "sg:tags":[
        "contractor"
    ],
    "sg:website":"www.nortrax.com",
    "wof:name":"Nortrax Columbus",
    "wof:placetype":"venue"
},
  "geometry": {"coordinates":[-83.13749,39.992356],"type":"Point"}
}