{
  "type": "Feature",
  "properties": {
    "iso:country":"US",
    "sg:address":"4010 Derr Rd",
    "sg:city":"Springfield",
    "sg:classifiers":[
        {
            "category":"Sports & Exercise",
            "subcategory":"Gym",
            "type":"Entertainment"
        }
    ],
    "sg:phone":"+1 937 342 9966",
    "sg:postcode":"45503",
    "sg:province":"OH",
    "sg:tags":[
        "club",
        "health",
        "studio",
        "gymnasium"
    ],
    "wof:name":"Curves For Women",
    "wof:placetype":"venue"
},
  "geometry": {"coordinates":[-83.78308699999999,39.984552],"type":"Point"}
}