{
  "type": "Feature",
  "properties": {
    "addr:full": "4010 Derr Rd Springfield OH 45503",
    "addr:housenumber": "4010",
    "addr:postcode": "45503",
    "addr:street": "Derr Rd",
    "iso:country": "US",
    "sg:address": "4010 Derr Rd",
    "sg:city": "Springfield",
    "sg:classifiers": [
      {
        "category": "Sports \u0026 Exercise",
        "subcategory": "Gym",
        "type": "Entertainment"
      }
    ],
    "sg:phone": "+1 937 342 9966",
    "sg:postcode": "45503",
    "sg:province": "OH",
    "sg:tags": [
      "club",
      "health",
      "studio",
      "gymnasium"
    ],
    "wof:name": "Curves For Women",
    "wof:placetype": "venue"
  },
  "geometry": {"coordinates":[-83.783087,39.984552],"type":"Point"}
}
