{
  "type": "Feature",
  "properties": {
    "iso:country":"US",
    "sg:address":"4314 Suder Ave",
    "sg:city":"Toledo",
    "sg:classifiers":[
        {
            "category":"Recreation",
            "type":"Entertainment"
        }
    ],
    "sg:phone":"+1 419 729 4360",
    "sg:postcode":"43611",
    "sg:province":"OH",
    "sg:tags":[
        "club",
        "membership"
    ],
    "wof:name":"H & H Custom Clubs LLC",
    "wof:placetype":"venue"
},
  "geometry": {"coordinates":[-83.497505,41.700223],"type":"Point"}
}