{
  "type": "Feature",
  "properties": {
    "addr:full": "10446 Frasure-Helber Rd Logan OH 43138",
    "addr:housenumber": "10446",
    "addr:postcode": "43138",
    "addr:street": "Frasure-Helber Rd",
    "iso:country": "US",
    "sg:address": "10446 Frasure-Helber Rd",
    "sg:city": "Logan",
    "sg:classifiers": [
      {
        "category": "Building \u0026 Trades",
        "subcategory": "Construction",
        "type": "Services"
      }
    ],
    "sg:phone": "+1 740 385 0116",
    "sg:postcode": "43138",
    "sg:province": "OH",
    "sg:tags": [
      "carpentry",
      "contractor"
    ],
    "wof:name": "Jason Richard Huffines",
    "wof:placetype": "venue"
  },
  "geometry": {"coordinates":[-82.443388,39.582301],"type":"Point"}
}
