{
  "type": "Feature",
  "properties": {
    "iso:country":"US",
    "sg:address":"150 W Center St",
    "sg:city":"Marion",
    "sg:classifiers":[
        {
            "category":"Education",
            "subcategory":"Special Training",
            "type":"Public Place"
        }
    ],
    "sg:phone":"+1 740 375 5267",
    "sg:postcode":"43302",
    "sg:province":"OH",
    "sg:tags":[
        "tutoring"
    ],
    "wof:name":"Lespwa",
    "wof:placetype":"venue"
},
  "geometry": {"coordinates":[-83.13016399999999,40.588673],"type":"Point"}
}