{
  "type": "Feature",
  "properties": {
    "iso:country":"US",
    "sg:address":"104 Washington St",
    "sg:city":"Jackson Center",
    "sg:classifiers":[
        {
            "category":"Manufacturing",
            "subcategory":"Tools & Machinery",
            "type":"Manufacturing & Wholesale Goods"
        }
    ],
    "sg:phone":"+1 937 596 6106",
    "sg:postcode":"45310",
    "sg:province":"OH",
    "sg:tags":[
        "lawn"
    ],
    "sg:website":"www.lacal.com",
    "wof:name":"Lacal Equipment",
    "wof:placetype":"venue"
},
  "geometry": {"coordinates":[-84.643011,40.355746],"type":"Point"}
}