{
  "type": "Feature",
  "properties": {
    "addr:full":"5200 Monroe St Toledo OH 43623",
    "addr:housenumber":"5200",
    "addr:postcode":"43623",
    "addr:street":"Monroe St",
    "iso:country":"US",
    "sg:address":"5200 Monroe St",
    "sg:city":"Toledo",
    "sg:classifiers":[
        {
            "category":"Recreation",
            "type":"Entertainment"
        }
    ],
    "sg:phone":"+1 419 843 7901",
    "sg:postcode":"43623",
    "sg:province":"OH",
    "sg:tags":[
        "martial",
        "arts",
        "instruction"
    ],
    "wof:name":"Japan Ryobu-Kai Karate School",
    "wof:placetype":"venue"
},
  "geometry": {"coordinates":[-83.651383,41.701064],"type":"Point"}
}