{
  "type": "Feature",
  "properties": {
    "addr:full": "2060 S Hamilton Rd Columbus OH 43232",
    "addr:housenumber": "2060",
    "addr:postcode": "43232",
    "addr:street": "S Hamilton Rd",
    "iso:country": "US",
    "sg:address": "2060 S Hamilton Rd",
    "sg:city": "Columbus",
    "sg:classifiers": [
      {
        "category": "Manufacturing",
        "subcategory": "Signs",
        "type": "Manufacturing \u0026 Wholesale Goods"
      },
      {
        "category": "Professional",
        "subcategory": "Art Services",
        "type": "Services"
      }
    ],
    "sg:phone": "+1 614 751 3141",
    "sg:postcode": "43232",
    "sg:province": "OH",
    "sg:tags": [
      "commercial",
      "printing",
      "design"
    ],
    "wof:name": "Rapid Graphics",
    "wof:placetype": "venue"
  },
  "geometry": {"coordinates":[-82.87911,39.93114],"type":"Point"}
}
