{
  "type": "Feature",
  "properties": {
    "iso:country":"US",
    "sg:address":"1294 Peru Center Rd N",
    "sg:city":"Monroeville",
    "sg:classifiers":[
        {
            "category":"Organizations",
            "subcategory":"Religious Organization",
            "type":"Services"
        }
    ],
    "sg:phone":"+1 419 933 7278",
    "sg:postcode":"44847",
    "sg:province":"OH",
    "sg:tags":[
        "church"
    ],
    "wof:name":"Congregational Church",
    "wof:placetype":"venue"
},
  "geometry": {"coordinates":[-82.683335,41.172537],"type":"Point"}
}