{
  "type": "Feature",
  "properties": {
    "iso:country":"US",
    "sg:address":"1651 Penworth Dr",
    "sg:city":"Columbus",
    "sg:classifiers":[
        {
            "category":"Building & Trades",
            "subcategory":"Construction",
            "type":"Services"
        }
    ],
    "sg:phone":"+1 614 848 9950",
    "sg:postcode":"43229",
    "sg:province":"OH",
    "sg:tags":[
        "resurfacing",
        "laying",
        "refinishing",
        "floor"
    ],
    "wof:name":"Current's Floor Svc",
    "wof:placetype":"venue"
},
  "geometry": {"coordinates":[-82.974039,40.072759],"type":"Point"}
}