{
  "type": "Feature",
  "properties": {
    "iso:country":"US",
    "sg:address":"30 W Union St",
    "sg:city":"Athens",
    "sg:classifiers":[
        {
            "category":"Restaurant",
            "type":"Food & Drink"
        }
    ],
    "sg:phone":"+1 740 594 7700",
    "sg:postcode":"45701",
    "sg:province":"OH",
    "sg:website":"www.happykobe.com",
    "wof:name":"Happy KOBE",
    "wof:placetype":"venue"
},
  "geometry": {"coordinates":[-82.101314,39.327518],"type":"Point"}
}