{
  "type": "Feature",
  "properties": {
    "iso:country":"US",
    "sg:address":"1405 N Cassady Ave",
    "sg:city":"Columbus",
    "sg:classifiers":[
        {
            "category":"Restaurant",
            "type":"Food & Drink"
        }
    ],
    "sg:menulink":"http://www.allmenus.com/oh/columbus/141799-waffle-house/menu/",
    "sg:phone":"+1 614 536 0409",
    "sg:postcode":"43219",
    "sg:province":"OH",
    "sg:tags":[
        "american"
    ],
    "wof:name":"Waffle House",
    "wof:placetype":"venue"
},
  "geometry": {"coordinates":[-82.930226,39.998379],"type":"Point"}
}