{
  "type": "Feature",
  "properties": {
    "iso:country":"US",
    "sg:address":"63 Castle Blvd",
    "sg:city":"Akron",
    "sg:classifiers":[
        {
            "category":"Shopping",
            "subcategory":"Hobbies, Toys, & Games",
            "type":"Retail Goods"
        }
    ],
    "sg:phone":"+1 330 867 7044",
    "sg:postcode":"44313",
    "sg:province":"OH",
    "wof:name":"Baskets & Traditions",
    "wof:placetype":"venue"
},
  "geometry": {"coordinates":[-81.56138900000001,41.106919],"type":"Point"}
}