{
  "type": "Feature",
  "properties": {
    "addr:full": "63 Castle Blvd Akron OH 44313",
    "addr:housenumber": "63",
    "addr:postcode": "44313",
    "addr:street": "Castle Blvd",
    "iso:country": "US",
    "sg:address": "63 Castle Blvd",
    "sg:city": "Akron",
    "sg:classifiers": [
      {
        "category": "Shopping",
        "subcategory": "Hobbies, Toys, \u0026 Games",
        "type": "Retail Goods"
      }
    ],
    "sg:phone": "+1 330 867 7044",
    "sg:postcode": "44313",
    "sg:province": "OH",
    "wof:name": "Baskets \u0026 Traditions",
    "wof:placetype": "venue"
  },
  "geometry": {"coordinates":[-81.561389,41.106919],"type":"Point"}
}
