{
  "type": "Feature",
  "properties": {
    "iso:country":"US",
    "sg:address":"1384 W 6th St",
    "sg:city":"Cleveland",
    "sg:classifiers":[
        {
            "category":"Restaurant",
            "type":"Food & Drink"
        }
    ],
    "sg:phone":"+1 216 861 3399",
    "sg:postcode":"44113",
    "sg:province":"OH",
    "sg:tags":[
        "eating"
    ],
    "wof:name":"China Sea Express Inc",
    "wof:placetype":"venue"
},
  "geometry": {"coordinates":[-81.698297,41.499356],"type":"Point"}
}