{
  "type": "Feature",
  "properties": {
    "iso:country":"US",
    "sg:address":"354 Congress Park Dr",
    "sg:city":"Dayton",
    "sg:classifiers":[
        {
            "category":"Manufacturing",
            "subcategory":"Furniture",
            "type":"Manufacturing & Wholesale Goods"
        }
    ],
    "sg:phone":"+1 937 434 2520",
    "sg:postcode":"45459",
    "sg:province":"OH",
    "sg:website":"www.augustinc.com",
    "wof:name":"August Inc",
    "wof:placetype":"venue"
},
  "geometry": {"coordinates":[-84.176474,39.629311],"type":"Point"}
}