{
  "type": "Feature",
  "properties": {
    "iso:country":"US",
    "sg:address":"402 W Park Ave",
    "sg:city":"Niles",
    "sg:classifiers":[
        {
            "category":"Building & Trades",
            "subcategory":"Plumbing",
            "type":"Services"
        }
    ],
    "sg:phone":"+1 330 652 7814",
    "sg:postcode":"44446",
    "sg:province":"OH",
    "sg:tags":[
        "air",
        "heating",
        "conditioning",
        "contractor"
    ],
    "wof:name":"Pirigyi Rfrgn & Heatting Co",
    "wof:placetype":"venue"
},
  "geometry": {"coordinates":[-80.772669,41.180593],"type":"Point"}
}