{
  "type": "Feature",
  "properties": {
    "iso:country":"US",
    "sg:address":"8355 Eagle Rd",
    "sg:city":"Willoughby",
    "sg:classifiers":[
        {
            "category":"Real Estate",
            "subcategory":"Real Estate Operator",
            "type":"Services"
        }
    ],
    "sg:phone":"+1 440 256 8838",
    "sg:postcode":"44094",
    "sg:province":"OH",
    "sg:tags":[
        "mobile",
        "home",
        "camp",
        "site",
        "community"
    ],
    "wof:name":"Eagle Mobile Homes Park Ltd",
    "wof:placetype":"venue"
},
  "geometry": {"coordinates":[-81.342476,41.604761],"type":"Point"}
}