{
  "type": "Feature",
  "properties": {
    "addr:full":"11291 Handle Rd Strongsville OH 44136",
    "addr:housenumber":"11291",
    "addr:postcode":"44136",
    "addr:street":"Handle Rd",
    "iso:country":"US",
    "sg:address":"11291 Handle Rd",
    "sg:city":"Strongsville",
    "sg:classifiers":[
        {
            "category":"Retail",
            "subcategory":"Animal Services",
            "type":"Services"
        }
    ],
    "sg:phone":"+1 440 238 0464",
    "sg:postcode":"44136",
    "sg:province":"OH",
    "wof:name":"Coventree Farm",
    "wof:placetype":"venue"
},
  "geometry": {"coordinates":[-81.81108999999999,41.329856],"type":"Point"}
}