{
  "type": "Feature",
  "properties": {
    "addr:full":"925 Ohio Pike Cincinnati OH 45245",
    "addr:housenumber":"925",
    "addr:postcode":"45245",
    "addr:street":"Ohio Pike",
    "iso:country":"US",
    "sg:address":"925 Ohio Pike",
    "sg:city":"Cincinnati",
    "sg:classifiers":[
        {
            "category":"Personal",
            "subcategory":"Tanning Parlor",
            "type":"Services"
        }
    ],
    "sg:phone":"+1 513 753 8833",
    "sg:postcode":"45245",
    "sg:province":"OH",
    "wof:name":"Golden Tanning Systems Inc",
    "wof:placetype":"venue"
},
  "geometry": {"coordinates":[-84.27130099999999,39.061298],"type":"Point"}
}