{
  "type": "Feature",
  "properties": {
    "addr:full": "318 W Cross St Summerfield OH 43788",
    "addr:housenumber": "318",
    "addr:postcode": "43788",
    "addr:street": "W Cross St",
    "iso:country": "US",
    "sg:address": "318 W Cross St",
    "sg:city": "Summerfield",
    "sg:classifiers": [
      {
        "category": "Government",
        "subcategory": "Office",
        "type": "Public Place"
      }
    ],
    "sg:phone": "+1 740 838 4047",
    "sg:postcode": "43788",
    "sg:province": "OH",
    "sg:tags": [
      "executive"
    ],
    "wof:name": "Village of Summerfield",
    "wof:placetype": "venue"
  },
  "geometry": {"coordinates":[-81.337993,39.79754],"type":"Point"}
}
