{
  "type": "Feature",
  "properties": {
    "addr:full":"1646 Center St Cleveland OH 44113",
    "addr:housenumber":"1646",
    "addr:postcode":"44113",
    "addr:street":"Center St",
    "iso:country":"US",
    "sg:address":"1646 Center St",
    "sg:city":"Cleveland",
    "sg:classifiers":[
        {
            "category":"Restaurant",
            "type":"Food & Drink"
        }
    ],
    "sg:phone":"+1 216 749 6556",
    "sg:postcode":"44113",
    "sg:province":"OH",
    "sg:tags":[
        "cafe"
    ],
    "wof:name":"Collision Bend Cafe",
    "wof:placetype":"venue"
},
  "geometry": {"coordinates":[-81.703723,41.494447],"type":"Point"}
}