{
  "type": "Feature",
  "properties": {
    "addr:full":"2669 Sawbury Blvd Columbus OH 43235",
    "addr:housenumber":"2669",
    "addr:postcode":"43235",
    "addr:street":"Sawbury Blvd",
    "iso:country":"US",
    "sg:address":"2669 Sawbury Blvd",
    "sg:city":"Columbus",
    "sg:classifiers":[
        {
            "category":"Professional",
            "type":"Services"
        }
    ],
    "sg:phone":"+1 614 792 9509",
    "sg:postcode":"43235",
    "sg:province":"OH",
    "sg:tags":[
        "establishment"
    ],
    "wof:name":"Merchants Guarantee",
    "wof:placetype":"venue"
},
  "geometry": {"coordinates":[-83.08947000000001,40.114086],"type":"Point"}
}