{
  "type": "Feature",
  "properties": {
    "addr:full": "14174 Ravenna Rd Newbury OH 44065",
    "addr:housenumber": "14174",
    "addr:postcode": "44065",
    "addr:street": "Ravenna Rd",
    "iso:country": "US",
    "sg:address": "14174 Ravenna Rd",
    "sg:city": "Newbury",
    "sg:phone": "+1 440 564 5729",
    "sg:postcode": "44065",
    "sg:province": "OH",
    "sg:tags": [
      "farm",
      "field",
      "crop"
    ],
    "wof:name": "Redlings Farm",
    "wof:placetype": "venue"
  },
  "geometry": {"coordinates":[-81.193687,41.490766],"type":"Point"}
}
