{
  "type": "Feature",
  "properties": {
    "addr:full":"5727 Medallion Dr E Westerville OH 43082",
    "addr:housenumber":"5727",
    "addr:postcode":"westerville oh 43082",
    "addr:street":"Medallion Dr E",
    "iso:country":"US",
    "sg:address":"5727 Medallion Dr E",
    "sg:city":"Westerville",
    "sg:classifiers":[
        {
            "category":"Restaurant",
            "type":"Food & Drink"
        }
    ],
    "sg:phone":"+1 614 899 6403",
    "sg:postcode":"43082",
    "sg:province":"OH",
    "sg:tags":[
        "eating"
    ],
    "wof:name":"Subway",
    "wof:placetype":"venue"
},
  "geometry": {"coordinates":[-82.886353,40.16525],"type":"Point"}
}