{
  "type": "Feature",
  "properties": {
    "addr:full":"1680 US Hwy 20 W Norwalk OH 44857",
    "addr:housenumber":"1680",
    "addr:postcode":"44857",
    "addr:street":"Us Hwy 20 W",
    "iso:country":"US",
    "sg:address":"1680 US Hwy 20 W",
    "sg:city":"Norwalk",
    "sg:classifiers":[
        {
            "category":"Home & Garden",
            "subcategory":"Furniture",
            "type":"Retail Goods"
        }
    ],
    "sg:phone":"+1 419 668 6117",
    "sg:postcode":"44857",
    "sg:province":"OH",
    "sg:tags":[
        "household"
    ],
    "wof:name":"Fisher Wayside Furniture Inc",
    "wof:placetype":"venue"
},
  "geometry": {"coordinates":[-82.651156,41.228941],"type":"Point"}
}