{
  "type": "Feature",
  "properties": {
    "addr:full": "3207 N Dixie Dr Dayton OH 45414",
    "addr:housenumber": "3207",
    "addr:postcode": "45414",
    "addr:street": "N Dixie Dr",
    "iso:country": "US",
    "sg:address": "3207 N Dixie Dr",
    "sg:city": "Dayton",
    "sg:classifiers": [
      {
        "category": "Professional",
        "subcategory": "Accounting \u0026 Tax Preparation",
        "type": "Services"
      }
    ],
    "sg:phone": "+1 937 387 0423",
    "sg:postcode": "45414",
    "sg:province": "OH",
    "sg:tags": [
      "return",
      "filing"
    ],
    "sg:website": "www.jacksonhewitt.com",
    "wof:name": "Jackson Hewitt Tax Svc",
    "wof:placetype": "venue"
  },
  "geometry": {"coordinates":[-84.191863,39.795139],"type":"Point"}
}
