{
  "type": "Feature",
  "properties": {
    "addr:full": "509 Fairview Ave Versailles OH 45380",
    "addr:housenumber": "509",
    "addr:postcode": "45380",
    "addr:street": "Fairview Ave",
    "iso:country": "US",
    "sg:address": "509 Fairview Ave",
    "sg:city": "Versailles",
    "sg:classifiers": [
      {
        "category": "Freight",
        "type": "Transportation"
      }
    ],
    "sg:phone": "+1 937 526 4071",
    "sg:postcode": "45380",
    "sg:province": "OH",
    "sg:tags": [
      "local",
      "trucking"
    ],
    "wof:name": "Meyer Trucking",
    "wof:placetype": "venue"
  },
  "geometry": {"coordinates":[-84.47716,40.219642],"type":"Point"}
}
