{
  "type": "Feature",
  "properties": {
    "iso:country":"US",
    "sg:address":"1000 Park Ave",
    "sg:city":"Piqua",
    "sg:classifiers":[
        {
            "category":"Retail",
            "subcategory":"Laundry & Dry Cleaning",
            "type":"Services"
        }
    ],
    "sg:phone":"+1 937 615 0179",
    "sg:postcode":"45356",
    "sg:province":"OH",
    "wof:name":"Fresh & Clean Laundry",
    "wof:placetype":"venue"
},
  "geometry": {"coordinates":[-84.253627,40.153652],"type":"Point"}
}