{
  "type": "Feature",
  "properties": {
    "addr:full": "1000 Park Ave Piqua OH 45356",
    "addr:housenumber": "1000",
    "addr:postcode": "45356",
    "addr:street": "Park Ave",
    "iso:country": "US",
    "sg:address": "1000 Park Ave",
    "sg:city": "Piqua",
    "sg:classifiers": [
      {
        "category": "Retail",
        "subcategory": "Laundry \u0026 Dry Cleaning",
        "type": "Services"
      }
    ],
    "sg:phone": "+1 937 615 0179",
    "sg:postcode": "45356",
    "sg:province": "OH",
    "wof:name": "Fresh \u0026 Clean Laundry",
    "wof:placetype": "venue"
  },
  "geometry": {"coordinates":[-84.253627,40.153652],"type":"Point"}
}
