{
  "type": "Feature",
  "properties": {
    "iso:country":"US",
    "sg:address":"11500 Rockfield Ct",
    "sg:city":"Cincinnati",
    "sg:classifiers":[
        {
            "category":"Professional",
            "subcategory":"Engineering",
            "type":"Services"
        }
    ],
    "sg:phone":"+1 513 772 1515",
    "sg:postcode":"45241",
    "sg:province":"OH",
    "wof:name":"Pakteem Technical Services",
    "wof:placetype":"venue"
},
  "geometry": {"coordinates":[-84.41726,39.281392],"type":"Point"}
}