{
  "type": "Feature",
  "properties": {
    "iso:country":"US",
    "sg:address":"210 N Gamble St",
    "sg:city":"Shelby",
    "sg:classifiers":[
        {
            "category":"Sports & Exercise",
            "subcategory":"Gym",
            "type":"Entertainment"
        }
    ],
    "sg:phone":"+1 419 342 2773",
    "sg:postcode":"44875",
    "sg:province":"OH",
    "sg:tags":[
        "club",
        "health",
        "studio",
        "gymnasium"
    ],
    "wof:name":"Curves",
    "wof:placetype":"venue"
},
  "geometry": {"coordinates":[-82.66249500000001,40.889658],"type":"Point"}
}