{
  "type": "Feature",
  "properties": {
    "addr:full":"2510 Elm Ave Cleveland OH 44113",
    "addr:housenumber":"2510",
    "addr:postcode":"44113",
    "addr:street":"Elm Ave",
    "iso:country":"US",
    "sg:address":"2510 Elm Ave",
    "sg:city":"Cleveland",
    "sg:classifiers":[
        {
            "category":"Bars & Pubs",
            "type":"Food & Drink"
        }
    ],
    "sg:phone":"+1 216 348 1135",
    "sg:postcode":"44113",
    "sg:province":"OH",
    "sg:tags":[
        "club",
        "night"
    ],
    "wof:name":"Mirage On The Water",
    "wof:placetype":"venue"
},
  "geometry": {"coordinates":[-81.71041200000001,41.497013],"type":"Point"}
}