{
  "type": "Feature",
  "properties": {
    "addr:full":"2800 State Rd Cuyahoga Falls OH 44223",
    "addr:housenumber":"2800",
    "addr:postcode":"44223",
    "addr:street":"State Rd",
    "iso:country":"US",
    "sg:address":"2800 State Rd",
    "sg:city":"Cuyahoga Falls",
    "sg:classifiers":[
        {
            "category":"Banks & Credit Unions",
            "subcategory":"Bank",
            "type":"Services"
        }
    ],
    "sg:phone":"+1 330 926 0517",
    "sg:postcode":"44223",
    "sg:province":"OH",
    "sg:tags":[
        "broker",
        "mortgage"
    ],
    "wof:name":"Rick Angheld Home Mortgage",
    "wof:placetype":"venue"
},
  "geometry": {"coordinates":[-81.508601,41.150664],"type":"Point"}
}