{
  "type": "Feature",
  "properties": {
    "iso:country":"US",
    "sg:address":"630 Brandt Pike",
    "sg:city":"Dayton",
    "sg:classifiers":[
        {
            "category":"Wholesale",
            "subcategory":"Metals & Minerals",
            "type":"Manufacturing & Wholesale Goods"
        }
    ],
    "sg:phone":"+1 937 222 5400",
    "sg:postcode":"45404",
    "sg:province":"OH",
    "sg:tags":[
        "parts",
        "representative",
        "stamping"
    ],
    "wof:name":"O E M Sales",
    "wof:placetype":"venue"
},
  "geometry": {"coordinates":[-84.15994,39.785948],"type":"Point"}
}