{
  "type": "Feature",
  "properties": {
    "addr:full": "630 Brandt Pike Dayton OH 45404",
    "addr:housenumber": "630",
    "addr:postcode": "45404",
    "addr:street": "Brandt Pike",
    "iso:country": "US",
    "sg:address": "630 Brandt Pike",
    "sg:city": "Dayton",
    "sg:classifiers": [
      {
        "category": "Wholesale",
        "subcategory": "Metals \u0026 Minerals",
        "type": "Manufacturing \u0026 Wholesale Goods"
      }
    ],
    "sg:phone": "+1 937 222 5400",
    "sg:postcode": "45404",
    "sg:province": "OH",
    "sg:tags": [
      "parts",
      "representative",
      "stamping"
    ],
    "wof:name": "O E M Sales",
    "wof:placetype": "venue"
  },
  "geometry": {"coordinates":[-84.15994,39.785948],"type":"Point"}
}
