{
  "type": "Feature",
  "properties": {
    "addr:full": "1278 State Rte 43 Richmond OH 43944",
    "addr:housenumber": "1278",
    "addr:postcode": "43944",
    "addr:street": "State Rte 43",
    "iso:country": "US",
    "sg:address": "1278 State Rte 43",
    "sg:city": "Richmond",
    "sg:classifiers": [
      {
        "category": "Bars \u0026 Pubs",
        "type": "Food \u0026 Drink"
      }
    ],
    "sg:phone": "+1 740 765 4438",
    "sg:postcode": "43944",
    "sg:province": "OH",
    "wof:name": "Lake Lodge Nite Club",
    "wof:placetype": "venue"
  },
  "geometry": {"coordinates":[-80.734791,40.40796],"type":"Point"}
}
