{
  "type": "Feature",
  "properties": {
    "addr:full": "7383 Southpointe Dr Cincinnati OH 45233",
    "addr:postcode": "7383;45233",
    "addr:street": "Southpointe Dr",
    "iso:country": "US",
    "sg:address": "7383 Southpointe Dr",
    "sg:city": "Cincinnati",
    "sg:classifiers": [
      {
        "category": "Restaurant",
        "type": "Food \u0026 Drink"
      }
    ],
    "sg:phone": "+1 513 533 3131",
    "sg:postcode": "45233",
    "sg:province": "OH",
    "wof:name": "Michael G's",
    "wof:placetype": "venue"
  },
  "geometry": {"coordinates":[-84.692384,39.128453],"type":"Point"}
}
