{
  "type": "Feature",
  "properties": {
    "iso:country":"US",
    "sg:address":"964 Grove Rd",
    "sg:city":"Zanesville",
    "sg:classifiers":[
        {
            "category":"Insurance",
            "subcategory":"Insurance Agent",
            "type":"Services"
        }
    ],
    "sg:phone":"+1 740 452 4596",
    "sg:postcode":"43701",
    "sg:province":"OH",
    "wof:name":"Northwestern Mutual Insurance",
    "wof:placetype":"venue"
},
  "geometry": {"coordinates":[-82.01982700000001,39.984144],"type":"Point"}
}