{
  "type": "Feature",
  "properties": {
    "addr:full":"3660 Fishinger Blvd Hilliard OH 43026",
    "addr:housenumber":"3660",
    "addr:postcode":"43026",
    "addr:street":"Fishinger Blvd",
    "iso:country":"US",
    "sg:address":"3660 Fishinger Blvd",
    "sg:city":"Hilliard",
    "sg:classifiers":[
        {
            "category":"Manufacturing",
            "subcategory":"Signs",
            "type":"Manufacturing & Wholesale Goods"
        }
    ],
    "sg:phone":"+1 614 921 9423",
    "sg:postcode":"43026",
    "sg:province":"OH",
    "sg:tags":[
        "specialty",
        "mfg"
    ],
    "sg:website":"www.signarama.com",
    "wof:name":"Sign-A-Rama",
    "wof:placetype":"venue"
},
  "geometry": {"coordinates":[-83.116905,40.028306],"type":"Point"}
}