{
  "type": "Feature",
  "properties": {
    "addr:full": "126 E Park St Fort Loramie OH 45845",
    "addr:housenumber": "126",
    "addr:postcode": "45845",
    "addr:street": "E Park St",
    "iso:country": "US",
    "sg:address": "126 E Park St",
    "sg:city": "Fort Loramie",
    "sg:classifiers": [
      {
        "category": "Shopping",
        "type": "Retail Goods"
      }
    ],
    "sg:phone": "+1 937 295 2676",
    "sg:postcode": "45845",
    "sg:province": "OH",
    "sg:tags": [
      "trophy",
      "medal",
      "award"
    ],
    "wof:name": "K \u0026 K Trophy Sales",
    "wof:placetype": "venue"
  },
  "geometry": {"coordinates":[-84.372778,40.349701],"type":"Point"}
}
