{
  "type": "Feature",
  "properties": {
    "iso:country":"US",
    "sg:address":"1550 Pumphouse Rd",
    "sg:city":"Springfield",
    "sg:classifiers":[
        {
            "category":"Recreation",
            "type":"Entertainment"
        }
    ],
    "sg:phone":"+1 937 324 1891",
    "sg:postcode":"45503",
    "sg:province":"OH",
    "sg:tags":[
        "fishing",
        "lake"
    ],
    "wof:name":"Beaver Lake",
    "wof:placetype":"venue"
},
  "geometry": {"coordinates":[-83.75787099999999,39.942251],"type":"Point"}
}