{
  "type": "Feature",
  "properties": {
    "iso:country":"US",
    "sg:address":"161 S Walnut St",
    "sg:city":"St Henry",
    "sg:classifiers":[
        {
            "category":"Health Services",
            "subcategory":"Doctor",
            "type":"Services"
        }
    ],
    "sg:phone":"+1 419 678 2371",
    "sg:postcode":"45883",
    "sg:province":"OH",
    "sg:tags":[
        "physician",
        "surgeon"
    ],
    "wof:name":"Mercer Osteopathic LTD",
    "wof:placetype":"venue"
},
  "geometry": {"coordinates":[-84.636796,40.416594],"type":"Point"}
}