{
  "type": "Feature",
  "properties": {
    "addr:full": "161 S Walnut St St Henry OH 45883",
    "addr:housenumber": "161",
    "addr:postcode": "45883",
    "addr:street": "S Walnut St St",
    "iso:country": "US",
    "sg:address": "161 S Walnut St",
    "sg:city": "St Henry",
    "sg:classifiers": [
      {
        "category": "Health Services",
        "subcategory": "Doctor",
        "type": "Services"
      }
    ],
    "sg:phone": "+1 419 678 2371",
    "sg:postcode": "45883",
    "sg:province": "OH",
    "sg:tags": [
      "physician",
      "surgeon"
    ],
    "wof:name": "Mercer Osteopathic LTD",
    "wof:placetype": "venue"
  },
  "geometry": {"coordinates":[-84.636796,40.416594],"type":"Point"}
}
