{
  "type": "Feature",
  "properties": {
    "addr:full": "583 W Fairground St Marion OH 43302",
    "addr:housenumber": "583",
    "addr:postcode": "43302",
    "addr:street": "W Fairground St",
    "iso:country": "US",
    "sg:address": "583 W Fairground St",
    "sg:city": "Marion",
    "sg:classifiers": [
      {
        "category": "Building \u0026 Trades",
        "subcategory": "Construction",
        "type": "Services"
      }
    ],
    "sg:phone": "+1 740 382 8934",
    "sg:postcode": "43302",
    "sg:province": "OH",
    "sg:tags": [
      "downspouts",
      "gutter"
    ],
    "wof:name": "Buckeye Seamless Gutters",
    "wof:placetype": "venue"
  },
  "geometry": {"coordinates":[-83.1414,40.600267],"type":"Point"}
}
