{
  "type": "Feature",
  "properties": {
    "addr:full": "20311 Pemberville Rd Pemberville OH 43450",
    "addr:housenumber": "20311",
    "addr:postcode": "43450",
    "addr:street": "Pemberville Rd",
    "iso:country": "US",
    "sg:address": "20311 Pemberville Rd",
    "sg:city": "Pemberville",
    "sg:classifiers": [
      {
        "category": "Health Services",
        "subcategory": "Podiatrist",
        "type": "Services"
      }
    ],
    "sg:phone": "+1 419 833 3668",
    "sg:postcode": "43450",
    "sg:province": "OH",
    "wof:name": "A Complete Foot Care Ctr",
    "wof:placetype": "venue"
  },
  "geometry": {"coordinates":[-83.453848,41.44573],"type":"Point"}
}
