{
  "type": "Feature",
  "properties": {
    "iso:country":"US",
    "sg:address":"1852 N Bridge St",
    "sg:city":"Chillicothe",
    "sg:classifiers":[
        {
            "category":"Autos & Motor Vehicles",
            "subcategory":"Auto Supplies",
            "type":"Retail Goods"
        }
    ],
    "sg:phone":"+1 740 774 1114",
    "sg:postcode":"45601",
    "sg:province":"OH",
    "wof:name":"Tire Discounters",
    "wof:placetype":"venue"
},
  "geometry": {"coordinates":[-82.975518,39.374666],"type":"Point"}
}