{
  "type": "Feature",
  "properties": {
    "iso:country":"US",
    "sg:address":"3640 W Dublin Granville Rd",
    "sg:city":"Columbus",
    "sg:classifiers":[
        {
            "category":"Shopping",
            "subcategory":"Shoes",
            "type":"Retail Goods"
        }
    ],
    "sg:phone":"+1 614 718 9088",
    "sg:postcode":"43235",
    "sg:province":"OH",
    "sg:website":"www.famousfootwear.com",
    "wof:name":"Famous Footwear",
    "wof:placetype":"venue"
},
  "geometry": {"coordinates":[-83.08590100000001,40.093914],"type":"Point"}
}