{
  "type": "Feature",
  "properties": {
    "addr:full":"969 High St Harrisburg OH 43126",
    "addr:housenumber":"969",
    "addr:postcode":"43126",
    "addr:street":"High St",
    "iso:country":"US",
    "sg:address":"969 High St",
    "sg:city":"Harrisburg",
    "sg:classifiers":[
        {
            "category":"Retail",
            "subcategory":"Auto Repair",
            "type":"Services"
        }
    ],
    "sg:phone":"+1 614 877 3288",
    "sg:postcode":"43126",
    "sg:province":"OH",
    "sg:tags":[
        "truck"
    ],
    "wof:name":"Southwest Truck",
    "wof:placetype":"venue"
},
  "geometry": {"coordinates":[-83.17187199999999,39.809219],"type":"Point"}
}