{
  "type": "Feature",
  "properties": {
    "addr:full": "3697 Highmont St Dayton OH 45432",
    "addr:postcode": "3697;45432",
    "addr:street": "Highmont St",
    "iso:country": "US",
    "sg:address": "3697 Highmont St",
    "sg:city": "Dayton",
    "sg:classifiers": [
      {
        "category": "Building \u0026 Trades",
        "subcategory": "Construction",
        "type": "Services"
      }
    ],
    "sg:phone": "+1 937 427 2245",
    "sg:postcode": "45432",
    "sg:province": "OH",
    "sg:tags": [
      "house"
    ],
    "wof:name": "VIP Windows",
    "wof:placetype": "venue"
  },
  "geometry": {"coordinates":[-84.071993,39.739417],"type":"Point"}
}
