{
  "type": "Feature",
  "properties": {
    "addr:full":"2200 Valley Pike Dayton OH 45404",
    "addr:housenumber":"2200",
    "addr:postcode":"45404",
    "addr:street":"Valley Pike",
    "iso:country":"US",
    "sg:address":"2200 Valley Pike",
    "sg:city":"Dayton",
    "sg:classifiers":[
        {
            "category":"Autos & Motor Vehicles",
            "subcategory":"Auto Supplies",
            "type":"Retail Goods"
        },
        {
            "category":"Wholesale",
            "subcategory":"Auto Parts",
            "type":"Manufacturing & Wholesale Goods"
        }
    ],
    "sg:phone":"+1 937 233 5481",
    "sg:postcode":"45404",
    "sg:province":"OH",
    "sg:tags":[
        "automotive",
        "truck",
        "automobile"
    ],
    "wof:name":"John's Auto Parts",
    "wof:placetype":"venue"
},
  "geometry": {"coordinates":[-84.144862,39.78868],"type":"Point"}
}