{
  "type": "Feature",
  "properties": {
    "addr:full": "333 Linden Ave Dayton OH 45403",
    "addr:housenumber": "333",
    "addr:postcode": "45403",
    "addr:street": "Linden Ave",
    "iso:country": "US",
    "sg:address": "333 Linden Ave",
    "sg:city": "Dayton",
    "sg:classifiers": [
      {
        "category": "Manufacturing",
        "subcategory": "Soap",
        "type": "Manufacturing \u0026 Wholesale Goods"
      }
    ],
    "sg:phone": "+1 937 253 1151",
    "sg:postcode": "45403",
    "sg:province": "OH",
    "sg:tags": [
      "bar",
      "mfg"
    ],
    "wof:name": "Hewitt Soap Works Inc",
    "wof:placetype": "venue"
  },
  "geometry": {"coordinates":[-84.158502,39.758348],"type":"Point"}
}
