{
  "type": "Feature",
  "properties": {
    "iso:country":"US",
    "sg:address":"6944 W 130th St",
    "sg:city":"Cleveland",
    "sg:classifiers":[
        {
            "category":"Utilities",
            "subcategory":"Mobile Phone",
            "type":"Services"
        }
    ],
    "sg:phone":"+1 440 887 0179",
    "sg:postcode":"44130",
    "sg:province":"OH",
    "sg:tags":[
        "telephone",
        "cellular"
    ],
    "wof:name":"Wireless Retail Inc",
    "wof:placetype":"venue"
},
  "geometry": {"coordinates":[-81.78483,41.379155],"type":"Point"}
}