{
  "type": "Feature",
  "properties": {
    "iso:country":"US",
    "sg:address":"1768 N Leutz Rd",
    "sg:city":"Oak Harbor",
    "sg:classifiers":[
        {
            "category":"Home & Garden",
            "subcategory":"Garden Supply",
            "type":"Retail Goods"
        }
    ],
    "sg:phone":"+1 419 898 5125",
    "sg:postcode":"43449",
    "sg:province":"OH",
    "wof:name":"Aldo Nursery",
    "wof:placetype":"venue"
},
  "geometry": {"coordinates":[-83.106395,41.543629],"type":"Point"}
}