{
  "type": "Feature",
  "properties": {
    "addr:full":"494 Graham Rd Cuyahoga Falls OH 44221",
    "addr:housenumber":"494",
    "addr:postcode":"44221",
    "addr:street":"Graham Rd",
    "iso:country":"US",
    "sg:address":"494 Graham Rd",
    "sg:city":"Cuyahoga Falls",
    "sg:classifiers":[
        {
            "category":"Personal",
            "subcategory":"Beauty Salon",
            "type":"Services"
        }
    ],
    "sg:phone":"+1 330 929 4242",
    "sg:postcode":"44221",
    "sg:province":"OH",
    "wof:name":"Razor's Edge Hair Studio",
    "wof:placetype":"venue"
},
  "geometry": {"coordinates":[-81.493362,41.157914],"type":"Point"}
}