{
  "type": "Feature",
  "properties": {
    "addr:full":"2300 Water Wheel Ct Holland OH 43528",
    "addr:housenumber":"2300",
    "addr:postcode":"43528",
    "addr:street":"Water Wheel Ct",
    "iso:country":"US",
    "sg:address":"2300 Water Wheel Ct",
    "sg:city":"Holland",
    "sg:classifiers":[
        {
            "category":"Freight",
            "type":"Transportation"
        }
    ],
    "sg:phone":"+1 419 266 2388",
    "sg:postcode":"43528",
    "sg:province":"OH",
    "sg:tags":[
        "arrangement"
    ],
    "wof:name":"Pettee/Associates",
    "wof:placetype":"venue"
},
  "geometry": {"coordinates":[-83.716184,41.5991],"type":"Point"}
}