{
  "type": "Feature",
  "properties": {
    "addr:full": "892 Park Ave E Mansfield OH 44905",
    "addr:housenumber": "892",
    "addr:postcode": "44905",
    "addr:street": "Park Ave E",
    "iso:country": "US",
    "sg:address": "892 Park Ave E",
    "sg:city": "Mansfield",
    "sg:classifiers": [
      {
        "category": "Retail",
        "subcategory": "Auto Repair",
        "type": "Services"
      }
    ],
    "sg:phone": "+1 419 589 8686",
    "sg:postcode": "44905",
    "sg:province": "OH",
    "sg:tags": [
      "shop",
      "automotive",
      "body",
      "paint"
    ],
    "wof:name": "Pro Auto Body Inc",
    "wof:placetype": "venue"
  },
  "geometry": {"coordinates":[-82.483702,40.758201],"type":"Point"}
}
