{
  "type": "Feature",
  "properties": {
    "iso:country":"US",
    "sg:address":"2642 Elm Rd NE",
    "sg:city":"Warren",
    "sg:classifiers":[
        {
            "category":"Food & Beverages",
            "subcategory":"Groceries & Convenience Stores",
            "type":"Retail Goods"
        }
    ],
    "sg:phone":"+1 330 372 3347",
    "sg:postcode":"44483",
    "sg:province":"OH",
    "wof:name":"Macali Elm Road Valu King",
    "wof:placetype":"venue"
},
  "geometry": {"coordinates":[-80.785178,41.258158],"type":"Point"}
}