{
  "type": "Feature",
  "properties": {
    "addr:full": "695 Lynnwood Dr Minerva OH 44657",
    "addr:housenumber": "695",
    "addr:postcode": "44657",
    "addr:street": "Lynnwood Dr",
    "iso:country": "US",
    "sg:address": "695 Lynnwood Dr",
    "sg:city": "Minerva",
    "sg:classifiers": [
      {
        "category": "Shopping",
        "subcategory": "Computers \u0026 Home Electronics",
        "type": "Retail Goods"
      }
    ],
    "sg:phone": "+1 330 868 4500",
    "sg:postcode": "44657",
    "sg:province": "OH",
    "sg:tags": [
      "equipment",
      "dealer"
    ],
    "wof:name": "TLC Technologies",
    "wof:placetype": "venue"
  },
  "geometry": {"coordinates":[-81.096609,40.731339],"type":"Point"}
}
