{
  "type": "Feature",
  "properties": {
    "iso:country":"US",
    "sg:address":"14920 Mc Callum Ave NE",
    "sg:city":"Alliance",
    "sg:classifiers":[
        {
            "category":"Wholesale",
            "subcategory":"Machinery & Supplies",
            "type":"Manufacturing & Wholesale Goods"
        }
    ],
    "sg:phone":"+1 330 947 3682",
    "sg:postcode":"44601",
    "sg:province":"OH",
    "sg:tags":[
        "equipment",
        "industrial"
    ],
    "wof:name":"Galaxy Enterprises",
    "wof:placetype":"venue"
},
  "geometry": {"coordinates":[-81.17205800000001,40.9864],"type":"Point"}
}