{
  "type": "Feature",
  "properties": {
    "addr:full": "14920 Mc Callum Ave NE Alliance OH 44601",
    "addr:housenumber": "14920",
    "addr:postcode": "44601",
    "addr:street": "Mc Callum Ave Ne",
    "iso:country": "US",
    "sg:address": "14920 Mc Callum Ave NE",
    "sg:city": "Alliance",
    "sg:classifiers": [
      {
        "category": "Wholesale",
        "subcategory": "Machinery \u0026 Supplies",
        "type": "Manufacturing \u0026 Wholesale Goods"
      }
    ],
    "sg:phone": "+1 330 947 3682",
    "sg:postcode": "44601",
    "sg:province": "OH",
    "sg:tags": [
      "equipment",
      "industrial"
    ],
    "wof:name": "Galaxy Enterprises",
    "wof:placetype": "venue"
  },
  "geometry": {"coordinates":[-81.172058,40.9864],"type":"Point"}
}
