{
  "type": "Feature",
  "properties": {
    "addr:full":"3341 Harrison Ave Cincinnati OH 45211",
    "addr:housenumber":"3341",
    "addr:postcode":"45211",
    "addr:street":"Harrison Ave",
    "iso:country":"US",
    "sg:address":"3341 Harrison Ave",
    "sg:city":"Cincinnati",
    "sg:classifiers":[
        {
            "category":"Insurance",
            "subcategory":"Insurance Agent",
            "type":"Services"
        }
    ],
    "sg:phone":"+1 513 662 4801",
    "sg:postcode":"45211",
    "sg:province":"OH",
    "wof:name":"Winters Financial Group",
    "wof:placetype":"venue"
},
  "geometry": {"coordinates":[-84.606381,39.155364],"type":"Point"}
}