{
  "type": "Feature",
  "properties": {
    "addr:full": "3327 Liberty Ave Vermilion OH 44089",
    "addr:housenumber": "3327",
    "addr:postcode": "44089",
    "addr:street": "Liberty Ave",
    "iso:country": "US",
    "sg:address": "3327 Liberty Ave",
    "sg:city": "Vermilion",
    "sg:classifiers": [
      {
        "category": "Wholesale",
        "subcategory": "Auto Parts",
        "type": "Manufacturing \u0026 Wholesale Goods"
      }
    ],
    "sg:phone": "+1 440 967 6174",
    "sg:postcode": "44089",
    "sg:province": "OH",
    "sg:tags": [
      "supply"
    ],
    "wof:name": "NAPA Auto Parts",
    "wof:placetype": "venue"
  },
  "geometry": {"coordinates":[-82.310575,41.424733],"type":"Point"}
}
