{
  "type": "Feature",
  "properties": {
    "addr:full": "129 Twp Rd 1248 Proctorville OH 45669",
    "addr:housenumber": "129",
    "addr:postcode": "45669",
    "addr:street": "Twp Rd 1248",
    "iso:country": "US",
    "sg:address": "129 Twp Rd 1248",
    "sg:city": "Proctorville",
    "sg:classifiers": [
      {
        "category": "Building \u0026 Trades",
        "subcategory": "Plumbing",
        "type": "Services"
      }
    ],
    "sg:phone": "+1 740 886 8509",
    "sg:postcode": "45669",
    "sg:province": "OH",
    "sg:tags": [
      "plumbing",
      "heating",
      "contractor"
    ],
    "wof:name": "United Plumbing Inc",
    "wof:placetype": "venue"
  },
  "geometry": {"coordinates":[-82.341877,38.45137],"type":"Point"}
}
