{
  "type": "Feature",
  "properties": {
    "addr:full": "3716 Columbus Ave Sandusky OH 44870",
    "addr:housenumber": "3716",
    "addr:postcode": "44870",
    "addr:street": "Columbus Ave",
    "iso:country": "US",
    "sg:address": "3716 Columbus Ave",
    "sg:city": "Sandusky",
    "sg:classifiers": [
      {
        "category": "Building \u0026 Trades",
        "subcategory": "Construction",
        "type": "Services"
      }
    ],
    "sg:phone": "+1 419 625 4962",
    "sg:postcode": "44870",
    "sg:province": "OH",
    "sg:tags": [
      "paving",
      "contractor"
    ],
    "wof:name": "Gerold Construction Co",
    "wof:placetype": "venue"
  },
  "geometry": {"coordinates":[-82.686778,41.414221],"type":"Point"}
}
