{
  "type": "Feature",
  "properties": {
    "iso:country":"US",
    "sg:address":"1831 E 40th St",
    "sg:city":"Cleveland",
    "sg:classifiers":[
        {
            "category":"Food & Beverages",
            "subcategory":"Specialty",
            "type":"Retail Goods"
        }
    ],
    "sg:phone":"+1 216 881 9283",
    "sg:postcode":"44103",
    "sg:province":"OH",
    "sg:tags":[
        "water",
        "bulk",
        "company"
    ],
    "wof:name":"Alpine Springs Water Co",
    "wof:placetype":"venue"
},
  "geometry": {"coordinates":[-81.65876900000001,41.508197],"type":"Point"}
}