{
  "type": "Feature",
  "properties": {
    "addr:full": "3670 Werk Rd Cincinnati OH 45248",
    "addr:postcode": "3670;45248",
    "addr:street": "Werk Rd",
    "iso:country": "US",
    "sg:address": "3670 Werk Rd",
    "sg:city": "Cincinnati",
    "sg:classifiers": [
      {
        "category": "Banks \u0026 Credit Unions",
        "subcategory": "Bank",
        "type": "Services"
      }
    ],
    "sg:phone": "+1 513 762 5070",
    "sg:postcode": "45248",
    "sg:province": "OH",
    "wof:name": "Kemba Credit Union",
    "wof:placetype": "venue"
  },
  "geometry": {"coordinates":[-84.624568,39.1418],"type":"Point"}
}
