{
  "type": "Feature",
  "properties": {
    "addr:full": "2420 Amethyst Ln Grove City OH 43123",
    "addr:housenumber": "2420",
    "addr:postcode": "43123",
    "addr:street": "Amethyst Ln",
    "iso:country": "US",
    "sg:address": "2420 Amethyst Ln",
    "sg:city": "Grove City",
    "sg:classifiers": [
      {
        "category": "Building \u0026 Trades",
        "subcategory": "Landscaping Services",
        "type": "Services"
      }
    ],
    "sg:phone": "+1 614 277 9093",
    "sg:postcode": "43123",
    "sg:province": "OH",
    "wof:name": "Buckeye Tree Service",
    "wof:placetype": "venue"
  },
  "geometry": {"coordinates":[-83.060799,39.913397],"type":"Point"}
}
