{
  "type": "Feature",
  "properties": {
    "iso:country":"US",
    "sg:address":"52218 Twp Rd 170",
    "sg:city":"Coshocton",
    "sg:classifiers":[
        {
            "category":"Building & Trades",
            "subcategory":"Construction",
            "type":"Services"
        }
    ],
    "sg:phone":"+1 740 622 9605",
    "sg:postcode":"43824",
    "sg:province":"OH",
    "sg:tags":[
        "home",
        "improvement"
    ],
    "wof:name":"Dekker Home Improvements",
    "wof:placetype":"venue"
},
  "geometry": {"coordinates":[-81.79322500000001,40.305534],"type":"Point"}
}