{
  "type": "Feature",
  "properties": {
    "iso:country":"US",
    "sg:address":"328 Southern Blvd NW",
    "sg:city":"Warren",
    "sg:classifiers":[
        {
            "category":"Restaurant",
            "type":"Food & Drink"
        }
    ],
    "sg:phone":"+1 330 898 2772",
    "sg:postcode":"44485",
    "sg:province":"OH",
    "wof:name":"Ianazone's Homemade Pizza",
    "wof:placetype":"venue"
},
  "geometry": {"coordinates":[-80.855138,41.237319],"type":"Point"}
}