{
  "type": "Feature",
  "properties": {
    "iso:country":"US",
    "sg:address":"794 Decatur St",
    "sg:city":"Vermilion",
    "sg:classifiers":[
        {
            "category":"Retail",
            "subcategory":"Animal Services",
            "type":"Services"
        }
    ],
    "sg:phone":"+1 440 967 5900",
    "sg:postcode":"44089",
    "sg:province":"OH",
    "wof:name":"Anns Wooly Woofers Grooming",
    "wof:placetype":"venue"
},
  "geometry": {"coordinates":[-82.369591,41.42001],"type":"Point"}
}