{
  "type": "Feature",
  "properties": {
    "addr:full":"275 E National Rd Vandalia OH 45377",
    "addr:housenumber":"275",
    "addr:postcode":"45377",
    "addr:street":"E National Rd",
    "iso:country":"US",
    "sg:address":"275 E National Rd",
    "sg:city":"Vandalia",
    "sg:classifiers":[
        {
            "category":"Restaurant",
            "type":"Food & Drink"
        }
    ],
    "sg:phone":"+1 937 898 4601",
    "sg:postcode":"45377",
    "sg:province":"OH",
    "sg:tags":[
        "drinking",
        "eating"
    ],
    "sg:website":"www.originalribhouse.com",
    "wof:name":"Original Rib House",
    "wof:placetype":"venue"
},
  "geometry": {"coordinates":[-84.19344599999999,39.891289],"type":"Point"}
}