{
  "type": "Feature",
  "properties": {
    "iso:country":"US",
    "sg:address":"2649 Marview Rd",
    "sg:city":"Columbus",
    "sg:classifiers":[
        {
            "category":"Professional",
            "type":"Services"
        },
        {
            "category":"Building & Trades",
            "subcategory":"Construction",
            "type":"Services"
        }
    ],
    "sg:phone":"+1 614 418 9040",
    "sg:postcode":"43219",
    "sg:province":"OH",
    "sg:tags":[
        "home",
        "builder"
    ],
    "wof:name":"Stidoms Home #1",
    "wof:placetype":"venue"
},
  "geometry": {"coordinates":[-82.926883,40.026175],"type":"Point"}
}