{
  "type": "Feature",
  "properties": {
    "addr:full": "2021 Coffey Rd Columbus OH 43210",
    "addr:housenumber": "2021",
    "addr:postcode": "43210",
    "addr:street": "Coffey Rd",
    "iso:country": "US",
    "sg:address": "2021 Coffey Rd",
    "sg:city": "Columbus",
    "sg:classifiers": [
      {
        "category": "Government",
        "subcategory": "Office",
        "type": "Public Place"
      }
    ],
    "sg:phone": "+1 614 469 5701",
    "sg:postcode": "43210",
    "sg:province": "OH",
    "sg:tags": [
      "federal"
    ],
    "wof:name": "US Interior Dept Field Rsrch",
    "wof:placetype": "venue"
  },
  "geometry": {"coordinates":[-83.025995,40.003797],"type":"Point"}
}
