{
  "type": "Feature",
  "properties": {
    "addr:full": "35226 State Rte 78 Lewisville OH 43754",
    "addr:housenumber": "35226",
    "addr:postcode": "43754",
    "addr:street": "State Rte 78",
    "iso:country": "US",
    "sg:address": "35226 State Rte 78",
    "sg:city": "Lewisville",
    "sg:classifiers": [
      {
        "category": "Travel",
        "subcategory": "Hotels \u0026 Motels",
        "type": "Entertainment"
      }
    ],
    "sg:phone": "+1 740 567 3465",
    "sg:postcode": "43754",
    "sg:province": "OH",
    "sg:tags": [
      "breakfast",
      "accommodation",
      "bed"
    ],
    "wof:name": "Country Hideaway B \u0026 B",
    "wof:placetype": "venue"
  },
  "geometry": {"coordinates":[-81.18386,39.766024],"type":"Point"}
}
