{
  "type": "Feature",
  "properties": {
    "iso:country":"US",
    "sg:address":"35226 State Rte 78",
    "sg:city":"Lewisville",
    "sg:classifiers":[
        {
            "category":"Travel",
            "subcategory":"Hotels & Motels",
            "type":"Entertainment"
        }
    ],
    "sg:phone":"+1 740 567 3465",
    "sg:postcode":"43754",
    "sg:province":"OH",
    "sg:tags":[
        "breakfast",
        "accommodation",
        "bed"
    ],
    "wof:name":"Country Hideaway B & B",
    "wof:placetype":"venue"
},
  "geometry": {"coordinates":[-81.18386,39.766024],"type":"Point"}
}