{
  "type": "Feature",
  "properties": {
    "addr:full":"525 Vine St Cincinnati OH 45202",
    "addr:housenumber":"525",
    "addr:postcode":"45202",
    "addr:street":"Vine St",
    "iso:country":"US",
    "sg:address":"525 Vine St",
    "sg:city":"Cincinnati",
    "sg:classifiers":[
        {
            "category":"Insurance",
            "subcategory":"Insurance Agent",
            "type":"Services"
        }
    ],
    "sg:phone":"+1 513 579 3370",
    "sg:postcode":"45202",
    "sg:province":"OH",
    "wof:name":"Aetna",
    "wof:placetype":"venue"
},
  "geometry": {"coordinates":[-84.51327000000001,39.102018],"type":"Point"}
}