{
  "type": "Feature",
  "properties": {
    "iso:country":"US",
    "sg:address":"2646 Froman Hill Rd",
    "sg:city":"Dover",
    "sg:classifiers":[
        {
            "category":"Farming",
            "subcategory":"Livestock Farm",
            "type":"Manufacturing & Wholesale Goods"
        }
    ],
    "sg:phone":"+1 330 343 8597",
    "sg:postcode":"44622",
    "sg:province":"OH",
    "sg:tags":[
        "animal",
        "general"
    ],
    "wof:name":"Gary Green",
    "wof:placetype":"venue"
},
  "geometry": {"coordinates":[-81.407449,40.57005],"type":"Point"}
}