{
  "type": "Feature",
  "properties": {
    "addr:full":"2931 Ralliston Ave Dayton OH 45418",
    "addr:housenumber":"2931",
    "addr:postcode":"45418",
    "addr:street":"Ralliston Ave",
    "iso:country":"US",
    "sg:address":"2931 Ralliston Ave",
    "sg:city":"Dayton",
    "sg:classifiers":[
        {
            "category":"Organizations",
            "subcategory":"Religious Organization",
            "type":"Services"
        }
    ],
    "sg:phone":"+1 937 262 9007",
    "sg:postcode":"45418",
    "sg:province":"OH",
    "sg:tags":[
        "church"
    ],
    "wof:name":"Pentecostal Church Of God",
    "wof:placetype":"venue"
},
  "geometry": {"coordinates":[-84.241715,39.731567],"type":"Point"}
}