{
  "type": "Feature",
  "properties": {
    "addr:full": "999 Sweitzer St Greenville OH 45331",
    "addr:housenumber": "999",
    "addr:postcode": "45331",
    "addr:street": "Sweitzer St",
    "iso:country": "US",
    "sg:address": "999 Sweitzer St",
    "sg:city": "Greenville",
    "sg:classifiers": [
      {
        "category": "Home \u0026 Garden",
        "subcategory": "Household Appliances",
        "type": "Retail Goods"
      }
    ],
    "sg:phone": "+1 937 548 5220",
    "sg:postcode": "45331",
    "sg:province": "OH",
    "wof:name": "Schmidt's Refrigeration",
    "wof:placetype": "venue"
  },
  "geometry": {"coordinates":[-84.634779,40.086338],"type":"Point"}
}
