{
  "type": "Feature",
  "properties": {
    "addr:full":"759 S State St Westerville OH 43081",
    "addr:housenumber":"759",
    "addr:postcode":"43081",
    "addr:street":"S State St",
    "iso:country":"US",
    "sg:address":"759 S State St",
    "sg:city":"Westerville",
    "sg:classifiers":[
        {
            "category":"Banks & Credit Unions",
            "subcategory":"Investment Brokerage",
            "type":"Services"
        }
    ],
    "sg:phone":"+1 614 890 8668",
    "sg:postcode":"43081",
    "sg:province":"OH",
    "sg:tags":[
        "consultant",
        "planning",
        "financial"
    ],
    "wof:name":"Special Needs Estate Planning",
    "wof:placetype":"venue"
},
  "geometry": {"coordinates":[-82.925645,40.109626],"type":"Point"}
}