{
  "type": "Feature",
  "properties": {
    "addr:full":"4283 Stoddard Ln Batavia OH 45103",
    "addr:housenumber":"4283",
    "addr:postcode":"45103",
    "addr:street":"Stoddard Ln",
    "iso:country":"US",
    "sg:address":"4283 Stoddard Ln",
    "sg:city":"Batavia",
    "sg:classifiers":[
        {
            "category":"Organizations",
            "subcategory":"Community Association",
            "type":"Services"
        }
    ],
    "sg:phone":"+1 513 732 0747",
    "sg:postcode":"45103",
    "sg:province":"OH",
    "sg:tags":[
        "military"
    ],
    "sg:website":"www.vfw.org",
    "wof:name":"Veterans Of Foreign Wars",
    "wof:placetype":"venue"
},
  "geometry": {"coordinates":[-84.232967,39.084999],"type":"Point"}
}