{
  "type": "Feature",
  "properties": {
    "iso:country":"US",
    "sg:address":"4125 Mayfield Rd",
    "sg:city":"Cleveland",
    "sg:classifiers":[
        {
            "category":"Retail",
            "subcategory":"Veterinary Services",
            "type":"Services"
        }
    ],
    "sg:phone":"+1 216 691 9100",
    "sg:postcode":"44121",
    "sg:province":"OH",
    "sg:tags":[
        "hospital",
        "animal"
    ],
    "wof:name":"Just Cats Hospital Inc",
    "wof:placetype":"venue"
},
  "geometry": {"coordinates":[-81.532079,41.520725],"type":"Point"}
}