{
  "type": "Feature",
  "properties": {
    "addr:full": "2704 Billingsley Rd Columbus OH 43235",
    "addr:housenumber": "2704",
    "addr:postcode": "43235",
    "addr:street": "Billingsley Rd",
    "iso:country": "US",
    "sg:address": "2704 Billingsley Rd",
    "sg:city": "Columbus",
    "sg:classifiers": [
      {
        "category": "Real Estate",
        "subcategory": "Real Estate Agent",
        "type": "Services"
      }
    ],
    "sg:phone": "+1 614 761 2111",
    "sg:postcode": "43235",
    "sg:province": "OH",
    "wof:name": "R E Invest Co",
    "wof:placetype": "venue"
  },
  "geometry": {"coordinates":[-83.086018,40.112536],"type":"Point"}
}
