{
  "type": "Feature",
  "properties": {
    "addr:full": "6665 Rosecliff Pl Dayton OH 45449",
    "addr:housenumber": "6665",
    "addr:postcode": "45449",
    "addr:street": "Rosecliff Pl",
    "iso:country": "US",
    "sg:address": "6665 Rosecliff Pl",
    "sg:city": "Dayton",
    "sg:classifiers": [
      {
        "category": "Shopping",
        "type": "Retail Goods"
      }
    ],
    "sg:phone": "+1 937 433 3352",
    "sg:postcode": "45449",
    "sg:province": "OH",
    "sg:tags": [
      "merchandise"
    ],
    "wof:name": "Cottage Garden",
    "wof:placetype": "venue"
  },
  "geometry": {"coordinates":[-84.215538,39.653015],"type":"Point"}
}
