{
  "type": "Feature",
  "properties": {
    "iso:country":"US",
    "sg:address":"11415 State Rte 28",
    "sg:city":"Leesburg",
    "sg:phone":"+1 937 981 7075",
    "sg:postcode":"45135",
    "sg:province":"OH",
    "sg:tags":[
        "farm",
        "corn"
    ],
    "wof:name":"Jeffrey Campbell",
    "wof:placetype":"venue"
},
  "geometry": {"coordinates":[-83.473861,39.356304],"type":"Point"}
}