{
  "type": "Feature",
  "properties": {
    "addr:full": "6980 Biddulph Rd Cleveland OH 44144",
    "addr:postcode": "6980;44144",
    "addr:street": "Biddulph Rd",
    "iso:country": "US",
    "sg:address": "6980 Biddulph Rd",
    "sg:city": "Cleveland",
    "sg:classifiers": [
      {
        "category": "Restaurant",
        "type": "Food \u0026 Drink"
      }
    ],
    "sg:phone": "+1 216 749 4460",
    "sg:postcode": "44144",
    "sg:province": "OH",
    "sg:tags": [
      "beverage"
    ],
    "wof:name": "Biddulph Beverage Store",
    "wof:placetype": "venue"
  },
  "geometry": {"coordinates":[-81.733512,41.430416],"type":"Point"}
}
