{
  "type": "Feature",
  "properties": {
    "iso:country":"US",
    "sg:address":"5100 Parkcenter Ave",
    "sg:city":"Dublin",
    "sg:classifiers":[
        {
            "category":"Professional",
            "subcategory":"Management & Consulting",
            "type":"Services"
        }
    ],
    "sg:phone":"+1 614 766 9990",
    "sg:postcode":"43017",
    "sg:province":"OH",
    "sg:tags":[
        "construction",
        "general",
        "contractor"
    ],
    "wof:name":"Contrak Corporation",
    "wof:placetype":"venue"
},
  "geometry": {"coordinates":[-83.12608400000001,40.079264],"type":"Point"}
}