{
  "type": "Feature",
  "properties": {
    "addr:full": "5100 Parkcenter Ave Dublin OH 43017",
    "addr:housenumber": "5100",
    "addr:postcode": "43017",
    "addr:street": "Parkcenter Ave",
    "iso:country": "US",
    "sg:address": "5100 Parkcenter Ave",
    "sg:city": "Dublin",
    "sg:classifiers": [
      {
        "category": "Professional",
        "subcategory": "Management \u0026 Consulting",
        "type": "Services"
      }
    ],
    "sg:phone": "+1 614 766 9990",
    "sg:postcode": "43017",
    "sg:province": "OH",
    "sg:tags": [
      "construction",
      "general",
      "contractor"
    ],
    "wof:name": "Contrak Corporation",
    "wof:placetype": "venue"
  },
  "geometry": {"coordinates":[-83.126084,40.079264],"type":"Point"}
}
