{
  "type": "Feature",
  "properties": {
    "iso:country":"US",
    "sg:address":"398 Mackinaw Ave",
    "sg:city":"Akron",
    "sg:classifiers":[
        {
            "category":"Building & Trades",
            "subcategory":"Construction",
            "type":"Services"
        }
    ],
    "sg:phone":"+1 330 836 2676",
    "sg:postcode":"44333",
    "sg:province":"OH",
    "sg:tags":[
        "contractor"
    ],
    "wof:name":"Picket Fence Properties LLC",
    "wof:placetype":"venue"
},
  "geometry": {"coordinates":[-81.60215100000001,41.134177],"type":"Point"}
}