{
  "type": "Feature",
  "properties": {
    "addr:full": "398 Mackinaw Ave Akron OH 44333",
    "addr:housenumber": "398",
    "addr:postcode": "44333",
    "addr:street": "Mackinaw Ave",
    "iso:country": "US",
    "sg:address": "398 Mackinaw Ave",
    "sg:city": "Akron",
    "sg:classifiers": [
      {
        "category": "Building \u0026 Trades",
        "subcategory": "Construction",
        "type": "Services"
      }
    ],
    "sg:phone": "+1 330 836 2676",
    "sg:postcode": "44333",
    "sg:province": "OH",
    "sg:tags": [
      "contractor"
    ],
    "wof:name": "Picket Fence Properties LLC",
    "wof:placetype": "venue"
  },
  "geometry": {"coordinates":[-81.602151,41.134177],"type":"Point"}
}
