{
  "type": "Feature",
  "properties": {
    "iso:country":"US",
    "sg:address":"2177 Scranton Rd",
    "sg:city":"Cleveland",
    "sg:classifiers":[
        {
            "category":"Retail",
            "subcategory":"Repair Shop",
            "type":"Services"
        }
    ],
    "sg:phone":"+1 216 574 2550",
    "sg:postcode":"44113",
    "sg:province":"OH",
    "sg:tags":[
        "bicycle"
    ],
    "wof:name":"Sickleweed",
    "wof:placetype":"venue"
},
  "geometry": {"coordinates":[-81.694666,41.483241],"type":"Point"}
}