{
  "type": "Feature",
  "properties": {
    "addr:full": "3991 Palace Way Akron OH 44321",
    "addr:housenumber": "3991",
    "addr:postcode": "44321",
    "addr:street": "Palace Way",
    "iso:country": "US",
    "sg:address": "3991 Palace Way",
    "sg:city": "Akron",
    "sg:classifiers": [
      {
        "category": "Building \u0026 Trades",
        "subcategory": "Construction",
        "type": "Services"
      }
    ],
    "sg:phone": "+1 330 668 2720",
    "sg:postcode": "44321",
    "sg:province": "OH",
    "sg:tags": [
      "house"
    ],
    "wof:name": "Ameri-Con Homes",
    "wof:placetype": "venue"
  },
  "geometry": {"coordinates":[-81.659821,41.118481],"type":"Point"}
}
