{
  "type": "Feature",
  "properties": {
    "iso:country":"US",
    "sg:address":"2087 Dublin Rd",
    "sg:city":"Columbus",
    "sg:classifiers":[
        {
            "category":"Freight",
            "type":"Transportation"
        }
    ],
    "sg:phone":"+1 614 488 9697",
    "sg:postcode":"43026",
    "sg:province":"OH",
    "sg:tags":[
        "special"
    ],
    "wof:name":"Dublin Road Mini Storage",
    "wof:placetype":"venue"
},
  "geometry": {"coordinates":[-83.093246,39.99945],"type":"Point"}
}