{
  "type": "Feature",
  "properties": {
    "addr:full": "310 W 7th St Lorain OH 44052",
    "addr:housenumber": "310",
    "addr:postcode": "44052",
    "addr:street": "W 7Th St",
    "iso:country": "US",
    "sg:address": "310 W 7th St",
    "sg:city": "Lorain",
    "sg:classifiers": [
      {
        "category": "Professional",
        "type": "Services"
      }
    ],
    "sg:phone": "+1 440 245 3334",
    "sg:postcode": "44052",
    "sg:province": "OH",
    "wof:name": "S Lowther",
    "wof:placetype": "venue"
  },
  "geometry": {"coordinates":[-82.177481,41.463605],"type":"Point"}
}
