{
  "type": "Feature",
  "properties": {
    "iso:country":"US",
    "sg:address":"1071 State Rte 141",
    "sg:city":"Gallipolis",
    "sg:classifiers":[
        {
            "category":"Building & Trades",
            "subcategory":"Construction",
            "type":"Services"
        }
    ],
    "sg:phone":"+1 740 441 1073",
    "sg:postcode":"45631",
    "sg:province":"OH",
    "sg:tags":[
        "concrete",
        "contractor"
    ],
    "wof:name":"Vertical Concrete Walls",
    "wof:placetype":"venue"
},
  "geometry": {"coordinates":[-82.228996,38.803127],"type":"Point"}
}