{
  "type": "Feature",
  "properties": {
    "addr:full":"2004 E OH-18 Tiffin OH 44883",
    "addr:housenumber":"2004;oh-18",
    "addr:postcode":"44883",
    "addr:street":"E",
    "iso:country":"US",
    "sg:address":"2004 E OH-18",
    "sg:city":"Tiffin",
    "sg:classifiers":[
        {
            "category":"Restaurant",
            "type":"Food & Drink"
        }
    ],
    "sg:menulink":"http://www.allmenus.com/oh/tiffin/200040-long-john-silvers/menu/",
    "sg:phone":"+1 419 448 9472",
    "sg:postcode":"44883",
    "sg:province":"OH",
    "sg:tags":[
        "seafood",
        "american"
    ],
    "wof:name":"Long John Silver's",
    "wof:placetype":"venue"
},
  "geometry": {"coordinates":[-83.209796,41.110696],"type":"Point"}
}