{
  "type": "Feature",
  "properties": {
    "iso:country":"US",
    "sg:address":"3900 Medina Rd",
    "sg:city":"Akron",
    "sg:classifiers":[
        {
            "category":"Ice Cream",
            "type":"Food & Drink"
        }
    ],
    "sg:menulink":"http://www.allmenus.com/oh/copley/184251-cold-stone-creamery/menu/",
    "sg:phone":"+1 330 665 4466",
    "sg:postcode":"44333",
    "sg:province":"OH",
    "sg:tags":[
        "smoothy",
        "juice",
        "american"
    ],
    "wof:name":"Cold Stone Creamery",
    "wof:placetype":"venue"
},
  "geometry": {"coordinates":[-81.638667,41.135671],"type":"Point"}
}