{
  "type": "Feature",
  "properties": {
    "iso:country":"US",
    "sg:address":"3645 Warrensville Center Rd",
    "sg:city":"Cleveland",
    "sg:classifiers":[
        {
            "category":"Insurance",
            "subcategory":"Insurance Agent",
            "type":"Services"
        }
    ],
    "sg:phone":"+1 216 752 6365",
    "sg:postcode":"44122",
    "sg:province":"OH",
    "sg:tags":[
        "auto"
    ],
    "wof:name":"A Better Auto Insurance Inc",
    "wof:placetype":"venue"
},
  "geometry": {"coordinates":[-81.535596,41.458352],"type":"Point"}
}