{
  "type": "Feature",
  "properties": {
    "addr:full": "15707 Madison Ave Cleveland OH 44107",
    "addr:housenumber": "15707",
    "addr:postcode": "44107",
    "addr:street": "Madison Ave",
    "iso:country": "US",
    "sg:address": "15707 Madison Ave",
    "sg:city": "Cleveland",
    "sg:classifiers": [
      {
        "category": "Shopping",
        "subcategory": "Used Merchandise",
        "type": "Retail Goods"
      }
    ],
    "sg:phone": "+1 216 226 0999",
    "sg:postcode": "44107",
    "sg:province": "OH",
    "sg:tags": [
      "antique"
    ],
    "wof:name": "O'Malley Antiques",
    "wof:placetype": "venue"
  },
  "geometry": {"coordinates":[-81.808586,41.477103],"type":"Point"}
}
