{
  "type": "Feature",
  "properties": {
    "iso:country":"US",
    "sg:address":"3262 S Main St",
    "sg:city":"Akron",
    "sg:classifiers":[
        {
            "category":"Building & Trades",
            "subcategory":"Construction",
            "type":"Services"
        }
    ],
    "sg:phone":"+1 330 644 1850",
    "sg:postcode":"44319",
    "sg:province":"OH",
    "sg:tags":[
        "carpentry",
        "contractor"
    ],
    "wof:name":"Acorn Woodshop",
    "wof:placetype":"venue"
},
  "geometry": {"coordinates":[-81.52365500000001,40.99888],"type":"Point"}
}