{
  "type": "Feature",
  "properties": {
    "addr:full": "3262 S Main St Akron OH 44319",
    "addr:housenumber": "3262",
    "addr:postcode": "44319",
    "addr:street": "S Main St",
    "iso:country": "US",
    "sg:address": "3262 S Main St",
    "sg:city": "Akron",
    "sg:classifiers": [
      {
        "category": "Building \u0026 Trades",
        "subcategory": "Construction",
        "type": "Services"
      }
    ],
    "sg:phone": "+1 330 644 1850",
    "sg:postcode": "44319",
    "sg:province": "OH",
    "sg:tags": [
      "carpentry",
      "contractor"
    ],
    "wof:name": "Acorn Woodshop",
    "wof:placetype": "venue"
  },
  "geometry": {"coordinates":[-81.523655,40.99888],"type":"Point"}
}
