{
  "type": "Feature",
  "properties": {
    "addr:full": "231 Lafayette Rd London OH 43140",
    "addr:housenumber": "231",
    "addr:postcode": "43140",
    "iso:country": "US",
    "sg:address": "231 Lafayette Rd",
    "sg:city": "London",
    "sg:classifiers": [
      {
        "category": "Building \u0026 Trades",
        "subcategory": "Equipment Rental",
        "type": "Services"
      }
    ],
    "sg:phone": "+1 740 852 3768",
    "sg:postcode": "43140",
    "sg:province": "OH",
    "sg:tags": [
      "yard"
    ],
    "wof:name": "Rent-A-Center",
    "wof:placetype": "venue"
  },
  "geometry": {"coordinates":[-83.441923,39.894055],"type":"Point"}
}
