{
  "type": "Feature",
  "properties": {
    "addr:full":"1300 E 9th St Cleveland OH 44114",
    "addr:housenumber":"1300",
    "addr:postcode":"44114",
    "addr:street":"E 9Th St",
    "iso:country":"US",
    "sg:address":"1300 E 9th St",
    "sg:city":"Cleveland",
    "sg:classifiers":[
        {
            "category":"Banks & Credit Unions",
            "subcategory":"Bank",
            "type":"Services"
        }
    ],
    "sg:phone":"+1 216 781 4437",
    "sg:postcode":"44114",
    "sg:province":"OH",
    "sg:tags":[
        "trust"
    ],
    "wof:name":"Bank One",
    "wof:placetype":"venue"
},
  "geometry": {"coordinates":[-81.691442,41.50555],"type":"Point"}
}