{
  "type": "Feature",
  "properties": {
    "addr:full":"1788 Middlehurst Rd Cleveland OH 44118",
    "addr:housenumber":"1788",
    "addr:postcode":"44118",
    "addr:street":"Middlehurst Rd",
    "iso:country":"US",
    "sg:address":"1788 Middlehurst Rd",
    "sg:city":"Cleveland",
    "sg:classifiers":[
        {
            "category":"Professional",
            "subcategory":"Advertising",
            "type":"Services"
        },
        {
            "category":"Professional",
            "subcategory":"Art Services",
            "type":"Services"
        }
    ],
    "sg:phone":"+1 216 397 4095",
    "sg:postcode":"44118",
    "sg:province":"OH",
    "sg:tags":[
        "graphic",
        "artist",
        "agency",
        "commercial",
        "specialty",
        "designer"
    ],
    "sg:website":"http://www.krizman.com",
    "wof:name":"Krizman Design Studio",
    "wof:placetype":"venue"
},
  "geometry": {"coordinates":[-81.574524,41.511426],"type":"Point"}
}