{
  "type": "Feature",
  "properties": {
    "addr:full": "2144 Baltimore St Defiance OH 43512",
    "addr:housenumber": "2144",
    "addr:postcode": "43512",
    "addr:street": "Baltimore St",
    "iso:country": "US",
    "sg:address": "2144 Baltimore St",
    "sg:city": "Defiance",
    "sg:classifiers": [
      {
        "category": "Autos \u0026 Motor Vehicles",
        "subcategory": "Auto Supplies",
        "type": "Retail Goods"
      }
    ],
    "sg:phone": "+1 419 782 8775",
    "sg:postcode": "43512",
    "sg:province": "OH",
    "sg:tags": [
      "tire"
    ],
    "wof:name": "Automotive Wholesale Warehouse",
    "wof:placetype": "venue"
  },
  "geometry": {"coordinates":[-84.40677,41.275622],"type":"Point"}
}
