{
  "type": "Feature",
  "properties": {
    "iso:country":"US",
    "sg:address":"2144 Baltimore St",
    "sg:city":"Defiance",
    "sg:classifiers":[
        {
            "category":"Autos & Motor Vehicles",
            "subcategory":"Auto Supplies",
            "type":"Retail Goods"
        }
    ],
    "sg:phone":"+1 419 782 8775",
    "sg:postcode":"43512",
    "sg:province":"OH",
    "sg:tags":[
        "tire"
    ],
    "wof:name":"Automotive Wholesale Warehouse",
    "wof:placetype":"venue"
},
  "geometry": {"coordinates":[-84.40676999999999,41.275622],"type":"Point"}
}