{
  "type": "Feature",
  "properties": {
    "addr:full": "4220 Sunset Blvd Steubenville OH 43952",
    "addr:housenumber": "4220",
    "addr:postcode": "43952",
    "addr:street": "Sunset Blvd",
    "iso:country": "US",
    "sg:address": "4220 Sunset Blvd",
    "sg:city": "Steubenville",
    "sg:classifiers": [
      {
        "category": "Professional",
        "subcategory": "Lawyer \u0026 Legal Services",
        "type": "Services"
      }
    ],
    "sg:phone": "+1 740 282 8522",
    "sg:postcode": "43952",
    "sg:province": "OH",
    "sg:tags": [
      "attorney"
    ],
    "wof:name": "Davis Law Ofice",
    "wof:placetype": "venue"
  },
  "geometry": {"coordinates":[-80.679788,40.373799],"type":"Point"}
}
