{
  "type": "Feature",
  "properties": {
    "addr:full": "1124 N High St Columbus OH 43201",
    "addr:housenumber": "1124",
    "addr:postcode": "43201",
    "addr:street": "N High St",
    "iso:country": "US",
    "sg:address": "1124 N High St",
    "sg:city": "Columbus",
    "sg:classifiers": [
      {
        "category": "Shopping",
        "subcategory": "Used Merchandise",
        "type": "Retail Goods"
      }
    ],
    "sg:phone": "+1 614 291 9696",
    "sg:postcode": "43201",
    "sg:province": "OH",
    "sg:tags": [
      "antique"
    ],
    "wof:name": "Rich's Antiques \u0026 Collectibles",
    "wof:placetype": "venue"
  },
  "geometry": {"coordinates":[-83.005185,39.985816],"type":"Point"}
}
