{
  "type": "Feature",
  "properties": {
    "addr:full": "113 W Jackson St Millersburg OH 44654",
    "addr:housenumber": "113",
    "addr:postcode": "44654",
    "addr:street": "W Jackson St",
    "iso:country": "US",
    "sg:address": "113 W Jackson St",
    "sg:city": "Millersburg",
    "sg:classifiers": [
      {
        "category": "Shopping",
        "type": "Retail Goods"
      }
    ],
    "sg:phone": "+1 330 674 6755",
    "sg:postcode": "44654",
    "sg:province": "OH",
    "sg:tags": [
      "picture",
      "frame"
    ],
    "sg:website": "www.graebnergallery.com",
    "wof:name": "Christopher David \u0026 Graebner",
    "wof:placetype": "venue"
  },
  "geometry": {"coordinates":[-81.919547,40.554169],"type":"Point"}
}
