{
  "type": "Feature",
  "properties": {
    "addr:full": "205 S Sandusky St Tiffin OH 44883",
    "addr:housenumber": "205",
    "addr:postcode": "44883",
    "addr:street": "S Sandusky St",
    "iso:country": "US",
    "sg:address": "205 S Sandusky St",
    "sg:city": "Tiffin",
    "sg:classifiers": [
      {
        "category": "Food \u0026 Beverages",
        "subcategory": "Liquor \u0026 Beverages",
        "type": "Retail Goods"
      }
    ],
    "sg:phone": "+1 419 447 6555",
    "sg:postcode": "44883",
    "sg:province": "OH",
    "sg:tags": [
      "beer",
      "ale"
    ],
    "wof:name": "Drive Thru",
    "wof:placetype": "venue"
  },
  "geometry": {"coordinates":[-83.186101,41.114579],"type":"Point"}
}
