{
  "type": "Feature",
  "properties": {
    "addr:full": "11 Federal Plz W Youngstown OH 44503",
    "addr:housenumber": "11",
    "addr:postcode": "44503",
    "addr:street": "Federal Plz W",
    "iso:country": "US",
    "sg:address": "11 Federal Plz W",
    "sg:city": "Youngstown",
    "sg:classifiers": [
      {
        "category": "Professional",
        "subcategory": "Lawyer \u0026 Legal Services",
        "type": "Services"
      }
    ],
    "sg:phone": "+1 330 747 4404",
    "sg:postcode": "44503",
    "sg:province": "OH",
    "sg:tags": [
      "attorney"
    ],
    "wof:name": "Newman Olson \u0026 Kerr",
    "wof:placetype": "venue"
  },
  "geometry": {"coordinates":[-80.651741,41.101014],"type":"Point"}
}
