{
  "type": "Feature",
  "properties": {
    "iso:country":"US",
    "sg:address":"7167 State Rte 180",
    "sg:city":"Hallsville",
    "sg:classifiers":[
        {
            "category":"Food & Beverages",
            "subcategory":"Groceries & Convenience Stores",
            "type":"Retail Goods"
        }
    ],
    "sg:phone":"+1 740 655 2060",
    "sg:postcode":"45644",
    "sg:province":"OH",
    "sg:tags":[
        "grocer"
    ],
    "wof:name":"Haynes Grocery",
    "wof:placetype":"venue"
},
  "geometry": {"coordinates":[-82.82650599999999,39.443987],"type":"Point"}
}