{
  "type": "Feature",
  "properties": {
    "addr:full": "7167 State Rte 180 Hallsville OH 45644",
    "addr:housenumber": "7167",
    "addr:postcode": "45644",
    "addr:street": "State Rte 180",
    "iso:country": "US",
    "sg:address": "7167 State Rte 180",
    "sg:city": "Hallsville",
    "sg:classifiers": [
      {
        "category": "Food \u0026 Beverages",
        "subcategory": "Groceries \u0026 Convenience Stores",
        "type": "Retail Goods"
      }
    ],
    "sg:phone": "+1 740 655 2060",
    "sg:postcode": "45644",
    "sg:province": "OH",
    "sg:tags": [
      "grocer"
    ],
    "wof:name": "Haynes Grocery",
    "wof:placetype": "venue"
  },
  "geometry": {"coordinates":[-82.826506,39.443987],"type":"Point"}
}
