{
  "type": "Feature",
  "properties": {
    "addr:full": "5544 Phillipsburg Union Rd Englewood OH 45322",
    "addr:housenumber": "5544",
    "addr:postcode": "45322",
    "addr:street": "Phillipsburg Union Rd",
    "iso:country": "US",
    "sg:address": "5544 Phillipsburg Union Rd",
    "sg:city": "Englewood",
    "sg:classifiers": [
      {
        "category": "Manufacturing",
        "subcategory": "Signs",
        "type": "Manufacturing \u0026 Wholesale Goods"
      }
    ],
    "sg:phone": "+1 937 836 0564",
    "sg:postcode": "45322",
    "sg:province": "OH",
    "sg:tags": [
      "auto",
      "b",
      "design",
      "specialty",
      "mfg"
    ],
    "wof:name": "Booth Signs",
    "wof:placetype": "venue"
  },
  "geometry": {"coordinates":[-84.358858,39.905239],"type":"Point"}
}
