{
  "type": "Feature",
  "properties": {
    "iso:country":"US",
    "sg:address":"119 S 1st St",
    "sg:city":"Oakwood",
    "sg:classifiers":[
        {
            "category":"Home & Garden",
            "subcategory":"Building Materials",
            "type":"Retail Goods"
        }
    ],
    "sg:phone":"+1 419 594 3338",
    "sg:postcode":"45873",
    "sg:province":"OH",
    "sg:tags":[
        "lumber"
    ],
    "wof:name":"Oakwood Lumber Co",
    "wof:placetype":"venue"
},
  "geometry": {"coordinates":[-84.37927000000001,41.090347],"type":"Point"}
}