{
  "type": "Feature",
  "properties": {
    "addr:full": "3476 Twin Bridges Rd Williamsburg OH 45176",
    "addr:housenumber": "3476",
    "addr:postcode": "45176",
    "addr:street": "Twin Bridges Rd",
    "iso:country": "US",
    "sg:address": "3476 Twin Bridges Rd",
    "sg:city": "Williamsburg",
    "sg:classifiers": [
      {
        "category": "Farming",
        "subcategory": "Livestock Farm",
        "type": "Manufacturing \u0026 Wholesale Goods"
      }
    ],
    "sg:phone": "+1 513 724 2376",
    "sg:postcode": "45176",
    "sg:province": "OH",
    "sg:tags": [
      "equine"
    ],
    "wof:name": "Gerald Fitzgerald",
    "wof:placetype": "venue"
  },
  "geometry": {"coordinates":[-84.056111,39.032344],"type":"Point"}
}
