{
  "type": "Feature",
  "properties": {
    "addr:full": "2940 Old Springfield Rd Springfield OH 45502",
    "addr:housenumber": "2940",
    "addr:postcode": "45502",
    "addr:street": "Old Springfield Rd",
    "iso:country": "US",
    "sg:address": "2940 Old Springfield Rd",
    "sg:city": "Springfield",
    "sg:classifiers": [
      {
        "category": "Bars \u0026 Pubs",
        "type": "Food \u0026 Drink"
      }
    ],
    "sg:phone": "+1 937 265 5227",
    "sg:postcode": "45502",
    "sg:province": "OH",
    "sg:tags": [
      "drinking"
    ],
    "wof:name": "Blue Monday",
    "wof:placetype": "venue"
  },
  "geometry": {"coordinates":[-83.748646,39.847812],"type":"Point"}
}
