{
  "type": "Feature",
  "properties": {
    "iso:country":"US",
    "sg:address":"2940 Old Springfield Rd",
    "sg:city":"Springfield",
    "sg:classifiers":[
        {
            "category":"Bars & Pubs",
            "type":"Food & Drink"
        }
    ],
    "sg:phone":"+1 937 265 5227",
    "sg:postcode":"45502",
    "sg:province":"OH",
    "sg:tags":[
        "drinking"
    ],
    "wof:name":"Blue Monday",
    "wof:placetype":"venue"
},
  "geometry": {"coordinates":[-83.74864599999999,39.847812],"type":"Point"}
}