{
  "type": "Feature",
  "properties": {
    "addr:full":"500 Grandview Ave Barberton OH 44203",
    "addr:housenumber":"500",
    "addr:postcode":"44203",
    "addr:street":"Grandview Ave",
    "iso:country":"US",
    "sg:address":"500 Grandview Ave",
    "sg:city":"Barberton",
    "sg:classifiers":[
        {
            "category":"Building & Trades",
            "subcategory":"Electrical",
            "type":"Services"
        }
    ],
    "sg:phone":"+1 330 745 2453",
    "sg:postcode":"44203",
    "sg:province":"OH",
    "sg:tags":[
        "electrical",
        "contractor"
    ],
    "wof:name":"Dependable Electric",
    "wof:placetype":"venue"
},
  "geometry": {"coordinates":[-81.58963199999999,41.02185],"type":"Point"}
}