{
  "type": "Feature",
  "properties": {
    "iso:country":"US",
    "sg:address":"156 E Warren St",
    "sg:city":"Germantown",
    "sg:classifiers":[
        {
            "category":"Wholesale",
            "subcategory":"Farm Supplies",
            "type":"Manufacturing & Wholesale Goods"
        }
    ],
    "sg:phone":"+1 937 855 2129",
    "sg:postcode":"45327",
    "sg:province":"OH",
    "sg:tags":[
        "feed"
    ],
    "wof:name":"Germantown Elevator",
    "wof:placetype":"venue"
},
  "geometry": {"coordinates":[-84.368374,39.627228],"type":"Point"}
}