{
  "type": "Feature",
  "properties": {
    "iso:country":"US",
    "sg:address":"2998 Yorkshire Rd",
    "sg:city":"Cleveland",
    "sg:classifiers":[
        {
            "category":"Manufacturing",
            "subcategory":"Printing",
            "type":"Manufacturing & Wholesale Goods"
        }
    ],
    "sg:phone":"+1 216 382 7540",
    "sg:postcode":"44118",
    "sg:province":"OH",
    "sg:tags":[
        "printer"
    ],
    "wof:name":"Printstone",
    "wof:placetype":"venue"
},
  "geometry": {"coordinates":[-81.57209899999999,41.504135],"type":"Point"}
}