{
  "type": "Feature",
  "properties": {
    "addr:full": "3054 Tuscarawas St W Canton OH 44708",
    "addr:housenumber": "3054",
    "addr:postcode": "44708",
    "addr:street": "Tuscarawas St W",
    "iso:country": "US",
    "sg:address": "3054 Tuscarawas St W",
    "sg:city": "Canton",
    "sg:classifiers": [
      {
        "category": "Manufacturing",
        "subcategory": "Chemicals \u0026 Compounds",
        "type": "Manufacturing \u0026 Wholesale Goods"
      }
    ],
    "sg:phone": "+1 330 451 1628",
    "sg:postcode": "44708",
    "sg:province": "OH",
    "sg:tags": [
      "hygiene",
      "oral",
      "product",
      "mfg"
    ],
    "wof:name": "Biocurv Medical Instruments",
    "wof:placetype": "venue"
  },
  "geometry": {"coordinates":[-81.409801,40.798245],"type":"Point"}
}
