{
  "type": "Feature",
  "properties": {
    "iso:country":"US",
    "sg:address":"117 N Greenwood St",
    "sg:city":"Marion",
    "sg:classifiers":[
        {
            "category":"Professional",
            "subcategory":"Detective & Security Services",
            "type":"Services"
        }
    ],
    "sg:phone":"+1 740 383 1165",
    "sg:postcode":"43302",
    "sg:province":"OH",
    "sg:tags":[
        "investigator"
    ],
    "wof:name":"Ron Scheiderer & Assoc",
    "wof:placetype":"venue"
},
  "geometry": {"coordinates":[-83.12038699999999,40.589781],"type":"Point"}
}