{
  "type": "Feature",
  "properties": {
    "addr:full": "117 N Greenwood St Marion OH 43302",
    "addr:housenumber": "117",
    "addr:postcode": "43302",
    "addr:street": "N Greenwood St",
    "iso:country": "US",
    "sg:address": "117 N Greenwood St",
    "sg:city": "Marion",
    "sg:classifiers": [
      {
        "category": "Professional",
        "subcategory": "Detective \u0026 Security Services",
        "type": "Services"
      }
    ],
    "sg:phone": "+1 740 383 1165",
    "sg:postcode": "43302",
    "sg:province": "OH",
    "sg:tags": [
      "investigator"
    ],
    "wof:name": "Ron Scheiderer \u0026 Assoc",
    "wof:placetype": "venue"
  },
  "geometry": {"coordinates":[-83.120387,40.589781],"type":"Point"}
}
