{
  "type": "Feature",
  "properties": {
    "addr:full":"158 Wilson St Struthers OH 44471",
    "addr:housenumber":"158",
    "addr:postcode":"44471",
    "addr:street":"Wilson St",
    "iso:country":"US",
    "sg:address":"158 Wilson St",
    "sg:city":"Struthers",
    "sg:classifiers":[
        {
            "category":"Recreation",
            "type":"Entertainment"
        }
    ],
    "sg:phone":"+1 330 755 3766",
    "sg:postcode":"44471",
    "sg:province":"OH",
    "sg:tags":[
        "lottery",
        "agent"
    ],
    "wof:name":"General Store",
    "wof:placetype":"venue"
},
  "geometry": {"coordinates":[-80.59678099999999,41.049665],"type":"Point"}
}