{
  "type": "Feature",
  "properties": {
    "addr:full": "4057 Cedarwood Ln Cincinnati OH 45245",
    "addr:housenumber": "4057",
    "addr:postcode": "45245",
    "addr:street": "Cedarwood Ln",
    "iso:country": "US",
    "sg:address": "4057 Cedarwood Ln",
    "sg:city": "Cincinnati",
    "sg:classifiers": [
      {
        "category": "Building \u0026 Trades",
        "subcategory": "Construction",
        "type": "Services"
      }
    ],
    "sg:phone": "+1 513 753 9605",
    "sg:postcode": "45245",
    "sg:province": "OH",
    "sg:tags": [
      "hanging",
      "contractor"
    ],
    "wof:name": "Linda Renee Craig",
    "wof:placetype": "venue"
  },
  "geometry": {"coordinates":[-84.283282,39.073147],"type":"Point"}
}
