{
  "type": "Feature",
  "properties": {
    "addr:full": "6551 Outville Rd SW Pataskala OH 43062",
    "addr:housenumber": "6551",
    "addr:postcode": "43062",
    "addr:street": "Outville Rd Sw",
    "iso:country": "US",
    "sg:address": "6551 Outville Rd SW",
    "sg:city": "Pataskala",
    "sg:classifiers": [
      {
        "category": "Building \u0026 Trades",
        "subcategory": "Electrical",
        "type": "Services"
      }
    ],
    "sg:phone": "+1 740 927 0657",
    "sg:postcode": "43062",
    "sg:province": "OH",
    "sg:tags": [
      "electrical",
      "contractor"
    ],
    "wof:name": "Security Contractors LLC",
    "wof:placetype": "venue"
  },
  "geometry": {"coordinates":[-82.59629,39.996169],"type":"Point"}
}
