{
  "type": "Feature",
  "properties": {
    "iso:country":"US",
    "sg:address":"12594 Rockside Rd",
    "sg:city":"Cleveland",
    "sg:classifiers":[
        {
            "category":"Shopping",
            "subcategory":"Discount & Variety Stores",
            "type":"Retail Goods"
        }
    ],
    "sg:phone":"+1 216 663 0566",
    "sg:postcode":"44125",
    "sg:province":"OH",
    "wof:name":"Dollar Tree",
    "wof:placetype":"venue"
},
  "geometry": {"coordinates":[-81.59707,41.400142],"type":"Point"}
}