{
  "type": "Feature",
  "properties": {
    "iso:country":"US",
    "sg:address":"221 Hermitage Ct",
    "sg:city":"Dayton",
    "sg:classifiers":[
        {
            "category":"Food & Beverages",
            "subcategory":"Bakery",
            "type":"Retail Goods"
        }
    ],
    "sg:phone":"+1 937 439 1039",
    "sg:postcode":"45459",
    "sg:province":"OH",
    "wof:name":"Jims Donut Shop",
    "wof:placetype":"venue"
},
  "geometry": {"coordinates":[-84.164536,39.640969],"type":"Point"}
}