{
  "type": "Feature",
  "properties": {
    "addr:full":"30 N Main St Poland OH 44514",
    "addr:housenumber":"30",
    "addr:postcode":"44514",
    "addr:street":"N Main St",
    "iso:country":"US",
    "sg:address":"30 N Main St",
    "sg:city":"Poland",
    "sg:classifiers":[
        {
            "category":"Banks & Credit Unions",
            "subcategory":"Bank",
            "type":"Services"
        }
    ],
    "sg:phone":"+1 330 757 0852",
    "sg:postcode":"44514",
    "sg:province":"OH",
    "wof:name":"Chase",
    "wof:placetype":"venue"
},
  "geometry": {"coordinates":[-80.615042,41.024536],"type":"Point"}
}