{
  "type": "Feature",
  "properties": {
    "iso:country":"US",
    "sg:address":"1251 E Dorothy Ln",
    "sg:city":"Dayton",
    "sg:classifiers":[
        {
            "category":"Health Services",
            "subcategory":"Clinic",
            "type":"Services"
        }
    ],
    "sg:phone":"+1 937 865 8771",
    "sg:postcode":"45419",
    "sg:province":"OH",
    "sg:tags":[
        "patient",
        "specialty",
        "out"
    ],
    "wof:name":"Kettering & Sycamore Hospitals",
    "wof:placetype":"venue"
},
  "geometry": {"coordinates":[-84.141944,39.703745],"type":"Point"}
}