{
  "type": "Feature",
  "properties": {
    "addr:full":"1500 Georgetown Rd Hudson OH 44236",
    "addr:housenumber":"1500",
    "addr:postcode":"44236",
    "addr:street":"Georgetown Rd",
    "iso:country":"US",
    "sg:address":"1500 Georgetown Rd",
    "sg:city":"Hudson",
    "sg:classifiers":[
        {
            "category":"Building & Trades",
            "subcategory":"Construction",
            "type":"Services"
        }
    ],
    "sg:phone":"+1 330 650 1488",
    "sg:postcode":"44236",
    "sg:province":"OH",
    "sg:tags":[
        "general",
        "contractor"
    ],
    "wof:name":"G P Zampelli Construction Inc",
    "wof:placetype":"venue"
},
  "geometry": {"coordinates":[-81.423828,41.207958],"type":"Point"}
}