{
  "type": "Feature",
  "properties": {
    "iso:country":"US",
    "sg:address":"1213 3rd St NW",
    "sg:city":"New Philadelphia",
    "sg:classifiers":[
        {
            "category":"Restaurant",
            "type":"Food & Drink"
        }
    ],
    "sg:phone":"+1 330 343 7807",
    "sg:postcode":"44663",
    "sg:province":"OH",
    "sg:tags":[
        "eating"
    ],
    "wof:name":"Kds Allegro Pizzeria Inc",
    "wof:placetype":"venue"
},
  "geometry": {"coordinates":[-81.45007,40.506077],"type":"Point"}
}