{
  "type": "Feature",
  "properties": {
    "addr:full":"8241 Camargo Rd Cincinnati OH 45243",
    "addr:housenumber":"8241",
    "addr:postcode":"45243",
    "addr:street":"Camargo Rd",
    "iso:country":"US",
    "sg:address":"8241 Camargo Rd",
    "sg:city":"Cincinnati",
    "sg:classifiers":[
        {
            "category":"Freight",
            "type":"Transportation"
        }
    ],
    "sg:phone":"+1 513 561 5679",
    "sg:postcode":"45243",
    "sg:province":"OH",
    "sg:tags":[
        "steel",
        "erection",
        "storage",
        "trucking",
        "without",
        "local"
    ],
    "sg:website":"www.beamerbrostrucking.com",
    "wof:name":"Beamer Brothers Trucking Co",
    "wof:placetype":"venue"
},
  "geometry": {"coordinates":[-84.339911,39.19928],"type":"Point"}
}