{
  "type": "Feature",
  "properties": {
    "addr:full": "800 Weber Ave Akron OH 44303",
    "addr:housenumber": "800",
    "addr:postcode": "44303",
    "addr:street": "Weber Ave",
    "iso:country": "US",
    "sg:address": "800 Weber Ave",
    "sg:city": "Akron",
    "sg:classifiers": [
      {
        "category": "Building \u0026 Trades",
        "subcategory": "Construction",
        "type": "Services"
      }
    ],
    "sg:phone": "+1 330 836 5699",
    "sg:postcode": "44303",
    "sg:province": "OH",
    "sg:tags": [
      "contractor"
    ],
    "wof:name": "Akron Demolition Inc",
    "wof:placetype": "venue"
  },
  "geometry": {"coordinates":[-81.539141,41.100754],"type":"Point"}
}
