{
  "type": "Feature",
  "properties": {
    "iso:country":"US",
    "sg:address":"5688 Kings Island Dr",
    "sg:city":"Mason",
    "sg:classifiers":[
        {
            "category":"Building & Trades",
            "subcategory":"Electrical",
            "type":"Services"
        }
    ],
    "sg:phone":"+1 513 339 9878",
    "sg:postcode":"45040",
    "sg:province":"OH",
    "sg:tags":[
        "electric",
        "contractor"
    ],
    "wof:name":"Hayden Electric",
    "wof:placetype":"venue"
},
  "geometry": {"coordinates":[-84.26539699999999,39.352536],"type":"Point"}
}