{
  "type": "Feature",
  "properties": {
    "addr:full": "5688 Kings Island Dr Mason OH 45040",
    "addr:housenumber": "5688",
    "addr:postcode": "45040",
    "addr:street": "Kings Island Dr",
    "iso:country": "US",
    "sg:address": "5688 Kings Island Dr",
    "sg:city": "Mason",
    "sg:classifiers": [
      {
        "category": "Building \u0026 Trades",
        "subcategory": "Electrical",
        "type": "Services"
      }
    ],
    "sg:phone": "+1 513 339 9878",
    "sg:postcode": "45040",
    "sg:province": "OH",
    "sg:tags": [
      "electric",
      "contractor"
    ],
    "wof:name": "Hayden Electric",
    "wof:placetype": "venue"
  },
  "geometry": {"coordinates":[-84.265397,39.352536],"type":"Point"}
}
