{
  "type": "Feature",
  "properties": {
    "addr:full": "521 W Finley St Upper Sandusky OH 43351",
    "addr:housenumber": "521",
    "addr:postcode": "43351",
    "addr:street": "W Finley St",
    "iso:country": "US",
    "sg:address": "521 W Finley St",
    "sg:city": "Upper Sandusky",
    "sg:classifiers": [
      {
        "category": "Building \u0026 Trades",
        "subcategory": "Construction",
        "type": "Services"
      }
    ],
    "sg:phone": "+1 419 294 5109",
    "sg:postcode": "43351",
    "sg:province": "OH",
    "sg:tags": [
      "concrete",
      "contractor"
    ],
    "wof:name": "C H McCarthy Corporation",
    "wof:placetype": "venue"
  },
  "geometry": {"coordinates":[-83.289194,40.830176],"type":"Point"}
}
