{
  "type": "Feature",
  "properties": {
    "addr:full":"521 W Finley St Upper Sandusky OH 43351",
    "addr:housenumber":"521",
    "addr:postcode":"43351",
    "addr:street":"W Finley St",
    "iso:country":"US",
    "sg:address":"521 W Finley St",
    "sg:city":"Upper Sandusky",
    "sg:classifiers":[
        {
            "category":"Building & Trades",
            "subcategory":"Construction",
            "type":"Services"
        }
    ],
    "sg:phone":"+1 419 294 5109",
    "sg:postcode":"43351",
    "sg:province":"OH",
    "sg:tags":[
        "concrete",
        "contractor"
    ],
    "wof:name":"C H McCarthy Corporation",
    "wof:placetype":"venue"
},
  "geometry": {"coordinates":[-83.28919399999999,40.830176],"type":"Point"}
}