{
  "type": "Feature",
  "properties": {
    "addr:full": "6771 W Henry Rd Ripley OH 45167",
    "addr:housenumber": "6771",
    "addr:postcode": "45167",
    "addr:street": "W Henry Rd",
    "iso:country": "US",
    "sg:address": "6771 W Henry Rd",
    "sg:city": "Ripley",
    "sg:classifiers": [
      {
        "category": "Farming",
        "subcategory": "Livestock Farm",
        "type": "Manufacturing \u0026 Wholesale Goods"
      }
    ],
    "sg:phone": "+1 937 392 4881",
    "sg:postcode": "45167",
    "sg:province": "OH",
    "sg:tags": [
      "beef",
      "tobacco",
      "corn",
      "field",
      "cattle",
      "feedlot"
    ],
    "wof:name": "Mary Fussnecker",
    "wof:placetype": "venue"
  },
  "geometry": {"coordinates":[-83.816826,38.806829],"type":"Point"}
}
