{
  "type": "Feature",
  "properties": {
    "iso:country":"US",
    "sg:address":"209 E Aurora Rd",
    "sg:city":"Northfield",
    "sg:classifiers":[
        {
            "category":"Professional",
            "subcategory":"Management & Consulting",
            "type":"Services"
        }
    ],
    "sg:phone":"+1 330 468 5779",
    "sg:postcode":"44067",
    "sg:province":"OH",
    "sg:tags":[
        "party",
        "planning"
    ],
    "wof:name":"Club Diva Lu",
    "wof:placetype":"venue"
},
  "geometry": {"coordinates":[-81.53206,41.31424],"type":"Point"}
}