{
  "type": "Feature",
  "properties": {
    "iso:country":"US",
    "sg:address":"4622 N High St",
    "sg:city":"Columbus",
    "sg:classifiers":[
        {
            "category":"Shopping",
            "subcategory":"Florist",
            "type":"Retail Goods"
        }
    ],
    "sg:phone":"+1 614 784 0017",
    "sg:postcode":"43214",
    "sg:province":"OH",
    "sg:tags":[
        "supply"
    ],
    "wof:name":"Mimosa Floral Design",
    "wof:placetype":"venue"
},
  "geometry": {"coordinates":[-83.019732,40.056912],"type":"Point"}
}