{
  "type": "Feature",
  "properties": {
    "iso:country":"US",
    "sg:address":"3128 Tremainsville Rd",
    "sg:city":"Toledo",
    "sg:classifiers":[
        {
            "category":"Wholesale",
            "subcategory":"Metals & Minerals",
            "type":"Manufacturing & Wholesale Goods"
        }
    ],
    "sg:phone":"+1 419 475 1238",
    "sg:postcode":"43613",
    "sg:province":"OH",
    "sg:tags":[
        "wholesaler",
        "steel"
    ],
    "wof:name":"Steel Sales & Processing",
    "wof:placetype":"venue"
},
  "geometry": {"coordinates":[-83.620141,41.719959],"type":"Point"}
}