{
  "type": "Feature",
  "properties": {
    "addr:full": "1957 Pressler Rd Akron OH 44312",
    "addr:housenumber": "1957",
    "addr:postcode": "44312",
    "addr:street": "Pressler Rd",
    "iso:country": "US",
    "sg:address": "1957 Pressler Rd",
    "sg:city": "Akron",
    "sg:phone": "+1 330 784 9778",
    "sg:postcode": "44312",
    "sg:province": "OH",
    "sg:tags": [
      "farm",
      "corn",
      "wheat",
      "soybean"
    ],
    "wof:name": "Hawk Farm",
    "wof:placetype": "venue"
  },
  "geometry": {"coordinates":[-81.444996,41.00877],"type":"Point"}
}
