{
  "type": "Feature",
  "properties": {
    "addr:full": "5115 Crookshank Rd Cincinnati OH 45238",
    "addr:housenumber": "5115",
    "addr:postcode": "45238",
    "addr:street": "Crookshank Rd",
    "iso:country": "US",
    "sg:address": "5115 Crookshank Rd",
    "sg:city": "Cincinnati",
    "sg:classifiers": [
      {
        "category": "Building \u0026 Trades",
        "subcategory": "Electrical",
        "type": "Services"
      }
    ],
    "sg:phone": "+1 513 451 1061",
    "sg:postcode": "45238",
    "sg:province": "OH",
    "sg:tags": [
      "electrical",
      "electric",
      "contractor"
    ],
    "wof:name": "Paff Electric LLC",
    "wof:placetype": "venue"
  },
  "geometry": {"coordinates":[-84.606982,39.127758],"type":"Point"}
}
