{
  "type": "Feature",
  "properties": {
    "addr:full": "1800 E 105th St Cleveland OH 44106",
    "addr:housenumber": "1800",
    "addr:postcode": "44106",
    "addr:street": "E 105Th St",
    "iso:country": "US",
    "sg:address": "1800 E 105th St",
    "sg:city": "Cleveland",
    "sg:classifiers": [
      {
        "category": "Government",
        "subcategory": "Office",
        "type": "Public Place"
      }
    ],
    "sg:phone": "+1 216 421 4852",
    "sg:postcode": "44106",
    "sg:province": "OH",
    "sg:tags": [
      "state",
      "program",
      "health"
    ],
    "wof:name": "WIC Program",
    "wof:placetype": "venue"
  },
  "geometry": {"coordinates":[-81.615337,41.506856],"type":"Point"}
}
