{
  "type": "Feature",
  "properties": {
    "addr:full": "24200 Chagrin Blvd Cleveland OH 44122",
    "addr:housenumber": "24200",
    "addr:postcode": "44122",
    "addr:street": "Chagrin Blvd",
    "iso:country": "US",
    "sg:address": "24200 Chagrin Blvd",
    "sg:city": "Cleveland",
    "sg:classifiers": [
      {
        "category": "Wholesale",
        "subcategory": "Computers",
        "type": "Manufacturing \u0026 Wholesale Goods"
      }
    ],
    "sg:phone": "+1 216 360 9911",
    "sg:postcode": "44122",
    "sg:province": "OH",
    "sg:tags": [
      "hardware",
      "software"
    ],
    "wof:name": "Vision Products Inc",
    "wof:placetype": "venue"
  },
  "geometry": {"coordinates":[-81.511034,41.464401],"type":"Point"}
}
