{
  "type": "Feature",
  "properties": {
    "iso:country":"US",
    "sg:address":"4118 Hunt Rd",
    "sg:city":"Cincinnati",
    "sg:classifiers":[
        {
            "category":"Food & Beverages",
            "subcategory":"Specialty",
            "type":"Retail Goods"
        }
    ],
    "sg:phone":"+1 513 984 9522",
    "sg:postcode":"45236",
    "sg:province":"OH",
    "sg:tags":[
        "health",
        "diet"
    ],
    "wof:name":"GNC",
    "wof:placetype":"venue"
},
  "geometry": {"coordinates":[-84.394764,39.226633],"type":"Point"}
}