{
  "type": "Feature",
  "properties": {
    "addr:full": "138 E Market St Tiffin OH 44883",
    "addr:housenumber": "138",
    "addr:postcode": "44883",
    "addr:street": "E Market St",
    "iso:country": "US",
    "sg:address": "138 E Market St",
    "sg:city": "Tiffin",
    "sg:classifiers": [
      {
        "category": "Education",
        "subcategory": "School",
        "type": "Public Place"
      }
    ],
    "sg:phone": "+1 419 447 4149",
    "sg:postcode": "44883",
    "sg:province": "OH",
    "wof:name": "Tiffin Junior High School",
    "wof:placetype": "venue"
  },
  "geometry": {"coordinates":[-83.173155,41.114811],"type":"Point"}
}
