{
  "type": "Feature",
  "properties": {
    "addr:full":"4105 Diane Dr Cleveland OH 44126",
    "addr:housenumber":"4105",
    "addr:postcode":"44126",
    "addr:street":"Diane Dr",
    "iso:country":"US",
    "sg:address":"4105 Diane Dr",
    "sg:city":"Cleveland",
    "sg:classifiers":[
        {
            "category":"Professional",
            "subcategory":"Accounting & Tax Preparation",
            "type":"Services"
        }
    ],
    "sg:phone":"+1 440 333 8045",
    "sg:postcode":"44126",
    "sg:province":"OH",
    "sg:tags":[
        "accountant"
    ],
    "wof:name":"John A Krebs CPA",
    "wof:placetype":"venue"
},
  "geometry": {"coordinates":[-81.827594,41.457666],"type":"Point"}
}