{
  "type": "Feature",
  "properties": {
    "iso:country":"US",
    "sg:address":"2118 Star Dr",
    "sg:city":"Wooster",
    "sg:classifiers":[
        {
            "category":"Wholesale",
            "subcategory":"Vending Machines",
            "type":"Manufacturing & Wholesale Goods"
        }
    ],
    "sg:phone":"+1 330 262 8594",
    "sg:postcode":"44691",
    "sg:province":"OH",
    "sg:tags":[
        "operator"
    ],
    "wof:name":"J & Bs Snack Time Vending",
    "wof:placetype":"venue"
},
  "geometry": {"coordinates":[-81.957588,40.825765],"type":"Point"}
}