{
  "type": "Feature",
  "properties": {
    "addr:full": "2118 Star Dr Wooster OH 44691",
    "addr:housenumber": "2118",
    "addr:postcode": "44691",
    "addr:street": "Star Dr",
    "iso:country": "US",
    "sg:address": "2118 Star Dr",
    "sg:city": "Wooster",
    "sg:classifiers": [
      {
        "category": "Wholesale",
        "subcategory": "Vending Machines",
        "type": "Manufacturing \u0026 Wholesale Goods"
      }
    ],
    "sg:phone": "+1 330 262 8594",
    "sg:postcode": "44691",
    "sg:province": "OH",
    "sg:tags": [
      "operator"
    ],
    "wof:name": "J \u0026 Bs Snack Time Vending",
    "wof:placetype": "venue"
  },
  "geometry": {"coordinates":[-81.957588,40.825765],"type":"Point"}
}
