{
  "type": "Feature",
  "properties": {
    "addr:full": "2711 Shoreline Dr Akron OH 44314",
    "addr:housenumber": "2711",
    "addr:postcode": "44314",
    "addr:street": "Shoreline Dr",
    "iso:country": "US",
    "sg:address": "2711 Shoreline Dr",
    "sg:city": "Akron",
    "sg:classifiers": [
      {
        "category": "Professional",
        "type": "Services"
      }
    ],
    "sg:phone": "+1 330 848 5184",
    "sg:postcode": "44314",
    "sg:province": "OH",
    "wof:name": "Thomas Buckeye Beverage",
    "wof:placetype": "venue"
  },
  "geometry": {"coordinates":[-81.5562,41.027097],"type":"Point"}
}
