{
  "type": "Feature",
  "properties": {
    "iso:country":"US",
    "sg:address":"52438 Peck Wadsworth Rd",
    "sg:city":"Wellington",
    "sg:classifiers":[
        {
            "category":"Professional",
            "type":"Services"
        }
    ],
    "sg:phone":"+1 440 647 4352",
    "sg:postcode":"44090",
    "sg:province":"OH",
    "wof:name":"Herb Fulger Jr",
    "wof:placetype":"venue"
},
  "geometry": {"coordinates":[-82.326331,41.185461],"type":"Point"}
}