{
  "type": "Feature",
  "properties": {
    "addr:full": "527 Chestnut St Coshocton OH 43812",
    "addr:housenumber": "527",
    "addr:postcode": "43812",
    "addr:street": "Chestnut St",
    "iso:country": "US",
    "sg:address": "527 Chestnut St",
    "sg:city": "Coshocton",
    "sg:classifiers": [
      {
        "category": "Shopping",
        "subcategory": "Used Merchandise",
        "type": "Retail Goods"
      }
    ],
    "sg:phone": "+1 740 622 9292",
    "sg:postcode": "43812",
    "sg:province": "OH",
    "wof:name": "Second Hand Rose",
    "wof:placetype": "venue"
  },
  "geometry": {"coordinates":[-81.863074,40.27486],"type":"Point"}
}
