{
  "type": "Feature",
  "properties": {
    "addr:full":"2767 Miller Paul Rd Galena OH 43021",
    "addr:housenumber":"2767",
    "addr:postcode":"43021",
    "addr:street":"Miller Paul Rd",
    "iso:country":"US",
    "sg:address":"2767 Miller Paul Rd",
    "sg:city":"Galena",
    "sg:classifiers":[
        {
            "category":"Education",
            "subcategory":"Library",
            "type":"Public Place"
        }
    ],
    "sg:phone":"+1 740 965 5642",
    "sg:postcode":"43021",
    "sg:province":"OH",
    "wof:name":"Asa Columbus Metro Softba",
    "wof:placetype":"venue"
},
  "geometry": {"coordinates":[-82.82626,40.187395],"type":"Point"}
}