{
  "type": "Feature",
  "properties": {
    "addr:full":"207 N River Ave Toronto OH 43964",
    "addr:housenumber":"207",
    "addr:postcode":"43964",
    "addr:street":"N River Ave",
    "iso:country":"US",
    "sg:address":"207 N River Ave",
    "sg:city":"Toronto",
    "sg:classifiers":[
        {
            "category":"Organizations",
            "subcategory":"Religious Organization",
            "type":"Services"
        }
    ],
    "sg:phone":"+1 740 537 3285",
    "sg:postcode":"43964",
    "sg:province":"OH",
    "sg:tags":[
        "church"
    ],
    "wof:name":"Church Of Christ",
    "wof:placetype":"venue"
},
  "geometry": {"coordinates":[-80.598822,40.466381],"type":"Point"}
}