{
  "type": "Feature",
  "properties": {
    "addr:full": "3291 Aspen Dr Wooster OH 44691",
    "addr:housenumber": "3291",
    "addr:postcode": "44691",
    "addr:street": "Aspen Dr",
    "iso:country": "US",
    "sg:address": "3291 Aspen Dr",
    "sg:city": "Wooster",
    "sg:classifiers": [
      {
        "category": "Restaurant",
        "type": "Food \u0026 Drink"
      }
    ],
    "sg:phone": "+1 330 264 2442",
    "sg:postcode": "44691",
    "sg:province": "OH",
    "sg:tags": [
      "eating"
    ],
    "wof:name": "East of Chicago Pizza",
    "wof:placetype": "venue"
  },
  "geometry": {"coordinates":[-81.987117,40.838914],"type":"Point"}
}
