{
  "type": "Feature",
  "properties": {
    "addr:full":"829 Far Hills Ave Dayton OH 45419",
    "addr:housenumber":"829",
    "addr:postcode":"45419",
    "addr:street":"Far Hills Ave",
    "iso:country":"US",
    "sg:address":"829 Far Hills Ave",
    "sg:city":"Dayton",
    "sg:classifiers":[
        {
            "category":"Professional",
            "subcategory":"Management & Consulting",
            "type":"Services"
        }
    ],
    "sg:phone":"+1 937 298 7073",
    "sg:postcode":"45419",
    "sg:province":"OH",
    "sg:tags":[
        "party",
        "planning"
    ],
    "wof:name":"Affordable Pony Rides",
    "wof:placetype":"venue"
},
  "geometry": {"coordinates":[-84.17317199999999,39.723295],"type":"Point"}
}