{
  "type": "Feature",
  "properties": {
    "iso:country":"US",
    "sg:address":"1617 Akron Peninsula Rd",
    "sg:city":"Akron",
    "sg:classifiers":[
        {
            "category":"Real Estate",
            "subcategory":"Architect",
            "type":"Services"
        }
    ],
    "sg:phone":"+1 330 928 5585",
    "sg:postcode":"44313",
    "sg:province":"OH",
    "sg:website":"www.martinarch.com",
    "wof:name":"Martin Associates Architects",
    "wof:placetype":"venue"
},
  "geometry": {"coordinates":[-81.548187,41.138842],"type":"Point"}
}