{
  "type": "Feature",
  "properties": {
    "addr:full": "5979 Hickorytree Ct Cincinnati OH 45233",
    "addr:housenumber": "5979",
    "addr:postcode": "45233",
    "addr:street": "Hickorytree Ct",
    "iso:country": "US",
    "sg:address": "5979 Hickorytree Ct",
    "sg:city": "Cincinnati",
    "sg:classifiers": [
      {
        "category": "Professional",
        "subcategory": "Management \u0026 Consulting",
        "type": "Services"
      }
    ],
    "sg:phone": "+1 513 922 3425",
    "sg:postcode": "45233",
    "sg:province": "OH",
    "sg:tags": [
      "consultant",
      "business"
    ],
    "wof:name": "G R Consulting",
    "wof:placetype": "venue"
  },
  "geometry": {"coordinates":[-84.647752,39.117001],"type":"Point"}
}
