{
  "type": "Feature",
  "properties": {
    "addr:full": "64 Marco Ln Dayton OH 45458",
    "addr:housenumber": "64",
    "addr:postcode": "45458",
    "addr:street": "Marco Ln",
    "iso:country": "US",
    "sg:address": "64 Marco Ln",
    "sg:city": "Dayton",
    "sg:classifiers": [
      {
        "category": "Health Services",
        "subcategory": "Clinic",
        "type": "Services"
      }
    ],
    "sg:phone": "+1 937 312 9900",
    "sg:postcode": "45458",
    "sg:province": "OH",
    "sg:tags": [
      "home"
    ],
    "wof:name": "Comfort Keepers",
    "wof:placetype": "venue"
  },
  "geometry": {"coordinates":[-84.156966,39.607494],"type":"Point"}
}
