{
  "type": "Feature",
  "properties": {
    "addr:full": "2154 Wooster Rd Cleveland OH 44116",
    "addr:housenumber": "2154",
    "addr:postcode": "44116",
    "addr:street": "Wooster Rd",
    "iso:country": "US",
    "sg:address": "2154 Wooster Rd",
    "sg:city": "Cleveland",
    "sg:classifiers": [
      {
        "category": "Retail",
        "subcategory": "Auto Repair",
        "type": "Services"
      }
    ],
    "sg:phone": "+1 440 331 7373",
    "sg:postcode": "44116",
    "sg:province": "OH",
    "sg:tags": [
      "repairing",
      "automobile"
    ],
    "wof:name": "Anthony Spremulli Auto Prfrmnc",
    "wof:placetype": "venue"
  },
  "geometry": {"coordinates":[-81.835279,41.475887],"type":"Point"}
}
