{
  "type": "Feature",
  "properties": {
    "addr:full": "20339 Mercedes Ave Cleveland OH 44116",
    "addr:housenumber": "20339",
    "addr:postcode": "44116",
    "addr:street": "Mercedes Ave",
    "iso:country": "US",
    "sg:address": "20339 Mercedes Ave",
    "sg:city": "Cleveland",
    "sg:classifiers": [
      {
        "category": "Organizations",
        "subcategory": "Community Association",
        "type": "Services"
      }
    ],
    "sg:phone": "+1 440 331 0598",
    "sg:postcode": "44116",
    "sg:province": "OH",
    "sg:tags": [
      "club"
    ],
    "wof:name": "Northeast Ohio PC Club",
    "wof:placetype": "venue"
  },
  "geometry": {"coordinates":[-81.845526,41.455794],"type":"Point"}
}
