{
  "type": "Feature",
  "properties": {
    "addr:full": "1330 Conwell Ave Willard OH 44890",
    "addr:housenumber": "1330",
    "addr:postcode": "44890",
    "addr:street": "Conwell Ave",
    "iso:country": "US",
    "sg:address": "1330 Conwell Ave",
    "sg:city": "Willard",
    "sg:classifiers": [
      {
        "category": "Autos \u0026 Motor Vehicles",
        "subcategory": "Automobile Sales",
        "type": "Retail Goods"
      }
    ],
    "sg:phone": "+1 419 935 0194",
    "sg:postcode": "44890",
    "sg:province": "OH",
    "sg:tags": [
      "car",
      "dealer"
    ],
    "sg:website": "www.sharpnack2chevy.com",
    "wof:name": "Sharpnack II Chevrolet Olds",
    "wof:placetype": "venue"
  },
  "geometry": {"coordinates":[-82.715733,41.042387],"type":"Point"}
}
