{
  "type": "Feature",
  "properties": {
    "addr:full": "1122 Portage Trl Cuyahoga Falls OH 44223",
    "addr:housenumber": "1122",
    "addr:postcode": "44223",
    "addr:street": "Portage Trl",
    "iso:country": "US",
    "sg:address": "1122 Portage Trl",
    "sg:city": "Cuyahoga Falls",
    "sg:classifiers": [
      {
        "category": "Bars \u0026 Pubs",
        "type": "Food \u0026 Drink"
      }
    ],
    "sg:phone": "+1 330 920 9213",
    "sg:postcode": "44223",
    "sg:province": "OH",
    "wof:name": "J R's Pub",
    "wof:placetype": "venue"
  },
  "geometry": {"coordinates":[-81.497245,41.14275],"type":"Point"}
}
