{
  "type": "Feature",
  "properties": {
    "addr:full":"619 Portage Trail Extended W Cuyahoga Falls OH 44223",
    "addr:housenumber":"619",
    "addr:postcode":"44223",
    "addr:street":"Portage Trail Extended W",
    "iso:country":"US",
    "sg:address":"619 Portage Trail Extended W",
    "sg:city":"Cuyahoga Falls",
    "sg:classifiers":[
        {
            "category":"Insurance",
            "subcategory":"Insurance Agent",
            "type":"Services"
        }
    ],
    "sg:phone":"+1 330 929 6006",
    "sg:postcode":"44223",
    "sg:province":"OH",
    "wof:name":"Budzowski Rnald Ntonwide Insur",
    "wof:placetype":"venue"
},
  "geometry": {"coordinates":[-81.522397,41.140994],"type":"Point"}
}