{
  "type": "Feature",
  "properties": {
    "iso:country":"US",
    "sg:address":"2800 E Powell Dr",
    "sg:city":"Lewis Center",
    "sg:classifiers":[
        {
            "category":"Education",
            "subcategory":"School",
            "type":"Public Place"
        }
    ],
    "sg:phone":"+1 740 881 5478",
    "sg:postcode":"43035",
    "sg:province":"OH",
    "wof:name":"Olentangy Local Schools",
    "wof:placetype":"venue"
},
  "geometry": {"coordinates":[-82.975756,40.156741],"type":"Point"}
}