{
  "type": "Feature",
  "properties": {
    "addr:full": "1786 Twp Rd 142 Van Buren OH 45889",
    "addr:housenumber": "1786;142",
    "addr:postcode": "45889",
    "addr:street": "Twp Rd",
    "iso:country": "US",
    "sg:address": "1786 Twp Rd 142",
    "sg:city": "Van Buren",
    "sg:phone": "+1 419 299 3664",
    "sg:postcode": "45889",
    "sg:province": "OH",
    "sg:tags": [
      "farm",
      "grain",
      "cash"
    ],
    "wof:name": "Darrell G Withrow",
    "wof:placetype": "venue"
  },
  "geometry": {"coordinates":[-83.669151,41.135241],"type":"Point"}
}
