{
  "type": "Feature",
  "properties": {
    "addr:full": "357 Central Ave Bolivar OH 44612",
    "addr:housenumber": "357",
    "addr:postcode": "44612",
    "addr:street": "Central Ave Bolivar",
    "iso:country": "US",
    "sg:address": "357 Central Ave",
    "sg:city": "Bolivar",
    "sg:classifiers": [
      {
        "category": "Autos \u0026 Motor Vehicles",
        "subcategory": "Fuel \u0026 Gas Station",
        "type": "Retail Goods"
      }
    ],
    "sg:phone": "+1 330 874 2020",
    "sg:postcode": "44612",
    "sg:province": "OH",
    "sg:tags": [
      "oil"
    ],
    "wof:name": "Bolivar Service Ctr",
    "wof:placetype": "venue"
  },
  "geometry": {"coordinates":[-81.452149,40.64707],"type":"Point"}
}
