{
  "type": "Feature",
  "properties": {
    "addr:full": "7419 W Chester Rd West Chester OH 45069",
    "addr:housenumber": "7419",
    "addr:postcode": "45069",
    "addr:street": "W Chester Rd",
    "iso:country": "US",
    "sg:address": "7419 W Chester Rd",
    "sg:city": "West Chester",
    "sg:classifiers": [
      {
        "category": "Restaurant",
        "type": "Food \u0026 Drink"
      }
    ],
    "sg:phone": "+1 513 777 2900",
    "sg:postcode": "45069",
    "sg:province": "OH",
    "sg:tags": [
      "eating"
    ],
    "wof:name": "Long John Silver's",
    "wof:placetype": "venue"
  },
  "geometry": {"coordinates":[-84.379981,39.319882],"type":"Point"}
}
