{
  "type": "Feature",
  "properties": {
    "addr:full":"405 Falcon Dr New Carlisle OH 45344",
    "addr:housenumber":"405",
    "addr:postcode":"45344",
    "addr:street":"Falcon Dr",
    "iso:country":"US",
    "sg:address":"405 Falcon Dr",
    "sg:city":"New Carlisle",
    "sg:classifiers":[
        {
            "category":"Professional",
            "type":"Services"
        }
    ],
    "sg:phone":"+1 937 845 1114",
    "sg:postcode":"45344",
    "sg:province":"OH",
    "wof:name":"Candle House",
    "wof:placetype":"venue"
},
  "geometry": {"coordinates":[-84.035669,39.940784],"type":"Point"}
}