{
  "type": "Feature",
  "properties": {
    "addr:full":"2311 Grand Ave Cincinnati OH 45214",
    "addr:housenumber":"2311",
    "addr:postcode":"45214",
    "addr:street":"Grand Ave",
    "iso:country":"US",
    "sg:address":"2311 Grand Ave",
    "sg:city":"Cincinnati",
    "sg:classifiers":[
        {
            "category":"Food & Beverages",
            "subcategory":"Liquor & Beverages",
            "type":"Retail Goods"
        }
    ],
    "sg:phone":"+1 513 921 1179",
    "sg:postcode":"45214",
    "sg:province":"OH",
    "sg:tags":[
        "alcoholic"
    ],
    "wof:name":"Package Routing Service",
    "wof:placetype":"venue"
},
  "geometry": {"coordinates":[-84.553296,39.125942],"type":"Point"}
}