{
  "type": "Feature",
  "properties": {
    "addr:full": "7021 Manchester Rd Ste B Canal Fulton OH 44614",
    "addr:housenumber": "7021",
    "addr:postcode": "44614",
    "addr:street": "Manchester Rd Ste B",
    "iso:country": "US",
    "sg:address": "7021 Manchester Rd Ste B",
    "sg:city": "Canal Fulton",
    "sg:classifiers": [
      {
        "category": "Retail",
        "subcategory": "Auto Repair",
        "type": "Services"
      }
    ],
    "sg:phone": "+1 330 854 0505",
    "sg:postcode": "44614",
    "sg:province": "OH",
    "wof:name": "Paul's Car Care",
    "wof:placetype": "venue"
  },
  "geometry": {"coordinates":[-81.5616,40.915901],"type":"Point"}
}
