{
  "type": "Feature",
  "properties": {
    "addr:full":"5115 Grandin Ridge Dr Hamilton OH 45011",
    "addr:housenumber":"5115",
    "addr:postcode":"45011",
    "addr:street":"Grandin Ridge Dr",
    "iso:country":"US",
    "sg:address":"5115 Grandin Ridge Dr",
    "sg:city":"Hamilton",
    "sg:classifiers":[
        {
            "category":"Building & Trades",
            "subcategory":"Construction",
            "type":"Services"
        }
    ],
    "sg:phone":"+1 513 896 7681",
    "sg:postcode":"45011",
    "sg:province":"OH",
    "sg:tags":[
        "handyman"
    ],
    "wof:name":"Handyman By Design",
    "wof:placetype":"venue"
},
  "geometry": {"coordinates":[-84.449763,39.383321],"type":"Point"}
}