{
  "type": "Feature",
  "properties": {
    "addr:full": "4945 Stoffer Rd Homeworth OH 44634",
    "addr:housenumber": "4945",
    "addr:postcode": "44634",
    "addr:street": "Stoffer Rd",
    "iso:country": "US",
    "sg:address": "4945 Stoffer Rd",
    "sg:city": "Homeworth",
    "sg:classifiers": [
      {
        "category": "Farming",
        "subcategory": "Dairy Farm",
        "type": "Manufacturing \u0026 Wholesale Goods"
      }
    ],
    "sg:phone": "+1 330 525 7057",
    "sg:postcode": "44634",
    "sg:province": "OH",
    "wof:name": "Twin Springs Farm",
    "wof:placetype": "venue"
  },
  "geometry": {"coordinates":[-81.004158,40.830022],"type":"Point"}
}
