{
  "type": "Feature",
  "properties": {
    "iso:country":"US",
    "sg:address":"4945 Stoffer Rd",
    "sg:city":"Homeworth",
    "sg:classifiers":[
        {
            "category":"Farming",
            "subcategory":"Dairy Farm",
            "type":"Manufacturing & Wholesale Goods"
        }
    ],
    "sg:phone":"+1 330 525 7057",
    "sg:postcode":"44634",
    "sg:province":"OH",
    "wof:name":"Twin Springs Farm",
    "wof:placetype":"venue"
},
  "geometry": {"coordinates":[-81.004158,40.830022],"type":"Point"}
}