{
  "type": "Feature",
  "properties": {
    "iso:country":"US",
    "sg:address":"5555 Scarborough Blvd",
    "sg:city":"Columbus",
    "sg:classifiers":[
        {
            "category":"Professional",
            "subcategory":"Employment Agencies",
            "type":"Services"
        }
    ],
    "sg:phone":"+1 614 322 3250",
    "sg:postcode":"43232",
    "sg:province":"OH",
    "sg:tags":[
        "help",
        "contractor"
    ],
    "wof:name":"Spherion",
    "wof:placetype":"venue"
},
  "geometry": {"coordinates":[-82.850431,39.931671],"type":"Point"}
}