{
  "type": "Feature",
  "properties": {
    "iso:country":"US",
    "sg:address":"4905 Delhi Ave",
    "sg:city":"Cincinnati",
    "sg:classifiers":[
        {
            "category":"Banks & Credit Unions",
            "subcategory":"Bank",
            "type":"Services"
        }
    ],
    "sg:phone":"+1 513 579 5300",
    "sg:postcode":"45238",
    "sg:province":"OH",
    "sg:tags":[
        "state",
        "commercial"
    ],
    "wof:name":"Fifth Third Bank",
    "wof:placetype":"venue"
},
  "geometry": {"coordinates":[-84.60628,39.095254],"type":"Point"}
}