{
  "type": "Feature",
  "properties": {
    "addr:full": "4905 Delhi Ave Cincinnati OH 45238",
    "addr:housenumber": "4905",
    "addr:postcode": "45238",
    "addr:street": "Delhi Ave",
    "iso:country": "US",
    "sg:address": "4905 Delhi Ave",
    "sg:city": "Cincinnati",
    "sg:classifiers": [
      {
        "category": "Banks \u0026 Credit Unions",
        "subcategory": "Bank",
        "type": "Services"
      }
    ],
    "sg:phone": "+1 513 579 5300",
    "sg:postcode": "45238",
    "sg:province": "OH",
    "sg:tags": [
      "state",
      "commercial"
    ],
    "wof:name": "Fifth Third Bank",
    "wof:placetype": "venue"
  },
  "geometry": {"coordinates":[-84.60628,39.095254],"type":"Point"}
}
