{
  "type": "Feature",
  "properties": {
    "addr:full": "63 Deerfield Dr Loveland OH 45140",
    "addr:housenumber": "63",
    "addr:postcode": "45140",
    "addr:street": "Deerfield Dr",
    "iso:country": "US",
    "sg:address": "63 Deerfield Dr",
    "sg:city": "Loveland",
    "sg:classifiers": [
      {
        "category": "Professional",
        "type": "Services"
      }
    ],
    "sg:phone": "+1 513 722 1643",
    "sg:postcode": "45140",
    "sg:province": "OH",
    "wof:name": "Paul Jones",
    "wof:placetype": "venue"
  },
  "geometry": {"coordinates":[-84.207138,39.206113],"type":"Point"}
}
