{
  "type": "Feature",
  "properties": {
    "iso:country":"US",
    "sg:address":"590 Barrett Rd",
    "sg:city":"Berea",
    "sg:classifiers":[
        {
            "category":"Wholesale",
            "subcategory":"Durable Goods & Equipment",
            "type":"Manufacturing & Wholesale Goods"
        }
    ],
    "sg:phone":"+1 440 816 9081",
    "sg:postcode":"44017",
    "sg:province":"OH",
    "sg:tags":[
        "representative",
        "manufacturer"
    ],
    "wof:name":"Omnex Quality Registrar",
    "wof:placetype":"venue"
},
  "geometry": {"coordinates":[-81.876525,41.387952],"type":"Point"}
}