{
  "type": "Feature",
  "properties": {
    "iso:country":"US",
    "sg:address":"8041 Hosbrook Rd",
    "sg:city":"Cincinnati",
    "sg:classifiers":[
        {
            "category":"Professional",
            "subcategory":"Accounting & Tax Preparation",
            "type":"Services"
        }
    ],
    "sg:phone":"+1 513 984 6795",
    "sg:postcode":"45236",
    "sg:province":"OH",
    "sg:tags":[
        "return",
        "filing"
    ],
    "sg:website":"www.hrblock.com",
    "wof:name":"H & R Block Tax Svc",
    "wof:placetype":"venue"
},
  "geometry": {"coordinates":[-84.37098,39.203686],"type":"Point"}
}