{
  "type": "Feature",
  "properties": {
    "addr:full": "8041 Hosbrook Rd Cincinnati OH 45236",
    "addr:housenumber": "8041",
    "addr:postcode": "45236",
    "addr:street": "Hosbrook Rd",
    "iso:country": "US",
    "sg:address": "8041 Hosbrook Rd",
    "sg:city": "Cincinnati",
    "sg:classifiers": [
      {
        "category": "Professional",
        "subcategory": "Accounting \u0026 Tax Preparation",
        "type": "Services"
      }
    ],
    "sg:phone": "+1 513 984 6795",
    "sg:postcode": "45236",
    "sg:province": "OH",
    "sg:tags": [
      "return",
      "filing"
    ],
    "sg:website": "www.hrblock.com",
    "wof:name": "H \u0026 R Block Tax Svc",
    "wof:placetype": "venue"
  },
  "geometry": {"coordinates":[-84.37098,39.203686],"type":"Point"}
}
