{
  "type": "Feature",
  "properties": {
    "addr:full":"11503 Springfield Pike Cincinnati OH 45246",
    "addr:housenumber":"11503",
    "addr:postcode":"45246",
    "addr:street":"Springfield Pike",
    "iso:country":"US",
    "sg:address":"11503 Springfield Pike",
    "sg:city":"Cincinnati",
    "sg:classifiers":[
        {
            "category":"Banks & Credit Unions",
            "subcategory":"Bank",
            "type":"Services"
        }
    ],
    "sg:phone":"+1 513 772 6522",
    "sg:postcode":"45246",
    "sg:province":"OH",
    "sg:tags":[
        "loan",
        "real estate"
    ],
    "wof:name":"EZ Mortgage Inc",
    "wof:placetype":"venue"
},
  "geometry": {"coordinates":[-84.485489,39.284346],"type":"Point"}
}