{
  "type": "Feature",
  "properties": {
    "iso:country":"US",
    "sg:address":"1939 Bailey Rd",
    "sg:city":"Cuyahoga Falls",
    "sg:classifiers":[
        {
            "category":"Restaurant",
            "type":"Food & Drink"
        }
    ],
    "sg:phone":"+1 330 929 2004",
    "sg:postcode":"44221",
    "sg:province":"OH",
    "sg:tags":[
        "eating"
    ],
    "wof:name":"Jeffrey J Janeda",
    "wof:placetype":"venue"
},
  "geometry": {"coordinates":[-81.465924,41.132864],"type":"Point"}
}