{
  "type": "Feature",
  "properties": {
    "addr:full": "133 N Gettysburg Ave Dayton OH 45417",
    "addr:housenumber": "133",
    "addr:postcode": "45417",
    "addr:street": "N Gettysburg Ave",
    "iso:country": "US",
    "sg:address": "133 N Gettysburg Ave",
    "sg:city": "Dayton",
    "sg:classifiers": [
      {
        "category": "Professional",
        "subcategory": "Management \u0026 Consulting",
        "type": "Services"
      }
    ],
    "sg:phone": "+1 937 262 5582",
    "sg:postcode": "45417",
    "sg:province": "OH",
    "sg:tags": [
      "employment",
      "screening"
    ],
    "wof:name": "Datalink Information Svc",
    "wof:placetype": "venue"
  },
  "geometry": {"coordinates":[-84.253201,39.751809],"type":"Point"}
}
