{
  "type": "Feature",
  "properties": {
    "iso:country":"US",
    "sg:address":"110 Island Rd",
    "sg:city":"Circleville",
    "sg:classifiers":[
        {
            "category":"Government",
            "subcategory":"Office",
            "type":"Public Place"
        }
    ],
    "sg:phone":"+1 740 477 1691",
    "sg:postcode":"43113",
    "sg:province":"OH",
    "sg:tags":[
        "federal"
    ],
    "wof:name":"US Consolidated Farm Svc Agcy",
    "wof:placetype":"venue"
},
  "geometry": {"coordinates":[-82.94952000000001,39.604211],"type":"Point"}
}