{
  "type": "Feature",
  "properties": {
    "iso:country":"US",
    "sg:address":"59 Spruce St",
    "sg:city":"Columbus",
    "sg:classifiers":[
        {
            "category":"Food & Beverages",
            "subcategory":"Fruits & Vegetables",
            "type":"Retail Goods"
        }
    ],
    "sg:phone":"+1 614 484 0081",
    "sg:postcode":"43215",
    "sg:province":"OH",
    "sg:tags":[
        "produce"
    ],
    "wof:name":"North Market Produce LLC",
    "wof:placetype":"venue"
},
  "geometry": {"coordinates":[-83.004297,39.972266],"type":"Point"}
}