{
  "type": "Feature",
  "properties": {
    "addr:full": "2300 Montana Ave Cincinnati OH 45211",
    "addr:housenumber": "2300",
    "addr:postcode": "45211",
    "addr:street": "Montana Ave",
    "iso:country": "US",
    "sg:address": "2300 Montana Ave",
    "sg:city": "Cincinnati",
    "sg:classifiers": [
      {
        "category": "Professional",
        "type": "Services"
      }
    ],
    "sg:phone": "+1 513 661 2100",
    "sg:postcode": "45211",
    "sg:province": "OH",
    "sg:tags": [
      "establishment"
    ],
    "wof:name": "William Hall Assoc Inc",
    "wof:placetype": "venue"
  },
  "geometry": {"coordinates":[-84.568047,39.15688],"type":"Point"}
}
