{
  "type": "Feature",
  "properties": {
    "addr:full":"5511 12th St NW Canton OH 44708",
    "addr:housenumber":"5511",
    "addr:postcode":"44708",
    "addr:street":"12Th St Nw",
    "iso:country":"US",
    "sg:address":"5511 12th St NW",
    "sg:city":"Canton",
    "sg:classifiers":[
        {
            "category":"Building & Trades",
            "subcategory":"Construction",
            "type":"Services"
        }
    ],
    "sg:phone":"+1 330 477 6776",
    "sg:postcode":"44708",
    "sg:province":"OH",
    "sg:tags":[
        "excavating",
        "contractor"
    ],
    "wof:name":"Mercier Trenching Svc",
    "wof:placetype":"venue"
},
  "geometry": {"coordinates":[-81.457527,40.812067],"type":"Point"}
}