{
  "type": "Feature",
  "properties": {
    "addr:full": "9235 W 3rd St Dayton OH 45427",
    "addr:housenumber": "9235",
    "addr:postcode": "45427",
    "addr:street": "W 3Rd St",
    "iso:country": "US",
    "sg:address": "9235 W 3rd St",
    "sg:city": "Dayton",
    "sg:classifiers": [
      {
        "category": "Professional",
        "type": "Services"
      }
    ],
    "sg:phone": "+1 937 835 3467",
    "sg:postcode": "45427",
    "sg:province": "OH",
    "wof:name": "Terry L Ruble",
    "wof:placetype": "venue"
  },
  "geometry": {"coordinates":[-84.351713,39.745973],"type":"Point"}
}
