{
  "type": "Feature",
  "properties": {
    "addr:full":"3822 E Broad St Columbus OH 43213",
    "addr:housenumber":"3822",
    "addr:postcode":"43213",
    "addr:street":"E Broad St",
    "iso:country":"US",
    "sg:address":"3822 E Broad St",
    "sg:city":"Columbus",
    "sg:classifiers":[
        {
            "category":"Shopping",
            "subcategory":"Department Store",
            "type":"Retail Goods"
        }
    ],
    "sg:phone":"+1 614 237 5253",
    "sg:postcode":"43213",
    "sg:province":"OH",
    "sg:tags":[
        "miscellaneous",
        "merchandise"
    ],
    "wof:name":"Just A Dollar",
    "wof:placetype":"venue"
},
  "geometry": {"coordinates":[-82.900172,39.973308],"type":"Point"}
}