{
  "type": "Feature",
  "properties": {
    "addr:full": "8201 Kellydale St NW Massillon OH 44646",
    "addr:housenumber": "8201",
    "addr:postcode": "44646",
    "addr:street": "Kellydale St Nw",
    "iso:country": "US",
    "sg:address": "8201 Kellydale St NW",
    "sg:city": "Massillon",
    "sg:classifiers": [
      {
        "category": "Real Estate",
        "subcategory": "Developer",
        "type": "Services"
      },
      {
        "category": "Real Estate",
        "subcategory": "Real Estate Agent",
        "type": "Services"
      }
    ],
    "sg:phone": "+1 330 837 5034",
    "sg:postcode": "44646",
    "sg:province": "OH",
    "sg:tags": [
      "manager",
      "subdivider"
    ],
    "wof:name": "Carl Oser Real Estate Agency",
    "wof:placetype": "venue"
  },
  "geometry": {"coordinates":[-81.501292,40.8412],"type":"Point"}
}
