{
  "type": "Feature",
  "properties": {
    "addr:full":"630 Viewpoint Ave Cuyahoga Falls OH 44221",
    "addr:housenumber":"630",
    "addr:postcode":"44221",
    "addr:street":"Viewpoint Ave",
    "iso:country":"US",
    "sg:address":"630 Viewpoint Ave",
    "sg:city":"Cuyahoga Falls",
    "sg:classifiers":[
        {
            "category":"Professional",
            "subcategory":"Computer Services",
            "type":"Services"
        }
    ],
    "sg:phone":"+1 330 923 1691",
    "sg:postcode":"44221",
    "sg:province":"OH",
    "sg:tags":[
        "repair"
    ],
    "wof:name":"Computer Cleaners Of Akron",
    "wof:placetype":"venue"
},
  "geometry": {"coordinates":[-81.471074,41.124338],"type":"Point"}
}