{
  "type": "Feature",
  "properties": {
    "addr:full":"5201 Whippoorwill St NW North Canton OH 44720",
    "addr:housenumber":"5201",
    "addr:postcode":"44720",
    "addr:street":"Whippoorwill St Nw",
    "iso:country":"US",
    "sg:address":"5201 Whippoorwill St NW",
    "sg:city":"North Canton",
    "sg:classifiers":[
        {
            "category":"Home & Garden",
            "subcategory":"Building Materials",
            "type":"Retail Goods"
        }
    ],
    "sg:phone":"+1 330 323 0963",
    "sg:postcode":"44720",
    "sg:province":"OH",
    "sg:tags":[
        "door"
    ],
    "wof:name":"Another Door Co",
    "wof:placetype":"venue"
},
  "geometry": {"coordinates":[-81.441857,40.880583],"type":"Point"}
}