{
  "type": "Feature",
  "properties": {
    "addr:full": "6121 S Union Rd Miamisburg OH 45342",
    "addr:housenumber": "6121",
    "addr:postcode": "45342",
    "addr:street": "S Union Rd",
    "iso:country": "US",
    "sg:address": "6121 S Union Rd",
    "sg:city": "Miamisburg",
    "sg:classifiers": [
      {
        "category": "Food \u0026 Beverages",
        "subcategory": "Meat \u0026 Fish",
        "type": "Retail Goods"
      }
    ],
    "sg:phone": "+1 937 866 3570",
    "sg:postcode": "45342",
    "sg:province": "OH",
    "wof:name": "Dale Zink Meats",
    "wof:placetype": "venue"
  },
  "geometry": {"coordinates":[-84.309128,39.655912],"type":"Point"}
}
