{
  "type": "Feature",
  "properties": {
    "iso:country":"US",
    "sg:address":"3250 Cleveland Ave NW",
    "sg:city":"Canton",
    "sg:classifiers":[
        {
            "category":"Shopping",
            "subcategory":"Discount & Variety Stores",
            "type":"Retail Goods"
        }
    ],
    "sg:phone":"+1 330 493 9187",
    "sg:postcode":"44709",
    "sg:province":"OH",
    "wof:name":"Dollar General",
    "wof:placetype":"venue"
},
  "geometry": {"coordinates":[-81.388822,40.834115],"type":"Point"}
}