{
  "type": "Feature",
  "properties": {
    "addr:full": "73 N 6th St Newark OH 43055",
    "addr:housenumber": "73",
    "addr:postcode": "43055",
    "addr:street": "N 6Th St",
    "iso:country": "US",
    "sg:address": "73 N 6th St",
    "sg:city": "Newark",
    "sg:classifiers": [
      {
        "category": "Professional",
        "type": "Services"
      }
    ],
    "sg:phone": "+1 740 328 8659",
    "sg:postcode": "43055",
    "sg:province": "OH",
    "sg:tags": [
      "establishment"
    ],
    "wof:name": "Family Connections",
    "wof:placetype": "venue"
  },
  "geometry": {"coordinates":[-82.409299,40.058545],"type":"Point"}
}
