{
  "type": "Feature",
  "properties": {
    "iso:country":"US",
    "sg:address":"73 N 6th St",
    "sg:city":"Newark",
    "sg:classifiers":[
        {
            "category":"Professional",
            "type":"Services"
        }
    ],
    "sg:phone":"+1 740 328 8659",
    "sg:postcode":"43055",
    "sg:province":"OH",
    "sg:tags":[
        "establishment"
    ],
    "wof:name":"Family Connections",
    "wof:placetype":"venue"
},
  "geometry": {"coordinates":[-82.409299,40.058545],"type":"Point"}
}