{
  "type": "Feature",
  "properties": {
    "addr:full": "136 E Findlay St Carey OH 43316",
    "addr:housenumber": "136",
    "addr:postcode": "43316",
    "addr:street": "E Findlay St",
    "iso:country": "US",
    "sg:address": "136 E Findlay St",
    "sg:city": "Carey",
    "sg:classifiers": [
      {
        "category": "Food \u0026 Beverages",
        "subcategory": "Groceries \u0026 Convenience Stores",
        "type": "Retail Goods"
      }
    ],
    "sg:phone": "+1 419 396 7607",
    "sg:postcode": "43316",
    "sg:province": "OH",
    "sg:tags": [
      "grocer"
    ],
    "wof:name": "Frederick Brothers Iga",
    "wof:placetype": "venue"
  },
  "geometry": {"coordinates":[-83.38147,40.952426],"type":"Point"}
}
