{
  "type": "Feature",
  "properties": {
    "addr:full": "7225 State Rte 674 S Stoutsville OH 43154",
    "addr:housenumber": "7225",
    "addr:postcode": "43154",
    "addr:street": "State Rte 674 S",
    "iso:country": "US",
    "sg:address": "7225 State Rte 674 S",
    "sg:city": "Stoutsville",
    "sg:classifiers": [
      {
        "category": "Freight",
        "type": "Transportation"
      }
    ],
    "sg:phone": "+1 740 477 7293",
    "sg:postcode": "43154",
    "sg:province": "OH",
    "sg:tags": [
      "storage"
    ],
    "wof:name": "County Line Storage",
    "wof:placetype": "venue"
  },
  "geometry": {"coordinates":[-82.836051,39.632501],"type":"Point"}
}
