{
  "type": "Feature",
  "properties": {
    "iso:country":"US",
    "sg:address":"5840 Troy Pike",
    "sg:city":"Dayton",
    "sg:classifiers":[
        {
            "category":"Personal",
            "subcategory":"Beauty Salon",
            "type":"Services"
        }
    ],
    "sg:phone":"+1 937 233 0900",
    "sg:postcode":"45424",
    "sg:province":"OH",
    "wof:name":"Mirror Images Designers & Hair",
    "wof:placetype":"venue"
},
  "geometry": {"coordinates":[-84.13995300000001,39.837942],"type":"Point"}
}