{
  "type": "Feature",
  "properties": {
    "addr:full": "5840 Troy Pike Dayton OH 45424",
    "addr:housenumber": "5840",
    "addr:postcode": "45424",
    "addr:street": "Troy Pike",
    "iso:country": "US",
    "sg:address": "5840 Troy Pike",
    "sg:city": "Dayton",
    "sg:classifiers": [
      {
        "category": "Personal",
        "subcategory": "Beauty Salon",
        "type": "Services"
      }
    ],
    "sg:phone": "+1 937 233 0900",
    "sg:postcode": "45424",
    "sg:province": "OH",
    "wof:name": "Mirror Images Designers \u0026 Hair",
    "wof:placetype": "venue"
  },
  "geometry": {"coordinates":[-84.139953,39.837942],"type":"Point"}
}
