{
  "type": "Feature",
  "properties": {
    "addr:full": "5455 Ridge Ln Cleveland OH 44139",
    "addr:housenumber": "5455",
    "addr:postcode": "44139",
    "addr:street": "Ridge Ln",
    "iso:country": "US",
    "sg:address": "5455 Ridge Ln",
    "sg:city": "Cleveland",
    "sg:classifiers": [
      {
        "category": "Professional",
        "subcategory": "Management \u0026 Consulting",
        "type": "Services"
      }
    ],
    "sg:phone": "+1 440 542 0999",
    "sg:postcode": "44139",
    "sg:province": "OH",
    "sg:tags": [
      "consultant",
      "business"
    ],
    "sg:website": "www.cfsp.com",
    "wof:name": "Council For Strategic Planning",
    "wof:placetype": "venue"
  },
  "geometry": {"coordinates":[-81.453981,41.410012],"type":"Point"}
}
