{
  "type": "Feature",
  "properties": {
    "addr:full": "6415 Angola Rd Holland OH 43528",
    "addr:housenumber": "6415",
    "addr:postcode": "43528",
    "addr:street": "Angola Rd",
    "iso:country": "US",
    "sg:address": "6415 Angola Rd",
    "sg:city": "Holland",
    "sg:classifiers": [
      {
        "category": "Retail",
        "subcategory": "Repair Shop",
        "type": "Services"
      }
    ],
    "sg:phone": "+1 419 868 1449",
    "sg:postcode": "43528",
    "sg:province": "OH",
    "sg:tags": [
      "related"
    ],
    "wof:name": "Hudson Automotive",
    "wof:placetype": "venue"
  },
  "geometry": {"coordinates":[-83.695901,41.624205],"type":"Point"}
}
