{
  "type": "Feature",
  "properties": {
    "addr:full": "25735 1st St Westlake OH 44145",
    "addr:housenumber": "25735",
    "addr:postcode": "44145",
    "addr:street": "1St St",
    "iso:country": "US",
    "sg:address": "25735 1st St",
    "sg:city": "Westlake",
    "sg:classifiers": [
      {
        "category": "Bars \u0026 Pubs",
        "subcategory": "Sports Bar",
        "type": "Food \u0026 Drink"
      },
      {
        "category": "Bars \u0026 Pubs",
        "type": "Food \u0026 Drink"
      },
      {
        "category": "Fast Food",
        "type": "Food \u0026 Drink"
      },
      {
        "category": "Restaurant",
        "type": "Food \u0026 Drink"
      },
      {
        "category": "Recreation",
        "subcategory": "Amusement Park",
        "type": "Entertainment"
      },
      {
        "category": "Bars \u0026 Pubs",
        "subcategory": "Lounge",
        "type": "Food \u0026 Drink"
      },
      {
        "category": "Personal",
        "type": "Services"
      },
      {
        "category": "Recreation",
        "subcategory": "Picnic Area",
        "type": "Entertainment"
      },
      {
        "category": "Retail",
        "subcategory": "Event Space",
        "type": "Services"
      }
    ],
    "sg:phone": "+1 440 249 0658",
    "sg:postcode": "44145",
    "sg:province": "OH",
    "sg:tags": [
      "style",
      "cocktail",
      "family",
      "facility",
      "arcade",
      "banquet",
      "american",
      "planning",
      "place",
      "take",
      "reception",
      "device",
      "party",
      "meeting",
      "hall",
      "pool"
    ],
    "sg:website": "http://cleveland.citysearch.com/profile/external/602901562/westlake_oh/dave_buster_s.html?publisher=yellowpages\u0026reference_id=1\u0026placement=ypwebsitemip",
    "wof:name": "Dave \u0026 Buster's",
    "wof:placetype": "venue"
  },
  "geometry": {"coordinates":[-81.903992,41.476213],"type":"Point"}
}
