{
  "type": "Feature",
  "properties": {
    "iso:country":"US",
    "sg:address":"25735 1st St",
    "sg:city":"Westlake",
    "sg:classifiers":[
        {
            "category":"Bars & Pubs",
            "subcategory":"Sports Bar",
            "type":"Food & Drink"
        },
        {
            "category":"Bars & Pubs",
            "type":"Food & Drink"
        },
        {
            "category":"Fast Food",
            "type":"Food & Drink"
        },
        {
            "category":"Restaurant",
            "type":"Food & Drink"
        },
        {
            "category":"Recreation",
            "subcategory":"Amusement Park",
            "type":"Entertainment"
        },
        {
            "category":"Bars & Pubs",
            "subcategory":"Lounge",
            "type":"Food & Drink"
        },
        {
            "category":"Personal",
            "type":"Services"
        },
        {
            "category":"Recreation",
            "subcategory":"Picnic Area",
            "type":"Entertainment"
        },
        {
            "category":"Retail",
            "subcategory":"Event Space",
            "type":"Services"
        }
    ],
    "sg:phone":"+1 440 249 0658",
    "sg:postcode":"44145",
    "sg:province":"OH",
    "sg:tags":[
        "style",
        "cocktail",
        "family",
        "facility",
        "arcade",
        "banquet",
        "american",
        "planning",
        "place",
        "take",
        "reception",
        "device",
        "party",
        "meeting",
        "hall",
        "pool"
    ],
    "sg:website":"http://cleveland.citysearch.com/profile/external/602901562/westlake_oh/dave_buster_s.html?publisher=yellowpages&reference_id=1&placement=ypwebsitemip",
    "wof:name":"Dave & Buster's",
    "wof:placetype":"venue"
},
  "geometry": {"coordinates":[-81.903992,41.476213],"type":"Point"}
}