{
  "type": "Feature",
  "properties": {
    "iso:country":"US",
    "sg:address":"5276 State Rte 197",
    "sg:city":"Spencerville",
    "sg:classifiers":[
        {
            "category":"Wholesale",
            "subcategory":"Farm Supplies",
            "type":"Manufacturing & Wholesale Goods"
        },
        {
            "category":"Manufacturing",
            "subcategory":"Chemicals & Compounds",
            "type":"Manufacturing & Wholesale Goods"
        }
    ],
    "sg:phone":"+1 419 657 6788",
    "sg:postcode":"45887",
    "sg:province":"OH",
    "sg:tags":[
        "fertilizer",
        "grain",
        "elevator"
    ],
    "wof:name":"United Equity Inc",
    "wof:placetype":"venue"
},
  "geometry": {"coordinates":[-84.35164,40.657892],"type":"Point"}
}