{
  "type": "Feature",
  "properties": {
    "iso:country":"US",
    "sg:address":"2000 Sycamore St",
    "sg:city":"Cleveland",
    "sg:classifiers":[
        {
            "category":"Bars & Pubs",
            "type":"Food & Drink"
        }
    ],
    "sg:phone":"+1 216 861 4982",
    "sg:postcode":"44113",
    "sg:province":"OH",
    "wof:name":"Powerhouse Pub",
    "wof:placetype":"venue"
},
  "geometry": {"coordinates":[-81.70638700000001,41.496753],"type":"Point"}
}