{
  "type": "Feature",
  "properties": {
    "addr:full": "1417 Youngstown Rd SE Warren OH 44484",
    "addr:housenumber": "1417",
    "addr:postcode": "44484",
    "addr:street": "Youngstown Rd Se",
    "iso:country": "US",
    "sg:address": "1417 Youngstown Rd SE",
    "sg:city": "Warren",
    "sg:classifiers": [
      {
        "category": "Shopping",
        "subcategory": "Gifts \u0026 Souvenirs",
        "type": "Retail Goods"
      }
    ],
    "sg:phone": "+1 330 393 8888",
    "sg:postcode": "44484",
    "sg:province": "OH",
    "sg:tags": [
      "party",
      "supply"
    ],
    "wof:name": "Nannicola Wholesale Co",
    "wof:placetype": "venue"
  },
  "geometry": {"coordinates":[-80.799311,41.229041],"type":"Point"}
}
