{
  "type": "Feature",
  "properties": {
    "addr:full": "1490 Southridge Ln Cincinnati OH 45231",
    "addr:housenumber": "1490",
    "addr:postcode": "45231",
    "addr:street": "Southridge Ln",
    "iso:country": "US",
    "sg:address": "1490 Southridge Ln",
    "sg:city": "Cincinnati",
    "sg:classifiers": [
      {
        "category": "Health Services",
        "subcategory": "Hospital",
        "type": "Services"
      }
    ],
    "sg:phone": "+1 513 931 9276",
    "sg:postcode": "45231",
    "sg:province": "OH",
    "sg:tags": [
      "mental"
    ],
    "wof:name": "Warmline",
    "wof:placetype": "venue"
  },
  "geometry": {"coordinates":[-84.543643,39.221708],"type":"Point"}
}
