{
  "type": "Feature",
  "properties": {
    "iso:country":"US",
    "sg:address":"3343 Midway Mall",
    "sg:city":"Elyria",
    "sg:classifiers":[
        {
            "category":"Wholesale",
            "subcategory":"Meat",
            "type":"Manufacturing & Wholesale Goods"
        }
    ],
    "sg:phone":"+1 440 324 3851",
    "sg:postcode":"44035",
    "sg:province":"OH",
    "wof:name":"Hickory Farms 12630",
    "wof:placetype":"venue"
},
  "geometry": {"coordinates":[-82.112294,41.398622],"type":"Point"}
}