{
  "type": "Feature",
  "properties": {
    "addr:full": "3343 Midway Mall Elyria OH 44035",
    "addr:housenumber": "3343",
    "addr:postcode": "44035",
    "addr:street": "Midway Mall",
    "iso:country": "US",
    "sg:address": "3343 Midway Mall",
    "sg:city": "Elyria",
    "sg:classifiers": [
      {
        "category": "Wholesale",
        "subcategory": "Meat",
        "type": "Manufacturing \u0026 Wholesale Goods"
      }
    ],
    "sg:phone": "+1 440 324 3851",
    "sg:postcode": "44035",
    "sg:province": "OH",
    "wof:name": "Hickory Farms 12630",
    "wof:placetype": "venue"
  },
  "geometry": {"coordinates":[-82.112294,41.398622],"type":"Point"}
}
