{
  "type": "Feature",
  "properties": {
    "iso:country":"US",
    "sg:address":"21 W Church St",
    "sg:city":"Newark",
    "sg:classifiers":[
        {
            "category":"Professional",
            "subcategory":"Lawyer & Legal Services",
            "type":"Services"
        }
    ],
    "sg:phone":"+1 740 345 6667",
    "sg:postcode":"43055",
    "sg:province":"OH",
    "sg:tags":[
        "attorney"
    ],
    "wof:name":"Wright Law Offices",
    "wof:placetype":"venue"
},
  "geometry": {"coordinates":[-82.404894,40.058642],"type":"Point"}
}