{
  "type": "Feature",
  "properties": {
    "addr:full": "480 W Tuscarawas Ave Barberton OH 44203",
    "addr:housenumber": "480",
    "addr:postcode": "44203",
    "addr:street": "W Tuscarawas Ave",
    "iso:country": "US",
    "sg:address": "480 W Tuscarawas Ave",
    "sg:city": "Barberton",
    "sg:classifiers": [
      {
        "category": "Insurance",
        "subcategory": "Insurance Agent",
        "type": "Services"
      }
    ],
    "sg:phone": "+1 330 861 5225",
    "sg:postcode": "44203",
    "sg:province": "OH",
    "sg:tags": [
      "accident"
    ],
    "wof:name": "Professional Benefit Strategie",
    "wof:placetype": "venue"
  },
  "geometry": {"coordinates":[-81.607005,41.012751],"type":"Point"}
}
