{
  "type": "Feature",
  "properties": {
    "addr:full":"725 Horning Rd Atwater OH 44201",
    "addr:housenumber":"725",
    "addr:postcode":"44201",
    "addr:street":"Horning Rd",
    "iso:country":"US",
    "sg:address":"725 Horning Rd",
    "sg:city":"Atwater",
    "sg:classifiers":[
        {
            "category":"Wholesale",
            "subcategory":"Machinery & Supplies",
            "type":"Manufacturing & Wholesale Goods"
        }
    ],
    "sg:phone":"+1 330 947 2345",
    "sg:postcode":"44201",
    "sg:province":"OH",
    "sg:tags":[
        "equipment",
        "establishment",
        "laying",
        "floor"
    ],
    "wof:name":"Kolasky Flooring",
    "wof:placetype":"venue"
},
  "geometry": {"coordinates":[-81.234465,41.007317],"type":"Point"}
}