{
  "type": "Feature",
  "properties": {
    "addr:full": "7450 E Snyder Rd Fletcher OH 45317",
    "addr:housenumber": "7450",
    "addr:postcode": "45317",
    "addr:street": "E Snyder Rd",
    "iso:country": "US",
    "sg:address": "7450 E Snyder Rd",
    "sg:city": "Fletcher",
    "sg:classifiers": [
      {
        "category": "Shopping",
        "subcategory": "Clothing, Apparel, \u0026 Fashions",
        "type": "Retail Goods"
      }
    ],
    "sg:phone": "+1 937 368 2642",
    "sg:postcode": "45317",
    "sg:province": "OH",
    "wof:name": "Rainbow Outfitters",
    "wof:placetype": "venue"
  },
  "geometry": {"coordinates":[-84.046074,40.15584],"type":"Point"}
}
