{
  "type": "Feature",
  "properties": {
    "addr:full":"6192 Warren Rd Cortland OH 44410",
    "addr:housenumber":"6192",
    "addr:postcode":"44410",
    "addr:street":"Warren Rd",
    "iso:country":"US",
    "sg:address":"6192 Warren Rd",
    "sg:city":"Cortland",
    "sg:classifiers":[
        {
            "category":"Wholesale",
            "subcategory":"Machinery & Supplies",
            "type":"Manufacturing & Wholesale Goods"
        }
    ],
    "sg:phone":"+1 330 924 2555",
    "sg:postcode":"44410",
    "sg:province":"OH",
    "sg:tags":[
        "farm",
        "equipment"
    ],
    "wof:name":"Cortland Tractor Sales Co",
    "wof:placetype":"venue"
},
  "geometry": {"coordinates":[-80.694163,41.372844],"type":"Point"}
}