{
  "type": "Feature",
  "properties": {
    "iso:country":"US",
    "sg:address":"5996 Lewisburg Rd",
    "sg:city":"Lewisburg",
    "sg:phone":"+1 937 962 4171",
    "sg:postcode":"45338",
    "sg:province":"OH",
    "sg:tags":[
        "farm",
        "corn"
    ],
    "wof:name":"William Riffel",
    "wof:placetype":"venue"
},
  "geometry": {"coordinates":[-84.502636,39.830194],"type":"Point"}
}