{
  "type": "Feature",
  "properties": {
    "addr:full": "5625 Squires Gate Dr Mason OH 45040",
    "addr:housenumber": "5625",
    "addr:postcode": "45040",
    "addr:street": "Squires Gate Dr",
    "iso:country": "US",
    "sg:address": "5625 Squires Gate Dr",
    "sg:city": "Mason",
    "sg:classifiers": [
      {
        "category": "Food \u0026 Beverages",
        "subcategory": "Groceries \u0026 Convenience Stores",
        "type": "Retail Goods"
      }
    ],
    "sg:phone": "+1 513 398 2742",
    "sg:postcode": "45040",
    "sg:province": "OH",
    "wof:name": "Jn Food \u0026 Beverage Corp",
    "wof:placetype": "venue"
  },
  "geometry": {"coordinates":[-84.325547,39.30377],"type":"Point"}
}
