{
  "type": "Feature",
  "properties": {
    "iso:country":"US",
    "sg:address":"5625 Squires Gate Dr",
    "sg:city":"Mason",
    "sg:classifiers":[
        {
            "category":"Food & Beverages",
            "subcategory":"Groceries & Convenience Stores",
            "type":"Retail Goods"
        }
    ],
    "sg:phone":"+1 513 398 2742",
    "sg:postcode":"45040",
    "sg:province":"OH",
    "wof:name":"Jn Food & Beverage Corp",
    "wof:placetype":"venue"
},
  "geometry": {"coordinates":[-84.325547,39.30377],"type":"Point"}
}