{
  "type": "Feature",
  "properties": {
    "addr:full": "109 Park Ave Amherst OH 44001",
    "addr:housenumber": "109",
    "addr:postcode": "44001",
    "addr:street": "Park Ave",
    "iso:country": "US",
    "sg:address": "109 Park Ave",
    "sg:city": "Amherst",
    "sg:classifiers": [
      {
        "category": "Shopping",
        "subcategory": "Books",
        "type": "Retail Goods"
      }
    ],
    "sg:phone": "+1 440 988 8400",
    "sg:postcode": "44001",
    "sg:province": "OH",
    "wof:name": "Three Crosses",
    "wof:placetype": "venue"
  },
  "geometry": {"coordinates":[-82.225158,41.398431],"type":"Point"}
}
