{
  "type": "Feature",
  "properties": {
    "iso:country":"US",
    "sg:address":"109 Park Ave",
    "sg:city":"Amherst",
    "sg:classifiers":[
        {
            "category":"Shopping",
            "subcategory":"Books",
            "type":"Retail Goods"
        }
    ],
    "sg:phone":"+1 440 988 8400",
    "sg:postcode":"44001",
    "sg:province":"OH",
    "wof:name":"Three Crosses",
    "wof:placetype":"venue"
},
  "geometry": {"coordinates":[-82.22515799999999,41.398431],"type":"Point"}
}