{
  "type": "Feature",
  "properties": {
    "addr:full": "230 E Sharon Rd Cincinnati OH 45246",
    "addr:housenumber": "230",
    "addr:postcode": "45246",
    "addr:street": "E Sharon Rd",
    "iso:country": "US",
    "sg:address": "230 E Sharon Rd",
    "sg:city": "Cincinnati",
    "sg:classifiers": [
      {
        "category": "Personal",
        "subcategory": "Beauty Salon",
        "type": "Services"
      }
    ],
    "sg:phone": "+1 513 771 0852",
    "sg:postcode": "45246",
    "sg:province": "OH",
    "wof:name": "Glendale Salon",
    "wof:placetype": "venue"
  },
  "geometry": {"coordinates":[-84.459211,39.272206],"type":"Point"}
}
