{
  "type": "Feature",
  "properties": {
    "addr:full": "1717 Krieger St Columbus OH 43228",
    "addr:housenumber": "1717",
    "addr:postcode": "43228",
    "addr:street": "Krieger St",
    "iso:country": "US",
    "sg:address": "1717 Krieger St",
    "sg:city": "Columbus",
    "sg:classifiers": [
      {
        "category": "Building \u0026 Trades",
        "subcategory": "Equipment Rental",
        "type": "Services"
      }
    ],
    "sg:phone": "+1 614 870 1022",
    "sg:postcode": "43228",
    "sg:province": "OH",
    "sg:tags": [
      "leasing"
    ],
    "sg:website": "www.connectionco.com",
    "wof:name": "Long Leasing Inc",
    "wof:placetype": "venue"
  },
  "geometry": {"coordinates":[-83.135213,39.918515],"type":"Point"}
}
