{
  "type": "Feature",
  "properties": {
    "addr:full": "10804 Union Ave Cleveland OH 44105",
    "addr:housenumber": "10804",
    "addr:postcode": "44105",
    "addr:street": "Union Ave",
    "iso:country": "US",
    "sg:address": "10804 Union Ave",
    "sg:city": "Cleveland",
    "sg:classifiers": [
      {
        "category": "Organizations",
        "subcategory": "Religious Organization",
        "type": "Services"
      }
    ],
    "sg:phone": "+1 216 883 5540",
    "sg:postcode": "44105",
    "sg:province": "OH",
    "sg:tags": [
      "church"
    ],
    "wof:name": "Faith Temple Baptist Church",
    "wof:placetype": "venue"
  },
  "geometry": {"coordinates":[-81.608435,41.463537],"type":"Point"}
}
