{
  "type": "Feature",
  "properties": {
    "iso:country":"US",
    "sg:address":"2641 Co Rd 169",
    "sg:city":"Cardington",
    "sg:phone":"+1 419 864 6191",
    "sg:postcode":"43315",
    "sg:province":"OH",
    "sg:tags":[
        "farm",
        "corn",
        "wheat",
        "soybean"
    ],
    "wof:name":"Jim & Mar Farm",
    "wof:placetype":"venue"
},
  "geometry": {"coordinates":[-82.870677,40.463439],"type":"Point"}
}