{
  "type": "Feature",
  "properties": {
    "addr:full": "2305 E Aurora Rd Twinsburg OH 44087",
    "addr:housenumber": "2305",
    "addr:postcode": "44087",
    "addr:street": "E Aurora Rd",
    "iso:country": "US",
    "sg:address": "2305 E Aurora Rd",
    "sg:city": "Twinsburg",
    "sg:classifiers": [
      {
        "category": "Wholesale",
        "subcategory": "Stationery",
        "type": "Manufacturing \u0026 Wholesale Goods"
      }
    ],
    "sg:phone": "+1 330 425 8484",
    "sg:postcode": "44087",
    "sg:province": "OH",
    "sg:tags": [
      "business",
      "form",
      "system"
    ],
    "wof:name": "System One Inc",
    "wof:placetype": "venue"
  },
  "geometry": {"coordinates":[-81.457752,41.311403],"type":"Point"}
}
