{
  "type": "Feature",
  "properties": {
    "addr:full":"13385 Ludwig Rd Grand Rapids OH 43522",
    "addr:housenumber":"13385",
    "addr:postcode":"43522",
    "addr:street":"Ludwig Rd",
    "iso:country":"US",
    "sg:address":"13385 Ludwig Rd",
    "sg:city":"Grand Rapids",
    "sg:classifiers":[
        {
            "category":"Freight",
            "type":"Transportation"
        }
    ],
    "sg:phone":"+1 419 832 4931",
    "sg:postcode":"43522",
    "sg:province":"OH",
    "sg:tags":[
        "grain",
        "elevator"
    ],
    "wof:name":"Northern Ohio Grain Co-Op Inc",
    "wof:placetype":"venue"
},
  "geometry": {"coordinates":[-83.86057099999999,41.420065],"type":"Point"}
}