{
  "type": "Feature",
  "properties": {
    "iso:country":"US",
    "sg:address":"148 Gross St",
    "sg:city":"Marietta",
    "sg:classifiers":[
        {
            "category":"Government",
            "subcategory":"Office",
            "type":"Public Place"
        }
    ],
    "sg:phone":"+1 740 373 3679",
    "sg:postcode":"45750",
    "sg:province":"OH",
    "sg:tags":[
        "state",
        "program"
    ],
    "wof:name":"Patrol Drivers Examination",
    "wof:placetype":"venue"
},
  "geometry": {"coordinates":[-81.447593,39.421117],"type":"Point"}
}