{
  "type": "Feature",
  "properties": {
    "addr:full": "516 Central Ave Greenville OH 45331",
    "addr:housenumber": "516",
    "addr:postcode": "45331",
    "addr:street": "Central Ave",
    "iso:country": "US",
    "sg:address": "516 Central Ave",
    "sg:city": "Greenville",
    "sg:classifiers": [
      {
        "category": "Manufacturing",
        "subcategory": "Signs",
        "type": "Manufacturing \u0026 Wholesale Goods"
      }
    ],
    "sg:phone": "+1 937 548 1893",
    "sg:postcode": "45331",
    "sg:province": "OH",
    "sg:tags": [
      "advertising",
      "specialty"
    ],
    "wof:name": "Kings' Glory Signs \u0026 Murals",
    "wof:placetype": "venue"
  },
  "geometry": {"coordinates":[-84.634111,40.094408],"type":"Point"}
}
