{
  "type": "Feature",
  "properties": {
    "addr:full": "85 Gay St Jackson OH 45640",
    "addr:housenumber": "85",
    "addr:postcode": "45640",
    "addr:street": "Gay St",
    "iso:country": "US",
    "sg:address": "85 Gay St",
    "sg:city": "Jackson",
    "sg:classifiers": [
      {
        "category": "Banks \u0026 Credit Unions",
        "subcategory": "Bank",
        "type": "Services"
      }
    ],
    "sg:phone": "+1 740 286 6061",
    "sg:postcode": "45640",
    "sg:province": "OH",
    "sg:tags": [
      "federally",
      "chartered"
    ],
    "wof:name": "Jcs Employees Federal Cu",
    "wof:placetype": "venue"
  },
  "geometry": {"coordinates":[-82.633344,39.046827],"type":"Point"}
}
