{
  "type": "Feature",
  "properties": {
    "iso:country":"US",
    "sg:address":"85 Gay St",
    "sg:city":"Jackson",
    "sg:classifiers":[
        {
            "category":"Banks & Credit Unions",
            "subcategory":"Bank",
            "type":"Services"
        }
    ],
    "sg:phone":"+1 740 286 6061",
    "sg:postcode":"45640",
    "sg:province":"OH",
    "sg:tags":[
        "federally",
        "chartered"
    ],
    "wof:name":"Jcs Employees Federal Cu",
    "wof:placetype":"venue"
},
  "geometry": {"coordinates":[-82.63334399999999,39.046827],"type":"Point"}
}