{
  "type": "Feature",
  "properties": {
    "addr:full":"13421 Hawke Rd Columbia Station OH 44028",
    "addr:postcode":"13421;44028",
    "addr:street":"Hawke Rd",
    "iso:country":"US",
    "sg:address":"13421 Hawke Rd",
    "sg:city":"Columbia Station",
    "sg:classifiers":[
        {
            "category":"Utilities",
            "subcategory":"Refuse",
            "type":"Services"
        }
    ],
    "sg:phone":"+1 440 236 8777",
    "sg:postcode":"44028",
    "sg:province":"OH",
    "sg:tags":[
        "system"
    ],
    "wof:name":"Gateway Recycling Products",
    "wof:placetype":"venue"
},
  "geometry": {"coordinates":[-81.97167,41.316454],"type":"Point"}
}