{
  "type": "Feature",
  "properties": {
    "addr:full":"1526 Gulf Rd Elyria OH 44035",
    "addr:housenumber":"1526",
    "addr:postcode":"44035",
    "addr:street":"Gulf Rd",
    "iso:country":"US",
    "sg:address":"1526 Gulf Rd",
    "sg:city":"Elyria",
    "sg:classifiers":[
        {
            "category":"Manufacturing",
            "subcategory":"Metals",
            "type":"Manufacturing & Wholesale Goods"
        }
    ],
    "sg:phone":"+1 440 327 0922",
    "sg:postcode":"44035",
    "sg:province":"OH",
    "sg:tags":[
        "building",
        "prefabricated",
        "mfg"
    ],
    "wof:name":"Plant Factory Inc",
    "wof:placetype":"venue"
},
  "geometry": {"coordinates":[-82.088973,41.413274],"type":"Point"}
}