{
  "type": "Feature",
  "properties": {
    "iso:country":"US",
    "sg:address":"842 E 79th St",
    "sg:city":"Cleveland",
    "sg:classifiers":[
        {
            "category":"Shopping",
            "subcategory":"Discount & Variety Stores",
            "type":"Retail Goods"
        }
    ],
    "sg:phone":"+1 216 431 6918",
    "sg:postcode":"44103",
    "sg:province":"OH",
    "wof:name":"Triple Play",
    "wof:placetype":"venue"
},
  "geometry": {"coordinates":[-81.633329,41.533162],"type":"Point"}
}