{
  "type": "Feature",
  "properties": {
    "addr:full": "1571 E 361st St Willoughby OH 44095",
    "addr:housenumber": "1571",
    "addr:postcode": "44095",
    "addr:street": "E 361St St",
    "iso:country": "US",
    "sg:address": "1571 E 361st St",
    "sg:city": "Willoughby",
    "sg:classifiers": [
      {
        "category": "Manufacturing",
        "subcategory": "Apparel",
        "type": "Manufacturing \u0026 Wholesale Goods"
      }
    ],
    "sg:phone": "+1 440 953 9095",
    "sg:postcode": "44095",
    "sg:province": "OH",
    "sg:tags": [
      "product",
      "mfg"
    ],
    "wof:name": "Hoidt Night",
    "wof:placetype": "venue"
  },
  "geometry": {"coordinates":[-81.43084,41.636525],"type":"Point"}
}
