{
  "type": "Feature",
  "properties": {
    "addr:full": "4461 Spratt Rd Cumberland OH 43732",
    "addr:housenumber": "4461",
    "addr:postcode": "43732",
    "addr:street": "Spratt Rd",
    "iso:country": "US",
    "sg:address": "4461 Spratt Rd",
    "sg:city": "Cumberland",
    "sg:classifiers": [
      {
        "category": "Farming",
        "subcategory": "Livestock Farm",
        "type": "Manufacturing \u0026 Wholesale Goods"
      }
    ],
    "sg:phone": "+1 740 638 5603",
    "sg:postcode": "43732",
    "sg:province": "OH",
    "sg:tags": [
      "beef",
      "feedlot",
      "cattle"
    ],
    "wof:name": "West End Cattle Company",
    "wof:placetype": "venue"
  },
  "geometry": {"coordinates":[-81.670417,39.848702],"type":"Point"}
}
