{
  "type": "Feature",
  "properties": {
    "iso:country":"US",
    "sg:address":"4461 Spratt Rd",
    "sg:city":"Cumberland",
    "sg:classifiers":[
        {
            "category":"Farming",
            "subcategory":"Livestock Farm",
            "type":"Manufacturing & Wholesale Goods"
        }
    ],
    "sg:phone":"+1 740 638 5603",
    "sg:postcode":"43732",
    "sg:province":"OH",
    "sg:tags":[
        "beef",
        "feedlot",
        "cattle"
    ],
    "wof:name":"West End Cattle Company",
    "wof:placetype":"venue"
},
  "geometry": {"coordinates":[-81.670417,39.848702],"type":"Point"}
}