{
  "type": "Feature",
  "properties": {
    "iso:country":"US",
    "sg:address":"26488 Dixie Hwy",
    "sg:city":"Perrysburg",
    "sg:classifiers":[
        {
            "category":"Food & Beverages",
            "subcategory":"Groceries & Convenience Stores",
            "type":"Retail Goods"
        }
    ],
    "sg:phone":"+1 419 874 3598",
    "sg:postcode":"43551",
    "sg:province":"OH",
    "wof:name":"Sterling Stores",
    "wof:placetype":"venue"
},
  "geometry": {"coordinates":[-83.635217,41.536076],"type":"Point"}
}