{
  "type": "Feature",
  "properties": {
    "addr:full": "26488 Dixie Hwy Perrysburg OH 43551",
    "addr:housenumber": "26488",
    "addr:postcode": "43551",
    "addr:street": "Dixie Hwy",
    "iso:country": "US",
    "sg:address": "26488 Dixie Hwy",
    "sg:city": "Perrysburg",
    "sg:classifiers": [
      {
        "category": "Food \u0026 Beverages",
        "subcategory": "Groceries \u0026 Convenience Stores",
        "type": "Retail Goods"
      }
    ],
    "sg:phone": "+1 419 874 3598",
    "sg:postcode": "43551",
    "sg:province": "OH",
    "wof:name": "Sterling Stores",
    "wof:placetype": "venue"
  },
  "geometry": {"coordinates":[-83.635217,41.536076],"type":"Point"}
}
