{
  "type": "Feature",
  "properties": {
    "addr:full":"144 Northcrest Dr Marysville OH 43040",
    "addr:housenumber":"144",
    "addr:postcode":"43040",
    "addr:street":"Northcrest Dr",
    "iso:country":"US",
    "sg:address":"144 Northcrest Dr",
    "sg:city":"Marysville",
    "sg:classifiers":[
        {
            "category":"Shopping",
            "subcategory":"Hobbies, Toys, & Games",
            "type":"Retail Goods"
        }
    ],
    "sg:phone":"+1 937 642 0809",
    "sg:postcode":"43040",
    "sg:province":"OH",
    "wof:name":"Tamis Pins & Needles",
    "wof:placetype":"venue"
},
  "geometry": {"coordinates":[-83.315744,40.214433],"type":"Point"}
}