{
  "type": "Feature",
  "properties": {
    "addr:full": "2855 Nichols Ridge Rd Seaman OH 45679",
    "addr:housenumber": "2855",
    "addr:postcode": "45679",
    "addr:street": "Nichols Ridge Rd",
    "iso:country": "US",
    "sg:address": "2855 Nichols Ridge Rd",
    "sg:city": "Seaman",
    "sg:phone": "+1 937 386 2251",
    "sg:postcode": "45679",
    "sg:province": "OH",
    "sg:tags": [
      "wheat",
      "beef",
      "farm",
      "corn",
      "soybean",
      "cattle"
    ],
    "wof:name": "Chris Baxla",
    "wof:placetype": "venue"
  },
  "geometry": {"coordinates":[-83.498859,38.939342],"type":"Point"}
}
