{
  "type": "Feature",
  "properties": {
    "iso:country":"US",
    "sg:address":"6009 Lander Haven Dr",
    "sg:city":"Cleveland",
    "sg:classifiers":[
        {
            "category":"Insurance",
            "subcategory":"Insurance Agent",
            "type":"Services"
        }
    ],
    "sg:phone":"+1 440 646 1202",
    "sg:postcode":"44124",
    "sg:province":"OH",
    "wof:name":"Mormile Agency",
    "wof:placetype":"venue"
},
  "geometry": {"coordinates":[-81.45376400000001,41.503331],"type":"Point"}
}