{
  "type": "Feature",
  "properties": {
    "addr:full": "1075 S 30th St Heath OH 43056",
    "addr:housenumber": "1075",
    "addr:postcode": "43056",
    "addr:street": "S 30Th St",
    "iso:country": "US",
    "sg:address": "1075 S 30th St",
    "sg:city": "Heath",
    "sg:classifiers": [
      {
        "category": "Organizations",
        "subcategory": "Religious Organization",
        "type": "Services"
      }
    ],
    "sg:phone": "+1 740 522 1717",
    "sg:postcode": "43056",
    "sg:province": "OH",
    "sg:tags": [
      "church"
    ],
    "sg:website": "www.southgatechurchofchrist.org",
    "wof:name": "Church Of Christ",
    "wof:placetype": "venue"
  },
  "geometry": {"coordinates":[-82.44465,40.022949],"type":"Point"}
}
