{
  "type": "Feature",
  "properties": {
    "iso:country":"US",
    "sg:address":"1008 Fremont Ave",
    "sg:city":"Findlay",
    "sg:classifiers":[
        {
            "category":"Building & Trades",
            "subcategory":"Plumbing",
            "type":"Services"
        }
    ],
    "sg:phone":"+1 419 422 9393",
    "sg:postcode":"45840",
    "sg:province":"OH",
    "sg:tags":[
        "plumbing",
        "contractor"
    ],
    "wof:name":"Marshall and Son",
    "wof:placetype":"venue"
},
  "geometry": {"coordinates":[-83.63651,41.028958],"type":"Point"}
}