{
  "type": "Feature",
  "properties": {
    "iso:country":"US",
    "sg:address":"601 Market St",
    "sg:city":"Richmond Dale",
    "sg:classifiers":[
        {
            "category":"Organizations",
            "subcategory":"Religious Organization",
            "type":"Services"
        }
    ],
    "sg:phone":"+1 740 884 4698",
    "sg:postcode":"45673",
    "sg:province":"OH",
    "sg:tags":[
        "church"
    ],
    "wof:name":"New Life Church Of Christ",
    "wof:placetype":"venue"
},
  "geometry": {"coordinates":[-82.811055,39.207442],"type":"Point"}
}