{
  "type": "Feature",
  "properties": {
    "iso:country":"US",
    "sg:address":"5561 Hoover Ave",
    "sg:city":"Dayton",
    "sg:classifiers":[
        {
            "category":"Organizations",
            "subcategory":"Religious Organization",
            "type":"Services"
        }
    ],
    "sg:phone":"+1 937 263 9591",
    "sg:postcode":"45427",
    "sg:province":"OH",
    "sg:tags":[
        "church"
    ],
    "wof:name":"Ebenezer Baptist Church",
    "wof:placetype":"venue"
},
  "geometry": {"coordinates":[-84.28376799999999,39.76138],"type":"Point"}
}