{
  "type": "Feature",
  "properties": {
    "iso:country":"US",
    "sg:address":"10875 Yankee St",
    "sg:city":"Dayton",
    "sg:classifiers":[
        {
            "category":"Professional",
            "subcategory":"Accounting & Tax Preparation",
            "type":"Services"
        }
    ],
    "sg:phone":"+1 937 885 5838",
    "sg:postcode":"45458",
    "sg:province":"OH",
    "sg:tags":[
        "return",
        "filing"
    ],
    "wof:name":"E-File Direct",
    "wof:placetype":"venue"
},
  "geometry": {"coordinates":[-84.20135000000001,39.58538],"type":"Point"}
}