{
  "type": "Feature",
  "properties": {
    "addr:full": "6239 N McMaken Rd Covington OH 45318",
    "addr:housenumber": "6239",
    "addr:postcode": "45318",
    "addr:street": "N Mcmaken Rd",
    "iso:country": "US",
    "sg:address": "6239 N McMaken Rd",
    "sg:city": "Covington",
    "sg:classifiers": [
      {
        "category": "Building \u0026 Trades",
        "subcategory": "Plumbing",
        "type": "Services"
      }
    ],
    "sg:phone": "+1 937 473 3311",
    "sg:postcode": "45318",
    "sg:province": "OH",
    "sg:tags": [
      "plumbing",
      "contractor"
    ],
    "wof:name": "Covington Plumbing Inc",
    "wof:placetype": "venue"
  },
  "geometry": {"coordinates":[-84.336051,40.135836],"type":"Point"}
}
