{
  "type": "Feature",
  "properties": {
    "iso:country":"US",
    "sg:address":"6239 N McMaken Rd",
    "sg:city":"Covington",
    "sg:classifiers":[
        {
            "category":"Building & Trades",
            "subcategory":"Plumbing",
            "type":"Services"
        }
    ],
    "sg:phone":"+1 937 473 3311",
    "sg:postcode":"45318",
    "sg:province":"OH",
    "sg:tags":[
        "plumbing",
        "contractor"
    ],
    "wof:name":"Covington Plumbing Inc",
    "wof:placetype":"venue"
},
  "geometry": {"coordinates":[-84.336051,40.135836],"type":"Point"}
}