{
  "type": "Feature",
  "properties": {
    "iso:country":"US",
    "sg:address":"949 Sharon Valley Rd",
    "sg:city":"Newark",
    "sg:classifiers":[
        {
            "category":"Recreation",
            "type":"Entertainment"
        }
    ],
    "sg:phone":"+1 740 366 3254",
    "sg:postcode":"43055",
    "sg:province":"OH",
    "sg:tags":[
        "club",
        "baseball"
    ],
    "wof:name":"North Newark Little League",
    "wof:placetype":"venue"
},
  "geometry": {"coordinates":[-82.436362,40.071216],"type":"Point"}
}