{
  "type": "Feature",
  "properties": {
    "addr:full": "830 N Mantua St Kent OH 44240",
    "addr:housenumber": "830",
    "addr:postcode": "44240",
    "addr:street": "N Mantua St",
    "iso:country": "US",
    "sg:address": "830 N Mantua St",
    "sg:city": "Kent",
    "sg:classifiers": [
      {
        "category": "Shopping",
        "subcategory": "Computers \u0026 Home Electronics",
        "type": "Retail Goods"
      }
    ],
    "sg:phone": "+1 330 676 9790",
    "sg:postcode": "44240",
    "sg:province": "OH",
    "wof:name": "Rim \u0026 Trim",
    "wof:placetype": "venue"
  },
  "geometry": {"coordinates":[-81.358813,41.160691],"type":"Point"}
}
