{
  "type": "Feature",
  "properties": {
    "addr:full":"140 Mansfield Industrial Pkwy Mansfield OH 44903",
    "addr:housenumber":"140",
    "addr:postcode":"44903",
    "addr:street":"Mansfield Industrial Pkwy",
    "iso:country":"US",
    "sg:address":"140 Mansfield Industrial Pkwy",
    "sg:city":"Mansfield",
    "sg:classifiers":[
        {
            "category":"Professional",
            "type":"Services"
        }
    ],
    "sg:phone":"+1 419 522 0091",
    "sg:postcode":"44903",
    "sg:province":"OH",
    "wof:name":"Enman",
    "wof:placetype":"venue"
},
  "geometry": {"coordinates":[-82.50923400000001,40.802945],"type":"Point"}
}