{
  "type": "Feature",
  "properties": {
    "addr:full": "130 S Main St Fredericktown OH 43019",
    "addr:housenumber": "130",
    "addr:postcode": "43019",
    "addr:street": "S Main St",
    "iso:country": "US",
    "sg:address": "130 S Main St",
    "sg:city": "Fredericktown",
    "sg:classifiers": [
      {
        "category": "Restaurant",
        "type": "Food \u0026 Drink"
      }
    ],
    "sg:menulink": "http://www.allmenus.com/oh/fredericktown/134109-subway/menu/",
    "sg:phone": "+1 740 694 7777",
    "sg:postcode": "43019",
    "sg:province": "OH",
    "sg:tags": [
      "american",
      "sandwich"
    ],
    "wof:name": "Subway",
    "wof:placetype": "venue"
  },
  "geometry": {"coordinates":[-82.541005,40.474964],"type":"Point"}
}
