{
  "type": "Feature",
  "properties": {
    "addr:full":"9979 State Rte 41 Greenfield OH 45123",
    "addr:housenumber":"9979",
    "addr:postcode":"45123",
    "addr:street":"State Rte 41",
    "iso:country":"US",
    "sg:address":"9979 State Rte 41",
    "sg:city":"Greenfield",
    "sg:phone":"+1 937 981 3100",
    "sg:postcode":"45123",
    "sg:province":"OH",
    "sg:tags":[
        "farm",
        "corn"
    ],
    "wof:name":"Clifford Royce",
    "wof:placetype":"venue"
},
  "geometry": {"coordinates":[-83.392426,39.400616],"type":"Point"}
}