{
  "type": "Feature",
  "properties": {
    "addr:full":"836 Refugee Rd Pickerington OH 43147",
    "addr:housenumber":"836",
    "addr:postcode":"43147",
    "addr:street":"Refugee Rd",
    "iso:country":"US",
    "sg:address":"836 Refugee Rd",
    "sg:city":"Pickerington",
    "sg:classifiers":[
        {
            "category":"Autos & Motor Vehicles",
            "subcategory":"Automobile Sales",
            "type":"Retail Goods"
        }
    ],
    "sg:phone":"+1 614 755 8895",
    "sg:postcode":"43147",
    "sg:province":"OH",
    "sg:tags":[
        "used"
    ],
    "wof:name":"Cat Tracks",
    "wof:placetype":"venue"
},
  "geometry": {"coordinates":[-82.77544,39.909793],"type":"Point"}
}