{
  "type": "Feature",
  "properties": {
    "iso:country":"US",
    "sg:address":"777 Scott St",
    "sg:city":"Napoleon",
    "sg:classifiers":[
        {
            "category":"Food & Beverages",
            "subcategory":"Groceries & Convenience Stores",
            "type":"Retail Goods"
        }
    ],
    "sg:phone":"+1 419 592 8906",
    "sg:postcode":"43545",
    "sg:province":"OH",
    "wof:name":"Sterling Food Store 24",
    "wof:placetype":"venue"
},
  "geometry": {"coordinates":[-84.127004,41.391794],"type":"Point"}
}