{
  "type": "Feature",
  "properties": {
    "addr:full": "2076 S Gaydos Rd Lakeside Marblhd OH 43440",
    "addr:housenumber": "2076",
    "addr:postcode": "43440",
    "addr:street": "S Gaydos Rd",
    "iso:country": "US",
    "sg:address": "2076 S Gaydos Rd",
    "sg:city": "Lakeside Marblhd",
    "sg:classifiers": [
      {
        "category": "Building \u0026 Trades",
        "subcategory": "Construction",
        "type": "Services"
      }
    ],
    "sg:phone": "+1 419 798 5322",
    "sg:postcode": "43440",
    "sg:province": "OH",
    "sg:tags": [
      "house",
      "general",
      "contractor"
    ],
    "wof:name": "M and P Development Corp",
    "wof:placetype": "venue"
  },
  "geometry": {"coordinates":[-82.735981,41.51257],"type":"Point"}
}
