{
  "type": "Feature",
  "properties": {
    "iso:country":"US",
    "sg:address":"358 5th St SW",
    "sg:city":"Strasburg",
    "sg:classifiers":[
        {
            "category":"Government",
            "subcategory":"Office",
            "type":"Public Place"
        }
    ],
    "sg:phone":"+1 330 878 7213",
    "sg:postcode":"44680",
    "sg:province":"OH",
    "sg:tags":[
        "city",
        "taxation"
    ],
    "wof:name":"Strasburg Income Tax Dept",
    "wof:placetype":"venue"
},
  "geometry": {"coordinates":[-81.529661,40.592566],"type":"Point"}
}