{
  "type": "Feature",
  "properties": {
    "addr:full": "100 N High St Somerset OH 43783",
    "addr:housenumber": "100",
    "addr:postcode": "43783",
    "addr:street": "N High St",
    "iso:country": "US",
    "sg:address": "100 N High St",
    "sg:city": "Somerset",
    "sg:classifiers": [
      {
        "category": "Education",
        "subcategory": "School",
        "type": "Public Place"
      }
    ],
    "sg:phone": "+1 740 743 1454",
    "sg:postcode": "43783",
    "sg:province": "OH",
    "wof:name": "Somerset Elementary School",
    "wof:placetype": "venue"
  },
  "geometry": {"coordinates":[-82.296805,39.809884],"type":"Point"}
}
