{
  "type": "Feature",
  "properties": {
    "iso:country":"US",
    "sg:address":"51 N Main St",
    "sg:city":"Rittman",
    "sg:classifiers":[
        {
            "category":"Social Services",
            "type":"Services"
        }
    ],
    "sg:phone":"+1 330 927 2244",
    "sg:postcode":"44270",
    "sg:province":"OH",
    "sg:tags":[
        "counselor",
        "marriage",
        "family"
    ],
    "wof:name":"Human Resource Ctr",
    "wof:placetype":"venue"
},
  "geometry": {"coordinates":[-81.781603,40.974387],"type":"Point"}
}