{
  "type": "Feature",
  "properties": {
    "addr:full": "9924 Forestview Ter Cleveland OH 44141",
    "addr:housenumber": "9924",
    "addr:postcode": "44141",
    "addr:street": "Forestview Ter",
    "iso:country": "US",
    "sg:address": "9924 Forestview Ter",
    "sg:city": "Cleveland",
    "sg:classifiers": [
      {
        "category": "Professional",
        "subcategory": "Management \u0026 Consulting",
        "type": "Services"
      }
    ],
    "sg:phone": "+1 440 526 2380",
    "sg:postcode": "44141",
    "sg:province": "OH",
    "sg:tags": [
      "consultant",
      "automation"
    ],
    "wof:name": "Krohne Inc",
    "wof:placetype": "venue"
  },
  "geometry": {"coordinates":[-81.611533,41.292992],"type":"Point"}
}
