{
  "type": "Feature",
  "properties": {
    "addr:full": "485 Neel Ave Van Wert OH 45891",
    "addr:housenumber": "485",
    "addr:postcode": "45891",
    "addr:street": "Neel Ave",
    "iso:country": "US",
    "sg:address": "485 Neel Ave",
    "sg:city": "Van Wert",
    "sg:classifiers": [
      {
        "category": "Real Estate",
        "subcategory": "Real Estate Agent",
        "type": "Services"
      }
    ],
    "sg:phone": "+1 419 238 1800",
    "sg:postcode": "45891",
    "sg:province": "OH",
    "sg:tags": [
      "agency"
    ],
    "wof:name": "Brown Leila",
    "wof:placetype": "venue"
  },
  "geometry": {"coordinates":[-84.597822,40.877798],"type":"Point"}
}
