{
  "type": "Feature",
  "properties": {
    "addr:full":"110 Sanderson Ave Swanton OH 43558",
    "addr:housenumber":"110",
    "addr:postcode":"43558",
    "addr:street":"Sanderson Ave",
    "iso:country":"US",
    "sg:address":"110 Sanderson Ave",
    "sg:city":"Swanton",
    "sg:classifiers":[
        {
            "category":"Manufacturing",
            "subcategory":"Printing",
            "type":"Manufacturing & Wholesale Goods"
        }
    ],
    "sg:phone":"+1 419 826 9977",
    "sg:postcode":"43558",
    "sg:province":"OH",
    "sg:tags":[
        "foil",
        "metal",
        "label"
    ],
    "wof:name":"Lincoln Research Inc",
    "wof:placetype":"venue"
},
  "geometry": {"coordinates":[-83.89062199999999,41.588095],"type":"Point"}
}