{
  "type": "Feature",
  "properties": {
    "addr:full": "7740 Sawmill Rd Dublin OH 43016",
    "addr:housenumber": "7740",
    "addr:postcode": "43016",
    "addr:street": "Sawmill Rd",
    "iso:country": "US",
    "sg:address": "7740 Sawmill Rd",
    "sg:city": "Dublin",
    "sg:classifiers": [
      {
        "category": "Shopping",
        "subcategory": "Pharmacy",
        "type": "Retail Goods"
      }
    ],
    "sg:phone": "+1 614 889 5716",
    "sg:postcode": "43016",
    "sg:province": "OH",
    "sg:website": "www.kroger.com",
    "wof:name": "Kroger",
    "wof:placetype": "venue"
  },
  "geometry": {"coordinates":[-83.090161,40.123134],"type":"Point"}
}
