{
  "type": "Feature",
  "properties": {
    "iso:country":"US",
    "sg:address":"645 E 6th St",
    "sg:city":"Ashtabula",
    "sg:classifiers":[
        {
            "category":"Railroad",
            "type":"Transportation"
        }
    ],
    "sg:phone":"+1 440 992 2274",
    "sg:postcode":"44004",
    "sg:province":"OH",
    "sg:tags":[
        "operator",
        "line"
    ],
    "wof:name":"Norfolk Southern Corporation",
    "wof:placetype":"venue"
},
  "geometry": {"coordinates":[-80.79025900000001,41.900058],"type":"Point"}
}