{
  "type": "Feature",
  "properties": {
    "addr:full":"6220 Wilmington Pike Dayton OH 45459",
    "addr:housenumber":"6220",
    "addr:postcode":"45459",
    "addr:street":"Wilmington Pike",
    "iso:country":"US",
    "sg:address":"6220 Wilmington Pike",
    "sg:city":"Dayton",
    "sg:classifiers":[
        {
            "category":"Banks & Credit Unions",
            "subcategory":"Bank",
            "type":"Services"
        }
    ],
    "sg:phone":"+1 937 848 4955",
    "sg:postcode":"45459",
    "sg:province":"OH",
    "sg:tags":[
        "national"
    ],
    "sg:website":"www.nationalcity.com",
    "wof:name":"National City Bank",
    "wof:placetype":"venue"
},
  "geometry": {"coordinates":[-84.11023299999999,39.635077],"type":"Point"}
}