{
  "type": "Feature",
  "properties": {
    "addr:full": "1284 Brice Rd Reynoldsburg OH 43068",
    "addr:housenumber": "1284",
    "addr:postcode": "43068",
    "addr:street": "Brice Rd",
    "iso:country": "US",
    "sg:address": "1284 Brice Rd",
    "sg:city": "Reynoldsburg",
    "sg:classifiers": [
      {
        "category": "Restaurant",
        "type": "Food \u0026 Drink"
      }
    ],
    "sg:phone": "+1 614 864 0400",
    "sg:postcode": "43068",
    "sg:province": "OH",
    "sg:tags": [
      "pizza"
    ],
    "wof:name": "Little Caesars Pizza",
    "wof:placetype": "venue"
  },
  "geometry": {"coordinates":[-82.829057,39.950148],"type":"Point"}
}
