{
  "type": "Feature",
  "properties": {
    "iso:country":"US",
    "sg:address":"1284 Brice Rd",
    "sg:city":"Reynoldsburg",
    "sg:classifiers":[
        {
            "category":"Restaurant",
            "type":"Food & Drink"
        }
    ],
    "sg:phone":"+1 614 864 0400",
    "sg:postcode":"43068",
    "sg:province":"OH",
    "sg:tags":[
        "pizza"
    ],
    "wof:name":"Little Caesars Pizza",
    "wof:placetype":"venue"
},
  "geometry": {"coordinates":[-82.82905700000001,39.950148],"type":"Point"}
}