{
  "type": "Feature",
  "properties": {
    "addr:full":"3039 US Hwy 68 Xenia OH 45385",
    "addr:housenumber":"3039",
    "addr:postcode":"45385",
    "addr:street":"Us Hwy 68",
    "iso:country":"US",
    "sg:address":"3039 US Hwy 68",
    "sg:city":"Xenia",
    "sg:classifiers":[
        {
            "category":"Home & Garden",
            "subcategory":"Building Materials",
            "type":"Retail Goods"
        }
    ],
    "sg:phone":"+1 937 572 9663",
    "sg:postcode":"45385",
    "sg:province":"OH",
    "sg:tags":[
        "lumber"
    ],
    "wof:name":"C R Muterspaw Lumber",
    "wof:placetype":"venue"
},
  "geometry": {"coordinates":[-83.86201199999999,39.582792],"type":"Point"}
}