{
  "type": "Feature",
  "properties": {
    "iso:country":"US",
    "sg:address":"4167 N High St",
    "sg:city":"Columbus",
    "sg:classifiers":[
        {
            "category":"Shopping",
            "subcategory":"Bicycles & Sporting Goods",
            "type":"Retail Goods"
        }
    ],
    "sg:phone":"+1 614 263 0369",
    "sg:postcode":"43214",
    "sg:province":"OH",
    "sg:tags":[
        "gun",
        "gunsmith"
    ],
    "wof:name":"Zane's Gun Rack",
    "wof:placetype":"venue"
},
  "geometry": {"coordinates":[-83.01993299999999,40.046361],"type":"Point"}
}