{
  "type": "Feature",
  "properties": {
    "addr:full": "4167 N High St Columbus OH 43214",
    "addr:housenumber": "4167",
    "addr:postcode": "43214",
    "addr:street": "N High St",
    "iso:country": "US",
    "sg:address": "4167 N High St",
    "sg:city": "Columbus",
    "sg:classifiers": [
      {
        "category": "Shopping",
        "subcategory": "Bicycles \u0026 Sporting Goods",
        "type": "Retail Goods"
      }
    ],
    "sg:phone": "+1 614 263 0369",
    "sg:postcode": "43214",
    "sg:province": "OH",
    "sg:tags": [
      "gun",
      "gunsmith"
    ],
    "wof:name": "Zane's Gun Rack",
    "wof:placetype": "venue"
  },
  "geometry": {"coordinates":[-83.019933,40.046361],"type":"Point"}
}
