{
  "type": "Feature",
  "properties": {
    "iso:country":"US",
    "sg:address":"7500 Coder Rd",
    "sg:city":"Maumee",
    "sg:classifiers":[
        {
            "category":"Professional",
            "type":"Services"
        }
    ],
    "sg:phone":"+1 419 865 7063",
    "sg:postcode":"43537",
    "sg:province":"OH",
    "wof:name":"Duraseal Inc",
    "wof:placetype":"venue"
},
  "geometry": {"coordinates":[-83.712425,41.571142],"type":"Point"}
}