{
  "type": "Feature",
  "properties": {
    "addr:full":"1395 US Hwy 42 Xenia OH 45385",
    "addr:housenumber":"1395",
    "addr:postcode":"45385",
    "addr:street":"Us Hwy 42",
    "iso:country":"US",
    "sg:address":"1395 US Hwy 42",
    "sg:city":"Xenia",
    "sg:classifiers":[
        {
            "category":"Home & Garden",
            "subcategory":"Garden Supply",
            "type":"Retail Goods"
        }
    ],
    "sg:phone":"+1 937 372 3943",
    "sg:postcode":"45385",
    "sg:province":"OH",
    "sg:tags":[
        "center"
    ],
    "wof:name":"Spring Valley Gardens",
    "wof:placetype":"venue"
},
  "geometry": {"coordinates":[-83.964015,39.646707],"type":"Point"}
}