{
  "type": "Feature",
  "properties": {
    "iso:country":"US",
    "sg:address":"267 Castle Blvd",
    "sg:city":"Akron",
    "sg:classifiers":[
        {
            "category":"Building & Trades",
            "subcategory":"Landscaping Services",
            "type":"Services"
        }
    ],
    "sg:phone":"+1 330 869 0199",
    "sg:postcode":"44313",
    "sg:province":"OH",
    "sg:tags":[
        "designer",
        "landscape"
    ],
    "wof:name":"John Vittum Landscape Arch",
    "wof:placetype":"venue"
},
  "geometry": {"coordinates":[-81.561294,41.114651],"type":"Point"}
}