{
  "type": "Feature",
  "properties": {
    "iso:country":"US",
    "sg:address":"402 E Washington St",
    "sg:city":"Napoleon",
    "sg:classifiers":[
        {
            "category":"Restaurant",
            "type":"Food & Drink"
        }
    ],
    "sg:phone":"+1 419 599 1946",
    "sg:postcode":"43545",
    "sg:province":"OH",
    "sg:tags":[
        "eating",
        "pizza"
    ],
    "sg:website":"www.pizzahawk.com",
    "wof:name":"Hawks Pizza and Drive-Thru",
    "wof:placetype":"venue"
},
  "geometry": {"coordinates":[-84.119194,41.393298],"type":"Point"}
}