{
  "type": "Feature",
  "properties": {
    "addr:full":"1200 W Main St Woodville OH 43469",
    "addr:housenumber":"1200",
    "addr:postcode":"43469",
    "addr:street":"W Main St",
    "iso:country":"US",
    "sg:address":"1200 W Main St",
    "sg:city":"Woodville",
    "sg:classifiers":[
        {
            "category":"Wholesale",
            "subcategory":"Farm Supplies",
            "type":"Manufacturing & Wholesale Goods"
        }
    ],
    "sg:phone":"+1 419 849 2711",
    "sg:postcode":"43469",
    "sg:province":"OH",
    "sg:website":"www.luckeyfarmers.com",
    "wof:name":"Luckey Farmers Inc",
    "wof:placetype":"venue"
},
  "geometry": {"coordinates":[-83.378415,41.456728],"type":"Point"}
}