{
  "type": "Feature",
  "properties": {
    "iso:country":"US",
    "sg:address":"837 Elm Rd NE",
    "sg:city":"Warren",
    "sg:classifiers":[
        {
            "category":"Manufacturing",
            "subcategory":"Apparel",
            "type":"Manufacturing & Wholesale Goods"
        }
    ],
    "sg:phone":"+1 330 399 7800",
    "sg:postcode":"44483",
    "sg:province":"OH",
    "sg:tags":[
        "dress",
        "mfg"
    ],
    "wof:name":"Diaa Designs Inc",
    "wof:placetype":"venue"
},
  "geometry": {"coordinates":[-80.805644,41.244844],"type":"Point"}
}