{
  "type": "Feature",
  "properties": {
    "addr:full": "837 Elm Rd NE Warren OH 44483",
    "addr:housenumber": "837",
    "addr:postcode": "44483",
    "addr:street": "Elm Rd Ne",
    "iso:country": "US",
    "sg:address": "837 Elm Rd NE",
    "sg:city": "Warren",
    "sg:classifiers": [
      {
        "category": "Manufacturing",
        "subcategory": "Apparel",
        "type": "Manufacturing \u0026 Wholesale Goods"
      }
    ],
    "sg:phone": "+1 330 399 7800",
    "sg:postcode": "44483",
    "sg:province": "OH",
    "sg:tags": [
      "dress",
      "mfg"
    ],
    "wof:name": "Diaa Designs Inc",
    "wof:placetype": "venue"
  },
  "geometry": {"coordinates":[-80.805644,41.244844],"type":"Point"}
}
