{
  "type": "Feature",
  "properties": {
    "addr:full":"2444 Key St Toledo OH 43537",
    "addr:housenumber":"2444",
    "addr:postcode":"43537",
    "addr:street":"Key St",
    "iso:country":"US",
    "sg:address":"2444 Key St",
    "sg:city":"Toledo",
    "sg:classifiers":[
        {
            "category":"Wholesale",
            "subcategory":"Farm Supplies",
            "type":"Manufacturing & Wholesale Goods"
        },
        {
            "category":"Shopping",
            "type":"Retail Goods"
        }
    ],
    "sg:phone":"+1 419 389 3100",
    "sg:postcode":"43537",
    "sg:province":"OH",
    "sg:tags":[
        "pet",
        "food"
    ],
    "wof:name":"Sweet Feed Co Inc",
    "wof:placetype":"venue"
},
  "geometry": {"coordinates":[-83.645561,41.595196],"type":"Point"}
}