{
  "type": "Feature",
  "properties": {
    "iso:country":"US",
    "sg:address":"200 Hutchinson Ave",
    "sg:city":"Columbus",
    "sg:classifiers":[
        {
            "category":"Cinema",
            "subcategory":"Movie Theater",
            "type":"Entertainment"
        }
    ],
    "sg:phone":"+1 614 840 9871",
    "sg:postcode":"43235",
    "sg:province":"OH",
    "wof:name":"Marcus Imax Cinema Crosswoods",
    "wof:placetype":"venue"
},
  "geometry": {"coordinates":[-83.012461,40.113803],"type":"Point"}
}