{
  "type": "Feature",
  "properties": {
    "addr:full": "4289 Swaffield Rd Cleveland OH 44121",
    "addr:housenumber": "4289",
    "addr:postcode": "44121",
    "addr:street": "Swaffield Rd",
    "iso:country": "US",
    "sg:address": "4289 Swaffield Rd",
    "sg:city": "Cleveland",
    "sg:classifiers": [
      {
        "category": "Freight",
        "type": "Transportation"
      }
    ],
    "sg:phone": "+1 216 381 0391",
    "sg:postcode": "44121",
    "sg:province": "OH",
    "sg:tags": [
      "operator",
      "trucking"
    ],
    "wof:name": "Anthony L Webster",
    "wof:placetype": "venue"
  },
  "geometry": {"coordinates":[-81.526302,41.529487],"type":"Point"}
}
