{
  "type": "Feature",
  "properties": {
    "addr:full": "6050 Oak Tree Blvd Cleveland OH 44131",
    "addr:housenumber": "6050",
    "addr:postcode": "44131",
    "addr:street": "Oak Tree Blvd",
    "iso:country": "US",
    "sg:address": "6050 Oak Tree Blvd",
    "sg:city": "Cleveland",
    "sg:classifiers": [
      {
        "category": "Communications",
        "type": "Services"
      }
    ],
    "sg:phone": "+1 216 986 0820",
    "sg:postcode": "44131",
    "sg:province": "OH",
    "sg:website": "www.ldmi.com",
    "wof:name": "LDMI Telecommunications Inc",
    "wof:placetype": "venue"
  },
  "geometry": {"coordinates":[-81.660882,41.39756],"type":"Point"}
}
