{
  "type": "Feature",
  "properties": {
    "addr:full": "935 Bryant St Richwood OH 43302",
    "addr:housenumber": "935",
    "addr:postcode": "43302",
    "addr:street": "Bryant St",
    "iso:country": "US",
    "sg:address": "935 Bryant St",
    "sg:city": "Richwood",
    "sg:classifiers": [
      {
        "category": "Organizations",
        "subcategory": "Religious Organization",
        "type": "Services"
      }
    ],
    "sg:phone": "+1 740 223 2886",
    "sg:postcode": "43302",
    "sg:province": "OH",
    "sg:tags": [
      "church"
    ],
    "wof:name": "Church Of God Prophecy",
    "wof:placetype": "venue"
  },
  "geometry": {"coordinates":[-83.127273,40.606647],"type":"Point"}
}
