{
  "type": "Feature",
  "properties": {
    "addr:full":"607 Sunbury Rd Delaware OH 43015",
    "addr:housenumber":"607",
    "addr:postcode":"43015",
    "addr:street":"Sunbury Rd",
    "iso:country":"US",
    "sg:address":"607 Sunbury Rd",
    "sg:city":"Delaware",
    "sg:classifiers":[
        {
            "category":"Social Services",
            "type":"Services"
        }
    ],
    "sg:phone":"+1 740 363 8810",
    "sg:postcode":"43015",
    "sg:province":"OH",
    "sg:tags":[
        "organization",
        "welfare"
    ],
    "wof:name":"Head Start",
    "wof:placetype":"venue"
},
  "geometry": {"coordinates":[-83.043126,40.296806],"type":"Point"}
}