{
  "type": "Feature",
  "properties": {
    "addr:full": "158 N High St Gahanna OH 43230",
    "addr:housenumber": "158",
    "addr:postcode": "43230",
    "addr:street": "N High St",
    "iso:country": "US",
    "sg:address": "158 N High St",
    "sg:city": "Gahanna",
    "sg:classifiers": [
      {
        "category": "Real Estate",
        "subcategory": "Real Estate Services",
        "type": "Services"
      }
    ],
    "sg:phone": "+1 614 428 7470",
    "sg:postcode": "43230",
    "sg:province": "OH",
    "sg:tags": [
      "company",
      "title"
    ],
    "wof:name": "New Vision Title \u0026 Abstract",
    "wof:placetype": "venue"
  },
  "geometry": {"coordinates":[-82.878059,40.021152],"type":"Point"}
}
