{
  "type": "Feature",
  "properties": {
    "iso:country":"US",
    "sg:address":"2139 Elida Rd",
    "sg:city":"Lima",
    "sg:classifiers":[
        {
            "category":"Personal",
            "type":"Services"
        }
    ],
    "sg:phone":"+1 419 227 3018",
    "sg:postcode":"45805",
    "sg:province":"OH",
    "sg:tags":[
        "formal",
        "wear",
        "rent"
    ],
    "wof:name":"Russells Tuxedos",
    "wof:placetype":"venue"
},
  "geometry": {"coordinates":[-84.142636,40.759662],"type":"Point"}
}