{
  "type": "Feature",
  "properties": {
    "addr:full": "6857 Pilliod Rd Holland OH 43528",
    "addr:postcode": "43528",
    "addr:street": "Pilliod Rd",
    "iso:country": "US",
    "sg:address": "6857 Pilliod Rd",
    "sg:city": "Holland",
    "sg:classifiers": [
      {
        "category": "Building \u0026 Trades",
        "subcategory": "Construction",
        "type": "Services"
      }
    ],
    "sg:phone": "+1 419 866 8794",
    "sg:postcode": "43528",
    "sg:province": "OH",
    "sg:tags": [
      "residential",
      "contractor"
    ],
    "wof:name": "D J U Enterprises Inc",
    "wof:placetype": "venue"
  },
  "geometry": {"coordinates":[-83.711121,41.602865],"type":"Point"}
}
