{
  "type": "Feature",
  "properties": {
    "iso:country":"US",
    "sg:address":"116 W Lincoln Way",
    "sg:city":"Lisbon",
    "sg:classifiers":[
        {
            "category":"Government",
            "subcategory":"Office",
            "type":"Public Place"
        }
    ],
    "sg:phone":"+1 330 424 3431",
    "sg:postcode":"44432",
    "sg:province":"OH",
    "wof:name":"Columbiana County RLP",
    "wof:placetype":"venue"
},
  "geometry": {"coordinates":[-80.769593,40.772171],"type":"Point"}
}