{
  "type": "Feature",
  "properties": {
    "addr:full": "116 W Lincoln Way Lisbon OH 44432",
    "addr:housenumber": "116",
    "addr:postcode": "44432",
    "addr:street": "W Lincoln Way",
    "iso:country": "US",
    "sg:address": "116 W Lincoln Way",
    "sg:city": "Lisbon",
    "sg:classifiers": [
      {
        "category": "Government",
        "subcategory": "Office",
        "type": "Public Place"
      }
    ],
    "sg:phone": "+1 330 424 3431",
    "sg:postcode": "44432",
    "sg:province": "OH",
    "wof:name": "Columbiana County RLP",
    "wof:placetype": "venue"
  },
  "geometry": {"coordinates":[-80.769593,40.772171],"type":"Point"}
}
