{
  "type": "Feature",
  "properties": {
    "iso:country":"US",
    "sg:address":"320 Orchardview Rd",
    "sg:city":"Cleveland",
    "sg:classifiers":[
        {
            "category":"Insurance",
            "subcategory":"Insurance Agent",
            "type":"Services"
        }
    ],
    "sg:phone":"+1 216 520 2622",
    "sg:postcode":"44131",
    "sg:province":"OH",
    "wof:name":"American Family Insurance",
    "wof:placetype":"venue"
},
  "geometry": {"coordinates":[-81.68312,41.355371],"type":"Point"}
}