{
  "type": "Feature",
  "properties": {
    "addr:full":"422 Pearl Rd Brunswick OH 44212",
    "addr:housenumber":"422",
    "addr:postcode":"44212",
    "addr:street":"Pearl Rd",
    "iso:country":"US",
    "sg:address":"422 Pearl Rd",
    "sg:city":"Brunswick",
    "sg:classifiers":[
        {
            "category":"Building & Trades",
            "subcategory":"Electrical",
            "type":"Services"
        }
    ],
    "sg:phone":"+1 330 273 3110",
    "sg:postcode":"44212",
    "sg:province":"OH",
    "sg:tags":[
        "electric",
        "contractor"
    ],
    "wof:name":"Dart Electrical",
    "wof:placetype":"venue"
},
  "geometry": {"coordinates":[-81.841224,41.264672],"type":"Point"}
}