{
  "type": "Feature",
  "properties": {
    "iso:country":"US",
    "sg:address":"2180 Brookpark Rd",
    "sg:city":"Cleveland",
    "sg:classifiers":[
        {
            "category":"Shopping",
            "subcategory":"Department Store",
            "type":"Retail Goods"
        }
    ],
    "sg:phone":"+1 216 351 8400",
    "sg:postcode":"44134",
    "sg:province":"OH",
    "sg:tags":[
        "shop"
    ],
    "wof:name":"Star-Valu Stores Inc",
    "wof:placetype":"venue"
},
  "geometry": {"coordinates":[-81.697493,41.41923],"type":"Point"}
}