{
  "type": "Feature",
  "properties": {
    "addr:full": "1251 East Ave Elyria OH 44035",
    "addr:housenumber": "1251",
    "addr:postcode": "44035",
    "addr:street": "East Ave",
    "iso:country": "US",
    "sg:address": "1251 East Ave",
    "sg:city": "Elyria",
    "sg:classifiers": [
      {
        "category": "Social Services",
        "subcategory": "Adult Care",
        "type": "Services"
      }
    ],
    "sg:phone": "+1 440 323 6310",
    "sg:postcode": "44035",
    "sg:province": "OH",
    "sg:tags": [
      "residential",
      "intermediate",
      "facility"
    ],
    "wof:name": "Sensi-Care Inc",
    "wof:placetype": "venue"
  },
  "geometry": {"coordinates":[-82.104154,41.354393],"type":"Point"}
}
