{
  "type": "Feature",
  "properties": {
    "iso:country":"US",
    "sg:address":"1251 East Ave",
    "sg:city":"Elyria",
    "sg:classifiers":[
        {
            "category":"Social Services",
            "subcategory":"Adult Care",
            "type":"Services"
        }
    ],
    "sg:phone":"+1 440 323 6310",
    "sg:postcode":"44035",
    "sg:province":"OH",
    "sg:tags":[
        "residential",
        "intermediate",
        "facility"
    ],
    "wof:name":"Sensi-Care Inc",
    "wof:placetype":"venue"
},
  "geometry": {"coordinates":[-82.10415399999999,41.354393],"type":"Point"}
}