{
  "type": "Feature",
  "properties": {
    "addr:full":"4595 Chambersburg Rd Dayton OH 45424",
    "addr:postcode":"4595;45424",
    "addr:street":"Chambersburg Rd",
    "iso:country":"US",
    "sg:address":"4595 Chambersburg Rd",
    "sg:city":"Dayton",
    "sg:classifiers":[
        {
            "category":"Autos & Motor Vehicles",
            "subcategory":"Auto Supplies",
            "type":"Retail Goods"
        }
    ],
    "sg:phone":"+1 937 236 9702",
    "sg:postcode":"45424",
    "sg:province":"OH",
    "sg:tags":[
        "also",
        "outfitter",
        "landscaping",
        "work",
        "concrete",
        "truck"
    ],
    "wof:name":"K E Rose Co",
    "wof:placetype":"venue"
},
  "geometry": {"coordinates":[-84.15669200000001,39.848902],"type":"Point"}
}