{
  "type": "Feature",
  "properties": {
    "iso:country":"US",
    "sg:address":"260 Springside Dr",
    "sg:city":"Akron",
    "sg:classifiers":[
        {
            "category":"Manufacturing",
            "subcategory":"Rubber & Plastics",
            "type":"Manufacturing & Wholesale Goods"
        }
    ],
    "sg:phone":"+1 330 666 4111",
    "sg:postcode":"44333",
    "sg:province":"OH",
    "sg:tags":[
        "supplier",
        "chemical",
        "for",
        "manufacturer"
    ],
    "wof:name":"Flexsys America LP",
    "wof:placetype":"venue"
},
  "geometry": {"coordinates":[-81.642414,41.142134],"type":"Point"}
}