{
  "type": "Feature",
  "properties": {
    "addr:full": "3956 Lee Rd Cleveland OH 44128",
    "addr:housenumber": "3956",
    "addr:postcode": "44128",
    "addr:street": "Lee Rd",
    "iso:country": "US",
    "sg:address": "3956 Lee Rd",
    "sg:city": "Cleveland",
    "sg:classifiers": [
      {
        "category": "Personal",
        "subcategory": "Beauty Salon",
        "type": "Services"
      }
    ],
    "sg:phone": "+1 216 751 2232",
    "sg:postcode": "44128",
    "sg:province": "OH",
    "wof:name": "Free Hands Nail Salon",
    "wof:placetype": "venue"
  },
  "geometry": {"coordinates":[-81.564939,41.452479],"type":"Point"}
}
