{
  "type": "Feature",
  "properties": {
    "addr:full":"274 Piedmont Rd Columbus OH 43214",
    "addr:housenumber":"274",
    "addr:postcode":"43214",
    "addr:street":"Piedmont Rd",
    "iso:country":"US",
    "sg:address":"274 Piedmont Rd",
    "sg:city":"Columbus",
    "sg:classifiers":[
        {
            "category":"Personal",
            "type":"Services"
        }
    ],
    "sg:phone":"+1 614 262 9505",
    "sg:postcode":"43214",
    "sg:province":"OH",
    "sg:tags":[
        "consultant",
        "program",
        "health",
        "fitness"
    ],
    "wof:name":"Sharon L Groves",
    "wof:placetype":"venue"
},
  "geometry": {"coordinates":[-83.01030799999999,40.035197],"type":"Point"}
}