{
  "type": "Feature",
  "properties": {
    "iso:country":"US",
    "sg:address":"1921 N Mistywood Ct",
    "sg:city":"Defiance",
    "sg:classifiers":[
        {
            "category":"Real Estate",
            "subcategory":"Real Estate Operator",
            "type":"Services"
        }
    ],
    "sg:phone":"+1 419 784 9746",
    "sg:postcode":"43512",
    "sg:province":"OH",
    "sg:tags":[
        "building",
        "apartment"
    ],
    "wof:name":"TNT Enterprises",
    "wof:placetype":"venue"
},
  "geometry": {"coordinates":[-84.368032,41.260007],"type":"Point"}
}