{
  "type": "Feature",
  "properties": {
    "addr:full": "10717 Yohe Rd West Manchester OH 45382",
    "addr:housenumber": "10717",
    "addr:postcode": "45382",
    "addr:street": "Yohe Rd",
    "iso:country": "US",
    "sg:address": "10717 Yohe Rd",
    "sg:city": "West Manchester",
    "sg:classifiers": [
      {
        "category": "Organizations",
        "subcategory": "Religious Organization",
        "type": "Services"
      }
    ],
    "sg:phone": "+1 937 678 6801",
    "sg:postcode": "45382",
    "sg:province": "OH",
    "sg:tags": [
      "church"
    ],
    "wof:name": "Twin Creek Chapel",
    "wof:placetype": "venue"
  },
  "geometry": {"coordinates":[-84.595947,39.894054],"type":"Point"}
}
