{
  "type": "Feature",
  "properties": {
    "addr:full":"2300 Hallock Young Rd Warren OH 44481",
    "addr:postcode":"2300;44481",
    "addr:street":"Young Rd",
    "iso:country":"US",
    "sg:address":"2300 Hallock Young Rd",
    "sg:city":"Warren",
    "sg:classifiers":[
        {
            "category":"Manufacturing",
            "subcategory":"Retail Goods",
            "type":"Manufacturing & Wholesale Goods"
        }
    ],
    "sg:phone":"+1 330 824 2217",
    "sg:postcode":"44481",
    "sg:province":"OH",
    "sg:tags":[
        "manufacturer"
    ],
    "wof:name":"Durr Industries Inc",
    "wof:placetype":"venue"
},
  "geometry": {"coordinates":[-80.882713,41.143665],"type":"Point"}
}