{
  "type": "Feature",
  "properties": {
    "iso:country":"US",
    "sg:address":"1625 N State St",
    "sg:city":"Girard",
    "sg:classifiers":[
        {
            "category":"Building & Trades",
            "subcategory":"Cleaning & Sanitation",
            "type":"Services"
        }
    ],
    "sg:phone":"+1 330 545 2323",
    "sg:postcode":"44420",
    "sg:province":"OH",
    "sg:tags":[
        "janitor"
    ],
    "wof:name":"Premier Image",
    "wof:placetype":"venue"
},
  "geometry": {"coordinates":[-80.710518,41.175434],"type":"Point"}
}