{
  "type": "Feature",
  "properties": {
    "addr:full": "307 S Main St Jackson Center OH 45334",
    "addr:housenumber": "307",
    "addr:postcode": "45334",
    "addr:street": "S Main St",
    "iso:country": "US",
    "sg:address": "307 S Main St",
    "sg:city": "Jackson Center",
    "sg:classifiers": [
      {
        "category": "Health Services",
        "subcategory": "Chiropractor",
        "type": "Services"
      }
    ],
    "sg:phone": "+1 937 596 6000",
    "sg:postcode": "45334",
    "sg:province": "OH",
    "wof:name": "Huffer Chiropractic",
    "wof:placetype": "venue"
  },
  "geometry": {"coordinates":[-84.04034,40.437773],"type":"Point"}
}
