{
  "type": "Feature",
  "properties": {
    "iso:country":"US",
    "sg:address":"21538 Maplewood Rd",
    "sg:city":"Weston",
    "sg:phone":"+1 419 669 3791",
    "sg:postcode":"43569",
    "sg:province":"OH",
    "sg:tags":[
        "farm",
        "corn",
        "wheat",
        "soybean"
    ],
    "wof:name":"Raymond Goris",
    "wof:placetype":"venue"
},
  "geometry": {"coordinates":[-83.815629,41.313773],"type":"Point"}
}