{
  "type": "Feature",
  "properties": {
    "iso:country":"US",
    "sg:address":"237 New Milford Rd",
    "sg:city":"Ravenna",
    "sg:classifiers":[
        {
            "category":"Organizations",
            "subcategory":"Religious Organization",
            "type":"Services"
        }
    ],
    "sg:phone":"+1 330 296 5660",
    "sg:postcode":"44266",
    "sg:province":"OH",
    "sg:tags":[
        "church"
    ],
    "wof:name":"First Church Of God",
    "wof:placetype":"venue"
},
  "geometry": {"coordinates":[-81.22378500000001,41.156758],"type":"Point"}
}