{
  "type": "Feature",
  "properties": {
    "addr:full":"17725 Haskins Rd Chagrin Falls OH 44023",
    "addr:housenumber":"17725",
    "addr:postcode":"44023",
    "addr:street":"Haskins Rd",
    "iso:country":"US",
    "sg:address":"17725 Haskins Rd",
    "sg:city":"Chagrin Falls",
    "sg:classifiers":[
        {
            "category":"Building & Trades",
            "subcategory":"Construction",
            "type":"Services"
        }
    ],
    "sg:phone":"+1 440 543 2753",
    "sg:postcode":"44023",
    "sg:province":"OH",
    "sg:tags":[
        "house"
    ],
    "wof:name":"Papesh Builders",
    "wof:placetype":"venue"
},
  "geometry": {"coordinates":[-81.322963,41.386216],"type":"Point"}
}