{
  "type": "Feature",
  "properties": {
    "addr:full":"4790 Powderhorn Dr Cincinnati OH 45244",
    "addr:housenumber":"4790",
    "addr:postcode":"45244",
    "addr:street":"Powderhorn Dr",
    "iso:country":"US",
    "sg:address":"4790 Powderhorn Dr",
    "sg:city":"Cincinnati",
    "sg:classifiers":[
        {
            "category":"Organizations",
            "subcategory":"Religious Organization",
            "type":"Services"
        }
    ],
    "sg:phone":"+1 513 528 9132",
    "sg:postcode":"45244",
    "sg:province":"OH",
    "sg:tags":[
        "clergy"
    ],
    "wof:name":"James R Dinkel",
    "wof:placetype":"venue"
},
  "geometry": {"coordinates":[-84.296657,39.122234],"type":"Point"}
}