{
  "type": "Feature",
  "properties": {
    "iso:country":"US",
    "sg:address":"4265 Lincoln Way",
    "sg:city":"Wooster",
    "sg:classifiers":[
        {
            "category":"Professional",
            "type":"Services"
        }
    ],
    "sg:phone":"+1 330 263 4502",
    "sg:postcode":"44691",
    "sg:province":"OH",
    "wof:name":"Rbb Systems Inc",
    "wof:placetype":"venue"
},
  "geometry": {"coordinates":[-81.884992,40.796139],"type":"Point"}
}