{
  "type": "Feature",
  "properties": {
    "iso:country":"US",
    "sg:address":"25159 State Rte 7",
    "sg:city":"Crown City",
    "sg:classifiers":[
        {
            "category":"Wholesale",
            "subcategory":"Machinery & Supplies",
            "type":"Manufacturing & Wholesale Goods"
        }
    ],
    "sg:phone":"+1 740 256 1623",
    "sg:postcode":"45623",
    "sg:province":"OH",
    "sg:tags":[
        "farm",
        "equipment"
    ],
    "wof:name":"Crown City Tractor Sales & Svc",
    "wof:placetype":"venue"
},
  "geometry": {"coordinates":[-82.27364300000001,38.596126],"type":"Point"}
}