{
  "type": "Feature",
  "properties": {
    "addr:full": "865 Desantis Ct Columbus OH 43214",
    "addr:housenumber": "865",
    "addr:postcode": "43214",
    "addr:street": "Desantis Ct",
    "iso:country": "US",
    "sg:address": "865 Desantis Ct",
    "sg:city": "Columbus",
    "sg:classifiers": [
      {
        "category": "Shopping",
        "subcategory": "Florist",
        "type": "Retail Goods"
      }
    ],
    "sg:phone": "+1 614 451 4414",
    "sg:postcode": "43214",
    "sg:province": "OH",
    "sg:website": "www.desantisflor.com",
    "wof:name": "De Santis Florist",
    "wof:placetype": "venue"
  },
  "geometry": {"coordinates":[-83.042256,40.052527],"type":"Point"}
}
