{
  "type": "Feature",
  "properties": {
    "addr:full":"6409 W Lake Rd Vermilion OH 44089",
    "addr:housenumber":"6409",
    "addr:postcode":"44089",
    "addr:street":"W Lake Rd",
    "iso:country":"US",
    "sg:address":"6409 W Lake Rd",
    "sg:city":"Vermilion",
    "sg:classifiers":[
        {
            "category":"Travel",
            "subcategory":"Hotels & Motels",
            "type":"Entertainment"
        }
    ],
    "sg:phone":"+1 440 967 5240",
    "sg:postcode":"44089",
    "sg:province":"OH",
    "sg:tags":[
        "cottage",
        "cabin"
    ],
    "wof:name":"Fosters Lakefront",
    "wof:placetype":"venue"
},
  "geometry": {"coordinates":[-82.436503,41.394022],"type":"Point"}
}