{
  "type": "Feature",
  "properties": {
    "addr:full":"1688 Harvard Ave Cleveland OH 44105",
    "addr:housenumber":"1688",
    "addr:postcode":"44105",
    "addr:street":"Harvard Ave",
    "iso:country":"US",
    "sg:address":"1688 Harvard Ave",
    "sg:city":"Cleveland",
    "sg:classifiers":[
        {
            "category":"Shopping",
            "subcategory":"Clothing, Apparel, & Fashions",
            "type":"Retail Goods"
        }
    ],
    "sg:phone":"+1 216 751 7630",
    "sg:postcode":"44105",
    "sg:province":"OH",
    "wof:name":"Fashion Retail Inc",
    "wof:placetype":"venue"
},
  "geometry": {"coordinates":[-81.675563,41.447507],"type":"Point"}
}