{
  "type": "Feature",
  "properties": {
    "addr:full":"8876 Shoemaker Ave NW Canal Fulton OH 44614",
    "addr:housenumber":"8876",
    "addr:postcode":"44614",
    "addr:street":"Shoemaker Ave Nw",
    "iso:country":"US",
    "sg:address":"8876 Shoemaker Ave NW",
    "sg:city":"Canal Fulton",
    "sg:classifiers":[
        {
            "category":"Professional",
            "type":"Services"
        }
    ],
    "sg:phone":"+1 330 854 4315",
    "sg:postcode":"44614",
    "sg:province":"OH",
    "wof:name":"Engineered Metal Prod Inc",
    "wof:placetype":"venue"
},
  "geometry": {"coordinates":[-81.62088,40.911119],"type":"Point"}
}