{
  "type": "Feature",
  "properties": {
    "addr:full": "410 Mc Clurg Rd Youngstown OH 44512",
    "addr:housenumber": "410",
    "addr:postcode": "44512",
    "addr:street": "Mc Clurg Rd",
    "iso:country": "US",
    "sg:address": "410 Mc Clurg Rd",
    "sg:city": "Youngstown",
    "sg:classifiers": [
      {
        "category": "Recreation",
        "type": "Entertainment"
      }
    ],
    "sg:phone": "+1 330 758 2123",
    "sg:postcode": "44512",
    "sg:province": "OH",
    "sg:tags": [
      "club",
      "baseball"
    ],
    "sg:website": "www.boardmanbaseball.com",
    "wof:name": "Boardman Community Baseball",
    "wof:placetype": "venue"
  },
  "geometry": {"coordinates":[-80.645967,40.995323],"type":"Point"}
}
