{
  "type": "Feature",
  "properties": {
    "iso:country":"US",
    "sg:address":"6 W Main St",
    "sg:city":"West Jefferson",
    "sg:classifiers":[
        {
            "category":"Food & Beverages",
            "subcategory":"Bakery",
            "type":"Retail Goods"
        }
    ],
    "sg:phone":"+1 614 879 6263",
    "sg:postcode":"43162",
    "sg:province":"OH",
    "wof:name":"Sweet Things",
    "wof:placetype":"venue"
},
  "geometry": {"coordinates":[-83.268103,39.944924],"type":"Point"}
}