{
  "type": "Feature",
  "properties": {
    "addr:full": "1158 Selsam St Zanesville OH 43701",
    "addr:housenumber": "1158",
    "addr:postcode": "43701",
    "addr:street": "Selsam St",
    "iso:country": "US",
    "sg:address": "1158 Selsam St",
    "sg:city": "Zanesville",
    "sg:classifiers": [
      {
        "category": "Shopping",
        "subcategory": "Catalog Store",
        "type": "Retail Goods"
      }
    ],
    "sg:phone": "+1 740 452 6896",
    "sg:postcode": "43701",
    "sg:province": "OH",
    "sg:tags": [
      "mail",
      "house"
    ],
    "wof:name": "Wyatt Michael",
    "wof:placetype": "venue"
  },
  "geometry": {"coordinates":[-81.994531,39.931408],"type":"Point"}
}
