{
  "type": "Feature",
  "properties": {
    "addr:full":"8140 Graves Rd Cincinnati OH 45243",
    "addr:housenumber":"8140",
    "addr:postcode":"45243",
    "addr:street":"Graves Rd",
    "iso:country":"US",
    "sg:address":"8140 Graves Rd",
    "sg:city":"Cincinnati",
    "sg:classifiers":[
        {
            "category":"Banks & Credit Unions",
            "subcategory":"Financial Services",
            "type":"Services"
        }
    ],
    "sg:phone":"+1 513 271 6852",
    "sg:postcode":"45243",
    "sg:province":"OH",
    "sg:tags":[
        "investor"
    ],
    "wof:name":"Wayne R Sievert",
    "wof:placetype":"venue"
},
  "geometry": {"coordinates":[-84.35375500000001,39.17181],"type":"Point"}
}