{
  "type": "Feature",
  "properties": {
    "addr:full": "2640 Lower Bellbrook Rd Spring Valley OH 45370",
    "addr:postcode": "2640;45370",
    "addr:street": "Lower Bellbrook Rd",
    "iso:country": "US",
    "sg:address": "2640 Lower Bellbrook Rd",
    "sg:city": "Spring Valley",
    "sg:classifiers": [
      {
        "category": "Building \u0026 Trades",
        "subcategory": "Construction",
        "type": "Services"
      }
    ],
    "sg:phone": "+1 937 848 7124",
    "sg:postcode": "45370",
    "sg:province": "OH",
    "sg:tags": [
      "house"
    ],
    "wof:name": "Pauls Repair",
    "wof:placetype": "venue"
  },
  "geometry": {"coordinates":[-84.031671,39.630558],"type":"Point"}
}
