{
  "type": "Feature",
  "properties": {
    "iso:country":"US",
    "sg:address":"11386 New Paris-Hillsboro Rd",
    "sg:city":"New Paris",
    "sg:phone":"+1 937 437 8562",
    "sg:postcode":"45347",
    "sg:province":"OH",
    "sg:tags":[
        "farm",
        "corn",
        "soybean"
    ],
    "wof:name":"Ronald Shelly Farm",
    "wof:placetype":"venue"
},
  "geometry": {"coordinates":[-84.806366,39.905372],"type":"Point"}
}