{
  "type": "Feature",
  "properties": {
    "addr:full":"1750 5th St Sandusky OH 44870",
    "addr:housenumber":"1750",
    "addr:postcode":"44870",
    "addr:street":"5Th St",
    "iso:country":"US",
    "sg:address":"1750 5th St",
    "sg:city":"Sandusky",
    "sg:classifiers":[
        {
            "category":"Manufacturing",
            "subcategory":"Metals",
            "type":"Manufacturing & Wholesale Goods"
        }
    ],
    "sg:phone":"+1 419 625 6288",
    "sg:postcode":"44870",
    "sg:province":"OH",
    "sg:tags":[
        "treating",
        "heat"
    ],
    "wof:name":"American Quality Stripping",
    "wof:placetype":"venue"
},
  "geometry": {"coordinates":[-82.683925,41.447636],"type":"Point"}
}