{
  "type": "Feature",
  "properties": {
    "addr:full":"1529 Harvard Ave NW Canton OH 44703",
    "addr:housenumber":"1529",
    "addr:postcode":"44703",
    "addr:street":"Harvard Ave Nw",
    "iso:country":"US",
    "sg:address":"1529 Harvard Ave NW",
    "sg:city":"Canton",
    "sg:classifiers":[
        {
            "category":"Social Services",
            "subcategory":"Adult Care",
            "type":"Services"
        }
    ],
    "sg:phone":"+1 330 454 4823",
    "sg:postcode":"44703",
    "sg:province":"OH",
    "sg:tags":[
        "home",
        "group"
    ],
    "wof:name":"Pathway Youth Advocate Network",
    "wof:placetype":"venue"
},
  "geometry": {"coordinates":[-81.37302699999999,40.815368],"type":"Point"}
}