{
  "type": "Feature",
  "properties": {
    "addr:full":"5200 Grant Ave Cleveland OH 44125",
    "addr:housenumber":"5200",
    "addr:postcode":"44125",
    "addr:street":"Grant Ave",
    "iso:country":"US",
    "sg:address":"5200 Grant Ave",
    "sg:city":"Cleveland",
    "sg:classifiers":[
        {
            "category":"Shopping",
            "type":"Retail Goods"
        }
    ],
    "sg:phone":"+1 216 641 1718",
    "sg:postcode":"44125",
    "sg:province":"OH",
    "sg:tags":[
        "equipment",
        "supply"
    ],
    "wof:name":"Superior Products",
    "wof:placetype":"venue"
},
  "geometry": {"coordinates":[-81.656059,41.441649],"type":"Point"}
}