{
  "type": "Feature",
  "properties": {
    "addr:full": "109 E Main St Mc Connelsville OH 43756",
    "addr:housenumber": "109",
    "addr:postcode": "43756",
    "addr:street": "E Main St",
    "iso:country": "US",
    "sg:address": "109 E Main St",
    "sg:city": "Mc Connelsville",
    "sg:classifiers": [
      {
        "category": "Government",
        "subcategory": "Court House",
        "type": "Public Place"
      }
    ],
    "sg:phone": "+1 740 962 6478",
    "sg:postcode": "43756",
    "sg:province": "OH",
    "sg:tags": [
      "county",
      "counsel"
    ],
    "wof:name": "Morgan County Prosecuting Atty",
    "wof:placetype": "venue"
  },
  "geometry": {"coordinates":[-81.851956,39.648823],"type":"Point"}
}
