{
  "type": "Feature",
  "properties": {
    "addr:full":"1841 Cockrells Run Rd Lucasville OH 45648",
    "addr:housenumber":"1841",
    "addr:postcode":"45648",
    "addr:street":"Cockrells Run Rd",
    "iso:country":"US",
    "sg:address":"1841 Cockrells Run Rd",
    "sg:city":"Lucasville",
    "sg:classifiers":[
        {
            "category":"Retail",
            "subcategory":"Auto Repair",
            "type":"Services"
        }
    ],
    "sg:phone":"+1 740 259 4441",
    "sg:postcode":"45648",
    "sg:province":"OH",
    "sg:tags":[
        "wrecker"
    ],
    "wof:name":"Week's Wrecker Svc",
    "wof:placetype":"venue"
},
  "geometry": {"coordinates":[-82.98844800000001,38.943715],"type":"Point"}
}