{
  "type": "Feature",
  "properties": {
    "iso:country":"US",
    "sg:address":"436 Croghan St",
    "sg:city":"Fremont",
    "sg:classifiers":[
        {
            "category":"Organizations",
            "subcategory":"Community Association",
            "type":"Services"
        }
    ],
    "sg:phone":"+1 419 332 3691",
    "sg:postcode":"43420",
    "sg:province":"OH",
    "wof:name":"Elks Lodge 169",
    "wof:placetype":"venue"
},
  "geometry": {"coordinates":[-83.11505200000001,41.346573],"type":"Point"}
}