{
  "type": "Feature",
  "properties": {
    "addr:full": "4600 Airway Rd Dayton OH 45431",
    "addr:housenumber": "4600",
    "addr:postcode": "45431",
    "addr:street": "Airway Rd",
    "iso:country": "US",
    "sg:address": "4600 Airway Rd",
    "sg:city": "Dayton",
    "sg:classifiers": [
      {
        "category": "Building \u0026 Trades",
        "subcategory": "Construction",
        "type": "Services"
      }
    ],
    "sg:phone": "+1 937 254 2651",
    "sg:postcode": "45431",
    "sg:province": "OH",
    "sg:tags": [
      "excavating",
      "contractor"
    ],
    "wof:name": "Ray Kline \u0026 Son Trucking",
    "wof:placetype": "venue"
  },
  "geometry": {"coordinates":[-84.131058,39.766315],"type":"Point"}
}
