{
  "type": "Feature",
  "properties": {
    "addr:full": "220 Market Ave S Canton OH 44702",
    "addr:housenumber": "220",
    "addr:postcode": "44702",
    "addr:street": "Market Ave S",
    "iso:country": "US",
    "sg:address": "220 Market Ave S",
    "sg:city": "Canton",
    "sg:classifiers": [
      {
        "category": "Professional",
        "subcategory": "Lawyer \u0026 Legal Services",
        "type": "Services"
      }
    ],
    "sg:phone": "+1 330 493 0700",
    "sg:postcode": "44702",
    "sg:province": "OH",
    "sg:tags": [
      "attorney"
    ],
    "wof:name": "David B Spalding LLC",
    "wof:placetype": "venue"
  },
  "geometry": {"coordinates":[-81.375186,40.79702],"type":"Point"}
}
