{
  "type": "Feature",
  "properties": {
    "addr:full": "1335 Krebs Dr Newark OH 43055",
    "addr:housenumber": "1335",
    "addr:postcode": "43055",
    "addr:street": "Krebs Dr",
    "iso:country": "US",
    "sg:address": "1335 Krebs Dr",
    "sg:city": "Newark",
    "sg:classifiers": [
      {
        "category": "Wholesale",
        "subcategory": "Non-durable Goods",
        "type": "Manufacturing \u0026 Wholesale Goods"
      }
    ],
    "sg:phone": "+1 740 349 7807",
    "sg:postcode": "43055",
    "sg:province": "OH",
    "sg:tags": [
      "specialty",
      "mfg"
    ],
    "wof:name": "Newark Flag",
    "wof:placetype": "venue"
  },
  "geometry": {"coordinates":[-82.450409,40.070652],"type":"Point"}
}
