{
  "type": "Feature",
  "properties": {
    "addr:full": "6046 Youngstown Warren Rd Niles OH 44446",
    "addr:housenumber": "6046",
    "addr:postcode": "44446",
    "addr:street": "Youngstown Warren Rd",
    "iso:country": "US",
    "sg:address": "6046 Youngstown Warren Rd",
    "sg:city": "Niles",
    "sg:classifiers": [
      {
        "category": "Shopping",
        "subcategory": "Clothing, Apparel, \u0026 Fashions",
        "type": "Retail Goods"
      }
    ],
    "sg:phone": "+1 330 652 6167",
    "sg:postcode": "44446",
    "sg:province": "OH",
    "sg:tags": [
      "wear"
    ],
    "wof:name": "Maxsons",
    "wof:placetype": "venue"
  },
  "geometry": {"coordinates":[-80.740463,41.205556],"type":"Point"}
}
