{
  "type": "Feature",
  "properties": {
    "addr:full": "4843 Reading Rd Cincinnati OH 45237",
    "addr:housenumber": "4843",
    "addr:postcode": "45237",
    "addr:street": "Reading Rd",
    "iso:country": "US",
    "sg:address": "4843 Reading Rd",
    "sg:city": "Cincinnati",
    "sg:classifiers": [
      {
        "category": "Personal",
        "subcategory": "Beauty Salon",
        "type": "Services"
      }
    ],
    "sg:phone": "+1 513 242 7149",
    "sg:postcode": "45237",
    "sg:province": "OH",
    "wof:name": "Reyarp's Drol Hair Fashion",
    "wof:placetype": "venue"
  },
  "geometry": {"coordinates":[-84.467289,39.174381],"type":"Point"}
}
