{
  "type": "Feature",
  "properties": {
    "iso:country":"US",
    "sg:address":"4235 Midway Ave",
    "sg:city":"Dayton",
    "sg:classifiers":[
        {
            "category":"Building & Trades",
            "subcategory":"Construction",
            "type":"Services"
        }
    ],
    "sg:phone":"+1 937 263 4813",
    "sg:postcode":"45417",
    "sg:province":"OH",
    "sg:tags":[
        "home",
        "general",
        "commercial",
        "contractor"
    ],
    "wof:name":"Nimock Construction Inc",
    "wof:placetype":"venue"
},
  "geometry": {"coordinates":[-84.25574400000001,39.752309],"type":"Point"}
}