{
  "type": "Feature",
  "properties": {
    "addr:full": "4235 Midway Ave Dayton OH 45417",
    "addr:housenumber": "4235",
    "addr:postcode": "45417",
    "addr:street": "Midway Ave",
    "iso:country": "US",
    "sg:address": "4235 Midway Ave",
    "sg:city": "Dayton",
    "sg:classifiers": [
      {
        "category": "Building \u0026 Trades",
        "subcategory": "Construction",
        "type": "Services"
      }
    ],
    "sg:phone": "+1 937 263 4813",
    "sg:postcode": "45417",
    "sg:province": "OH",
    "sg:tags": [
      "home",
      "general",
      "commercial",
      "contractor"
    ],
    "wof:name": "Nimock Construction Inc",
    "wof:placetype": "venue"
  },
  "geometry": {"coordinates":[-84.255744,39.752309],"type":"Point"}
}
