{
  "type": "Feature",
  "properties": {
    "addr:full":"4380 Skylane Dr Cleveland OH 44109",
    "addr:postcode":"4380;44109",
    "addr:street":"Skylane Dr",
    "iso:country":"US",
    "sg:address":"4380 Skylane Dr",
    "sg:city":"Cleveland",
    "sg:classifiers":[
        {
            "category":"Local Transit",
            "type":"Transportation"
        }
    ],
    "sg:phone":"+1 216 398 1984",
    "sg:postcode":"44109",
    "sg:province":"OH",
    "sg:tags":[
        "passenger"
    ],
    "wof:name":"Hamm Ambulance Service",
    "wof:placetype":"venue"
},
  "geometry": {"coordinates":[-81.678201,41.4359],"type":"Point"}
}