{
  "type": "Feature",
  "properties": {
    "addr:full": "6990 Spinach Dr Mentor OH 44060",
    "addr:housenumber": "6990",
    "addr:postcode": "44060",
    "addr:street": "Spinach",
    "iso:country": "US",
    "sg:address": "6990 Spinach Dr",
    "sg:city": "Mentor",
    "sg:classifiers": [
      {
        "category": "Professional",
        "subcategory": "Business Services",
        "type": "Services"
      }
    ],
    "sg:phone": "+1 440 255 7526",
    "sg:postcode": "44060",
    "sg:province": "OH",
    "sg:tags": [
      "drafting"
    ],
    "wof:name": "Plan Works",
    "wof:placetype": "venue"
  },
  "geometry": {"coordinates":[-81.344355,41.679617],"type":"Point"}
}
