{
  "type": "Feature",
  "properties": {
    "addr:full":"4935 Co Hwy 400 Millersburg OH 44654",
    "addr:housenumber":"4935",
    "addr:postcode":"44654",
    "addr:street":"Co Hwy 400",
    "iso:country":"US",
    "sg:address":"4935 Co Hwy 400",
    "sg:city":"Millersburg",
    "sg:classifiers":[
        {
            "category":"Farming",
            "subcategory":"Livestock Farm",
            "type":"Manufacturing & Wholesale Goods"
        }
    ],
    "sg:phone":"+1 330 674 6312",
    "sg:postcode":"44654",
    "sg:province":"OH",
    "sg:tags":[
        "dairy",
        "beef",
        "feedlot",
        "cattle"
    ],
    "wof:name":"San/Mar Holsteins",
    "wof:placetype":"venue"
},
  "geometry": {"coordinates":[-81.98329099999999,40.559838],"type":"Point"}
}