{
  "type": "Feature",
  "properties": {
    "iso:country":"US",
    "sg:address":"595 S Main St",
    "sg:city":"Bluffton",
    "sg:classifiers":[
        {
            "category":"Restaurant",
            "type":"Food & Drink"
        }
    ],
    "sg:phone":"+1 419 369 4050",
    "sg:postcode":"45817",
    "sg:province":"OH",
    "wof:name":"Bluffton Dari Freeze",
    "wof:placetype":"venue"
},
  "geometry": {"coordinates":[-83.89978499999999,40.887305],"type":"Point"}
}