{
  "type": "Feature",
  "properties": {
    "addr:full": "595 S Main St Bluffton OH 45817",
    "addr:housenumber": "595",
    "addr:postcode": "45817",
    "addr:street": "S Main St",
    "iso:country": "US",
    "sg:address": "595 S Main St",
    "sg:city": "Bluffton",
    "sg:classifiers": [
      {
        "category": "Restaurant",
        "type": "Food \u0026 Drink"
      }
    ],
    "sg:phone": "+1 419 369 4050",
    "sg:postcode": "45817",
    "sg:province": "OH",
    "wof:name": "Bluffton Dari Freeze",
    "wof:placetype": "venue"
  },
  "geometry": {"coordinates":[-83.899785,40.887305],"type":"Point"}
}
