{
  "type": "Feature",
  "properties": {
    "iso:country":"US",
    "sg:address":"9090 State Rte 48",
    "sg:city":"Dayton",
    "sg:classifiers":[
        {
            "category":"Wholesale",
            "subcategory":"Computers",
            "type":"Manufacturing & Wholesale Goods"
        }
    ],
    "sg:phone":"+1 937 339 6644",
    "sg:postcode":"45458",
    "sg:province":"OH",
    "sg:website":"www.quanexus.com",
    "wof:name":"Quanexus",
    "wof:placetype":"venue"
},
  "geometry": {"coordinates":[-84.160375,39.611868],"type":"Point"}
}