{
  "type": "Feature",
  "properties": {
    "addr:full":"2680 Cory Ave Akron OH 44314",
    "addr:housenumber":"2680",
    "addr:postcode":"44314",
    "addr:street":"Cory Ave",
    "iso:country":"US",
    "sg:address":"2680 Cory Ave",
    "sg:city":"Akron",
    "sg:classifiers":[
        {
            "category":"Manufacturing",
            "subcategory":"Tools & Machinery",
            "type":"Manufacturing & Wholesale Goods"
        }
    ],
    "sg:phone":"+1 330 745 9045",
    "sg:postcode":"44314",
    "sg:province":"OH",
    "sg:tags":[
        "mold"
    ],
    "wof:name":"Manchester Products Inc",
    "wof:placetype":"venue"
},
  "geometry": {"coordinates":[-81.56671,41.031473],"type":"Point"}
}