{
  "type": "Feature",
  "properties": {
    "iso:country":"US",
    "sg:address":"3252 Haskell Dr",
    "sg:city":"Columbus",
    "sg:classifiers":[
        {
            "category":"Manufacturing",
            "subcategory":"Apparel",
            "type":"Manufacturing & Wholesale Goods"
        }
    ],
    "sg:phone":"+1 614 471 1348",
    "sg:postcode":"43219",
    "sg:province":"OH",
    "sg:tags":[
        "mfg"
    ],
    "wof:name":"Joyces Hats",
    "wof:placetype":"venue"
},
  "geometry": {"coordinates":[-82.92616,40.024989],"type":"Point"}
}