{
  "type": "Feature",
  "properties": {
    "iso:country":"US",
    "sg:address":"1257 E Canal St",
    "sg:city":"Nelsonville",
    "sg:classifiers":[
        {
            "category":"Health Services",
            "subcategory":"Chiropractor",
            "type":"Services"
        }
    ],
    "sg:phone":"+1 740 753 1902",
    "sg:postcode":"45764",
    "sg:province":"OH",
    "wof:name":"ABC Chiropractic Ltd",
    "wof:placetype":"venue"
},
  "geometry": {"coordinates":[-82.216563,39.447077],"type":"Point"}
}