{
  "type": "Feature",
  "properties": {
    "addr:full": "16205 Hilliard Rd Cleveland OH 44107",
    "addr:housenumber": "16205",
    "addr:postcode": "44107",
    "addr:street": "Hilliard Rd",
    "iso:country": "US",
    "sg:address": "16205 Hilliard Rd",
    "sg:city": "Cleveland",
    "sg:classifiers": [
      {
        "category": "Building \u0026 Trades",
        "subcategory": "Equipment Rental",
        "type": "Services"
      }
    ],
    "sg:phone": "+1 216 226 7368",
    "sg:postcode": "44107",
    "sg:province": "OH",
    "sg:tags": [
      "contractor"
    ],
    "wof:name": "Alternative Rental \u0026 Svc",
    "wof:placetype": "venue"
  },
  "geometry": {"coordinates":[-81.810147,41.476592],"type":"Point"}
}
