{
  "type": "Feature",
  "properties": {
    "iso:country":"US",
    "sg:address":"67 W Vine St",
    "sg:city":"Alliance",
    "sg:classifiers":[
        {
            "category":"Manufacturing",
            "subcategory":"Tools & Machinery",
            "type":"Manufacturing & Wholesale Goods"
        },
        {
            "category":"Shopping",
            "subcategory":"Computers & Home Electronics",
            "type":"Retail Goods"
        }
    ],
    "sg:phone":"+1 330 454 2020",
    "sg:postcode":"44601",
    "sg:province":"OH",
    "sg:tags":[
        "equipment",
        "dealer"
    ],
    "wof:name":"Alliance Computer Exchange",
    "wof:placetype":"venue"
},
  "geometry": {"coordinates":[-81.106084,40.930502],"type":"Point"}
}