{
  "type": "Feature",
  "properties": {
    "addr:full": "67 W Vine St Alliance OH 44601",
    "addr:housenumber": "67",
    "addr:postcode": "44601",
    "addr:street": "W Vine St",
    "iso:country": "US",
    "sg:address": "67 W Vine St",
    "sg:city": "Alliance",
    "sg:classifiers": [
      {
        "category": "Manufacturing",
        "subcategory": "Tools \u0026 Machinery",
        "type": "Manufacturing \u0026 Wholesale Goods"
      },
      {
        "category": "Shopping",
        "subcategory": "Computers \u0026 Home Electronics",
        "type": "Retail Goods"
      }
    ],
    "sg:phone": "+1 330 454 2020",
    "sg:postcode": "44601",
    "sg:province": "OH",
    "sg:tags": [
      "equipment",
      "dealer"
    ],
    "wof:name": "Alliance Computer Exchange",
    "wof:placetype": "venue"
  },
  "geometry": {"coordinates":[-81.106084,40.930502],"type":"Point"}
}
