{
  "type": "Feature",
  "properties": {
    "addr:full": "1713 NE Catawba Rd Port Clinton OH 43452",
    "addr:housenumber": "1713",
    "addr:postcode": "43452",
    "addr:street": "Ne Catawba Rd",
    "iso:country": "US",
    "sg:address": "1713 NE Catawba Rd",
    "sg:city": "Port Clinton",
    "sg:classifiers": [
      {
        "category": "Shopping",
        "subcategory": "Bicycles \u0026 Sporting Goods",
        "type": "Retail Goods"
      }
    ],
    "sg:phone": "+1 419 797 2455",
    "sg:postcode": "43452",
    "sg:province": "OH",
    "sg:tags": [
      "equipment",
      "liquor",
      "bait",
      "fishing"
    ],
    "wof:name": "Herb's Sportsman's Supply",
    "wof:placetype": "venue"
  },
  "geometry": {"coordinates":[-82.845656,41.54643],"type":"Point"}
}
