{
  "type": "Feature",
  "properties": {
    "addr:full": "7035 Columbia Rd Olmsted Falls OH 44138",
    "addr:housenumber": "7035",
    "addr:postcode": "44138",
    "addr:street": "Columbia Rd",
    "iso:country": "US",
    "sg:address": "7035 Columbia Rd",
    "sg:city": "Olmsted Falls",
    "sg:classifiers": [
      {
        "category": "Professional",
        "type": "Services"
      }
    ],
    "sg:phone": "+1 440 235 5025",
    "sg:postcode": "44138",
    "sg:province": "OH",
    "wof:name": "Leprechaun Foundation Inc",
    "wof:placetype": "venue"
  },
  "geometry": {"coordinates":[-81.903016,41.387744],"type":"Point"}
}
