{
  "type": "Feature",
  "properties": {
    "iso:country":"US",
    "sg:address":"4574 Broadview Rd",
    "sg:city":"Cleveland",
    "sg:classifiers":[
        {
            "category":"Retail",
            "subcategory":"Repair Shop",
            "type":"Services"
        }
    ],
    "sg:phone":"+1 216 741 0188",
    "sg:postcode":"44109",
    "sg:province":"OH",
    "sg:tags":[
        "equipment"
    ],
    "wof:name":"Roppel's Services Inc",
    "wof:placetype":"venue"
},
  "geometry": {"coordinates":[-81.697422,41.431368],"type":"Point"}
}