{
  "type": "Feature",
  "properties": {
    "iso:country":"US",
    "sg:address":"36 W Main St",
    "sg:city":"Xenia",
    "sg:classifiers":[
        {
            "category":"Food & Beverages",
            "subcategory":"Bakery",
            "type":"Retail Goods"
        }
    ],
    "sg:phone":"+1 937 376 1082",
    "sg:postcode":"45385",
    "sg:province":"OH",
    "wof:name":"Mehaffies Pies",
    "wof:placetype":"venue"
},
  "geometry": {"coordinates":[-83.930549,39.684955],"type":"Point"}
}