{
  "type": "Feature",
  "properties": {
    "addr:full": "8626 Ravenna Rd Twinsburg OH 44087",
    "addr:housenumber": "8626",
    "addr:postcode": "44087",
    "addr:street": "Ravenna Rd",
    "iso:country": "US",
    "sg:address": "8626 Ravenna Rd",
    "sg:city": "Twinsburg",
    "sg:classifiers": [
      {
        "category": "Building \u0026 Trades",
        "subcategory": "Landscaping Services",
        "type": "Services"
      }
    ],
    "sg:phone": "+1 330 963 5988",
    "sg:postcode": "44087",
    "sg:province": "OH",
    "sg:tags": [
      "landscape",
      "contractor"
    ],
    "wof:name": "Tishma Landscaping",
    "wof:placetype": "venue"
  },
  "geometry": {"coordinates":[-81.411784,41.296474],"type":"Point"}
}
