{
  "type": "Feature",
  "properties": {
    "addr:full":"3975 Main St Hilliard OH 43026",
    "addr:housenumber":"3975",
    "addr:postcode":"43026",
    "addr:street":"Main St",
    "iso:country":"US",
    "sg:address":"3975 Main St",
    "sg:city":"Hilliard",
    "sg:classifiers":[
        {
            "category":"Food & Beverages",
            "subcategory":"Liquor & Beverages",
            "type":"Retail Goods"
        }
    ],
    "sg:phone":"+1 614 771 7096",
    "sg:postcode":"43026",
    "sg:province":"OH",
    "sg:tags":[
        "beer",
        "ale"
    ],
    "wof:name":"L & S Carry Out",
    "wof:placetype":"venue"
},
  "geometry": {"coordinates":[-83.1614,40.03098],"type":"Point"}
}