{
  "type": "Feature",
  "properties": {
    "iso:country":"US",
    "sg:address":"429 Cleveland Rd W",
    "sg:city":"Huron",
    "sg:classifiers":[
        {
            "category":"Wholesale",
            "subcategory":"Drugs",
            "type":"Manufacturing & Wholesale Goods"
        }
    ],
    "sg:phone":"+1 419 433 0775",
    "sg:postcode":"44839",
    "sg:province":"OH",
    "sg:tags":[
        "merchandise"
    ],
    "wof:name":"Mary Kay Inc",
    "wof:placetype":"venue"
},
  "geometry": {"coordinates":[-82.559162,41.397263],"type":"Point"}
}