{
  "type": "Feature",
  "properties": {
    "addr:full":"1931 W 25th St Cleveland OH 44113",
    "addr:housenumber":"1931",
    "addr:postcode":"44113",
    "addr:street":"W 25Th St",
    "iso:country":"US",
    "sg:address":"1931 W 25th St",
    "sg:city":"Cleveland",
    "sg:classifiers":[
        {
            "category":"Professional",
            "subcategory":"Art Services",
            "type":"Services"
        }
    ],
    "sg:phone":"+1 216 621 6868",
    "sg:postcode":"44113",
    "sg:province":"OH",
    "sg:tags":[
        "graphic",
        "designer"
    ],
    "wof:name":"Poleo Design",
    "wof:placetype":"venue"
},
  "geometry": {"coordinates":[-81.70380299999999,41.484855],"type":"Point"}
}