{
  "type": "Feature",
  "properties": {
    "addr:full":"61302 Southgate Rd Cambridge OH 43725",
    "addr:housenumber":"61302",
    "addr:postcode":"43725",
    "addr:street":"Southgate Rd",
    "iso:country":"US",
    "sg:address":"61302 Southgate Rd",
    "sg:city":"Cambridge",
    "sg:classifiers":[
        {
            "category":"Ice Cream",
            "type":"Food & Drink"
        }
    ],
    "sg:menulink":"http://www.allmenus.com/oh/jackson/165254-dairy-queen/menu/",
    "sg:phone":"+1 740 435 8070",
    "sg:postcode":"43725",
    "sg:province":"OH",
    "sg:tags":[
        "burger",
        "american"
    ],
    "wof:name":"Dairy Queen",
    "wof:placetype":"venue"
},
  "geometry": {"coordinates":[-81.573275,39.990376],"type":"Point"}
}