{
  "type": "Feature",
  "properties": {
    "addr:full": "250 Federal Plz E Youngstown OH 44503",
    "addr:housenumber": "250",
    "addr:postcode": "44503",
    "addr:street": "Federal Plz E",
    "iso:country": "US",
    "sg:address": "250 Federal Plz E",
    "sg:city": "Youngstown",
    "sg:classifiers": [
      {
        "category": "Shopping",
        "subcategory": "Computers \u0026 Home Electronics",
        "type": "Retail Goods"
      }
    ],
    "sg:phone": "+1 330 742 3800",
    "sg:postcode": "44503",
    "sg:province": "OH",
    "sg:tags": [
      "software"
    ],
    "wof:name": "I Bm Corp",
    "wof:placetype": "venue"
  },
  "geometry": {"coordinates":[-80.645327,41.098321],"type":"Point"}
}
