{
  "type": "Feature",
  "properties": {
    "iso:country":"US",
    "sg:address":"250 Federal Plz E",
    "sg:city":"Youngstown",
    "sg:classifiers":[
        {
            "category":"Shopping",
            "subcategory":"Computers & Home Electronics",
            "type":"Retail Goods"
        }
    ],
    "sg:phone":"+1 330 742 3800",
    "sg:postcode":"44503",
    "sg:province":"OH",
    "sg:tags":[
        "software"
    ],
    "wof:name":"I Bm Corp",
    "wof:placetype":"venue"
},
  "geometry": {"coordinates":[-80.64532699999999,41.098321],"type":"Point"}
}