{
  "type": "Feature",
  "properties": {
    "iso:country":"US",
    "sg:address":"50 Town Sq",
    "sg:city":"Lima",
    "sg:classifiers":[
        {
            "category":"Government",
            "subcategory":"Office",
            "type":"Public Place"
        }
    ],
    "sg:phone":"+1 419 221 5140",
    "sg:postcode":"45801",
    "sg:province":"OH",
    "sg:tags":[
        "general"
    ],
    "wof:name":"Purchasing Department",
    "wof:placetype":"venue"
},
  "geometry": {"coordinates":[-84.10396,40.740346],"type":"Point"}
}