{
  "type": "Feature",
  "properties": {
    "addr:full": "26000 Euclid Ave Euclid OH 44132",
    "addr:housenumber": "26000",
    "addr:postcode": "44132",
    "addr:street": "Euclid Ave",
    "iso:country": "US",
    "sg:address": "26000 Euclid Ave",
    "sg:city": "Euclid",
    "sg:classifiers": [
      {
        "category": "Ice Cream",
        "type": "Food \u0026 Drink"
      }
    ],
    "sg:menulink": "http://www.allmenus.com/oh/euclid/175715-dairy-queen/menu/",
    "sg:phone": "+1 216 731 5394",
    "sg:postcode": "44132",
    "sg:province": "OH",
    "sg:tags": [
      "burger",
      "american"
    ],
    "wof:name": "Dairy Queen",
    "wof:placetype": "venue"
  },
  "geometry": {"coordinates":[-81.50254,41.587527],"type":"Point"}
}
