{
  "type": "Feature",
  "properties": {
    "addr:full": "1230 S Expressway Dr Toledo OH 43608",
    "addr:housenumber": "1230",
    "addr:postcode": "43608",
    "addr:street": "S Expressway Dr",
    "iso:country": "US",
    "sg:address": "1230 S Expressway Dr",
    "sg:city": "Toledo",
    "sg:classifiers": [
      {
        "category": "Manufacturing",
        "subcategory": "Rubber \u0026 Plastics",
        "type": "Manufacturing \u0026 Wholesale Goods"
      }
    ],
    "sg:phone": "+1 419 727 8320",
    "sg:postcode": "43608",
    "sg:province": "OH",
    "wof:name": "Jensar Manufacturing",
    "wof:placetype": "venue"
  },
  "geometry": {"coordinates":[-83.518262,41.687402],"type":"Point"}
}
