{
  "type": "Feature",
  "properties": {
    "addr:full":"5730 Springboro Pike Dayton OH 45449",
    "addr:housenumber":"5730",
    "addr:postcode":"45449",
    "addr:street":"Springboro Pike",
    "iso:country":"US",
    "sg:address":"5730 Springboro Pike",
    "sg:city":"Dayton",
    "sg:classifiers":[
        {
            "category":"Personal",
            "subcategory":"Tanning Parlor",
            "type":"Services"
        }
    ],
    "sg:phone":"+1 937 299 1225",
    "sg:postcode":"45449",
    "sg:province":"OH",
    "sg:tags":[
        "salon"
    ],
    "wof:name":"A Place To Tan",
    "wof:placetype":"venue"
},
  "geometry": {"coordinates":[-84.221492,39.677257],"type":"Point"}
}