{
  "type": "Feature",
  "properties": {
    "iso:country":"US",
    "sg:address":"115 S Market St",
    "sg:city":"Van Wert",
    "sg:classifiers":[
        {
            "category":"Retail",
            "subcategory":"Repair Shop",
            "type":"Services"
        }
    ],
    "sg:phone":"+1 419 232 6383",
    "sg:postcode":"45891",
    "sg:province":"OH",
    "sg:tags":[
        "co",
        "golf",
        "public"
    ],
    "wof:name":"Gold Tee Indoor Golf Center",
    "wof:placetype":"venue"
},
  "geometry": {"coordinates":[-84.58087,40.869516],"type":"Point"}
}