{
  "type": "Feature",
  "properties": {
    "iso:country":"US",
    "sg:address":"13531 Lorain Ave",
    "sg:city":"Cleveland",
    "sg:classifiers":[
        {
            "category":"Retail",
            "subcategory":"Self-service Laundry",
            "type":"Services"
        }
    ],
    "sg:phone":"+1 216 476 1172",
    "sg:postcode":"44111",
    "sg:province":"OH",
    "wof:name":"Johnson's Coin Laundry",
    "wof:placetype":"venue"
},
  "geometry": {"coordinates":[-81.784948,41.456671],"type":"Point"}
}