{
  "type": "Feature",
  "properties": {
    "addr:full": "225 3rd St Elyria OH 44035",
    "addr:housenumber": "225",
    "addr:postcode": "44035",
    "addr:street": "3Rd St",
    "iso:country": "US",
    "sg:address": "225 3rd St",
    "sg:city": "Elyria",
    "sg:classifiers": [
      {
        "category": "Government",
        "subcategory": "Office",
        "type": "Public Place"
      }
    ],
    "sg:phone": "+1 440 329 5389",
    "sg:postcode": "44035",
    "sg:province": "OH",
    "wof:name": "Lorain County Prosecutor",
    "wof:placetype": "venue"
  },
  "geometry": {"coordinates":[-82.106345,41.365449],"type":"Point"}
}
