{
  "type": "Feature",
  "properties": {
    "addr:full": "7236 Fitzwilliam Dr Dublin OH 43017",
    "addr:housenumber": "7236",
    "addr:postcode": "43017",
    "addr:street": "Fitzwilliam Dr",
    "iso:country": "US",
    "sg:address": "7236 Fitzwilliam Dr",
    "sg:city": "Dublin",
    "sg:classifiers": [
      {
        "category": "Professional",
        "subcategory": "Employment Agencies",
        "type": "Services"
      }
    ],
    "sg:phone": "+1 614 798 0431",
    "sg:postcode": "43017",
    "sg:province": "OH",
    "sg:tags": [
      "consultant",
      "search",
      "executive"
    ],
    "wof:name": "R Wegesin \u0026 Assoc",
    "wof:placetype": "venue"
  },
  "geometry": {"coordinates":[-83.140969,40.116195],"type":"Point"}
}
