{
  "type": "Feature",
  "properties": {
    "addr:full": "370 E 222nd St Euclid OH 44123",
    "addr:housenumber": "370",
    "addr:postcode": "44123",
    "addr:street": "E 222Nd St",
    "iso:country": "US",
    "sg:address": "370 E 222nd St",
    "sg:city": "Euclid",
    "sg:classifiers": [
      {
        "category": "Building \u0026 Trades",
        "subcategory": "Landscaping Services",
        "type": "Services"
      }
    ],
    "sg:phone": "+1 216 731 8585",
    "sg:postcode": "44123",
    "sg:province": "OH",
    "sg:tags": [
      "consultant",
      "designer",
      "landscape",
      "contractor"
    ],
    "wof:name": "Dureiko Landscape Contractors Inc",
    "wof:placetype": "venue"
  },
  "geometry": {"coordinates":[-81.526847,41.604814],"type":"Point"}
}
