{
  "type": "Feature",
  "properties": {
    "addr:full": "1136 Montgomery Rd NE Newark OH 43055",
    "addr:housenumber": "1136",
    "addr:postcode": "43055",
    "addr:street": "Montgomery Rd Ne",
    "iso:country": "US",
    "sg:address": "1136 Montgomery Rd NE",
    "sg:city": "Newark",
    "sg:classifiers": [
      {
        "category": "Wholesale",
        "subcategory": "Machinery \u0026 Supplies",
        "type": "Manufacturing \u0026 Wholesale Goods"
      }
    ],
    "sg:phone": "+1 740 763 0264",
    "sg:postcode": "43055",
    "sg:province": "OH",
    "sg:tags": [
      "equipment",
      "industrial"
    ],
    "wof:name": "Steven Waspe",
    "wof:placetype": "venue"
  },
  "geometry": {"coordinates":[-82.309929,40.0749],"type":"Point"}
}
