{
  "type": "Feature",
  "properties": {
    "addr:full": "440 Dayton Towers Dr Dayton OH 45410",
    "addr:housenumber": "440",
    "addr:postcode": "45410",
    "addr:street": "Dayton Towers Dr",
    "iso:country": "US",
    "sg:address": "440 Dayton Towers Dr",
    "sg:city": "Dayton",
    "sg:classifiers": [
      {
        "category": "Professional",
        "type": "Services"
      }
    ],
    "sg:phone": "+1 937 223 2917",
    "sg:postcode": "45410",
    "sg:province": "OH",
    "wof:name": "G Shafer",
    "wof:placetype": "venue"
  },
  "geometry": {"coordinates":[-84.178334,39.756967],"type":"Point"}
}
