{
  "type": "Feature",
  "properties": {
    "addr:full":"3475 Forest Lake Dr Uniontown OH 44685",
    "addr:housenumber":"3475",
    "addr:postcode":"44685",
    "addr:street":"Forest Lake Dr",
    "iso:country":"US",
    "sg:address":"3475 Forest Lake Dr",
    "sg:city":"Uniontown",
    "sg:classifiers":[
        {
            "category":"Shopping",
            "subcategory":"Department Store",
            "type":"Retail Goods"
        }
    ],
    "sg:phone":"+1 330 677 8801",
    "sg:postcode":"44685",
    "sg:province":"OH",
    "sg:tags":[
        "club",
        "wholesale"
    ],
    "wof:name":"U Cc Total Home Of Akron",
    "wof:placetype":"venue"
},
  "geometry": {"coordinates":[-81.471068,40.966132],"type":"Point"}
}