{
  "type": "Feature",
  "properties": {
    "addr:full": "23792 Center Ridge Rd Cleveland OH 44145",
    "addr:housenumber": "23792",
    "addr:postcode": "44145",
    "addr:street": "Center Ridge Rd",
    "iso:country": "US",
    "sg:address": "23792 Center Ridge Rd",
    "sg:city": "Cleveland",
    "sg:classifiers": [
      {
        "category": "Autos \u0026 Motor Vehicles",
        "subcategory": "Auto Supplies",
        "type": "Retail Goods"
      },
      {
        "category": "Wholesale",
        "subcategory": "Auto Parts",
        "type": "Manufacturing \u0026 Wholesale Goods"
      }
    ],
    "sg:phone": "+1 440 835 3539",
    "sg:postcode": "44145",
    "sg:province": "OH",
    "sg:tags": [
      "equipment",
      "truck"
    ],
    "wof:name": "Cleveland Off Road Equipment",
    "wof:placetype": "venue"
  },
  "geometry": {"coordinates":[-81.886656,41.457512],"type":"Point"}
}
