{
  "type": "Feature",
  "properties": {
    "iso:country":"US",
    "sg:address":"5950 Birdsall Rd",
    "sg:city":"Toledo",
    "sg:classifiers":[
        {
            "category":"Retail",
            "subcategory":"Auto Repair",
            "type":"Services"
        }
    ],
    "sg:phone":"+1 419 476 4581",
    "sg:postcode":"43612",
    "sg:province":"OH",
    "sg:tags":[
        "repairing",
        "automobile"
    ],
    "wof:name":"Krueger's Collision",
    "wof:placetype":"venue"
},
  "geometry": {"coordinates":[-83.533176,41.724341],"type":"Point"}
}