{
  "type": "Feature",
  "properties": {
    "addr:full":"1415 Grandin Rd Maineville OH 45039",
    "addr:housenumber":"1415",
    "addr:postcode":"45039",
    "addr:street":"Grandin Rd",
    "iso:country":"US",
    "sg:address":"1415 Grandin Rd",
    "sg:city":"Maineville",
    "sg:classifiers":[
        {
            "category":"Real Estate",
            "subcategory":"Real Estate Agent",
            "type":"Services"
        }
    ],
    "sg:phone":"+1 513 677 8181",
    "sg:postcode":"45039",
    "sg:province":"OH",
    "wof:name":"Kings Mills Commerce Park",
    "wof:placetype":"venue"
},
  "geometry": {"coordinates":[-84.24125100000001,39.350754],"type":"Point"}
}