{
  "type": "Feature",
  "properties": {
    "addr:full": "1260 Center St Ashland OH 44805",
    "addr:housenumber": "1260",
    "addr:postcode": "44805",
    "addr:street": "Center St",
    "iso:country": "US",
    "sg:address": "1260 Center St",
    "sg:city": "Ashland",
    "sg:classifiers": [
      {
        "category": "Government",
        "subcategory": "Office",
        "type": "Public Place"
      }
    ],
    "sg:phone": "+1 419 281 9405",
    "sg:postcode": "44805",
    "sg:province": "OH",
    "sg:tags": [
      "general"
    ],
    "wof:name": "Juvenile Court",
    "wof:placetype": "venue"
  },
  "geometry": {"coordinates":[-82.309732,40.8573],"type":"Point"}
}
