{
  "type": "Feature",
  "properties": {
    "iso:country":"US",
    "sg:address":"6583 N Ridge Rd",
    "sg:city":"Madison",
    "sg:classifiers":[
        {
            "category":"Restaurant",
            "type":"Food & Drink"
        }
    ],
    "sg:phone":"+1 440 428 2852",
    "sg:postcode":"44057",
    "sg:province":"OH",
    "sg:tags":[
        "eating"
    ],
    "wof:name":"Ming Moon Chinese Restaurant",
    "wof:placetype":"venue"
},
  "geometry": {"coordinates":[-81.050567,41.802482],"type":"Point"}
}