{
  "type": "Feature",
  "properties": {
    "iso:country":"US",
    "sg:address":"3177 Westfield-Fulton Rd",
    "sg:city":"Cardington",
    "sg:classifiers":[
        {
            "category":"Farming",
            "subcategory":"Farm",
            "type":"Manufacturing & Wholesale Goods"
        }
    ],
    "sg:phone":"+1 419 864 3360",
    "sg:postcode":"43315",
    "sg:province":"OH",
    "sg:tags":[
        "crop",
        "general"
    ],
    "wof:name":"Beje Farms",
    "wof:placetype":"venue"
},
  "geometry": {"coordinates":[-82.869918,40.437327],"type":"Point"}
}