{
  "type": "Feature",
  "properties": {
    "addr:full": "925 Trailwood Dr Youngstown OH 44512",
    "addr:housenumber": "925",
    "addr:postcode": "44512",
    "addr:street": "Trailwood Dr",
    "iso:country": "US",
    "sg:address": "925 Trailwood Dr",
    "sg:city": "Youngstown",
    "sg:classifiers": [
      {
        "category": "Health Services",
        "subcategory": "Doctor",
        "type": "Services"
      }
    ],
    "sg:phone": "+1 330 758 7575",
    "sg:postcode": "44512",
    "sg:province": "OH",
    "sg:tags": [
      "physician",
      "surgeons",
      "disease",
      "internal",
      "medicine",
      "surgeon",
      "pulmonary"
    ],
    "wof:name": "Pulmonary Rehabilitation Associates",
    "wof:placetype": "venue"
  },
  "geometry": {"coordinates":[-80.638674,41.027489],"type":"Point"}
}
