{
  "type": "Feature",
  "properties": {
    "addr:full": "2490 Shawnee Rd Lima OH 45806",
    "addr:housenumber": "2490",
    "addr:postcode": "45806",
    "addr:street": "Shawnee Rd",
    "iso:country": "US",
    "sg:address": "2490 Shawnee Rd",
    "sg:city": "Lima",
    "sg:classifiers": [
      {
        "category": "Restaurant",
        "type": "Food \u0026 Drink"
      }
    ],
    "sg:menulink": "http://www.allmenus.com/oh/shawnee/170305-burger-king/menu/",
    "sg:phone": "+1 419 228 4880",
    "sg:postcode": "45806",
    "sg:province": "OH",
    "sg:tags": [
      "burger",
      "american"
    ],
    "wof:name": "Burger King",
    "wof:placetype": "venue"
  },
  "geometry": {"coordinates":[-84.151401,40.704117],"type":"Point"}
}
