{
  "type": "Feature",
  "properties": {
    "addr:full": "6649 Belleshire St Columbus OH 43229",
    "addr:housenumber": "6649",
    "addr:postcode": "43229",
    "addr:street": "Belleshire St",
    "iso:country": "US",
    "sg:address": "6649 Belleshire St",
    "sg:city": "Columbus",
    "sg:classifiers": [
      {
        "category": "Manufacturing",
        "subcategory": "Rubber \u0026 Plastics",
        "type": "Manufacturing \u0026 Wholesale Goods"
      }
    ],
    "sg:phone": "+1 614 794 9793",
    "sg:postcode": "43229",
    "sg:province": "OH",
    "sg:tags": [
      "product",
      "metal",
      "molded",
      "mfg"
    ],
    "wof:name": "Barry Wright Corporation",
    "wof:placetype": "venue"
  },
  "geometry": {"coordinates":[-82.960873,40.105797],"type":"Point"}
}
