{
  "type": "Feature",
  "properties": {
    "addr:full":"30010 Lake Shore Blvd Willowick OH 44095",
    "addr:housenumber":"30010",
    "addr:postcode":"44095",
    "addr:street":"Lake Shore Blvd",
    "iso:country":"US",
    "sg:address":"30010 Lake Shore Blvd",
    "sg:city":"Willowick",
    "sg:classifiers":[
        {
            "category":"Food & Beverages",
            "subcategory":"Specialty",
            "type":"Retail Goods"
        }
    ],
    "sg:phone":"+1 440 585 8580",
    "sg:postcode":"44095",
    "sg:province":"OH",
    "sg:tags":[
        "health",
        "diet"
    ],
    "wof:name":"GNC",
    "wof:placetype":"venue"
},
  "geometry": {"coordinates":[-81.480013,41.632527],"type":"Point"}
}