{
  "type": "Feature",
  "properties": {
    "iso:country":"US",
    "sg:address":"1170 Sweitzer St",
    "sg:city":"Greenville",
    "sg:classifiers":[
        {
            "category":"Shopping",
            "type":"Retail Goods"
        }
    ],
    "sg:phone":"+1 937 548 8856",
    "sg:postcode":"45331",
    "sg:province":"OH",
    "wof:name":"Designer Pets",
    "wof:placetype":"venue"
},
  "geometry": {"coordinates":[-84.634356,40.083923],"type":"Point"}
}