{
  "type": "Feature",
  "properties": {
    "addr:full":"133 Martha St Yorkville OH 43971",
    "addr:housenumber":"133",
    "addr:postcode":"43971",
    "addr:street":"Martha St",
    "iso:country":"US",
    "sg:address":"133 Martha St",
    "sg:city":"Yorkville",
    "sg:classifiers":[
        {
            "category":"Health Services",
            "subcategory":"Health Practitioner",
            "type":"Services"
        }
    ],
    "sg:phone":"+1 740 859 5059",
    "sg:postcode":"43971",
    "sg:province":"OH",
    "sg:tags":[
        "therapist",
        "physical"
    ],
    "wof:name":"Valley Physical Therapy",
    "wof:placetype":"venue"
},
  "geometry": {"coordinates":[-80.70646499999999,40.160977],"type":"Point"}
}