{
  "type": "Feature",
  "properties": {
    "addr:full": "555 Stumbo Rd N Mansfield OH 44906",
    "addr:housenumber": "555",
    "addr:postcode": "44906",
    "addr:street": "Stumbo Rd N",
    "iso:country": "US",
    "sg:address": "555 Stumbo Rd N",
    "sg:city": "Mansfield",
    "sg:classifiers": [
      {
        "category": "Government",
        "subcategory": "Police Station",
        "type": "Public Place"
      }
    ],
    "sg:phone": "+1 419 529 2115",
    "sg:postcode": "44906",
    "sg:province": "OH",
    "sg:tags": [
      "department"
    ],
    "wof:name": "Police Dept",
    "wof:placetype": "venue"
  },
  "geometry": {"coordinates":[-82.596941,40.766548],"type":"Point"}
}
