{
  "type": "Feature",
  "properties": {
    "addr:full": "1253 Morse Rd Columbus OH 43229",
    "addr:housenumber": "1253",
    "addr:postcode": "43229",
    "addr:street": "Morse Rd",
    "iso:country": "US",
    "sg:address": "1253 Morse Rd",
    "sg:city": "Columbus",
    "sg:classifiers": [
      {
        "category": "Education",
        "subcategory": "Special Training",
        "type": "Public Place"
      }
    ],
    "sg:phone": "+1 614 784 1988",
    "sg:postcode": "43229",
    "sg:province": "OH",
    "sg:tags": [
      "instruction",
      "music"
    ],
    "sg:website": "www.columbusmusicacademy.com",
    "wof:name": "Columbus Music Academy LTD",
    "wof:placetype": "venue"
  },
  "geometry": {"coordinates":[-82.984375,40.06092],"type":"Point"}
}
