{
  "type": "Feature",
  "properties": {
    "addr:full":"372 Hampshire Dr Hamilton OH 45011",
    "addr:housenumber":"372",
    "addr:postcode":"45011",
    "addr:street":"Hampshire Dr",
    "iso:country":"US",
    "sg:address":"372 Hampshire Dr",
    "sg:city":"Hamilton",
    "sg:classifiers":[
        {
            "category":"Banks & Credit Unions",
            "subcategory":"Investment Brokerage",
            "type":"Services"
        }
    ],
    "sg:phone":"+1 513 737 2542",
    "sg:postcode":"45011",
    "sg:province":"OH",
    "sg:tags":[
        "security"
    ],
    "wof:name":"Jaron Joiner",
    "wof:placetype":"venue"
},
  "geometry": {"coordinates":[-84.5334,39.387314],"type":"Point"}
}