{
  "type": "Feature",
  "properties": {
    "addr:full":"1450 Bethel Rd Columbus OH 43220",
    "addr:housenumber":"1450",
    "addr:postcode":"43220",
    "addr:street":"Bethel Rd",
    "iso:country":"US",
    "sg:address":"1450 Bethel Rd",
    "sg:city":"Columbus",
    "sg:classifiers":[
        {
            "category":"Restaurant",
            "type":"Food & Drink"
        }
    ],
    "sg:phone":"+1 614 273 4444",
    "sg:postcode":"43220",
    "sg:province":"OH",
    "wof:name":"Shishkebab",
    "wof:placetype":"venue"
},
  "geometry": {"coordinates":[-83.05708199999999,40.063794],"type":"Point"}
}