{
  "type": "Feature",
  "properties": {
    "addr:full":"6939 E Broad St Columbus OH 43213",
    "addr:housenumber":"6939",
    "addr:postcode":"43213",
    "addr:street":"E Broad St",
    "iso:country":"US",
    "sg:address":"6939 E Broad St",
    "sg:city":"Columbus",
    "sg:classifiers":[
        {
            "category":"Cinema",
            "subcategory":"Movie Rental",
            "type":"Entertainment"
        }
    ],
    "sg:phone":"+1 614 501 1840",
    "sg:postcode":"43213",
    "sg:province":"OH",
    "sg:tags":[
        "leasing",
        "video",
        "disc",
        "tape"
    ],
    "wof:name":"Hollywood Video",
    "wof:placetype":"venue"
},
  "geometry": {"coordinates":[-82.81566599999999,39.982478],"type":"Point"}
}