{
  "type": "Feature",
  "properties": {
    "addr:full":"600 N Main St Bellefontaine OH 43311",
    "addr:housenumber":"600",
    "addr:postcode":"43311",
    "addr:street":"N Main St",
    "iso:country":"US",
    "sg:address":"600 N Main St",
    "sg:city":"Bellefontaine",
    "sg:classifiers":[
        {
            "category":"Organizations",
            "subcategory":"Community Association",
            "type":"Services"
        }
    ],
    "sg:phone":"+1 937 592 5636",
    "sg:postcode":"43311",
    "sg:province":"OH",
    "sg:tags":[
        "fraternal"
    ],
    "wof:name":"Masonic Lodge",
    "wof:placetype":"venue"
},
  "geometry": {"coordinates":[-83.758865,40.369128],"type":"Point"}
}