{
  "type": "Feature",
  "properties": {
    "addr:full": "358 S Hamilton Rd Columbus OH 43213",
    "addr:housenumber": "358",
    "addr:postcode": "43213",
    "addr:street": "S Hamilton Rd",
    "iso:country": "US",
    "sg:address": "358 S Hamilton Rd",
    "sg:city": "Columbus",
    "sg:classifiers": [
      {
        "category": "Real Estate",
        "subcategory": "Real Estate Services",
        "type": "Services"
      },
      {
        "category": "Banks \u0026 Credit Unions",
        "subcategory": "Financial Services",
        "type": "Services"
      }
    ],
    "sg:phone": "+1 614 478 1500",
    "sg:postcode": "43213",
    "sg:province": "OH",
    "sg:tags": [
      "financing",
      "loan"
    ],
    "sg:website": "http://citi.bridgetrack.com/citifi/_redir.htm?BTData=302177C736961705A55424AB8BEBEABA298948493FBFBF6E9EAC5C2DECE67BE2\u0026BT_TRF=10467\u0026RedirectID=YLLWPGS_US_CTGRY_TRD_LNK_FNCL_SRVCS_CPC\u0026creativeID=YP_Link",
    "wof:name": "CitiFinancial",
    "wof:placetype": "venue"
  },
  "geometry": {"coordinates":[-82.875725,39.968069],"type":"Point"}
}
