{
  "type": "Feature",
  "properties": {
    "addr:full": "964 N 21st St Newark OH 43055",
    "addr:housenumber": "964",
    "addr:postcode": "43055",
    "addr:street": "N 21St St",
    "iso:country": "US",
    "sg:address": "964 N 21st St",
    "sg:city": "Newark",
    "sg:classifiers": [
      {
        "category": "Personal",
        "subcategory": "Beauty Salon",
        "type": "Services"
      }
    ],
    "sg:phone": "+1 740 366 0613",
    "sg:postcode": "43055",
    "sg:province": "OH",
    "sg:tags": [
      "manicuring"
    ],
    "wof:name": "Envi Nails",
    "wof:placetype": "venue"
  },
  "geometry": {"coordinates":[-82.428499,40.074788],"type":"Point"}
}
