{
  "type": "Feature",
  "properties": {
    "addr:full": "440 S Main St Englewood OH 45322",
    "addr:housenumber": "440",
    "addr:postcode": "45322",
    "addr:street": "S Main St",
    "iso:country": "US",
    "sg:address": "440 S Main St",
    "sg:city": "Englewood",
    "sg:classifiers": [
      {
        "category": "Professional",
        "subcategory": "Lawyer \u0026 Legal Services",
        "type": "Services"
      }
    ],
    "sg:phone": "+1 937 836 8639",
    "sg:postcode": "45322",
    "sg:province": "OH",
    "sg:tags": [
      "attorney"
    ],
    "wof:name": "Geisenfeld Law Office",
    "wof:placetype": "venue"
  },
  "geometry": {"coordinates":[-84.298542,39.873162],"type":"Point"}
}
