{
  "type": "Feature",
  "properties": {
    "addr:full":"1369 Market Ave N Canton OH 44714",
    "addr:housenumber":"1369",
    "addr:postcode":"44714",
    "addr:street":"Market Ave N",
    "iso:country":"US",
    "sg:address":"1369 Market Ave N",
    "sg:city":"Canton",
    "sg:classifiers":[
        {
            "category":"Professional",
            "subcategory":"Lawyer & Legal Services",
            "type":"Services"
        }
    ],
    "sg:phone":"+1 330 454 5612",
    "sg:postcode":"44714",
    "sg:province":"OH",
    "sg:tags":[
        "attorney"
    ],
    "wof:name":"Cranston Law Office",
    "wof:placetype":"venue"
},
  "geometry": {"coordinates":[-81.371548,40.811838],"type":"Point"}
}