{
  "type": "Feature",
  "properties": {
    "addr:full": "32360 Twp Hwy 212 Racine OH 45771",
    "addr:postcode": "32360;45771",
    "addr:street": "Twp Hwy 212",
    "iso:country": "US",
    "sg:address": "32360 Twp Hwy 212",
    "sg:city": "Racine",
    "sg:classifiers": [
      {
        "category": "Professional",
        "type": "Services"
      }
    ],
    "sg:phone": "+1 740 949 2405",
    "sg:postcode": "45771",
    "sg:province": "OH",
    "wof:name": "Edward L Nottingham",
    "wof:placetype": "venue"
  },
  "geometry": {"coordinates":[-81.930983,39.023609],"type":"Point"}
}
