{
  "type": "Feature",
  "properties": {
    "addr:full":"8759 S Raccoon Rd Canfield OH 44406",
    "addr:housenumber":"8759",
    "addr:postcode":"44406",
    "addr:street":"S Raccoon Rd",
    "iso:country":"US",
    "sg:address":"8759 S Raccoon Rd",
    "sg:city":"Canfield",
    "sg:classifiers":[
        {
            "category":"Building & Trades",
            "subcategory":"Construction",
            "type":"Services"
        }
    ],
    "sg:phone":"+1 330 533 7429",
    "sg:postcode":"44406",
    "sg:province":"OH",
    "sg:tags":[
        "general",
        "contractor"
    ],
    "wof:name":"R T Builders Inc Rich Troiano",
    "wof:placetype":"venue"
},
  "geometry": {"coordinates":[-80.73835699999999,40.993654],"type":"Point"}
}