{
  "type": "Feature",
  "properties": {
    "iso:country":"US",
    "sg:address":"4802 Turney Rd",
    "sg:city":"Cleveland",
    "sg:classifiers":[
        {
            "category":"Shopping",
            "subcategory":"Gifts & Souvenirs",
            "type":"Retail Goods"
        }
    ],
    "sg:phone":"+1 216 341 2232",
    "sg:postcode":"44125",
    "sg:province":"OH",
    "wof:name":"Ritas Touch Floral & Gift",
    "wof:placetype":"venue"
},
  "geometry": {"coordinates":[-81.61523,41.429402],"type":"Point"}
}