{
  "type": "Feature",
  "properties": {
    "addr:full": "12755 US Hwy 68 Kenton OH 43326",
    "addr:housenumber": "12755",
    "addr:postcode": "43326",
    "addr:street": "Us Hwy 68",
    "iso:country": "US",
    "sg:address": "12755 US Hwy 68",
    "sg:city": "Kenton",
    "sg:classifiers": [
      {
        "category": "Autos \u0026 Motor Vehicles",
        "subcategory": "Automobile Sales",
        "type": "Retail Goods"
      }
    ],
    "sg:phone": "+1 419 673 1133",
    "sg:postcode": "43326",
    "sg:province": "OH",
    "wof:name": "Kenton Truck \u0026 Equipment",
    "wof:placetype": "venue"
  },
  "geometry": {"coordinates":[-83.614454,40.633346],"type":"Point"}
}
