{
  "type": "Feature",
  "properties": {
    "iso:country":"US",
    "sg:address":"12755 US Hwy 68",
    "sg:city":"Kenton",
    "sg:classifiers":[
        {
            "category":"Autos & Motor Vehicles",
            "subcategory":"Automobile Sales",
            "type":"Retail Goods"
        }
    ],
    "sg:phone":"+1 419 673 1133",
    "sg:postcode":"43326",
    "sg:province":"OH",
    "wof:name":"Kenton Truck & Equipment",
    "wof:placetype":"venue"
},
  "geometry": {"coordinates":[-83.614454,40.633346],"type":"Point"}
}