{
  "type": "Feature",
  "properties": {
    "iso:country":"US",
    "sg:address":"3872 Paxton Ave",
    "sg:city":"Cincinnati",
    "sg:classifiers":[
        {
            "category":"Autos & Motor Vehicles",
            "subcategory":"Auto Supplies",
            "type":"Retail Goods"
        }
    ],
    "sg:phone":"+1 513 321 0032",
    "sg:postcode":"45209",
    "sg:province":"OH",
    "sg:tags":[
        "shop",
        "automotive",
        "tire",
        "repair"
    ],
    "wof:name":"Goodyear",
    "wof:placetype":"venue"
},
  "geometry": {"coordinates":[-84.430199,39.145853],"type":"Point"}
}