{
  "type": "Feature",
  "properties": {
    "addr:full":"760 Sugar Rd Copley OH 44321",
    "addr:housenumber":"760",
    "addr:postcode":"44321",
    "addr:street":"Sugar Rd",
    "iso:country":"US",
    "sg:address":"760 Sugar Rd",
    "sg:city":"Copley",
    "sg:classifiers":[
        {
            "category":"Wholesale",
            "subcategory":"Chemicals & Plastics",
            "type":"Manufacturing & Wholesale Goods"
        }
    ],
    "sg:phone":"+1 330 666 4057",
    "sg:postcode":"44321",
    "sg:province":"OH",
    "wof:name":"A C Chemical Distribution Inc",
    "wof:placetype":"venue"
},
  "geometry": {"coordinates":[-81.614947,41.107873],"type":"Point"}
}