{
  "type": "Feature",
  "properties": {
    "addr:full":"7633 Mentor Ave Mentor OH 44060",
    "addr:housenumber":"7633",
    "addr:postcode":"44060",
    "addr:street":"Mentor Ave",
    "iso:country":"US",
    "sg:address":"7633 Mentor Ave",
    "sg:city":"Mentor",
    "sg:classifiers":[
        {
            "category":"Shopping",
            "subcategory":"Books",
            "type":"Retail Goods"
        }
    ],
    "sg:phone":"+1 440 951 5859",
    "sg:postcode":"44060",
    "sg:province":"OH",
    "wof:name":"Family Christian Stores 395",
    "wof:placetype":"venue"
},
  "geometry": {"coordinates":[-81.365824,41.659642],"type":"Point"}
}