{
  "type": "Feature",
  "properties": {
    "iso:country":"US",
    "sg:address":"3712 Florian Dr",
    "sg:city":"Columbus",
    "sg:classifiers":[
        {
            "category":"Building & Trades",
            "subcategory":"Construction",
            "type":"Services"
        }
    ],
    "sg:phone":"+1 614 337 8959",
    "sg:postcode":"43219",
    "sg:province":"OH",
    "sg:tags":[
        "excavation",
        "contractor"
    ],
    "wof:name":"Knorwood Excavtg",
    "wof:placetype":"venue"
},
  "geometry": {"coordinates":[-82.91531000000001,40.039738],"type":"Point"}
}