{
  "type": "Feature",
  "properties": {
    "addr:full": "2608 Westrock Dr Hilliard OH 43026",
    "addr:housenumber": "2608",
    "addr:postcode": "43026",
    "addr:street": "Westrock Dr",
    "iso:country": "US",
    "sg:address": "2608 Westrock Dr",
    "sg:city": "Hilliard",
    "sg:classifiers": [
      {
        "category": "Building \u0026 Trades",
        "subcategory": "Construction",
        "type": "Services"
      }
    ],
    "sg:phone": "+1 614 771 5744",
    "sg:postcode": "43026",
    "sg:province": "OH",
    "sg:tags": [
      "house"
    ],
    "wof:name": "Homewood Homes",
    "wof:placetype": "venue"
  },
  "geometry": {"coordinates":[-83.173987,40.005406],"type":"Point"}
}
