{
  "type": "Feature",
  "properties": {
    "iso:country":"US",
    "sg:address":"34501 Aurora Rd",
    "sg:city":"Cleveland",
    "sg:classifiers":[
        {
            "category":"Professional",
            "subcategory":"Computer Services",
            "type":"Services"
        }
    ],
    "sg:phone":"+1 440 542 0652",
    "sg:postcode":"44139",
    "sg:province":"OH",
    "sg:tags":[
        "information",
        "technology"
    ],
    "wof:name":"MK2 Technologies",
    "wof:placetype":"venue"
},
  "geometry": {"coordinates":[-81.428631,41.380846],"type":"Point"}
}