{
  "type": "Feature",
  "properties": {
    "addr:full": "2971 Derr Rd Springfield OH 45503",
    "addr:housenumber": "2971",
    "addr:postcode": "45503",
    "addr:street": "Derr Rd",
    "iso:country": "US",
    "sg:address": "2971 Derr Rd",
    "sg:city": "Springfield",
    "sg:classifiers": [
      {
        "category": "Shopping",
        "type": "Retail Goods"
      }
    ],
    "sg:phone": "+1 937 390 9970",
    "sg:postcode": "45503",
    "sg:province": "OH",
    "sg:tags": [
      "cosmetic",
      "perfume"
    ],
    "sg:website": "www.merlenorman.com",
    "wof:name": "Merle Norman Cosmetics",
    "wof:placetype": "venue"
  },
  "geometry": {"coordinates":[-83.785335,39.965764],"type":"Point"}
}
