{
  "type": "Feature",
  "properties": {
    "addr:full": "9821 Olde Eight Rd Northfield OH 44067",
    "addr:housenumber": "9821",
    "addr:postcode": "44067",
    "addr:street": "Olde Eight Rd",
    "iso:country": "US",
    "sg:address": "9821 Olde Eight Rd",
    "sg:city": "Northfield",
    "sg:classifiers": [
      {
        "category": "Insurance",
        "subcategory": "Insurance Agent",
        "type": "Services"
      }
    ],
    "sg:phone": "+1 330 467 2138",
    "sg:postcode": "44067",
    "sg:province": "OH",
    "wof:name": "KERR Insurance Inc",
    "wof:placetype": "venue"
  },
  "geometry": {"coordinates":[-81.537355,41.324784],"type":"Point"}
}
