{
  "type": "Feature",
  "properties": {
    "addr:full": "5001 Mayfield Rd Cleveland OH 44124",
    "addr:housenumber": "5001",
    "addr:postcode": "44124",
    "addr:street": "Mayfield Rd",
    "iso:country": "US",
    "sg:address": "5001 Mayfield Rd",
    "sg:city": "Cleveland",
    "sg:classifiers": [
      {
        "category": "Health Services",
        "subcategory": "Health Practitioner",
        "type": "Services"
      }
    ],
    "sg:phone": "+1 216 291 4000",
    "sg:postcode": "44124",
    "sg:province": "OH",
    "sg:tags": [
      "psychologist"
    ],
    "wof:name": "Psychological Transitions",
    "wof:placetype": "venue"
  },
  "geometry": {"coordinates":[-81.497965,41.519913],"type":"Point"}
}
