{
  "type": "Feature",
  "properties": {
    "addr:full":"3233 N Kemp Rd Elida OH 45807",
    "addr:housenumber":"3233",
    "addr:postcode":"45807",
    "addr:street":"N Kemp Rd",
    "iso:country":"US",
    "sg:address":"3233 N Kemp Rd",
    "sg:city":"Elida",
    "sg:classifiers":[
        {
            "category":"Home & Garden",
            "subcategory":"Building Materials",
            "type":"Retail Goods"
        },
        {
            "category":"Building & Trades",
            "subcategory":"Construction",
            "type":"Services"
        }
    ],
    "sg:phone":"+1 419 339 3909",
    "sg:postcode":"45807",
    "sg:province":"OH",
    "sg:tags":[
        "carpentry",
        "door",
        "contractor"
    ],
    "wof:name":"Bi Rite Overhead Doors",
    "wof:placetype":"venue"
},
  "geometry": {"coordinates":[-84.22378999999999,40.777123],"type":"Point"}
}