{
  "type": "Feature",
  "properties": {
    "addr:full": "213 N 8th St Cambridge OH 43725",
    "addr:housenumber": "213",
    "addr:postcode": "43725",
    "addr:street": "N 8Th St",
    "iso:country": "US",
    "sg:address": "213 N 8th St",
    "sg:city": "Cambridge",
    "sg:classifiers": [
      {
        "category": "Professional",
        "subcategory": "Lawyer \u0026 Legal Services",
        "type": "Services"
      }
    ],
    "sg:phone": "+1 740 432 7844",
    "sg:postcode": "43725",
    "sg:province": "OH",
    "sg:tags": [
      "attorney"
    ],
    "sg:website": "www.fmcclurelaw.com",
    "wof:name": "Frank A Mc Clure Co Lpa",
    "wof:placetype": "venue"
  },
  "geometry": {"coordinates":[-81.590029,40.026682],"type":"Point"}
}
