{
  "type": "Feature",
  "properties": {
    "addr:full":"27 S Clairmont Ave Springfield OH 45505",
    "addr:housenumber":"27",
    "addr:postcode":"45505",
    "addr:street":"S Clairmont Ave",
    "iso:country":"US",
    "sg:address":"27 S Clairmont Ave",
    "sg:city":"Springfield",
    "sg:classifiers":[
        {
            "category":"Shopping",
            "subcategory":"Gifts & Souvenirs",
            "type":"Retail Goods"
        }
    ],
    "sg:phone":"+1 937 323 6174",
    "sg:postcode":"45505",
    "sg:province":"OH",
    "wof:name":"Ds Sweets Breads & Gifts",
    "wof:placetype":"venue"
},
  "geometry": {"coordinates":[-83.775854,39.921822],"type":"Point"}
}