{
  "type": "Feature",
  "properties": {
    "addr:full": "5040 Eber Rd Monclova OH 43542",
    "addr:housenumber": "5040",
    "addr:postcode": "43542",
    "addr:street": "Eber Rd",
    "iso:country": "US",
    "sg:address": "5040 Eber Rd",
    "sg:city": "Monclova",
    "sg:classifiers": [
      {
        "category": "Building \u0026 Trades",
        "subcategory": "Construction",
        "type": "Services"
      }
    ],
    "sg:phone": "+1 419 877 5312",
    "sg:postcode": "43542",
    "sg:province": "OH",
    "sg:tags": [
      "general",
      "commercial",
      "contractor"
    ],
    "wof:name": "General Contractor",
    "wof:placetype": "venue"
  },
  "geometry": {"coordinates":[-83.786117,41.549766],"type":"Point"}
}
