{
  "type": "Feature",
  "properties": {
    "addr:full":"5420 Battee Rd Alexandria OH 43001",
    "addr:housenumber":"5420",
    "addr:postcode":"43001",
    "addr:street":"Battee Rd",
    "iso:country":"US",
    "sg:address":"5420 Battee Rd",
    "sg:city":"Alexandria",
    "sg:classifiers":[
        {
            "category":"Professional",
            "subcategory":"Management & Consulting",
            "type":"Services"
        }
    ],
    "sg:phone":"+1 740 924 1941",
    "sg:postcode":"43001",
    "sg:province":"OH",
    "sg:tags":[
        "school",
        "scientific",
        "sales",
        "direct",
        "to",
        "computer",
        "software"
    ],
    "wof:name":"Interactive Science",
    "wof:placetype":"venue"
},
  "geometry": {"coordinates":[-82.59875,40.106014],"type":"Point"}
}