{
  "type": "Feature",
  "properties": {
    "addr:full": "10501 Success Ln Dayton OH 45458",
    "addr:housenumber": "10501",
    "addr:postcode": "45458",
    "addr:street": "Success Ln",
    "iso:country": "US",
    "sg:address": "10501 Success Ln",
    "sg:city": "Dayton",
    "sg:classifiers": [
      {
        "category": "Professional",
        "subcategory": "Advertising",
        "type": "Services"
      }
    ],
    "sg:phone": "+1 937 886 0185",
    "sg:postcode": "45458",
    "sg:province": "OH",
    "sg:website": "www.mcafee.com",
    "wof:name": "MCAFEE.COM",
    "wof:placetype": "venue"
  },
  "geometry": {"coordinates":[-84.205839,39.593002],"type":"Point"}
}
