{
  "type": "Feature",
  "properties": {
    "addr:full":"221 W Wayne St Dunkirk OH 45836",
    "addr:housenumber":"221",
    "addr:postcode":"45836",
    "addr:street":"W Wayne St",
    "iso:country":"US",
    "sg:address":"221 W Wayne St",
    "sg:city":"Dunkirk",
    "sg:classifiers":[
        {
            "category":"Professional",
            "type":"Services"
        }
    ],
    "sg:phone":"+1 419 759 2965",
    "sg:postcode":"45836",
    "sg:province":"OH",
    "wof:name":"Russell A Rizor",
    "wof:placetype":"venue"
},
  "geometry": {"coordinates":[-83.64496200000001,40.789038],"type":"Point"}
}