{
  "type": "Feature",
  "properties": {
    "addr:full":"210 N 7th St Marietta OH 45750",
    "addr:housenumber":"210",
    "addr:postcode":"45750",
    "addr:street":"N 7Th St",
    "iso:country":"US",
    "sg:address":"210 N 7th St",
    "sg:city":"Marietta",
    "sg:classifiers":[
        {
            "category":"Health Services",
            "subcategory":"Doctor",
            "type":"Services"
        }
    ],
    "sg:phone":"+1 740 373 8046",
    "sg:postcode":"45750",
    "sg:province":"OH",
    "sg:tags":[
        "medical"
    ],
    "wof:name":"Jones Brenda F MD",
    "wof:placetype":"venue"
},
  "geometry": {"coordinates":[-81.44795999999999,39.419241],"type":"Point"}
}