{
  "type": "Feature",
  "properties": {
    "addr:full": "177 Porter St Lancaster OH 43130",
    "addr:housenumber": "177",
    "addr:postcode": "43130",
    "addr:street": "Porter St",
    "iso:country": "US",
    "sg:address": "177 Porter St",
    "sg:city": "Lancaster",
    "sg:classifiers": [
      {
        "category": "Wholesale",
        "subcategory": "Durable Goods \u0026 Equipment",
        "type": "Manufacturing \u0026 Wholesale Goods"
      }
    ],
    "sg:phone": "+1 740 687 5888",
    "sg:postcode": "43130",
    "sg:province": "OH",
    "sg:tags": [
      "fire",
      "extinguisher"
    ],
    "wof:name": "Humes Fire Safety",
    "wof:placetype": "venue"
  },
  "geometry": {"coordinates":[-82.599903,39.709542],"type":"Point"}
}
