{
  "type": "Feature",
  "properties": {
    "iso:country":"US",
    "sg:address":"3550 Columbus Rd NE",
    "sg:city":"Canton",
    "sg:classifiers":[
        {
            "category":"Sports & Exercise",
            "subcategory":"Golf",
            "type":"Entertainment"
        }
    ],
    "sg:phone":"+1 330 454 5131",
    "sg:postcode":"44705",
    "sg:province":"OH",
    "sg:tags":[
        "course",
        "public"
    ],
    "wof:name":"Skyland Golf Course",
    "wof:placetype":"venue"
},
  "geometry": {"coordinates":[-81.318259,40.847959],"type":"Point"}
}