{
  "type": "Feature",
  "properties": {
    "addr:full": "3550 Columbus Rd NE Canton OH 44705",
    "addr:housenumber": "3550",
    "addr:postcode": "44705",
    "addr:street": "Columbus Rd Ne",
    "iso:country": "US",
    "sg:address": "3550 Columbus Rd NE",
    "sg:city": "Canton",
    "sg:classifiers": [
      {
        "category": "Sports \u0026 Exercise",
        "subcategory": "Golf",
        "type": "Entertainment"
      }
    ],
    "sg:phone": "+1 330 454 5131",
    "sg:postcode": "44705",
    "sg:province": "OH",
    "sg:tags": [
      "course",
      "public"
    ],
    "wof:name": "Skyland Golf Course",
    "wof:placetype": "venue"
  },
  "geometry": {"coordinates":[-81.318259,40.847959],"type":"Point"}
}
