{
  "type": "Feature",
  "properties": {
    "addr:full":"8182 Davis St Masury OH 44438",
    "addr:housenumber":"8182",
    "addr:postcode":"44438",
    "addr:street":"Davis St",
    "iso:country":"US",
    "sg:address":"8182 Davis St",
    "sg:city":"Masury",
    "sg:classifiers":[
        {
            "category":"Recreation",
            "type":"Entertainment"
        }
    ],
    "sg:phone":"+1 330 448 1152",
    "sg:postcode":"44438",
    "sg:province":"OH",
    "sg:tags":[
        "club",
        "membership"
    ],
    "wof:name":"Thomas Community Center",
    "wof:placetype":"venue"
},
  "geometry": {"coordinates":[-80.522853,41.22307],"type":"Point"}
}