{
  "type": "Feature",
  "properties": {
    "iso:country":"US",
    "sg:address":"10210 Winstead Ln",
    "sg:city":"Cincinnati",
    "sg:classifiers":[
        {
            "category":"Building & Trades",
            "subcategory":"Construction",
            "type":"Services"
        }
    ],
    "sg:phone":"+1 513 772 4670",
    "sg:postcode":"45231",
    "sg:province":"OH",
    "sg:tags":[
        "concrete",
        "contractor"
    ],
    "wof:name":"F & W Concrete",
    "wof:placetype":"venue"
},
  "geometry": {"coordinates":[-84.490334,39.253679],"type":"Point"}
}