{
  "type": "Feature",
  "properties": {
    "addr:full": "10210 Winstead Ln Cincinnati OH 45231",
    "addr:housenumber": "10210",
    "addr:postcode": "45231",
    "addr:street": "Winstead Ln",
    "iso:country": "US",
    "sg:address": "10210 Winstead Ln",
    "sg:city": "Cincinnati",
    "sg:classifiers": [
      {
        "category": "Building \u0026 Trades",
        "subcategory": "Construction",
        "type": "Services"
      }
    ],
    "sg:phone": "+1 513 772 4670",
    "sg:postcode": "45231",
    "sg:province": "OH",
    "sg:tags": [
      "concrete",
      "contractor"
    ],
    "wof:name": "F \u0026 W Concrete",
    "wof:placetype": "venue"
  },
  "geometry": {"coordinates":[-84.490334,39.253679],"type":"Point"}
}
