{
  "type": "Feature",
  "properties": {
    "addr:full": "565 N Canfield Niles Rd Austintown OH 44515",
    "addr:housenumber": "565",
    "addr:postcode": "44515",
    "addr:street": "N Canfield Niles Rd",
    "iso:country": "US",
    "sg:address": "565 N Canfield Niles Rd",
    "sg:city": "Austintown",
    "sg:classifiers": [
      {
        "category": "Professional",
        "subcategory": "Computer Services",
        "type": "Services"
      }
    ],
    "sg:phone": "+1 330 792 7318",
    "sg:postcode": "44515",
    "sg:province": "OH",
    "sg:tags": [
      "internet"
    ],
    "wof:name": "Compunet Services Inc",
    "wof:placetype": "venue"
  },
  "geometry": {"coordinates":[-80.767982,41.117765],"type":"Point"}
}
