{
  "type": "Feature",
  "properties": {
    "addr:full": "12701 Amber Cir NW Uniontown OH 44685",
    "addr:housenumber": "12701",
    "addr:postcode": "44685",
    "addr:street": "Amber Cir Nw",
    "iso:country": "US",
    "sg:address": "12701 Amber Cir NW",
    "sg:city": "Uniontown",
    "sg:classifiers": [
      {
        "category": "Shopping",
        "type": "Retail Goods"
      }
    ],
    "sg:phone": "+1 330 699 5323",
    "sg:postcode": "44685",
    "sg:province": "OH",
    "sg:tags": [
      "merchandise"
    ],
    "wof:name": "Panache Gallery",
    "wof:placetype": "venue"
  },
  "geometry": {"coordinates":[-81.403069,40.97095],"type":"Point"}
}
