{
  "type": "Feature",
  "properties": {
    "addr:full": "6323 Promway Ave NW North Canton OH 44720",
    "addr:housenumber": "6323",
    "addr:postcode": "44720",
    "addr:street": "Promway Ave Nw",
    "iso:country": "US",
    "sg:address": "6323 Promway Ave NW",
    "sg:city": "North Canton",
    "sg:classifiers": [
      {
        "category": "Wholesale",
        "subcategory": "Machinery \u0026 Supplies",
        "type": "Manufacturing \u0026 Wholesale Goods"
      }
    ],
    "sg:phone": "+1 330 305 1112",
    "sg:postcode": "44720",
    "sg:province": "OH",
    "sg:tags": [
      "repairing"
    ],
    "wof:name": "Bergie's Skid Load Repair",
    "wof:placetype": "venue"
  },
  "geometry": {"coordinates":[-81.426956,40.874005],"type":"Point"}
}
