{
  "type": "Feature",
  "properties": {
    "iso:country":"US",
    "sg:address":"6323 Promway Ave NW",
    "sg:city":"North Canton",
    "sg:classifiers":[
        {
            "category":"Wholesale",
            "subcategory":"Machinery & Supplies",
            "type":"Manufacturing & Wholesale Goods"
        }
    ],
    "sg:phone":"+1 330 305 1112",
    "sg:postcode":"44720",
    "sg:province":"OH",
    "sg:tags":[
        "repairing"
    ],
    "wof:name":"Bergie's Skid Load Repair",
    "wof:placetype":"venue"
},
  "geometry": {"coordinates":[-81.426956,40.874005],"type":"Point"}
}