{
  "type": "Feature",
  "properties": {
    "addr:full": "316 Orchard Rd Wilmington OH 45177",
    "addr:housenumber": "316",
    "addr:postcode": "45177",
    "addr:street": "Orchard Rd",
    "iso:country": "US",
    "sg:address": "316 Orchard Rd",
    "sg:city": "Wilmington",
    "sg:classifiers": [
      {
        "category": "Organizations",
        "subcategory": "Religious Organization",
        "type": "Services"
      }
    ],
    "sg:phone": "+1 937 383 1012",
    "sg:postcode": "45177",
    "sg:province": "OH",
    "sg:tags": [
      "church"
    ],
    "wof:name": "Covenant Presbyterian Church",
    "wof:placetype": "venue"
  },
  "geometry": {"coordinates":[-83.835421,39.475413],"type":"Point"}
}
