{
  "type": "Feature",
  "properties": {
    "iso:country":"US",
    "sg:address":"15604 Detroit Ave",
    "sg:city":"Cleveland",
    "sg:classifiers":[
        {
            "category":"Personal",
            "subcategory":"Beauty Salon",
            "type":"Services"
        }
    ],
    "sg:phone":"+1 216 221 4184",
    "sg:postcode":"44107",
    "sg:province":"OH",
    "wof:name":"Hair Shoppe Of Lakewood",
    "wof:placetype":"venue"
},
  "geometry": {"coordinates":[-81.80704900000001,41.485215],"type":"Point"}
}