{
  "type": "Feature",
  "properties": {
    "addr:full":"6425 New Carlisle Pike Springfield OH 45504",
    "addr:housenumber":"6425",
    "addr:postcode":"45504",
    "addr:street":"New Carlisle Pike",
    "iso:country":"US",
    "sg:address":"6425 New Carlisle Pike",
    "sg:city":"Springfield",
    "sg:classifiers":[
        {
            "category":"Organizations",
            "subcategory":"Religious Organization",
            "type":"Services"
        }
    ],
    "sg:phone":"+1 937 882 6871",
    "sg:postcode":"45504",
    "sg:province":"OH",
    "sg:tags":[
        "church"
    ],
    "sg:website":"www.bethelbaptistspringfield.org",
    "wof:name":"Church Bethel Bpt Prsn",
    "wof:placetype":"venue"
},
  "geometry": {"coordinates":[-83.92909299999999,39.93858],"type":"Point"}
}