{
  "type": "Feature",
  "properties": {
    "addr:full": "5939 Darrow Rd Hudson OH 44236",
    "addr:housenumber": "5939",
    "addr:postcode": "44236",
    "addr:street": "Darrow Rd",
    "iso:country": "US",
    "sg:address": "5939 Darrow Rd",
    "sg:city": "Hudson",
    "sg:classifiers": [
      {
        "category": "Retail",
        "subcategory": "Veterinary Services",
        "type": "Services"
      }
    ],
    "sg:phone": "+1 330 650 2929",
    "sg:postcode": "44236",
    "sg:province": "OH",
    "sg:tags": [
      "animal"
    ],
    "wof:name": "Hudson Veterinary Hospital",
    "wof:placetype": "venue"
  },
  "geometry": {"coordinates":[-81.440339,41.224152],"type":"Point"}
}
