{
  "type": "Feature",
  "properties": {
    "iso:country":"US",
    "sg:address":"626 Carnwise St SE",
    "sg:city":"Canton",
    "sg:classifiers":[
        {
            "category":"Wholesale",
            "subcategory":"Sporting Goods",
            "type":"Manufacturing & Wholesale Goods"
        }
    ],
    "sg:phone":"+1 330 484 9920",
    "sg:postcode":"44707",
    "sg:province":"OH",
    "wof:name":"Sports South Ohio Office",
    "wof:placetype":"venue"
},
  "geometry": {"coordinates":[-81.374084,40.757334],"type":"Point"}
}