{
  "type": "Feature",
  "properties": {
    "addr:full": "626 Carnwise St SE Canton OH 44707",
    "addr:housenumber": "626",
    "addr:postcode": "44707",
    "addr:street": "Carnwise St Se",
    "iso:country": "US",
    "sg:address": "626 Carnwise St SE",
    "sg:city": "Canton",
    "sg:classifiers": [
      {
        "category": "Wholesale",
        "subcategory": "Sporting Goods",
        "type": "Manufacturing \u0026 Wholesale Goods"
      }
    ],
    "sg:phone": "+1 330 484 9920",
    "sg:postcode": "44707",
    "sg:province": "OH",
    "wof:name": "Sports South Ohio Office",
    "wof:placetype": "venue"
  },
  "geometry": {"coordinates":[-81.374084,40.757334],"type":"Point"}
}
