{
  "type": "Feature",
  "properties": {
    "addr:full": "20617 Hillgrove Ave Cleveland OH 44137",
    "addr:postcode": "20617;44137",
    "addr:street": "Hillgrove Ave",
    "iso:country": "US",
    "sg:address": "20617 Hillgrove Ave",
    "sg:city": "Cleveland",
    "sg:classifiers": [
      {
        "category": "Building \u0026 Trades",
        "subcategory": "Construction",
        "type": "Services"
      }
    ],
    "sg:phone": "+1 216 780 4966",
    "sg:postcode": "44137",
    "sg:province": "OH",
    "sg:tags": [
      "home",
      "improvement"
    ],
    "wof:name": "Affordable Home Repair",
    "wof:placetype": "venue"
  },
  "geometry": {"coordinates":[-81.536076,41.420234],"type":"Point"}
}
