{
  "type": "Feature",
  "properties": {
    "addr:full": "1690 W Mound St Columbus OH 43223",
    "addr:housenumber": "1690",
    "addr:postcode": "43223",
    "addr:street": "W Mound St",
    "iso:country": "US",
    "sg:address": "1690 W Mound St",
    "sg:city": "Columbus",
    "sg:classifiers": [
      {
        "category": "Bars \u0026 Pubs",
        "type": "Food \u0026 Drink"
      }
    ],
    "sg:phone": "+1 614 272 9320",
    "sg:postcode": "43223",
    "sg:province": "OH",
    "wof:name": "Eureka Cafe",
    "wof:placetype": "venue"
  },
  "geometry": {"coordinates":[-83.042424,39.944098],"type":"Point"}
}
