{
  "type": "Feature",
  "properties": {
    "iso:country":"US",
    "sg:address":"5454 Brant Rd",
    "sg:city":"Morrow",
    "sg:classifiers":[
        {
            "category":"Professional",
            "subcategory":"Engineering",
            "type":"Services"
        }
    ],
    "sg:phone":"+1 513 899 3181",
    "sg:postcode":"45152",
    "sg:province":"OH",
    "sg:tags":[
        "engineer"
    ],
    "wof:name":"Tag Consulting Inc",
    "wof:placetype":"venue"
},
  "geometry": {"coordinates":[-84.097454,39.379706],"type":"Point"}
}