{
  "type": "Feature",
  "properties": {
    "addr:full":"3410 Ravenna Ave NE Louisville OH 44641",
    "addr:housenumber":"3410",
    "addr:postcode":"44641",
    "addr:street":"Ravenna Ave Ne",
    "iso:country":"US",
    "sg:address":"3410 Ravenna Ave NE",
    "sg:city":"Louisville",
    "sg:phone":"+1 330 875 7279",
    "sg:postcode":"44641",
    "sg:province":"OH",
    "sg:tags":[
        "farm",
        "grain",
        "cash"
    ],
    "wof:name":"David Hohman",
    "wof:placetype":"venue"
},
  "geometry": {"coordinates":[-81.27428999999999,40.820076],"type":"Point"}
}