{
  "type": "Feature",
  "properties": {
    "addr:full": "238 Catalpa Ct Dayton OH 45440",
    "addr:housenumber": "238",
    "addr:postcode": "45440",
    "addr:street": "Catalpa Ct",
    "iso:country": "US",
    "sg:address": "238 Catalpa Ct",
    "sg:city": "Dayton",
    "sg:classifiers": [
      {
        "category": "Utilities",
        "subcategory": "Cable",
        "type": "Services"
      }
    ],
    "sg:phone": "+1 937 431 1602",
    "sg:postcode": "45440",
    "sg:province": "OH",
    "sg:tags": [
      "television"
    ],
    "wof:name": "Gary Cable",
    "wof:placetype": "venue"
  },
  "geometry": {"coordinates":[-84.081881,39.686633],"type":"Point"}
}
