{
  "type": "Feature",
  "properties": {
    "addr:full":"3452 Manchester Rd Akron OH 44319",
    "addr:housenumber":"3452",
    "addr:postcode":"44319",
    "addr:street":"Manchester Rd",
    "iso:country":"US",
    "sg:address":"3452 Manchester Rd",
    "sg:city":"Akron",
    "sg:classifiers":[
        {
            "category":"Shopping",
            "subcategory":"Hobbies, Toys, & Games",
            "type":"Retail Goods"
        }
    ],
    "sg:phone":"+1 330 644 5883",
    "sg:postcode":"44319",
    "sg:province":"OH",
    "sg:tags":[
        "supply"
    ],
    "wof:name":"Game A Rima",
    "wof:placetype":"venue"
},
  "geometry": {"coordinates":[-81.555661,41.006742],"type":"Point"}
}