{
  "type": "Feature",
  "properties": {
    "addr:full": "6553 County Line Rd Kinsman OH 44428",
    "addr:housenumber": "6553",
    "addr:postcode": "44428",
    "addr:street": "County Line Rd",
    "iso:country": "US",
    "sg:address": "6553 County Line Rd",
    "sg:city": "Kinsman",
    "sg:classifiers": [
      {
        "category": "Building \u0026 Trades",
        "subcategory": "Landscaping Services",
        "type": "Services"
      }
    ],
    "sg:phone": "+1 330 876 8300",
    "sg:postcode": "44428",
    "sg:province": "OH",
    "sg:tags": [
      "landscape",
      "contractor"
    ],
    "wof:name": "New Beginnings Landscape Inc",
    "wof:placetype": "venue"
  },
  "geometry": {"coordinates":[-80.530221,41.49943],"type":"Point"}
}
