{
  "type": "Feature",
  "properties": {
    "iso:country":"US",
    "sg:address":"2670 Broken Woods Dr",
    "sg:city":"Troy",
    "sg:classifiers":[
        {
            "category":"Professional",
            "subcategory":"Engineering",
            "type":"Services"
        }
    ],
    "sg:phone":"+1 937 335 5041",
    "sg:postcode":"45373",
    "sg:province":"OH",
    "wof:name":"Debar Inc",
    "wof:placetype":"venue"
},
  "geometry": {"coordinates":[-84.21128299999999,40.000254],"type":"Point"}
}