{
  "type": "Feature",
  "properties": {
    "addr:full": "2670 Broken Woods Dr Troy OH 45373",
    "addr:housenumber": "2670",
    "addr:postcode": "45373",
    "addr:street": "Broken Woods Dr",
    "iso:country": "US",
    "sg:address": "2670 Broken Woods Dr",
    "sg:city": "Troy",
    "sg:classifiers": [
      {
        "category": "Professional",
        "subcategory": "Engineering",
        "type": "Services"
      }
    ],
    "sg:phone": "+1 937 335 5041",
    "sg:postcode": "45373",
    "sg:province": "OH",
    "wof:name": "Debar Inc",
    "wof:placetype": "venue"
  },
  "geometry": {"coordinates":[-84.211283,40.000254],"type":"Point"}
}
