{
  "type": "Feature",
  "properties": {
    "iso:country":"US",
    "sg:address":"445 Earlwood Ave",
    "sg:city":"Oregon",
    "sg:classifiers":[
        {
            "category":"Building & Trades",
            "subcategory":"Construction",
            "type":"Services"
        }
    ],
    "sg:phone":"+1 419 693 6634",
    "sg:postcode":"43616",
    "sg:province":"OH",
    "sg:tags":[
        "general",
        "contractor"
    ],
    "wof:name":"Associated Home Svc Of America",
    "wof:placetype":"venue"
},
  "geometry": {"coordinates":[-83.494949,41.641458],"type":"Point"}
}