{
  "type": "Feature",
  "properties": {
    "iso:country":"US",
    "sg:address":"10036 Kensington Rd NE",
    "sg:city":"Kensington",
    "sg:classifiers":[
        {
            "category":"Freight",
            "type":"Transportation"
        }
    ],
    "sg:phone":"+1 330 894 2802",
    "sg:postcode":"44427",
    "sg:province":"OH",
    "sg:tags":[
        "local",
        "storage",
        "trucking"
    ],
    "wof:name":"Fred Kloos",
    "wof:placetype":"venue"
},
  "geometry": {"coordinates":[-80.98820499999999,40.714881],"type":"Point"}
}