{
  "type": "Feature",
  "properties": {
    "addr:full":"4135 Prosway Ave SW Massillon OH 44646",
    "addr:housenumber":"4135",
    "addr:postcode":"44646",
    "addr:street":"Prosway Ave Sw",
    "iso:country":"US",
    "sg:address":"4135 Prosway Ave SW",
    "sg:city":"Massillon",
    "sg:classifiers":[
        {
            "category":"Insurance",
            "subcategory":"Insurance Agent",
            "type":"Services"
        }
    ],
    "sg:phone":"+1 330 830 8789",
    "sg:postcode":"44646",
    "sg:province":"OH",
    "wof:name":"American National Insurance Co",
    "wof:placetype":"venue"
},
  "geometry": {"coordinates":[-81.478853,40.749968],"type":"Point"}
}