{
  "type": "Feature",
  "properties": {
    "addr:full":"6665 Iris Ave Cincinnati OH 45213",
    "addr:housenumber":"6665",
    "addr:postcode":"45213",
    "addr:street":"Iris Ave",
    "iso:country":"US",
    "sg:address":"6665 Iris Ave",
    "sg:city":"Cincinnati",
    "sg:classifiers":[
        {
            "category":"Building & Trades",
            "subcategory":"Landscaping Services",
            "type":"Services"
        }
    ],
    "sg:phone":"+1 513 841 1284",
    "sg:postcode":"45213",
    "sg:province":"OH",
    "wof:name":"Jr S Lawn Care & Light Hauling",
    "wof:placetype":"venue"
},
  "geometry": {"coordinates":[-84.411739,39.19258],"type":"Point"}
}