{
  "type": "Feature",
  "properties": {
    "iso:country":"US",
    "sg:address":"7015 Mullen Rd",
    "sg:city":"Cincinnati",
    "sg:classifiers":[
        {
            "category":"Manufacturing",
            "subcategory":"Tools & Machinery",
            "type":"Manufacturing & Wholesale Goods"
        }
    ],
    "sg:phone":"+1 513 353 3144",
    "sg:postcode":"45247",
    "sg:province":"OH",
    "sg:tags":[
        "machine",
        "shop"
    ],
    "wof:name":"Godfrey Tool & Die",
    "wof:placetype":"venue"
},
  "geometry": {"coordinates":[-84.672344,39.210359],"type":"Point"}
}