{
  "type": "Feature",
  "properties": {
    "addr:full":"3095 Maysville Pike Zanesville OH 43701",
    "addr:postcode":"3095;43701",
    "addr:street":"Maysville Pike",
    "iso:country":"US",
    "sg:address":"3095 Maysville Pike",
    "sg:city":"Zanesville",
    "sg:classifiers":[
        {
            "category":"Social Services",
            "subcategory":"Child Care",
            "type":"Services"
        }
    ],
    "sg:phone":"+1 740 452 6884",
    "sg:postcode":"43701",
    "sg:province":"OH",
    "sg:tags":[
        "day"
    ],
    "wof:name":"Child Development Center",
    "wof:placetype":"venue"
},
  "geometry": {"coordinates":[-82.048756,39.889329],"type":"Point"}
}