{
  "type": "Feature",
  "properties": {
    "addr:full": "111 Wellington Pl Cincinnati OH 45219",
    "addr:housenumber": "111",
    "addr:postcode": "45219",
    "addr:street": "Wellington Pl",
    "iso:country": "US",
    "sg:address": "111 Wellington Pl",
    "sg:city": "Cincinnati",
    "sg:classifiers": [
      {
        "category": "Manufacturing",
        "subcategory": "Tools \u0026 Machinery",
        "type": "Manufacturing \u0026 Wholesale Goods"
      }
    ],
    "sg:phone": "+1 513 421 5653",
    "sg:postcode": "45219",
    "sg:province": "OH",
    "sg:tags": [
      "braces",
      "orthopedic",
      "prosthetic",
      "devices",
      "mfg"
    ],
    "wof:name": "Brace Sp Prsthtic Orthtic Ctrs",
    "wof:placetype": "venue"
  },
  "geometry": {"coordinates":[-84.50899,39.12428],"type":"Point"}
}
