{
  "type": "Feature",
  "properties": {
    "addr:full": "3380 Tremont Rd Columbus OH 43221",
    "addr:housenumber": "3380",
    "addr:postcode": "43221",
    "addr:street": "Tremont Rd",
    "iso:country": "US",
    "sg:address": "3380 Tremont Rd",
    "sg:city": "Columbus",
    "sg:classifiers": [
      {
        "category": "Manufacturing",
        "subcategory": "Glass \u0026 Minerals",
        "type": "Manufacturing \u0026 Wholesale Goods"
      }
    ],
    "sg:phone": "+1 614 451 6420",
    "sg:postcode": "43221",
    "sg:province": "OH",
    "sg:tags": [
      "fiberglass"
    ],
    "wof:name": "Owens Corning",
    "wof:placetype": "venue"
  },
  "geometry": {"coordinates":[-83.057452,40.025203],"type":"Point"}
}
