{
  "type": "Feature",
  "properties": {
    "iso:country":"US",
    "sg:address":"3380 Tremont Rd",
    "sg:city":"Columbus",
    "sg:classifiers":[
        {
            "category":"Manufacturing",
            "subcategory":"Glass & Minerals",
            "type":"Manufacturing & Wholesale Goods"
        }
    ],
    "sg:phone":"+1 614 451 6420",
    "sg:postcode":"43221",
    "sg:province":"OH",
    "sg:tags":[
        "fiberglass"
    ],
    "wof:name":"Owens Corning",
    "wof:placetype":"venue"
},
  "geometry": {"coordinates":[-83.057452,40.025203],"type":"Point"}
}