{
  "type": "Feature",
  "properties": {
    "addr:full": "10680 Steiner Rd Rittman OH 44270",
    "addr:housenumber": "10680",
    "addr:postcode": "44270",
    "addr:street": "Steiner Rd",
    "iso:country": "US",
    "sg:address": "10680 Steiner Rd",
    "sg:city": "Rittman",
    "sg:classifiers": [
      {
        "category": "Health Services",
        "subcategory": "Nursing And Care Facility",
        "type": "Services"
      }
    ],
    "sg:phone": "+1 330 927 1010",
    "sg:postcode": "44270",
    "sg:province": "OH",
    "sg:tags": [
      "intermediate"
    ],
    "wof:name": "Apostolic Christian Home Inc",
    "wof:placetype": "venue"
  },
  "geometry": {"coordinates":[-81.784304,40.93131],"type":"Point"}
}
