{
  "type": "Feature",
  "properties": {
    "addr:full": "6950 Chippewa Rd Medina OH 44256",
    "addr:housenumber": "6950",
    "addr:postcode": "44256",
    "addr:street": "Chippewa Rd",
    "iso:country": "US",
    "sg:address": "6950 Chippewa Rd",
    "sg:city": "Medina",
    "sg:classifiers": [
      {
        "category": "Shopping",
        "type": "Retail Goods"
      }
    ],
    "sg:phone": "+1 330 887 5592",
    "sg:postcode": "44256",
    "sg:province": "OH",
    "sg:tags": [
      "merchandise"
    ],
    "wof:name": "Exhibit Store Inc",
    "wof:placetype": "venue"
  },
  "geometry": {"coordinates":[-81.937971,41.074909],"type":"Point"}
}
