{
  "type": "Feature",
  "properties": {
    "addr:full": "4130 Market St Boardman OH 44512",
    "addr:housenumber": "4130",
    "addr:postcode": "44512",
    "addr:street": "Market St",
    "iso:country": "US",
    "sg:address": "4130 Market St",
    "sg:city": "Boardman",
    "sg:classifiers": [
      {
        "category": "Insurance",
        "subcategory": "Insurance Agent",
        "type": "Services"
      }
    ],
    "sg:phone": "+1 330 782 7827",
    "sg:postcode": "44512",
    "sg:province": "OH",
    "wof:name": "All-Star Insurance",
    "wof:placetype": "venue"
  },
  "geometry": {"coordinates":[-80.662873,41.058016],"type":"Point"}
}
