{
  "type": "Feature",
  "properties": {
    "addr:full": "398 W Bagley Rd Berea OH 44017",
    "addr:housenumber": "398",
    "addr:postcode": "44017",
    "addr:street": "W Bagley Rd",
    "iso:country": "US",
    "sg:address": "398 W Bagley Rd",
    "sg:city": "Berea",
    "sg:classifiers": [
      {
        "category": "Health Services",
        "subcategory": "Health Practitioner",
        "type": "Services"
      }
    ],
    "sg:phone": "+1 440 243 1606",
    "sg:postcode": "44017",
    "sg:province": "OH",
    "sg:tags": [
      "psychologist"
    ],
    "wof:name": "John E Grimm PHD",
    "wof:placetype": "venue"
  },
  "geometry": {"coordinates":[-81.865087,41.372349],"type":"Point"}
}
