{
  "type": "Feature",
  "properties": {
    "addr:full": "1300 Susan Dr Hamilton IN 45013",
    "addr:housenumber": "1300",
    "addr:postcode": "45013",
    "addr:street": "Susan Dr",
    "iso:country": "US",
    "sg:address": "1300 Susan Dr",
    "sg:city": "Hamilton",
    "sg:classifiers": [
      {
        "category": "Building \u0026 Trades",
        "subcategory": "Plumbing",
        "type": "Services"
      }
    ],
    "sg:phone": "+1 513 868 7258",
    "sg:postcode": "45013",
    "sg:province": "IN",
    "sg:tags": [
      "contractor"
    ],
    "wof:name": "Sandlin Heating \u0026 Cooling",
    "wof:placetype": "venue"
  },
  "geometry": {"coordinates":[-84.600634,39.401318],"type":"Point"}
}
