{
  "type": "Feature",
  "properties": {
    "iso:country":"US",
    "sg:address":"1300 Susan Dr",
    "sg:city":"Hamilton",
    "sg:classifiers":[
        {
            "category":"Building & Trades",
            "subcategory":"Plumbing",
            "type":"Services"
        }
    ],
    "sg:phone":"+1 513 868 7258",
    "sg:postcode":"45013",
    "sg:province":"IN",
    "sg:tags":[
        "contractor"
    ],
    "wof:name":"Sandlin Heating & Cooling",
    "wof:placetype":"venue"
},
  "geometry": {"coordinates":[-84.600634,39.401318],"type":"Point"}
}