{
  "type": "Feature",
  "properties": {
    "iso:country":"US",
    "sg:address":"70 Carnation Pl SW",
    "sg:city":"Pataskala",
    "sg:classifiers":[
        {
            "category":"Professional",
            "subcategory":"Management & Consulting",
            "type":"Services"
        }
    ],
    "sg:phone":"+1 740 927 9004",
    "sg:postcode":"43062",
    "sg:province":"OH",
    "sg:tags":[
        "communications",
        "consultant"
    ],
    "wof:name":"Alfa 1 Communications",
    "wof:placetype":"venue"
},
  "geometry": {"coordinates":[-82.639579,39.963831],"type":"Point"}
}