{
  "type": "Feature",
  "properties": {
    "iso:country":"US",
    "sg:address":"1530 Watkins Rd",
    "sg:city":"Fort Recovery",
    "sg:classifiers":[
        {
            "category":"Farming",
            "subcategory":"Farm",
            "type":"Manufacturing & Wholesale Goods"
        }
    ],
    "sg:phone":"+1 419 375 2884",
    "sg:postcode":"45846",
    "sg:province":"OH",
    "sg:tags":[
        "crop",
        "general"
    ],
    "wof:name":"Homan Farm S",
    "wof:placetype":"venue"
},
  "geometry": {"coordinates":[-84.746702,40.366819],"type":"Point"}
}