{
  "type": "Feature",
  "properties": {
    "addr:full":"3937 Georgetown Verona Rd Lewisburg OH 45338",
    "addr:housenumber":"3937",
    "addr:postcode":"45338",
    "addr:street":"Georgetown Verona Rd",
    "iso:country":"US",
    "sg:address":"3937 Georgetown Verona Rd",
    "sg:city":"Lewisburg",
    "sg:phone":"+1 937 962 2762",
    "sg:postcode":"45338",
    "sg:province":"OH",
    "sg:tags":[
        "farm",
        "corn",
        "soybean"
    ],
    "wof:name":"Bruns Bob Farm of",
    "wof:placetype":"venue"
},
  "geometry": {"coordinates":[-84.55714500000001,39.902443],"type":"Point"}
}