{
  "type": "Feature",
  "properties": {
    "iso:country":"US",
    "sg:address":"15432 Glynn Rd",
    "sg:city":"Cleveland",
    "sg:classifiers":[
        {
            "category":"Manufacturing",
            "subcategory":"Jewelry",
            "type":"Manufacturing & Wholesale Goods"
        }
    ],
    "sg:phone":"+1 216 321 5890",
    "sg:postcode":"44112",
    "sg:province":"OH",
    "sg:tags":[
        "precious",
        "metal",
        "mfg"
    ],
    "wof:name":"Michael Romanik",
    "wof:placetype":"venue"
},
  "geometry": {"coordinates":[-81.570733,41.529362],"type":"Point"}
}