{
  "type": "Feature",
  "properties": {
    "addr:full": "6112 Pickway Dr Cleveland OH 44142",
    "addr:housenumber": "6112",
    "addr:postcode": "44142",
    "addr:street": "Pickway Dr",
    "iso:country": "US",
    "sg:address": "6112 Pickway Dr",
    "sg:city": "Cleveland",
    "sg:classifiers": [
      {
        "category": "Building \u0026 Trades",
        "subcategory": "Construction",
        "type": "Services"
      }
    ],
    "sg:phone": "+1 216 433 0025",
    "sg:postcode": "44142",
    "sg:province": "OH",
    "sg:tags": [
      "house"
    ],
    "wof:name": "Sykora Bud Construction Svcs",
    "wof:placetype": "venue"
  },
  "geometry": {"coordinates":[-81.799851,41.400552],"type":"Point"}
}
