{
  "type": "Feature",
  "properties": {
    "iso:country":"US",
    "sg:address":"3900 Broadview Rd",
    "sg:city":"Richfield",
    "sg:classifiers":[
        {
            "category":"Professional",
            "subcategory":"Business Services",
            "type":"Services"
        },
        {
            "category":"Government",
            "subcategory":"Post Office",
            "type":"Public Place"
        }
    ],
    "sg:phone":"+1 330 659 3561",
    "sg:postcode":"44286",
    "sg:province":"OH",
    "sg:tags":[
        "mail",
        "shipping"
    ],
    "sg:website":"http://www.usps.gov",
    "wof:name":"USPS - United States Post Office",
    "wof:placetype":"venue"
},
  "geometry": {"coordinates":[-81.653671,41.238171],"type":"Point"}
}