{
  "type": "Feature",
  "properties": {
    "addr:full": "252 E Vance St Rawson OH 45881",
    "addr:housenumber": "252",
    "addr:postcode": "45881",
    "addr:street": "E Vance St",
    "iso:country": "US",
    "sg:address": "252 E Vance St",
    "sg:city": "Rawson",
    "sg:classifiers": [
      {
        "category": "Retail",
        "subcategory": "Laundry \u0026 Dry Cleaning",
        "type": "Services"
      }
    ],
    "sg:phone": "+1 419 963 2400",
    "sg:postcode": "45881",
    "sg:province": "OH",
    "sg:tags": [
      "cleaners",
      "rug",
      "carpet"
    ],
    "wof:name": "John's Carpet Cleaning",
    "wof:placetype": "venue"
  },
  "geometry": {"coordinates":[-83.784516,40.958832],"type":"Point"}
}
