{
  "type": "Feature",
  "properties": {
    "addr:full":"531 Elmwood Rd Bay Village OH 44140",
    "addr:housenumber":"531",
    "addr:postcode":"44140",
    "addr:street":"Elmwood Rd",
    "iso:country":"US",
    "sg:address":"531 Elmwood Rd",
    "sg:city":"Bay Village",
    "sg:classifiers":[
        {
            "category":"Shopping",
            "subcategory":"Gifts & Souvenirs",
            "type":"Retail Goods"
        }
    ],
    "sg:phone":"+1 440 835 0994",
    "sg:postcode":"44140",
    "sg:province":"OH",
    "sg:tags":[
        "basket"
    ],
    "wof:name":"Northcoast Gift Baskets",
    "wof:placetype":"venue"
},
  "geometry": {"coordinates":[-81.909978,41.480132],"type":"Point"}
}