{
  "type": "Feature",
  "properties": {
    "addr:full": "10450 New Haven Rd Harrison OH 45030",
    "addr:housenumber": "10450",
    "addr:postcode": "45030",
    "addr:street": "New Haven Rd",
    "iso:country": "US",
    "sg:address": "10450 New Haven Rd",
    "sg:city": "Harrison",
    "sg:classifiers": [
      {
        "category": "Health Services",
        "subcategory": "Doctor",
        "type": "Services"
      }
    ],
    "sg:phone": "+1 513 542 5142",
    "sg:postcode": "45030",
    "sg:province": "OH",
    "sg:tags": [
      "physician",
      "surgeon"
    ],
    "wof:name": "Urology Group",
    "wof:placetype": "venue"
  },
  "geometry": {"coordinates":[-84.788057,39.262122],"type":"Point"}
}
