{
  "type": "Feature",
  "properties": {
    "addr:full":"1900 Cooper Foster Park Rd W Lorain OH 44053",
    "addr:housenumber":"1900",
    "addr:postcode":"44053",
    "addr:street":"Cooper Foster Park Rd W",
    "iso:country":"US",
    "sg:address":"1900 Cooper Foster Park Rd W",
    "sg:city":"Lorain",
    "sg:classifiers":[
        {
            "category":"Fast Food",
            "type":"Food & Drink"
        },
        {
            "category":"Restaurant",
            "type":"Food & Drink"
        }
    ],
    "sg:phone":"+1 440 282 4060",
    "sg:postcode":"44053",
    "sg:province":"OH",
    "sg:tags":[
        "american",
        "hot",
        "hamburger",
        "dog"
    ],
    "sg:website":"http://www.bk.com",
    "wof:name":"Burger King",
    "wof:placetype":"venue"
},
  "geometry": {"coordinates":[-82.20005,41.41827],"type":"Point"}
}