{
  "type": "Feature",
  "properties": {
    "addr:full": "9509 Montgomery Rd Cincinnati OH 45242",
    "addr:housenumber": "9509",
    "addr:postcode": "45242",
    "addr:street": "Montgomery Rd",
    "iso:country": "US",
    "sg:address": "9509 Montgomery Rd",
    "sg:city": "Cincinnati",
    "sg:classifiers": [
      {
        "category": "Health Services",
        "subcategory": "Doctor",
        "type": "Services"
      }
    ],
    "sg:phone": "+1 513 891 7051",
    "sg:postcode": "45242",
    "sg:province": "OH",
    "sg:tags": [
      "dentist"
    ],
    "wof:name": "James D White DMD",
    "wof:placetype": "venue"
  },
  "geometry": {"coordinates":[-84.3539,39.228711],"type":"Point"}
}
