{
  "type": "Feature",
  "properties": {
    "addr:full":"2041 Riverside Dr Columbus OH 43221",
    "addr:housenumber":"2041",
    "addr:postcode":"43221",
    "addr:street":"Riverside Dr",
    "iso:country":"US",
    "sg:address":"2041 Riverside Dr",
    "sg:city":"Columbus",
    "sg:classifiers":[
        {
            "category":"Building & Trades",
            "subcategory":"Construction",
            "type":"Services"
        },
        {
            "category":"Professional",
            "subcategory":"Art Services",
            "type":"Services"
        }
    ],
    "sg:phone":"+1 614 486 5254",
    "sg:postcode":"43221",
    "sg:province":"OH",
    "sg:tags":[
        "graphic",
        "designer",
        "contractor"
    ],
    "wof:name":"Terrazzo Creative",
    "wof:placetype":"venue"
},
  "geometry": {"coordinates":[-83.07508799999999,39.998183],"type":"Point"}
}