{
  "type": "Feature",
  "properties": {
    "addr:full": "21400 Mastick Rd Cleveland OH 44126",
    "addr:housenumber": "21400",
    "addr:postcode": "44126",
    "addr:street": "Mastick Rd",
    "iso:country": "US",
    "sg:address": "21400 Mastick Rd",
    "sg:city": "Cleveland",
    "sg:classifiers": [
      {
        "category": "Insurance",
        "subcategory": "Insurance Agent",
        "type": "Services"
      }
    ],
    "sg:phone": "+1 440 356 1484",
    "sg:postcode": "44126",
    "sg:province": "OH",
    "wof:name": "B E Reasoner \u0026 Associates",
    "wof:placetype": "venue"
  },
  "geometry": {"coordinates":[-81.859709,41.427722],"type":"Point"}
}
