{
  "type": "Feature",
  "properties": {
    "addr:full": "155 N Cedar St Newark OH 43055",
    "addr:housenumber": "155",
    "addr:postcode": "43055",
    "addr:street": "N Cedar St",
    "iso:country": "US",
    "sg:address": "155 N Cedar St",
    "sg:city": "Newark",
    "sg:classifiers": [
      {
        "category": "Bars \u0026 Pubs",
        "type": "Food \u0026 Drink"
      }
    ],
    "sg:phone": "+1 740 349 7228",
    "sg:postcode": "43055",
    "sg:province": "OH",
    "wof:name": "Bummie's Hi Spot",
    "wof:placetype": "venue"
  },
  "geometry": {"coordinates":[-82.385695,40.065715],"type":"Point"}
}
