{
  "type": "Feature",
  "properties": {
    "iso:country":"US",
    "sg:address":"628 Wooster Rd W",
    "sg:city":"Barberton",
    "sg:classifiers":[
        {
            "category":"Retail",
            "subcategory":"Auto Repair",
            "type":"Services"
        }
    ],
    "sg:phone":"+1 330 745 6428",
    "sg:postcode":"44203",
    "sg:province":"OH",
    "sg:tags":[
        "repairing",
        "automobile"
    ],
    "wof:name":"Daves Foreign Car Svc",
    "wof:placetype":"venue"
},
  "geometry": {"coordinates":[-81.61371800000001,41.012028],"type":"Point"}
}