{
  "type": "Feature",
  "properties": {
    "iso:country":"US",
    "sg:address":"121 W 9th St",
    "sg:city":"Cincinnati",
    "sg:classifiers":[
        {
            "category":"Professional",
            "subcategory":"Lawyer & Legal Services",
            "type":"Services"
        }
    ],
    "sg:phone":"+1 513 421 2540",
    "sg:postcode":"45202",
    "sg:province":"OH",
    "wof:name":"Ennis Roberts & Fischer",
    "wof:placetype":"venue"
},
  "geometry": {"coordinates":[-84.515794,39.105054],"type":"Point"}
}