{
  "type": "Feature",
  "properties": {
    "addr:full":"746 Loveland Miamiville Rd Loveland OH 45140",
    "addr:housenumber":"746",
    "addr:postcode":"45140",
    "addr:street":"Loveland Miamiville Rd",
    "iso:country":"US",
    "sg:address":"746 Loveland Miamiville Rd",
    "sg:city":"Loveland",
    "sg:classifiers":[
        {
            "category":"Shopping",
            "type":"Retail Goods"
        },
        {
            "category":"Professional",
            "subcategory":"Management & Consulting",
            "type":"Services"
        }
    ],
    "sg:phone":"+1 513 683 1555",
    "sg:postcode":"45140",
    "sg:province":"OH",
    "sg:tags":[
        "direct",
        "sales",
        "cosmetic",
        "perfume"
    ],
    "wof:name":"Mary Kay Cosmetics",
    "wof:placetype":"venue"
},
  "geometry": {"coordinates":[-84.2595,39.227711],"type":"Point"}
}