{
  "type": "Feature",
  "properties": {
    "iso:country":"US",
    "sg:address":"9301 Detroit Ave",
    "sg:city":"Cleveland",
    "sg:classifiers":[
        {
            "category":"Wholesale",
            "subcategory":"Scrap",
            "type":"Manufacturing & Wholesale Goods"
        }
    ],
    "sg:phone":"+1 216 961 0062",
    "sg:postcode":"44102",
    "sg:province":"OH",
    "sg:tags":[
        "material"
    ],
    "wof:name":"Frank James Gurkles",
    "wof:placetype":"venue"
},
  "geometry": {"coordinates":[-81.74852799999999,41.480138],"type":"Point"}
}