{
  "type": "Feature",
  "properties": {
    "iso:country":"US",
    "sg:address":"4950 N High St",
    "sg:city":"Columbus",
    "sg:classifiers":[
        {
            "category":"Banks & Credit Unions",
            "subcategory":"Bank",
            "type":"Services"
        }
    ],
    "sg:phone":"+1 614 883 5960",
    "sg:postcode":"43214",
    "sg:province":"OH",
    "sg:tags":[
        "cashing",
        "check"
    ],
    "wof:name":"National Check Cashers",
    "wof:placetype":"venue"
},
  "geometry": {"coordinates":[-83.019403,40.062571],"type":"Point"}
}