{
  "type": "Feature",
  "properties": {
    "addr:full":"6016 Turney Rd Cleveland OH 44125",
    "addr:housenumber":"6016",
    "addr:postcode":"44125",
    "addr:street":"Turney Rd",
    "iso:country":"US",
    "sg:address":"6016 Turney Rd",
    "sg:city":"Cleveland",
    "sg:classifiers":[
        {
            "category":"Banks & Credit Unions",
            "subcategory":"Bank",
            "type":"Services"
        }
    ],
    "sg:phone":"+1 216 475 3010",
    "sg:postcode":"44125",
    "sg:province":"OH",
    "sg:tags":[
        "savings",
        "loan"
    ],
    "sg:website":"www.ohiosavings.com",
    "wof:name":"Ohio Savings Bank",
    "wof:placetype":"venue"
},
  "geometry": {"coordinates":[-81.59421399999999,41.400388],"type":"Point"}
}