{
  "type": "Feature",
  "properties": {
    "iso:country":"US",
    "sg:address":"8349 Plainfield Rd",
    "sg:city":"Cincinnati",
    "sg:classifiers":[
        {
            "category":"Home & Garden",
            "subcategory":"Building Materials",
            "type":"Retail Goods"
        }
    ],
    "sg:phone":"+1 513 469 8090",
    "sg:postcode":"45236",
    "sg:province":"OH",
    "sg:tags":[
        "windows"
    ],
    "wof:name":"Sycamore Windows & Doors",
    "wof:placetype":"venue"
},
  "geometry": {"coordinates":[-84.39914,39.208498],"type":"Point"}
}