{
  "type": "Feature",
  "properties": {
    "addr:full": "8349 Plainfield Rd Cincinnati OH 45236",
    "addr:housenumber": "8349",
    "addr:postcode": "45236",
    "addr:street": "Plainfield Rd",
    "iso:country": "US",
    "sg:address": "8349 Plainfield Rd",
    "sg:city": "Cincinnati",
    "sg:classifiers": [
      {
        "category": "Home \u0026 Garden",
        "subcategory": "Building Materials",
        "type": "Retail Goods"
      }
    ],
    "sg:phone": "+1 513 469 8090",
    "sg:postcode": "45236",
    "sg:province": "OH",
    "sg:tags": [
      "windows"
    ],
    "wof:name": "Sycamore Windows \u0026 Doors",
    "wof:placetype": "venue"
  },
  "geometry": {"coordinates":[-84.39914,39.208498],"type":"Point"}
}
