{
  "type": "Feature",
  "properties": {
    "iso:country":"US",
    "sg:address":"1192 E Central Ave",
    "sg:city":"Dayton",
    "sg:classifiers":[
        {
            "category":"Professional",
            "subcategory":"Business Services",
            "type":"Services"
        }
    ],
    "sg:phone":"+1 937 384 0430",
    "sg:postcode":"45449",
    "sg:province":"OH",
    "sg:tags":[
        "pr",
        "commercial"
    ],
    "wof:name":"Appleheart",
    "wof:placetype":"venue"
},
  "geometry": {"coordinates":[-84.234881,39.678907],"type":"Point"}
}