{
  "type": "Feature",
  "properties": {
    "iso:country":"US",
    "sg:address":"16576 Co Rd F",
    "sg:city":"Holgate",
    "sg:classifiers":[
        {
            "category":"Real Estate",
            "subcategory":"Real Estate Operator",
            "type":"Services"
        }
    ],
    "sg:phone":"+1 419 264 7572",
    "sg:postcode":"43527",
    "sg:province":"OH",
    "sg:tags":[
        "property",
        "lessor"
    ],
    "wof:name":"Arthur Gustwiller",
    "wof:placetype":"venue"
},
  "geometry": {"coordinates":[-84.182012,41.238887],"type":"Point"}
}