{
  "type": "Feature",
  "properties": {
    "iso:country":"US",
    "sg:address":"30 Troy Road Shopping Center",
    "sg:city":"Delaware",
    "sg:classifiers":[
        {
            "category":"Banks & Credit Unions",
            "subcategory":"Investment Brokerage",
            "type":"Services"
        }
    ],
    "sg:phone":"+1 740 363 7557",
    "sg:postcode":"43015",
    "sg:province":"OH",
    "sg:tags":[
        "consultant",
        "planning",
        "financial"
    ],
    "wof:name":"Haller & Haller Financial Svc",
    "wof:placetype":"venue"
},
  "geometry": {"coordinates":[-83.09146200000001,40.307409],"type":"Point"}
}