{
  "type": "Feature",
  "properties": {
    "addr:full": "30 Troy Road Shopping Center Delaware OH 43015",
    "addr:housenumber": "30",
    "addr:postcode": "43015",
    "addr:street": "Troy Road Shopping",
    "iso:country": "US",
    "sg:address": "30 Troy Road Shopping Center",
    "sg:city": "Delaware",
    "sg:classifiers": [
      {
        "category": "Banks \u0026 Credit Unions",
        "subcategory": "Investment Brokerage",
        "type": "Services"
      }
    ],
    "sg:phone": "+1 740 363 7557",
    "sg:postcode": "43015",
    "sg:province": "OH",
    "sg:tags": [
      "consultant",
      "planning",
      "financial"
    ],
    "wof:name": "Haller \u0026 Haller Financial Svc",
    "wof:placetype": "venue"
  },
  "geometry": {"coordinates":[-83.091462,40.307409],"type":"Point"}
}
