{
  "type": "Feature",
  "properties": {
    "addr:full":"449 N Main St Munroe Falls OH 44262",
    "addr:housenumber":"449",
    "addr:postcode":"44262",
    "addr:street":"N Main St",
    "iso:country":"US",
    "sg:address":"449 N Main St",
    "sg:city":"Munroe Falls",
    "sg:classifiers":[
        {
            "category":"Manufacturing",
            "subcategory":"Tools & Machinery",
            "type":"Manufacturing & Wholesale Goods"
        }
    ],
    "sg:phone":"+1 330 688 8251",
    "sg:postcode":"44262",
    "sg:province":"OH",
    "sg:tags":[
        "industrial",
        "mold",
        "mfg"
    ],
    "wof:name":"Superior Mold & Die Co",
    "wof:placetype":"venue"
},
  "geometry": {"coordinates":[-81.440462,41.152061],"type":"Point"}
}