{
  "type": "Feature",
  "properties": {
    "addr:full": "3101 Regal Ln Cincinnati OH 45251",
    "addr:housenumber": "3101",
    "addr:postcode": "45251",
    "addr:street": "Regal Ln",
    "iso:country": "US",
    "sg:address": "3101 Regal Ln",
    "sg:city": "Cincinnati",
    "sg:classifiers": [
      {
        "category": "Wholesale",
        "subcategory": "Furniture",
        "type": "Manufacturing \u0026 Wholesale Goods"
      }
    ],
    "sg:phone": "+1 513 923 9535",
    "sg:postcode": "45251",
    "sg:province": "OH",
    "wof:name": "Smed International",
    "wof:placetype": "venue"
  },
  "geometry": {"coordinates":[-84.585418,39.22767],"type":"Point"}
}
