{
  "type": "Feature",
  "properties": {
    "iso:country":"US",
    "sg:address":"415 Straight St",
    "sg:city":"Cincinnati",
    "sg:classifiers":[
        {
            "category":"Health Services",
            "subcategory":"Doctor",
            "type":"Services"
        }
    ],
    "sg:phone":"+1 513 751 4722",
    "sg:postcode":"45219",
    "sg:province":"OH",
    "sg:tags":[
        "physician",
        "surgeon"
    ],
    "wof:name":"Greater Cincinnati Crdvsclr",
    "wof:placetype":"venue"
},
  "geometry": {"coordinates":[-84.52444800000001,39.12982],"type":"Point"}
}