{
  "type": "Feature",
  "properties": {
    "addr:full": "415 Straight St Cincinnati OH 45219",
    "addr:housenumber": "415",
    "addr:postcode": "45219",
    "addr:street": "Straight St",
    "iso:country": "US",
    "sg:address": "415 Straight St",
    "sg:city": "Cincinnati",
    "sg:classifiers": [
      {
        "category": "Health Services",
        "subcategory": "Doctor",
        "type": "Services"
      }
    ],
    "sg:phone": "+1 513 751 4722",
    "sg:postcode": "45219",
    "sg:province": "OH",
    "sg:tags": [
      "physician",
      "surgeon"
    ],
    "wof:name": "Greater Cincinnati Crdvsclr",
    "wof:placetype": "venue"
  },
  "geometry": {"coordinates":[-84.524448,39.12982],"type":"Point"}
}
