{
  "type": "Feature",
  "properties": {
    "addr:full":"1156 Jesus Fan West Harrison OH 47060",
    "addr:housenumber":"1156",
    "addr:postcode":"47060",
    "addr:street":"Jesus Fan",
    "iso:country":"US",
    "sg:address":"1156 Jesus Fan",
    "sg:city":"West Harrison",
    "sg:classifiers":[
        {
            "category":"Building & Trades",
            "subcategory":"Construction",
            "type":"Services"
        }
    ],
    "sg:phone":"+1 812 637 5747",
    "sg:postcode":"47060",
    "sg:province":"OH",
    "sg:tags":[
        "house"
    ],
    "wof:name":"HM Exterior Home Repairs Inc",
    "wof:placetype":"venue"
},
  "geometry": {"coordinates":[-84.90713599999999,39.315439],"type":"Point"}
}