{
  "type": "Feature",
  "properties": {
    "iso:country":"US",
    "sg:address":"2900 Jefferson Ave",
    "sg:city":"Cincinnati",
    "sg:classifiers":[
        {
            "category":"Professional",
            "type":"Services"
        }
    ],
    "sg:phone":"+1 513 665 9070",
    "sg:postcode":"45219",
    "sg:province":"OH",
    "sg:tags":[
        "establishment"
    ],
    "wof:name":"On Line Rewards",
    "wof:placetype":"venue"
},
  "geometry": {"coordinates":[-84.51082599999999,39.134288],"type":"Point"}
}