{
  "type": "Feature",
  "properties": {
    "addr:full":"1027 Doyle Rd Jefferson OH 44047",
    "addr:housenumber":"1027",
    "addr:postcode":"44047",
    "addr:street":"Doyle Rd",
    "iso:country":"US",
    "sg:address":"1027 Doyle Rd",
    "sg:city":"Jefferson",
    "sg:classifiers":[
        {
            "category":"Freight",
            "type":"Transportation"
        }
    ],
    "sg:phone":"+1 440 576 0171",
    "sg:postcode":"44047",
    "sg:province":"OH",
    "sg:tags":[
        "hauling",
        "trucking"
    ],
    "wof:name":"Mrm Trucking",
    "wof:placetype":"venue"
},
  "geometry": {"coordinates":[-80.789751,41.748763],"type":"Point"}
}