{
  "type": "Feature",
  "properties": {
    "addr:full":"13895 Cedar Rd Cleveland OH 44118",
    "addr:housenumber":"13895",
    "addr:postcode":"44118",
    "addr:street":"Cedar Rd",
    "iso:country":"US",
    "sg:address":"13895 Cedar Rd",
    "sg:city":"Cleveland",
    "sg:classifiers":[
        {
            "category":"Shopping",
            "subcategory":"Jewelry",
            "type":"Retail Goods"
        }
    ],
    "sg:phone":"+1 216 320 2942",
    "sg:postcode":"44118",
    "sg:province":"OH",
    "sg:tags":[
        "jeweler"
    ],
    "wof:name":"I E Jewelry & Gifts",
    "wof:placetype":"venue"
},
  "geometry": {"coordinates":[-81.544465,41.501444],"type":"Point"}
}