{
  "type": "Feature",
  "properties": {
    "iso:country":"US",
    "sg:address":"8820 Bender Rd",
    "sg:city":"North Ridgeville",
    "sg:classifiers":[
        {
            "category":"Restaurant",
            "type":"Food & Drink"
        }
    ],
    "sg:phone":"+1 440 327 2306",
    "sg:postcode":"44039",
    "sg:province":"OH",
    "sg:tags":[
        "caterer"
    ],
    "wof:name":"Melody Grove",
    "wof:placetype":"venue"
},
  "geometry": {"coordinates":[-82.056343,41.363039],"type":"Point"}
}