{
  "type": "Feature",
  "properties": {
    "iso:country":"US",
    "sg:address":"7350 Monclova Rd",
    "sg:city":"Maumee",
    "sg:classifiers":[
        {
            "category":"Farming",
            "subcategory":"Farm",
            "type":"Manufacturing & Wholesale Goods"
        }
    ],
    "sg:phone":"+1 419 868 8499",
    "sg:postcode":"43537",
    "sg:province":"OH",
    "sg:tags":[
        "crop",
        "general"
    ],
    "wof:name":"Graystone Farm Sporthorses LLC",
    "wof:placetype":"venue"
},
  "geometry": {"coordinates":[-83.71552,41.558918],"type":"Point"}
}