{
  "type": "Feature",
  "properties": {
    "addr:full": "8595 Jonathan Ln Maineville OH 45039",
    "addr:housenumber": "8595",
    "addr:postcode": "45039",
    "addr:street": "Jonathan Ln",
    "iso:country": "US",
    "sg:address": "8595 Jonathan Ln",
    "sg:city": "Maineville",
    "sg:classifiers": [
      {
        "category": "Building \u0026 Trades",
        "subcategory": "Plumbing",
        "type": "Services"
      }
    ],
    "sg:phone": "+1 513 677 2485",
    "sg:postcode": "45039",
    "sg:province": "OH",
    "sg:tags": [
      "contractor"
    ],
    "wof:name": "Jack Sturgis Plumbing",
    "wof:placetype": "venue"
  },
  "geometry": {"coordinates":[-84.27209,39.313534],"type":"Point"}
}
