{
  "type": "Feature",
  "properties": {
    "iso:country":"US",
    "sg:address":"8595 Jonathan Ln",
    "sg:city":"Maineville",
    "sg:classifiers":[
        {
            "category":"Building & Trades",
            "subcategory":"Plumbing",
            "type":"Services"
        }
    ],
    "sg:phone":"+1 513 677 2485",
    "sg:postcode":"45039",
    "sg:province":"OH",
    "sg:tags":[
        "contractor"
    ],
    "wof:name":"Jack Sturgis Plumbing",
    "wof:placetype":"venue"
},
  "geometry": {"coordinates":[-84.27209000000001,39.313534],"type":"Point"}
}