{
  "type": "Feature",
  "properties": {
    "iso:country":"US",
    "sg:address":"306 W Main St",
    "sg:city":"Scio",
    "sg:classifiers":[
        {
            "category":"Government",
            "subcategory":"Office",
            "type":"Public Place"
        }
    ],
    "sg:phone":"+1 740 945 5571",
    "sg:postcode":"43988",
    "sg:province":"OH",
    "sg:tags":[
        "city"
    ],
    "wof:name":"Scio Mayor's Office",
    "wof:placetype":"venue"
},
  "geometry": {"coordinates":[-81.086146,40.398346],"type":"Point"}
}