{
  "type": "Feature",
  "properties": {
    "iso:country":"US",
    "sg:address":"14641 Pruden Rd",
    "sg:city":"Sidney",
    "sg:phone":"+1 937 492 4163",
    "sg:postcode":"45365",
    "sg:province":"OH",
    "sg:tags":[
        "farm",
        "soybean"
    ],
    "wof:name":"Mitch Brautigam",
    "wof:placetype":"venue"
},
  "geometry": {"coordinates":[-84.134321,40.227303],"type":"Point"}
}