{
  "type": "Feature",
  "properties": {
    "iso:country":"US",
    "sg:address":"7219 Winchester Dr",
    "sg:city":"Solon",
    "sg:classifiers":[
        {
            "category":"Wholesale",
            "subcategory":"Machinery & Supplies",
            "type":"Manufacturing & Wholesale Goods"
        }
    ],
    "sg:phone":"+1 440 519 1614",
    "sg:postcode":"44139",
    "sg:province":"OH",
    "sg:tags":[
        "engineering",
        "industrial",
        "computer"
    ],
    "wof:name":"Rav International",
    "wof:placetype":"venue"
},
  "geometry": {"coordinates":[-81.439117,41.362071],"type":"Point"}
}