{
  "type": "Feature",
  "properties": {
    "iso:country":"US",
    "sg:address":"19615 Lake Rd",
    "sg:city":"Cleveland",
    "sg:classifiers":[
        {
            "category":"Marine",
            "type":"Transportation"
        }
    ],
    "sg:phone":"+1 440 333 9292",
    "sg:postcode":"44116",
    "sg:province":"OH",
    "sg:tags":[
        "surveyor"
    ],
    "wof:name":"Lake Erie Appraisal Co",
    "wof:placetype":"venue"
},
  "geometry": {"coordinates":[-81.835493,41.484478],"type":"Point"}
}