{
  "type": "Feature",
  "properties": {
    "addr:full":"7421 W Chester Rd West Chester OH 45069",
    "addr:housenumber":"7421",
    "addr:postcode":"45069",
    "addr:street":"W Chester Rd",
    "iso:country":"US",
    "sg:address":"7421 W Chester Rd",
    "sg:city":"West Chester",
    "sg:classifiers":[
        {
            "category":"Professional",
            "subcategory":"Management & Consulting",
            "type":"Services"
        }
    ],
    "sg:phone":"+1 513 942 3972",
    "sg:postcode":"45069",
    "sg:province":"OH",
    "sg:tags":[
        "consultant",
        "business"
    ],
    "wof:name":"Leadership Ventures",
    "wof:placetype":"venue"
},
  "geometry": {"coordinates":[-84.380033,39.319893],"type":"Point"}
}