{
  "type": "Feature",
  "properties": {
    "iso:country":"US",
    "sg:address":"7011 Springdale Rd",
    "sg:city":"Cincinnati",
    "sg:classifiers":[
        {
            "category":"Manufacturing",
            "subcategory":"Printing",
            "type":"Manufacturing & Wholesale Goods"
        }
    ],
    "sg:phone":"+1 513 353 4700",
    "sg:postcode":"45247",
    "sg:province":"OH",
    "sg:tags":[
        "commercial"
    ],
    "wof:name":"Service Printing Co",
    "wof:placetype":"venue"
},
  "geometry": {"coordinates":[-84.674908,39.214501],"type":"Point"}
}