{
  "type": "Feature",
  "properties": {
    "addr:full": "7401 Co Rd 236 Findlay OH 45840",
    "addr:housenumber": "7401;236",
    "addr:postcode": "45840",
    "addr:street": "Co Rd",
    "iso:country": "US",
    "sg:address": "7401 Co Rd 236",
    "sg:city": "Findlay",
    "sg:classifiers": [
      {
        "category": "Farming",
        "subcategory": "Farm",
        "type": "Manufacturing \u0026 Wholesale Goods"
      }
    ],
    "sg:phone": "+1 419 422 7445",
    "sg:postcode": "45840",
    "sg:province": "OH",
    "sg:tags": [
      "crop",
      "general"
    ],
    "wof:name": "Gerald L Johnson",
    "wof:placetype": "venue"
  },
  "geometry": {"coordinates":[-83.592726,41.059047],"type":"Point"}
}
