{
  "type": "Feature",
  "properties": {
    "iso:country":"US",
    "sg:address":"7401 Co Rd 236",
    "sg:city":"Findlay",
    "sg:classifiers":[
        {
            "category":"Farming",
            "subcategory":"Farm",
            "type":"Manufacturing & Wholesale Goods"
        }
    ],
    "sg:phone":"+1 419 422 7445",
    "sg:postcode":"45840",
    "sg:province":"OH",
    "sg:tags":[
        "crop",
        "general"
    ],
    "wof:name":"Gerald L Johnson",
    "wof:placetype":"venue"
},
  "geometry": {"coordinates":[-83.592726,41.059047],"type":"Point"}
}