{
  "type": "Feature",
  "properties": {
    "addr:full": "6437 Eby Rd Smithville OH 44677",
    "addr:housenumber": "6437",
    "addr:postcode": "44677",
    "addr:street": "Eby Rd",
    "iso:country": "US",
    "sg:address": "6437 Eby Rd",
    "sg:city": "Smithville",
    "sg:classifiers": [
      {
        "category": "Farming",
        "subcategory": "Farm",
        "type": "Manufacturing \u0026 Wholesale Goods"
      }
    ],
    "sg:phone": "+1 330 669 3237",
    "sg:postcode": "44677",
    "sg:province": "OH",
    "sg:tags": [
      "crop",
      "general"
    ],
    "wof:name": "Earnest Rehm",
    "wof:placetype": "venue"
  },
  "geometry": {"coordinates":[-81.861293,40.875277],"type":"Point"}
}
