{
  "type": "Feature",
  "properties": {
    "iso:country":"US",
    "sg:address":"6437 Eby Rd",
    "sg:city":"Smithville",
    "sg:classifiers":[
        {
            "category":"Farming",
            "subcategory":"Farm",
            "type":"Manufacturing & Wholesale Goods"
        }
    ],
    "sg:phone":"+1 330 669 3237",
    "sg:postcode":"44677",
    "sg:province":"OH",
    "sg:tags":[
        "crop",
        "general"
    ],
    "wof:name":"Earnest Rehm",
    "wof:placetype":"venue"
},
  "geometry": {"coordinates":[-81.861293,40.875277],"type":"Point"}
}