{
  "type": "Feature",
  "properties": {
    "addr:full":"12585 Oxford Rd Germantown OH 45327",
    "addr:housenumber":"12585",
    "addr:postcode":"45327",
    "addr:street":"Oxford Rd",
    "iso:country":"US",
    "sg:address":"12585 Oxford Rd",
    "sg:city":"Germantown",
    "sg:classifiers":[
        {
            "category":"Real Estate",
            "subcategory":"Real Estate Agent",
            "type":"Services"
        }
    ],
    "sg:phone":"+1 937 855 2552",
    "sg:postcode":"45327",
    "sg:province":"OH",
    "wof:name":"B R Campbell Real Estate",
    "wof:placetype":"venue"
},
  "geometry": {"coordinates":[-84.416837,39.618708],"type":"Point"}
}