{
  "type": "Feature",
  "properties": {
    "addr:full": "28017 W Oakland Rd Cleveland OH 44140",
    "addr:housenumber": "28017",
    "addr:postcode": "44140",
    "addr:street": "W Oakland Rd",
    "iso:country": "US",
    "sg:address": "28017 W Oakland Rd",
    "sg:city": "Cleveland",
    "sg:classifiers": [
      {
        "category": "Professional",
        "subcategory": "Computer Services",
        "type": "Services"
      }
    ],
    "sg:phone": "+1 440 250 9432",
    "sg:postcode": "44140",
    "sg:province": "OH",
    "sg:tags": [
      "internet"
    ],
    "wof:name": "Leap Frog Co",
    "wof:placetype": "venue"
  },
  "geometry": {"coordinates":[-81.929426,41.483079],"type":"Point"}
}
