{
  "type": "Feature",
  "properties": {
    "addr:full":"4111 Executive Pkwy Westerville OH 43081",
    "addr:housenumber":"4111",
    "addr:postcode":"43081",
    "addr:street":"Executive Pkwy",
    "iso:country":"US",
    "sg:address":"4111 Executive Pkwy",
    "sg:city":"Westerville",
    "sg:classifiers":[
        {
            "category":"Professional",
            "subcategory":"Management & Consulting",
            "type":"Services"
        }
    ],
    "sg:phone":"+1 800 576 4377",
    "sg:postcode":"43081",
    "sg:province":"OH",
    "sg:tags":[
        "grocery",
        "public",
        "relations"
    ],
    "wof:name":"Kroger",
    "wof:placetype":"venue"
},
  "geometry": {"coordinates":[-82.901365,40.083789],"type":"Point"}
}