{
  "type": "Feature",
  "properties": {
    "addr:full": "590 Lilley Ave Columbus OH 43205",
    "addr:housenumber": "590",
    "addr:postcode": "43205",
    "addr:street": "Lilley Ave",
    "iso:country": "US",
    "sg:address": "590 Lilley Ave",
    "sg:city": "Columbus",
    "sg:classifiers": [
      {
        "category": "Wholesale",
        "subcategory": "Vending Machines",
        "type": "Manufacturing \u0026 Wholesale Goods"
      }
    ],
    "sg:phone": "+1 614 258 4789",
    "sg:postcode": "43205",
    "sg:province": "OH",
    "sg:tags": [
      "operator",
      "device",
      "amusement"
    ],
    "wof:name": "Murphy S Vending",
    "wof:placetype": "venue"
  },
  "geometry": {"coordinates":[-82.957663,39.954323],"type":"Point"}
}
