{
  "type": "Feature",
  "properties": {
    "iso:country":"US",
    "sg:address":"140 Cameron Ridge Dr",
    "sg:city":"Columbus",
    "sg:classifiers":[
        {
            "category":"Real Estate",
            "subcategory":"Real Estate Operator",
            "type":"Services"
        }
    ],
    "sg:phone":"+1 614 844 6064",
    "sg:postcode":"43235",
    "sg:province":"OH",
    "sg:tags":[
        "condominium"
    ],
    "wof:name":"Triangle Real Estate",
    "wof:placetype":"venue"
},
  "geometry": {"coordinates":[-83.013109,40.125174],"type":"Point"}
}