{
  "type": "Feature",
  "properties": {
    "addr:full": "6041 Trinity Rd Defiance OH 43512",
    "addr:housenumber": "6041",
    "addr:postcode": "43512",
    "addr:street": "Trinity Rd",
    "iso:country": "US",
    "sg:address": "6041 Trinity Rd",
    "sg:city": "Defiance",
    "sg:classifiers": [
      {
        "category": "Building \u0026 Trades",
        "subcategory": "Construction",
        "type": "Services"
      }
    ],
    "sg:phone": "+1 419 658 2335",
    "sg:postcode": "43512",
    "sg:province": "OH",
    "sg:tags": [
      "house"
    ],
    "wof:name": "Rons Construction",
    "wof:placetype": "venue"
  },
  "geometry": {"coordinates":[-84.437917,41.352754],"type":"Point"}
}
