{
  "type": "Feature",
  "properties": {
    "addr:full":"525 W Pete Rose Way Cincinnati OH 45202",
    "addr:housenumber":"525",
    "addr:postcode":"45202",
    "addr:street":"W Pete Rose Way",
    "iso:country":"US",
    "sg:address":"525 W Pete Rose Way",
    "sg:city":"Cincinnati",
    "sg:classifiers":[
        {
            "category":"Insurance",
            "subcategory":"Insurance Agent",
            "type":"Services"
        }
    ],
    "sg:phone":"+1 513 721 3778",
    "sg:postcode":"45202",
    "sg:province":"OH",
    "wof:name":"Atlas Insurance",
    "wof:placetype":"venue"
},
  "geometry": {"coordinates":[-84.520843,39.09577],"type":"Point"}
}