{
  "type": "Feature",
  "properties": {
    "addr:full": "908 E Center St Marion OH 43302",
    "addr:housenumber": "908",
    "addr:postcode": "43302",
    "addr:street": "E Center St",
    "iso:country": "US",
    "sg:address": "908 E Center St",
    "sg:city": "Marion",
    "sg:classifiers": [
      {
        "category": "Organizations",
        "subcategory": "Religious Organization",
        "type": "Services"
      }
    ],
    "sg:phone": "+1 740 387 3477",
    "sg:postcode": "43302",
    "sg:province": "OH",
    "sg:tags": [
      "cemetery"
    ],
    "wof:name": "Forest Lawn Presbt Church",
    "wof:placetype": "venue"
  },
  "geometry": {"coordinates":[-83.107217,40.589557],"type":"Point"}
}
