{
  "type": "Feature",
  "properties": {
    "iso:country":"US",
    "sg:address":"9795 Dayton Lebanon Pike",
    "sg:city":"Dayton",
    "sg:classifiers":[
        {
            "category":"Social Services",
            "type":"Services"
        }
    ],
    "sg:phone":"+1 937 885 0074",
    "sg:postcode":"45458",
    "sg:province":"OH",
    "sg:tags":[
        "development",
        "education",
        "child"
    ],
    "wof:name":"Goddard School",
    "wof:placetype":"venue"
},
  "geometry": {"coordinates":[-84.16127400000001,39.601903],"type":"Point"}
}