{
  "type": "Feature",
  "properties": {
    "addr:full": "11645 Chesterdale Rd Cincinnati OH 45246",
    "addr:housenumber": "11645",
    "addr:postcode": "45246",
    "addr:street": "Chesterdale Rd",
    "iso:country": "US",
    "sg:address": "11645 Chesterdale Rd",
    "sg:city": "Cincinnati",
    "sg:classifiers": [
      {
        "category": "Travel",
        "subcategory": "Hotels \u0026 Motels",
        "type": "Entertainment"
      }
    ],
    "sg:phone": "+1 513 771 2457",
    "sg:postcode": "45246",
    "sg:province": "OH",
    "wof:name": "Extended Stay America Inc",
    "wof:placetype": "venue"
  },
  "geometry": {"coordinates":[-84.448188,39.286173],"type":"Point"}
}
