{
  "type": "Feature",
  "properties": {
    "iso:country":"US",
    "sg:address":"11645 Chesterdale Rd",
    "sg:city":"Cincinnati",
    "sg:classifiers":[
        {
            "category":"Travel",
            "subcategory":"Hotels & Motels",
            "type":"Entertainment"
        }
    ],
    "sg:phone":"+1 513 771 2457",
    "sg:postcode":"45246",
    "sg:province":"OH",
    "wof:name":"Extended Stay America Inc",
    "wof:placetype":"venue"
},
  "geometry": {"coordinates":[-84.448188,39.286173],"type":"Point"}
}