{
  "type": "Feature",
  "properties": {
    "addr:full": "9 E 2nd St London OH 43140",
    "addr:housenumber": "9",
    "addr:postcode": "43140",
    "addr:street": "E 2Nd St",
    "iso:country": "US",
    "sg:address": "9 E 2nd St",
    "sg:city": "London",
    "sg:classifiers": [
      {
        "category": "Health Services",
        "subcategory": "Doctor",
        "type": "Services"
      }
    ],
    "sg:phone": "+1 740 852 3440",
    "sg:postcode": "43140",
    "sg:province": "OH",
    "sg:tags": [
      "medical"
    ],
    "wof:name": "Greater Ohio Eye Surgeons",
    "wof:placetype": "venue"
  },
  "geometry": {"coordinates":[-83.446942,39.88626],"type":"Point"}
}
