{
  "type": "Feature",
  "properties": {
    "addr:full": "15627 Co Hwy 385 Loudonville OH 44842",
    "addr:housenumber": "15627",
    "addr:postcode": "44842",
    "addr:street": "Co Hwy 385",
    "iso:country": "US",
    "sg:address": "15627 Co Hwy 385",
    "sg:city": "Loudonville",
    "sg:classifiers": [
      {
        "category": "Retail",
        "subcategory": "Auto Repair",
        "type": "Services"
      }
    ],
    "sg:phone": "+1 419 994 4312",
    "sg:postcode": "44842",
    "sg:province": "OH",
    "sg:tags": [
      "body",
      "automobile",
      "painting"
    ],
    "wof:name": "Bishop's Collision Repair Ctr",
    "wof:placetype": "venue"
  },
  "geometry": {"coordinates":[-82.176725,40.646157],"type":"Point"}
}
