{
  "type": "Feature",
  "properties": {
    "addr:full":"400 Gargrave Rd Dayton OH 45449",
    "addr:housenumber":"400",
    "addr:postcode":"45449",
    "addr:street":"Gargrave Rd",
    "iso:country":"US",
    "sg:address":"400 Gargrave Rd",
    "sg:city":"Dayton",
    "sg:classifiers":[
        {
            "category":"Wholesale",
            "subcategory":"Machinery & Supplies",
            "type":"Manufacturing & Wholesale Goods"
        },
        {
            "category":"Wholesale",
            "subcategory":"Hardware",
            "type":"Manufacturing & Wholesale Goods"
        }
    ],
    "sg:phone":"+1 937 847 8888",
    "sg:postcode":"45449",
    "sg:province":"OH",
    "sg:tags":[
        "distributor",
        "equipment",
        "tool",
        "industrial"
    ],
    "sg:website":"www.buckeyetools.com",
    "wof:name":"Buckeye Tools & Supply Company",
    "wof:placetype":"venue"
},
  "geometry": {"coordinates":[-84.238817,39.652488],"type":"Point"}
}