{
  "type": "Feature",
  "properties": {
    "addr:full":"1867 W Market St Akron OH 44313",
    "addr:housenumber":"1867",
    "addr:postcode":"44313",
    "addr:street":"W Market St",
    "iso:country":"US",
    "sg:address":"1867 W Market St",
    "sg:city":"Akron",
    "sg:classifiers":[
        {
            "category":"Banks & Credit Unions",
            "subcategory":"Investment Brokerage",
            "type":"Services"
        }
    ],
    "sg:phone":"+1 330 867 4050",
    "sg:postcode":"44313",
    "sg:province":"OH",
    "sg:tags":[
        "consultant",
        "planning",
        "financial"
    ],
    "wof:name":"Hanzel Consulting Group Inc",
    "wof:placetype":"venue"
},
  "geometry": {"coordinates":[-81.57472,41.111971],"type":"Point"}
}