{
  "type": "Feature",
  "properties": {
    "iso:country":"US",
    "sg:address":"4289 Manhattan Ave",
    "sg:city":"Brunswick",
    "sg:classifiers":[
        {
            "category":"Education",
            "subcategory":"Special Training",
            "type":"Public Place"
        }
    ],
    "sg:phone":"+1 330 273 2772",
    "sg:postcode":"44212",
    "sg:province":"OH",
    "sg:tags":[
        "instruction",
        "music"
    ],
    "wof:name":"Brunswick Music Ctr",
    "wof:placetype":"venue"
},
  "geometry": {"coordinates":[-81.84036999999999,41.236541],"type":"Point"}
}