{
  "type": "Feature",
  "properties": {
    "addr:full": "4289 Manhattan Ave Brunswick OH 44212",
    "addr:housenumber": "4289",
    "addr:postcode": "44212",
    "addr:street": "Manhattan Ave",
    "iso:country": "US",
    "sg:address": "4289 Manhattan Ave",
    "sg:city": "Brunswick",
    "sg:classifiers": [
      {
        "category": "Education",
        "subcategory": "Special Training",
        "type": "Public Place"
      }
    ],
    "sg:phone": "+1 330 273 2772",
    "sg:postcode": "44212",
    "sg:province": "OH",
    "sg:tags": [
      "instruction",
      "music"
    ],
    "wof:name": "Brunswick Music Ctr",
    "wof:placetype": "venue"
  },
  "geometry": {"coordinates":[-81.84037,41.236541],"type":"Point"}
}
