{
  "type": "Feature",
  "properties": {
    "addr:full":"1329 Cherryway Dr Gahanna OH 43230",
    "addr:housenumber":"1329",
    "addr:postcode":"43230",
    "addr:street":"Cherryway Dr",
    "iso:country":"US",
    "sg:address":"1329 Cherryway Dr",
    "sg:city":"Gahanna",
    "sg:classifiers":[
        {
            "category":"Health Services",
            "subcategory":"Health Practitioner",
            "type":"Services"
        }
    ],
    "sg:phone":"+1 614 475 4060",
    "sg:postcode":"43230",
    "sg:province":"OH",
    "sg:tags":[
        "therapist",
        "physical"
    ],
    "wof:name":"University Area Physical Thrpy",
    "wof:placetype":"venue"
},
  "geometry": {"coordinates":[-82.887593,40.056109],"type":"Point"}
}