{
  "type": "Feature",
  "properties": {
    "iso:country":"US",
    "sg:address":"160 N Chestnut St",
    "sg:city":"Kent",
    "sg:classifiers":[
        {
            "category":"Mining & Drilling",
            "type":"Manufacturing & Wholesale Goods"
        }
    ],
    "sg:phone":"+1 330 297 6891",
    "sg:postcode":"44240",
    "sg:province":"OH",
    "sg:tags":[
        "development",
        "gas",
        "oil",
        "exploration"
    ],
    "wof:name":"Beck Energy Corp",
    "wof:placetype":"venue"
},
  "geometry": {"coordinates":[-81.368709,41.154706],"type":"Point"}
}