{
  "type": "Feature",
  "properties": {
    "addr:full":"1470 N Bridge St Chillicothe OH 45601",
    "addr:housenumber":"1470",
    "addr:postcode":"45601",
    "addr:street":"N Bridge St",
    "iso:country":"US",
    "sg:address":"1470 N Bridge St",
    "sg:city":"Chillicothe",
    "sg:classifiers":[
        {
            "category":"Banks & Credit Unions",
            "subcategory":"Bank",
            "type":"Services"
        }
    ],
    "sg:phone":"+1 740 773 9840",
    "sg:postcode":"45601",
    "sg:province":"OH",
    "wof:name":"Oak Hill Banks",
    "wof:placetype":"venue"
},
  "geometry": {"coordinates":[-82.975966,39.368059],"type":"Point"}
}