{
  "type": "Feature",
  "properties": {
    "addr:full": "62 W 6th St Cincinnati OH 45202",
    "addr:housenumber": "62",
    "addr:postcode": "45202",
    "addr:street": "W 6Th St",
    "iso:country": "US",
    "sg:address": "62 W 6th St",
    "sg:city": "Cincinnati",
    "sg:classifiers": [
      {
        "category": "Shopping",
        "type": "Retail Goods"
      }
    ],
    "sg:phone": "+1 513 421 5653",
    "sg:postcode": "45202",
    "sg:province": "OH",
    "sg:tags": [
      "orthopedic",
      "appliance"
    ],
    "wof:name": "Brace Shop",
    "wof:placetype": "venue"
  },
  "geometry": {"coordinates":[-84.51464,39.102336],"type":"Point"}
}
