{
  "type": "Feature",
  "properties": {
    "iso:country":"US",
    "sg:address":"32849 Fox Chappell Ln",
    "sg:city":"Avon Lake",
    "sg:classifiers":[
        {
            "category":"Freight",
            "type":"Transportation"
        }
    ],
    "sg:phone":"+1 440 933 7725",
    "sg:postcode":"44012",
    "sg:province":"OH",
    "sg:tags":[
        "mover"
    ],
    "wof:name":"Mike Mccoy",
    "wof:placetype":"venue"
},
  "geometry": {"coordinates":[-82.020561,41.487791],"type":"Point"}
}