{
  "type": "Feature",
  "properties": {
    "addr:full": "32849 Fox Chappell Ln Avon Lake OH 44012",
    "addr:housenumber": "32849",
    "addr:postcode": "44012",
    "addr:street": "Fox Chappell Ln",
    "iso:country": "US",
    "sg:address": "32849 Fox Chappell Ln",
    "sg:city": "Avon Lake",
    "sg:classifiers": [
      {
        "category": "Freight",
        "type": "Transportation"
      }
    ],
    "sg:phone": "+1 440 933 7725",
    "sg:postcode": "44012",
    "sg:province": "OH",
    "sg:tags": [
      "mover"
    ],
    "wof:name": "Mike Mccoy",
    "wof:placetype": "venue"
  },
  "geometry": {"coordinates":[-82.020561,41.487791],"type":"Point"}
}
