{
  "type": "Feature",
  "properties": {
    "addr:full":"919 Chagrin River Rd Gates Mills OH 44040",
    "addr:housenumber":"919",
    "addr:postcode":"44040",
    "addr:street":"Chagrin River Rd",
    "iso:country":"US",
    "sg:address":"919 Chagrin River Rd",
    "sg:city":"Gates Mills",
    "sg:classifiers":[
        {
            "category":"Shopping",
            "type":"Retail Goods"
        }
    ],
    "sg:phone":"+1 440 423 1825",
    "sg:postcode":"44040",
    "sg:province":"OH",
    "sg:tags":[
        "cosmetic",
        "perfume"
    ],
    "wof:name":"Mischele A Bender Cosmetics",
    "wof:placetype":"venue"
},
  "geometry": {"coordinates":[-81.408478,41.534442],"type":"Point"}
}