{
  "type": "Feature",
  "properties": {
    "iso:country":"US",
    "sg:address":"4433 Diana Dr",
    "sg:city":"Broadview Heights",
    "sg:classifiers":[
        {
            "category":"Real Estate",
            "subcategory":"Real Estate Operator",
            "type":"Services"
        }
    ],
    "sg:phone":"+1 440 526 4112",
    "sg:postcode":"44147",
    "sg:province":"OH",
    "sg:tags":[
        "building",
        "nonresidential"
    ],
    "wof:name":"Chm Properties LLC",
    "wof:placetype":"venue"
},
  "geometry": {"coordinates":[-81.658609,41.339093],"type":"Point"}
}