{
  "type": "Feature",
  "properties": {
    "addr:full": "7465 State Rte 366 Huntsville OH 43324",
    "addr:housenumber": "7465",
    "addr:postcode": "43324",
    "addr:street": "State Rte 366",
    "iso:country": "US",
    "sg:address": "7465 State Rte 366",
    "sg:city": "Huntsville",
    "sg:classifiers": [
      {
        "category": "Banks \u0026 Credit Unions",
        "subcategory": "Investment Brokerage",
        "type": "Services"
      }
    ],
    "sg:phone": "+1 937 843 3999",
    "sg:postcode": "43324",
    "sg:province": "OH",
    "sg:tags": [
      "advisory",
      "financial"
    ],
    "wof:name": "Brennan Financial Group",
    "wof:placetype": "venue"
  },
  "geometry": {"coordinates":[-83.857387,40.46981],"type":"Point"}
}
