{
  "type": "Feature",
  "properties": {
    "addr:full": "1900 Sheridan Ave Springfield OH 45505",
    "addr:housenumber": "1900",
    "addr:postcode": "45505",
    "addr:street": "Sheridan Ave",
    "iso:country": "US",
    "sg:address": "1900 Sheridan Ave",
    "sg:city": "Springfield",
    "sg:classifiers": [
      {
        "category": "Restaurant",
        "type": "Food \u0026 Drink"
      }
    ],
    "sg:phone": "+1 937 324 7383",
    "sg:postcode": "45505",
    "sg:province": "OH",
    "sg:tags": [
      "eating"
    ],
    "wof:name": "Snyder Park Restaurant",
    "wof:placetype": "venue"
  },
  "geometry": {"coordinates":[-83.780664,39.913734],"type":"Point"}
}
