{
  "type": "Feature",
  "properties": {
    "iso:country":"US",
    "sg:address":"5665 Hogpath Rd",
    "sg:city":"Greenville",
    "sg:classifiers":[
        {
            "category":"Manufacturing",
            "subcategory":"Signs",
            "type":"Manufacturing & Wholesale Goods"
        }
    ],
    "sg:phone":"+1 937 548 4780",
    "sg:postcode":"45331",
    "sg:province":"OH",
    "sg:tags":[
        "specialty",
        "mfg"
    ],
    "wof:name":"Dietrich Signs",
    "wof:placetype":"venue"
},
  "geometry": {"coordinates":[-84.59392099999999,40.048501],"type":"Point"}
}