{
  "type": "Feature",
  "properties": {
    "addr:full": "5665 Hogpath Rd Greenville OH 45331",
    "addr:housenumber": "5665",
    "addr:postcode": "45331",
    "addr:street": "Hogpath Rd",
    "iso:country": "US",
    "sg:address": "5665 Hogpath Rd",
    "sg:city": "Greenville",
    "sg:classifiers": [
      {
        "category": "Manufacturing",
        "subcategory": "Signs",
        "type": "Manufacturing \u0026 Wholesale Goods"
      }
    ],
    "sg:phone": "+1 937 548 4780",
    "sg:postcode": "45331",
    "sg:province": "OH",
    "sg:tags": [
      "specialty",
      "mfg"
    ],
    "wof:name": "Dietrich Signs",
    "wof:placetype": "venue"
  },
  "geometry": {"coordinates":[-84.593921,40.048501],"type":"Point"}
}
