{
  "type": "Feature",
  "properties": {
    "iso:country":"US",
    "sg:address":"505 Karen Ave",
    "sg:city":"Sidney",
    "sg:classifiers":[
        {
            "category":"Banks & Credit Unions",
            "subcategory":"Investment Brokerage",
            "type":"Services"
        },
        {
            "category":"Insurance",
            "subcategory":"Insurance Agent",
            "type":"Services"
        }
    ],
    "sg:phone":"+1 937 498 9884",
    "sg:postcode":"45365",
    "sg:province":"OH",
    "sg:tags":[
        "planning",
        "consultant",
        "consulting",
        "management",
        "financial"
    ],
    "wof:name":"Strayer Financial Service",
    "wof:placetype":"venue"
},
  "geometry": {"coordinates":[-84.172627,40.281773],"type":"Point"}
}