{
  "type": "Feature",
  "properties": {
    "addr:full": "26 S Shawnee Ave Zanesville OH 43701",
    "addr:housenumber": "26",
    "addr:postcode": "43701",
    "addr:street": "S Shawnee Ave",
    "iso:country": "US",
    "sg:address": "26 S Shawnee Ave",
    "sg:city": "Zanesville",
    "sg:classifiers": [
      {
        "category": "Professional",
        "type": "Services"
      }
    ],
    "sg:phone": "+1 740 452 3634",
    "sg:postcode": "43701",
    "sg:province": "OH",
    "sg:tags": [
      "establishment"
    ],
    "wof:name": "Clay Burley Products Co",
    "wof:placetype": "venue"
  },
  "geometry": {"coordinates":[-82.019633,39.901533],"type":"Point"}
}
