{
  "type": "Feature",
  "properties": {
    "addr:full":"1755 Merriman Rd Akron OH 44313",
    "addr:housenumber":"1755",
    "addr:postcode":"44313",
    "addr:street":"Merriman Rd",
    "iso:country":"US",
    "sg:address":"1755 Merriman Rd",
    "sg:city":"Akron",
    "sg:classifiers":[
        {
            "category":"Social Services",
            "type":"Services"
        }
    ],
    "sg:phone":"+1 330 873 1444",
    "sg:postcode":"44313",
    "sg:province":"OH",
    "sg:tags":[
        "counselor",
        "marriage",
        "family"
    ],
    "wof:name":"Pastoral Counseling Ctr",
    "wof:placetype":"venue"
},
  "geometry": {"coordinates":[-81.548918,41.133417],"type":"Point"}
}