{
  "type": "Feature",
  "properties": {
    "addr:full": "37841 Vine St Willoughby OH 44094",
    "addr:housenumber": "37841",
    "addr:postcode": "44094",
    "addr:street": "Vine St",
    "iso:country": "US",
    "sg:address": "37841 Vine St",
    "sg:city": "Willoughby",
    "sg:classifiers": [
      {
        "category": "Wholesale",
        "subcategory": "Machinery \u0026 Supplies",
        "type": "Manufacturing \u0026 Wholesale Goods"
      }
    ],
    "sg:phone": "+1 440 951 2949",
    "sg:postcode": "44094",
    "sg:province": "OH",
    "wof:name": "HWFS Supply Inc",
    "wof:placetype": "venue"
  },
  "geometry": {"coordinates":[-81.412554,41.642633],"type":"Point"}
}
