{
  "type": "Feature",
  "properties": {
    "iso:country":"US",
    "sg:address":"11260 Chester Rd",
    "sg:city":"Cincinnati",
    "sg:classifiers":[
        {
            "category":"Banks & Credit Unions",
            "subcategory":"Investment Brokerage",
            "type":"Services"
        }
    ],
    "sg:phone":"+1 513 772 3370",
    "sg:postcode":"45246",
    "sg:province":"OH",
    "sg:tags":[
        "advisory",
        "financial"
    ],
    "wof:name":"Householder Group",
    "wof:placetype":"venue"
},
  "geometry": {"coordinates":[-84.444213,39.272852],"type":"Point"}
}