{
  "type": "Feature",
  "properties": {
    "iso:country":"US",
    "sg:address":"1501 Findlay Rd",
    "sg:city":"Lima",
    "sg:classifiers":[
        {
            "category":"Home & Garden",
            "subcategory":"Hardware",
            "type":"Retail Goods"
        },
        {
            "category":"Home & Garden",
            "subcategory":"Garden Supply",
            "type":"Retail Goods"
        }
    ],
    "sg:phone":"+1 419 228 4241",
    "sg:postcode":"45801",
    "sg:province":"OH",
    "sg:tags":[
        "repair",
        "lawn",
        "saw",
        "chain",
        "mower"
    ],
    "wof:name":"Derringer's Inc",
    "wof:placetype":"venue"
},
  "geometry": {"coordinates":[-84.080068,40.755084],"type":"Point"}
}