{
  "type": "Feature",
  "properties": {
    "addr:full": "11424 Oxfordshire Ln Cincinnati OH 45240",
    "addr:postcode": "11424;45240",
    "addr:street": "Oxfordshire Ln",
    "iso:country": "US",
    "sg:address": "11424 Oxfordshire Ln",
    "sg:city": "Cincinnati",
    "sg:classifiers": [
      {
        "category": "Banks \u0026 Credit Unions",
        "subcategory": "Bank",
        "type": "Services"
      }
    ],
    "sg:phone": "+1 513 648 9947",
    "sg:postcode": "45240",
    "sg:province": "OH",
    "sg:tags": [
      "financing"
    ],
    "wof:name": "SBS Consultants",
    "wof:placetype": "venue"
  },
  "geometry": {"coordinates":[-84.542548,39.287304],"type":"Point"}
}
