{
  "type": "Feature",
  "properties": {
    "addr:full": "409 Kroft St Galion OH 44833",
    "addr:housenumber": "409",
    "addr:postcode": "44833",
    "addr:street": "Kroft St",
    "iso:country": "US",
    "sg:address": "409 Kroft St",
    "sg:city": "Galion",
    "sg:classifiers": [
      {
        "category": "Building \u0026 Trades",
        "subcategory": "Construction",
        "type": "Services"
      }
    ],
    "sg:phone": "+1 419 468 6944",
    "sg:postcode": "44833",
    "sg:province": "OH",
    "sg:tags": [
      "general",
      "contractor"
    ],
    "wof:name": "Weithman Brothers Inc",
    "wof:placetype": "venue"
  },
  "geometry": {"coordinates":[-82.795333,40.722169],"type":"Point"}
}
