{
  "type": "Feature",
  "properties": {
    "iso:country":"US",
    "sg:address":"1516 Woodrow Ave",
    "sg:city":"Cleveland",
    "sg:classifiers":[
        {
            "category":"Building & Trades",
            "subcategory":"Construction",
            "type":"Services"
        }
    ],
    "sg:phone":"+1 440 684 9970",
    "sg:postcode":"44124",
    "sg:province":"OH",
    "sg:tags":[
        "house"
    ],
    "wof:name":"Woodrow Remodeling & Cnstr",
    "wof:placetype":"venue"
},
  "geometry": {"coordinates":[-81.45225,41.515332],"type":"Point"}
}