{
  "type": "Feature",
  "properties": {
    "addr:full": "1516 Woodrow Ave Cleveland OH 44124",
    "addr:housenumber": "1516",
    "addr:postcode": "44124",
    "addr:street": "Woodrow Ave",
    "iso:country": "US",
    "sg:address": "1516 Woodrow Ave",
    "sg:city": "Cleveland",
    "sg:classifiers": [
      {
        "category": "Building \u0026 Trades",
        "subcategory": "Construction",
        "type": "Services"
      }
    ],
    "sg:phone": "+1 440 684 9970",
    "sg:postcode": "44124",
    "sg:province": "OH",
    "sg:tags": [
      "house"
    ],
    "wof:name": "Woodrow Remodeling \u0026 Cnstr",
    "wof:placetype": "venue"
  },
  "geometry": {"coordinates":[-81.45225,41.515332],"type":"Point"}
}
