{
  "type": "Feature",
  "properties": {
    "addr:full": "1225 Indiana Ave Toledo OH 43607",
    "addr:housenumber": "1225",
    "addr:postcode": "43607",
    "addr:street": "Indiana Ave",
    "iso:country": "US",
    "sg:address": "1225 Indiana Ave",
    "sg:city": "Toledo",
    "sg:classifiers": [
      {
        "category": "Freight",
        "type": "Transportation"
      }
    ],
    "sg:phone": "+1 419 244 7740",
    "sg:postcode": "43607",
    "sg:province": "OH",
    "sg:tags": [
      "warehouse"
    ],
    "wof:name": "B O B Inc",
    "wof:placetype": "venue"
  },
  "geometry": {"coordinates":[-83.573208,41.650271],"type":"Point"}
}
