{
  "type": "Feature",
  "properties": {
    "iso:country":"US",
    "sg:address":"1225 Indiana Ave",
    "sg:city":"Toledo",
    "sg:classifiers":[
        {
            "category":"Freight",
            "type":"Transportation"
        }
    ],
    "sg:phone":"+1 419 244 7740",
    "sg:postcode":"43607",
    "sg:province":"OH",
    "sg:tags":[
        "warehouse"
    ],
    "wof:name":"B O B Inc",
    "wof:placetype":"venue"
},
  "geometry": {"coordinates":[-83.57320799999999,41.650271],"type":"Point"}
}