{
  "type": "Feature",
  "properties": {
    "addr:full":"1407 S Main St Akron OH 44301",
    "addr:housenumber":"1407",
    "addr:postcode":"44301",
    "addr:street":"S Main St",
    "iso:country":"US",
    "sg:address":"1407 S Main St",
    "sg:city":"Akron",
    "sg:classifiers":[
        {
            "category":"Retail",
            "subcategory":"Repair Shop",
            "type":"Services"
        }
    ],
    "sg:phone":"+1 330 929 5737",
    "sg:postcode":"44301",
    "sg:province":"OH",
    "sg:tags":[
        "scooter",
        "motorcycle",
        "motor"
    ],
    "wof:name":"American Standard Supply",
    "wof:placetype":"venue"
},
  "geometry": {"coordinates":[-81.527908,41.04918],"type":"Point"}
}