{
  "type": "Feature",
  "properties": {
    "addr:full":"4458 E 131st St Cleveland OH 44105",
    "addr:housenumber":"4458",
    "addr:postcode":"44105",
    "addr:street":"E 131St St",
    "iso:country":"US",
    "sg:address":"4458 E 131st St",
    "sg:city":"Cleveland",
    "sg:classifiers":[
        {
            "category":"Building & Trades",
            "subcategory":"Electrical",
            "type":"Services"
        }
    ],
    "sg:phone":"+1 216 441 6625",
    "sg:postcode":"44105",
    "sg:province":"OH",
    "sg:tags":[
        "electric",
        "contractor"
    ],
    "wof:name":"Perram Electric",
    "wof:placetype":"venue"
},
  "geometry": {"coordinates":[-81.591084,41.43906],"type":"Point"}
}