{
  "type": "Feature",
  "properties": {
    "iso:country":"US",
    "sg:address":"10357 State Rte 81",
    "sg:city":"Dola",
    "sg:classifiers":[
        {
            "category":"Real Estate",
            "subcategory":"Real Estate Operator",
            "type":"Services"
        }
    ],
    "sg:phone":"+1 419 759 2661",
    "sg:postcode":"45835",
    "sg:province":"OH",
    "sg:tags":[
        "farm",
        "corn",
        "property",
        "soybean",
        "lessor"
    ],
    "wof:name":"Kenneth Pees",
    "wof:placetype":"venue"
},
  "geometry": {"coordinates":[-83.683154,40.77981],"type":"Point"}
}