{
  "type": "Feature",
  "properties": {
    "addr:full":"6432 W Chester Rd West Chester OH 45069",
    "addr:housenumber":"6432",
    "addr:postcode":"45069",
    "addr:street":"W Chester Rd",
    "iso:country":"US",
    "sg:address":"6432 W Chester Rd",
    "sg:city":"West Chester",
    "sg:classifiers":[
        {
            "category":"Retail",
            "subcategory":"Auto Repair",
            "type":"Services"
        }
    ],
    "sg:phone":"+1 513 771 2020",
    "sg:postcode":"45069",
    "sg:province":"OH",
    "sg:tags":[
        "trailer"
    ],
    "wof:name":"Fasig Co",
    "wof:placetype":"venue"
},
  "geometry": {"coordinates":[-84.41273,39.325936],"type":"Point"}
}