{
  "type": "Feature",
  "properties": {
    "addr:full": "3100 Manchester Rd Akron OH 44319",
    "addr:housenumber": "3100",
    "addr:postcode": "44319",
    "addr:street": "Manchester Rd",
    "iso:country": "US",
    "sg:address": "3100 Manchester Rd",
    "sg:city": "Akron",
    "sg:classifiers": [
      {
        "category": "Professional",
        "subcategory": "Accounting \u0026 Tax Preparation",
        "type": "Services"
      }
    ],
    "sg:phone": "+1 330 245 0954",
    "sg:postcode": "44319",
    "sg:province": "OH",
    "sg:tags": [
      "return",
      "filing"
    ],
    "sg:website": "www.jacksonhewitt.com",
    "wof:name": "Jackson Hewitt Tax Svc",
    "wof:placetype": "venue"
  },
  "geometry": {"coordinates":[-81.553163,41.014408],"type":"Point"}
}
