{
  "type": "Feature",
  "properties": {
    "addr:full": "100 Hidden Valley Dr NE Warren OH 44484",
    "addr:housenumber": "100",
    "addr:postcode": "44484",
    "addr:street": "Hidden Valley Dr Ne",
    "iso:country": "US",
    "sg:address": "100 Hidden Valley Dr NE",
    "sg:city": "Warren",
    "sg:classifiers": [
      {
        "category": "Building \u0026 Trades",
        "subcategory": "Construction",
        "type": "Services"
      }
    ],
    "sg:phone": "+1 330 372 5317",
    "sg:postcode": "44484",
    "sg:province": "OH",
    "sg:tags": [
      "contractor"
    ],
    "wof:name": "Z-Tech Builders-Excavators Inc",
    "wof:placetype": "venue"
  },
  "geometry": {"coordinates":[-80.726663,41.268805],"type":"Point"}
}
