{
  "type": "Feature",
  "properties": {
    "addr:full": "9930 Colton Rd Windham OH 44288",
    "addr:housenumber": "9930",
    "addr:postcode": "44288",
    "addr:street": "Colton Rd",
    "iso:country": "US",
    "sg:address": "9930 Colton Rd",
    "sg:city": "Windham",
    "sg:classifiers": [
      {
        "category": "Real Estate",
        "subcategory": "Real Estate Operator",
        "type": "Services"
      }
    ],
    "sg:phone": "+1 330 326 2829",
    "sg:postcode": "44288",
    "sg:province": "OH",
    "sg:tags": [
      "property",
      "lessor"
    ],
    "wof:name": "Brobst Mighnon",
    "wof:placetype": "venue"
  },
  "geometry": {"coordinates":[-81.008499,41.268682],"type":"Point"}
}
