{
  "type": "Feature",
  "properties": {
    "iso:country":"US",
    "sg:address":"5855 Turney Rd",
    "sg:city":"Cleveland",
    "sg:classifiers":[
        {
            "category":"Wholesale",
            "subcategory":"Non-durable Goods",
            "type":"Manufacturing & Wholesale Goods"
        }
    ],
    "sg:phone":"+1 216 475 4815",
    "sg:postcode":"44125",
    "sg:province":"OH",
    "sg:tags":[
        "cigarette",
        "cigar",
        "lighter"
    ],
    "wof:name":"Discount Cigarette Mart",
    "wof:placetype":"venue"
},
  "geometry": {"coordinates":[-81.59626400000001,41.403543],"type":"Point"}
}