{
  "type": "Feature",
  "properties": {
    "iso:country":"US",
    "sg:address":"710 W Smith Rd",
    "sg:city":"Medina",
    "sg:classifiers":[
        {
            "category":"Health Services",
            "subcategory":"Hospital",
            "type":"Services"
        }
    ],
    "sg:phone":"+1 330 336 6657",
    "sg:postcode":"44256",
    "sg:province":"OH",
    "sg:tags":[
        "mental"
    ],
    "wof:name":"Community Mental Health Servs",
    "wof:placetype":"venue"
},
  "geometry": {"coordinates":[-81.881836,41.136102],"type":"Point"}
}