{
  "type": "Feature",
  "properties": {
    "addr:full": "14110 Mahoning Ave North Jackson OH 44451",
    "addr:housenumber": "14110",
    "addr:postcode": "44451",
    "addr:street": "Mahoning Ave North",
    "iso:country": "US",
    "sg:address": "14110 Mahoning Ave",
    "sg:city": "North Jackson",
    "sg:classifiers": [
      {
        "category": "Social Services",
        "subcategory": "Child Care",
        "type": "Services"
      }
    ],
    "sg:phone": "+1 330 538 2320",
    "sg:postcode": "44451",
    "sg:province": "OH",
    "sg:tags": [
      "kindergarten",
      "academic",
      "school"
    ],
    "wof:name": "Mahoning County Educational",
    "wof:placetype": "venue"
  },
  "geometry": {"coordinates":[-80.916414,41.099347],"type":"Point"}
}
