{
  "type": "Feature",
  "properties": {
    "addr:full":"125 Long Lake Blvd Akron OH 44319",
    "addr:housenumber":"125",
    "addr:postcode":"44319",
    "addr:street":"Long Lake Blvd",
    "iso:country":"US",
    "sg:address":"125 Long Lake Blvd",
    "sg:city":"Akron",
    "sg:classifiers":[
        {
            "category":"Building & Trades",
            "subcategory":"Landscaping Services",
            "type":"Services"
        }
    ],
    "sg:phone":"+1 330 644 9305",
    "sg:postcode":"44319",
    "sg:province":"OH",
    "sg:tags":[
        "lawn",
        "garden"
    ],
    "wof:name":"Quality Lawn & Landscape",
    "wof:placetype":"venue"
},
  "geometry": {"coordinates":[-81.528527,41.00849],"type":"Point"}
}