{
  "type": "Feature",
  "properties": {
    "iso:country":"US",
    "sg:address":"516 W 5th St",
    "sg:city":"Delphos",
    "sg:classifiers":[
        {
            "category":"Shopping",
            "subcategory":"Gifts & Souvenirs",
            "type":"Retail Goods"
        }
    ],
    "sg:phone":"+1 419 692 6446",
    "sg:postcode":"45833",
    "sg:province":"OH",
    "wof:name":"Bases Loaded",
    "wof:placetype":"venue"
},
  "geometry": {"coordinates":[-84.345926,40.847157],"type":"Point"}
}