{
  "type": "Feature",
  "properties": {
    "addr:full":"532 Adams St Marion OH 43302",
    "addr:housenumber":"532",
    "addr:postcode":"43302",
    "addr:street":"Adams St",
    "iso:country":"US",
    "sg:address":"532 Adams St",
    "sg:city":"Marion",
    "sg:classifiers":[
        {
            "category":"Building & Trades",
            "subcategory":"Landscaping Services",
            "type":"Services"
        }
    ],
    "sg:phone":"+1 740 382 6003",
    "sg:postcode":"43302",
    "sg:province":"OH",
    "sg:tags":[
        "landscape"
    ],
    "wof:name":"M&M Landscaping",
    "wof:placetype":"venue"
},
  "geometry": {"coordinates":[-83.11689800000001,40.59619],"type":"Point"}
}