{
  "type": "Feature",
  "properties": {
    "addr:full": "7835 Kiowa Way Worthington OH 43085",
    "addr:housenumber": "7835",
    "addr:postcode": "43085",
    "addr:street": "Kiowa Way",
    "iso:country": "US",
    "sg:address": "7835 Kiowa Way",
    "sg:city": "Worthington",
    "sg:classifiers": [
      {
        "category": "Professional",
        "subcategory": "Accounting \u0026 Tax Preparation",
        "type": "Services"
      }
    ],
    "sg:phone": "+1 614 888 7959",
    "sg:postcode": "43085",
    "sg:province": "OH",
    "sg:tags": [
      "accountant"
    ],
    "wof:name": "Your Concerns Accounting Svc",
    "wof:placetype": "venue"
  },
  "geometry": {"coordinates":[-82.990724,40.125179],"type":"Point"}
}
