{
  "type": "Feature",
  "properties": {
    "iso:country":"US",
    "sg:address":"7835 Kiowa Way",
    "sg:city":"Worthington",
    "sg:classifiers":[
        {
            "category":"Professional",
            "subcategory":"Accounting & Tax Preparation",
            "type":"Services"
        }
    ],
    "sg:phone":"+1 614 888 7959",
    "sg:postcode":"43085",
    "sg:province":"OH",
    "sg:tags":[
        "accountant"
    ],
    "wof:name":"Your Concerns Accounting Svc",
    "wof:placetype":"venue"
},
  "geometry": {"coordinates":[-82.990724,40.125179],"type":"Point"}
}