{
  "type": "Feature",
  "properties": {
    "iso:country":"US",
    "sg:address":"3709 W 140th St",
    "sg:city":"Cleveland",
    "sg:classifiers":[
        {
            "category":"Shopping",
            "type":"Retail Goods"
        }
    ],
    "sg:phone":"+1 216 941 5797",
    "sg:postcode":"44111",
    "sg:province":"OH",
    "sg:tags":[
        "pet",
        "shop"
    ],
    "wof:name":"Petey's Petstop",
    "wof:placetype":"venue"
},
  "geometry": {"coordinates":[-81.790221,41.453137],"type":"Point"}
}