{
  "type": "Feature",
  "properties": {
    "addr:full": "594 W Main St Wilmington OH 45177",
    "addr:housenumber": "594",
    "addr:postcode": "45177",
    "addr:street": "W Main St",
    "iso:country": "US",
    "sg:address": "594 W Main St",
    "sg:city": "Wilmington",
    "sg:classifiers": [
      {
        "category": "Health Services",
        "subcategory": "Clinic",
        "type": "Services"
      },
      {
        "category": "Health Services",
        "subcategory": "Doctor",
        "type": "Services"
      }
    ],
    "sg:phone": "+1 937 382 5438",
    "sg:postcode": "45177",
    "sg:province": "OH",
    "sg:tags": [
      "physician",
      "surgeon",
      "specialty",
      "outpatient"
    ],
    "wof:name": "Clinton Neurological Services",
    "wof:placetype": "venue"
  },
  "geometry": {"coordinates":[-83.838253,39.445436],"type":"Point"}
}
