{
  "type": "Feature",
  "properties": {
    "addr:full": "11497 Springfield Pike Cincinnati OH 45246",
    "addr:housenumber": "11497",
    "addr:postcode": "45246",
    "addr:street": "Springfield Pike",
    "iso:country": "US",
    "sg:address": "11497 Springfield Pike",
    "sg:city": "Cincinnati",
    "sg:classifiers": [
      {
        "category": "Health Services",
        "subcategory": "Health Practitioner",
        "type": "Services"
      }
    ],
    "sg:phone": "+1 513 772 9300",
    "sg:postcode": "45246",
    "sg:province": "OH",
    "wof:name": "Family Success Consortium",
    "wof:placetype": "venue"
  },
  "geometry": {"coordinates":[-84.485397,39.284604],"type":"Point"}
}
