{
  "type": "Feature",
  "properties": {
    "iso:country":"US",
    "sg:address":"11497 Springfield Pike",
    "sg:city":"Cincinnati",
    "sg:classifiers":[
        {
            "category":"Health Services",
            "subcategory":"Health Practitioner",
            "type":"Services"
        }
    ],
    "sg:phone":"+1 513 772 9300",
    "sg:postcode":"45246",
    "sg:province":"OH",
    "wof:name":"Family Success Consortium",
    "wof:placetype":"venue"
},
  "geometry": {"coordinates":[-84.48539700000001,39.284604],"type":"Point"}
}