{
  "type": "Feature",
  "properties": {
    "addr:full":"948 Ashcreek Dr Dayton OH 45458",
    "addr:housenumber":"948",
    "addr:postcode":"45458",
    "addr:street":"Ashcreek Dr",
    "iso:country":"US",
    "sg:address":"948 Ashcreek Dr",
    "sg:city":"Dayton",
    "sg:classifiers":[
        {
            "category":"Farming",
            "subcategory":"Livestock Farm",
            "type":"Manufacturing & Wholesale Goods"
        }
    ],
    "sg:phone":"+1 937 433 8789",
    "sg:postcode":"45458",
    "sg:province":"OH",
    "sg:tags":[
        "bearing",
        "fur",
        "animal"
    ],
    "wof:name":"Mink Ronald Bruce and",
    "wof:placetype":"venue"
},
  "geometry": {"coordinates":[-84.182022,39.614497],"type":"Point"}
}