{
  "type": "Feature",
  "properties": {
    "iso:country":"US",
    "sg:address":"1 E High St",
    "sg:city":"Oxford",
    "sg:classifiers":[
        {
            "category":"Organizations",
            "subcategory":"Community Association",
            "type":"Services"
        }
    ],
    "sg:phone":"+1 513 523 4535",
    "sg:postcode":"45056",
    "sg:province":"IN",
    "wof:name":"Oxford Masonic Lodge",
    "wof:placetype":"venue"
},
  "geometry": {"coordinates":[-84.74162,39.510474],"type":"Point"}
}