{
  "type": "Feature",
  "properties": {
    "addr:full": "1133 Hale Rd Wilmington OH 45177",
    "addr:housenumber": "1133",
    "addr:postcode": "45177",
    "addr:street": "Hale Rd",
    "iso:country": "US",
    "sg:address": "1133 Hale Rd",
    "sg:city": "Wilmington",
    "sg:classifiers": [
      {
        "category": "Professional",
        "subcategory": "Engineering",
        "type": "Services"
      }
    ],
    "sg:phone": "+1 937 382 4397",
    "sg:postcode": "45177",
    "sg:province": "OH",
    "sg:tags": [
      "aviation",
      "consulting",
      "maintenance"
    ],
    "wof:name": "Barnhart Aviation Service Inc",
    "wof:placetype": "venue"
  },
  "geometry": {"coordinates":[-83.911584,39.457396],"type":"Point"}
}
