{
  "type": "Feature",
  "properties": {
    "addr:full": "11121 Deerfield Rd Cincinnati OH 45242",
    "addr:housenumber": "11121",
    "addr:postcode": "45242",
    "addr:street": "Deerfield Rd",
    "iso:country": "US",
    "sg:address": "11121 Deerfield Rd",
    "sg:city": "Cincinnati",
    "sg:classifiers": [
      {
        "category": "Manufacturing",
        "subcategory": "Electronics",
        "type": "Manufacturing \u0026 Wholesale Goods"
      }
    ],
    "sg:phone": "+1 513 891 1888",
    "sg:postcode": "45242",
    "sg:province": "OH",
    "sg:tags": [
      "signal",
      "traffic",
      "sign"
    ],
    "wof:name": "IST Intl",
    "wof:placetype": "venue"
  },
  "geometry": {"coordinates":[-84.360828,39.266964],"type":"Point"}
}
