{
  "type": "Feature",
  "properties": {
    "iso:country":"US",
    "sg:address":"3800 Lakeside Ave E",
    "sg:city":"Cleveland",
    "sg:classifiers":[
        {
            "category":"Professional",
            "subcategory":"Business Services",
            "type":"Services"
        },
        {
            "category":"Manufacturing",
            "subcategory":"Printing",
            "type":"Manufacturing & Wholesale Goods"
        }
    ],
    "sg:phone":"+1 216 431 7005",
    "sg:postcode":"44114",
    "sg:province":"OH",
    "sg:tags":[
        "printer"
    ],
    "wof:name":"J L Zubin & Company",
    "wof:placetype":"venue"
},
  "geometry": {"coordinates":[-81.66607399999999,41.51853],"type":"Point"}
}