{
  "type": "Feature",
  "properties": {
    "addr:full": "153 Woodcliff Dr Findlay OH 45840",
    "addr:housenumber": "153",
    "addr:postcode": "45840",
    "addr:street": "Woodcliff Dr",
    "iso:country": "US",
    "sg:address": "153 Woodcliff Dr",
    "sg:city": "Findlay",
    "sg:classifiers": [
      {
        "category": "Real Estate",
        "subcategory": "Developer",
        "type": "Services"
      }
    ],
    "sg:phone": "+1 419 422 8101",
    "sg:postcode": "45840",
    "sg:province": "OH",
    "wof:name": "Headquarters Development",
    "wof:placetype": "venue"
  },
  "geometry": {"coordinates":[-83.652593,41.078501],"type":"Point"}
}
