{
  "type": "Feature",
  "properties": {
    "addr:full":"3951 Rocky River Dr Cleveland OH 44111",
    "addr:housenumber":"3951",
    "addr:postcode":"44111",
    "addr:street":"Rocky River Dr",
    "iso:country":"US",
    "sg:address":"3951 Rocky River Dr",
    "sg:city":"Cleveland",
    "sg:classifiers":[
        {
            "category":"Social Services",
            "subcategory":"Job Training",
            "type":"Services"
        }
    ],
    "sg:phone":"+1 216 671 0476",
    "sg:postcode":"44111",
    "sg:province":"OH",
    "sg:tags":[
        "retardation",
        "disabled",
        "mental",
        "dev"
    ],
    "sg:website":"www.blhs.org",
    "wof:name":"Bethesda Lutheran Group Home",
    "wof:placetype":"venue"
},
  "geometry": {"coordinates":[-81.81771500000001,41.446839],"type":"Point"}
}