{
  "type": "Feature",
  "properties": {
    "iso:country":"US",
    "sg:address":"25 Walnut St",
    "sg:city":"Lexington",
    "sg:classifiers":[
        {
            "category":"Professional",
            "subcategory":"Engineering",
            "type":"Services"
        }
    ],
    "sg:phone":"+1 419 884 2001",
    "sg:postcode":"44904",
    "sg:province":"OH",
    "sg:tags":[
        "engineer"
    ],
    "wof:name":"Poggemeyer Design Group",
    "wof:placetype":"venue"
},
  "geometry": {"coordinates":[-82.58242,40.680462],"type":"Point"}
}