{
  "type": "Feature",
  "properties": {
    "addr:full":"15 Main St Tiffin OH 44883",
    "addr:housenumber":"15",
    "addr:postcode":"44883",
    "addr:street":"Main St",
    "iso:country":"US",
    "sg:address":"15 Main St",
    "sg:city":"Tiffin",
    "sg:classifiers":[
        {
            "category":"Shopping",
            "subcategory":"Computers & Home Electronics",
            "type":"Retail Goods"
        }
    ],
    "sg:phone":"+1 419 448 4999",
    "sg:postcode":"44883",
    "sg:province":"OH",
    "wof:name":"BBC Computers",
    "wof:placetype":"venue"
},
  "geometry": {"coordinates":[-83.172932,41.111661],"type":"Point"}
}