{
  "type": "Feature",
  "properties": {
    "addr:full":"640 Foster Ave Hamilton OH 45015",
    "addr:housenumber":"640",
    "addr:postcode":"45015",
    "addr:street":"Foster Ave",
    "iso:country":"US",
    "sg:address":"640 Foster Ave",
    "sg:city":"Hamilton",
    "sg:classifiers":[
        {
            "category":"Education",
            "subcategory":"Special Training",
            "type":"Public Place"
        }
    ],
    "sg:phone":"+1 513 887 0600",
    "sg:postcode":"45015",
    "sg:province":"OH",
    "sg:tags":[
        "self",
        "motivational",
        "improvement"
    ],
    "wof:name":"ASW Consultants",
    "wof:placetype":"venue"
},
  "geometry": {"coordinates":[-84.557267,39.357222],"type":"Point"}
}