{
  "type": "Feature",
  "properties": {
    "addr:full":"2525 2nd St Cuyahoga Falls OH 44221",
    "addr:housenumber":"2525",
    "addr:postcode":"44221",
    "addr:street":"2Nd St",
    "iso:country":"US",
    "sg:address":"2525 2nd St",
    "sg:city":"Cuyahoga Falls",
    "sg:classifiers":[
        {
            "category":"Real Estate",
            "subcategory":"Architect",
            "type":"Services"
        }
    ],
    "sg:phone":"+1 330 928 6688",
    "sg:postcode":"44221",
    "sg:province":"OH",
    "sg:tags":[
        "architectural"
    ],
    "wof:name":"Hecky Group The",
    "wof:placetype":"venue"
},
  "geometry": {"coordinates":[-81.47732000000001,41.143888],"type":"Point"}
}