{
  "type": "Feature",
  "properties": {
    "addr:full":"18675 Parkland Dr Cleveland OH 44122",
    "addr:housenumber":"18675",
    "addr:postcode":"44122",
    "addr:street":"Parkland Dr",
    "iso:country":"US",
    "sg:address":"18675 Parkland Dr",
    "sg:city":"Cleveland",
    "sg:classifiers":[
        {
            "category":"Wholesale",
            "subcategory":"Metals & Minerals",
            "type":"Manufacturing & Wholesale Goods"
        }
    ],
    "sg:phone":"+1 216 491 1166",
    "sg:postcode":"44122",
    "sg:province":"OH",
    "wof:name":"Ak Steel Corp",
    "wof:placetype":"venue"
},
  "geometry": {"coordinates":[-81.54779600000001,41.470342],"type":"Point"}
}