{
  "type": "Feature",
  "properties": {
    "addr:full": "1755 Harding Hwy W Marion OH 43302",
    "addr:housenumber": "1755",
    "addr:postcode": "43302",
    "addr:street": "Harding Hwy W",
    "iso:country": "US",
    "sg:address": "1755 Harding Hwy W",
    "sg:city": "Marion",
    "sg:classifiers": [
      {
        "category": "Wholesale",
        "subcategory": "Farm Supplies",
        "type": "Manufacturing \u0026 Wholesale Goods"
      }
    ],
    "sg:phone": "+1 740 387 3404",
    "sg:postcode": "43302",
    "sg:province": "OH",
    "sg:tags": [
      "feed"
    ],
    "wof:name": "Cottonwood Drive Thru Feed/Spl",
    "wof:placetype": "venue"
  },
  "geometry": {"coordinates":[-83.177784,40.608539],"type":"Point"}
}
