{
  "type": "Feature",
  "properties": {
    "iso:country":"US",
    "sg:address":"1755 Harding Hwy W",
    "sg:city":"Marion",
    "sg:classifiers":[
        {
            "category":"Wholesale",
            "subcategory":"Farm Supplies",
            "type":"Manufacturing & Wholesale Goods"
        }
    ],
    "sg:phone":"+1 740 387 3404",
    "sg:postcode":"43302",
    "sg:province":"OH",
    "sg:tags":[
        "feed"
    ],
    "wof:name":"Cottonwood Drive Thru Feed/Spl",
    "wof:placetype":"venue"
},
  "geometry": {"coordinates":[-83.177784,40.608539],"type":"Point"}
}