{
  "type": "Feature",
  "properties": {
    "iso:country":"US",
    "sg:address":"216 Woodland St SW",
    "sg:city":"Hartville",
    "sg:classifiers":[
        {
            "category":"Building & Trades",
            "subcategory":"Construction",
            "type":"Services"
        }
    ],
    "sg:phone":"+1 330 877 7098",
    "sg:postcode":"44632",
    "sg:province":"OH",
    "sg:tags":[
        "hanging",
        "contractor"
    ],
    "wof:name":"Stormer Painting",
    "wof:placetype":"venue"
},
  "geometry": {"coordinates":[-81.33933500000001,40.957939],"type":"Point"}
}