{
  "type": "Feature",
  "properties": {
    "iso:country":"US",
    "sg:address":"9370 Jug St",
    "sg:city":"Pataskala",
    "sg:classifiers":[
        {
            "category":"Building & Trades",
            "subcategory":"Construction",
            "type":"Services"
        }
    ],
    "sg:phone":"+1 740 924 5231",
    "sg:postcode":"43062",
    "sg:province":"OH",
    "sg:tags":[
        "new",
        "remodeling",
        "family",
        "general"
    ],
    "wof:name":"Mc Clanahan Builders",
    "wof:placetype":"venue"
},
  "geometry": {"coordinates":[-82.66919,40.096631],"type":"Point"}
}