{
  "type": "Feature",
  "properties": {
    "addr:full": "15943 Nauvoo Rd Middlefield OH 44062",
    "addr:housenumber": "15943",
    "addr:postcode": "44062",
    "addr:street": "Nauvoo Rd",
    "iso:country": "US",
    "sg:address": "15943 Nauvoo Rd",
    "sg:city": "Middlefield",
    "sg:classifiers": [
      {
        "category": "Building \u0026 Trades",
        "subcategory": "Construction",
        "type": "Services"
      }
    ],
    "sg:phone": "+1 440 632 0276",
    "sg:postcode": "44062",
    "sg:province": "OH",
    "sg:tags": [
      "house"
    ],
    "wof:name": "Bilt Right Construction",
    "wof:placetype": "venue"
  },
  "geometry": {"coordinates":[-81.055152,41.479144],"type":"Point"}
}
