{
  "type": "Feature",
  "properties": {
    "addr:full": "31243 Primmer Rd Logan OH 43138",
    "addr:postcode": "31243;43138",
    "addr:street": "Primmer Rd",
    "iso:country": "US",
    "sg:address": "31243 Primmer Rd",
    "sg:city": "Logan",
    "sg:classifiers": [
      {
        "category": "Farming",
        "subcategory": "Farm",
        "type": "Manufacturing \u0026 Wholesale Goods"
      }
    ],
    "sg:phone": "+1 740 385 3702",
    "sg:postcode": "43138",
    "sg:province": "OH",
    "sg:tags": [
      "crop",
      "general"
    ],
    "wof:name": "Merl Primmer",
    "wof:placetype": "venue"
  },
  "geometry": {"coordinates":[-82.442236,39.5404],"type":"Point"}
}
