{
  "type": "Feature",
  "properties": {
    "iso:country":"US",
    "sg:address":"31243 Primmer Rd",
    "sg:city":"Logan",
    "sg:classifiers":[
        {
            "category":"Farming",
            "subcategory":"Farm",
            "type":"Manufacturing & Wholesale Goods"
        }
    ],
    "sg:phone":"+1 740 385 3702",
    "sg:postcode":"43138",
    "sg:province":"OH",
    "sg:tags":[
        "crop",
        "general"
    ],
    "wof:name":"Merl Primmer",
    "wof:placetype":"venue"
},
  "geometry": {"coordinates":[-82.44223599999999,39.5404],"type":"Point"}
}