{
  "type": "Feature",
  "properties": {
    "addr:full": "38005 Fairmount Blvd Chagrin Falls OH 44022",
    "addr:housenumber": "38005",
    "addr:postcode": "44022",
    "addr:street": "Fairmount Blvd",
    "iso:country": "US",
    "sg:address": "38005 Fairmount Blvd",
    "sg:city": "Chagrin Falls",
    "sg:classifiers": [
      {
        "category": "Building \u0026 Trades",
        "subcategory": "Construction",
        "type": "Services"
      }
    ],
    "sg:phone": "+1 440 247 9964",
    "sg:postcode": "44022",
    "sg:province": "OH",
    "sg:tags": [
      "house"
    ],
    "wof:name": "Berns Custom Homes Inc",
    "wof:placetype": "venue"
  },
  "geometry": {"coordinates":[-81.401595,41.489448],"type":"Point"}
}
