{
  "type": "Feature",
  "properties": {
    "iso:country":"US",
    "sg:address":"3553 Darrow Rd",
    "sg:city":"Stow",
    "sg:classifiers":[
        {
            "category":"Health Services",
            "subcategory":"Doctor",
            "type":"Services"
        }
    ],
    "sg:phone":"+1 330 688 9918",
    "sg:postcode":"44224",
    "sg:province":"OH",
    "sg:tags":[
        "physician",
        "medical",
        "surgeon"
    ],
    "wof:name":"Ann L Pavlovich Do Inc",
    "wof:placetype":"venue"
},
  "geometry": {"coordinates":[-81.44031,41.15954],"type":"Point"}
}