{
  "type": "Feature",
  "properties": {
    "iso:country":"US",
    "sg:address":"2030 Tod Ave SW",
    "sg:city":"Warren",
    "sg:classifiers":[
        {
            "category":"Freight",
            "type":"Transportation"
        }
    ],
    "sg:phone":"+1 330 395 2287",
    "sg:postcode":"44485",
    "sg:province":"OH",
    "wof:name":"Trumbull Community Action Prgm",
    "wof:placetype":"venue"
},
  "geometry": {"coordinates":[-80.83645199999999,41.216488],"type":"Point"}
}