{
  "type": "Feature",
  "properties": {
    "addr:full":"1799 Akron Peninsula Rd Akron OH 44313",
    "addr:housenumber":"1799",
    "addr:postcode":"44313",
    "addr:street":"Akron Peninsula Rd",
    "iso:country":"US",
    "sg:address":"1799 Akron Peninsula Rd",
    "sg:city":"Akron",
    "sg:classifiers":[
        {
            "category":"Professional",
            "subcategory":"Lawyer & Legal Services",
            "type":"Services"
        }
    ],
    "sg:phone":"+1 330 928 0307",
    "sg:postcode":"44313",
    "sg:province":"OH",
    "sg:tags":[
        "attorney"
    ],
    "wof:name":"Allan Johnson",
    "wof:placetype":"venue"
},
  "geometry": {"coordinates":[-81.55459999999999,41.143395],"type":"Point"}
}