{
  "type": "Feature",
  "properties": {
    "addr:full":"13846 Spencer Rd Yorkshire OH 45388",
    "addr:housenumber":"13846",
    "addr:postcode":"45388",
    "addr:street":"Spencer Rd",
    "iso:country":"US",
    "sg:address":"13846 Spencer Rd",
    "sg:city":"Yorkshire",
    "sg:phone":"+1 419 582 4174",
    "sg:postcode":"45388",
    "sg:province":"OH",
    "sg:tags":[
        "farm",
        "real",
        "property",
        "wheat",
        "lessor"
    ],
    "wof:name":"William Grieshop",
    "wof:placetype":"venue"
},
  "geometry": {"coordinates":[-84.47266,40.323308],"type":"Point"}
}