{
  "type": "Feature",
  "properties": {
    "addr:full":"45 Kurtz Ave Dayton OH 45405",
    "addr:housenumber":"45",
    "addr:postcode":"45405",
    "addr:street":"Kurtz Ave",
    "iso:country":"US",
    "sg:address":"45 Kurtz Ave",
    "sg:city":"Dayton",
    "sg:classifiers":[
        {
            "category":"Organizations",
            "subcategory":"Religious Organization",
            "type":"Services"
        }
    ],
    "sg:phone":"+1 937 275 5750",
    "sg:postcode":"45405",
    "sg:province":"OH",
    "sg:tags":[
        "church"
    ],
    "sg:website":"www.nrlchurch.org",
    "wof:name":"North Riverdale Lutheran Chrch",
    "wof:placetype":"venue"
},
  "geometry": {"coordinates":[-84.21668200000001,39.793444],"type":"Point"}
}