{
  "type": "Feature",
  "properties": {
    "addr:full": "414 Wayne St Sandusky OH 44870",
    "addr:housenumber": "414",
    "addr:postcode": "44870",
    "addr:street": "Wayne St",
    "iso:country": "US",
    "sg:address": "414 Wayne St",
    "sg:city": "Sandusky",
    "sg:classifiers": [
      {
        "category": "Professional",
        "subcategory": "Lawyer \u0026 Legal Services",
        "type": "Services"
      }
    ],
    "sg:phone": "+1 419 627 0414",
    "sg:postcode": "44870",
    "sg:province": "OH",
    "sg:tags": [
      "attorney"
    ],
    "wof:name": "Buckingham Lucal Mc Gookey",
    "wof:placetype": "venue"
  },
  "geometry": {"coordinates":[-82.708476,41.454107],"type":"Point"}
}
