{
  "type": "Feature",
  "properties": {
    "addr:full":"110 W High St Ashley OH 43003",
    "addr:housenumber":"110",
    "addr:postcode":"43003",
    "addr:street":"W High St",
    "iso:country":"US",
    "sg:address":"110 W High St",
    "sg:city":"Ashley",
    "sg:classifiers":[
        {
            "category":"Wholesale",
            "subcategory":"Medical Equipment & Supplies",
            "type":"Manufacturing & Wholesale Goods"
        }
    ],
    "sg:phone":"+1 740 747 2538",
    "sg:postcode":"43003",
    "sg:province":"OH",
    "sg:tags":[
        "physician",
        "surgeon"
    ],
    "wof:name":"Home Oxygen Co",
    "wof:placetype":"venue"
},
  "geometry": {"coordinates":[-82.963823,40.409555],"type":"Point"}
}