{
  "type": "Feature",
  "properties": {
    "addr:full": "2583 Grange Hall Rd Dayton OH 45431",
    "addr:housenumber": "2583",
    "addr:postcode": "45431",
    "addr:street": "Grange Hall Rd",
    "iso:country": "US",
    "sg:address": "2583 Grange Hall Rd",
    "sg:city": "Dayton",
    "sg:classifiers": [
      {
        "category": "Personal",
        "subcategory": "Beauty Salon",
        "type": "Services"
      }
    ],
    "sg:phone": "+1 937 426 8444",
    "sg:postcode": "45431",
    "sg:province": "OH",
    "wof:name": "Grange Hair Fashions",
    "wof:placetype": "venue"
  },
  "geometry": {"coordinates":[-84.075738,39.767682],"type":"Point"}
}
