{
  "type": "Feature",
  "properties": {
    "iso:country":"US",
    "sg:address":"1557 State Rte 303",
    "sg:city":"Streetsboro",
    "sg:classifiers":[
        {
            "category":"Professional",
            "subcategory":"Employment Agencies",
            "type":"Services"
        }
    ],
    "sg:phone":"+1 330 626 9800",
    "sg:postcode":"44241",
    "sg:province":"OH",
    "sg:tags":[
        "help",
        "contractor"
    ],
    "wof:name":"Callos Personnel Svc",
    "wof:placetype":"venue"
},
  "geometry": {"coordinates":[-81.337806,41.239183],"type":"Point"}
}