{
  "type": "Feature",
  "properties": {
    "addr:full":"1401 E State St Fremont OH 43420",
    "addr:housenumber":"1401",
    "addr:postcode":"43420",
    "addr:street":"E State St",
    "iso:country":"US",
    "sg:address":"1401 E State St",
    "sg:city":"Fremont",
    "sg:classifiers":[
        {
            "category":"Ice Cream",
            "type":"Food & Drink"
        }
    ],
    "sg:menulink":"http://www.allmenus.com/oh/ballville/175666-dairy-queen/menu/",
    "sg:phone":"+1 419 332 0335",
    "sg:postcode":"43420",
    "sg:province":"OH",
    "sg:tags":[
        "burger",
        "american"
    ],
    "wof:name":"Dairy Queen",
    "wof:placetype":"venue"
},
  "geometry": {"coordinates":[-83.091401,41.341473],"type":"Point"}
}