{
  "type": "Feature",
  "properties": {
    "iso:country":"US",
    "sg:address":"686 S Sandusky St",
    "sg:city":"Tiffin",
    "sg:classifiers":[
        {
            "category":"Real Estate",
            "subcategory":"Real Estate Operator",
            "type":"Services"
        }
    ],
    "sg:phone":"+1 419 447 9033",
    "sg:postcode":"44883",
    "sg:province":"OH",
    "sg:tags":[
        "mobile",
        "home",
        "site",
        "community"
    ],
    "wof:name":"Highland Park Estates MBL Pk",
    "wof:placetype":"venue"
},
  "geometry": {"coordinates":[-83.195409,41.10359],"type":"Point"}
}