{
  "type": "Feature",
  "properties": {
    "addr:full": "10255 Northfield Rd Northfield OH 44067",
    "addr:housenumber": "10255",
    "addr:postcode": "44067",
    "addr:street": "Northfield Rd",
    "iso:country": "US",
    "sg:address": "10255 Northfield Rd",
    "sg:city": "Northfield",
    "sg:classifiers": [
      {
        "category": "Coffee \u0026 Tea",
        "type": "Food \u0026 Drink"
      }
    ],
    "sg:menulink": "http://www.allmenus.com/oh/northfield/258365-peggys-lunch-box/menu/",
    "sg:phone": "+1 330 467 6025",
    "sg:postcode": "44067",
    "sg:province": "OH",
    "sg:tags": [
      "burger",
      "american",
      "sandwich",
      "diner",
      "dessert"
    ],
    "wof:name": "Peggy's Lunch Box",
    "wof:placetype": "venue"
  },
  "geometry": {"coordinates":[-81.530251,41.337795],"type":"Point"}
}
