{
  "type": "Feature",
  "properties": {
    "iso:country":"US",
    "sg:address":"10255 Northfield Rd",
    "sg:city":"Northfield",
    "sg:classifiers":[
        {
            "category":"Coffee & Tea",
            "type":"Food & Drink"
        }
    ],
    "sg:menulink":"http://www.allmenus.com/oh/northfield/258365-peggys-lunch-box/menu/",
    "sg:phone":"+1 330 467 6025",
    "sg:postcode":"44067",
    "sg:province":"OH",
    "sg:tags":[
        "burger",
        "american",
        "sandwich",
        "diner",
        "dessert"
    ],
    "wof:name":"Peggy's Lunch Box",
    "wof:placetype":"venue"
},
  "geometry": {"coordinates":[-81.53025100000001,41.337795],"type":"Point"}
}