{
  "type": "Feature",
  "properties": {
    "iso:country":"US",
    "sg:address":"1449 Catalpa Dr",
    "sg:city":"Dayton",
    "sg:classifiers":[
        {
            "category":"Shopping",
            "subcategory":"Beauty & Cosmetics",
            "type":"Retail Goods"
        }
    ],
    "sg:phone":"+1 937 279 9222",
    "sg:postcode":"45406",
    "sg:province":"OH",
    "sg:tags":[
        "merchandise"
    ],
    "wof:name":"Mary Kay Cosmetics",
    "wof:placetype":"venue"
},
  "geometry": {"coordinates":[-84.224771,39.775045],"type":"Point"}
}