{
  "type": "Feature",
  "properties": {
    "iso:country":"US",
    "sg:address":"60 Public Sq",
    "sg:city":"Medina",
    "sg:classifiers":[
        {
            "category":"Government",
            "subcategory":"Office",
            "type":"Public Place"
        }
    ],
    "sg:phone":"+1 330 723 9536",
    "sg:postcode":"44256",
    "sg:province":"OH",
    "wof:name":"Medina County Prosecutor-Crmnl",
    "wof:placetype":"venue"
},
  "geometry": {"coordinates":[-81.86339099999999,41.137955],"type":"Point"}
}