{
  "type": "Feature",
  "properties": {
    "addr:full": "60 Public Sq Medina OH 44256",
    "addr:housenumber": "60",
    "addr:postcode": "44256",
    "addr:street": "Public Sq",
    "iso:country": "US",
    "sg:address": "60 Public Sq",
    "sg:city": "Medina",
    "sg:classifiers": [
      {
        "category": "Government",
        "subcategory": "Office",
        "type": "Public Place"
      }
    ],
    "sg:phone": "+1 330 723 9536",
    "sg:postcode": "44256",
    "sg:province": "OH",
    "wof:name": "Medina County Prosecutor-Crmnl",
    "wof:placetype": "venue"
  },
  "geometry": {"coordinates":[-81.863391,41.137955],"type":"Point"}
}
