{
  "type": "Feature",
  "properties": {
    "addr:full": "715 Mellwood Dr New Lexington OH 43764",
    "addr:housenumber": "715",
    "addr:postcode": "43764",
    "addr:street": "Mellwood Dr",
    "iso:country": "US",
    "sg:address": "715 Mellwood Dr",
    "sg:city": "New Lexington",
    "sg:classifiers": [
      {
        "category": "Building \u0026 Trades",
        "subcategory": "Construction",
        "type": "Services"
      }
    ],
    "sg:phone": "+1 740 342 1312",
    "sg:postcode": "43764",
    "sg:province": "OH",
    "sg:tags": [
      "house"
    ],
    "wof:name": "Conrad Builders",
    "wof:placetype": "venue"
  },
  "geometry": {"coordinates":[-82.195431,39.714109],"type":"Point"}
}
