{
  "type": "Feature",
  "properties": {
    "iso:country":"US",
    "sg:address":"715 Mellwood Dr",
    "sg:city":"New Lexington",
    "sg:classifiers":[
        {
            "category":"Building & Trades",
            "subcategory":"Construction",
            "type":"Services"
        }
    ],
    "sg:phone":"+1 740 342 1312",
    "sg:postcode":"43764",
    "sg:province":"OH",
    "sg:tags":[
        "house"
    ],
    "wof:name":"Conrad Builders",
    "wof:placetype":"venue"
},
  "geometry": {"coordinates":[-82.195431,39.714109],"type":"Point"}
}