{
  "type": "Feature",
  "properties": {
    "addr:full":"1337 Commerce Dr Cuyahoga Falls OH 44224",
    "addr:housenumber":"1337",
    "addr:postcode":"44224",
    "addr:street":"Commerce Dr",
    "iso:country":"US",
    "sg:address":"1337 Commerce Dr",
    "sg:city":"Cuyahoga Falls",
    "sg:classifiers":[
        {
            "category":"Building & Trades",
            "subcategory":"Construction",
            "type":"Services"
        }
    ],
    "sg:phone":"+1 330 688 5400",
    "sg:postcode":"44224",
    "sg:province":"OH",
    "sg:tags":[
        "maker",
        "cabinet"
    ],
    "wof:name":"Custom Creations",
    "wof:placetype":"venue"
},
  "geometry": {"coordinates":[-81.45501299999999,41.190851],"type":"Point"}
}