{
  "type": "Feature",
  "properties": {
    "addr:full":"75 N Main St Cedarville OH 45314",
    "addr:housenumber":"75",
    "addr:postcode":"45314",
    "addr:street":"N Main St",
    "iso:country":"US",
    "sg:address":"75 N Main St",
    "sg:city":"Cedarville",
    "sg:classifiers":[
        {
            "category":"Shopping",
            "subcategory":"Florist",
            "type":"Retail Goods"
        }
    ],
    "sg:phone":"+1 937 766 5768",
    "sg:postcode":"45314",
    "sg:province":"OH",
    "wof:name":"Ladybug's Blossoms & Bows",
    "wof:placetype":"venue"
},
  "geometry": {"coordinates":[-83.80720100000001,39.74164],"type":"Point"}
}