{
  "type": "Feature",
  "properties": {
    "addr:full": "800 S Main St Bellefontaine OH 43311",
    "addr:housenumber": "800",
    "addr:postcode": "43311",
    "addr:street": "S Main St",
    "iso:country": "US",
    "sg:address": "800 S Main St",
    "sg:city": "Bellefontaine",
    "sg:classifiers": [
      {
        "category": "Restaurant",
        "type": "Food \u0026 Drink"
      }
    ],
    "sg:menulink": "http://www.allmenus.com/oh/lake/134827-subway/menu/",
    "sg:phone": "+1 937 592 3000",
    "sg:postcode": "43311",
    "sg:province": "OH",
    "sg:tags": [
      "american",
      "sandwich"
    ],
    "wof:name": "Subway",
    "wof:placetype": "venue"
  },
  "geometry": {"coordinates":[-83.760719,40.350856],"type":"Point"}
}
