{
  "type": "Feature",
  "properties": {
    "iso:country":"US",
    "sg:address":"1889 Graham Rd",
    "sg:city":"Stow",
    "sg:classifiers":[
        {
            "category":"Real Estate",
            "subcategory":"Real Estate Agent",
            "type":"Services"
        }
    ],
    "sg:phone":"+1 330 686 9454",
    "sg:postcode":"44224",
    "sg:province":"OH",
    "sg:tags":[
        "inspection"
    ],
    "sg:website":"www.pillartopost.com",
    "wof:name":"Pillar To Post",
    "wof:placetype":"venue"
},
  "geometry": {"coordinates":[-81.44611399999999,41.166793],"type":"Point"}
}