{
  "type": "Feature",
  "properties": {
    "addr:full": "204 W Mcmillan St Cincinnati OH 45219",
    "addr:housenumber": "204",
    "addr:postcode": "45219",
    "addr:street": "W Mcmillan St",
    "iso:country": "US",
    "sg:address": "204 W Mcmillan St",
    "sg:city": "Cincinnati",
    "sg:classifiers": [
      {
        "category": "Restaurant",
        "type": "Food \u0026 Drink"
      }
    ],
    "sg:phone": "+1 513 559 9229",
    "sg:postcode": "45219",
    "sg:province": "OH",
    "sg:tags": [
      "asian",
      "chinese",
      "pan"
    ],
    "wof:name": "Neo Origin Inc",
    "wof:placetype": "venue"
  },
  "geometry": {"coordinates":[-84.519468,39.127864],"type":"Point"}
}
