{
  "type": "Feature",
  "properties": {
    "iso:country":"US",
    "sg:address":"2401 Cincinnati Dayton Rd",
    "sg:city":"Middletown",
    "sg:classifiers":[
        {
            "category":"Autos & Motor Vehicles",
            "subcategory":"Fuel & Gas Station",
            "type":"Retail Goods"
        }
    ],
    "sg:phone":"+1 513 422 6591",
    "sg:postcode":"45044",
    "sg:province":"OH",
    "sg:tags":[
        "oil"
    ],
    "wof:name":"Sunrise Sunoco",
    "wof:placetype":"venue"
},
  "geometry": {"coordinates":[-84.33891199999999,39.487065],"type":"Point"}
}