{
  "type": "Feature",
  "properties": {
    "addr:full": "2401 Cincinnati Dayton Rd Middletown OH 45044",
    "addr:housenumber": "2401",
    "addr:postcode": "45044",
    "addr:street": "Cincinnati Dayton Rd",
    "iso:country": "US",
    "sg:address": "2401 Cincinnati Dayton Rd",
    "sg:city": "Middletown",
    "sg:classifiers": [
      {
        "category": "Autos \u0026 Motor Vehicles",
        "subcategory": "Fuel \u0026 Gas Station",
        "type": "Retail Goods"
      }
    ],
    "sg:phone": "+1 513 422 6591",
    "sg:postcode": "45044",
    "sg:province": "OH",
    "sg:tags": [
      "oil"
    ],
    "wof:name": "Sunrise Sunoco",
    "wof:placetype": "venue"
  },
  "geometry": {"coordinates":[-84.338912,39.487065],"type":"Point"}
}
