{
  "type": "Feature",
  "properties": {
    "addr:full": "6152 W Market St Leavittsburg OH 44430",
    "addr:housenumber": "6152",
    "addr:postcode": "44430",
    "addr:street": "W Market St",
    "iso:country": "US",
    "sg:address": "6152 W Market St",
    "sg:city": "Leavittsburg",
    "sg:classifiers": [
      {
        "category": "Restaurant",
        "type": "Food \u0026 Drink"
      }
    ],
    "sg:phone": "+1 330 898 7797",
    "sg:postcode": "44430",
    "sg:province": "OH",
    "sg:tags": [
      "eating"
    ],
    "wof:name": "Kountry Kupboard Restaurant",
    "wof:placetype": "venue"
  },
  "geometry": {"coordinates":[-80.881141,41.238875],"type":"Point"}
}
