{
  "type": "Feature",
  "properties": {
    "addr:full": "530 S Breiel Blvd Middletown OH 45044",
    "addr:housenumber": "530",
    "addr:postcode": "45044",
    "addr:street": "S Breiel Blvd",
    "iso:country": "US",
    "sg:address": "530 S Breiel Blvd",
    "sg:city": "Middletown",
    "sg:classifiers": [
      {
        "category": "Restaurant",
        "type": "Food \u0026 Drink"
      }
    ],
    "sg:phone": "+1 513 425 7330",
    "sg:postcode": "45044",
    "sg:province": "OH",
    "sg:tags": [
      "out"
    ],
    "wof:name": "Dauggie's Drive Thru",
    "wof:placetype": "venue"
  },
  "geometry": {"coordinates":[-84.355191,39.504758],"type":"Point"}
}
