{
  "type": "Feature",
  "properties": {
    "addr:full":"9434 Rd X Leipsic OH 45856",
    "addr:housenumber":"9434",
    "addr:postcode":"45856",
    "addr:street":"Rd X",
    "iso:country":"US",
    "sg:address":"9434 Rd X",
    "sg:city":"Leipsic",
    "sg:classifiers":[
        {
            "category":"Building & Trades",
            "subcategory":"Construction",
            "type":"Services"
        }
    ],
    "sg:phone":"+1 419 943 1077",
    "sg:postcode":"45856",
    "sg:province":"OH",
    "sg:tags":[
        "concrete",
        "contractor"
    ],
    "wof:name":"Dales Concrete & Decorative St",
    "wof:placetype":"venue"
},
  "geometry": {"coordinates":[-84.04746900000001,41.128149],"type":"Point"}
}