{
  "type": "Feature",
  "properties": {
    "addr:full":"590 Terrace Ave Cincinnati OH 45220",
    "addr:housenumber":"590",
    "addr:postcode":"45220",
    "addr:street":"Terrace Ave",
    "iso:country":"US",
    "sg:address":"590 Terrace Ave",
    "sg:city":"Cincinnati",
    "sg:classifiers":[
        {
            "category":"Professional",
            "type":"Services"
        }
    ],
    "sg:phone":"+1 513 569 0290",
    "sg:postcode":"45220",
    "sg:province":"OH",
    "wof:name":"George J Swaidan",
    "wof:placetype":"venue"
},
  "geometry": {"coordinates":[-84.52725599999999,39.142391],"type":"Point"}
}