{
  "type": "Feature",
  "properties": {
    "addr:full": "663 Park Meadow Rd Westerville OH 43081",
    "addr:housenumber": "663",
    "addr:postcode": "43081",
    "addr:street": "Park Meadow Rd",
    "iso:country": "US",
    "sg:address": "663 Park Meadow Rd",
    "sg:city": "Westerville",
    "sg:classifiers": [
      {
        "category": "Organizations",
        "subcategory": "Non-profit Organization",
        "type": "Services"
      }
    ],
    "sg:phone": "+1 614 895 2371",
    "sg:postcode": "43081",
    "sg:province": "OH",
    "wof:name": "Columbus Dental Society",
    "wof:placetype": "venue"
  },
  "geometry": {"coordinates":[-82.936479,40.10887],"type":"Point"}
}
