{
  "type": "Feature",
  "properties": {
    "iso:country":"US",
    "sg:address":"663 Park Meadow Rd",
    "sg:city":"Westerville",
    "sg:classifiers":[
        {
            "category":"Organizations",
            "subcategory":"Non-profit Organization",
            "type":"Services"
        }
    ],
    "sg:phone":"+1 614 895 2371",
    "sg:postcode":"43081",
    "sg:province":"OH",
    "wof:name":"Columbus Dental Society",
    "wof:placetype":"venue"
},
  "geometry": {"coordinates":[-82.93647900000001,40.10887],"type":"Point"}
}