{
  "type": "Feature",
  "properties": {
    "addr:full": "10651 Avenue Rd Perrysburg OH 43551",
    "addr:housenumber": "10651",
    "addr:postcode": "43551",
    "addr:street": "Avenue Rd",
    "iso:country": "US",
    "sg:address": "10651 Avenue Rd",
    "sg:city": "Perrysburg",
    "sg:classifiers": [
      {
        "category": "Retail",
        "subcategory": "Laundry \u0026 Dry Cleaning",
        "type": "Services"
      }
    ],
    "sg:phone": "+1 419 476 4985",
    "sg:postcode": "43551",
    "sg:province": "OH",
    "sg:tags": [
      "cleaners",
      "rug",
      "carpet"
    ],
    "wof:name": "Scrubby Carpet \u0026 Upholstery",
    "wof:placetype": "venue"
  },
  "geometry": {"coordinates":[-83.600228,41.564967],"type":"Point"}
}
