{
  "type": "Feature",
  "properties": {
    "iso:country":"US",
    "sg:address":"10651 Avenue Rd",
    "sg:city":"Perrysburg",
    "sg:classifiers":[
        {
            "category":"Retail",
            "subcategory":"Laundry & Dry Cleaning",
            "type":"Services"
        }
    ],
    "sg:phone":"+1 419 476 4985",
    "sg:postcode":"43551",
    "sg:province":"OH",
    "sg:tags":[
        "cleaners",
        "rug",
        "carpet"
    ],
    "wof:name":"Scrubby Carpet & Upholstery",
    "wof:placetype":"venue"
},
  "geometry": {"coordinates":[-83.600228,41.564967],"type":"Point"}
}