{
  "type": "Feature",
  "properties": {
    "iso:country":"US",
    "sg:address":"220 S Wayne St",
    "sg:city":"Fort Recovery",
    "sg:classifiers":[
        {
            "category":"Banks & Credit Unions",
            "subcategory":"Bank",
            "type":"Services"
        }
    ],
    "sg:phone":"+1 419 375 4125",
    "sg:postcode":"45846",
    "sg:province":"OH",
    "sg:website":"www.comfirst.com",
    "wof:name":"Community First Bank & Trust",
    "wof:placetype":"venue"
},
  "geometry": {"coordinates":[-84.779811,40.411776],"type":"Point"}
}