{
  "type": "Feature",
  "properties": {
    "addr:full": "475 Northland Blvd Cincinnati OH 45240",
    "addr:housenumber": "475",
    "addr:postcode": "45240",
    "addr:street": "Northland Blvd",
    "iso:country": "US",
    "sg:address": "475 Northland Blvd",
    "sg:city": "Cincinnati",
    "sg:classifiers": [
      {
        "category": "Manufacturing",
        "subcategory": "Metals",
        "type": "Manufacturing \u0026 Wholesale Goods"
      }
    ],
    "sg:phone": "+1 513 825 1171",
    "sg:postcode": "45240",
    "sg:province": "OH",
    "wof:name": "American Mtal Clg of Cncinnati",
    "wof:placetype": "venue"
  },
  "geometry": {"coordinates":[-84.500443,39.280686],"type":"Point"}
}
