{
  "type": "Feature",
  "properties": {
    "iso:country":"US",
    "sg:address":"475 Northland Blvd",
    "sg:city":"Cincinnati",
    "sg:classifiers":[
        {
            "category":"Manufacturing",
            "subcategory":"Metals",
            "type":"Manufacturing & Wholesale Goods"
        }
    ],
    "sg:phone":"+1 513 825 1171",
    "sg:postcode":"45240",
    "sg:province":"OH",
    "wof:name":"American Mtal Clg of Cncinnati",
    "wof:placetype":"venue"
},
  "geometry": {"coordinates":[-84.500443,39.280686],"type":"Point"}
}