{
  "type": "Feature",
  "properties": {
    "addr:full":"14532 Pearl Rd Cleveland OH 44136",
    "addr:housenumber":"14532",
    "addr:postcode":"44136",
    "addr:street":"Pearl Rd",
    "iso:country":"US",
    "sg:address":"14532 Pearl Rd",
    "sg:city":"Cleveland",
    "sg:classifiers":[
        {
            "category":"Marine",
            "type":"Transportation"
        }
    ],
    "sg:phone":"+1 440 572 5781",
    "sg:postcode":"44136",
    "sg:province":"OH",
    "sg:tags":[
        "surveyor"
    ],
    "wof:name":"Marine Survey Professionals",
    "wof:placetype":"venue"
},
  "geometry": {"coordinates":[-81.835309,41.309553],"type":"Point"}
}