{
  "type": "Feature",
  "properties": {
    "addr:full": "11300 Butternut Rd Chardon OH 44024",
    "addr:housenumber": "11300",
    "addr:postcode": "44024",
    "addr:street": "Butternut Rd",
    "iso:country": "US",
    "sg:address": "11300 Butternut Rd",
    "sg:city": "Chardon",
    "sg:classifiers": [
      {
        "category": "Building \u0026 Trades",
        "subcategory": "Landscaping Services",
        "type": "Services"
      }
    ],
    "sg:phone": "+1 440 564 1035",
    "sg:postcode": "44024",
    "sg:province": "OH",
    "sg:tags": [
      "landscape"
    ],
    "wof:name": "United Diversified Services",
    "wof:placetype": "venue"
  },
  "geometry": {"coordinates":[-81.238076,41.499871],"type":"Point"}
}
