{
  "type": "Feature",
  "properties": {
    "iso:country":"US",
    "sg:address":"11300 Butternut Rd",
    "sg:city":"Chardon",
    "sg:classifiers":[
        {
            "category":"Building & Trades",
            "subcategory":"Landscaping Services",
            "type":"Services"
        }
    ],
    "sg:phone":"+1 440 564 1035",
    "sg:postcode":"44024",
    "sg:province":"OH",
    "sg:tags":[
        "landscape"
    ],
    "wof:name":"United Diversified Services",
    "wof:placetype":"venue"
},
  "geometry": {"coordinates":[-81.23807600000001,41.499871],"type":"Point"}
}