{
  "type": "Feature",
  "properties": {
    "iso:country":"US",
    "sg:address":"18350 Waterford Rd",
    "sg:city":"Fredericktown",
    "sg:classifiers":[
        {
            "category":"Government",
            "subcategory":"Office",
            "type":"Public Place"
        }
    ],
    "sg:phone":"+1 740 694 7942",
    "sg:postcode":"43019",
    "sg:province":"OH",
    "sg:tags":[
        "engineering"
    ],
    "wof:name":"US Army Corps Of Engineers",
    "wof:placetype":"venue"
},
  "geometry": {"coordinates":[-82.581585,40.503317],"type":"Point"}
}