{
  "type": "Feature",
  "properties": {
    "addr:full":"1237 N Monroe Dr Xenia OH 45385",
    "addr:housenumber":"1237",
    "addr:postcode":"45385",
    "addr:street":"N Monroe Dr",
    "iso:country":"US",
    "sg:address":"1237 N Monroe Dr",
    "sg:city":"Xenia",
    "sg:classifiers":[
        {
            "category":"Social Services",
            "type":"Services"
        }
    ],
    "sg:phone":"+1 937 374 0830",
    "sg:postcode":"45385",
    "sg:province":"OH",
    "sg:tags":[
        "youth",
        "organization",
        "center"
    ],
    "wof:name":"Integrated Youth Svc",
    "wof:placetype":"venue"
},
  "geometry": {"coordinates":[-83.92883,39.701042],"type":"Point"}
}