{
  "type": "Feature",
  "properties": {
    "addr:full":"1603 Estate Ct Mansfield OH 44906",
    "addr:housenumber":"1603",
    "addr:postcode":"44906",
    "addr:street":"Estate Ct",
    "iso:country":"US",
    "sg:address":"1603 Estate Ct",
    "sg:city":"Mansfield",
    "sg:classifiers":[
        {
            "category":"Shopping",
            "subcategory":"Florist",
            "type":"Retail Goods"
        }
    ],
    "sg:phone":"+1 419 774 0616",
    "sg:postcode":"44906",
    "sg:province":"OH",
    "sg:tags":[
        "floral",
        "design"
    ],
    "wof:name":"K & K Creations Inc",
    "wof:placetype":"venue"
},
  "geometry": {"coordinates":[-82.56059999999999,40.716157],"type":"Point"}
}