{
  "type": "Feature",
  "properties": {
    "addr:full":"5754 Laurel Pine Ln Dublin OH 43016",
    "addr:housenumber":"5754",
    "addr:postcode":"43016",
    "addr:street":"Laurel Pine Ln",
    "iso:country":"US",
    "sg:address":"5754 Laurel Pine Ln",
    "sg:city":"Dublin",
    "sg:classifiers":[
        {
            "category":"Shopping",
            "subcategory":"Computers & Home Electronics",
            "type":"Retail Goods"
        }
    ],
    "sg:phone":"+1 614 529 4962",
    "sg:postcode":"43016",
    "sg:province":"OH",
    "wof:name":"Reliable Computer Parts Inc",
    "wof:placetype":"venue"
},
  "geometry": {"coordinates":[-83.15400699999999,40.069565],"type":"Point"}
}