{
  "type": "Feature",
  "properties": {
    "iso:country":"US",
    "sg:address":"8905 Symmes Trace Ct",
    "sg:city":"Loveland",
    "sg:classifiers":[
        {
            "category":"Wholesale",
            "subcategory":"Home Furnishings",
            "type":"Manufacturing & Wholesale Goods"
        }
    ],
    "sg:phone":"+1 513 677 0081",
    "sg:postcode":"45140",
    "sg:province":"OH",
    "wof:name":"Gill Tercek Inc",
    "wof:placetype":"venue"
},
  "geometry": {"coordinates":[-84.316576,39.280088],"type":"Point"}
}