{
  "type": "Feature",
  "properties": {
    "iso:country":"US",
    "sg:address":"123 N Fulton St",
    "sg:city":"Wauseon",
    "sg:classifiers":[
        {
            "category":"Shopping",
            "subcategory":"Clothing, Apparel, & Fashions",
            "type":"Retail Goods"
        }
    ],
    "sg:phone":"+1 419 335 5511",
    "sg:postcode":"43567",
    "sg:province":"OH",
    "sg:tags":[
        "item",
        "boutique"
    ],
    "wof:name":"Maria's Boutique Crafts & More",
    "wof:placetype":"venue"
},
  "geometry": {"coordinates":[-84.141548,41.548941],"type":"Point"}
}