{
  "type": "Feature",
  "properties": {
    "addr:full":"1400 E State St Fremont OH 43420",
    "addr:housenumber":"1400",
    "addr:postcode":"43420",
    "addr:street":"E State St",
    "iso:country":"US",
    "sg:address":"1400 E State St",
    "sg:city":"Fremont",
    "sg:classifiers":[
        {
            "category":"Manufacturing",
            "subcategory":"Motor Vehicles & Parts",
            "type":"Manufacturing & Wholesale Goods"
        }
    ],
    "sg:phone":"+1 419 332 9963",
    "sg:postcode":"43420",
    "sg:province":"OH",
    "sg:tags":[
        "automotive",
        "findings"
    ],
    "sg:website":"www.consolitecorp.com",
    "wof:name":"Consolite Corp",
    "wof:placetype":"venue"
},
  "geometry": {"coordinates":[-83.09427599999999,41.342257],"type":"Point"}
}