{
  "type": "Feature",
  "properties": {
    "addr:full":"5261 Pawnee Rd Toledo OH 43613",
    "addr:housenumber":"5261",
    "addr:postcode":"43613",
    "addr:street":"Pawnee Rd",
    "iso:country":"US",
    "sg:address":"5261 Pawnee Rd",
    "sg:city":"Toledo",
    "sg:classifiers":[
        {
            "category":"Shopping",
            "subcategory":"Clothing, Apparel, & Fashions",
            "type":"Retail Goods"
        }
    ],
    "sg:phone":"+1 419 292 1771",
    "sg:postcode":"43613",
    "sg:province":"OH",
    "wof:name":"Ohios Beauty T Shirts",
    "wof:placetype":"venue"
},
  "geometry": {"coordinates":[-83.61985799999999,41.70994],"type":"Point"}
}