{
  "type": "Feature",
  "properties": {
    "addr:full":"20716 Hillgrove Ave Cleveland OH 44137",
    "addr:housenumber":"20716",
    "addr:postcode":"44137",
    "addr:street":"Hillgrove Ave",
    "iso:country":"US",
    "sg:address":"20716 Hillgrove Ave",
    "sg:city":"Cleveland",
    "sg:classifiers":[
        {
            "category":"Organizations",
            "subcategory":"Religious Organization",
            "type":"Services"
        }
    ],
    "sg:phone":"+1 216 662 5079",
    "sg:postcode":"44137",
    "sg:province":"OH",
    "sg:tags":[
        "church"
    ],
    "wof:name":"Maple Heights United Meth Chr",
    "wof:placetype":"venue"
},
  "geometry": {"coordinates":[-81.53143,41.420084],"type":"Point"}
}