{
  "type": "Feature",
  "properties": {
    "iso:country":"US",
    "sg:address":"27 Federal Plz W",
    "sg:city":"Youngstown",
    "sg:classifiers":[
        {
            "category":"Shopping",
            "subcategory":"Clothing, Apparel, & Fashions",
            "type":"Retail Goods"
        }
    ],
    "sg:phone":"+1 330 744 7819",
    "sg:postcode":"44503",
    "sg:province":"OH",
    "sg:tags":[
        "leather",
        "garment",
        "furnishing",
        "sportswear",
        "suit"
    ],
    "wof:name":"Silver's Vogue Shop",
    "wof:placetype":"venue"
},
  "geometry": {"coordinates":[-80.65167,41.100972],"type":"Point"}
}