{
  "type": "Feature",
  "properties": {
    "addr:full": "2300 National Rd SW Hebron OH 43025",
    "addr:housenumber": "2300",
    "addr:postcode": "43025",
    "addr:street": "National Rd Sw",
    "iso:country": "US",
    "sg:address": "2300 National Rd SW",
    "sg:city": "Hebron",
    "sg:classifiers": [
      {
        "category": "Travel",
        "subcategory": "Campground",
        "type": "Entertainment"
      }
    ],
    "sg:phone": "+1 740 928 5300",
    "sg:postcode": "43025",
    "sg:province": "OH",
    "wof:name": "Robb Companies Inc",
    "wof:placetype": "venue"
  },
  "geometry": {"coordinates":[-82.546743,39.957711],"type":"Point"}
}
