{
  "type": "Feature",
  "properties": {
    "iso:country":"US",
    "sg:address":"2300 National Rd SW",
    "sg:city":"Hebron",
    "sg:classifiers":[
        {
            "category":"Travel",
            "subcategory":"Campground",
            "type":"Entertainment"
        }
    ],
    "sg:phone":"+1 740 928 5300",
    "sg:postcode":"43025",
    "sg:province":"OH",
    "wof:name":"Robb Companies Inc",
    "wof:placetype":"venue"
},
  "geometry": {"coordinates":[-82.54674300000001,39.957711],"type":"Point"}
}