{
  "type": "Feature",
  "properties": {
    "addr:full": "14550 New Buffalo Rd Columbiana OH 44408",
    "addr:housenumber": "14550",
    "addr:postcode": "44408",
    "addr:street": "New Buffalo Rd",
    "iso:country": "US",
    "sg:address": "14550 New Buffalo Rd",
    "sg:city": "Columbiana",
    "sg:classifiers": [
      {
        "category": "Organizations",
        "subcategory": "Religious Organization",
        "type": "Services"
      }
    ],
    "sg:phone": "+1 330 482 4446",
    "sg:postcode": "44408",
    "sg:province": "OH",
    "sg:tags": [
      "church"
    ],
    "wof:name": "Zion Hill Church Of Brethren",
    "wof:placetype": "venue"
  },
  "geometry": {"coordinates":[-80.703881,40.909155],"type":"Point"}
}
