{
  "type": "Feature",
  "properties": {
    "iso:country":"US",
    "sg:address":"6823 Lake Ave",
    "sg:city":"Elyria",
    "sg:classifiers":[
        {
            "category":"Retail",
            "subcategory":"Repair Shop",
            "type":"Services"
        }
    ],
    "sg:phone":"+1 440 327 3999",
    "sg:postcode":"44035",
    "sg:province":"OH",
    "sg:tags":[
        "operator",
        "local",
        "trucking"
    ],
    "wof:name":"F & J Contractors",
    "wof:placetype":"venue"
},
  "geometry": {"coordinates":[-82.13159400000001,41.401295],"type":"Point"}
}