{
  "type": "Feature",
  "properties": {
    "addr:full": "6823 Lake Ave Elyria OH 44035",
    "addr:housenumber": "6823",
    "addr:postcode": "44035",
    "addr:street": "Lake Ave",
    "iso:country": "US",
    "sg:address": "6823 Lake Ave",
    "sg:city": "Elyria",
    "sg:classifiers": [
      {
        "category": "Retail",
        "subcategory": "Repair Shop",
        "type": "Services"
      }
    ],
    "sg:phone": "+1 440 327 3999",
    "sg:postcode": "44035",
    "sg:province": "OH",
    "sg:tags": [
      "operator",
      "local",
      "trucking"
    ],
    "wof:name": "F \u0026 J Contractors",
    "wof:placetype": "venue"
  },
  "geometry": {"coordinates":[-82.131594,41.401295],"type":"Point"}
}
