{
  "type": "Feature",
  "properties": {
    "addr:full":"305 Vernon St Steubenville OH 43952",
    "addr:housenumber":"305",
    "addr:postcode":"43952",
    "addr:street":"Vernon St",
    "iso:country":"US",
    "sg:address":"305 Vernon St",
    "sg:city":"Steubenville",
    "sg:classifiers":[
        {
            "category":"Real Estate",
            "subcategory":"Real Estate Agent",
            "type":"Services"
        }
    ],
    "sg:phone":"+1 740 266 9100",
    "sg:postcode":"43952",
    "sg:province":"OH",
    "wof:name":"Bigsby Bigco",
    "wof:placetype":"venue"
},
  "geometry": {"coordinates":[-80.651405,40.377403],"type":"Point"}
}