{
  "type": "Feature",
  "properties": {
    "addr:full":"3009 Smith Rd Ste 75 Fairlawn OH 44333",
    "addr:housenumber":"3009;75",
    "addr:postcode":"44333",
    "addr:street":"Smith Rd Ste",
    "iso:country":"US",
    "sg:address":"3009 Smith Rd Ste 75",
    "sg:city":"Fairlawn",
    "sg:classifiers":[
        {
            "category":"Personal",
            "subcategory":"Beauty Salon",
            "type":"Services"
        },
        {
            "category":"Personal",
            "subcategory":"Barber",
            "type":"Services"
        },
        {
            "category":"Personal",
            "subcategory":"Day Spa",
            "type":"Services"
        }
    ],
    "sg:phone":"+1 330 665 5569",
    "sg:postcode":"44333",
    "sg:province":"OH",
    "sg:website":"http://www.mjames.com",
    "wof:name":"James M Salon Inc",
    "wof:placetype":"venue"
},
  "geometry": {"coordinates":[-81.618486,41.135858],"type":"Point"}
}