{
  "type": "Feature",
  "properties": {
    "iso:country":"US",
    "sg:address":"317 Sycamore Glen Dr",
    "sg:city":"Miamisburg",
    "sg:classifiers":[
        {
            "category":"Health Services",
            "subcategory":"Nursing And Care Facility",
            "type":"Services"
        },
        {
            "category":"Real Estate",
            "subcategory":"Real Estate Operator",
            "type":"Services"
        }
    ],
    "sg:phone":"+1 937 866 2984",
    "sg:postcode":"45342",
    "sg:province":"OH",
    "sg:tags":[
        "building",
        "retirement",
        "apartment",
        "community",
        "home"
    ],
    "wof:name":"Sycamore Glen Retirement Cmnty",
    "wof:placetype":"venue"
},
  "geometry": {"coordinates":[-84.24795899999999,39.634984],"type":"Point"}
}