{
  "type": "Feature",
  "properties": {
    "addr:full": "317 Sycamore Glen Dr Miamisburg OH 45342",
    "addr:housenumber": "317",
    "addr:postcode": "45342",
    "addr:street": "Sycamore Glen Dr",
    "iso:country": "US",
    "sg:address": "317 Sycamore Glen Dr",
    "sg:city": "Miamisburg",
    "sg:classifiers": [
      {
        "category": "Health Services",
        "subcategory": "Nursing And Care Facility",
        "type": "Services"
      },
      {
        "category": "Real Estate",
        "subcategory": "Real Estate Operator",
        "type": "Services"
      }
    ],
    "sg:phone": "+1 937 866 2984",
    "sg:postcode": "45342",
    "sg:province": "OH",
    "sg:tags": [
      "building",
      "retirement",
      "apartment",
      "community",
      "home"
    ],
    "wof:name": "Sycamore Glen Retirement Cmnty",
    "wof:placetype": "venue"
  },
  "geometry": {"coordinates":[-84.247959,39.634984],"type":"Point"}
}
