{
  "type": "Feature",
  "properties": {
    "iso:country":"US",
    "sg:address":"513 N Main St",
    "sg:city":"Piqua",
    "sg:classifiers":[
        {
            "category":"Wholesale",
            "subcategory":"Auto Parts",
            "type":"Manufacturing & Wholesale Goods"
        }
    ],
    "sg:phone":"+1 937 773 2967",
    "sg:postcode":"45356",
    "sg:province":"OH",
    "sg:tags":[
        "automotive"
    ],
    "wof:name":"Piqua Automotive Inc",
    "wof:placetype":"venue"
},
  "geometry": {"coordinates":[-84.23970199999999,40.1508],"type":"Point"}
}