{
  "type": "Feature",
  "properties": {
    "addr:full": "513 N Main St Piqua OH 45356",
    "addr:housenumber": "513",
    "addr:postcode": "45356",
    "addr:street": "N Main St",
    "iso:country": "US",
    "sg:address": "513 N Main St",
    "sg:city": "Piqua",
    "sg:classifiers": [
      {
        "category": "Wholesale",
        "subcategory": "Auto Parts",
        "type": "Manufacturing \u0026 Wholesale Goods"
      }
    ],
    "sg:phone": "+1 937 773 2967",
    "sg:postcode": "45356",
    "sg:province": "OH",
    "sg:tags": [
      "automotive"
    ],
    "wof:name": "Piqua Automotive Inc",
    "wof:placetype": "venue"
  },
  "geometry": {"coordinates":[-84.239702,40.1508],"type":"Point"}
}
