{
  "type": "Feature",
  "properties": {
    "addr:full":"3372 Clayton Blvd Cleveland OH 44120",
    "addr:housenumber":"3372",
    "addr:postcode":"44120",
    "addr:street":"Clayton Blvd",
    "iso:country":"US",
    "sg:address":"3372 Clayton Blvd",
    "sg:city":"Cleveland",
    "sg:classifiers":[
        {
            "category":"Health Services",
            "subcategory":"Health Practitioner",
            "type":"Services"
        }
    ],
    "sg:phone":"+1 440 473 8973",
    "sg:postcode":"44120",
    "sg:province":"OH",
    "sg:tags":[
        "psychologist"
    ],
    "wof:name":"James Kepner PHD",
    "wof:placetype":"venue"
},
  "geometry": {"coordinates":[-81.567651,41.468376],"type":"Point"}
}