{
  "type": "Feature",
  "properties": {
    "addr:full": "204 E Wood St Versailles OH 45380",
    "addr:housenumber": "204",
    "addr:postcode": "45380",
    "addr:street": "E Wood St",
    "iso:country": "US",
    "sg:address": "204 E Wood St",
    "sg:city": "Versailles",
    "sg:classifiers": [
      {
        "category": "Organizations",
        "subcategory": "Religious Organization",
        "type": "Services"
      }
    ],
    "sg:phone": "+1 937 526 3091",
    "sg:postcode": "45380",
    "sg:province": "OH",
    "wof:name": "Trinity Lutheran Church",
    "wof:placetype": "venue"
  },
  "geometry": {"coordinates":[-84.480772,40.221894],"type":"Point"}
}
