{
  "type": "Feature",
  "properties": {
    "addr:full":"1214 Anita Dr Kent OH 44240",
    "addr:housenumber":"1214",
    "addr:postcode":"44240",
    "addr:street":"Anita Dr",
    "iso:country":"US",
    "sg:address":"1214 Anita Dr",
    "sg:city":"Kent",
    "sg:classifiers":[
        {
            "category":"Real Estate",
            "subcategory":"Real Estate Agent",
            "type":"Services"
        }
    ],
    "sg:phone":"+1 330 678 0761",
    "sg:postcode":"44240",
    "sg:province":"OH",
    "wof:name":"Silver Meadows",
    "wof:placetype":"venue"
},
  "geometry": {"coordinates":[-81.387767,41.161128],"type":"Point"}
}