{
  "type": "Feature",
  "properties": {
    "iso:country":"US",
    "sg:address":"10850 Industrial First Ave",
    "sg:city":"Cleveland",
    "sg:classifiers":[
        {
            "category":"Wholesale",
            "subcategory":"Machinery & Supplies",
            "type":"Manufacturing & Wholesale Goods"
        }
    ],
    "sg:phone":"+1 440 582 0260",
    "sg:postcode":"44133",
    "sg:province":"OH",
    "sg:tags":[
        "compressor",
        "gas"
    ],
    "wof:name":"Bruce Air Co",
    "wof:placetype":"venue"
},
  "geometry": {"coordinates":[-81.772251,41.324753],"type":"Point"}
}