{
  "type": "Feature",
  "properties": {
    "addr:full": "10850 Industrial First Ave Cleveland OH 44133",
    "addr:housenumber": "10850",
    "addr:postcode": "44133",
    "addr:street": "Industrial First Ave",
    "iso:country": "US",
    "sg:address": "10850 Industrial First Ave",
    "sg:city": "Cleveland",
    "sg:classifiers": [
      {
        "category": "Wholesale",
        "subcategory": "Machinery \u0026 Supplies",
        "type": "Manufacturing \u0026 Wholesale Goods"
      }
    ],
    "sg:phone": "+1 440 582 0260",
    "sg:postcode": "44133",
    "sg:province": "OH",
    "sg:tags": [
      "compressor",
      "gas"
    ],
    "wof:name": "Bruce Air Co",
    "wof:placetype": "venue"
  },
  "geometry": {"coordinates":[-81.772251,41.324753],"type":"Point"}
}
