{
  "type": "Feature",
  "properties": {
    "addr:full": "2297 Sundew Ave Grove City OH 43123",
    "addr:housenumber": "2297",
    "addr:postcode": "43123",
    "addr:street": "Sundew Ave",
    "iso:country": "US",
    "sg:address": "2297 Sundew Ave",
    "sg:city": "Grove City",
    "sg:classifiers": [
      {
        "category": "Wholesale",
        "subcategory": "Drugs",
        "type": "Manufacturing \u0026 Wholesale Goods"
      }
    ],
    "sg:phone": "+1 614 539 8074",
    "sg:postcode": "43123",
    "sg:province": "OH",
    "sg:tags": [
      "pharmaceutical"
    ],
    "wof:name": "Priority Healthcare Corp",
    "wof:placetype": "venue"
  },
  "geometry": {"coordinates":[-83.066516,39.849907],"type":"Point"}
}
