{
  "type": "Feature",
  "properties": {
    "iso:country":"US",
    "sg:address":"4160 Co Hwy 39",
    "sg:city":"Upper Sandusky",
    "sg:classifiers":[
        {
            "category":"Building & Trades",
            "subcategory":"Construction",
            "type":"Services"
        }
    ],
    "sg:phone":"+1 419 927 9303",
    "sg:postcode":"43351",
    "sg:province":"OH",
    "sg:tags":[
        "carpenter"
    ],
    "wof:name":"Tim Riedel",
    "wof:placetype":"venue"
},
  "geometry": {"coordinates":[-83.191643,40.906204],"type":"Point"}
}