{
  "type": "Feature",
  "properties": {
    "iso:country":"US",
    "sg:address":"6510 Corporate Dr",
    "sg:city":"Cincinnati",
    "sg:classifiers":[
        {
            "category":"Manufacturing",
            "subcategory":"Tools & Machinery",
            "type":"Manufacturing & Wholesale Goods"
        },
        {
            "category":"Building & Trades",
            "subcategory":"Plumbing",
            "type":"Services"
        }
    ],
    "sg:phone":"+1 513 489 1317",
    "sg:postcode":"45242",
    "sg:province":"OH",
    "sg:tags":[
        "jig",
        "fixture",
        "maker",
        "die"
    ],
    "wof:name":"Rhinestahl Corporation",
    "wof:placetype":"venue"
},
  "geometry": {"coordinates":[-84.360749,39.273371],"type":"Point"}
}