{
  "type": "Feature",
  "properties": {
    "addr:full":"7713 Hamilton Ave Cincinnati OH 45231",
    "addr:housenumber":"7713",
    "addr:postcode":"45231",
    "addr:street":"Hamilton Ave",
    "iso:country":"US",
    "sg:address":"7713 Hamilton Ave",
    "sg:city":"Cincinnati",
    "sg:classifiers":[
        {
            "category":"Social Services",
            "subcategory":"Child Care",
            "type":"Services"
        }
    ],
    "sg:phone":"+1 513 522 1555",
    "sg:postcode":"45231",
    "sg:province":"OH",
    "sg:tags":[
        "day"
    ],
    "wof:name":"Children Unlimited Inc",
    "wof:placetype":"venue"
},
  "geometry": {"coordinates":[-84.548108,39.234385],"type":"Point"}
}