{
  "type": "Feature",
  "properties": {
    "addr:full":"264 Vista Dr Columbus OH 43230",
    "addr:housenumber":"264",
    "addr:postcode":"43230",
    "addr:street":"Vista Dr",
    "iso:country":"US",
    "sg:address":"264 Vista Dr",
    "sg:city":"Columbus",
    "sg:classifiers":[
        {
            "category":"Food & Beverages",
            "subcategory":"Groceries & Convenience Stores",
            "type":"Retail Goods"
        }
    ],
    "sg:phone":"+1 614 428 7492",
    "sg:postcode":"43230",
    "sg:province":"OH",
    "wof:name":"Wide Waters Food Co LLC",
    "wof:placetype":"venue"
},
  "geometry": {"coordinates":[-82.866449,40.04844],"type":"Point"}
}