{
  "type": "Feature",
  "properties": {
    "addr:full":"601 E Main St Canfield OH 44406",
    "addr:housenumber":"601",
    "addr:postcode":"44406",
    "addr:street":"E Main St",
    "iso:country":"US",
    "sg:address":"601 E Main St",
    "sg:city":"Canfield",
    "sg:classifiers":[
        {
            "category":"Shopping",
            "subcategory":"Pharmacy",
            "type":"Retail Goods"
        }
    ],
    "sg:phone":"+1 330 702 8030",
    "sg:postcode":"44406",
    "sg:province":"OH",
    "wof:name":"CVS Pharmacy",
    "wof:placetype":"venue"
},
  "geometry": {"coordinates":[-80.740713,41.024732],"type":"Point"}
}