{
  "type": "Feature",
  "properties": {
    "iso:country":"US",
    "sg:address":"740 E State St",
    "sg:city":"Sharon",
    "sg:classifiers":[
        {
            "category":"Health Services",
            "subcategory":"Doctor",
            "type":"Services"
        }
    ],
    "sg:phone":"+1   ",
    "sg:postcode":"16146",
    "sg:province":"OH",
    "sg:tags":[
        "physician"
    ],
    "wof:name":"Sharon Regional Physician Svcs",
    "wof:placetype":"venue"
},
  "geometry": {"coordinates":[-80.49606900000001,41.232931],"type":"Point"}
}