{
  "type": "Feature",
  "properties": {
    "iso:country":"US",
    "sg:address":"1718 Lakenoll Dr",
    "sg:city":"Cincinnati",
    "sg:classifiers":[
        {
            "category":"Wholesale",
            "subcategory":"Durable Goods & Equipment",
            "type":"Manufacturing & Wholesale Goods"
        }
    ],
    "sg:phone":"+1 513 522 8701",
    "sg:postcode":"45231",
    "sg:province":"OH",
    "wof:name":"MB Hiatt Inc",
    "wof:placetype":"venue"
},
  "geometry": {"coordinates":[-84.550179,39.22744],"type":"Point"}
}