{
  "type": "Feature",
  "properties": {
    "addr:full": "1718 Lakenoll Dr Cincinnati OH 45231",
    "addr:housenumber": "1718",
    "addr:postcode": "45231",
    "addr:street": "Lakenoll Dr",
    "iso:country": "US",
    "sg:address": "1718 Lakenoll Dr",
    "sg:city": "Cincinnati",
    "sg:classifiers": [
      {
        "category": "Wholesale",
        "subcategory": "Durable Goods \u0026 Equipment",
        "type": "Manufacturing \u0026 Wholesale Goods"
      }
    ],
    "sg:phone": "+1 513 522 8701",
    "sg:postcode": "45231",
    "sg:province": "OH",
    "wof:name": "MB Hiatt Inc",
    "wof:placetype": "venue"
  },
  "geometry": {"coordinates":[-84.550179,39.22744],"type":"Point"}
}
