{
  "type": "Feature",
  "properties": {
    "iso:country":"US",
    "sg:address":"846 Country Club Dr",
    "sg:city":"Cincinnati",
    "sg:classifiers":[
        {
            "category":"Real Estate",
            "subcategory":"Real Estate Agent",
            "type":"Services"
        }
    ],
    "sg:phone":"+1 513 753 3852",
    "sg:postcode":"45245",
    "sg:province":"OH",
    "wof:name":"Theme Park Concepts Inc",
    "wof:placetype":"venue"
},
  "geometry": {"coordinates":[-84.267322,39.049939],"type":"Point"}
}