{
  "type": "Feature",
  "properties": {
    "iso:country":"US",
    "sg:address":"6516 Detroit Ave",
    "sg:city":"Cleveland",
    "sg:classifiers":[
        {
            "category":"Social Services",
            "subcategory":"Adult Care",
            "type":"Services"
        }
    ],
    "sg:phone":"+1 216 939 0145",
    "sg:postcode":"44102",
    "sg:province":"OH",
    "sg:tags":[
        "foster"
    ],
    "sg:website":"www.ohyap.org",
    "wof:name":"Ohio Youth Advocate Program",
    "wof:placetype":"venue"
},
  "geometry": {"coordinates":[-81.73134899999999,41.483872],"type":"Point"}
}