{
  "type": "Feature",
  "properties": {
    "iso:country":"US",
    "sg:address":"352 3rd Ave",
    "sg:city":"Gallipolis",
    "sg:classifiers":[
        {
            "category":"Shopping",
            "type":"Retail Goods"
        }
    ],
    "sg:phone":"+1 740 446 6352",
    "sg:postcode":"45631",
    "sg:province":"OH",
    "sg:tags":[
        "monument"
    ],
    "wof:name":"Stanley Saunders Monuments",
    "wof:placetype":"venue"
},
  "geometry": {"coordinates":[-82.207133,38.808152],"type":"Point"}
}