{
  "type": "Feature",
  "properties": {
    "addr:full":"1177 S Hametown Rd Copley OH 44321",
    "addr:housenumber":"1177",
    "addr:postcode":"44321",
    "addr:street":"S Hametown Rd",
    "iso:country":"US",
    "sg:address":"1177 S Hametown Rd",
    "sg:city":"Copley",
    "sg:classifiers":[
        {
            "category":"Recreation",
            "type":"Entertainment"
        }
    ],
    "sg:phone":"+1 330 807 0798",
    "sg:postcode":"44321",
    "sg:province":"OH",
    "sg:tags":[
        "martial",
        "arts",
        "instruction"
    ],
    "wof:name":"Hakko Denshin Ryu Jujutsu Fed",
    "wof:placetype":"venue"
},
  "geometry": {"coordinates":[-81.66788200000001,41.102797],"type":"Point"}
}