{
  "type": "Feature",
  "properties": {
    "addr:full": "9520 Woodland Hills Dr Hamilton OH 45011",
    "addr:housenumber": "9520",
    "addr:postcode": "45011",
    "addr:street": "Woodland Hills Dr",
    "iso:country": "US",
    "sg:address": "9520 Woodland Hills Dr",
    "sg:city": "Hamilton",
    "sg:classifiers": [
      {
        "category": "Real Estate",
        "subcategory": "Real Estate Operator",
        "type": "Services"
      }
    ],
    "sg:phone": "+1 513 942 3386",
    "sg:postcode": "45011",
    "sg:province": "OH",
    "sg:tags": [
      "condominium"
    ],
    "wof:name": "Indian Ridge Condominium",
    "wof:placetype": "venue"
  },
  "geometry": {"coordinates":[-84.454482,39.317672],"type":"Point"}
}
