{
  "type": "Feature",
  "properties": {
    "iso:country":"US",
    "sg:address":"14818 Rapids Rd",
    "sg:city":"Burton",
    "sg:classifiers":[
        {
            "category":"Building & Trades",
            "subcategory":"Landscaping Services",
            "type":"Services"
        }
    ],
    "sg:phone":"+1 440 655 2079",
    "sg:postcode":"44021",
    "sg:province":"OH",
    "sg:tags":[
        "tree"
    ],
    "wof:name":"Ryes Tree Svc",
    "wof:placetype":"venue"
},
  "geometry": {"coordinates":[-81.15455799999999,41.465621],"type":"Point"}
}