{
  "type": "Feature",
  "properties": {
    "addr:full":"2050 E Main St Springfield OH 45503",
    "addr:housenumber":"2050",
    "addr:postcode":"45503",
    "addr:street":"E Main St",
    "iso:country":"US",
    "sg:address":"2050 E Main St",
    "sg:city":"Springfield",
    "sg:classifiers":[
        {
            "category":"Banks & Credit Unions",
            "subcategory":"Bank",
            "type":"Services"
        }
    ],
    "sg:phone":"+1 937 325 5446",
    "sg:postcode":"45503",
    "sg:province":"OH",
    "sg:tags":[
        "cashing",
        "check"
    ],
    "sg:website":"www.cashlandloans.com",
    "wof:name":"Cashland",
    "wof:placetype":"venue"
},
  "geometry": {"coordinates":[-83.779251,39.923404],"type":"Point"}
}