{
  "type": "Feature",
  "properties": {
    "iso:country":"US",
    "sg:address":"1173 Neil Ave",
    "sg:city":"Columbus",
    "sg:classifiers":[
        {
            "category":"Manufacturing",
            "subcategory":"Food",
            "type":"Manufacturing & Wholesale Goods"
        }
    ],
    "sg:phone":"+1 614 294 4026",
    "sg:postcode":"43201",
    "sg:province":"OH",
    "sg:tags":[
        "product",
        "manufacturer"
    ],
    "wof:name":"Happy Trails",
    "wof:placetype":"venue"
},
  "geometry": {"coordinates":[-83.01253800000001,39.983771],"type":"Point"}
}