{
  "type": "Feature",
  "properties": {
    "addr:full": "5312 Johnston-Slagle Rd Sidney OH 45365",
    "addr:housenumber": "5312",
    "addr:postcode": "45365",
    "addr:street": "Johnston-Slagle Rd",
    "iso:country": "US",
    "sg:address": "5312 Johnston-Slagle Rd",
    "sg:city": "Sidney",
    "sg:phone": "+1 937 492 2947",
    "sg:postcode": "45365",
    "sg:province": "OH",
    "sg:tags": [
      "farm",
      "corn",
      "soybean"
    ],
    "wof:name": "Lowell Borland",
    "wof:placetype": "venue"
  },
  "geometry": {"coordinates":[-84.064289,40.261208],"type":"Point"}
}
