{
  "type": "Feature",
  "properties": {
    "addr:full": "8119 Mansfield Ave Cleveland OH 44105",
    "addr:housenumber": "8119",
    "addr:postcode": "44105",
    "addr:street": "Mansfield Ave",
    "iso:country": "US",
    "sg:address": "8119 Mansfield Ave",
    "sg:city": "Cleveland",
    "sg:classifiers": [
      {
        "category": "Manufacturing",
        "subcategory": "Tools \u0026 Machinery",
        "type": "Manufacturing \u0026 Wholesale Goods"
      }
    ],
    "sg:phone": "+1 216 429 2424",
    "sg:postcode": "44105",
    "sg:province": "OH",
    "sg:tags": [
      "machine",
      "shop"
    ],
    "wof:name": "Faith Tech",
    "wof:placetype": "venue"
  },
  "geometry": {"coordinates":[-81.630153,41.463148],"type":"Point"}
}
