{
  "type": "Feature",
  "properties": {
    "iso:country":"US",
    "sg:address":"8119 Mansfield Ave",
    "sg:city":"Cleveland",
    "sg:classifiers":[
        {
            "category":"Manufacturing",
            "subcategory":"Tools & Machinery",
            "type":"Manufacturing & Wholesale Goods"
        }
    ],
    "sg:phone":"+1 216 429 2424",
    "sg:postcode":"44105",
    "sg:province":"OH",
    "sg:tags":[
        "machine",
        "shop"
    ],
    "wof:name":"Faith Tech",
    "wof:placetype":"venue"
},
  "geometry": {"coordinates":[-81.63015300000001,41.463148],"type":"Point"}
}