{
  "type": "Feature",
  "properties": {
    "addr:full": "2939 Scarborough Rd Cleveland OH 44118",
    "addr:housenumber": "2939",
    "addr:postcode": "44118",
    "addr:street": "Scarborough Rd",
    "iso:country": "US",
    "sg:address": "2939 Scarborough Rd",
    "sg:city": "Cleveland",
    "sg:classifiers": [
      {
        "category": "Utilities",
        "subcategory": "Telephone",
        "type": "Services"
      }
    ],
    "sg:phone": "+1 216 321 8980",
    "sg:postcode": "44118",
    "sg:province": "OH",
    "sg:tags": [
      "communications"
    ],
    "wof:name": "Hughnix Inc",
    "wof:placetype": "venue"
  },
  "geometry": {"coordinates":[-81.572337,41.493842],"type":"Point"}
}
