{
  "type": "Feature",
  "properties": {
    "addr:full":"400 Broadway St Sandusky OH 44870",
    "addr:housenumber":"400",
    "addr:postcode":"44870",
    "addr:street":"Broadway St",
    "iso:country":"US",
    "sg:address":"400 Broadway St",
    "sg:city":"Sandusky",
    "sg:classifiers":[
        {
            "category":"Manufacturing",
            "subcategory":"Paper Products",
            "type":"Manufacturing & Wholesale Goods"
        },
        {
            "category":"Manufacturing",
            "subcategory":"Rubber & Plastics",
            "type":"Manufacturing & Wholesale Goods"
        }
    ],
    "sg:phone":"+1 419 624 3088",
    "sg:postcode":"44870",
    "sg:province":"OH",
    "sg:tags":[
        "corrugated",
        "box",
        "mfg"
    ],
    "wof:name":"Georgia-Pacific Corp",
    "wof:placetype":"venue"
},
  "geometry": {"coordinates":[-82.73019600000001,41.449004],"type":"Point"}
}