{
  "type": "Feature",
  "properties": {
    "addr:full":"400 Mill Ave SE New Philadelphia OH 44663",
    "addr:housenumber":"400",
    "addr:postcode":"44663",
    "addr:street":"Mill Ave Se",
    "iso:country":"US",
    "sg:address":"400 Mill Ave SE",
    "sg:city":"New Philadelphia",
    "sg:classifiers":[
        {
            "category":"Health Services",
            "subcategory":"Optometrist",
            "type":"Services"
        }
    ],
    "sg:phone":"+1 330 339 8788",
    "sg:postcode":"44663",
    "sg:province":"OH",
    "sg:tags":[
        "optical",
        "good"
    ],
    "wof:name":"Eyexam 2000",
    "wof:placetype":"venue"
},
  "geometry": {"coordinates":[-81.44312499999999,40.48318],"type":"Point"}
}