{
  "type": "Feature",
  "properties": {
    "addr:full": "1669 Wesleyan Rd Dayton OH 45406",
    "addr:housenumber": "1669",
    "addr:postcode": "45406",
    "addr:street": "Wesleyan Rd",
    "iso:country": "US",
    "sg:address": "1669 Wesleyan Rd",
    "sg:city": "Dayton",
    "sg:classifiers": [
      {
        "category": "Organizations",
        "subcategory": "Religious Organization",
        "type": "Services"
      }
    ],
    "sg:phone": "+1 937 274 8427",
    "sg:postcode": "45406",
    "sg:province": "OH",
    "sg:tags": [
      "clergy"
    ],
    "wof:name": "Larry Coleman",
    "wof:placetype": "venue"
  },
  "geometry": {"coordinates":[-84.243691,39.778718],"type":"Point"}
}
