{
  "type": "Feature",
  "properties": {
    "iso:country":"US",
    "sg:address":"3167 Linden Rd",
    "sg:city":"Cleveland",
    "sg:classifiers":[
        {
            "category":"Shopping",
            "subcategory":"Music",
            "type":"Retail Goods"
        }
    ],
    "sg:phone":"+1 440 331 3714",
    "sg:postcode":"44116",
    "sg:province":"OH",
    "sg:tags":[
        "compact",
        "record",
        "disc",
        "tape"
    ],
    "wof:name":"Off The Record",
    "wof:placetype":"venue"
},
  "geometry": {"coordinates":[-81.84693799999999,41.459692],"type":"Point"}
}