{
  "type": "Feature",
  "properties": {
    "addr:full": "3167 Linden Rd Cleveland OH 44116",
    "addr:housenumber": "3167",
    "addr:postcode": "44116",
    "addr:street": "Linden Rd",
    "iso:country": "US",
    "sg:address": "3167 Linden Rd",
    "sg:city": "Cleveland",
    "sg:classifiers": [
      {
        "category": "Shopping",
        "subcategory": "Music",
        "type": "Retail Goods"
      }
    ],
    "sg:phone": "+1 440 331 3714",
    "sg:postcode": "44116",
    "sg:province": "OH",
    "sg:tags": [
      "compact",
      "record",
      "disc",
      "tape"
    ],
    "wof:name": "Off The Record",
    "wof:placetype": "venue"
  },
  "geometry": {"coordinates":[-81.846938,41.459692],"type":"Point"}
}
