{
  "type": "Feature",
  "properties": {
    "iso:country":"US",
    "sg:address":"4331 Pennswood Dr",
    "sg:city":"Middletown",
    "sg:classifiers":[
        {
            "category":"Shopping",
            "subcategory":"Hobbies, Toys, & Games",
            "type":"Retail Goods"
        }
    ],
    "sg:phone":"+1 513 424 0076",
    "sg:postcode":"45042",
    "sg:province":"OH",
    "sg:tags":[
        "craft"
    ],
    "wof:name":"Hilltop House",
    "wof:placetype":"venue"
},
  "geometry": {"coordinates":[-84.350509,39.537295],"type":"Point"}
}