{
  "type": "Feature",
  "properties": {
    "iso:country":"US",
    "sg:address":"845 Homewood Ave",
    "sg:city":"Salem",
    "sg:classifiers":[
        {
            "category":"Building & Trades",
            "subcategory":"Construction",
            "type":"Services"
        }
    ],
    "sg:phone":"+1 330 337 3694",
    "sg:postcode":"44460",
    "sg:province":"OH",
    "sg:tags":[
        "contractor"
    ],
    "wof:name":"Dennis Kubina Drywall",
    "wof:placetype":"venue"
},
  "geometry": {"coordinates":[-80.847311,40.894841],"type":"Point"}
}