{
  "type": "Feature",
  "properties": {
    "addr:full": "136 E 3rd St Perrysburg OH 43551",
    "addr:housenumber": "136",
    "addr:postcode": "43551",
    "addr:street": "E 3Rd St",
    "iso:country": "US",
    "sg:address": "136 E 3rd St",
    "sg:city": "Perrysburg",
    "sg:classifiers": [
      {
        "category": "Personal",
        "subcategory": "Beauty Salon",
        "type": "Services"
      }
    ],
    "sg:phone": "+1 419 874 7301",
    "sg:postcode": "43551",
    "sg:province": "OH",
    "wof:name": "Tievoli Salon \u0026 Retreat",
    "wof:placetype": "venue"
  },
  "geometry": {"coordinates":[-83.626952,41.558606],"type":"Point"}
}
