{
  "type": "Feature",
  "properties": {
    "addr:full":"6171 Cherry Hollow Ln Kent OH 44240",
    "addr:housenumber":"6171",
    "addr:postcode":"44240",
    "addr:street":"Cherry Hollow Ln",
    "iso:country":"US",
    "sg:address":"6171 Cherry Hollow Ln",
    "sg:city":"Kent",
    "sg:classifiers":[
        {
            "category":"Insurance",
            "subcategory":"Insurance Agent",
            "type":"Services"
        }
    ],
    "sg:phone":"+1 330 673 0053",
    "sg:postcode":"44240",
    "sg:province":"OH",
    "wof:name":"Johnson Agency",
    "wof:placetype":"venue"
},
  "geometry": {"coordinates":[-81.333091,41.158852],"type":"Point"}
}