{
  "type": "Feature",
  "properties": {
    "addr:full": "312 Walnut St Cincinnati OH 45202",
    "addr:housenumber": "312",
    "addr:postcode": "45202",
    "addr:street": "Walnut St",
    "iso:country": "US",
    "sg:address": "312 Walnut St",
    "sg:city": "Cincinnati",
    "sg:classifiers": [
      {
        "category": "Professional",
        "subcategory": "Management \u0026 Consulting",
        "type": "Services"
      }
    ],
    "sg:phone": "+1 513 632 2600",
    "sg:postcode": "45202",
    "sg:province": "OH",
    "sg:tags": [
      "consultant",
      "business"
    ],
    "sg:website": "www.mercerhr.com",
    "wof:name": "Mercer Human Resource Cnsltng",
    "wof:placetype": "venue"
  },
  "geometry": {"coordinates":[-84.510814,39.099463],"type":"Point"}
}
