{
  "type": "Feature",
  "properties": {
    "iso:country":"US",
    "sg:address":"9600 Colerain Ave",
    "sg:city":"Cincinnati",
    "sg:classifiers":[
        {
            "category":"Professional",
            "subcategory":"Lawyer & Legal Services",
            "type":"Services"
        }
    ],
    "sg:phone":"+1 513 721 1200",
    "sg:postcode":"45251",
    "sg:province":"OH",
    "sg:tags":[
        "attorney"
    ],
    "wof:name":"Young Reverman & Mazzei",
    "wof:placetype":"venue"
},
  "geometry": {"coordinates":[-84.596144,39.247029],"type":"Point"}
}