{
  "type": "Feature",
  "properties": {
    "addr:full": "1121 W Water St Piqua OH 45356",
    "addr:housenumber": "1121",
    "addr:postcode": "45356",
    "addr:street": "W Water St",
    "iso:country": "US",
    "sg:address": "1121 W Water St",
    "sg:city": "Piqua",
    "sg:classifiers": [
      {
        "category": "Insurance",
        "subcategory": "Insurance Agent",
        "type": "Services"
      }
    ],
    "sg:phone": "+1 937 773 5626",
    "sg:postcode": "45356",
    "sg:province": "OH",
    "wof:name": "James R Henestofel",
    "wof:placetype": "venue"
  },
  "geometry": {"coordinates":[-84.256086,40.147314],"type":"Point"}
}
