{
  "type": "Feature",
  "properties": {
    "addr:full": "785 Marlow Pl Mansfield OH 44906",
    "addr:housenumber": "785",
    "addr:postcode": "44906",
    "addr:street": "Marlow Pl",
    "iso:country": "US",
    "sg:address": "785 Marlow Pl",
    "sg:city": "Mansfield",
    "sg:classifiers": [
      {
        "category": "Professional",
        "subcategory": "Business Services",
        "type": "Services"
      }
    ],
    "sg:phone": "+1 419 522 6759",
    "sg:postcode": "44906",
    "sg:province": "OH",
    "sg:tags": [
      "notary"
    ],
    "wof:name": "Public Notary",
    "wof:placetype": "venue"
  },
  "geometry": {"coordinates":[-82.544943,40.755264],"type":"Point"}
}
