{
  "type": "Feature",
  "properties": {
    "iso:country":"US",
    "sg:address":"4499 US Rte 127 S",
    "sg:city":"Eaton",
    "sg:classifiers":[
        {
            "category":"Utilities",
            "subcategory":"Refuse",
            "type":"Services"
        }
    ],
    "sg:phone":"+1 937 456 6880",
    "sg:postcode":"45320",
    "sg:province":"OH",
    "sg:tags":[
        "disposal",
        "waste"
    ],
    "wof:name":"Preble Co Solid Waste District",
    "wof:placetype":"venue"
},
  "geometry": {"coordinates":[-84.63188100000001,39.684825],"type":"Point"}
}