{
  "type": "Feature",
  "properties": {
    "addr:full": "2279 N Moraine Blvd Dayton OH 45439",
    "addr:housenumber": "2279",
    "addr:postcode": "45439",
    "addr:street": "N Moraine Blvd",
    "iso:country": "US",
    "sg:address": "2279 N Moraine Blvd",
    "sg:city": "Dayton",
    "sg:classifiers": [
      {
        "category": "Shopping",
        "type": "Retail Goods"
      },
      {
        "category": "Wholesale",
        "subcategory": "Non-durable Goods",
        "type": "Manufacturing \u0026 Wholesale Goods"
      }
    ],
    "sg:phone": "+1 937 297 0515",
    "sg:postcode": "45439",
    "sg:province": "OH",
    "sg:tags": [
      "tropical",
      "water",
      "fish",
      "salt"
    ],
    "wof:name": "Gerber's Tropical Fish Inc",
    "wof:placetype": "venue"
  },
  "geometry": {"coordinates":[-84.218194,39.722526],"type":"Point"}
}
