{
  "type": "Feature",
  "properties": {
    "addr:full": "526 Graham Rd Cuyahoga Falls OH 44221",
    "addr:housenumber": "526",
    "addr:postcode": "44221",
    "addr:street": "Graham Rd",
    "iso:country": "US",
    "sg:address": "526 Graham Rd",
    "sg:city": "Cuyahoga Falls",
    "sg:classifiers": [
      {
        "category": "Professional",
        "subcategory": "Lawyer \u0026 Legal Services",
        "type": "Services"
      }
    ],
    "sg:phone": "+1 330 923 8190",
    "sg:postcode": "44221",
    "sg:province": "OH",
    "sg:tags": [
      "attorney"
    ],
    "wof:name": "James D Craft Attorney At Law",
    "wof:placetype": "venue"
  },
  "geometry": {"coordinates":[-81.491838,41.158899],"type":"Point"}
}
