{
  "type": "Feature",
  "properties": {
    "addr:full": "2238 Briarhurst Ln Columbus OH 43220",
    "addr:housenumber": "2238",
    "addr:postcode": "43220",
    "addr:street": "Briarhurst Ln",
    "iso:country": "US",
    "sg:address": "2238 Briarhurst Ln",
    "sg:city": "Columbus",
    "sg:classifiers": [
      {
        "category": "Real Estate",
        "subcategory": "Real Estate Operator",
        "type": "Services"
      }
    ],
    "sg:phone": "+1 614 451 6080",
    "sg:postcode": "43220",
    "sg:province": "OH",
    "sg:tags": [
      "apartment"
    ],
    "wof:name": "Slate Run Apartments",
    "wof:placetype": "venue"
  },
  "geometry": {"coordinates":[-83.078729,40.060853],"type":"Point"}
}
