{
  "type": "Feature",
  "properties": {
    "addr:full": "35 S Franklin St Delaware OH 43015",
    "addr:housenumber": "35",
    "addr:postcode": "43015",
    "addr:street": "S Franklin St",
    "iso:country": "US",
    "sg:address": "35 S Franklin St",
    "sg:city": "Delaware",
    "sg:classifiers": [
      {
        "category": "Autos \u0026 Motor Vehicles",
        "subcategory": "Motorcycle Sales",
        "type": "Retail Goods"
      }
    ],
    "sg:phone": "+1 740 362 5595",
    "sg:postcode": "43015",
    "sg:province": "OH",
    "wof:name": "Cycle Search International",
    "wof:placetype": "venue"
  },
  "geometry": {"coordinates":[-83.069638,40.297339],"type":"Point"}
}
