{
  "type": "Feature",
  "properties": {
    "addr:full":"12201 Larchmere Blvd Cleveland OH 44120",
    "addr:housenumber":"12201",
    "addr:postcode":"44120",
    "addr:street":"Larchmere Blvd",
    "iso:country":"US",
    "sg:address":"12201 Larchmere Blvd",
    "sg:city":"Cleveland",
    "sg:classifiers":[
        {
            "category":"Education",
            "subcategory":"School",
            "type":"Public Place"
        }
    ],
    "sg:phone":"+1 216 421 7587",
    "sg:postcode":"44120",
    "sg:province":"OH",
    "wof:name":"Life Skills Ctr Northeast Ohio",
    "wof:placetype":"venue"
},
  "geometry": {"coordinates":[-81.59658899999999,41.4879],"type":"Point"}
}