{
  "type": "Feature",
  "properties": {
    "addr:full":"6050 Blacksnake Rd Utica OH 43080",
    "addr:housenumber":"6050",
    "addr:postcode":"43080",
    "addr:street":"Blacksnake Rd",
    "iso:country":"US",
    "sg:address":"6050 Blacksnake Rd",
    "sg:city":"Utica",
    "sg:classifiers":[
        {
            "category":"Travel",
            "subcategory":"Hotels & Motels",
            "type":"Entertainment"
        }
    ],
    "sg:phone":"+1 740 892 2997",
    "sg:postcode":"43080",
    "sg:province":"OH",
    "sg:tags":[
        "breakfast",
        "accommodation",
        "bed"
    ],
    "wof:name":"Cabin In The Woods B & B",
    "wof:placetype":"venue"
},
  "geometry": {"coordinates":[-82.42737099999999,40.225577],"type":"Point"}
}