{
  "type": "Feature",
  "properties": {
    "addr:full": "6050 Blacksnake Rd Utica OH 43080",
    "addr:housenumber": "6050",
    "addr:postcode": "43080",
    "addr:street": "Blacksnake Rd",
    "iso:country": "US",
    "sg:address": "6050 Blacksnake Rd",
    "sg:city": "Utica",
    "sg:classifiers": [
      {
        "category": "Travel",
        "subcategory": "Hotels \u0026 Motels",
        "type": "Entertainment"
      }
    ],
    "sg:phone": "+1 740 892 2997",
    "sg:postcode": "43080",
    "sg:province": "OH",
    "sg:tags": [
      "breakfast",
      "accommodation",
      "bed"
    ],
    "wof:name": "Cabin In The Woods B \u0026 B",
    "wof:placetype": "venue"
  },
  "geometry": {"coordinates":[-82.427371,40.225577],"type":"Point"}
}
