{
  "type": "Feature",
  "properties": {
    "addr:full":"38301 Apollo Pkwy Willoughby OH 44094",
    "addr:postcode":"38301;44094",
    "addr:street":"Apollo Pkwy",
    "iso:country":"US",
    "sg:address":"38301 Apollo Pkwy",
    "sg:city":"Willoughby",
    "sg:classifiers":[
        {
            "category":"Manufacturing",
            "subcategory":"Metals",
            "type":"Manufacturing & Wholesale Goods"
        }
    ],
    "sg:phone":"+1 440 918 9718",
    "sg:postcode":"44094",
    "sg:province":"OH",
    "sg:tags":[
        "thread"
    ],
    "wof:name":"Ball Gage & Inspection Inc",
    "wof:placetype":"venue"
},
  "geometry": {"coordinates":[-81.402066,41.650459],"type":"Point"}
}