{
  "type": "Feature",
  "properties": {
    "addr:full":"2151 S Arlington Rd Akron OH 44306",
    "addr:housenumber":"2151",
    "addr:postcode":"44306",
    "addr:street":"S Arlington Rd",
    "iso:country":"US",
    "sg:address":"2151 S Arlington Rd",
    "sg:city":"Akron",
    "sg:classifiers":[
        {
            "category":"Banks & Credit Unions",
            "subcategory":"Bank",
            "type":"Services"
        }
    ],
    "sg:phone":"+1 330 785 3530",
    "sg:postcode":"44306",
    "sg:province":"OH",
    "sg:tags":[
        "mortgage"
    ],
    "wof:name":"Allied Home Mrtg Capitl Corp",
    "wof:placetype":"venue"
},
  "geometry": {"coordinates":[-81.49176300000001,41.013287],"type":"Point"}
}