{
  "type": "Feature",
  "properties": {
    "addr:full":"25877 Scheider Rd Perrysburg OH 43551",
    "addr:postcode":"25877;43551",
    "addr:street":"Scheider Rd",
    "iso:country":"US",
    "sg:address":"25877 Scheider Rd",
    "sg:city":"Perrysburg",
    "sg:classifiers":[
        {
            "category":"Organizations",
            "subcategory":"Religious Organization",
            "type":"Services"
        }
    ],
    "sg:phone":"+1 419 874 3509",
    "sg:postcode":"43551",
    "sg:province":"OH",
    "sg:tags":[
        "church"
    ],
    "wof:name":"Islamic Center Of Toledo",
    "wof:placetype":"venue"
},
  "geometry": {"coordinates":[-83.616585,41.522863],"type":"Point"}
}