{
  "type": "Feature",
  "properties": {
    "addr:full":"16915 Detroit Ave Lakewood OH 44107",
    "addr:housenumber":"16915",
    "addr:postcode":"44107",
    "addr:street":"Detroit Ave",
    "iso:country":"US",
    "sg:address":"16915 Detroit Ave",
    "sg:city":"Lakewood",
    "sg:classifiers":[
        {
            "category":"Home & Garden",
            "subcategory":"Garden Supply",
            "type":"Retail Goods"
        }
    ],
    "sg:phone":"+1 216 228 4007",
    "sg:postcode":"44107",
    "sg:province":"OH",
    "wof:name":"West Park Gardens",
    "wof:placetype":"venue"
},
  "geometry": {"coordinates":[-81.815583,41.485307],"type":"Point"}
}