{
  "type": "Feature",
  "properties": {
    "addr:full": "40 Twp Rd 1031 Nova OH 44859",
    "addr:housenumber": "40;1031",
    "addr:postcode": "44859",
    "addr:street": "Twp Rd",
    "iso:country": "US",
    "sg:address": "40 Twp Rd 1031",
    "sg:city": "Nova",
    "sg:classifiers": [
      {
        "category": "Shopping",
        "subcategory": "Musical Instruments",
        "type": "Retail Goods"
      }
    ],
    "sg:phone": "+1 419 652 2345",
    "sg:postcode": "44859",
    "sg:province": "OH",
    "wof:name": "Country Stage Music Park",
    "wof:placetype": "venue"
  },
  "geometry": {"coordinates":[-82.326488,41.055194],"type":"Point"}
}
