{
  "type": "Feature",
  "properties": {
    "addr:full": "6100 Oak Tree Blvd Cleveland OH 44131",
    "addr:housenumber": "6100",
    "addr:postcode": "44131",
    "addr:street": "Oak Tree Blvd",
    "iso:country": "US",
    "sg:address": "6100 Oak Tree Blvd",
    "sg:city": "Cleveland",
    "sg:classifiers": [
      {
        "category": "Professional",
        "subcategory": "Lawyer \u0026 Legal Services",
        "type": "Services"
      }
    ],
    "sg:phone": "+1 216 241 5900",
    "sg:postcode": "44131",
    "sg:province": "OH",
    "sg:tags": [
      "attorney"
    ],
    "wof:name": "Payne Payne \u0026 Cook",
    "wof:placetype": "venue"
  },
  "geometry": {"coordinates":[-81.661233,41.398296],"type":"Point"}
}
