{
  "type": "Feature",
  "properties": {
    "addr:full":"3444 Westerville Rd Columbus OH 43224",
    "addr:housenumber":"3444",
    "addr:postcode":"43224",
    "addr:street":"Westerville Rd",
    "iso:country":"US",
    "sg:address":"3444 Westerville Rd",
    "sg:city":"Columbus",
    "sg:classifiers":[
        {
            "category":"Food & Beverages",
            "subcategory":"Groceries & Convenience Stores",
            "type":"Retail Goods"
        }
    ],
    "sg:phone":"+1 614 471 9500",
    "sg:postcode":"43224",
    "sg:province":"OH",
    "sg:tags":[
        "grocer"
    ],
    "wof:name":"Westerville Market Inc",
    "wof:placetype":"venue"
},
  "geometry": {"coordinates":[-82.952155,40.038121],"type":"Point"}
}