{
  "type": "Feature",
  "properties": {
    "addr:full": "2473 North Rd NE Warren OH 44483",
    "addr:housenumber": "2473",
    "addr:postcode": "44483",
    "addr:street": "North Rd Ne",
    "iso:country": "US",
    "sg:address": "2473 North Rd NE",
    "sg:city": "Warren",
    "sg:classifiers": [
      {
        "category": "Social Services",
        "subcategory": "Job Training",
        "type": "Services"
      }
    ],
    "sg:phone": "+1 330 372 0267",
    "sg:postcode": "44483",
    "sg:province": "OH",
    "sg:tags": [
      "rehabilitation"
    ],
    "wof:name": "Rehabworks",
    "wof:placetype": "venue"
  },
  "geometry": {"coordinates":[-80.77459,41.264376],"type":"Point"}
}
