{
  "type": "Feature",
  "properties": {
    "addr:full": "2685 Blue Heron Dr Hudson OH 44236",
    "addr:housenumber": "2685",
    "addr:postcode": "44236",
    "addr:street": "Blue Heron Dr",
    "iso:country": "US",
    "sg:address": "2685 Blue Heron Dr",
    "sg:city": "Hudson",
    "sg:classifiers": [
      {
        "category": "Manufacturing",
        "subcategory": "Chemicals \u0026 Compounds",
        "type": "Manufacturing \u0026 Wholesale Goods"
      }
    ],
    "sg:phone": "+1 330 650 0237",
    "sg:postcode": "44236",
    "sg:province": "OH",
    "sg:tags": [
      "mfr",
      "industrial",
      "organic"
    ],
    "wof:name": "Hercules Incorporated",
    "wof:placetype": "venue"
  },
  "geometry": {"coordinates":[-81.415449,41.26617],"type":"Point"}
}
