{
  "type": "Feature",
  "properties": {
    "iso:country":"US",
    "sg:address":"2685 Blue Heron Dr",
    "sg:city":"Hudson",
    "sg:classifiers":[
        {
            "category":"Manufacturing",
            "subcategory":"Chemicals & Compounds",
            "type":"Manufacturing & Wholesale Goods"
        }
    ],
    "sg:phone":"+1 330 650 0237",
    "sg:postcode":"44236",
    "sg:province":"OH",
    "sg:tags":[
        "mfr",
        "industrial",
        "organic"
    ],
    "wof:name":"Hercules Incorporated",
    "wof:placetype":"venue"
},
  "geometry": {"coordinates":[-81.415449,41.26617],"type":"Point"}
}