{
  "type": "Feature",
  "properties": {
    "addr:full":"7300 Industrial Row Dr Mason OH 45040",
    "addr:housenumber":"7300",
    "addr:postcode":"45040",
    "addr:street":"Industrial Row Dr",
    "iso:country":"US",
    "sg:address":"7300 Industrial Row Dr",
    "sg:city":"Mason",
    "sg:classifiers":[
        {
            "category":"Manufacturing",
            "subcategory":"Chemicals & Compounds",
            "type":"Manufacturing & Wholesale Goods"
        }
    ],
    "sg:phone":"+1 513 398 7300",
    "sg:postcode":"45040",
    "sg:province":"OH",
    "sg:tags":[
        "mfg"
    ],
    "wof:name":"Bonsal American",
    "wof:placetype":"venue"
},
  "geometry": {"coordinates":[-84.33815300000001,39.334481],"type":"Point"}
}