{
  "type": "Feature",
  "properties": {
    "addr:full":"5240 Dixie Hwy Fairfield OH 45014",
    "addr:housenumber":"5240",
    "addr:postcode":"45014",
    "addr:street":"Dixie Hwy",
    "iso:country":"US",
    "sg:address":"5240 Dixie Hwy",
    "sg:city":"Fairfield",
    "sg:classifiers":[
        {
            "category":"Autos & Motor Vehicles",
            "subcategory":"Recreational Vehicle Sales",
            "type":"Retail Goods"
        }
    ],
    "sg:phone":"+1 513 939 3739",
    "sg:postcode":"45014",
    "sg:province":"OH",
    "sg:tags":[
        "parts",
        "trailer"
    ],
    "wof:name":"Drews Truck Accessories",
    "wof:placetype":"venue"
},
  "geometry": {"coordinates":[-84.531648,39.338123],"type":"Point"}
}