{
  "type": "Feature",
  "properties": {
    "iso:country":"US",
    "sg:address":"10302 Crestland Ct",
    "sg:city":"Cincinnati",
    "sg:classifiers":[
        {
            "category":"Retail",
            "subcategory":"Repair Shop",
            "type":"Services"
        }
    ],
    "sg:phone":"+1 513 851 6889",
    "sg:postcode":"45251",
    "sg:province":"OH",
    "sg:tags":[
        "machine",
        "sewing"
    ],
    "wof:name":"Barry W Brown Sewing Machine",
    "wof:placetype":"venue"
},
  "geometry": {"coordinates":[-84.57526,39.260347],"type":"Point"}
}