{
  "type": "Feature",
  "properties": {
    "addr:full":"1179 W Church St Newark OH 43055",
    "addr:housenumber":"1179",
    "addr:postcode":"43055",
    "addr:street":"W Church St",
    "iso:country":"US",
    "sg:address":"1179 W Church St",
    "sg:city":"Newark",
    "sg:classifiers":[
        {
            "category":"Personal",
            "subcategory":"Beauty Salon",
            "type":"Services"
        }
    ],
    "sg:phone":"+1 740 344 4158",
    "sg:postcode":"43055",
    "sg:province":"OH",
    "wof:name":"Sun Teasers",
    "wof:placetype":"venue"
},
  "geometry": {"coordinates":[-82.44571500000001,40.058205],"type":"Point"}
}