{
  "type": "Feature",
  "properties": {
    "addr:full":"812 Chandler Dr Dayton OH 45426",
    "addr:housenumber":"812",
    "addr:postcode":"45426",
    "addr:street":"Chandler Dr",
    "iso:country":"US",
    "sg:address":"812 Chandler Dr",
    "sg:city":"Dayton",
    "sg:classifiers":[
        {
            "category":"Personal",
            "subcategory":"Beauty Salon",
            "type":"Services"
        }
    ],
    "sg:phone":"+1 937 854 2853",
    "sg:postcode":"45426",
    "sg:province":"OH",
    "wof:name":"Myrtle's Style-O-Rama",
    "wof:placetype":"venue"
},
  "geometry": {"coordinates":[-84.29621299999999,39.805073],"type":"Point"}
}