{
  "type": "Feature",
  "properties": {
    "addr:full":"4084 S Ridge Rd Perry OH 44081",
    "addr:housenumber":"4084",
    "addr:postcode":"44081",
    "addr:street":"S Ridge Rd",
    "iso:country":"US",
    "sg:address":"4084 S Ridge Rd",
    "sg:city":"Perry",
    "sg:classifiers":[
        {
            "category":"Wholesale",
            "subcategory":"Scrap",
            "type":"Manufacturing & Wholesale Goods"
        }
    ],
    "sg:phone":"+1 440 259 2837",
    "sg:postcode":"44081",
    "sg:province":"OH",
    "sg:tags":[
        "metal",
        "iron"
    ],
    "wof:name":"Estell Inc",
    "wof:placetype":"venue"
},
  "geometry": {"coordinates":[-81.142428,41.745927],"type":"Point"}
}