{
  "type": "Feature",
  "properties": {
    "addr:full": "2056 Oldtown Valley Rd SE New Philadelphia OH 44663",
    "addr:housenumber": "2056",
    "addr:postcode": "44663",
    "addr:street": "Oldtown Valley Rd Se New",
    "iso:country": "US",
    "sg:address": "2056 Oldtown Valley Rd SE",
    "sg:city": "New Philadelphia",
    "sg:classifiers": [
      {
        "category": "Real Estate",
        "subcategory": "Real Estate Agent",
        "type": "Services"
      }
    ],
    "sg:phone": "+1 330 339 2131",
    "sg:postcode": "44663",
    "sg:province": "OH",
    "wof:name": "Frederick Allen Kinsey",
    "wof:placetype": "venue"
  },
  "geometry": {"coordinates":[-81.454064,40.451785],"type":"Point"}
}
