{
  "type": "Feature",
  "properties": {
    "iso:country":"US",
    "sg:address":"2318 Taymouth Rd",
    "sg:city":"Columbus",
    "sg:classifiers":[
        {
            "category":"Shopping",
            "type":"Retail Goods"
        }
    ],
    "sg:phone":"+1 614 476 6480",
    "sg:postcode":"43229",
    "sg:province":"OH",
    "sg:tags":[
        "equipment",
        "miscellaneous",
        "supply"
    ],
    "wof:name":"Musical Microlith",
    "wof:placetype":"venue"
},
  "geometry": {"coordinates":[-82.956543,40.066404],"type":"Point"}
}