{
  "type": "Feature",
  "properties": {
    "iso:country":"US",
    "sg:address":"3200 E Broad St",
    "sg:city":"Columbus",
    "sg:classifiers":[
        {
            "category":"Banks & Credit Unions",
            "subcategory":"Bank",
            "type":"Services"
        }
    ],
    "sg:phone":"+1 614 248 2460",
    "sg:postcode":"43209",
    "sg:province":"OH",
    "wof:name":"Chase",
    "wof:placetype":"venue"
},
  "geometry": {"coordinates":[-82.91493699999999,39.971908],"type":"Point"}
}