{
  "type": "Feature",
  "properties": {
    "addr:full": "3200 E Broad St Columbus OH 43209",
    "addr:housenumber": "3200",
    "addr:postcode": "43209",
    "addr:street": "E Broad St",
    "iso:country": "US",
    "sg:address": "3200 E Broad St",
    "sg:city": "Columbus",
    "sg:classifiers": [
      {
        "category": "Banks \u0026 Credit Unions",
        "subcategory": "Bank",
        "type": "Services"
      }
    ],
    "sg:phone": "+1 614 248 2460",
    "sg:postcode": "43209",
    "sg:province": "OH",
    "wof:name": "Chase",
    "wof:placetype": "venue"
  },
  "geometry": {"coordinates":[-82.914937,39.971908],"type":"Point"}
}
