{
  "type": "Feature",
  "properties": {
    "iso:country":"US",
    "sg:address":"112 S Miami Ave",
    "sg:city":"Cleves",
    "sg:classifiers":[
        {
            "category":"Government",
            "subcategory":"Office",
            "type":"Public Place"
        }
    ],
    "sg:phone":"+1 513 941 2890",
    "sg:postcode":"45002",
    "sg:province":"OH",
    "sg:tags":[
        "village"
    ],
    "wof:name":"Miami Township Hall",
    "wof:placetype":"venue"
},
  "geometry": {"coordinates":[-84.749602,39.159963],"type":"Point"}
}