{
  "type": "Feature",
  "properties": {
    "addr:full":"8050 Ohio River Rd Wheelersburg OH 45694",
    "addr:housenumber":"8050",
    "addr:postcode":"45694",
    "addr:street":"Ohio River Rd",
    "iso:country":"US",
    "sg:address":"8050 Ohio River Rd",
    "sg:city":"Wheelersburg",
    "sg:classifiers":[
        {
            "category":"Insurance",
            "subcategory":"Insurance Agent",
            "type":"Services"
        }
    ],
    "sg:phone":"+1 740 574 9500",
    "sg:postcode":"45694",
    "sg:province":"OH",
    "wof:name":"State Farm Insurance",
    "wof:placetype":"venue"
},
  "geometry": {"coordinates":[-82.85950200000001,38.731574],"type":"Point"}
}