{
  "type": "Feature",
  "properties": {
    "addr:full": "1171 Gorge Blvd Akron OH 44310",
    "addr:housenumber": "1171",
    "addr:postcode": "44310",
    "addr:street": "Gorge Blvd",
    "iso:country": "US",
    "sg:address": "1171 Gorge Blvd",
    "sg:city": "Akron",
    "sg:classifiers": [
      {
        "category": "Building \u0026 Trades",
        "subcategory": "Cleaning \u0026 Sanitation",
        "type": "Services"
      }
    ],
    "sg:phone": "+1 330 928 9089",
    "sg:postcode": "44310",
    "sg:province": "OH",
    "sg:tags": [
      "janitor",
      "maintenance"
    ],
    "wof:name": "Richards Cleaning Service",
    "wof:placetype": "venue"
  },
  "geometry": {"coordinates":[-81.497149,41.108215],"type":"Point"}
}
