{
  "type": "Feature",
  "properties": {
    "iso:country":"US",
    "sg:address":"1171 Gorge Blvd",
    "sg:city":"Akron",
    "sg:classifiers":[
        {
            "category":"Building & Trades",
            "subcategory":"Cleaning & Sanitation",
            "type":"Services"
        }
    ],
    "sg:phone":"+1 330 928 9089",
    "sg:postcode":"44310",
    "sg:province":"OH",
    "sg:tags":[
        "janitor",
        "maintenance"
    ],
    "wof:name":"Richards Cleaning Service",
    "wof:placetype":"venue"
},
  "geometry": {"coordinates":[-81.49714899999999,41.108215],"type":"Point"}
}