{
  "type": "Feature",
  "properties": {
    "addr:full": "5549 Salem Ave Trotwood OH 45426",
    "addr:housenumber": "5549",
    "addr:postcode": "45426",
    "addr:street": "Salem Ave",
    "iso:country": "US",
    "sg:address": "5549 Salem Ave",
    "sg:city": "Trotwood",
    "sg:classifiers": [
      {
        "category": "Shopping",
        "subcategory": "Clothing, Apparel, \u0026 Fashions",
        "type": "Retail Goods"
      }
    ],
    "sg:phone": "+1 937 837 8004",
    "sg:postcode": "45426",
    "sg:province": "OH",
    "sg:tags": [
      "sportswear"
    ],
    "wof:name": "TNT Fashions",
    "wof:placetype": "venue"
  },
  "geometry": {"coordinates":[-84.291703,39.825322],"type":"Point"}
}
