{
  "type": "Feature",
  "properties": {
    "iso:country":"US",
    "sg:address":"1 S 2nd St",
    "sg:city":"Ripley",
    "sg:classifiers":[
        {
            "category":"Professional",
            "type":"Services"
        }
    ],
    "sg:phone":"+1 937 392 1555",
    "sg:postcode":"45167",
    "sg:province":"OH",
    "sg:tags":[
        "establishment"
    ],
    "wof:name":"Super Dave's",
    "wof:placetype":"venue"
},
  "geometry": {"coordinates":[-83.845258,38.745577],"type":"Point"}
}