{
  "type": "Feature",
  "properties": {
    "addr:full": "1110 Mount Vernon Rd Newark OH 43055",
    "addr:housenumber": "1110",
    "addr:postcode": "43055",
    "addr:street": "Mount Vernon Rd",
    "iso:country": "US",
    "sg:address": "1110 Mount Vernon Rd",
    "sg:city": "Newark",
    "sg:classifiers": [
      {
        "category": "Freight",
        "type": "Transportation"
      }
    ],
    "sg:phone": "+1 740 366 3105",
    "sg:postcode": "43055",
    "sg:province": "OH",
    "sg:tags": [
      "commercial",
      "storage"
    ],
    "wof:name": "J \u0026 D Storage",
    "wof:placetype": "venue"
  },
  "geometry": {"coordinates":[-82.418229,40.086621],"type":"Point"}
}
