{
  "type": "Feature",
  "properties": {
    "addr:full": "602 W Ervin Rd Van Wert OH 45891",
    "addr:housenumber": "602",
    "addr:postcode": "45891",
    "addr:street": "W Ervin Rd",
    "iso:country": "US",
    "sg:address": "602 W Ervin Rd",
    "sg:city": "Van Wert",
    "sg:classifiers": [
      {
        "category": "Autos \u0026 Motor Vehicles",
        "subcategory": "Auto Supplies",
        "type": "Retail Goods"
      }
    ],
    "sg:phone": "+1 419 238 1137",
    "sg:postcode": "45891",
    "sg:province": "OH",
    "sg:tags": [
      "automobile",
      "parts"
    ],
    "wof:name": "Carquest Auto Parts",
    "wof:placetype": "venue"
  },
  "geometry": {"coordinates":[-84.591152,40.858807],"type":"Point"}
}
