{
  "type": "Feature",
  "properties": {
    "iso:country":"US",
    "sg:address":"109 E Grant Ave",
    "sg:city":"Georgetown",
    "sg:classifiers":[
        {
            "category":"Shopping",
            "subcategory":"Florist",
            "type":"Retail Goods"
        }
    ],
    "sg:phone":"+1 937 378 3215",
    "sg:postcode":"45121",
    "sg:province":"OH",
    "wof:name":"A Georgetown Florist",
    "wof:placetype":"venue"
},
  "geometry": {"coordinates":[-83.904302,38.866075],"type":"Point"}
}