{
  "type": "Feature",
  "properties": {
    "iso:country":"US",
    "sg:address":"5674 State Rte 193",
    "sg:city":"Andover",
    "sg:classifiers":[
        {
            "category":"Building & Trades",
            "subcategory":"Plumbing",
            "type":"Services"
        }
    ],
    "sg:phone":"+1 440 293 7005",
    "sg:postcode":"44003",
    "sg:province":"OH",
    "sg:tags":[
        "tank",
        "septic"
    ],
    "wof:name":"Ohio Aeration Inc",
    "wof:placetype":"venue"
},
  "geometry": {"coordinates":[-80.66628900000001,41.593791],"type":"Point"}
}