{
  "type": "Feature",
  "properties": {
    "addr:full": "5674 State Rte 193 Andover OH 44003",
    "addr:housenumber": "5674",
    "addr:postcode": "44003",
    "addr:street": "State Rte 193",
    "iso:country": "US",
    "sg:address": "5674 State Rte 193",
    "sg:city": "Andover",
    "sg:classifiers": [
      {
        "category": "Building \u0026 Trades",
        "subcategory": "Plumbing",
        "type": "Services"
      }
    ],
    "sg:phone": "+1 440 293 7005",
    "sg:postcode": "44003",
    "sg:province": "OH",
    "sg:tags": [
      "tank",
      "septic"
    ],
    "wof:name": "Ohio Aeration Inc",
    "wof:placetype": "venue"
  },
  "geometry": {"coordinates":[-80.666289,41.593791],"type":"Point"}
}
