{
  "type": "Feature",
  "properties": {
    "iso:country":"US",
    "sg:address":"6936 Fieldbrook Dr",
    "sg:city":"Springfield",
    "sg:classifiers":[
        {
            "category":"Building & Trades",
            "subcategory":"Construction",
            "type":"Services"
        }
    ],
    "sg:phone":"+1 937 390 0908",
    "sg:postcode":"45502",
    "sg:province":"OH",
    "sg:tags":[
        "fire",
        "restoration",
        "damage"
    ],
    "wof:name":"Magic Master",
    "wof:placetype":"venue"
},
  "geometry": {"coordinates":[-83.77769,40.024522],"type":"Point"}
}