{
  "type": "Feature",
  "properties": {
    "iso:country":"US",
    "sg:address":"21 S 6th St",
    "sg:city":"Zanesville",
    "sg:classifiers":[
        {
            "category":"Professional",
            "subcategory":"Accounting & Tax Preparation",
            "type":"Services"
        }
    ],
    "sg:phone":"+1 740 455 3443",
    "sg:postcode":"43701",
    "sg:province":"OH",
    "sg:tags":[
        "return",
        "filing"
    ],
    "wof:name":"Jackson Hewitt Tax Svc",
    "wof:placetype":"venue"
},
  "geometry": {"coordinates":[-82.00529899999999,39.9397],"type":"Point"}
}