{
  "type": "Feature",
  "properties": {
    "addr:full": "21 S 6th St Zanesville OH 43701",
    "addr:housenumber": "21",
    "addr:postcode": "43701",
    "addr:street": "S 6Th St",
    "iso:country": "US",
    "sg:address": "21 S 6th St",
    "sg:city": "Zanesville",
    "sg:classifiers": [
      {
        "category": "Professional",
        "subcategory": "Accounting \u0026 Tax Preparation",
        "type": "Services"
      }
    ],
    "sg:phone": "+1 740 455 3443",
    "sg:postcode": "43701",
    "sg:province": "OH",
    "sg:tags": [
      "return",
      "filing"
    ],
    "wof:name": "Jackson Hewitt Tax Svc",
    "wof:placetype": "venue"
  },
  "geometry": {"coordinates":[-82.005299,39.9397],"type":"Point"}
}
