{
  "type": "Feature",
  "properties": {
    "addr:full": "5555 N Marginal Rd Cleveland OH 44114",
    "addr:housenumber": "5555",
    "addr:postcode": "44114",
    "addr:street": "N Marginal Rd",
    "iso:country": "US",
    "sg:address": "5555 N Marginal Rd",
    "sg:city": "Cleveland",
    "sg:classifiers": [
      {
        "category": "Recreation",
        "subcategory": "Marina",
        "type": "Entertainment"
      }
    ],
    "sg:phone": "+1 216 391 5566",
    "sg:postcode": "44114",
    "sg:province": "OH",
    "wof:name": "East 55th St Marina",
    "wof:placetype": "venue"
  },
  "geometry": {"coordinates":[-81.652048,41.530899],"type":"Point"}
}
