{
  "type": "Feature",
  "properties": {
    "addr:full": "1299 W 5th St Marysville OH 43040",
    "addr:housenumber": "1299",
    "addr:postcode": "43040",
    "addr:street": "W 5Th St",
    "iso:country": "US",
    "sg:address": "1299 W 5th St",
    "sg:city": "Marysville",
    "sg:classifiers": [
      {
        "category": "Building \u0026 Trades",
        "subcategory": "Equipment Rental",
        "type": "Services"
      }
    ],
    "sg:phone": "+1 937 644 2911",
    "sg:postcode": "43040",
    "sg:province": "OH",
    "sg:tags": [
      "yard"
    ],
    "wof:name": "McAuliffes Ace Rental Place",
    "wof:placetype": "venue"
  },
  "geometry": {"coordinates":[-83.388733,40.240648],"type":"Point"}
}
