{
  "type": "Feature",
  "properties": {
    "addr:full":"576 Moore Dr Campbell OH 44405",
    "addr:housenumber":"576",
    "addr:postcode":"44405",
    "addr:street":"Moore Dr",
    "iso:country":"US",
    "sg:address":"576 Moore Dr",
    "sg:city":"Campbell",
    "sg:classifiers":[
        {
            "category":"Building & Trades",
            "subcategory":"Construction",
            "type":"Services"
        }
    ],
    "sg:phone":"+1 330 750 9441",
    "sg:postcode":"44405",
    "sg:province":"OH",
    "sg:tags":[
        "painter"
    ],
    "wof:name":"A 1 Ind Maintenance & Painting",
    "wof:placetype":"venue"
},
  "geometry": {"coordinates":[-80.5925,41.085088],"type":"Point"}
}