{
  "type": "Feature",
  "properties": {
    "addr:full":"1952 W Sylvania Ave Toledo OH 43613",
    "addr:housenumber":"1952",
    "addr:postcode":"43613",
    "addr:street":"W Sylvania Ave",
    "iso:country":"US",
    "sg:address":"1952 W Sylvania Ave",
    "sg:city":"Toledo",
    "sg:classifiers":[
        {
            "category":"Building & Trades",
            "subcategory":"Electrical",
            "type":"Services"
        }
    ],
    "sg:phone":"+1 419 472 6911",
    "sg:postcode":"43613",
    "sg:province":"OH",
    "sg:tags":[
        "electrical",
        "contractor"
    ],
    "wof:name":"King Electric Inc",
    "wof:placetype":"venue"
},
  "geometry": {"coordinates":[-83.592366,41.692334],"type":"Point"}
}