{
  "type": "Feature",
  "properties": {
    "addr:full":"7804 Glenwood Cir Cleveland OH 44147",
    "addr:housenumber":"7804",
    "addr:postcode":"44147",
    "addr:street":"Glenwood Cir",
    "iso:country":"US",
    "sg:address":"7804 Glenwood Cir",
    "sg:city":"Cleveland",
    "sg:classifiers":[
        {
            "category":"Shopping",
            "subcategory":"Florist",
            "type":"Retail Goods"
        }
    ],
    "sg:phone":"+1 440 884 8608",
    "sg:postcode":"44147",
    "sg:province":"OH",
    "wof:name":"Present Co",
    "wof:placetype":"venue"
},
  "geometry": {"coordinates":[-81.695123,41.325343],"type":"Point"}
}