{
  "type": "Feature",
  "properties": {
    "addr:full":"1279 Lyons Rd Dayton OH 45458",
    "addr:housenumber":"1279",
    "addr:postcode":"45458",
    "addr:street":"Lyons Rd",
    "iso:country":"US",
    "sg:address":"1279 Lyons Rd",
    "sg:city":"Dayton",
    "sg:classifiers":[
        {
            "category":"Real Estate",
            "subcategory":"Real Estate Agent",
            "type":"Services"
        }
    ],
    "sg:phone":"+1 937 435 6442",
    "sg:postcode":"45458",
    "sg:province":"OH",
    "sg:tags":[
        "consultant"
    ],
    "wof:name":"Jonathan Co",
    "wof:placetype":"venue"
},
  "geometry": {"coordinates":[-84.195306,39.626482],"type":"Point"}
}