{
  "type": "Feature",
  "properties": {
    "addr:full":"673 W Turkeyfoot Lake Rd Akron OH 44319",
    "addr:housenumber":"673",
    "addr:postcode":"44319",
    "addr:street":"W Turkeyfoot Lake Rd",
    "iso:country":"US",
    "sg:address":"673 W Turkeyfoot Lake Rd",
    "sg:city":"Akron",
    "sg:classifiers":[
        {
            "category":"Health Services",
            "subcategory":"Chiropractor",
            "type":"Services"
        }
    ],
    "sg:phone":"+1 330 256 3308",
    "sg:postcode":"44319",
    "sg:province":"OH",
    "wof:name":"Akron Chiropractic Clinic",
    "wof:placetype":"venue"
},
  "geometry": {"coordinates":[-81.542976,40.981874],"type":"Point"}
}