{
  "type": "Feature",
  "properties": {
    "addr:full": "12596 Chillicothe Rd Chesterland OH 44026",
    "addr:housenumber": "12596",
    "addr:postcode": "44026",
    "addr:street": "Chillicothe Rd",
    "iso:country": "US",
    "sg:address": "12596 Chillicothe Rd",
    "sg:city": "Chesterland",
    "sg:classifiers": [
      {
        "category": "Social Services",
        "subcategory": "Child Care",
        "type": "Services"
      }
    ],
    "sg:phone": "+1 440 729 7567",
    "sg:postcode": "44026",
    "sg:province": "OH",
    "wof:name": "Miss Pat's Day Care Ctr I",
    "wof:placetype": "venue"
  },
  "geometry": {"coordinates":[-81.337992,41.526154],"type":"Point"}
}
