{
  "type": "Feature",
  "properties": {
    "iso:country":"US",
    "sg:address":"1364 E High Ave",
    "sg:city":"New Philadelphia",
    "sg:classifiers":[
        {
            "category":"Health Services",
            "subcategory":"Clinic",
            "type":"Services"
        }
    ],
    "sg:phone":"+1 330 339 9030",
    "sg:postcode":"44663",
    "sg:province":"OH",
    "sg:tags":[
        "home"
    ],
    "wof:name":"All American Home Health Care",
    "wof:placetype":"venue"
},
  "geometry": {"coordinates":[-81.425736,40.47831],"type":"Point"}
}