{
  "type": "Feature",
  "properties": {
    "iso:country":"US",
    "sg:address":"1825 State Rte 19",
    "sg:city":"Fremont",
    "sg:classifiers":[
        {
            "category":"Shopping",
            "subcategory":"Computers & Home Electronics",
            "type":"Retail Goods"
        }
    ],
    "sg:phone":"+1 419 355 0024",
    "sg:postcode":"43420",
    "sg:province":"OH",
    "sg:tags":[
        "equipment",
        "electronic",
        "supply"
    ],
    "wof:name":"Fundt Transfer Electronic",
    "wof:placetype":"venue"
},
  "geometry": {"coordinates":[-83.050884,41.293185],"type":"Point"}
}