{
  "type": "Feature",
  "properties": {
    "addr:full": "1825 State Rte 19 Fremont OH 43420",
    "addr:housenumber": "1825",
    "addr:postcode": "43420",
    "addr:street": "State Rte 19",
    "iso:country": "US",
    "sg:address": "1825 State Rte 19",
    "sg:city": "Fremont",
    "sg:classifiers": [
      {
        "category": "Shopping",
        "subcategory": "Computers \u0026 Home Electronics",
        "type": "Retail Goods"
      }
    ],
    "sg:phone": "+1 419 355 0024",
    "sg:postcode": "43420",
    "sg:province": "OH",
    "sg:tags": [
      "equipment",
      "electronic",
      "supply"
    ],
    "wof:name": "Fundt Transfer Electronic",
    "wof:placetype": "venue"
  },
  "geometry": {"coordinates":[-83.050884,41.293185],"type":"Point"}
}
