{
  "type": "Feature",
  "properties": {
    "addr:full": "120 Maple St Wadsworth OH 44281",
    "addr:housenumber": "120",
    "addr:postcode": "44281",
    "addr:street": "Maple St",
    "iso:country": "US",
    "sg:address": "120 Maple St",
    "sg:city": "Wadsworth",
    "sg:classifiers": [
      {
        "category": "Government",
        "subcategory": "Office",
        "type": "Public Place"
      }
    ],
    "sg:phone": "+1 330 335 2700",
    "sg:postcode": "44281",
    "sg:province": "OH",
    "sg:tags": [
      "govt",
      "city"
    ],
    "wof:name": "Wadsworth City Utility Billing",
    "wof:placetype": "venue"
  },
  "geometry": {"coordinates":[-81.728631,41.026963],"type":"Point"}
}
