{
  "type": "Feature",
  "properties": {
    "iso:country":"US",
    "sg:address":"1956 South Ave",
    "sg:city":"Marion",
    "sg:classifiers":[
        {
            "category":"Professional",
            "subcategory":"Business Services",
            "type":"Services"
        }
    ],
    "sg:phone":"+1 740 383 6484",
    "sg:postcode":"43302",
    "sg:province":"OH",
    "sg:tags":[
        "auctioneer"
    ],
    "wof:name":"James J Denton Auctioneer",
    "wof:placetype":"venue"
},
  "geometry": {"coordinates":[-83.077887,40.635519],"type":"Point"}
}