{
  "type": "Feature",
  "properties": {
    "addr:full":"5050 Blazer Pkwy Dublin OH 43017",
    "addr:housenumber":"5050",
    "addr:postcode":"43017",
    "addr:street":"Blazer Pkwy",
    "iso:country":"US",
    "sg:address":"5050 Blazer Pkwy",
    "sg:city":"Dublin",
    "sg:classifiers":[
        {
            "category":"Health Services",
            "subcategory":"Doctor",
            "type":"Services"
        }
    ],
    "sg:phone":"+1 614 761 1408",
    "sg:postcode":"43017",
    "sg:province":"OH",
    "sg:tags":[
        "dentist"
    ],
    "wof:name":"John E Duckworth DDS",
    "wof:placetype":"venue"
},
  "geometry": {"coordinates":[-83.128101,40.075799],"type":"Point"}
}