{
  "type": "Feature",
  "properties": {
    "iso:country":"US",
    "sg:address":"336 W Oak St",
    "sg:city":"Union City",
    "sg:classifiers":[
        {
            "category":"Cinema",
            "subcategory":"Movie Rental",
            "type":"Entertainment"
        }
    ],
    "sg:phone":"+1 765 964 6608",
    "sg:postcode":"47390",
    "sg:province":"OH",
    "sg:tags":[
        "leasing",
        "video",
        "disc",
        "tape"
    ],
    "wof:name":"K & K Video",
    "wof:placetype":"venue"
},
  "geometry": {"coordinates":[-84.808919,40.200045],"type":"Point"}
}