{
  "type": "Feature",
  "properties": {
    "addr:full": "567 Tionda Dr N Vandalia OH 45377",
    "addr:housenumber": "567",
    "addr:postcode": "45377",
    "addr:street": "Tionda Dr N",
    "iso:country": "US",
    "sg:address": "567 Tionda Dr N",
    "sg:city": "Vandalia",
    "sg:classifiers": [
      {
        "category": "Building \u0026 Trades",
        "subcategory": "Plumbing",
        "type": "Services"
      }
    ],
    "sg:phone": "+1 937 898 6386",
    "sg:postcode": "45377",
    "sg:province": "OH",
    "sg:tags": [
      "plumbing",
      "contractor"
    ],
    "wof:name": "Big EDS Plumbing LLC",
    "wof:placetype": "venue"
  },
  "geometry": {"coordinates":[-84.190999,39.890396],"type":"Point"}
}
