{
  "type": "Feature",
  "properties": {
    "iso:country":"US",
    "sg:address":"567 Tionda Dr N",
    "sg:city":"Vandalia",
    "sg:classifiers":[
        {
            "category":"Building & Trades",
            "subcategory":"Plumbing",
            "type":"Services"
        }
    ],
    "sg:phone":"+1 937 898 6386",
    "sg:postcode":"45377",
    "sg:province":"OH",
    "sg:tags":[
        "plumbing",
        "contractor"
    ],
    "wof:name":"Big EDS Plumbing LLC",
    "wof:placetype":"venue"
},
  "geometry": {"coordinates":[-84.19099900000001,39.890396],"type":"Point"}
}