{
  "type": "Feature",
  "properties": {
    "addr:full":"2250 Beechmont Ave Cincinnati OH 45230",
    "addr:housenumber":"2250",
    "addr:postcode":"45230",
    "addr:street":"Beechmont Ave",
    "iso:country":"US",
    "sg:address":"2250 Beechmont Ave",
    "sg:city":"Cincinnati",
    "sg:classifiers":[
        {
            "category":"Banks & Credit Unions",
            "subcategory":"Investment Brokerage",
            "type":"Services"
        }
    ],
    "sg:phone":"+1 513 624 9300",
    "sg:postcode":"45230",
    "sg:province":"OH",
    "sg:tags":[
        "advisory",
        "financial"
    ],
    "wof:name":"Jabin Fossett Advisory Group",
    "wof:placetype":"venue"
},
  "geometry": {"coordinates":[-84.387117,39.096053],"type":"Point"}
}