{
  "type": "Feature",
  "properties": {
    "addr:full": "5800 Monroe St Sylvania OH 43560",
    "addr:housenumber": "5800",
    "addr:postcode": "43560",
    "addr:street": "Monroe St",
    "iso:country": "US",
    "sg:address": "5800 Monroe St",
    "sg:city": "Sylvania",
    "sg:classifiers": [
      {
        "category": "Health Services",
        "subcategory": "Doctor",
        "type": "Services"
      }
    ],
    "sg:phone": "+1 419 885 8449",
    "sg:postcode": "43560",
    "sg:province": "OH",
    "sg:tags": [
      "medical"
    ],
    "wof:name": "REA \u0026 Associates",
    "wof:placetype": "venue"
  },
  "geometry": {"coordinates":[-83.684654,41.714327],"type":"Point"}
}
