{
  "type": "Feature",
  "properties": {
    "addr:full": "1612 Lancaster Ave Reynoldsburg OH 43068",
    "addr:housenumber": "1612",
    "addr:postcode": "43068",
    "addr:street": "Lancaster Ave",
    "iso:country": "US",
    "sg:address": "1612 Lancaster Ave",
    "sg:city": "Reynoldsburg",
    "sg:classifiers": [
      {
        "category": "Building \u0026 Trades",
        "subcategory": "Construction",
        "type": "Services"
      }
    ],
    "sg:phone": "+1 614 866 9667",
    "sg:postcode": "43068",
    "sg:province": "OH",
    "sg:tags": [
      "contractor"
    ],
    "wof:name": "Providence Building \u0026 Develop",
    "wof:placetype": "venue"
  },
  "geometry": {"coordinates":[-82.7996,39.951014],"type":"Point"}
}
