{
  "type": "Feature",
  "properties": {
    "iso:country":"US",
    "sg:address":"1155 W Mound St",
    "sg:city":"Columbus",
    "sg:classifiers":[
        {
            "category":"Government",
            "subcategory":"Office",
            "type":"Public Place"
        }
    ],
    "sg:phone":"+1 614 462 5250",
    "sg:postcode":"43223",
    "sg:province":"OH",
    "sg:website":"www.clippersbaseball.com",
    "wof:name":"Columbus Clippers",
    "wof:placetype":"venue"
},
  "geometry": {"coordinates":[-83.028256,39.94782],"type":"Point"}
}