{
  "type": "Feature",
  "properties": {
    "iso:country":"US",
    "sg:address":"1801 Vine St",
    "sg:city":"Cincinnati",
    "sg:classifiers":[
        {
            "category":"Shopping",
            "subcategory":"Shoes",
            "type":"Retail Goods"
        }
    ],
    "sg:phone":"+1 513 621 5362",
    "sg:postcode":"45202",
    "sg:province":"OH",
    "wof:name":"Lena's Shoebilie",
    "wof:placetype":"venue"
},
  "geometry": {"coordinates":[-84.516706,39.115984],"type":"Point"}
}