{
  "type": "Feature",
  "properties": {
    "addr:full":"2934 Sleepy Hollow Rd Brunswick OH 44212",
    "addr:housenumber":"2934",
    "addr:postcode":"44212",
    "addr:street":"Sleepy Hollow Rd",
    "iso:country":"US",
    "sg:address":"2934 Sleepy Hollow Rd",
    "sg:city":"Brunswick",
    "sg:classifiers":[
        {
            "category":"Food & Beverages",
            "subcategory":"Specialty",
            "type":"Retail Goods"
        }
    ],
    "sg:phone":"+1 216 276 0222",
    "sg:postcode":"44212",
    "sg:province":"OH",
    "sg:tags":[
        "lawn",
        "garden",
        "supply"
    ],
    "wof:name":"Urban Organics Inc",
    "wof:placetype":"venue"
},
  "geometry": {"coordinates":[-81.789002,41.215317],"type":"Point"}
}