{
  "type": "Feature",
  "properties": {
    "addr:full": "1936 Rosebery Dr Columbus OH 43220",
    "addr:housenumber": "1936",
    "addr:postcode": "43220",
    "addr:street": "Rosebery Dr",
    "iso:country": "US",
    "sg:address": "1936 Rosebery Dr",
    "sg:city": "Columbus",
    "sg:classifiers": [
      {
        "category": "Professional",
        "type": "Services"
      }
    ],
    "sg:phone": "+1 614 457 2008",
    "sg:postcode": "43220",
    "sg:province": "OH",
    "wof:name": "Ng Family Ltd",
    "wof:placetype": "venue"
  },
  "geometry": {"coordinates":[-83.0754,40.049607],"type":"Point"}
}
