{
  "type": "Feature",
  "properties": {
    "iso:country":"US",
    "sg:address":"3912 E Galbraith Rd",
    "sg:city":"Cincinnati",
    "sg:classifiers":[
        {
            "category":"Banks & Credit Unions",
            "subcategory":"Bank",
            "type":"Services"
        }
    ],
    "sg:phone":"+1 513 793 7400",
    "sg:postcode":"45236",
    "sg:province":"OH",
    "wof:name":"Pnc Bank",
    "wof:placetype":"venue"
},
  "geometry": {"coordinates":[-84.402299,39.208768],"type":"Point"}
}