{
  "type": "Feature",
  "properties": {
    "addr:full":"2310 South Ave Toledo OH 43609",
    "addr:housenumber":"2310",
    "addr:postcode":"43609",
    "addr:street":"South Ave",
    "iso:country":"US",
    "sg:address":"2310 South Ave",
    "sg:city":"Toledo",
    "sg:classifiers":[
        {
            "category":"Building & Trades",
            "subcategory":"Construction",
            "type":"Services"
        }
    ],
    "sg:phone":"+1 419 476 1997",
    "sg:postcode":"43609",
    "sg:province":"OH",
    "sg:tags":[
        "repairing",
        "remodeling",
        "contractor"
    ],
    "wof:name":"James Allen Remodeling LTD",
    "wof:placetype":"venue"
},
  "geometry": {"coordinates":[-83.601939,41.630741],"type":"Point"}
}