{
  "type": "Feature",
  "properties": {
    "addr:full": "31 Erie Rd Tallmadge OH 44278",
    "addr:housenumber": "31",
    "addr:postcode": "44278",
    "addr:street": "Erie Rd",
    "iso:country": "US",
    "sg:address": "31 Erie Rd",
    "sg:city": "Tallmadge",
    "sg:classifiers": [
      {
        "category": "Restaurant",
        "type": "Food \u0026 Drink"
      }
    ],
    "sg:menulink": "http://www.allmenus.com/oh/tallmadge/68810-marcos-pizza/menu/",
    "sg:phone": "+1 330 630 0000",
    "sg:postcode": "44278",
    "sg:province": "OH",
    "sg:tags": [
      "american",
      "pizza"
    ],
    "wof:name": "Marco's Pizza",
    "wof:placetype": "venue"
  },
  "geometry": {"coordinates":[-81.437582,41.100894],"type":"Point"}
}
