{
  "type": "Feature",
  "properties": {
    "addr:full": "10165 Catalpa St Byesville OH 43723",
    "addr:housenumber": "10165",
    "addr:postcode": "43723",
    "addr:street": "Catalpa St",
    "iso:country": "US",
    "sg:address": "10165 Catalpa St",
    "sg:city": "Byesville",
    "sg:classifiers": [
      {
        "category": "Farming",
        "subcategory": "Farm",
        "type": "Manufacturing \u0026 Wholesale Goods"
      }
    ],
    "sg:phone": "+1 740 432 2078",
    "sg:postcode": "43723",
    "sg:province": "OH",
    "sg:tags": [
      "crop",
      "general"
    ],
    "wof:name": "Robert May",
    "wof:placetype": "venue"
  },
  "geometry": {"coordinates":[-81.5549,39.984926],"type":"Point"}
}
