{
  "type": "Feature",
  "properties": {
    "iso:country":"US",
    "sg:address":"10165 Catalpa St",
    "sg:city":"Byesville",
    "sg:classifiers":[
        {
            "category":"Farming",
            "subcategory":"Farm",
            "type":"Manufacturing & Wholesale Goods"
        }
    ],
    "sg:phone":"+1 740 432 2078",
    "sg:postcode":"43723",
    "sg:province":"OH",
    "sg:tags":[
        "crop",
        "general"
    ],
    "wof:name":"Robert May",
    "wof:placetype":"venue"
},
  "geometry": {"coordinates":[-81.5549,39.984926],"type":"Point"}
}