{
  "type": "Feature",
  "properties": {
    "addr:full":"211 E Liberty St Wooster OH 44691",
    "addr:housenumber":"211",
    "addr:postcode":"44691",
    "addr:street":"E Liberty St",
    "iso:country":"US",
    "sg:address":"211 E Liberty St",
    "sg:city":"Wooster",
    "sg:classifiers":[
        {
            "category":"Shopping",
            "subcategory":"Jewelry",
            "type":"Retail Goods"
        }
    ],
    "sg:phone":"+1 330 264 3324",
    "sg:postcode":"44691",
    "sg:province":"OH",
    "sg:tags":[
        "precious",
        "j",
        "mfg"
    ],
    "wof:name":"White Jewelers",
    "wof:placetype":"venue"
},
  "geometry": {"coordinates":[-81.93759900000001,40.798486],"type":"Point"}
}