{
  "type": "Feature",
  "properties": {
    "addr:full": "110 Auburn St Shelby OH 44875",
    "addr:housenumber": "110",
    "addr:postcode": "44875",
    "addr:street": "Auburn St",
    "iso:country": "US",
    "sg:address": "110 Auburn St",
    "sg:city": "Shelby",
    "sg:classifiers": [
      {
        "category": "Health Services",
        "subcategory": "Doctor",
        "type": "Services"
      }
    ],
    "sg:phone": "+1 419 342 4242",
    "sg:postcode": "44875",
    "sg:province": "OH",
    "sg:tags": [
      "physician",
      "surgeon"
    ],
    "wof:name": "Ohio Medical Assoc",
    "wof:placetype": "venue"
  },
  "geometry": {"coordinates":[-82.673334,40.883405],"type":"Point"}
}
