{
  "type": "Feature",
  "properties": {
    "iso:country":"US",
    "sg:address":"1400 Grogan Ave",
    "sg:city":"Columbus",
    "sg:classifiers":[
        {
            "category":"Taxi",
            "type":"Transportation"
        }
    ],
    "sg:phone":"+1 614 486 2432",
    "sg:postcode":"43211",
    "sg:province":"OH",
    "sg:tags":[
        "taxicab"
    ],
    "wof:name":"Arlington-Grandview Cabs",
    "wof:placetype":"venue"
},
  "geometry": {"coordinates":[-82.989361,39.993302],"type":"Point"}
}