{
  "type": "Feature",
  "properties": {
    "addr:full": "4710 Meadow Crest Ln New Paris OH 45347",
    "addr:housenumber": "4710",
    "addr:postcode": "45347",
    "addr:street": "Meadow Crest Ln",
    "iso:country": "US",
    "sg:address": "4710 Meadow Crest Ln",
    "sg:city": "New Paris",
    "sg:classifiers": [
      {
        "category": "Building \u0026 Trades",
        "subcategory": "Construction",
        "type": "Services"
      }
    ],
    "sg:phone": "+1 937 437 8331",
    "sg:postcode": "45347",
    "sg:province": "OH",
    "sg:tags": [
      "contractor"
    ],
    "wof:name": "Bakers Custom Exterior",
    "wof:placetype": "venue"
  },
  "geometry": {"coordinates":[-84.810119,39.825262],"type":"Point"}
}
