{
  "type": "Feature",
  "properties": {
    "iso:country":"US",
    "sg:address":"6833 Angola Rd",
    "sg:city":"Holland",
    "sg:classifiers":[
        {
            "category":"Manufacturing",
            "subcategory":"Signs",
            "type":"Manufacturing & Wholesale Goods"
        }
    ],
    "sg:phone":"+1 419 861 3994",
    "sg:postcode":"43528",
    "sg:province":"OH",
    "sg:tags":[
        "specialty",
        "mfg"
    ],
    "wof:name":"Yard Signs",
    "wof:placetype":"venue"
},
  "geometry": {"coordinates":[-83.708686,41.624867],"type":"Point"}
}