{
  "type": "Feature",
  "properties": {
    "addr:full": "8121 Glynwood Rd Wapakoneta OH 45895",
    "addr:housenumber": "8121",
    "addr:postcode": "45895",
    "addr:street": "Glynwood Rd",
    "iso:country": "US",
    "sg:address": "8121 Glynwood Rd",
    "sg:city": "Wapakoneta",
    "sg:phone": "+1 419 738 4102",
    "sg:postcode": "45895",
    "sg:province": "OH",
    "sg:tags": [
      "farm",
      "corn",
      "dairy",
      "soybean"
    ],
    "wof:name": "PS Jerseys",
    "wof:placetype": "venue"
  },
  "geometry": {"coordinates":[-84.286501,40.579633],"type":"Point"}
}
