{
  "type": "Feature",
  "properties": {
    "addr:full":"5005 Rockside Rd Cleveland OH 44131",
    "addr:housenumber":"5005",
    "addr:postcode":"44131",
    "addr:street":"Rockside Rd",
    "iso:country":"US",
    "sg:address":"5005 Rockside Rd",
    "sg:city":"Cleveland",
    "sg:classifiers":[
        {
            "category":"Wholesale",
            "subcategory":"Chemicals & Plastics",
            "type":"Manufacturing & Wholesale Goods"
        }
    ],
    "sg:phone":"+1 514 931 7278",
    "sg:postcode":"44131",
    "sg:province":"OH",
    "sg:tags":[
        "import",
        "export"
    ],
    "wof:name":"Punda Mercantile Inc",
    "wof:placetype":"venue"
},
  "geometry": {"coordinates":[-81.65351,41.396943],"type":"Point"}
}