{
  "type": "Feature",
  "properties": {
    "addr:full":"3383 W 118th St Cleveland OH 44111",
    "addr:housenumber":"3383",
    "addr:postcode":"44111",
    "addr:street":"W 118Th St",
    "iso:country":"US",
    "sg:address":"3383 W 118th St",
    "sg:city":"Cleveland",
    "sg:classifiers":[
        {
            "category":"Real Estate",
            "subcategory":"Real Estate Agent",
            "type":"Services"
        }
    ],
    "sg:phone":"+1 216 688 1194",
    "sg:postcode":"44111",
    "sg:province":"OH",
    "wof:name":"Greater Cleveland Appraisals",
    "wof:placetype":"venue"
},
  "geometry": {"coordinates":[-81.769854,41.45974],"type":"Point"}
}