{
  "type": "Feature",
  "properties": {
    "addr:full": "505 Forestview Ct Circleville OH 43113",
    "addr:housenumber": "505",
    "addr:postcode": "43113",
    "addr:street": "Forestview Ct",
    "iso:country": "US",
    "sg:address": "505 Forestview Ct",
    "sg:city": "Circleville",
    "sg:classifiers": [
      {
        "category": "Shopping",
        "subcategory": "Used Merchandise",
        "type": "Retail Goods"
      }
    ],
    "sg:phone": "+1 740 474 8693",
    "sg:postcode": "43113",
    "sg:province": "OH",
    "wof:name": "Court Street Junction",
    "wof:placetype": "venue"
  },
  "geometry": {"coordinates":[-82.935546,39.607436],"type":"Point"}
}
