{
  "type": "Feature",
  "properties": {
    "addr:full": "6475 E Main St Reynoldsburg OH 43068",
    "addr:housenumber": "6475",
    "addr:postcode": "43068",
    "addr:street": "E Main St",
    "iso:country": "US",
    "sg:address": "6475 E Main St",
    "sg:city": "Reynoldsburg",
    "sg:classifiers": [
      {
        "category": "Building \u0026 Trades",
        "subcategory": "Construction",
        "type": "Services"
      }
    ],
    "sg:phone": "+1 614 577 9566",
    "sg:postcode": "43068",
    "sg:province": "OH",
    "sg:tags": [
      "roofing",
      "contractor"
    ],
    "wof:name": "Andrews Construction",
    "wof:placetype": "venue"
  },
  "geometry": {"coordinates":[-82.824301,39.954797],"type":"Point"}
}
