{
  "type": "Feature",
  "properties": {
    "iso:country":"US",
    "sg:address":"6475 E Main St",
    "sg:city":"Reynoldsburg",
    "sg:classifiers":[
        {
            "category":"Building & Trades",
            "subcategory":"Construction",
            "type":"Services"
        }
    ],
    "sg:phone":"+1 614 577 9566",
    "sg:postcode":"43068",
    "sg:province":"OH",
    "sg:tags":[
        "roofing",
        "contractor"
    ],
    "wof:name":"Andrews Construction",
    "wof:placetype":"venue"
},
  "geometry": {"coordinates":[-82.82430100000001,39.954797],"type":"Point"}
}