{
  "type": "Feature",
  "properties": {
    "iso:country":"US",
    "sg:address":"140 N Hamilton Rd",
    "sg:city":"Columbus",
    "sg:classifiers":[
        {
            "category":"Building & Trades",
            "subcategory":"Electrical",
            "type":"Services"
        }
    ],
    "sg:phone":"+1 614 858 0120",
    "sg:postcode":"43230",
    "sg:province":"OH",
    "sg:tags":[
        "integrator",
        "solution",
        "network",
        "provider"
    ],
    "wof:name":"Muzo Technologies Inc",
    "wof:placetype":"venue"
},
  "geometry": {"coordinates":[-82.866462,40.018362],"type":"Point"}
}