{
  "type": "Feature",
  "properties": {
    "addr:full": "27333 Detroit Rd Cleveland OH 44145",
    "addr:housenumber": "27333",
    "addr:postcode": "44145",
    "addr:street": "Detroit Rd",
    "iso:country": "US",
    "sg:address": "27333 Detroit Rd",
    "sg:city": "Cleveland",
    "sg:classifiers": [
      {
        "category": "Professional",
        "type": "Services"
      },
      {
        "category": "Restaurant",
        "type": "Food \u0026 Drink"
      }
    ],
    "sg:phone": "+1 440 617 9068",
    "sg:postcode": "44145",
    "sg:province": "OH",
    "wof:name": "Mandarian",
    "wof:placetype": "venue"
  },
  "geometry": {"coordinates":[-81.926165,41.46661],"type":"Point"}
}
