{
  "type": "Feature",
  "properties": {
    "addr:full":"140 Silvercreek Rd Wadsworth OH 44281",
    "addr:housenumber":"140",
    "addr:postcode":"44281",
    "addr:street":"Silvercreek Rd",
    "iso:country":"US",
    "sg:address":"140 Silvercreek Rd",
    "sg:city":"Wadsworth",
    "sg:classifiers":[
        {
            "category":"Building & Trades",
            "subcategory":"Construction",
            "type":"Services"
        }
    ],
    "sg:phone":"+1 330 336 7726",
    "sg:postcode":"44281",
    "sg:province":"OH",
    "sg:tags":[
        "house"
    ],
    "wof:name":"Kirvel Projects Inc",
    "wof:placetype":"venue"
},
  "geometry": {"coordinates":[-81.703942,41.02453],"type":"Point"}
}