{
  "type": "Feature",
  "properties": {
    "iso:country":"US",
    "sg:address":"1187 Twp Rd 1426",
    "sg:city":"Ashland",
    "sg:classifiers":[
        {
            "category":"Wholesale",
            "subcategory":"Stationery",
            "type":"Manufacturing & Wholesale Goods"
        }
    ],
    "sg:phone":"+1 419 281 9557",
    "sg:postcode":"44805",
    "sg:province":"OH",
    "sg:tags":[
        "paper"
    ],
    "wof:name":"Americraft Carton",
    "wof:placetype":"venue"
},
  "geometry": {"coordinates":[-82.36068899999999,40.857519],"type":"Point"}
}