{
  "type": "Feature",
  "properties": {
    "addr:full": "1312 Devereux Dr Dayton OH 45419",
    "addr:housenumber": "1312",
    "addr:postcode": "45419",
    "addr:street": "Devereux Dr",
    "iso:country": "US",
    "sg:address": "1312 Devereux Dr",
    "sg:city": "Dayton",
    "sg:classifiers": [
      {
        "category": "Professional",
        "subcategory": "Business Services",
        "type": "Services"
      }
    ],
    "sg:phone": "+1 937 297 1551",
    "sg:postcode": "45419",
    "sg:province": "OH",
    "sg:tags": [
      "interior",
      "consultant",
      "design",
      "decorator"
    ],
    "wof:name": "Lori Sowder Interiors",
    "wof:placetype": "venue"
  },
  "geometry": {"coordinates":[-84.174018,39.718377],"type":"Point"}
}
