{
  "type": "Feature",
  "properties": {
    "addr:full": "6272 Eagles Lake Dr Cincinnati OH 45248",
    "addr:housenumber": "6272",
    "addr:postcode": "45248",
    "addr:street": "Eagles Lake Dr",
    "iso:country": "US",
    "sg:address": "6272 Eagles Lake Dr",
    "sg:city": "Cincinnati",
    "sg:classifiers": [
      {
        "category": "Home \u0026 Garden",
        "subcategory": "Building Materials",
        "type": "Retail Goods"
      }
    ],
    "sg:phone": "+1 513 598 1046",
    "sg:postcode": "45248",
    "sg:province": "OH",
    "wof:name": "Ceint Ltd",
    "wof:placetype": "venue"
  },
  "geometry": {"coordinates":[-84.660996,39.186931],"type":"Point"}
}
