{
  "type": "Feature",
  "properties": {
    "iso:country":"US",
    "sg:address":"3200 Kettering Blvd",
    "sg:city":"Dayton",
    "sg:classifiers":[
        {
            "category":"Home & Garden",
            "subcategory":"Carpets & Floor Coverings",
            "type":"Retail Goods"
        }
    ],
    "sg:phone":"+1 937 866 6807",
    "sg:postcode":"45439",
    "sg:province":"OH",
    "sg:tags":[
        "material"
    ],
    "wof:name":"Capitol Flooring",
    "wof:placetype":"venue"
},
  "geometry": {"coordinates":[-84.206683,39.702304],"type":"Point"}
}