{
  "type": "Feature",
  "properties": {
    "addr:full": "3200 Kettering Blvd Dayton OH 45439",
    "addr:housenumber": "3200",
    "addr:postcode": "45439",
    "addr:street": "Kettering Blvd",
    "iso:country": "US",
    "sg:address": "3200 Kettering Blvd",
    "sg:city": "Dayton",
    "sg:classifiers": [
      {
        "category": "Home \u0026 Garden",
        "subcategory": "Carpets \u0026 Floor Coverings",
        "type": "Retail Goods"
      }
    ],
    "sg:phone": "+1 937 866 6807",
    "sg:postcode": "45439",
    "sg:province": "OH",
    "sg:tags": [
      "material"
    ],
    "wof:name": "Capitol Flooring",
    "wof:placetype": "venue"
  },
  "geometry": {"coordinates":[-84.206683,39.702304],"type":"Point"}
}
