{
  "type": "Feature",
  "properties": {
    "addr:full": "525 Mariner Village Huron OH 44839",
    "addr:housenumber": "525",
    "addr:postcode": "44839",
    "addr:street": "Mariner Village",
    "iso:country": "US",
    "sg:address": "525 Mariner Village",
    "sg:city": "Huron",
    "sg:classifiers": [
      {
        "category": "Real Estate",
        "subcategory": "Real Estate Operator",
        "type": "Services"
      }
    ],
    "sg:phone": "+1 419 433 8056",
    "sg:postcode": "44839",
    "sg:province": "OH",
    "sg:tags": [
      "building",
      "nonresidential"
    ],
    "wof:name": "Wil Cin Properties Ltd",
    "wof:placetype": "venue"
  },
  "geometry": {"coordinates":[-82.595609,41.415411],"type":"Point"}
}
