{
  "type": "Feature",
  "properties": {
    "addr:full": "1345 Dusky St Syracuse OH 45779",
    "addr:housenumber": "1345",
    "addr:postcode": "45779",
    "addr:street": "Dusky St",
    "iso:country": "US",
    "sg:address": "1345 Dusky St",
    "sg:city": "Syracuse",
    "sg:classifiers": [
      {
        "category": "Personal",
        "subcategory": "Beauty Salon",
        "type": "Services"
      }
    ],
    "sg:phone": "+1 740 992 7220",
    "sg:postcode": "45779",
    "sg:province": "OH",
    "wof:name": "Cutting Crew",
    "wof:placetype": "venue"
  },
  "geometry": {"coordinates":[-81.97847,39.001787],"type":"Point"}
}
