{
  "type": "Feature",
  "properties": {
    "addr:full": "1491 Aster Ave Akron OH 44301",
    "addr:housenumber": "1491",
    "addr:postcode": "44301",
    "addr:street": "Aster Ave",
    "iso:country": "US",
    "sg:address": "1491 Aster Ave",
    "sg:city": "Akron",
    "sg:classifiers": [
      {
        "category": "Retail",
        "subcategory": "Portrait Studio",
        "type": "Services"
      }
    ],
    "sg:phone": "+1 330 724 8225",
    "sg:postcode": "44301",
    "sg:province": "OH",
    "sg:tags": [
      "photographer"
    ],
    "wof:name": "Drobny Studio",
    "wof:placetype": "venue"
  },
  "geometry": {"coordinates":[-81.514698,41.041926],"type":"Point"}
}
