{
  "type": "Feature",
  "properties": {
    "iso:country":"US",
    "sg:address":"4625 W Bancroft St",
    "sg:city":"Toledo",
    "sg:classifiers":[
        {
            "category":"Professional",
            "type":"Services"
        }
    ],
    "sg:phone":"+1 419 531 1311",
    "sg:postcode":"43615",
    "sg:province":"OH",
    "sg:tags":[
        "establishment"
    ],
    "wof:name":"Dox Systems",
    "wof:placetype":"venue"
},
  "geometry": {"coordinates":[-83.649913,41.662358],"type":"Point"}
}