{
  "type": "Feature",
  "properties": {
    "iso:country":"US",
    "sg:address":"10221 Sweet Valley Dr",
    "sg:city":"Cleveland",
    "sg:classifiers":[
        {
            "category":"Manufacturing",
            "subcategory":"Printing",
            "type":"Manufacturing & Wholesale Goods"
        }
    ],
    "sg:phone":"+1 216 433 9400",
    "sg:postcode":"44125",
    "sg:province":"OH",
    "sg:tags":[
        "work",
        "book"
    ],
    "wof:name":"LPI",
    "wof:placetype":"venue"
},
  "geometry": {"coordinates":[-81.6159,41.396417],"type":"Point"}
}