{
  "type": "Feature",
  "properties": {
    "addr:full":"4536 Cleveland Rd Wooster OH 44691",
    "addr:housenumber":"4536",
    "addr:postcode":"44691",
    "addr:street":"Cleveland Rd",
    "iso:country":"US",
    "sg:address":"4536 Cleveland Rd",
    "sg:city":"Wooster",
    "sg:classifiers":[
        {
            "category":"Autos & Motor Vehicles",
            "subcategory":"Automobile Sales",
            "type":"Retail Goods"
        }
    ],
    "sg:phone":"+1 330 345 4565",
    "sg:postcode":"44691",
    "sg:province":"OH",
    "sg:tags":[
        "car",
        "dealer"
    ],
    "wof:name":"J D Byrider Auto Sales Of Woos",
    "wof:placetype":"venue"
},
  "geometry": {"coordinates":[-81.925786,40.853909],"type":"Point"}
}