{
  "type": "Feature",
  "properties": {
    "addr:full": "748 Mountainview Dr Westerville OH 43081",
    "addr:housenumber": "748",
    "addr:postcode": "43081",
    "addr:street": "Mountainview Dr",
    "iso:country": "US",
    "sg:address": "748 Mountainview Dr",
    "sg:city": "Westerville",
    "sg:classifiers": [
      {
        "category": "Professional",
        "subcategory": "Employment Agencies",
        "type": "Services"
      }
    ],
    "sg:phone": "+1 614 846 2346",
    "sg:postcode": "43081",
    "sg:province": "OH",
    "wof:name": "Baldwin Gilman LLC",
    "wof:placetype": "venue"
  },
  "geometry": {"coordinates":[-82.995795,40.132435],"type":"Point"}
}
