{
  "type": "Feature",
  "properties": {
    "iso:country":"US",
    "sg:address":"5930 Taylorsville Rd",
    "sg:city":"Dayton",
    "sg:classifiers":[
        {
            "category":"Real Estate",
            "subcategory":"Real Estate Agent",
            "type":"Services"
        }
    ],
    "sg:phone":"+1 937 236 5200",
    "sg:postcode":"45424",
    "sg:province":"OH",
    "wof:name":"R C A Realty Co",
    "wof:placetype":"venue"
},
  "geometry": {"coordinates":[-84.130621,39.862411],"type":"Point"}
}