{
  "type": "Feature",
  "properties": {
    "addr:full": "500 E Waterloo Rd Akron OH 44319",
    "addr:housenumber": "500",
    "addr:postcode": "44319",
    "addr:street": "E Waterloo Rd",
    "iso:country": "US",
    "sg:address": "500 E Waterloo Rd",
    "sg:city": "Akron",
    "sg:classifiers": [
      {
        "category": "Personal",
        "type": "Services"
      },
      {
        "category": "Restaurant",
        "type": "Food \u0026 Drink"
      }
    ],
    "sg:phone": "+1 330 724 6373",
    "sg:postcode": "44319",
    "sg:province": "OH",
    "sg:tags": [
      "eating",
      "banquet",
      "rooms"
    ],
    "wof:name": "Guy's Party Ctr",
    "wof:placetype": "venue"
  },
  "geometry": {"coordinates":[-81.507654,41.028939],"type":"Point"}
}
