{
  "type": "Feature",
  "properties": {
    "iso:country":"US",
    "sg:address":"4030 Rhodes Ave",
    "sg:city":"Portsmouth",
    "sg:classifiers":[
        {
            "category":"Ice Cream",
            "type":"Food & Drink"
        }
    ],
    "sg:menulink":"http://www.allmenus.com/oh/new-boston/165175-dairy-queen/menu/",
    "sg:phone":"+1 740 456 4277",
    "sg:postcode":"45662",
    "sg:province":"OH",
    "sg:tags":[
        "burger",
        "american"
    ],
    "wof:name":"Dairy Queen",
    "wof:placetype":"venue"
},
  "geometry": {"coordinates":[-82.934027,38.75321],"type":"Point"}
}