{
  "type": "Feature",
  "properties": {
    "addr:full":"3781 Town Center Blvd Columbus OH 43219",
    "addr:housenumber":"3781",
    "addr:postcode":"43219",
    "addr:street":"Town Center Blvd",
    "iso:country":"US",
    "sg:address":"3781 Town Center Blvd",
    "sg:city":"Columbus",
    "sg:classifiers":[
        {
            "category":"Real Estate",
            "subcategory":"Real Estate Agent",
            "type":"Services"
        }
    ],
    "sg:phone":"+1 614 478 8175",
    "sg:postcode":"43219",
    "sg:province":"OH",
    "wof:name":"Ohio Properties & Repairs",
    "wof:placetype":"venue"
},
  "geometry": {"coordinates":[-82.911109,40.025491],"type":"Point"}
}