{
  "type": "Feature",
  "properties": {
    "addr:full": "3391 Park St Grove City OH 43123",
    "addr:housenumber": "3391",
    "addr:postcode": "43123",
    "addr:street": "Park St",
    "iso:country": "US",
    "sg:address": "3391 Park St",
    "sg:city": "Grove City",
    "sg:classifiers": [
      {
        "category": "Manufacturing",
        "subcategory": "Printing",
        "type": "Manufacturing \u0026 Wholesale Goods"
      }
    ],
    "sg:phone": "+1 614 875 0755",
    "sg:postcode": "43123",
    "sg:province": "OH",
    "sg:tags": [
      "commercial"
    ],
    "wof:name": "Art Haven \u0026 Small Print Shop",
    "wof:placetype": "venue"
  },
  "geometry": {"coordinates":[-83.093237,39.88182],"type":"Point"}
}
