{
  "type": "Feature",
  "properties": {
    "iso:country":"US",
    "sg:address":"2717 Goddard Rd",
    "sg:city":"Toledo",
    "sg:classifiers":[
        {
            "category":"Manufacturing",
            "subcategory":"Printing",
            "type":"Manufacturing & Wholesale Goods"
        }
    ],
    "sg:phone":"+1 419 578 2762",
    "sg:postcode":"43606",
    "sg:province":"OH",
    "sg:tags":[
        "publishes",
        "newspaper",
        "shopping",
        "weekly"
    ],
    "wof:name":"Access Communication",
    "wof:placetype":"venue"
},
  "geometry": {"coordinates":[-83.613601,41.675082],"type":"Point"}
}