{
  "type": "Feature",
  "properties": {
    "addr:full": "2717 Goddard Rd Toledo OH 43606",
    "addr:housenumber": "2717",
    "addr:postcode": "43606",
    "addr:street": "Goddard Rd",
    "iso:country": "US",
    "sg:address": "2717 Goddard Rd",
    "sg:city": "Toledo",
    "sg:classifiers": [
      {
        "category": "Manufacturing",
        "subcategory": "Printing",
        "type": "Manufacturing \u0026 Wholesale Goods"
      }
    ],
    "sg:phone": "+1 419 578 2762",
    "sg:postcode": "43606",
    "sg:province": "OH",
    "sg:tags": [
      "publishes",
      "newspaper",
      "shopping",
      "weekly"
    ],
    "wof:name": "Access Communication",
    "wof:placetype": "venue"
  },
  "geometry": {"coordinates":[-83.613601,41.675082],"type":"Point"}
}
