{
  "type": "Feature",
  "properties": {
    "addr:full": "15841 E Liverpool Rd East Liverpool OH 43920",
    "addr:housenumber": "15841",
    "addr:postcode": "43920",
    "addr:street": "E Liverpool Rd",
    "iso:country": "US",
    "sg:address": "15841 E Liverpool Rd",
    "sg:city": "East Liverpool",
    "sg:classifiers": [
      {
        "category": "Health Services",
        "subcategory": "Doctor",
        "type": "Services"
      }
    ],
    "sg:phone": "+1 330 385 6201",
    "sg:postcode": "43920",
    "sg:province": "OH",
    "wof:name": "Dentistry For Children \u0026 Teens",
    "wof:placetype": "venue"
  },
  "geometry": {"coordinates":[-80.603005,40.672353],"type":"Point"}
}
