{
  "type": "Feature",
  "properties": {
    "iso:country":"US",
    "sg:address":"15841 E Liverpool Rd",
    "sg:city":"East Liverpool",
    "sg:classifiers":[
        {
            "category":"Health Services",
            "subcategory":"Doctor",
            "type":"Services"
        }
    ],
    "sg:phone":"+1 330 385 6201",
    "sg:postcode":"43920",
    "sg:province":"OH",
    "wof:name":"Dentistry For Children & Teens",
    "wof:placetype":"venue"
},
  "geometry": {"coordinates":[-80.603005,40.672353],"type":"Point"}
}