{
  "type": "Feature",
  "properties": {
    "addr:full": "3185 Dot Dr Cincinnati OH 45213",
    "addr:housenumber": "3185",
    "addr:postcode": "45213",
    "addr:street": "Dot Dr",
    "iso:country": "US",
    "sg:address": "3185 Dot Dr",
    "sg:city": "Cincinnati",
    "sg:classifiers": [
      {
        "category": "Health Services",
        "subcategory": "Health Practitioner",
        "type": "Services"
      }
    ],
    "sg:phone": "+1 513 984 8636",
    "sg:postcode": "45213",
    "sg:province": "OH",
    "sg:tags": [
      "psychologist"
    ],
    "wof:name": "M L Griswold \u0026 Assoc",
    "wof:placetype": "venue"
  },
  "geometry": {"coordinates":[-84.429649,39.191234],"type":"Point"}
}
