{
  "type": "Feature",
  "properties": {
    "iso:country":"US",
    "sg:address":"7431 W Central Ave",
    "sg:city":"Toledo",
    "sg:classifiers":[
        {
            "category":"Personal",
            "type":"Services"
        }
    ],
    "sg:phone":"+1 419 662 9901",
    "sg:postcode":"43617",
    "sg:province":"OH",
    "sg:tags":[
        "therapist",
        "massage"
    ],
    "wof:name":"Linda Hamilton",
    "wof:placetype":"venue"
},
  "geometry": {"coordinates":[-83.721751,41.67379],"type":"Point"}
}