{
  "type": "Feature",
  "properties": {
    "addr:full": "115 Warren St Rayland OH 43943",
    "addr:housenumber": "115",
    "addr:postcode": "43943",
    "addr:street": "Warren St",
    "iso:country": "US",
    "sg:address": "115 Warren St",
    "sg:city": "Rayland",
    "sg:classifiers": [
      {
        "category": "Government",
        "subcategory": "Fire Station",
        "type": "Public Place"
      }
    ],
    "sg:phone": "+1 740 859 5122",
    "sg:postcode": "43943",
    "sg:province": "OH",
    "sg:tags": [
      "department"
    ],
    "wof:name": "Rayland Fire Dept",
    "wof:placetype": "venue"
  },
  "geometry": {"coordinates":[-80.689022,40.187919],"type":"Point"}
}
