{
  "type": "Feature",
  "properties": {
    "addr:full":"5 E Ashtabula St Jefferson OH 44047",
    "addr:housenumber":"5",
    "addr:postcode":"44047",
    "addr:street":"E Ashtabula St",
    "iso:country":"US",
    "sg:address":"5 E Ashtabula St",
    "sg:city":"Jefferson",
    "sg:classifiers":[
        {
            "category":"Shopping",
            "subcategory":"Pharmacy",
            "type":"Retail Goods"
        }
    ],
    "sg:phone":"+1 440 576 3921",
    "sg:postcode":"44047",
    "sg:province":"OH",
    "sg:tags":[
        "aid",
        "supply",
        "first"
    ],
    "sg:website":"http://www.riteaid.com",
    "wof:name":"Rite Aid",
    "wof:placetype":"venue"
},
  "geometry": {"coordinates":[-80.769223,41.74239],"type":"Point"}
}