{
  "type": "Feature",
  "properties": {
    "addr:full": "104 Plaza Dr St Clairsville OH 43950",
    "addr:housenumber": "104",
    "addr:postcode": "43950",
    "addr:street": "Plaza Dr",
    "iso:country": "US",
    "sg:address": "104 Plaza Dr",
    "sg:city": "St Clairsville",
    "sg:classifiers": [
      {
        "category": "Shopping",
        "subcategory": "Pharmacy",
        "type": "Retail Goods"
      }
    ],
    "sg:phone": "+1 740 695 0274",
    "sg:postcode": "43950",
    "sg:province": "OH",
    "wof:name": "Reisbecks Pharmacy",
    "wof:placetype": "venue"
  },
  "geometry": {"coordinates":[-80.917723,40.074906],"type":"Point"}
}
