{
  "type": "Feature",
  "properties": {
    "iso:country":"US",
    "sg:address":"4276 Monticello Blvd",
    "sg:city":"Cleveland",
    "sg:classifiers":[
        {
            "category":"Recreation",
            "type":"Entertainment"
        }
    ],
    "sg:phone":"+1 216 382 3522",
    "sg:postcode":"44121",
    "sg:province":"OH",
    "sg:tags":[
        "parlor",
        "billiard"
    ],
    "wof:name":"Shark Key Pool Club",
    "wof:placetype":"venue"
},
  "geometry": {"coordinates":[-81.531355,41.53669],"type":"Point"}
}