{
  "type": "Feature",
  "properties": {
    "iso:country":"US",
    "sg:address":"2868 Lakeland Pkwy",
    "sg:city":"Silver Lake",
    "sg:classifiers":[
        {
            "category":"Professional",
            "subcategory":"Business Services",
            "type":"Services"
        }
    ],
    "sg:phone":"+1 330 929 9771",
    "sg:postcode":"44224",
    "sg:province":"OH",
    "sg:tags":[
        "interior",
        "consultant",
        "design",
        "decorator"
    ],
    "wof:name":"Decorator's Workshop",
    "wof:placetype":"venue"
},
  "geometry": {"coordinates":[-81.465377,41.16021],"type":"Point"}
}