{
  "type": "Feature",
  "properties": {
    "addr:full":"2410 Brittany Ct Dayton OH 45459",
    "addr:housenumber":"2410",
    "addr:postcode":"45459",
    "addr:street":"Brittany Ct",
    "iso:country":"US",
    "sg:address":"2410 Brittany Ct",
    "sg:city":"Dayton",
    "sg:classifiers":[
        {
            "category":"Manufacturing",
            "subcategory":"Printing",
            "type":"Manufacturing & Wholesale Goods"
        }
    ],
    "sg:phone":"+1 937 434 5455",
    "sg:postcode":"45459",
    "sg:province":"OH",
    "sg:tags":[
        "publisher",
        "software"
    ],
    "wof:name":"Fall Prevention Technology",
    "wof:placetype":"venue"
},
  "geometry": {"coordinates":[-84.216374,39.636784],"type":"Point"}
}