{
  "type": "Feature",
  "properties": {
    "addr:full":"6233 Wanlow Ln Dayton OH 45459",
    "addr:housenumber":"6233",
    "addr:postcode":"45459",
    "addr:street":"Wanlow Ln",
    "iso:country":"US",
    "sg:address":"6233 Wanlow Ln",
    "sg:city":"Dayton",
    "sg:classifiers":[
        {
            "category":"Utilities",
            "subcategory":"Telephone",
            "type":"Services"
        }
    ],
    "sg:phone":"+1 937 433 6797",
    "sg:postcode":"45459",
    "sg:province":"OH",
    "sg:tags":[
        "communications"
    ],
    "wof:name":"Lobo Ranch",
    "wof:placetype":"venue"
},
  "geometry": {"coordinates":[-84.194394,39.657778],"type":"Point"}
}