{
  "type": "Feature",
  "properties": {
    "addr:full":"3673 Court Rd Collins OH 44826",
    "addr:housenumber":"3673",
    "addr:postcode":"44826",
    "addr:street":"Court Rd",
    "iso:country":"US",
    "sg:address":"3673 Court Rd",
    "sg:city":"Collins",
    "sg:classifiers":[
        {
            "category":"Retail",
            "subcategory":"Auto Repair",
            "type":"Services"
        }
    ],
    "sg:phone":"+1 419 929 8571",
    "sg:postcode":"44826",
    "sg:province":"OH",
    "sg:tags":[
        "wrecker"
    ],
    "wof:name":"Bob's Midnight Towing",
    "wof:placetype":"venue"
},
  "geometry": {"coordinates":[-82.47257399999999,41.174927],"type":"Point"}
}