{
  "type": "Feature",
  "properties": {
    "iso:country":"US",
    "sg:address":"606 S 7th St",
    "sg:city":"Byesville",
    "sg:classifiers":[
        {
            "category":"Professional",
            "subcategory":"Accounting & Tax Preparation",
            "type":"Services"
        }
    ],
    "sg:phone":"+1 740 685 6119",
    "sg:postcode":"43723",
    "sg:province":"OH",
    "sg:tags":[
        "return",
        "filing"
    ],
    "wof:name":"Miller's Tax Svc",
    "wof:placetype":"venue"
},
  "geometry": {"coordinates":[-81.544158,39.964766],"type":"Point"}
}