{
  "type": "Feature",
  "properties": {
    "iso:country":"US",
    "sg:address":"1801 Broad Ave",
    "sg:city":"Findlay",
    "sg:classifiers":[
        {
            "category":"Restaurant",
            "type":"Food & Drink"
        }
    ],
    "sg:phone":"+1 419 422 7211",
    "sg:postcode":"45840",
    "sg:province":"OH",
    "wof:name":"Bob Evans Farms Restaurant",
    "wof:placetype":"venue"
},
  "geometry": {"coordinates":[-83.66435,41.063899],"type":"Point"}
}