{
  "type": "Feature",
  "properties": {
    "addr:full": "1801 Broad Ave Findlay OH 45840",
    "addr:housenumber": "1801",
    "addr:postcode": "45840",
    "addr:street": "Broad Ave",
    "iso:country": "US",
    "sg:address": "1801 Broad Ave",
    "sg:city": "Findlay",
    "sg:classifiers": [
      {
        "category": "Restaurant",
        "type": "Food \u0026 Drink"
      }
    ],
    "sg:phone": "+1 419 422 7211",
    "sg:postcode": "45840",
    "sg:province": "OH",
    "wof:name": "Bob Evans Farms Restaurant",
    "wof:placetype": "venue"
  },
  "geometry": {"coordinates":[-83.66435,41.063899],"type":"Point"}
}
