{
  "type": "Feature",
  "properties": {
    "addr:full": "4286 Mount Carmel Tobasco Rd Cincinnati OH 45244",
    "addr:housenumber": "4286",
    "addr:postcode": "45244",
    "addr:street": "Mount Carmel Tobasco Rd",
    "iso:country": "US",
    "sg:address": "4286 Mount Carmel Tobasco Rd",
    "sg:city": "Cincinnati",
    "sg:classifiers": [
      {
        "category": "Personal",
        "subcategory": "Beauty Salon",
        "type": "Services"
      }
    ],
    "sg:phone": "+1 513 528 6474",
    "sg:postcode": "45244",
    "sg:province": "OH",
    "wof:name": "Hair Finale",
    "wof:placetype": "venue"
  },
  "geometry": {"coordinates":[-84.300673,39.086941],"type":"Point"}
}
