{
  "type": "Feature",
  "properties": {
    "addr:full": "5400 Elder Rd Canal Winchester OH 43110",
    "addr:housenumber": "5400",
    "addr:postcode": "43110",
    "addr:street": "Elder Rd",
    "iso:country": "US",
    "sg:address": "5400 Elder Rd",
    "sg:city": "Canal Winchester",
    "sg:classifiers": [
      {
        "category": "Banks \u0026 Credit Unions",
        "subcategory": "Financial Services",
        "type": "Services"
      }
    ],
    "sg:phone": "+1 614 833 2645",
    "sg:postcode": "43110",
    "sg:province": "OH",
    "sg:tags": [
      "trust",
      "management"
    ],
    "wof:name": "Earth Angel Foundation Inc",
    "wof:placetype": "venue"
  },
  "geometry": {"coordinates":[-82.838282,39.803918],"type":"Point"}
}
