{
  "type": "Feature",
  "properties": {
    "iso:country":"US",
    "sg:address":"112 4th St NW",
    "sg:city":"New Philadelphia",
    "sg:classifiers":[
        {
            "category":"Insurance",
            "subcategory":"Insurance Agent",
            "type":"Services"
        }
    ],
    "sg:phone":"+1 330 364 7716",
    "sg:postcode":"44663",
    "sg:province":"OH",
    "wof:name":"B Taylor Insurance",
    "wof:placetype":"venue"
},
  "geometry": {"coordinates":[-81.45206899999999,40.491186],"type":"Point"}
}