{
  "type": "Feature",
  "properties": {
    "addr:full": "112 4th St NW New Philadelphia OH 44663",
    "addr:housenumber": "112",
    "addr:postcode": "44663",
    "addr:street": "4Th St Nw New Philadelphia",
    "iso:country": "US",
    "sg:address": "112 4th St NW",
    "sg:city": "New Philadelphia",
    "sg:classifiers": [
      {
        "category": "Insurance",
        "subcategory": "Insurance Agent",
        "type": "Services"
      }
    ],
    "sg:phone": "+1 330 364 7716",
    "sg:postcode": "44663",
    "sg:province": "OH",
    "wof:name": "B Taylor Insurance",
    "wof:placetype": "venue"
  },
  "geometry": {"coordinates":[-81.452069,40.491186],"type":"Point"}
}
