{
  "type": "Feature",
  "properties": {
    "addr:full": "140 Buckeye Blvd Port Clinton OH 43452",
    "addr:housenumber": "140",
    "addr:postcode": "43452",
    "addr:street": "Buckeye Blvd",
    "iso:country": "US",
    "sg:address": "140 Buckeye Blvd",
    "sg:city": "Port Clinton",
    "sg:classifiers": [
      {
        "category": "Insurance",
        "subcategory": "Insurance Agent",
        "type": "Services"
      }
    ],
    "sg:phone": "+1 419 734 2715",
    "sg:postcode": "43452",
    "sg:province": "OH",
    "wof:name": "State Farm Insurance",
    "wof:placetype": "venue"
  },
  "geometry": {"coordinates":[-82.913297,41.513909],"type":"Point"}
}
