{
  "type": "Feature",
  "properties": {
    "iso:country":"US",
    "sg:address":"1425 Wooster Rd W",
    "sg:city":"Barberton",
    "sg:classifiers":[
        {
            "category":"Restaurant",
            "type":"Food & Drink"
        }
    ],
    "sg:menulink":"http://www.allmenus.com/oh/barberton/233289-mr-hero/menu/",
    "sg:phone":"+1 330 825 5273",
    "sg:postcode":"44203",
    "sg:province":"OH",
    "sg:tags":[
        "wrap",
        "american",
        "sandwich"
    ],
    "wof:name":"Mr. Hero",
    "wof:placetype":"venue"
},
  "geometry": {"coordinates":[-81.639732,41.005283],"type":"Point"}
}