{
  "type": "Feature",
  "properties": {
    "addr:full": "4996 Boston Rd Brunswick OH 44212",
    "addr:housenumber": "4996",
    "addr:postcode": "44212",
    "addr:street": "Boston Rd",
    "iso:country": "US",
    "sg:address": "4996 Boston Rd",
    "sg:city": "Brunswick",
    "sg:classifiers": [
      {
        "category": "Building \u0026 Trades",
        "subcategory": "Pest Control",
        "type": "Services"
      }
    ],
    "sg:phone": "+1 330 723 0903",
    "sg:postcode": "44212",
    "sg:province": "OH",
    "sg:tags": [
      "mothproofing"
    ],
    "sg:website": "http://www.alphapestcontrol.net",
    "wof:name": "Alpha Pest Control",
    "wof:placetype": "venue"
  },
  "geometry": {"coordinates":[-81.865915,41.275205],"type":"Point"}
}
