{
  "type": "Feature",
  "properties": {
    "addr:full": "559 E Center St Marion OH 43302",
    "addr:housenumber": "559",
    "addr:postcode": "43302",
    "addr:street": "E Center St",
    "iso:country": "US",
    "sg:address": "559 E Center St",
    "sg:city": "Marion",
    "sg:classifiers": [
      {
        "category": "Banks \u0026 Credit Unions",
        "subcategory": "Bank",
        "type": "Services"
      }
    ],
    "sg:phone": "+1 740 383 3355",
    "sg:postcode": "43302",
    "sg:province": "OH",
    "sg:tags": [
      "mortgage"
    ],
    "wof:name": "United Bank N A",
    "wof:placetype": "venue"
  },
  "geometry": {"coordinates":[-83.116032,40.589052],"type":"Point"}
}
