{
  "type": "Feature",
  "properties": {
    "addr:full":"440 N Main St New Carlisle OH 45344",
    "addr:housenumber":"440",
    "addr:postcode":"45344",
    "addr:street":"N Main St",
    "iso:country":"US",
    "sg:address":"440 N Main St",
    "sg:city":"New Carlisle",
    "sg:classifiers":[
        {
            "category":"Recreation",
            "type":"Entertainment"
        }
    ],
    "sg:phone":"+1 937 845 9779",
    "sg:postcode":"45344",
    "sg:province":"OH",
    "sg:tags":[
        "club",
        "membership"
    ],
    "wof:name":"New Crlsl Baseball Assoc",
    "wof:placetype":"venue"
},
  "geometry": {"coordinates":[-84.024123,39.945323],"type":"Point"}
}