{
  "type": "Feature",
  "properties": {
    "addr:full":"8250 Allen Dr NE Alliance OH 44601",
    "addr:housenumber":"8250",
    "addr:postcode":"44601",
    "addr:street":"Allen Dr Ne",
    "iso:country":"US",
    "sg:address":"8250 Allen Dr NE",
    "sg:city":"Alliance",
    "sg:classifiers":[
        {
            "category":"Building & Trades",
            "subcategory":"Construction",
            "type":"Services"
        }
    ],
    "sg:phone":"+1 330 935 0828",
    "sg:postcode":"44601",
    "sg:province":"OH",
    "sg:tags":[
        "home",
        "residential",
        "improvement"
    ],
    "wof:name":"DC Property Improvement LLC",
    "wof:placetype":"venue"
},
  "geometry": {"coordinates":[-81.247523,40.976248],"type":"Point"}
}