{
  "type": "Feature",
  "properties": {
    "addr:full":"60 Norton Rd Columbus OH 43228",
    "addr:housenumber":"60",
    "addr:postcode":"43228",
    "addr:street":"Norton Rd",
    "iso:country":"US",
    "sg:address":"60 Norton Rd",
    "sg:city":"Columbus",
    "sg:classifiers":[
        {
            "category":"Social Services",
            "subcategory":"Child Care",
            "type":"Services"
        }
    ],
    "sg:phone":"+1 614 851 2265",
    "sg:postcode":"43228",
    "sg:province":"OH",
    "sg:tags":[
        "kindergarten",
        "academic",
        "school"
    ],
    "wof:name":"Norton Road Head Start",
    "wof:placetype":"venue"
},
  "geometry": {"coordinates":[-83.139594,39.951238],"type":"Point"}
}