{
  "type": "Feature",
  "properties": {
    "addr:full": "408 Dana St NE Warren OH 44483",
    "addr:housenumber": "408",
    "addr:postcode": "44483",
    "addr:street": "Dana St Ne",
    "iso:country": "US",
    "sg:address": "408 Dana St NE",
    "sg:city": "Warren",
    "sg:classifiers": [
      {
        "category": "Manufacturing",
        "subcategory": "Motor Vehicles \u0026 Parts",
        "type": "Manufacturing \u0026 Wholesale Goods"
      }
    ],
    "sg:phone": "+1 330 373 2121",
    "sg:postcode": "44483",
    "sg:province": "OH",
    "sg:tags": [
      "engine",
      "electric",
      "mfg"
    ],
    "wof:name": "Delphi",
    "wof:placetype": "venue"
  },
  "geometry": {"coordinates":[-80.812223,41.247966],"type":"Point"}
}
