{
  "type": "Feature",
  "properties": {
    "iso:country":"US",
    "sg:address":"408 Dana St NE",
    "sg:city":"Warren",
    "sg:classifiers":[
        {
            "category":"Manufacturing",
            "subcategory":"Motor Vehicles & Parts",
            "type":"Manufacturing & Wholesale Goods"
        }
    ],
    "sg:phone":"+1 330 373 2121",
    "sg:postcode":"44483",
    "sg:province":"OH",
    "sg:tags":[
        "engine",
        "electric",
        "mfg"
    ],
    "wof:name":"Delphi",
    "wof:placetype":"venue"
},
  "geometry": {"coordinates":[-80.812223,41.247966],"type":"Point"}
}