{
  "type": "Feature",
  "properties": {
    "iso:country":"US",
    "sg:address":"628 Dewey St",
    "sg:city":"Delphos",
    "sg:classifiers":[
        {
            "category":"Building & Trades",
            "subcategory":"Construction",
            "type":"Services"
        }
    ],
    "sg:phone":"+1 419 692 0630",
    "sg:postcode":"45833",
    "sg:province":"OH",
    "sg:tags":[
        "house",
        "residential"
    ],
    "wof:name":"Lawson General Contracting",
    "wof:placetype":"venue"
},
  "geometry": {"coordinates":[-84.330087,40.835976],"type":"Point"}
}