{
  "type": "Feature",
  "properties": {
    "addr:full":"17771 Mahoning Ave Lake Milton OH 44429",
    "addr:housenumber":"17771",
    "addr:postcode":"44429",
    "addr:street":"Mahoning Ave",
    "iso:country":"US",
    "sg:address":"17771 Mahoning Ave",
    "sg:city":"Lake Milton",
    "sg:classifiers":[
        {
            "category":"Shopping",
            "subcategory":"Gifts & Souvenirs",
            "type":"Retail Goods"
        }
    ],
    "sg:phone":"+1 330 654 2544",
    "sg:postcode":"44429",
    "sg:province":"OH",
    "sg:tags":[
        "shop"
    ],
    "wof:name":"Awake By The Lake Coffe & Gift",
    "wof:placetype":"venue"
},
  "geometry": {"coordinates":[-80.990584,41.096188],"type":"Point"}
}