{
  "type": "Feature",
  "properties": {
    "addr:full": "62 S Williams St Newark OH 43055",
    "addr:housenumber": "62",
    "addr:postcode": "43055",
    "addr:street": "S Williams St",
    "iso:country": "US",
    "sg:address": "62 S Williams St",
    "sg:city": "Newark",
    "sg:classifiers": [
      {
        "category": "Taxi",
        "type": "Transportation"
      }
    ],
    "sg:phone": "+1 740 345 6411",
    "sg:postcode": "43055",
    "sg:province": "OH",
    "sg:tags": [
      "taxicab"
    ],
    "wof:name": "Peoples Choice Taxi Service",
    "wof:placetype": "venue"
  },
  "geometry": {"coordinates":[-82.425772,40.050751],"type":"Point"}
}
