{
  "type": "Feature",
  "properties": {
    "iso:country":"US",
    "sg:address":"6997 Harrisburg Pike",
    "sg:city":"Orient",
    "sg:classifiers":[
        {
            "category":"Autos & Motor Vehicles",
            "subcategory":"Fuel & Gas Station",
            "type":"Retail Goods"
        }
    ],
    "sg:phone":"+1 614 875 3697",
    "sg:postcode":"43146",
    "sg:province":"OH",
    "sg:tags":[
        "station",
        "gasoline"
    ],
    "wof:name":"Sunoco",
    "wof:placetype":"venue"
},
  "geometry": {"coordinates":[-83.140057,39.825986],"type":"Point"}
}