{
  "type": "Feature",
  "properties": {
    "addr:full": "6997 Harrisburg Pike Orient OH 43146",
    "addr:housenumber": "6997",
    "addr:postcode": "43146",
    "addr:street": "Harrisburg Pike",
    "iso:country": "US",
    "sg:address": "6997 Harrisburg Pike",
    "sg:city": "Orient",
    "sg:classifiers": [
      {
        "category": "Autos \u0026 Motor Vehicles",
        "subcategory": "Fuel \u0026 Gas Station",
        "type": "Retail Goods"
      }
    ],
    "sg:phone": "+1 614 875 3697",
    "sg:postcode": "43146",
    "sg:province": "OH",
    "sg:tags": [
      "station",
      "gasoline"
    ],
    "wof:name": "Sunoco",
    "wof:placetype": "venue"
  },
  "geometry": {"coordinates":[-83.140057,39.825986],"type":"Point"}
}
