{
  "type": "Feature",
  "properties": {
    "addr:full":"311 W Oak St Union City OH 47390",
    "addr:housenumber":"311",
    "addr:postcode":"47390",
    "addr:street":"W Oak St",
    "iso:country":"US",
    "sg:address":"311 W Oak St",
    "sg:city":"Union City",
    "sg:classifiers":[
        {
            "category":"Professional",
            "subcategory":"Computer Services",
            "type":"Services"
        }
    ],
    "sg:phone":"+1 765 584 9120",
    "sg:postcode":"47390",
    "sg:province":"OH",
    "sg:tags":[
        "website",
        "design"
    ],
    "sg:website":"www.localinsight.com",
    "wof:name":"LOCALINSIGHT.COM",
    "wof:placetype":"venue"
},
  "geometry": {"coordinates":[-84.808538,40.199981],"type":"Point"}
}