{
  "type": "Feature",
  "properties": {
    "iso:country":"US",
    "sg:address":"1000 Cook Rd",
    "sg:city":"Lebanon",
    "sg:classifiers":[
        {
            "category":"Building & Trades",
            "subcategory":"Plumbing",
            "type":"Services"
        }
    ],
    "sg:phone":"+1 513 932 3207",
    "sg:postcode":"45036",
    "sg:province":"OH",
    "sg:tags":[
        "contractor"
    ],
    "wof:name":"M E Merrell Plumbing",
    "wof:placetype":"venue"
},
  "geometry": {"coordinates":[-84.195787,39.413228],"type":"Point"}
}