{
  "type": "Feature",
  "properties": {
    "iso:country":"US",
    "sg:address":"10400 New Haven Rd",
    "sg:city":"Harrison",
    "sg:classifiers":[
        {
            "category":"Government",
            "subcategory":"Office",
            "type":"Public Place"
        }
    ],
    "sg:phone":"+1 513 367 5383",
    "sg:postcode":"45030",
    "sg:province":"OH",
    "sg:tags":[
        "city",
        "resource",
        "human"
    ],
    "wof:name":"Cincinnati City WIC",
    "wof:placetype":"venue"
},
  "geometry": {"coordinates":[-84.78045899999999,39.262008],"type":"Point"}
}