{
  "type": "Feature",
  "properties": {
    "iso:country":"US",
    "sg:address":"19500 Center Ridge Rd",
    "sg:city":"Cleveland",
    "sg:classifiers":[
        {
            "category":"Personal",
            "type":"Services"
        }
    ],
    "sg:phone":"+1 440 333 2800",
    "sg:postcode":"44116",
    "sg:province":"OH",
    "sg:tags":[
        "therapist",
        "massage"
    ],
    "wof:name":"Italian Masseuse",
    "wof:placetype":"venue"
},
  "geometry": {"coordinates":[-81.838503,41.465741],"type":"Point"}
}