{
  "type": "Feature",
  "properties": {
    "iso:country":"US",
    "sg:address":"9614 Willard Ave",
    "sg:city":"Cleveland",
    "sg:classifiers":[
        {
            "category":"Building & Trades",
            "subcategory":"Construction",
            "type":"Services"
        }
    ],
    "sg:phone":"+1 216 651 5939",
    "sg:postcode":"44102",
    "sg:province":"OH",
    "sg:tags":[
        "commercial",
        "contractor"
    ],
    "wof:name":"Rivera Mark Construction",
    "wof:placetype":"venue"
},
  "geometry": {"coordinates":[-81.750321,41.471229],"type":"Point"}
}