{
  "type": "Feature",
  "properties": {
    "iso:country":"US",
    "sg:address":"7110 Whipple Ave NW",
    "sg:city":"North Canton",
    "sg:classifiers":[
        {
            "category":"Wholesale",
            "subcategory":"Machinery & Supplies",
            "type":"Manufacturing & Wholesale Goods"
        }
    ],
    "sg:phone":"+1 330 966 5909",
    "sg:postcode":"44720",
    "sg:province":"OH",
    "sg:tags":[
        "fire",
        "department",
        "equipment"
    ],
    "wof:name":"Elias Enterprises",
    "wof:placetype":"venue"
},
  "geometry": {"coordinates":[-81.423021,40.883875],"type":"Point"}
}