{
  "type": "Feature",
  "properties": {
    "addr:full": "7110 Whipple Ave NW North Canton OH 44720",
    "addr:housenumber": "7110",
    "addr:postcode": "44720",
    "addr:street": "Whipple Ave Nw",
    "iso:country": "US",
    "sg:address": "7110 Whipple Ave NW",
    "sg:city": "North Canton",
    "sg:classifiers": [
      {
        "category": "Wholesale",
        "subcategory": "Machinery \u0026 Supplies",
        "type": "Manufacturing \u0026 Wholesale Goods"
      }
    ],
    "sg:phone": "+1 330 966 5909",
    "sg:postcode": "44720",
    "sg:province": "OH",
    "sg:tags": [
      "fire",
      "department",
      "equipment"
    ],
    "wof:name": "Elias Enterprises",
    "wof:placetype": "venue"
  },
  "geometry": {"coordinates":[-81.423021,40.883875],"type":"Point"}
}
