{
  "type": "Feature",
  "properties": {
    "iso:country":"US",
    "sg:address":"8107 Stone Rd",
    "sg:city":"Cleveland",
    "sg:classifiers":[
        {
            "category":"Food & Beverages",
            "subcategory":"Specialty",
            "type":"Retail Goods"
        }
    ],
    "sg:phone":"+1 216 524 3141",
    "sg:postcode":"44131",
    "sg:province":"OH",
    "sg:tags":[
        "health",
        "diet"
    ],
    "wof:name":"Aaaah Yoga Macrobiotics & More",
    "wof:placetype":"venue"
},
  "geometry": {"coordinates":[-81.623998,41.38181],"type":"Point"}
}