{
  "type": "Feature",
  "properties": {
    "iso:country":"US",
    "sg:address":"2519 N Ridge Rd",
    "sg:city":"Painesville",
    "sg:classifiers":[
        {
            "category":"Building & Trades",
            "subcategory":"Landscaping Services",
            "type":"Services"
        }
    ],
    "sg:phone":"+1 440 257 3348",
    "sg:postcode":"44077",
    "sg:province":"OH",
    "sg:tags":[
        "landscape",
        "contractor"
    ],
    "wof:name":"Mc Callister's Landscaping",
    "wof:placetype":"venue"
},
  "geometry": {"coordinates":[-81.189318,41.761255],"type":"Point"}
}