{
  "type": "Feature",
  "properties": {
    "iso:country":"US",
    "sg:address":"631 Washington Ave",
    "sg:city":"Cuyahoga Falls",
    "sg:classifiers":[
        {
            "category":"Professional",
            "subcategory":"Advertising",
            "type":"Services"
        }
    ],
    "sg:phone":"+1 330 926 1534",
    "sg:postcode":"44221",
    "sg:province":"OH",
    "wof:name":"BALACHILD.COM",
    "wof:placetype":"venue"
},
  "geometry": {"coordinates":[-81.490915,41.146659],"type":"Point"}
}