{
  "type": "Feature",
  "properties": {
    "iso:country":"US",
    "sg:address":"31 W Whipp Rd",
    "sg:city":"Dayton",
    "sg:classifiers":[
        {
            "category":"Shopping",
            "subcategory":"Pharmacy",
            "type":"Retail Goods"
        }
    ],
    "sg:phone":"+1 937 436 8090",
    "sg:postcode":"45459",
    "sg:province":"OH",
    "wof:name":"Columbus Prescription Pharmacy",
    "wof:placetype":"venue"
},
  "geometry": {"coordinates":[-84.160918,39.659085],"type":"Point"}
}