{
  "type": "Feature",
  "properties": {
    "addr:full": "2650 Courtright Rd Columbus OH 43232",
    "addr:housenumber": "2650",
    "addr:postcode": "43232",
    "addr:street": "Courtright Rd",
    "iso:country": "US",
    "sg:address": "2650 Courtright Rd",
    "sg:city": "Columbus",
    "sg:classifiers": [
      {
        "category": "Organizations",
        "subcategory": "Religious Organization",
        "type": "Services"
      }
    ],
    "sg:phone": "+1 614 501 7357",
    "sg:postcode": "43232",
    "sg:province": "OH",
    "sg:tags": [
      "church"
    ],
    "wof:name": "Grace \u0026 Truth Church Of Jc",
    "wof:placetype": "venue"
  },
  "geometry": {"coordinates":[-82.896607,39.919672],"type":"Point"}
}
