{
  "type": "Feature",
  "properties": {
    "addr:full": "16041 State Rte 170 East Liverpool OH 43920",
    "addr:housenumber": "16041",
    "addr:postcode": "43920",
    "addr:street": "State Rte 170",
    "iso:country": "US",
    "sg:address": "16041 State Rte 170",
    "sg:city": "East Liverpool",
    "sg:classifiers": [
      {
        "category": "Shopping",
        "subcategory": "Shoes",
        "type": "Retail Goods"
      }
    ],
    "sg:phone": "+1 330 385 0409",
    "sg:postcode": "43920",
    "sg:province": "OH",
    "wof:name": "Payless Shoesource",
    "wof:placetype": "venue"
  },
  "geometry": {"coordinates":[-80.599884,40.667918],"type":"Point"}
}
