{
  "type": "Feature",
  "properties": {
    "addr:full": "586 Lighthouse Ct Westerville OH 43082",
    "addr:housenumber": "586",
    "addr:postcode": "43082",
    "addr:street": "Lighthouse Ct",
    "iso:country": "US",
    "sg:address": "586 Lighthouse Ct",
    "sg:city": "Westerville",
    "sg:classifiers": [
      {
        "category": "Professional",
        "subcategory": "Business Services",
        "type": "Services"
      }
    ],
    "sg:phone": "+1 614 818 4100",
    "sg:postcode": "43082",
    "sg:province": "OH",
    "sg:tags": [
      "auctioneer"
    ],
    "wof:name": "Albert Mike Realtors \u0026 Auction",
    "wof:placetype": "venue"
  },
  "geometry": {"coordinates":[-82.894405,40.14089],"type":"Point"}
}
