{
  "type": "Feature",
  "properties": {
    "iso:country":"US",
    "sg:address":"586 Lighthouse Ct",
    "sg:city":"Westerville",
    "sg:classifiers":[
        {
            "category":"Professional",
            "subcategory":"Business Services",
            "type":"Services"
        }
    ],
    "sg:phone":"+1 614 818 4100",
    "sg:postcode":"43082",
    "sg:province":"OH",
    "sg:tags":[
        "auctioneer"
    ],
    "wof:name":"Albert Mike Realtors & Auction",
    "wof:placetype":"venue"
},
  "geometry": {"coordinates":[-82.89440500000001,40.14089],"type":"Point"}
}