{
  "type": "Feature",
  "properties": {
    "addr:full":"631 Monnett Rd Marion OH 43302",
    "addr:housenumber":"631",
    "addr:postcode":"43302",
    "addr:street":"Monnett Rd",
    "iso:country":"US",
    "sg:address":"631 Monnett Rd",
    "sg:city":"Marion",
    "sg:classifiers":[
        {
            "category":"Farming",
            "subcategory":"Nursery",
            "type":"Manufacturing & Wholesale Goods"
        }
    ],
    "sg:phone":"+1 740 387 4328",
    "sg:postcode":"43302",
    "sg:province":"OH",
    "sg:tags":[
        "ornamental"
    ],
    "wof:name":"Country Corners",
    "wof:placetype":"venue"
},
  "geometry": {"coordinates":[-83.03784899999999,40.727251],"type":"Point"}
}