{
  "type": "Feature",
  "properties": {
    "addr:full":"312 Dussel Dr Maumee OH 43537",
    "addr:housenumber":"312",
    "addr:postcode":"43537",
    "addr:street":"Dussel Dr",
    "iso:country":"US",
    "sg:address":"312 Dussel Dr",
    "sg:city":"Maumee",
    "sg:classifiers":[
        {
            "category":"Retail",
            "subcategory":"Auto Rental",
            "type":"Services"
        }
    ],
    "sg:phone":"+1 419 891 1233",
    "sg:postcode":"43537",
    "sg:province":"OH",
    "sg:tags":[
        "renting",
        "automobile"
    ],
    "wof:name":"Enterprise Rent A Car",
    "wof:placetype":"venue"
},
  "geometry": {"coordinates":[-83.664998,41.58538],"type":"Point"}
}