{
  "type": "Feature",
  "properties": {
    "addr:full": "5709 Laubert Rd Atwater OH 44201",
    "addr:housenumber": "5709",
    "addr:postcode": "44201",
    "addr:street": "Laubert Rd",
    "iso:country": "US",
    "sg:address": "5709 Laubert Rd",
    "sg:city": "Atwater",
    "sg:classifiers": [
      {
        "category": "Building \u0026 Trades",
        "subcategory": "Construction",
        "type": "Services"
      }
    ],
    "sg:phone": "+1 330 947 2461",
    "sg:postcode": "44201",
    "sg:province": "OH",
    "sg:tags": [
      "excavation",
      "contractor"
    ],
    "wof:name": "Jeh Excavating",
    "wof:placetype": "venue"
  },
  "geometry": {"coordinates":[-81.188973,40.997007],"type":"Point"}
}
