{
  "type": "Feature",
  "properties": {
    "addr:full": "130 N Breiel Blvd Middletown OH 45042",
    "addr:housenumber": "130",
    "addr:postcode": "45042",
    "addr:street": "N Breiel Blvd",
    "iso:country": "US",
    "sg:address": "130 N Breiel Blvd",
    "sg:city": "Middletown",
    "sg:classifiers": [
      {
        "category": "Health Services",
        "subcategory": "Doctor",
        "type": "Services"
      }
    ],
    "sg:phone": "+1 513 424 5349",
    "sg:postcode": "45042",
    "sg:province": "OH",
    "wof:name": "J T Johnson Jr DDS",
    "wof:placetype": "venue"
  },
  "geometry": {"coordinates":[-84.354621,39.510636],"type":"Point"}
}
