{
  "type": "Feature",
  "properties": {
    "iso:country":"US",
    "sg:address":"130 N Breiel Blvd",
    "sg:city":"Middletown",
    "sg:classifiers":[
        {
            "category":"Health Services",
            "subcategory":"Doctor",
            "type":"Services"
        }
    ],
    "sg:phone":"+1 513 424 5349",
    "sg:postcode":"45042",
    "sg:province":"OH",
    "wof:name":"J T Johnson Jr DDS",
    "wof:placetype":"venue"
},
  "geometry": {"coordinates":[-84.35462099999999,39.510636],"type":"Point"}
}