{
  "type": "Feature",
  "properties": {
    "addr:full": "511 E Main St Greenville OH 45331",
    "addr:housenumber": "511",
    "addr:postcode": "45331",
    "addr:street": "E Main St",
    "iso:country": "US",
    "sg:address": "511 E Main St",
    "sg:city": "Greenville",
    "sg:classifiers": [
      {
        "category": "Real Estate",
        "subcategory": "Real Estate Agent",
        "type": "Services"
      }
    ],
    "sg:phone": "+1 937 548 6060",
    "sg:postcode": "45331",
    "sg:province": "OH",
    "wof:name": "Treaty Realty Inc",
    "wof:placetype": "venue"
  },
  "geometry": {"coordinates":[-84.627799,40.106006],"type":"Point"}
}
