{
  "type": "Feature",
  "properties": {
    "addr:full": "67800 Pine Ln Saint Clairsville OH 43950",
    "addr:housenumber": "67800",
    "addr:postcode": "43950",
    "addr:street": "Pine Ln Saint",
    "iso:country": "US",
    "sg:address": "67800 Pine Ln",
    "sg:city": "Saint Clairsville",
    "sg:classifiers": [
      {
        "category": "Wholesale",
        "subcategory": "Machinery \u0026 Supplies",
        "type": "Manufacturing \u0026 Wholesale Goods"
      }
    ],
    "sg:phone": "+1 740 695 5895",
    "sg:postcode": "43950",
    "sg:province": "OH",
    "sg:tags": [
      "wa",
      "wash",
      "car",
      "self",
      "operates",
      "equipment"
    ],
    "wof:name": "Tri Valley Equipment Sales",
    "wof:placetype": "venue"
  },
  "geometry": {"coordinates":[-80.951671,40.072304],"type":"Point"}
}
