{
  "type": "Feature",
  "properties": {
    "iso:country":"US",
    "sg:address":"67800 Pine Ln",
    "sg:city":"Saint Clairsville",
    "sg:classifiers":[
        {
            "category":"Wholesale",
            "subcategory":"Machinery & Supplies",
            "type":"Manufacturing & Wholesale Goods"
        }
    ],
    "sg:phone":"+1 740 695 5895",
    "sg:postcode":"43950",
    "sg:province":"OH",
    "sg:tags":[
        "wa",
        "wash",
        "car",
        "self",
        "operates",
        "equipment"
    ],
    "wof:name":"Tri Valley Equipment Sales",
    "wof:placetype":"venue"
},
  "geometry": {"coordinates":[-80.951671,40.072304],"type":"Point"}
}