{
  "type": "Feature",
  "properties": {
    "iso:country":"US",
    "sg:address":"11118 Hamilton Ave",
    "sg:city":"Cincinnati",
    "sg:classifiers":[
        {
            "category":"Ice Cream",
            "type":"Food & Drink"
        }
    ],
    "sg:menulink":"http://www.allmenus.com/oh/forest-park/175643-dairy-queen/menu/",
    "sg:phone":"+1 513 825 3111",
    "sg:postcode":"45231",
    "sg:province":"OH",
    "sg:tags":[
        "burger",
        "american"
    ],
    "wof:name":"Dairy Queen",
    "wof:placetype":"venue"
},
  "geometry": {"coordinates":[-84.563799,39.280875],"type":"Point"}
}