{
  "type": "Feature",
  "properties": {
    "addr:full":"90 N Diamond St Mansfield OH 44902",
    "addr:housenumber":"90",
    "addr:postcode":"44902",
    "addr:street":"N Diamond St",
    "iso:country":"US",
    "sg:address":"90 N Diamond St",
    "sg:city":"Mansfield",
    "sg:classifiers":[
        {
            "category":"Shopping",
            "subcategory":"Pharmacy",
            "type":"Retail Goods"
        }
    ],
    "sg:phone":"+1 419 524 0521",
    "sg:postcode":"44902",
    "sg:province":"OH",
    "sg:tags":[
        "supply",
        "hospital",
        "drug",
        "surgical",
        "rent",
        "home",
        "heal",
        "store"
    ],
    "wof:name":"Hursh IV Associates",
    "wof:placetype":"venue"
},
  "geometry": {"coordinates":[-82.513842,40.760611],"type":"Point"}
}