{
  "type": "Feature",
  "properties": {
    "addr:full": "7586 Doty Rd Madison OH 44057",
    "addr:housenumber": "7586",
    "addr:postcode": "44057",
    "addr:street": "Doty Rd",
    "iso:country": "US",
    "sg:address": "7586 Doty Rd",
    "sg:city": "Madison",
    "sg:classifiers": [
      {
        "category": "Farming",
        "subcategory": "Vineyard",
        "type": "Manufacturing \u0026 Wholesale Goods"
      }
    ],
    "sg:phone": "+1 440 466 1376",
    "sg:postcode": "44057",
    "sg:province": "OH",
    "sg:tags": [
      "grape"
    ],
    "wof:name": "Stephen Burk",
    "wof:placetype": "venue"
  },
  "geometry": {"coordinates":[-81.014529,41.740682],"type":"Point"}
}
