{
  "type": "Feature",
  "properties": {
    "iso:country":"US",
    "sg:address":"1024 S Bon Aire Ave",
    "sg:city":"Tiffin",
    "sg:classifiers":[
        {
            "category":"Shopping",
            "subcategory":"News",
            "type":"Retail Goods"
        }
    ],
    "sg:phone":"+1 419 447 3822",
    "sg:postcode":"44883",
    "sg:province":"OH",
    "sg:tags":[
        "dealer"
    ],
    "wof:name":"Tiffin News Agency",
    "wof:placetype":"venue"
},
  "geometry": {"coordinates":[-83.205915,41.10759],"type":"Point"}
}