{
  "type": "Feature",
  "properties": {
    "addr:full":"7796 Montgomery Rd Cincinnati OH 45236",
    "addr:housenumber":"7796",
    "addr:postcode":"45236",
    "addr:street":"Montgomery Rd",
    "iso:country":"US",
    "sg:address":"7796 Montgomery Rd",
    "sg:city":"Cincinnati",
    "sg:classifiers":[
        {
            "category":"Shopping",
            "subcategory":"Hobbies, Toys, & Games",
            "type":"Retail Goods"
        }
    ],
    "sg:phone":"+1 513 891 7487",
    "sg:postcode":"45236",
    "sg:province":"OH",
    "wof:name":"Pit Row Hobbies",
    "wof:placetype":"venue"
},
  "geometry": {"coordinates":[-84.381624,39.198297],"type":"Point"}
}