{
  "type": "Feature",
  "properties": {
    "addr:full": "297 Deo Dr Newark OH 43055",
    "addr:housenumber": "297",
    "addr:postcode": "43055",
    "addr:street": "Deo Dr",
    "iso:country": "US",
    "sg:address": "297 Deo Dr",
    "sg:city": "Newark",
    "sg:classifiers": [
      {
        "category": "Banks \u0026 Credit Unions",
        "subcategory": "Bank",
        "type": "Services"
      }
    ],
    "sg:phone": "+1 740 364 1928",
    "sg:postcode": "43055",
    "sg:province": "OH",
    "sg:tags": [
      "depository",
      "banking"
    ],
    "wof:name": "First American Cash Advance",
    "wof:placetype": "venue"
  },
  "geometry": {"coordinates":[-82.420498,40.086053],"type":"Point"}
}
