{
  "type": "Feature",
  "properties": {
    "iso:country":"US",
    "sg:address":"297 Deo Dr",
    "sg:city":"Newark",
    "sg:classifiers":[
        {
            "category":"Banks & Credit Unions",
            "subcategory":"Bank",
            "type":"Services"
        }
    ],
    "sg:phone":"+1 740 364 1928",
    "sg:postcode":"43055",
    "sg:province":"OH",
    "sg:tags":[
        "depository",
        "banking"
    ],
    "wof:name":"First American Cash Advance",
    "wof:placetype":"venue"
},
  "geometry": {"coordinates":[-82.42049799999999,40.086053],"type":"Point"}
}