{
  "type": "Feature",
  "properties": {
    "addr:full":"220 W Main St Ravenna OH 44266",
    "addr:housenumber":"220",
    "addr:postcode":"44266",
    "addr:street":"W Main St",
    "iso:country":"US",
    "sg:address":"220 W Main St",
    "sg:city":"Ravenna",
    "sg:classifiers":[
        {
            "category":"Social Services",
            "type":"Services"
        }
    ],
    "sg:phone":"+1 330 296 6655",
    "sg:postcode":"44266",
    "sg:province":"OH",
    "sg:tags":[
        "organization",
        "mentoring",
        "welfare"
    ],
    "wof:name":"Big Brothers & Big Sisters",
    "wof:placetype":"venue"
},
  "geometry": {"coordinates":[-81.24471699999999,41.157813],"type":"Point"}
}