{
  "type": "Feature",
  "properties": {
    "addr:full":"2191 S Cleveland Massillon Rd Copley OH 44321",
    "addr:housenumber":"2191",
    "addr:postcode":"44321",
    "addr:street":"S Cleveland Massillon Rd",
    "iso:country":"US",
    "sg:address":"2191 S Cleveland Massillon Rd",
    "sg:city":"Copley",
    "sg:classifiers":[
        {
            "category":"Local Transit",
            "type":"Transportation"
        }
    ],
    "sg:phone":"+1 330 670 6491",
    "sg:postcode":"44321",
    "sg:province":"OH",
    "sg:tags":[
        "limousine"
    ],
    "wof:name":"City Lights Limousine Svc",
    "wof:placetype":"venue"
},
  "geometry": {"coordinates":[-81.64263099999999,41.081072],"type":"Point"}
}