{
  "type": "Feature",
  "properties": {
    "addr:full":"11444 Brookpark Rd Cleveland OH 44130",
    "addr:housenumber":"11444",
    "addr:postcode":"44130",
    "addr:street":"Brookpark Rd",
    "iso:country":"US",
    "sg:address":"11444 Brookpark Rd",
    "sg:city":"Cleveland",
    "sg:classifiers":[
        {
            "category":"Building & Trades",
            "subcategory":"Cleaning & Sanitation",
            "type":"Services"
        },
        {
            "category":"Utilities",
            "type":"Services"
        }
    ],
    "sg:phone":"+1 216 267 4516",
    "sg:postcode":"44130",
    "sg:province":"OH",
    "sg:tags":[
        "sanitary",
        "snow",
        "removal"
    ],
    "wof:name":"Abraxus Snow Removal Inc",
    "wof:placetype":"venue"
},
  "geometry": {"coordinates":[-81.763468,41.418504],"type":"Point"}
}