{
  "type": "Feature",
  "properties": {
    "addr:full": "50 W Broad St Columbus OH 43215",
    "addr:housenumber": "50",
    "addr:postcode": "43215",
    "addr:street": "W Broad St",
    "iso:country": "US",
    "sg:address": "50 W Broad St",
    "sg:city": "Columbus",
    "sg:classifiers": [
      {
        "category": "Restaurant",
        "type": "Food \u0026 Drink"
      }
    ],
    "sg:phone": "+1 614 224 8922",
    "sg:postcode": "43215",
    "sg:province": "OH",
    "sg:tags": [
      "eating"
    ],
    "wof:name": "Roger's Cafe",
    "wof:placetype": "venue"
  },
  "geometry": {"coordinates":[-83.001973,39.962163],"type":"Point"}
}
