{
  "type": "Feature",
  "properties": {
    "addr:full": "513 Yates St Williamsport OH 43164",
    "addr:housenumber": "513",
    "addr:postcode": "43164",
    "addr:street": "Yates St",
    "iso:country": "US",
    "sg:address": "513 Yates St",
    "sg:city": "Williamsport",
    "sg:classifiers": [
      {
        "category": "Building \u0026 Trades",
        "subcategory": "Construction",
        "type": "Services"
      }
    ],
    "sg:phone": "+1 740 986 9027",
    "sg:postcode": "43164",
    "sg:province": "OH",
    "sg:tags": [
      "general",
      "contractor"
    ],
    "wof:name": "Pence Quality Construction",
    "wof:placetype": "venue"
  },
  "geometry": {"coordinates":[-83.118872,39.576283],"type":"Point"}
}
