{
  "type": "Feature",
  "properties": {
    "iso:country":"US",
    "sg:address":"513 Yates St",
    "sg:city":"Williamsport",
    "sg:classifiers":[
        {
            "category":"Building & Trades",
            "subcategory":"Construction",
            "type":"Services"
        }
    ],
    "sg:phone":"+1 740 986 9027",
    "sg:postcode":"43164",
    "sg:province":"OH",
    "sg:tags":[
        "general",
        "contractor"
    ],
    "wof:name":"Pence Quality Construction",
    "wof:placetype":"venue"
},
  "geometry": {"coordinates":[-83.118872,39.576283],"type":"Point"}
}