{
  "type": "Feature",
  "properties": {
    "iso:country":"US",
    "sg:address":"1880 Tewksbury Rd",
    "sg:city":"Columbus",
    "sg:classifiers":[
        {
            "category":"Shopping",
            "subcategory":"Computers & Home Electronics",
            "type":"Retail Goods"
        }
    ],
    "sg:phone":"+1 614 481 3444",
    "sg:postcode":"43221",
    "sg:province":"OH",
    "sg:tags":[
        "software"
    ],
    "wof:name":"Cobox",
    "wof:placetype":"venue"
},
  "geometry": {"coordinates":[-83.059212,40.004321],"type":"Point"}
}