{
  "type": "Feature",
  "properties": {
    "addr:full": "1880 Tewksbury Rd Columbus OH 43221",
    "addr:postcode": "1880;43221",
    "addr:street": "Tewksbury Rd",
    "iso:country": "US",
    "sg:address": "1880 Tewksbury Rd",
    "sg:city": "Columbus",
    "sg:classifiers": [
      {
        "category": "Shopping",
        "subcategory": "Computers \u0026 Home Electronics",
        "type": "Retail Goods"
      }
    ],
    "sg:phone": "+1 614 481 3444",
    "sg:postcode": "43221",
    "sg:province": "OH",
    "sg:tags": [
      "software"
    ],
    "wof:name": "Cobox",
    "wof:placetype": "venue"
  },
  "geometry": {"coordinates":[-83.059212,40.004321],"type":"Point"}
}
