{
  "type": "Feature",
  "properties": {
    "iso:country":"US",
    "sg:address":"501 W Broadway St",
    "sg:city":"Maumee",
    "sg:classifiers":[
        {
            "category":"Building & Trades",
            "subcategory":"Construction",
            "type":"Services"
        }
    ],
    "sg:phone":"+1 419 893 1614",
    "sg:postcode":"43537",
    "sg:province":"OH",
    "sg:tags":[
        "house"
    ],
    "wof:name":"Marc Adams Construction",
    "wof:placetype":"venue"
},
  "geometry": {"coordinates":[-83.66156,41.558402],"type":"Point"}
}