{
  "type": "Feature",
  "properties": {
    "addr:full": "501 W Broadway St Maumee OH 43537",
    "addr:housenumber": "501",
    "addr:postcode": "43537",
    "addr:street": "W Broadway St",
    "iso:country": "US",
    "sg:address": "501 W Broadway St",
    "sg:city": "Maumee",
    "sg:classifiers": [
      {
        "category": "Building \u0026 Trades",
        "subcategory": "Construction",
        "type": "Services"
      }
    ],
    "sg:phone": "+1 419 893 1614",
    "sg:postcode": "43537",
    "sg:province": "OH",
    "sg:tags": [
      "house"
    ],
    "wof:name": "Marc Adams Construction",
    "wof:placetype": "venue"
  },
  "geometry": {"coordinates":[-83.66156,41.558402],"type":"Point"}
}
