{
  "type": "Feature",
  "properties": {
    "iso:country":"US",
    "sg:address":"850 Johnston St",
    "sg:city":"Akron",
    "sg:classifiers":[
        {
            "category":"Building & Trades",
            "subcategory":"Construction",
            "type":"Services"
        }
    ],
    "sg:phone":"+1 330 253 9321",
    "sg:postcode":"44306",
    "sg:province":"OH",
    "sg:tags":[
        "house"
    ],
    "wof:name":"Leidal Construction",
    "wof:placetype":"venue"
},
  "geometry": {"coordinates":[-81.499611,41.067125],"type":"Point"}
}