{
  "type": "Feature",
  "properties": {
    "addr:full":"1717 Section Rd Cincinnati OH 45237",
    "addr:housenumber":"1717",
    "addr:postcode":"45237",
    "addr:street":"Section Rd",
    "iso:country":"US",
    "sg:address":"1717 Section Rd",
    "sg:city":"Cincinnati",
    "sg:classifiers":[
        {
            "category":"Professional",
            "subcategory":"Management & Consulting",
            "type":"Services"
        }
    ],
    "sg:phone":"+1 513 631 8998",
    "sg:postcode":"45237",
    "sg:province":"OH",
    "sg:tags":[
        "consultant",
        "safety"
    ],
    "wof:name":"Clifford Consulting",
    "wof:placetype":"venue"
},
  "geometry": {"coordinates":[-84.45764800000001,39.197243],"type":"Point"}
}