{
  "type": "Feature",
  "properties": {
    "iso:country":"US",
    "sg:address":"2744 Green Rd",
    "sg:city":"Cleveland",
    "sg:classifiers":[
        {
            "category":"Real Estate",
            "subcategory":"Architect",
            "type":"Services"
        }
    ],
    "sg:phone":"+1 216 378 2800",
    "sg:postcode":"44122",
    "sg:province":"OH",
    "wof:name":"Edward H Swick & Assoc",
    "wof:placetype":"venue"
},
  "geometry": {"coordinates":[-81.517121,41.482996],"type":"Point"}
}