{
  "type": "Feature",
  "properties": {
    "iso:country":"US",
    "sg:address":"25705 Chagrin Blvd",
    "sg:city":"Beachwood",
    "sg:classifiers":[
        {
            "category":"Restaurant",
            "type":"Food & Drink"
        }
    ],
    "sg:menulink":"http://www.allmenus.com/oh/beachwood/134372-subway/menu/",
    "sg:phone":"+1 216 464 6115",
    "sg:postcode":"44122",
    "sg:province":"OH",
    "sg:tags":[
        "american",
        "sandwich"
    ],
    "wof:name":"Subway",
    "wof:placetype":"venue"
},
  "geometry": {"coordinates":[-81.497528,41.4648],"type":"Point"}
}