{
  "type": "Feature",
  "properties": {
    "iso:country":"US",
    "sg:address":"246 E Hudson St",
    "sg:city":"Toledo",
    "sg:classifiers":[
        {
            "category":"Retail",
            "subcategory":"Car Wash",
            "type":"Services"
        }
    ],
    "sg:phone":"+1 419 244 1741",
    "sg:postcode":"43608",
    "sg:province":"OH",
    "sg:tags":[
        "automobile",
        "detail",
        "clean"
    ],
    "wof:name":"Ramone J Green",
    "wof:placetype":"venue"
},
  "geometry": {"coordinates":[-83.540345,41.683111],"type":"Point"}
}