{
  "type": "Feature",
  "properties": {
    "addr:full":"119 N Miami St West Milton OH 45383",
    "addr:housenumber":"119",
    "addr:postcode":"45383",
    "addr:street":"N Miami St West",
    "iso:country":"US",
    "sg:address":"119 N Miami St",
    "sg:city":"West Milton",
    "sg:classifiers":[
        {
            "category":"Manufacturing",
            "subcategory":"Printing",
            "type":"Manufacturing & Wholesale Goods"
        }
    ],
    "sg:phone":"+1 937 698 3619",
    "sg:postcode":"45383",
    "sg:province":"OH",
    "sg:tags":[
        "publisher"
    ],
    "wof:name":"Bookworks Inc",
    "wof:placetype":"venue"
},
  "geometry": {"coordinates":[-84.32838099999999,39.963955],"type":"Point"}
}