{
  "type": "Feature",
  "properties": {
    "iso:country":"US",
    "sg:address":"601 W South Range Rd",
    "sg:city":"North Lima",
    "sg:classifiers":[
        {
            "category":"Government",
            "subcategory":"Office",
            "type":"Public Place"
        }
    ],
    "sg:phone":"+1 330 549 5338",
    "sg:postcode":"44452",
    "sg:province":"OH",
    "sg:tags":[
        "executive"
    ],
    "wof:name":"Beaver Township Government",
    "wof:placetype":"venue"
},
  "geometry": {"coordinates":[-80.664676,40.943945],"type":"Point"}
}