{
  "type": "Feature",
  "properties": {
    "addr:full": "14260 Ellett Rd Beloit OH 44609",
    "addr:postcode": "14260;44609",
    "addr:street": "Ellett Rd",
    "iso:country": "US",
    "sg:address": "14260 Ellett Rd",
    "sg:city": "Beloit",
    "sg:classifiers": [
      {
        "category": "Building \u0026 Trades",
        "subcategory": "Construction",
        "type": "Services"
      }
    ],
    "sg:phone": "+1 330 537 2557",
    "sg:postcode": "44609",
    "sg:province": "OH",
    "sg:tags": [
      "excavating",
      "contractor"
    ],
    "wof:name": "Don's Excavating \u0026 Truck Inc",
    "wof:placetype": "venue"
  },
  "geometry": {"coordinates":[-80.983116,40.912649],"type":"Point"}
}
