{
  "type": "Feature",
  "properties": {
    "iso:country":"US",
    "sg:address":"7555 E Pleasant Valley Rd",
    "sg:city":"Cleveland",
    "sg:classifiers":[
        {
            "category":"Professional",
            "subcategory":"Advertising",
            "type":"Services"
        }
    ],
    "sg:phone":"+1 216 642 1212",
    "sg:postcode":"44131",
    "sg:province":"OH",
    "sg:tags":[
        "mailing",
        "shipping"
    ],
    "wof:name":"International Mailing Systems",
    "wof:placetype":"venue"
},
  "geometry": {"coordinates":[-81.619382,41.361587],"type":"Point"}
}