{
  "type": "Feature",
  "properties": {
    "addr:full": "11629 Euclid Ave Cleveland OH 44106",
    "addr:housenumber": "11629",
    "addr:postcode": "44106",
    "addr:street": "Euclid Ave",
    "iso:country": "US",
    "sg:address": "11629 Euclid Ave",
    "sg:city": "Cleveland",
    "sg:classifiers": [
      {
        "category": "Bars \u0026 Pubs",
        "type": "Food \u0026 Drink"
      }
    ],
    "sg:phone": "+1 216 229 7788",
    "sg:postcode": "44106",
    "sg:province": "OH",
    "sg:tags": [
      "drinking",
      "eating"
    ],
    "wof:name": "Euclid Tavern",
    "wof:placetype": "venue"
  },
  "geometry": {"coordinates":[-81.601718,41.511844],"type":"Point"}
}
