{
  "type": "Feature",
  "properties": {
    "iso:country":"US",
    "sg:address":"11629 Euclid Ave",
    "sg:city":"Cleveland",
    "sg:classifiers":[
        {
            "category":"Bars & Pubs",
            "type":"Food & Drink"
        }
    ],
    "sg:phone":"+1 216 229 7788",
    "sg:postcode":"44106",
    "sg:province":"OH",
    "sg:tags":[
        "drinking",
        "eating"
    ],
    "wof:name":"Euclid Tavern",
    "wof:placetype":"venue"
},
  "geometry": {"coordinates":[-81.601718,41.511844],"type":"Point"}
}