{
  "type": "Feature",
  "properties": {
    "iso:country":"US",
    "sg:address":"1311 Keystover Trl",
    "sg:city":"Dayton",
    "sg:classifiers":[
        {
            "category":"Taxi",
            "type":"Transportation"
        }
    ],
    "sg:phone":"+1 937 435 7433",
    "sg:postcode":"45459",
    "sg:province":"OH",
    "sg:tags":[
        "taxicab"
    ],
    "wof:name":"B G Taxi",
    "wof:placetype":"venue"
},
  "geometry": {"coordinates":[-84.130768,39.653693],"type":"Point"}
}