{
  "type": "Feature",
  "properties": {
    "iso:country":"US",
    "sg:address":"1418 Morgan Center Rd",
    "sg:city":"Utica",
    "sg:classifiers":[
        {
            "category":"Farming",
            "subcategory":"Livestock Farm",
            "type":"Manufacturing & Wholesale Goods"
        }
    ],
    "sg:phone":"+1 740 892 2046",
    "sg:postcode":"43080",
    "sg:province":"OH",
    "sg:tags":[
        "beef",
        "feedlot",
        "cattle"
    ],
    "wof:name":"Bruce Butcher",
    "wof:placetype":"venue"
},
  "geometry": {"coordinates":[-82.410988,40.253684],"type":"Point"}
}