{
  "type": "Feature",
  "properties": {
    "addr:full": "56 Stroup Rd Atwater OH 44201",
    "addr:housenumber": "56",
    "addr:postcode": "44201",
    "addr:street": "Stroup Rd",
    "iso:country": "US",
    "sg:address": "56 Stroup Rd",
    "sg:city": "Atwater",
    "sg:phone": "+1 330 947 2794",
    "sg:postcode": "44201",
    "sg:province": "OH",
    "sg:tags": [
      "farm",
      "corn",
      "soybean"
    ],
    "wof:name": "Lloyd Myers",
    "wof:placetype": "venue"
  },
  "geometry": {"coordinates":[-81.172018,40.991391],"type":"Point"}
}
