{
  "type": "Feature",
  "properties": {
    "addr:full": "6330 York Rd Cleveland OH 44130",
    "addr:housenumber": "6330",
    "addr:postcode": "44130",
    "addr:street": "York Rd",
    "iso:country": "US",
    "sg:address": "6330 York Rd",
    "sg:city": "Cleveland",
    "sg:classifiers": [
      {
        "category": "Retail",
        "subcategory": "Auto Repair",
        "type": "Services"
      }
    ],
    "sg:phone": "+1 440 885 2101",
    "sg:postcode": "44130",
    "sg:province": "OH",
    "sg:tags": [
      "repairing",
      "automobile"
    ],
    "wof:name": "Midas Auto Svc Experts",
    "wof:placetype": "venue"
  },
  "geometry": {"coordinates":[-81.759695,41.381992],"type":"Point"}
}
