{
  "type": "Feature",
  "properties": {
    "iso:country":"US",
    "sg:address":"6330 York Rd",
    "sg:city":"Cleveland",
    "sg:classifiers":[
        {
            "category":"Retail",
            "subcategory":"Auto Repair",
            "type":"Services"
        }
    ],
    "sg:phone":"+1 440 885 2101",
    "sg:postcode":"44130",
    "sg:province":"OH",
    "sg:tags":[
        "repairing",
        "automobile"
    ],
    "wof:name":"Midas Auto Svc Experts",
    "wof:placetype":"venue"
},
  "geometry": {"coordinates":[-81.75969499999999,41.381992],"type":"Point"}
}