{
  "type": "Feature",
  "properties": {
    "iso:country":"US",
    "sg:address":"7589 Race Rd",
    "sg:city":"Elyria",
    "sg:classifiers":[
        {
            "category":"Manufacturing",
            "subcategory":"Metals",
            "type":"Manufacturing & Wholesale Goods"
        }
    ],
    "sg:phone":"+1 440 353 0650",
    "sg:postcode":"44039",
    "sg:province":"OH",
    "sg:tags":[
        "manufacture",
        "heater",
        "oil",
        "heating",
        "equipment",
        "waste"
    ],
    "wof:name":"Compu Heat Inc",
    "wof:placetype":"venue"
},
  "geometry": {"coordinates":[-82.044291,41.381276],"type":"Point"}
}