{
  "type": "Feature",
  "properties": {
    "iso:country":"US",
    "sg:address":"1129 E Weber Rd",
    "sg:city":"Columbus",
    "sg:classifiers":[
        {
            "category":"Autos & Motor Vehicles",
            "subcategory":"Automobile Sales",
            "type":"Retail Goods"
        }
    ],
    "sg:phone":"+1 614 263 8500",
    "sg:postcode":"43211",
    "sg:province":"OH",
    "sg:tags":[
        "grill",
        "used"
    ],
    "wof:name":"M & M Motors",
    "wof:placetype":"venue"
},
  "geometry": {"coordinates":[-82.982285,40.023452],"type":"Point"}
}