{
  "type": "Feature",
  "properties": {
    "iso:country":"US",
    "sg:address":"11415 Century Cir W",
    "sg:city":"Cincinnati",
    "sg:classifiers":[
        {
            "category":"Professional",
            "subcategory":"Computer Services",
            "type":"Services"
        }
    ],
    "sg:phone":"+1 513 671 2234",
    "sg:postcode":"45246",
    "sg:province":"OH",
    "sg:tags":[
        "consultant",
        "designer"
    ],
    "wof:name":"Business Systems Integrated",
    "wof:placetype":"venue"
},
  "geometry": {"coordinates":[-84.454642,39.282067],"type":"Point"}
}