{
  "type": "Feature",
  "properties": {
    "addr:full": "10333 Northfield Rd Northfield OH 44067",
    "addr:housenumber": "10333",
    "addr:postcode": "44067",
    "addr:street": "Northfield Rd",
    "iso:country": "US",
    "sg:address": "10333 Northfield Rd",
    "sg:city": "Northfield",
    "sg:classifiers": [
      {
        "category": "Shopping",
        "subcategory": "Discount \u0026 Variety Stores",
        "type": "Retail Goods"
      }
    ],
    "sg:phone": "+1 330 468 5266",
    "sg:postcode": "44067",
    "sg:province": "OH",
    "wof:name": "Dollar General",
    "wof:placetype": "venue"
  },
  "geometry": {"coordinates":[-81.529767,41.33955],"type":"Point"}
}
