{
  "type": "Feature",
  "properties": {
    "iso:country":"US",
    "sg:address":"10333 Northfield Rd",
    "sg:city":"Northfield",
    "sg:classifiers":[
        {
            "category":"Shopping",
            "subcategory":"Discount & Variety Stores",
            "type":"Retail Goods"
        }
    ],
    "sg:phone":"+1 330 468 5266",
    "sg:postcode":"44067",
    "sg:province":"OH",
    "wof:name":"Dollar General",
    "wof:placetype":"venue"
},
  "geometry": {"coordinates":[-81.52976700000001,41.33955],"type":"Point"}
}