{
  "type": "Feature",
  "properties": {
    "addr:full":"1324 W Alexis Rd Toledo OH 43612",
    "addr:housenumber":"1324",
    "addr:postcode":"43612",
    "addr:street":"W Alexis Rd",
    "iso:country":"US",
    "sg:address":"1324 W Alexis Rd",
    "sg:city":"Toledo",
    "sg:classifiers":[
        {
            "category":"Freight",
            "type":"Transportation"
        }
    ],
    "sg:phone":"+1 419 476 1400",
    "sg:postcode":"43612",
    "sg:province":"OH",
    "sg:tags":[
        "commercial",
        "storage"
    ],
    "wof:name":"A Plus Self Storage",
    "wof:placetype":"venue"
},
  "geometry": {"coordinates":[-83.574124,41.721489],"type":"Point"}
}