{
  "type": "Feature",
  "properties": {
    "addr:full": "3431 Tremaine Rd Columbus OH 43232",
    "addr:housenumber": "3431",
    "addr:postcode": "43232",
    "addr:street": "Tremaine Rd",
    "iso:country": "US",
    "sg:address": "3431 Tremaine Rd",
    "sg:city": "Columbus",
    "sg:classifiers": [
      {
        "category": "Local Transit",
        "type": "Transportation"
      }
    ],
    "sg:phone": "+1 614 834 4390",
    "sg:postcode": "43232",
    "sg:province": "OH",
    "sg:tags": [
      "passenger"
    ],
    "wof:name": "All Occasion Limousine",
    "wof:placetype": "venue"
  },
  "geometry": {"coordinates":[-82.863818,39.906738],"type":"Point"}
}
