{
  "type": "Feature",
  "properties": {
    "iso:country":"US",
    "sg:address":"740 Emerald Rd",
    "sg:city":"Paulding",
    "sg:classifiers":[
        {
            "category":"Professional",
            "type":"Services"
        }
    ],
    "sg:phone":"+1 419 399 3328",
    "sg:postcode":"45879",
    "sg:province":"OH",
    "sg:tags":[
        "establishment"
    ],
    "wof:name":"Dannaley's Eats' N Treats",
    "wof:placetype":"venue"
},
  "geometry": {"coordinates":[-84.574027,41.148133],"type":"Point"}
}