{
  "type": "Feature",
  "properties": {
    "addr:full": "13982 Carey Ln Danville OH 43014",
    "addr:housenumber": "13982",
    "addr:postcode": "43014",
    "addr:street": "Carey Ln",
    "iso:country": "US",
    "sg:address": "13982 Carey Ln",
    "sg:city": "Danville",
    "sg:classifiers": [
      {
        "category": "Manufacturing",
        "subcategory": "Furniture",
        "type": "Manufacturing \u0026 Wholesale Goods"
      }
    ],
    "sg:phone": "+1 740 599 7615",
    "sg:postcode": "43014",
    "sg:province": "OH",
    "sg:tags": [
      "household",
      "wood",
      "mfg"
    ],
    "wof:name": "Davids Wood Shop",
    "wof:placetype": "venue"
  },
  "geometry": {"coordinates":[-82.280182,40.430116],"type":"Point"}
}
