{
  "type": "Feature",
  "properties": {
    "addr:full":"274 S 6th St Newark OH 43055",
    "addr:housenumber":"274",
    "addr:postcode":"43055",
    "addr:street":"S 6Th St",
    "iso:country":"US",
    "sg:address":"274 S 6th St",
    "sg:city":"Newark",
    "sg:classifiers":[
        {
            "category":"Retail",
            "subcategory":"Repair Shop",
            "type":"Services"
        },
        {
            "category":"Building & Trades",
            "subcategory":"Plumbing",
            "type":"Services"
        }
    ],
    "sg:phone":"+1 740 366 3255",
    "sg:postcode":"43055",
    "sg:province":"OH",
    "sg:tags":[
        "tank",
        "cleaning",
        "septic"
    ],
    "wof:name":"Jacks Septic Tank Cleaning &",
    "wof:placetype":"venue"
},
  "geometry": {"coordinates":[-82.405929,40.049867],"type":"Point"}
}