{
  "type": "Feature",
  "properties": {
    "addr:full": "16 W Pleasant St Cincinnati OH 45215",
    "addr:housenumber": "16",
    "addr:postcode": "45215",
    "addr:street": "W Pleasant St",
    "iso:country": "US",
    "sg:address": "16 W Pleasant St",
    "sg:city": "Cincinnati",
    "sg:classifiers": [
      {
        "category": "Retail",
        "subcategory": "Auto Repair",
        "type": "Services"
      }
    ],
    "sg:phone": "+1 513 733 8526",
    "sg:postcode": "45215",
    "sg:province": "OH",
    "sg:tags": [
      "repairing",
      "automobile"
    ],
    "wof:name": "Stall's Auto Repair",
    "wof:placetype": "venue"
  },
  "geometry": {"coordinates":[-84.43869,39.228913],"type":"Point"}
}
