{
  "type": "Feature",
  "properties": {
    "addr:full": "11538 Blott Rd North Jackson OH 44451",
    "addr:housenumber": "11538",
    "addr:postcode": "44451",
    "addr:street": "Blott Rd",
    "iso:country": "US",
    "sg:address": "11538 Blott Rd",
    "sg:city": "North Jackson",
    "sg:classifiers": [
      {
        "category": "Freight",
        "type": "Transportation"
      }
    ],
    "sg:phone": "+1 330 538 3409",
    "sg:postcode": "44451",
    "sg:province": "OH",
    "sg:tags": [
      "local",
      "storage",
      "trucking"
    ],
    "wof:name": "Maxi Enterprises",
    "wof:placetype": "venue"
  },
  "geometry": {"coordinates":[-80.871566,41.076638],"type":"Point"}
}
