{
  "type": "Feature",
  "properties": {
    "addr:full": "2846 Ambarwent Rd Reynoldsburg OH 43068",
    "addr:housenumber": "2846",
    "addr:postcode": "43068",
    "addr:street": "Ambarwent Rd",
    "iso:country": "US",
    "sg:address": "2846 Ambarwent Rd",
    "sg:city": "Reynoldsburg",
    "sg:classifiers": [
      {
        "category": "Building \u0026 Trades",
        "subcategory": "Construction",
        "type": "Services"
      }
    ],
    "sg:phone": "+1 614 575 1010",
    "sg:postcode": "43068",
    "sg:province": "OH",
    "sg:tags": [
      "house"
    ],
    "wof:name": "Mobley Builders/Trinity Homes",
    "wof:placetype": "venue"
  },
  "geometry": {"coordinates":[-82.811386,39.925842],"type":"Point"}
}
