{
  "type": "Feature",
  "properties": {
    "addr:full": "18023 Fernway Rd Cleveland OH 44122",
    "addr:postcode": "18023;44122",
    "addr:street": "Fernway Rd",
    "iso:country": "US",
    "sg:address": "18023 Fernway Rd",
    "sg:city": "Cleveland",
    "sg:classifiers": [
      {
        "category": "Wholesale",
        "subcategory": "Durable Goods \u0026 Equipment",
        "type": "Manufacturing \u0026 Wholesale Goods"
      }
    ],
    "sg:phone": "+1 216 991 6516",
    "sg:postcode": "44122",
    "sg:province": "OH",
    "sg:tags": [
      "representative",
      "manufacturer"
    ],
    "wof:name": "Automated Technologies",
    "wof:placetype": "venue"
  },
  "geometry": {"coordinates":[-81.553063,41.471466],"type":"Point"}
}
