{
  "type": "Feature",
  "properties": {
    "iso:country":"US",
    "sg:address":"18023 Fernway Rd",
    "sg:city":"Cleveland",
    "sg:classifiers":[
        {
            "category":"Wholesale",
            "subcategory":"Durable Goods & Equipment",
            "type":"Manufacturing & Wholesale Goods"
        }
    ],
    "sg:phone":"+1 216 991 6516",
    "sg:postcode":"44122",
    "sg:province":"OH",
    "sg:tags":[
        "representative",
        "manufacturer"
    ],
    "wof:name":"Automated Technologies",
    "wof:placetype":"venue"
},
  "geometry": {"coordinates":[-81.55306299999999,41.471466],"type":"Point"}
}