{
  "type": "Feature",
  "properties": {
    "iso:country":"US",
    "sg:address":"166 E State St",
    "sg:city":"Barberton",
    "sg:classifiers":[
        {
            "category":"Utilities",
            "subcategory":"Mobile Phone",
            "type":"Services"
        },
        {
            "category":"Wholesale",
            "subcategory":"Electrical",
            "type":"Manufacturing & Wholesale Goods"
        }
    ],
    "sg:phone":"+1 330 745 7451",
    "sg:postcode":"44203",
    "sg:province":"OH",
    "sg:tags":[
        "equipment",
        "communication",
        "paging",
        "system",
        "signaling"
    ],
    "sg:website":"www.tricitycomm.com",
    "wof:name":"Tri-City Communications Inc",
    "wof:placetype":"venue"
},
  "geometry": {"coordinates":[-81.58479,41.023927],"type":"Point"}
}