{
  "type": "Feature",
  "properties": {
    "addr:full": "442 W High St Bryan OH 43506",
    "addr:housenumber": "442",
    "addr:postcode": "43506",
    "addr:street": "W High St",
    "iso:country": "US",
    "sg:address": "442 W High St",
    "sg:city": "Bryan",
    "sg:classifiers": [
      {
        "category": "Shopping",
        "subcategory": "Pharmacy",
        "type": "Retail Goods"
      }
    ],
    "sg:phone": "+1 419 636 7314",
    "sg:postcode": "43506",
    "sg:province": "OH",
    "wof:name": "Ringer S Professional Pharmacy",
    "wof:placetype": "venue"
  },
  "geometry": {"coordinates":[-84.556249,41.474683],"type":"Point"}
}
