{
  "type": "Feature",
  "properties": {
    "addr:full":"106 Greenlawn Dr Hicksville OH 43526",
    "addr:housenumber":"106",
    "addr:postcode":"43526",
    "addr:street":"Greenlawn Dr",
    "iso:country":"US",
    "sg:address":"106 Greenlawn Dr",
    "sg:city":"Hicksville",
    "sg:classifiers":[
        {
            "category":"Building & Trades",
            "subcategory":"Electrical",
            "type":"Services"
        }
    ],
    "sg:phone":"+1 419 542 6784",
    "sg:postcode":"43526",
    "sg:province":"OH",
    "sg:tags":[
        "electrical",
        "contractor"
    ],
    "wof:name":"Source One Electrical Flp",
    "wof:placetype":"venue"
},
  "geometry": {"coordinates":[-84.771243,41.300794],"type":"Point"}
}