{
  "type": "Feature",
  "properties": {
    "addr:full": "2296 Kilbourne Ave Columbus OH 43229",
    "addr:housenumber": "2296",
    "addr:postcode": "43229",
    "addr:street": "Kilbourne Ave",
    "iso:country": "US",
    "sg:address": "2296 Kilbourne Ave",
    "sg:city": "Columbus",
    "sg:classifiers": [
      {
        "category": "Banks \u0026 Credit Unions",
        "subcategory": "Investment Brokerage",
        "type": "Services"
      }
    ],
    "sg:phone": "+1 614 882 4499",
    "sg:postcode": "43229",
    "sg:province": "OH",
    "wof:name": "D C Investments",
    "wof:placetype": "venue"
  },
  "geometry": {"coordinates":[-82.958517,40.070197],"type":"Point"}
}
