{
  "type": "Feature",
  "properties": {
    "iso:country":"US",
    "sg:address":"2296 Kilbourne Ave",
    "sg:city":"Columbus",
    "sg:classifiers":[
        {
            "category":"Banks & Credit Unions",
            "subcategory":"Investment Brokerage",
            "type":"Services"
        }
    ],
    "sg:phone":"+1 614 882 4499",
    "sg:postcode":"43229",
    "sg:province":"OH",
    "wof:name":"D C Investments",
    "wof:placetype":"venue"
},
  "geometry": {"coordinates":[-82.958517,40.070197],"type":"Point"}
}