{
  "type": "Feature",
  "properties": {
    "iso:country":"US",
    "sg:address":"4565 Willow Pkwy",
    "sg:city":"Cleveland",
    "sg:classifiers":[
        {
            "category":"Manufacturing",
            "subcategory":"Metals",
            "type":"Manufacturing & Wholesale Goods"
        }
    ],
    "sg:phone":"+1 216 341 7700",
    "sg:postcode":"44125",
    "sg:province":"OH",
    "sg:tags":[
        "windows"
    ],
    "sg:website":"www.stanekwindows.com",
    "wof:name":"E F Stanek & Assoc",
    "wof:placetype":"venue"
},
  "geometry": {"coordinates":[-81.650665,41.435628],"type":"Point"}
}