{
  "type": "Feature",
  "properties": {
    "addr:full": "4565 Willow Pkwy Cleveland OH 44125",
    "addr:housenumber": "4565",
    "addr:postcode": "44125",
    "addr:street": "Willow Pkwy",
    "iso:country": "US",
    "sg:address": "4565 Willow Pkwy",
    "sg:city": "Cleveland",
    "sg:classifiers": [
      {
        "category": "Manufacturing",
        "subcategory": "Metals",
        "type": "Manufacturing \u0026 Wholesale Goods"
      }
    ],
    "sg:phone": "+1 216 341 7700",
    "sg:postcode": "44125",
    "sg:province": "OH",
    "sg:tags": [
      "windows"
    ],
    "sg:website": "www.stanekwindows.com",
    "wof:name": "E F Stanek \u0026 Assoc",
    "wof:placetype": "venue"
  },
  "geometry": {"coordinates":[-81.650665,41.435628],"type":"Point"}
}
