{
  "type": "Feature",
  "properties": {
    "iso:country":"US",
    "sg:address":"110 Ginghamsburg Rd",
    "sg:city":"Tipp City",
    "sg:classifiers":[
        {
            "category":"Retail",
            "subcategory":"Repair Shop",
            "type":"Services"
        }
    ],
    "sg:phone":"+1 937 361 1589",
    "sg:postcode":"45371",
    "sg:province":"OH",
    "sg:tags":[
        "lock",
        "locksmith"
    ],
    "wof:name":"Don's Lock Shop",
    "wof:placetype":"venue"
},
  "geometry": {"coordinates":[-84.195451,39.92935],"type":"Point"}
}