{
  "type": "Feature",
  "properties": {
    "addr:full": "1988 S Main St Mansfield OH 44907",
    "addr:housenumber": "1988",
    "addr:postcode": "44907",
    "addr:street": "S Main St",
    "iso:country": "US",
    "sg:address": "1988 S Main St",
    "sg:city": "Mansfield",
    "sg:classifiers": [
      {
        "category": "Manufacturing",
        "subcategory": "Lumber",
        "type": "Manufacturing \u0026 Wholesale Goods"
      }
    ],
    "sg:phone": "+1 419 756 6787",
    "sg:postcode": "44907",
    "sg:province": "OH",
    "sg:tags": [
      "logging"
    ],
    "wof:name": "Wert Produce",
    "wof:placetype": "venue"
  },
  "geometry": {"coordinates":[-82.511639,40.702505],"type":"Point"}
}
