{
  "type": "Feature",
  "properties": {
    "addr:full":"11700 Princeton Pike Cincinnati OH 45246",
    "addr:housenumber":"11700",
    "addr:postcode":"45246",
    "addr:street":"Princeton Pike",
    "iso:country":"US",
    "sg:address":"11700 Princeton Pike",
    "sg:city":"Cincinnati",
    "sg:classifiers":[
        {
            "category":"Retail",
            "subcategory":"Auto Repair",
            "type":"Services"
        }
    ],
    "sg:phone":"+1 513 671 4720",
    "sg:postcode":"45246",
    "sg:province":"OH",
    "sg:tags":[
        "body",
        "automobile",
        "painting"
    ],
    "sg:website":"www.bodyc.com",
    "wof:name":"Body Central",
    "wof:placetype":"venue"
},
  "geometry": {"coordinates":[-84.466252,39.294854],"type":"Point"}
}