{
  "type": "Feature",
  "properties": {
    "iso:country":"US",
    "sg:address":"50 Public Sq",
    "sg:city":"Cleveland",
    "sg:classifiers":[
        {
            "category":"Professional",
            "subcategory":"Research",
            "type":"Services"
        }
    ],
    "sg:phone":"+1 216 623 4770",
    "sg:postcode":"44113",
    "sg:province":"OH",
    "sg:tags":[
        "foundation",
        "philanthropic"
    ],
    "wof:name":"John P Murphy Foundation",
    "wof:placetype":"venue"
},
  "geometry": {"coordinates":[-81.69426199999999,41.500327],"type":"Point"}
}