{
  "type": "Feature",
  "properties": {
    "iso:country":"US",
    "sg:address":"16309 S Boone Rd",
    "sg:city":"Columbia Station",
    "sg:classifiers":[
        {
            "category":"Building & Trades",
            "subcategory":"Construction",
            "type":"Services"
        }
    ],
    "sg:phone":"+1 440 236 3558",
    "sg:postcode":"44028",
    "sg:province":"OH",
    "sg:tags":[
        "contractor"
    ],
    "wof:name":"Hickory Ridge Farms",
    "wof:placetype":"venue"
},
  "geometry": {"coordinates":[-81.897155,41.303445],"type":"Point"}
}