{
  "type": "Feature",
  "properties": {
    "iso:country":"US",
    "sg:address":"6340 Melbury Ave",
    "sg:city":"Solon",
    "sg:classifiers":[
        {
            "category":"Retail",
            "subcategory":"Event Space",
            "type":"Services"
        },
        {
            "category":"Bars & Pubs",
            "subcategory":"Nightclub",
            "type":"Food & Drink"
        }
    ],
    "sg:phone":"+1 440 248 4893",
    "sg:postcode":"44139",
    "sg:province":"OH",
    "sg:tags":[
        "venue",
        "nightlife"
    ],
    "wof:name":"Solon Valley Party Center",
    "wof:placetype":"venue"
},
  "geometry": {"coordinates":[-81.44229900000001,41.387501],"type":"Point"}
}