{
  "type": "Feature",
  "properties": {
    "iso:country":"US",
    "sg:address":"2505 Lexington Ave",
    "sg:city":"Mansfield",
    "sg:classifiers":[
        {
            "category":"Manufacturing",
            "subcategory":"Rubber & Plastics",
            "type":"Manufacturing & Wholesale Goods"
        }
    ],
    "sg:phone":"+1 419 884 1881",
    "sg:postcode":"44904",
    "sg:province":"OH",
    "sg:tags":[
        "product",
        "mfg"
    ],
    "wof:name":"Odyssey Plastic Fabrication",
    "wof:placetype":"venue"
},
  "geometry": {"coordinates":[-82.562703,40.69461],"type":"Point"}
}