{
  "type": "Feature",
  "properties": {
    "addr:full": "2557 Baptist Hill Rd Chillicothe OH 45601",
    "addr:housenumber": "2557",
    "addr:postcode": "45601",
    "addr:street": "Baptist Hill Rd",
    "iso:country": "US",
    "sg:address": "2557 Baptist Hill Rd",
    "sg:city": "Chillicothe",
    "sg:classifiers": [
      {
        "category": "Building \u0026 Trades",
        "subcategory": "Pest Control",
        "type": "Services"
      }
    ],
    "sg:phone": "+1 740 775 1526",
    "sg:postcode": "45601",
    "sg:province": "OH",
    "wof:name": "Conley's Termite \u0026 Pest Cntrl",
    "wof:placetype": "venue"
  },
  "geometry": {"coordinates":[-83.013337,39.279696],"type":"Point"}
}
