{
  "type": "Feature",
  "properties": {
    "iso:country":"US",
    "sg:address":"528 Wheeler Dr",
    "sg:city":"Marion",
    "sg:classifiers":[
        {
            "category":"Home & Garden",
            "subcategory":"Building Materials",
            "type":"Retail Goods"
        }
    ],
    "sg:phone":"+1 740 383 5259",
    "sg:postcode":"43302",
    "sg:province":"OH",
    "wof:name":"Stained Glass and More",
    "wof:placetype":"venue"
},
  "geometry": {"coordinates":[-83.084722,40.588747],"type":"Point"}
}