{
  "type": "Feature",
  "properties": {
    "iso:country":"US",
    "sg:address":"1559 S Main St",
    "sg:city":"Akron",
    "sg:classifiers":[
        {
            "category":"Professional",
            "subcategory":"Engineering",
            "type":"Services"
        }
    ],
    "sg:phone":"+1 330 724 7827",
    "sg:postcode":"44301",
    "sg:province":"OH",
    "sg:tags":[
        "engineer"
    ],
    "wof:name":"Starboyz Engineering",
    "wof:placetype":"venue"
},
  "geometry": {"coordinates":[-81.527163,41.044471],"type":"Point"}
}