{
  "type": "Feature",
  "properties": {
    "addr:full": "1455 E Schaaf Rd Cleveland OH 44131",
    "addr:housenumber": "1455",
    "addr:postcode": "44131",
    "addr:street": "E Schaaf Rd",
    "iso:country": "US",
    "sg:address": "1455 E Schaaf Rd",
    "sg:city": "Cleveland",
    "sg:classifiers": [
      {
        "category": "Building \u0026 Trades",
        "subcategory": "Plumbing",
        "type": "Services"
      }
    ],
    "sg:phone": "+1 216 398 5566",
    "sg:postcode": "44131",
    "sg:province": "OH",
    "sg:tags": [
      "installs",
      "repair",
      "boiler",
      "cleaning"
    ],
    "wof:name": "Wilco Boilers Inc",
    "wof:placetype": "venue"
  },
  "geometry": {"coordinates":[-81.658399,41.414536],"type":"Point"}
}
