{
  "type": "Feature",
  "properties": {
    "addr:full": "3364 E Breese Rd Lima OH 45806",
    "addr:housenumber": "3364",
    "addr:postcode": "45806",
    "addr:street": "E Breese Rd",
    "iso:country": "US",
    "sg:address": "3364 E Breese Rd",
    "sg:city": "Lima",
    "sg:classifiers": [
      {
        "category": "Professional",
        "subcategory": "Computer Services",
        "type": "Services"
      }
    ],
    "sg:phone": "+1 419 222 5817",
    "sg:postcode": "45806",
    "sg:province": "OH",
    "sg:tags": [
      "repair"
    ],
    "wof:name": "Compulete LLC",
    "wof:placetype": "venue"
  },
  "geometry": {"coordinates":[-84.040454,40.687698],"type":"Point"}
}
