{
  "type": "Feature",
  "properties": {
    "iso:country":"US",
    "sg:address":"1564 Pin Oak Trl",
    "sg:city":"Mansfield",
    "sg:classifiers":[
        {
            "category":"Building & Trades",
            "subcategory":"Electrical",
            "type":"Services"
        }
    ],
    "sg:phone":"+1 419 774 9400",
    "sg:postcode":"44906",
    "sg:province":"OH",
    "sg:tags":[
        "electric",
        "contractor"
    ],
    "wof:name":"Ace Electrical Svc",
    "wof:placetype":"venue"
},
  "geometry": {"coordinates":[-82.564957,40.717441],"type":"Point"}
}