{
  "type": "Feature",
  "properties": {
    "iso:country":"US",
    "sg:address":"7580 Pinehurst Dr",
    "sg:city":"Mentor On Lake",
    "sg:classifiers":[
        {
            "category":"Building & Trades",
            "subcategory":"Landscaping Services",
            "type":"Services"
        }
    ],
    "sg:phone":"+1 440 257 7095",
    "sg:postcode":"44060",
    "sg:province":"OH",
    "sg:tags":[
        "tree"
    ],
    "wof:name":"Green Leaf Tree Care Inc",
    "wof:placetype":"venue"
},
  "geometry": {"coordinates":[-81.36436,41.712034],"type":"Point"}
}