{
  "type": "Feature",
  "properties": {
    "addr:full": "19111 Detroit Rd Cleveland OH 44116",
    "addr:housenumber": "19111",
    "addr:postcode": "44116",
    "addr:street": "Detroit Rd",
    "iso:country": "US",
    "sg:address": "19111 Detroit Rd",
    "sg:city": "Cleveland",
    "sg:classifiers": [
      {
        "category": "Shopping",
        "subcategory": "Computers \u0026 Home Electronics",
        "type": "Retail Goods"
      }
    ],
    "sg:phone": "+1 216 535 4470",
    "sg:postcode": "44116",
    "sg:province": "OH",
    "sg:tags": [
      "software"
    ],
    "wof:name": "E Snard Digital Business Archs",
    "wof:placetype": "venue"
  },
  "geometry": {"coordinates":[-81.833952,41.482946],"type":"Point"}
}
