{
  "type": "Feature",
  "properties": {
    "iso:country":"US",
    "sg:address":"22659 Collins Rd",
    "sg:city":"Milford Center",
    "sg:classifiers":[
        {
            "category":"Building & Trades",
            "subcategory":"Construction",
            "type":"Services"
        }
    ],
    "sg:phone":"+1 937 644 4000",
    "sg:postcode":"43045",
    "sg:province":"OH",
    "sg:tags":[
        "siding",
        "contractor"
    ],
    "wof:name":"Tri-County Roofing & Siding",
    "wof:placetype":"venue"
},
  "geometry": {"coordinates":[-83.470861,40.194956],"type":"Point"}
}