{
  "type": "Feature",
  "properties": {
    "addr:full": "22659 Collins Rd Milford Center OH 43045",
    "addr:housenumber": "22659",
    "addr:postcode": "43045",
    "addr:street": "Collins Rd",
    "iso:country": "US",
    "sg:address": "22659 Collins Rd",
    "sg:city": "Milford Center",
    "sg:classifiers": [
      {
        "category": "Building \u0026 Trades",
        "subcategory": "Construction",
        "type": "Services"
      }
    ],
    "sg:phone": "+1 937 644 4000",
    "sg:postcode": "43045",
    "sg:province": "OH",
    "sg:tags": [
      "siding",
      "contractor"
    ],
    "wof:name": "Tri-County Roofing \u0026 Siding",
    "wof:placetype": "venue"
  },
  "geometry": {"coordinates":[-83.470861,40.194956],"type":"Point"}
}
