{
  "type": "Feature",
  "properties": {
    "addr:full":"7417 W Chester Rd West Chester OH 45069",
    "addr:housenumber":"7417",
    "addr:postcode":"45069",
    "addr:street":"W Chester Rd",
    "iso:country":"US",
    "sg:address":"7417 W Chester Rd",
    "sg:city":"West Chester",
    "sg:classifiers":[
        {
            "category":"Utilities",
            "type":"Services"
        }
    ],
    "sg:phone":"+1 937 262 0123",
    "sg:postcode":"45069",
    "sg:province":"OH",
    "sg:tags":[
        "sweeping"
    ],
    "wof:name":"Dayton Sweeping Service Inc",
    "wof:placetype":"venue"
},
  "geometry": {"coordinates":[-84.379879,39.319871],"type":"Point"}
}