{
  "type": "Feature",
  "properties": {
    "iso:country":"US",
    "sg:address":"205 Southbrook Dr",
    "sg:city":"Dayton",
    "sg:classifiers":[
        {
            "category":"Shopping",
            "subcategory":"Books",
            "type":"Retail Goods"
        }
    ],
    "sg:phone":"+1 937 434 5795",
    "sg:postcode":"45459",
    "sg:province":"OH",
    "sg:tags":[
        "dealer",
        "store"
    ],
    "wof:name":"Reader's Choice Book Store",
    "wof:placetype":"venue"
},
  "geometry": {"coordinates":[-84.16597,39.649304],"type":"Point"}
}