{
  "type": "Feature",
  "properties": {
    "addr:full": "2837 Lee Rd Silver Lake OH 44224",
    "addr:housenumber": "2837",
    "addr:postcode": "44224",
    "addr:street": "Lee Rd",
    "iso:country": "US",
    "sg:address": "2837 Lee Rd",
    "sg:city": "Silver Lake",
    "sg:classifiers": [
      {
        "category": "Shopping",
        "subcategory": "Used Merchandise",
        "type": "Retail Goods"
      }
    ],
    "sg:phone": "+1 330 940 3020",
    "sg:postcode": "44224",
    "sg:province": "OH",
    "sg:tags": [
      "antique"
    ],
    "wof:name": "P C Pair",
    "wof:placetype": "venue"
  },
  "geometry": {"coordinates":[-81.46751,41.15232],"type":"Point"}
}
