{
  "type": "Feature",
  "properties": {
    "addr:full": "2800 Wilson Ave Campbell OH 44405",
    "addr:housenumber": "2800",
    "addr:postcode": "44405",
    "addr:street": "Wilson Ave",
    "iso:country": "US",
    "sg:address": "2800 Wilson Ave",
    "sg:city": "Campbell",
    "sg:classifiers": [
      {
        "category": "Utilities",
        "subcategory": "Water",
        "type": "Services"
      }
    ],
    "sg:phone": "+1 330 755 4822",
    "sg:postcode": "44405",
    "sg:province": "OH",
    "sg:tags": [
      "company",
      "sewage"
    ],
    "wof:name": "Campbell Water Works",
    "wof:placetype": "venue"
  },
  "geometry": {"coordinates":[-80.603486,41.07581],"type":"Point"}
}
