{
  "type": "Feature",
  "properties": {
    "addr:full": "3200 Roanoke Ave Cleveland OH 44109",
    "addr:housenumber": "3200",
    "addr:postcode": "44109",
    "addr:street": "Roanoke Ave",
    "iso:country": "US",
    "sg:address": "3200 Roanoke Ave",
    "sg:city": "Cleveland",
    "sg:classifiers": [
      {
        "category": "Manufacturing",
        "subcategory": "Printing",
        "type": "Manufacturing \u0026 Wholesale Goods"
      }
    ],
    "sg:phone": "+1 216 749 4221",
    "sg:postcode": "44109",
    "sg:province": "OH",
    "sg:tags": [
      "lithographic",
      "commercial"
    ],
    "wof:name": "Offset Xpress",
    "wof:placetype": "venue"
  },
  "geometry": {"coordinates":[-81.705781,41.436399],"type":"Point"}
}
