{
  "type": "Feature",
  "properties": {
    "iso:country":"US",
    "sg:address":"3200 Roanoke Ave",
    "sg:city":"Cleveland",
    "sg:classifiers":[
        {
            "category":"Manufacturing",
            "subcategory":"Printing",
            "type":"Manufacturing & Wholesale Goods"
        }
    ],
    "sg:phone":"+1 216 749 4221",
    "sg:postcode":"44109",
    "sg:province":"OH",
    "sg:tags":[
        "lithographic",
        "commercial"
    ],
    "wof:name":"Offset Xpress",
    "wof:placetype":"venue"
},
  "geometry": {"coordinates":[-81.705781,41.436399],"type":"Point"}
}