{
  "type": "Feature",
  "properties": {
    "addr:full": "100 N Sandusky Ave Upper Sandusky OH 43351",
    "addr:housenumber": "100",
    "addr:postcode": "43351",
    "addr:street": "N Sandusky Ave",
    "iso:country": "US",
    "sg:address": "100 N Sandusky Ave",
    "sg:city": "Upper Sandusky",
    "sg:classifiers": [
      {
        "category": "Banks \u0026 Credit Unions",
        "subcategory": "Bank",
        "type": "Services"
      }
    ],
    "sg:phone": "+1 419 294 2351",
    "sg:postcode": "43351",
    "sg:province": "OH",
    "sg:website": "www.firstcitizensnational.com",
    "wof:name": "First Citizens National Bank",
    "wof:placetype": "venue"
  },
  "geometry": {"coordinates":[-83.28137,40.828897],"type":"Point"}
}
