{
  "type": "Feature",
  "properties": {
    "iso:country":"US",
    "sg:address":"355 West Ave",
    "sg:city":"Tallmadge",
    "sg:classifiers":[
        {
            "category":"Professional",
            "type":"Services"
        }
    ],
    "sg:phone":"+1 330 633 9990",
    "sg:postcode":"44278",
    "sg:province":"OH",
    "sg:tags":[
        "establishment"
    ],
    "wof:name":"Tom Mc Neill's Auto Pro WHOL",
    "wof:placetype":"venue"
},
  "geometry": {"coordinates":[-81.452159,41.101611],"type":"Point"}
}