{
  "type": "Feature",
  "properties": {
    "iso:country":"US",
    "sg:address":"2281 US Hwy 68 N",
    "sg:city":"Bellefontaine",
    "sg:classifiers":[
        {
            "category":"Professional",
            "subcategory":"Accounting & Tax Preparation",
            "type":"Services"
        }
    ],
    "sg:phone":"+1 937 599 4220",
    "sg:postcode":"43311",
    "sg:province":"OH",
    "sg:tags":[
        "return",
        "filing"
    ],
    "wof:name":"H & R Block Tax Svc",
    "wof:placetype":"venue"
},
  "geometry": {"coordinates":[-83.76144499999999,40.33167],"type":"Point"}
}