{
  "type": "Feature",
  "properties": {
    "addr:full": "270 N Main St Youngstown OH 44514",
    "addr:housenumber": "270",
    "addr:postcode": "44514",
    "addr:street": "N Main St",
    "iso:country": "US",
    "sg:address": "270 N Main St",
    "sg:city": "Youngstown",
    "sg:classifiers": [
      {
        "category": "Retail",
        "subcategory": "Funeral Services",
        "type": "Services"
      }
    ],
    "sg:phone": "+1 330 757 4851",
    "sg:postcode": "44514",
    "sg:province": "OH",
    "wof:name": "Becker Funeral Home",
    "wof:placetype": "venue"
  },
  "geometry": {"coordinates":[-80.615498,41.028793],"type":"Point"}
}
