{
  "type": "Feature",
  "properties": {
    "iso:country":"US",
    "sg:address":"1035 Gardner Blvd",
    "sg:city":"Norton",
    "sg:classifiers":[
        {
            "category":"Home & Garden",
            "subcategory":"Garden Supply",
            "type":"Retail Goods"
        }
    ],
    "sg:phone":"+1 330 745 9322",
    "sg:postcode":"44203",
    "sg:province":"OH",
    "sg:tags":[
        "landscaping",
        "equipment"
    ],
    "sg:website":"www.klawog-klacon.com",
    "wof:name":"Klawog Wessco Inc",
    "wof:placetype":"venue"
},
  "geometry": {"coordinates":[-81.627123,41.021412],"type":"Point"}
}