{
  "type": "Feature",
  "properties": {
    "addr:full":"27040 Cedar Rd Cleveland OH 44122",
    "addr:housenumber":"27040",
    "addr:postcode":"44122",
    "addr:street":"Cedar Rd",
    "iso:country":"US",
    "sg:address":"27040 Cedar Rd",
    "sg:city":"Cleveland",
    "sg:classifiers":[
        {
            "category":"Shopping",
            "subcategory":"Clothing, Apparel, & Fashions",
            "type":"Retail Goods"
        }
    ],
    "sg:phone":"+1 216 292 9600",
    "sg:postcode":"44122",
    "sg:province":"OH",
    "wof:name":"Classy Bag",
    "wof:placetype":"venue"
},
  "geometry": {"coordinates":[-81.488731,41.501094],"type":"Point"}
}