{
  "type": "Feature",
  "properties": {
    "addr:full": "2339 Bevington Ln Hamilton IN 45013",
    "addr:housenumber": "2339",
    "addr:postcode": "45013",
    "addr:street": "Bevington Ln",
    "iso:country": "US",
    "sg:address": "2339 Bevington Ln",
    "sg:city": "Hamilton",
    "sg:classifiers": [
      {
        "category": "Building \u0026 Trades",
        "subcategory": "Construction",
        "type": "Services"
      }
    ],
    "sg:phone": "+1 513 863 9996",
    "sg:postcode": "45013",
    "sg:province": "IN",
    "sg:tags": [
      "repairing",
      "remodeling",
      "contractor"
    ],
    "wof:name": "Meyer Brothers Building",
    "wof:placetype": "venue"
  },
  "geometry": {"coordinates":[-84.605798,39.447531],"type":"Point"}
}
