{
  "type": "Feature",
  "properties": {
    "iso:country":"US",
    "sg:address":"70 S Cleveland Ave",
    "sg:city":"Mogadore",
    "sg:classifiers":[
        {
            "category":"Restaurant",
            "type":"Food & Drink"
        }
    ],
    "sg:menulink":"http://www.allmenus.com/oh/mogadore/245096-sams-tavern/menu/",
    "sg:phone":"+1 330 628 3517",
    "sg:postcode":"44260",
    "sg:province":"OH",
    "sg:tags":[
        "american",
        "pub"
    ],
    "wof:name":"Sam's Tavern",
    "wof:placetype":"venue"
},
  "geometry": {"coordinates":[-81.39313799999999,41.049232],"type":"Point"}
}