{
  "type": "Feature",
  "properties": {
    "addr:full": "70 S Cleveland Ave Mogadore OH 44260",
    "addr:housenumber": "70",
    "addr:postcode": "44260",
    "addr:street": "S Cleveland Ave",
    "iso:country": "US",
    "sg:address": "70 S Cleveland Ave",
    "sg:city": "Mogadore",
    "sg:classifiers": [
      {
        "category": "Restaurant",
        "type": "Food \u0026 Drink"
      }
    ],
    "sg:menulink": "http://www.allmenus.com/oh/mogadore/245096-sams-tavern/menu/",
    "sg:phone": "+1 330 628 3517",
    "sg:postcode": "44260",
    "sg:province": "OH",
    "sg:tags": [
      "american",
      "pub"
    ],
    "wof:name": "Sam's Tavern",
    "wof:placetype": "venue"
  },
  "geometry": {"coordinates":[-81.393138,41.049232],"type":"Point"}
}
