{
  "type": "Feature",
  "properties": {
    "addr:full": "5838 Hamilton Ave Cincinnati OH 45224",
    "addr:housenumber": "5838",
    "addr:postcode": "45224",
    "addr:street": "Hamilton Ave",
    "iso:country": "US",
    "sg:address": "5838 Hamilton Ave",
    "sg:city": "Cincinnati",
    "sg:classifiers": [
      {
        "category": "Manufacturing",
        "subcategory": "Jewelry",
        "type": "Manufacturing \u0026 Wholesale Goods"
      }
    ],
    "sg:phone": "+1 513 541 5200",
    "sg:postcode": "45224",
    "sg:province": "OH",
    "wof:name": "D \u0026 J Mfg Jewelers",
    "wof:placetype": "venue"
  },
  "geometry": {"coordinates":[-84.546285,39.198013],"type":"Point"}
}
