{
  "type": "Feature",
  "properties": {
    "addr:full":"2891 Waterloo Rd Mogadore OH 44260",
    "addr:housenumber":"2891",
    "addr:postcode":"44260",
    "addr:street":"Waterloo Rd",
    "iso:country":"US",
    "sg:address":"2891 Waterloo Rd",
    "sg:city":"Mogadore",
    "sg:classifiers":[
        {
            "category":"Shopping",
            "type":"Retail Goods"
        }
    ],
    "sg:phone":"+1 330 628 0176",
    "sg:postcode":"44260",
    "sg:province":"OH",
    "sg:tags":[
        "pet",
        "food",
        "supply"
    ],
    "sg:website":"www.petsuppliesplus.com",
    "wof:name":"Pet Supplies Plus",
    "wof:placetype":"venue"
},
  "geometry": {"coordinates":[-81.288568,41.029223],"type":"Point"}
}