{
  "type": "Feature",
  "properties": {
    "addr:full":"2016 Elm St Cincinnati OH 45202",
    "addr:housenumber":"2016",
    "addr:postcode":"45202",
    "addr:street":"Elm St",
    "iso:country":"US",
    "sg:address":"2016 Elm St",
    "sg:city":"Cincinnati",
    "sg:classifiers":[
        {
            "category":"Manufacturing",
            "subcategory":"Printing",
            "type":"Manufacturing & Wholesale Goods"
        }
    ],
    "sg:phone":"+1 513 421 7799",
    "sg:postcode":"45202",
    "sg:province":"OH",
    "sg:tags":[
        "lithographic",
        "commercial"
    ],
    "wof:name":"P E S",
    "wof:placetype":"venue"
},
  "geometry": {"coordinates":[-84.520709,39.118789],"type":"Point"}
}