{
  "type": "Feature",
  "properties": {
    "addr:full": "2597 Needmore Rd Dayton OH 45414",
    "addr:housenumber": "2597",
    "addr:postcode": "45414",
    "addr:street": "Needmore Rd",
    "iso:country": "US",
    "sg:address": "2597 Needmore Rd",
    "sg:city": "Dayton",
    "sg:classifiers": [
      {
        "category": "Building \u0026 Trades",
        "subcategory": "Construction",
        "type": "Services"
      }
    ],
    "sg:phone": "+1 937 276 5412",
    "sg:postcode": "45414",
    "sg:province": "OH",
    "sg:tags": [
      "contractor"
    ],
    "wof:name": "Dale Spencer",
    "wof:placetype": "venue"
  },
  "geometry": {"coordinates":[-84.185964,39.819893],"type":"Point"}
}
