{
  "type": "Feature",
  "properties": {
    "addr:full": "18314 Euclid Ave Cleveland OH 44112",
    "addr:housenumber": "18314",
    "addr:postcode": "44112",
    "addr:street": "Euclid Ave",
    "iso:country": "US",
    "sg:address": "18314 Euclid Ave",
    "sg:city": "Cleveland",
    "sg:classifiers": [
      {
        "category": "Retail",
        "subcategory": "Laundry \u0026 Dry Cleaning",
        "type": "Services"
      }
    ],
    "sg:phone": "+1 216 481 2468",
    "sg:postcode": "44112",
    "sg:province": "OH",
    "sg:tags": [
      "cleaners"
    ],
    "wof:name": "Avon-Sparkletown Dry Cleaning",
    "wof:placetype": "venue"
  },
  "geometry": {"coordinates":[-81.550986,41.556074],"type":"Point"}
}
