{
  "type": "Feature",
  "properties": {
    "iso:country":"US",
    "sg:address":"18314 Euclid Ave",
    "sg:city":"Cleveland",
    "sg:classifiers":[
        {
            "category":"Retail",
            "subcategory":"Laundry & Dry Cleaning",
            "type":"Services"
        }
    ],
    "sg:phone":"+1 216 481 2468",
    "sg:postcode":"44112",
    "sg:province":"OH",
    "sg:tags":[
        "cleaners"
    ],
    "wof:name":"Avon-Sparkletown Dry Cleaning",
    "wof:placetype":"venue"
},
  "geometry": {"coordinates":[-81.55098599999999,41.556074],"type":"Point"}
}