{
  "type": "Feature",
  "properties": {
    "addr:full":"2624 21st St NW Canton OH 44708",
    "addr:housenumber":"2624",
    "addr:postcode":"44708",
    "addr:street":"21St St Nw",
    "iso:country":"US",
    "sg:address":"2624 21st St NW",
    "sg:city":"Canton",
    "sg:classifiers":[
        {
            "category":"Building & Trades",
            "subcategory":"Construction",
            "type":"Services"
        }
    ],
    "sg:phone":"+1 330 453 0532",
    "sg:postcode":"44708",
    "sg:province":"OH",
    "sg:tags":[
        "house",
        "nonresidential"
    ],
    "wof:name":"Kmetz Construction",
    "wof:placetype":"venue"
},
  "geometry": {"coordinates":[-81.403751,40.821629],"type":"Point"}
}