{
  "type": "Feature",
  "properties": {
    "iso:country":"US",
    "sg:address":"6875 April Cir",
    "sg:city":"Middletown",
    "sg:classifiers":[
        {
            "category":"Professional",
            "type":"Services"
        }
    ],
    "sg:phone":"+1 513 424 8189",
    "sg:postcode":"45042",
    "sg:province":"OH",
    "wof:name":"James P Wendel",
    "wof:placetype":"venue"
},
  "geometry": {"coordinates":[-84.431611,39.505127],"type":"Point"}
}