{
  "type": "Feature",
  "properties": {
    "addr:full": "2241 Rombach Ave Wilmington OH 45177",
    "addr:housenumber": "2241",
    "addr:postcode": "45177",
    "addr:street": "Rombach Ave",
    "iso:country": "US",
    "sg:address": "2241 Rombach Ave",
    "sg:city": "Wilmington",
    "sg:classifiers": [
      {
        "category": "Social Services",
        "subcategory": "Job Training",
        "type": "Services"
      }
    ],
    "sg:phone": "+1 937 383 7722",
    "sg:postcode": "45177",
    "sg:province": "OH",
    "sg:tags": [
      "rehabilitation"
    ],
    "sg:website": "www.cmhregional.com",
    "wof:name": "CMH Rehabilitation Svc",
    "wof:placetype": "venue"
  },
  "geometry": {"coordinates":[-83.790541,39.452226],"type":"Point"}
}
