{
  "type": "Feature",
  "properties": {
    "addr:full": "850 Mc Clurg Rd Youngstown OH 44512",
    "addr:housenumber": "850",
    "addr:postcode": "44512",
    "addr:street": "Mc Clurg Rd",
    "iso:country": "US",
    "sg:address": "850 Mc Clurg Rd",
    "sg:city": "Youngstown",
    "sg:classifiers": [
      {
        "category": "Wholesale",
        "subcategory": "Hardware",
        "type": "Manufacturing \u0026 Wholesale Goods"
      }
    ],
    "sg:phone": "+1 330 758 0932",
    "sg:postcode": "44512",
    "sg:province": "OH",
    "sg:tags": [
      "fastener"
    ],
    "wof:name": "Wurth/Service Supply Inc",
    "wof:placetype": "venue"
  },
  "geometry": {"coordinates":[-80.636253,40.995279],"type":"Point"}
}
