{
  "type": "Feature",
  "properties": {
    "addr:full": "3723 S High St Columbus OH 43207",
    "addr:housenumber": "3723",
    "addr:postcode": "43207",
    "addr:street": "S High St",
    "iso:country": "US",
    "sg:address": "3723 S High St",
    "sg:city": "Columbus",
    "sg:classifiers": [
      {
        "category": "Government",
        "subcategory": "Office",
        "type": "Public Place"
      }
    ],
    "sg:phone": "+1 614 492 6900",
    "sg:postcode": "43207",
    "sg:province": "OH",
    "sg:website": "www.co.franklin.oh.us",
    "wof:name": "Franklin County Community Ctr",
    "wof:placetype": "venue"
  },
  "geometry": {"coordinates":[-82.998958,39.886752],"type":"Point"}
}
