{
  "type": "Feature",
  "properties": {
    "addr:full": "207 S Main St Delphos OH 45833",
    "addr:housenumber": "207",
    "addr:postcode": "45833",
    "addr:street": "S Main St",
    "iso:country": "US",
    "sg:address": "207 S Main St",
    "sg:city": "Delphos",
    "sg:classifiers": [
      {
        "category": "Retail",
        "subcategory": "Repair Shop",
        "type": "Services"
      }
    ],
    "sg:phone": "+1 419 692 5831",
    "sg:postcode": "45833",
    "sg:province": "OH",
    "sg:tags": [
      "television",
      "radio"
    ],
    "wof:name": "Gerdeman's TV",
    "wof:placetype": "venue"
  },
  "geometry": {"coordinates":[-84.339756,40.841715],"type":"Point"}
}
