{
  "type": "Feature",
  "properties": {
    "iso:country":"US",
    "sg:address":"821 S Downing St",
    "sg:city":"Piqua",
    "sg:classifiers":[
        {
            "category":"Manufacturing",
            "subcategory":"Metals",
            "type":"Manufacturing & Wholesale Goods"
        }
    ],
    "sg:phone":"+1 937 773 4134",
    "sg:postcode":"45356",
    "sg:province":"OH",
    "sg:tags":[
        "foundry"
    ],
    "wof:name":"Piqua Emery Cutter & Foundry",
    "wof:placetype":"venue"
},
  "geometry": {"coordinates":[-84.241907,40.137018],"type":"Point"}
}