{
  "type": "Feature",
  "properties": {
    "addr:full": "821 S Downing St Piqua OH 45356",
    "addr:housenumber": "821",
    "addr:postcode": "45356",
    "addr:street": "S Downing St",
    "iso:country": "US",
    "sg:address": "821 S Downing St",
    "sg:city": "Piqua",
    "sg:classifiers": [
      {
        "category": "Manufacturing",
        "subcategory": "Metals",
        "type": "Manufacturing \u0026 Wholesale Goods"
      }
    ],
    "sg:phone": "+1 937 773 4134",
    "sg:postcode": "45356",
    "sg:province": "OH",
    "sg:tags": [
      "foundry"
    ],
    "wof:name": "Piqua Emery Cutter \u0026 Foundry",
    "wof:placetype": "venue"
  },
  "geometry": {"coordinates":[-84.241907,40.137018],"type":"Point"}
}
