{
  "type": "Feature",
  "properties": {
    "addr:full":"2618 Spring Grove Ave Cincinnati OH 45214",
    "addr:housenumber":"2618",
    "addr:postcode":"45214",
    "addr:street":"Spring Grove Ave",
    "iso:country":"US",
    "sg:address":"2618 Spring Grove Ave",
    "sg:city":"Cincinnati",
    "sg:classifiers":[
        {
            "category":"Building & Trades",
            "subcategory":"Construction",
            "type":"Services"
        }
    ],
    "sg:phone":"+1 513 588 4051",
    "sg:postcode":"45214",
    "sg:province":"OH",
    "sg:tags":[
        "paving",
        "contractor"
    ],
    "wof:name":"Jacobsen Asphalt Sealing",
    "wof:placetype":"venue"
},
  "geometry": {"coordinates":[-84.536697,39.130332],"type":"Point"}
}