{
  "type": "Feature",
  "properties": {
    "iso:country":"US",
    "sg:address":"8710 East Ave",
    "sg:city":"Mentor",
    "sg:classifiers":[
        {
            "category":"Manufacturing",
            "subcategory":"Tools & Machinery",
            "type":"Manufacturing & Wholesale Goods"
        }
    ],
    "sg:phone":"+1 440 255 8383",
    "sg:postcode":"44060",
    "sg:province":"OH",
    "sg:tags":[
        "lighting",
        "fixture"
    ],
    "sg:website":"www.medallionlighting.com",
    "wof:name":"Medallion Lighting Group",
    "wof:placetype":"venue"
},
  "geometry": {"coordinates":[-81.328439,41.683579],"type":"Point"}
}