{
  "type": "Feature",
  "properties": {
    "addr:full": "3651 Massillon Rd Uniontown OH 44685",
    "addr:housenumber": "3651",
    "addr:postcode": "44685",
    "addr:street": "Massillon Rd",
    "iso:country": "US",
    "sg:address": "3651 Massillon Rd",
    "sg:city": "Uniontown",
    "sg:classifiers": [
      {
        "category": "Communications",
        "type": "Services"
      }
    ],
    "sg:phone": "+1 330 899 0059",
    "sg:postcode": "44685",
    "sg:province": "OH",
    "wof:name": "Mobile Communications Systems",
    "wof:placetype": "venue"
  },
  "geometry": {"coordinates":[-81.465189,40.961335],"type":"Point"}
}
