{
  "type": "Feature",
  "properties": {
    "addr:full": "905 Main St Milford OH 45150",
    "addr:housenumber": "905",
    "addr:postcode": "45150",
    "addr:street": "Main St",
    "iso:country": "US",
    "sg:address": "905 Main St",
    "sg:city": "Milford",
    "sg:classifiers": [
      {
        "category": "Health Services",
        "subcategory": "Doctor",
        "type": "Services"
      }
    ],
    "sg:phone": "+1 513 831 0184",
    "sg:postcode": "45150",
    "sg:province": "OH",
    "sg:tags": [
      "dentist"
    ],
    "wof:name": "Vance Family \u0026 Cosmetic",
    "wof:placetype": "venue"
  },
  "geometry": {"coordinates":[-84.279122,39.178601],"type":"Point"}
}
