{
  "type": "Feature",
  "properties": {
    "iso:country":"US",
    "sg:address":"111 N Hambden St",
    "sg:city":"Willoughby",
    "sg:classifiers":[
        {
            "category":"Insurance",
            "subcategory":"Title Insurance",
            "type":"Services"
        }
    ],
    "sg:phone":"+1 440 946 8744",
    "sg:postcode":"44024",
    "sg:province":"OH",
    "wof:name":"First American Title Ins Co",
    "wof:placetype":"venue"
},
  "geometry": {"coordinates":[-81.202856,41.583529],"type":"Point"}
}