{
  "type": "Feature",
  "properties": {
    "addr:full": "7625 Beechmont Ave Cincinnati OH 45255",
    "addr:housenumber": "7625",
    "addr:postcode": "45255",
    "addr:street": "Beechmont Ave",
    "iso:country": "US",
    "sg:address": "7625 Beechmont Ave",
    "sg:city": "Cincinnati",
    "sg:classifiers": [
      {
        "category": "Restaurant",
        "type": "Food \u0026 Drink"
      }
    ],
    "sg:menulink": "http://www.allmenus.com/oh/anderson/16953-izzys/menu/",
    "sg:phone": "+1 513 231 5550",
    "sg:postcode": "45255",
    "sg:province": "OH",
    "sg:tags": [
      "american"
    ],
    "wof:name": "Izzy's",
    "wof:placetype": "venue"
  },
  "geometry": {"coordinates":[-84.345887,39.072326],"type":"Point"}
}
