{
  "type": "Feature",
  "properties": {
    "addr:full":"38 N Jefferson St Dayton OH 45402",
    "addr:housenumber":"38",
    "addr:postcode":"45402",
    "addr:street":"N Jefferson St",
    "iso:country":"US",
    "sg:address":"38 N Jefferson St",
    "sg:city":"Dayton",
    "sg:classifiers":[
        {
            "category":"Manufacturing",
            "subcategory":"Wood Products",
            "type":"Manufacturing & Wholesale Goods"
        }
    ],
    "sg:phone":"+1 937 223 6255",
    "sg:postcode":"45402",
    "sg:province":"OH",
    "sg:tags":[
        "ad",
        "incentive",
        "mfr",
        "corp",
        "recognition",
        "plaque"
    ],
    "wof:name":"Milford Plaque & Met Design Co",
    "wof:placetype":"venue"
},
  "geometry": {"coordinates":[-84.190235,39.760733],"type":"Point"}
}