{
  "type": "Feature",
  "properties": {
    "iso:country":"US",
    "sg:address":"5710 Twp Rd 259",
    "sg:city":"Fostoria",
    "sg:classifiers":[
        {
            "category":"Retail",
            "subcategory":"Laundry & Dry Cleaning",
            "type":"Services"
        }
    ],
    "sg:phone":"+1 419 894 6078",
    "sg:postcode":"44830",
    "sg:province":"OH",
    "sg:tags":[
        "shop",
        "repair",
        "garment",
        "sewing",
        "needlework",
        "alteration"
    ],
    "wof:name":"Betsy Ross Shoppe",
    "wof:placetype":"venue"
},
  "geometry": {"coordinates":[-83.459313,41.084024],"type":"Point"}
}