{
  "type": "Feature",
  "properties": {
    "addr:full": "5710 Twp Rd 259 Fostoria OH 44830",
    "addr:housenumber": "259",
    "addr:postcode": "5710;44830",
    "addr:street": "Twp Rd",
    "iso:country": "US",
    "sg:address": "5710 Twp Rd 259",
    "sg:city": "Fostoria",
    "sg:classifiers": [
      {
        "category": "Retail",
        "subcategory": "Laundry \u0026 Dry Cleaning",
        "type": "Services"
      }
    ],
    "sg:phone": "+1 419 894 6078",
    "sg:postcode": "44830",
    "sg:province": "OH",
    "sg:tags": [
      "shop",
      "repair",
      "garment",
      "sewing",
      "needlework",
      "alteration"
    ],
    "wof:name": "Betsy Ross Shoppe",
    "wof:placetype": "venue"
  },
  "geometry": {"coordinates":[-83.459313,41.084024],"type":"Point"}
}
