{
  "type": "Feature",
  "properties": {
    "addr:full":"926 N High St Columbus OH 43201",
    "addr:housenumber":"926",
    "addr:postcode":"43201",
    "addr:street":"N High St",
    "iso:country":"US",
    "sg:address":"926 N High St",
    "sg:city":"Columbus",
    "sg:classifiers":[
        {
            "category":"Shopping",
            "subcategory":"Pharmacy",
            "type":"Retail Goods"
        }
    ],
    "sg:phone":"+1 614 888 6366",
    "sg:postcode":"43201",
    "sg:province":"OH",
    "sg:website":"www.cvs.com",
    "wof:name":"CVS Pharmacy",
    "wof:placetype":"venue"
},
  "geometry": {"coordinates":[-83.004307,39.981256],"type":"Point"}
}