{
  "type": "Feature",
  "properties": {
    "iso:country":"US",
    "sg:address":"1533 Lake Shore Dr",
    "sg:city":"Columbus",
    "sg:classifiers":[
        {
            "category":"Manufacturing",
            "subcategory":"Glass & Minerals",
            "type":"Manufacturing & Wholesale Goods"
        }
    ],
    "sg:phone":"+1 614 488 4133",
    "sg:postcode":"43204",
    "sg:province":"OH",
    "sg:tags":[
        "concrete",
        "brick"
    ],
    "wof:name":"Patton Investment Holding",
    "wof:placetype":"venue"
},
  "geometry": {"coordinates":[-83.067576,39.980063],"type":"Point"}
}