{
  "type": "Feature",
  "properties": {
    "addr:full":"1263 Norton Ave Norton OH 44203",
    "addr:housenumber":"1263",
    "addr:postcode":"44203",
    "addr:street":"Norton Ave",
    "iso:country":"US",
    "sg:address":"1263 Norton Ave",
    "sg:city":"Norton",
    "sg:classifiers":[
        {
            "category":"Personal",
            "subcategory":"Beauty Salon",
            "type":"Services"
        }
    ],
    "sg:phone":"+1 330 825 5249",
    "sg:postcode":"44203",
    "sg:province":"OH",
    "sg:tags":[
        "manicuring"
    ],
    "wof:name":"Nail Sensations Inc",
    "wof:placetype":"venue"
},
  "geometry": {"coordinates":[-81.635946,41.025892],"type":"Point"}
}