{
  "type": "Feature",
  "properties": {
    "iso:country":"US",
    "sg:address":"536 S 3rd St",
    "sg:city":"Columbus",
    "sg:classifiers":[
        {
            "category":"Professional",
            "subcategory":"Business Services",
            "type":"Services"
        }
    ],
    "sg:phone":"+1 614 228 5515",
    "sg:postcode":"43215",
    "sg:province":"OH",
    "sg:tags":[
        "arbitration"
    ],
    "wof:name":"Mediation Service Of Ohio",
    "wof:placetype":"venue"
},
  "geometry": {"coordinates":[-82.995833,39.951962],"type":"Point"}
}