{
  "type": "Feature",
  "properties": {
    "addr:full": "534 Race St Cincinnati OH 45202",
    "addr:housenumber": "534",
    "addr:postcode": "45202",
    "addr:street": "Race St",
    "iso:country": "US",
    "sg:address": "534 Race St",
    "sg:city": "Cincinnati",
    "sg:classifiers": [
      {
        "category": "Shopping",
        "subcategory": "Clothing, Apparel, \u0026 Fashions",
        "type": "Retail Goods"
      }
    ],
    "sg:phone": "+1 513 651 9183",
    "sg:postcode": "45202",
    "sg:province": "OH",
    "wof:name": "Fashion Cents",
    "wof:placetype": "venue"
  },
  "geometry": {"coordinates":[-84.514842,39.102143],"type":"Point"}
}
