{
  "type": "Feature",
  "properties": {
    "iso:country":"US",
    "sg:address":"534 Race St",
    "sg:city":"Cincinnati",
    "sg:classifiers":[
        {
            "category":"Shopping",
            "subcategory":"Clothing, Apparel, & Fashions",
            "type":"Retail Goods"
        }
    ],
    "sg:phone":"+1 513 651 9183",
    "sg:postcode":"45202",
    "sg:province":"OH",
    "wof:name":"Fashion Cents",
    "wof:placetype":"venue"
},
  "geometry": {"coordinates":[-84.514842,39.102143],"type":"Point"}
}