{
  "type": "Feature",
  "properties": {
    "addr:full": "14922 Kinsman Rd Cleveland OH 44120",
    "addr:housenumber": "14922",
    "addr:postcode": "44120",
    "addr:street": "Kinsman Rd",
    "iso:country": "US",
    "sg:address": "14922 Kinsman Rd",
    "sg:city": "Cleveland",
    "sg:classifiers": [
      {
        "category": "Personal",
        "subcategory": "Beauty Salon",
        "type": "Services"
      }
    ],
    "sg:phone": "+1 216 283 1657",
    "sg:postcode": "44120",
    "sg:province": "OH",
    "wof:name": "Family Hair Ctr",
    "wof:placetype": "venue"
  },
  "geometry": {"coordinates":[-81.576407,41.464314],"type":"Point"}
}
