{
  "type": "Feature",
  "properties": {
    "iso:country":"US",
    "sg:address":"3270 East Pike",
    "sg:city":"Zanesville",
    "sg:classifiers":[
        {
            "category":"Building & Trades",
            "subcategory":"Construction",
            "type":"Services"
        }
    ],
    "sg:phone":"+1 740 455 9496",
    "sg:postcode":"43701",
    "sg:province":"OH",
    "sg:tags":[
        "masonry",
        "contractor"
    ],
    "wof:name":"Simply Stone Masonry",
    "wof:placetype":"venue"
},
  "geometry": {"coordinates":[-81.943392,39.951604],"type":"Point"}
}