{
  "type": "Feature",
  "properties": {
    "addr:full": "5200 Miller Rd Brecksville OH 44141",
    "addr:housenumber": "5200",
    "addr:postcode": "44141",
    "addr:street": "Miller Rd",
    "iso:country": "US",
    "sg:address": "5200 Miller Rd",
    "sg:city": "Brecksville",
    "sg:classifiers": [
      {
        "category": "Shopping",
        "subcategory": "Bicycles \u0026 Sporting Goods",
        "type": "Retail Goods"
      }
    ],
    "sg:phone": "+1 440 838 7569",
    "sg:postcode": "44141",
    "sg:province": "OH",
    "wof:name": "R-Joy Inc",
    "wof:placetype": "venue"
  },
  "geometry": {"coordinates":[-81.651177,41.289395],"type":"Point"}
}
