{
  "type": "Feature",
  "properties": {
    "iso:country":"US",
    "sg:address":"233 Market Ave S",
    "sg:city":"Canton",
    "sg:classifiers":[
        {
            "category":"Parking",
            "type":"Transportation"
        }
    ],
    "sg:phone":"+1 330 455 4044",
    "sg:postcode":"44702",
    "sg:province":"OH",
    "sg:tags":[
        "garage"
    ],
    "wof:name":"AMPCO System Parking",
    "wof:placetype":"venue"
},
  "geometry": {"coordinates":[-81.375186,40.79702],"type":"Point"}
}