{
  "type": "Feature",
  "properties": {
    "addr:full": "8541 Ashley Rd Ashley OH 43003",
    "addr:housenumber": "8541",
    "addr:postcode": "43003",
    "addr:street": "Ashley Rd",
    "iso:country": "US",
    "sg:address": "8541 Ashley Rd",
    "sg:city": "Ashley",
    "sg:classifiers": [
      {
        "category": "Shopping",
        "subcategory": "Books",
        "type": "Retail Goods"
      }
    ],
    "sg:phone": "+1 740 747 7113",
    "sg:postcode": "43003",
    "sg:province": "OH",
    "wof:name": "Professor Safety Inc",
    "wof:placetype": "venue"
  },
  "geometry": {"coordinates":[-82.948546,40.390676],"type":"Point"}
}
