{
  "type": "Feature",
  "properties": {
    "addr:full": "300 E Silver St Lebanon OH 45036",
    "addr:housenumber": "300",
    "addr:postcode": "45036",
    "addr:street": "E Silver St",
    "iso:country": "US",
    "sg:address": "300 E Silver St",
    "sg:city": "Lebanon",
    "sg:classifiers": [
      {
        "category": "Education",
        "subcategory": "College",
        "type": "Public Place"
      }
    ],
    "sg:phone": "+1 513 932 8292",
    "sg:postcode": "45036",
    "sg:province": "OH",
    "wof:name": "Warren Center",
    "wof:placetype": "venue"
  },
  "geometry": {"coordinates":[-84.202306,39.435117],"type":"Point"}
}
