{
  "type": "Feature",
  "properties": {
    "addr:full": "18 Swigart St Barberton OH 44203",
    "addr:housenumber": "18",
    "addr:postcode": "44203",
    "addr:street": "Swigart St",
    "iso:country": "US",
    "sg:address": "18 Swigart St",
    "sg:city": "Barberton",
    "sg:classifiers": [
      {
        "category": "Building \u0026 Trades",
        "subcategory": "Landscaping Services",
        "type": "Services"
      }
    ],
    "sg:phone": "+1 330 753 5103",
    "sg:postcode": "44203",
    "sg:province": "OH",
    "wof:name": "Dyes Lawn Care",
    "wof:placetype": "venue"
  },
  "geometry": {"coordinates":[-81.590445,41.030346],"type":"Point"}
}
