{
  "type": "Feature",
  "properties": {
    "iso:country":"US",
    "sg:address":"18 Swigart St",
    "sg:city":"Barberton",
    "sg:classifiers":[
        {
            "category":"Building & Trades",
            "subcategory":"Landscaping Services",
            "type":"Services"
        }
    ],
    "sg:phone":"+1 330 753 5103",
    "sg:postcode":"44203",
    "sg:province":"OH",
    "wof:name":"Dyes Lawn Care",
    "wof:placetype":"venue"
},
  "geometry": {"coordinates":[-81.590445,41.030346],"type":"Point"}
}