{
  "type": "Feature",
  "properties": {
    "addr:full":"1925 E Dublin Granville Rd Columbus OH 43229",
    "addr:housenumber":"1925",
    "addr:postcode":"43229",
    "addr:street":"E Dublin Granville Rd",
    "iso:country":"US",
    "sg:address":"1925 E Dublin Granville Rd",
    "sg:city":"Columbus",
    "sg:classifiers":[
        {
            "category":"Health Services",
            "subcategory":"Health Practitioner",
            "type":"Services"
        }
    ],
    "sg:phone":"+1 614 847 3617",
    "sg:postcode":"43229",
    "sg:province":"OH",
    "sg:tags":[
        "nurse",
        "registry"
    ],
    "wof:name":"ALIA Healthcare Svc",
    "wof:placetype":"venue"
},
  "geometry": {"coordinates":[-82.96750299999999,40.086763],"type":"Point"}
}