{
  "type": "Feature",
  "properties": {
    "iso:country":"US",
    "sg:address":"371 1/2 Mill Rd",
    "sg:city":"Conneaut",
    "sg:classifiers":[
        {
            "category":"Retail",
            "subcategory":"Auto Repair",
            "type":"Services"
        }
    ],
    "sg:phone":"+1 440 593 3923",
    "sg:postcode":"44030",
    "sg:province":"OH",
    "wof:name":"Norms Svc",
    "wof:placetype":"venue"
},
  "geometry": {"coordinates":[-80.56347599999999,41.937672],"type":"Point"}
}