{
  "type": "Feature",
  "properties": {
    "addr:full": "1755 E Main St Ottawa OH 45875",
    "addr:housenumber": "1755",
    "addr:postcode": "45875",
    "addr:street": "E Main St",
    "iso:country": "US",
    "sg:address": "1755 E Main St",
    "sg:city": "Ottawa",
    "sg:classifiers": [
      {
        "category": "Food \u0026 Beverages",
        "subcategory": "Groceries \u0026 Convenience Stores",
        "type": "Retail Goods"
      }
    ],
    "sg:phone": "+1 419 523 6248",
    "sg:postcode": "45875",
    "sg:province": "OH",
    "wof:name": "Kohls Super Value",
    "wof:placetype": "venue"
  },
  "geometry": {"coordinates":[-84.024538,41.021372],"type":"Point"}
}
