{
  "type": "Feature",
  "properties": {
    "iso:country":"US",
    "sg:address":"140 N Market St",
    "sg:city":"Wooster",
    "sg:classifiers":[
        {
            "category":"Organizations",
            "subcategory":"Non-profit Organization",
            "type":"Services"
        }
    ],
    "sg:phone":"+1 330 262 6706",
    "sg:postcode":"44691",
    "sg:province":"OH",
    "wof:name":"Masonic Lodge",
    "wof:placetype":"venue"
},
  "geometry": {"coordinates":[-81.94022,40.798926],"type":"Point"}
}