{
  "type": "Feature",
  "properties": {
    "addr:full": "4700 E Broad St Columbus OH 43213",
    "addr:housenumber": "4700",
    "addr:postcode": "43213",
    "addr:street": "E Broad St",
    "iso:country": "US",
    "sg:address": "4700 E Broad St",
    "sg:city": "Columbus",
    "sg:classifiers": [
      {
        "category": "Autos \u0026 Motor Vehicles",
        "subcategory": "Automobile Sales",
        "type": "Retail Goods"
      }
    ],
    "sg:phone": "+1 614 861 6230",
    "sg:postcode": "43213",
    "sg:province": "OH",
    "sg:tags": [
      "car",
      "used",
      "dealer"
    ],
    "sg:website": "www.davegill.org",
    "wof:name": "Dave Gill Pontiac G M C Truck",
    "wof:placetype": "venue"
  },
  "geometry": {"coordinates":[-82.875482,39.976054],"type":"Point"}
}
