{
  "type": "Feature",
  "properties": {
    "addr:full":"2425 Holt Ave Columbus OH 43219",
    "addr:housenumber":"2425",
    "addr:postcode":"43219",
    "addr:street":"Holt Ave",
    "iso:country":"US",
    "sg:address":"2425 Holt Ave",
    "sg:city":"Columbus",
    "sg:classifiers":[
        {
            "category":"Organizations",
            "subcategory":"Religious Organization",
            "type":"Services"
        }
    ],
    "sg:phone":"+1 614 253 5017",
    "sg:postcode":"43219",
    "sg:province":"OH",
    "sg:tags":[
        "church"
    ],
    "wof:name":"Eternal Life Church Of Christ",
    "wof:placetype":"venue"
},
  "geometry": {"coordinates":[-82.94056,39.999573],"type":"Point"}
}