{
  "type": "Feature",
  "properties": {
    "iso:country":"US",
    "sg:address":"4925 W Main St",
    "sg:city":"Berlin",
    "sg:classifiers":[
        {
            "category":"Banks & Credit Unions",
            "subcategory":"Bank",
            "type":"Services"
        }
    ],
    "sg:phone":"+1 330 893 3300",
    "sg:postcode":"44654",
    "sg:province":"OH",
    "sg:tags":[
        "loan",
        "real estate"
    ],
    "wof:name":"Financial Solutions Group",
    "wof:placetype":"venue"
},
  "geometry": {"coordinates":[-81.79946700000001,40.56181],"type":"Point"}
}