{
  "type": "Feature",
  "properties": {
    "iso:country":"US",
    "sg:address":"3257 Fulton Rd",
    "sg:city":"Cleveland",
    "sg:classifiers":[
        {
            "category":"Retail",
            "subcategory":"Auto Repair",
            "type":"Services"
        }
    ],
    "sg:phone":"+1 216 741 2326",
    "sg:postcode":"44109",
    "sg:province":"OH",
    "sg:tags":[
        "repairing",
        "automobile"
    ],
    "wof:name":"Ruben's Auto Repair",
    "wof:placetype":"venue"
},
  "geometry": {"coordinates":[-81.708243,41.465679],"type":"Point"}
}