{
  "type": "Feature",
  "properties": {
    "iso:country":"US",
    "sg:address":"1235 W Gambier St",
    "sg:city":"Mount Vernon",
    "sg:classifiers":[
        {
            "category":"Wholesale",
            "subcategory":"Scrap",
            "type":"Manufacturing & Wholesale Goods"
        }
    ],
    "sg:phone":"+1 740 392 9510",
    "sg:postcode":"43050",
    "sg:province":"OH",
    "sg:tags":[
        "material"
    ],
    "wof:name":"Ramey John",
    "wof:placetype":"venue"
},
  "geometry": {"coordinates":[-82.500506,40.392553],"type":"Point"}
}