{
  "type": "Feature",
  "properties": {
    "iso:country":"US",
    "sg:address":"2500 W State St",
    "sg:city":"Alliance",
    "sg:classifiers":[
        {
            "category":"Recreation",
            "type":"Entertainment"
        }
    ],
    "sg:phone":"+1 330 829 0178",
    "sg:postcode":"44601",
    "sg:province":"OH",
    "sg:tags":[
        "course",
        "golf"
    ],
    "wof:name":"Perry's Glo Putt",
    "wof:placetype":"venue"
},
  "geometry": {"coordinates":[-81.157723,40.901955],"type":"Point"}
}