{
  "type": "Feature",
  "properties": {
    "iso:country":"US",
    "sg:address":"5315 Heatherdowns Blvd",
    "sg:city":"Toledo",
    "sg:classifiers":[
        {
            "category":"Recreation",
            "type":"Entertainment"
        }
    ],
    "sg:phone":"+1 419 865 2622",
    "sg:postcode":"43614",
    "sg:province":"OH",
    "sg:tags":[
        "course",
        "golf"
    ],
    "wof:name":"Putt Putt Golf & Games",
    "wof:placetype":"venue"
},
  "geometry": {"coordinates":[-83.66661499999999,41.594567],"type":"Point"}
}