{
  "type": "Feature",
  "properties": {
    "iso:country":"US",
    "sg:address":"5763 Mayfield Rd",
    "sg:city":"Cleveland",
    "sg:classifiers":[
        {
            "category":"Health Services",
            "subcategory":"Doctor",
            "type":"Services"
        }
    ],
    "sg:phone":"+1 440 449 2440",
    "sg:postcode":"44124",
    "sg:province":"OH",
    "sg:tags":[
        "dentist"
    ],
    "wof:name":"Alfonso A Rossi Inc",
    "wof:placetype":"venue"
},
  "geometry": {"coordinates":[-81.47153,41.52011],"type":"Point"}
}