{
  "type": "Feature",
  "properties": {
    "addr:full": "716 Adams St Steubenville OH 43952",
    "addr:housenumber": "716",
    "addr:postcode": "43952",
    "addr:street": "Adams St",
    "iso:country": "US",
    "sg:address": "716 Adams St",
    "sg:city": "Steubenville",
    "sg:classifiers": [
      {
        "category": "Wholesale",
        "subcategory": "Stationery",
        "type": "Manufacturing \u0026 Wholesale Goods"
      },
      {
        "category": "Wholesale",
        "subcategory": "Chemicals \u0026 Plastics",
        "type": "Manufacturing \u0026 Wholesale Goods"
      }
    ],
    "sg:phone": "+1 740 283 3416",
    "sg:postcode": "43952",
    "sg:province": "OH",
    "sg:tags": [
      "product",
      "paper",
      "cleaning",
      "supply"
    ],
    "wof:name": "Fort Steuben Supplies Inc",
    "wof:placetype": "venue"
  },
  "geometry": {"coordinates":[-80.620518,40.359583],"type":"Point"}
}
