{
  "type": "Feature",
  "properties": {
    "iso:country":"US",
    "sg:address":"716 Adams St",
    "sg:city":"Steubenville",
    "sg:classifiers":[
        {
            "category":"Wholesale",
            "subcategory":"Stationery",
            "type":"Manufacturing & Wholesale Goods"
        },
        {
            "category":"Wholesale",
            "subcategory":"Chemicals & Plastics",
            "type":"Manufacturing & Wholesale Goods"
        }
    ],
    "sg:phone":"+1 740 283 3416",
    "sg:postcode":"43952",
    "sg:province":"OH",
    "sg:tags":[
        "product",
        "paper",
        "cleaning",
        "supply"
    ],
    "wof:name":"Fort Steuben Supplies Inc",
    "wof:placetype":"venue"
},
  "geometry": {"coordinates":[-80.620518,40.359583],"type":"Point"}
}