{
  "type": "Feature",
  "properties": {
    "iso:country":"US",
    "sg:address":"221 Elyria St",
    "sg:city":"Lodi",
    "sg:classifiers":[
        {
            "category":"Health Services",
            "subcategory":"Optometrist",
            "type":"Services"
        }
    ],
    "sg:phone":"+1 419 289 6466",
    "sg:postcode":"44254",
    "sg:province":"OH",
    "sg:website":"www.itsyoureyes.com",
    "wof:name":"Gupta Mohinder K MD",
    "wof:placetype":"venue"
},
  "geometry": {"coordinates":[-82.013215,41.035084],"type":"Point"}
}