{
  "type": "Feature",
  "properties": {
    "addr:full": "217 S Main St Van Buren OH 45889",
    "addr:housenumber": "217",
    "addr:postcode": "45889",
    "addr:street": "S Main St",
    "iso:country": "US",
    "sg:address": "217 S Main St",
    "sg:city": "Van Buren",
    "sg:classifiers": [
      {
        "category": "Government",
        "subcategory": "Office",
        "type": "Public Place"
      },
      {
        "category": "Education",
        "subcategory": "School",
        "type": "Public Place"
      }
    ],
    "sg:phone": "+1 419 299 3416",
    "sg:postcode": "45889",
    "sg:province": "OH",
    "sg:tags": [
      "educational",
      "program",
      "administrative"
    ],
    "wof:name": "Van Buren Local School Dst",
    "wof:placetype": "venue"
  },
  "geometry": {"coordinates":[-83.649396,41.136195],"type":"Point"}
}
