{
  "type": "Feature",
  "properties": {
    "addr:full": "1230 Lexington Ave Mansfield OH 44907",
    "addr:housenumber": "1230",
    "addr:postcode": "44907",
    "addr:street": "Lexington Ave",
    "iso:country": "US",
    "sg:address": "1230 Lexington Ave",
    "sg:city": "Mansfield",
    "sg:classifiers": [
      {
        "category": "Real Estate",
        "subcategory": "Real Estate Agent",
        "type": "Services"
      }
    ],
    "sg:phone": "+1 419 756 8678",
    "sg:postcode": "44907",
    "sg:province": "OH",
    "sg:website": "www.natepurdy.com",
    "wof:name": "Re/Max Integrity Realty",
    "wof:placetype": "venue"
  },
  "geometry": {"coordinates":[-82.540885,40.724548],"type":"Point"}
}
