{
  "type": "Feature",
  "properties": {
    "addr:full":"1550 Old Henderson Rd Columbus OH 43220",
    "addr:housenumber":"1550",
    "addr:postcode":"43220",
    "addr:street":"Old Henderson Rd",
    "iso:country":"US",
    "sg:address":"1550 Old Henderson Rd",
    "sg:city":"Columbus",
    "sg:classifiers":[
        {
            "category":"Retail",
            "subcategory":"Repair Shop",
            "type":"Services"
        }
    ],
    "sg:phone":"+1 614 442 3981",
    "sg:postcode":"43220",
    "sg:province":"OH",
    "sg:tags":[
        "equipment"
    ],
    "wof:name":"Divisions",
    "wof:placetype":"venue"
},
  "geometry": {"coordinates":[-83.05995900000001,40.051815],"type":"Point"}
}