{
  "type": "Feature",
  "properties": {
    "addr:full": "4003 Bach Buxton Rd Amelia OH 45102",
    "addr:postcode": "4003;45102",
    "addr:street": "Buxton Rd",
    "iso:country": "US",
    "sg:address": "4003 Bach Buxton Rd",
    "sg:city": "Amelia",
    "sg:classifiers": [
      {
        "category": "Retail",
        "subcategory": "Repair Shop",
        "type": "Services"
      }
    ],
    "sg:phone": "+1 513 753 6292",
    "sg:postcode": "45102",
    "sg:province": "OH",
    "sg:tags": [
      "commercial",
      "welding"
    ],
    "wof:name": "Wolf Creek Welding Inc",
    "wof:placetype": "venue"
  },
  "geometry": {"coordinates":[-84.245294,39.067228],"type":"Point"}
}
