{
  "type": "Feature",
  "properties": {
    "iso:country":"US",
    "sg:address":"9994 International Blvd",
    "sg:city":"Cincinnati",
    "sg:classifiers":[
        {
            "category":"Wholesale",
            "subcategory":"Medical Equipment & Supplies",
            "type":"Manufacturing & Wholesale Goods"
        }
    ],
    "sg:phone":"+1 513 874 0002",
    "sg:postcode":"45246",
    "sg:province":"OH",
    "sg:tags":[
        "hospital"
    ],
    "wof:name":"Primedica Home Health Ctr",
    "wof:placetype":"venue"
},
  "geometry": {"coordinates":[-84.442632,39.305602],"type":"Point"}
}