{
  "type": "Feature",
  "properties": {
    "addr:full":"3653 Lost Nation Rd Willoughby OH 44094",
    "addr:housenumber":"3653",
    "addr:postcode":"44094",
    "addr:street":"Lost Nation Rd",
    "iso:country":"US",
    "sg:address":"3653 Lost Nation Rd",
    "sg:city":"Willoughby",
    "sg:classifiers":[
        {
            "category":"Retail",
            "subcategory":"Auto Repair",
            "type":"Services"
        }
    ],
    "sg:phone":"+1 440 918 1500",
    "sg:postcode":"44094",
    "sg:province":"OH",
    "sg:tags":[
        "repairing",
        "automobile"
    ],
    "wof:name":"Service Garage Inc",
    "wof:placetype":"venue"
},
  "geometry": {"coordinates":[-81.40393299999999,41.653724],"type":"Point"}
}