{
  "type": "Feature",
  "properties": {
    "addr:full":"12811 State Rte 664 Scn Logan OH 43138",
    "addr:housenumber":"12811",
    "addr:postcode":"43138",
    "addr:street":"State Rte 664 Scn",
    "iso:country":"US",
    "sg:address":"12811 State Rte 664 Scn",
    "sg:city":"Logan",
    "sg:classifiers":[
        {
            "category":"Shopping",
            "type":"Retail Goods"
        }
    ],
    "sg:phone":"+1 740 380 9400",
    "sg:postcode":"43138",
    "sg:province":"OH",
    "sg:tags":[
        "factory",
        "outlet"
    ],
    "wof:name":"Midwest Glassware Outlet",
    "wof:placetype":"venue"
},
  "geometry": {"coordinates":[-82.438169,39.541574],"type":"Point"}
}