{
  "type": "Feature",
  "properties": {
    "addr:full":"1707 E Main St Kent OH 44240",
    "addr:housenumber":"1707",
    "addr:postcode":"44240",
    "addr:street":"E Main St",
    "iso:country":"US",
    "sg:address":"1707 E Main St",
    "sg:city":"Kent",
    "sg:classifiers":[
        {
            "category":"Personal",
            "subcategory":"Tanning Parlor",
            "type":"Services"
        }
    ],
    "sg:phone":"+1 330 677 7084",
    "sg:postcode":"44240",
    "sg:province":"OH",
    "sg:tags":[
        "salon"
    ],
    "wof:name":"Sun Tan Co",
    "wof:placetype":"venue"
},
  "geometry": {"coordinates":[-81.330676,41.154795],"type":"Point"}
}