{
  "type": "Feature",
  "properties": {
    "addr:full": "1681 E Middletown Rd North Lima OH 44452",
    "addr:housenumber": "1681",
    "addr:postcode": "44452",
    "addr:street": "E Middletown Rd",
    "iso:country": "US",
    "sg:address": "1681 E Middletown Rd",
    "sg:city": "North Lima",
    "sg:classifiers": [
      {
        "category": "Social Services",
        "type": "Services"
      }
    ],
    "sg:phone": "+1 330 549 5465",
    "sg:postcode": "44452",
    "sg:province": "OH",
    "sg:tags": [
      "organization",
      "welfare"
    ],
    "wof:name": "Club Hollwywood Inc",
    "wof:placetype": "venue"
  },
  "geometry": {"coordinates":[-80.620393,40.958074],"type":"Point"}
}
