{
  "type": "Feature",
  "properties": {
    "iso:country":"US",
    "sg:address":"215 Oak St",
    "sg:city":"Mansfield",
    "sg:classifiers":[
        {
            "category":"Building & Trades",
            "subcategory":"Construction",
            "type":"Services"
        }
    ],
    "sg:phone":"+1 419 522 2715",
    "sg:postcode":"44907",
    "sg:province":"OH",
    "sg:tags":[
        "product",
        "asphalt"
    ],
    "sg:website":"www.kokosing.biz",
    "wof:name":"Kokosing Materials Inc",
    "wof:placetype":"venue"
},
  "geometry": {"coordinates":[-82.50045299999999,40.755202],"type":"Point"}
}