{
  "type": "Feature",
  "properties": {
    "addr:full":"11885 Prospect Rd Strongsville OH 44149",
    "addr:housenumber":"11885",
    "addr:postcode":"44149",
    "addr:street":"Prospect Rd",
    "iso:country":"US",
    "sg:address":"11885 Prospect Rd",
    "sg:city":"Strongsville",
    "sg:classifiers":[
        {
            "category":"Building & Trades",
            "subcategory":"Electrical",
            "type":"Services"
        },
        {
            "category":"Building & Trades",
            "subcategory":"Construction",
            "type":"Services"
        }
    ],
    "sg:phone":"+1 440 878 3791",
    "sg:postcode":"44149",
    "sg:province":"OH",
    "sg:tags":[
        "electric",
        "commercial",
        "contractor",
        "electrical",
        "new",
        "con"
    ],
    "wof:name":"Richard Sanders Construction",
    "wof:placetype":"venue"
},
  "geometry": {"coordinates":[-81.85769500000001,41.320304],"type":"Point"}
}