{
  "type": "Feature",
  "properties": {
    "addr:full":"801 W High St Mt Vernon OH 43050",
    "addr:housenumber":"801",
    "addr:postcode":"43050",
    "addr:street":"W High St",
    "iso:country":"US",
    "sg:address":"801 W High St",
    "sg:city":"Mt Vernon",
    "sg:classifiers":[
        {
            "category":"Organizations",
            "subcategory":"Religious Organization",
            "type":"Services"
        }
    ],
    "sg:phone":"+1 740 392 2777",
    "sg:postcode":"43050",
    "sg:province":"OH",
    "sg:tags":[
        "church"
    ],
    "wof:name":"Apostolic Faith Church",
    "wof:placetype":"venue"
},
  "geometry": {"coordinates":[-82.49650099999999,40.394133],"type":"Point"}
}