{
  "type": "Feature",
  "properties": {
    "addr:full": "10068 Settlement House Rd Dayton OH 45458",
    "addr:housenumber": "10068",
    "addr:postcode": "45458",
    "addr:street": "Settlement House Rd",
    "iso:country": "US",
    "sg:address": "10068 Settlement House Rd",
    "sg:city": "Dayton",
    "sg:classifiers": [
      {
        "category": "Real Estate",
        "subcategory": "Real Estate Agent",
        "type": "Services"
      }
    ],
    "sg:phone": "+1 937 885 5705",
    "sg:postcode": "45458",
    "sg:province": "OH",
    "wof:name": "Spencer Jack Sandra Realators",
    "wof:placetype": "venue"
  },
  "geometry": {"coordinates":[-84.14324,39.594775],"type":"Point"}
}
