{
  "type": "Feature",
  "properties": {
    "iso:country":"US",
    "sg:address":"17055 Kinsman Rd",
    "sg:city":"Middlefield",
    "sg:classifiers":[
        {
            "category":"Home & Garden",
            "subcategory":"Building Materials",
            "type":"Retail Goods"
        }
    ],
    "sg:phone":"+1 440 632 6353",
    "sg:postcode":"44062",
    "sg:province":"OH",
    "wof:name":"Troymill Lumber",
    "wof:placetype":"venue"
},
  "geometry": {"coordinates":[-81.026702,41.458943],"type":"Point"}
}