{
  "type": "Feature",
  "properties": {
    "addr:full": "4415 Neely Rd Lima OH 45807",
    "addr:housenumber": "4415",
    "addr:postcode": "45807",
    "addr:street": "Neely Rd",
    "iso:country": "US",
    "sg:address": "4415 Neely Rd",
    "sg:city": "Lima",
    "sg:classifiers": [
      {
        "category": "Building \u0026 Trades",
        "subcategory": "Construction",
        "type": "Services"
      }
    ],
    "sg:phone": "+1 419 339 7112",
    "sg:postcode": "45807",
    "sg:province": "OH",
    "sg:tags": [
      "mfg",
      "cabinet",
      "furniture"
    ],
    "wof:name": "Heatwoles Custom Made Cabinet",
    "wof:placetype": "venue"
  },
  "geometry": {"coordinates":[-84.174259,40.765663],"type":"Point"}
}
