{
  "type": "Feature",
  "properties": {
    "iso:country":"US",
    "sg:address":"4415 Neely Rd",
    "sg:city":"Lima",
    "sg:classifiers":[
        {
            "category":"Building & Trades",
            "subcategory":"Construction",
            "type":"Services"
        }
    ],
    "sg:phone":"+1 419 339 7112",
    "sg:postcode":"45807",
    "sg:province":"OH",
    "sg:tags":[
        "mfg",
        "cabinet",
        "furniture"
    ],
    "wof:name":"Heatwoles Custom Made Cabinet",
    "wof:placetype":"venue"
},
  "geometry": {"coordinates":[-84.17425900000001,40.765663],"type":"Point"}
}