{
  "type": "Feature",
  "properties": {
    "addr:full":"3683 S Meridian Rd Youngstown OH 44511",
    "addr:housenumber":"3683",
    "addr:postcode":"44511",
    "addr:street":"S Meridian Rd",
    "iso:country":"US",
    "sg:address":"3683 S Meridian Rd",
    "sg:city":"Youngstown",
    "sg:classifiers":[
        {
            "category":"Shopping",
            "subcategory":"Pharmacy",
            "type":"Retail Goods"
        }
    ],
    "sg:phone":"+1 330 799 6997",
    "sg:postcode":"44511",
    "sg:province":"OH",
    "sg:tags":[
        "drug",
        "store"
    ],
    "wof:name":"Rite Aid",
    "wof:placetype":"venue"
},
  "geometry": {"coordinates":[-80.710993,41.06395],"type":"Point"}
}