{
  "type": "Feature",
  "properties": {
    "iso:country":"US",
    "sg:address":"872 Valley View Dr NW",
    "sg:city":"Lancaster",
    "sg:classifiers":[
        {
            "category":"Real Estate",
            "subcategory":"Real Estate Operator",
            "type":"Services"
        }
    ],
    "sg:phone":"+1 740 687 0118",
    "sg:postcode":"43130",
    "sg:province":"OH",
    "sg:tags":[
        "building",
        "nonresidential"
    ],
    "wof:name":"4m One Stop Properties LLC",
    "wof:placetype":"venue"
},
  "geometry": {"coordinates":[-82.617245,39.76101],"type":"Point"}
}