{
  "type": "Feature",
  "properties": {
    "iso:country":"US",
    "sg:address":"81 E Washburn St",
    "sg:city":"New London",
    "sg:classifiers":[
        {
            "category":"Manufacturing",
            "subcategory":"Tools & Machinery",
            "type":"Manufacturing & Wholesale Goods"
        }
    ],
    "sg:phone":"+1 419 929 1554",
    "sg:postcode":"44851",
    "sg:province":"OH",
    "sg:tags":[
        "repair",
        "industrial",
        "electrical",
        "welding",
        "mfg"
    ],
    "sg:website":"www.rothmfg.net",
    "wof:name":"Roth Manufacturing Corporation",
    "wof:placetype":"venue"
},
  "geometry": {"coordinates":[-82.395144,41.089386],"type":"Point"}
}