{
  "type": "Feature",
  "properties": {
    "addr:full": "81 E Washburn St New London OH 44851",
    "addr:housenumber": "81",
    "addr:postcode": "44851",
    "addr:street": "E Washburn St",
    "iso:country": "US",
    "sg:address": "81 E Washburn St",
    "sg:city": "New London",
    "sg:classifiers": [
      {
        "category": "Manufacturing",
        "subcategory": "Tools \u0026 Machinery",
        "type": "Manufacturing \u0026 Wholesale Goods"
      }
    ],
    "sg:phone": "+1 419 929 1554",
    "sg:postcode": "44851",
    "sg:province": "OH",
    "sg:tags": [
      "repair",
      "industrial",
      "electrical",
      "welding",
      "mfg"
    ],
    "sg:website": "www.rothmfg.net",
    "wof:name": "Roth Manufacturing Corporation",
    "wof:placetype": "venue"
  },
  "geometry": {"coordinates":[-82.395144,41.089386],"type":"Point"}
}
