{
  "type": "Feature",
  "properties": {
    "iso:country":"US",
    "sg:address":"428 Clough St",
    "sg:city":"Bowling Green",
    "sg:classifiers":[
        {
            "category":"Manufacturing",
            "subcategory":"Retail Goods",
            "type":"Manufacturing & Wholesale Goods"
        }
    ],
    "sg:phone":"+1 419 354 2844",
    "sg:postcode":"43402",
    "sg:province":"OH",
    "sg:tags":[
        "assembly",
        "fabricating"
    ],
    "wof:name":"Advanced Specialty Products",
    "wof:placetype":"venue"
},
  "geometry": {"coordinates":[-83.64460099999999,41.373062],"type":"Point"}
}