{
  "type": "Feature",
  "properties": {
    "addr:full": "428 Clough St Bowling Green OH 43402",
    "addr:housenumber": "428",
    "addr:postcode": "43402",
    "addr:street": "Clough St",
    "iso:country": "US",
    "sg:address": "428 Clough St",
    "sg:city": "Bowling Green",
    "sg:classifiers": [
      {
        "category": "Manufacturing",
        "subcategory": "Retail Goods",
        "type": "Manufacturing \u0026 Wholesale Goods"
      }
    ],
    "sg:phone": "+1 419 354 2844",
    "sg:postcode": "43402",
    "sg:province": "OH",
    "sg:tags": [
      "assembly",
      "fabricating"
    ],
    "wof:name": "Advanced Specialty Products",
    "wof:placetype": "venue"
  },
  "geometry": {"coordinates":[-83.644601,41.373062],"type":"Point"}
}
