{
  "type": "Feature",
  "properties": {
    "addr:full": "2666 State Rte 19 Oak Harbor OH 43449",
    "addr:housenumber": "2666",
    "addr:postcode": "43449",
    "addr:street": "State Rte 19",
    "iso:country": "US",
    "sg:address": "2666 State Rte 19",
    "sg:city": "Oak Harbor",
    "sg:classifiers": [
      {
        "category": "Manufacturing",
        "subcategory": "Food",
        "type": "Manufacturing \u0026 Wholesale Goods"
      }
    ],
    "sg:phone": "+1 419 898 2638",
    "sg:postcode": "43449",
    "sg:province": "OH",
    "sg:tags": [
      "mfg"
    ],
    "wof:name": "Bigbenzkis Inc",
    "wof:placetype": "venue"
  },
  "geometry": {"coordinates":[-83.14497,41.566559],"type":"Point"}
}
