{
  "type": "Feature",
  "properties": {
    "iso:country":"US",
    "sg:address":"2666 State Rte 19",
    "sg:city":"Oak Harbor",
    "sg:classifiers":[
        {
            "category":"Manufacturing",
            "subcategory":"Food",
            "type":"Manufacturing & Wholesale Goods"
        }
    ],
    "sg:phone":"+1 419 898 2638",
    "sg:postcode":"43449",
    "sg:province":"OH",
    "sg:tags":[
        "mfg"
    ],
    "wof:name":"Bigbenzkis Inc",
    "wof:placetype":"venue"
},
  "geometry": {"coordinates":[-83.14497,41.566559],"type":"Point"}
}