{
  "type": "Feature",
  "properties": {
    "addr:full": "5621 Walnut Creek Rd Kingston OH 45644",
    "addr:housenumber": "5621",
    "addr:postcode": "45644",
    "addr:street": "Walnut Creek Rd",
    "iso:country": "US",
    "sg:address": "5621 Walnut Creek Rd",
    "sg:city": "Kingston",
    "sg:classifiers": [
      {
        "category": "Building \u0026 Trades",
        "subcategory": "Construction",
        "type": "Services"
      }
    ],
    "sg:phone": "+1 740 655 3577",
    "sg:postcode": "45644",
    "sg:province": "OH",
    "sg:tags": [
      "general",
      "contractor"
    ],
    "wof:name": "Persinger Basic Construction",
    "wof:placetype": "venue"
  },
  "geometry": {"coordinates":[-82.83541,39.394257],"type":"Point"}
}
