{
  "type": "Feature",
  "properties": {
    "addr:full": "4400 Marketing Pl Groveport OH 43125",
    "addr:postcode": "4400;43125",
    "addr:street": "Marketing Pl",
    "iso:country": "US",
    "sg:address": "4400 Marketing Pl",
    "sg:city": "Groveport",
    "sg:classifiers": [
      {
        "category": "Professional",
        "subcategory": "Advertising",
        "type": "Services"
      }
    ],
    "sg:phone": "+1 614 836 5703",
    "sg:postcode": "43125",
    "sg:province": "OH",
    "sg:tags": [
      "mail",
      "mailing",
      "direct",
      "shipping"
    ],
    "wof:name": "W C National Mailing Corp",
    "wof:placetype": "venue"
  },
  "geometry": {"coordinates":[-82.89058,39.883083],"type":"Point"}
}
