{
  "type": "Feature",
  "properties": {
    "iso:country":"US",
    "sg:address":"4400 Marketing Pl",
    "sg:city":"Groveport",
    "sg:classifiers":[
        {
            "category":"Professional",
            "subcategory":"Advertising",
            "type":"Services"
        }
    ],
    "sg:phone":"+1 614 836 5703",
    "sg:postcode":"43125",
    "sg:province":"OH",
    "sg:tags":[
        "mail",
        "mailing",
        "direct",
        "shipping"
    ],
    "wof:name":"W C National Mailing Corp",
    "wof:placetype":"venue"
},
  "geometry": {"coordinates":[-82.89058,39.883083],"type":"Point"}
}