{
  "type": "Feature",
  "properties": {
    "iso:country":"US",
    "sg:address":"23571 State Rte 51",
    "sg:city":"Genoa",
    "sg:classifiers":[
        {
            "category":"Recreation",
            "type":"Entertainment"
        }
    ],
    "sg:phone":"+1 419 855 9060",
    "sg:postcode":"43430",
    "sg:province":"OH",
    "sg:tags":[
        "amusement"
    ],
    "wof:name":"D Z Motor Sports",
    "wof:placetype":"venue"
},
  "geometry": {"coordinates":[-83.388526,41.550988],"type":"Point"}
}