{
  "type": "Feature",
  "properties": {
    "iso:country":"US",
    "sg:address":"3610 Chesterton Dr",
    "sg:city":"Toledo",
    "sg:classifiers":[
        {
            "category":"Farming",
            "subcategory":"Farm",
            "type":"Manufacturing & Wholesale Goods"
        }
    ],
    "sg:phone":"+1 419 841 3758",
    "sg:postcode":"43615",
    "sg:province":"OH",
    "sg:tags":[
        "crop",
        "general"
    ],
    "wof:name":"7 Lazey D Acres",
    "wof:placetype":"venue"
},
  "geometry": {"coordinates":[-83.654758,41.684621],"type":"Point"}
}