{
  "type": "Feature",
  "properties": {
    "iso:country":"US",
    "sg:address":"842 W Boundary St",
    "sg:city":"Perrysburg",
    "sg:classifiers":[
        {
            "category":"Social Services",
            "type":"Services"
        }
    ],
    "sg:phone":"+1 419 873 4673",
    "sg:postcode":"43551",
    "sg:province":"OH",
    "sg:tags":[
        "organization",
        "welfare"
    ],
    "wof:name":"New Hope Christian Community",
    "wof:placetype":"venue"
},
  "geometry": {"coordinates":[-83.63592199999999,41.547242],"type":"Point"}
}