{
  "type": "Feature",
  "properties": {
    "addr:full": "4352 W Sylvania Ave Toledo OH 43623",
    "addr:housenumber": "4352",
    "addr:postcode": "43623",
    "addr:street": "W Sylvania Ave",
    "iso:country": "US",
    "sg:address": "4352 W Sylvania Ave",
    "sg:city": "Toledo",
    "sg:classifiers": [
      {
        "category": "Building \u0026 Trades",
        "subcategory": "Construction",
        "type": "Services"
      }
    ],
    "sg:phone": "+1 419 843 7156",
    "sg:postcode": "43623",
    "sg:province": "OH",
    "sg:tags": [
      "contractor"
    ],
    "wof:name": "Forum Building",
    "wof:placetype": "venue"
  },
  "geometry": {"coordinates":[-83.648068,41.691274],"type":"Point"}
}
