{
  "type": "Feature",
  "properties": {
    "iso:country":"US",
    "sg:address":"6901 State Rte 305",
    "sg:city":"Hartford",
    "sg:classifiers":[
        {
            "category":"Government",
            "subcategory":"Office",
            "type":"Public Place"
        }
    ],
    "sg:phone":"+1 330 772 6186",
    "sg:postcode":"44424",
    "sg:province":"OH",
    "sg:tags":[
        "village"
    ],
    "wof:name":"Hartford Twp Municipal Bldg",
    "wof:placetype":"venue"
},
  "geometry": {"coordinates":[-80.58850099999999,41.311543],"type":"Point"}
}