{
  "type": "Feature",
  "properties": {
    "iso:country":"US",
    "sg:address":"2820 Venice Rd",
    "sg:city":"Sandusky",
    "sg:classifiers":[
        {
            "category":"Professional",
            "subcategory":"Accounting & Tax Preparation",
            "type":"Services"
        }
    ],
    "sg:phone":"+1 419 625 5756",
    "sg:postcode":"44870",
    "sg:province":"OH",
    "sg:tags":[
        "return",
        "filing"
    ],
    "wof:name":"Firelands Income Tax Svc Inc",
    "wof:placetype":"venue"
},
  "geometry": {"coordinates":[-82.738987,41.440416],"type":"Point"}
}