{
  "type": "Feature",
  "properties": {
    "addr:full":"30650 Pinetree Rd Cleveland OH 44124",
    "addr:housenumber":"30650",
    "addr:postcode":"44124",
    "addr:street":"Pinetree Rd",
    "iso:country":"US",
    "sg:address":"30650 Pinetree Rd",
    "sg:city":"Cleveland",
    "sg:classifiers":[
        {
            "category":"Professional",
            "subcategory":"Detective & Security Services",
            "type":"Services"
        }
    ],
    "sg:phone":"+1 216 464 1925",
    "sg:postcode":"44124",
    "sg:province":"OH",
    "wof:name":"Branon Mc Cann Group",
    "wof:placetype":"venue"
},
  "geometry": {"coordinates":[-81.460165,41.46225],"type":"Point"}
}