{
  "type": "Feature",
  "properties": {
    "addr:full": "6501 Cornell Rd Cincinnati OH 45242",
    "addr:housenumber": "6501",
    "addr:postcode": "45242",
    "addr:street": "Cornell Rd",
    "iso:country": "US",
    "sg:address": "6501 Cornell Rd",
    "sg:city": "Cincinnati",
    "sg:classifiers": [
      {
        "category": "Manufacturing",
        "subcategory": "Apparel",
        "type": "Manufacturing \u0026 Wholesale Goods"
      }
    ],
    "sg:phone": "+1 513 648 0222",
    "sg:postcode": "45242",
    "sg:province": "OH",
    "sg:tags": [
      "product",
      "mfg",
      "fabricated",
      "textile",
      "flag",
      "banner"
    ],
    "wof:name": "Banner Shoppe",
    "wof:placetype": "venue"
  },
  "geometry": {"coordinates":[-84.36082,39.268142],"type":"Point"}
}
