{
  "type": "Feature",
  "properties": {
    "iso:country":"US",
    "sg:address":"21 Hamilton St",
    "sg:city":"Monroeville",
    "sg:classifiers":[
        {
            "category":"Manufacturing",
            "subcategory":"Rubber & Plastics",
            "type":"Manufacturing & Wholesale Goods"
        }
    ],
    "sg:phone":"+1 419 465 3303",
    "sg:postcode":"44847",
    "sg:province":"OH",
    "sg:tags":[
        "product",
        "mfg"
    ],
    "sg:website":"www.burkettmolding.com",
    "wof:name":"Burkett Molding Inc",
    "wof:placetype":"venue"
},
  "geometry": {"coordinates":[-82.69222600000001,41.243875],"type":"Point"}
}