{
  "type": "Feature",
  "properties": {
    "iso:country":"US",
    "sg:address":"2909 Farrington Rd",
    "sg:city":"Piqua",
    "sg:classifiers":[
        {
            "category":"Building & Trades",
            "subcategory":"Construction",
            "type":"Services"
        }
    ],
    "sg:phone":"+1 937 773 0111",
    "sg:postcode":"45356",
    "sg:province":"OH",
    "sg:tags":[
        "excavation",
        "contractor"
    ],
    "wof:name":"Miller Trenching",
    "wof:placetype":"venue"
},
  "geometry": {"coordinates":[-84.25721,40.104125],"type":"Point"}
}