{
  "type": "Feature",
  "properties": {
    "addr:full": "5000 N Detroit Ave Toledo OH 43612",
    "addr:housenumber": "5000",
    "addr:postcode": "43612",
    "addr:street": "N Detroit Ave",
    "iso:country": "US",
    "sg:address": "5000 N Detroit Ave",
    "sg:city": "Toledo",
    "sg:classifiers": [
      {
        "category": "Wholesale",
        "subcategory": "Scrap",
        "type": "Manufacturing \u0026 Wholesale Goods"
      }
    ],
    "sg:phone": "+1 419 535 8217",
    "sg:postcode": "43612",
    "sg:province": "OH",
    "sg:tags": [
      "material"
    ],
    "sg:website": "www.omnisource.com",
    "wof:name": "Omni Source Corp",
    "wof:placetype": "venue"
  },
  "geometry": {"coordinates":[-83.544258,41.707533],"type":"Point"}
}
