{
  "type": "Feature",
  "properties": {
    "iso:country":"US",
    "sg:address":"7089 Taylorsville Rd",
    "sg:city":"Dayton",
    "sg:classifiers":[
        {
            "category":"Organizations",
            "subcategory":"Community Association",
            "type":"Services"
        }
    ],
    "sg:phone":"+1 937 233 6666",
    "sg:postcode":"45424",
    "sg:province":"OH",
    "sg:tags":[
        "club"
    ],
    "wof:name":"Northside Fellowship Club Inc",
    "wof:placetype":"venue"
},
  "geometry": {"coordinates":[-84.10517299999999,39.860874],"type":"Point"}
}