{
  "type": "Feature",
  "properties": {
    "iso:country":"US",
    "sg:address":"39 E Gay St",
    "sg:city":"Columbus",
    "sg:classifiers":[
        {
            "category":"Manufacturing",
            "subcategory":"Apparel",
            "type":"Manufacturing & Wholesale Goods"
        }
    ],
    "sg:phone":"+1 614 221 7803",
    "sg:postcode":"43215",
    "sg:province":"OH",
    "sg:tags":[
        "flag",
        "banner"
    ],
    "sg:website":"www.signarama.com",
    "wof:name":"Sign-A-Rama",
    "wof:placetype":"venue"
},
  "geometry": {"coordinates":[-82.99848900000001,39.963802],"type":"Point"}
}