{
  "type": "Feature",
  "properties": {
    "addr:full": "4415 Aicholtz Rd Cincinnati OH 45245",
    "addr:housenumber": "4415",
    "addr:postcode": "45245",
    "addr:street": "Aicholtz Rd",
    "iso:country": "US",
    "sg:address": "4415 Aicholtz Rd",
    "sg:city": "Cincinnati",
    "sg:classifiers": [
      {
        "category": "Health Services",
        "subcategory": "Clinic",
        "type": "Services"
      },
      {
        "category": "Health Services",
        "subcategory": "Doctor",
        "type": "Services"
      }
    ],
    "sg:phone": "+1 513 947 1130",
    "sg:postcode": "45245",
    "sg:province": "OH",
    "sg:tags": [
      "surgery",
      "center",
      "surgical"
    ],
    "wof:name": "Surgery Center Of Cincinnati",
    "wof:placetype": "venue"
  },
  "geometry": {"coordinates":[-84.279284,39.094555],"type":"Point"}
}
