{
  "type": "Feature",
  "properties": {
    "iso:country":"US",
    "sg:address":"5742 Barbanna Ln",
    "sg:city":"Dayton",
    "sg:classifiers":[
        {
            "category":"Food & Beverages",
            "subcategory":"Specialty",
            "type":"Retail Goods"
        }
    ],
    "sg:phone":"+1 937 534 6976",
    "sg:postcode":"45415",
    "sg:province":"OH",
    "wof:name":"Irvin Enterprises",
    "wof:placetype":"venue"
},
  "geometry": {"coordinates":[-84.254993,39.827654],"type":"Point"}
}