{
  "type": "Feature",
  "properties": {
    "addr:full": "3223 Profit Dr Fairfield OH 45014",
    "addr:housenumber": "3223",
    "addr:postcode": "45014",
    "addr:street": "Profit Dr",
    "iso:country": "US",
    "sg:address": "3223 Profit Dr",
    "sg:city": "Fairfield",
    "sg:classifiers": [
      {
        "category": "Wholesale",
        "subcategory": "Metals \u0026 Minerals",
        "type": "Manufacturing \u0026 Wholesale Goods"
      }
    ],
    "sg:phone": "+1 513 942 2525",
    "sg:postcode": "45014",
    "sg:province": "OH",
    "sg:tags": [
      "pipe"
    ],
    "wof:name": "Midwest Pipe \u0026 Supply Co",
    "wof:placetype": "venue"
  },
  "geometry": {"coordinates":[-84.505636,39.33417],"type":"Point"}
}
