{
  "type": "Feature",
  "properties": {
    "addr:full": "20141 Detroit Rd Cleveland OH 44116",
    "addr:housenumber": "20141",
    "addr:postcode": "44116",
    "addr:street": "Detroit Rd",
    "iso:country": "US",
    "sg:address": "20141 Detroit Rd",
    "sg:city": "Cleveland",
    "sg:classifiers": [
      {
        "category": "Organizations",
        "subcategory": "Religious Organization",
        "type": "Services"
      }
    ],
    "sg:phone": "+1 440 331 4255",
    "sg:postcode": "44116",
    "sg:province": "OH",
    "sg:tags": [
      "church"
    ],
    "wof:name": "St Christopher's Church",
    "wof:placetype": "venue"
  },
  "geometry": {"coordinates":[-81.845363,41.478035],"type":"Point"}
}
