{
  "type": "Feature",
  "properties": {
    "addr:full": "241 N Superior St Toledo OH 43604",
    "addr:housenumber": "241",
    "addr:postcode": "43604",
    "addr:street": "N Superior St",
    "iso:country": "US",
    "sg:address": "241 N Superior St",
    "sg:city": "Toledo",
    "sg:classifiers": [
      {
        "category": "Social Services",
        "type": "Services"
      }
    ],
    "sg:phone": "+1 419 242 9587",
    "sg:postcode": "43604",
    "sg:province": "OH",
    "sg:tags": [
      "organization",
      "welfare"
    ],
    "wof:name": "Parent Helping Parents Tough",
    "wof:placetype": "venue"
  },
  "geometry": {"coordinates":[-83.536178,41.651332],"type":"Point"}
}
