{
  "type": "Feature",
  "properties": {
    "iso:country":"US",
    "sg:address":"3355 Eastern Rd",
    "sg:city":"Norton",
    "sg:classifiers":[
        {
            "category":"Insurance",
            "subcategory":"Insurance Agent",
            "type":"Services"
        }
    ],
    "sg:phone":"+1 330 825 4790",
    "sg:postcode":"44203",
    "sg:province":"OH",
    "wof:name":"Bragg Insurance",
    "wof:placetype":"venue"
},
  "geometry": {"coordinates":[-81.64576700000001,40.988632],"type":"Point"}
}