{
  "type": "Feature",
  "properties": {
    "iso:country":"US",
    "sg:address":"773 Ohio Pike",
    "sg:city":"Cincinnati",
    "sg:classifiers":[
        {
            "category":"Personal",
            "subcategory":"Beauty Salon",
            "type":"Services"
        }
    ],
    "sg:phone":"+1 513 752 1111",
    "sg:postcode":"45245",
    "sg:province":"OH",
    "sg:tags":[
        "shop",
        "barber"
    ],
    "wof:name":"Collage",
    "wof:placetype":"venue"
},
  "geometry": {"coordinates":[-84.283699,39.064999],"type":"Point"}
}