{
  "type": "Feature",
  "properties": {
    "addr:full": "219 W Boardman St Youngstown OH 44503",
    "addr:housenumber": "219",
    "addr:postcode": "44503",
    "addr:street": "W Boardman St",
    "iso:country": "US",
    "sg:address": "219 W Boardman St",
    "sg:city": "Youngstown",
    "sg:classifiers": [
      {
        "category": "Manufacturing",
        "subcategory": "Printing",
        "type": "Manufacturing \u0026 Wholesale Goods"
      }
    ],
    "sg:phone": "+1 330 747 2282",
    "sg:postcode": "44503",
    "sg:province": "OH",
    "sg:tags": [
      "newspaper"
    ],
    "wof:name": "Youngstown Newspaper Guild",
    "wof:placetype": "venue"
  },
  "geometry": {"coordinates":[-80.654119,41.100858],"type":"Point"}
}
