{
  "type": "Feature",
  "properties": {
    "iso:country":"US",
    "sg:address":"219 W Boardman St",
    "sg:city":"Youngstown",
    "sg:classifiers":[
        {
            "category":"Manufacturing",
            "subcategory":"Printing",
            "type":"Manufacturing & Wholesale Goods"
        }
    ],
    "sg:phone":"+1 330 747 2282",
    "sg:postcode":"44503",
    "sg:province":"OH",
    "sg:tags":[
        "newspaper"
    ],
    "wof:name":"Youngstown Newspaper Guild",
    "wof:placetype":"venue"
},
  "geometry": {"coordinates":[-80.65411899999999,41.100858],"type":"Point"}
}