{
  "type": "Feature",
  "properties": {
    "iso:country":"US",
    "sg:address":"33689 State Rte 93",
    "sg:city":"Mc Arthur",
    "sg:classifiers":[
        {
            "category":"Food & Beverages",
            "subcategory":"Liquor & Beverages",
            "type":"Retail Goods"
        }
    ],
    "sg:phone":"+1 740 596 8300",
    "sg:postcode":"45651",
    "sg:province":"OH",
    "sg:tags":[
        "beer",
        "ale",
        "alcoholic"
    ],
    "wof:name":"Reedy's Drive Thru",
    "wof:placetype":"venue"
},
  "geometry": {"coordinates":[-82.479939,39.237418],"type":"Point"}
}