{
  "type": "Feature",
  "properties": {
    "iso:country":"US",
    "sg:address":"11351 Pearl Rd",
    "sg:city":"Cleveland",
    "sg:classifiers":[
        {
            "category":"Banks & Credit Unions",
            "subcategory":"Investment Brokerage",
            "type":"Services"
        }
    ],
    "sg:phone":"+1 440 878 0328",
    "sg:postcode":"44136",
    "sg:province":"OH",
    "sg:tags":[
        "consultant",
        "planning",
        "financial"
    ],
    "wof:name":"Comprehensive Financial",
    "wof:placetype":"venue"
},
  "geometry": {"coordinates":[-81.837042,41.327482],"type":"Point"}
}