{
  "type": "Feature",
  "properties": {
    "addr:full": "226 Breaden Dr Monroe OH 45050",
    "addr:housenumber": "226",
    "addr:postcode": "45050",
    "addr:street": "Breaden Dr",
    "iso:country": "US",
    "sg:address": "226 Breaden Dr",
    "sg:city": "Monroe",
    "sg:classifiers": [
      {
        "category": "Retail",
        "subcategory": "Auto Rental",
        "type": "Services"
      }
    ],
    "sg:phone": "+1 513 539 9761",
    "sg:postcode": "45050",
    "sg:province": "OH",
    "sg:tags": [
      "renting",
      "truck",
      "leasing"
    ],
    "wof:name": "Ryder Integrated Logistics Inc",
    "wof:placetype": "venue"
  },
  "geometry": {"coordinates":[-84.339235,39.437253],"type":"Point"}
}
