{
  "type": "Feature",
  "properties": {
    "iso:country":"US",
    "sg:address":"832 Copley Rd",
    "sg:city":"Akron",
    "sg:classifiers":[
        {
            "category":"Personal",
            "subcategory":"Barber",
            "type":"Services"
        }
    ],
    "sg:phone":"+1 330 535 6894",
    "sg:postcode":"44320",
    "sg:province":"OH",
    "wof:name":"Jessie's Barber Shop",
    "wof:placetype":"venue"
},
  "geometry": {"coordinates":[-81.55191600000001,41.084424],"type":"Point"}
}