{
  "type": "Feature",
  "properties": {
    "addr:full": "7681 W Ridgewood Dr Cleveland OH 44129",
    "addr:housenumber": "7681",
    "addr:postcode": "44129",
    "addr:street": "W Ridgewood Dr",
    "iso:country": "US",
    "sg:address": "7681 W Ridgewood Dr",
    "sg:city": "Cleveland",
    "sg:classifiers": [
      {
        "category": "Shopping",
        "subcategory": "Clothing, Apparel, \u0026 Fashions",
        "type": "Retail Goods"
      }
    ],
    "sg:phone": "+1 440 843 8144",
    "sg:postcode": "44129",
    "sg:province": "OH",
    "sg:tags": [
      "wear",
      "formal"
    ],
    "sg:website": "www.tuxedojunction.com",
    "wof:name": "Tuxedo Junction",
    "wof:placetype": "venue"
  },
  "geometry": {"coordinates":[-81.737025,41.384434],"type":"Point"}
}
