{
  "type": "Feature",
  "properties": {
    "addr:full": "502 W 3rd Ave Columbus OH 43201",
    "addr:housenumber": "502",
    "addr:postcode": "43201",
    "addr:street": "W 3Rd Ave",
    "iso:country": "US",
    "sg:address": "502 W 3rd Ave",
    "sg:city": "Columbus",
    "sg:classifiers": [
      {
        "category": "Shopping",
        "subcategory": "Used Merchandise",
        "type": "Retail Goods"
      }
    ],
    "sg:phone": "+1 614 294 5998",
    "sg:postcode": "43201",
    "sg:province": "OH",
    "sg:tags": [
      "antique",
      "shop"
    ],
    "wof:name": "James V Carpino",
    "wof:placetype": "venue"
  },
  "geometry": {"coordinates":[-83.018553,39.984037],"type":"Point"}
}
