{
  "type": "Feature",
  "properties": {
    "iso:country":"US",
    "sg:address":"450 Boardman Poland Rd",
    "sg:city":"Youngstown",
    "sg:classifiers":[
        {
            "category":"Real Estate",
            "subcategory":"Developer",
            "type":"Services"
        }
    ],
    "sg:phone":"+1 330 726 7653",
    "sg:postcode":"44514",
    "sg:province":"OH",
    "wof:name":"Gardenridge Development LLC",
    "wof:placetype":"venue"
},
  "geometry": {"coordinates":[-80.646371,41.024379],"type":"Point"}
}