{
  "type": "Feature",
  "properties": {
    "addr:full":"29299 Clemens Rd Westlake OH 44145",
    "addr:housenumber":"29299",
    "addr:postcode":"44145",
    "addr:street":"Clemens Rd",
    "iso:country":"US",
    "sg:address":"29299 Clemens Rd",
    "sg:city":"Westlake",
    "sg:classifiers":[
        {
            "category":"Wholesale",
            "subcategory":"Machinery & Supplies",
            "type":"Manufacturing & Wholesale Goods"
        }
    ],
    "sg:phone":"+1 440 871 7504",
    "sg:postcode":"44145",
    "sg:province":"OH",
    "sg:tags":[
        "equipment",
        "industrial",
        "graphite"
    ],
    "wof:name":"Tim Cal America",
    "wof:placetype":"venue"
},
  "geometry": {"coordinates":[-81.94377299999999,41.470454],"type":"Point"}
}