{
  "type": "Feature",
  "properties": {
    "iso:country":"US",
    "sg:address":"615 Merrick Ave",
    "sg:city":"Zanesville",
    "sg:classifiers":[
        {
            "category":"Building & Trades",
            "subcategory":"Electrical",
            "type":"Services"
        }
    ],
    "sg:phone":"+1 740 453 6932",
    "sg:postcode":"43701",
    "sg:province":"OH",
    "sg:tags":[
        "electrical",
        "contractor"
    ],
    "wof:name":"John E Maziar Elec",
    "wof:placetype":"venue"
},
  "geometry": {"coordinates":[-82.014841,39.916807],"type":"Point"}
}