{
  "type": "Feature",
  "properties": {
    "iso:country":"US",
    "sg:address":"209 Bridge St",
    "sg:city":"Malvern",
    "sg:classifiers":[
        {
            "category":"Professional",
            "subcategory":"Lawyer & Legal Services",
            "type":"Services"
        }
    ],
    "sg:phone":"+1 330 863 9455",
    "sg:postcode":"44644",
    "sg:province":"OH",
    "sg:tags":[
        "attorney"
    ],
    "wof:name":"Vincent Slabaugh",
    "wof:placetype":"venue"
},
  "geometry": {"coordinates":[-81.178849,40.688142],"type":"Point"}
}