{
  "type": "Feature",
  "properties": {
    "addr:full":"1084 Rarig Ave Columbus OH 43219",
    "addr:housenumber":"1084",
    "addr:postcode":"43219",
    "addr:street":"Rarig Ave",
    "iso:country":"US",
    "sg:address":"1084 Rarig Ave",
    "sg:city":"Columbus",
    "sg:classifiers":[
        {
            "category":"Building & Trades",
            "subcategory":"Construction",
            "type":"Services"
        }
    ],
    "sg:phone":"+1 614 252 0086",
    "sg:postcode":"43219",
    "sg:province":"OH",
    "sg:tags":[
        "general",
        "contractor"
    ],
    "wof:name":"John James Estes & Assoc",
    "wof:placetype":"venue"
},
  "geometry": {"coordinates":[-82.922516,39.997739],"type":"Point"}
}