{
  "type": "Feature",
  "properties": {
    "addr:full": "9221 Ravenna Rd Twinsburg OH 44087",
    "addr:housenumber": "9221",
    "addr:postcode": "44087",
    "addr:street": "Ravenna Rd",
    "iso:country": "US",
    "sg:address": "9221 Ravenna Rd",
    "sg:city": "Twinsburg",
    "sg:classifiers": [
      {
        "category": "Manufacturing",
        "subcategory": "Printing",
        "type": "Manufacturing \u0026 Wholesale Goods"
      }
    ],
    "sg:phone": "+1 330 405 3662",
    "sg:postcode": "44087",
    "sg:province": "OH",
    "wof:name": "Rm Graphics Inc",
    "wof:placetype": "venue"
  },
  "geometry": {"coordinates":[-81.424057,41.305855],"type":"Point"}
}
