{
  "type": "Feature",
  "properties": {
    "addr:full": "8466 Cliffview Cir Macedonia OH 44056",
    "addr:housenumber": "8466",
    "addr:postcode": "44056",
    "addr:street": "Cliffview Cir",
    "iso:country": "US",
    "sg:address": "8466 Cliffview Cir",
    "sg:city": "Macedonia",
    "sg:classifiers": [
      {
        "category": "Building \u0026 Trades",
        "subcategory": "Construction",
        "type": "Services"
      }
    ],
    "sg:phone": "+1 330 467 3014",
    "sg:postcode": "44056",
    "sg:province": "OH",
    "sg:tags": [
      "contractor"
    ],
    "wof:name": "Roof Tech Systems Inc",
    "wof:placetype": "venue"
  },
  "geometry": {"coordinates":[-81.496245,41.308082],"type":"Point"}
}
