{
  "type": "Feature",
  "properties": {
    "iso:country":"US",
    "sg:address":"13426 Heatherwood Dr",
    "sg:city":"Cleveland",
    "sg:classifiers":[
        {
            "category":"Building & Trades",
            "subcategory":"Plumbing",
            "type":"Services"
        }
    ],
    "sg:phone":"+1 216 661 4066",
    "sg:postcode":"44142",
    "sg:province":"OH",
    "sg:tags":[
        "contractor"
    ],
    "wof:name":"Jims Heating & AC",
    "wof:placetype":"venue"
},
  "geometry": {"coordinates":[-81.792986,41.398917],"type":"Point"}
}