{
  "type": "Feature",
  "properties": {
    "addr:full": "3138 Allendale Ave Youngstown OH 44511",
    "addr:housenumber": "3138",
    "addr:postcode": "44511",
    "addr:street": "Allendale Ave",
    "iso:country": "US",
    "sg:address": "3138 Allendale Ave",
    "sg:city": "Youngstown",
    "sg:classifiers": [
      {
        "category": "Place Of Worship",
        "subcategory": "Church",
        "type": "Public Place"
      }
    ],
    "sg:phone": "+1 330 793 0599",
    "sg:postcode": "44511",
    "sg:province": "OH",
    "sg:tags": [
      "ceremony",
      "chapel",
      "wedding"
    ],
    "wof:name": "Just Married Wedding Minister",
    "wof:placetype": "venue"
  },
  "geometry": {"coordinates":[-80.714225,41.068181],"type":"Point"}
}
