{
  "type": "Feature",
  "properties": {
    "iso:country":"US",
    "sg:address":"6726 Providence St",
    "sg:city":"Whitehouse",
    "sg:classifiers":[
        {
            "category":"Restaurant",
            "type":"Food & Drink"
        }
    ],
    "sg:phone":"+1 419 877 9533",
    "sg:postcode":"43571",
    "sg:province":"OH",
    "sg:tags":[
        "delicatessen"
    ],
    "wof:name":"Murph's Deli",
    "wof:placetype":"venue"
},
  "geometry": {"coordinates":[-83.803008,41.518033],"type":"Point"}
}