{
  "type": "Feature",
  "properties": {
    "addr:full": "1167 E Main St Ashland OH 44805",
    "addr:housenumber": "1167",
    "addr:postcode": "44805",
    "addr:street": "E Main St",
    "iso:country": "US",
    "sg:address": "1167 E Main St",
    "sg:city": "Ashland",
    "sg:classifiers": [
      {
        "category": "Recreation",
        "type": "Entertainment"
      }
    ],
    "sg:phone": "+1 419 289 6371",
    "sg:postcode": "44805",
    "sg:province": "OH",
    "sg:tags": [
      "amusement"
    ],
    "wof:name": "Ashland Police \u0026 Recreation",
    "wof:placetype": "venue"
  },
  "geometry": {"coordinates":[-82.294626,40.864931],"type":"Point"}
}
