{
  "type": "Feature",
  "properties": {
    "iso:country":"US",
    "sg:address":"1167 E Main St",
    "sg:city":"Ashland",
    "sg:classifiers":[
        {
            "category":"Recreation",
            "type":"Entertainment"
        }
    ],
    "sg:phone":"+1 419 289 6371",
    "sg:postcode":"44805",
    "sg:province":"OH",
    "sg:tags":[
        "amusement"
    ],
    "wof:name":"Ashland Police & Recreation",
    "wof:placetype":"venue"
},
  "geometry": {"coordinates":[-82.294626,40.864931],"type":"Point"}
}