{
  "type": "Feature",
  "properties": {
    "addr:full": "35 Grace Dr Powell OH 43065",
    "addr:housenumber": "35",
    "addr:postcode": "43065",
    "addr:street": "Grace Dr",
    "iso:country": "US",
    "sg:address": "35 Grace Dr",
    "sg:city": "Powell",
    "sg:classifiers": [
      {
        "category": "Retail",
        "subcategory": "Auto Repair",
        "type": "Services"
      }
    ],
    "sg:phone": "+1 614 846 2577",
    "sg:postcode": "43065",
    "sg:province": "OH",
    "sg:tags": [
      "body",
      "automobile",
      "painting"
    ],
    "wof:name": "H \u0026 H Corvette",
    "wof:placetype": "venue"
  },
  "geometry": {"coordinates":[-83.075012,40.16337],"type":"Point"}
}
