{
  "type": "Feature",
  "properties": {
    "addr:full":"2690 Highland Ave Cincinnati OH 45212",
    "addr:housenumber":"2690",
    "addr:postcode":"45212",
    "addr:street":"Highland Ave",
    "iso:country":"US",
    "sg:address":"2690 Highland Ave",
    "sg:city":"Cincinnati",
    "sg:classifiers":[
        {
            "category":"Professional",
            "subcategory":"Advertising",
            "type":"Services"
        }
    ],
    "sg:phone":"+1 513 631 5849",
    "sg:postcode":"45212",
    "sg:province":"OH",
    "sg:tags":[
        "distribution"
    ],
    "wof:name":"Rail & Truck Distribution",
    "wof:placetype":"venue"
},
  "geometry": {"coordinates":[-84.443832,39.166485],"type":"Point"}
}