{
  "type": "Feature",
  "properties": {
    "addr:full":"1672 Lora Lane Rd NW Canal Winchester OH 43110",
    "addr:housenumber":"1672",
    "addr:postcode":"43110",
    "addr:street":"Lora Lane Rd Nw",
    "iso:country":"US",
    "sg:address":"1672 Lora Lane Rd NW",
    "sg:city":"Canal Winchester",
    "sg:classifiers":[
        {
            "category":"Shopping",
            "subcategory":"Gifts & Souvenirs",
            "type":"Retail Goods"
        }
    ],
    "sg:phone":"+1 614 833 0605",
    "sg:postcode":"43110",
    "sg:province":"OH",
    "wof:name":"Harts Gifts",
    "wof:placetype":"venue"
},
  "geometry": {"coordinates":[-82.81493500000001,39.761268],"type":"Point"}
}