{
  "type": "Feature",
  "properties": {
    "iso:country":"US",
    "sg:address":"180 Cochran Rd",
    "sg:city":"Cuyahoga Falls",
    "sg:classifiers":[
        {
            "category":"Building & Trades",
            "subcategory":"Construction",
            "type":"Services"
        }
    ],
    "sg:phone":"+1 330 923 9588",
    "sg:postcode":"44223",
    "sg:province":"OH",
    "sg:tags":[
        "general",
        "contractor"
    ],
    "wof:name":"Design Construction",
    "wof:placetype":"venue"
},
  "geometry": {"coordinates":[-81.505832,41.168274],"type":"Point"}
}