{
  "type": "Feature",
  "properties": {
    "addr:full":"5430 Lauby Rd North Canton OH 44720",
    "addr:housenumber":"5430",
    "addr:postcode":"44720",
    "addr:street":"Lauby Rd",
    "iso:country":"US",
    "sg:address":"5430 Lauby Rd",
    "sg:city":"North Canton",
    "sg:classifiers":[
        {
            "category":"Airline",
            "type":"Transportation"
        }
    ],
    "sg:phone":"+1 330 490 2930",
    "sg:postcode":"44720",
    "sg:province":"OH",
    "sg:tags":[
        "company"
    ],
    "wof:name":"Jetstream International Arlns",
    "wof:placetype":"venue"
},
  "geometry": {"coordinates":[-81.430297,40.914376],"type":"Point"}
}