{
  "type": "Feature",
  "properties": {
    "addr:full": "1039 Hilbish Ave Akron OH 44312",
    "addr:housenumber": "1039",
    "addr:postcode": "44312",
    "addr:street": "Hilbish Ave",
    "iso:country": "US",
    "sg:address": "1039 Hilbish Ave",
    "sg:city": "Akron",
    "sg:classifiers": [
      {
        "category": "Building \u0026 Trades",
        "subcategory": "Construction",
        "type": "Services"
      }
    ],
    "sg:phone": "+1 330 798 8356",
    "sg:postcode": "44312",
    "sg:province": "OH",
    "sg:tags": [
      "paving",
      "asphalt",
      "contractor"
    ],
    "wof:name": "Budget Asphalt Paving \u0026 Seal",
    "wof:placetype": "venue"
  },
  "geometry": {"coordinates":[-81.453962,41.034143],"type":"Point"}
}
