{
  "type": "Feature",
  "properties": {
    "iso:country":"US",
    "sg:address":"3155 Co Rd 15",
    "sg:city":"Bryan",
    "sg:classifiers":[
        {
            "category":"Arts & Performance",
            "subcategory":"Theater",
            "type":"Entertainment"
        }
    ],
    "sg:phone":"+1 419 636 7988",
    "sg:postcode":"43506",
    "sg:province":"OH",
    "sg:tags":[
        "live",
        "music"
    ],
    "wof:name":"Midnight Express Mobile DJ",
    "wof:placetype":"venue"
},
  "geometry": {"coordinates":[-84.536223,41.456509],"type":"Point"}
}