{
  "type": "Feature",
  "properties": {
    "addr:full":"14118 Fairgate Blvd Newbury OH 44065",
    "addr:housenumber":"14118",
    "addr:postcode":"44065",
    "addr:street":"Fairgate Blvd",
    "iso:country":"US",
    "sg:address":"14118 Fairgate Blvd",
    "sg:city":"Newbury",
    "sg:classifiers":[
        {
            "category":"Manufacturing",
            "subcategory":"Tools & Machinery",
            "type":"Manufacturing & Wholesale Goods"
        }
    ],
    "sg:phone":"+1 440 564 9776",
    "sg:postcode":"44065",
    "sg:province":"OH",
    "sg:tags":[
        "power",
        "mfg"
    ],
    "wof:name":"Hawk Equipment",
    "wof:placetype":"venue"
},
  "geometry": {"coordinates":[-81.25089199999999,41.482384],"type":"Point"}
}