{
  "type": "Feature",
  "properties": {
    "iso:country":"US",
    "sg:address":"19901 N Dixie Hwy",
    "sg:city":"Bowling Green",
    "sg:classifiers":[
        {
            "category":"Home & Garden",
            "subcategory":"Furniture",
            "type":"Retail Goods"
        }
    ],
    "sg:phone":"+1 419 354 3507",
    "sg:postcode":"43402",
    "sg:province":"OH",
    "sg:tags":[
        "wooden"
    ],
    "wof:name":"Amish Oak Gallery & Home Ctr",
    "wof:placetype":"venue"
},
  "geometry": {"coordinates":[-83.651098,41.438231],"type":"Point"}
}