{
  "type": "Feature",
  "properties": {
    "addr:full": "8450 Depot Rd Lisbon OH 44432",
    "addr:housenumber": "8450",
    "addr:postcode": "44432",
    "addr:street": "Depot Rd",
    "iso:country": "US",
    "sg:address": "8450 Depot Rd",
    "sg:city": "Lisbon",
    "sg:classifiers": [
      {
        "category": "Professional",
        "subcategory": "Business Services",
        "type": "Services"
      }
    ],
    "sg:phone": "+1 330 424 5900",
    "sg:postcode": "44432",
    "sg:province": "OH",
    "sg:tags": [
      "paging",
      "answering"
    ],
    "wof:name": "Lisbon Veterinary Clinic",
    "wof:placetype": "venue"
  },
  "geometry": {"coordinates":[-80.858984,40.776591],"type":"Point"}
}
