{
  "type": "Feature",
  "properties": {
    "iso:country":"US",
    "sg:address":"8450 Depot Rd",
    "sg:city":"Lisbon",
    "sg:classifiers":[
        {
            "category":"Professional",
            "subcategory":"Business Services",
            "type":"Services"
        }
    ],
    "sg:phone":"+1 330 424 5900",
    "sg:postcode":"44432",
    "sg:province":"OH",
    "sg:tags":[
        "paging",
        "answering"
    ],
    "wof:name":"Lisbon Veterinary Clinic",
    "wof:placetype":"venue"
},
  "geometry": {"coordinates":[-80.85898400000001,40.776591],"type":"Point"}
}