{
  "type": "Feature",
  "properties": {
    "addr:full": "205 Greenridge Dr Bellefontaine OH 43311",
    "addr:housenumber": "205",
    "addr:postcode": "43311",
    "addr:street": "Greenridge Dr",
    "iso:country": "US",
    "sg:address": "205 Greenridge Dr",
    "sg:city": "Bellefontaine",
    "sg:classifiers": [
      {
        "category": "Real Estate",
        "subcategory": "Real Estate Agent",
        "type": "Services"
      }
    ],
    "sg:phone": "+1 937 593 2949",
    "sg:postcode": "43311",
    "sg:province": "OH",
    "wof:name": "Zimmerman/ H E R Realtor",
    "wof:placetype": "venue"
  },
  "geometry": {"coordinates":[-83.733212,40.357452],"type":"Point"}
}
