{
  "type": "Feature",
  "properties": {
    "iso:country":"US",
    "sg:address":"205 Greenridge Dr",
    "sg:city":"Bellefontaine",
    "sg:classifiers":[
        {
            "category":"Real Estate",
            "subcategory":"Real Estate Agent",
            "type":"Services"
        }
    ],
    "sg:phone":"+1 937 593 2949",
    "sg:postcode":"43311",
    "sg:province":"OH",
    "wof:name":"Zimmerman/ H E R Realtor",
    "wof:placetype":"venue"
},
  "geometry": {"coordinates":[-83.73321199999999,40.357452],"type":"Point"}
}