{
  "type": "Feature",
  "properties": {
    "addr:full": "1081 E Weber Rd Columbus OH 43211",
    "addr:housenumber": "1081",
    "addr:postcode": "43211",
    "addr:street": "E Weber Rd",
    "iso:country": "US",
    "sg:address": "1081 E Weber Rd",
    "sg:city": "Columbus",
    "sg:classifiers": [
      {
        "category": "Organizations",
        "subcategory": "Religious Organization",
        "type": "Services"
      }
    ],
    "sg:phone": "+1 614 267 6508",
    "sg:postcode": "43211",
    "sg:province": "OH",
    "sg:tags": [
      "church"
    ],
    "wof:name": "Spiritualist Church-Revelation",
    "wof:placetype": "venue"
  },
  "geometry": {"coordinates":[-82.983303,40.023493],"type":"Point"}
}
