{
  "type": "Feature",
  "properties": {
    "addr:full": "11082 London Rd Orient OH 43146",
    "addr:housenumber": "11082",
    "addr:postcode": "43146",
    "addr:street": "London Rd",
    "iso:country": "US",
    "sg:address": "11082 London Rd",
    "sg:city": "Orient",
    "sg:phone": "+1 614 877 9504",
    "sg:postcode": "43146",
    "sg:province": "OH",
    "sg:tags": [
      "farm",
      "corn",
      "soybean"
    ],
    "wof:name": "Jerrold Fields",
    "wof:placetype": "venue"
  },
  "geometry": {"coordinates":[-83.221299,39.779191],"type":"Point"}
}
