{
  "type": "Feature",
  "properties": {
    "addr:full":"815 N Mantua St Kent OH 44240",
    "addr:housenumber":"815",
    "addr:postcode":"44240",
    "addr:street":"N Mantua St",
    "iso:country":"US",
    "sg:address":"815 N Mantua St",
    "sg:city":"Kent",
    "sg:classifiers":[
        {
            "category":"Wholesale",
            "subcategory":"Non-durable Goods",
            "type":"Manufacturing & Wholesale Goods"
        }
    ],
    "sg:phone":"+1 330 673 9398",
    "sg:postcode":"44240",
    "sg:province":"OH",
    "wof:name":"Gassin Import Tuning",
    "wof:placetype":"venue"
},
  "geometry": {"coordinates":[-81.358574,41.160879],"type":"Point"}
}