{
  "type": "Feature",
  "properties": {
    "addr:full": "126 W 6th St East Liverpool OH 43920",
    "addr:housenumber": "126",
    "addr:postcode": "43920",
    "addr:street": "W 6Th St",
    "iso:country": "US",
    "sg:address": "126 W 6th St",
    "sg:city": "East Liverpool",
    "sg:classifiers": [
      {
        "category": "Government",
        "subcategory": "Office",
        "type": "Public Place"
      }
    ],
    "sg:phone": "+1 330 385 7302",
    "sg:postcode": "43920",
    "sg:province": "OH",
    "sg:tags": [
      "village"
    ],
    "wof:name": "East Liverpool Criminal Law",
    "wof:placetype": "venue"
  },
  "geometry": {"coordinates":[-80.580323,40.62039],"type":"Point"}
}
