{
  "type": "Feature",
  "properties": {
    "addr:full": "116 N Pearl St Granville OH 43023",
    "addr:housenumber": "116",
    "addr:postcode": "43023",
    "addr:street": "N Pearl St",
    "iso:country": "US",
    "sg:address": "116 N Pearl St",
    "sg:city": "Granville",
    "sg:classifiers": [
      {
        "category": "Personal",
        "subcategory": "Beauty Salon",
        "type": "Services"
      }
    ],
    "sg:phone": "+1 740 587 2988",
    "sg:postcode": "43023",
    "sg:province": "OH",
    "wof:name": "Newkirk Designs Studio",
    "wof:placetype": "venue"
  },
  "geometry": {"coordinates":[-82.516541,40.068796],"type":"Point"}
}
