{
  "type": "Feature",
  "properties": {
    "addr:full": "6135 Wilson Mills Rd Cleveland OH 44143",
    "addr:housenumber": "6135",
    "addr:postcode": "44143",
    "addr:street": "Wilson Mills Rd",
    "iso:country": "US",
    "sg:address": "6135 Wilson Mills Rd",
    "sg:city": "Cleveland",
    "sg:classifiers": [
      {
        "category": "Banks \u0026 Credit Unions",
        "subcategory": "Bank",
        "type": "Services"
      }
    ],
    "sg:phone": "+1 440 449 2900",
    "sg:postcode": "44143",
    "sg:province": "OH",
    "wof:name": "US Bank",
    "wof:placetype": "venue"
  },
  "geometry": {"coordinates":[-81.456022,41.539042],"type":"Point"}
}
