{
  "type": "Feature",
  "properties": {
    "iso:country":"US",
    "sg:address":"6135 Wilson Mills Rd",
    "sg:city":"Cleveland",
    "sg:classifiers":[
        {
            "category":"Banks & Credit Unions",
            "subcategory":"Bank",
            "type":"Services"
        }
    ],
    "sg:phone":"+1 440 449 2900",
    "sg:postcode":"44143",
    "sg:province":"OH",
    "wof:name":"US Bank",
    "wof:placetype":"venue"
},
  "geometry": {"coordinates":[-81.456022,41.539042],"type":"Point"}
}