{
  "type": "Feature",
  "properties": {
    "addr:full": "8382 S Pricetown Rd Berlin Center OH 44401",
    "addr:housenumber": "8382",
    "addr:postcode": "44401",
    "addr:street": "S Pricetown Rd",
    "iso:country": "US",
    "sg:address": "8382 S Pricetown Rd",
    "sg:city": "Berlin Center",
    "sg:classifiers": [
      {
        "category": "Wholesale",
        "subcategory": "Farm Supplies",
        "type": "Manufacturing \u0026 Wholesale Goods"
      }
    ],
    "sg:phone": "+1 330 547 9169",
    "sg:postcode": "44401",
    "sg:province": "OH",
    "sg:tags": [
      "livestock"
    ],
    "wof:name": "Mahonng Cnty Mrkt Lvestck Comm",
    "wof:placetype": "venue"
  },
  "geometry": {"coordinates":[-80.947473,40.99766],"type":"Point"}
}
