{
  "type": "Feature",
  "properties": {
    "addr:full":"541 S Hyatt St Tipp City OH 45371",
    "addr:housenumber":"541",
    "addr:postcode":"45371",
    "addr:street":"S Hyatt St",
    "iso:country":"US",
    "sg:address":"541 S Hyatt St",
    "sg:city":"Tipp City",
    "sg:classifiers":[
        {
            "category":"Building & Trades",
            "subcategory":"Plumbing",
            "type":"Services"
        }
    ],
    "sg:phone":"+1 937 667 8130",
    "sg:postcode":"45371",
    "sg:province":"OH",
    "sg:tags":[
        "contractor"
    ],
    "wof:name":"Morland Heating & Air",
    "wof:placetype":"venue"
},
  "geometry": {"coordinates":[-84.17579000000001,39.954475],"type":"Point"}
}