{
  "type": "Feature",
  "properties": {
    "addr:full": "208 S 5th St Upper Sandusky OH 43351",
    "addr:housenumber": "208",
    "addr:postcode": "43351",
    "addr:street": "S 5Th St",
    "iso:country": "US",
    "sg:address": "208 S 5th St",
    "sg:city": "Upper Sandusky",
    "sg:classifiers": [
      {
        "category": "Building \u0026 Trades",
        "subcategory": "Electrical",
        "type": "Services"
      }
    ],
    "sg:phone": "+1 419 294 5614",
    "sg:postcode": "43351",
    "sg:province": "OH",
    "sg:tags": [
      "electrical",
      "electric",
      "contractor"
    ],
    "wof:name": "Gottfried Electric Warehouse",
    "wof:placetype": "venue"
  },
  "geometry": {"coordinates":[-83.279864,40.825839],"type":"Point"}
}
