{
  "type": "Feature",
  "properties": {
    "addr:full": "988 Ohio Pike Cincinnati OH 45245",
    "addr:housenumber": "988",
    "addr:postcode": "45245",
    "addr:street": "Ohio Pike",
    "iso:country": "US",
    "sg:address": "988 Ohio Pike",
    "sg:city": "Cincinnati",
    "sg:classifiers": [
      {
        "category": "Insurance",
        "subcategory": "Insurance Agent",
        "type": "Services"
      }
    ],
    "sg:phone": "+1 513 943 7760",
    "sg:postcode": "45245",
    "sg:province": "OH",
    "wof:name": "Terri's Secretarial Svc",
    "wof:placetype": "venue"
  },
  "geometry": {"coordinates":[-84.265166,39.058847],"type":"Point"}
}
