{
  "type": "Feature",
  "properties": {
    "addr:full": "5116 Richmond Rd Cleveland OH 44146",
    "addr:housenumber": "5116",
    "addr:postcode": "44146",
    "addr:street": "Richmond Rd",
    "iso:country": "US",
    "sg:address": "5116 Richmond Rd",
    "sg:city": "Cleveland",
    "sg:classifiers": [
      {
        "category": "Retail",
        "subcategory": "Auto Repair",
        "type": "Services"
      }
    ],
    "sg:phone": "+1 440 248 0300",
    "sg:postcode": "44146",
    "sg:province": "OH",
    "sg:tags": [
      "repairing",
      "automobile"
    ],
    "wof:name": "Premier Automotive",
    "wof:placetype": "venue"
  },
  "geometry": {"coordinates":[-81.498076,41.423943],"type":"Point"}
}
