{
  "type": "Feature",
  "properties": {
    "iso:country":"US",
    "sg:address":"2600 State Rte 568",
    "sg:city":"Carey",
    "sg:classifiers":[
        {
            "category":"Manufacturing",
            "subcategory":"Tools & Machinery",
            "type":"Manufacturing & Wholesale Goods"
        }
    ],
    "sg:phone":"+1 419 425 3473",
    "sg:postcode":"43316",
    "sg:province":"OH",
    "sg:tags":[
        "fire",
        "equipment",
        "protection"
    ],
    "wof:name":"Vulcan Enterprises Inc",
    "wof:placetype":"venue"
},
  "geometry": {"coordinates":[-83.40140599999999,40.957945],"type":"Point"}
}