{
  "type": "Feature",
  "properties": {
    "addr:full": "2600 State Rte 568 Carey OH 43316",
    "addr:housenumber": "2600",
    "addr:postcode": "43316",
    "addr:street": "State Rte 568",
    "iso:country": "US",
    "sg:address": "2600 State Rte 568",
    "sg:city": "Carey",
    "sg:classifiers": [
      {
        "category": "Manufacturing",
        "subcategory": "Tools \u0026 Machinery",
        "type": "Manufacturing \u0026 Wholesale Goods"
      }
    ],
    "sg:phone": "+1 419 425 3473",
    "sg:postcode": "43316",
    "sg:province": "OH",
    "sg:tags": [
      "fire",
      "equipment",
      "protection"
    ],
    "wof:name": "Vulcan Enterprises Inc",
    "wof:placetype": "venue"
  },
  "geometry": {"coordinates":[-83.401406,40.957945],"type":"Point"}
}
