{
  "type": "Feature",
  "properties": {
    "iso:country":"US",
    "sg:address":"2007 W Sylvania Ave",
    "sg:city":"Toledo",
    "sg:classifiers":[
        {
            "category":"Professional",
            "type":"Services"
        }
    ],
    "sg:phone":"+1 419 475 2122",
    "sg:postcode":"43613",
    "sg:province":"OH",
    "sg:tags":[
        "establishment"
    ],
    "wof:name":"GOTSLLC",
    "wof:placetype":"venue"
},
  "geometry": {"coordinates":[-83.593403,41.692175],"type":"Point"}
}