{
  "type": "Feature",
  "properties": {
    "addr:full": "2000 Auburn Ave Cincinnati OH 45219",
    "addr:housenumber": "2000",
    "addr:postcode": "45219",
    "addr:street": "Auburn Ave",
    "iso:country": "US",
    "sg:address": "2000 Auburn Ave",
    "sg:city": "Cincinnati",
    "sg:classifiers": [
      {
        "category": "Food \u0026 Beverages",
        "subcategory": "Liquor \u0026 Beverages",
        "type": "Retail Goods"
      }
    ],
    "sg:phone": "+1 513 621 0113",
    "sg:postcode": "45219",
    "sg:province": "OH",
    "sg:tags": [
      "alcoholic"
    ],
    "wof:name": "Body Snatcher Inc",
    "wof:placetype": "venue"
  },
  "geometry": {"coordinates":[-84.508782,39.118486],"type":"Point"}
}
