{
  "type": "Feature",
  "properties": {
    "iso:country":"US",
    "sg:address":"5 Drummond",
    "sg:city":"Cincinnati",
    "sg:classifiers":[
        {
            "category":"Professional",
            "subcategory":"Business Services",
            "type":"Services"
        }
    ],
    "sg:phone":"+1 513 825 1873",
    "sg:postcode":"45218",
    "sg:province":"OH",
    "sg:tags":[
        "patent",
        "searcher"
    ],
    "wof:name":"William M Selenke",
    "wof:placetype":"venue"
},
  "geometry": {"coordinates":[-84.525296,39.267022],"type":"Point"}
}