{
  "type": "Feature",
  "properties": {
    "iso:country":"US",
    "sg:address":"4808 Turney Rd",
    "sg:city":"Cleveland",
    "sg:classifiers":[
        {
            "category":"Professional",
            "subcategory":"Employment Agencies",
            "type":"Services"
        }
    ],
    "sg:phone":"+1 216 429 0206",
    "sg:postcode":"44125",
    "sg:province":"OH",
    "sg:tags":[
        "help",
        "contractor"
    ],
    "wof:name":"Just In Temps Cleveland",
    "wof:placetype":"venue"
},
  "geometry": {"coordinates":[-81.61533900000001,41.429588],"type":"Point"}
}