{
  "type": "Feature",
  "properties": {
    "iso:country":"US",
    "sg:address":"8580 Ashcraft Rd",
    "sg:city":"Frazeysburg",
    "sg:classifiers":[
        {
            "category":"Building & Trades",
            "subcategory":"Construction",
            "type":"Services"
        }
    ],
    "sg:phone":"+1 740 828 3010",
    "sg:postcode":"43822",
    "sg:province":"OH",
    "sg:tags":[
        "water",
        "well",
        "drilling"
    ],
    "wof:name":"Hawk Water Well Service",
    "wof:placetype":"venue"
},
  "geometry": {"coordinates":[-82.140347,40.159185],"type":"Point"}
}