{
  "type": "Feature",
  "properties": {
    "addr:full": "8580 Ashcraft Rd Frazeysburg OH 43822",
    "addr:housenumber": "8580",
    "addr:postcode": "43822",
    "addr:street": "Ashcraft Rd",
    "iso:country": "US",
    "sg:address": "8580 Ashcraft Rd",
    "sg:city": "Frazeysburg",
    "sg:classifiers": [
      {
        "category": "Building \u0026 Trades",
        "subcategory": "Construction",
        "type": "Services"
      }
    ],
    "sg:phone": "+1 740 828 3010",
    "sg:postcode": "43822",
    "sg:province": "OH",
    "sg:tags": [
      "water",
      "well",
      "drilling"
    ],
    "wof:name": "Hawk Water Well Service",
    "wof:placetype": "venue"
  },
  "geometry": {"coordinates":[-82.140347,40.159185],"type":"Point"}
}
