{
  "type": "Feature",
  "properties": {
    "iso:country":"US",
    "sg:address":"1238 Lost Nation Rd",
    "sg:city":"Willoughby",
    "sg:classifiers":[
        {
            "category":"Food & Beverages",
            "subcategory":"Candy",
            "type":"Retail Goods"
        }
    ],
    "sg:phone":"+1 440 942 1016",
    "sg:postcode":"44094",
    "sg:province":"OH",
    "sg:tags":[
        "mfg",
        "chocolate"
    ],
    "wof:name":"Brandts Candies",
    "wof:placetype":"venue"
},
  "geometry": {"coordinates":[-81.39960600000001,41.69091],"type":"Point"}
}