{
  "type": "Feature",
  "properties": {
    "addr:full": "1238 Lost Nation Rd Willoughby OH 44094",
    "addr:housenumber": "1238",
    "addr:postcode": "44094",
    "addr:street": "Lost Nation Rd",
    "iso:country": "US",
    "sg:address": "1238 Lost Nation Rd",
    "sg:city": "Willoughby",
    "sg:classifiers": [
      {
        "category": "Food \u0026 Beverages",
        "subcategory": "Candy",
        "type": "Retail Goods"
      }
    ],
    "sg:phone": "+1 440 942 1016",
    "sg:postcode": "44094",
    "sg:province": "OH",
    "sg:tags": [
      "mfg",
      "chocolate"
    ],
    "wof:name": "Brandts Candies",
    "wof:placetype": "venue"
  },
  "geometry": {"coordinates":[-81.399606,41.69091],"type":"Point"}
}
