{
  "type": "Feature",
  "properties": {
    "addr:full": "9300 Detroit Ave Cleveland OH 44102",
    "addr:housenumber": "9300",
    "addr:postcode": "44102",
    "addr:street": "Detroit Ave",
    "iso:country": "US",
    "sg:address": "9300 Detroit Ave",
    "sg:city": "Cleveland",
    "sg:classifiers": [
      {
        "category": "Restaurant",
        "type": "Food \u0026 Drink"
      }
    ],
    "sg:phone": "+1 216 651 5588",
    "sg:postcode": "44102",
    "sg:province": "OH",
    "sg:tags": [
      "beverage"
    ],
    "wof:name": "Ed's Drive-In Beverage",
    "wof:placetype": "venue"
  },
  "geometry": {"coordinates":[-81.748528,41.480138],"type":"Point"}
}
