{
  "type": "Feature",
  "properties": {
    "iso:country":"US",
    "sg:address":"9300 Detroit Ave",
    "sg:city":"Cleveland",
    "sg:classifiers":[
        {
            "category":"Restaurant",
            "type":"Food & Drink"
        }
    ],
    "sg:phone":"+1 216 651 5588",
    "sg:postcode":"44102",
    "sg:province":"OH",
    "sg:tags":[
        "beverage"
    ],
    "wof:name":"Ed's Drive-In Beverage",
    "wof:placetype":"venue"
},
  "geometry": {"coordinates":[-81.74852799999999,41.480138],"type":"Point"}
}