{
  "type": "Feature",
  "properties": {
    "addr:full": "585 Sports St Fairborn OH 45324",
    "addr:housenumber": "585",
    "addr:postcode": "45324",
    "addr:street": "Sports St",
    "iso:country": "US",
    "sg:address": "585 Sports St",
    "sg:city": "Fairborn",
    "sg:classifiers": [
      {
        "category": "Retail",
        "subcategory": "Auto Repair",
        "type": "Services"
      }
    ],
    "sg:phone": "+1 937 878 7936",
    "sg:postcode": "45324",
    "sg:province": "OH",
    "sg:tags": [
      "repairing",
      "automobile"
    ],
    "wof:name": "Uptowne Automotive",
    "wof:placetype": "venue"
  },
  "geometry": {"coordinates":[-84.010275,39.821372],"type":"Point"}
}
