{
  "type": "Feature",
  "properties": {
    "addr:full":"777 W Smith Rd Medina OH 44256",
    "addr:housenumber":"777",
    "addr:postcode":"44256",
    "addr:street":"W Smith Rd",
    "iso:country":"US",
    "sg:address":"777 W Smith Rd",
    "sg:city":"Medina",
    "sg:classifiers":[
        {
            "category":"Professional",
            "subcategory":"Advertising",
            "type":"Services"
        }
    ],
    "sg:phone":"+1 330 723 3002",
    "sg:postcode":"44256",
    "sg:province":"OH",
    "sg:tags":[
        "distribution"
    ],
    "wof:name":"Medina BKD Distribution",
    "wof:placetype":"venue"
},
  "geometry": {"coordinates":[-81.886447,41.136225],"type":"Point"}
}