{
  "type": "Feature",
  "properties": {
    "addr:full": "941 Bellefontaine Ave Lima OH 45804",
    "addr:housenumber": "941",
    "addr:postcode": "45804",
    "addr:street": "Bellefontaine Ave",
    "iso:country": "US",
    "sg:address": "941 Bellefontaine Ave",
    "sg:city": "Lima",
    "sg:classifiers": [
      {
        "category": "Retail",
        "subcategory": "Laundry \u0026 Dry Cleaning",
        "type": "Services"
      }
    ],
    "sg:phone": "+1 419 223 6951",
    "sg:postcode": "45804",
    "sg:province": "OH",
    "sg:tags": [
      "cleaners"
    ],
    "wof:name": "Time Cleaning Co",
    "wof:placetype": "venue"
  },
  "geometry": {"coordinates":[-84.090682,40.737684],"type":"Point"}
}
