{
  "type": "Feature",
  "properties": {
    "addr:full": "458 Blossom Ln Cincinnati OH 45244",
    "addr:housenumber": "458",
    "addr:postcode": "45244",
    "addr:street": "Blossom Ln",
    "iso:country": "US",
    "sg:address": "458 Blossom Ln",
    "sg:city": "Cincinnati",
    "sg:classifiers": [
      {
        "category": "Wholesale",
        "subcategory": "Machinery \u0026 Supplies",
        "type": "Manufacturing \u0026 Wholesale Goods"
      }
    ],
    "sg:phone": "+1 513 528 7158",
    "sg:postcode": "45244",
    "sg:province": "OH",
    "sg:tags": [
      "equipment",
      "industrial"
    ],
    "wof:name": "North Coast Instruments",
    "wof:placetype": "venue"
  },
  "geometry": {"coordinates":[-84.301147,39.121968],"type":"Point"}
}
