{
  "type": "Feature",
  "properties": {
    "iso:country":"US",
    "sg:address":"458 Blossom Ln",
    "sg:city":"Cincinnati",
    "sg:classifiers":[
        {
            "category":"Wholesale",
            "subcategory":"Machinery & Supplies",
            "type":"Manufacturing & Wholesale Goods"
        }
    ],
    "sg:phone":"+1 513 528 7158",
    "sg:postcode":"45244",
    "sg:province":"OH",
    "sg:tags":[
        "equipment",
        "industrial"
    ],
    "wof:name":"North Coast Instruments",
    "wof:placetype":"venue"
},
  "geometry": {"coordinates":[-84.301147,39.121968],"type":"Point"}
}