{
  "type": "Feature",
  "properties": {
    "addr:full":"248 Raff Rd NW Canton OH 44708",
    "addr:housenumber":"248",
    "addr:postcode":"44708",
    "addr:street":"Raff Rd Nw",
    "iso:country":"US",
    "sg:address":"248 Raff Rd NW",
    "sg:city":"Canton",
    "sg:classifiers":[
        {
            "category":"Autos & Motor Vehicles",
            "subcategory":"Auto Supplies",
            "type":"Retail Goods"
        }
    ],
    "sg:phone":"+1 330 455 4340",
    "sg:postcode":"44708",
    "sg:province":"OH",
    "wof:name":"International Coordinators",
    "wof:placetype":"venue"
},
  "geometry": {"coordinates":[-81.41668199999999,40.800298],"type":"Point"}
}