{
  "type": "Feature",
  "properties": {
    "addr:full": "1615 Brook Lynn Dr Dayton OH 45432",
    "addr:housenumber": "1615",
    "addr:postcode": "45432",
    "addr:street": "Brook Lynn Dr",
    "iso:country": "US",
    "sg:address": "1615 Brook Lynn Dr",
    "sg:city": "Dayton",
    "sg:classifiers": [
      {
        "category": "Professional",
        "subcategory": "Advertising",
        "type": "Services"
      },
      {
        "category": "Wholesale",
        "subcategory": "Electrical",
        "type": "Manufacturing \u0026 Wholesale Goods"
      }
    ],
    "sg:phone": "+1 937 431 5430",
    "sg:postcode": "45432",
    "sg:province": "OH",
    "sg:tags": [
      "distribution",
      "wire",
      "cable"
    ],
    "wof:name": "A E Petsche Company Inc",
    "wof:placetype": "venue"
  },
  "geometry": {"coordinates":[-84.086911,39.738834],"type":"Point"}
}
