{
  "type": "Feature",
  "properties": {
    "iso:country":"US",
    "sg:address":"1045 Dalton Ave",
    "sg:city":"Cincinnati",
    "sg:classifiers":[
        {
            "category":"Manufacturing",
            "subcategory":"Printing",
            "type":"Manufacturing & Wholesale Goods"
        }
    ],
    "sg:phone":"+1 513 241 7708",
    "sg:postcode":"45203",
    "sg:province":"OH",
    "sg:tags":[
        "commercial",
        "lithographic"
    ],
    "wof:name":"Starr Printing Services Inc",
    "wof:placetype":"venue"
},
  "geometry": {"coordinates":[-84.536554,39.108724],"type":"Point"}
}