{
  "type": "Feature",
  "properties": {
    "addr:full":"2230 Brymwood Rd Lexington OH 44904",
    "addr:housenumber":"2230",
    "addr:postcode":"44904",
    "addr:street":"Brymwood Rd",
    "iso:country":"US",
    "sg:address":"2230 Brymwood Rd",
    "sg:city":"Lexington",
    "sg:classifiers":[
        {
            "category":"Wholesale",
            "subcategory":"Construction Materials",
            "type":"Manufacturing & Wholesale Goods"
        }
    ],
    "sg:phone":"+1 419 543 7399",
    "sg:postcode":"44904",
    "sg:province":"OH",
    "sg:tags":[
        "concrete",
        "form"
    ],
    "wof:name":"HTH Poured Walls",
    "wof:placetype":"venue"
},
  "geometry": {"coordinates":[-82.56738199999999,40.698429],"type":"Point"}
}