{
  "type": "Feature",
  "properties": {
    "iso:country":"US",
    "sg:address":"108 W Main St",
    "sg:city":"Van Wert",
    "sg:classifiers":[
        {
            "category":"Shopping",
            "subcategory":"Used Merchandise",
            "type":"Retail Goods"
        }
    ],
    "sg:phone":"+1 419 238 3362",
    "sg:postcode":"45891",
    "sg:province":"OH",
    "sg:tags":[
        "repair"
    ],
    "wof:name":"Years Ago Antique Mall",
    "wof:placetype":"venue"
},
  "geometry": {"coordinates":[-84.584164,40.869544],"type":"Point"}
}