{
  "type": "Feature",
  "properties": {
    "iso:country":"US",
    "sg:address":"3666 Paxton Ave",
    "sg:city":"Cincinnati",
    "sg:classifiers":[
        {
            "category":"Shopping",
            "type":"Retail Goods"
        }
    ],
    "sg:phone":"+1 513 871 4646",
    "sg:postcode":"45208",
    "sg:province":"OH",
    "sg:tags":[
        "art",
        "gallery",
        "dealer"
    ],
    "wof:name":"Ehoodin Williams Inc",
    "wof:placetype":"venue"
},
  "geometry": {"coordinates":[-84.433381,39.144056],"type":"Point"}
}