{
  "type": "Feature",
  "properties": {
    "addr:full":"6475 Monroe St Sylvania OH 43560",
    "addr:housenumber":"6475",
    "addr:postcode":"43560",
    "addr:street":"Monroe St",
    "iso:country":"US",
    "sg:address":"6475 Monroe St",
    "sg:city":"Sylvania",
    "sg:classifiers":[
        {
            "category":"Personal",
            "subcategory":"Beauty Salon",
            "type":"Services"
        }
    ],
    "sg:phone":"+1 419 882 2030",
    "sg:postcode":"43560",
    "sg:province":"OH",
    "wof:name":"Artco Hair Salon",
    "wof:placetype":"venue"
},
  "geometry": {"coordinates":[-83.702924,41.715529],"type":"Point"}
}