{
  "type": "Feature",
  "properties": {
    "addr:full":"2138 Wyandotte Ave Lakewood OH 44107",
    "addr:housenumber":"2138",
    "addr:postcode":"44107",
    "addr:street":"Wyandotte Ave",
    "iso:country":"US",
    "sg:address":"2138 Wyandotte Ave",
    "sg:city":"Lakewood",
    "sg:classifiers":[
        {
            "category":"Professional",
            "type":"Services"
        }
    ],
    "sg:phone":"+1 216 521 0240",
    "sg:postcode":"44107",
    "sg:province":"OH",
    "wof:name":"Springhead Inc",
    "wof:placetype":"venue"
},
  "geometry": {"coordinates":[-81.787592,41.471319],"type":"Point"}
}