{
  "type": "Feature",
  "properties": {
    "addr:full": "13505 Kettlersville Rd Wapakoneta OH 45895",
    "addr:housenumber": "13505",
    "addr:postcode": "45895",
    "addr:street": "Kettlersville Rd",
    "iso:country": "US",
    "sg:address": "13505 Kettlersville Rd",
    "sg:city": "Wapakoneta",
    "sg:phone": "+1 419 738 6924",
    "sg:postcode": "45895",
    "sg:province": "OH",
    "sg:tags": [
      "farm",
      "grain",
      "cash"
    ],
    "wof:name": "Evelyn Zwiebel Farm",
    "wof:placetype": "venue"
  },
  "geometry": {"coordinates":[-84.259908,40.549861],"type":"Point"}
}
