{
  "type": "Feature",
  "properties": {
    "addr:full":"359 State Ave NW Massillon OH 44647",
    "addr:housenumber":"359",
    "addr:postcode":"44647",
    "addr:street":"State Ave Nw",
    "iso:country":"US",
    "sg:address":"359 State Ave NW",
    "sg:city":"Massillon",
    "sg:classifiers":[
        {
            "category":"Manufacturing",
            "subcategory":"Retail Goods",
            "type":"Manufacturing & Wholesale Goods"
        }
    ],
    "sg:phone":"+1 330 832 5205",
    "sg:postcode":"44647",
    "sg:province":"OH",
    "sg:tags":[
        "assembly",
        "fabricating"
    ],
    "wof:name":"Alpha Omega Assembly & Pkgng",
    "wof:placetype":"venue"
},
  "geometry": {"coordinates":[-81.53067799999999,40.804537],"type":"Point"}
}