{
  "type": "Feature",
  "properties": {
    "iso:country":"US",
    "sg:address":"6201 Red Bank Rd",
    "sg:city":"Cincinnati",
    "sg:classifiers":[
        {
            "category":"Organizations",
            "subcategory":"Religious Organization",
            "type":"Services"
        }
    ],
    "sg:phone":"+1 513 793 5642",
    "sg:postcode":"45213",
    "sg:province":"OH",
    "sg:tags":[
        "church"
    ],
    "wof:name":"First Baptist Church Inc",
    "wof:placetype":"venue"
},
  "geometry": {"coordinates":[-84.407935,39.184749],"type":"Point"}
}