{
  "type": "Feature",
  "properties": {
    "addr:full": "399 Kathleen Dr Jefferson OH 44047",
    "addr:housenumber": "399",
    "addr:postcode": "44047",
    "addr:street": "Kathleen Dr",
    "iso:country": "US",
    "sg:address": "399 Kathleen Dr",
    "sg:city": "Jefferson",
    "sg:classifiers": [
      {
        "category": "Building \u0026 Trades",
        "subcategory": "Construction",
        "type": "Services"
      }
    ],
    "sg:phone": "+1 440 576 1188",
    "sg:postcode": "44047",
    "sg:province": "OH",
    "sg:tags": [
      "demolition",
      "contractor"
    ],
    "wof:name": "T \u0026 S Material Processing LLC",
    "wof:placetype": "venue"
  },
  "geometry": {"coordinates":[-80.785834,41.735842],"type":"Point"}
}
