{
  "type": "Feature",
  "properties": {
    "iso:country":"US",
    "sg:address":"531 Wooster Rd W",
    "sg:city":"Barberton",
    "sg:classifiers":[
        {
            "category":"Government",
            "subcategory":"Post Office",
            "type":"Public Place"
        }
    ],
    "sg:phone":"+1 330 848 2838",
    "sg:postcode":"44203",
    "sg:province":"OH",
    "sg:tags":[
        "postal",
        "us"
    ],
    "wof:name":"Barberton Post Office",
    "wof:placetype":"venue"
},
  "geometry": {"coordinates":[-81.609559,41.012096],"type":"Point"}
}