{
  "type": "Feature",
  "properties": {
    "addr:full": "8213 Simons Rd Williamsfield OH 44093",
    "addr:housenumber": "8213",
    "addr:postcode": "44093",
    "addr:street": "Simons Rd",
    "iso:country": "US",
    "sg:address": "8213 Simons Rd",
    "sg:city": "Williamsfield",
    "sg:classifiers": [
      {
        "category": "Building \u0026 Trades",
        "subcategory": "Construction",
        "type": "Services"
      }
    ],
    "sg:phone": "+1 440 293 8827",
    "sg:postcode": "44093",
    "sg:province": "OH",
    "sg:tags": [
      "hanging",
      "contractor"
    ],
    "wof:name": "Weese Painting",
    "wof:placetype": "venue"
  },
  "geometry": {"coordinates":[-80.532366,41.526142],"type":"Point"}
}
