{
  "type": "Feature",
  "properties": {
    "addr:full":"118 E Spring St Eaton OH 45320",
    "addr:housenumber":"118",
    "addr:postcode":"45320",
    "addr:street":"E Spring St",
    "iso:country":"US",
    "sg:address":"118 E Spring St",
    "sg:city":"Eaton",
    "sg:classifiers":[
        {
            "category":"Retail",
            "subcategory":"Auto Repair",
            "type":"Services"
        }
    ],
    "sg:phone":"+1 937 456 2882",
    "sg:postcode":"45320",
    "sg:province":"OH",
    "sg:tags":[
        "repairing",
        "automobile"
    ],
    "wof:name":"Lonnie's Garage & Towing",
    "wof:placetype":"venue"
},
  "geometry": {"coordinates":[-84.63614200000001,39.753536],"type":"Point"}
}