{
  "type": "Feature",
  "properties": {
    "iso:country":"US",
    "sg:address":"5963 Glenway Ave",
    "sg:city":"Cincinnati",
    "sg:classifiers":[
        {
            "category":"Insurance",
            "subcategory":"Insurance Agent",
            "type":"Services"
        }
    ],
    "sg:phone":"+1 513 451 2020",
    "sg:postcode":"45238",
    "sg:province":"OH",
    "wof:name":"Nationwide Mutual Insurance",
    "wof:placetype":"venue"
},
  "geometry": {"coordinates":[-84.61817499999999,39.141301],"type":"Point"}
}