{
  "type": "Feature",
  "properties": {
    "addr:full": "2348 Johnston Rd Columbus OH 43220",
    "addr:housenumber": "2348",
    "addr:postcode": "43220",
    "addr:street": "Johnston Rd",
    "iso:country": "US",
    "sg:address": "2348 Johnston Rd",
    "sg:city": "Columbus",
    "sg:classifiers": [
      {
        "category": "Real Estate",
        "subcategory": "Real Estate Agent",
        "type": "Services"
      }
    ],
    "sg:phone": "+1 614 451 8787",
    "sg:postcode": "43220",
    "sg:province": "OH",
    "sg:tags": [
      "inspection"
    ],
    "wof:name": "Dannan Home Inspections",
    "wof:placetype": "venue"
  },
  "geometry": {"coordinates":[-83.080846,40.035137],"type":"Point"}
}
