{
  "type": "Feature",
  "properties": {
    "addr:full":"2294 N Moraine Blvd Dayton OH 45439",
    "addr:housenumber":"2294",
    "addr:postcode":"45439",
    "addr:street":"N Moraine Blvd",
    "iso:country":"US",
    "sg:address":"2294 N Moraine Blvd",
    "sg:city":"Dayton",
    "sg:classifiers":[
        {
            "category":"Wholesale",
            "subcategory":"Machinery & Supplies",
            "type":"Manufacturing & Wholesale Goods"
        },
        {
            "category":"Autos & Motor Vehicles",
            "subcategory":"Auto Supplies",
            "type":"Retail Goods"
        }
    ],
    "sg:phone":"+1 937 293 4611",
    "sg:postcode":"45439",
    "sg:province":"OH",
    "sg:tags":[
        "gas",
        "contract",
        "air",
        "filter",
        "distributor",
        "preventative"
    ],
    "wof:name":"Dayton Reliable Air-Filter Svc",
    "wof:placetype":"venue"
},
  "geometry": {"coordinates":[-84.21772799999999,39.722351],"type":"Point"}
}