{
  "type": "Feature",
  "properties": {
    "addr:full": "3148 N River Rd Stow OH 44224",
    "addr:housenumber": "3148",
    "addr:postcode": "44224",
    "addr:street": "N River Rd",
    "iso:country": "US",
    "sg:address": "3148 N River Rd",
    "sg:city": "Stow",
    "sg:classifiers": [
      {
        "category": "Building \u0026 Trades",
        "subcategory": "Construction",
        "type": "Services"
      }
    ],
    "sg:phone": "+1 330 677 1188",
    "sg:postcode": "44224",
    "sg:province": "OH",
    "sg:tags": [
      "painting",
      "contractor"
    ],
    "wof:name": "John A Pinter",
    "wof:placetype": "venue"
  },
  "geometry": {"coordinates":[-81.396813,41.145635],"type":"Point"}
}
