{
  "type": "Feature",
  "properties": {
    "iso:country":"US",
    "sg:address":"3148 N River Rd",
    "sg:city":"Stow",
    "sg:classifiers":[
        {
            "category":"Building & Trades",
            "subcategory":"Construction",
            "type":"Services"
        }
    ],
    "sg:phone":"+1 330 677 1188",
    "sg:postcode":"44224",
    "sg:province":"OH",
    "sg:tags":[
        "painting",
        "contractor"
    ],
    "wof:name":"John A Pinter",
    "wof:placetype":"venue"
},
  "geometry": {"coordinates":[-81.39681299999999,41.145635],"type":"Point"}
}