{
  "type": "Feature",
  "properties": {
    "addr:full":"5085 Timber Edge Dr Richfield OH 44286",
    "addr:housenumber":"5085",
    "addr:postcode":"44286",
    "addr:street":"Timber Edge Dr",
    "iso:country":"US",
    "sg:address":"5085 Timber Edge Dr",
    "sg:city":"Richfield",
    "sg:classifiers":[
        {
            "category":"Building & Trades",
            "subcategory":"Construction",
            "type":"Services"
        }
    ],
    "sg:phone":"+1 330 659 6826",
    "sg:postcode":"44286",
    "sg:province":"OH",
    "sg:tags":[
        "house"
    ],
    "wof:name":"Cambridge Restoration Inc",
    "wof:placetype":"venue"
},
  "geometry": {"coordinates":[-81.649536,41.273821],"type":"Point"}
}