{
  "type": "Feature",
  "properties": {
    "addr:full":"395 Baird St Akron OH 44311",
    "addr:housenumber":"395",
    "addr:postcode":"44311",
    "addr:street":"Baird St",
    "iso:country":"US",
    "sg:address":"395 Baird St",
    "sg:city":"Akron",
    "sg:classifiers":[
        {
            "category":"Freight",
            "type":"Transportation"
        }
    ],
    "sg:phone":"+1 330 374 0850",
    "sg:postcode":"44311",
    "sg:province":"OH",
    "sg:tags":[
        "consultant"
    ],
    "wof:name":"Chem Freight",
    "wof:placetype":"venue"
},
  "geometry": {"coordinates":[-81.51635400000001,41.058035],"type":"Point"}
}