{
  "type": "Feature",
  "properties": {
    "iso:country":"US",
    "sg:address":"1393 Harrison Ave",
    "sg:city":"Cincinnati",
    "sg:classifiers":[
        {
            "category":"Building & Trades",
            "subcategory":"Construction",
            "type":"Services"
        }
    ],
    "sg:phone":"+1 513 921 3720",
    "sg:postcode":"45214",
    "sg:province":"OH",
    "sg:tags":[
        "repairing",
        "remodeling",
        "contractor"
    ],
    "wof:name":"Sensible Lead Renovation Inc",
    "wof:placetype":"venue"
},
  "geometry": {"coordinates":[-84.54424899999999,39.123173],"type":"Point"}
}