{
  "type": "Feature",
  "properties": {
    "addr:full": "1393 Harrison Ave Cincinnati OH 45214",
    "addr:housenumber": "1393",
    "addr:postcode": "45214",
    "addr:street": "Harrison Ave",
    "iso:country": "US",
    "sg:address": "1393 Harrison Ave",
    "sg:city": "Cincinnati",
    "sg:classifiers": [
      {
        "category": "Building \u0026 Trades",
        "subcategory": "Construction",
        "type": "Services"
      }
    ],
    "sg:phone": "+1 513 921 3720",
    "sg:postcode": "45214",
    "sg:province": "OH",
    "sg:tags": [
      "repairing",
      "remodeling",
      "contractor"
    ],
    "wof:name": "Sensible Lead Renovation Inc",
    "wof:placetype": "venue"
  },
  "geometry": {"coordinates":[-84.544249,39.123173],"type":"Point"}
}
