{
  "type": "Feature",
  "properties": {
    "addr:full": "429 N Main St New Carlisle OH 45344",
    "addr:housenumber": "429",
    "addr:postcode": "45344",
    "addr:street": "N Main St",
    "iso:country": "US",
    "sg:address": "429 N Main St",
    "sg:city": "New Carlisle",
    "sg:classifiers": [
      {
        "category": "Health Services",
        "subcategory": "Doctor",
        "type": "Services"
      }
    ],
    "sg:phone": "+1 937 845 2335",
    "sg:postcode": "45344",
    "sg:province": "OH",
    "sg:tags": [
      "clinic"
    ],
    "wof:name": "WIC Satellite Office",
    "wof:placetype": "venue"
  },
  "geometry": {"coordinates":[-84.024521,39.94347],"type":"Point"}
}
