{
  "type": "Feature",
  "properties": {
    "addr:full": "48 W Main St Enon OH 45323",
    "addr:housenumber": "48",
    "addr:postcode": "45323",
    "addr:street": "W Main St",
    "iso:country": "US",
    "sg:address": "48 W Main St",
    "sg:city": "Enon",
    "sg:classifiers": [
      {
        "category": "Banks \u0026 Credit Unions",
        "subcategory": "Bank",
        "type": "Services"
      }
    ],
    "sg:phone": "+1 937 864 0300",
    "sg:postcode": "45323",
    "sg:province": "OH",
    "sg:tags": [
      "mortgage"
    ],
    "wof:name": "Amer Mortgage Service Co",
    "wof:placetype": "venue"
  },
  "geometry": {"coordinates":[-83.937776,39.878089],"type":"Point"}
}
