{
  "type": "Feature",
  "properties": {
    "iso:country":"US",
    "sg:address":"48 W Main St",
    "sg:city":"Enon",
    "sg:classifiers":[
        {
            "category":"Banks & Credit Unions",
            "subcategory":"Bank",
            "type":"Services"
        }
    ],
    "sg:phone":"+1 937 864 0300",
    "sg:postcode":"45323",
    "sg:province":"OH",
    "sg:tags":[
        "mortgage"
    ],
    "wof:name":"Amer Mortgage Service Co",
    "wof:placetype":"venue"
},
  "geometry": {"coordinates":[-83.937776,39.878089],"type":"Point"}
}