{
  "type": "Feature",
  "properties": {
    "iso:country":"US",
    "sg:address":"1851 Hubbard Rd",
    "sg:city":"Madison",
    "sg:classifiers":[
        {
            "category":"Real Estate",
            "subcategory":"Real Estate Operator",
            "type":"Services"
        }
    ],
    "sg:phone":"+1 440 428 1958",
    "sg:postcode":"44057",
    "sg:province":"OH",
    "sg:tags":[
        "building",
        "apartment"
    ],
    "wof:name":"Harsax",
    "wof:placetype":"venue"
},
  "geometry": {"coordinates":[-81.04848800000001,41.82361],"type":"Point"}
}