{
  "type": "Feature",
  "properties": {
    "addr:full":"1074 Scott St Napoleon OH 43545",
    "addr:housenumber":"1074",
    "addr:postcode":"43545",
    "addr:street":"Scott St",
    "iso:country":"US",
    "sg:address":"1074 Scott St",
    "sg:city":"Napoleon",
    "sg:classifiers":[
        {
            "category":"Retail",
            "subcategory":"Car Wash",
            "type":"Services"
        }
    ],
    "sg:phone":"+1 419 592 9213",
    "sg:postcode":"43545",
    "sg:province":"OH",
    "sg:tags":[
        "polishing",
        "washing"
    ],
    "wof:name":"Super Wash",
    "wof:placetype":"venue"
},
  "geometry": {"coordinates":[-84.131066,41.395935],"type":"Point"}
}