{
  "type": "Feature",
  "properties": {
    "addr:full": "4474 Indian Ripple Rd Dayton OH 45430",
    "addr:housenumber": "4474",
    "addr:postcode": "45430",
    "addr:street": "Indian Ripple Rd",
    "iso:country": "US",
    "sg:address": "4474 Indian Ripple Rd",
    "sg:city": "Dayton",
    "sg:classifiers": [
      {
        "category": "Shopping",
        "subcategory": "Crafts \u0026 Fabrics",
        "type": "Retail Goods"
      }
    ],
    "sg:phone": "+1 937 429 5895",
    "sg:postcode": "45430",
    "sg:province": "OH",
    "sg:tags": [
      "shop",
      "store"
    ],
    "sg:website": "www.hancockfabrics.com",
    "wof:name": "Hancock Fabrics",
    "wof:placetype": "venue"
  },
  "geometry": {"coordinates":[-84.103512,39.696512],"type":"Point"}
}
