{
  "type": "Feature",
  "properties": {
    "addr:full": "480 Glessner Ave Mansfield OH 44903",
    "addr:housenumber": "480",
    "addr:postcode": "44903",
    "addr:street": "Glessner Ave",
    "iso:country": "US",
    "sg:address": "480 Glessner Ave",
    "sg:city": "Mansfield",
    "sg:classifiers": [
      {
        "category": "Health Services",
        "subcategory": "Doctor",
        "type": "Services"
      }
    ],
    "sg:phone": "+1 419 522 3372",
    "sg:postcode": "44903",
    "sg:province": "OH",
    "sg:tags": [
      "physician",
      "surgeon",
      "medical"
    ],
    "wof:name": "Medical Arts Internists Inc",
    "wof:placetype": "venue"
  },
  "geometry": {"coordinates":[-82.533703,40.75338],"type":"Point"}
}
