{
  "type": "Feature",
  "properties": {
    "addr:full": "125 E Northgate Pkwy Toledo OH 43612",
    "addr:housenumber": "125",
    "addr:postcode": "43612",
    "addr:street": "E Northgate Pkwy",
    "iso:country": "US",
    "sg:address": "125 E Northgate Pkwy",
    "sg:city": "Toledo",
    "sg:classifiers": [
      {
        "category": "Freight",
        "type": "Transportation"
      }
    ],
    "sg:phone": "+1 419 478 4413",
    "sg:postcode": "43612",
    "sg:province": "OH",
    "sg:tags": [
      "operator",
      "trucking"
    ],
    "wof:name": "B Way Trucking",
    "wof:placetype": "venue"
  },
  "geometry": {"coordinates":[-83.545637,41.714886],"type":"Point"}
}
