{
  "type": "Feature",
  "properties": {
    "addr:full":"29 Illinois Ave S Mansfield OH 44905",
    "addr:housenumber":"29",
    "addr:postcode":"44905",
    "addr:street":"Illinois Ave S",
    "iso:country":"US",
    "sg:address":"29 Illinois Ave S",
    "sg:city":"Mansfield",
    "sg:classifiers":[
        {
            "category":"Building & Trades",
            "subcategory":"Plumbing",
            "type":"Services"
        },
        {
            "category":"Building & Trades",
            "subcategory":"Construction",
            "type":"Services"
        },
        {
            "category":"Building & Trades",
            "subcategory":"Electrical",
            "type":"Services"
        }
    ],
    "sg:phone":"+1 419 756 7585",
    "sg:postcode":"44905",
    "sg:province":"OH",
    "sg:tags":[
        "plumber",
        "industrial",
        "electrician",
        "electric",
        "system",
        "contractor",
        "air conditioning",
        "contractors-commercial"
    ],
    "sg:website":"http://www.ashlandcomfortcontrol.com",
    "wof:name":"Christensen Plumbing, Heating & Electric, Inc",
    "wof:placetype":"venue"
},
  "geometry": {"coordinates":[-82.484228,40.757725],"type":"Point"}
}