{
  "type": "Feature",
  "properties": {
    "addr:full": "6224 Ross Rd Fairfield OH 45014",
    "addr:housenumber": "6224",
    "addr:postcode": "45014",
    "addr:street": "Ross Rd",
    "iso:country": "US",
    "sg:address": "6224 Ross Rd",
    "sg:city": "Fairfield",
    "sg:classifiers": [
      {
        "category": "Local Transit",
        "type": "Transportation"
      }
    ],
    "sg:phone": "+1 513 942 5282",
    "sg:postcode": "45014",
    "sg:province": "OH",
    "sg:tags": [
      "passenger",
      "metal",
      "machinery",
      "mfg"
    ],
    "wof:name": "Professional Touch Limousine",
    "wof:placetype": "venue"
  },
  "geometry": {"coordinates":[-84.504476,39.3104],"type":"Point"}
}
