{
  "type": "Feature",
  "properties": {
    "addr:full":"17 E Kossuth St Columbus OH 43206",
    "addr:housenumber":"17",
    "addr:postcode":"43206",
    "addr:street":"E Kossuth St",
    "iso:country":"US",
    "sg:address":"17 E Kossuth St",
    "sg:city":"Columbus",
    "sg:classifiers":[
        {
            "category":"Banks & Credit Unions",
            "subcategory":"Investment Brokerage",
            "type":"Services"
        }
    ],
    "sg:phone":"+1 614 449 9025",
    "sg:postcode":"43206",
    "sg:province":"OH",
    "sg:tags":[
        "security"
    ],
    "wof:name":"Erik Thompson",
    "wof:placetype":"venue"
},
  "geometry": {"coordinates":[-82.996948,39.945433],"type":"Point"}
}