{
  "type": "Feature",
  "properties": {
    "addr:full":"5237 Autumnwood Dr Cincinnati OH 45242",
    "addr:housenumber":"5237",
    "addr:postcode":"45242",
    "addr:street":"Autumnwood Dr",
    "iso:country":"US",
    "sg:address":"5237 Autumnwood Dr",
    "sg:city":"Cincinnati",
    "sg:classifiers":[
        {
            "category":"Education",
            "subcategory":"Special Training",
            "type":"Public Place"
        }
    ],
    "sg:phone":"+1 513 791 4551",
    "sg:postcode":"45242",
    "sg:province":"OH",
    "sg:tags":[
        "tutoring"
    ],
    "wof:name":"Success Tutorial Assoc",
    "wof:placetype":"venue"
},
  "geometry": {"coordinates":[-84.377088,39.214335],"type":"Point"}
}