{
  "type": "Feature",
  "properties": {
    "iso:country":"US",
    "sg:address":"2800 Linden Ave",
    "sg:city":"Dayton",
    "sg:classifiers":[
        {
            "category":"Personal",
            "subcategory":"Beauty Salon",
            "type":"Services"
        }
    ],
    "sg:phone":"+1 937 256 7991",
    "sg:postcode":"45410",
    "sg:province":"OH",
    "wof:name":"Avenue Salon",
    "wof:placetype":"venue"
},
  "geometry": {"coordinates":[-84.141371,39.748208],"type":"Point"}
}