{
  "type": "Feature",
  "properties": {
    "addr:full": "4026 Cherry St Cincinnati OH 45223",
    "addr:housenumber": "4026",
    "addr:postcode": "45223",
    "addr:street": "Cherry St",
    "iso:country": "US",
    "sg:address": "4026 Cherry St",
    "sg:city": "Cincinnati",
    "sg:classifiers": [
      {
        "category": "Wholesale",
        "subcategory": "Stationery",
        "type": "Manufacturing \u0026 Wholesale Goods"
      }
    ],
    "sg:phone": "+1 513 541 3010",
    "sg:postcode": "45223",
    "sg:province": "OH",
    "sg:tags": [
      "supply"
    ],
    "wof:name": "Natmar Inc",
    "wof:placetype": "venue"
  },
  "geometry": {"coordinates":[-84.542653,39.159229],"type":"Point"}
}
