{
  "type": "Feature",
  "properties": {
    "addr:full": "4435 Reading Rd Cincinnati OH 45229",
    "addr:housenumber": "4435",
    "addr:postcode": "45229",
    "addr:street": "Reading Rd",
    "iso:country": "US",
    "sg:address": "4435 Reading Rd",
    "sg:city": "Cincinnati",
    "sg:classifiers": [
      {
        "category": "Retail",
        "subcategory": "Auto Repair",
        "type": "Services"
      }
    ],
    "sg:phone": "+1 513 242 5710",
    "sg:postcode": "45229",
    "sg:province": "OH",
    "sg:tags": [
      "repairing",
      "automobile"
    ],
    "wof:name": "Huber \u0026 Kessel Svc",
    "wof:placetype": "venue"
  },
  "geometry": {"coordinates":[-84.472579,39.16336],"type":"Point"}
}
