{
  "type": "Feature",
  "properties": {
    "addr:full": "289 S 3rd St Columbus OH 43215",
    "addr:housenumber": "289",
    "addr:postcode": "43215",
    "addr:street": "S 3Rd St",
    "iso:country": "US",
    "sg:address": "289 S 3rd St",
    "sg:city": "Columbus",
    "sg:classifiers": [
      {
        "category": "Utilities",
        "subcategory": "Mobile Phone",
        "type": "Services"
      }
    ],
    "sg:phone": "+1 614 846 5050",
    "sg:postcode": "43215",
    "sg:province": "OH",
    "sg:tags": [
      "communication",
      "radiotelephone"
    ],
    "wof:name": "USA Mobile",
    "wof:placetype": "venue"
  },
  "geometry": {"coordinates":[-82.996913,39.957111],"type":"Point"}
}
