{
  "type": "Feature",
  "properties": {
    "addr:full": "2727 Gaylord Ave Dayton OH 45419",
    "addr:housenumber": "2727",
    "addr:postcode": "45419",
    "addr:street": "Gaylord Ave",
    "iso:country": "US",
    "sg:address": "2727 Gaylord Ave",
    "sg:city": "Dayton",
    "sg:classifiers": [
      {
        "category": "Professional",
        "subcategory": "Business Services",
        "type": "Services"
      }
    ],
    "sg:phone": "+1 937 298 2727",
    "sg:postcode": "45419",
    "sg:province": "OH",
    "sg:tags": [
      "recording",
      "studio"
    ],
    "wof:name": "Refraze Recording Studios",
    "wof:placetype": "venue"
  },
  "geometry": {"coordinates":[-84.148963,39.707375],"type":"Point"}
}
