{
  "type": "Feature",
  "properties": {
    "iso:country":"US",
    "sg:address":"1475 Upper Valley Pike",
    "sg:city":"Springfield",
    "sg:classifiers":[
        {
            "category":"Food & Beverages",
            "subcategory":"Bakery",
            "type":"Retail Goods"
        },
        {
            "category":"Bakery",
            "type":"Food & Drink"
        }
    ],
    "sg:menulink":"http://www.allmenus.com/oh/german/235767-pretzel-time/menu/",
    "sg:phone":"+1 937 325 5883",
    "sg:postcode":"45504",
    "sg:province":"OH",
    "sg:tags":[
        "new",
        "american",
        "bakery",
        "pastry"
    ],
    "wof:name":"Pretzel Time",
    "wof:placetype":"venue"
},
  "geometry": {"coordinates":[-83.85209999999999,39.947538],"type":"Point"}
}