{
  "type": "Feature",
  "properties": {
    "addr:full": "1475 Upper Valley Pike Springfield OH 45504",
    "addr:housenumber": "1475",
    "addr:postcode": "45504",
    "addr:street": "Upper Valley Pike",
    "iso:country": "US",
    "sg:address": "1475 Upper Valley Pike",
    "sg:city": "Springfield",
    "sg:classifiers": [
      {
        "category": "Food \u0026 Beverages",
        "subcategory": "Bakery",
        "type": "Retail Goods"
      },
      {
        "category": "Bakery",
        "type": "Food \u0026 Drink"
      }
    ],
    "sg:menulink": "http://www.allmenus.com/oh/german/235767-pretzel-time/menu/",
    "sg:phone": "+1 937 325 5883",
    "sg:postcode": "45504",
    "sg:province": "OH",
    "sg:tags": [
      "new",
      "american",
      "bakery",
      "pastry"
    ],
    "wof:name": "Pretzel Time",
    "wof:placetype": "venue"
  },
  "geometry": {"coordinates":[-83.8521,39.947538],"type":"Point"}
}
