{
  "type": "Feature",
  "properties": {
    "addr:full": "11 N Mill St Mansfield OH 44904",
    "addr:housenumber": "11",
    "addr:postcode": "44904",
    "addr:street": "N Mill St",
    "iso:country": "US",
    "sg:address": "11 N Mill St",
    "sg:city": "Mansfield",
    "sg:classifiers": [
      {
        "category": "Freight",
        "type": "Transportation"
      }
    ],
    "sg:phone": "+1 419 884 2411",
    "sg:postcode": "44904",
    "sg:province": "OH",
    "sg:tags": [
      "cartage",
      "trucking"
    ],
    "wof:name": "Hayes Cartage LLC",
    "wof:placetype": "venue"
  },
  "geometry": {"coordinates":[-82.581168,40.678834],"type":"Point"}
}
