{
  "type": "Feature",
  "properties": {
    "iso:country":"US",
    "sg:address":"9609 Hayes Ave",
    "sg:city":"Sandusky",
    "sg:classifiers":[
        {
            "category":"Building & Trades",
            "subcategory":"Construction",
            "type":"Services"
        }
    ],
    "sg:phone":"+1 419 359 2203",
    "sg:postcode":"44870",
    "sg:province":"OH",
    "sg:tags":[
        "general",
        "contractor"
    ],
    "wof:name":"Keller General Contractors",
    "wof:placetype":"venue"
},
  "geometry": {"coordinates":[-82.764061,41.330529],"type":"Point"}
}