{
  "type": "Feature",
  "properties": {
    "addr:full": "111 N Jonesville St Montpelier OH 43543",
    "addr:housenumber": "111",
    "addr:postcode": "43543",
    "addr:street": "N Jonesville St",
    "iso:country": "US",
    "sg:address": "111 N Jonesville St",
    "sg:city": "Montpelier",
    "sg:classifiers": [
      {
        "category": "Restaurant",
        "type": "Food \u0026 Drink"
      }
    ],
    "sg:phone": "+1 419 485 8334",
    "sg:postcode": "43543",
    "sg:province": "OH",
    "sg:tags": [
      "pizza"
    ],
    "wof:name": "Tano's Pizza",
    "wof:placetype": "venue"
  },
  "geometry": {"coordinates":[-84.611172,41.58695],"type":"Point"}
}
