{
  "type": "Feature",
  "properties": {
    "addr:full": "11014 Briggs Rd Cleveland OH 44111",
    "addr:housenumber": "11014",
    "addr:postcode": "44111",
    "addr:street": "Briggs Rd",
    "iso:country": "US",
    "sg:address": "11014 Briggs Rd",
    "sg:city": "Cleveland",
    "sg:classifiers": [
      {
        "category": "Manufacturing",
        "subcategory": "Tools \u0026 Machinery",
        "type": "Manufacturing \u0026 Wholesale Goods"
      }
    ],
    "sg:phone": "+1 216 671 1900",
    "sg:postcode": "44111",
    "sg:province": "OH",
    "sg:tags": [
      "die",
      "maker"
    ],
    "wof:name": "Windsor Tool \u0026 Die",
    "wof:placetype": "venue"
  },
  "geometry": {"coordinates":[-81.762891,41.446849],"type":"Point"}
}
