{
  "type": "Feature",
  "properties": {
    "iso:country":"US",
    "sg:address":"182 N Washington St",
    "sg:city":"Tiffin",
    "sg:classifiers":[
        {
            "category":"Real Estate",
            "subcategory":"Real Estate Agent",
            "type":"Services"
        }
    ],
    "sg:phone":"+1 419 447 2080",
    "sg:postcode":"44883",
    "sg:province":"OH",
    "wof:name":"Scheiber Rentals",
    "wof:placetype":"venue"
},
  "geometry": {"coordinates":[-83.177853,41.123181],"type":"Point"}
}