{
  "type": "Feature",
  "properties": {
    "addr:full": "182 N Washington St Tiffin OH 44883",
    "addr:housenumber": "182",
    "addr:postcode": "44883",
    "addr:street": "N Washington St",
    "iso:country": "US",
    "sg:address": "182 N Washington St",
    "sg:city": "Tiffin",
    "sg:classifiers": [
      {
        "category": "Real Estate",
        "subcategory": "Real Estate Agent",
        "type": "Services"
      }
    ],
    "sg:phone": "+1 419 447 2080",
    "sg:postcode": "44883",
    "sg:province": "OH",
    "wof:name": "Scheiber Rentals",
    "wof:placetype": "venue"
  },
  "geometry": {"coordinates":[-83.177853,41.123181],"type":"Point"}
}
