{
  "type": "Feature",
  "properties": {
    "addr:full": "620 W 1st St Uhrichsville OH 44683",
    "addr:housenumber": "620",
    "addr:postcode": "44683",
    "addr:street": "W 1St St",
    "iso:country": "US",
    "sg:address": "620 W 1st St",
    "sg:city": "Uhrichsville",
    "sg:classifiers": [
      {
        "category": "Mining \u0026 Drilling",
        "type": "Manufacturing \u0026 Wholesale Goods"
      }
    ],
    "sg:phone": "+1 740 922 0923",
    "sg:postcode": "44683",
    "sg:province": "OH",
    "sg:tags": [
      "development",
      "gas",
      "oil",
      "exploration"
    ],
    "wof:name": "Haddad \u0026 Brooks Inc",
    "wof:placetype": "venue"
  },
  "geometry": {"coordinates":[-81.354059,40.390942],"type":"Point"}
}
