{
  "type": "Feature",
  "properties": {
    "iso:country":"US",
    "sg:address":"620 W 1st St",
    "sg:city":"Uhrichsville",
    "sg:classifiers":[
        {
            "category":"Mining & Drilling",
            "type":"Manufacturing & Wholesale Goods"
        }
    ],
    "sg:phone":"+1 740 922 0923",
    "sg:postcode":"44683",
    "sg:province":"OH",
    "sg:tags":[
        "development",
        "gas",
        "oil",
        "exploration"
    ],
    "wof:name":"Haddad & Brooks Inc",
    "wof:placetype":"venue"
},
  "geometry": {"coordinates":[-81.35405900000001,40.390942],"type":"Point"}
}