{
  "type": "Feature",
  "properties": {
    "addr:full": "3592 E Main St Columbus OH 43213",
    "addr:housenumber": "3592",
    "addr:postcode": "43213",
    "addr:street": "E Main St",
    "iso:country": "US",
    "sg:address": "3592 E Main St",
    "sg:city": "Columbus",
    "sg:classifiers": [
      {
        "category": "Personal",
        "subcategory": "Beauty Salon",
        "type": "Services"
      }
    ],
    "sg:phone": "+1 614 231 5799",
    "sg:postcode": "43213",
    "sg:province": "OH",
    "wof:name": "Sequoia's Nail Studio",
    "wof:placetype": "venue"
  },
  "geometry": {"coordinates":[-82.901372,39.956265],"type":"Point"}
}
