{
  "type": "Feature",
  "properties": {
    "iso:country":"US",
    "sg:address":"3592 E Main St",
    "sg:city":"Columbus",
    "sg:classifiers":[
        {
            "category":"Personal",
            "subcategory":"Beauty Salon",
            "type":"Services"
        }
    ],
    "sg:phone":"+1 614 231 5799",
    "sg:postcode":"43213",
    "sg:province":"OH",
    "wof:name":"Sequoia's Nail Studio",
    "wof:placetype":"venue"
},
  "geometry": {"coordinates":[-82.90137199999999,39.956265],"type":"Point"}
}