{
  "type": "Feature",
  "properties": {
    "addr:full":"7801 Harriott Rd Dublin OH 43017",
    "addr:housenumber":"7801",
    "addr:postcode":"43017",
    "addr:street":"Harriott Rd",
    "iso:country":"US",
    "sg:address":"7801 Harriott Rd",
    "sg:city":"Dublin",
    "sg:classifiers":[
        {
            "category":"Building & Trades",
            "subcategory":"Construction",
            "type":"Services"
        }
    ],
    "sg:phone":"+1 614 873 8498",
    "sg:postcode":"43017",
    "sg:province":"OH",
    "sg:tags":[
        "builder",
        "operative"
    ],
    "wof:name":"Annette Builders",
    "wof:placetype":"venue"
},
  "geometry": {"coordinates":[-83.16665999999999,40.167197],"type":"Point"}
}