{
  "type": "Feature",
  "properties": {
    "addr:full": "3313 N High St Columbus OH 43202",
    "addr:housenumber": "3313",
    "addr:postcode": "43202",
    "addr:street": "N High St",
    "iso:country": "US",
    "sg:address": "3313 N High St",
    "sg:city": "Columbus",
    "sg:classifiers": [
      {
        "category": "Shopping",
        "subcategory": "Photographic Equipment",
        "type": "Retail Goods"
      }
    ],
    "sg:phone": "+1 614 261 1264",
    "sg:postcode": "43202",
    "sg:province": "OH",
    "sg:tags": [
      "supply"
    ],
    "wof:name": "Midwest Photo Exchange",
    "wof:placetype": "venue"
  },
  "geometry": {"coordinates":[-83.015544,40.030011],"type":"Point"}
}
