{
  "type": "Feature",
  "properties": {
    "iso:country":"US",
    "sg:address":"4229 Emerald Blvd",
    "sg:city":"Richfield",
    "sg:classifiers":[
        {
            "category":"Manufacturing",
            "subcategory":"Retail Goods",
            "type":"Manufacturing & Wholesale Goods"
        }
    ],
    "sg:phone":"+1 330 659 9080",
    "sg:postcode":"44286",
    "sg:province":"OH",
    "sg:tags":[
        "manufacturer"
    ],
    "wof:name":"ALRA",
    "wof:placetype":"venue"
},
  "geometry": {"coordinates":[-81.658202,41.248205],"type":"Point"}
}