{
  "type": "Feature",
  "properties": {
    "addr:full": "4229 Emerald Blvd Richfield OH 44286",
    "addr:housenumber": "4229",
    "addr:postcode": "44286",
    "addr:street": "Emerald Blvd",
    "iso:country": "US",
    "sg:address": "4229 Emerald Blvd",
    "sg:city": "Richfield",
    "sg:classifiers": [
      {
        "category": "Manufacturing",
        "subcategory": "Retail Goods",
        "type": "Manufacturing \u0026 Wholesale Goods"
      }
    ],
    "sg:phone": "+1 330 659 9080",
    "sg:postcode": "44286",
    "sg:province": "OH",
    "sg:tags": [
      "manufacturer"
    ],
    "wof:name": "ALRA",
    "wof:placetype": "venue"
  },
  "geometry": {"coordinates":[-81.658202,41.248205],"type":"Point"}
}
