{
  "type": "Feature",
  "properties": {
    "iso:country":"US",
    "sg:address":"1030 Symmes Rd",
    "sg:city":"Fairfield",
    "sg:classifiers":[
        {
            "category":"Professional",
            "subcategory":"Art Services",
            "type":"Services"
        }
    ],
    "sg:phone":"+1 513 863 7368",
    "sg:postcode":"45014",
    "sg:province":"OH",
    "sg:tags":[
        "photographer"
    ],
    "sg:website":"www.groverphotography.com",
    "wof:name":"Grover Photography",
    "wof:placetype":"venue"
},
  "geometry": {"coordinates":[-84.544095,39.351588],"type":"Point"}
}