{
  "type": "Feature",
  "properties": {
    "addr:full": "199 Sunrise Ter New Carlisle OH 45344",
    "addr:housenumber": "199",
    "addr:postcode": "45344",
    "addr:street": "Sunrise Ter",
    "iso:country": "US",
    "sg:address": "199 Sunrise Ter",
    "sg:city": "New Carlisle",
    "sg:classifiers": [
      {
        "category": "Organizations",
        "subcategory": "Non-profit Organization",
        "type": "Services"
      }
    ],
    "sg:phone": "+1 937 845 8062",
    "sg:postcode": "45344",
    "sg:province": "OH",
    "wof:name": "Senior Citizens Assoc Inc",
    "wof:placetype": "venue"
  },
  "geometry": {"coordinates":[-84.021785,39.941662],"type":"Point"}
}
