{
  "type": "Feature",
  "properties": {
    "iso:country":"US",
    "sg:address":"124 N 2nd St",
    "sg:city":"Ironton",
    "sg:classifiers":[
        {
            "category":"Restaurant",
            "type":"Food & Drink"
        }
    ],
    "sg:phone":"+1 740 532 8938",
    "sg:postcode":"45638",
    "sg:province":"OH",
    "sg:tags":[
        "eating"
    ],
    "wof:name":"Ming Moon",
    "wof:placetype":"venue"
},
  "geometry": {"coordinates":[-82.686984,38.535755],"type":"Point"}
}