{
  "type": "Feature",
  "properties": {
    "addr:full":"1219 Plainfield Rd Cleveland OH 44121",
    "addr:housenumber":"1219",
    "addr:postcode":"44121",
    "addr:street":"Plainfield Rd",
    "iso:country":"US",
    "sg:address":"1219 Plainfield Rd",
    "sg:city":"Cleveland",
    "sg:classifiers":[
        {
            "category":"Building & Trades",
            "subcategory":"Construction",
            "type":"Services"
        }
    ],
    "sg:phone":"+1 216 382 4026",
    "sg:postcode":"44121",
    "sg:province":"OH",
    "sg:tags":[
        "house",
        "co"
    ],
    "wof:name":"Quintana & Son Construction",
    "wof:placetype":"venue"
},
  "geometry": {"coordinates":[-81.533834,41.525649],"type":"Point"}
}