{
  "type": "Feature",
  "properties": {
    "addr:full":"6491 Brecksville Rd Cleveland OH 44131",
    "addr:housenumber":"6491",
    "addr:postcode":"44131",
    "addr:street":"Brecksville Rd",
    "iso:country":"US",
    "sg:address":"6491 Brecksville Rd",
    "sg:city":"Cleveland",
    "sg:classifiers":[
        {
            "category":"Shopping",
            "subcategory":"Musical Instruments",
            "type":"Retail Goods"
        }
    ],
    "sg:phone":"+1 216 642 8110",
    "sg:postcode":"44131",
    "sg:province":"OH",
    "wof:name":"Independence Music Studio Inc",
    "wof:placetype":"venue"
},
  "geometry": {"coordinates":[-81.641085,41.384465],"type":"Point"}
}