{
  "type": "Feature",
  "properties": {
    "iso:country":"US",
    "sg:address":"44155 Jones Rd",
    "sg:city":"Wellington",
    "sg:classifiers":[
        {
            "category":"Building & Trades",
            "subcategory":"Construction",
            "type":"Services"
        }
    ],
    "sg:phone":"+1 440 647 6750",
    "sg:postcode":"44090",
    "sg:province":"OH",
    "sg:tags":[
        "contractor"
    ],
    "wof:name":"All American Fence",
    "wof:placetype":"venue"
},
  "geometry": {"coordinates":[-82.184044,41.1475],"type":"Point"}
}