{
  "type": "Feature",
  "properties": {
    "addr:full":"849 Umbleby Pl Pickerington OH 43147",
    "addr:housenumber":"849",
    "addr:postcode":"43147",
    "addr:street":"Umbleby Pl",
    "iso:country":"US",
    "sg:address":"849 Umbleby Pl",
    "sg:city":"Pickerington",
    "sg:classifiers":[
        {
            "category":"Wholesale",
            "subcategory":"Vending Machines",
            "type":"Manufacturing & Wholesale Goods"
        }
    ],
    "sg:phone":"+1 614 837 7793",
    "sg:postcode":"43147",
    "sg:province":"OH",
    "sg:tags":[
        "operator"
    ],
    "wof:name":"Ronald C Bayer Candy",
    "wof:placetype":"venue"
},
  "geometry": {"coordinates":[-82.765451,39.902409],"type":"Point"}
}