{
  "type": "Feature",
  "properties": {
    "addr:full": "1259 Cleveland Heights Blvd Cleveland OH 44121",
    "addr:housenumber": "1259",
    "addr:postcode": "44121",
    "addr:street": "Cleveland Heights Blvd",
    "iso:country": "US",
    "sg:address": "1259 Cleveland Heights Blvd",
    "sg:city": "Cleveland",
    "sg:classifiers": [
      {
        "category": "Manufacturing",
        "subcategory": "Apparel",
        "type": "Manufacturing \u0026 Wholesale Goods"
      }
    ],
    "sg:phone": "+1 216 291 4908",
    "sg:postcode": "44121",
    "sg:province": "OH",
    "sg:tags": [
      "clothing"
    ],
    "wof:name": "Maria Iris Clothing Fab",
    "wof:placetype": "venue"
  },
  "geometry": {"coordinates":[-81.544505,41.52603],"type":"Point"}
}
