{
  "type": "Feature",
  "properties": {
    "addr:full": "10908 Rayner Ln Blue Rock OH 43720",
    "addr:housenumber": "10908",
    "addr:postcode": "43720",
    "addr:street": "Rayner Ln",
    "iso:country": "US",
    "sg:address": "10908 Rayner Ln",
    "sg:city": "Blue Rock",
    "sg:classifiers": [
      {
        "category": "Recreation",
        "type": "Entertainment"
      }
    ],
    "sg:phone": "+1 740 674 7019",
    "sg:postcode": "43720",
    "sg:province": "OH",
    "sg:tags": [
      "amusement"
    ],
    "wof:name": "Rayner's Range Inc",
    "wof:placetype": "venue"
  },
  "geometry": {"coordinates":[-81.791343,39.766625],"type":"Point"}
}
