{
  "type": "Feature",
  "properties": {
    "addr:full":"556 Tamplin St Sharon OH 16146",
    "addr:housenumber":"556",
    "addr:postcode":"16146",
    "addr:street":"Tamplin St",
    "iso:country":"US",
    "sg:address":"556 Tamplin St",
    "sg:city":"Sharon",
    "sg:classifiers":[
        {
            "category":"Utilities",
            "subcategory":"Telephone",
            "type":"Services"
        }
    ],
    "sg:phone":"+1   ",
    "sg:postcode":"16146",
    "sg:province":"OH",
    "sg:tags":[
        "communications"
    ],
    "wof:name":"Localconnect Shenango",
    "wof:placetype":"venue"
},
  "geometry": {"coordinates":[-80.50081,41.247853],"type":"Point"}
}