{
  "type": "Feature",
  "properties": {
    "addr:full": "517 S 2nd St Coldwater OH 45828",
    "addr:housenumber": "517",
    "addr:postcode": "45828",
    "addr:street": "S 2Nd St",
    "iso:country": "US",
    "sg:address": "517 S 2nd St",
    "sg:city": "Coldwater",
    "sg:classifiers": [
      {
        "category": "Autos \u0026 Motor Vehicles",
        "subcategory": "Automobile Sales",
        "type": "Retail Goods"
      }
    ],
    "sg:phone": "+1 419 678 2334",
    "sg:postcode": "45828",
    "sg:province": "OH",
    "sg:tags": [
      "new",
      "used",
      "sales"
    ],
    "wof:name": "Werling Motors",
    "wof:placetype": "venue"
  },
  "geometry": {"coordinates":[-84.628683,40.475569],"type":"Point"}
}
