{
  "type": "Feature",
  "properties": {
    "addr:full": "1434 Tomilu Dr Girard OH 44420",
    "addr:housenumber": "1434",
    "addr:postcode": "44420",
    "addr:street": "Tomilu Dr",
    "iso:country": "US",
    "sg:address": "1434 Tomilu Dr",
    "sg:city": "Girard",
    "sg:classifiers": [
      {
        "category": "Sports \u0026 Exercise",
        "subcategory": "Sports Center",
        "type": "Entertainment"
      }
    ],
    "sg:phone": "+1 330 539 4292",
    "sg:postcode": "44420",
    "sg:province": "OH",
    "wof:name": "Hubbard Swim Club",
    "wof:placetype": "venue"
  },
  "geometry": {"coordinates":[-80.673306,41.170286],"type":"Point"}
}
