{
  "type": "Feature",
  "properties": {
    "addr:full":"4849 Turney Rd Cleveland OH 44125",
    "addr:housenumber":"4849",
    "addr:postcode":"44125",
    "addr:street":"Turney Rd",
    "iso:country":"US",
    "sg:address":"4849 Turney Rd",
    "sg:city":"Cleveland",
    "sg:classifiers":[
        {
            "category":"Personal",
            "subcategory":"Beauty Salon",
            "type":"Services"
        }
    ],
    "sg:phone":"+1 216 883 1919",
    "sg:postcode":"44125",
    "sg:province":"OH",
    "wof:name":"Maryann's Styling Salon",
    "wof:placetype":"venue"
},
  "geometry": {"coordinates":[-81.613899,41.427964],"type":"Point"}
}