{
  "type": "Feature",
  "properties": {
    "iso:country":"US",
    "sg:address":"1 S Main St",
    "sg:city":"Columbiana",
    "sg:classifiers":[
        {
            "category":"Organizations",
            "subcategory":"Professional Association",
            "type":"Services"
        }
    ],
    "sg:phone":"+1 330 482 3822",
    "sg:postcode":"44408",
    "sg:province":"OH",
    "sg:tags":[
        "chambers",
        "commerce"
    ],
    "wof:name":"Columbiana Chamber Of Commerce",
    "wof:placetype":"venue"
},
  "geometry": {"coordinates":[-80.693632,40.888656],"type":"Point"}
}