{
  "type": "Feature",
  "properties": {
    "addr:full": "1490 W River St S Elyria OH 44035",
    "addr:housenumber": "1490",
    "addr:postcode": "44035",
    "addr:street": "W River St S",
    "iso:country": "US",
    "sg:address": "1490 W River St S",
    "sg:city": "Elyria",
    "sg:classifiers": [
      {
        "category": "Shopping",
        "type": "Retail Goods"
      }
    ],
    "sg:phone": "+1 440 324 6999",
    "sg:postcode": "44035",
    "sg:province": "OH",
    "sg:tags": [
      "aids",
      "hearing"
    ],
    "wof:name": "Beltone Hearing Center",
    "wof:placetype": "venue"
  },
  "geometry": {"coordinates":[-82.11941,41.35274],"type":"Point"}
}
