{
  "type": "Feature",
  "properties": {
    "addr:full": "18 E Main St South Vienna OH 45369",
    "addr:housenumber": "18",
    "addr:postcode": "45369",
    "addr:street": "E Main St South",
    "iso:country": "US",
    "sg:address": "18 E Main St",
    "sg:city": "South Vienna",
    "sg:classifiers": [
      {
        "category": "Freight",
        "type": "Transportation"
      }
    ],
    "sg:phone": "+1 937 568 4010",
    "sg:postcode": "45369",
    "sg:province": "OH",
    "sg:tags": [
      "broker",
      "trucking"
    ],
    "wof:name": "Power Logistics",
    "wof:placetype": "venue"
  },
  "geometry": {"coordinates":[-83.611918,39.927862],"type":"Point"}
}
