{
  "type": "Feature",
  "properties": {
    "iso:country":"US",
    "sg:address":"18 E Main St",
    "sg:city":"South Vienna",
    "sg:classifiers":[
        {
            "category":"Freight",
            "type":"Transportation"
        }
    ],
    "sg:phone":"+1 937 568 4010",
    "sg:postcode":"45369",
    "sg:province":"OH",
    "sg:tags":[
        "broker",
        "trucking"
    ],
    "wof:name":"Power Logistics",
    "wof:placetype":"venue"
},
  "geometry": {"coordinates":[-83.611918,39.927862],"type":"Point"}
}