{
  "type": "Feature",
  "properties": {
    "iso:country":"US",
    "sg:address":"75 Hale Dr",
    "sg:city":"West Union",
    "sg:classifiers":[
        {
            "category":"Professional",
            "subcategory":"Computer Services",
            "type":"Services"
        }
    ],
    "sg:phone":"+1 937 544 5906",
    "sg:postcode":"45693",
    "sg:province":"OH",
    "sg:tags":[
        "repair"
    ],
    "wof:name":"Spires & Spires",
    "wof:placetype":"venue"
},
  "geometry": {"coordinates":[-83.58246200000001,38.773179],"type":"Point"}
}