{
  "type": "Feature",
  "properties": {
    "addr:full": "75 Hale Dr West Union OH 45693",
    "addr:housenumber": "75",
    "addr:postcode": "45693",
    "addr:street": "Hale Dr West",
    "iso:country": "US",
    "sg:address": "75 Hale Dr",
    "sg:city": "West Union",
    "sg:classifiers": [
      {
        "category": "Professional",
        "subcategory": "Computer Services",
        "type": "Services"
      }
    ],
    "sg:phone": "+1 937 544 5906",
    "sg:postcode": "45693",
    "sg:province": "OH",
    "sg:tags": [
      "repair"
    ],
    "wof:name": "Spires \u0026 Spires",
    "wof:placetype": "venue"
  },
  "geometry": {"coordinates":[-83.582462,38.773179],"type":"Point"}
}
