{
  "type": "Feature",
  "properties": {
    "iso:country":"US",
    "sg:address":"1350 E 2nd St",
    "sg:city":"Franklin",
    "sg:classifiers":[
        {
            "category":"Restaurant",
            "type":"Food & Drink"
        }
    ],
    "sg:menulink":"http://www.allmenus.com/oh/franklin/16833-cazadores/menu/",
    "sg:phone":"+1 937 746 7977",
    "sg:postcode":"45005",
    "sg:province":"OH",
    "sg:tags":[
        "mexican"
    ],
    "wof:name":"Cazadores",
    "wof:placetype":"venue"
},
  "geometry": {"coordinates":[-84.28181499999999,39.56385],"type":"Point"}
}