{
  "type": "Feature",
  "properties": {
    "addr:full": "48360 Bowmans Run Rd Racine OH 45771",
    "addr:postcode": "48360;45771",
    "addr:street": "Bowmans Run Rd",
    "iso:country": "US",
    "sg:address": "48360 Bowmans Run Rd",
    "sg:city": "Racine",
    "sg:classifiers": [
      {
        "category": "Health Services",
        "subcategory": "Medical Lab",
        "type": "Services"
      }
    ],
    "sg:phone": "+1 740 949 2779",
    "sg:postcode": "45771",
    "sg:province": "OH",
    "sg:tags": [
      "laboratory"
    ],
    "wof:name": "Tri-County Dental Lab",
    "wof:placetype": "venue"
  },
  "geometry": {"coordinates":[-81.898895,38.999174],"type":"Point"}
}
