{
  "type": "Feature",
  "properties": {
    "addr:full":"296 Home Ave Xenia OH 45385",
    "addr:housenumber":"296",
    "addr:postcode":"45385",
    "addr:street":"Home Ave",
    "iso:country":"US",
    "sg:address":"296 Home Ave",
    "sg:city":"Xenia",
    "sg:classifiers":[
        {
            "category":"Food & Beverages",
            "subcategory":"Groceries & Convenience Stores",
            "type":"Retail Goods"
        }
    ],
    "sg:phone":"+1 937 374 2842",
    "sg:postcode":"45385",
    "sg:province":"OH",
    "wof:name":"Citgo",
    "wof:placetype":"venue"
},
  "geometry": {"coordinates":[-83.92765300000001,39.677848],"type":"Point"}
}