{
  "type": "Feature",
  "properties": {
    "addr:full": "381 Kennedy Rd Akron OH 44305",
    "addr:housenumber": "381",
    "addr:postcode": "44305",
    "addr:street": "Kennedy Rd",
    "iso:country": "US",
    "sg:address": "381 Kennedy Rd",
    "sg:city": "Akron",
    "sg:classifiers": [
      {
        "category": "Wholesale",
        "subcategory": "Machinery \u0026 Supplies",
        "type": "Manufacturing \u0026 Wholesale Goods"
      }
    ],
    "sg:phone": "+1 330 733 8779",
    "sg:postcode": "44305",
    "sg:province": "OH",
    "sg:tags": [
      "food",
      "equipment",
      "industry",
      "processing"
    ],
    "sg:website": "www.tuskosales.com",
    "wof:name": "Tusko Sales \u0026 Service Inc",
    "wof:placetype": "venue"
  },
  "geometry": {"coordinates":[-81.42505,41.063952],"type":"Point"}
}
