{
  "type": "Feature",
  "properties": {
    "iso:country":"US",
    "sg:address":"381 Kennedy Rd",
    "sg:city":"Akron",
    "sg:classifiers":[
        {
            "category":"Wholesale",
            "subcategory":"Machinery & Supplies",
            "type":"Manufacturing & Wholesale Goods"
        }
    ],
    "sg:phone":"+1 330 733 8779",
    "sg:postcode":"44305",
    "sg:province":"OH",
    "sg:tags":[
        "food",
        "equipment",
        "industry",
        "processing"
    ],
    "sg:website":"www.tuskosales.com",
    "wof:name":"Tusko Sales & Service Inc",
    "wof:placetype":"venue"
},
  "geometry": {"coordinates":[-81.42505,41.063952],"type":"Point"}
}