{
  "type": "Feature",
  "properties": {
    "addr:full":"1830 Hilliard Rome Rd Hilliard OH 43026",
    "addr:housenumber":"1830",
    "addr:postcode":"43026",
    "addr:street":"Hilliard Rome Rd",
    "iso:country":"US",
    "sg:address":"1830 Hilliard Rome Rd",
    "sg:city":"Hilliard",
    "sg:classifiers":[
        {
            "category":"Museum",
            "type":"Entertainment"
        }
    ],
    "sg:phone":"+1 614 876 6294",
    "sg:postcode":"43026",
    "sg:province":"OH",
    "sg:tags":[
        "organization",
        "arts",
        "information"
    ],
    "wof:name":"Michaels Stores",
    "wof:placetype":"venue"
},
  "geometry": {"coordinates":[-83.15156,39.989508],"type":"Point"}
}