{
  "type": "Feature",
  "properties": {
    "addr:full": "89 N Main St Chagrin Falls OH 44022",
    "addr:housenumber": "89",
    "addr:postcode": "44022",
    "addr:street": "N Main St",
    "iso:country": "US",
    "sg:address": "89 N Main St",
    "sg:city": "Chagrin Falls",
    "sg:classifiers": [
      {
        "category": "Personal",
        "subcategory": "Beauty Salon",
        "type": "Services"
      }
    ],
    "sg:phone": "+1 216 839 4850",
    "sg:postcode": "44022",
    "sg:province": "OH",
    "wof:name": "John Roberts Studio",
    "wof:placetype": "venue"
  },
  "geometry": {"coordinates":[-81.392528,41.43196],"type":"Point"}
}
