{
  "type": "Feature",
  "properties": {
    "addr:full":"4667 Cooper Rd Cincinnati OH 45242",
    "addr:housenumber":"4667",
    "addr:postcode":"45242",
    "addr:street":"Cooper Rd",
    "iso:country":"US",
    "sg:address":"4667 Cooper Rd",
    "sg:city":"Cincinnati",
    "sg:classifiers":[
        {
            "category":"Organizations",
            "subcategory":"Religious Organization",
            "type":"Services"
        }
    ],
    "sg:phone":"+1 513 891 3174",
    "sg:postcode":"45242",
    "sg:province":"OH",
    "sg:tags":[
        "church"
    ],
    "wof:name":"Church Of Christ",
    "wof:placetype":"venue"
},
  "geometry": {"coordinates":[-84.379034,39.231895],"type":"Point"}
}