{
  "type": "Feature",
  "properties": {
    "addr:full": "103 S Blackhoof St Wapakoneta OH 45895",
    "addr:housenumber": "103",
    "addr:postcode": "45895",
    "addr:street": "S Blackhoof St",
    "iso:country": "US",
    "sg:address": "103 S Blackhoof St",
    "sg:city": "Wapakoneta",
    "sg:classifiers": [
      {
        "category": "Manufacturing",
        "subcategory": "Tools \u0026 Machinery",
        "type": "Manufacturing \u0026 Wholesale Goods"
      }
    ],
    "sg:phone": "+1 419 739 7616",
    "sg:postcode": "45895",
    "sg:province": "OH",
    "sg:tags": [
      "machine",
      "shop"
    ],
    "wof:name": "Machine Drive Co",
    "wof:placetype": "venue"
  },
  "geometry": {"coordinates":[-84.196251,40.569574],"type":"Point"}
}
