{
  "type": "Feature",
  "properties": {
    "iso:country":"US",
    "sg:address":"1252 Crooked Tree Ct",
    "sg:city":"Westerville",
    "sg:classifiers":[
        {
            "category":"Communications",
            "type":"Services"
        }
    ],
    "sg:phone":"+1 614 891 9959",
    "sg:postcode":"43081",
    "sg:province":"OH",
    "sg:tags":[
        "communication"
    ],
    "wof:name":"Wind River Technologies LLC",
    "wof:placetype":"venue"
},
  "geometry": {"coordinates":[-82.889374,40.10512],"type":"Point"}
}