{
  "type": "Feature",
  "properties": {
    "addr:full": "11384 Chamberlain Rd Aurora OH 44202",
    "addr:housenumber": "11384",
    "addr:postcode": "44202",
    "addr:street": "Chamberlain Rd",
    "iso:country": "US",
    "sg:address": "11384 Chamberlain Rd",
    "sg:city": "Aurora",
    "sg:classifiers": [
      {
        "category": "Building \u0026 Trades",
        "subcategory": "Construction",
        "type": "Services"
      }
    ],
    "sg:phone": "+1 330 995 0883",
    "sg:postcode": "44202",
    "sg:province": "OH",
    "sg:tags": [
      "pavement",
      "marking"
    ],
    "wof:name": "Dura Mark Inc",
    "wof:placetype": "venue"
  },
  "geometry": {"coordinates":[-81.285155,41.300711],"type":"Point"}
}
