{
  "type": "Feature",
  "properties": {
    "iso:country":"US",
    "sg:address":"421 Mission Ln",
    "sg:city":"Franklin",
    "sg:classifiers":[
        {
            "category":"Health Services",
            "subcategory":"Nursing And Care Facility",
            "type":"Services"
        }
    ],
    "sg:phone":"+1 937 866 7390",
    "sg:postcode":"45005",
    "sg:province":"OH",
    "sg:tags":[
        "home",
        "convalescent"
    ],
    "wof:name":"Franklin Nursing Home",
    "wof:placetype":"venue"
},
  "geometry": {"coordinates":[-84.29636600000001,39.555675],"type":"Point"}
}