{
  "type": "Feature",
  "properties": {
    "addr:full":"1309 Mount Vernon Ave Marion OH 43302",
    "addr:housenumber":"1309",
    "addr:postcode":"43302",
    "addr:street":"Mount Vernon Ave",
    "iso:country":"US",
    "sg:address":"1309 Mount Vernon Ave",
    "sg:city":"Marion",
    "sg:classifiers":[
        {
            "category":"Restaurant",
            "type":"Food & Drink"
        }
    ],
    "sg:menulink":"http://www.allmenus.com/oh/marion/213879-taco-bell/menu/",
    "sg:phone":"+1 740 386 5418",
    "sg:postcode":"43302",
    "sg:province":"OH",
    "sg:tags":[
        "mexican"
    ],
    "wof:name":"Taco Bell",
    "wof:placetype":"venue"
},
  "geometry": {"coordinates":[-83.09420299999999,40.580972],"type":"Point"}
}