{
  "type": "Feature",
  "properties": {
    "addr:full": "7563 Salida Rd Mentor On Lake OH 44060",
    "addr:postcode": "7563;lake;44060",
    "addr:street": "Salida Rd",
    "iso:country": "US",
    "sg:address": "7563 Salida Rd",
    "sg:city": "Mentor On Lake",
    "sg:classifiers": [
      {
        "category": "Wholesale",
        "subcategory": "Durable Goods \u0026 Equipment",
        "type": "Manufacturing \u0026 Wholesale Goods"
      }
    ],
    "sg:phone": "+1 440 209 8955",
    "sg:postcode": "44060",
    "sg:province": "OH",
    "sg:tags": [
      "representative",
      "manufacturer"
    ],
    "wof:name": "W M Black \u0026 Co",
    "wof:placetype": "venue"
  },
  "geometry": {"coordinates":[-81.372031,41.714782],"type":"Point"}
}
