{
  "type": "Feature",
  "properties": {
    "iso:country":"US",
    "sg:address":"7563 Salida Rd",
    "sg:city":"Mentor On Lake",
    "sg:classifiers":[
        {
            "category":"Wholesale",
            "subcategory":"Durable Goods & Equipment",
            "type":"Manufacturing & Wholesale Goods"
        }
    ],
    "sg:phone":"+1 440 209 8955",
    "sg:postcode":"44060",
    "sg:province":"OH",
    "sg:tags":[
        "representative",
        "manufacturer"
    ],
    "wof:name":"W M Black & Co",
    "wof:placetype":"venue"
},
  "geometry": {"coordinates":[-81.37203100000001,41.714782],"type":"Point"}
}