{
  "type": "Feature",
  "properties": {
    "addr:full": "1715 Galena Pike West Portsmouth OH 45663",
    "addr:housenumber": "1715",
    "addr:postcode": "45663",
    "addr:street": "Galena Pike",
    "iso:country": "US",
    "sg:address": "1715 Galena Pike",
    "sg:city": "West Portsmouth",
    "sg:classifiers": [
      {
        "category": "Personal",
        "subcategory": "Beauty Salon",
        "type": "Services"
      }
    ],
    "sg:phone": "+1 740 858 5878",
    "sg:postcode": "45663",
    "sg:province": "OH",
    "wof:name": "Beck's Hair Styling",
    "wof:placetype": "venue"
  },
  "geometry": {"coordinates":[-83.023604,38.756262],"type":"Point"}
}
