{
  "type": "Feature",
  "properties": {
    "iso:country":"US",
    "sg:address":"7342 Armstrong Rd",
    "sg:city":"Butler",
    "sg:classifiers":[
        {
            "category":"Building & Trades",
            "subcategory":"Construction",
            "type":"Services"
        }
    ],
    "sg:phone":"+1 419 883 2638",
    "sg:postcode":"44822",
    "sg:province":"OH",
    "sg:tags":[
        "general",
        "contractor"
    ],
    "wof:name":"Johnson & Johnson Construction",
    "wof:placetype":"venue"
},
  "geometry": {"coordinates":[-82.433198,40.561075],"type":"Point"}
}