{
  "type": "Feature",
  "properties": {
    "addr:full": "7342 Armstrong Rd Butler OH 44822",
    "addr:housenumber": "7342",
    "addr:postcode": "44822",
    "addr:street": "Armstrong Rd",
    "iso:country": "US",
    "sg:address": "7342 Armstrong Rd",
    "sg:city": "Butler",
    "sg:classifiers": [
      {
        "category": "Building \u0026 Trades",
        "subcategory": "Construction",
        "type": "Services"
      }
    ],
    "sg:phone": "+1 419 883 2638",
    "sg:postcode": "44822",
    "sg:province": "OH",
    "sg:tags": [
      "general",
      "contractor"
    ],
    "wof:name": "Johnson \u0026 Johnson Construction",
    "wof:placetype": "venue"
  },
  "geometry": {"coordinates":[-82.433198,40.561075],"type":"Point"}
}
