{
  "type": "Feature",
  "properties": {
    "iso:country":"US",
    "sg:address":"1357 W Waterloo Rd",
    "sg:city":"Akron",
    "sg:classifiers":[
        {
            "category":"Building & Trades",
            "subcategory":"Construction",
            "type":"Services"
        }
    ],
    "sg:phone":"+1 330 773 0109",
    "sg:postcode":"44314",
    "sg:province":"OH",
    "sg:tags":[
        "waterproofing",
        "basement"
    ],
    "wof:name":"Pioneer Basement Waterproofing",
    "wof:placetype":"venue"
},
  "geometry": {"coordinates":[-81.576609,41.032639],"type":"Point"}
}