{
  "type": "Feature",
  "properties": {
    "iso:country":"US",
    "sg:address":"1798 Coventry Rd",
    "sg:city":"Cleveland",
    "sg:classifiers":[
        {
            "category":"Shopping",
            "subcategory":"Bicycles & Sporting Goods",
            "type":"Retail Goods"
        }
    ],
    "sg:phone":"+1 217 321 4731",
    "sg:postcode":"44118",
    "sg:province":"OH",
    "sg:tags":[
        "outdoor",
        "gear"
    ],
    "wof:name":"Wilderness Shop",
    "wof:placetype":"venue"
},
  "geometry": {"coordinates":[-81.579976,41.51086],"type":"Point"}
}