{
  "type": "Feature",
  "properties": {
    "addr:full": "1798 Coventry Rd Cleveland OH 44118",
    "addr:housenumber": "1798",
    "addr:postcode": "44118",
    "addr:street": "Coventry Rd",
    "iso:country": "US",
    "sg:address": "1798 Coventry Rd",
    "sg:city": "Cleveland",
    "sg:classifiers": [
      {
        "category": "Shopping",
        "subcategory": "Bicycles \u0026 Sporting Goods",
        "type": "Retail Goods"
      }
    ],
    "sg:phone": "+1 217 321 4731",
    "sg:postcode": "44118",
    "sg:province": "OH",
    "sg:tags": [
      "outdoor",
      "gear"
    ],
    "wof:name": "Wilderness Shop",
    "wof:placetype": "venue"
  },
  "geometry": {"coordinates":[-81.579976,41.51086],"type":"Point"}
}
