{
  "type": "Feature",
  "properties": {
    "addr:full": "200 S 4th St Martins Ferry OH 43935",
    "addr:housenumber": "200",
    "addr:postcode": "43935",
    "addr:street": "S 4Th St Martins Ferry",
    "iso:country": "US",
    "sg:address": "200 S 4th St",
    "sg:city": "Martins Ferry",
    "sg:classifiers": [
      {
        "category": "Manufacturing",
        "subcategory": "Printing",
        "type": "Manufacturing \u0026 Wholesale Goods"
      }
    ],
    "sg:phone": "+1 740 633 1131",
    "sg:postcode": "43935",
    "sg:province": "OH",
    "sg:tags": [
      "newspaper"
    ],
    "wof:name": "Times Leader Inc",
    "wof:placetype": "venue"
  },
  "geometry": {"coordinates":[-80.726114,40.094338],"type":"Point"}
}
