{
  "type": "Feature",
  "properties": {
    "iso:country":"US",
    "sg:address":"12 Stanton St",
    "sg:city":"Bloomville",
    "sg:classifiers":[
        {
            "category":"Building & Trades",
            "subcategory":"Construction",
            "type":"Services"
        }
    ],
    "sg:phone":"+1 419 983 5235",
    "sg:postcode":"44818",
    "sg:province":"OH",
    "sg:tags":[
        "house"
    ],
    "wof:name":"Bloomville Builders",
    "wof:placetype":"venue"
},
  "geometry": {"coordinates":[-83.00858599999999,41.050644],"type":"Point"}
}