{
  "type": "Feature",
  "properties": {
    "addr:full": "12 Stanton St Bloomville OH 44818",
    "addr:housenumber": "12",
    "addr:postcode": "44818",
    "addr:street": "Stanton St",
    "iso:country": "US",
    "sg:address": "12 Stanton St",
    "sg:city": "Bloomville",
    "sg:classifiers": [
      {
        "category": "Building \u0026 Trades",
        "subcategory": "Construction",
        "type": "Services"
      }
    ],
    "sg:phone": "+1 419 983 5235",
    "sg:postcode": "44818",
    "sg:province": "OH",
    "sg:tags": [
      "house"
    ],
    "wof:name": "Bloomville Builders",
    "wof:placetype": "venue"
  },
  "geometry": {"coordinates":[-83.008586,41.050644],"type":"Point"}
}
