{
  "type": "Feature",
  "properties": {
    "iso:country":"US",
    "sg:address":"21 E Railroad St",
    "sg:city":"Columbiana",
    "sg:classifiers":[
        {
            "category":"Retail",
            "subcategory":"Auto Repair",
            "type":"Services"
        }
    ],
    "sg:phone":"+1 330 482 2669",
    "sg:postcode":"44408",
    "sg:province":"OH",
    "sg:tags":[
        "repairing",
        "automobile"
    ],
    "wof:name":"Extended Automotive Svc",
    "wof:placetype":"venue"
},
  "geometry": {"coordinates":[-80.692211,40.883742],"type":"Point"}
}