{
  "type": "Feature",
  "properties": {
    "addr:full": "2405 S Smithville Rd Dayton OH 45420",
    "addr:housenumber": "2405",
    "addr:postcode": "45420",
    "addr:street": "S Smithville Rd",
    "iso:country": "US",
    "sg:address": "2405 S Smithville Rd",
    "sg:city": "Dayton",
    "sg:classifiers": [
      {
        "category": "Restaurant",
        "type": "Food \u0026 Drink"
      }
    ],
    "sg:phone": "+1 937 294 5464",
    "sg:postcode": "45420",
    "sg:province": "OH",
    "sg:website": "www.cassanos.com",
    "wof:name": "Cassano's Pizza King",
    "wof:placetype": "venue"
  },
  "geometry": {"coordinates":[-84.141176,39.730581],"type":"Point"}
}
