{
  "type": "Feature",
  "properties": {
    "addr:full": "245 Union Ave Pomeroy OH 45769",
    "addr:housenumber": "245",
    "addr:postcode": "45769",
    "addr:street": "Union Ave",
    "iso:country": "US",
    "sg:address": "245 Union Ave",
    "sg:city": "Pomeroy",
    "sg:classifiers": [
      {
        "category": "Real Estate",
        "subcategory": "Real Estate Operator",
        "type": "Services"
      }
    ],
    "sg:phone": "+1 740 992 7772",
    "sg:postcode": "45769",
    "sg:province": "OH",
    "sg:tags": [
      "building",
      "apartment"
    ],
    "wof:name": "Pomeroy Cliff Apartments",
    "wof:placetype": "venue"
  },
  "geometry": {"coordinates":[-82.046554,39.032549],"type":"Point"}
}
