{
  "type": "Feature",
  "properties": {
    "addr:full": "2490 State Rte 49 Fort Recovery OH 45846",
    "addr:housenumber": "2490",
    "addr:postcode": "45846",
    "addr:street": "State Rte 49 Fort",
    "iso:country": "US",
    "sg:address": "2490 State Rte 49",
    "sg:city": "Fort Recovery",
    "sg:classifiers": [
      {
        "category": "Organizations",
        "subcategory": "Community Association",
        "type": "Services"
      }
    ],
    "sg:phone": "+1 419 375 2398",
    "sg:postcode": "45846",
    "sg:province": "OH",
    "sg:tags": [
      "military"
    ],
    "wof:name": "American Legion",
    "wof:placetype": "venue"
  },
  "geometry": {"coordinates":[-84.784594,40.41979],"type":"Point"}
}
