{
  "type": "Feature",
  "properties": {
    "addr:full":"771 W Main St Loveland OH 45140",
    "addr:housenumber":"771",
    "addr:postcode":"45140",
    "addr:street":"W Main St",
    "iso:country":"US",
    "sg:address":"771 W Main St",
    "sg:city":"Loveland",
    "sg:classifiers":[
        {
            "category":"Building & Trades",
            "subcategory":"Cleaning & Sanitation",
            "type":"Services"
        }
    ],
    "sg:phone":"+1 513 683 2479",
    "sg:postcode":"45140",
    "sg:province":"OH",
    "sg:tags":[
        "janitor"
    ],
    "wof:name":"SAM Cleaning Solutions",
    "wof:placetype":"venue"
},
  "geometry": {"coordinates":[-84.269153,39.267816],"type":"Point"}
}