{
  "type": "Feature",
  "properties": {
    "addr:full":"6262 Seeds Rd Grove City OH 43123",
    "addr:postcode":"6262;43123",
    "addr:street":"Seeds Rd",
    "iso:country":"US",
    "sg:address":"6262 Seeds Rd",
    "sg:city":"Grove City",
    "sg:classifiers":[
        {
            "category":"Freight",
            "type":"Transportation"
        }
    ],
    "sg:phone":"+1 614 539 5965",
    "sg:postcode":"43123",
    "sg:province":"OH",
    "sg:tags":[
        "consultant"
    ],
    "wof:name":"Exnet Freight Svc",
    "wof:placetype":"venue"
},
  "geometry": {"coordinates":[-83.091747,39.837277],"type":"Point"}
}