{
  "type": "Feature",
  "properties": {
    "iso:country":"US",
    "sg:address":"105 E Market St",
    "sg:city":"Orrville",
    "sg:classifiers":[
        {
            "category":"Personal",
            "subcategory":"Beauty Salon",
            "type":"Services"
        }
    ],
    "sg:phone":"+1 330 682 3901",
    "sg:postcode":"44667",
    "sg:province":"OH",
    "wof:name":"Hair Hut",
    "wof:placetype":"venue"
},
  "geometry": {"coordinates":[-81.76419,40.840745],"type":"Point"}
}