{
  "type": "Feature",
  "properties": {
    "addr:full":"8020 Montgomery Rd Cincinnati OH 45236",
    "addr:housenumber":"8020",
    "addr:postcode":"45236",
    "addr:street":"Montgomery Rd",
    "iso:country":"US",
    "sg:address":"8020 Montgomery Rd",
    "sg:city":"Cincinnati",
    "sg:classifiers":[
        {
            "category":"Travel",
            "subcategory":"Hotels & Motels",
            "type":"Entertainment"
        }
    ],
    "sg:phone":"+1 513 793 4300",
    "sg:postcode":"45236",
    "sg:province":"OH",
    "wof:name":"Sheraton",
    "wof:placetype":"venue"
},
  "geometry": {"coordinates":[-84.370132,39.20321],"type":"Point"}
}