{
  "type": "Feature",
  "properties": {
    "addr:full":"449 Birchwood Dr Berea OH 44017",
    "addr:housenumber":"449",
    "addr:postcode":"44017",
    "addr:street":"Birchwood Dr",
    "iso:country":"US",
    "sg:address":"449 Birchwood Dr",
    "sg:city":"Berea",
    "sg:classifiers":[
        {
            "category":"Home & Garden",
            "subcategory":"Home Furnishings",
            "type":"Retail Goods"
        }
    ],
    "sg:phone":"+1 440 243 3642",
    "sg:postcode":"44017",
    "sg:province":"OH",
    "wof:name":"Jans Baskets",
    "wof:placetype":"venue"
},
  "geometry": {"coordinates":[-81.874584,41.383808],"type":"Point"}
}