{
  "type": "Feature",
  "properties": {
    "iso:country":"US",
    "sg:address":"7710 Aldersyde Dr",
    "sg:city":"Cleveland",
    "sg:classifiers":[
        {
            "category":"Professional",
            "type":"Services"
        }
    ],
    "sg:phone":"+1 440 234 6618",
    "sg:postcode":"44130",
    "sg:province":"OH",
    "wof:name":"World Federatn Hungary",
    "wof:placetype":"venue"
},
  "geometry": {"coordinates":[-81.78908699999999,41.35502],"type":"Point"}
}