{
  "type": "Feature",
  "properties": {
    "iso:country":"US",
    "sg:address":"40490 Jones Rd",
    "sg:city":"Wellington",
    "sg:classifiers":[
        {
            "category":"Building & Trades",
            "subcategory":"Construction",
            "type":"Services"
        }
    ],
    "sg:phone":"+1 440 647 3246",
    "sg:postcode":"44090",
    "sg:province":"OH",
    "sg:tags":[
        "excavation",
        "contractor"
    ],
    "wof:name":"J&S Excavating",
    "wof:placetype":"venue"
},
  "geometry": {"coordinates":[-82.11135400000001,41.154234],"type":"Point"}
}