{
  "type": "Feature",
  "properties": {
    "addr:full": "40490 Jones Rd Wellington OH 44090",
    "addr:housenumber": "40490",
    "addr:postcode": "44090",
    "addr:street": "Jones Rd",
    "iso:country": "US",
    "sg:address": "40490 Jones Rd",
    "sg:city": "Wellington",
    "sg:classifiers": [
      {
        "category": "Building \u0026 Trades",
        "subcategory": "Construction",
        "type": "Services"
      }
    ],
    "sg:phone": "+1 440 647 3246",
    "sg:postcode": "44090",
    "sg:province": "OH",
    "sg:tags": [
      "excavation",
      "contractor"
    ],
    "wof:name": "J\u0026S Excavating",
    "wof:placetype": "venue"
  },
  "geometry": {"coordinates":[-82.111354,41.154234],"type":"Point"}
}
