{
  "type": "Feature",
  "properties": {
    "addr:full":"3235 Midway Mall Elyria OH 44035",
    "addr:housenumber":"3235",
    "addr:postcode":"44035",
    "addr:street":"Midway Mall",
    "iso:country":"US",
    "sg:address":"3235 Midway Mall",
    "sg:city":"Elyria",
    "sg:classifiers":[
        {
            "category":"Utilities",
            "subcategory":"Mobile Phone",
            "type":"Services"
        }
    ],
    "sg:phone":"+1 440 324 1040",
    "sg:postcode":"44035",
    "sg:province":"OH",
    "sg:tags":[
        "telephone",
        "cellular"
    ],
    "sg:website":"www.t-mobile.com",
    "wof:name":"T-Mobile USA",
    "wof:placetype":"venue"
},
  "geometry": {"coordinates":[-82.11215300000001,41.398624],"type":"Point"}
}