{
  "type": "Feature",
  "properties": {
    "addr:full": "4412 Carver Woods Dr Cincinnati OH 45242",
    "addr:housenumber": "4412",
    "addr:postcode": "45242",
    "addr:street": "Carver Woods Dr",
    "iso:country": "US",
    "sg:address": "4412 Carver Woods Dr",
    "sg:city": "Cincinnati",
    "sg:classifiers": [
      {
        "category": "Real Estate",
        "subcategory": "Architect",
        "type": "Services"
      }
    ],
    "sg:phone": "+1 513 984 6000",
    "sg:postcode": "45242",
    "sg:province": "OH",
    "wof:name": "East Interiors",
    "wof:placetype": "venue"
  },
  "geometry": {"coordinates":[-84.386924,39.245479],"type":"Point"}
}
