{
  "type": "Feature",
  "properties": {
    "addr:full":"1160 Oak St Toledo OH 43605",
    "addr:housenumber":"1160",
    "addr:postcode":"43605",
    "addr:street":"Oak St",
    "iso:country":"US",
    "sg:address":"1160 Oak St",
    "sg:city":"Toledo",
    "sg:classifiers":[
        {
            "category":"Social Services",
            "subcategory":"Child Care",
            "type":"Services"
        }
    ],
    "sg:phone":"+1 419 691 0755",
    "sg:postcode":"43605",
    "sg:province":"OH",
    "wof:name":"Happy Faces Child Care",
    "wof:placetype":"venue"
},
  "geometry": {"coordinates":[-83.525173,41.630128],"type":"Point"}
}