{
  "type": "Feature",
  "properties": {
    "addr:full":"319 S Wayne St Piqua OH 45356",
    "addr:housenumber":"319",
    "addr:postcode":"45356",
    "addr:street":"S Wayne St",
    "iso:country":"US",
    "sg:address":"319 S Wayne St",
    "sg:city":"Piqua",
    "sg:classifiers":[
        {
            "category":"Bars & Pubs",
            "type":"Food & Drink"
        }
    ],
    "sg:phone":"+1 937 773 9190",
    "sg:postcode":"45356",
    "sg:province":"OH",
    "sg:tags":[
        "tavern"
    ],
    "wof:name":"ZS Tavern",
    "wof:placetype":"venue"
},
  "geometry": {"coordinates":[-84.24078299999999,40.144048],"type":"Point"}
}