{
  "type": "Feature",
  "properties": {
    "addr:full": "100 Calumet Ct Delaware OH 43061",
    "addr:housenumber": "100",
    "addr:postcode": "43061",
    "addr:street": "Calumet Ct",
    "iso:country": "US",
    "sg:address": "100 Calumet Ct",
    "sg:city": "Delaware",
    "sg:classifiers": [
      {
        "category": "Manufacturing",
        "subcategory": "Chemicals \u0026 Compounds",
        "type": "Manufacturing \u0026 Wholesale Goods"
      }
    ],
    "sg:phone": "+1 740 363 6622",
    "sg:postcode": "43061",
    "sg:province": "OH",
    "sg:tags": [
      "plastic"
    ],
    "wof:name": "Carolina Color Corp",
    "wof:placetype": "venue"
  },
  "geometry": {"coordinates":[-83.199544,40.273765],"type":"Point"}
}
