{
  "type": "Feature",
  "properties": {
    "addr:full": "6482 Ridge Rd Cleveland OH 44129",
    "addr:housenumber": "6482",
    "addr:postcode": "44129",
    "addr:street": "Ridge Rd",
    "iso:country": "US",
    "sg:address": "6482 Ridge Rd",
    "sg:city": "Cleveland",
    "sg:classifiers": [
      {
        "category": "Professional",
        "subcategory": "Accounting \u0026 Tax Preparation",
        "type": "Services"
      }
    ],
    "sg:phone": "+1 440 843 6400",
    "sg:postcode": "44129",
    "sg:province": "OH",
    "sg:tags": [
      "accountant"
    ],
    "wof:name": "De Luca Assoc",
    "wof:placetype": "venue"
  },
  "geometry": {"coordinates":[-81.734705,41.38916],"type":"Point"}
}
