{
  "type": "Feature",
  "properties": {
    "addr:full": "1253 Madison Rd Fostoria OH 44830",
    "addr:housenumber": "1253",
    "addr:postcode": "44830",
    "addr:street": "Madison Rd",
    "iso:country": "US",
    "sg:address": "1253 Madison Rd",
    "sg:city": "Fostoria",
    "sg:classifiers": [
      {
        "category": "Farming",
        "subcategory": "Farm",
        "type": "Manufacturing \u0026 Wholesale Goods"
      }
    ],
    "sg:phone": "+1 419 435 6981",
    "sg:postcode": "44830",
    "sg:province": "OH",
    "sg:tags": [
      "crop",
      "general"
    ],
    "wof:name": "Robert J Fast Farm",
    "wof:placetype": "venue"
  },
  "geometry": {"coordinates":[-83.436743,41.160075],"type":"Point"}
}
