{
  "type": "Feature",
  "properties": {
    "iso:country":"US",
    "sg:address":"1264 Weaver Dr",
    "sg:city":"Granville",
    "sg:classifiers":[
        {
            "category":"Health Services",
            "subcategory":"Doctor",
            "type":"Services"
        }
    ],
    "sg:phone":"+1 740 348 4840",
    "sg:postcode":"43023",
    "sg:province":"OH",
    "sg:tags":[
        "physician",
        "surgeon"
    ],
    "wof:name":"Licking Memorial Family",
    "wof:placetype":"venue"
},
  "geometry": {"coordinates":[-82.527231,40.061767],"type":"Point"}
}