{
  "type": "Feature",
  "properties": {
    "addr:full": "6751 Oakland Rd Loveland OH 45140",
    "addr:housenumber": "6751",
    "addr:postcode": "45140",
    "addr:street": "Oakland Rd",
    "iso:country": "US",
    "sg:address": "6751 Oakland Rd",
    "sg:city": "Loveland",
    "sg:classifiers": [
      {
        "category": "Manufacturing",
        "subcategory": "Building Materials",
        "type": "Manufacturing \u0026 Wholesale Goods"
      }
    ],
    "sg:phone": "+1 513 575 3800",
    "sg:postcode": "45140",
    "sg:province": "OH",
    "sg:tags": [
      "frames",
      "manufacturer",
      "doors-wholesale",
      "doors",
      "accessory"
    ],
    "wof:name": "Air Shop, The",
    "wof:placetype": "venue"
  },
  "geometry": {"coordinates":[-84.216515,39.248299],"type":"Point"}
}
