{
  "type": "Feature",
  "properties": {
    "addr:full":"600 E Rich St Columbus OH 43215",
    "addr:housenumber":"600",
    "addr:postcode":"43215",
    "addr:street":"E Rich St",
    "iso:country":"US",
    "sg:address":"600 E Rich St",
    "sg:city":"Columbus",
    "sg:classifiers":[
        {
            "category":"Social Services",
            "type":"Services"
        }
    ],
    "sg:phone":"+1 614 253 2770",
    "sg:postcode":"43215",
    "sg:province":"OH",
    "wof:name":"Friends of The Homeless Inc",
    "wof:placetype":"venue"
},
  "geometry": {"coordinates":[-82.98403,39.959328],"type":"Point"}
}