{
  "type": "Feature",
  "properties": {
    "addr:full": "5500 Glendon Ct Dublin OH 43016",
    "addr:housenumber": "5500",
    "addr:postcode": "43016",
    "addr:street": "Glendon Ct",
    "iso:country": "US",
    "sg:address": "5500 Glendon Ct",
    "sg:city": "Dublin",
    "sg:classifiers": [
      {
        "category": "Insurance",
        "subcategory": "Insurance Agent",
        "type": "Services"
      }
    ],
    "sg:phone": "+1 614 764 7600",
    "sg:postcode": "43016",
    "sg:province": "OH",
    "sg:tags": [
      "consultant",
      "compensation"
    ],
    "sg:website": "www.cciworkerscomp.com",
    "wof:name": "Compensation Consultants Inc",
    "wof:placetype": "venue"
  },
  "geometry": {"coordinates":[-83.139856,40.080925],"type":"Point"}
}
