{
  "type": "Feature",
  "properties": {
    "addr:full": "7103 Angola Rd Holland OH 43528",
    "addr:housenumber": "7103",
    "addr:postcode": "43528",
    "addr:street": "Angola Rd",
    "iso:country": "US",
    "sg:address": "7103 Angola Rd",
    "sg:city": "Holland",
    "sg:classifiers": [
      {
        "category": "Freight",
        "type": "Transportation"
      }
    ],
    "sg:phone": "+1 419 865 6206",
    "sg:postcode": "43528",
    "sg:province": "OH",
    "sg:tags": [
      "operator",
      "local",
      "trucking"
    ],
    "wof:name": "Key Delivery Systems Inc",
    "wof:placetype": "venue"
  },
  "geometry": {"coordinates":[-83.711706,41.624883],"type":"Point"}
}
