{
  "type": "Feature",
  "properties": {
    "addr:full": "900 Gray St Columbus OH 43201",
    "addr:housenumber": "900",
    "addr:postcode": "43201",
    "addr:street": "Gray St",
    "iso:country": "US",
    "sg:address": "900 Gray St",
    "sg:city": "Columbus",
    "sg:classifiers": [
      {
        "category": "Wholesale",
        "subcategory": "Electrical",
        "type": "Manufacturing \u0026 Wholesale Goods"
      }
    ],
    "sg:phone": "+1 614 297 1600",
    "sg:postcode": "43201",
    "sg:province": "OH",
    "sg:tags": [
      "electric",
      "motor"
    ],
    "wof:name": "American Electric Motor Svc",
    "wof:placetype": "venue"
  },
  "geometry": {"coordinates":[-82.978484,39.982406],"type":"Point"}
}
