{
  "type": "Feature",
  "properties": {
    "addr:full":"601 Findlay St Fostoria OH 44830",
    "addr:housenumber":"601",
    "addr:postcode":"44830",
    "addr:street":"Findlay St",
    "iso:country":"US",
    "sg:address":"601 Findlay St",
    "sg:city":"Fostoria",
    "sg:classifiers":[
        {
            "category":"Restaurant",
            "type":"Food & Drink"
        }
    ],
    "sg:phone":"+1 419 436 2264",
    "sg:postcode":"44830",
    "sg:province":"OH",
    "sg:tags":[
        "eating"
    ],
    "wof:name":"Cafe Family Restaurant",
    "wof:placetype":"venue"
},
  "geometry": {"coordinates":[-83.431816,41.149937],"type":"Point"}
}