{
  "type": "Feature",
  "properties": {
    "addr:full": "6421 Glenway Ave Cincinnati OH 45211",
    "addr:housenumber": "6421",
    "addr:postcode": "45211",
    "addr:street": "Glenway Ave",
    "iso:country": "US",
    "sg:address": "6421 Glenway Ave",
    "sg:city": "Cincinnati",
    "sg:classifiers": [
      {
        "category": "Restaurant",
        "type": "Food \u0026 Drink"
      }
    ],
    "sg:phone": "+1 513 598 9532",
    "sg:postcode": "45211",
    "sg:province": "OH",
    "sg:tags": [
      "family"
    ],
    "wof:name": "Compass Group USA Inc",
    "wof:placetype": "venue"
  },
  "geometry": {"coordinates":[-84.627791,39.149241],"type":"Point"}
}
