{
  "type": "Feature",
  "properties": {
    "addr:full": "14408 Union Ave NE Alliance OH 44601",
    "addr:housenumber": "14408",
    "addr:postcode": "44601",
    "addr:street": "Union Ave Ne",
    "iso:country": "US",
    "sg:address": "14408 Union Ave NE",
    "sg:city": "Alliance",
    "sg:classifiers": [
      {
        "category": "Building \u0026 Trades",
        "subcategory": "Plumbing",
        "type": "Services"
      }
    ],
    "sg:phone": "+1 330 829 9995",
    "sg:postcode": "44601",
    "sg:province": "OH",
    "sg:tags": [
      "contractor"
    ],
    "wof:name": "Ensinger Refrigeration",
    "wof:placetype": "venue"
  },
  "geometry": {"coordinates":[-81.098227,40.98012],"type":"Point"}
}
