{
  "type": "Feature",
  "properties": {
    "addr:full": "500 E 4th St East Liverpool OH 43920",
    "addr:housenumber": "500",
    "addr:postcode": "43920",
    "addr:street": "E 4Th St",
    "iso:country": "US",
    "sg:address": "500 E 4th St",
    "sg:city": "East Liverpool",
    "sg:classifiers": [
      {
        "category": "Organizations",
        "subcategory": "Professional Association",
        "type": "Services"
      }
    ],
    "sg:phone": "+1 330 385 0663",
    "sg:postcode": "43920",
    "sg:province": "OH",
    "sg:website": "www.ymcanet.org",
    "wof:name": "YMCA",
    "wof:placetype": "venue"
  },
  "geometry": {"coordinates":[-80.57601,40.617408],"type":"Point"}
}
