{
  "type": "Feature",
  "properties": {
    "iso:country":"US",
    "sg:address":"2015 Claudia Ct",
    "sg:city":"Cincinnati",
    "sg:classifiers":[
        {
            "category":"Shopping",
            "subcategory":"Discount & Variety Stores",
            "type":"Retail Goods"
        }
    ],
    "sg:phone":"+1 513 231 1636",
    "sg:postcode":"45230",
    "sg:province":"OH",
    "sg:tags":[
        "merchandise",
        "general"
    ],
    "wof:name":"Wave Walker Enterprises",
    "wof:placetype":"venue"
},
  "geometry": {"coordinates":[-84.384693,39.091526],"type":"Point"}
}