{
  "type": "Feature",
  "properties": {
    "addr:full":"103 W Butler St Bryan OH 43506",
    "addr:housenumber":"103",
    "addr:postcode":"43506",
    "addr:street":"W Butler St",
    "iso:country":"US",
    "sg:address":"103 W Butler St",
    "sg:city":"Bryan",
    "sg:classifiers":[
        {
            "category":"Shopping",
            "subcategory":"Used Merchandise",
            "type":"Retail Goods"
        }
    ],
    "sg:phone":"+1 419 633 3902",
    "sg:postcode":"43506",
    "sg:province":"OH",
    "sg:tags":[
        "shop",
        "thrift"
    ],
    "wof:name":"Clothing By Grace",
    "wof:placetype":"venue"
},
  "geometry": {"coordinates":[-84.551723,41.473213],"type":"Point"}
}