{
  "type": "Feature",
  "properties": {
    "addr:full":"328 S Columbus St Somerset OH 43783",
    "addr:housenumber":"328",
    "addr:postcode":"43783",
    "addr:street":"S Columbus St",
    "iso:country":"US",
    "sg:address":"328 S Columbus St",
    "sg:city":"Somerset",
    "sg:classifiers":[
        {
            "category":"Retail",
            "subcategory":"Auto Rental",
            "type":"Services"
        }
    ],
    "sg:phone":"+1 740 743 2589",
    "sg:postcode":"43783",
    "sg:province":"OH",
    "sg:tags":[
        "renting",
        "truck",
        "leasing"
    ],
    "wof:name":"U-Haul Co",
    "wof:placetype":"venue"
},
  "geometry": {"coordinates":[-82.295666,39.803118],"type":"Point"}
}