{
  "type": "Feature",
  "properties": {
    "iso:country":"US",
    "sg:address":"12815 Elmwood Ave",
    "sg:city":"Cleveland",
    "sg:classifiers":[
        {
            "category":"Real Estate",
            "subcategory":"Real Estate Agent",
            "type":"Services"
        }
    ],
    "sg:phone":"+1 216 671 9400",
    "sg:postcode":"44111",
    "sg:province":"OH",
    "wof:name":"Raw Properties",
    "wof:placetype":"venue"
},
  "geometry": {"coordinates":[-81.78113,41.467882],"type":"Point"}
}