{
  "type": "Feature",
  "properties": {
    "addr:full":"4880 Rebert Pike Springfield OH 45502",
    "addr:postcode":"4880;45502",
    "addr:street":"Rebert Pike",
    "iso:country":"US",
    "sg:address":"4880 Rebert Pike",
    "sg:city":"Springfield",
    "sg:phone":"+1 937 322 4774",
    "sg:postcode":"45502",
    "sg:province":"OH",
    "sg:tags":[
        "farm",
        "corn",
        "soybean"
    ],
    "wof:name":"Gary Shank",
    "wof:placetype":"venue"
},
  "geometry": {"coordinates":[-83.907494,39.863866],"type":"Point"}
}