{
  "type": "Feature",
  "properties": {
    "iso:country":"US",
    "sg:address":"12155 State Rte 66",
    "sg:city":"Minster",
    "sg:classifiers":[
        {
            "category":"Building & Trades",
            "subcategory":"Landscaping Services",
            "type":"Services"
        }
    ],
    "sg:phone":"+1 419 628 2984",
    "sg:postcode":"45865",
    "sg:province":"OH",
    "sg:tags":[
        "landscape",
        "contractor"
    ],
    "wof:name":"Gehret Nursery Inc",
    "wof:placetype":"venue"
},
  "geometry": {"coordinates":[-84.376814,40.373923],"type":"Point"}
}