{
  "type": "Feature",
  "properties": {
    "addr:full":"134 Park Ave Amherst OH 44001",
    "addr:housenumber":"134",
    "addr:postcode":"44001",
    "addr:street":"Park Ave",
    "iso:country":"US",
    "sg:address":"134 Park Ave",
    "sg:city":"Amherst",
    "sg:classifiers":[
        {
            "category":"Professional",
            "type":"Services"
        },
        {
            "category":"Bars & Pubs",
            "type":"Food & Drink"
        }
    ],
    "sg:phone":"+1 440 984 3705",
    "sg:postcode":"44001",
    "sg:province":"OH",
    "sg:tags":[
        "drinking",
        "establishment"
    ],
    "wof:name":"Hank's Place",
    "wof:placetype":"venue"
},
  "geometry": {"coordinates":[-82.22551300000001,41.398286],"type":"Point"}
}