{
  "type": "Feature",
  "properties": {
    "addr:full":"137 S Main St Akron OH 44308",
    "addr:housenumber":"137",
    "addr:postcode":"44308",
    "addr:street":"S Main St",
    "iso:country":"US",
    "sg:address":"137 S Main St",
    "sg:city":"Akron",
    "sg:classifiers":[
        {
            "category":"Professional",
            "subcategory":"Lawyer & Legal Services",
            "type":"Services"
        }
    ],
    "sg:phone":"+1 330 253 7171",
    "sg:postcode":"44308",
    "sg:province":"OH",
    "sg:tags":[
        "firm",
        "attorney",
        "law"
    ],
    "wof:name":"Burdon & Merlitti",
    "wof:placetype":"venue"
},
  "geometry": {"coordinates":[-81.51882999999999,41.081202],"type":"Point"}
}