{
  "type": "Feature",
  "properties": {
    "addr:full": "133 York St Circleville OH 43113",
    "addr:housenumber": "133",
    "addr:postcode": "43113",
    "addr:street": "York St",
    "iso:country": "US",
    "sg:address": "133 York St",
    "sg:city": "Circleville",
    "sg:classifiers": [
      {
        "category": "Shopping",
        "subcategory": "Bicycles \u0026 Sporting Goods",
        "type": "Retail Goods"
      }
    ],
    "sg:phone": "+1 740 477 2409",
    "sg:postcode": "43113",
    "sg:province": "OH",
    "wof:name": "Grandpa Tims",
    "wof:placetype": "venue"
  },
  "geometry": {"coordinates":[-82.942121,39.611468],"type":"Point"}
}
