{
  "type": "Feature",
  "properties": {
    "iso:country":"US",
    "sg:address":"481 N Cleveland Massillon Rd",
    "sg:city":"Akron",
    "sg:classifiers":[
        {
            "category":"Professional",
            "subcategory":"Engineering",
            "type":"Services"
        }
    ],
    "sg:phone":"+1 330 666 3702",
    "sg:postcode":"44333",
    "sg:province":"OH",
    "sg:tags":[
        "electrical"
    ],
    "wof:name":"Peters Tschant Bandwin Inc",
    "wof:placetype":"venue"
},
  "geometry": {"coordinates":[-81.63710399999999,41.149916],"type":"Point"}
}