{
  "type": "Feature",
  "properties": {
    "addr:full":"23980 Elm Rd North Olmsted OH 44070",
    "addr:housenumber":"23980",
    "addr:postcode":"44070",
    "addr:street":"Elm Rd",
    "iso:country":"US",
    "sg:address":"23980 Elm Rd",
    "sg:city":"North Olmsted",
    "sg:classifiers":[
        {
            "category":"Real Estate",
            "subcategory":"Real Estate Agent",
            "type":"Services"
        }
    ],
    "sg:phone":"+1 440 979 1970",
    "sg:postcode":"44070",
    "sg:province":"OH",
    "sg:tags":[
        "investor"
    ],
    "wof:name":"Griffin Enterprises",
    "wof:placetype":"venue"
},
  "geometry": {"coordinates":[-81.887072,41.422327],"type":"Point"}
}