{
  "type": "Feature",
  "properties": {
    "addr:full":"1749 Grand Blvd Hamilton OH 45011",
    "addr:housenumber":"1749",
    "addr:postcode":"45011",
    "addr:street":"Grand Blvd",
    "iso:country":"US",
    "sg:address":"1749 Grand Blvd",
    "sg:city":"Hamilton",
    "sg:classifiers":[
        {
            "category":"Shopping",
            "subcategory":"Used Merchandise",
            "type":"Retail Goods"
        }
    ],
    "sg:phone":"+1 513 737 7927",
    "sg:postcode":"45011",
    "sg:province":"OH",
    "wof:name":"Grand Boulevard Swap Shop",
    "wof:placetype":"venue"
},
  "geometry": {"coordinates":[-84.545174,39.381641],"type":"Point"}
}