{
  "type": "Feature",
  "properties": {
    "addr:full": "6932 Hillside Rd Cleveland OH 44131",
    "addr:housenumber": "6932",
    "addr:postcode": "44131",
    "addr:street": "Hillside Rd",
    "iso:country": "US",
    "sg:address": "6932 Hillside Rd",
    "sg:city": "Cleveland",
    "sg:classifiers": [
      {
        "category": "Restaurant",
        "type": "Food \u0026 Drink"
      }
    ],
    "sg:phone": "+1 216 524 8101",
    "sg:postcode": "44131",
    "sg:province": "OH",
    "sg:tags": [
      "eating"
    ],
    "wof:name": "Angies Pizza Shop",
    "wof:placetype": "venue"
  },
  "geometry": {"coordinates":[-81.638252,41.369052],"type":"Point"}
}
