{
  "type": "Feature",
  "properties": {
    "iso:country":"US",
    "sg:address":"6932 Hillside Rd",
    "sg:city":"Cleveland",
    "sg:classifiers":[
        {
            "category":"Restaurant",
            "type":"Food & Drink"
        }
    ],
    "sg:phone":"+1 216 524 8101",
    "sg:postcode":"44131",
    "sg:province":"OH",
    "sg:tags":[
        "eating"
    ],
    "wof:name":"Angies Pizza Shop",
    "wof:placetype":"venue"
},
  "geometry": {"coordinates":[-81.638252,41.369052],"type":"Point"}
}