{
  "type": "Feature",
  "properties": {
    "addr:full": "5132 Delhi Ave Cincinnati OH 45238",
    "addr:housenumber": "5132",
    "addr:postcode": "45238",
    "addr:street": "Delhi Ave",
    "iso:country": "US",
    "sg:address": "5132 Delhi Ave",
    "sg:city": "Cincinnati",
    "sg:classifiers": [
      {
        "category": "Sports \u0026 Exercise",
        "subcategory": "Gym",
        "type": "Entertainment"
      }
    ],
    "sg:phone": "+1 513 347 6789",
    "sg:postcode": "45238",
    "sg:province": "OH",
    "sg:tags": [
      "club",
      "health",
      "studio",
      "gymnasium"
    ],
    "wof:name": "Curves For Women",
    "wof:placetype": "venue"
  },
  "geometry": {"coordinates":[-84.614781,39.094678],"type":"Point"}
}
