{
  "type": "Feature",
  "properties": {
    "iso:country":"US",
    "sg:address":"5132 Delhi Ave",
    "sg:city":"Cincinnati",
    "sg:classifiers":[
        {
            "category":"Sports & Exercise",
            "subcategory":"Gym",
            "type":"Entertainment"
        }
    ],
    "sg:phone":"+1 513 347 6789",
    "sg:postcode":"45238",
    "sg:province":"OH",
    "sg:tags":[
        "club",
        "health",
        "studio",
        "gymnasium"
    ],
    "wof:name":"Curves For Women",
    "wof:placetype":"venue"
},
  "geometry": {"coordinates":[-84.61478099999999,39.094678],"type":"Point"}
}