{
  "type": "Feature",
  "properties": {
    "iso:country":"US",
    "sg:address":"12030 W Co Rd 60",
    "sg:city":"Fostoria",
    "sg:classifiers":[
        {
            "category":"Railroad",
            "type":"Transportation"
        }
    ],
    "sg:phone":"+1 419 435 6686",
    "sg:postcode":"44830",
    "sg:province":"OH",
    "sg:website":"www.norfolksoutherncorp.com",
    "wof:name":"Norfolk Southern Railway Co",
    "wof:placetype":"venue"
},
  "geometry": {"coordinates":[-83.38379999999999,41.159515],"type":"Point"}
}