{
  "type": "Feature",
  "properties": {
    "addr:full": "3931 Clay St Austinburg OH 44010",
    "addr:housenumber": "3931",
    "addr:postcode": "44010",
    "addr:street": "Clay St",
    "iso:country": "US",
    "sg:address": "3931 Clay St",
    "sg:city": "Austinburg",
    "sg:classifiers": [
      {
        "category": "Building \u0026 Trades",
        "subcategory": "Construction",
        "type": "Services"
      }
    ],
    "sg:phone": "+1 440 466 1888",
    "sg:postcode": "44010",
    "sg:province": "OH",
    "sg:tags": [
      "excavation",
      "contractor"
    ],
    "wof:name": "Pyramid Concrete",
    "wof:placetype": "venue"
  },
  "geometry": {"coordinates":[-80.897545,41.782121],"type":"Point"}
}
