{
  "type": "Feature",
  "properties": {
    "iso:country":"US",
    "sg:address":"70 Pearl Dr",
    "sg:city":"Shelby",
    "sg:classifiers":[
        {
            "category":"Real Estate",
            "subcategory":"Real Estate Agent",
            "type":"Services"
        }
    ],
    "sg:phone":"+1 419 347 4024",
    "sg:postcode":"44875",
    "sg:province":"OH",
    "wof:name":"Roush Realty & Auction Inc",
    "wof:placetype":"venue"
},
  "geometry": {"coordinates":[-82.642447,40.877672],"type":"Point"}
}