{
  "type": "Feature",
  "properties": {
    "addr:full": "513 Jefferson Ave Toledo OH 43604",
    "addr:housenumber": "513",
    "addr:postcode": "43604",
    "addr:street": "Jefferson Ave",
    "iso:country": "US",
    "sg:address": "513 Jefferson Ave",
    "sg:city": "Toledo",
    "sg:classifiers": [
      {
        "category": "Bars \u0026 Pubs",
        "type": "Food \u0026 Drink"
      }
    ],
    "sg:phone": "+1 419 255 3873",
    "sg:postcode": "43604",
    "sg:province": "OH",
    "sg:tags": [
      "club",
      "night"
    ],
    "wof:name": "Fuze",
    "wof:placetype": "venue"
  },
  "geometry": {"coordinates":[-83.537861,41.650893],"type":"Point"}
}
