{
  "type": "Feature",
  "properties": {
    "addr:full": "6749 Gilmore Rd Hamilton OH 45011",
    "addr:housenumber": "6749",
    "addr:postcode": "45011",
    "addr:street": "Gilmore Rd",
    "iso:country": "US",
    "sg:address": "6749 Gilmore Rd",
    "sg:city": "Hamilton",
    "sg:classifiers": [
      {
        "category": "Manufacturing",
        "subcategory": "Printing",
        "type": "Manufacturing \u0026 Wholesale Goods"
      }
    ],
    "sg:phone": "+1 513 942 7775",
    "sg:postcode": "45011",
    "sg:province": "OH",
    "sg:tags": [
      "book"
    ],
    "wof:name": "Centre Point Learning",
    "wof:placetype": "venue"
  },
  "geometry": {"coordinates":[-84.515157,39.387348],"type":"Point"}
}
