{
  "type": "Feature",
  "properties": {
    "addr:full": "3950 Bus Park Dr Columbus OH 43204",
    "addr:postcode": "3950;43204",
    "addr:street": "Bus Park Dr",
    "iso:country": "US",
    "sg:address": "3950 Bus Park Dr",
    "sg:city": "Columbus",
    "sg:classifiers": [
      {
        "category": "Manufacturing",
        "subcategory": "Printing",
        "type": "Manufacturing \u0026 Wholesale Goods"
      }
    ],
    "sg:phone": "+1 614 351 6868",
    "sg:postcode": "43204",
    "sg:province": "OH",
    "sg:tags": [
      "lithographic",
      "general",
      "commercial",
      "warehousing"
    ],
    "wof:name": "Vectra",
    "wof:placetype": "venue"
  },
  "geometry": {"coordinates":[-83.10675,39.977262],"type":"Point"}
}
