{
  "type": "Feature",
  "properties": {
    "iso:country":"US",
    "sg:address":"6876 Center St",
    "sg:city":"Mentor",
    "sg:classifiers":[
        {
            "category":"Retail",
            "subcategory":"Auto Rental",
            "type":"Services"
        }
    ],
    "sg:phone":"+1 440 205 6950",
    "sg:postcode":"44060",
    "sg:province":"OH",
    "sg:tags":[
        "renting",
        "automobile"
    ],
    "wof:name":"Enterprise Rent A Car",
    "wof:placetype":"venue"
},
  "geometry": {"coordinates":[-81.339421,41.684881],"type":"Point"}
}