{
  "type": "Feature",
  "properties": {
    "addr:full": "322 Norlick Dr Bryan OH 43506",
    "addr:housenumber": "322",
    "addr:postcode": "43506",
    "addr:street": "Norlick Dr",
    "iso:country": "US",
    "sg:address": "322 Norlick Dr",
    "sg:city": "Bryan",
    "sg:classifiers": [
      {
        "category": "Retail",
        "subcategory": "Repair Shop",
        "type": "Services"
      }
    ],
    "sg:phone": "+1 419 636 9170",
    "sg:postcode": "43506",
    "sg:province": "OH",
    "sg:tags": [
      "appliance"
    ],
    "wof:name": "Lloyd's Appliance Svc",
    "wof:placetype": "venue"
  },
  "geometry": {"coordinates":[-84.579687,41.486871],"type":"Point"}
}
