{
  "type": "Feature",
  "properties": {
    "iso:country":"US",
    "sg:address":"21861 Lorain Rd",
    "sg:city":"Cleveland",
    "sg:classifiers":[
        {
            "category":"Personal",
            "subcategory":"Beauty Salon",
            "type":"Services"
        }
    ],
    "sg:phone":"+1 440 333 8893",
    "sg:postcode":"44126",
    "sg:province":"OH",
    "wof:name":"Best Cuts",
    "wof:placetype":"venue"
},
  "geometry": {"coordinates":[-81.861513,41.442631],"type":"Point"}
}