{
  "type": "Feature",
  "properties": {
    "addr:full":"107 Lakeview Ct Loveland OH 45140",
    "addr:housenumber":"107",
    "addr:postcode":"45140",
    "addr:street":"Lakeview Ct",
    "iso:country":"US",
    "sg:address":"107 Lakeview Ct",
    "sg:city":"Loveland",
    "sg:classifiers":[
        {
            "category":"Restaurant",
            "type":"Food & Drink"
        }
    ],
    "sg:phone":"+1 513 683 0803",
    "sg:postcode":"45140",
    "sg:province":"OH",
    "sg:tags":[
        "eating"
    ],
    "wof:name":"Rob Stansel & Assoc Inc A",
    "wof:placetype":"venue"
},
  "geometry": {"coordinates":[-84.295208,39.266196],"type":"Point"}
}