{
  "type": "Feature",
  "properties": {
    "addr:full":"244 3rd Ave Gallipolis OH 45631",
    "addr:housenumber":"244",
    "addr:postcode":"45631",
    "addr:street":"3Rd Ave",
    "iso:country":"US",
    "sg:address":"244 3rd Ave",
    "sg:city":"Gallipolis",
    "sg:classifiers":[
        {
            "category":"Shopping",
            "subcategory":"Florist",
            "type":"Retail Goods"
        }
    ],
    "sg:phone":"+1 740 446 1833",
    "sg:postcode":"45631",
    "sg:province":"OH",
    "wof:name":"Floral Fashions",
    "wof:placetype":"venue"
},
  "geometry": {"coordinates":[-82.209065,38.806927],"type":"Point"}
}