{
  "type": "Feature",
  "properties": {
    "addr:full":"50 S Rocky River Dr Berea OH 44017",
    "addr:housenumber":"50",
    "addr:postcode":"44017",
    "addr:street":"S Rocky River Dr",
    "iso:country":"US",
    "sg:address":"50 S Rocky River Dr",
    "sg:city":"Berea",
    "sg:classifiers":[
        {
            "category":"Real Estate",
            "subcategory":"Real Estate Agent",
            "type":"Services"
        }
    ],
    "sg:phone":"+1 440 234 9686",
    "sg:postcode":"44017",
    "sg:province":"OH",
    "wof:name":"Baldwin House Condo Owners",
    "wof:placetype":"venue"
},
  "geometry": {"coordinates":[-81.853869,41.365103],"type":"Point"}
}