{
  "type": "Feature",
  "properties": {
    "addr:full": "303 N Church St Edon OH 43518",
    "addr:housenumber": "303",
    "addr:postcode": "43518",
    "addr:street": "N Church St",
    "iso:country": "US",
    "sg:address": "303 N Church St",
    "sg:city": "Edon",
    "sg:classifiers": [
      {
        "category": "Personal",
        "subcategory": "Beauty Salon",
        "type": "Services"
      }
    ],
    "sg:phone": "+1 419 272 3350",
    "sg:postcode": "43518",
    "sg:province": "OH",
    "wof:name": "Marie's Beauty Salon",
    "wof:placetype": "venue"
  },
  "geometry": {"coordinates":[-84.767377,41.55838],"type":"Point"}
}
