{
  "type": "Feature",
  "properties": {
    "addr:full": "1981 S High St Columbus OH 43207",
    "addr:housenumber": "1981",
    "addr:postcode": "43207",
    "addr:street": "S High St",
    "iso:country": "US",
    "sg:address": "1981 S High St",
    "sg:city": "Columbus",
    "sg:classifiers": [
      {
        "category": "Freight",
        "type": "Transportation"
      }
    ],
    "sg:phone": "+1 740 369 0702",
    "sg:postcode": "43207",
    "sg:province": "OH",
    "sg:tags": [
      "trucking"
    ],
    "wof:name": "Burko Trucking",
    "wof:placetype": "venue"
  },
  "geometry": {"coordinates":[-82.995476,39.921129],"type":"Point"}
}
