{
  "type": "Feature",
  "properties": {
    "addr:full": "9514 Salisbury Rd Monclova OH 43542",
    "addr:housenumber": "9514",
    "addr:postcode": "43542",
    "addr:street": "Salisbury Rd",
    "iso:country": "US",
    "sg:address": "9514 Salisbury Rd",
    "sg:city": "Monclova",
    "sg:classifiers": [
      {
        "category": "Real Estate",
        "subcategory": "Real Estate Agent",
        "type": "Services"
      }
    ],
    "sg:phone": "+1 419 865 6238",
    "sg:postcode": "43542",
    "sg:province": "OH",
    "sg:tags": [
      "inspection"
    ],
    "wof:name": "Seagate Inspections Inc",
    "wof:placetype": "venue"
  },
  "geometry": {"coordinates":[-83.766868,41.580943],"type":"Point"}
}
