{
  "type": "Feature",
  "properties": {
    "addr:full": "8885 York Rd SW Pataskala OH 43062",
    "addr:housenumber": "8885",
    "addr:postcode": "43062",
    "addr:street": "York Rd Sw",
    "iso:country": "US",
    "sg:address": "8885 York Rd SW",
    "sg:city": "Pataskala",
    "sg:classifiers": [
      {
        "category": "Building \u0026 Trades",
        "subcategory": "Plumbing",
        "type": "Services"
      }
    ],
    "sg:phone": "+1 740 964 2821",
    "sg:postcode": "43062",
    "sg:province": "OH",
    "sg:tags": [
      "heating",
      "air",
      "conditioning",
      "mechanical",
      "plumbing",
      "contractor"
    ],
    "wof:name": "Wolfe Mechanical Services",
    "wof:placetype": "venue"
  },
  "geometry": {"coordinates":[-82.62668,39.962594],"type":"Point"}
}
