{
  "type": "Feature",
  "properties": {
    "iso:country":"US",
    "sg:address":"8885 York Rd SW",
    "sg:city":"Pataskala",
    "sg:classifiers":[
        {
            "category":"Building & Trades",
            "subcategory":"Plumbing",
            "type":"Services"
        }
    ],
    "sg:phone":"+1 740 964 2821",
    "sg:postcode":"43062",
    "sg:province":"OH",
    "sg:tags":[
        "heating",
        "air",
        "conditioning",
        "mechanical",
        "plumbing",
        "contractor"
    ],
    "wof:name":"Wolfe Mechanical Services",
    "wof:placetype":"venue"
},
  "geometry": {"coordinates":[-82.62667999999999,39.962594],"type":"Point"}
}