{
  "type": "Feature",
  "properties": {
    "addr:full": "23230 Chagrin Blvd Cleveland OH 44122",
    "addr:housenumber": "23230",
    "addr:postcode": "44122",
    "addr:street": "Chagrin Blvd",
    "iso:country": "US",
    "sg:address": "23230 Chagrin Blvd",
    "sg:city": "Cleveland",
    "sg:classifiers": [
      {
        "category": "Banks \u0026 Credit Unions",
        "subcategory": "Bank",
        "type": "Services"
      }
    ],
    "sg:phone": "+1 513 771 7440",
    "sg:postcode": "44122",
    "sg:province": "OH",
    "sg:tags": [
      "mortgage",
      "loan",
      "broker",
      "banker",
      "real estate"
    ],
    "wof:name": "North American Mortgage Loan",
    "wof:placetype": "venue"
  },
  "geometry": {"coordinates":[-81.5055,41.464401],"type":"Point"}
}
