{
  "type": "Feature",
  "properties": {
    "addr:full":"111 W Broadway St New Lexington OH 43764",
    "addr:housenumber":"111",
    "addr:postcode":"43764",
    "addr:street":"W Broadway St",
    "iso:country":"US",
    "sg:address":"111 W Broadway St",
    "sg:city":"New Lexington",
    "sg:classifiers":[
        {
            "category":"Food & Beverages",
            "subcategory":"Bakery",
            "type":"Retail Goods"
        }
    ],
    "sg:phone":"+1 740 342 3302",
    "sg:postcode":"43764",
    "sg:province":"OH",
    "sg:tags":[
        "baker"
    ],
    "wof:name":"Stan's Bake Shop",
    "wof:placetype":"venue"
},
  "geometry": {"coordinates":[-82.21041700000001,39.720107],"type":"Point"}
}