{
  "type": "Feature",
  "properties": {
    "addr:full": "7867 Buffham Rd Lodi OH 44254",
    "addr:housenumber": "7867",
    "addr:postcode": "44254",
    "addr:street": "Buffham Rd",
    "iso:country": "US",
    "sg:address": "7867 Buffham Rd",
    "sg:city": "Lodi",
    "sg:phone": "+1 330 948 3160",
    "sg:postcode": "44254",
    "sg:province": "OH",
    "sg:tags": [
      "farm",
      "field",
      "crop"
    ],
    "wof:name": "James Coldren Farm",
    "wof:placetype": "venue"
  },
  "geometry": {"coordinates":[-81.971606,41.041812],"type":"Point"}
}
