{
  "type": "Feature",
  "properties": {
    "iso:country":"US",
    "sg:address":"2287 State Rte 503",
    "sg:city":"Arcanum",
    "sg:classifiers":[
        {
            "category":"Farming",
            "subcategory":"Farm",
            "type":"Manufacturing & Wholesale Goods"
        }
    ],
    "sg:phone":"+1 937 692 5034",
    "sg:postcode":"45304",
    "sg:province":"OH",
    "sg:tags":[
        "crop",
        "general"
    ],
    "wof:name":"Scott Fourman",
    "wof:placetype":"venue"
},
  "geometry": {"coordinates":[-84.61009,39.9841],"type":"Point"}
}