{
  "type": "Feature",
  "properties": {
    "addr:full": "2287 State Rte 503 Arcanum OH 45304",
    "addr:housenumber": "2287",
    "addr:postcode": "45304",
    "addr:street": "State Rte 503",
    "iso:country": "US",
    "sg:address": "2287 State Rte 503",
    "sg:city": "Arcanum",
    "sg:classifiers": [
      {
        "category": "Farming",
        "subcategory": "Farm",
        "type": "Manufacturing \u0026 Wholesale Goods"
      }
    ],
    "sg:phone": "+1 937 692 5034",
    "sg:postcode": "45304",
    "sg:province": "OH",
    "sg:tags": [
      "crop",
      "general"
    ],
    "wof:name": "Scott Fourman",
    "wof:placetype": "venue"
  },
  "geometry": {"coordinates":[-84.61009,39.9841],"type":"Point"}
}
