{
  "type": "Feature",
  "properties": {
    "iso:country":"US",
    "sg:address":"609 Wood St",
    "sg:city":"Elyria",
    "sg:classifiers":[
        {
            "category":"Freight",
            "type":"Transportation"
        }
    ],
    "sg:phone":"+1 440 458 6450",
    "sg:postcode":"44035",
    "sg:province":"OH",
    "sg:tags":[
        "delivery"
    ],
    "wof:name":"J & B Deliveries",
    "wof:placetype":"venue"
},
  "geometry": {"coordinates":[-82.106449,41.342504],"type":"Point"}
}