{
  "type": "Feature",
  "properties": {
    "addr:full": "609 Wood St Elyria OH 44035",
    "addr:housenumber": "609",
    "addr:postcode": "44035",
    "addr:street": "Wood St",
    "iso:country": "US",
    "sg:address": "609 Wood St",
    "sg:city": "Elyria",
    "sg:classifiers": [
      {
        "category": "Freight",
        "type": "Transportation"
      }
    ],
    "sg:phone": "+1 440 458 6450",
    "sg:postcode": "44035",
    "sg:province": "OH",
    "sg:tags": [
      "delivery"
    ],
    "wof:name": "J \u0026 B Deliveries",
    "wof:placetype": "venue"
  },
  "geometry": {"coordinates":[-82.106449,41.342504],"type":"Point"}
}
