{
  "type": "Feature",
  "properties": {
    "addr:full":"3398 Eastwind Cir NW Canton OH 44720",
    "addr:housenumber":"3398",
    "addr:postcode":"44720",
    "addr:street":"Eastwind Cir Nw",
    "iso:country":"US",
    "sg:address":"3398 Eastwind Cir NW",
    "sg:city":"Canton",
    "sg:classifiers":[
        {
            "category":"Professional",
            "type":"Services"
        }
    ],
    "sg:phone":"+1 330 497 1855",
    "sg:postcode":"44720",
    "sg:province":"OH",
    "wof:name":"Michael A & Lisa M Lintne",
    "wof:placetype":"venue"
},
  "geometry": {"coordinates":[-81.410228,40.89781],"type":"Point"}
}