{
  "type": "Feature",
  "properties": {
    "iso:country":"US",
    "sg:address":"16 Raymond Ave",
    "sg:city":"Shelby",
    "sg:classifiers":[
        {
            "category":"Building & Trades",
            "subcategory":"Construction",
            "type":"Services"
        }
    ],
    "sg:phone":"+1 419 347 7060",
    "sg:postcode":"44875",
    "sg:province":"OH",
    "sg:tags":[
        "masonry",
        "contractor"
    ],
    "wof:name":"Stine Masonry",
    "wof:placetype":"venue"
},
  "geometry": {"coordinates":[-82.665518,40.88237],"type":"Point"}
}