{
  "type": "Feature",
  "properties": {
    "addr:full": "160 N Union St Akron OH 44304",
    "addr:housenumber": "160",
    "addr:postcode": "44304",
    "addr:street": "N Union St",
    "iso:country": "US",
    "sg:address": "160 N Union St",
    "sg:city": "Akron",
    "sg:classifiers": [
      {
        "category": "Manufacturing",
        "subcategory": "Tools \u0026 Machinery",
        "type": "Manufacturing \u0026 Wholesale Goods"
      }
    ],
    "sg:phone": "+1 330 762 7676",
    "sg:postcode": "44304",
    "sg:province": "OH",
    "sg:tags": [
      "machine",
      "shop",
      "job"
    ],
    "wof:name": "Markham Machine Co Inc",
    "wof:placetype": "venue"
  },
  "geometry": {"coordinates":[-81.504728,41.085958],"type":"Point"}
}
