{
  "type": "Feature",
  "properties": {
    "addr:full": "306 N 3rd St Toronto OH 43964",
    "addr:housenumber": "306",
    "addr:postcode": "43964",
    "addr:street": "N 3Rd St",
    "iso:country": "US",
    "sg:address": "306 N 3rd St",
    "sg:city": "Toronto",
    "sg:classifiers": [
      {
        "category": "Organizations",
        "subcategory": "Labor Organization",
        "type": "Services"
      }
    ],
    "sg:phone": "+1 740 537 2201",
    "sg:postcode": "43964",
    "sg:province": "OH",
    "wof:name": "Utility Workers Union Of America",
    "wof:placetype": "venue"
  },
  "geometry": {"coordinates":[-80.599822,40.466555],"type":"Point"}
}
