{
  "type": "Feature",
  "properties": {
    "addr:full": "4720 Mega St NW North Canton OH 44720",
    "addr:postcode": "4720;44720",
    "addr:street": "Mega St Nw",
    "iso:country": "US",
    "sg:address": "4720 Mega St NW",
    "sg:city": "North Canton",
    "sg:classifiers": [
      {
        "category": "Cinema",
        "subcategory": "Movie Theater",
        "type": "Entertainment"
      }
    ],
    "sg:phone": "+1 330 305 9888",
    "sg:postcode": "44720",
    "sg:province": "OH",
    "wof:name": "Tinseltown Canton",
    "wof:placetype": "venue"
  },
  "geometry": {"coordinates":[-81.438466,40.872429],"type":"Point"}
}
