{
  "type": "Feature",
  "properties": {
    "iso:country":"US",
    "sg:address":"4720 Mega St NW",
    "sg:city":"North Canton",
    "sg:classifiers":[
        {
            "category":"Cinema",
            "subcategory":"Movie Theater",
            "type":"Entertainment"
        }
    ],
    "sg:phone":"+1 330 305 9888",
    "sg:postcode":"44720",
    "sg:province":"OH",
    "wof:name":"Tinseltown Canton",
    "wof:placetype":"venue"
},
  "geometry": {"coordinates":[-81.43846600000001,40.872429],"type":"Point"}
}