{
  "type": "Feature",
  "properties": {
    "iso:country":"US",
    "sg:address":"110 N Columbus St",
    "sg:city":"Lancaster",
    "sg:classifiers":[
        {
            "category":"Restaurant",
            "type":"Food & Drink"
        }
    ],
    "sg:phone":"+1 740 654 3692",
    "sg:postcode":"43130",
    "sg:province":"OH",
    "sg:website":"www.anniescheesecake.com",
    "wof:name":"Annie's Cheesecake & Tea Room",
    "wof:placetype":"venue"
},
  "geometry": {"coordinates":[-82.604483,39.714314],"type":"Point"}
}