{
  "type": "Feature",
  "properties": {
    "addr:full":"970 N High St Columbus OH 43085",
    "addr:housenumber":"970",
    "addr:postcode":"43085",
    "addr:street":"N High St",
    "iso:country":"US",
    "sg:address":"970 N High St",
    "sg:city":"Columbus",
    "sg:classifiers":[
        {
            "category":"Food & Beverages",
            "subcategory":"Bakery",
            "type":"Retail Goods"
        }
    ],
    "sg:phone":"+1 614 888 4040",
    "sg:postcode":"43085",
    "sg:province":"OH",
    "sg:tags":[
        "reporting"
    ],
    "wof:name":"A Sprig of Parsley",
    "wof:placetype":"venue"
},
  "geometry": {"coordinates":[-83.017725,40.093418],"type":"Point"}
}