{
  "type": "Feature",
  "properties": {
    "addr:full": "2978 E 75th St Cleveland OH 44104",
    "addr:housenumber": "2978",
    "addr:postcode": "44104",
    "addr:street": "E 75Th St",
    "iso:country": "US",
    "sg:address": "2978 E 75th St",
    "sg:city": "Cleveland",
    "sg:classifiers": [
      {
        "category": "Building \u0026 Trades",
        "subcategory": "Construction",
        "type": "Services"
      }
    ],
    "sg:phone": "+1 216 341 8899",
    "sg:postcode": "44104",
    "sg:province": "OH",
    "sg:tags": [
      "general",
      "contractor"
    ],
    "wof:name": "LTM Construction Systems Inc",
    "wof:placetype": "venue"
  },
  "geometry": {"coordinates":[-81.636416,41.478495],"type":"Point"}
}
