{
  "type": "Feature",
  "properties": {
    "iso:country":"US",
    "sg:address":"2978 E 75th St",
    "sg:city":"Cleveland",
    "sg:classifiers":[
        {
            "category":"Building & Trades",
            "subcategory":"Construction",
            "type":"Services"
        }
    ],
    "sg:phone":"+1 216 341 8899",
    "sg:postcode":"44104",
    "sg:province":"OH",
    "sg:tags":[
        "general",
        "contractor"
    ],
    "wof:name":"LTM Construction Systems Inc",
    "wof:placetype":"venue"
},
  "geometry": {"coordinates":[-81.636416,41.478495],"type":"Point"}
}