{
  "type": "Feature",
  "properties": {
    "addr:full": "1750 Laurel Ave Columbus OH 43223",
    "addr:housenumber": "1750",
    "addr:postcode": "43223",
    "addr:street": "Laurel Ave",
    "iso:country": "US",
    "sg:address": "1750 Laurel Ave",
    "sg:city": "Columbus",
    "sg:classifiers": [
      {
        "category": "Building \u0026 Trades",
        "subcategory": "Construction",
        "type": "Services"
      }
    ],
    "sg:phone": "+1 614 276 2286",
    "sg:postcode": "43223",
    "sg:province": "OH",
    "sg:tags": [
      "demolition",
      "contractor"
    ],
    "wof:name": "Spaulding Demolition",
    "wof:placetype": "venue"
  },
  "geometry": {"coordinates":[-83.041702,39.934284],"type":"Point"}
}
