{
  "type": "Feature",
  "properties": {
    "addr:full": "1711 W Market St Akron OH 44313",
    "addr:housenumber": "1711",
    "addr:postcode": "44313",
    "addr:street": "W Market St",
    "iso:country": "US",
    "sg:address": "1711 W Market St",
    "sg:city": "Akron",
    "sg:classifiers": [
      {
        "category": "Food \u0026 Beverages",
        "subcategory": "Groceries \u0026 Convenience Stores",
        "type": "Retail Goods"
      },
      {
        "category": "Shopping",
        "subcategory": "Gifts \u0026 Souvenirs",
        "type": "Retail Goods"
      }
    ],
    "sg:phone": "+1 330 864 2151",
    "sg:postcode": "44313",
    "sg:province": "OH",
    "sg:tags": [
      "basket",
      "grocer",
      "retailer",
      "parcel"
    ],
    "sg:website": "www.westpointmarket.com",
    "wof:name": "West Point Market Inc",
    "wof:placetype": "venue"
  },
  "geometry": {"coordinates":[-81.569505,41.109744],"type":"Point"}
}
