{
  "type": "Feature",
  "properties": {
    "iso:country":"US",
    "sg:address":"790 S Troy Ave",
    "sg:city":"Cincinnati",
    "sg:classifiers":[
        {
            "category":"Professional",
            "subcategory":"Business Services",
            "type":"Services"
        }
    ],
    "sg:phone":"+1 513 772 6022",
    "sg:postcode":"45246",
    "sg:province":"OH",
    "sg:tags":[
        "building",
        "inspection"
    ],
    "wof:name":"Sta Building Conslnts Inc",
    "wof:placetype":"venue"
},
  "geometry": {"coordinates":[-84.460286,39.267479],"type":"Point"}
}