{
  "type": "Feature",
  "properties": {
    "addr:full": "5516 Stokeswood Ct Cincinnati OH 45238",
    "addr:postcode": "5516;45238",
    "addr:street": "Stokeswood Ct",
    "iso:country": "US",
    "sg:address": "5516 Stokeswood Ct",
    "sg:city": "Cincinnati",
    "sg:classifiers": [
      {
        "category": "Wholesale",
        "subcategory": "Auto Parts",
        "type": "Manufacturing \u0026 Wholesale Goods"
      }
    ],
    "sg:phone": "+1 513 922 2212",
    "sg:postcode": "45238",
    "sg:province": "OH",
    "sg:tags": [
      "automotive",
      "general",
      "tire",
      "repair"
    ],
    "wof:name": "Tc Tire Sales",
    "wof:placetype": "venue"
  },
  "geometry": {"coordinates":[-84.628372,39.115825],"type":"Point"}
}
