{
  "type": "Feature",
  "properties": {
    "iso:country":"US",
    "sg:address":"5516 Stokeswood Ct",
    "sg:city":"Cincinnati",
    "sg:classifiers":[
        {
            "category":"Wholesale",
            "subcategory":"Auto Parts",
            "type":"Manufacturing & Wholesale Goods"
        }
    ],
    "sg:phone":"+1 513 922 2212",
    "sg:postcode":"45238",
    "sg:province":"OH",
    "sg:tags":[
        "automotive",
        "general",
        "tire",
        "repair"
    ],
    "wof:name":"Tc Tire Sales",
    "wof:placetype":"venue"
},
  "geometry": {"coordinates":[-84.628372,39.115825],"type":"Point"}
}