{
  "type": "Feature",
  "properties": {
    "addr:full":"523 Wellman Ave SE Massillon OH 44646",
    "addr:housenumber":"523",
    "addr:postcode":"44646",
    "addr:street":"Wellman Ave Se",
    "iso:country":"US",
    "sg:address":"523 Wellman Ave SE",
    "sg:city":"Massillon",
    "sg:classifiers":[
        {
            "category":"Professional",
            "type":"Services"
        }
    ],
    "sg:phone":"+1 330 833 2910",
    "sg:postcode":"44646",
    "sg:province":"OH",
    "wof:name":"Robert P Eisenbrei",
    "wof:placetype":"venue"
},
  "geometry": {"coordinates":[-81.515151,40.796693],"type":"Point"}
}