{
  "type": "Feature",
  "properties": {
    "iso:country":"US",
    "sg:address":"132 Highland Dr",
    "sg:city":"Medina",
    "sg:classifiers":[
        {
            "category":"Shopping",
            "type":"Retail Goods"
        }
    ],
    "sg:phone":"+1 330 723 6679",
    "sg:postcode":"44256",
    "sg:province":"OH",
    "sg:tags":[
        "limb",
        "artificial"
    ],
    "wof:name":"Orthotic & Prosthetic Svc Inc",
    "wof:placetype":"venue"
},
  "geometry": {"coordinates":[-81.866056,41.148993],"type":"Point"}
}