{
  "type": "Feature",
  "properties": {
    "addr:full": "132 Highland Dr Medina OH 44256",
    "addr:housenumber": "132",
    "addr:postcode": "44256",
    "addr:street": "Highland Dr",
    "iso:country": "US",
    "sg:address": "132 Highland Dr",
    "sg:city": "Medina",
    "sg:classifiers": [
      {
        "category": "Shopping",
        "type": "Retail Goods"
      }
    ],
    "sg:phone": "+1 330 723 6679",
    "sg:postcode": "44256",
    "sg:province": "OH",
    "sg:tags": [
      "limb",
      "artificial"
    ],
    "wof:name": "Orthotic \u0026 Prosthetic Svc Inc",
    "wof:placetype": "venue"
  },
  "geometry": {"coordinates":[-81.866056,41.148993],"type":"Point"}
}
