{
  "type": "Feature",
  "properties": {
    "addr:full": "28461 Oak St Millbury OH 43447",
    "addr:housenumber": "28461",
    "addr:postcode": "43447",
    "addr:street": "Oak St",
    "iso:country": "US",
    "sg:address": "28461 Oak St",
    "sg:city": "Millbury",
    "sg:classifiers": [
      {
        "category": "Communications",
        "type": "Services"
      }
    ],
    "sg:phone": "+1 419 836 4066",
    "sg:postcode": "43447",
    "sg:province": "OH",
    "wof:name": "M C Cabling",
    "wof:placetype": "venue"
  },
  "geometry": {"coordinates":[-83.42371,41.565218],"type":"Point"}
}
