{
  "type": "Feature",
  "properties": {
    "iso:country":"US",
    "sg:address":"28461 Oak St",
    "sg:city":"Millbury",
    "sg:classifiers":[
        {
            "category":"Communications",
            "type":"Services"
        }
    ],
    "sg:phone":"+1 419 836 4066",
    "sg:postcode":"43447",
    "sg:province":"OH",
    "wof:name":"M C Cabling",
    "wof:placetype":"venue"
},
  "geometry": {"coordinates":[-83.42371,41.565218],"type":"Point"}
}