{
  "type": "Feature",
  "properties": {
    "addr:full":"205 S Main St Urbana OH 43078",
    "addr:housenumber":"205",
    "addr:postcode":"43078",
    "addr:street":"S Main St",
    "iso:country":"US",
    "sg:address":"205 S Main St",
    "sg:city":"Urbana",
    "sg:classifiers":[
        {
            "category":"Government",
            "subcategory":"Police Station",
            "type":"Public Place"
        }
    ],
    "sg:phone":"+1 937 652 4350",
    "sg:postcode":"43078",
    "sg:province":"OH",
    "sg:tags":[
        "department"
    ],
    "wof:name":"Urbana Police Dept",
    "wof:placetype":"venue"
},
  "geometry": {"coordinates":[-83.752551,40.10691],"type":"Point"}
}