{
  "type": "Feature",
  "properties": {
    "addr:full": "310 2nd St SW Warren OH 44483",
    "addr:housenumber": "310",
    "addr:postcode": "44483",
    "addr:street": "2Nd St Sw",
    "iso:country": "US",
    "sg:address": "310 2nd St SW",
    "sg:city": "Warren",
    "sg:classifiers": [
      {
        "category": "Building \u0026 Trades",
        "subcategory": "Construction",
        "type": "Services"
      }
    ],
    "sg:phone": "+1 330 637 5951",
    "sg:postcode": "44483",
    "sg:province": "OH",
    "sg:tags": [
      "road",
      "contractor"
    ],
    "wof:name": "Highway Dept",
    "wof:placetype": "venue"
  },
  "geometry": {"coordinates":[-80.820432,41.224735],"type":"Point"}
}
