{
  "type": "Feature",
  "properties": {
    "iso:country":"US",
    "sg:address":"340 N Main St",
    "sg:city":"Englewood",
    "sg:classifiers":[
        {
            "category":"Utilities",
            "subcategory":"Fuel Oil & Lpg",
            "type":"Services"
        }
    ],
    "sg:phone":"+1 937 836 8818",
    "sg:postcode":"45322",
    "sg:province":"OH",
    "sg:tags":[
        "firewood"
    ],
    "wof:name":"Area-Wide Svc & Landscaping",
    "wof:placetype":"venue"
},
  "geometry": {"coordinates":[-84.303555,39.883222],"type":"Point"}
}