{
  "type": "Feature",
  "properties": {
    "iso:country":"US",
    "sg:address":"17791 Sheldon Rd",
    "sg:city":"Cleveland",
    "sg:classifiers":[
        {
            "category":"Food & Beverages",
            "subcategory":"Groceries & Convenience Stores",
            "type":"Retail Goods"
        }
    ],
    "sg:phone":"+1 440 234 8328",
    "sg:postcode":"44130",
    "sg:province":"OH",
    "sg:tags":[
        "grocer"
    ],
    "wof:name":"Dairy Deli",
    "wof:placetype":"venue"
},
  "geometry": {"coordinates":[-81.822405,41.388789],"type":"Point"}
}