{
  "type": "Feature",
  "properties": {
    "addr:full": "17791 Sheldon Rd Cleveland OH 44130",
    "addr:housenumber": "17791",
    "addr:postcode": "44130",
    "addr:street": "Sheldon Rd",
    "iso:country": "US",
    "sg:address": "17791 Sheldon Rd",
    "sg:city": "Cleveland",
    "sg:classifiers": [
      {
        "category": "Food \u0026 Beverages",
        "subcategory": "Groceries \u0026 Convenience Stores",
        "type": "Retail Goods"
      }
    ],
    "sg:phone": "+1 440 234 8328",
    "sg:postcode": "44130",
    "sg:province": "OH",
    "sg:tags": [
      "grocer"
    ],
    "wof:name": "Dairy Deli",
    "wof:placetype": "venue"
  },
  "geometry": {"coordinates":[-81.822405,41.388789],"type":"Point"}
}
