{
  "type": "Feature",
  "properties": {
    "iso:country":"US",
    "sg:address":"230 E 9th St",
    "sg:city":"Cincinnati",
    "sg:classifiers":[
        {
            "category":"Organizations",
            "subcategory":"Community Association",
            "type":"Services"
        }
    ],
    "sg:phone":"+1 513 946 3300",
    "sg:postcode":"45202",
    "sg:province":"OH",
    "wof:name":"Veterans Services",
    "wof:placetype":"venue"
},
  "geometry": {"coordinates":[-84.509998,39.106068],"type":"Point"}
}