{
  "type": "Feature",
  "properties": {
    "addr:full": "9346 Towne Square Ave Cincinnati OH 45242",
    "addr:housenumber": "9346",
    "addr:postcode": "45242",
    "addr:street": "Towne Square Ave",
    "iso:country": "US",
    "sg:address": "9346 Towne Square Ave",
    "sg:city": "Cincinnati",
    "sg:classifiers": [
      {
        "category": "Health Services",
        "subcategory": "Doctor",
        "type": "Services"
      }
    ],
    "sg:phone": "+1 513 793 3535",
    "sg:postcode": "45242",
    "sg:province": "OH",
    "sg:tags": [
      "dentist"
    ],
    "wof:name": "Petricone \u0026 Pick Inc",
    "wof:placetype": "venue"
  },
  "geometry": {"coordinates":[-84.376404,39.226659],"type":"Point"}
}
