{
  "type": "Feature",
  "properties": {
    "iso:country":"US",
    "sg:address":"9346 Towne Square Ave",
    "sg:city":"Cincinnati",
    "sg:classifiers":[
        {
            "category":"Health Services",
            "subcategory":"Doctor",
            "type":"Services"
        }
    ],
    "sg:phone":"+1 513 793 3535",
    "sg:postcode":"45242",
    "sg:province":"OH",
    "sg:tags":[
        "dentist"
    ],
    "wof:name":"Petricone & Pick Inc",
    "wof:placetype":"venue"
},
  "geometry": {"coordinates":[-84.37640399999999,39.226659],"type":"Point"}
}