{
  "type": "Feature",
  "properties": {
    "addr:full":"827 Leona Ave Columbus OH 43201",
    "addr:housenumber":"827",
    "addr:postcode":"43201",
    "addr:street":"Leona Ave",
    "iso:country":"US",
    "sg:address":"827 Leona Ave",
    "sg:city":"Columbus",
    "sg:classifiers":[
        {
            "category":"Building & Trades",
            "subcategory":"Construction",
            "type":"Services"
        }
    ],
    "sg:phone":"+1 614 294 2728",
    "sg:postcode":"43201",
    "sg:province":"OH",
    "sg:tags":[
        "restoration",
        "preservation"
    ],
    "wof:name":"Brick Clean Restoration",
    "wof:placetype":"venue"
},
  "geometry": {"coordinates":[-82.98355599999999,39.989503],"type":"Point"}
}