{
  "type": "Feature",
  "properties": {
    "addr:full": "20325 Center Ridge Rd Cleveland OH 44116",
    "addr:housenumber": "20325",
    "addr:postcode": "44116",
    "addr:street": "Center Ridge Rd",
    "iso:country": "US",
    "sg:address": "20325 Center Ridge Rd",
    "sg:city": "Cleveland",
    "sg:classifiers": [
      {
        "category": "Real Estate",
        "subcategory": "Real Estate Agent",
        "type": "Services"
      },
      {
        "category": "Banks \u0026 Credit Unions",
        "subcategory": "Financial Services",
        "type": "Services"
      }
    ],
    "sg:phone": "+1 440 331 1175",
    "sg:postcode": "44116",
    "sg:province": "OH",
    "sg:tags": [
      "trust",
      "investment"
    ],
    "wof:name": "Campbell Properties Inc",
    "wof:placetype": "venue"
  },
  "geometry": {"coordinates":[-81.844165,41.464431],"type":"Point"}
}
