{
  "type": "Feature",
  "properties": {
    "addr:full": "144 Hollywood Blvd Steubenville OH 43952",
    "addr:housenumber": "144",
    "addr:postcode": "43952",
    "addr:street": "Hollywood Blvd",
    "iso:country": "US",
    "sg:address": "144 Hollywood Blvd",
    "sg:city": "Steubenville",
    "sg:classifiers": [
      {
        "category": "Shopping",
        "subcategory": "Discount \u0026 Variety Stores",
        "type": "Retail Goods"
      },
      {
        "category": "Shopping",
        "subcategory": "Department Store",
        "type": "Retail Goods"
      }
    ],
    "sg:phone": "+1 740 266 2259",
    "sg:postcode": "43952",
    "sg:province": "OH",
    "wof:name": "Dollar General",
    "wof:placetype": "venue"
  },
  "geometry": {"coordinates":[-80.641446,40.369753],"type":"Point"}
}
