{
  "type": "Feature",
  "properties": {
    "addr:full": "5381 Ferngrove Dr Dayton OH 45432",
    "addr:housenumber": "5381",
    "addr:postcode": "45432",
    "addr:street": "Ferngrove Dr",
    "iso:country": "US",
    "sg:address": "5381 Ferngrove Dr",
    "sg:city": "Dayton",
    "sg:classifiers": [
      {
        "category": "Building \u0026 Trades",
        "subcategory": "Pest Control",
        "type": "Services"
      }
    ],
    "sg:phone": "+1 937 478 8991",
    "sg:postcode": "45432",
    "sg:province": "OH",
    "wof:name": "Z-Best Pest CONTROL LLC",
    "wof:placetype": "venue"
  },
  "geometry": {"coordinates":[-84.11559,39.732378],"type":"Point"}
}
