{
  "type": "Feature",
  "properties": {
    "addr:full": "7816 Cooper Rd Cincinnati OH 45242",
    "addr:housenumber": "7816",
    "addr:postcode": "45242",
    "addr:street": "Cooper Rd",
    "iso:country": "US",
    "sg:address": "7816 Cooper Rd",
    "sg:city": "Cincinnati",
    "sg:classifiers": [
      {
        "category": "Insurance",
        "subcategory": "Insurance Agent",
        "type": "Services"
      }
    ],
    "sg:phone": "+1 513 792 9000",
    "sg:postcode": "45242",
    "sg:province": "OH",
    "wof:name": "Thomas L Matthews Insurance",
    "wof:placetype": "venue"
  },
  "geometry": {"coordinates":[-84.355235,39.226655],"type":"Point"}
}
