{
  "type": "Feature",
  "properties": {
    "addr:full":"10667 Loveland Madeira Rd Loveland OH 45140",
    "addr:housenumber":"10667",
    "addr:postcode":"45140",
    "addr:street":"Loveland Madeira Rd",
    "iso:country":"US",
    "sg:address":"10667 Loveland Madeira Rd",
    "sg:city":"Loveland",
    "sg:classifiers":[
        {
            "category":"Restaurant",
            "type":"Food & Drink"
        }
    ],
    "sg:phone":"+1 513 677 9296",
    "sg:postcode":"45140",
    "sg:province":"OH",
    "sg:tags":[
        "eating"
    ],
    "wof:name":"Dragon Wok",
    "wof:placetype":"venue"
},
  "geometry": {"coordinates":[-84.29652400000001,39.25139],"type":"Point"}
}