{
  "type": "Feature",
  "properties": {
    "iso:country":"US",
    "sg:address":"250 Benedict Ave",
    "sg:city":"Norwalk",
    "sg:classifiers":[
        {
            "category":"Organizations",
            "subcategory":"Religious Organization",
            "type":"Services"
        }
    ],
    "sg:phone":"+1 419 668 3206",
    "sg:postcode":"44857",
    "sg:province":"OH",
    "sg:tags":[
        "church"
    ],
    "sg:website":"www.norwalkcalvarybaptist.org",
    "wof:name":"Calvary Baptist Church",
    "wof:placetype":"venue"
},
  "geometry": {"coordinates":[-82.60336,41.227436],"type":"Point"}
}