{
  "type": "Feature",
  "properties": {
    "addr:full": "1422 Wilson Ave Columbus OH 43206",
    "addr:housenumber": "1422",
    "addr:postcode": "43206",
    "addr:street": "Wilson Ave",
    "iso:country": "US",
    "sg:address": "1422 Wilson Ave",
    "sg:city": "Columbus",
    "sg:classifiers": [
      {
        "category": "Building \u0026 Trades",
        "subcategory": "Construction",
        "type": "Services"
      }
    ],
    "sg:phone": "+1 614 444 2226",
    "sg:postcode": "43206",
    "sg:province": "OH",
    "sg:tags": [
      "carpentry",
      "contractor"
    ],
    "wof:name": "Gregory A Leibrand",
    "wof:placetype": "venue"
  },
  "geometry": {"coordinates":[-82.968335,39.935183],"type":"Point"}
}
