{
  "type": "Feature",
  "properties": {
    "iso:country":"US",
    "sg:address":"618 Mount Moriah Dr",
    "sg:city":"Cincinnati",
    "sg:classifiers":[
        {
            "category":"Real Estate",
            "subcategory":"Architect",
            "type":"Services"
        }
    ],
    "sg:phone":"+1 513 752 6106",
    "sg:postcode":"45245",
    "sg:province":"OH",
    "wof:name":"Mc Clorey & Savage Architects",
    "wof:placetype":"venue"
},
  "geometry": {"coordinates":[-84.293648,39.068176],"type":"Point"}
}