{
  "type": "Feature",
  "properties": {
    "iso:country":"US",
    "sg:address":"1901 Covington Ave",
    "sg:city":"Piqua",
    "sg:classifiers":[
        {
            "category":"Manufacturing",
            "subcategory":"Pottery",
            "type":"Manufacturing & Wholesale Goods"
        }
    ],
    "sg:phone":"+1 937 615 9458",
    "sg:postcode":"45356",
    "sg:province":"OH",
    "sg:tags":[
        "product",
        "mfg"
    ],
    "wof:name":"A&A Glass Engraving",
    "wof:placetype":"venue"
},
  "geometry": {"coordinates":[-84.269668,40.140764],"type":"Point"}
}