{
  "type": "Feature",
  "properties": {
    "addr:full": "1901 Covington Ave Piqua OH 45356",
    "addr:housenumber": "1901",
    "addr:postcode": "45356",
    "addr:street": "Covington Ave",
    "iso:country": "US",
    "sg:address": "1901 Covington Ave",
    "sg:city": "Piqua",
    "sg:classifiers": [
      {
        "category": "Manufacturing",
        "subcategory": "Pottery",
        "type": "Manufacturing \u0026 Wholesale Goods"
      }
    ],
    "sg:phone": "+1 937 615 9458",
    "sg:postcode": "45356",
    "sg:province": "OH",
    "sg:tags": [
      "product",
      "mfg"
    ],
    "wof:name": "A\u0026A Glass Engraving",
    "wof:placetype": "venue"
  },
  "geometry": {"coordinates":[-84.269668,40.140764],"type":"Point"}
}
