{
  "type": "Feature",
  "properties": {
    "iso:country":"US",
    "sg:address":"170 W High Ave",
    "sg:city":"New Philadelphia",
    "sg:classifiers":[
        {
            "category":"Professional",
            "subcategory":"Computer Services",
            "type":"Services"
        }
    ],
    "sg:phone":"+1 330 343 5753",
    "sg:postcode":"44663",
    "sg:province":"OH",
    "sg:tags":[
        "developer"
    ],
    "wof:name":"Artos Systems Inc",
    "wof:placetype":"venue"
},
  "geometry": {"coordinates":[-81.448853,40.490071],"type":"Point"}
}