{
  "type": "Feature",
  "properties": {
    "iso:country":"US",
    "sg:address":"122 Poland Rd",
    "sg:city":"New Springfield",
    "sg:classifiers":[
        {
            "category":"Professional",
            "type":"Services"
        }
    ],
    "sg:phone":"+1 330 426 9149",
    "sg:postcode":"44443",
    "sg:province":"OH",
    "wof:name":"Kevin Roush",
    "wof:placetype":"venue"
},
  "geometry": {"coordinates":[-80.575198,40.895051],"type":"Point"}
}