{
  "type": "Feature",
  "properties": {
    "iso:country":"US",
    "sg:address":"755 Boardman Canfield Rd",
    "sg:city":"Youngstown",
    "sg:classifiers":[
        {
            "category":"Banks & Credit Unions",
            "subcategory":"Bank",
            "type":"Services"
        }
    ],
    "sg:phone":"+1 330 965 2290",
    "sg:postcode":"44512",
    "sg:province":"OH",
    "sg:tags":[
        "escrow"
    ],
    "sg:website":"www.commonwealthyng.com",
    "wof:name":"Land America Commonwealth",
    "wof:placetype":"venue"
},
  "geometry": {"coordinates":[-80.68386,41.024436],"type":"Point"}
}