{
  "type": "Feature",
  "properties": {
    "iso:country":"US",
    "sg:address":"555 Bacon Ave",
    "sg:city":"East Palestine",
    "sg:classifiers":[
        {
            "category":"Museum",
            "type":"Entertainment"
        }
    ],
    "sg:phone":"+1 330 426 9094",
    "sg:postcode":"44413",
    "sg:province":"OH",
    "wof:name":"East Palestine Area Hstrcl Soc",
    "wof:placetype":"venue"
},
  "geometry": {"coordinates":[-80.547274,40.832723],"type":"Point"}
}