{
  "type": "Feature",
  "properties": {
    "addr:full": "18607 Vermont St Grafton OH 44044",
    "addr:housenumber": "18607",
    "addr:postcode": "44044",
    "addr:street": "Vermont St",
    "iso:country": "US",
    "sg:address": "18607 Vermont St",
    "sg:city": "Grafton",
    "sg:classifiers": [
      {
        "category": "Travel",
        "subcategory": "Travel Agent",
        "type": "Entertainment"
      }
    ],
    "sg:phone": "+1 440 355 5564",
    "sg:postcode": "44044",
    "sg:province": "OH",
    "sg:tags": [
      "tours",
      "promoter"
    ],
    "wof:name": "Vanguard Tours Inclusive",
    "wof:placetype": "venue"
  },
  "geometry": {"coordinates":[-82.077266,41.209777],"type":"Point"}
}
