{
  "type": "Feature",
  "properties": {
    "iso:country":"US",
    "sg:address":"1120 Pearl Rd",
    "sg:city":"Brunswick",
    "sg:classifiers":[
        {
            "category":"Restaurant",
            "type":"Food & Drink"
        }
    ],
    "sg:menulink":"http://www.allmenus.com/oh/brunswick/238970-china-king-restaurant/menu/",
    "sg:phone":"+1 330 225 7911",
    "sg:postcode":"44212",
    "sg:province":"OH",
    "sg:tags":[
        "asian",
        "chinese"
    ],
    "wof:name":"China King Restaurant",
    "wof:placetype":"venue"
},
  "geometry": {"coordinates":[-81.84125299999999,41.245077],"type":"Point"}
}