{
  "type": "Feature",
  "properties": {
    "addr:full": "1406 Danbury Rd NW Canton OH 44720",
    "addr:housenumber": "1406",
    "addr:postcode": "44720",
    "addr:street": "Danbury Rd Nw",
    "iso:country": "US",
    "sg:address": "1406 Danbury Rd NW",
    "sg:city": "Canton",
    "sg:classifiers": [
      {
        "category": "Manufacturing",
        "subcategory": "Chemicals \u0026 Compounds",
        "type": "Manufacturing \u0026 Wholesale Goods"
      }
    ],
    "sg:phone": "+1 330 497 4741",
    "sg:postcode": "44720",
    "sg:province": "OH",
    "sg:tags": [
      "pharmaceutical",
      "prep",
      "mfg"
    ],
    "wof:name": "Gingi-Pak",
    "wof:placetype": "venue"
  },
  "geometry": {"coordinates":[-81.370782,40.890926],"type":"Point"}
}
