{
  "type": "Feature",
  "properties": {
    "iso:country":"US",
    "sg:address":"1406 Danbury Rd NW",
    "sg:city":"Canton",
    "sg:classifiers":[
        {
            "category":"Manufacturing",
            "subcategory":"Chemicals & Compounds",
            "type":"Manufacturing & Wholesale Goods"
        }
    ],
    "sg:phone":"+1 330 497 4741",
    "sg:postcode":"44720",
    "sg:province":"OH",
    "sg:tags":[
        "pharmaceutical",
        "prep",
        "mfg"
    ],
    "wof:name":"Gingi-Pak",
    "wof:placetype":"venue"
},
  "geometry": {"coordinates":[-81.370782,40.890926],"type":"Point"}
}