{
  "type": "Feature",
  "properties": {
    "addr:full": "3573 Old Airport Rd Wooster OH 44691",
    "addr:housenumber": "3573",
    "addr:postcode": "44691",
    "addr:street": "Old Airport Rd",
    "iso:country": "US",
    "sg:address": "3573 Old Airport Rd",
    "sg:city": "Wooster",
    "sg:classifiers": [
      {
        "category": "Retail",
        "subcategory": "Auto Repair",
        "type": "Services"
      }
    ],
    "sg:phone": "+1 330 263 4005",
    "sg:postcode": "44691",
    "sg:province": "OH",
    "sg:tags": [
      "truck"
    ],
    "wof:name": "KIRK National Lease",
    "wof:placetype": "venue"
  },
  "geometry": {"coordinates":[-81.910308,40.839554],"type":"Point"}
}
