{
  "type": "Feature",
  "properties": {
    "iso:country":"US",
    "sg:address":"7101 State Rte 66",
    "sg:city":"Fort Loramie",
    "sg:classifiers":[
        {
            "category":"Arts & Performance",
            "subcategory":"Theater",
            "type":"Entertainment"
        },
        {
            "category":"Travel",
            "subcategory":"Campground",
            "type":"Entertainment"
        }
    ],
    "sg:phone":"+1 937 295 3000",
    "sg:postcode":"45845",
    "sg:province":"OH",
    "sg:tags":[
        "entertainer",
        "trailer",
        "family"
    ],
    "sg:website":"www.countryconcert.com",
    "wof:name":"Country Concert At Hickory",
    "wof:placetype":"venue"
},
  "geometry": {"coordinates":[-84.36888399999999,40.300907],"type":"Point"}
}