{
  "type": "Feature",
  "properties": {
    "addr:full": "2145 Whittaker Dr Fremont OH 43420",
    "addr:housenumber": "2145",
    "addr:postcode": "43420",
    "addr:street": "Whittaker Dr",
    "iso:country": "US",
    "sg:address": "2145 Whittaker Dr",
    "sg:city": "Fremont",
    "sg:classifiers": [
      {
        "category": "Wholesale",
        "subcategory": "Scrap",
        "type": "Manufacturing \u0026 Wholesale Goods"
      }
    ],
    "sg:phone": "+1 419 334 7286",
    "sg:postcode": "43420",
    "sg:province": "OH",
    "sg:tags": [
      "recycling",
      "center"
    ],
    "wof:name": "ACD Recycling",
    "wof:placetype": "venue"
  },
  "geometry": {"coordinates":[-83.098122,41.382813],"type":"Point"}
}
