{
  "type": "Feature",
  "properties": {
    "iso:country":"US",
    "sg:address":"1430 S Main St",
    "sg:city":"Akron",
    "sg:classifiers":[
        {
            "category":"Retail",
            "subcategory":"Auto Repair",
            "type":"Services"
        }
    ],
    "sg:phone":"+1 330 724 3995",
    "sg:postcode":"44301",
    "sg:province":"OH",
    "sg:tags":[
        "muffler",
        "exhaust",
        "system"
    ],
    "wof:name":"Main Street Muffler",
    "wof:placetype":"venue"
},
  "geometry": {"coordinates":[-81.527621,41.047715],"type":"Point"}
}