{
  "type": "Feature",
  "properties": {
    "addr:full": "1430 S Main St Akron OH 44301",
    "addr:housenumber": "1430",
    "addr:postcode": "44301",
    "addr:street": "S Main St",
    "iso:country": "US",
    "sg:address": "1430 S Main St",
    "sg:city": "Akron",
    "sg:classifiers": [
      {
        "category": "Retail",
        "subcategory": "Auto Repair",
        "type": "Services"
      }
    ],
    "sg:phone": "+1 330 724 3995",
    "sg:postcode": "44301",
    "sg:province": "OH",
    "sg:tags": [
      "muffler",
      "exhaust",
      "system"
    ],
    "wof:name": "Main Street Muffler",
    "wof:placetype": "venue"
  },
  "geometry": {"coordinates":[-81.527621,41.047715],"type":"Point"}
}
