{
  "type": "Feature",
  "properties": {
    "addr:full": "41 N Perry St Vandalia OH 45377",
    "addr:housenumber": "41",
    "addr:postcode": "45377",
    "addr:street": "N Perry St",
    "iso:country": "US",
    "sg:address": "41 N Perry St",
    "sg:city": "Vandalia",
    "sg:classifiers": [
      {
        "category": "Government",
        "subcategory": "Court House",
        "type": "Public Place"
      }
    ],
    "sg:phone": "+1 937 225 4432",
    "sg:postcode": "45377",
    "sg:province": "OH",
    "sg:tags": [
      "county"
    ],
    "wof:name": "Montgomery Common Pleas Court",
    "wof:placetype": "venue"
  },
  "geometry": {"coordinates":[-84.197522,39.892061],"type":"Point"}
}
