{
  "type": "Feature",
  "properties": {
    "addr:full":"5200 Market St Youngstown OH 44512",
    "addr:housenumber":"5200",
    "addr:postcode":"44512",
    "addr:street":"Market St",
    "iso:country":"US",
    "sg:address":"5200 Market St",
    "sg:city":"Youngstown",
    "sg:classifiers":[
        {
            "category":"Professional",
            "subcategory":"Accounting & Tax Preparation",
            "type":"Services"
        }
    ],
    "sg:phone":"+1 330 788 1095",
    "sg:postcode":"44512",
    "sg:province":"OH",
    "sg:tags":[
        "return",
        "filing"
    ],
    "sg:website":"www.libertytax.com",
    "wof:name":"Liberty Tax Svc",
    "wof:placetype":"venue"
},
  "geometry": {"coordinates":[-80.662778,41.045532],"type":"Point"}
}