{
  "type": "Feature",
  "properties": {
    "iso:country":"US",
    "sg:address":"38851 State Rte 26",
    "sg:city":"Graysville",
    "sg:classifiers":[
        {
            "category":"Government",
            "subcategory":"Fire Station",
            "type":"Public Place"
        }
    ],
    "sg:phone":"+1 740 934 2510",
    "sg:postcode":"45734",
    "sg:province":"OH",
    "sg:tags":[
        "department",
        "volunteer"
    ],
    "wof:name":"Graysville & Community Volunte",
    "wof:placetype":"venue"
},
  "geometry": {"coordinates":[-81.176146,39.66145],"type":"Point"}
}