{
  "type": "Feature",
  "properties": {
    "addr:full": "878 E 152nd St Cleveland OH 44110",
    "addr:housenumber": "878",
    "addr:postcode": "44110",
    "addr:street": "E 152Nd St",
    "iso:country": "US",
    "sg:address": "878 E 152nd St",
    "sg:city": "Cleveland",
    "sg:classifiers": [
      {
        "category": "Manufacturing",
        "subcategory": "Building Materials",
        "type": "Manufacturing \u0026 Wholesale Goods"
      },
      {
        "category": "Building \u0026 Trades",
        "subcategory": "Construction",
        "type": "Services"
      }
    ],
    "sg:phone": "+1 216 531 4295",
    "sg:postcode": "44110",
    "sg:province": "OH",
    "sg:tags": [
      "cabinet",
      "kitchen",
      "door",
      "refinishing",
      "mfg"
    ],
    "wof:name": "Eagle Custom Doors Inc",
    "wof:placetype": "venue"
  },
  "geometry": {"coordinates":[-81.57544,41.553275],"type":"Point"}
}
