{
  "type": "Feature",
  "properties": {
    "addr:full": "3384 W 119th St Cleveland OH 44111",
    "addr:housenumber": "3384",
    "addr:postcode": "44111",
    "addr:street": "W 119Th St",
    "iso:country": "US",
    "sg:address": "3384 W 119th St",
    "sg:city": "Cleveland",
    "sg:classifiers": [
      {
        "category": "Organizations",
        "subcategory": "Religious Organization",
        "type": "Services"
      }
    ],
    "sg:phone": "+1 216 671 8208",
    "sg:postcode": "44111",
    "sg:province": "OH",
    "sg:tags": [
      "church"
    ],
    "wof:name": "International Christian Church",
    "wof:placetype": "venue"
  },
  "geometry": {"coordinates":[-81.770956,41.459436],"type":"Point"}
}
