{
  "type": "Feature",
  "properties": {
    "iso:country":"US",
    "sg:address":"6415 Westfall Rd",
    "sg:city":"Frankfort",
    "sg:classifiers":[
        {
            "category":"Farming",
            "subcategory":"Farm",
            "type":"Manufacturing & Wholesale Goods"
        }
    ],
    "sg:phone":"+1 740 998 4679",
    "sg:postcode":"45628",
    "sg:province":"OH",
    "sg:tags":[
        "crop",
        "general"
    ],
    "wof:name":"Edwan Kruger and Sons",
    "wof:placetype":"venue"
},
  "geometry": {"coordinates":[-83.206413,39.390474],"type":"Point"}
}