{
  "type": "Feature",
  "properties": {
    "iso:country":"US",
    "sg:address":"2722 Oakwood Dr",
    "sg:city":"Cuyahoga Falls",
    "sg:classifiers":[
        {
            "category":"Building & Trades",
            "subcategory":"Construction",
            "type":"Services"
        }
    ],
    "sg:phone":"+1 330 923 4794",
    "sg:postcode":"44221",
    "sg:province":"OH",
    "sg:tags":[
        "contractor"
    ],
    "wof:name":"Bivens Plastering & Dry Wall",
    "wof:placetype":"venue"
},
  "geometry": {"coordinates":[-81.487696,41.146697],"type":"Point"}
}