{
  "type": "Feature",
  "properties": {
    "addr:full":"3083 Columbus St Grove City OH 43123",
    "addr:housenumber":"3083",
    "addr:postcode":"43123",
    "addr:street":"Columbus St",
    "iso:country":"US",
    "sg:address":"3083 Columbus St",
    "sg:city":"Grove City",
    "sg:classifiers":[
        {
            "category":"Insurance",
            "subcategory":"Insurance Agent",
            "type":"Services"
        }
    ],
    "sg:phone":"+1 614 871 1200",
    "sg:postcode":"43123",
    "sg:province":"OH",
    "wof:name":"Morley-Parren-Bright Ins",
    "wof:placetype":"venue"
},
  "geometry": {"coordinates":[-83.085353,39.881614],"type":"Point"}
}