{
  "type": "Feature",
  "properties": {
    "addr:full":"1081 Chestnut Grove Rd Jackson OH 45640",
    "addr:housenumber":"1081",
    "addr:postcode":"45640",
    "addr:street":"Chestnut Grove Rd",
    "iso:country":"US",
    "sg:address":"1081 Chestnut Grove Rd",
    "sg:city":"Jackson",
    "sg:classifiers":[
        {
            "category":"Building & Trades",
            "subcategory":"Plumbing",
            "type":"Services"
        }
    ],
    "sg:phone":"+1 740 286 4094",
    "sg:postcode":"45640",
    "sg:province":"OH",
    "sg:tags":[
        "plumbing",
        "contractor"
    ],
    "wof:name":"John's Plumbing",
    "wof:placetype":"venue"
},
  "geometry": {"coordinates":[-82.659463,39.005643],"type":"Point"}
}