{
  "type": "Feature",
  "properties": {
    "iso:country":"US",
    "sg:address":"10 Willettsville Pike",
    "sg:city":"Hillsboro",
    "sg:classifiers":[
        {
            "category":"Education",
            "subcategory":"Library",
            "type":"Public Place"
        }
    ],
    "sg:phone":"+1 937 393 3114",
    "sg:postcode":"45133",
    "sg:province":"OH",
    "wof:name":"Highland County District Lib",
    "wof:placetype":"venue"
},
  "geometry": {"coordinates":[-83.627651,39.208309],"type":"Point"}
}