{
  "type": "Feature",
  "properties": {
    "addr:full":"23715 Mercantile Rd Cleveland OH 44122",
    "addr:postcode":"23715;44122",
    "addr:street":"Mercantile Rd",
    "iso:country":"US",
    "sg:address":"23715 Mercantile Rd",
    "sg:city":"Cleveland",
    "sg:classifiers":[
        {
            "category":"Professional",
            "subcategory":"Employment Agencies",
            "type":"Services"
        }
    ],
    "sg:phone":"+1 216 288 8062",
    "sg:postcode":"44122",
    "sg:province":"OH",
    "sg:tags":[
        "help",
        "contractor"
    ],
    "wof:name":"Complete Party Help",
    "wof:placetype":"venue"
},
  "geometry": {"coordinates":[-81.513232,41.45871],"type":"Point"}
}