{
  "type": "Feature",
  "properties": {
    "addr:full":"1198 Rombach Ave Wilmington OH 45177",
    "addr:housenumber":"1198",
    "addr:postcode":"45177",
    "addr:street":"Rombach Ave",
    "iso:country":"US",
    "sg:address":"1198 Rombach Ave",
    "sg:city":"Wilmington",
    "sg:classifiers":[
        {
            "category":"Restaurant",
            "type":"Food & Drink"
        }
    ],
    "sg:menulink":"http://www.allmenus.com/oh/wilmington/194892-mcdonalds/menu/",
    "sg:postcode":"45177",
    "sg:province":"OH",
    "sg:tags":[
        "burger",
        "american"
    ],
    "wof:name":"McDonald's",
    "wof:placetype":"venue"
},
  "geometry": {"coordinates":[-83.810064,39.447665],"type":"Point"}
}