{
  "type": "Feature",
  "properties": {
    "addr:full":"119 Laird Ave NE Warren OH 44483",
    "addr:housenumber":"119",
    "addr:postcode":"44483",
    "addr:street":"Laird Ave Ne",
    "iso:country":"US",
    "sg:address":"119 Laird Ave NE",
    "sg:city":"Warren",
    "sg:classifiers":[
        {
            "category":"Organizations",
            "subcategory":"Religious Organization",
            "type":"Services"
        }
    ],
    "sg:phone":"+1 330 392 6365",
    "sg:postcode":"44483",
    "sg:province":"OH",
    "sg:tags":[
        "church"
    ],
    "wof:name":"Calvary Presbyterian Church",
    "wof:placetype":"venue"
},
  "geometry": {"coordinates":[-80.800742,41.237619],"type":"Point"}
}