{
  "type": "Feature",
  "properties": {
    "iso:country":"US",
    "sg:address":"606 W Wyoming Ave",
    "sg:city":"Cincinnati",
    "sg:classifiers":[
        {
            "category":"Shopping",
            "subcategory":"Clothing, Apparel, & Fashions",
            "type":"Retail Goods"
        }
    ],
    "sg:phone":"+1 513 521 6600",
    "sg:postcode":"45215",
    "sg:province":"OH",
    "wof:name":"S B Fashion Shop",
    "wof:placetype":"venue"
},
  "geometry": {"coordinates":[-84.46189,39.227271],"type":"Point"}
}