{
  "type": "Feature",
  "properties": {
    "addr:full": "9176 West Rd Cleves OH 45002",
    "addr:housenumber": "9176",
    "addr:postcode": "45002",
    "addr:street": "West Rd",
    "iso:country": "US",
    "sg:address": "9176 West Rd",
    "sg:city": "Cleves",
    "sg:classifiers": [
      {
        "category": "Building \u0026 Trades",
        "subcategory": "Landscaping Services",
        "type": "Services"
      }
    ],
    "sg:phone": "+1 513 353 2445",
    "sg:postcode": "45002",
    "sg:province": "OH",
    "wof:name": "Tuff Turf Lawn Care",
    "wof:placetype": "venue"
  },
  "geometry": {"coordinates":[-84.749147,39.233319],"type":"Point"}
}
