{
  "type": "Feature",
  "properties": {
    "iso:country":"US",
    "sg:address":"2345 E 83rd St",
    "sg:city":"Cleveland",
    "sg:classifiers":[
        {
            "category":"Education",
            "subcategory":"School",
            "type":"Public Place"
        }
    ],
    "sg:phone":"+1 216 881 6250",
    "sg:postcode":"44104",
    "sg:province":"OH",
    "sg:tags":[
        "religious"
    ],
    "wof:name":"St Adalbert Church School",
    "wof:placetype":"venue"
},
  "geometry": {"coordinates":[-81.629536,41.494911],"type":"Point"}
}