{
  "type": "Feature",
  "properties": {
    "iso:country":"US",
    "sg:address":"3535 Johnny Appleseed Ct",
    "sg:city":"Columbus",
    "sg:classifiers":[
        {
            "category":"Building & Trades",
            "subcategory":"Construction",
            "type":"Services"
        }
    ],
    "sg:phone":"+1 614 895 3535",
    "sg:postcode":"43231",
    "sg:province":"OH",
    "sg:tags":[
        "tile",
        "dealer"
    ],
    "wof:name":"Ardit Co",
    "wof:placetype":"venue"
},
  "geometry": {"coordinates":[-82.925988,40.077189],"type":"Point"}
}