{
  "type": "Feature",
  "properties": {
    "iso:country":"US",
    "sg:address":"105 W Main St",
    "sg:city":"Somerset",
    "sg:classifiers":[
        {
            "category":"Professional",
            "subcategory":"Business Services",
            "type":"Services"
        }
    ],
    "sg:phone":"+1 740 342 0853",
    "sg:postcode":"43783",
    "sg:province":"OH",
    "sg:tags":[
        "event"
    ],
    "wof:name":"HFP Racing",
    "wof:placetype":"venue"
},
  "geometry": {"coordinates":[-82.299763,39.806807],"type":"Point"}
}