{
  "type": "Feature",
  "properties": {
    "addr:full": "1049 Dana Ave Cincinnati OH 45229",
    "addr:housenumber": "1049",
    "addr:postcode": "45229",
    "addr:street": "Dana Ave",
    "iso:country": "US",
    "sg:address": "1049 Dana Ave",
    "sg:city": "Cincinnati",
    "sg:classifiers": [
      {
        "category": "Real Estate",
        "subcategory": "Real Estate Operator",
        "type": "Services"
      }
    ],
    "sg:phone": "+1 513 961 2169",
    "sg:postcode": "45229",
    "sg:province": "OH",
    "sg:tags": [
      "building",
      "nonresidential"
    ],
    "wof:name": "Shopping In A Breeze",
    "wof:placetype": "venue"
  },
  "geometry": {"coordinates":[-84.479134,39.147424],"type":"Point"}
}
