{
  "type": "Feature",
  "properties": {
    "addr:full": "45 Pleasant Dr Chagrin Falls OH 44022",
    "addr:housenumber": "45",
    "addr:postcode": "44022",
    "addr:street": "Pleasant Dr",
    "iso:country": "US",
    "sg:address": "45 Pleasant Dr",
    "sg:city": "Chagrin Falls",
    "sg:classifiers": [
      {
        "category": "Building \u0026 Trades",
        "subcategory": "Construction",
        "type": "Services"
      }
    ],
    "sg:phone": "+1 440 247 4991",
    "sg:postcode": "44022",
    "sg:province": "OH",
    "sg:tags": [
      "home",
      "builder"
    ],
    "wof:name": "Main Street Holdings LLC",
    "wof:placetype": "venue"
  },
  "geometry": {"coordinates":[-81.390996,41.430939],"type":"Point"}
}
