{
  "type": "Feature",
  "properties": {
    "addr:full":"10101 Alliance Rd Cincinnati OH 45242",
    "addr:housenumber":"10101",
    "addr:postcode":"45242",
    "addr:street":"Alliance Rd",
    "iso:country":"US",
    "sg:address":"10101 Alliance Rd",
    "sg:city":"Cincinnati",
    "sg:classifiers":[
        {
            "category":"Professional",
            "subcategory":"Lawyer & Legal Services",
            "type":"Services"
        }
    ],
    "sg:phone":"+1 513 322 6820",
    "sg:postcode":"45242",
    "sg:province":"OH",
    "sg:tags":[
        "attorney"
    ],
    "wof:name":"Martin & Wharton Law LLP",
    "wof:placetype":"venue"
},
  "geometry": {"coordinates":[-84.38159899999999,39.239823],"type":"Point"}
}