{
  "type": "Feature",
  "properties": {
    "iso:country":"US",
    "sg:address":"5840 Rockport Ln",
    "sg:city":"Cleveland",
    "sg:classifiers":[
        {
            "category":"Freight",
            "type":"Transportation"
        }
    ],
    "sg:phone":"+1 440 686 0498",
    "sg:postcode":"44126",
    "sg:province":"OH",
    "sg:tags":[
        "mover"
    ],
    "wof:name":"Bogdan Moving Systems",
    "wof:placetype":"venue"
},
  "geometry": {"coordinates":[-81.86201699999999,41.422939],"type":"Point"}
}