{
  "type": "Feature",
  "properties": {
    "iso:country":"US",
    "sg:address":"1020 W 1st St",
    "sg:city":"Uhrichsville",
    "sg:classifiers":[
        {
            "category":"Building & Trades",
            "subcategory":"Plumbing",
            "type":"Services"
        }
    ],
    "sg:phone":"+1 740 922 4843",
    "sg:postcode":"44683",
    "sg:province":"OH",
    "sg:tags":[
        "contractor"
    ],
    "wof:name":"Reichman Plumbing",
    "wof:placetype":"venue"
},
  "geometry": {"coordinates":[-81.358636,40.39236],"type":"Point"}
}