{
  "type": "Feature",
  "properties": {
    "iso:country":"US",
    "sg:address":"2341 Old Springfield Rd",
    "sg:city":"Vandalia",
    "sg:classifiers":[
        {
            "category":"Retail",
            "subcategory":"Veterinary Services",
            "type":"Services"
        }
    ],
    "sg:phone":"+1 937 264 0382",
    "sg:postcode":"45377",
    "sg:province":"OH",
    "wof:name":"Susan M Goss Dvm",
    "wof:placetype":"venue"
},
  "geometry": {"coordinates":[-84.247507,39.91049],"type":"Point"}
}