{
  "type": "Feature",
  "properties": {
    "addr:full": "1980 N High St  Columbus OH 43201",
    "addr:housenumber": "1980",
    "addr:postcode": "43201",
    "addr:street": "N High St",
    "iso:country": "US",
    "sg:address": "1980 N High St ",
    "sg:city": "Columbus",
    "sg:classifiers": [
      {
        "category": "Restaurant",
        "type": "Food \u0026 Drink"
      }
    ],
    "sg:menulink": "http://www.allmenus.com/oh/columbus/293191-penn-station-east-coast-subs/menu/",
    "sg:phone": "+1 614 586 1491",
    "sg:postcode": "43201",
    "sg:province": "OH",
    "sg:tags": [
      "sandwich"
    ],
    "wof:name": "Penn Station East Coast Subs",
    "wof:placetype": "venue"
  },
  "geometry": {"coordinates":[-83.008431,40.002771],"type":"Point"}
}
