{
  "type": "Feature",
  "properties": {
    "addr:full":"865 Bassett Rd Cleveland OH 44145",
    "addr:housenumber":"865",
    "addr:postcode":"44145",
    "addr:street":"Bassett Rd",
    "iso:country":"US",
    "sg:address":"865 Bassett Rd",
    "sg:city":"Cleveland",
    "sg:classifiers":[
        {
            "category":"Banks & Credit Unions",
            "subcategory":"Bank",
            "type":"Services"
        }
    ],
    "sg:phone":"+1 440 835 3230",
    "sg:postcode":"44145",
    "sg:province":"OH",
    "sg:tags":[
        "financing"
    ],
    "wof:name":"United Consumer Financial Svc",
    "wof:placetype":"venue"
},
  "geometry": {"coordinates":[-81.94852899999999,41.476176],"type":"Point"}
}