{
  "type": "Feature",
  "properties": {
    "iso:country":"US",
    "sg:address":"2118 Jade St",
    "sg:city":"Grove City",
    "sg:classifiers":[
        {
            "category":"Restaurant",
            "type":"Food & Drink"
        }
    ],
    "sg:phone":"+1 614 871 6204",
    "sg:postcode":"43123",
    "sg:province":"OH",
    "sg:tags":[
        "eating"
    ],
    "wof:name":"Crimson & Clover",
    "wof:placetype":"venue"
},
  "geometry": {"coordinates":[-83.062651,39.910315],"type":"Point"}
}