{
  "type": "Feature",
  "properties": {
    "addr:full": "2118 Jade St Grove City OH 43123",
    "addr:housenumber": "2118",
    "addr:postcode": "43123",
    "addr:street": "Jade St",
    "iso:country": "US",
    "sg:address": "2118 Jade St",
    "sg:city": "Grove City",
    "sg:classifiers": [
      {
        "category": "Restaurant",
        "type": "Food \u0026 Drink"
      }
    ],
    "sg:phone": "+1 614 871 6204",
    "sg:postcode": "43123",
    "sg:province": "OH",
    "sg:tags": [
      "eating"
    ],
    "wof:name": "Crimson \u0026 Clover",
    "wof:placetype": "venue"
  },
  "geometry": {"coordinates":[-83.062651,39.910315],"type":"Point"}
}
