{
  "type": "Feature",
  "properties": {
    "addr:full":"1010 W Main St Sharpsville OH 16150",
    "addr:housenumber":"1010",
    "addr:postcode":"16150",
    "addr:street":"W Main St",
    "iso:country":"US",
    "sg:address":"1010 W Main St",
    "sg:city":"Sharpsville",
    "sg:classifiers":[
        {
            "category":"Professional",
            "type":"Services"
        }
    ],
    "sg:phone":"+1   ",
    "sg:postcode":"16150",
    "sg:province":"OH",
    "wof:name":"Horgos",
    "wof:placetype":"venue"
},
  "geometry": {"coordinates":[-80.48989899999999,41.260441],"type":"Point"}
}