{
  "type": "Feature",
  "properties": {
    "addr:full": "5700 W Alexis Rd Sylvania OH 43560",
    "addr:housenumber": "5700",
    "addr:postcode": "43560",
    "addr:street": "W Alexis Rd",
    "iso:country": "US",
    "sg:address": "5700 W Alexis Rd",
    "sg:city": "Sylvania",
    "sg:classifiers": [
      {
        "category": "Insurance",
        "subcategory": "Insurance Agent",
        "type": "Services"
      }
    ],
    "sg:phone": "+1 419 882 8181",
    "sg:postcode": "43560",
    "sg:province": "OH",
    "wof:name": "Bob Paxton Agency",
    "wof:placetype": "venue"
  },
  "geometry": {"coordinates":[-83.680294,41.716151],"type":"Point"}
}
