{
  "type": "Feature",
  "properties": {
    "iso:country":"US",
    "sg:address":"645 Moorfield Rd",
    "sg:city":"Akron",
    "sg:classifiers":[
        {
            "category":"Education",
            "subcategory":"School",
            "type":"Public Place"
        }
    ],
    "sg:phone":"+1 330 867 8720",
    "sg:postcode":"44333",
    "sg:province":"OH",
    "sg:website":"www.st-hilaryschool.org",
    "wof:name":"St Hilary School",
    "wof:placetype":"venue"
},
  "geometry": {"coordinates":[-81.604174,41.124252],"type":"Point"}
}