{
  "type": "Feature",
  "properties": {
    "addr:full":"2877 E Broad St Bexley OH 43209",
    "addr:housenumber":"2877",
    "addr:postcode":"43209",
    "addr:street":"E Broad St",
    "iso:country":"US",
    "sg:address":"2877 E Broad St",
    "sg:city":"Bexley",
    "sg:classifiers":[
        {
            "category":"Real Estate",
            "subcategory":"Real Estate Operator",
            "type":"Services"
        }
    ],
    "sg:phone":"+1 614 237 8004",
    "sg:postcode":"43209",
    "sg:province":"OH",
    "sg:tags":[
        "building",
        "apartment"
    ],
    "wof:name":"Bexley House Apartments",
    "wof:placetype":"venue"
},
  "geometry": {"coordinates":[-82.923519,39.970825],"type":"Point"}
}