{
  "type": "Feature",
  "properties": {
    "addr:full":"7010 Cross Creek Ln Hamilton OH 45011",
    "addr:housenumber":"7010",
    "addr:postcode":"45011",
    "addr:street":"Cross Creek Ln",
    "iso:country":"US",
    "sg:address":"7010 Cross Creek Ln",
    "sg:city":"Hamilton",
    "sg:classifiers":[
        {
            "category":"Building & Trades",
            "subcategory":"Construction",
            "type":"Services"
        }
    ],
    "sg:phone":"+1 513 737 0921",
    "sg:postcode":"45011",
    "sg:province":"OH",
    "sg:tags":[
        "contractor"
    ],
    "wof:name":"Dixon Builder",
    "wof:placetype":"venue"
},
  "geometry": {"coordinates":[-84.472556,39.379241],"type":"Point"}
}