{
  "type": "Feature",
  "properties": {
    "addr:full":"509 W Auglaize St Wapakoneta OH 45895",
    "addr:housenumber":"509",
    "addr:postcode":"45895",
    "addr:street":"W Auglaize St",
    "iso:country":"US",
    "sg:address":"509 W Auglaize St",
    "sg:city":"Wapakoneta",
    "sg:classifiers":[
        {
            "category":"Farming",
            "subcategory":"Nursery",
            "type":"Manufacturing & Wholesale Goods"
        }
    ],
    "sg:phone":"+1 419 738 6939",
    "sg:postcode":"45895",
    "sg:province":"OH",
    "sg:tags":[
        "ornamental"
    ],
    "wof:name":"Art Works",
    "wof:placetype":"venue"
},
  "geometry": {"coordinates":[-84.200434,40.569987],"type":"Point"}
}