{
  "type": "Feature",
  "properties": {
    "iso:country":"US",
    "sg:address":"1401 E Main St",
    "sg:city":"Eaton",
    "sg:classifiers":[
        {
            "category":"Food & Beverages",
            "subcategory":"Bakery",
            "type":"Retail Goods"
        }
    ],
    "sg:phone":"+1 937 456 1600",
    "sg:postcode":"45320",
    "sg:province":"OH",
    "sg:tags":[
        "baker"
    ],
    "wof:name":"Bread Of Life Bakery",
    "wof:placetype":"venue"
},
  "geometry": {"coordinates":[-84.61157300000001,39.743823],"type":"Point"}
}