{
  "type": "Feature",
  "properties": {
    "addr:full":"333 E South St Wooster OH 44691",
    "addr:housenumber":"333 e",
    "addr:postcode":"44691",
    "addr:street":"South St",
    "iso:country":"US",
    "sg:address":"333 E South St",
    "sg:city":"Wooster",
    "sg:classifiers":[
        {
            "category":"Retail",
            "subcategory":"Repair Shop",
            "type":"Services"
        }
    ],
    "sg:phone":"+1 330 263 0159",
    "sg:postcode":"44691",
    "sg:province":"OH",
    "sg:tags":[
        "equipment",
        "electronic",
        "supply"
    ],
    "wof:name":"Danny L Landacre Electronics",
    "wof:placetype":"venue"
},
  "geometry": {"coordinates":[-81.936099,40.797461],"type":"Point"}
}