{
  "type": "Feature",
  "properties": {
    "addr:full":"551 Wabash Ave NW New Philadelphia OH 44663",
    "addr:housenumber":"551",
    "addr:postcode":"44663",
    "addr:street":"Wabash Ave Nw New Philadelphia",
    "iso:country":"US",
    "sg:address":"551 Wabash Ave NW",
    "sg:city":"New Philadelphia",
    "sg:classifiers":[
        {
            "category":"Government",
            "subcategory":"Office",
            "type":"Public Place"
        }
    ],
    "sg:phone":"+1 330 343 2343",
    "sg:postcode":"44663",
    "sg:province":"OH",
    "wof:name":"US Geological Water Resources",
    "wof:placetype":"venue"
},
  "geometry": {"coordinates":[-81.456261,40.504668],"type":"Point"}
}