{
  "type": "Feature",
  "properties": {
    "addr:full":"16626 Broadway Ave Cleveland OH 44137",
    "addr:housenumber":"16626",
    "addr:postcode":"44137",
    "addr:street":"Broadway Ave",
    "iso:country":"US",
    "sg:address":"16626 Broadway Ave",
    "sg:city":"Cleveland",
    "sg:classifiers":[
        {
            "category":"Building & Trades",
            "subcategory":"Landscaping Services",
            "type":"Services"
        }
    ],
    "sg:phone":"+1 216 587 5980",
    "sg:postcode":"44137",
    "sg:province":"OH",
    "sg:tags":[
        "landscape",
        "contractor"
    ],
    "sg:website":"www.turfworldco.com",
    "wof:name":"Turf World Co",
    "wof:placetype":"venue"
},
  "geometry": {"coordinates":[-81.563847,41.411029],"type":"Point"}
}