{
  "type": "Feature",
  "properties": {
    "addr:full": "309 Factory St NE Sugarcreek OH 44681",
    "addr:housenumber": "309",
    "addr:postcode": "44681",
    "addr:street": "Factory St Ne",
    "iso:country": "US",
    "sg:address": "309 Factory St NE",
    "sg:city": "Sugarcreek",
    "sg:classifiers": [
      {
        "category": "Building \u0026 Trades",
        "subcategory": "Plumbing",
        "type": "Services"
      }
    ],
    "sg:phone": "+1 330 852 2332",
    "sg:postcode": "44681",
    "sg:province": "OH",
    "sg:tags": [
      "plumbing",
      "contractor"
    ],
    "wof:name": "K James Jones Plumbing",
    "wof:placetype": "venue"
  },
  "geometry": {"coordinates":[-81.637729,40.506312],"type":"Point"}
}
