{
  "type": "Feature",
  "properties": {
    "iso:country":"US",
    "sg:address":"309 Factory St NE",
    "sg:city":"Sugarcreek",
    "sg:classifiers":[
        {
            "category":"Building & Trades",
            "subcategory":"Plumbing",
            "type":"Services"
        }
    ],
    "sg:phone":"+1 330 852 2332",
    "sg:postcode":"44681",
    "sg:province":"OH",
    "sg:tags":[
        "plumbing",
        "contractor"
    ],
    "wof:name":"K James Jones Plumbing",
    "wof:placetype":"venue"
},
  "geometry": {"coordinates":[-81.63772899999999,40.506312],"type":"Point"}
}