{
  "type": "Feature",
  "properties": {
    "addr:full":"29124 Center Ridge Rd Cleveland OH 44145",
    "addr:housenumber":"29124",
    "addr:postcode":"44145",
    "addr:street":"Center Ridge Rd",
    "iso:country":"US",
    "sg:address":"29124 Center Ridge Rd",
    "sg:city":"Cleveland",
    "sg:classifiers":[
        {
            "category":"Retail",
            "subcategory":"Funeral Services",
            "type":"Services"
        }
    ],
    "sg:phone":"+1 440 617 1911",
    "sg:postcode":"44145",
    "sg:province":"OH",
    "sg:tags":[
        "director"
    ],
    "wof:name":"Donald Martens & Sons Funeral",
    "wof:placetype":"venue"
},
  "geometry": {"coordinates":[-81.94255699999999,41.434387],"type":"Point"}
}