{
  "type": "Feature",
  "properties": {
    "addr:full": "1912 E 6th St Cleveland OH 44114",
    "addr:housenumber": "1912",
    "addr:postcode": "44114",
    "addr:street": "E 6Th St",
    "iso:country": "US",
    "sg:address": "1912 E 6th St",
    "sg:city": "Cleveland",
    "sg:classifiers": [
      {
        "category": "Bars \u0026 Pubs",
        "type": "Food \u0026 Drink"
      }
    ],
    "sg:phone": "+1 216 771 0211",
    "sg:postcode": "44114",
    "sg:province": "OH",
    "wof:name": "Moriarty's Pubs",
    "wof:placetype": "venue"
  },
  "geometry": {"coordinates":[-81.689345,41.499995],"type":"Point"}
}
