{
  "type": "Feature",
  "properties": {
    "addr:full":"9901 Princeton Glendale Rd Cincinnati OH 45246",
    "addr:housenumber":"9901",
    "addr:postcode":"45246",
    "addr:street":"Princeton Glendale Rd",
    "iso:country":"US",
    "sg:address":"9901 Princeton Glendale Rd",
    "sg:city":"Cincinnati",
    "sg:classifiers":[
        {
            "category":"Government",
            "subcategory":"Office",
            "type":"Public Place"
        }
    ],
    "sg:phone":"+1 513 881 2120",
    "sg:postcode":"45246",
    "sg:province":"OH",
    "sg:tags":[
        "federal",
        "program",
        "adm"
    ],
    "wof:name":"US Census Bureau",
    "wof:placetype":"venue"
},
  "geometry": {"coordinates":[-84.464817,39.312183],"type":"Point"}
}