{
  "type": "Feature",
  "properties": {
    "addr:full": "6647 Winchell Rd Hiram OH 44234",
    "addr:housenumber": "6647",
    "addr:postcode": "44234",
    "addr:street": "Winchell Rd",
    "iso:country": "US",
    "sg:address": "6647 Winchell Rd",
    "sg:city": "Hiram",
    "sg:classifiers": [
      {
        "category": "Building \u0026 Trades",
        "subcategory": "Plumbing",
        "type": "Services"
      }
    ],
    "sg:phone": "+1 330 569 7420",
    "sg:postcode": "44234",
    "sg:province": "OH",
    "sg:tags": [
      "mechanical",
      "contractor"
    ],
    "wof:name": "S \u0026 J Mechanical Inc",
    "wof:placetype": "venue"
  },
  "geometry": {"coordinates":[-81.1468,41.33361],"type":"Point"}
}
