{
  "type": "Feature",
  "properties": {
    "iso:country":"US",
    "sg:address":"6647 Winchell Rd",
    "sg:city":"Hiram",
    "sg:classifiers":[
        {
            "category":"Building & Trades",
            "subcategory":"Plumbing",
            "type":"Services"
        }
    ],
    "sg:phone":"+1 330 569 7420",
    "sg:postcode":"44234",
    "sg:province":"OH",
    "sg:tags":[
        "mechanical",
        "contractor"
    ],
    "wof:name":"S & J Mechanical Inc",
    "wof:placetype":"venue"
},
  "geometry": {"coordinates":[-81.1468,41.33361],"type":"Point"}
}