{
  "type": "Feature",
  "properties": {
    "addr:full":"1985 Gene Cox Memorial Dr Dresden OH 43821",
    "addr:housenumber":"1985",
    "addr:postcode":"43821",
    "addr:street":"Gene Cox Memorial Dr",
    "iso:country":"US",
    "sg:address":"1985 Gene Cox Memorial Dr",
    "sg:city":"Dresden",
    "sg:classifiers":[
        {
            "category":"Wholesale",
            "subcategory":"Construction Materials",
            "type":"Manufacturing & Wholesale Goods"
        }
    ],
    "sg:phone":"+1 740 754 3311",
    "sg:postcode":"43821",
    "sg:province":"OH",
    "sg:tags":[
        "sand",
        "gravel"
    ],
    "wof:name":"Shelly Materials Inc",
    "wof:placetype":"venue"
},
  "geometry": {"coordinates":[-81.99077200000001,40.13255],"type":"Point"}
}