{
  "type": "Feature",
  "properties": {
    "addr:full": "14111 Scottslawn Rd Marysville OH 43040",
    "addr:housenumber": "14111",
    "addr:postcode": "43040",
    "addr:street": "Scottslawn Rd",
    "iso:country": "US",
    "sg:address": "14111 Scottslawn Rd",
    "sg:city": "Marysville",
    "sg:classifiers": [
      {
        "category": "Manufacturing",
        "subcategory": "Chemicals \u0026 Compounds",
        "type": "Manufacturing \u0026 Wholesale Goods"
      }
    ],
    "sg:phone": "+1 937 644 0011",
    "sg:postcode": "43040",
    "sg:province": "OH",
    "sg:tags": [
      "fertilizer"
    ],
    "sg:website": "www.scotts.com",
    "wof:name": "Scotts Miracle-Gro Co",
    "wof:placetype": "venue"
  },
  "geometry": {"coordinates":[-83.313271,40.206488],"type":"Point"}
}
