{
  "type": "Feature",
  "properties": {
    "iso:country":"US",
    "sg:address":"350 E State St",
    "sg:city":"Alliance",
    "sg:classifiers":[
        {
            "category":"Home & Garden",
            "subcategory":"Household Appliances",
            "type":"Retail Goods"
        }
    ],
    "sg:phone":"+1 330 821 1500",
    "sg:postcode":"44601",
    "sg:province":"OH",
    "sg:website":"www.groveappliance.com",
    "wof:name":"Grove Appliance TV & Audio",
    "wof:placetype":"venue"
},
  "geometry": {"coordinates":[-81.100526,40.901755],"type":"Point"}
}