{
  "type": "Feature",
  "properties": {
    "addr:full": "350 E State St Alliance OH 44601",
    "addr:housenumber": "350",
    "addr:postcode": "44601",
    "addr:street": "E State St",
    "iso:country": "US",
    "sg:address": "350 E State St",
    "sg:city": "Alliance",
    "sg:classifiers": [
      {
        "category": "Home \u0026 Garden",
        "subcategory": "Household Appliances",
        "type": "Retail Goods"
      }
    ],
    "sg:phone": "+1 330 821 1500",
    "sg:postcode": "44601",
    "sg:province": "OH",
    "sg:website": "www.groveappliance.com",
    "wof:name": "Grove Appliance TV \u0026 Audio",
    "wof:placetype": "venue"
  },
  "geometry": {"coordinates":[-81.100526,40.901755],"type":"Point"}
}
