{
  "type": "Feature",
  "properties": {
    "addr:full": "1408 E 300th St Wickliffe OH 44092",
    "addr:housenumber": "1408",
    "addr:postcode": "44092",
    "addr:street": "E 300Th St",
    "iso:country": "US",
    "sg:address": "1408 E 300th St",
    "sg:city": "Wickliffe",
    "sg:classifiers": [
      {
        "category": "Building \u0026 Trades",
        "subcategory": "Landscaping Services",
        "type": "Services"
      }
    ],
    "sg:phone": "+1 440 944 1735",
    "sg:postcode": "44092",
    "sg:province": "OH",
    "sg:tags": [
      "tree"
    ],
    "wof:name": "Acorn Tree Svc Inc",
    "wof:placetype": "venue"
  },
  "geometry": {"coordinates":[-81.465942,41.615118],"type":"Point"}
}
