{
  "type": "Feature",
  "properties": {
    "iso:country":"US",
    "sg:address":"40 S Main St",
    "sg:city":"New London",
    "sg:classifiers":[
        {
            "category":"Manufacturing",
            "subcategory":"Glass & Minerals",
            "type":"Manufacturing & Wholesale Goods"
        }
    ],
    "sg:phone":"+1 419 929 2240",
    "sg:postcode":"44851",
    "sg:province":"OH",
    "sg:tags":[
        "cut",
        "mfg"
    ],
    "wof:name":"Stone Age Creations Ltd",
    "wof:placetype":"venue"
},
  "geometry": {"coordinates":[-82.399039,41.084423],"type":"Point"}
}