{
  "type": "Feature",
  "properties": {
    "addr:full": "40 S Main St New London OH 44851",
    "addr:housenumber": "40",
    "addr:postcode": "44851",
    "addr:street": "S Main St",
    "iso:country": "US",
    "sg:address": "40 S Main St",
    "sg:city": "New London",
    "sg:classifiers": [
      {
        "category": "Manufacturing",
        "subcategory": "Glass \u0026 Minerals",
        "type": "Manufacturing \u0026 Wholesale Goods"
      }
    ],
    "sg:phone": "+1 419 929 2240",
    "sg:postcode": "44851",
    "sg:province": "OH",
    "sg:tags": [
      "cut",
      "mfg"
    ],
    "wof:name": "Stone Age Creations Ltd",
    "wof:placetype": "venue"
  },
  "geometry": {"coordinates":[-82.399039,41.084423],"type":"Point"}
}
