{
  "type": "Feature",
  "properties": {
    "iso:country":"US",
    "sg:address":"28 W Auglaize St",
    "sg:city":"Wapakoneta",
    "sg:classifiers":[
        {
            "category":"Retail",
            "subcategory":"Repair Shop",
            "type":"Services"
        }
    ],
    "sg:phone":"+1 419 738 5175",
    "sg:postcode":"45895",
    "sg:province":"OH",
    "sg:tags":[
        "lock",
        "locksmith"
    ],
    "wof:name":"Roger's Lock & Key",
    "wof:placetype":"venue"
},
  "geometry": {"coordinates":[-84.194599,40.570659],"type":"Point"}
}