{
  "type": "Feature",
  "properties": {
    "addr:full":"111 Byesville Rd Cambridge OH 43725",
    "addr:housenumber":"111",
    "addr:postcode":"43725",
    "addr:street":"Byesville Rd",
    "iso:country":"US",
    "sg:address":"111 Byesville Rd",
    "sg:city":"Cambridge",
    "sg:classifiers":[
        {
            "category":"Building & Trades",
            "subcategory":"Landscaping Services",
            "type":"Services"
        }
    ],
    "sg:phone":"+1 740 439 6614",
    "sg:postcode":"43725",
    "sg:province":"OH",
    "sg:tags":[
        "landscape"
    ],
    "wof:name":"Dennis Daugherty & Dan Da",
    "wof:placetype":"venue"
},
  "geometry": {"coordinates":[-81.56701099999999,40.027818],"type":"Point"}
}