{
  "type": "Feature",
  "properties": {
    "addr:full":"7300 Old Mill Rd Gates Mills OH 44040",
    "addr:housenumber":"7300",
    "addr:postcode":"44040",
    "addr:street":"Old Mill Rd",
    "iso:country":"US",
    "sg:address":"7300 Old Mill Rd",
    "sg:city":"Gates Mills",
    "sg:classifiers":[
        {
            "category":"Communications",
            "subcategory":"Film & Video Production",
            "type":"Services"
        }
    ],
    "sg:phone":"+1 440 423 1601",
    "sg:postcode":"44040",
    "sg:province":"OH",
    "sg:tags":[
        "taping"
    ],
    "sg:website":"www.griesingerfilms.com",
    "wof:name":"Griesinger Films",
    "wof:placetype":"venue"
},
  "geometry": {"coordinates":[-81.421915,41.520168],"type":"Point"}
}