{
  "type": "Feature",
  "properties": {
    "addr:full":"9330 Yankeetown-Chenoweth Rd Mount Sterling OH 43143",
    "addr:postcode":"9330;43143",
    "addr:street":"Yankeetown-Chenoweth Rd",
    "iso:country":"US",
    "sg:address":"9330 Yankeetown-Chenoweth Rd",
    "sg:city":"Mount Sterling",
    "sg:phone":"+1 740 852 0849",
    "sg:postcode":"43143",
    "sg:province":"OH",
    "sg:tags":[
        "farm",
        "grain",
        "cash"
    ],
    "wof:name":"John Jacobs",
    "wof:placetype":"venue"
},
  "geometry": {"coordinates":[-83.426106,39.80062],"type":"Point"}
}