{
  "type": "Feature",
  "properties": {
    "iso:country":"US",
    "sg:address":"4077 Upper Five Mile East Rd",
    "sg:city":"Mount Orab",
    "sg:phone":"+1 937 444 3660",
    "sg:postcode":"45154",
    "sg:province":"OH",
    "sg:tags":[
        "farm",
        "corn",
        "wheat",
        "soybean"
    ],
    "wof:name":"Raymond Barber Farm",
    "wof:placetype":"venue"
},
  "geometry": {"coordinates":[-83.919056,39.119815],"type":"Point"}
}