{
  "type": "Feature",
  "properties": {
    "iso:country":"US",
    "sg:address":"6004 State Rte 730",
    "sg:city":"Wilmington",
    "sg:classifiers":[
        {
            "category":"Farming",
            "subcategory":"Livestock Farm",
            "type":"Manufacturing & Wholesale Goods"
        }
    ],
    "sg:phone":"+1 937 382 6147",
    "sg:postcode":"45177",
    "sg:province":"OH",
    "sg:tags":[
        "equine"
    ],
    "wof:name":"Sharpe Dave Show Horses Inc",
    "wof:placetype":"venue"
},
  "geometry": {"coordinates":[-83.914903,39.400199],"type":"Point"}
}