{
  "type": "Feature",
  "properties": {
    "addr:full":"1502 Abbey Ave Cleveland OH 44113",
    "addr:housenumber":"1502",
    "addr:postcode":"44113",
    "addr:street":"Abbey Ave",
    "iso:country":"US",
    "sg:address":"1502 Abbey Ave",
    "sg:city":"Cleveland",
    "sg:classifiers":[
        {
            "category":"Retail",
            "subcategory":"Veterinary Services",
            "type":"Services"
        }
    ],
    "sg:phone":"+1 216 771 4414",
    "sg:postcode":"44113",
    "sg:province":"OH",
    "wof:name":"Gateway Animal Clinic",
    "wof:placetype":"venue"
},
  "geometry": {"coordinates":[-81.693624,41.484475],"type":"Point"}
}