{
  "type": "Feature",
  "properties": {
    "iso:country":"US",
    "sg:address":"6124 Avery Rd",
    "sg:city":"Dublin",
    "sg:classifiers":[
        {
            "category":"Organizations",
            "subcategory":"Professional Association",
            "type":"Services"
        }
    ],
    "sg:phone":"+1 614 889 1309",
    "sg:postcode":"43016",
    "sg:province":"OH",
    "sg:website":"www.omeda.org",
    "wof:name":"Ohio-Michigan Equip Dealers",
    "wof:placetype":"venue"
},
  "geometry": {"coordinates":[-83.15848099999999,40.09336],"type":"Point"}
}