{
  "type": "Feature",
  "properties": {
    "addr:full": "524 E 3rd St Greenville OH 45331",
    "addr:housenumber": "524",
    "addr:postcode": "45331",
    "addr:street": "E 3Rd St",
    "iso:country": "US",
    "sg:address": "524 E 3rd St",
    "sg:city": "Greenville",
    "sg:classifiers": [
      {
        "category": "Building \u0026 Trades",
        "subcategory": "Construction",
        "type": "Services"
      },
      {
        "category": "Autos \u0026 Motor Vehicles",
        "subcategory": "Auto Supplies",
        "type": "Retail Goods"
      }
    ],
    "sg:phone": "+1 937 548 6622",
    "sg:postcode": "45331",
    "sg:province": "OH",
    "sg:tags": [
      "home",
      "improvement"
    ],
    "wof:name": "Great Maintenance Company",
    "wof:placetype": "venue"
  },
  "geometry": {"coordinates":[-84.626198,40.105708],"type":"Point"}
}
