{
  "type": "Feature",
  "properties": {
    "addr:full":"214 Depot St Wauseon OH 43567",
    "addr:housenumber":"214",
    "addr:postcode":"43567",
    "addr:street":"Depot St",
    "iso:country":"US",
    "sg:address":"214 Depot St",
    "sg:city":"Wauseon",
    "sg:classifiers":[
        {
            "category":"Professional",
            "subcategory":"Accounting & Tax Preparation",
            "type":"Services"
        }
    ],
    "sg:phone":"+1 419 335 2851",
    "sg:postcode":"43567",
    "sg:province":"OH",
    "sg:tags":[
        "return",
        "filing"
    ],
    "wof:name":"Harold Sauber Accounting",
    "wof:placetype":"venue"
},
  "geometry": {"coordinates":[-84.14298599999999,41.547957],"type":"Point"}
}