{
  "type": "Feature",
  "properties": {
    "iso:country":"US",
    "sg:address":"6106 London Groveport Rd",
    "sg:city":"Harrisburg",
    "sg:classifiers":[
        {
            "category":"Real Estate",
            "subcategory":"Real Estate Operator",
            "type":"Services"
        }
    ],
    "sg:phone":"+1 614 877 3717",
    "sg:postcode":"43146",
    "sg:province":"OH",
    "sg:tags":[
        "mobile",
        "home",
        "community"
    ],
    "wof:name":"Pleasant Acres",
    "wof:placetype":"venue"
},
  "geometry": {"coordinates":[-83.159486,39.849255],"type":"Point"}
}