{
  "type": "Feature",
  "properties": {
    "iso:country":"US",
    "sg:address":"2950 S 1st St",
    "sg:city":"Clinton",
    "sg:classifiers":[
        {
            "category":"Home & Garden",
            "subcategory":"Furniture",
            "type":"Retail Goods"
        }
    ],
    "sg:phone":"+1 330 882 3331",
    "sg:postcode":"44216",
    "sg:province":"OH",
    "sg:tags":[
        "top",
        "counter"
    ],
    "wof:name":"Artisan Countertop Builders",
    "wof:placetype":"venue"
},
  "geometry": {"coordinates":[-81.64228,40.921654],"type":"Point"}
}