{
  "type": "Feature",
  "properties": {
    "addr:full": "415 Wellman Ave SE Girard OH 44420",
    "addr:housenumber": "415",
    "addr:postcode": "44420",
    "addr:street": "Wellman Ave Se",
    "iso:country": "US",
    "sg:address": "415 Wellman Ave SE",
    "sg:city": "Girard",
    "sg:classifiers": [
      {
        "category": "Building \u0026 Trades",
        "subcategory": "Plumbing",
        "type": "Services"
      }
    ],
    "sg:phone": "+1 330 545 2788",
    "sg:postcode": "44420",
    "sg:province": "OH",
    "sg:tags": [
      "contractor"
    ],
    "wof:name": "Stevens Plumbing",
    "wof:placetype": "venue"
  },
  "geometry": {"coordinates":[-80.686328,41.159068],"type":"Point"}
}
