{
  "type": "Feature",
  "properties": {
    "addr:full":"37701 Colorado Ave Avon OH 44011",
    "addr:postcode":"37701;44011",
    "addr:street":"Colorado Ave",
    "iso:country":"US",
    "sg:address":"37701 Colorado Ave",
    "sg:city":"Avon",
    "sg:classifiers":[
        {
            "category":"Professional",
            "type":"Services"
        }
    ],
    "sg:phone":"+1 440 934 5801",
    "sg:postcode":"44011",
    "sg:province":"OH",
    "wof:name":"Ashai & Adenwalla Orthodonics",
    "wof:placetype":"venue"
},
  "geometry": {"coordinates":[-82.044219,41.459116],"type":"Point"}
}