{
  "type": "Feature",
  "properties": {
    "addr:full":"366 E Waterloo Rd Akron OH 44319",
    "addr:housenumber":"366",
    "addr:postcode":"44319",
    "addr:street":"E Waterloo Rd",
    "iso:country":"US",
    "sg:address":"366 E Waterloo Rd",
    "sg:city":"Akron",
    "sg:classifiers":[
        {
            "category":"Restaurant",
            "type":"Food & Drink"
        }
    ],
    "sg:phone":"+1 330 785 1099",
    "sg:postcode":"44319",
    "sg:province":"OH",
    "sg:website":"www.hungryhowies.com",
    "wof:name":"Hungry Howie's Pizza & Subs",
    "wof:placetype":"venue"
},
  "geometry": {"coordinates":[-81.513575,41.028777],"type":"Point"}
}