{
  "type": "Feature",
  "properties": {
    "iso:country":"US",
    "sg:address":"6015 Market St",
    "sg:city":"Youngstown",
    "sg:classifiers":[
        {
            "category":"Food & Beverages",
            "subcategory":"Specialty",
            "type":"Retail Goods"
        },
        {
            "category":"Food & Beverages",
            "subcategory":"Fruits & Vegetables",
            "type":"Retail Goods"
        }
    ],
    "sg:phone":"+1 330 965 1515",
    "sg:postcode":"44512",
    "sg:province":"OH",
    "sg:tags":[
        "product",
        "herb",
        "vitamin",
        "diet",
        "supplement",
        "health"
    ],
    "sg:website":"http://www.HFCSHOP.com",
    "wof:name":"Health Food Center Of Youngstown",
    "wof:placetype":"venue"
},
  "geometry": {"coordinates":[-80.66274300000001,41.037521],"type":"Point"}
}