{
  "type": "Feature",
  "properties": {
    "addr:full":"410 Beechwood Dr Akron OH 44320",
    "addr:housenumber":"410",
    "addr:postcode":"44320",
    "addr:street":"Beechwood Dr",
    "iso:country":"US",
    "sg:address":"410 Beechwood Dr",
    "sg:city":"Akron",
    "sg:classifiers":[
        {
            "category":"Railroad",
            "type":"Transportation"
        }
    ],
    "sg:phone":"+1 330 253 3495",
    "sg:postcode":"44320",
    "sg:province":"OH",
    "sg:tags":[
        "operator",
        "line"
    ],
    "wof:name":"RR Lambacher Co",
    "wof:placetype":"venue"
},
  "geometry": {"coordinates":[-81.546677,41.087456],"type":"Point"}
}