{
  "type": "Feature",
  "properties": {
    "addr:full":"15227 Triskett Rd Cleveland OH 44111",
    "addr:postcode":"15227;44111",
    "addr:street":"Triskett Rd",
    "iso:country":"US",
    "sg:address":"15227 Triskett Rd",
    "sg:city":"Cleveland",
    "sg:classifiers":[
        {
            "category":"Professional",
            "subcategory":"Accounting & Tax Preparation",
            "type":"Services"
        }
    ],
    "sg:phone":"+1 216 941 3144",
    "sg:postcode":"44111",
    "sg:province":"OH",
    "sg:tags":[
        "accountant"
    ],
    "wof:name":"Abrar CPA Inc",
    "wof:placetype":"venue"
},
  "geometry": {"coordinates":[-81.801502,41.456317],"type":"Point"}
}