{
  "type": "Feature",
  "properties": {
    "addr:full": "14216 Euclid Ave Cleveland OH 44112",
    "addr:housenumber": "14216",
    "addr:postcode": "44112",
    "addr:street": "Euclid Ave",
    "iso:country": "US",
    "sg:address": "14216 Euclid Ave",
    "sg:city": "Cleveland",
    "sg:classifiers": [
      {
        "category": "Insurance",
        "subcategory": "Hazard Insurance",
        "type": "Services"
      }
    ],
    "sg:phone": "+1 216 541 2663",
    "sg:postcode": "44112",
    "sg:province": "OH",
    "sg:tags": [
      "bond"
    ],
    "wof:name": "Eazy Bail Bonding Co",
    "wof:placetype": "venue"
  },
  "geometry": {"coordinates":[-81.582761,41.529569],"type":"Point"}
}
