{
  "type": "Feature",
  "properties": {
    "iso:country":"US",
    "sg:address":"450 W 7th St",
    "sg:city":"Minster",
    "sg:phone":"+1 419 628 4092",
    "sg:postcode":"45865",
    "sg:province":"OH",
    "sg:tags":[
        "farm",
        "corn",
        "soybean",
        "crop",
        "general"
    ],
    "wof:name":"R and D Tebbe Farm",
    "wof:placetype":"venue"
},
  "geometry": {"coordinates":[-84.38395800000001,40.400276],"type":"Point"}
}