{
  "type": "Feature",
  "properties": {
    "addr:full":"3030 Houston Rd Barberton OH 44203",
    "addr:housenumber":"3030",
    "addr:postcode":"44203",
    "addr:street":"Houston Rd",
    "iso:country":"US",
    "sg:address":"3030 Houston Rd",
    "sg:city":"Barberton",
    "sg:classifiers":[
        {
            "category":"Shopping",
            "subcategory":"Hobbies, Toys, & Games",
            "type":"Retail Goods"
        },
        {
            "category":"Building & Trades",
            "subcategory":"Construction",
            "type":"Services"
        }
    ],
    "sg:phone":"+1 330 848 5000",
    "sg:postcode":"44203",
    "sg:province":"OH",
    "sg:tags":[
        "tile",
        "dealer"
    ],
    "wof:name":"Frost Tile & Marble Co",
    "wof:placetype":"venue"
},
  "geometry": {"coordinates":[-81.62299,41.052048],"type":"Point"}
}