{
  "type": "Feature",
  "properties": {
    "addr:full": "21340 Westport Ave Cleveland OH 44123",
    "addr:housenumber": "21340",
    "addr:postcode": "44123",
    "addr:street": "Westport Ave",
    "iso:country": "US",
    "sg:address": "21340 Westport Ave",
    "sg:city": "Cleveland",
    "sg:classifiers": [
      {
        "category": "Organizations",
        "subcategory": "Religious Organization",
        "type": "Services"
      }
    ],
    "sg:phone": "+1 216 731 6354",
    "sg:postcode": "44123",
    "sg:province": "OH",
    "sg:tags": [
      "clergy"
    ],
    "wof:name": "C Skovira",
    "wof:placetype": "venue"
  },
  "geometry": {"coordinates":[-81.531958,41.59635],"type":"Point"}
}
