{
  "type": "Feature",
  "properties": {
    "addr:full":"4016 Townsfair Way Columbus OH 43219",
    "addr:housenumber":"4016",
    "addr:postcode":"43219",
    "addr:street":"Townsfair Way",
    "iso:country":"US",
    "sg:address":"4016 Townsfair Way",
    "sg:city":"Columbus",
    "sg:classifiers":[
        {
            "category":"Real Estate",
            "subcategory":"Real Estate Services",
            "type":"Services"
        }
    ],
    "sg:phone":"+1 614 428 7260",
    "sg:postcode":"43219",
    "sg:province":"OH",
    "sg:tags":[
        "company",
        "title"
    ],
    "wof:name":"Builder Title Co",
    "wof:placetype":"venue"
},
  "geometry": {"coordinates":[-82.91453300000001,40.049094],"type":"Point"}
}