{
  "type": "Feature",
  "properties": {
    "addr:full":"3047 Madison Rd Cincinnati OH 45209",
    "addr:housenumber":"3047",
    "addr:postcode":"45209",
    "addr:street":"Madison Rd",
    "iso:country":"US",
    "sg:address":"3047 Madison Rd",
    "sg:city":"Cincinnati",
    "sg:classifiers":[
        {
            "category":"Shopping",
            "subcategory":"Catalog Store",
            "type":"Retail Goods"
        }
    ],
    "sg:phone":"+1 513 731 5900",
    "sg:postcode":"45209",
    "sg:province":"OH",
    "sg:tags":[
        "product",
        "recognition"
    ],
    "wof:name":"Jostens Inc",
    "wof:placetype":"venue"
},
  "geometry": {"coordinates":[-84.432282,39.151697],"type":"Point"}
}