{
  "type": "Feature",
  "properties": {
    "addr:full":"11550 Mahoning Ave North Jackson OH 44451",
    "addr:housenumber":"11550",
    "addr:postcode":"44451",
    "addr:street":"Mahoning Ave North",
    "iso:country":"US",
    "sg:address":"11550 Mahoning Ave",
    "sg:city":"North Jackson",
    "sg:classifiers":[
        {
            "category":"Retail",
            "subcategory":"Repair Shop",
            "type":"Services"
        }
    ],
    "sg:phone":"+1 330 538 2232",
    "sg:postcode":"44451",
    "sg:province":"OH",
    "sg:tags":[
        "equipment",
        "hydraulic"
    ],
    "wof:name":"North Jackson Hydralics",
    "wof:placetype":"venue"
},
  "geometry": {"coordinates":[-80.86639,41.099802],"type":"Point"}
}