{
  "type": "Feature",
  "properties": {
    "addr:full": "2210 Arbor Blvd Dayton OH 45439",
    "addr:housenumber": "2210",
    "addr:postcode": "45439",
    "addr:street": "Arbor Blvd",
    "iso:country": "US",
    "sg:address": "2210 Arbor Blvd",
    "sg:city": "Dayton",
    "sg:classifiers": [
      {
        "category": "Organizations",
        "subcategory": "Professional Association",
        "type": "Services"
      }
    ],
    "sg:phone": "+1 937 294 0023",
    "sg:postcode": "45439",
    "sg:province": "OH",
    "sg:tags": [
      "trade"
    ],
    "wof:name": "Miami Valley Roofing Ind Jaf",
    "wof:placetype": "venue"
  },
  "geometry": {"coordinates":[-84.21107,39.725725],"type":"Point"}
}
