{
  "type": "Feature",
  "properties": {
    "iso:country":"US",
    "sg:address":"36 E 4th St",
    "sg:city":"Cincinnati",
    "sg:classifiers":[
        {
            "category":"Real Estate",
            "subcategory":"Real Estate Agent",
            "type":"Services"
        }
    ],
    "sg:phone":"+1 513 345 6233",
    "sg:postcode":"45202",
    "sg:province":"OH",
    "wof:name":"Bartlett Real Estate Group Inc",
    "wof:placetype":"venue"
},
  "geometry": {"coordinates":[-84.511207,39.100233],"type":"Point"}
}