{
  "type": "Feature",
  "properties": {
    "addr:full":"257 S Main St Dayton OH 45402",
    "addr:housenumber":"257",
    "addr:postcode":"45402",
    "addr:street":"S Main St",
    "iso:country":"US",
    "sg:address":"257 S Main St",
    "sg:city":"Dayton",
    "sg:classifiers":[
        {
            "category":"Wholesale",
            "subcategory":"Jewelry",
            "type":"Manufacturing & Wholesale Goods"
        }
    ],
    "sg:phone":"+1 937 228 5570",
    "sg:postcode":"45402",
    "sg:province":"OH",
    "sg:tags":[
        "stone"
    ],
    "wof:name":"B & B Jewelry Mfg Co",
    "wof:placetype":"venue"
},
  "geometry": {"coordinates":[-84.190966,39.756165],"type":"Point"}
}