{
  "type": "Feature",
  "properties": {
    "addr:full":"374 Good Manor Rd Lucasville OH 45687",
    "addr:housenumber":"374",
    "addr:postcode":"45687",
    "addr:street":"Good Manor Rd",
    "iso:country":"US",
    "sg:address":"374 Good Manor Rd",
    "sg:city":"Lucasville",
    "sg:classifiers":[
        {
            "category":"Professional",
            "subcategory":"Business Services",
            "type":"Services"
        }
    ],
    "sg:phone":"+1 740 289 4843",
    "sg:postcode":"45687",
    "sg:province":"OH",
    "wof:name":"Pike County Adult Activity Ctr",
    "wof:placetype":"venue"
},
  "geometry": {"coordinates":[-83.02659800000001,38.967916],"type":"Point"}
}