{
  "type": "Feature",
  "properties": {
    "iso:country":"US",
    "sg:address":"3415 Standish Ave",
    "sg:city":"Cleveland",
    "sg:classifiers":[
        {
            "category":"Personal",
            "subcategory":"Adult",
            "type":"Services"
        }
    ],
    "sg:phone":"+1 440 842 3149",
    "sg:postcode":"44134",
    "sg:province":"OH",
    "sg:tags":[
        "escort"
    ],
    "wof:name":"Elite Enterprises",
    "wof:placetype":"venue"
},
  "geometry": {"coordinates":[-81.70868900000001,41.390816],"type":"Point"}
}