{
  "type": "Feature",
  "properties": {
    "addr:full": "3415 Standish Ave Cleveland OH 44134",
    "addr:housenumber": "3415",
    "addr:postcode": "44134",
    "addr:street": "Standish Ave",
    "iso:country": "US",
    "sg:address": "3415 Standish Ave",
    "sg:city": "Cleveland",
    "sg:classifiers": [
      {
        "category": "Personal",
        "subcategory": "Adult",
        "type": "Services"
      }
    ],
    "sg:phone": "+1 440 842 3149",
    "sg:postcode": "44134",
    "sg:province": "OH",
    "sg:tags": [
      "escort"
    ],
    "wof:name": "Elite Enterprises",
    "wof:placetype": "venue"
  },
  "geometry": {"coordinates":[-81.708689,41.390816],"type":"Point"}
}
