{
  "type": "Feature",
  "properties": {
    "addr:full":"4900 Reed Rd Columbus OH 43220",
    "addr:housenumber":"4900",
    "addr:postcode":"43220",
    "addr:street":"Reed Rd",
    "iso:country":"US",
    "sg:address":"4900 Reed Rd",
    "sg:city":"Columbus",
    "sg:classifiers":[
        {
            "category":"Insurance",
            "subcategory":"Insurance Agent",
            "type":"Services"
        }
    ],
    "sg:phone":"+1 614 732 0711",
    "sg:postcode":"43220",
    "sg:province":"OH",
    "wof:name":"Primerica Financial Svc",
    "wof:placetype":"venue"
},
  "geometry": {"coordinates":[-83.066816,40.054758],"type":"Point"}
}