{
  "type": "Feature",
  "properties": {
    "addr:full":"71785 Tysons Mill Rd Freeport OH 43973",
    "addr:postcode":"71785;43973",
    "addr:street":"Tysons Mill Rd",
    "iso:country":"US",
    "sg:address":"71785 Tysons Mill Rd",
    "sg:city":"Freeport",
    "sg:classifiers":[
        {
            "category":"Farming",
            "subcategory":"Farm",
            "type":"Manufacturing & Wholesale Goods"
        }
    ],
    "sg:phone":"+1 740 758 5211",
    "sg:postcode":"43973",
    "sg:province":"OH",
    "sg:tags":[
        "crop",
        "general"
    ],
    "wof:name":"Charles Henry",
    "wof:placetype":"venue"
},
  "geometry": {"coordinates":[-81.288481,40.131553],"type":"Point"}
}