{
  "type": "Feature",
  "properties": {
    "addr:full": "35325 Vine St Willowick OH 44095",
    "addr:housenumber": "35325",
    "addr:postcode": "44095",
    "addr:street": "Vine St",
    "iso:country": "US",
    "sg:address": "35325 Vine St",
    "sg:city": "Willowick",
    "sg:classifiers": [
      {
        "category": "Professional",
        "subcategory": "Lawyer \u0026 Legal Services",
        "type": "Services"
      }
    ],
    "sg:phone": "+1 440 953 9180",
    "sg:postcode": "44095",
    "sg:province": "OH",
    "sg:tags": [
      "attorney"
    ],
    "wof:name": "Mark Warren George",
    "wof:placetype": "venue"
  },
  "geometry": {"coordinates":[-81.436953,41.642643],"type":"Point"}
}
