{
  "type": "Feature",
  "properties": {
    "addr:full": "6270 N Ridge Rd W Geneva OH 44004",
    "addr:housenumber": "6270",
    "addr:postcode": "44004",
    "addr:street": "N Ridge Rd W",
    "iso:country": "US",
    "sg:address": "6270 N Ridge Rd W",
    "sg:city": "Geneva",
    "sg:classifiers": [
      {
        "category": "Building \u0026 Trades",
        "subcategory": "Construction",
        "type": "Services"
      }
    ],
    "sg:phone": "+1 440 415 0473",
    "sg:postcode": "44004",
    "sg:province": "OH",
    "sg:tags": [
      "excavating",
      "contractor"
    ],
    "wof:name": "Boris Blacktop \u0026 Excavating",
    "wof:placetype": "venue"
  },
  "geometry": {"coordinates":[-80.879297,41.823894],"type":"Point"}
}
