{
  "type": "Feature",
  "properties": {
    "iso:country":"US",
    "sg:address":"6270 N Ridge Rd W",
    "sg:city":"Geneva",
    "sg:classifiers":[
        {
            "category":"Building & Trades",
            "subcategory":"Construction",
            "type":"Services"
        }
    ],
    "sg:phone":"+1 440 415 0473",
    "sg:postcode":"44004",
    "sg:province":"OH",
    "sg:tags":[
        "excavating",
        "contractor"
    ],
    "wof:name":"Boris Blacktop & Excavating",
    "wof:placetype":"venue"
},
  "geometry": {"coordinates":[-80.87929699999999,41.823894],"type":"Point"}
}