{
  "type": "Feature",
  "properties": {
    "iso:country":"US",
    "sg:address":"7947 Old US Hwy 35 SE",
    "sg:city":"Washington Court House",
    "sg:phone":"+1 740 335 5521",
    "sg:postcode":"43160",
    "sg:province":"OH",
    "sg:tags":[
        "farm",
        "corn",
        "wheat",
        "soybean"
    ],
    "wof:name":"Glen Geesling",
    "wof:placetype":"venue"
},
  "geometry": {"coordinates":[-83.337744,39.480089],"type":"Point"}
}