{
  "type": "Feature",
  "properties": {
    "addr:full":"464 Batavia Pike Cincinnati OH 45244",
    "addr:housenumber":"464",
    "addr:postcode":"45244",
    "addr:street":"Batavia Pike",
    "iso:country":"US",
    "sg:address":"464 Batavia Pike",
    "sg:city":"Cincinnati",
    "sg:classifiers":[
        {
            "category":"Wholesale",
            "subcategory":"Machinery & Supplies",
            "type":"Manufacturing & Wholesale Goods"
        }
    ],
    "sg:phone":"+1 513 528 5535",
    "sg:postcode":"45244",
    "sg:province":"OH",
    "sg:tags":[
        "equipment",
        "dairy"
    ],
    "wof:name":"Funke Filters Inc",
    "wof:placetype":"venue"
},
  "geometry": {"coordinates":[-84.30613700000001,39.11132],"type":"Point"}
}