{
  "type": "Feature",
  "properties": {
    "addr:full":"64 W Oakland Blvd Struthers OH 44471",
    "addr:housenumber":"64",
    "addr:postcode":"44471",
    "addr:street":"W Oakland Blvd",
    "iso:country":"US",
    "sg:address":"64 W Oakland Blvd",
    "sg:city":"Struthers",
    "sg:classifiers":[
        {
            "category":"Retail",
            "subcategory":"Repair Shop",
            "type":"Services"
        }
    ],
    "sg:phone":"+1 330 755 7820",
    "sg:postcode":"44471",
    "sg:province":"OH",
    "sg:tags":[
        "television",
        "radio"
    ],
    "wof:name":"Struthers Television Repair",
    "wof:placetype":"venue"
},
  "geometry": {"coordinates":[-80.583673,41.043575],"type":"Point"}
}