{
  "type": "Feature",
  "properties": {
    "addr:full":"860 Shady Ct Monroe OH 45050",
    "addr:housenumber":"860",
    "addr:postcode":"45050",
    "addr:street":"Shady Ct",
    "iso:country":"US",
    "sg:address":"860 Shady Ct",
    "sg:city":"Monroe",
    "sg:classifiers":[
        {
            "category":"Professional",
            "subcategory":"Business Services",
            "type":"Services"
        }
    ],
    "sg:phone":"+1 513 539 0124",
    "sg:postcode":"45050",
    "sg:province":"OH",
    "sg:tags":[
        "drafting"
    ],
    "wof:name":"Altercad Inc",
    "wof:placetype":"venue"
},
  "geometry": {"coordinates":[-84.364659,39.429339],"type":"Point"}
}