{
  "type": "Feature",
  "properties": {
    "addr:full": "400 N Sandusky Ave Upper Sandusky OH 43351",
    "addr:housenumber": "400",
    "addr:postcode": "43351",
    "addr:street": "N Sandusky Ave",
    "iso:country": "US",
    "sg:address": "400 N Sandusky Ave",
    "sg:city": "Upper Sandusky",
    "sg:classifiers": [
      {
        "category": "Banks \u0026 Credit Unions",
        "subcategory": "Bank",
        "type": "Services"
      }
    ],
    "sg:phone": "+1 419 294 5222",
    "sg:postcode": "43351",
    "sg:province": "OH",
    "wof:name": "Commercial Savings Bank",
    "wof:placetype": "venue"
  },
  "geometry": {"coordinates":[-83.281359,40.83293],"type":"Point"}
}
