{
  "type": "Feature",
  "properties": {
    "addr:full": "110 S Main St Dayton OH 45402",
    "addr:housenumber": "110",
    "addr:postcode": "45402",
    "addr:street": "S Main St",
    "iso:country": "US",
    "sg:address": "110 S Main St",
    "sg:city": "Dayton",
    "sg:classifiers": [
      {
        "category": "Shopping",
        "subcategory": "Hobbies, Toys, \u0026 Games",
        "type": "Retail Goods"
      }
    ],
    "sg:phone": "+1 937 898 2509",
    "sg:postcode": "45402",
    "sg:province": "OH",
    "sg:tags": [
      "supply"
    ],
    "sg:website": "www.notnecessarilyrum.com",
    "wof:name": "Shaygo Enterprises",
    "wof:placetype": "venue"
  },
  "geometry": {"coordinates":[-84.190993,39.757056],"type":"Point"}
}
