{
  "type": "Feature",
  "properties": {
    "addr:full": "33752 Vine St Eastlake OH 44095",
    "addr:housenumber": "33752",
    "addr:postcode": "44095",
    "addr:street": "Vine St",
    "iso:country": "US",
    "sg:address": "33752 Vine St",
    "sg:city": "Eastlake",
    "sg:classifiers": [
      {
        "category": "Restaurant",
        "type": "Food \u0026 Drink"
      }
    ],
    "sg:menulink": "http://www.allmenus.com/oh/eastlake/86322-little-caesars-pizza/menu/",
    "sg:phone": "+1 440 946 1640",
    "sg:postcode": "44095",
    "sg:province": "OH",
    "sg:tags": [
      "american",
      "pizza"
    ],
    "wof:name": "Little Caesar's Pizza",
    "wof:placetype": "venue"
  },
  "geometry": {"coordinates":[-81.447385,41.64234],"type":"Point"}
}
