{
  "type": "Feature",
  "properties": {
    "addr:full": "3655 State Rte 73 Hillsboro OH 45133",
    "addr:housenumber": "3655",
    "addr:postcode": "45133",
    "addr:street": "State Rte 73",
    "iso:country": "US",
    "sg:address": "3655 State Rte 73",
    "sg:city": "Hillsboro",
    "sg:classifiers": [
      {
        "category": "Health Services",
        "subcategory": "Doctor",
        "type": "Services"
      }
    ],
    "sg:phone": "+1 937 764 0333",
    "sg:postcode": "45133",
    "sg:province": "OH",
    "sg:tags": [
      "dentist"
    ],
    "wof:name": "Thomas Partridge DDS",
    "wof:placetype": "venue"
  },
  "geometry": {"coordinates":[-83.548655,39.115806],"type":"Point"}
}
