{
  "type": "Feature",
  "properties": {
    "addr:full": "11345 Century Cir W Cincinnati OH 45246",
    "addr:housenumber": "11345",
    "addr:postcode": "45246",
    "addr:street": "Century Cir W",
    "iso:country": "US",
    "sg:address": "11345 Century Cir W",
    "sg:city": "Cincinnati",
    "sg:classifiers": [
      {
        "category": "Wholesale",
        "subcategory": "Farm Supplies",
        "type": "Manufacturing \u0026 Wholesale Goods"
      }
    ],
    "sg:phone": "+1 513 671 8900",
    "sg:postcode": "45246",
    "sg:province": "OH",
    "sg:tags": [
      "bulb",
      "seed"
    ],
    "wof:name": "Beelen Bulb Co",
    "wof:placetype": "venue"
  },
  "geometry": {"coordinates":[-84.454611,39.282379],"type":"Point"}
}
