{
  "type": "Feature",
  "properties": {
    "iso:country":"US",
    "sg:address":"1801 E 9th St",
    "sg:city":"Cleveland",
    "sg:classifiers":[
        {
            "category":"Professional",
            "subcategory":"Lawyer & Legal Services",
            "type":"Services"
        }
    ],
    "sg:phone":"+1 216 452 9740",
    "sg:postcode":"44114",
    "sg:province":"OH",
    "sg:tags":[
        "litigation",
        "juvenile",
        "law",
        "family",
        "business",
        "attorney",
        "criminal"
    ],
    "sg:website":"http://www.jimmeimaris.com",
    "wof:name":"Meimaris James",
    "wof:placetype":"venue"
},
  "geometry": {"coordinates":[-81.688118,41.501701],"type":"Point"}
}