{
  "type": "Feature",
  "properties": {
    "iso:country":"US",
    "sg:address":"38294 Pelton Rd",
    "sg:city":"Willoughby",
    "sg:classifiers":[
        {
            "category":"Manufacturing",
            "subcategory":"Tools & Machinery",
            "type":"Manufacturing & Wholesale Goods"
        }
    ],
    "sg:phone":"+1 440 918 1701",
    "sg:postcode":"44094",
    "sg:province":"OH",
    "wof:name":"Us Molding Machine",
    "wof:placetype":"venue"
},
  "geometry": {"coordinates":[-81.40491900000001,41.647667],"type":"Point"}
}