{
  "type": "Feature",
  "properties": {
    "addr:full": "38294 Pelton Rd Willoughby OH 44094",
    "addr:housenumber": "38294",
    "addr:postcode": "44094",
    "addr:street": "Pelton Rd",
    "iso:country": "US",
    "sg:address": "38294 Pelton Rd",
    "sg:city": "Willoughby",
    "sg:classifiers": [
      {
        "category": "Manufacturing",
        "subcategory": "Tools \u0026 Machinery",
        "type": "Manufacturing \u0026 Wholesale Goods"
      }
    ],
    "sg:phone": "+1 440 918 1701",
    "sg:postcode": "44094",
    "sg:province": "OH",
    "wof:name": "Us Molding Machine",
    "wof:placetype": "venue"
  },
  "geometry": {"coordinates":[-81.404919,41.647667],"type":"Point"}
}
