{
  "type": "Feature",
  "properties": {
    "addr:full": "150 E Columbus St Lithopolis OH 43136",
    "addr:housenumber": "150",
    "addr:postcode": "43136",
    "addr:street": "E Columbus St",
    "iso:country": "US",
    "sg:address": "150 E Columbus St",
    "sg:city": "Lithopolis",
    "sg:classifiers": [
      {
        "category": "Education",
        "subcategory": "Library",
        "type": "Public Place"
      }
    ],
    "sg:phone": "+1 614 837 4765",
    "sg:postcode": "43136",
    "sg:province": "OH",
    "sg:website": "www.wagnalls.com",
    "wof:name": "Wagnalls Memorial Foundation",
    "wof:placetype": "venue"
  },
  "geometry": {"coordinates":[-82.806219,39.801956],"type":"Point"}
}
