{
  "type": "Feature",
  "properties": {
    "addr:full": "9225 Meadow Ln Cleveland OH 44141",
    "addr:housenumber": "9225",
    "addr:postcode": "44141",
    "addr:street": "Meadow Ln",
    "iso:country": "US",
    "sg:address": "9225 Meadow Ln",
    "sg:city": "Cleveland",
    "sg:classifiers": [
      {
        "category": "Professional",
        "subcategory": "Computer Services",
        "type": "Services"
      }
    ],
    "sg:phone": "+1 440 740 0480",
    "sg:postcode": "44141",
    "sg:province": "OH",
    "sg:tags": [
      "internet"
    ],
    "wof:name": "Pathfinder Bandwidth LLC",
    "wof:placetype": "venue"
  },
  "geometry": {"coordinates":[-81.620219,41.338694],"type":"Point"}
}
