{
  "type": "Feature",
  "properties": {
    "iso:country":"US",
    "sg:address":"3207 Youngstown Rd SE",
    "sg:city":"Warren",
    "sg:classifiers":[
        {
            "category":"Shopping",
            "type":"Retail Goods"
        }
    ],
    "sg:phone":"+1 330 369 1300",
    "sg:postcode":"44484",
    "sg:province":"OH",
    "sg:tags":[
        "stone",
        "merchandise"
    ],
    "wof:name":"Brehm Trophy",
    "wof:placetype":"venue"
},
  "geometry": {"coordinates":[-80.780788,41.220574],"type":"Point"}
}