{
  "type": "Feature",
  "properties": {
    "addr:full": "126 S Main St Dayton OH 45402",
    "addr:housenumber": "126",
    "addr:postcode": "45402",
    "addr:street": "S Main St",
    "iso:country": "US",
    "sg:address": "126 S Main St",
    "sg:city": "Dayton",
    "sg:classifiers": [
      {
        "category": "Shopping",
        "type": "Retail Goods"
      }
    ],
    "sg:phone": "+1 937 223 7921",
    "sg:postcode": "45402",
    "sg:province": "OH",
    "sg:tags": [
      "art",
      "gallery",
      "dealer"
    ],
    "wof:name": "Montgomery County Art",
    "wof:placetype": "venue"
  },
  "geometry": {"coordinates":[-84.191025,39.757285],"type":"Point"}
}
