{
  "type": "Feature",
  "properties": {
    "addr:full": "11911 Emerson Rd Apple Creek OH 44606",
    "addr:housenumber": "11911",
    "addr:postcode": "44606",
    "addr:street": "Emerson Rd",
    "iso:country": "US",
    "sg:address": "11911 Emerson Rd",
    "sg:city": "Apple Creek",
    "sg:phone": "+1 330 857 3027",
    "sg:postcode": "44606",
    "sg:province": "OH",
    "sg:tags": [
      "farm",
      "corn",
      "soybean"
    ],
    "wof:name": "Doyle Amstutz",
    "wof:placetype": "venue"
  },
  "geometry": {"coordinates":[-81.767012,40.741274],"type":"Point"}
}
