{
  "type": "Feature",
  "properties": {
    "addr:full": "9870 Killduff Rd Gambier OH 43022",
    "addr:postcode": "9870;43022",
    "addr:street": "Killduff Rd",
    "iso:country": "US",
    "sg:address": "9870 Killduff Rd",
    "sg:city": "Gambier",
    "sg:classifiers": [
      {
        "category": "Building \u0026 Trades",
        "subcategory": "Construction",
        "type": "Services"
      }
    ],
    "sg:phone": "+1 740 427 2030",
    "sg:postcode": "43022",
    "sg:province": "OH",
    "sg:tags": [
      "residential",
      "commercial",
      "painting",
      "contractor"
    ],
    "wof:name": "Mack Painting \u0026 Decorating",
    "wof:placetype": "venue"
  },
  "geometry": {"coordinates":[-82.353734,40.370806],"type":"Point"}
}
