{
  "type": "Feature",
  "properties": {
    "addr:full":"109 W Main St Conneaut OH 44030",
    "addr:housenumber":"109",
    "addr:postcode":"44030",
    "addr:street":"W Main St",
    "iso:country":"US",
    "sg:address":"109 W Main St",
    "sg:city":"Conneaut",
    "sg:classifiers":[
        {
            "category":"Organizations",
            "subcategory":"Religious Organization",
            "type":"Services"
        }
    ],
    "sg:phone":"+1 440 599 8857",
    "sg:postcode":"44030",
    "sg:province":"OH",
    "sg:tags":[
        "church"
    ],
    "wof:name":"Foursquare Gospel Church",
    "wof:placetype":"venue"
},
  "geometry": {"coordinates":[-80.582515,41.936978],"type":"Point"}
}