{
  "type": "Feature",
  "properties": {
    "iso:country":"US",
    "sg:address":"923 Starr Ave",
    "sg:city":"Toledo",
    "sg:classifiers":[
        {
            "category":"Restaurant",
            "type":"Food & Drink"
        }
    ],
    "sg:phone":"+1 419 693 4976",
    "sg:postcode":"43605",
    "sg:province":"OH",
    "sg:tags":[
        "eating"
    ],
    "wof:name":"Milianos Pizza",
    "wof:placetype":"venue"
},
  "geometry": {"coordinates":[-83.515944,41.643556],"type":"Point"}
}