{
  "type": "Feature",
  "properties": {
    "addr:full":"2057 Carabell Ave Cleveland OH 44107",
    "addr:housenumber":"2057",
    "addr:postcode":"44107",
    "addr:street":"Carabell Ave",
    "iso:country":"US",
    "sg:address":"2057 Carabell Ave",
    "sg:city":"Cleveland",
    "sg:classifiers":[
        {
            "category":"Professional",
            "subcategory":"Art Services",
            "type":"Services"
        }
    ],
    "sg:phone":"+1 216 529 0626",
    "sg:postcode":"44107",
    "sg:province":"OH",
    "sg:tags":[
        "artist"
    ],
    "wof:name":"Top Dog Studio",
    "wof:placetype":"venue"
},
  "geometry": {"coordinates":[-81.808566,41.475944],"type":"Point"}
}