{
  "type": "Feature",
  "properties": {
    "addr:full": "17525 Chagrin River Rd Chagrin Falls OH 44023",
    "addr:housenumber": "17525",
    "addr:postcode": "44023",
    "addr:street": "Chagrin River Rd",
    "iso:country": "US",
    "sg:address": "17525 Chagrin River Rd",
    "sg:city": "Chagrin Falls",
    "sg:classifiers": [
      {
        "category": "Building \u0026 Trades",
        "subcategory": "Electrical",
        "type": "Services"
      }
    ],
    "sg:phone": "+1 440 247 7644",
    "sg:postcode": "44023",
    "sg:province": "OH",
    "sg:tags": [
      "house",
      "electrical",
      "contractor"
    ],
    "wof:name": "Martin Giel",
    "wof:placetype": "venue"
  },
  "geometry": {"coordinates":[-81.387682,41.394475],"type":"Point"}
}
