{
  "type": "Feature",
  "properties": {
    "iso:country":"US",
    "sg:address":"17525 Chagrin River Rd",
    "sg:city":"Chagrin Falls",
    "sg:classifiers":[
        {
            "category":"Building & Trades",
            "subcategory":"Electrical",
            "type":"Services"
        }
    ],
    "sg:phone":"+1 440 247 7644",
    "sg:postcode":"44023",
    "sg:province":"OH",
    "sg:tags":[
        "house",
        "electrical",
        "contractor"
    ],
    "wof:name":"Martin Giel",
    "wof:placetype":"venue"
},
  "geometry": {"coordinates":[-81.387682,41.394475],"type":"Point"}
}