{
  "type": "Feature",
  "properties": {
    "addr:full": "3128 Midway Mall Elyria OH 44035",
    "addr:housenumber": "3128",
    "addr:postcode": "44035",
    "addr:street": "Midway Mall",
    "iso:country": "US",
    "sg:address": "3128 Midway Mall",
    "sg:city": "Elyria",
    "sg:classifiers": [
      {
        "category": "Shopping",
        "subcategory": "Music",
        "type": "Retail Goods"
      }
    ],
    "sg:phone": "+1 440 324 6777",
    "sg:postcode": "44035",
    "sg:province": "OH",
    "sg:tags": [
      "product",
      "prerecorded",
      "tape",
      "blank",
      "small",
      "video",
      "audio"
    ],
    "wof:name": "Suncoast",
    "wof:placetype": "venue"
  },
  "geometry": {"coordinates":[-82.112015,41.398775],"type":"Point"}
}
