{
  "type": "Feature",
  "properties": {
    "addr:full":"2919 W Market St Akron OH 44333",
    "addr:housenumber":"2919",
    "addr:postcode":"44333",
    "addr:street":"W Market St",
    "iso:country":"US",
    "sg:address":"2919 W Market St",
    "sg:city":"Akron",
    "sg:classifiers":[
        {
            "category":"Personal",
            "type":"Services"
        }
    ],
    "sg:phone":"+1 330 869 9604",
    "sg:postcode":"44333",
    "sg:province":"OH",
    "sg:tags":[
        "tuxedo",
        "formal",
        "wear",
        "rent"
    ],
    "wof:name":"Mayatux-Mayapparel",
    "wof:placetype":"venue"
},
  "geometry": {"coordinates":[-81.60915199999999,41.127806],"type":"Point"}
}