{
  "type": "Feature",
  "properties": {
    "iso:country":"US",
    "sg:address":"1951 State Ave",
    "sg:city":"Cincinnati",
    "sg:classifiers":[
        {
            "category":"Wholesale",
            "subcategory":"Construction Materials",
            "type":"Manufacturing & Wholesale Goods"
        }
    ],
    "sg:phone":"+1 513 251 7625",
    "sg:postcode":"45204",
    "sg:province":"OH",
    "sg:tags":[
        "concrete",
        "shape",
        "block"
    ],
    "wof:name":"First Rock Masonry Products",
    "wof:placetype":"venue"
},
  "geometry": {"coordinates":[-84.546116,39.118789],"type":"Point"}
}