{
  "type": "Feature",
  "properties": {
    "addr:full": "1351 Harris Rd Sheffield Vlg OH 44054",
    "addr:housenumber": "1351",
    "addr:postcode": "44054",
    "addr:street": "Harris Rd",
    "iso:country": "US",
    "sg:address": "1351 Harris Rd",
    "sg:city": "Sheffield Vlg",
    "sg:classifiers": [
      {
        "category": "Professional",
        "subcategory": "Business Services",
        "type": "Services"
      }
    ],
    "sg:phone": "+1 440 949 7942",
    "sg:postcode": "44054",
    "sg:province": "OH",
    "wof:name": "Polar Ice Art",
    "wof:placetype": "venue"
  },
  "geometry": {"coordinates":[-82.094838,41.465451],"type":"Point"}
}
