{
  "type": "Feature",
  "properties": {
    "iso:country":"US",
    "sg:address":"53 S Jay St",
    "sg:city":"West Milton",
    "sg:classifiers":[
        {
            "category":"Professional",
            "type":"Services"
        }
    ],
    "sg:phone":"+1 937 698 7251",
    "sg:postcode":"45383",
    "sg:province":"OH",
    "wof:name":"John C Mercer",
    "wof:placetype":"venue"
},
  "geometry": {"coordinates":[-84.332218,39.960343],"type":"Point"}
}