{
  "type": "Feature",
  "properties": {
    "addr:full":"5005 Cincinnati Brookville Rd Hamilton IN 45013",
    "addr:housenumber":"5005",
    "addr:postcode":"45013",
    "addr:street":"Cincinnati Brookville Rd",
    "iso:country":"US",
    "sg:address":"5005 Cincinnati Brookville Rd",
    "sg:city":"Hamilton",
    "sg:classifiers":[
        {
            "category":"Home & Garden",
            "subcategory":"Furniture",
            "type":"Retail Goods"
        }
    ],
    "sg:phone":"+1 513 738 0980",
    "sg:postcode":"45013",
    "sg:province":"IN",
    "wof:name":"Muenchen's Furniture Express",
    "wof:placetype":"venue"
},
  "geometry": {"coordinates":[-84.720865,39.329316],"type":"Point"}
}