{
  "type": "Feature",
  "properties": {
    "iso:country":"US",
    "sg:address":"4017 Colonel Glenn Hwy",
    "sg:city":"Dayton",
    "sg:classifiers":[
        {
            "category":"Autos & Motor Vehicles",
            "subcategory":"Automobile Sales",
            "type":"Retail Goods"
        }
    ],
    "sg:phone":"+1 937 429 9377",
    "sg:postcode":"45431",
    "sg:province":"OH",
    "sg:tags":[
        "used"
    ],
    "wof:name":"Luxury Car Connection Inc",
    "wof:placetype":"venue"
},
  "geometry": {"coordinates":[-84.085421,39.773634],"type":"Point"}
}