{
  "type": "Feature",
  "properties": {
    "addr:full":"3575 Maple Ave Zanesville OH 43701",
    "addr:housenumber":"3575",
    "addr:postcode":"43701",
    "addr:street":"Maple Ave",
    "iso:country":"US",
    "sg:address":"3575 Maple Ave",
    "sg:city":"Zanesville",
    "sg:classifiers":[
        {
            "category":"Shopping",
            "subcategory":"Clothing, Apparel, & Fashions",
            "type":"Retail Goods"
        }
    ],
    "sg:phone":"+1 740 450 9370",
    "sg:postcode":"43701",
    "sg:province":"OH",
    "sg:tags":[
        "family"
    ],
    "sg:website":"www.hottopic.com",
    "wof:name":"Hot Topic",
    "wof:placetype":"venue"
},
  "geometry": {"coordinates":[-82.02225199999999,39.986451],"type":"Point"}
}