{
  "type": "Feature",
  "properties": {
    "addr:full":"2586 Tiller Ln Columbus OH 43231",
    "addr:housenumber":"2586",
    "addr:postcode":"43231",
    "addr:street":"Tiller Ln",
    "iso:country":"US",
    "sg:address":"2586 Tiller Ln",
    "sg:city":"Columbus",
    "sg:classifiers":[
        {
            "category":"Building & Trades",
            "subcategory":"Construction",
            "type":"Services"
        }
    ],
    "sg:phone":"+1 614 899 7226",
    "sg:postcode":"43231",
    "sg:province":"OH",
    "sg:tags":[
        "contractor"
    ],
    "wof:name":"Reliable Waterproofing Inc",
    "wof:placetype":"venue"
},
  "geometry": {"coordinates":[-82.947582,40.097086],"type":"Point"}
}