{
  "type": "Feature",
  "properties": {
    "iso:country":"US",
    "sg:address":"5759 Ridge Rd",
    "sg:city":"Cleveland",
    "sg:classifiers":[
        {
            "category":"Bars & Pubs",
            "type":"Food & Drink"
        },
        {
            "category":"Travel",
            "subcategory":"Bed & Breakfast",
            "type":"Entertainment"
        }
    ],
    "sg:phone":"+1 440 884 0310",
    "sg:postcode":"44129",
    "sg:province":"OH",
    "sg:tags":[
        "tavern",
        "inn"
    ],
    "wof:name":"Ridgewood Inn",
    "wof:placetype":"venue"
},
  "geometry": {"coordinates":[-81.73455,41.405708],"type":"Point"}
}