{
  "type": "Feature",
  "properties": {
    "addr:full": "4241 US Hwy 23 Piketon OH 45661",
    "addr:housenumber": "4241",
    "addr:postcode": "45661",
    "addr:street": "Us Hwy 23",
    "iso:country": "US",
    "sg:address": "4241 US Hwy 23",
    "sg:city": "Piketon",
    "sg:classifiers": [
      {
        "category": "Manufacturing",
        "subcategory": "Tools \u0026 Machinery",
        "type": "Manufacturing \u0026 Wholesale Goods"
      }
    ],
    "sg:phone": "+1 740 289 2161",
    "sg:postcode": "45661",
    "sg:province": "OH",
    "sg:tags": [
      "air",
      "parts",
      "conditioning",
      "supply"
    ],
    "wof:name": "2-J Supply Co",
    "wof:placetype": "venue"
  },
  "geometry": {"coordinates":[-83.025769,39.019735],"type":"Point"}
}
