{
  "type": "Feature",
  "properties": {
    "iso:country":"US",
    "sg:address":"1616 Blue Ave",
    "sg:city":"Zanesville",
    "sg:classifiers":[
        {
            "category":"Organizations",
            "subcategory":"Religious Organization",
            "type":"Services"
        }
    ],
    "sg:phone":"+1 740 453 7988",
    "sg:postcode":"43701",
    "sg:province":"OH",
    "wof:name":"Faith United Methodist Church",
    "wof:placetype":"venue"
},
  "geometry": {"coordinates":[-82.016593,39.962619],"type":"Point"}
}