{
  "type": "Feature",
  "properties": {
    "addr:full":"8525 Clinton Rd Cleveland OH 44144",
    "addr:housenumber":"8525",
    "addr:postcode":"44144",
    "addr:street":"Clinton Rd",
    "iso:country":"US",
    "sg:address":"8525 Clinton Rd",
    "sg:city":"Cleveland",
    "sg:classifiers":[
        {
            "category":"Manufacturing",
            "subcategory":"Metals",
            "type":"Manufacturing & Wholesale Goods"
        }
    ],
    "sg:phone":"+1 248 354 1720",
    "sg:postcode":"44144",
    "sg:province":"OH",
    "sg:tags":[
        "aluminum",
        "primary",
        "producer"
    ],
    "wof:name":"Reynolds Aluminum Deutschland",
    "wof:placetype":"venue"
},
  "geometry": {"coordinates":[-81.74622599999999,41.453021],"type":"Point"}
}