{
  "type": "Feature",
  "properties": {
    "addr:full": "769 Rothrock Cir Copley OH 44321",
    "addr:housenumber": "769",
    "addr:postcode": "44321",
    "addr:street": "Rothrock Cir",
    "iso:country": "US",
    "sg:address": "769 Rothrock Cir",
    "sg:city": "Copley",
    "sg:classifiers": [
      {
        "category": "Banks \u0026 Credit Unions",
        "subcategory": "Investment Brokerage",
        "type": "Services"
      }
    ],
    "sg:phone": "+1 330 666 6728",
    "sg:postcode": "44321",
    "sg:province": "OH",
    "sg:tags": [
      "consultant",
      "planning",
      "financial"
    ],
    "wof:name": "Iconart",
    "wof:placetype": "venue"
  },
  "geometry": {"coordinates":[-81.64461,41.114156],"type":"Point"}
}
