{
  "type": "Feature",
  "properties": {
    "addr:full": "7721 Beechmont Ave Cincinnati OH 45255",
    "addr:housenumber": "7721",
    "addr:postcode": "45255",
    "addr:street": "Beechmont Ave",
    "iso:country": "US",
    "sg:address": "7721 Beechmont Ave",
    "sg:city": "Cincinnati",
    "sg:classifiers": [
      {
        "category": "Professional",
        "type": "Services"
      },
      {
        "category": "Professional",
        "subcategory": "Business Services",
        "type": "Services"
      },
      {
        "category": "Freight",
        "type": "Transportation"
      },
      {
        "category": "Professional",
        "subcategory": "Printing \u0026 Photocopies",
        "type": "Services"
      },
      {
        "category": "Shopping",
        "subcategory": "Stationery \u0026 Office Supplies",
        "type": "Retail Goods"
      },
      {
        "category": "Manufacturing",
        "subcategory": "Printing",
        "type": "Manufacturing \u0026 Wholesale Goods"
      },
      {
        "category": "Manufacturing",
        "subcategory": "Signs",
        "type": "Manufacturing \u0026 Wholesale Goods"
      }
    ],
    "sg:phone": "+1 513 624 6357",
    "sg:postcode": "45255",
    "sg:province": "OH",
    "sg:tags": [
      "machine",
      "document",
      "duplicating",
      "shipping",
      "materials-shipping",
      "packaging",
      "packing",
      "imaging",
      "copying",
      "digital",
      "copy"
    ],
    "sg:website": "www.fedex.com/us/office/",
    "wof:name": "FedEx Office Print \u0026 Ship Center",
    "wof:placetype": "venue"
  },
  "geometry": {"coordinates":[-84.343956,39.07206],"type":"Point"}
}
