{
  "type": "Feature",
  "properties": {
    "iso:country":"US",
    "sg:address":"4908 Van Epps Rd",
    "sg:city":"Cleveland",
    "sg:classifiers":[
        {
            "category":"Freight",
            "type":"Transportation"
        }
    ],
    "sg:phone":"+1 216 661 3861",
    "sg:postcode":"44131",
    "sg:province":"OH",
    "sg:tags":[
        "delivery"
    ],
    "wof:name":"R W Delivery Inc",
    "wof:placetype":"venue"
},
  "geometry": {"coordinates":[-81.67643200000001,41.425937],"type":"Point"}
}