{
  "type": "Feature",
  "properties": {
    "addr:full":"6106 Winton Rd Fairfield OH 45014",
    "addr:housenumber":"6106",
    "addr:postcode":"45014",
    "addr:street":"Winton Rd",
    "iso:country":"US",
    "sg:address":"6106 Winton Rd",
    "sg:city":"Fairfield",
    "sg:classifiers":[
        {
            "category":"Restaurant",
            "type":"Food & Drink"
        }
    ],
    "sg:menulink":"http://www.allmenus.com/oh/fairfield/78343-dominos-pizza/menu/",
    "sg:phone":"+1 513 829 7755",
    "sg:postcode":"45014",
    "sg:province":"OH",
    "sg:tags":[
        "american",
        "wing",
        "pizza"
    ],
    "wof:name":"Domino's Pizza",
    "wof:placetype":"venue"
},
  "geometry": {"coordinates":[-84.54183399999999,39.312982],"type":"Point"}
}