{
  "type": "Feature",
  "properties": {
    "iso:country":"US",
    "sg:address":"410 W 10th Ave",
    "sg:city":"Columbus",
    "sg:classifiers":[
        {
            "category":"Health Services",
            "subcategory":"Doctor",
            "type":"Services"
        }
    ],
    "sg:phone":"+1 614 293 8992",
    "sg:postcode":"43201",
    "sg:province":"OH",
    "sg:tags":[
        "medical"
    ],
    "wof:name":"Hagop S Mekhjian",
    "wof:placetype":"venue"
},
  "geometry": {"coordinates":[-83.021101,39.99401],"type":"Point"}
}