{
  "type": "Feature",
  "properties": {
    "iso:country":"US",
    "sg:address":"2837 Charter St",
    "sg:city":"Columbus",
    "sg:classifiers":[
        {
            "category":"Wholesale",
            "subcategory":"Groceries",
            "type":"Manufacturing & Wholesale Goods"
        }
    ],
    "sg:phone":"+1 614 529 9918",
    "sg:postcode":"43228",
    "sg:province":"OH",
    "sg:tags":[
        "food"
    ],
    "wof:name":"KCW Trade Inc",
    "wof:placetype":"venue"
},
  "geometry": {"coordinates":[-83.135024,40.009763],"type":"Point"}
}