{
  "type": "Feature",
  "properties": {
    "iso:country":"US",
    "sg:address":"3680 E Broad St",
    "sg:city":"Columbus",
    "sg:classifiers":[
        {
            "category":"Government",
            "subcategory":"Office",
            "type":"Public Place"
        }
    ],
    "sg:phone":"+1 614 235 1271",
    "sg:postcode":"43213",
    "sg:province":"OH",
    "sg:tags":[
        "city"
    ],
    "wof:name":"Town & Country City Inc",
    "wof:placetype":"venue"
},
  "geometry": {"coordinates":[-82.902648,39.973216],"type":"Point"}
}