{
  "type": "Feature",
  "properties": {
    "addr:full": "3680 E Broad St Columbus OH 43213",
    "addr:housenumber": "3680",
    "addr:postcode": "43213",
    "addr:street": "E Broad St",
    "iso:country": "US",
    "sg:address": "3680 E Broad St",
    "sg:city": "Columbus",
    "sg:classifiers": [
      {
        "category": "Government",
        "subcategory": "Office",
        "type": "Public Place"
      }
    ],
    "sg:phone": "+1 614 235 1271",
    "sg:postcode": "43213",
    "sg:province": "OH",
    "sg:tags": [
      "city"
    ],
    "wof:name": "Town \u0026 Country City Inc",
    "wof:placetype": "venue"
  },
  "geometry": {"coordinates":[-82.902648,39.973216],"type":"Point"}
}
