{
  "type": "Feature",
  "properties": {
    "iso:country":"US",
    "sg:address":"238 Academy Woods Dr",
    "sg:city":"Gahanna",
    "sg:classifiers":[
        {
            "category":"Real Estate",
            "subcategory":"Surveying",
            "type":"Services"
        }
    ],
    "sg:phone":"+1 614 471 0663",
    "sg:postcode":"43230",
    "sg:province":"OH",
    "sg:tags":[
        "surveyor"
    ],
    "wof:name":"Terra Surveying Svc LLC",
    "wof:placetype":"venue"
},
  "geometry": {"coordinates":[-82.871881,40.041322],"type":"Point"}
}