{
  "type": "Feature",
  "properties": {
    "addr:full":"5614 Autumn Wynd Ln Milford OH 45150",
    "addr:housenumber":"5614",
    "addr:postcode":"45150",
    "addr:street":"Autumn Wynd Ln",
    "iso:country":"US",
    "sg:address":"5614 Autumn Wynd Ln",
    "sg:city":"Milford",
    "sg:classifiers":[
        {
            "category":"Building & Trades",
            "subcategory":"Construction",
            "type":"Services"
        }
    ],
    "sg:phone":"+1 513 831 9263",
    "sg:postcode":"45150",
    "sg:province":"OH",
    "sg:tags":[
        "house"
    ],
    "wof:name":"Zaring Homes Inc",
    "wof:placetype":"venue"
},
  "geometry": {"coordinates":[-84.239846,39.1729],"type":"Point"}
}