{
  "type": "Feature",
  "properties": {
    "iso:country":"US",
    "sg:address":"5299 Baker Rd",
    "sg:city":"Delaware",
    "sg:classifiers":[
        {
            "category":"Building & Trades",
            "subcategory":"Cleaning & Sanitation",
            "type":"Services"
        }
    ],
    "sg:phone":"+1 740 362 1601",
    "sg:postcode":"43015",
    "sg:province":"OH",
    "sg:tags":[
        "janitor"
    ],
    "wof:name":"Commercial Building Svc",
    "wof:placetype":"venue"
},
  "geometry": {"coordinates":[-82.96746400000001,40.286414],"type":"Point"}
}