{
  "type": "Feature",
  "properties": {
    "addr:full": "5299 Baker Rd Delaware OH 43015",
    "addr:housenumber": "5299",
    "addr:postcode": "43015",
    "addr:street": "Baker Rd",
    "iso:country": "US",
    "sg:address": "5299 Baker Rd",
    "sg:city": "Delaware",
    "sg:classifiers": [
      {
        "category": "Building \u0026 Trades",
        "subcategory": "Cleaning \u0026 Sanitation",
        "type": "Services"
      }
    ],
    "sg:phone": "+1 740 362 1601",
    "sg:postcode": "43015",
    "sg:province": "OH",
    "sg:tags": [
      "janitor"
    ],
    "wof:name": "Commercial Building Svc",
    "wof:placetype": "venue"
  },
  "geometry": {"coordinates":[-82.967464,40.286414],"type":"Point"}
}
