{
  "type": "Feature",
  "properties": {
    "iso:country":"US",
    "sg:address":"6976 Meadowbrook Blvd",
    "sg:city":"Cleveland",
    "sg:classifiers":[
        {
            "category":"Building & Trades",
            "subcategory":"Construction",
            "type":"Services"
        }
    ],
    "sg:phone":"+1 440 888 0013",
    "sg:postcode":"44131",
    "sg:province":"OH",
    "sg:tags":[
        "roofing",
        "contractor"
    ],
    "wof:name":"Predey's Roofing",
    "wof:placetype":"venue"
},
  "geometry": {"coordinates":[-81.64236699999999,41.380336],"type":"Point"}
}