{
  "type": "Feature",
  "properties": {
    "addr:full": "6976 Meadowbrook Blvd Cleveland OH 44131",
    "addr:housenumber": "6976",
    "addr:postcode": "44131",
    "addr:street": "Meadowbrook Blvd",
    "iso:country": "US",
    "sg:address": "6976 Meadowbrook Blvd",
    "sg:city": "Cleveland",
    "sg:classifiers": [
      {
        "category": "Building \u0026 Trades",
        "subcategory": "Construction",
        "type": "Services"
      }
    ],
    "sg:phone": "+1 440 888 0013",
    "sg:postcode": "44131",
    "sg:province": "OH",
    "sg:tags": [
      "roofing",
      "contractor"
    ],
    "wof:name": "Predey's Roofing",
    "wof:placetype": "venue"
  },
  "geometry": {"coordinates":[-81.642367,41.380336],"type":"Point"}
}
