{
  "type": "Feature",
  "properties": {
    "addr:full": "68 Subler Dr Versailles OH 45380",
    "addr:housenumber": "68",
    "addr:postcode": "45380",
    "addr:street": "Subler Dr",
    "iso:country": "US",
    "sg:address": "68 Subler Dr",
    "sg:city": "Versailles",
    "sg:classifiers": [
      {
        "category": "Wholesale",
        "subcategory": "Construction Materials",
        "type": "Manufacturing \u0026 Wholesale Goods"
      }
    ],
    "sg:phone": "+1 937 526 3446",
    "sg:postcode": "45380",
    "sg:province": "OH",
    "sg:tags": [
      "pallet",
      "skid"
    ],
    "wof:name": "PFP",
    "wof:placetype": "venue"
  },
  "geometry": {"coordinates":[-84.461745,40.225528],"type":"Point"}
}
