{
  "type": "Feature",
  "properties": {
    "iso:country":"US",
    "sg:address":"68 Subler Dr",
    "sg:city":"Versailles",
    "sg:classifiers":[
        {
            "category":"Wholesale",
            "subcategory":"Construction Materials",
            "type":"Manufacturing & Wholesale Goods"
        }
    ],
    "sg:phone":"+1 937 526 3446",
    "sg:postcode":"45380",
    "sg:province":"OH",
    "sg:tags":[
        "pallet",
        "skid"
    ],
    "wof:name":"PFP",
    "wof:placetype":"venue"
},
  "geometry": {"coordinates":[-84.46174499999999,40.225528],"type":"Point"}
}