{
  "type": "Feature",
  "properties": {
    "addr:full":"1379 River St Columbus OH 43222",
    "addr:housenumber":"1379",
    "addr:postcode":"43222",
    "addr:street":"River St",
    "iso:country":"US",
    "sg:address":"1379 River St",
    "sg:city":"Columbus",
    "sg:classifiers":[
        {
            "category":"Building & Trades",
            "subcategory":"Plumbing",
            "type":"Services"
        }
    ],
    "sg:phone":"+1 614 279 3891",
    "sg:postcode":"43222",
    "sg:province":"OH",
    "sg:tags":[
        "shop",
        "repair",
        "contractor",
        "setting",
        "boiler",
        "welding"
    ],
    "wof:name":"Gurina Company",
    "wof:placetype":"venue"
},
  "geometry": {"coordinates":[-83.038982,39.963109],"type":"Point"}
}