{
  "type": "Feature",
  "properties": {
    "addr:full": "1570 Morse Rd Columbus OH 43229",
    "addr:housenumber": "1570",
    "addr:postcode": "43229",
    "addr:street": "Morse Rd",
    "iso:country": "US",
    "sg:address": "1570 Morse Rd",
    "sg:city": "Columbus",
    "sg:classifiers": [
      {
        "category": "Autos \u0026 Motor Vehicles",
        "subcategory": "Fuel \u0026 Gas Station",
        "type": "Retail Goods"
      }
    ],
    "sg:phone": "+1 614 846 7496",
    "sg:postcode": "43229",
    "sg:province": "OH",
    "sg:tags": [
      "oil"
    ],
    "wof:name": "Fast Max Sunoco",
    "wof:placetype": "venue"
  },
  "geometry": {"coordinates":[-82.979228,40.060746],"type":"Point"}
}
