{
  "type": "Feature",
  "properties": {
    "iso:country":"US",
    "sg:address":"1570 Morse Rd",
    "sg:city":"Columbus",
    "sg:classifiers":[
        {
            "category":"Autos & Motor Vehicles",
            "subcategory":"Fuel & Gas Station",
            "type":"Retail Goods"
        }
    ],
    "sg:phone":"+1 614 846 7496",
    "sg:postcode":"43229",
    "sg:province":"OH",
    "sg:tags":[
        "oil"
    ],
    "wof:name":"Fast Max Sunoco",
    "wof:placetype":"venue"
},
  "geometry": {"coordinates":[-82.97922800000001,40.060746],"type":"Point"}
}