{
  "type": "Feature",
  "properties": {
    "addr:full":"4236 Americana Dr Stow OH 44224",
    "addr:housenumber":"4236",
    "addr:postcode":"44224",
    "addr:street":"Americana Dr",
    "iso:country":"US",
    "sg:address":"4236 Americana Dr",
    "sg:city":"Stow",
    "sg:classifiers":[
        {
            "category":"Professional",
            "type":"Services"
        }
    ],
    "sg:phone":"+1 330 922 0347",
    "sg:postcode":"44224",
    "sg:province":"OH",
    "wof:name":"Brian Kline",
    "wof:placetype":"venue"
},
  "geometry": {"coordinates":[-81.49224,41.191112],"type":"Point"}
}