{
  "type": "Feature",
  "properties": {
    "addr:full": "50 Foxglen Rd Chagrin Falls OH 44022",
    "addr:housenumber": "50",
    "addr:postcode": "44022",
    "addr:street": "Foxglen Rd",
    "iso:country": "US",
    "sg:address": "50 Foxglen Rd",
    "sg:city": "Chagrin Falls",
    "sg:classifiers": [
      {
        "category": "Wholesale",
        "subcategory": "Wine \u0026 Distilled Alcoholic Beverages",
        "type": "Manufacturing \u0026 Wholesale Goods"
      }
    ],
    "sg:phone": "+1 440 914 0655",
    "sg:postcode": "44022",
    "sg:province": "OH",
    "wof:name": "Wineworks Ohio",
    "wof:placetype": "venue"
  },
  "geometry": {"coordinates":[-81.433085,41.435727],"type":"Point"}
}
