{
  "type": "Feature",
  "properties": {
    "iso:country":"US",
    "sg:address":"900 W Boundary St",
    "sg:city":"Perrysburg",
    "sg:classifiers":[
        {
            "category":"Manufacturing",
            "subcategory":"Tools & Machinery",
            "type":"Manufacturing & Wholesale Goods"
        }
    ],
    "sg:phone":"+1 419 873 0000",
    "sg:postcode":"43551",
    "sg:province":"OH",
    "sg:tags":[
        "control",
        "industrial",
        "system",
        "mfg"
    ],
    "wof:name":"Encompass Automation & Engnr",
    "wof:placetype":"venue"
},
  "geometry": {"coordinates":[-83.63449199999999,41.543332],"type":"Point"}
}