{
  "type": "Feature",
  "properties": {
    "addr:full": "900 W Boundary St Perrysburg OH 43551",
    "addr:housenumber": "900",
    "addr:postcode": "43551",
    "addr:street": "W Boundary St",
    "iso:country": "US",
    "sg:address": "900 W Boundary St",
    "sg:city": "Perrysburg",
    "sg:classifiers": [
      {
        "category": "Manufacturing",
        "subcategory": "Tools \u0026 Machinery",
        "type": "Manufacturing \u0026 Wholesale Goods"
      }
    ],
    "sg:phone": "+1 419 873 0000",
    "sg:postcode": "43551",
    "sg:province": "OH",
    "sg:tags": [
      "control",
      "industrial",
      "system",
      "mfg"
    ],
    "wof:name": "Encompass Automation \u0026 Engnr",
    "wof:placetype": "venue"
  },
  "geometry": {"coordinates":[-83.634492,41.543332],"type":"Point"}
}
