{
  "type": "Feature",
  "properties": {
    "addr:full": "551 Clarion Ave Holland OH 43528",
    "addr:housenumber": "551",
    "addr:postcode": "43528",
    "addr:street": "Clarion Ave",
    "iso:country": "US",
    "sg:address": "551 Clarion Ave",
    "sg:city": "Holland",
    "sg:classifiers": [
      {
        "category": "Real Estate",
        "subcategory": "Real Estate Operator",
        "type": "Services"
      }
    ],
    "sg:phone": "+1 419 867 7180",
    "sg:postcode": "43528",
    "sg:province": "OH",
    "sg:tags": [
      "building",
      "apartment"
    ],
    "wof:name": "Rodney D Rehm Apts",
    "wof:placetype": "venue"
  },
  "geometry": {"coordinates":[-83.69742,41.630766],"type":"Point"}
}
