{
  "type": "Feature",
  "properties": {
    "iso:country":"US",
    "sg:address":"402 N West St",
    "sg:city":"Hillsboro",
    "sg:classifiers":[
        {
            "category":"Home & Garden",
            "subcategory":"Building Materials",
            "type":"Retail Goods"
        }
    ],
    "sg:phone":"+1 937 393 5700",
    "sg:postcode":"45133",
    "sg:province":"OH",
    "sg:tags":[
        "glass",
        "window",
        "plate"
    ],
    "wof:name":"Ken's Glass",
    "wof:placetype":"venue"
},
  "geometry": {"coordinates":[-83.612861,39.206854],"type":"Point"}
}