{
  "type": "Feature",
  "properties": {
    "iso:country":"US",
    "sg:address":"5576 E 141st St",
    "sg:city":"Cleveland",
    "sg:classifiers":[
        {
            "category":"Building & Trades",
            "subcategory":"Construction",
            "type":"Services"
        }
    ],
    "sg:phone":"+1 216 662 0873",
    "sg:postcode":"44137",
    "sg:province":"OH",
    "sg:tags":[
        "home",
        "improvement"
    ],
    "wof:name":"Bestway Home Improvement",
    "wof:placetype":"venue"
},
  "geometry": {"coordinates":[-81.58409899999999,41.408196],"type":"Point"}
}