{
  "type": "Feature",
  "properties": {
    "iso:country":"US",
    "sg:address":"209 Main St",
    "sg:city":"Pleasant City",
    "sg:classifiers":[
        {
            "category":"Personal",
            "subcategory":"Beauty Salon",
            "type":"Services"
        }
    ],
    "sg:phone":"+1 740 685 2090",
    "sg:postcode":"43772",
    "sg:province":"OH",
    "wof:name":"Shear Design",
    "wof:placetype":"venue"
},
  "geometry": {"coordinates":[-81.546733,39.903704],"type":"Point"}
}