{
  "type": "Feature",
  "properties": {
    "iso:country":"US",
    "sg:address":"1306 Main St",
    "sg:city":"Cincinnati",
    "sg:classifiers":[
        {
            "category":"Real Estate",
            "subcategory":"Real Estate Services",
            "type":"Services"
        }
    ],
    "sg:phone":"+1 513 621 0402",
    "sg:postcode":"45202",
    "sg:province":"OH",
    "sg:tags":[
        "management",
        "condominium"
    ],
    "wof:name":"Good Fellows Hall Condo Assn.",
    "wof:placetype":"venue"
},
  "geometry": {"coordinates":[-84.511887,39.110123],"type":"Point"}
}