{
  "type": "Feature",
  "properties": {
    "iso:country":"US",
    "sg:address":"2285 Celina Rd",
    "sg:city":"St Marys",
    "sg:classifiers":[
        {
            "category":"Restaurant",
            "type":"Food & Drink"
        }
    ],
    "sg:phone":"+1 419 394 5456",
    "sg:postcode":"45885",
    "sg:province":"OH",
    "wof:name":"Bud's Pizza & Drive Thru",
    "wof:placetype":"venue"
},
  "geometry": {"coordinates":[-84.42124200000001,40.545263],"type":"Point"}
}