{
  "type": "Feature",
  "properties": {
    "addr:full":"9315 Felger Rd New Middletown OH 44442",
    "addr:housenumber":"9315",
    "addr:postcode":"44442",
    "addr:street":"Felger Rd",
    "iso:country":"US",
    "sg:address":"9315 Felger Rd",
    "sg:city":"New Middletown",
    "sg:classifiers":[
        {
            "category":"Farming",
            "subcategory":"Livestock Farm",
            "type":"Manufacturing & Wholesale Goods"
        }
    ],
    "sg:phone":"+1 330 542 2100",
    "sg:postcode":"44442",
    "sg:province":"OH",
    "sg:tags":[
        "feedlot",
        "field",
        "crop",
        "beef",
        "cattle"
    ],
    "wof:name":"Dorothy Lyda",
    "wof:placetype":"venue"
},
  "geometry": {"coordinates":[-80.526971,40.979723],"type":"Point"}
}