{
  "type": "Feature",
  "properties": {
    "iso:country":"US",
    "sg:address":"10705 Northfield Rd",
    "sg:city":"Northfield",
    "sg:classifiers":[
        {
            "category":"Retail",
            "subcategory":"Animal Services",
            "type":"Services"
        }
    ],
    "sg:phone":"+1 330 468 1819",
    "sg:postcode":"44067",
    "sg:province":"OH",
    "sg:tags":[
        "horse",
        "training"
    ],
    "wof:name":"John Oliverio Stable",
    "wof:placetype":"venue"
},
  "geometry": {"coordinates":[-81.526639,41.349944],"type":"Point"}
}