{
  "type": "Feature",
  "properties": {
    "addr:full":"507 Van Buren Ct Bowling Green OH 43402",
    "addr:housenumber":"507",
    "addr:postcode":"43402",
    "addr:street":"Van Buren Ct",
    "iso:country":"US",
    "sg:address":"507 Van Buren Ct",
    "sg:city":"Bowling Green",
    "sg:classifiers":[
        {
            "category":"Social Services",
            "type":"Services"
        }
    ],
    "sg:phone":"+1 419 353 1099",
    "sg:postcode":"43402",
    "sg:province":"OH",
    "sg:tags":[
        "organization",
        "welfare"
    ],
    "wof:name":"Arc Of Wood County",
    "wof:placetype":"venue"
},
  "geometry": {"coordinates":[-83.667326,41.38002],"type":"Point"}
}