{
  "type": "Feature",
  "properties": {
    "iso:country":"US",
    "sg:address":"1718 Springfield St",
    "sg:city":"Dayton",
    "sg:classifiers":[
        {
            "category":"Building & Trades",
            "subcategory":"Landscaping Services",
            "type":"Services"
        }
    ],
    "sg:phone":"+1 937 256 7560",
    "sg:postcode":"45403",
    "sg:province":"OH",
    "wof:name":"Atlantis Lawn & Landscaping",
    "wof:placetype":"venue"
},
  "geometry": {"coordinates":[-84.14006000000001,39.77769],"type":"Point"}
}