{
  "type": "Feature",
  "properties": {
    "addr:full": "4890 Duff Dr Cincinnati OH 45246",
    "addr:housenumber": "4890",
    "addr:postcode": "45246",
    "addr:street": "Duff Dr",
    "iso:country": "US",
    "sg:address": "4890 Duff Dr",
    "sg:city": "Cincinnati",
    "sg:classifiers": [
      {
        "category": "Professional",
        "subcategory": "Computer Services",
        "type": "Services"
      }
    ],
    "sg:phone": "+1 513 874 2586",
    "sg:postcode": "45246",
    "sg:province": "OH",
    "sg:tags": [
      "information",
      "retrieval"
    ],
    "wof:name": "AT\u0026T",
    "wof:placetype": "venue"
  },
  "geometry": {"coordinates":[-84.462888,39.31017],"type":"Point"}
}
