{
  "type": "Feature",
  "properties": {
    "iso:country":"US",
    "sg:address":"2649 E 130th St",
    "sg:city":"Cleveland",
    "sg:classifiers":[
        {
            "category":"Real Estate",
            "subcategory":"Architect",
            "type":"Services"
        }
    ],
    "sg:phone":"+1 216 421 2260",
    "sg:postcode":"44120",
    "sg:province":"OH",
    "wof:name":"Atlas Architectural Svc",
    "wof:placetype":"venue"
},
  "geometry": {"coordinates":[-81.591812,41.485722],"type":"Point"}
}