{
  "type": "Feature",
  "properties": {
    "addr:full": "51 Garfield Ln Cleveland OH 44108",
    "addr:housenumber": "51",
    "addr:postcode": "44108",
    "addr:street": "Garfield Ln",
    "iso:country": "US",
    "sg:address": "51 Garfield Ln",
    "sg:city": "Cleveland",
    "sg:classifiers": [
      {
        "category": "Professional",
        "type": "Services"
      }
    ],
    "sg:phone": "+1 216 268 2279",
    "sg:postcode": "44108",
    "sg:province": "OH",
    "wof:name": "Lana Products Limited",
    "wof:placetype": "venue"
  },
  "geometry": {"coordinates":[-81.621042,41.543181],"type":"Point"}
}
