{
  "type": "Feature",
  "properties": {
    "addr:full":"184 S Summit St Smithville OH 44677",
    "addr:housenumber":"184",
    "addr:postcode":"44677",
    "addr:street":"S Summit St",
    "iso:country":"US",
    "sg:address":"184 S Summit St",
    "sg:city":"Smithville",
    "sg:classifiers":[
        {
            "category":"Professional",
            "type":"Services"
        }
    ],
    "sg:phone":"+1 330 567 9421",
    "sg:postcode":"44677",
    "sg:province":"OH",
    "wof:name":"Lawman's Locker",
    "wof:placetype":"venue"
},
  "geometry": {"coordinates":[-81.86156699999999,40.860871],"type":"Point"}
}