{
  "type": "Feature",
  "properties": {
    "addr:full": "7345 Presley Ave Mentor OH 44060",
    "addr:housenumber": "7345",
    "addr:postcode": "44060",
    "addr:street": "Presley Ave",
    "iso:country": "US",
    "sg:address": "7345 Presley Ave",
    "sg:city": "Mentor",
    "sg:classifiers": [
      {
        "category": "Freight",
        "type": "Transportation"
      }
    ],
    "sg:phone": "+1 440 266 0136",
    "sg:postcode": "44060",
    "sg:province": "OH",
    "sg:tags": [
      "operator",
      "local",
      "trucking"
    ],
    "wof:name": "S\u0026L Trucking Inc",
    "wof:placetype": "venue"
  },
  "geometry": {"coordinates":[-81.341124,41.669889],"type":"Point"}
}
