{
  "type": "Feature",
  "properties": {
    "addr:full": "121 S Main St Mt Vernon OH 43050",
    "addr:housenumber": "121",
    "addr:postcode": "43050",
    "addr:street": "S Main St",
    "iso:country": "US",
    "sg:address": "121 S Main St",
    "sg:city": "Mt Vernon",
    "sg:classifiers": [
      {
        "category": "Home \u0026 Garden",
        "subcategory": "Household Appliances",
        "type": "Retail Goods"
      }
    ],
    "sg:phone": "+1 740 393 1806",
    "sg:postcode": "43050",
    "sg:province": "OH",
    "wof:name": "Herald's Appliances \u0026 Elec",
    "wof:placetype": "venue"
  },
  "geometry": {"coordinates":[-82.485608,40.392477],"type":"Point"}
}
