{
  "type": "Feature",
  "properties": {
    "iso:country":"US",
    "sg:address":"42478 National Rd",
    "sg:city":"Belmont",
    "sg:classifiers":[
        {
            "category":"Restaurant",
            "type":"Food & Drink"
        }
    ],
    "sg:phone":"+1 740 695 4040",
    "sg:postcode":"43718",
    "sg:province":"OH",
    "wof:name":"Kelly's Steakhouse",
    "wof:placetype":"venue"
},
  "geometry": {"coordinates":[-81.032614,40.069537],"type":"Point"}
}