{
  "type": "Feature",
  "properties": {
    "addr:full":"607 S State St West Harrison IN 45030",
    "addr:housenumber":"607",
    "addr:postcode":"45030",
    "addr:street":"S State St",
    "iso:country":"US",
    "sg:address":"607 S State St",
    "sg:city":"West Harrison",
    "sg:classifiers":[
        {
            "category":"Autos & Motor Vehicles",
            "subcategory":"Automobile Sales",
            "type":"Retail Goods"
        }
    ],
    "sg:phone":"+1 812 637 0600",
    "sg:postcode":"45030",
    "sg:province":"IN",
    "sg:tags":[
        "car",
        "dealer"
    ],
    "wof:name":"Daugherty Automotive",
    "wof:placetype":"venue"
},
  "geometry": {"coordinates":[-84.81997699999999,39.256313],"type":"Point"}
}