{
  "type": "Feature",
  "properties": {
    "addr:full":"7180 Agenbroad Rd Tipp City OH 45371",
    "addr:housenumber":"7180",
    "addr:postcode":"45371",
    "addr:street":"Agenbroad Rd",
    "iso:country":"US",
    "sg:address":"7180 Agenbroad Rd",
    "sg:city":"Tipp City",
    "sg:classifiers":[
        {
            "category":"Building & Trades",
            "subcategory":"Construction",
            "type":"Services"
        }
    ],
    "sg:phone":"+1 937 845 0324",
    "sg:postcode":"45371",
    "sg:province":"OH",
    "sg:tags":[
        "house"
    ],
    "wof:name":"Denlinger Construction",
    "wof:placetype":"venue"
},
  "geometry": {"coordinates":[-84.081323,39.925705],"type":"Point"}
}