{
  "type": "Feature",
  "properties": {
    "addr:full":"2601 Stanley Ave Dayton OH 45404",
    "addr:housenumber":"2601",
    "addr:postcode":"45404",
    "addr:street":"Stanley Ave",
    "iso:country":"US",
    "sg:address":"2601 Stanley Ave",
    "sg:city":"Dayton",
    "sg:classifiers":[
        {
            "category":"Building & Trades",
            "subcategory":"Electrical",
            "type":"Services"
        }
    ],
    "sg:phone":"+1 937 224 3445",
    "sg:postcode":"45404",
    "sg:province":"OH",
    "sg:tags":[
        "installs",
        "equipment",
        "retail",
        "telephone",
        "system"
    ],
    "sg:website":"www.reliablecomm.com",
    "wof:name":"Reliable Communications Inc",
    "wof:placetype":"venue"
},
  "geometry": {"coordinates":[-84.167765,39.784994],"type":"Point"}
}