{
  "type": "Feature",
  "properties": {
    "addr:full":"1355 S Hamilton Rd Columbus OH 43227",
    "addr:housenumber":"1355",
    "addr:postcode":"43227",
    "addr:street":"S Hamilton Rd",
    "iso:country":"US",
    "sg:address":"1355 S Hamilton Rd",
    "sg:city":"Columbus",
    "sg:classifiers":[
        {
            "category":"Organizations",
            "subcategory":"Religious Organization",
            "type":"Services"
        }
    ],
    "sg:phone":"+1 614 235 4995",
    "sg:postcode":"43227",
    "sg:province":"OH",
    "sg:tags":[
        "church"
    ],
    "wof:name":"Reformation Lutheran Church",
    "wof:placetype":"venue"
},
  "geometry": {"coordinates":[-82.87788,39.944871],"type":"Point"}
}