{
  "type": "Feature",
  "properties": {
    "addr:full": "712 Phillips Ave Toledo OH 43612",
    "addr:housenumber": "712",
    "addr:postcode": "43612",
    "addr:street": "Phillips Ave",
    "iso:country": "US",
    "sg:address": "712 Phillips Ave",
    "sg:city": "Toledo",
    "sg:classifiers": [
      {
        "category": "Retail",
        "subcategory": "Auto Repair",
        "type": "Services"
      }
    ],
    "sg:phone": "+1 419 478 8185",
    "sg:postcode": "43612",
    "sg:province": "OH",
    "sg:tags": [
      "body",
      "automobile",
      "top",
      "upholstery"
    ],
    "wof:name": "E V's Auto Tops \u0026 Seat Covers",
    "wof:placetype": "venue"
  },
  "geometry": {"coordinates":[-83.562285,41.691698],"type":"Point"}
}
