{
  "type": "Feature",
  "properties": {
    "addr:full":"10485 Eaton Pike New Lebanon OH 45345",
    "addr:housenumber":"10485",
    "addr:postcode":"45345",
    "addr:street":"Eaton Pike",
    "iso:country":"US",
    "sg:address":"10485 Eaton Pike",
    "sg:city":"New Lebanon",
    "sg:classifiers":[
        {
            "category":"Personal",
            "subcategory":"Beauty Salon",
            "type":"Services"
        }
    ],
    "sg:phone":"+1 937 687 2131",
    "sg:postcode":"45345",
    "sg:province":"OH",
    "sg:tags":[
        "shop"
    ],
    "wof:name":"Rainbo-Tique Hair Design",
    "wof:placetype":"venue"
},
  "geometry": {"coordinates":[-84.37576,39.745782],"type":"Point"}
}