{
  "type": "Feature",
  "properties": {
    "addr:full": "5544 State Rd Cleveland OH 44134",
    "addr:housenumber": "5544",
    "addr:postcode": "44134",
    "addr:street": "State Rd",
    "iso:country": "US",
    "sg:address": "5544 State Rd",
    "sg:city": "Cleveland",
    "sg:classifiers": [
      {
        "category": "Wholesale",
        "subcategory": "Machinery \u0026 Supplies",
        "type": "Manufacturing \u0026 Wholesale Goods"
      }
    ],
    "sg:phone": "+1 216 351 6565",
    "sg:postcode": "44134",
    "sg:province": "OH",
    "sg:tags": [
      "temperature",
      "for",
      "level",
      "rep",
      "flow",
      "devices",
      "v"
    ],
    "wof:name": "Carrig \u0026 Associates Inc",
    "wof:placetype": "venue"
  },
  "geometry": {"coordinates":[-81.710525,41.411167],"type":"Point"}
}
