{
  "type": "Feature",
  "properties": {
    "addr:full":"6115 N Spring St Ravenna OH 44266",
    "addr:housenumber":"6115",
    "addr:postcode":"44266",
    "addr:street":"N Spring St",
    "iso:country":"US",
    "sg:address":"6115 N Spring St",
    "sg:city":"Ravenna",
    "sg:classifiers":[
        {
            "category":"Government",
            "subcategory":"Office",
            "type":"Public Place"
        }
    ],
    "sg:phone":"+1 330 297 1998",
    "sg:postcode":"44266",
    "sg:province":"OH",
    "sg:tags":[
        "village"
    ],
    "wof:name":"Ravenna Twp Adm",
    "wof:placetype":"venue"
},
  "geometry": {"coordinates":[-81.27120499999999,41.157051],"type":"Point"}
}