{
  "type": "Feature",
  "properties": {
    "iso:country":"US",
    "sg:address":"222 Sheffield Center",
    "sg:city":"Lorain",
    "sg:classifiers":[
        {
            "category":"Real Estate",
            "subcategory":"Real Estate Operator",
            "type":"Services"
        }
    ],
    "sg:phone":"+1 440 233 5007",
    "sg:postcode":"44055",
    "sg:province":"OH",
    "sg:tags":[
        "mall",
        "shopping",
        "center"
    ],
    "wof:name":"Sheffield Enterprises LTD",
    "wof:placetype":"venue"
},
  "geometry": {"coordinates":[-82.149163,41.4184],"type":"Point"}
}