{
  "type": "Feature",
  "properties": {
    "iso:country":"US",
    "sg:address":"635 Ashwood Dr",
    "sg:city":"Mansfield",
    "sg:classifiers":[
        {
            "category":"Real Estate",
            "subcategory":"Real Estate Agent",
            "type":"Services"
        }
    ],
    "sg:phone":"+1 419 529 2534",
    "sg:postcode":"44906",
    "sg:province":"OH",
    "wof:name":"Malabar Realty",
    "wof:placetype":"venue"
},
  "geometry": {"coordinates":[-82.584377,40.741603],"type":"Point"}
}