{
  "type": "Feature",
  "properties": {
    "iso:country":"US",
    "sg:address":"601 Co Rd 46",
    "sg:city":"Toronto",
    "sg:classifiers":[
        {
            "category":"Building & Trades",
            "subcategory":"Construction",
            "type":"Services"
        }
    ],
    "sg:phone":"+1 740 544 5146",
    "sg:postcode":"43964",
    "sg:province":"OH",
    "sg:tags":[
        "house"
    ],
    "wof:name":"RAD S Home Improvements",
    "wof:placetype":"venue"
},
  "geometry": {"coordinates":[-80.645567,40.458828],"type":"Point"}
}