{
  "type": "Feature",
  "properties": {
    "addr:full":"927 Wheeling Ave Cambridge OH 43725",
    "addr:housenumber":"927",
    "addr:postcode":"43725",
    "addr:street":"Wheeling Ave",
    "iso:country":"US",
    "sg:address":"927 Wheeling Ave",
    "sg:city":"Cambridge",
    "sg:classifiers":[
        {
            "category":"Professional",
            "subcategory":"Business Services",
            "type":"Services"
        }
    ],
    "sg:phone":"+1 740 439 2238",
    "sg:postcode":"43725",
    "sg:province":"OH",
    "sg:tags":[
        "organizing"
    ],
    "wof:name":"Cambridge Main Street",
    "wof:placetype":"venue"
},
  "geometry": {"coordinates":[-81.58739199999999,40.024735],"type":"Point"}
}