{
  "type": "Feature",
  "properties": {
    "addr:full": "137 Walton St Struthers OH 44471",
    "addr:housenumber": "137",
    "addr:postcode": "44471",
    "addr:street": "Walton St",
    "iso:country": "US",
    "sg:address": "137 Walton St",
    "sg:city": "Struthers",
    "sg:classifiers": [
      {
        "category": "Manufacturing",
        "subcategory": "Tools \u0026 Machinery",
        "type": "Manufacturing \u0026 Wholesale Goods"
      }
    ],
    "sg:phone": "+1 330 755 0722",
    "sg:postcode": "44471",
    "sg:province": "OH",
    "sg:tags": [
      "die",
      "maker"
    ],
    "wof:name": "Youngstown Die Development Inc",
    "wof:placetype": "venue"
  },
  "geometry": {"coordinates":[-80.603269,41.062645],"type":"Point"}
}
