{
  "type": "Feature",
  "properties": {
    "addr:full":"929 Eastwind Dr Westerville OH 43081",
    "addr:housenumber":"929",
    "addr:postcode":"43081",
    "addr:street":"Eastwind Dr",
    "iso:country":"US",
    "sg:address":"929 Eastwind Dr",
    "sg:city":"Westerville",
    "sg:classifiers":[
        {
            "category":"Shopping",
            "subcategory":"Computers & Home Electronics",
            "type":"Retail Goods"
        }
    ],
    "sg:phone":"+1 614 523 1067",
    "sg:postcode":"43081",
    "sg:province":"OH",
    "sg:tags":[
        "software"
    ],
    "sg:website":"www.netmapanalytics.com",
    "wof:name":"Alta Analytics",
    "wof:placetype":"venue"
},
  "geometry": {"coordinates":[-82.918965,40.101845],"type":"Point"}
}