{
  "type": "Feature",
  "properties": {
    "iso:country":"US",
    "sg:address":"13515 Yarmouth Rd",
    "sg:city":"Pickerington",
    "sg:classifiers":[
        {
            "category":"Organizations",
            "subcategory":"Professional Association",
            "type":"Services"
        }
    ],
    "sg:phone":"+1 614 856 1900",
    "sg:postcode":"43147",
    "sg:province":"OH",
    "sg:website":"www.amajoin.org",
    "wof:name":"American Motorcyclist Assn",
    "wof:placetype":"venue"
},
  "geometry": {"coordinates":[-82.78389300000001,39.930587],"type":"Point"}
}