{
  "type": "Feature",
  "properties": {
    "addr:full": "13515 Yarmouth Rd Pickerington OH 43147",
    "addr:housenumber": "13515",
    "addr:postcode": "43147",
    "addr:street": "Yarmouth Rd",
    "iso:country": "US",
    "sg:address": "13515 Yarmouth Rd",
    "sg:city": "Pickerington",
    "sg:classifiers": [
      {
        "category": "Organizations",
        "subcategory": "Professional Association",
        "type": "Services"
      }
    ],
    "sg:phone": "+1 614 856 1900",
    "sg:postcode": "43147",
    "sg:province": "OH",
    "sg:website": "www.amajoin.org",
    "wof:name": "American Motorcyclist Assn",
    "wof:placetype": "venue"
  },
  "geometry": {"coordinates":[-82.783893,39.930587],"type":"Point"}
}
