{
  "type": "Feature",
  "properties": {
    "iso:country":"US",
    "sg:address":"2960 S Arlington Rd",
    "sg:city":"Akron",
    "sg:classifiers":[
        {
            "category":"Retail",
            "subcategory":"Auto Repair",
            "type":"Services"
        }
    ],
    "sg:phone":"+1 330 645 1314",
    "sg:postcode":"44312",
    "sg:province":"OH",
    "sg:tags":[
        "automotive"
    ],
    "wof:name":"Jiffy Lube",
    "wof:placetype":"venue"
},
  "geometry": {"coordinates":[-81.492411,40.991229],"type":"Point"}
}