{
  "type": "Feature",
  "properties": {
    "addr:full":"6315 Warrick St Cincinnati OH 45227",
    "addr:postcode":"6315;45227",
    "addr:street":"Warrick St",
    "iso:country":"US",
    "sg:address":"6315 Warrick St",
    "sg:city":"Cincinnati",
    "sg:classifiers":[
        {
            "category":"Health Services",
            "subcategory":"Health Practitioner",
            "type":"Services"
        }
    ],
    "sg:phone":"+1 513 272 3999",
    "sg:postcode":"45227",
    "sg:province":"OH",
    "sg:tags":[
        "nurse",
        "registry"
    ],
    "wof:name":"Trustaff",
    "wof:placetype":"venue"
},
  "geometry": {"coordinates":[-84.38583,39.159123],"type":"Point"}
}