{
  "type": "Feature",
  "properties": {
    "addr:full":"224 Pepperidge Dr Geneva OH 44041",
    "addr:housenumber":"224",
    "addr:postcode":"44041",
    "addr:street":"Pepperidge Dr",
    "iso:country":"US",
    "sg:address":"224 Pepperidge Dr",
    "sg:city":"Geneva",
    "sg:classifiers":[
        {
            "category":"Professional",
            "subcategory":"Lawyer & Legal Services",
            "type":"Services"
        }
    ],
    "sg:phone":"+1 440 466 7378",
    "sg:postcode":"44041",
    "sg:province":"OH",
    "sg:tags":[
        "attorney"
    ],
    "wof:name":"William A Kobelak",
    "wof:placetype":"venue"
},
  "geometry": {"coordinates":[-80.939772,41.78768],"type":"Point"}
}