{
  "type": "Feature",
  "properties": {
    "addr:full": "1106 E 74th St Cleveland OH 44103",
    "addr:housenumber": "1106",
    "addr:postcode": "44103",
    "addr:street": "E 74Th St",
    "iso:country": "US",
    "sg:address": "1106 E 74th St",
    "sg:city": "Cleveland",
    "sg:classifiers": [
      {
        "category": "Professional",
        "type": "Services"
      }
    ],
    "sg:phone": "+1 216 391 4119",
    "sg:postcode": "44103",
    "sg:province": "OH",
    "sg:tags": [
      "establishment"
    ],
    "wof:name": "I'm On Fire",
    "wof:placetype": "venue"
  },
  "geometry": {"coordinates":[-81.637298,41.524821],"type":"Point"}
}
