{
  "type": "Feature",
  "properties": {
    "addr:full": "1380 E 6th St Cleveland OH 44114",
    "addr:housenumber": "1380",
    "addr:postcode": "44114",
    "addr:street": "E 6Th St",
    "iso:country": "US",
    "sg:address": "1380 E 6th St",
    "sg:city": "Cleveland",
    "sg:classifiers": [
      {
        "category": "Education",
        "subcategory": "School",
        "type": "Public Place"
      }
    ],
    "sg:phone": "+1 216 431 4132",
    "sg:postcode": "44114",
    "sg:province": "OH",
    "wof:name": "Alfred A Benesch Elementary",
    "wof:placetype": "venue"
  },
  "geometry": {"coordinates":[-81.690919,41.502041],"type":"Point"}
}
