{
  "type": "Feature",
  "properties": {
    "addr:full": "610 E Broadway St Toledo OH 43605",
    "addr:housenumber": "610",
    "addr:postcode": "43605",
    "addr:street": "E Broadway St",
    "iso:country": "US",
    "sg:address": "610 E Broadway St",
    "sg:city": "Toledo",
    "sg:classifiers": [
      {
        "category": "Social Services",
        "type": "Services"
      }
    ],
    "sg:phone": "+1 419 691 9631",
    "sg:postcode": "43605",
    "sg:province": "OH",
    "sg:tags": [
      "youth",
      "organization",
      "center"
    ],
    "wof:name": "Glassmen Bingo Hall",
    "wof:placetype": "venue"
  },
  "geometry": {"coordinates":[-83.515808,41.638257],"type":"Point"}
}
