{
  "type": "Feature",
  "properties": {
    "addr:full":"312 Buckeye Blvd Port Clinton OH 43452",
    "addr:housenumber":"312",
    "addr:postcode":"43452",
    "addr:street":"Buckeye Blvd",
    "iso:country":"US",
    "sg:address":"312 Buckeye Blvd",
    "sg:city":"Port Clinton",
    "sg:classifiers":[
        {
            "category":"Home & Garden",
            "subcategory":"Building Materials",
            "type":"Retail Goods"
        }
    ],
    "sg:phone":"+1 419 734 1991",
    "sg:postcode":"43452",
    "sg:province":"OH",
    "sg:tags":[
        "glass",
        "window",
        "plate"
    ],
    "wof:name":"Erie Window",
    "wof:placetype":"venue"
},
  "geometry": {"coordinates":[-82.91324400000001,41.510343],"type":"Point"}
}