{
  "type": "Feature",
  "properties": {
    "addr:full":"11435 Princeton Pike Cincinnati OH 45246",
    "addr:housenumber":"11435",
    "addr:postcode":"45246",
    "addr:street":"Princeton Pike",
    "iso:country":"US",
    "sg:address":"11435 Princeton Pike",
    "sg:city":"Cincinnati",
    "sg:classifiers":[
        {
            "category":"Banks & Credit Unions",
            "subcategory":"Bank",
            "type":"Services"
        }
    ],
    "sg:phone":"+1 513 772 4520",
    "sg:postcode":"45246",
    "sg:province":"OH",
    "sg:tags":[
        "cashing",
        "check"
    ],
    "wof:name":"Check Smart",
    "wof:placetype":"venue"
},
  "geometry": {"coordinates":[-84.467169,39.285883],"type":"Point"}
}