{
  "type": "Feature",
  "properties": {
    "addr:full":"22061 Brister Rd Coolville OH 45723",
    "addr:postcode":"22061;45723",
    "addr:street":"Brister Rd",
    "iso:country":"US",
    "sg:address":"22061 Brister Rd",
    "sg:city":"Coolville",
    "sg:classifiers":[
        {
            "category":"Manufacturing",
            "subcategory":"Toys & Sporting Goods",
            "type":"Manufacturing & Wholesale Goods"
        }
    ],
    "sg:phone":"+1 740 667 3346",
    "sg:postcode":"45723",
    "sg:province":"OH",
    "sg:tags":[
        "mfg"
    ],
    "wof:name":"Myra Woomer",
    "wof:placetype":"venue"
},
  "geometry": {"coordinates":[-81.84233999999999,39.194862],"type":"Point"}
}