{
  "type": "Feature",
  "properties": {
    "addr:full": "9980 Newberry-Washington North Rd Piqua OH 45356",
    "addr:housenumber": "9980",
    "addr:postcode": "45356",
    "addr:street": "Newberry-Washington North Rd",
    "iso:country": "US",
    "sg:address": "9980 Newberry-Washington North Rd",
    "sg:city": "Piqua",
    "sg:classifiers": [
      {
        "category": "Organizations",
        "subcategory": "Membership Organization",
        "type": "Services"
      }
    ],
    "sg:phone": "+1 937 773 4581",
    "sg:postcode": "45356",
    "sg:province": "OH",
    "wof:name": "Pioneer Travelers Chapter",
    "wof:placetype": "venue"
  },
  "geometry": {"coordinates":[-84.317972,40.18052],"type":"Point"}
}
