{
  "type": "Feature",
  "properties": {
    "addr:full": "205 Liberty St West Liberty OH 43357",
    "addr:housenumber": "205",
    "addr:postcode": "43357",
    "addr:street": "Liberty St",
    "iso:country": "US",
    "sg:address": "205 Liberty St",
    "sg:city": "West Liberty",
    "sg:classifiers": [
      {
        "category": "Banks \u0026 Credit Unions",
        "subcategory": "Bank",
        "type": "Services"
      }
    ],
    "sg:phone": "+1 937 465 9050",
    "sg:postcode": "43357",
    "sg:province": "OH",
    "wof:name": "Champaign National Bank",
    "wof:placetype": "venue"
  },
  "geometry": {"coordinates":[-83.75187,40.25427],"type":"Point"}
}
