{
  "type": "Feature",
  "properties": {
    "iso:country":"US",
    "sg:address":"205 Liberty St",
    "sg:city":"West Liberty",
    "sg:classifiers":[
        {
            "category":"Banks & Credit Unions",
            "subcategory":"Bank",
            "type":"Services"
        }
    ],
    "sg:phone":"+1 937 465 9050",
    "sg:postcode":"43357",
    "sg:province":"OH",
    "wof:name":"Champaign National Bank",
    "wof:placetype":"venue"
},
  "geometry": {"coordinates":[-83.75187,40.25427],"type":"Point"}
}