{
  "type": "Feature",
  "properties": {
    "addr:full":"1075 Western Ave Chillicothe OH 45601",
    "addr:housenumber":"1075",
    "addr:postcode":"45601",
    "addr:street":"Western Ave",
    "iso:country":"US",
    "sg:address":"1075 Western Ave",
    "sg:city":"Chillicothe",
    "sg:classifiers":[
        {
            "category":"Professional",
            "type":"Services"
        }
    ],
    "sg:phone":"+1 740 775 2583",
    "sg:postcode":"45601",
    "sg:province":"OH",
    "wof:name":"Wendy Jo Ratliff Crowe",
    "wof:placetype":"venue"
},
  "geometry": {"coordinates":[-83.01399000000001,39.333093],"type":"Point"}
}