{
  "type": "Feature",
  "properties": {
    "iso:country":"US",
    "sg:address":"6056 Porter Rd",
    "sg:city":"North Olmsted",
    "sg:classifiers":[
        {
            "category":"Building & Trades",
            "subcategory":"Plumbing",
            "type":"Services"
        }
    ],
    "sg:phone":"+1 440 734 2916",
    "sg:postcode":"44070",
    "sg:province":"OH",
    "sg:tags":[
        "contractor"
    ],
    "wof:name":"David Sancer",
    "wof:placetype":"venue"
},
  "geometry": {"coordinates":[-81.928914,41.405105],"type":"Point"}
}