{
  "type": "Feature",
  "properties": {
    "iso:country":"US",
    "sg:address":"5807 Adams Ave",
    "sg:city":"Ashtabula",
    "sg:classifiers":[
        {
            "category":"Organizations",
            "subcategory":"Religious Organization",
            "type":"Services"
        }
    ],
    "sg:phone":"+1 440 993 0516",
    "sg:postcode":"44004",
    "sg:province":"OH",
    "sg:tags":[
        "church"
    ],
    "wof:name":"Harris Memorial Presbyterian",
    "wof:placetype":"venue"
},
  "geometry": {"coordinates":[-80.789891,41.855116],"type":"Point"}
}