{
  "type": "Feature",
  "properties": {
    "addr:full": "700 W Pete Rose Way Cincinnati OH 45203",
    "addr:housenumber": "700",
    "addr:postcode": "45203",
    "addr:street": "W Pete Rose Way",
    "iso:country": "US",
    "sg:address": "700 W Pete Rose Way",
    "sg:city": "Cincinnati",
    "sg:classifiers": [
      {
        "category": "Professional",
        "subcategory": "Advertising",
        "type": "Services"
      }
    ],
    "sg:phone": "+1 513 861 3668",
    "sg:postcode": "45203",
    "sg:province": "OH",
    "sg:tags": [
      "counselor",
      "agency"
    ],
    "sg:website": "www.barefootadvertising.com",
    "wof:name": "Barefoot Advertising Inc",
    "wof:placetype": "venue"
  },
  "geometry": {"coordinates":[-84.52336,39.095608],"type":"Point"}
}
