{
  "type": "Feature",
  "properties": {
    "addr:full": "3243 W Bath Rd Akron OH 44333",
    "addr:housenumber": "3243",
    "addr:postcode": "44333",
    "addr:street": "W Bath Rd",
    "iso:country": "US",
    "sg:address": "3243 W Bath Rd",
    "sg:city": "Akron",
    "sg:classifiers": [
      {
        "category": "Building \u0026 Trades",
        "subcategory": "Construction",
        "type": "Services"
      }
    ],
    "sg:phone": "+1 330 666 9166",
    "sg:postcode": "44333",
    "sg:province": "OH",
    "sg:tags": [
      "general",
      "contractor"
    ],
    "wof:name": "Wright's Construction",
    "wof:placetype": "venue"
  },
  "geometry": {"coordinates":[-81.610769,41.169208],"type":"Point"}
}
