{
  "type": "Feature",
  "properties": {
    "iso:country":"US",
    "sg:address":"3243 W Bath Rd",
    "sg:city":"Akron",
    "sg:classifiers":[
        {
            "category":"Building & Trades",
            "subcategory":"Construction",
            "type":"Services"
        }
    ],
    "sg:phone":"+1 330 666 9166",
    "sg:postcode":"44333",
    "sg:province":"OH",
    "sg:tags":[
        "general",
        "contractor"
    ],
    "wof:name":"Wright's Construction",
    "wof:placetype":"venue"
},
  "geometry": {"coordinates":[-81.610769,41.169208],"type":"Point"}
}