{
  "type": "Feature",
  "properties": {
    "addr:full": "7528 Broadview Rd Cleveland OH 44134",
    "addr:housenumber": "7528",
    "addr:postcode": "44134",
    "addr:street": "Broadview Rd",
    "iso:country": "US",
    "sg:address": "7528 Broadview Rd",
    "sg:city": "Cleveland",
    "sg:classifiers": [
      {
        "category": "Restaurant",
        "type": "Food \u0026 Drink"
      }
    ],
    "sg:phone": "+1 440 887 0818",
    "sg:postcode": "44134",
    "sg:province": "OH",
    "wof:name": "Mi Mi's Family Restaurant",
    "wof:placetype": "venue"
  },
  "geometry": {"coordinates":[-81.684655,41.360679],"type":"Point"}
}
