{
  "type": "Feature",
  "properties": {
    "addr:full": "6534 Akins Rd Cleveland OH 44133",
    "addr:housenumber": "6534",
    "addr:postcode": "44133",
    "addr:street": "Akins Rd",
    "iso:country": "US",
    "sg:address": "6534 Akins Rd",
    "sg:city": "Cleveland",
    "sg:classifiers": [
      {
        "category": "Home \u0026 Garden",
        "subcategory": "Garden Supply",
        "type": "Retail Goods"
      }
    ],
    "sg:phone": "+1 440 838 5006",
    "sg:postcode": "44133",
    "sg:province": "OH",
    "sg:tags": [
      "sprinkler"
    ],
    "wof:name": "Outdoor Delight Landscaping",
    "wof:placetype": "venue"
  },
  "geometry": {"coordinates":[-81.729768,41.306551],"type":"Point"}
}
