{
  "type": "Feature",
  "properties": {
    "addr:full":"542 W Union St Athens OH 45701",
    "addr:housenumber":"542",
    "addr:postcode":"45701",
    "addr:street":"W Union St",
    "iso:country":"US",
    "sg:address":"542 W Union St",
    "sg:city":"Athens",
    "sg:classifiers":[
        {
            "category":"Health Services",
            "subcategory":"Chiropractor",
            "type":"Services"
        }
    ],
    "sg:phone":"+1 740 589 2225",
    "sg:postcode":"45701",
    "sg:province":"OH",
    "wof:name":"Freed Chiropractic Clinic",
    "wof:placetype":"venue"
},
  "geometry": {"coordinates":[-82.124071,39.33112],"type":"Point"}
}