{
  "type": "Feature",
  "properties": {
    "addr:full": "2140 E Dorothy Ln Kettering OH 45420",
    "addr:housenumber": "2140",
    "addr:postcode": "45420",
    "addr:street": "E Dorothy Ln",
    "iso:country": "US",
    "sg:address": "2140 E Dorothy Ln",
    "sg:city": "Kettering",
    "sg:classifiers": [
      {
        "category": "Shopping",
        "subcategory": "Pharmacy",
        "type": "Retail Goods"
      }
    ],
    "sg:phone": "+1 937 395 0619",
    "sg:postcode": "45420",
    "sg:province": "OH",
    "sg:website": "www.walgreens.com",
    "wof:name": "Walgreens",
    "wof:placetype": "venue"
  },
  "geometry": {"coordinates":[-84.123905,39.702653],"type":"Point"}
}
