{
  "type": "Feature",
  "properties": {
    "addr:full": "11035 Napoleon Rd Bluffton OH 45817",
    "addr:housenumber": "11035",
    "addr:postcode": "45817",
    "addr:street": "Napoleon Rd",
    "iso:country": "US",
    "sg:address": "11035 Napoleon Rd",
    "sg:city": "Bluffton",
    "sg:phone": "+1 419 358 0609",
    "sg:postcode": "45817",
    "sg:province": "OH",
    "sg:tags": [
      "farm",
      "corn",
      "wheat",
      "soybean"
    ],
    "wof:name": "Althaus Farming",
    "wof:placetype": "venue"
  },
  "geometry": {"coordinates":[-83.976705,40.896916],"type":"Point"}
}
