{
  "type": "Feature",
  "properties": {
    "iso:country":"US",
    "sg:address":"306 Maple St",
    "sg:city":"Cincinnati",
    "sg:classifiers":[
        {
            "category":"Government",
            "subcategory":"Office",
            "type":"Public Place"
        }
    ],
    "sg:phone":"+1 513 242 3920",
    "sg:postcode":"45216",
    "sg:province":"OH",
    "sg:tags":[
        "city",
        "taxation"
    ],
    "wof:name":"Elmwood Place Commissioner-Tax",
    "wof:placetype":"venue"
},
  "geometry": {"coordinates":[-84.486541,39.186571],"type":"Point"}
}