{
  "type": "Feature",
  "properties": {
    "iso:country":"US",
    "sg:address":"1802 Central Ave",
    "sg:city":"Cleveland",
    "sg:classifiers":[
        {
            "category":"Retail",
            "subcategory":"Auto Rental",
            "type":"Services"
        }
    ],
    "sg:phone":"+1 216 664 0547",
    "sg:postcode":"44115",
    "sg:province":"OH",
    "sg:tags":[
        "renting",
        "automobile"
    ],
    "wof:name":"Thrifty Car Rental",
    "wof:placetype":"venue"
},
  "geometry": {"coordinates":[-81.677466,41.497357],"type":"Point"}
}