{
  "type": "Feature",
  "properties": {
    "addr:full": "198 River St Gallipolis OH 45631",
    "addr:housenumber": "198",
    "addr:postcode": "45631",
    "addr:street": "River St",
    "iso:country": "US",
    "sg:address": "198 River St",
    "sg:city": "Gallipolis",
    "sg:classifiers": [
      {
        "category": "Airline",
        "type": "Transportation"
      }
    ],
    "sg:phone": "+1 740 446 3698",
    "sg:postcode": "45631",
    "sg:province": "OH",
    "sg:tags": [
      "sc",
      "nonscheduled",
      "air"
    ],
    "wof:name": "Appalachian Aviation Inc",
    "wof:placetype": "venue"
  },
  "geometry": {"coordinates":[-82.147313,38.840765],"type":"Point"}
}
