{
  "type": "Feature",
  "properties": {
    "iso:country":"US",
    "sg:address":"454 Dry Lane Rd S",
    "sg:city":"La Rue",
    "sg:classifiers":[
        {
            "category":"Building & Trades",
            "subcategory":"Landscaping Services",
            "type":"Services"
        }
    ],
    "sg:phone":"+1 740 499 2264",
    "sg:postcode":"43332",
    "sg:province":"OH",
    "wof:name":"Marnas Mowing Service LLC",
    "wof:placetype":"venue"
},
  "geometry": {"coordinates":[-83.36178200000001,40.58051],"type":"Point"}
}