{
  "type": "Feature",
  "properties": {
    "addr:full": "454 Dry Lane Rd S La Rue OH 43332",
    "addr:housenumber": "454",
    "addr:postcode": "43332",
    "addr:street": "Dry Lane Rd S La Rue Oh",
    "iso:country": "US",
    "sg:address": "454 Dry Lane Rd S",
    "sg:city": "La Rue",
    "sg:classifiers": [
      {
        "category": "Building \u0026 Trades",
        "subcategory": "Landscaping Services",
        "type": "Services"
      }
    ],
    "sg:phone": "+1 740 499 2264",
    "sg:postcode": "43332",
    "sg:province": "OH",
    "wof:name": "Marnas Mowing Service LLC",
    "wof:placetype": "venue"
  },
  "geometry": {"coordinates":[-83.361782,40.58051],"type":"Point"}
}
