{
  "type": "Feature",
  "properties": {
    "addr:full": "4291 Manhattan Ave Brunswick OH 44212",
    "addr:housenumber": "4291",
    "addr:postcode": "44212",
    "addr:street": "Manhattan Ave",
    "iso:country": "US",
    "sg:address": "4291 Manhattan Ave",
    "sg:city": "Brunswick",
    "sg:classifiers": [
      {
        "category": "Building \u0026 Trades",
        "subcategory": "Cleaning \u0026 Sanitation",
        "type": "Services"
      }
    ],
    "sg:phone": "+1 330 220 9342",
    "sg:postcode": "44212",
    "sg:province": "OH",
    "sg:tags": [
      "house"
    ],
    "wof:name": "Molly Maids",
    "wof:placetype": "venue"
  },
  "geometry": {"coordinates":[-81.84044,41.23654],"type":"Point"}
}
