{
  "type": "Feature",
  "properties": {
    "iso:country":"US",
    "sg:address":"8314 Quincy Ave",
    "sg:city":"Cleveland",
    "sg:classifiers":[
        {
            "category":"Organizations",
            "subcategory":"Religious Organization",
            "type":"Services"
        }
    ],
    "sg:phone":"+1 216 421 8471",
    "sg:postcode":"44104",
    "sg:province":"OH",
    "sg:tags":[
        "church"
    ],
    "wof:name":"Victory In Praise Chr-God",
    "wof:placetype":"venue"
},
  "geometry": {"coordinates":[-81.628629,41.493333],"type":"Point"}
}