{
  "type": "Feature",
  "properties": {
    "addr:full": "1363 Cherrywood Way Uniontown OH 44685",
    "addr:housenumber": "1363",
    "addr:postcode": "44685",
    "addr:street": "Cherrywood Way",
    "iso:country": "US",
    "sg:address": "1363 Cherrywood Way",
    "sg:city": "Uniontown",
    "sg:classifiers": [
      {
        "category": "Professional",
        "subcategory": "Advertising",
        "type": "Services"
      }
    ],
    "sg:phone": "+1 330 896 0400",
    "sg:postcode": "44685",
    "sg:province": "OH",
    "sg:tags": [
      "counselor"
    ],
    "wof:name": "Bender Advertising Inc",
    "wof:placetype": "venue"
  },
  "geometry": {"coordinates":[-81.478718,40.952302],"type":"Point"}
}
