{
  "type": "Feature",
  "properties": {
    "addr:full":"13159 Woodworth Rd New Springfield OH 44443",
    "addr:housenumber":"13159",
    "addr:postcode":"44443",
    "addr:street":"Woodworth Rd",
    "iso:country":"US",
    "sg:address":"13159 Woodworth Rd",
    "sg:city":"New Springfield",
    "sg:classifiers":[
        {
            "category":"Home & Garden",
            "subcategory":"Garden Supply",
            "type":"Retail Goods"
        }
    ],
    "sg:phone":"+1 330 549 2828",
    "sg:postcode":"44443",
    "sg:province":"OH",
    "sg:tags":[
        "landscaping",
        "equipment"
    ],
    "wof:name":"AAA Topsoil",
    "wof:placetype":"venue"
},
  "geometry": {"coordinates":[-80.621236,40.927364],"type":"Point"}
}