{
  "type": "Feature",
  "properties": {
    "addr:full":"749 Commercial Ave SW New Philadelphia OH 44663",
    "addr:housenumber":"749",
    "addr:postcode":"44663",
    "addr:street":"Commercial Ave Sw",
    "iso:country":"US",
    "sg:address":"749 Commercial Ave SW",
    "sg:city":"New Philadelphia",
    "sg:classifiers":[
        {
            "category":"Organizations",
            "subcategory":"Religious Organization",
            "type":"Services"
        }
    ],
    "sg:phone":"+1 330 339 1252",
    "sg:postcode":"44663",
    "sg:province":"OH",
    "sg:tags":[
        "church"
    ],
    "wof:name":"Church Of Christ",
    "wof:placetype":"venue"
},
  "geometry": {"coordinates":[-81.462416,40.482444],"type":"Point"}
}