{
  "type": "Feature",
  "properties": {
    "iso:country":"US",
    "sg:address":"400 Metro Pl N",
    "sg:city":"Dublin",
    "sg:classifiers":[
        {
            "category":"Professional",
            "type":"Services"
        }
    ],
    "sg:phone":"+1 614 764 5609",
    "sg:postcode":"43017",
    "sg:province":"OH",
    "sg:tags":[
        "establishment"
    ],
    "wof:name":"ACEUSA",
    "wof:placetype":"venue"
},
  "geometry": {"coordinates":[-83.129082,40.09598],"type":"Point"}
}