{
  "type": "Feature",
  "properties": {
    "addr:full": "625 Reid Ave Lorain OH 44052",
    "addr:housenumber": "625",
    "addr:postcode": "44052",
    "addr:street": "Reid Ave",
    "iso:country": "US",
    "sg:address": "625 Reid Ave",
    "sg:city": "Lorain",
    "sg:classifiers": [
      {
        "category": "Organizations",
        "subcategory": "Non-profit Organization",
        "type": "Services"
      }
    ],
    "sg:phone": "+1 440 244 4566",
    "sg:postcode": "44052",
    "sg:province": "OH",
    "sg:tags": [
      "information",
      "alcoholism",
      "treatment"
    ],
    "wof:name": "Lorain County Alcohol \u0026 Drug",
    "wof:placetype": "venue"
  },
  "geometry": {"coordinates":[-82.176367,41.464385],"type":"Point"}
}
