{
  "type": "Feature",
  "properties": {
    "addr:full": "3718 Settle Rd Cincinnati OH 45227",
    "addr:housenumber": "3718",
    "addr:postcode": "45227",
    "addr:street": "Settle Rd",
    "iso:country": "US",
    "sg:address": "3718 Settle Rd",
    "sg:city": "Cincinnati",
    "sg:classifiers": [
      {
        "category": "Organizations",
        "subcategory": "Professional Association",
        "type": "Services"
      }
    ],
    "sg:phone": "+1 513 271 8519",
    "sg:postcode": "45227",
    "sg:province": "OH",
    "wof:name": "Guild Of Carillonneurs",
    "wof:placetype": "venue"
  },
  "geometry": {"coordinates":[-84.386394,39.145523],"type":"Point"}
}
