{
  "type": "Feature",
  "properties": {
    "iso:country":"US",
    "sg:address":"2167 Ross Rd",
    "sg:city":"Greenville",
    "sg:classifiers":[
        {
            "category":"Professional",
            "type":"Services"
        }
    ],
    "sg:phone":"+1 937 547 0710",
    "sg:postcode":"45331",
    "sg:province":"OH",
    "sg:tags":[
        "personal"
    ],
    "wof:name":"Hunt Butcher Shop",
    "wof:placetype":"venue"
},
  "geometry": {"coordinates":[-84.71017999999999,40.062368],"type":"Point"}
}