{
  "type": "Feature",
  "properties": {
    "iso:country":"US",
    "sg:address":"8566 Twp Rd 95",
    "sg:city":"Findlay",
    "sg:classifiers":[
        {
            "category":"Home & Garden",
            "subcategory":"Mobile Homes",
            "type":"Retail Goods"
        }
    ],
    "sg:phone":"+1 419 422 1421",
    "sg:postcode":"45840",
    "sg:province":"OH",
    "wof:name":"Lsm Dream Homes LLC",
    "wof:placetype":"venue"
},
  "geometry": {"coordinates":[-83.727335,41.073102],"type":"Point"}
}