{
  "type": "Feature",
  "properties": {
    "addr:full":"3710 Southern Ave Cincinnati OH 45227",
    "addr:housenumber":"3710",
    "addr:postcode":"45227",
    "addr:street":"Southern Ave",
    "iso:country":"US",
    "sg:address":"3710 Southern Ave",
    "sg:city":"Cincinnati",
    "sg:classifiers":[
        {
            "category":"Professional",
            "subcategory":"Management & Consulting",
            "type":"Services"
        },
        {
            "category":"Banks & Credit Unions",
            "subcategory":"Investment Brokerage",
            "type":"Services"
        }
    ],
    "sg:phone":"+1 513 527 7000",
    "sg:postcode":"45227",
    "sg:province":"OH",
    "sg:tags":[
        "planning",
        "retirement"
    ],
    "wof:name":"Futures Planning Group",
    "wof:placetype":"venue"
},
  "geometry": {"coordinates":[-84.392471,39.142183],"type":"Point"}
}