{
  "type": "Feature",
  "properties": {
    "iso:country":"US",
    "sg:address":"4708 Derbyshire Dr",
    "sg:city":"Cleveland",
    "sg:classifiers":[
        {
            "category":"Freight",
            "type":"Transportation"
        }
    ],
    "sg:phone":"+1 216 581 1356",
    "sg:postcode":"44128",
    "sg:province":"OH",
    "sg:tags":[
        "operator",
        "local",
        "trucking"
    ],
    "wof:name":"R J & R Edwards Trucking",
    "wof:placetype":"venue"
},
  "geometry": {"coordinates":[-81.522688,41.431171],"type":"Point"}
}