{
  "type": "Feature",
  "properties": {
    "addr:full":"2222 Belvedere Dr Toledo OH 43614",
    "addr:housenumber":"2222",
    "addr:postcode":"43614",
    "addr:street":"Belvedere Dr",
    "iso:country":"US",
    "sg:address":"2222 Belvedere Dr",
    "sg:city":"Toledo",
    "sg:classifiers":[
        {
            "category":"Building & Trades",
            "subcategory":"Landscaping Services",
            "type":"Services"
        }
    ],
    "sg:phone":"+1 419 381 1892",
    "sg:postcode":"43614",
    "sg:province":"OH",
    "sg:tags":[
        "lawn",
        "garden"
    ],
    "wof:name":"JB Lawn Service",
    "wof:placetype":"venue"
},
  "geometry": {"coordinates":[-83.64507999999999,41.599423],"type":"Point"}
}