{
  "type": "Feature",
  "properties": {
    "iso:country":"US",
    "sg:address":"395 E Broad St",
    "sg:city":"Columbus",
    "sg:classifiers":[
        {
            "category":"Health Services",
            "subcategory":"Clinic",
            "type":"Services"
        }
    ],
    "sg:phone":"+1 614 221 3370",
    "sg:postcode":"43215",
    "sg:province":"OH",
    "sg:tags":[
        "organization",
        "maintenance"
    ],
    "sg:website":"www.care-source.com",
    "wof:name":"Caresource",
    "wof:placetype":"venue"
},
  "geometry": {"coordinates":[-82.990848,39.963254],"type":"Point"}
}