{
  "type": "Feature",
  "properties": {
    "addr:full": "3050 N Sulphur Springs Rd West Alexandria OH 45381",
    "addr:housenumber": "3050",
    "addr:postcode": "45381",
    "addr:street": "N Sulphur Springs Rd",
    "iso:country": "US",
    "sg:address": "3050 N Sulphur Springs Rd",
    "sg:city": "West Alexandria",
    "sg:classifiers": [
      {
        "category": "Farming",
        "subcategory": "Farm",
        "type": "Manufacturing \u0026 Wholesale Goods"
      }
    ],
    "sg:phone": "+1 937 833 5799",
    "sg:postcode": "45381",
    "sg:province": "OH",
    "sg:tags": [
      "crop",
      "general"
    ],
    "wof:name": "Randall Bowman Farms Inc",
    "wof:placetype": "venue"
  },
  "geometry": {"coordinates":[-84.461157,39.809564],"type":"Point"}
}
