{
  "type": "Feature",
  "properties": {
    "addr:full": "1118 Pendleton St Cincinnati OH 45202",
    "addr:housenumber": "1118",
    "addr:postcode": "45202",
    "addr:street": "Pendleton St",
    "iso:country": "US",
    "sg:address": "1118 Pendleton St",
    "sg:city": "Cincinnati",
    "sg:classifiers": [
      {
        "category": "Professional",
        "subcategory": "Lawyer \u0026 Legal Services",
        "type": "Services"
      }
    ],
    "sg:phone": "+1 513 421 9797",
    "sg:postcode": "45202",
    "sg:province": "OH",
    "sg:tags": [
      "attorney"
    ],
    "wof:name": "Houston Warren \u0026 Griffin",
    "wof:placetype": "venue"
  },
  "geometry": {"coordinates":[-84.506707,39.109845],"type":"Point"}
}
