{
  "type": "Feature",
  "properties": {
    "iso:country":"US",
    "sg:address":"700 S Main St",
    "sg:city":"Findlay",
    "sg:classifiers":[
        {
            "category":"Ice Cream",
            "type":"Food & Drink"
        }
    ],
    "sg:menulink":"http://www.allmenus.com/oh/findlay/165281-dairy-queen/menu/",
    "sg:phone":"+1 419 424 0722",
    "sg:postcode":"45840",
    "sg:province":"OH",
    "sg:tags":[
        "burger",
        "american"
    ],
    "wof:name":"Dairy Queen",
    "wof:placetype":"venue"
},
  "geometry": {"coordinates":[-83.650299,41.034335],"type":"Point"}
}