{
  "type": "Feature",
  "properties": {
    "addr:full": "700 S Main St Findlay OH 45840",
    "addr:housenumber": "700",
    "addr:postcode": "45840",
    "addr:street": "S Main St",
    "iso:country": "US",
    "sg:address": "700 S Main St",
    "sg:city": "Findlay",
    "sg:classifiers": [
      {
        "category": "Ice Cream",
        "type": "Food \u0026 Drink"
      }
    ],
    "sg:menulink": "http://www.allmenus.com/oh/findlay/165281-dairy-queen/menu/",
    "sg:phone": "+1 419 424 0722",
    "sg:postcode": "45840",
    "sg:province": "OH",
    "sg:tags": [
      "burger",
      "american"
    ],
    "wof:name": "Dairy Queen",
    "wof:placetype": "venue"
  },
  "geometry": {"coordinates":[-83.650299,41.034335],"type":"Point"}
}
