{
  "type": "Feature",
  "properties": {
    "iso:country":"US",
    "sg:address":"3660 Shaw Ave",
    "sg:city":"Cincinnati",
    "sg:classifiers":[
        {
            "category":"Wholesale",
            "subcategory":"Machinery & Supplies",
            "type":"Manufacturing & Wholesale Goods"
        }
    ],
    "sg:phone":"+1 513 321 8925",
    "sg:postcode":"45208",
    "sg:province":"OH",
    "sg:tags":[
        "equipment",
        "construction"
    ],
    "wof:name":"Tricon Scaffolding Inc",
    "wof:placetype":"venue"
},
  "geometry": {"coordinates":[-84.439617,39.144522],"type":"Point"}
}