{
  "type": "Feature",
  "properties": {
    "addr:full": "8787 Denman Rd Lexington OH 44904",
    "addr:housenumber": "8787",
    "addr:postcode": "44904",
    "addr:street": "Denman Rd",
    "iso:country": "US",
    "sg:address": "8787 Denman Rd",
    "sg:city": "Lexington",
    "sg:classifiers": [
      {
        "category": "Building \u0026 Trades",
        "subcategory": "Landscaping Services",
        "type": "Services"
      }
    ],
    "sg:phone": "+1 419 884 8874",
    "sg:postcode": "44904",
    "sg:province": "OH",
    "sg:tags": [
      "landscape",
      "contractor"
    ],
    "wof:name": "Lawn Salon",
    "wof:placetype": "venue"
  },
  "geometry": {"coordinates":[-82.632954,40.67722],"type":"Point"}
}
