{
  "type": "Feature",
  "properties": {
    "addr:full": "2714 Tytus Ave Middletown OH 45042",
    "addr:housenumber": "2714",
    "addr:postcode": "45042",
    "addr:street": "Tytus Ave",
    "iso:country": "US",
    "sg:address": "2714 Tytus Ave",
    "sg:city": "Middletown",
    "sg:classifiers": [
      {
        "category": "Retail",
        "subcategory": "Repair Shop",
        "type": "Services"
      }
    ],
    "sg:phone": "+1 513 422 1914",
    "sg:postcode": "45042",
    "sg:province": "OH",
    "sg:tags": [
      "welding"
    ],
    "wof:name": "Orman's Welding Ctr",
    "wof:placetype": "venue"
  },
  "geometry": {"coordinates":[-84.377032,39.528365],"type":"Point"}
}
