{
  "type": "Feature",
  "properties": {
    "iso:country":"US",
    "sg:address":"1440 Snow Rd",
    "sg:city":"Cleveland",
    "sg:classifiers":[
        {
            "category":"Professional",
            "subcategory":"Employment Agencies",
            "type":"Services"
        }
    ],
    "sg:phone":"+1 216 749 2820",
    "sg:postcode":"44134",
    "sg:province":"OH",
    "sg:tags":[
        "consultant",
        "search",
        "executive"
    ],
    "sg:website":"www.searchlinejobs.com",
    "wof:name":"Searchline Services",
    "wof:placetype":"venue"
},
  "geometry": {"coordinates":[-81.69060399999999,41.405327],"type":"Point"}
}