{
  "type": "Feature",
  "properties": {
    "iso:country":"US",
    "sg:address":"626 Angiline Dr",
    "sg:city":"Youngstown",
    "sg:classifiers":[
        {
            "category":"Shopping",
            "subcategory":"Clothing, Apparel, & Fashions",
            "type":"Retail Goods"
        }
    ],
    "sg:phone":"+1 330 726 3896",
    "sg:postcode":"44512",
    "sg:province":"OH",
    "wof:name":"Jbm Enterprises Inc",
    "wof:placetype":"venue"
},
  "geometry": {"coordinates":[-80.687634,40.997216],"type":"Point"}
}