{
  "type": "Feature",
  "properties": {
    "iso:country":"US",
    "sg:address":"1885 Marion Rd",
    "sg:city":"Bucyrus",
    "sg:classifiers":[
        {
            "category":"Autos & Motor Vehicles",
            "subcategory":"Automobile Sales",
            "type":"Retail Goods"
        }
    ],
    "sg:phone":"+1 419 562 5806",
    "sg:postcode":"44820",
    "sg:province":"OH",
    "sg:tags":[
        "car",
        "dealer"
    ],
    "sg:website":"www.walstonmotors.com",
    "wof:name":"Walston Motors Inc",
    "wof:placetype":"venue"
},
  "geometry": {"coordinates":[-82.993758,40.781607],"type":"Point"}
}