{
  "type": "Feature",
  "properties": {
    "addr:full": "27544 US Hwy 30 Kensington OH 44427",
    "addr:postcode": "27544;44427",
    "addr:street": "Us Hwy 30",
    "iso:country": "US",
    "sg:address": "27544 US Hwy 30",
    "sg:city": "Kensington",
    "sg:classifiers": [
      {
        "category": "Building \u0026 Trades",
        "subcategory": "Electrical",
        "type": "Services"
      }
    ],
    "sg:phone": "+1 330 894 2525",
    "sg:postcode": "44427",
    "sg:province": "OH",
    "sg:tags": [
      "electrical",
      "contractor"
    ],
    "wof:name": "Tri-County Electrical Systems",
    "wof:placetype": "venue"
  },
  "geometry": {"coordinates":[-80.986711,40.737413],"type":"Point"}
}
