{
  "type": "Feature",
  "properties": {
    "addr:full": "3100 E 45th St Cleveland OH 44127",
    "addr:housenumber": "3100",
    "addr:postcode": "44127",
    "addr:street": "E 45Th St",
    "iso:country": "US",
    "sg:address": "3100 E 45th St",
    "sg:city": "Cleveland",
    "sg:classifiers": [
      {
        "category": "Organizations",
        "subcategory": "Labor Organization",
        "type": "Services"
      }
    ],
    "sg:phone": "+1 216 883 6633",
    "sg:postcode": "44127",
    "sg:province": "OH",
    "wof:name": "Northern Ohio Fire Fighters",
    "wof:placetype": "venue"
  },
  "geometry": {"coordinates":[-81.661688,41.475926],"type":"Point"}
}
