{
  "type": "Feature",
  "properties": {
    "addr:full": "800 Walnut St Martins Ferry OH 43935",
    "addr:housenumber": "800",
    "addr:postcode": "43935",
    "addr:street": "Walnut St Martins Ferry",
    "iso:country": "US",
    "sg:address": "800 Walnut St",
    "sg:city": "Martins Ferry",
    "sg:classifiers": [
      {
        "category": "Food \u0026 Beverages",
        "subcategory": "Groceries \u0026 Convenience Stores",
        "type": "Retail Goods"
      }
    ],
    "sg:phone": "+1 740 633 0845",
    "sg:postcode": "43935",
    "sg:province": "OH",
    "sg:tags": [
      "grocer"
    ],
    "wof:name": "Tolbert's",
    "wof:placetype": "venue"
  },
  "geometry": {"coordinates":[-80.728422,40.098293],"type":"Point"}
}
