{
  "type": "Feature",
  "properties": {
    "iso:country":"US",
    "sg:address":"800 Walnut St",
    "sg:city":"Martins Ferry",
    "sg:classifiers":[
        {
            "category":"Food & Beverages",
            "subcategory":"Groceries & Convenience Stores",
            "type":"Retail Goods"
        }
    ],
    "sg:phone":"+1 740 633 0845",
    "sg:postcode":"43935",
    "sg:province":"OH",
    "sg:tags":[
        "grocer"
    ],
    "wof:name":"Tolbert's",
    "wof:placetype":"venue"
},
  "geometry": {"coordinates":[-80.72842199999999,40.098293],"type":"Point"}
}