{
  "type": "Feature",
  "properties": {
    "addr:full": "135 N Tuscarawas Ave Dover OH 44622",
    "addr:housenumber": "135",
    "addr:postcode": "44622",
    "addr:street": "N Tuscarawas Ave",
    "iso:country": "US",
    "sg:address": "135 N Tuscarawas Ave",
    "sg:city": "Dover",
    "sg:classifiers": [
      {
        "category": "Wholesale",
        "subcategory": "Auto Parts",
        "type": "Manufacturing \u0026 Wholesale Goods"
      }
    ],
    "sg:phone": "+1 330 364 7767",
    "sg:postcode": "44622",
    "sg:province": "OH",
    "wof:name": "United Sales Co",
    "wof:placetype": "venue"
  },
  "geometry": {"coordinates":[-81.477199,40.518446],"type":"Point"}
}
