{
  "type": "Feature",
  "properties": {
    "addr:full": "4352 W 202nd St Cleveland OH 44126",
    "addr:housenumber": "4352",
    "addr:postcode": "44126",
    "addr:street": "W 202Nd St",
    "iso:country": "US",
    "sg:address": "4352 W 202nd St",
    "sg:city": "Cleveland",
    "sg:classifiers": [
      {
        "category": "Shopping",
        "subcategory": "Gifts \u0026 Souvenirs",
        "type": "Retail Goods"
      }
    ],
    "sg:phone": "+1 440 333 3378",
    "sg:postcode": "44126",
    "sg:province": "OH",
    "sg:tags": [
      "collectible"
    ],
    "wof:name": "Collectables \u0026 More",
    "wof:placetype": "venue"
  },
  "geometry": {"coordinates":[-81.843937,41.44955],"type":"Point"}
}
