{
  "type": "Feature",
  "properties": {
    "iso:country":"US",
    "sg:address":"7 W Broad St",
    "sg:city":"Newton Falls",
    "sg:classifiers":[
        {
            "category":"Personal",
            "subcategory":"Tanning Parlor",
            "type":"Services"
        }
    ],
    "sg:phone":"+1 330 872 0301",
    "sg:postcode":"44444",
    "sg:province":"OH",
    "sg:tags":[
        "salon"
    ],
    "wof:name":"Sunspot Tanning & Nail Salon",
    "wof:placetype":"venue"
},
  "geometry": {"coordinates":[-80.97604800000001,41.187871],"type":"Point"}
}