{
  "type": "Feature",
  "properties": {
    "addr:full": "7 W Broad St Newton Falls OH 44444",
    "addr:housenumber": "7",
    "addr:postcode": "44444",
    "addr:street": "W Broad St",
    "iso:country": "US",
    "sg:address": "7 W Broad St",
    "sg:city": "Newton Falls",
    "sg:classifiers": [
      {
        "category": "Personal",
        "subcategory": "Tanning Parlor",
        "type": "Services"
      }
    ],
    "sg:phone": "+1 330 872 0301",
    "sg:postcode": "44444",
    "sg:province": "OH",
    "sg:tags": [
      "salon"
    ],
    "wof:name": "Sunspot Tanning \u0026 Nail Salon",
    "wof:placetype": "venue"
  },
  "geometry": {"coordinates":[-80.976048,41.187871],"type":"Point"}
}
