{
  "type": "Feature",
  "properties": {
    "iso:country":"US",
    "sg:address":"548 Orchard St",
    "sg:city":"Perrysburg",
    "sg:classifiers":[
        {
            "category":"Health Services",
            "subcategory":"Clinic",
            "type":"Services"
        }
    ],
    "sg:phone":"+1 419 874 8686",
    "sg:postcode":"43551",
    "sg:province":"OH",
    "sg:tags":[
        "home",
        "care"
    ],
    "sg:website":"www.homehelpers.cc",
    "wof:name":"Home Helpers",
    "wof:placetype":"venue"
},
  "geometry": {"coordinates":[-83.611528,41.552027],"type":"Point"}
}