{
  "type": "Feature",
  "properties": {
    "iso:country":"US",
    "sg:address":"1116 Carbon Ave",
    "sg:city":"Fremont",
    "sg:classifiers":[
        {
            "category":"Shopping",
            "subcategory":"Computers & Home Electronics",
            "type":"Retail Goods"
        }
    ],
    "sg:phone":"+1 419 333 9186",
    "sg:postcode":"43420",
    "sg:province":"OH",
    "wof:name":"Intense Car Audio",
    "wof:placetype":"venue"
},
  "geometry": {"coordinates":[-83.12961,41.358783],"type":"Point"}
}