{
  "type": "Feature",
  "properties": {
    "addr:full":"4216 Pearl Rd Cleveland OH 44109",
    "addr:housenumber":"4216",
    "addr:postcode":"44109",
    "addr:street":"Pearl Rd",
    "iso:country":"US",
    "sg:address":"4216 Pearl Rd",
    "sg:city":"Cleveland",
    "sg:classifiers":[
        {
            "category":"Organizations",
            "subcategory":"Religious Organization",
            "type":"Services"
        }
    ],
    "sg:phone":"+1 216 351 4422",
    "sg:postcode":"44109",
    "sg:province":"OH",
    "sg:tags":[
        "church"
    ],
    "wof:name":"St Luke's United Church-Christ",
    "wof:placetype":"venue"
},
  "geometry": {"coordinates":[-81.705124,41.441619],"type":"Point"}
}