{
  "type": "Feature",
  "properties": {
    "iso:country":"US",
    "sg:address":"4500 E Broad St",
    "sg:city":"Columbus",
    "sg:classifiers":[
        {
            "category":"Organizations",
            "subcategory":"Non-profit Organization",
            "type":"Services"
        }
    ],
    "sg:phone":"+1 614 863 1219",
    "sg:postcode":"43213",
    "sg:province":"OH",
    "wof:name":"Employment For Seniors",
    "wof:placetype":"venue"
},
  "geometry": {"coordinates":[-82.880312,39.975556],"type":"Point"}
}