{
  "type": "Feature",
  "properties": {
    "addr:full":"85 E Wilson Bridge Rd Columbus OH 43085",
    "addr:housenumber":"85",
    "addr:postcode":"43085",
    "addr:street":"E Wilson Bridge Rd",
    "iso:country":"US",
    "sg:address":"85 E Wilson Bridge Rd",
    "sg:city":"Columbus",
    "sg:classifiers":[
        {
            "category":"Real Estate",
            "subcategory":"Real Estate Services",
            "type":"Services"
        }
    ],
    "sg:phone":"+1 614 451 0545",
    "sg:postcode":"43085",
    "sg:province":"OH",
    "sg:tags":[
        "insurance",
        "search",
        "company",
        "title"
    ],
    "wof:name":"Marketable Title Agency Inc",
    "wof:placetype":"venue"
},
  "geometry": {"coordinates":[-83.015533,40.106906],"type":"Point"}
}