{
  "type": "Feature",
  "properties": {
    "iso:country":"US",
    "sg:address":"908 Croghan St",
    "sg:city":"Fremont",
    "sg:classifiers":[
        {
            "category":"Health Services",
            "subcategory":"Health Practitioner",
            "type":"Services"
        }
    ],
    "sg:phone":"+1 419 332 6709",
    "sg:postcode":"43420",
    "sg:province":"OH",
    "sg:tags":[
        "therapist",
        "physical"
    ],
    "wof:name":"P T Svc Inc",
    "wof:placetype":"venue"
},
  "geometry": {"coordinates":[-83.121021,41.34656],"type":"Point"}
}