{
  "type": "Feature",
  "properties": {
    "iso:country":"US",
    "sg:address":"536 Pearl St",
    "sg:city":"Bowling Green",
    "sg:classifiers":[
        {
            "category":"Health Services",
            "subcategory":"Chiropractor",
            "type":"Services"
        }
    ],
    "sg:phone":"+1 419 352 8946",
    "sg:postcode":"43402",
    "sg:province":"OH",
    "wof:name":"Huntington Chiropractic",
    "wof:placetype":"venue"
},
  "geometry": {"coordinates":[-83.656353,41.3715],"type":"Point"}
}