{
  "type": "Feature",
  "properties": {
    "addr:full": "8219 Clinton Rd Cleveland OH 44144",
    "addr:housenumber": "8219",
    "addr:postcode": "44144",
    "addr:street": "Clinton Rd",
    "iso:country": "US",
    "sg:address": "8219 Clinton Rd",
    "sg:city": "Cleveland",
    "sg:classifiers": [
      {
        "category": "Manufacturing",
        "subcategory": "Motor Vehicles \u0026 Parts",
        "type": "Manufacturing \u0026 Wholesale Goods"
      }
    ],
    "sg:phone": "+1 216 631 6980",
    "sg:postcode": "44144",
    "sg:province": "OH",
    "sg:tags": [
      "exhaust",
      "system",
      "mfg"
    ],
    "wof:name": "Hmf Engineering Inc",
    "wof:placetype": "venue"
  },
  "geometry": {"coordinates":[-81.747683,41.45213],"type":"Point"}
}
