{
  "type": "Feature",
  "properties": {
    "iso:country":"US",
    "sg:address":"8219 Clinton Rd",
    "sg:city":"Cleveland",
    "sg:classifiers":[
        {
            "category":"Manufacturing",
            "subcategory":"Motor Vehicles & Parts",
            "type":"Manufacturing & Wholesale Goods"
        }
    ],
    "sg:phone":"+1 216 631 6980",
    "sg:postcode":"44144",
    "sg:province":"OH",
    "sg:tags":[
        "exhaust",
        "system",
        "mfg"
    ],
    "wof:name":"Hmf Engineering Inc",
    "wof:placetype":"venue"
},
  "geometry": {"coordinates":[-81.74768299999999,41.45213],"type":"Point"}
}