{
  "type": "Feature",
  "properties": {
    "iso:country":"US",
    "sg:address":"106 W Washington St",
    "sg:city":"Medina",
    "sg:classifiers":[
        {
            "category":"Personal",
            "subcategory":"Barber",
            "type":"Services"
        }
    ],
    "sg:phone":"+1 330 722 0352",
    "sg:postcode":"44256",
    "sg:province":"OH",
    "wof:name":"Hershey's Barber Shop",
    "wof:placetype":"venue"
},
  "geometry": {"coordinates":[-81.864807,41.137958],"type":"Point"}
}