{
  "type": "Feature",
  "properties": {
    "addr:full": "1942 Elklick Rd Batavia OH 45103",
    "addr:housenumber": "1942",
    "addr:postcode": "45103",
    "addr:street": "Elklick Rd",
    "iso:country": "US",
    "sg:address": "1942 Elklick Rd",
    "sg:city": "Batavia",
    "sg:classifiers": [
      {
        "category": "Freight",
        "type": "Transportation"
      }
    ],
    "sg:phone": "+1 513 732 6100",
    "sg:postcode": "45103",
    "sg:province": "OH",
    "sg:tags": [
      "mover"
    ],
    "wof:name": "Robbe Van Lines",
    "wof:placetype": "venue"
  },
  "geometry": {"coordinates":[-84.17089,39.05905],"type":"Point"}
}
