{
  "type": "Feature",
  "properties": {
    "addr:full":"17571 Lakesedge Trl Chagrin Falls OH 44023",
    "addr:housenumber":"17571",
    "addr:postcode":"44023",
    "addr:street":"Lakesedge Trl",
    "iso:country":"US",
    "sg:address":"17571 Lakesedge Trl",
    "sg:city":"Chagrin Falls",
    "sg:classifiers":[
        {
            "category":"Shopping",
            "subcategory":"Gifts & Souvenirs",
            "type":"Retail Goods"
        }
    ],
    "sg:phone":"+1 440 708 1448",
    "sg:postcode":"44023",
    "sg:province":"OH",
    "sg:tags":[
        "shop"
    ],
    "wof:name":"M C Collection",
    "wof:placetype":"venue"
},
  "geometry": {"coordinates":[-81.36469099999999,41.391997],"type":"Point"}
}