{
  "type": "Feature",
  "properties": {
    "iso:country":"US",
    "sg:address":"2220 Green Rd",
    "sg:city":"Cleveland",
    "sg:classifiers":[
        {
            "category":"Professional",
            "type":"Services"
        }
    ],
    "sg:phone":"+1 216 486 4094",
    "sg:postcode":"44121",
    "sg:province":"OH",
    "sg:tags":[
        "establishment"
    ],
    "wof:name":"Wells Airlaundy",
    "wof:placetype":"venue"
},
  "geometry": {"coordinates":[-81.536435,41.546167],"type":"Point"}
}