{
  "type": "Feature",
  "properties": {
    "iso:country":"US",
    "sg:address":"13000 Shaker Blvd",
    "sg:city":"Cleveland",
    "sg:classifiers":[
        {
            "category":"Manufacturing",
            "subcategory":"Tools & Machinery",
            "type":"Manufacturing & Wholesale Goods"
        }
    ],
    "sg:phone":"+1 216 491 0030",
    "sg:postcode":"44120",
    "sg:province":"OH",
    "sg:tags":[
        "analytical",
        "instrument",
        "mfg",
        "testing",
        "laboratory"
    ],
    "wof:name":"Fertility Solutions Inc",
    "wof:placetype":"venue"
},
  "geometry": {"coordinates":[-81.591562,41.484114],"type":"Point"}
}