{
  "type": "Feature",
  "properties": {
    "addr:full": "14314 Alder Ave Cleveland OH 44112",
    "addr:housenumber": "14314",
    "addr:postcode": "44112",
    "addr:street": "Alder Ave",
    "iso:country": "US",
    "sg:address": "14314 Alder Ave",
    "sg:city": "Cleveland",
    "sg:classifiers": [
      {
        "category": "Building \u0026 Trades",
        "subcategory": "Pest Control",
        "type": "Services"
      }
    ],
    "sg:phone": "+1 216 851 3275",
    "sg:postcode": "44112",
    "sg:province": "OH",
    "wof:name": "Urban Pest Control Svc",
    "wof:placetype": "venue"
  },
  "geometry": {"coordinates":[-81.579114,41.542864],"type":"Point"}
}
