{
  "type": "Feature",
  "properties": {
    "iso:country":"US",
    "sg:address":"120 Niles Cortland Rd SE",
    "sg:city":"Warren",
    "sg:classifiers":[
        {
            "category":"Professional",
            "subcategory":"Lawyer & Legal Services",
            "type":"Services"
        }
    ],
    "sg:phone":"+1 330 856 7552",
    "sg:postcode":"44484",
    "sg:province":"OH",
    "sg:tags":[
        "attorney"
    ],
    "wof:name":"Betras Maruca & Kopp LLC",
    "wof:placetype":"venue"
},
  "geometry": {"coordinates":[-80.74059699999999,41.238006],"type":"Point"}
}