{
  "type": "Feature",
  "properties": {
    "addr:full": "10193 Diagonal Rd Mantua OH 44255",
    "addr:housenumber": "10193",
    "addr:postcode": "44255",
    "addr:street": "Diagonal Rd",
    "iso:country": "US",
    "sg:address": "10193 Diagonal Rd",
    "sg:city": "Mantua",
    "sg:classifiers": [
      {
        "category": "Professional",
        "subcategory": "Employment Agencies",
        "type": "Services"
      }
    ],
    "sg:phone": "+1 330 274 8469",
    "sg:postcode": "44255",
    "sg:province": "OH",
    "sg:tags": [
      "opportunity"
    ],
    "wof:name": "Travis Technical Svc LTD",
    "wof:placetype": "venue"
  },
  "geometry": {"coordinates":[-81.2765,41.269306],"type":"Point"}
}
