{
  "type": "Feature",
  "properties": {
    "addr:full": "1 E Garfield Rd Aurora OH 44202",
    "addr:housenumber": "1",
    "addr:postcode": "44202",
    "addr:street": "E Garfield Rd",
    "iso:country": "US",
    "sg:address": "1 E Garfield Rd",
    "sg:city": "Aurora",
    "sg:classifiers": [
      {
        "category": "Insurance",
        "subcategory": "Insurance Agent",
        "type": "Services"
      }
    ],
    "sg:phone": "+1 330 562 8818",
    "sg:postcode": "44202",
    "sg:province": "OH",
    "wof:name": "Sam Fiorentino \u0026 Assoc",
    "wof:placetype": "venue"
  },
  "geometry": {"coordinates":[-81.344696,41.317406],"type":"Point"}
}
