{
  "type": "Feature",
  "properties": {
    "addr:full": "1009 Wooster Rd W Barberton OH 44203",
    "addr:housenumber": "1009",
    "addr:postcode": "44203",
    "addr:street": "Wooster Rd W",
    "iso:country": "US",
    "sg:address": "1009 Wooster Rd W",
    "sg:city": "Barberton",
    "sg:classifiers": [
      {
        "category": "Bars \u0026 Pubs",
        "type": "Food \u0026 Drink"
      }
    ],
    "sg:phone": "+1 330 825 7766",
    "sg:postcode": "44203",
    "sg:province": "OH",
    "sg:tags": [
      "drinking"
    ],
    "wof:name": "Bullseye Sports Pub",
    "wof:placetype": "venue"
  },
  "geometry": {"coordinates":[-81.626575,41.009701],"type":"Point"}
}
