{
  "type": "Feature",
  "properties": {
    "iso:country":"US",
    "sg:address":"1009 Wooster Rd W",
    "sg:city":"Barberton",
    "sg:classifiers":[
        {
            "category":"Bars & Pubs",
            "type":"Food & Drink"
        }
    ],
    "sg:phone":"+1 330 825 7766",
    "sg:postcode":"44203",
    "sg:province":"OH",
    "sg:tags":[
        "drinking"
    ],
    "wof:name":"Bullseye Sports Pub",
    "wof:placetype":"venue"
},
  "geometry": {"coordinates":[-81.626575,41.009701],"type":"Point"}
}