{
  "type": "Feature",
  "properties": {
    "addr:full":"3413 E Main St Columbus OH 43213",
    "addr:housenumber":"3413",
    "addr:postcode":"43213",
    "addr:street":"E Main St",
    "iso:country":"US",
    "sg:address":"3413 E Main St",
    "sg:city":"Columbus",
    "sg:classifiers":[
        {
            "category":"Shopping",
            "type":"Retail Goods"
        }
    ],
    "sg:phone":"+1 614 236 1000",
    "sg:postcode":"43213",
    "sg:province":"OH",
    "sg:tags":[
        "telephone",
        "cellular"
    ],
    "wof:name":"Comstation",
    "wof:placetype":"venue"
},
  "geometry": {"coordinates":[-82.90722700000001,39.956277],"type":"Point"}
}