{
  "type": "Feature",
  "properties": {
    "iso:country":"US",
    "sg:address":"267 Hazen Ave",
    "sg:city":"Ravenna",
    "sg:classifiers":[
        {
            "category":"Freight",
            "type":"Transportation"
        }
    ],
    "sg:phone":"+1 330 296 1871",
    "sg:postcode":"44266",
    "sg:province":"OH",
    "sg:tags":[
        "warehouse"
    ],
    "wof:name":"R W Martin & Sons Inc",
    "wof:placetype":"venue"
},
  "geometry": {"coordinates":[-81.246447,41.150265],"type":"Point"}
}