{
  "type": "Feature",
  "properties": {
    "addr:full": "267 Hazen Ave Ravenna OH 44266",
    "addr:housenumber": "267",
    "addr:postcode": "44266",
    "addr:street": "Hazen Ave",
    "iso:country": "US",
    "sg:address": "267 Hazen Ave",
    "sg:city": "Ravenna",
    "sg:classifiers": [
      {
        "category": "Freight",
        "type": "Transportation"
      }
    ],
    "sg:phone": "+1 330 296 1871",
    "sg:postcode": "44266",
    "sg:province": "OH",
    "sg:tags": [
      "warehouse"
    ],
    "wof:name": "R W Martin \u0026 Sons Inc",
    "wof:placetype": "venue"
  },
  "geometry": {"coordinates":[-81.246447,41.150265],"type":"Point"}
}
