{
  "type": "Feature",
  "properties": {
    "addr:full": "1144 Co Rd 175 Polk OH 44866",
    "addr:housenumber": "1144;175",
    "addr:postcode": "44866",
    "addr:street": "Co Rd",
    "iso:country": "US",
    "sg:address": "1144 Co Rd 175",
    "sg:city": "Polk",
    "sg:classifiers": [
      {
        "category": "Freight",
        "type": "Transportation"
      }
    ],
    "sg:phone": "+1 419 869 7452",
    "sg:postcode": "44866",
    "sg:province": "OH",
    "sg:tags": [
      "operator",
      "local",
      "trucking"
    ],
    "wof:name": "Denny Reed Milk Hauling",
    "wof:placetype": "venue"
  },
  "geometry": {"coordinates":[-82.156271,40.896022],"type":"Point"}
}
