{
  "type": "Feature",
  "properties": {
    "addr:full": "2723 Mahoning Ave Youngstown OH 44509",
    "addr:housenumber": "2723",
    "addr:postcode": "44509",
    "addr:street": "Mahoning Ave",
    "iso:country": "US",
    "sg:address": "2723 Mahoning Ave",
    "sg:city": "Youngstown",
    "sg:classifiers": [
      {
        "category": "Banks \u0026 Credit Unions",
        "subcategory": "Bank",
        "type": "Services"
      }
    ],
    "sg:phone": "+1 330 270 3092",
    "sg:postcode": "44509",
    "sg:province": "OH",
    "sg:tags": [
      "cashing",
      "check"
    ],
    "wof:name": "Payday Cash Advance",
    "wof:placetype": "venue"
  },
  "geometry": {"coordinates":[-80.699769,41.102961],"type":"Point"}
}
