{
  "type": "Feature",
  "properties": {
    "iso:country":"US",
    "sg:address":"2054 Cherry Valley Rd NE",
    "sg:city":"Newark",
    "sg:classifiers":[
        {
            "category":"Building & Trades",
            "subcategory":"Construction",
            "type":"Services"
        }
    ],
    "sg:phone":"+1 740 788 8320",
    "sg:postcode":"43055",
    "sg:province":"OH",
    "sg:tags":[
        "house"
    ],
    "wof:name":"Buckeye Vinyl",
    "wof:placetype":"venue"
},
  "geometry": {"coordinates":[-82.47329499999999,40.044519],"type":"Point"}
}