{
  "type": "Feature",
  "properties": {
    "addr:full": "5758 N High St Worthington OH 43085",
    "addr:housenumber": "5758",
    "addr:postcode": "43085",
    "addr:street": "N High St",
    "iso:country": "US",
    "sg:address": "5758 N High St",
    "sg:city": "Worthington",
    "sg:classifiers": [
      {
        "category": "Retail",
        "subcategory": "Animal Services",
        "type": "Services"
      }
    ],
    "sg:phone": "+1 614 888 8686",
    "sg:postcode": "43085",
    "sg:province": "OH",
    "sg:tags": [
      "pet",
      "boarding",
      "sitting"
    ],
    "wof:name": "Animal Hospital Of Worthington",
    "wof:placetype": "venue"
  },
  "geometry": {"coordinates":[-83.018688,40.077915],"type":"Point"}
}
