{
  "type": "Feature",
  "properties": {
    "addr:full": "4000 Coonpath Rd NW Carroll OH 43112",
    "addr:housenumber": "4000",
    "addr:postcode": "43112",
    "addr:street": "Coonpath Rd Nw",
    "iso:country": "US",
    "sg:address": "4000 Coonpath Rd NW",
    "sg:city": "Carroll",
    "sg:classifiers": [
      {
        "category": "Organizations",
        "subcategory": "Religious Organization",
        "type": "Services"
      }
    ],
    "sg:phone": "+1 740 756 7563",
    "sg:postcode": "43112",
    "sg:province": "OH",
    "sg:website": "www.victoryhill.org",
    "wof:name": "Victory Hill Church Of God",
    "wof:placetype": "venue"
  },
  "geometry": {"coordinates":[-82.681843,39.771891],"type":"Point"}
}
