{
  "type": "Feature",
  "properties": {
    "iso:country":"US",
    "sg:address":"513 Scott Cir",
    "sg:city":"New Carlisle",
    "sg:classifiers":[
        {
            "category":"Professional",
            "subcategory":"Management & Consulting",
            "type":"Services"
        }
    ],
    "sg:phone":"+1 937 846 1935",
    "sg:postcode":"45344",
    "sg:province":"OH",
    "wof:name":"Arete Partners",
    "wof:placetype":"venue"
},
  "geometry": {"coordinates":[-84.027715,39.943163],"type":"Point"}
}