{
  "type": "Feature",
  "properties": {
    "addr:full": "7509 Canal Rd Cleveland OH 44125",
    "addr:housenumber": "7509",
    "addr:postcode": "44125",
    "addr:street": "Canal Rd",
    "iso:country": "US",
    "sg:address": "7509 Canal Rd",
    "sg:city": "Cleveland",
    "sg:classifiers": [
      {
        "category": "Wholesale",
        "subcategory": "Durable Goods \u0026 Equipment",
        "type": "Manufacturing \u0026 Wholesale Goods"
      }
    ],
    "sg:phone": "+1 216 586 4552",
    "sg:postcode": "44125",
    "sg:province": "OH",
    "sg:tags": [
      "representative",
      "manufacturer"
    ],
    "wof:name": "Joseph W Gross",
    "wof:placetype": "venue"
  },
  "geometry": {"coordinates":[-81.59902,41.360237],"type":"Point"}
}
