{
  "type": "Feature",
  "properties": {
    "addr:full":"7045 Stanhope-Kelloggsville Rd Williamsfield OH 44093",
    "addr:housenumber":"7045",
    "addr:postcode":"44093",
    "addr:street":"Stanhope-Kelloggsville Rd",
    "iso:country":"US",
    "sg:address":"7045 Stanhope-Kelloggsville Rd",
    "sg:city":"Williamsfield",
    "sg:classifiers":[
        {
            "category":"Farming",
            "subcategory":"Dairy Farm",
            "type":"Manufacturing & Wholesale Goods"
        }
    ],
    "sg:phone":"+1 440 293 7647",
    "sg:postcode":"44093",
    "sg:province":"OH",
    "wof:name":"Struna Holstiens",
    "wof:placetype":"venue"
},
  "geometry": {"coordinates":[-80.608948,41.556846],"type":"Point"}
}