{
  "type": "Feature",
  "properties": {
    "iso:country":"US",
    "sg:address":"764 W Central Ave",
    "sg:city":"Springboro",
    "sg:classifiers":[
        {
            "category":"Personal",
            "type":"Services"
        }
    ],
    "sg:phone":"+1 937 743 2099",
    "sg:postcode":"45066",
    "sg:province":"OH",
    "sg:tags":[
        "therapist",
        "massage"
    ],
    "wof:name":"Springboro Therapeutic Massage",
    "wof:placetype":"venue"
},
  "geometry": {"coordinates":[-84.249426,39.561307],"type":"Point"}
}