{
  "type": "Feature",
  "properties": {
    "iso:country":"US",
    "sg:address":"49251 State Rte 800",
    "sg:city":"Jerusalem",
    "sg:classifiers":[
        {
            "category":"Farming",
            "subcategory":"Farm",
            "type":"Manufacturing & Wholesale Goods"
        }
    ],
    "sg:phone":"+1 740 472 1742",
    "sg:postcode":"43747",
    "sg:province":"OH",
    "sg:tags":[
        "crop",
        "general"
    ],
    "wof:name":"Fred H Wittenbrook",
    "wof:placetype":"venue"
},
  "geometry": {"coordinates":[-81.132274,39.803592],"type":"Point"}
}