{
  "type": "Feature",
  "properties": {
    "addr:full": "6791 Lakota Ln Liberty Twp OH 45044",
    "addr:housenumber": "6791",
    "addr:postcode": "45044",
    "addr:street": "Lakota Ln",
    "iso:country": "US",
    "sg:address": "6791 Lakota Ln",
    "sg:city": "Liberty Twp",
    "sg:classifiers": [
      {
        "category": "Retail",
        "subcategory": "Auto Repair",
        "type": "Services"
      }
    ],
    "sg:phone": "+1 513 755 8668",
    "sg:postcode": "45044",
    "sg:province": "OH",
    "sg:tags": [
      "repairing",
      "automobile"
    ],
    "wof:name": "Koebbe Auto Tech",
    "wof:placetype": "venue"
  },
  "geometry": {"coordinates":[-84.373066,39.380923],"type":"Point"}
}
