{
  "type": "Feature",
  "properties": {
    "iso:country":"US",
    "sg:address":"6791 Lakota Ln",
    "sg:city":"Liberty Twp",
    "sg:classifiers":[
        {
            "category":"Retail",
            "subcategory":"Auto Repair",
            "type":"Services"
        }
    ],
    "sg:phone":"+1 513 755 8668",
    "sg:postcode":"45044",
    "sg:province":"OH",
    "sg:tags":[
        "repairing",
        "automobile"
    ],
    "wof:name":"Koebbe Auto Tech",
    "wof:placetype":"venue"
},
  "geometry": {"coordinates":[-84.37306599999999,39.380923],"type":"Point"}
}