{
  "type": "Feature",
  "properties": {
    "addr:full": "4900 W Clinton St Albany OH 45710",
    "addr:housenumber": "4900",
    "addr:postcode": "45710",
    "addr:street": "W Clinton St",
    "iso:country": "US",
    "sg:address": "4900 W Clinton St",
    "sg:city": "Albany",
    "sg:classifiers": [
      {
        "category": "Building \u0026 Trades",
        "subcategory": "Construction",
        "type": "Services"
      }
    ],
    "sg:phone": "+1 740 698 6847",
    "sg:postcode": "45710",
    "sg:province": "OH",
    "sg:tags": [
      "masonry",
      "contractor"
    ],
    "wof:name": "Brick-It Co",
    "wof:placetype": "venue"
  },
  "geometry": {"coordinates":[-82.209121,39.22692],"type":"Point"}
}
