{
  "type": "Feature",
  "properties": {
    "addr:full": "14297 State Rte 41 West Union OH 45693",
    "addr:housenumber": "14297",
    "addr:postcode": "45693",
    "addr:street": "State Rte 41 West",
    "iso:country": "US",
    "sg:address": "14297 State Rte 41",
    "sg:city": "West Union",
    "sg:classifiers": [
      {
        "category": "Building \u0026 Trades",
        "subcategory": "Construction",
        "type": "Services"
      }
    ],
    "sg:phone": "+1 937 544 4218",
    "sg:postcode": "45693",
    "sg:province": "OH",
    "sg:tags": [
      "contractor"
    ],
    "wof:name": "Shirleys Construction",
    "wof:placetype": "venue"
  },
  "geometry": {"coordinates":[-83.521639,38.810939],"type":"Point"}
}
