{
  "type": "Feature",
  "properties": {
    "iso:country":"US",
    "sg:address":"14297 State Rte 41",
    "sg:city":"West Union",
    "sg:classifiers":[
        {
            "category":"Building & Trades",
            "subcategory":"Construction",
            "type":"Services"
        }
    ],
    "sg:phone":"+1 937 544 4218",
    "sg:postcode":"45693",
    "sg:province":"OH",
    "sg:tags":[
        "contractor"
    ],
    "wof:name":"Shirleys Construction",
    "wof:placetype":"venue"
},
  "geometry": {"coordinates":[-83.52163899999999,38.810939],"type":"Point"}
}