{
  "type": "Feature",
  "properties": {
    "addr:full":"6672 Williams Center Cecil Rd Mark Center OH 43536",
    "addr:housenumber":"6672",
    "addr:postcode":"43536",
    "addr:street":"Williams Center Cecil Rd",
    "iso:country":"US",
    "sg:address":"6672 Williams Center Cecil Rd",
    "sg:city":"Mark Center",
    "sg:phone":"+1 419 899 4033",
    "sg:postcode":"43536",
    "sg:province":"OH",
    "sg:tags":[
        "farm",
        "corn",
        "wheat",
        "soybean"
    ],
    "wof:name":"Howard Mast",
    "wof:placetype":"venue"
},
  "geometry": {"coordinates":[-84.611352,41.343457],"type":"Point"}
}