{
  "type": "Feature",
  "properties": {
    "addr:full": "45 Bell St Chagrin Falls OH 44022",
    "addr:housenumber": "45",
    "addr:postcode": "44022",
    "addr:street": "Bell St",
    "iso:country": "US",
    "sg:address": "45 Bell St",
    "sg:city": "Chagrin Falls",
    "sg:classifiers": [
      {
        "category": "Health Services",
        "subcategory": "Doctor",
        "type": "Services"
      }
    ],
    "sg:phone": "+1 440 247 6462",
    "sg:postcode": "44022",
    "sg:province": "OH",
    "sg:tags": [
      "surgeon",
      "oral"
    ],
    "wof:name": "Kinstle John M DDS",
    "wof:placetype": "venue"
  },
  "geometry": {"coordinates":[-81.389801,41.431999],"type":"Point"}
}
