{
  "type": "Feature",
  "properties": {
    "addr:full": "3726 S Detroit Ave Toledo OH 43614",
    "addr:housenumber": "3726",
    "addr:postcode": "43614",
    "addr:street": "S Detroit Ave",
    "iso:country": "US",
    "sg:address": "3726 S Detroit Ave",
    "sg:city": "Toledo",
    "sg:classifiers": [
      {
        "category": "Home \u0026 Garden",
        "subcategory": "Hardware",
        "type": "Retail Goods"
      }
    ],
    "sg:phone": "+1 419 382 5972",
    "sg:postcode": "43614",
    "sg:province": "OH",
    "wof:name": "Beverly Hardware",
    "wof:placetype": "venue"
  },
  "geometry": {"coordinates":[-83.610629,41.598414],"type":"Point"}
}
