{
  "type": "Feature",
  "properties": {
    "addr:full": "4550 Nantucket Dr Youngstown OH 44515",
    "addr:housenumber": "4550",
    "addr:postcode": "44515",
    "addr:street": "Nantucket Dr",
    "iso:country": "US",
    "sg:address": "4550 Nantucket Dr",
    "sg:city": "Youngstown",
    "sg:classifiers": [
      {
        "category": "Real Estate",
        "subcategory": "Real Estate Operator",
        "type": "Services"
      }
    ],
    "sg:phone": "+1 330 792 1181",
    "sg:postcode": "44515",
    "sg:province": "OH",
    "sg:tags": [
      "apartment"
    ],
    "sg:website": "http://www.cpwapartments.com",
    "wof:name": "Central Park West Exercise",
    "wof:placetype": "venue"
  },
  "geometry": {"coordinates":[-80.739316,41.087754],"type":"Point"}
}
