{
  "type": "Feature",
  "properties": {
    "addr:full":"09915 Us Route 127 Sherwood OH 43556",
    "addr:housenumber":"09915",
    "addr:postcode":"43556",
    "addr:street":"Us Route 127",
    "iso:country":"US",
    "sg:address":"09915 Us Route 127",
    "sg:city":"Sherwood",
    "sg:classifiers":[
        {
            "category":"Restaurant",
            "type":"Food & Drink"
        }
    ],
    "sg:menulink":"http://www.allmenus.com/oh/delaware/88963-figaros-pizza/menu/",
    "sg:phone":"+1 419 899 3333",
    "sg:postcode":"43556",
    "sg:province":"OH",
    "sg:tags":[
        "american",
        "italian",
        "pizza"
    ],
    "wof:name":"Figaro's Pizza",
    "wof:placetype":"venue"
},
  "geometry": {"coordinates":[-84.553453,41.296893],"type":"Point"}
}