{
  "type": "Feature",
  "properties": {
    "iso:country":"US",
    "sg:address":"180 Concord Ln",
    "sg:city":"Hinckley",
    "sg:classifiers":[
        {
            "category":"Shopping",
            "subcategory":"Florist",
            "type":"Retail Goods"
        }
    ],
    "sg:phone":"+1 330 273 2191",
    "sg:postcode":"44233",
    "sg:province":"OH",
    "wof:name":"Juenke Flowerama",
    "wof:placetype":"venue"
},
  "geometry": {"coordinates":[-81.76264,41.270883],"type":"Point"}
}