{
  "type": "Feature",
  "properties": {
    "iso:country":"US",
    "sg:address":"246 Lincoln Cir",
    "sg:city":"Columbus",
    "sg:classifiers":[
        {
            "category":"Real Estate",
            "subcategory":"Real Estate Agent",
            "type":"Services"
        }
    ],
    "sg:phone":"+1 614 231 0037",
    "sg:postcode":"43230",
    "sg:province":"OH",
    "wof:name":"Randolph & Assoc Real Estate",
    "wof:placetype":"venue"
},
  "geometry": {"coordinates":[-82.873255,40.017877],"type":"Point"}
}