{
  "type": "Feature",
  "properties": {
    "addr:full":"1230 Goodale Blvd Columbus OH 43212",
    "addr:housenumber":"1230",
    "addr:postcode":"43212",
    "addr:street":"Goodale Blvd",
    "iso:country":"US",
    "sg:address":"1230 Goodale Blvd",
    "sg:city":"Columbus",
    "sg:classifiers":[
        {
            "category":"Wholesale",
            "subcategory":"Construction Materials",
            "type":"Manufacturing & Wholesale Goods"
        }
    ],
    "sg:phone":"+1 614 486 5249",
    "sg:postcode":"43212",
    "sg:province":"OH",
    "sg:tags":[
        "fence"
    ],
    "wof:name":"Byers Fence Co",
    "wof:placetype":"venue"
},
  "geometry": {"coordinates":[-83.0369,39.974757],"type":"Point"}
}