{
  "type": "Feature",
  "properties": {
    "addr:full": "2107 Poplar St Obetz OH 43207",
    "addr:housenumber": "2107",
    "addr:postcode": "43207",
    "addr:street": "Poplar St",
    "iso:country": "US",
    "sg:address": "2107 Poplar St",
    "sg:city": "Obetz",
    "sg:classifiers": [
      {
        "category": "Shopping",
        "type": "Retail Goods"
      }
    ],
    "sg:phone": "+1 614 491 7046",
    "sg:postcode": "43207",
    "sg:province": "OH",
    "sg:tags": [
      "cards",
      "sport",
      "baseball",
      "memorabilia"
    ],
    "wof:name": "Castle Football Cards",
    "wof:placetype": "venue"
  },
  "geometry": {"coordinates":[-82.948032,39.87924],"type":"Point"}
}
