{
  "type": "Feature",
  "properties": {
    "iso:country":"US",
    "sg:address":"415 Storer Ave",
    "sg:city":"Akron",
    "sg:classifiers":[
        {
            "category":"Education",
            "subcategory":"School",
            "type":"Public Place"
        }
    ],
    "sg:phone":"+1 330 761 3235",
    "sg:postcode":"44320",
    "sg:province":"OH",
    "wof:name":"Rankin Technology School",
    "wof:placetype":"venue"
},
  "geometry": {"coordinates":[-81.556204,41.090917],"type":"Point"}
}