{
  "type": "Feature",
  "properties": {
    "iso:country":"US",
    "sg:address":"4465 Fulton Dr NW",
    "sg:city":"Canton",
    "sg:classifiers":[
        {
            "category":"Insurance",
            "subcategory":"Insurance Agent",
            "type":"Services"
        }
    ],
    "sg:phone":"+1 330 494 4382",
    "sg:postcode":"44718",
    "sg:province":"OH",
    "wof:name":"Peoples Health Plan",
    "wof:placetype":"venue"
},
  "geometry": {"coordinates":[-81.433864,40.842664],"type":"Point"}
}