{
  "type": "Feature",
  "properties": {
    "addr:full": "4465 Fulton Dr NW Canton OH 44718",
    "addr:housenumber": "4465",
    "addr:postcode": "44718",
    "addr:street": "Fulton Dr Nw",
    "iso:country": "US",
    "sg:address": "4465 Fulton Dr NW",
    "sg:city": "Canton",
    "sg:classifiers": [
      {
        "category": "Insurance",
        "subcategory": "Insurance Agent",
        "type": "Services"
      }
    ],
    "sg:phone": "+1 330 494 4382",
    "sg:postcode": "44718",
    "sg:province": "OH",
    "wof:name": "Peoples Health Plan",
    "wof:placetype": "venue"
  },
  "geometry": {"coordinates":[-81.433864,40.842664],"type":"Point"}
}
