{
  "type": "Feature",
  "properties": {
    "iso:country":"US",
    "sg:address":"7200 Euclid Ave",
    "sg:city":"Cincinnati",
    "sg:classifiers":[
        {
            "category":"Professional",
            "type":"Services"
        }
    ],
    "sg:phone":"+1 513 793 7500",
    "sg:postcode":"45243",
    "sg:province":"OH",
    "sg:tags":[
        "establishment"
    ],
    "wof:name":"Curee Enterprises",
    "wof:placetype":"venue"
},
  "geometry": {"coordinates":[-84.367791,39.191407],"type":"Point"}
}