{
  "type": "Feature",
  "properties": {
    "addr:full": "1101 Steubenville Ave Cambridge OH 43725",
    "addr:housenumber": "1101",
    "addr:postcode": "43725",
    "addr:street": "Steubenville Ave",
    "iso:country": "US",
    "sg:address": "1101 Steubenville Ave",
    "sg:city": "Cambridge",
    "sg:classifiers": [
      {
        "category": "Social Services",
        "type": "Services"
      }
    ],
    "sg:phone": "+1 740 439 4214",
    "sg:postcode": "43725",
    "sg:province": "OH",
    "sg:tags": [
      "organization",
      "welfare"
    ],
    "wof:name": "Feed My People",
    "wof:placetype": "venue"
  },
  "geometry": {"coordinates":[-81.584769,40.025999],"type":"Point"}
}
