{
  "type": "Feature",
  "properties": {
    "addr:full":"231 Amelia-Olive Branch Rd Amelia OH 45102",
    "addr:housenumber":"231",
    "addr:postcode":"45102",
    "addr:street":"Amelia-Olive Branch Rd",
    "iso:country":"US",
    "sg:address":"231 Amelia-Olive Branch Rd",
    "sg:city":"Amelia",
    "sg:classifiers":[
        {
            "category":"Building & Trades",
            "subcategory":"Construction",
            "type":"Services"
        }
    ],
    "sg:phone":"+1 513 753 6947",
    "sg:postcode":"45102",
    "sg:province":"OH",
    "sg:tags":[
        "repairing",
        "house",
        "remodeling",
        "contractor"
    ],
    "wof:name":"Juilfs Construction",
    "wof:placetype":"venue"
},
  "geometry": {"coordinates":[-84.226069,39.049927],"type":"Point"}
}