{
  "type": "Feature",
  "properties": {
    "addr:full": "777 Pole Lane Rd Marion OH 43302",
    "addr:housenumber": "777",
    "addr:postcode": "43302",
    "addr:street": "Pole Lane Rd",
    "iso:country": "US",
    "sg:address": "777 Pole Lane Rd",
    "sg:city": "Marion",
    "sg:phone": "+1 740 223 3701",
    "sg:postcode": "43302",
    "sg:province": "OH",
    "sg:tags": [
      "farm",
      "wheat",
      "soybean"
    ],
    "wof:name": "Walter Ermin",
    "wof:placetype": "venue"
  },
  "geometry": {"coordinates":[-83.073592,40.597939],"type":"Point"}
}
