{
  "type": "Feature",
  "properties": {
    "addr:full": "830 Bowen St Dayton OH 45410",
    "addr:housenumber": "830",
    "addr:postcode": "45410",
    "addr:street": "Bowen St",
    "iso:country": "US",
    "sg:address": "830 Bowen St",
    "sg:city": "Dayton",
    "sg:classifiers": [
      {
        "category": "Banks \u0026 Credit Unions",
        "subcategory": "Bank",
        "type": "Services"
      }
    ],
    "sg:phone": "+1 937 254 0046",
    "sg:postcode": "45410",
    "sg:province": "OH",
    "wof:name": "St Anthony Credit Union",
    "wof:placetype": "venue"
  },
  "geometry": {"coordinates":[-84.154508,39.747928],"type":"Point"}
}
