{
  "type": "Feature",
  "properties": {
    "iso:country":"US",
    "sg:address":"830 Bowen St",
    "sg:city":"Dayton",
    "sg:classifiers":[
        {
            "category":"Banks & Credit Unions",
            "subcategory":"Bank",
            "type":"Services"
        }
    ],
    "sg:phone":"+1 937 254 0046",
    "sg:postcode":"45410",
    "sg:province":"OH",
    "wof:name":"St Anthony Credit Union",
    "wof:placetype":"venue"
},
  "geometry": {"coordinates":[-84.15450800000001,39.747928],"type":"Point"}
}