{
  "type": "Feature",
  "properties": {
    "addr:full": "515 N Wooster Ave Dover OH 44622",
    "addr:housenumber": "515",
    "addr:postcode": "44622",
    "addr:street": "N Wooster Ave",
    "iso:country": "US",
    "sg:address": "515 N Wooster Ave",
    "sg:city": "Dover",
    "sg:classifiers": [
      {
        "category": "Health Services",
        "subcategory": "Optometrist",
        "type": "Services"
      }
    ],
    "sg:phone": "+1 330 343 6941",
    "sg:postcode": "44622",
    "sg:province": "OH",
    "wof:name": "Vision Perception Ctr",
    "wof:placetype": "venue"
  },
  "geometry": {"coordinates":[-81.479439,40.525371],"type":"Point"}
}
