{
  "type": "Feature",
  "properties": {
    "addr:full":"2355 Front St Cuyahoga Falls OH 44221",
    "addr:housenumber":"2355",
    "addr:postcode":"44221",
    "addr:street":"Front St",
    "iso:country":"US",
    "sg:address":"2355 Front St",
    "sg:city":"Cuyahoga Falls",
    "sg:classifiers":[
        {
            "category":"Retail",
            "subcategory":"Auto Repair",
            "type":"Services"
        }
    ],
    "sg:phone":"+1 330 928 1330",
    "sg:postcode":"44221",
    "sg:province":"OH",
    "sg:tags":[
        "repairing",
        "automobile"
    ],
    "wof:name":"River Front Automotive Group",
    "wof:placetype":"venue"
},
  "geometry": {"coordinates":[-81.48105099999999,41.139258],"type":"Point"}
}