{
  "type": "Feature",
  "properties": {
    "iso:country":"US",
    "sg:address":"2925 Pine Lake Rd",
    "sg:city":"Uniontown",
    "sg:classifiers":[
        {
            "category":"Shopping",
            "subcategory":"Gifts & Souvenirs",
            "type":"Retail Goods"
        }
    ],
    "sg:phone":"+1 330 699 5288",
    "sg:postcode":"44685",
    "sg:province":"OH",
    "sg:tags":[
        "merchandise"
    ],
    "wof:name":"Frames By James",
    "wof:placetype":"venue"
},
  "geometry": {"coordinates":[-81.419776,40.991878],"type":"Point"}
}