{
  "type": "Feature",
  "properties": {
    "addr:full":"1390 W 1st St Springfield OH 45504",
    "addr:housenumber":"1390",
    "addr:postcode":"45504",
    "addr:street":"W 1St St",
    "iso:country":"US",
    "sg:address":"1390 W 1st St",
    "sg:city":"Springfield",
    "sg:classifiers":[
        {
            "category":"Banks & Credit Unions",
            "subcategory":"Bank",
            "type":"Services"
        }
    ],
    "sg:phone":"+1 937 322 0761",
    "sg:postcode":"45504",
    "sg:province":"OH",
    "sg:tags":[
        "financing"
    ],
    "wof:name":"American General Finance Inc",
    "wof:placetype":"venue"
},
  "geometry": {"coordinates":[-83.835432,39.940546],"type":"Point"}
}