{
  "type": "Feature",
  "properties": {
    "addr:full":"4825 Marburg Ave Cincinnati OH 45209",
    "addr:housenumber":"4825",
    "addr:postcode":"45209",
    "addr:street":"Marburg Ave",
    "iso:country":"US",
    "sg:address":"4825 Marburg Ave",
    "sg:city":"Cincinnati",
    "sg:classifiers":[
        {
            "category":"Personal",
            "subcategory":"Beauty Salon",
            "type":"Services"
        }
    ],
    "sg:phone":"+1 513 924 0541",
    "sg:postcode":"45209",
    "sg:province":"OH",
    "sg:tags":[
        "barber"
    ],
    "sg:website":"http://www.greatclips.com/",
    "wof:name":"Great Clips",
    "wof:placetype":"venue"
},
  "geometry": {"coordinates":[-84.42467499999999,39.162109],"type":"Point"}
}