{
  "type": "Feature",
  "properties": {
    "addr:full": "15 E Midlothian Blvd Youngstown OH 44507",
    "addr:housenumber": "15",
    "addr:postcode": "44507",
    "addr:street": "E Midlothian Blvd",
    "iso:country": "US",
    "sg:address": "15 E Midlothian Blvd",
    "sg:city": "Youngstown",
    "sg:classifiers": [
      {
        "category": "Restaurant",
        "type": "Food \u0026 Drink"
      }
    ],
    "sg:phone": "+1 330 788 9530",
    "sg:postcode": "44507",
    "sg:province": "OH",
    "sg:tags": [
      "eating"
    ],
    "wof:name": "Burger King",
    "wof:placetype": "venue"
  },
  "geometry": {"coordinates":[-80.660551,41.060855],"type":"Point"}
}
