{
  "type": "Feature",
  "properties": {
    "iso:country":"US",
    "sg:address":"15 E Midlothian Blvd",
    "sg:city":"Youngstown",
    "sg:classifiers":[
        {
            "category":"Restaurant",
            "type":"Food & Drink"
        }
    ],
    "sg:phone":"+1 330 788 9530",
    "sg:postcode":"44507",
    "sg:province":"OH",
    "sg:tags":[
        "eating"
    ],
    "wof:name":"Burger King",
    "wof:placetype":"venue"
},
  "geometry": {"coordinates":[-80.660551,41.060855],"type":"Point"}
}