{
  "type": "Feature",
  "properties": {
    "iso:country":"US",
    "sg:address":"5595 Dixie Hwy",
    "sg:city":"Fairfield",
    "sg:classifiers":[
        {
            "category":"Sports & Exercise",
            "subcategory":"Bowling",
            "type":"Entertainment"
        }
    ],
    "sg:phone":"+1 513 874 3838",
    "sg:postcode":"45014",
    "sg:province":"OH",
    "sg:tags":[
        "center"
    ],
    "wof:name":"Gilmore Lanes",
    "wof:placetype":"venue"
},
  "geometry": {"coordinates":[-84.519342,39.331223],"type":"Point"}
}