{
  "type": "Feature",
  "properties": {
    "addr:full":"5810 Southwyck Blvd Toledo OH 43614",
    "addr:housenumber":"5810",
    "addr:postcode":"43614",
    "addr:street":"Southwyck Blvd",
    "iso:country":"US",
    "sg:address":"5810 Southwyck Blvd",
    "sg:city":"Toledo",
    "sg:classifiers":[
        {
            "category":"Insurance",
            "subcategory":"Insurance Agent",
            "type":"Services"
        }
    ],
    "sg:phone":"+1 419 866 5511",
    "sg:postcode":"43614",
    "sg:province":"OH",
    "wof:name":"State Auto Insurance Co",
    "wof:placetype":"venue"
},
  "geometry": {"coordinates":[-83.66477,41.604875],"type":"Point"}
}