{
  "type": "Feature",
  "properties": {
    "addr:full":"8445 Lincoln Dr Chesterland OH 44026",
    "addr:housenumber":"8445",
    "addr:postcode":"44026",
    "addr:street":"Lincoln Dr",
    "iso:country":"US",
    "sg:address":"8445 Lincoln Dr",
    "sg:city":"Chesterland",
    "sg:classifiers":[
        {
            "category":"Professional",
            "type":"Services"
        }
    ],
    "sg:phone":"+1 440 729 9290",
    "sg:postcode":"44026",
    "sg:province":"OH",
    "wof:name":"Brooks1com",
    "wof:placetype":"venue"
},
  "geometry": {"coordinates":[-81.341022,41.531319],"type":"Point"}
}