{
  "type": "Feature",
  "properties": {
    "addr:full": "7975 Cleveland Ave NW North Canton OH 44720",
    "addr:housenumber": "7975",
    "addr:postcode": "44720",
    "addr:street": "Cleveland Ave Nw",
    "iso:country": "US",
    "sg:address": "7975 Cleveland Ave NW",
    "sg:city": "North Canton",
    "sg:classifiers": [
      {
        "category": "Personal",
        "subcategory": "Beauty Salon",
        "type": "Services"
      }
    ],
    "sg:phone": "+1 330 494 7249",
    "sg:postcode": "44720",
    "sg:province": "OH",
    "wof:name": "Today's Total Look",
    "wof:placetype": "venue"
  },
  "geometry": {"coordinates":[-81.406249,40.898455],"type":"Point"}
}
