{
  "type": "Feature",
  "properties": {
    "iso:country":"US",
    "sg:address":"1405 US Hwy 23",
    "sg:city":"Delaware",
    "sg:classifiers":[
        {
            "category":"Government",
            "subcategory":"Office",
            "type":"Public Place"
        }
    ],
    "sg:phone":"+1 740 368 1450",
    "sg:postcode":"43015",
    "sg:province":"OH",
    "sg:tags":[
        "county",
        "payable",
        "account",
        "administration",
        "dept"
    ],
    "wof:name":"Department of Facilities",
    "wof:placetype":"venue"
},
  "geometry": {"coordinates":[-83.068889,40.318232],"type":"Point"}
}