{
  "type": "Feature",
  "properties": {
    "iso:country":"US",
    "sg:address":"1060 Park Ave W",
    "sg:city":"Mansfield",
    "sg:classifiers":[
        {
            "category":"Shopping",
            "subcategory":"Tobacco",
            "type":"Retail Goods"
        }
    ],
    "sg:phone":"+1 419 529 4428",
    "sg:postcode":"44906",
    "sg:province":"OH",
    "sg:tags":[
        "cigarette",
        "cigar",
        "dealer"
    ],
    "wof:name":"E & N Tobacco Warehouse",
    "wof:placetype":"venue"
},
  "geometry": {"coordinates":[-82.553468,40.759297],"type":"Point"}
}