{
  "type": "Feature",
  "properties": {
    "iso:country":"US",
    "sg:address":"305 W 12th Ave",
    "sg:city":"Columbus",
    "sg:classifiers":[
        {
            "category":"Health Services",
            "subcategory":"Doctor",
            "type":"Services"
        }
    ],
    "sg:phone":"+1 614 292 2212",
    "sg:postcode":"43210",
    "sg:province":"OH",
    "wof:name":"Oral and Maxillofacial Surgery",
    "wof:placetype":"venue"
},
  "geometry": {"coordinates":[-83.020325,39.995956],"type":"Point"}
}