{
  "type": "Feature",
  "properties": {
    "iso:country":"US",
    "sg:address":"252 Cherry St",
    "sg:city":"Orrville",
    "sg:classifiers":[
        {
            "category":"Wholesale",
            "subcategory":"Machinery & Supplies",
            "type":"Manufacturing & Wholesale Goods"
        }
    ],
    "sg:phone":"+1 330 682 0087",
    "sg:postcode":"44667",
    "sg:province":"OH",
    "sg:tags":[
        "equipment",
        "laundry"
    ],
    "wof:name":"Orr Suds",
    "wof:placetype":"venue"
},
  "geometry": {"coordinates":[-81.779772,40.84347],"type":"Point"}
}