{
  "type": "Feature",
  "properties": {
    "addr:full": "1600 W Main St Troy OH 45373",
    "addr:housenumber": "1600",
    "addr:postcode": "45373",
    "addr:street": "W Main St",
    "iso:country": "US",
    "sg:address": "1600 W Main St",
    "sg:city": "Troy",
    "sg:classifiers": [
      {
        "category": "Restaurant",
        "type": "Food \u0026 Drink"
      }
    ],
    "sg:menulink": "http://www.allmenus.com/oh/concord/67870-foxs-pizza-den/menu/",
    "sg:phone": "+1 937 335 3697",
    "sg:postcode": "45373",
    "sg:province": "OH",
    "sg:tags": [
      "american",
      "pizza"
    ],
    "wof:name": "Fox's Pizza Den",
    "wof:placetype": "venue"
  },
  "geometry": {"coordinates":[-84.229841,40.051071],"type":"Point"}
}
