{
  "type": "Feature",
  "properties": {
    "addr:full": "221 E Tiffin St Willard OH 44890",
    "addr:housenumber": "221",
    "addr:postcode": "44890",
    "addr:street": "E Tiffin St",
    "iso:country": "US",
    "sg:address": "221 E Tiffin St",
    "sg:city": "Willard",
    "sg:classifiers": [
      {
        "category": "Autos \u0026 Motor Vehicles",
        "subcategory": "Fuel \u0026 Gas Station",
        "type": "Retail Goods"
      }
    ],
    "sg:phone": "+1 419 935 1301",
    "sg:postcode": "44890",
    "sg:province": "OH",
    "sg:tags": [
      "oil"
    ],
    "wof:name": "Steve's Auto Care",
    "wof:placetype": "venue"
  },
  "geometry": {"coordinates":[-82.722912,41.053178],"type":"Point"}
}
