{
  "type": "Feature",
  "properties": {
    "addr:full":"440 Miamisburg Centerville Rd Dayton OH 45459",
    "addr:housenumber":"440",
    "addr:postcode":"45459",
    "addr:street":"Miamisburg Centerville Rd",
    "iso:country":"US",
    "sg:address":"440 Miamisburg Centerville Rd",
    "sg:city":"Dayton",
    "sg:classifiers":[
        {
            "category":"Home & Garden",
            "subcategory":"Home Furnishings",
            "type":"Retail Goods"
        }
    ],
    "sg:phone":"+1 937 434 1765",
    "sg:postcode":"45459",
    "sg:province":"OH",
    "sg:tags":[
        "equipment",
        "fireplace"
    ],
    "wof:name":"Provincial House Fireplace",
    "wof:placetype":"venue"
},
  "geometry": {"coordinates":[-84.175961,39.627748],"type":"Point"}
}