{
  "type": "Feature",
  "properties": {
    "iso:country":"US",
    "sg:address":"504 Washington St",
    "sg:city":"Steubenville",
    "sg:classifiers":[
        {
            "category":"Personal",
            "subcategory":"Beauty Salon",
            "type":"Services"
        }
    ],
    "sg:phone":"+1 740 282 3410",
    "sg:postcode":"43952",
    "sg:province":"OH",
    "wof:name":"Patrick's Beauty Salon",
    "wof:placetype":"venue"
},
  "geometry": {"coordinates":[-80.616049,40.362159],"type":"Point"}
}