{
  "type": "Feature",
  "properties": {
    "addr:full":"805 N Hazelwood Ave Youngstown OH 44509",
    "addr:housenumber":"805",
    "addr:postcode":"44509",
    "addr:street":"N Hazelwood Ave",
    "iso:country":"US",
    "sg:address":"805 N Hazelwood Ave",
    "sg:city":"Youngstown",
    "sg:classifiers":[
        {
            "category":"Building & Trades",
            "subcategory":"Plumbing",
            "type":"Services"
        }
    ],
    "sg:phone":"+1 330 792 4418",
    "sg:postcode":"44509",
    "sg:province":"OH",
    "sg:tags":[
        "conditioning",
        "air",
        "system",
        "contractor"
    ],
    "wof:name":"Smaldino's Heating & Air Cond",
    "wof:placetype":"venue"
},
  "geometry": {"coordinates":[-80.69778599999999,41.111318],"type":"Point"}
}