{
  "type": "Feature",
  "properties": {
    "iso:country":"US",
    "sg:address":"6789 Kentford Ct",
    "sg:city":"Cincinnati",
    "sg:classifiers":[
        {
            "category":"Building & Trades",
            "subcategory":"Construction",
            "type":"Services"
        }
    ],
    "sg:phone":"+1 513 941 0264",
    "sg:postcode":"45233",
    "sg:province":"OH",
    "sg:tags":[
        "home",
        "builder"
    ],
    "wof:name":"My Builder",
    "wof:placetype":"venue"
},
  "geometry": {"coordinates":[-84.679709,39.109839],"type":"Point"}
}