{
  "type": "Feature",
  "properties": {
    "addr:full":"405 W Jackson St Grover Hill OH 45849",
    "addr:housenumber":"405",
    "addr:postcode":"45849",
    "addr:street":"W Jackson St",
    "iso:country":"US",
    "sg:address":"405 W Jackson St",
    "sg:city":"Grover Hill",
    "sg:classifiers":[
        {
            "category":"Manufacturing",
            "subcategory":"Tools & Machinery",
            "type":"Manufacturing & Wholesale Goods"
        }
    ],
    "sg:phone":"+1 419 587 3074",
    "sg:postcode":"45849",
    "sg:province":"OH",
    "sg:tags":[
        "cleaners",
        "household",
        "vacuum"
    ],
    "wof:name":"RDC Vacuum Svc",
    "wof:placetype":"venue"
},
  "geometry": {"coordinates":[-84.480373,41.019153],"type":"Point"}
}