{
  "type": "Feature",
  "properties": {
    "addr:full":"8895 State Rte 14 Streetsboro OH 44241",
    "addr:housenumber":"8895",
    "addr:postcode":"44241",
    "addr:street":"State Rte 14",
    "iso:country":"US",
    "sg:address":"8895 State Rte 14",
    "sg:city":"Streetsboro",
    "sg:classifiers":[
        {
            "category":"Retail",
            "subcategory":"Auto Repair",
            "type":"Services"
        }
    ],
    "sg:phone":"+1 330 626 3116",
    "sg:postcode":"44241",
    "sg:province":"OH",
    "sg:tags":[
        "body",
        "shop"
    ],
    "wof:name":"Action Auto Body",
    "wof:placetype":"venue"
},
  "geometry": {"coordinates":[-81.334198,41.23609],"type":"Point"}
}