{
  "type": "Feature",
  "properties": {
    "addr:full":"2262 S Arlington Rd Akron OH 44319",
    "addr:housenumber":"2262",
    "addr:postcode":"44319",
    "addr:street":"S Arlington Rd",
    "iso:country":"US",
    "sg:address":"2262 S Arlington Rd",
    "sg:city":"Akron",
    "sg:classifiers":[
        {
            "category":"Sports & Exercise",
            "subcategory":"Gym",
            "type":"Entertainment"
        }
    ],
    "sg:phone":"+1 330 785 4202",
    "sg:postcode":"44319",
    "sg:province":"OH",
    "sg:tags":[
        "club",
        "health",
        "studio",
        "gymnasium"
    ],
    "wof:name":"Unique Fitness",
    "wof:placetype":"venue"
},
  "geometry": {"coordinates":[-81.492042,41.007731],"type":"Point"}
}