{
  "type": "Feature",
  "properties": {
    "iso:country":"US",
    "sg:address":"5587 N Dixie Dr",
    "sg:city":"Dayton",
    "sg:classifiers":[
        {
            "category":"Autos & Motor Vehicles",
            "subcategory":"Automobile Sales",
            "type":"Retail Goods"
        }
    ],
    "sg:phone":"+1 937 275 5101",
    "sg:postcode":"45414",
    "sg:province":"OH",
    "sg:tags":[
        "cart"
    ],
    "wof:name":"S S S Racing Enterprises",
    "wof:placetype":"venue"
},
  "geometry": {"coordinates":[-84.198352,39.817218],"type":"Point"}
}