{
  "type": "Feature",
  "properties": {
    "iso:country":"US",
    "sg:address":"50 N Rocky River Dr",
    "sg:city":"Berea",
    "sg:classifiers":[
        {
            "category":"Shopping",
            "subcategory":"Baby Store",
            "type":"Retail Goods"
        },
        {
            "category":"Professional",
            "type":"Services"
        },
        {
            "category":"Personal",
            "type":"Services"
        },
        {
            "category":"Social Services",
            "subcategory":"Child Care",
            "type":"Services"
        },
        {
            "category":"Health Services",
            "subcategory":"Clinic",
            "type":"Services"
        }
    ],
    "sg:phone":"+1 440 243 2520",
    "sg:postcode":"44017",
    "sg:province":"OH",
    "sg:tags":[
        "information",
        "family",
        "abortion",
        "planning",
        "pregnancy",
        "counseling",
        "alternative"
    ],
    "sg:website":"http://www.northcoastphc.org",
    "wof:name":"Cleveland Pregnancy Center",
    "wof:placetype":"venue"
},
  "geometry": {"coordinates":[-81.85449199999999,41.369701],"type":"Point"}
}