{
  "type": "Feature",
  "properties": {
    "addr:full": "1010 Cereal Ave Hamilton OH 45013",
    "addr:housenumber": "1010",
    "addr:postcode": "45013",
    "addr:street": "Cereal Ave",
    "iso:country": "US",
    "sg:address": "1010 Cereal Ave",
    "sg:city": "Hamilton",
    "sg:classifiers": [
      {
        "category": "Health Services",
        "subcategory": "Doctor",
        "type": "Services"
      }
    ],
    "sg:phone": "+1 513 867 2622",
    "sg:postcode": "45013",
    "sg:province": "OH",
    "sg:tags": [
      "physician",
      "medical",
      "surgeon"
    ],
    "wof:name": "Associates In Adult Hlth Care",
    "wof:placetype": "venue"
  },
  "geometry": {"coordinates":[-84.573534,39.41463],"type":"Point"}
}
