{
  "type": "Feature",
  "properties": {
    "iso:country":"US",
    "sg:address":"1412 N Main St",
    "sg:city":"Urbana",
    "sg:classifiers":[
        {
            "category":"Government",
            "subcategory":"Office",
            "type":"Public Place"
        }
    ],
    "sg:phone":"+1 937 484 3016",
    "sg:postcode":"43078",
    "sg:province":"OH",
    "sg:tags":[
        "national",
        "security"
    ],
    "wof:name":"Urbana Recruiting Office",
    "wof:placetype":"venue"
},
  "geometry": {"coordinates":[-83.748655,40.128603],"type":"Point"}
}