{
  "type": "Feature",
  "properties": {
    "iso:country":"US",
    "sg:address":"201 S Main St",
    "sg:city":"Gibsonburg",
    "sg:classifiers":[
        {
            "category":"Food & Beverages",
            "subcategory":"Liquor & Beverages",
            "type":"Retail Goods"
        }
    ],
    "sg:phone":"+1 419 637 7348",
    "sg:postcode":"43431",
    "sg:province":"OH",
    "sg:tags":[
        "beer",
        "ale"
    ],
    "wof:name":"Gail's Party Shoppe",
    "wof:placetype":"venue"
},
  "geometry": {"coordinates":[-83.32006199999999,41.383517],"type":"Point"}
}