{
  "type": "Feature",
  "properties": {
    "addr:full": "201 S Main St Gibsonburg OH 43431",
    "addr:housenumber": "201",
    "addr:postcode": "43431",
    "addr:street": "S Main St",
    "iso:country": "US",
    "sg:address": "201 S Main St",
    "sg:city": "Gibsonburg",
    "sg:classifiers": [
      {
        "category": "Food \u0026 Beverages",
        "subcategory": "Liquor \u0026 Beverages",
        "type": "Retail Goods"
      }
    ],
    "sg:phone": "+1 419 637 7348",
    "sg:postcode": "43431",
    "sg:province": "OH",
    "sg:tags": [
      "beer",
      "ale"
    ],
    "wof:name": "Gail's Party Shoppe",
    "wof:placetype": "venue"
  },
  "geometry": {"coordinates":[-83.320062,41.383517],"type":"Point"}
}
