{
  "type": "Feature",
  "properties": {
    "addr:full": "11513 US Hwy 250 Milan OH 44846",
    "addr:housenumber": "11513",
    "addr:postcode": "44846",
    "addr:street": "Us Hwy 250",
    "iso:country": "US",
    "sg:address": "11513 US Hwy 250",
    "sg:city": "Milan",
    "sg:classifiers": [
      {
        "category": "Wholesale",
        "subcategory": "Farm Supplies",
        "type": "Manufacturing \u0026 Wholesale Goods"
      }
    ],
    "sg:phone": "+1 419 499 2572",
    "sg:postcode": "44846",
    "sg:province": "OH",
    "sg:tags": [
      "oil",
      "marketing",
      "crop",
      "soybean",
      "mill",
      "prep"
    ],
    "sg:website": "www.schlessman-seed.com",
    "wof:name": "Schlessman Seed Co",
    "wof:placetype": "venue"
  },
  "geometry": {"coordinates":[-82.606771,41.311095],"type":"Point"}
}
