{
  "type": "Feature",
  "properties": {
    "iso:country":"US",
    "sg:address":"11513 US Hwy 250",
    "sg:city":"Milan",
    "sg:classifiers":[
        {
            "category":"Wholesale",
            "subcategory":"Farm Supplies",
            "type":"Manufacturing & Wholesale Goods"
        }
    ],
    "sg:phone":"+1 419 499 2572",
    "sg:postcode":"44846",
    "sg:province":"OH",
    "sg:tags":[
        "oil",
        "marketing",
        "crop",
        "soybean",
        "mill",
        "prep"
    ],
    "sg:website":"www.schlessman-seed.com",
    "wof:name":"Schlessman Seed Co",
    "wof:placetype":"venue"
},
  "geometry": {"coordinates":[-82.60677099999999,41.311095],"type":"Point"}
}