{
  "type": "Feature",
  "properties": {
    "iso:country":"US",
    "sg:address":"14979 State Rte 199",
    "sg:city":"Pemberville",
    "sg:phone":"+1 419 287 4226",
    "sg:postcode":"43450",
    "sg:province":"OH",
    "sg:tags":[
        "farm",
        "corn",
        "soybean"
    ],
    "wof:name":"Allen Kemner",
    "wof:placetype":"venue"
},
  "geometry": {"coordinates":[-83.512641,41.376768],"type":"Point"}
}