{
  "type": "Feature",
  "properties": {
    "addr:full":"6250 Corporate Center Dr Dublin OH 43016",
    "addr:housenumber":"6250",
    "addr:postcode":"43016",
    "addr:street":"Corporate Center Dr",
    "iso:country":"US",
    "sg:address":"6250 Corporate Center Dr",
    "sg:city":"Dublin",
    "sg:classifiers":[
        {
            "category":"Wholesale",
            "subcategory":"Construction Materials",
            "type":"Manufacturing & Wholesale Goods"
        }
    ],
    "sg:phone":"+1 614 659 9480",
    "sg:postcode":"43016",
    "sg:province":"OH",
    "sg:tags":[
        "cement"
    ],
    "wof:name":"Ellis Cement Contracting",
    "wof:placetype":"venue"
},
  "geometry": {"coordinates":[-83.159448,40.082354],"type":"Point"}
}