{
  "type": "Feature",
  "properties": {
    "addr:full":"3518 Monroe St Toledo OH 43606",
    "addr:housenumber":"3518",
    "addr:postcode":"43606",
    "addr:street":"Monroe St",
    "iso:country":"US",
    "sg:address":"3518 Monroe St",
    "sg:city":"Toledo",
    "sg:classifiers":[
        {
            "category":"Social Services",
            "subcategory":"Child Care",
            "type":"Services"
        }
    ],
    "sg:phone":"+1 419 242 8271",
    "sg:postcode":"43606",
    "sg:province":"OH",
    "wof:name":"Utley's Center Caring",
    "wof:placetype":"venue"
},
  "geometry": {"coordinates":[-83.581625,41.670009],"type":"Point"}
}