{
  "type": "Feature",
  "properties": {
    "addr:full": "401 Market St Steubenville OH 43952",
    "addr:housenumber": "401",
    "addr:postcode": "43952",
    "addr:street": "Market St",
    "iso:country": "US",
    "sg:address": "401 Market St",
    "sg:city": "Steubenville",
    "sg:classifiers": [
      {
        "category": "Professional",
        "subcategory": "Lawyer \u0026 Legal Services",
        "type": "Services"
      }
    ],
    "sg:phone": "+1 740 284 1682",
    "sg:postcode": "43952",
    "sg:province": "OH",
    "sg:tags": [
      "attorney"
    ],
    "wof:name": "Dickie Mc Cammey \u0026 Chilkote",
    "wof:placetype": "venue"
  },
  "geometry": {"coordinates":[-80.615938,40.360238],"type":"Point"}
}
