{
  "type": "Feature",
  "properties": {
    "addr:full": "202 N Columbus St Lancaster OH 43130",
    "addr:housenumber": "202",
    "addr:postcode": "43130",
    "addr:street": "N Columbus St",
    "iso:country": "US",
    "sg:address": "202 N Columbus St",
    "sg:city": "Lancaster",
    "sg:classifiers": [
      {
        "category": "Personal",
        "subcategory": "Beauty Salon",
        "type": "Services"
      }
    ],
    "sg:phone": "+1 740 681 1970",
    "sg:postcode": "43130",
    "sg:province": "OH",
    "wof:name": "United Hair Artist",
    "wof:placetype": "venue"
  },
  "geometry": {"coordinates":[-82.604429,39.715622],"type":"Point"}
}
