{
  "type": "Feature",
  "properties": {
    "addr:full":"4565 New Rd Youngstown OH 44515",
    "addr:housenumber":"4565",
    "addr:postcode":"44515",
    "addr:street":"New Rd",
    "iso:country":"US",
    "sg:address":"4565 New Rd",
    "sg:city":"Youngstown",
    "sg:classifiers":[
        {
            "category":"Education",
            "subcategory":"School",
            "type":"Public Place"
        }
    ],
    "sg:phone":"+1 330 793 1250",
    "sg:postcode":"44515",
    "sg:province":"OH",
    "wof:name":"St Joseph School-Youngstown",
    "wof:placetype":"venue"
},
  "geometry": {"coordinates":[-80.742375,41.083444],"type":"Point"}
}