{
  "type": "Feature",
  "properties": {
    "addr:full": "3323 Wunder Ave Cincinnati OH 45211",
    "addr:housenumber": "3323",
    "addr:postcode": "45211",
    "addr:street": "Wunder Ave",
    "iso:country": "US",
    "sg:address": "3323 Wunder Ave",
    "sg:city": "Cincinnati",
    "sg:classifiers": [
      {
        "category": "Food \u0026 Beverages",
        "subcategory": "Groceries \u0026 Convenience Stores",
        "type": "Retail Goods"
      }
    ],
    "sg:phone": "+1 513 661 0820",
    "sg:postcode": "45211",
    "sg:province": "OH",
    "wof:name": "Quick Shop",
    "wof:placetype": "venue"
  },
  "geometry": {"coordinates":[-84.592579,39.147371],"type":"Point"}
}
