{
  "type": "Feature",
  "properties": {
    "iso:country":"US",
    "sg:address":"3323 Wunder Ave",
    "sg:city":"Cincinnati",
    "sg:classifiers":[
        {
            "category":"Food & Beverages",
            "subcategory":"Groceries & Convenience Stores",
            "type":"Retail Goods"
        }
    ],
    "sg:phone":"+1 513 661 0820",
    "sg:postcode":"45211",
    "sg:province":"OH",
    "wof:name":"Quick Shop",
    "wof:placetype":"venue"
},
  "geometry": {"coordinates":[-84.592579,39.147371],"type":"Point"}
}