{
  "type": "Feature",
  "properties": {
    "iso:country":"US",
    "sg:address":"4049 Northwood Dr SE",
    "sg:city":"Warren",
    "sg:classifiers":[
        {
            "category":"Real Estate",
            "subcategory":"Real Estate Operator",
            "type":"Services"
        }
    ],
    "sg:phone":"+1 330 856 4058",
    "sg:postcode":"44484",
    "sg:province":"OH",
    "sg:tags":[
        "building",
        "apartment"
    ],
    "wof:name":"Car Lor Ltd",
    "wof:placetype":"venue"
},
  "geometry": {"coordinates":[-80.764933,41.233138],"type":"Point"}
}