{
  "type": "Feature",
  "properties": {
    "iso:country":"US",
    "sg:address":"4777 Spring Grove Ave",
    "sg:city":"Cincinnati",
    "sg:classifiers":[
        {
            "category":"Autos & Motor Vehicles",
            "subcategory":"Automobile Sales",
            "type":"Retail Goods"
        }
    ],
    "sg:phone":"+1 513 542 8000",
    "sg:postcode":"45232",
    "sg:province":"OH",
    "sg:website":"www.superiorhondastore.com",
    "wof:name":"Superior Honda",
    "wof:placetype":"venue"
},
  "geometry": {"coordinates":[-84.51678699999999,39.164642],"type":"Point"}
}