{
  "type": "Feature",
  "properties": {
    "addr:full": "4777 Spring Grove Ave Cincinnati OH 45232",
    "addr:housenumber": "4777",
    "addr:postcode": "45232",
    "addr:street": "Spring Grove Ave",
    "iso:country": "US",
    "sg:address": "4777 Spring Grove Ave",
    "sg:city": "Cincinnati",
    "sg:classifiers": [
      {
        "category": "Autos \u0026 Motor Vehicles",
        "subcategory": "Automobile Sales",
        "type": "Retail Goods"
      }
    ],
    "sg:phone": "+1 513 542 8000",
    "sg:postcode": "45232",
    "sg:province": "OH",
    "sg:website": "www.superiorhondastore.com",
    "wof:name": "Superior Honda",
    "wof:placetype": "venue"
  },
  "geometry": {"coordinates":[-84.516787,39.164642],"type":"Point"}
}
