{
  "type": "Feature",
  "properties": {
    "iso:country":"US",
    "sg:address":"3275 S Dixie Hwy",
    "sg:city":"Lima",
    "sg:classifiers":[
        {
            "category":"Education",
            "subcategory":"Dance Studio",
            "type":"Public Place"
        }
    ],
    "sg:phone":"+1 419 991 7231",
    "sg:postcode":"45804",
    "sg:province":"OH",
    "sg:tags":[
        "instruction",
        "dancing"
    ],
    "wof:name":"Patti Runser Dance Studio",
    "wof:placetype":"venue"
},
  "geometry": {"coordinates":[-84.126001,40.692085],"type":"Point"}
}