{
  "type": "Feature",
  "properties": {
    "addr:full": "6135 Memorial Dr Dublin OH 43017",
    "addr:housenumber": "6135",
    "addr:postcode": "43017",
    "addr:street": "Memorial Dr",
    "iso:country": "US",
    "sg:address": "6135 Memorial Dr",
    "sg:city": "Dublin",
    "sg:classifiers": [
      {
        "category": "Professional",
        "subcategory": "Lawyer \u0026 Legal Services",
        "type": "Services"
      }
    ],
    "sg:phone": "+1 614 761 9988",
    "sg:postcode": "43017",
    "sg:province": "OH",
    "sg:tags": [
      "attorney"
    ],
    "wof:name": "Purcell Law Office LLC",
    "wof:placetype": "venue"
  },
  "geometry": {"coordinates":[-83.149503,40.134623],"type":"Point"}
}
