{
  "type": "Feature",
  "properties": {
    "addr:full":"6406 Pebblecreek Dr Cleveland OH 44131",
    "addr:housenumber":"6406",
    "addr:postcode":"44131",
    "addr:street":"Pebblecreek Dr",
    "iso:country":"US",
    "sg:address":"6406 Pebblecreek Dr",
    "sg:city":"Cleveland",
    "sg:classifiers":[
        {
            "category":"Shopping",
            "subcategory":"Clothing, Apparel, & Fashions",
            "type":"Retail Goods"
        }
    ],
    "sg:phone":"+1 216 781 0280",
    "sg:postcode":"44131",
    "sg:province":"OH",
    "wof:name":"Crazy Cowboy",
    "wof:placetype":"venue"
},
  "geometry": {"coordinates":[-81.65841399999999,41.387637],"type":"Point"}
}