{
  "type": "Feature",
  "properties": {
    "iso:country":"US",
    "sg:address":"184 Currie Hall Pkwy",
    "sg:city":"Kent",
    "sg:classifiers":[
        {
            "category":"Health Services",
            "subcategory":"Doctor",
            "type":"Services"
        }
    ],
    "sg:phone":"+1 330 677 1451",
    "sg:postcode":"44240",
    "sg:province":"OH",
    "sg:tags":[
        "medical",
        "merchandise"
    ],
    "wof:name":"Kent Orthtic Prosthetic Clinic",
    "wof:placetype":"venue"
},
  "geometry": {"coordinates":[-81.361305,41.135337],"type":"Point"}
}