{
  "type": "Feature",
  "properties": {
    "addr:full":"4914 S Prospect St Ravenna OH 44266",
    "addr:housenumber":"4914",
    "addr:postcode":"44266",
    "addr:street":"S Prospect St",
    "iso:country":"US",
    "sg:address":"4914 S Prospect St",
    "sg:city":"Ravenna",
    "sg:classifiers":[
        {
            "category":"Restaurant",
            "type":"Food & Drink"
        }
    ],
    "sg:menulink":"http://www.allmenus.com/oh/rootstown/159049-acapulco/menu/",
    "sg:phone":"+1 330 297 5250",
    "sg:postcode":"44266",
    "sg:province":"OH",
    "sg:tags":[
        "american",
        "mexican",
        "tex-mex"
    ],
    "wof:name":"Acapulco",
    "wof:placetype":"venue"
},
  "geometry": {"coordinates":[-81.242099,41.124843],"type":"Point"}
}