{
  "type": "Feature",
  "properties": {
    "addr:full": "1100 E Main Cross St Findlay OH 45840",
    "addr:housenumber": "1100",
    "addr:postcode": "45840",
    "addr:street": "E Main Cross St",
    "iso:country": "US",
    "sg:address": "1100 E Main Cross St",
    "sg:city": "Findlay",
    "sg:classifiers": [
      {
        "category": "Banks \u0026 Credit Unions",
        "subcategory": "Investment Brokerage",
        "type": "Services"
      }
    ],
    "sg:phone": "+1 419 422 4400",
    "sg:postcode": "45840",
    "sg:province": "OH",
    "sg:tags": [
      "advisory",
      "financial"
    ],
    "wof:name": "Stragetic Investments Advisors",
    "wof:placetype": "venue"
  },
  "geometry": {"coordinates":[-83.628374,41.041494],"type":"Point"}
}
