{
  "type": "Feature",
  "properties": {
    "iso:country":"US",
    "sg:address":"4460 Drinkle Rd SW",
    "sg:city":"Amanda",
    "sg:phone":"+1 740 969 2719",
    "sg:postcode":"43102",
    "sg:province":"OH",
    "sg:tags":[
        "farm",
        "corn",
        "soybean"
    ],
    "wof:name":"George Sharp",
    "wof:placetype":"venue"
},
  "geometry": {"coordinates":[-82.69318699999999,39.590674],"type":"Point"}
}