{
  "type": "Feature",
  "properties": {
    "addr:full": "902 Dixie Hwy Wapakoneta OH 45895",
    "addr:housenumber": "902",
    "addr:postcode": "45895",
    "addr:street": "Dixie Hwy",
    "iso:country": "US",
    "sg:address": "902 Dixie Hwy",
    "sg:city": "Wapakoneta",
    "sg:classifiers": [
      {
        "category": "Home \u0026 Garden",
        "subcategory": "Building Materials",
        "type": "Retail Goods"
      }
    ],
    "sg:phone": "+1 419 738 7117",
    "sg:postcode": "45895",
    "sg:province": "OH",
    "sg:tags": [
      "glass",
      "window",
      "plate"
    ],
    "wof:name": "Gates Brothers Glass Shop",
    "wof:placetype": "venue"
  },
  "geometry": {"coordinates":[-84.175845,40.579748],"type":"Point"}
}
