{
  "type": "Feature",
  "properties": {
    "iso:country":"US",
    "sg:address":"902 Dixie Hwy",
    "sg:city":"Wapakoneta",
    "sg:classifiers":[
        {
            "category":"Home & Garden",
            "subcategory":"Building Materials",
            "type":"Retail Goods"
        }
    ],
    "sg:phone":"+1 419 738 7117",
    "sg:postcode":"45895",
    "sg:province":"OH",
    "sg:tags":[
        "glass",
        "window",
        "plate"
    ],
    "wof:name":"Gates Brothers Glass Shop",
    "wof:placetype":"venue"
},
  "geometry": {"coordinates":[-84.175845,40.579748],"type":"Point"}
}