{
  "type": "Feature",
  "properties": {
    "addr:full":"2540 Niles Rd SE Warren OH 44484",
    "addr:housenumber":"2540",
    "addr:postcode":"44484",
    "addr:street":"Niles Rd Se",
    "iso:country":"US",
    "sg:address":"2540 Niles Rd SE",
    "sg:city":"Warren",
    "sg:classifiers":[
        {
            "category":"Retail",
            "subcategory":"Car Wash",
            "type":"Services"
        }
    ],
    "sg:phone":"+1 330 369 1985",
    "sg:postcode":"44484",
    "sg:province":"OH",
    "sg:tags":[
        "polishing",
        "washing"
    ],
    "wof:name":"Willie's Car Wash",
    "wof:placetype":"venue"
},
  "geometry": {"coordinates":[-80.7923,41.216664],"type":"Point"}
}