{
  "type": "Feature",
  "properties": {
    "addr:full": "4568 Star Rd N Greenwich OH 44837",
    "addr:housenumber": "4568",
    "addr:postcode": "44837",
    "addr:street": "Star Rd N",
    "iso:country": "US",
    "sg:address": "4568 Star Rd N",
    "sg:city": "Greenwich",
    "sg:classifiers": [
      {
        "category": "Manufacturing",
        "subcategory": "Chemicals \u0026 Compounds",
        "type": "Manufacturing \u0026 Wholesale Goods"
      }
    ],
    "sg:phone": "+1 419 752 5104",
    "sg:postcode": "44837",
    "sg:province": "OH",
    "sg:tags": [
      "mfg"
    ],
    "wof:name": "Dale A Wilson",
    "wof:placetype": "venue"
  },
  "geometry": {"coordinates":[-82.5186,41.01172],"type":"Point"}
}
