{
  "type": "Feature",
  "properties": {
    "iso:country":"US",
    "sg:address":"4568 Star Rd N",
    "sg:city":"Greenwich",
    "sg:classifiers":[
        {
            "category":"Manufacturing",
            "subcategory":"Chemicals & Compounds",
            "type":"Manufacturing & Wholesale Goods"
        }
    ],
    "sg:phone":"+1 419 752 5104",
    "sg:postcode":"44837",
    "sg:province":"OH",
    "sg:tags":[
        "mfg"
    ],
    "wof:name":"Dale A Wilson",
    "wof:placetype":"venue"
},
  "geometry": {"coordinates":[-82.51860000000001,41.01172],"type":"Point"}
}