{
  "type": "Feature",
  "properties": {
    "addr:full": "750 E Central Ave Toledo OH 43608",
    "addr:housenumber": "750",
    "addr:postcode": "43608",
    "addr:street": "E Central Ave",
    "iso:country": "US",
    "sg:address": "750 E Central Ave",
    "sg:city": "Toledo",
    "sg:classifiers": [
      {
        "category": "Autos \u0026 Motor Vehicles",
        "subcategory": "Fuel \u0026 Gas Station",
        "type": "Retail Goods"
      }
    ],
    "sg:phone": "+1 419 244 0033",
    "sg:postcode": "43608",
    "sg:province": "OH",
    "sg:tags": [
      "station",
      "gasoline",
      "oil"
    ],
    "wof:name": "American Petroleum 3",
    "wof:placetype": "venue"
  },
  "geometry": {"coordinates":[-83.527487,41.678879],"type":"Point"}
}
