{
  "type": "Feature",
  "properties": {
    "iso:country":"US",
    "sg:address":"750 E Central Ave",
    "sg:city":"Toledo",
    "sg:classifiers":[
        {
            "category":"Autos & Motor Vehicles",
            "subcategory":"Fuel & Gas Station",
            "type":"Retail Goods"
        }
    ],
    "sg:phone":"+1 419 244 0033",
    "sg:postcode":"43608",
    "sg:province":"OH",
    "sg:tags":[
        "station",
        "gasoline",
        "oil"
    ],
    "wof:name":"American Petroleum 3",
    "wof:placetype":"venue"
},
  "geometry": {"coordinates":[-83.52748699999999,41.678879],"type":"Point"}
}