{
  "type": "Feature",
  "properties": {
    "addr:full":"1357 W Lane Ave Columbus OH 43221",
    "addr:housenumber":"1357",
    "addr:postcode":"43221",
    "addr:street":"W Lane Ave",
    "iso:country":"US",
    "sg:address":"1357 W Lane Ave",
    "sg:city":"Columbus",
    "sg:classifiers":[
        {
            "category":"Professional",
            "subcategory":"Business Services",
            "type":"Services"
        }
    ],
    "sg:phone":"+1 614 324 1610",
    "sg:postcode":"43221",
    "sg:province":"OH",
    "sg:tags":[
        "telemarketing"
    ],
    "wof:name":"Global Technology LTD",
    "wof:placetype":"venue"
},
  "geometry": {"coordinates":[-83.047386,40.006835],"type":"Point"}
}