{
  "type": "Feature",
  "properties": {
    "addr:full":"1175 Worthington Woods Blvd Columbus OH 43085",
    "addr:housenumber":"1175",
    "addr:postcode":"43085",
    "addr:street":"Worthington Woods Blvd",
    "iso:country":"US",
    "sg:address":"1175 Worthington Woods Blvd",
    "sg:city":"Columbus",
    "sg:classifiers":[
        {
            "category":"Restaurant",
            "type":"Food & Drink"
        }
    ],
    "sg:phone":"+1 614 844 4210",
    "sg:postcode":"43085",
    "sg:province":"OH",
    "sg:tags":[
        "eating"
    ],
    "wof:name":"Giuseppes Bistro Italiano",
    "wof:placetype":"venue"
},
  "geometry": {"coordinates":[-82.987172,40.118457],"type":"Point"}
}