{
  "type": "Feature",
  "properties": {
    "iso:country":"US",
    "sg:address":"2954 Walnut St",
    "sg:city":"Portsmouth",
    "sg:classifiers":[
        {
            "category":"Shopping",
            "type":"Retail Goods"
        }
    ],
    "sg:phone":"+1 740 354 4775",
    "sg:postcode":"45662",
    "sg:province":"OH",
    "sg:tags":[
        "limb",
        "artificial"
    ],
    "sg:website":"www.hanger.com",
    "wof:name":"Hanger Prosthetics & Orthotics",
    "wof:placetype":"venue"
},
  "geometry": {"coordinates":[-82.955381,38.742354],"type":"Point"}
}