{
  "type": "Feature",
  "properties": {
    "addr:full":"60 Fir Hill Akron OH 44304",
    "addr:housenumber":"60",
    "addr:postcode":"44304",
    "addr:street":"Fir Hill",
    "iso:country":"US",
    "sg:address":"60 Fir Hill",
    "sg:city":"Akron",
    "sg:classifiers":[
        {
            "category":"Shopping",
            "subcategory":"Gifts & Souvenirs",
            "type":"Retail Goods"
        }
    ],
    "sg:phone":"+1 330 972 6909",
    "sg:postcode":"44304",
    "sg:province":"OH",
    "wof:name":"Cellar Door Store",
    "wof:placetype":"venue"
},
  "geometry": {"coordinates":[-81.507547,41.077127],"type":"Point"}
}