{
  "type": "Feature",
  "properties": {
    "addr:full": "1869 W Main St Troy OH 45373",
    "addr:housenumber": "1869",
    "addr:postcode": "45373",
    "addr:street": "W Main St",
    "iso:country": "US",
    "sg:address": "1869 W Main St",
    "sg:city": "Troy",
    "sg:classifiers": [
      {
        "category": "Shopping",
        "subcategory": "Department Store",
        "type": "Retail Goods"
      }
    ],
    "sg:phone": "+1 937 335 0858",
    "sg:postcode": "45373",
    "sg:province": "OH",
    "wof:name": "Kohl's",
    "wof:placetype": "venue"
  },
  "geometry": {"coordinates":[-84.239588,40.055448],"type":"Point"}
}
