{
  "type": "Feature",
  "properties": {
    "iso:country":"US",
    "sg:address":"1042 Argonne Rd",
    "sg:city":"Cleveland",
    "sg:classifiers":[
        {
            "category":"Manufacturing",
            "subcategory":"Printing",
            "type":"Manufacturing & Wholesale Goods"
        }
    ],
    "sg:phone":"+1 216 382 0188",
    "sg:postcode":"44121",
    "sg:province":"OH",
    "sg:tags":[
        "multimedia"
    ],
    "wof:name":"Bill G Media",
    "wof:placetype":"venue"
},
  "geometry": {"coordinates":[-81.530427,41.532612],"type":"Point"}
}