{
  "type": "Feature",
  "properties": {
    "iso:country":"US",
    "sg:address":"7482 E Main St",
    "sg:city":"Reynoldsburg",
    "sg:classifiers":[
        {
            "category":"Retail",
            "subcategory":"Portrait Studio",
            "type":"Services"
        }
    ],
    "sg:phone":"+1 614 866 3609",
    "sg:postcode":"43068",
    "sg:province":"OH",
    "sg:tags":[
        "photographer"
    ],
    "wof:name":"Studio One Photography",
    "wof:placetype":"venue"
},
  "geometry": {"coordinates":[-82.796744,39.95545],"type":"Point"}
}