{
  "type": "Feature",
  "properties": {
    "iso:country":"US",
    "sg:address":"21757 Gate House Ln",
    "sg:city":"Rocky River",
    "sg:classifiers":[
        {
            "category":"Wholesale",
            "subcategory":"Non-durable Goods",
            "type":"Manufacturing & Wholesale Goods"
        }
    ],
    "sg:phone":"+1 440 333 2636",
    "sg:postcode":"44116",
    "sg:province":"OH",
    "sg:tags":[
        "packaging",
        "material"
    ],
    "wof:name":"International Packaging Netwrk",
    "wof:placetype":"venue"
},
  "geometry": {"coordinates":[-81.862054,41.474676],"type":"Point"}
}