{
  "type": "Feature",
  "properties": {
    "addr:full":"1500 Lake Shore Dr Columbus OH 43204",
    "addr:housenumber":"1500",
    "addr:postcode":"43204",
    "addr:street":"Lake Shore Dr",
    "iso:country":"US",
    "sg:address":"1500 Lake Shore Dr",
    "sg:city":"Columbus",
    "sg:classifiers":[
        {
            "category":"Professional",
            "subcategory":"Accounting & Tax Preparation",
            "type":"Services"
        }
    ],
    "sg:phone":"+1 614 486 3600",
    "sg:postcode":"43204",
    "sg:province":"OH",
    "sg:tags":[
        "accountant"
    ],
    "wof:name":"Ary Roepcke & Mulchaey PC",
    "wof:placetype":"venue"
},
  "geometry": {"coordinates":[-83.06704999999999,39.980344],"type":"Point"}
}