{
  "type": "Feature",
  "properties": {
    "addr:full":"5455 N Marginal Rd Cleveland OH 44114",
    "addr:housenumber":"5455",
    "addr:postcode":"44114",
    "addr:street":"N Marginal Rd",
    "iso:country":"US",
    "sg:address":"5455 N Marginal Rd",
    "sg:city":"Cleveland",
    "sg:classifiers":[
        {
            "category":"Professional",
            "subcategory":"Lawyer & Legal Services",
            "type":"Services"
        }
    ],
    "sg:phone":"+1 216 361 9616",
    "sg:postcode":"44114",
    "sg:province":"OH",
    "sg:tags":[
        "attorney"
    ],
    "wof:name":"Carter R Dodge Law Office",
    "wof:placetype":"venue"
},
  "geometry": {"coordinates":[-81.651976,41.531024],"type":"Point"}
}