{
  "type": "Feature",
  "properties": {
    "addr:full": "4323 Payne Ave Cleveland OH 44103",
    "addr:housenumber": "4323",
    "addr:postcode": "44103",
    "addr:street": "Payne Ave",
    "iso:country": "US",
    "sg:address": "4323 Payne Ave",
    "sg:city": "Cleveland",
    "sg:classifiers": [
      {
        "category": "Restaurant",
        "type": "Food \u0026 Drink"
      }
    ],
    "sg:phone": "+1 216 391 9131",
    "sg:postcode": "44103",
    "sg:province": "OH",
    "sg:tags": [
      "eating"
    ],
    "wof:name": "Jack Sprat S Pizza",
    "wof:placetype": "venue"
  },
  "geometry": {"coordinates":[-81.65583,41.511621],"type":"Point"}
}
