{
  "type": "Feature",
  "properties": {
    "addr:full": "1500 S University Blvd Middletown OH 45044",
    "addr:housenumber": "1500",
    "addr:postcode": "45044",
    "addr:street": "S University Blvd",
    "iso:country": "US",
    "sg:address": "1500 S University Blvd",
    "sg:city": "Middletown",
    "sg:classifiers": [
      {
        "category": "Wholesale",
        "subcategory": "Stationery",
        "type": "Manufacturing \u0026 Wholesale Goods"
      }
    ],
    "sg:phone": "+1 513 423 0319",
    "sg:postcode": "45044",
    "sg:province": "OH",
    "sg:tags": [
      "box",
      "fiber"
    ],
    "wof:name": "N-Stock Box Inc",
    "wof:placetype": "venue"
  },
  "geometry": {"coordinates":[-84.396741,39.501076],"type":"Point"}
}
