{
  "type": "Feature",
  "properties": {
    "iso:country":"US",
    "sg:address":"3372 Red Bank Rd",
    "sg:city":"Cincinnati",
    "sg:classifiers":[
        {
            "category":"Government",
            "subcategory":"Office",
            "type":"Public Place"
        }
    ],
    "sg:phone":"+1 513 271 2770",
    "sg:postcode":"45227",
    "sg:province":"OH",
    "wof:name":"Red Bank License Svc",
    "wof:placetype":"venue"
},
  "geometry": {"coordinates":[-84.401069,39.136447],"type":"Point"}
}