{
  "type": "Feature",
  "properties": {
    "iso:country":"US",
    "sg:address":"1400 Cavalcade Dr",
    "sg:city":"Youngstown",
    "sg:classifiers":[
        {
            "category":"Retail",
            "subcategory":"Car Wash",
            "type":"Services"
        }
    ],
    "sg:phone":"+1 330 792 9262",
    "sg:postcode":"44515",
    "sg:province":"OH",
    "sg:tags":[
        "auto",
        "detailing"
    ],
    "wof:name":"Custom Detailing",
    "wof:placetype":"venue"
},
  "geometry": {"coordinates":[-80.74658100000001,41.086522],"type":"Point"}
}