{
  "type": "Feature",
  "properties": {
    "addr:full": "949 Old Farm Rd Columbus OH 43213",
    "addr:housenumber": "949",
    "addr:postcode": "43213",
    "addr:street": "Old Farm Rd",
    "iso:country": "US",
    "sg:address": "949 Old Farm Rd",
    "sg:city": "Columbus",
    "sg:classifiers": [
      {
        "category": "Restaurant",
        "type": "Food \u0026 Drink"
      }
    ],
    "sg:phone": "+1 614 864 9499",
    "sg:postcode": "43213",
    "sg:province": "OH",
    "sg:tags": [
      "eating"
    ],
    "wof:name": "For Special Occasions",
    "wof:placetype": "venue"
  },
  "geometry": {"coordinates":[-82.847239,39.959625],"type":"Point"}
}
