{
  "type": "Feature",
  "properties": {
    "iso:country":"US",
    "sg:address":"949 Old Farm Rd",
    "sg:city":"Columbus",
    "sg:classifiers":[
        {
            "category":"Restaurant",
            "type":"Food & Drink"
        }
    ],
    "sg:phone":"+1 614 864 9499",
    "sg:postcode":"43213",
    "sg:province":"OH",
    "sg:tags":[
        "eating"
    ],
    "wof:name":"For Special Occasions",
    "wof:placetype":"venue"
},
  "geometry": {"coordinates":[-82.847239,39.959625],"type":"Point"}
}