{
  "type": "Feature",
  "properties": {
    "addr:full":"14536 State Rte 595 Logan OH 43138",
    "addr:housenumber":"14536",
    "addr:postcode":"43138",
    "addr:street":"State Rte 595",
    "iso:country":"US",
    "sg:address":"14536 State Rte 595",
    "sg:city":"Logan",
    "sg:classifiers":[
        {
            "category":"Real Estate",
            "subcategory":"Real Estate Agent",
            "type":"Services"
        }
    ],
    "sg:phone":"+1 740 385 8743",
    "sg:postcode":"43138",
    "sg:province":"OH",
    "wof:name":"Johnsons Corner",
    "wof:placetype":"venue"
},
  "geometry": {"coordinates":[-82.307667,39.509098],"type":"Point"}
}