{
  "type": "Feature",
  "properties": {
    "addr:full":"464 N Twp Rd 169 Republic OH 44867",
    "addr:housenumber":"464;169",
    "addr:postcode":"44867",
    "addr:street":"N Twp Rd",
    "iso:country":"US",
    "sg:address":"464 N Twp Rd 169",
    "sg:city":"Republic",
    "sg:classifiers":[
        {
            "category":"Professional",
            "type":"Services"
        }
    ],
    "sg:phone":"+1 419 585 0190",
    "sg:postcode":"44867",
    "sg:province":"OH",
    "wof:name":"Linda Schultz",
    "wof:placetype":"venue"
},
  "geometry": {"coordinates":[-83.07396300000001,41.124607],"type":"Point"}
}