{
  "type": "Feature",
  "properties": {
    "addr:full": "500 Danberry Dr Wooster OH 44691",
    "addr:housenumber": "500",
    "addr:postcode": "44691",
    "addr:street": "Danberry Dr",
    "iso:country": "US",
    "sg:address": "500 Danberry Dr",
    "sg:city": "Wooster",
    "sg:classifiers": [
      {
        "category": "Farming",
        "subcategory": "Farm",
        "type": "Manufacturing \u0026 Wholesale Goods"
      }
    ],
    "sg:phone": "+1 330 264 4155",
    "sg:postcode": "44691",
    "sg:province": "OH",
    "sg:tags": [
      "crop",
      "general"
    ],
    "wof:name": "Howard N Lafever",
    "wof:placetype": "venue"
  },
  "geometry": {"coordinates":[-81.946947,40.825719],"type":"Point"}
}
