{
  "type": "Feature",
  "properties": {
    "addr:full": "4349 S Arlington Rd Uniontown OH 44685",
    "addr:housenumber": "4349",
    "addr:postcode": "44685",
    "addr:street": "S Arlington Rd",
    "iso:country": "US",
    "sg:address": "4349 S Arlington Rd",
    "sg:city": "Uniontown",
    "sg:classifiers": [
      {
        "category": "Building \u0026 Trades",
        "subcategory": "Pest Control",
        "type": "Services"
      }
    ],
    "sg:phone": "+1 330 644 2838",
    "sg:postcode": "44685",
    "sg:province": "OH",
    "wof:name": "Eliminator Pest Control",
    "wof:placetype": "venue"
  },
  "geometry": {"coordinates":[-81.494346,40.955],"type":"Point"}
}
