{
  "type": "Feature",
  "properties": {
    "iso:country":"US",
    "sg:address":"4349 S Arlington Rd",
    "sg:city":"Uniontown",
    "sg:classifiers":[
        {
            "category":"Building & Trades",
            "subcategory":"Pest Control",
            "type":"Services"
        }
    ],
    "sg:phone":"+1 330 644 2838",
    "sg:postcode":"44685",
    "sg:province":"OH",
    "wof:name":"Eliminator Pest Control",
    "wof:placetype":"venue"
},
  "geometry": {"coordinates":[-81.49434599999999,40.955],"type":"Point"}
}