{
  "type": "Feature",
  "properties": {
    "iso:country":"US",
    "sg:address":"5151 Fulton Dr NW",
    "sg:city":"Canton",
    "sg:classifiers":[
        {
            "category":"Restaurant",
            "type":"Food & Drink"
        }
    ],
    "sg:menulink":"http://www.allmenus.com/oh/canton/170175-burger-king/menu/",
    "sg:phone":"+1 216 494 6602",
    "sg:postcode":"44718",
    "sg:province":"OH",
    "sg:tags":[
        "burger",
        "american"
    ],
    "wof:name":"Burger King",
    "wof:placetype":"venue"
},
  "geometry": {"coordinates":[-81.445024,40.850009],"type":"Point"}
}