{
  "type": "Feature",
  "properties": {
    "addr:full": "5151 Fulton Dr NW Canton OH 44718",
    "addr:housenumber": "5151",
    "addr:postcode": "44718",
    "addr:street": "Fulton Dr Nw",
    "iso:country": "US",
    "sg:address": "5151 Fulton Dr NW",
    "sg:city": "Canton",
    "sg:classifiers": [
      {
        "category": "Restaurant",
        "type": "Food \u0026 Drink"
      }
    ],
    "sg:menulink": "http://www.allmenus.com/oh/canton/170175-burger-king/menu/",
    "sg:phone": "+1 216 494 6602",
    "sg:postcode": "44718",
    "sg:province": "OH",
    "sg:tags": [
      "burger",
      "american"
    ],
    "wof:name": "Burger King",
    "wof:placetype": "venue"
  },
  "geometry": {"coordinates":[-81.445024,40.850009],"type":"Point"}
}
