{
  "type": "Feature",
  "properties": {
    "addr:full":"25022 Center Ridge Rd Cleveland OH 44145",
    "addr:housenumber":"25022",
    "addr:postcode":"44145",
    "addr:street":"Center Ridge Rd",
    "iso:country":"US",
    "sg:address":"25022 Center Ridge Rd",
    "sg:city":"Cleveland",
    "sg:classifiers":[
        {
            "category":"Real Estate",
            "subcategory":"Real Estate Agent",
            "type":"Services"
        }
    ],
    "sg:phone":"+1 440 835 0279",
    "sg:postcode":"44145",
    "sg:province":"OH",
    "wof:name":"Realty Professionals Inc",
    "wof:placetype":"venue"
},
  "geometry": {"coordinates":[-81.893171,41.458103],"type":"Point"}
}