{
  "type": "Feature",
  "properties": {
    "addr:full": "8992 Cotter St Lewis Center OH 43035",
    "addr:housenumber": "8992",
    "addr:postcode": "43035",
    "addr:street": "Cotter St",
    "iso:country": "US",
    "sg:address": "8992 Cotter St",
    "sg:city": "Lewis Center",
    "sg:phone": "+1 740 548 8112",
    "sg:postcode": "43035",
    "sg:province": "OH",
    "sg:tags": [
      "scale"
    ],
    "wof:name": "A C Lister \u0026 Co",
    "wof:placetype": "venue"
  },
  "geometry": {"coordinates":[-83.010547,40.157591],"type":"Point"}
}
