{
  "type": "Feature",
  "properties": {
    "iso:country":"US",
    "sg:address":"3511 W Michigan St",
    "sg:city":"Sidney",
    "sg:classifiers":[
        {
            "category":"Bars & Pubs",
            "type":"Food & Drink"
        }
    ],
    "sg:phone":"+1 937 498 9667",
    "sg:postcode":"45365",
    "sg:province":"OH",
    "sg:tags":[
        "drinking",
        "eating"
    ],
    "wof:name":"Winners Inn",
    "wof:placetype":"venue"
},
  "geometry": {"coordinates":[-84.21590399999999,40.28723],"type":"Point"}
}