{
  "type": "Feature",
  "properties": {
    "addr:full": "3511 W Michigan St Sidney OH 45365",
    "addr:housenumber": "3511",
    "addr:postcode": "45365",
    "addr:street": "W Michigan St",
    "iso:country": "US",
    "sg:address": "3511 W Michigan St",
    "sg:city": "Sidney",
    "sg:classifiers": [
      {
        "category": "Bars \u0026 Pubs",
        "type": "Food \u0026 Drink"
      }
    ],
    "sg:phone": "+1 937 498 9667",
    "sg:postcode": "45365",
    "sg:province": "OH",
    "sg:tags": [
      "drinking",
      "eating"
    ],
    "wof:name": "Winners Inn",
    "wof:placetype": "venue"
  },
  "geometry": {"coordinates":[-84.215904,40.28723],"type":"Point"}
}
