{
  "type": "Feature",
  "properties": {
    "addr:full":"531 S Main St Englewood OH 45322",
    "addr:housenumber":"531",
    "addr:postcode":"45322",
    "addr:street":"S Main St",
    "iso:country":"US",
    "sg:address":"531 S Main St",
    "sg:city":"Englewood",
    "sg:classifiers":[
        {
            "category":"Food & Beverages",
            "subcategory":"Groceries & Convenience Stores",
            "type":"Retail Goods"
        }
    ],
    "sg:phone":"+1 937 836 2676",
    "sg:postcode":"45322",
    "sg:province":"OH",
    "sg:tags":[
        "grocer"
    ],
    "wof:name":"Stumps Market",
    "wof:placetype":"venue"
},
  "geometry": {"coordinates":[-84.295965,39.870684],"type":"Point"}
}