{
  "type": "Feature",
  "properties": {
    "addr:full":"29933 Euclid Ave Wickliffe OH 44092",
    "addr:housenumber":"29933",
    "addr:postcode":"44092",
    "addr:street":"Euclid Ave",
    "iso:country":"US",
    "sg:address":"29933 Euclid Ave",
    "sg:city":"Wickliffe",
    "sg:classifiers":[
        {
            "category":"Banks & Credit Unions",
            "subcategory":"Bank",
            "type":"Services"
        }
    ],
    "sg:phone":"+1 440 585 1840",
    "sg:postcode":"44092",
    "sg:province":"OH",
    "sg:tags":[
        "state"
    ],
    "sg:website":"www.skyfi.com",
    "wof:name":"Sky Bank",
    "wof:placetype":"venue"
},
  "geometry": {"coordinates":[-81.46562900000001,41.612608],"type":"Point"}
}