{
  "type": "Feature",
  "properties": {
    "addr:full":"2205 Greensburg Rd North Canton OH 44720",
    "addr:housenumber":"2205",
    "addr:postcode":"44720",
    "addr:street":"Greensburg Rd",
    "iso:country":"US",
    "sg:address":"2205 Greensburg Rd",
    "sg:city":"North Canton",
    "sg:classifiers":[
        {
            "category":"Insurance",
            "subcategory":"Insurance Agent",
            "type":"Services"
        }
    ],
    "sg:phone":"+1 330 896 1500",
    "sg:postcode":"44720",
    "sg:province":"OH",
    "wof:name":"Kenneth A Boldt Clu Insurance",
    "wof:placetype":"venue"
},
  "geometry": {"coordinates":[-81.465502,40.931635],"type":"Point"}
}