{
  "type": "Feature",
  "properties": {
    "iso:country":"US",
    "sg:address":"6615 Knightsbridge Ave NW",
    "sg:city":"Canton",
    "sg:classifiers":[
        {
            "category":"Communications",
            "type":"Services"
        }
    ],
    "sg:phone":"+1 330 834 1749",
    "sg:postcode":"44718",
    "sg:province":"OH",
    "sg:tags":[
        "communication"
    ],
    "wof:name":"Midwest Global Communications",
    "wof:placetype":"venue"
},
  "geometry": {"coordinates":[-81.474474,40.857901],"type":"Point"}
}