{
  "type": "Feature",
  "properties": {
    "iso:country":"US",
    "sg:address":"632 Murray Hill Dr",
    "sg:city":"Youngstown",
    "sg:classifiers":[
        {
            "category":"Real Estate",
            "subcategory":"Real Estate Operator",
            "type":"Services"
        }
    ],
    "sg:phone":"+1 330 759 1630",
    "sg:postcode":"44505",
    "sg:province":"OH",
    "sg:tags":[
        "property",
        "lessor"
    ],
    "wof:name":"Grace Mastran Property",
    "wof:placetype":"venue"
},
  "geometry": {"coordinates":[-80.65082,41.15425],"type":"Point"}
}