{
  "type": "Feature",
  "properties": {
    "addr:full": "5429 Center St Hilliard OH 43026",
    "addr:housenumber": "5429",
    "addr:postcode": "43026",
    "addr:street": "Center St",
    "iso:country": "US",
    "sg:address": "5429 Center St",
    "sg:city": "Hilliard",
    "sg:classifiers": [
      {
        "category": "Autos \u0026 Motor Vehicles",
        "subcategory": "Auto Supplies",
        "type": "Retail Goods"
      }
    ],
    "sg:phone": "+1 614 658 1313",
    "sg:postcode": "43026",
    "sg:province": "OH",
    "sg:tags": [
      "equipment",
      "racing",
      "car",
      "automobile"
    ],
    "wof:name": "Mac Nealy Performance Svc",
    "wof:placetype": "venue"
  },
  "geometry": {"coordinates":[-83.163731,40.036605],"type":"Point"}
}
