{
  "type": "Feature",
  "properties": {
    "iso:country":"US",
    "sg:address":"5429 Center St",
    "sg:city":"Hilliard",
    "sg:classifiers":[
        {
            "category":"Autos & Motor Vehicles",
            "subcategory":"Auto Supplies",
            "type":"Retail Goods"
        }
    ],
    "sg:phone":"+1 614 658 1313",
    "sg:postcode":"43026",
    "sg:province":"OH",
    "sg:tags":[
        "equipment",
        "racing",
        "car",
        "automobile"
    ],
    "wof:name":"Mac Nealy Performance Svc",
    "wof:placetype":"venue"
},
  "geometry": {"coordinates":[-83.163731,40.036605],"type":"Point"}
}