{
  "type": "Feature",
  "properties": {
    "iso:country":"US",
    "sg:address":"3812 Center Rd",
    "sg:city":"Brunswick",
    "sg:classifiers":[
        {
            "category":"Health Services",
            "subcategory":"Doctor",
            "type":"Services"
        }
    ],
    "sg:phone":"+1 330 225 5200",
    "sg:postcode":"44212",
    "sg:province":"OH",
    "sg:tags":[
        "physician",
        "surgeon"
    ],
    "wof:name":"Gregory Kitagawa MD",
    "wof:placetype":"venue"
},
  "geometry": {"coordinates":[-81.823001,41.238226],"type":"Point"}
}