{
  "type": "Feature",
  "properties": {
    "addr:full": "8601 Cedar Rd Chesterland OH 44026",
    "addr:housenumber": "8601",
    "addr:postcode": "44026",
    "addr:street": "Cedar Rd",
    "iso:country": "US",
    "sg:address": "8601 Cedar Rd",
    "sg:city": "Chesterland",
    "sg:classifiers": [
      {
        "category": "Building \u0026 Trades",
        "subcategory": "Construction",
        "type": "Services"
      }
    ],
    "sg:phone": "+1 440 729 8811",
    "sg:postcode": "44026",
    "sg:province": "OH",
    "sg:tags": [
      "contractor"
    ],
    "wof:name": "Tenant Construction Services",
    "wof:placetype": "venue"
  },
  "geometry": {"coordinates":[-81.334702,41.507401],"type":"Point"}
}
