{
  "type": "Feature",
  "properties": {
    "addr:full":"33223 Railroad St Lewisville OH 43754",
    "addr:housenumber":"33223",
    "addr:postcode":"43754",
    "addr:street":"Railroad St",
    "iso:country":"US",
    "sg:address":"33223 Railroad St",
    "sg:city":"Lewisville",
    "sg:classifiers":[
        {
            "category":"Shopping",
            "subcategory":"Discount & Variety Stores",
            "type":"Retail Goods"
        }
    ],
    "sg:phone":"+1 740 567 3349",
    "sg:postcode":"43754",
    "sg:province":"OH",
    "wof:name":"Pennell's Variety Store",
    "wof:placetype":"venue"
},
  "geometry": {"coordinates":[-81.217833,39.764815],"type":"Point"}
}