{
  "type": "Feature",
  "properties": {
    "addr:full": "2872 W Broad St Columbus OH 43204",
    "addr:housenumber": "2872",
    "addr:postcode": "43204",
    "addr:street": "W Broad St",
    "iso:country": "US",
    "sg:address": "2872 W Broad St",
    "sg:city": "Columbus",
    "sg:classifiers": [
      {
        "category": "Health Services",
        "subcategory": "Clinic",
        "type": "Services"
      },
      {
        "category": "Health Services",
        "subcategory": "Health Practitioner",
        "type": "Services"
      }
    ],
    "sg:phone": "+1 614 274 3400",
    "sg:postcode": "43204",
    "sg:province": "OH",
    "sg:tags": [
      "therapist",
      "physical",
      "specialty",
      "outpatient"
    ],
    "wof:name": "Hilltop Therapy Center",
    "wof:placetype": "venue"
  },
  "geometry": {"coordinates":[-83.077126,39.954881],"type":"Point"}
}
