{
  "type": "Feature",
  "properties": {
    "iso:country":"US",
    "sg:address":"4376 Midway Mall",
    "sg:city":"Elyria",
    "sg:classifiers":[
        {
            "category":"Shopping",
            "subcategory":"Clothing, Apparel, & Fashions",
            "type":"Retail Goods"
        }
    ],
    "sg:phone":"+1 440 324 5200",
    "sg:postcode":"44035",
    "sg:province":"OH",
    "sg:tags":[
        "store"
    ],
    "wof:name":"American Eagle Outfitters",
    "wof:placetype":"venue"
},
  "geometry": {"coordinates":[-82.1135,41.398763],"type":"Point"}
}