{
  "type": "Feature",
  "properties": {
    "addr:full":"46625 State Rte 536 Woodsfield OH 43793",
    "addr:housenumber":"46625",
    "addr:postcode":"43793",
    "addr:street":"State Rte 536",
    "iso:country":"US",
    "sg:address":"46625 State Rte 536",
    "sg:city":"Woodsfield",
    "sg:classifiers":[
        {
            "category":"Government",
            "subcategory":"Office",
            "type":"Public Place"
        }
    ],
    "sg:phone":"+1 740 472 1416",
    "sg:postcode":"43793",
    "sg:province":"OH",
    "sg:tags":[
        "executive"
    ],
    "wof:name":"Township of Adams",
    "wof:placetype":"venue"
},
  "geometry": {"coordinates":[-80.981465,39.741528],"type":"Point"}
}