{
  "type": "Feature",
  "properties": {
    "addr:full": "162 Walnut Grove Dr Dayton OH 45458",
    "addr:housenumber": "162",
    "addr:postcode": "45458",
    "addr:street": "Walnut Grove Dr",
    "iso:country": "US",
    "sg:address": "162 Walnut Grove Dr",
    "sg:city": "Dayton",
    "sg:classifiers": [
      {
        "category": "Real Estate",
        "subcategory": "Real Estate Agent",
        "type": "Services"
      }
    ],
    "sg:phone": "+1 937 885 3777",
    "sg:postcode": "45458",
    "sg:province": "OH",
    "wof:name": "Rtw Development Inc",
    "wof:placetype": "venue"
  },
  "geometry": {"coordinates":[-84.166132,39.597573],"type":"Point"}
}
