{
  "type": "Feature",
  "properties": {
    "iso:country":"US",
    "sg:address":"1192 E 40th St",
    "sg:city":"Cleveland",
    "sg:classifiers":[
        {
            "category":"Building & Trades",
            "subcategory":"Construction",
            "type":"Services"
        }
    ],
    "sg:phone":"+1 216 360 9393",
    "sg:postcode":"44114",
    "sg:province":"OH",
    "sg:tags":[
        "roofing",
        "contractor"
    ],
    "wof:name":"Katz The Roofer",
    "wof:placetype":"venue"
},
  "geometry": {"coordinates":[-81.666439,41.518839],"type":"Point"}
}