{
  "type": "Feature",
  "properties": {
    "iso:country":"US",
    "sg:address":"2421 Danube Ct",
    "sg:city":"Dayton",
    "sg:classifiers":[
        {
            "category":"Shopping",
            "subcategory":"Hobbies, Toys, & Games",
            "type":"Retail Goods"
        }
    ],
    "sg:phone":"+1 937 643 2221",
    "sg:postcode":"45420",
    "sg:province":"OH",
    "wof:name":"Shane Schaefer",
    "wof:placetype":"venue"
},
  "geometry": {"coordinates":[-84.120584,39.696784],"type":"Point"}
}