{
  "type": "Feature",
  "properties": {
    "addr:full":"1325 W 1st St Springfield OH 45504",
    "addr:housenumber":"1325",
    "addr:postcode":"45504",
    "addr:street":"W 1St St",
    "iso:country":"US",
    "sg:address":"1325 W 1st St",
    "sg:city":"Springfield",
    "sg:classifiers":[
        {
            "category":"Shopping",
            "subcategory":"Musical Instruments",
            "type":"Retail Goods"
        }
    ],
    "sg:phone":"+1 937 325 7071",
    "sg:postcode":"45504",
    "sg:province":"OH",
    "sg:website":"www.kincaidsmusic.com",
    "wof:name":"Kincaid's Is Music",
    "wof:placetype":"venue"
},
  "geometry": {"coordinates":[-83.832132,39.940762],"type":"Point"}
}