{
  "type": "Feature",
  "properties": {
    "addr:full": "8148 Augusta Ln Northfield OH 44067",
    "addr:housenumber": "8148",
    "addr:postcode": "44067",
    "addr:street": "Augusta Ln",
    "iso:country": "US",
    "sg:address": "8148 Augusta Ln",
    "sg:city": "Northfield",
    "sg:classifiers": [
      {
        "category": "Professional",
        "type": "Services"
      }
    ],
    "sg:phone": "+1 330 908 0810",
    "sg:postcode": "44067",
    "sg:province": "OH",
    "wof:name": "Deborah B Sanford",
    "wof:placetype": "venue"
  },
  "geometry": {"coordinates":[-81.542502,41.336537],"type":"Point"}
}
