{
  "type": "Feature",
  "properties": {
    "iso:country":"US",
    "sg:address":"803 Sharon Dr",
    "sg:city":"Cleveland",
    "sg:classifiers":[
        {
            "category":"Home & Garden",
            "subcategory":"Furniture",
            "type":"Retail Goods"
        }
    ],
    "sg:phone":"+1 440 614 0150",
    "sg:postcode":"44145",
    "sg:province":"OH",
    "sg:tags":[
        "cabinet"
    ],
    "wof:name":"All Commercial Cabinets LLC",
    "wof:placetype":"venue"
},
  "geometry": {"coordinates":[-81.89100000000001,41.473078],"type":"Point"}
}