{
  "type": "Feature",
  "properties": {
    "addr:full": "803 Sharon Dr Cleveland OH 44145",
    "addr:housenumber": "803",
    "addr:postcode": "44145",
    "addr:street": "Sharon Dr",
    "iso:country": "US",
    "sg:address": "803 Sharon Dr",
    "sg:city": "Cleveland",
    "sg:classifiers": [
      {
        "category": "Home \u0026 Garden",
        "subcategory": "Furniture",
        "type": "Retail Goods"
      }
    ],
    "sg:phone": "+1 440 614 0150",
    "sg:postcode": "44145",
    "sg:province": "OH",
    "sg:tags": [
      "cabinet"
    ],
    "wof:name": "All Commercial Cabinets LLC",
    "wof:placetype": "venue"
  },
  "geometry": {"coordinates":[-81.891,41.473078],"type":"Point"}
}
