{
  "type": "Feature",
  "properties": {
    "iso:country":"US",
    "sg:address":"22621 Lorain Rd",
    "sg:city":"Cleveland",
    "sg:classifiers":[
        {
            "category":"Shopping",
            "subcategory":"Used Merchandise",
            "type":"Retail Goods"
        }
    ],
    "sg:phone":"+1 440 777 2750",
    "sg:postcode":"44126",
    "sg:province":"OH",
    "sg:tags":[
        "shop",
        "consignment"
    ],
    "wof:name":"Consignment Depot",
    "wof:placetype":"venue"
},
  "geometry": {"coordinates":[-81.871317,41.438805],"type":"Point"}
}