{
  "type": "Feature",
  "properties": {
    "addr:full": "106 N Church St Oak Harbor OH 43449",
    "addr:housenumber": "106",
    "addr:postcode": "43449",
    "addr:street": "N Church St",
    "iso:country": "US",
    "sg:address": "106 N Church St",
    "sg:city": "Oak Harbor",
    "sg:classifiers": [
      {
        "category": "Manufacturing",
        "subcategory": "Electronics",
        "type": "Manufacturing \u0026 Wholesale Goods"
      }
    ],
    "sg:phone": "+1 419 898 4357",
    "sg:postcode": "43449",
    "sg:province": "OH",
    "sg:tags": [
      "phonograph",
      "tape"
    ],
    "sg:website": "www.1800anxiety.org",
    "wof:name": "Midwest Center For Stress",
    "wof:placetype": "venue"
  },
  "geometry": {"coordinates":[-83.147446,41.508778],"type":"Point"}
}
