{
  "type": "Feature",
  "properties": {
    "iso:country":"US",
    "sg:address":"106 N Church St",
    "sg:city":"Oak Harbor",
    "sg:classifiers":[
        {
            "category":"Manufacturing",
            "subcategory":"Electronics",
            "type":"Manufacturing & Wholesale Goods"
        }
    ],
    "sg:phone":"+1 419 898 4357",
    "sg:postcode":"43449",
    "sg:province":"OH",
    "sg:tags":[
        "phonograph",
        "tape"
    ],
    "sg:website":"www.1800anxiety.org",
    "wof:name":"Midwest Center For Stress",
    "wof:placetype":"venue"
},
  "geometry": {"coordinates":[-83.147446,41.508778],"type":"Point"}
}