{
  "type": "Feature",
  "properties": {
    "addr:full": "202 Pine Knoll Ter Saint Clairsville OH 43950",
    "addr:housenumber": "202",
    "addr:postcode": "43950",
    "addr:street": "Pine Knoll Ter",
    "iso:country": "US",
    "sg:address": "202 Pine Knoll Ter",
    "sg:city": "Saint Clairsville",
    "sg:classifiers": [
      {
        "category": "Real Estate",
        "subcategory": "Developer",
        "type": "Services"
      }
    ],
    "sg:phone": "+1 740 695 1575",
    "sg:postcode": "43950",
    "sg:province": "OH",
    "wof:name": "EDC Realty Inc",
    "wof:placetype": "venue"
  },
  "geometry": {"coordinates":[-80.89452,40.071209],"type":"Point"}
}
