{
  "type": "Feature",
  "properties": {
    "addr:full": "10050 State Rte 772 Piketon OH 45661",
    "addr:housenumber": "10050",
    "addr:postcode": "45661",
    "addr:street": "State Rte 772",
    "iso:country": "US",
    "sg:address": "10050 State Rte 772",
    "sg:city": "Piketon",
    "sg:classifiers": [
      {
        "category": "Building \u0026 Trades",
        "subcategory": "Construction",
        "type": "Services"
      }
    ],
    "sg:phone": "+1 740 493 3075",
    "sg:postcode": "45661",
    "sg:province": "OH",
    "sg:tags": [
      "excavation",
      "contractor"
    ],
    "wof:name": "Roger A Carson",
    "wof:placetype": "venue"
  },
  "geometry": {"coordinates":[-83.141657,39.035196],"type":"Point"}
}
