{
  "type": "Feature",
  "properties": {
    "addr:full": "501 E Main St Greenville OH 45331",
    "addr:housenumber": "501",
    "addr:postcode": "45331",
    "addr:street": "E Main St",
    "iso:country": "US",
    "sg:address": "501 E Main St",
    "sg:city": "Greenville",
    "sg:classifiers": [
      {
        "category": "Retail",
        "subcategory": "Laundry \u0026 Dry Cleaning",
        "type": "Services"
      }
    ],
    "sg:phone": "+1 937 548 1505",
    "sg:postcode": "45331",
    "sg:province": "OH",
    "sg:tags": [
      "cleaners"
    ],
    "wof:name": "Boyd Cleaners",
    "wof:placetype": "venue"
  },
  "geometry": {"coordinates":[-84.627749,40.106149],"type":"Point"}
}
