{
  "type": "Feature",
  "properties": {
    "iso:country":"US",
    "sg:address":"501 E Main St",
    "sg:city":"Greenville",
    "sg:classifiers":[
        {
            "category":"Retail",
            "subcategory":"Laundry & Dry Cleaning",
            "type":"Services"
        }
    ],
    "sg:phone":"+1 937 548 1505",
    "sg:postcode":"45331",
    "sg:province":"OH",
    "sg:tags":[
        "cleaners"
    ],
    "wof:name":"Boyd Cleaners",
    "wof:placetype":"venue"
},
  "geometry": {"coordinates":[-84.62774899999999,40.106149],"type":"Point"}
}