{
  "type": "Feature",
  "properties": {
    "iso:country":"US",
    "sg:address":"4016 Wichita Ave",
    "sg:city":"Cleveland",
    "sg:classifiers":[
        {
            "category":"Shopping",
            "subcategory":"Catalog Store",
            "type":"Retail Goods"
        }
    ],
    "sg:phone":"+1 216 351 7813",
    "sg:postcode":"44109",
    "sg:province":"OH",
    "sg:tags":[
        "mail",
        "house"
    ],
    "wof:name":"Craft Tastic",
    "wof:placetype":"venue"
},
  "geometry": {"coordinates":[-81.71349,41.433039],"type":"Point"}
}