{
  "type": "Feature",
  "properties": {
    "addr:full": "723 E Main St Lebanon OH 45036",
    "addr:housenumber": "723",
    "addr:postcode": "45036",
    "addr:street": "E Main St",
    "iso:country": "US",
    "sg:address": "723 E Main St",
    "sg:city": "Lebanon",
    "sg:classifiers": [
      {
        "category": "Restaurant",
        "type": "Food \u0026 Drink"
      }
    ],
    "sg:menulink": "http://www.allmenus.com/oh/lebanon/170302-burger-king/menu/",
    "sg:phone": "+1 513 932 6153",
    "sg:postcode": "45036",
    "sg:province": "OH",
    "sg:tags": [
      "burger",
      "american"
    ],
    "wof:name": "Burger King",
    "wof:placetype": "venue"
  },
  "geometry": {"coordinates":[-84.193445,39.432321],"type":"Point"}
}
