{
  "type": "Feature",
  "properties": {
    "addr:full":"4345 Good Rd Seville OH 44273",
    "addr:housenumber":"4345",
    "addr:postcode":"44273",
    "addr:street":"Good Rd",
    "iso:country":"US",
    "sg:address":"4345 Good Rd",
    "sg:city":"Seville",
    "sg:classifiers":[
        {
            "category":"Building & Trades",
            "subcategory":"Construction",
            "type":"Services"
        }
    ],
    "sg:phone":"+1 330 336 4346",
    "sg:postcode":"44273",
    "sg:province":"OH",
    "sg:tags":[
        "landscaping"
    ],
    "wof:name":"J T S Landscaping Inc",
    "wof:placetype":"venue"
},
  "geometry": {"coordinates":[-81.844792,41.062503],"type":"Point"}
}