{
  "type": "Feature",
  "properties": {
    "addr:full": "14314 US Hwy 23 Waverly OH 45690",
    "addr:housenumber": "14314",
    "addr:postcode": "45690",
    "addr:street": "Us Hwy 23",
    "iso:country": "US",
    "sg:address": "14314 US Hwy 23",
    "sg:city": "Waverly",
    "sg:phone": "+1 740 947 8410",
    "sg:postcode": "45690",
    "sg:province": "OH",
    "sg:tags": [
      "product",
      "petroleum"
    ],
    "wof:name": "Busters Bilo",
    "wof:placetype": "venue"
  },
  "geometry": {"coordinates":[-82.97692,39.151829],"type":"Point"}
}
