{
  "type": "Feature",
  "properties": {
    "iso:country":"US",
    "sg:address":"1115 Kendall Ave",
    "sg:city":"Portsmouth",
    "sg:classifiers":[
        {
            "category":"Professional",
            "type":"Services"
        }
    ],
    "sg:phone":"+1 740 353 0616",
    "sg:postcode":"45662",
    "sg:province":"OH",
    "sg:tags":[
        "establishment"
    ],
    "wof:name":"Cavett LP Co",
    "wof:placetype":"venue"
},
  "geometry": {"coordinates":[-82.968706,38.738722],"type":"Point"}
}