{
  "type": "Feature",
  "properties": {
    "iso:country":"US",
    "sg:address":"19832 W 130th St",
    "sg:city":"Cleveland",
    "sg:classifiers":[
        {
            "category":"Sports & Exercise",
            "subcategory":"Gym",
            "type":"Entertainment"
        }
    ],
    "sg:phone":"+1 440 572 3835",
    "sg:postcode":"44136",
    "sg:province":"OH",
    "sg:tags":[
        "club",
        "health",
        "studio",
        "gymnasium"
    ],
    "wof:name":"Fuel Fitness",
    "wof:placetype":"venue"
},
  "geometry": {"coordinates":[-81.78518200000001,41.276926],"type":"Point"}
}