{
  "type": "Feature",
  "properties": {
    "addr:full": "1521 Mark Rd Washington Court House OH 43160",
    "addr:housenumber": "1521",
    "addr:postcode": "43160",
    "addr:street": "Mark Rd",
    "iso:country": "US",
    "sg:address": "1521 Mark Rd",
    "sg:city": "Washington Court House",
    "sg:classifiers": [
      {
        "category": "Banks \u0026 Credit Unions",
        "subcategory": "Bank",
        "type": "Services"
      }
    ],
    "sg:phone": "+1 740 335 5550",
    "sg:postcode": "43160",
    "sg:province": "OH",
    "sg:tags": [
      "personal",
      "institution"
    ],
    "wof:name": "First Community Financial Svc",
    "wof:placetype": "venue"
  },
  "geometry": {"coordinates":[-83.459153,39.484338],"type":"Point"}
}
