{
  "type": "Feature",
  "properties": {
    "iso:country":"US",
    "sg:address":"1521 Mark Rd",
    "sg:city":"Washington Court House",
    "sg:classifiers":[
        {
            "category":"Banks & Credit Unions",
            "subcategory":"Bank",
            "type":"Services"
        }
    ],
    "sg:phone":"+1 740 335 5550",
    "sg:postcode":"43160",
    "sg:province":"OH",
    "sg:tags":[
        "personal",
        "institution"
    ],
    "wof:name":"First Community Financial Svc",
    "wof:placetype":"venue"
},
  "geometry": {"coordinates":[-83.459153,39.484338],"type":"Point"}
}