{
  "type": "Feature",
  "properties": {
    "iso:country":"US",
    "sg:address":"137 North St NW",
    "sg:city":"Warren",
    "sg:classifiers":[
        {
            "category":"Professional",
            "subcategory":"Business Services",
            "type":"Services"
        }
    ],
    "sg:phone":"+1 330 394 6242",
    "sg:postcode":"44483",
    "sg:province":"OH",
    "sg:tags":[
        "drafting"
    ],
    "wof:name":"Konwal Co",
    "wof:placetype":"venue"
},
  "geometry": {"coordinates":[-80.81956599999999,41.247924],"type":"Point"}
}