{
  "type": "Feature",
  "properties": {
    "iso:country":"US",
    "sg:address":"10454 Christian Rd",
    "sg:city":"Versailles",
    "sg:classifiers":[
        {
            "category":"Farming",
            "subcategory":"Farm",
            "type":"Manufacturing & Wholesale Goods"
        }
    ],
    "sg:phone":"+1 937 526 4428",
    "sg:postcode":"45380",
    "sg:province":"OH",
    "wof:name":"Weaver Brothers Farm",
    "wof:placetype":"venue"
},
  "geometry": {"coordinates":[-84.44967,40.220647],"type":"Point"}
}