{
  "type": "Feature",
  "properties": {
    "addr:full": "34 E 7th St Cincinnati OH 45202",
    "addr:housenumber": "34",
    "addr:postcode": "45202",
    "addr:street": "E 7Th St",
    "iso:country": "US",
    "sg:address": "34 E 7th St",
    "sg:city": "Cincinnati",
    "sg:classifiers": [
      {
        "category": "Restaurant",
        "type": "Food \u0026 Drink"
      }
    ],
    "sg:menulink": "http://www.allmenus.com/oh/cincinnati/134467-subway/menu/",
    "sg:phone": "+1 513 421 1113",
    "sg:postcode": "45202",
    "sg:province": "OH",
    "sg:tags": [
      "american",
      "sandwich"
    ],
    "wof:name": "Subway",
    "wof:placetype": "venue"
  },
  "geometry": {"coordinates":[-84.512636,39.103946],"type":"Point"}
}
