{
  "type": "Feature",
  "properties": {
    "addr:full": "1122 N Court St Medina OH 44256",
    "addr:housenumber": "1122",
    "addr:postcode": "44256",
    "addr:street": "N Court St",
    "iso:country": "US",
    "sg:address": "1122 N Court St",
    "sg:city": "Medina",
    "sg:classifiers": [
      {
        "category": "Personal",
        "subcategory": "Beauty Salon",
        "type": "Services"
      }
    ],
    "sg:phone": "+1 330 723 3579",
    "sg:postcode": "44256",
    "sg:province": "OH",
    "sg:tags": [
      "manicuring"
    ],
    "wof:name": "Lovely Nails",
    "wof:placetype": "venue"
  },
  "geometry": {"coordinates":[-81.862777,41.153469],"type":"Point"}
}
