{
  "type": "Feature",
  "properties": {
    "addr:full":"2008 Scottwood Ave Toledo OH 43620",
    "addr:housenumber":"2008",
    "addr:postcode":"43620",
    "addr:street":"Scottwood Ave",
    "iso:country":"US",
    "sg:address":"2008 Scottwood Ave",
    "sg:city":"Toledo",
    "sg:classifiers":[
        {
            "category":"Building & Trades",
            "subcategory":"Plumbing",
            "type":"Services"
        }
    ],
    "sg:phone":"+1 419 243 3500",
    "sg:postcode":"43620",
    "sg:province":"OH",
    "sg:tags":[
        "contractor"
    ],
    "wof:name":"Perkins Sales",
    "wof:placetype":"venue"
},
  "geometry": {"coordinates":[-83.558995,41.661918],"type":"Point"}
}