{
  "type": "Feature",
  "properties": {
    "addr:full": "8101 N High St Columbus OH 43235",
    "addr:housenumber": "8101",
    "addr:postcode": "43235",
    "addr:street": "N High St",
    "iso:country": "US",
    "sg:address": "8101 N High St",
    "sg:city": "Columbus",
    "sg:classifiers": [
      {
        "category": "Retail",
        "subcategory": "Laundry \u0026 Dry Cleaning",
        "type": "Services"
      }
    ],
    "sg:phone": "+1 888 272 9374",
    "sg:postcode": "43235",
    "sg:province": "OH",
    "sg:tags": [
      "upholstery",
      "carpet"
    ],
    "wof:name": "Sears",
    "wof:placetype": "venue"
  },
  "geometry": {"coordinates":[-83.016306,40.126895],"type":"Point"}
}
