{
  "type": "Feature",
  "properties": {
    "addr:full": "8874 Colerain Ave Cincinnati OH 45251",
    "addr:housenumber": "8874",
    "addr:postcode": "45251",
    "addr:street": "Colerain Ave",
    "iso:country": "US",
    "sg:address": "8874 Colerain Ave",
    "sg:city": "Cincinnati",
    "sg:classifiers": [
      {
        "category": "Professional",
        "subcategory": "Management \u0026 Consulting",
        "type": "Services"
      }
    ],
    "sg:phone": "+1 513 245 9888",
    "sg:postcode": "45251",
    "sg:province": "OH",
    "sg:tags": [
      "fuel"
    ],
    "wof:name": "R \u0026 R Management",
    "wof:placetype": "venue"
  },
  "geometry": {"coordinates":[-84.592284,39.236793],"type":"Point"}
}
