{
  "type": "Feature",
  "properties": {
    "iso:country":"US",
    "sg:address":"8874 Colerain Ave",
    "sg:city":"Cincinnati",
    "sg:classifiers":[
        {
            "category":"Professional",
            "subcategory":"Management & Consulting",
            "type":"Services"
        }
    ],
    "sg:phone":"+1 513 245 9888",
    "sg:postcode":"45251",
    "sg:province":"OH",
    "sg:tags":[
        "fuel"
    ],
    "wof:name":"R & R Management",
    "wof:placetype":"venue"
},
  "geometry": {"coordinates":[-84.592284,39.236793],"type":"Point"}
}