{
  "type": "Feature",
  "properties": {
    "addr:full":"430 E Linden Ave Miamisburg OH 45342",
    "addr:housenumber":"430",
    "addr:postcode":"45342",
    "addr:street":"E Linden Ave",
    "iso:country":"US",
    "sg:address":"430 E Linden Ave",
    "sg:city":"Miamisburg",
    "sg:classifiers":[
        {
            "category":"Shopping",
            "subcategory":"Gifts & Souvenirs",
            "type":"Retail Goods"
        }
    ],
    "sg:phone":"+1 937 847 2885",
    "sg:postcode":"45342",
    "sg:province":"OH",
    "wof:name":"Isabellas",
    "wof:placetype":"venue"
},
  "geometry": {"coordinates":[-84.283894,39.639043],"type":"Point"}
}