{
  "type": "Feature",
  "properties": {
    "addr:full": "1356 Cherryway Dr Gahanna OH 43230",
    "addr:housenumber": "1356",
    "addr:postcode": "43230",
    "addr:street": "Cherryway Dr",
    "iso:country": "US",
    "sg:address": "1356 Cherryway Dr",
    "sg:city": "Gahanna",
    "sg:classifiers": [
      {
        "category": "Personal",
        "subcategory": "Beauty Salon",
        "type": "Services"
      }
    ],
    "sg:phone": "+1 614 418 5350",
    "sg:postcode": "43230",
    "sg:province": "OH",
    "sg:tags": [
      "manicuring"
    ],
    "wof:name": "Charles Penzone Grand Salons",
    "wof:placetype": "venue"
  },
  "geometry": {"coordinates":[-82.887593,40.056109],"type":"Point"}
}
