{
  "type": "Feature",
  "properties": {
    "addr:full":"6538 Sales Rd Waynesville OH 45068",
    "addr:housenumber":"6538",
    "addr:postcode":"45068",
    "addr:street":"Sales Rd",
    "iso:country":"US",
    "sg:address":"6538 Sales Rd",
    "sg:city":"Waynesville",
    "sg:classifiers":[
        {
            "category":"Building & Trades",
            "subcategory":"Cleaning & Sanitation",
            "type":"Services"
        }
    ],
    "sg:phone":"+1 513 897 0777",
    "sg:postcode":"45068",
    "sg:province":"OH",
    "sg:tags":[
        "window"
    ],
    "wof:name":"Southtown Pro Window Cleaning",
    "wof:placetype":"venue"
},
  "geometry": {"coordinates":[-84.08063900000001,39.491677],"type":"Point"}
}