{
  "type": "Feature",
  "properties": {
    "iso:country":"US",
    "sg:address":"224 E Broad St",
    "sg:city":"Columbus",
    "sg:classifiers":[
        {
            "category":"Shopping",
            "subcategory":"Books",
            "type":"Retail Goods"
        }
    ],
    "sg:phone":"+1 614 221 6981",
    "sg:postcode":"43215",
    "sg:province":"OH",
    "sg:tags":[
        "bookstore"
    ],
    "wof:name":"Cathedral Bookshop",
    "wof:placetype":"venue"
},
  "geometry": {"coordinates":[-82.995037,39.962915],"type":"Point"}
}