{
  "type": "Feature",
  "properties": {
    "addr:full":"24 Lincoln Way E Massillon OH 44646",
    "addr:housenumber":"24",
    "addr:postcode":"44646",
    "addr:street":"Lincoln Way E",
    "iso:country":"US",
    "sg:address":"24 Lincoln Way E",
    "sg:city":"Massillon",
    "sg:classifiers":[
        {
            "category":"Shopping",
            "subcategory":"Jewelry",
            "type":"Retail Goods"
        }
    ],
    "sg:phone":"+1 330 833 7253",
    "sg:postcode":"44646",
    "sg:province":"OH",
    "wof:name":"C J Duncan Inc",
    "wof:placetype":"venue"
},
  "geometry": {"coordinates":[-81.522932,40.796581],"type":"Point"}
}