{
  "type": "Feature",
  "properties": {
    "addr:full": "98 E Mapledale Ave Akron OH 44301",
    "addr:housenumber": "98",
    "addr:postcode": "44301",
    "addr:street": "E Mapledale Ave",
    "iso:country": "US",
    "sg:address": "98 E Mapledale Ave",
    "sg:city": "Akron",
    "sg:classifiers": [
      {
        "category": "Education",
        "subcategory": "Dance Studio",
        "type": "Public Place"
      }
    ],
    "sg:phone": "+1 330 753 0483",
    "sg:postcode": "44301",
    "sg:province": "OH",
    "sg:tags": [
      "instruction",
      "dancing"
    ],
    "wof:name": "Henderson's Performing Arts",
    "wof:placetype": "venue"
  },
  "geometry": {"coordinates":[-81.524008,41.04571],"type":"Point"}
}
