{
  "type": "Feature",
  "properties": {
    "iso:country":"US",
    "sg:address":"23645 Lorain Ave",
    "sg:city":"North Olmsted",
    "sg:classifiers":[
        {
            "category":"Shopping",
            "type":"Retail Goods"
        }
    ],
    "sg:phone":"+1 440 734 3535",
    "sg:postcode":"44070",
    "sg:province":"OH",
    "sg:tags":[
        "cosmetic",
        "perfume"
    ],
    "wof:name":"Barnum Beauty Systems",
    "wof:placetype":"venue"
},
  "geometry": {"coordinates":[-81.878307,41.441766],"type":"Point"}
}