{
  "type": "Feature",
  "properties": {
    "addr:full": "9840 Harrison Ave Harrison OH 45030",
    "addr:housenumber": "9840",
    "addr:postcode": "45030",
    "addr:street": "Harrison Ave",
    "iso:country": "US",
    "sg:address": "9840 Harrison Ave",
    "sg:city": "Harrison",
    "sg:classifiers": [
      {
        "category": "Freight",
        "type": "Transportation"
      }
    ],
    "sg:phone": "+1 513 367 9579",
    "sg:postcode": "45030",
    "sg:province": "OH",
    "sg:tags": [
      "operator",
      "local",
      "trucking"
    ],
    "wof:name": "Earth Transport",
    "wof:placetype": "venue"
  },
  "geometry": {"coordinates":[-84.767565,39.236299],"type":"Point"}
}
