{
  "type": "Feature",
  "properties": {
    "addr:full":"3025 Noe Bixby Rd Columbus OH 43232",
    "addr:housenumber":"3025",
    "addr:postcode":"43232",
    "addr:street":"Noe Bixby Rd",
    "iso:country":"US",
    "sg:address":"3025 Noe Bixby Rd",
    "sg:city":"Columbus",
    "sg:classifiers":[
        {
            "category":"Home & Garden",
            "subcategory":"Building Materials",
            "type":"Retail Goods"
        },
        {
            "category":"Building & Trades",
            "subcategory":"Construction",
            "type":"Services"
        }
    ],
    "sg:phone":"+1 614 833 1416",
    "sg:postcode":"43232",
    "sg:province":"OH",
    "sg:tags":[
        "garage",
        "door",
        "installation"
    ],
    "sg:website":"www.mckeedoor.com",
    "wof:name":"Mc Kee Door Sales",
    "wof:placetype":"venue"
},
  "geometry": {"coordinates":[-82.86339,39.914889],"type":"Point"}
}