{
  "type": "Feature",
  "properties": {
    "addr:full":"2326 Edmund Ave Akron OH 44312",
    "addr:housenumber":"2326",
    "addr:postcode":"44312",
    "addr:street":"Edmund Ave",
    "iso:country":"US",
    "sg:address":"2326 Edmund Ave",
    "sg:city":"Akron",
    "sg:classifiers":[
        {
            "category":"Banks & Credit Unions",
            "subcategory":"Financial Services",
            "type":"Services"
        }
    ],
    "sg:phone":"+1 330 723 2225",
    "sg:postcode":"44312",
    "sg:province":"OH",
    "sg:tags":[
        "company",
        "holding"
    ],
    "wof:name":"Mlr Holdings Ltd",
    "wof:placetype":"venue"
},
  "geometry": {"coordinates":[-81.44683999999999,41.048967],"type":"Point"}
}