{
  "type": "Feature",
  "properties": {
    "iso:country":"US",
    "sg:address":"6662 Cleveland Rd",
    "sg:city":"Ravenna",
    "sg:classifiers":[
        {
            "category":"Education",
            "subcategory":"School",
            "type":"Public Place"
        }
    ],
    "sg:phone":"+1 330 673 6704",
    "sg:postcode":"44266",
    "sg:province":"OH",
    "wof:name":"Franklin Elementary School",
    "wof:placetype":"venue"
},
  "geometry": {"coordinates":[-81.261195,41.172055],"type":"Point"}
}