{
  "type": "Feature",
  "properties": {
    "addr:full": "501 W Sophia St Maumee OH 43537",
    "addr:housenumber": "501",
    "addr:postcode": "43537",
    "addr:street": "W Sophia St",
    "iso:country": "US",
    "sg:address": "501 W Sophia St",
    "sg:city": "Maumee",
    "sg:classifiers": [
      {
        "category": "Retail",
        "subcategory": "Animal Services",
        "type": "Services"
      }
    ],
    "sg:phone": "+1 419 893 4110",
    "sg:postcode": "43537",
    "sg:province": "OH",
    "wof:name": "Pups n People",
    "wof:placetype": "venue"
  },
  "geometry": {"coordinates":[-83.664209,41.563207],"type":"Point"}
}
