{
  "type": "Feature",
  "properties": {
    "addr:full": "3800 Tanager Dr Columbus OH 43230",
    "addr:housenumber": "3800",
    "addr:postcode": "43230",
    "addr:street": "Tanager Dr",
    "iso:country": "US",
    "sg:address": "3800 Tanager Dr",
    "sg:city": "Columbus",
    "sg:classifiers": [
      {
        "category": "Wholesale",
        "subcategory": "Non-durable Goods",
        "type": "Manufacturing \u0026 Wholesale Goods"
      }
    ],
    "sg:phone": "+1 614 471 2007",
    "sg:postcode": "43230",
    "sg:province": "OH",
    "wof:name": "Vkn Tradings",
    "wof:placetype": "venue"
  },
  "geometry": {"coordinates":[-82.918663,40.069546],"type":"Point"}
}
