{
  "type": "Feature",
  "properties": {
    "addr:full":"69 Sychar Rd Mount Vernon OH 43050",
    "addr:housenumber":"69",
    "addr:postcode":"43050",
    "addr:street":"Sychar Rd",
    "iso:country":"US",
    "sg:address":"69 Sychar Rd",
    "sg:city":"Mount Vernon",
    "sg:classifiers":[
        {
            "category":"Health Services",
            "subcategory":"Clinic",
            "type":"Services"
        }
    ],
    "sg:phone":"+1 740 397 0145",
    "sg:postcode":"43050",
    "sg:province":"OH",
    "sg:tags":[
        "specialty",
        "outpatient"
    ],
    "wof:name":"Family Planning",
    "wof:placetype":"venue"
},
  "geometry": {"coordinates":[-82.47040200000001,40.402876],"type":"Point"}
}