{
  "type": "Feature",
  "properties": {
    "addr:full": "1634 State Rte 48 Lebanon OH 45036",
    "addr:housenumber": "1634",
    "addr:postcode": "45036",
    "addr:street": "State Rte 48",
    "iso:country": "US",
    "sg:address": "1634 State Rte 48",
    "sg:city": "Lebanon",
    "sg:classifiers": [
      {
        "category": "Building \u0026 Trades",
        "subcategory": "Construction",
        "type": "Services"
      }
    ],
    "sg:phone": "+1 513 932 1222",
    "sg:postcode": "45036",
    "sg:province": "OH",
    "sg:tags": [
      "demolition",
      "contractor"
    ],
    "wof:name": "A-1 Demolition \u0026 Wrecking",
    "wof:placetype": "venue"
  },
  "geometry": {"coordinates":[-84.203571,39.458909],"type":"Point"}
}
