{
  "type": "Feature",
  "properties": {
    "addr:full": "4143 Weaver Ct Hilliard OH 43026",
    "addr:housenumber": "4143",
    "addr:postcode": "43026",
    "addr:street": "Weaver Ct",
    "iso:country": "US",
    "sg:address": "4143 Weaver Ct",
    "sg:city": "Hilliard",
    "sg:classifiers": [
      {
        "category": "Manufacturing",
        "subcategory": "Metals",
        "type": "Manufacturing \u0026 Wholesale Goods"
      }
    ],
    "sg:phone": "+1 614 529 6440",
    "sg:postcode": "43026",
    "sg:province": "OH",
    "sg:tags": [
      "pipe",
      "sewer"
    ],
    "wof:name": "American Water Svc Inc",
    "wof:placetype": "venue"
  },
  "geometry": {"coordinates":[-83.145101,40.036966],"type":"Point"}
}
