{
  "type": "Feature",
  "properties": {
    "addr:full": "171 3rd St Zoar OH 44697",
    "addr:housenumber": "171",
    "addr:postcode": "44697",
    "addr:street": "3Rd St",
    "iso:country": "US",
    "sg:address": "171 3rd St",
    "sg:city": "Zoar",
    "sg:classifiers": [
      {
        "category": "Professional",
        "subcategory": "Engineering",
        "type": "Services"
      }
    ],
    "sg:phone": "+1 330 874 4117",
    "sg:postcode": "44697",
    "sg:province": "OH",
    "sg:tags": [
      "engineer"
    ],
    "sg:website": "www.structuraltechnology.com",
    "wof:name": "Structural Technology Corp",
    "wof:placetype": "venue"
  },
  "geometry": {"coordinates":[-81.421079,40.61344],"type":"Point"}
}
