{
  "type": "Feature",
  "properties": {
    "iso:country":"US",
    "sg:address":"171 3rd St",
    "sg:city":"Zoar",
    "sg:classifiers":[
        {
            "category":"Professional",
            "subcategory":"Engineering",
            "type":"Services"
        }
    ],
    "sg:phone":"+1 330 874 4117",
    "sg:postcode":"44697",
    "sg:province":"OH",
    "sg:tags":[
        "engineer"
    ],
    "sg:website":"www.structuraltechnology.com",
    "wof:name":"Structural Technology Corp",
    "wof:placetype":"venue"
},
  "geometry": {"coordinates":[-81.42107900000001,40.61344],"type":"Point"}
}