{
  "type": "Feature",
  "properties": {
    "addr:full": "1153 Steubenville Ave Cambridge OH 43725",
    "addr:housenumber": "1153",
    "addr:postcode": "43725",
    "addr:street": "Steubenville Ave",
    "iso:country": "US",
    "sg:address": "1153 Steubenville Ave",
    "sg:city": "Cambridge",
    "sg:classifiers": [
      {
        "category": "Organizations",
        "subcategory": "Religious Organization",
        "type": "Services"
      }
    ],
    "sg:phone": "+1 740 435 0150",
    "sg:postcode": "43725",
    "sg:province": "OH",
    "wof:name": "LDS Missionaries",
    "wof:placetype": "venue"
  },
  "geometry": {"coordinates":[-81.58314,40.02602],"type":"Point"}
}
