{
  "type": "Feature",
  "properties": {
    "addr:full":"5318 Argonne Dr Youngstown OH 44515",
    "addr:housenumber":"5318",
    "addr:postcode":"44515",
    "addr:street":"Argonne Dr",
    "iso:country":"US",
    "sg:address":"5318 Argonne Dr",
    "sg:city":"Youngstown",
    "sg:classifiers":[
        {
            "category":"Retail",
            "subcategory":"Repair Shop",
            "type":"Services"
        }
    ],
    "sg:phone":"+1 330 793 8573",
    "sg:postcode":"44515",
    "sg:province":"OH",
    "sg:tags":[
        "repairing",
        "piano",
        "refinishing"
    ],
    "wof:name":"Piano Tuning",
    "wof:placetype":"venue"
},
  "geometry": {"coordinates":[-80.753274,41.103322],"type":"Point"}
}