{
  "type": "Feature",
  "properties": {
    "iso:country":"US",
    "sg:address":"1729 W High St",
    "sg:city":"Orrville",
    "sg:classifiers":[
        {
            "category":"Real Estate",
            "subcategory":"Developer",
            "type":"Services"
        }
    ],
    "sg:phone":"+1 330 684 5075",
    "sg:postcode":"44667",
    "sg:province":"OH",
    "sg:tags":[
        "executive",
        "cemetery"
    ],
    "wof:name":"Crown Hill Cemetery",
    "wof:placetype":"venue"
},
  "geometry": {"coordinates":[-81.78710599999999,40.844373],"type":"Point"}
}