{
  "type": "Feature",
  "properties": {
    "addr:full": "4029 E Broad St Columbus OH 43213",
    "addr:housenumber": "4029",
    "addr:postcode": "43213",
    "addr:street": "E Broad St",
    "iso:country": "US",
    "sg:address": "4029 E Broad St",
    "sg:city": "Columbus",
    "sg:classifiers": [
      {
        "category": "Professional",
        "subcategory": "Accounting \u0026 Tax Preparation",
        "type": "Services"
      }
    ],
    "sg:phone": "+1 614 237 2523",
    "sg:postcode": "43213",
    "sg:province": "OH",
    "sg:tags": [
      "accountant",
      "public",
      "certified"
    ],
    "wof:name": "Mellman Perdue \u0026 Sahr",
    "wof:placetype": "venue"
  },
  "geometry": {"coordinates":[-82.892039,39.974267],"type":"Point"}
}
