{
  "type": "Feature",
  "properties": {
    "iso:country":"US",
    "sg:address":"665 W Westbrook Rd",
    "sg:city":"Brookville",
    "sg:classifiers":[
        {
            "category":"Organizations",
            "subcategory":"Religious Organization",
            "type":"Services"
        }
    ],
    "sg:phone":"+1 937 833 5562",
    "sg:postcode":"45309",
    "sg:province":"OH",
    "sg:website":"www.brookvillegrace.org",
    "wof:name":"Brookville Grace Brethren",
    "wof:placetype":"venue"
},
  "geometry": {"coordinates":[-84.420378,39.83136],"type":"Point"}
}