{
  "type": "Feature",
  "properties": {
    "addr:full": "4317 Center St Willoughby OH 44094",
    "addr:housenumber": "4317",
    "addr:postcode": "44094",
    "addr:street": "Center St",
    "iso:country": "US",
    "sg:address": "4317 Center St",
    "sg:city": "Willoughby",
    "sg:classifiers": [
      {
        "category": "Shopping",
        "type": "Retail Goods"
      }
    ],
    "sg:phone": "+1 440 951 4452",
    "sg:postcode": "44094",
    "sg:province": "OH",
    "sg:tags": [
      "flagpole",
      "flag"
    ],
    "wof:name": "All Things Patriotic",
    "wof:placetype": "venue"
  },
  "geometry": {"coordinates":[-81.406796,41.636942],"type":"Point"}
}
