{
  "type": "Feature",
  "properties": {
    "iso:country":"US",
    "sg:address":"35608 Lake Shore Blvd",
    "sg:city":"Willoughby",
    "sg:classifiers":[
        {
            "category":"Restaurant",
            "type":"Food & Drink"
        }
    ],
    "sg:phone":"+1 440 942 3470",
    "sg:postcode":"44095",
    "sg:province":"OH",
    "sg:tags":[
        "beverage"
    ],
    "wof:name":"Erieshore Beverage & Bait",
    "wof:placetype":"venue"
},
  "geometry": {"coordinates":[-81.429693,41.66453],"type":"Point"}
}