{
  "type": "Feature",
  "properties": {
    "iso:country":"US",
    "sg:address":"2759 Maysville Pike",
    "sg:city":"Zanesville",
    "sg:classifiers":[
        {
            "category":"Food & Beverages",
            "subcategory":"Groceries & Convenience Stores",
            "type":"Retail Goods"
        }
    ],
    "sg:phone":"+1 740 454 7342",
    "sg:postcode":"43701",
    "sg:province":"OH",
    "wof:name":"Mac N Turf's",
    "wof:placetype":"venue"
},
  "geometry": {"coordinates":[-82.041342,39.895149],"type":"Point"}
}