{
  "type": "Feature",
  "properties": {
    "addr:full": "2759 Maysville Pike Zanesville OH 43701",
    "addr:housenumber": "2759",
    "addr:postcode": "43701",
    "addr:street": "Maysville Pike",
    "iso:country": "US",
    "sg:address": "2759 Maysville Pike",
    "sg:city": "Zanesville",
    "sg:classifiers": [
      {
        "category": "Food \u0026 Beverages",
        "subcategory": "Groceries \u0026 Convenience Stores",
        "type": "Retail Goods"
      }
    ],
    "sg:phone": "+1 740 454 7342",
    "sg:postcode": "43701",
    "sg:province": "OH",
    "wof:name": "Mac N Turf's",
    "wof:placetype": "venue"
  },
  "geometry": {"coordinates":[-82.041342,39.895149],"type":"Point"}
}
