{
  "type": "Feature",
  "properties": {
    "iso:country":"US",
    "sg:address":"15 E Gay St",
    "sg:city":"Columbus",
    "sg:classifiers":[
        {
            "category":"Real Estate",
            "subcategory":"Architect",
            "type":"Services"
        }
    ],
    "sg:phone":"+1 614 221 9433",
    "sg:postcode":"43215",
    "sg:province":"OH",
    "sg:website":"www.meyerswelsh.com",
    "wof:name":"Meyers Welsh Architecture Dsgn",
    "wof:placetype":"venue"
},
  "geometry": {"coordinates":[-83.000508,39.963574],"type":"Point"}
}