{
  "type": "Feature",
  "properties": {
    "addr:full": "11150 Woodward Ln Cincinnati OH 45241",
    "addr:housenumber": "11150",
    "addr:postcode": "45241",
    "addr:street": "Woodward Ln",
    "iso:country": "US",
    "sg:address": "11150 Woodward Ln",
    "sg:city": "Cincinnati",
    "sg:classifiers": [
      {
        "category": "Professional",
        "subcategory": "Computer Services",
        "type": "Services"
      }
    ],
    "sg:phone": "+1 513 771 4220",
    "sg:postcode": "45241",
    "sg:province": "OH",
    "sg:tags": [
      "installation",
      "network",
      "maintenance"
    ],
    "sg:website": "www.iii-333.com",
    "wof:name": "Intelligent Information Inc",
    "wof:placetype": "venue"
  },
  "geometry": {"coordinates":[-84.436054,39.270733],"type":"Point"}
}
