{
  "type": "Feature",
  "properties": {
    "addr:full":"6909 Philip Ln Wooster OH 44691",
    "addr:housenumber":"6909",
    "addr:postcode":"44691",
    "addr:street":"Philip Ln",
    "iso:country":"US",
    "sg:address":"6909 Philip Ln",
    "sg:city":"Wooster",
    "sg:classifiers":[
        {
            "category":"Government",
            "subcategory":"Office",
            "type":"Public Place"
        }
    ],
    "sg:phone":"+1 330 345 9900",
    "sg:postcode":"44691",
    "sg:province":"OH",
    "sg:tags":[
        "international",
        "affairs"
    ],
    "wof:name":"Midwest Marketing and MGT",
    "wof:placetype":"venue"
},
  "geometry": {"coordinates":[-81.91447100000001,40.880423],"type":"Point"}
}