{
  "type": "Feature",
  "properties": {
    "iso:country":"US",
    "sg:address":"6909 Philip Ln",
    "sg:city":"Wooster",
    "sg:classifiers":[
        {
            "category":"Government",
            "subcategory":"Office",
            "type":"Public Place"
        }
    ],
    "sg:phone":"+1 330 345 9900",
    "sg:postcode":"44691",
    "sg:province":"OH",
    "sg:tags":[
        "international",
        "affairs"
    ],
    "wof:name":"Midwest Marketing and MGT",
    "wof:placetype":"venue"
},
  "geometry": {"coordinates":[-81.914471,40.880423],"type":"Point"}
}