{
  "type": "Feature",
  "properties": {
    "addr:full": "3207 Cherry St Toledo OH 43608",
    "addr:housenumber": "3207",
    "addr:postcode": "43608",
    "addr:street": "Cherry St",
    "iso:country": "US",
    "sg:address": "3207 Cherry St",
    "sg:city": "Toledo",
    "sg:classifiers": [
      {
        "category": "Professional",
        "type": "Services"
      }
    ],
    "sg:phone": "+1 419 255 6016",
    "sg:postcode": "43608",
    "sg:province": "OH",
    "wof:name": "Image Quest",
    "wof:placetype": "venue"
  },
  "geometry": {"coordinates":[-83.552373,41.680876],"type":"Point"}
}
