{
  "type": "Feature",
  "properties": {
    "iso:country":"US",
    "sg:address":"13995 State Rte 220",
    "sg:city":"Waverly",
    "sg:classifiers":[
        {
            "category":"Professional",
            "type":"Services"
        }
    ],
    "sg:phone":"+1 740 289 8165",
    "sg:postcode":"45690",
    "sg:province":"OH",
    "wof:name":"Shell Michael",
    "wof:placetype":"venue"
},
  "geometry": {"coordinates":[-82.954489,39.058437],"type":"Point"}
}