{
  "type": "Feature",
  "properties": {
    "addr:full": "1596 W Broad St Columbus OH 43223",
    "addr:housenumber": "1596",
    "addr:postcode": "43223",
    "addr:street": "W Broad St",
    "iso:country": "US",
    "sg:address": "1596 W Broad St",
    "sg:city": "Columbus",
    "sg:classifiers": [
      {
        "category": "Government",
        "subcategory": "Office",
        "type": "Public Place"
      }
    ],
    "sg:phone": "+1 614 279 5054",
    "sg:postcode": "43223",
    "sg:province": "OH",
    "sg:tags": [
      "national",
      "security"
    ],
    "wof:name": "US Army Corps of Engineers",
    "wof:placetype": "venue"
  },
  "geometry": {"coordinates":[-83.042251,39.957176],"type":"Point"}
}
