{
  "type": "Feature",
  "properties": {
    "addr:full": "4255 Harrison Ave Cincinnati OH 45211",
    "addr:housenumber": "4255",
    "addr:postcode": "45211",
    "addr:street": "Harrison Ave",
    "iso:country": "US",
    "sg:address": "4255 Harrison Ave",
    "sg:city": "Cincinnati",
    "sg:classifiers": [
      {
        "category": "Banks \u0026 Credit Unions",
        "subcategory": "Investment Brokerage",
        "type": "Services"
      },
      {
        "category": "Real Estate",
        "subcategory": "Real Estate Operator",
        "type": "Services"
      }
    ],
    "sg:phone": "+1 513 574 7700",
    "sg:postcode": "45211",
    "sg:province": "OH",
    "sg:tags": [
      "building",
      "apartment"
    ],
    "wof:name": "Regis Investment Inc",
    "wof:placetype": "venue"
  },
  "geometry": {"coordinates":[-84.624117,39.162028],"type":"Point"}
}
