{
  "type": "Feature",
  "properties": {
    "addr:full":"100 Executive Dr Marion OH 43302",
    "addr:housenumber":"100",
    "addr:postcode":"43302",
    "addr:street":"Executive Dr",
    "iso:country":"US",
    "sg:address":"100 Executive Dr",
    "sg:city":"Marion",
    "sg:classifiers":[
        {
            "category":"Utilities",
            "subcategory":"Telephone",
            "type":"Services"
        }
    ],
    "sg:phone":"+1 740 383 0411",
    "sg:postcode":"43302",
    "sg:province":"OH",
    "sg:tags":[
        "telecommunication"
    ],
    "sg:website":"www.verizon.com",
    "wof:name":"Verizon",
    "wof:placetype":"venue"
},
  "geometry": {"coordinates":[-83.12293699999999,40.571002],"type":"Point"}
}