{
  "type": "Feature",
  "properties": {
    "addr:full": "2051 Richland Ave Lakewood OH 44107",
    "addr:housenumber": "2051",
    "addr:postcode": "44107",
    "addr:street": "Richland Ave",
    "iso:country": "US",
    "sg:address": "2051 Richland Ave",
    "sg:city": "Lakewood",
    "sg:classifiers": [
      {
        "category": "Building \u0026 Trades",
        "subcategory": "Construction",
        "type": "Services"
      }
    ],
    "sg:phone": "+1 216 407 1766",
    "sg:postcode": "44107",
    "sg:province": "OH",
    "sg:tags": [
      "residential"
    ],
    "wof:name": "Save On Service",
    "wof:placetype": "venue"
  },
  "geometry": {"coordinates":[-81.790777,41.47553],"type":"Point"}
}
