{
  "type": "Feature",
  "properties": {
    "iso:country":"US",
    "sg:address":"2051 Richland Ave",
    "sg:city":"Lakewood",
    "sg:classifiers":[
        {
            "category":"Building & Trades",
            "subcategory":"Construction",
            "type":"Services"
        }
    ],
    "sg:phone":"+1 216 407 1766",
    "sg:postcode":"44107",
    "sg:province":"OH",
    "sg:tags":[
        "residential"
    ],
    "wof:name":"Save On Service",
    "wof:placetype":"venue"
},
  "geometry": {"coordinates":[-81.79077700000001,41.47553],"type":"Point"}
}