{
  "type": "Feature",
  "properties": {
    "addr:full": "2310 E Dorothy Ln Kettering OH 45420",
    "addr:housenumber": "2310",
    "addr:postcode": "45420",
    "addr:street": "E Dorothy Ln",
    "iso:country": "US",
    "sg:address": "2310 E Dorothy Ln",
    "sg:city": "Kettering",
    "sg:classifiers": [
      {
        "category": "Personal",
        "subcategory": "Beauty Salon",
        "type": "Services"
      }
    ],
    "sg:phone": "+1 937 299 6931",
    "sg:postcode": "45420",
    "sg:province": "OH",
    "wof:name": "Top Notch Hair Salon \u0026 Tanning",
    "wof:placetype": "venue"
  },
  "geometry": {"coordinates":[-84.120541,39.701723],"type":"Point"}
}
