{
  "type": "Feature",
  "properties": {
    "addr:full": "1400 W Main St Tipp City OH 45371",
    "addr:housenumber": "1400",
    "addr:postcode": "45371",
    "addr:street": "W Main St",
    "iso:country": "US",
    "sg:address": "1400 W Main St",
    "sg:city": "Tipp City",
    "sg:classifiers": [
      {
        "category": "Shopping",
        "subcategory": "Florist",
        "type": "Retail Goods"
      }
    ],
    "sg:phone": "+1 937 667 2419",
    "sg:postcode": "45371",
    "sg:province": "OH",
    "sg:tags": [
      "ornamental",
      "nursery",
      "sup"
    ],
    "wof:name": "Tipp Florist Shop",
    "wof:placetype": "venue"
  },
  "geometry": {"coordinates":[-84.190053,39.960877],"type":"Point"}
}
