{
  "type": "Feature",
  "properties": {
    "addr:full":"5075 N Bend Rd Cincinnati OH 45211",
    "addr:housenumber":"5075",
    "addr:postcode":"45211",
    "addr:street":"N Bend Rd",
    "iso:country":"US",
    "sg:address":"5075 N Bend Rd",
    "sg:city":"Cincinnati",
    "sg:classifiers":[
        {
            "category":"Freight",
            "type":"Transportation"
        }
    ],
    "sg:phone":"+1 513 661 6342",
    "sg:postcode":"45211",
    "sg:province":"OH",
    "sg:tags":[
        "operator",
        "local",
        "trucking"
    ],
    "wof:name":"Ray Price Trucking",
    "wof:placetype":"venue"
},
  "geometry": {"coordinates":[-84.602464,39.174796],"type":"Point"}
}