{
  "type": "Feature",
  "properties": {
    "addr:full":"126 S Ewing St Lancaster OH 43130",
    "addr:housenumber":"126",
    "addr:postcode":"43130",
    "addr:street":"S Ewing St",
    "iso:country":"US",
    "sg:address":"126 S Ewing St",
    "sg:city":"Lancaster",
    "sg:classifiers":[
        {
            "category":"Building & Trades",
            "subcategory":"Construction",
            "type":"Services"
        }
    ],
    "sg:phone":"+1 740 654 1765",
    "sg:postcode":"43130",
    "sg:province":"OH",
    "sg:tags":[
        "housing"
    ],
    "wof:name":"Shumaker Home Improvement",
    "wof:placetype":"venue"
},
  "geometry": {"coordinates":[-82.576831,39.713593],"type":"Point"}
}