{
  "type": "Feature",
  "properties": {
    "addr:full":"4949 Mahoning Ave Austintown OH 44515",
    "addr:housenumber":"4949",
    "addr:postcode":"44515",
    "addr:street":"Mahoning Ave",
    "iso:country":"US",
    "sg:address":"4949 Mahoning Ave",
    "sg:city":"Austintown",
    "sg:classifiers":[
        {
            "category":"Banks & Credit Unions",
            "subcategory":"Bank",
            "type":"Services"
        }
    ],
    "sg:phone":"+1 330 742 4093",
    "sg:postcode":"44515",
    "sg:province":"OH",
    "sg:tags":[
        "national",
        "commercial"
    ],
    "sg:website":"www.nationalcity.com",
    "wof:name":"National City Bank",
    "wof:placetype":"venue"
},
  "geometry": {"coordinates":[-80.74698600000001,41.100207],"type":"Point"}
}