{
  "type": "Feature",
  "properties": {
    "addr:full":"2345 Cleveland Ave Columbus OH 43211",
    "addr:housenumber":"2345",
    "addr:postcode":"43211",
    "addr:street":"Cleveland Ave",
    "iso:country":"US",
    "sg:address":"2345 Cleveland Ave",
    "sg:city":"Columbus",
    "sg:classifiers":[
        {
            "category":"Health Services",
            "subcategory":"Doctor",
            "type":"Services"
        }
    ],
    "sg:phone":"+1 614 447 0496",
    "sg:postcode":"43211",
    "sg:province":"OH",
    "sg:tags":[
        "dentist"
    ],
    "wof:name":"Dental One",
    "wof:placetype":"venue"
},
  "geometry": {"coordinates":[-82.966448,40.015257],"type":"Point"}
}