{
  "type": "Feature",
  "properties": {
    "addr:full":"3854 Twp Rd 110 Mount Gilead OH 43338",
    "addr:housenumber":"110",
    "addr:postcode":"3854;43338",
    "addr:street":"Twp Rd;Mount",
    "iso:country":"US",
    "sg:address":"3854 Twp Rd 110",
    "sg:city":"Mount Gilead",
    "sg:phone":"+1 419 947 9740",
    "sg:postcode":"43338",
    "sg:province":"OH",
    "sg:tags":[
        "farm",
        "corn",
        "wheat",
        "soybean"
    ],
    "wof:name":"Bruce McKirgan",
    "wof:placetype":"venue"
},
  "geometry": {"coordinates":[-82.822029,40.523463],"type":"Point"}
}