{
  "type": "Feature",
  "properties": {
    "addr:full":"10981 Hamilton Ave Cincinnati OH 45231",
    "addr:housenumber":"10981",
    "addr:postcode":"45231",
    "addr:street":"Hamilton Ave",
    "iso:country":"US",
    "sg:address":"10981 Hamilton Ave",
    "sg:city":"Cincinnati",
    "sg:classifiers":[
        {
            "category":"Food & Beverages",
            "subcategory":"Liquor & Beverages",
            "type":"Retail Goods"
        }
    ],
    "sg:phone":"+1 513 742 0870",
    "sg:postcode":"45231",
    "sg:province":"OH",
    "sg:tags":[
        "beer",
        "ale"
    ],
    "wof:name":"Party Pantry",
    "wof:placetype":"venue"
},
  "geometry": {"coordinates":[-84.56366800000001,39.278101],"type":"Point"}
}