{
  "type": "Feature",
  "properties": {
    "addr:full": "10981 Hamilton Ave Cincinnati OH 45231",
    "addr:housenumber": "10981",
    "addr:postcode": "45231",
    "addr:street": "Hamilton Ave",
    "iso:country": "US",
    "sg:address": "10981 Hamilton Ave",
    "sg:city": "Cincinnati",
    "sg:classifiers": [
      {
        "category": "Food \u0026 Beverages",
        "subcategory": "Liquor \u0026 Beverages",
        "type": "Retail Goods"
      }
    ],
    "sg:phone": "+1 513 742 0870",
    "sg:postcode": "45231",
    "sg:province": "OH",
    "sg:tags": [
      "beer",
      "ale"
    ],
    "wof:name": "Party Pantry",
    "wof:placetype": "venue"
  },
  "geometry": {"coordinates":[-84.563668,39.278101],"type":"Point"}
}
