{
  "type": "Feature",
  "properties": {
    "iso:country":"US",
    "sg:address":"464 Eagle Point Rd",
    "sg:city":"Rossford",
    "sg:classifiers":[
        {
            "category":"Professional",
            "type":"Services"
        }
    ],
    "sg:phone":"+1 419 666 6865",
    "sg:postcode":"43460",
    "sg:province":"OH",
    "wof:name":"Grinonneau & Yoder",
    "wof:placetype":"venue"
},
  "geometry": {"coordinates":[-83.570145,41.606049],"type":"Point"}
}