{
  "type": "Feature",
  "properties": {
    "addr:full": "102 Sarah Blvd Toronto OH 43964",
    "addr:housenumber": "102",
    "addr:postcode": "43964",
    "addr:street": "Sarah Blvd",
    "iso:country": "US",
    "sg:address": "102 Sarah Blvd",
    "sg:city": "Toronto",
    "sg:classifiers": [
      {
        "category": "Home \u0026 Garden",
        "subcategory": "Carpets \u0026 Floor Coverings",
        "type": "Retail Goods"
      }
    ],
    "sg:phone": "+1 740 537 3073",
    "sg:postcode": "43964",
    "sg:province": "OH",
    "wof:name": "Dee Jays Carpet Service",
    "wof:placetype": "venue"
  },
  "geometry": {"coordinates":[-80.625402,40.457731],"type":"Point"}
}
