{
  "type": "Feature",
  "properties": {
    "addr:full": "5599 Liberty Ave Vermilion OH 44089",
    "addr:housenumber": "5599",
    "addr:postcode": "44089",
    "addr:street": "Liberty Ave",
    "iso:country": "US",
    "sg:address": "5599 Liberty Ave",
    "sg:city": "Vermilion",
    "sg:classifiers": [
      {
        "category": "Autos \u0026 Motor Vehicles",
        "subcategory": "Auto Supplies",
        "type": "Retail Goods"
      },
      {
        "category": "Wholesale",
        "subcategory": "Auto Parts",
        "type": "Manufacturing \u0026 Wholesale Goods"
      }
    ],
    "sg:phone": "+1 440 967 6171",
    "sg:postcode": "44089",
    "sg:province": "OH",
    "sg:tags": [
      "automobile"
    ],
    "wof:name": "Fulper's Auto Parts Inc",
    "wof:placetype": "venue"
  },
  "geometry": {"coordinates":[-82.367534,41.42196],"type":"Point"}
}
