{
  "type": "Feature",
  "properties": {
    "addr:full":"5599 Liberty Ave Vermilion OH 44089",
    "addr:housenumber":"5599",
    "addr:postcode":"44089",
    "addr:street":"Liberty Ave",
    "iso:country":"US",
    "sg:address":"5599 Liberty Ave",
    "sg:city":"Vermilion",
    "sg:classifiers":[
        {
            "category":"Autos & Motor Vehicles",
            "subcategory":"Auto Supplies",
            "type":"Retail Goods"
        },
        {
            "category":"Wholesale",
            "subcategory":"Auto Parts",
            "type":"Manufacturing & Wholesale Goods"
        }
    ],
    "sg:phone":"+1 440 967 6171",
    "sg:postcode":"44089",
    "sg:province":"OH",
    "sg:tags":[
        "automobile"
    ],
    "wof:name":"Fulper's Auto Parts Inc",
    "wof:placetype":"venue"
},
  "geometry": {"coordinates":[-82.36753400000001,41.42196],"type":"Point"}
}