{
  "type": "Feature",
  "properties": {
    "iso:country":"US",
    "sg:address":"307 S Patterson St",
    "sg:city":"Forest",
    "sg:classifiers":[
        {
            "category":"Government",
            "subcategory":"Fire Station",
            "type":"Public Place"
        }
    ],
    "sg:phone":"+1 419 273 2417",
    "sg:postcode":"45843",
    "sg:province":"OH",
    "sg:tags":[
        "protection"
    ],
    "wof:name":"Jackson Twp Hardin C",
    "wof:placetype":"venue"
},
  "geometry": {"coordinates":[-83.512079,40.799591],"type":"Point"}
}