{
  "type": "Feature",
  "properties": {
    "addr:full":"241 University Dr NE New Philadelphia OH 44663",
    "addr:housenumber":"241",
    "addr:postcode":"44663",
    "addr:street":"University Dr Ne",
    "iso:country":"US",
    "sg:address":"241 University Dr NE",
    "sg:city":"New Philadelphia",
    "sg:classifiers":[
        {
            "category":"Social Services",
            "subcategory":"Adult Care",
            "type":"Services"
        },
        {
            "category":"Social Services",
            "type":"Services"
        }
    ],
    "sg:phone":"+1 330 339 7775",
    "sg:postcode":"44663",
    "sg:province":"OH",
    "sg:tags":[
        "organization",
        "residential",
        "welfare"
    ],
    "wof:name":"Multi County Juvenile ATT Ctr",
    "wof:placetype":"venue"
},
  "geometry": {"coordinates":[-81.411402,40.468958],"type":"Point"}
}