{
  "type": "Feature",
  "properties": {
    "addr:full": "8818 Oak Valley Rd Holland OH 43528",
    "addr:housenumber": "8818",
    "addr:postcode": "43528",
    "addr:street": "Oak Valley Rd",
    "iso:country": "US",
    "sg:address": "8818 Oak Valley Rd",
    "sg:city": "Holland",
    "sg:classifiers": [
      {
        "category": "Professional",
        "type": "Services"
      }
    ],
    "sg:phone": "+1 419 868 6780",
    "sg:postcode": "43528",
    "sg:province": "OH",
    "wof:name": "Lark Family Ltd Pt An",
    "wof:placetype": "venue"
  },
  "geometry": {"coordinates":[-83.749619,41.631708],"type":"Point"}
}
