{
  "type": "Feature",
  "properties": {
    "iso:country":"US",
    "sg:address":"2696 Coblentz Dr",
    "sg:city":"Youngstown",
    "sg:classifiers":[
        {
            "category":"Building & Trades",
            "subcategory":"Construction",
            "type":"Services"
        }
    ],
    "sg:phone":"+1 330 757 0995",
    "sg:postcode":"44514",
    "sg:province":"OH",
    "sg:tags":[
        "hanging",
        "contractor"
    ],
    "wof:name":"Himes Painting",
    "wof:placetype":"venue"
},
  "geometry": {"coordinates":[-80.602175,41.016802],"type":"Point"}
}