{
  "type": "Feature",
  "properties": {
    "addr:full": "2210 Woodward Ave Cleveland OH 44107",
    "addr:housenumber": "2210",
    "addr:postcode": "44107",
    "addr:street": "Woodward Ave",
    "iso:country": "US",
    "sg:address": "2210 Woodward Ave",
    "sg:city": "Cleveland",
    "sg:classifiers": [
      {
        "category": "Building \u0026 Trades",
        "subcategory": "Construction",
        "type": "Services"
      }
    ],
    "sg:phone": "+1 440 358 9799",
    "sg:postcode": "44107",
    "sg:province": "OH",
    "sg:tags": [
      "wallpaper"
    ],
    "wof:name": "Mary Anne Colopy Paperhanging",
    "wof:placetype": "venue"
  },
  "geometry": {"coordinates":[-81.811814,41.471746],"type":"Point"}
}
