{
  "type": "Feature",
  "properties": {
    "addr:full": "17501 Laverne Ave Cleveland OH 44135",
    "addr:housenumber": "17501",
    "addr:postcode": "44135",
    "addr:street": "Laverne Ave",
    "iso:country": "US",
    "sg:address": "17501 Laverne Ave",
    "sg:city": "Cleveland",
    "sg:classifiers": [
      {
        "category": "Manufacturing",
        "subcategory": "Motor Vehicles \u0026 Parts",
        "type": "Manufacturing \u0026 Wholesale Goods"
      }
    ],
    "sg:phone": "+1 216 251 8101",
    "sg:postcode": "44135",
    "sg:province": "OH",
    "sg:tags": [
      "mfg",
      "trimming"
    ],
    "wof:name": "Tulle Time",
    "wof:placetype": "venue"
  },
  "geometry": {"coordinates":[-81.816138,41.436926],"type":"Point"}
}
