{
  "type": "Feature",
  "properties": {
    "addr:full": "3833 Northridge Rd Alexandria OH 43001",
    "addr:housenumber": "3833",
    "addr:postcode": "43001",
    "addr:street": "Northridge Rd",
    "iso:country": "US",
    "sg:address": "3833 Northridge Rd",
    "sg:city": "Alexandria",
    "sg:classifiers": [
      {
        "category": "Sports \u0026 Exercise",
        "subcategory": "Golf",
        "type": "Entertainment"
      }
    ],
    "sg:phone": "+1 740 924 8885",
    "sg:postcode": "43001",
    "sg:province": "OH",
    "sg:tags": [
      "course"
    ],
    "sg:website": "www.stalbansgc.com",
    "wof:name": "St Albans Golf Club",
    "wof:placetype": "venue"
  },
  "geometry": {"coordinates":[-82.61624,40.11069],"type":"Point"}
}
