{
  "type": "Feature",
  "properties": {
    "iso:country":"US",
    "sg:address":"3833 Northridge Rd",
    "sg:city":"Alexandria",
    "sg:classifiers":[
        {
            "category":"Sports & Exercise",
            "subcategory":"Golf",
            "type":"Entertainment"
        }
    ],
    "sg:phone":"+1 740 924 8885",
    "sg:postcode":"43001",
    "sg:province":"OH",
    "sg:tags":[
        "course"
    ],
    "sg:website":"www.stalbansgc.com",
    "wof:name":"St Albans Golf Club",
    "wof:placetype":"venue"
},
  "geometry": {"coordinates":[-82.61624,40.11069],"type":"Point"}
}