{
  "type": "Feature",
  "properties": {
    "addr:full":"200 W Main St New London OH 44851",
    "addr:housenumber":"200",
    "addr:postcode":"44851",
    "addr:street":"W Main St",
    "iso:country":"US",
    "sg:address":"200 W Main St",
    "sg:city":"New London",
    "sg:classifiers":[
        {
            "category":"Retail",
            "subcategory":"Funeral Services",
            "type":"Services"
        }
    ],
    "sg:phone":"+1 419 929 3781",
    "sg:postcode":"44851",
    "sg:province":"OH",
    "sg:tags":[
        "director"
    ],
    "wof:name":"Eastman Funeral Home",
    "wof:placetype":"venue"
},
  "geometry": {"coordinates":[-82.408969,41.086007],"type":"Point"}
}