{
  "type": "Feature",
  "properties": {
    "addr:full": "7989 Fultonrose Rd Roseville OH 43777",
    "addr:housenumber": "7989",
    "addr:postcode": "43777",
    "addr:street": "Fultonrose Rd",
    "iso:country": "US",
    "sg:address": "7989 Fultonrose Rd",
    "sg:city": "Roseville",
    "sg:classifiers": [
      {
        "category": "Autos \u0026 Motor Vehicles",
        "subcategory": "Automobile Sales",
        "type": "Retail Goods"
      }
    ],
    "sg:phone": "+1 740 697 2610",
    "sg:postcode": "43777",
    "sg:province": "OH",
    "sg:tags": [
      "car",
      "used",
      "dealer"
    ],
    "wof:name": "93 Auto Sales",
    "wof:placetype": "venue"
  },
  "geometry": {"coordinates":[-82.079604,39.819788],"type":"Point"}
}
