{
  "type": "Feature",
  "properties": {
    "addr:full": "11260 Chester Rd Cincinnati OH 45246",
    "addr:housenumber": "11260",
    "addr:postcode": "45246",
    "addr:street": "Chester Rd",
    "iso:country": "US",
    "sg:address": "11260 Chester Rd",
    "sg:city": "Cincinnati",
    "sg:classifiers": [
      {
        "category": "Professional",
        "subcategory": "Accounting \u0026 Tax Preparation",
        "type": "Services"
      }
    ],
    "sg:phone": "+1 513 769 9000",
    "sg:postcode": "45246",
    "sg:province": "OH",
    "sg:tags": [
      "accountant"
    ],
    "wof:name": "Wanner Patterson \u0026 Co",
    "wof:placetype": "venue"
  },
  "geometry": {"coordinates":[-84.444213,39.272852],"type":"Point"}
}
