{
  "type": "Feature",
  "properties": {
    "iso:country":"US",
    "sg:address":"299 S State St",
    "sg:city":"Westerville",
    "sg:classifiers":[
        {
            "category":"Professional",
            "subcategory":"Lawyer & Legal Services",
            "type":"Services"
        }
    ],
    "sg:phone":"+1 614 436 0346",
    "sg:postcode":"43081",
    "sg:province":"OH",
    "sg:tags":[
        "attorney"
    ],
    "wof:name":"Johnson Synder & Assoc",
    "wof:placetype":"venue"
},
  "geometry": {"coordinates":[-82.929082,40.119064],"type":"Point"}
}