{
  "type": "Feature",
  "properties": {
    "iso:country":"US",
    "sg:address":"812 Huron Rd E",
    "sg:city":"Cleveland",
    "sg:classifiers":[
        {
            "category":"Professional",
            "subcategory":"Management & Consulting",
            "type":"Services"
        }
    ],
    "sg:phone":"+1 216 685 9905",
    "sg:postcode":"44115",
    "sg:province":"OH",
    "sg:tags":[
        "consultant",
        "business"
    ],
    "wof:name":"R S Gordon & Assoc",
    "wof:placetype":"venue"
},
  "geometry": {"coordinates":[-81.686187,41.498589],"type":"Point"}
}