{
  "type": "Feature",
  "properties": {
    "iso:country":"US",
    "sg:address":"154 Erie St",
    "sg:city":"Oak Harbor",
    "sg:classifiers":[
        {
            "category":"Building & Trades",
            "subcategory":"Construction",
            "type":"Services"
        }
    ],
    "sg:phone":"+1 419 898 0537",
    "sg:postcode":"43449",
    "sg:province":"OH",
    "sg:tags":[
        "house"
    ],
    "wof:name":"Mike Fettermen Rmdlg & Cnstr",
    "wof:placetype":"venue"
},
  "geometry": {"coordinates":[-83.141903,41.505975],"type":"Point"}
}