{
  "type": "Feature",
  "properties": {
    "addr:full": "154 Erie St Oak Harbor OH 43449",
    "addr:housenumber": "154",
    "addr:postcode": "43449",
    "addr:street": "Erie St",
    "iso:country": "US",
    "sg:address": "154 Erie St",
    "sg:city": "Oak Harbor",
    "sg:classifiers": [
      {
        "category": "Building \u0026 Trades",
        "subcategory": "Construction",
        "type": "Services"
      }
    ],
    "sg:phone": "+1 419 898 0537",
    "sg:postcode": "43449",
    "sg:province": "OH",
    "sg:tags": [
      "house"
    ],
    "wof:name": "Mike Fettermen Rmdlg \u0026 Cnstr",
    "wof:placetype": "venue"
  },
  "geometry": {"coordinates":[-83.141903,41.505975],"type":"Point"}
}
