{
  "type": "Feature",
  "properties": {
    "iso:country":"US",
    "sg:address":"3306 Executive Pkwy",
    "sg:city":"Toledo",
    "sg:classifiers":[
        {
            "category":"Real Estate",
            "subcategory":"Real Estate Services",
            "type":"Services"
        }
    ],
    "sg:phone":"+1 419 531 1192",
    "sg:postcode":"43606",
    "sg:province":"OH",
    "sg:tags":[
        "abstract",
        "title"
    ],
    "wof:name":"Midland Title Security",
    "wof:placetype":"venue"
},
  "geometry": {"coordinates":[-83.628489,41.678924],"type":"Point"}
}