{
  "type": "Feature",
  "properties": {
    "iso:country":"US",
    "sg:address":"603 River Rd",
    "sg:city":"Maumee",
    "sg:classifiers":[
        {
            "category":"Insurance",
            "subcategory":"Insurance Agent",
            "type":"Services"
        }
    ],
    "sg:phone":"+1 419 893 4741",
    "sg:postcode":"43537",
    "sg:province":"OH",
    "wof:name":"Harold J Mouch Son Agcy Insur",
    "wof:placetype":"venue"
},
  "geometry": {"coordinates":[-83.643379,41.569576],"type":"Point"}
}