{
  "type": "Feature",
  "properties": {
    "addr:full":"111 Youngstown Warren Rd Niles OH 44446",
    "addr:housenumber":"111",
    "addr:postcode":"44446",
    "addr:street":"Youngstown Warren Rd",
    "iso:country":"US",
    "sg:address":"111 Youngstown Warren Rd",
    "sg:city":"Niles",
    "sg:classifiers":[
        {
            "category":"Travel",
            "subcategory":"Hotels & Motels",
            "type":"Entertainment"
        }
    ],
    "sg:phone":"+1 330 652 9988",
    "sg:postcode":"44446",
    "sg:province":"OH",
    "wof:name":"Villa Arms Motel",
    "wof:placetype":"venue"
},
  "geometry": {"coordinates":[-80.718609,41.183191],"type":"Point"}
}