{
  "type": "Feature",
  "properties": {
    "iso:country":"US",
    "sg:address":"4030 E 5th Ave",
    "sg:city":"Columbus",
    "sg:classifiers":[
        {
            "category":"Professional",
            "type":"Services"
        }
    ],
    "sg:phone":"+1 614 235 2941",
    "sg:postcode":"43219",
    "sg:province":"OH",
    "sg:tags":[
        "establishment"
    ],
    "wof:name":"Columbus International",
    "wof:placetype":"venue"
},
  "geometry": {"coordinates":[-82.892763,39.986761],"type":"Point"}
}