{
  "type": "Feature",
  "properties": {
    "iso:country":"US",
    "sg:address":"3641 Irving St",
    "sg:city":"Cincinnati",
    "sg:classifiers":[
        {
            "category":"Real Estate",
            "subcategory":"Real Estate Operator",
            "type":"Services"
        }
    ],
    "sg:phone":"+1 513 221 8330",
    "sg:postcode":"45220",
    "sg:province":"OH",
    "sg:tags":[
        "apartment"
    ],
    "wof:name":"Colonial Village Apartments",
    "wof:placetype":"venue"
},
  "geometry": {"coordinates":[-84.50791700000001,39.148448],"type":"Point"}
}