{
  "type": "Feature",
  "properties": {
    "addr:full": "9813 Montgomery Rd Cincinnati OH 45242",
    "addr:housenumber": "9813",
    "addr:postcode": "45242",
    "addr:street": "Montgomery Rd",
    "iso:country": "US",
    "sg:address": "9813 Montgomery Rd",
    "sg:city": "Cincinnati",
    "sg:classifiers": [
      {
        "category": "Banks \u0026 Credit Unions",
        "subcategory": "Bank",
        "type": "Services"
      }
    ],
    "sg:phone": "+1 513 793 2422",
    "sg:postcode": "45242",
    "sg:province": "OH",
    "sg:tags": [
      "commercial"
    ],
    "wof:name": "Cottage Savings Bank",
    "wof:placetype": "venue"
  },
  "geometry": {"coordinates":[-84.350986,39.234982],"type":"Point"}
}
