{
  "type": "Feature",
  "properties": {
    "addr:full": "100 E 3rd St Cincinnati OH 45202",
    "addr:housenumber": "100",
    "addr:postcode": "45202",
    "addr:street": "E 3Rd St",
    "iso:country": "US",
    "sg:address": "100 E 3rd St",
    "sg:city": "Cincinnati",
    "sg:classifiers": [
      {
        "category": "Banks \u0026 Credit Unions",
        "subcategory": "Bank",
        "type": "Services"
      }
    ],
    "sg:phone": "+1 937 228 5314",
    "sg:postcode": "45202",
    "sg:province": "OH",
    "sg:tags": [
      "cashing",
      "check"
    ],
    "wof:name": "Cashland",
    "wof:placetype": "venue"
  },
  "geometry": {"coordinates":[-84.509934,39.099056],"type":"Point"}
}
