{
  "type": "Feature",
  "properties": {
    "addr:full": "165 Sycamore Dr Painesville OH 44077",
    "addr:housenumber": "165",
    "addr:postcode": "44077",
    "addr:street": "Sycamore Dr",
    "iso:country": "US",
    "sg:address": "165 Sycamore Dr",
    "sg:city": "Painesville",
    "sg:classifiers": [
      {
        "category": "Building \u0026 Trades",
        "subcategory": "Construction",
        "type": "Services"
      }
    ],
    "sg:phone": "+1 440 639 8425",
    "sg:postcode": "44077",
    "sg:province": "OH",
    "sg:tags": [
      "siding",
      "contractor"
    ],
    "wof:name": "Kay Home Improvements Inc",
    "wof:placetype": "venue"
  },
  "geometry": {"coordinates":[-81.226487,41.766861],"type":"Point"}
}
