{
  "type": "Feature",
  "properties": {
    "addr:full": "8718 Auburn Rd Chardon OH 44024",
    "addr:housenumber": "8718",
    "addr:postcode": "44024",
    "addr:street": "Auburn Rd",
    "iso:country": "US",
    "sg:address": "8718 Auburn Rd",
    "sg:city": "Chardon",
    "sg:classifiers": [
      {
        "category": "Shopping",
        "type": "Retail Goods"
      }
    ],
    "sg:phone": "+1 440 352 6953",
    "sg:postcode": "44024",
    "sg:province": "OH",
    "sg:tags": [
      "wedding",
      "supply"
    ],
    "wof:name": "Dove Releases By Hearts",
    "wof:placetype": "venue"
  },
  "geometry": {"coordinates":[-81.243157,41.638055],"type":"Point"}
}
