{
  "type": "Feature",
  "properties": {
    "iso:country":"US",
    "sg:address":"1505 Woodville Rd",
    "sg:city":"Millbury",
    "sg:classifiers":[
        {
            "category":"Retail",
            "subcategory":"Portrait Studio",
            "type":"Services"
        }
    ],
    "sg:phone":"+1 419 836 2216",
    "sg:postcode":"43447",
    "sg:province":"OH",
    "sg:tags":[
        "photographer"
    ],
    "wof:name":"Innovations Portrait Studio",
    "wof:placetype":"venue"
},
  "geometry": {"coordinates":[-83.42575600000001,41.575671],"type":"Point"}
}