{
  "type": "Feature",
  "properties": {
    "iso:country":"US",
    "sg:address":"4571 Lyndon Good Hope Rd",
    "sg:city":"Greenfield",
    "sg:classifiers":[
        {
            "category":"Building & Trades",
            "subcategory":"Construction",
            "type":"Services"
        }
    ],
    "sg:phone":"+1 740 335 7277",
    "sg:postcode":"45123",
    "sg:province":"OH",
    "sg:tags":[
        "woodworker"
    ],
    "wof:name":"W-N-W Wood Products",
    "wof:placetype":"venue"
},
  "geometry": {"coordinates":[-83.33174099999999,39.420721],"type":"Point"}
}