{
  "type": "Feature",
  "properties": {
    "addr:full": "4571 Lyndon Good Hope Rd Greenfield OH 45123",
    "addr:housenumber": "4571",
    "addr:postcode": "45123",
    "addr:street": "Lyndon Good Hope Rd",
    "iso:country": "US",
    "sg:address": "4571 Lyndon Good Hope Rd",
    "sg:city": "Greenfield",
    "sg:classifiers": [
      {
        "category": "Building \u0026 Trades",
        "subcategory": "Construction",
        "type": "Services"
      }
    ],
    "sg:phone": "+1 740 335 7277",
    "sg:postcode": "45123",
    "sg:province": "OH",
    "sg:tags": [
      "woodworker"
    ],
    "wof:name": "W-N-W Wood Products",
    "wof:placetype": "venue"
  },
  "geometry": {"coordinates":[-83.331741,39.420721],"type":"Point"}
}
