{
  "type": "Feature",
  "properties": {
    "addr:full":"67 Apple Blossom Pl Dayton OH 45440",
    "addr:housenumber":"67",
    "addr:postcode":"45440",
    "addr:street":"Apple Blossom Pl",
    "iso:country":"US",
    "sg:address":"67 Apple Blossom Pl",
    "sg:city":"Dayton",
    "sg:classifiers":[
        {
            "category":"Building & Trades",
            "subcategory":"Construction",
            "type":"Services"
        }
    ],
    "sg:phone":"+1 937 429 5844",
    "sg:postcode":"45440",
    "sg:province":"OH",
    "sg:tags":[
        "house"
    ],
    "wof:name":"Eldridge Construction Co",
    "wof:placetype":"venue"
},
  "geometry": {"coordinates":[-84.087019,39.696966],"type":"Point"}
}