{
  "type": "Feature",
  "properties": {
    "addr:full": "3072 NE Catawba Rd Port Clinton OH 43452",
    "addr:housenumber": "3072",
    "addr:postcode": "43452",
    "addr:street": "Ne Catawba Rd",
    "iso:country": "US",
    "sg:address": "3072 NE Catawba Rd",
    "sg:city": "Port Clinton",
    "sg:classifiers": [
      {
        "category": "Recreation",
        "subcategory": "Marina",
        "type": "Entertainment"
      }
    ],
    "sg:phone": "+1 419 797 4618",
    "sg:postcode": "43452",
    "sg:province": "OH",
    "sg:tags": [
      "storage",
      "boat"
    ],
    "wof:name": "Winke's Boat Storage Inc",
    "wof:placetype": "venue"
  },
  "geometry": {"coordinates":[-82.832259,41.569036],"type":"Point"}
}
