{
  "type": "Feature",
  "properties": {
    "iso:country":"US",
    "sg:address":"123 4th St SW",
    "sg:city":"New Philadelphia",
    "sg:classifiers":[
        {
            "category":"Banks & Credit Unions",
            "subcategory":"Bank",
            "type":"Services"
        }
    ],
    "sg:phone":"+1 330 339 4335",
    "sg:postcode":"44663",
    "sg:province":"OH",
    "sg:tags":[
        "loan",
        "real estate"
    ],
    "wof:name":"Republic State Mortgage",
    "wof:placetype":"venue"
},
  "geometry": {"coordinates":[-81.452204,40.49009],"type":"Point"}
}