{
  "type": "Feature",
  "properties": {
    "addr:full": "123 4th St SW New Philadelphia OH 44663",
    "addr:housenumber": "123",
    "addr:postcode": "44663",
    "addr:street": "4Th St Sw",
    "iso:country": "US",
    "sg:address": "123 4th St SW",
    "sg:city": "New Philadelphia",
    "sg:classifiers": [
      {
        "category": "Banks \u0026 Credit Unions",
        "subcategory": "Bank",
        "type": "Services"
      }
    ],
    "sg:phone": "+1 330 339 4335",
    "sg:postcode": "44663",
    "sg:province": "OH",
    "sg:tags": [
      "loan",
      "real estate"
    ],
    "wof:name": "Republic State Mortgage",
    "wof:placetype": "venue"
  },
  "geometry": {"coordinates":[-81.452204,40.49009],"type":"Point"}
}
