{
  "type": "Feature",
  "properties": {
    "addr:full":"22653 Euclid Ave Cleveland OH 44117",
    "addr:housenumber":"22653",
    "addr:postcode":"44117",
    "addr:street":"Euclid Ave",
    "iso:country":"US",
    "sg:address":"22653 Euclid Ave",
    "sg:city":"Cleveland",
    "sg:classifiers":[
        {
            "category":"Personal",
            "subcategory":"Barber",
            "type":"Services"
        }
    ],
    "sg:phone":"+1 216 383 0093",
    "sg:postcode":"44117",
    "sg:province":"OH",
    "wof:name":"Fine Lines Barber & Styles",
    "wof:placetype":"venue"
},
  "geometry": {"coordinates":[-81.525575,41.572268],"type":"Point"}
}