{
  "type": "Feature",
  "properties": {
    "iso:country":"US",
    "sg:address":"18413 Windward Rd",
    "sg:city":"Cleveland",
    "sg:classifiers":[
        {
            "category":"Shopping",
            "subcategory":"Hobbies, Toys, & Games",
            "type":"Retail Goods"
        }
    ],
    "sg:phone":"+1 216 481 5605",
    "sg:postcode":"44119",
    "sg:province":"OH",
    "wof:name":"Memory Designer",
    "wof:placetype":"venue"
},
  "geometry": {"coordinates":[-81.552772,41.590181],"type":"Point"}
}