{
  "type": "Feature",
  "properties": {
    "iso:country":"US",
    "sg:address":"5481 Buenos Aires Blvd",
    "sg:city":"Westerville",
    "sg:classifiers":[
        {
            "category":"Recreation",
            "type":"Entertainment"
        }
    ],
    "sg:phone":"+1 614 523 2955",
    "sg:postcode":"43081",
    "sg:province":"OH",
    "sg:tags":[
        "club",
        "membership"
    ],
    "wof:name":"Little League BWLL",
    "wof:placetype":"venue"
},
  "geometry": {"coordinates":[-82.916505,40.082201],"type":"Point"}
}