{
  "type": "Feature",
  "properties": {
    "addr:full":"1941 Walker Rd Hilliard OH 43026",
    "addr:housenumber":"1941",
    "addr:postcode":"43026",
    "addr:street":"Walker Rd",
    "iso:country":"US",
    "sg:address":"1941 Walker Rd",
    "sg:city":"Hilliard",
    "sg:classifiers":[
        {
            "category":"Building & Trades",
            "subcategory":"Landscaping Services",
            "type":"Services"
        }
    ],
    "sg:phone":"+1 614 876 0338",
    "sg:postcode":"43026",
    "sg:province":"OH",
    "sg:tags":[
        "lawn",
        "maintenance",
        "grounds"
    ],
    "wof:name":"Country Green Lawn Svc",
    "wof:placetype":"venue"
},
  "geometry": {"coordinates":[-83.189362,39.990122],"type":"Point"}
}