{
  "type": "Feature",
  "properties": {
    "iso:country":"US",
    "sg:address":"21471 Schenck Creek Rd",
    "sg:city":"Howard",
    "sg:classifiers":[
        {
            "category":"Freight",
            "type":"Transportation"
        }
    ],
    "sg:phone":"+1 740 427 3004",
    "sg:postcode":"43028",
    "sg:province":"OH",
    "sg:tags":[
        "operator",
        "trucking"
    ],
    "wof:name":"Richard E Norman",
    "wof:placetype":"venue"
},
  "geometry": {"coordinates":[-82.369237,40.399517],"type":"Point"}
}