{
  "type": "Feature",
  "properties": {
    "addr:full":"2723 Elida Rd Lima OH 45805",
    "addr:housenumber":"2723",
    "addr:postcode":"45805",
    "addr:street":"Elida Rd",
    "iso:country":"US",
    "sg:address":"2723 Elida Rd",
    "sg:city":"Lima",
    "sg:classifiers":[
        {
            "category":"Restaurant",
            "type":"Food & Drink"
        }
    ],
    "sg:menulink":"http://www.allmenus.com/oh/american/211499-kfc---kentucky-fried-chicken/menu/",
    "sg:phone":"+1 419 331 3355",
    "sg:postcode":"45805",
    "sg:province":"OH",
    "sg:tags":[
        "american",
        "chicken"
    ],
    "wof:name":"KFC - Kentucky Fried Chicken",
    "wof:placetype":"venue"
},
  "geometry": {"coordinates":[-84.155697,40.765829],"type":"Point"}
}