{
  "type": "Feature",
  "properties": {
    "iso:country":"US",
    "sg:address":"3894 Columbus Rd",
    "sg:city":"Centerburg",
    "sg:classifiers":[
        {
            "category":"Organizations",
            "subcategory":"Non-profit Organization",
            "type":"Services"
        }
    ],
    "sg:phone":"+1 740 625 6750",
    "sg:postcode":"43011",
    "sg:province":"OH",
    "wof:name":"Amvet Post 59",
    "wof:placetype":"venue"
},
  "geometry": {"coordinates":[-82.70508,40.298189],"type":"Point"}
}