{
  "type": "Feature",
  "properties": {
    "addr:full":"190 N Central Ave Columbus OH 43222",
    "addr:housenumber":"190",
    "addr:postcode":"43222",
    "addr:street":"N Central Ave",
    "iso:country":"US",
    "sg:address":"190 N Central Ave",
    "sg:city":"Columbus",
    "sg:classifiers":[
        {
            "category":"Retail",
            "subcategory":"Auto Repair",
            "type":"Services"
        }
    ],
    "sg:phone":"+1 614 276 9692",
    "sg:postcode":"43222",
    "sg:province":"OH",
    "sg:tags":[
        "wrecker"
    ],
    "wof:name":"Alexis Towing",
    "wof:placetype":"venue"
},
  "geometry": {"coordinates":[-83.038923,39.961888],"type":"Point"}
}