{
  "type": "Feature",
  "properties": {
    "iso:country":"US",
    "sg:address":"32100 Solon Rd",
    "sg:city":"Cleveland",
    "sg:classifiers":[
        {
            "category":"Professional",
            "subcategory":"Employment Agencies",
            "type":"Services"
        }
    ],
    "sg:phone":"+1 440 519 0717",
    "sg:postcode":"44139",
    "sg:province":"OH",
    "sg:tags":[
        "opportunity"
    ],
    "wof:name":"National Accounting Search",
    "wof:placetype":"venue"
},
  "geometry": {"coordinates":[-81.45112,41.387167],"type":"Point"}
}