{
  "type": "Feature",
  "properties": {
    "iso:country":"US",
    "sg:address":"14204 E Co Rd 56",
    "sg:city":"Attica",
    "sg:classifiers":[
        {
            "category":"Organizations",
            "subcategory":"Religious Organization",
            "type":"Services"
        }
    ],
    "sg:phone":"+1 419 426 3043",
    "sg:postcode":"44807",
    "sg:province":"OH",
    "sg:tags":[
        "church"
    ],
    "wof:name":"Ss Peter & Paul's Catholic Chr",
    "wof:placetype":"venue"
},
  "geometry": {"coordinates":[-82.904339,41.06633],"type":"Point"}
}