{
  "type": "Feature",
  "properties": {
    "iso:country":"US",
    "sg:address":"330 Arco Dr",
    "sg:city":"Toledo",
    "sg:classifiers":[
        {
            "category":"Professional",
            "type":"Services"
        }
    ],
    "sg:phone":"+1 419 535 0101",
    "sg:postcode":"43607",
    "sg:province":"OH",
    "sg:tags":[
        "establishment"
    ],
    "wof:name":"Chempace Corp",
    "wof:placetype":"venue"
},
  "geometry": {"coordinates":[-83.62348,41.63292],"type":"Point"}
}