{
  "type": "Feature",
  "properties": {
    "addr:full": "4446 Old State Rte 68 Ripley OH 45167",
    "addr:housenumber": "4446",
    "addr:postcode": "45167",
    "addr:street": "Old State Rte 68",
    "iso:country": "US",
    "sg:address": "4446 Old State Rte 68",
    "sg:city": "Ripley",
    "sg:classifiers": [
      {
        "category": "Freight",
        "type": "Transportation"
      }
    ],
    "sg:phone": "+1 937 392 4690",
    "sg:postcode": "45167",
    "sg:province": "OH",
    "sg:tags": [
      "local",
      "trucking"
    ],
    "wof:name": "Truitt Trucking",
    "wof:placetype": "venue"
  },
  "geometry": {"coordinates":[-83.849956,38.757822],"type":"Point"}
}
