{
  "type": "Feature",
  "properties": {
    "iso:country":"US",
    "sg:address":"5122 Sunrise View Cir",
    "sg:city":"Middletown",
    "sg:classifiers":[
        {
            "category":"Building & Trades",
            "subcategory":"Construction",
            "type":"Services"
        }
    ],
    "sg:phone":"+1 513 755 0972",
    "sg:postcode":"45044",
    "sg:province":"OH",
    "sg:tags":[
        "residential"
    ],
    "wof:name":"Inverness Group",
    "wof:placetype":"venue"
},
  "geometry": {"coordinates":[-84.363562,39.418982],"type":"Point"}
}