{
  "type": "Feature",
  "properties": {
    "addr:full":"6917 Harvard Ave Cleveland OH 44105",
    "addr:housenumber":"6917",
    "addr:postcode":"44105",
    "addr:street":"Harvard Ave",
    "iso:country":"US",
    "sg:address":"6917 Harvard Ave",
    "sg:city":"Cleveland",
    "sg:classifiers":[
        {
            "category":"Personal",
            "subcategory":"Beauty Salon",
            "type":"Services"
        }
    ],
    "sg:phone":"+1 216 376 4290",
    "sg:postcode":"44105",
    "sg:province":"OH",
    "sg:tags":[
        "hair",
        "supply",
        "accessory"
    ],
    "sg:website":"http://www.royalessence.com",
    "wof:name":"Royal Essence",
    "wof:placetype":"venue"
},
  "geometry": {"coordinates":[-81.64137599999999,41.44858],"type":"Point"}
}