{
  "type": "Feature",
  "properties": {
    "iso:country":"US",
    "sg:address":"10809 Bryant Ave",
    "sg:city":"Cleveland",
    "sg:classifiers":[
        {
            "category":"Shopping",
            "subcategory":"Discount & Variety Stores",
            "type":"Retail Goods"
        }
    ],
    "sg:phone":"+1 216 268 1787",
    "sg:postcode":"44108",
    "sg:province":"OH",
    "sg:tags":[
        "merchandise",
        "general"
    ],
    "wof:name":"Teras Closet Shop",
    "wof:placetype":"venue"
},
  "geometry": {"coordinates":[-81.613302,41.533732],"type":"Point"}
}