{
  "type": "Feature",
  "properties": {
    "addr:full": "121 N Arch St Fremont OH 43420",
    "addr:housenumber": "121",
    "addr:postcode": "43420",
    "addr:street": "N Arch St",
    "iso:country": "US",
    "sg:address": "121 N Arch St",
    "sg:city": "Fremont",
    "sg:classifiers": [
      {
        "category": "Professional",
        "subcategory": "Lawyer \u0026 Legal Services",
        "type": "Services"
      }
    ],
    "sg:phone": "+1 419 334 8908",
    "sg:postcode": "43420",
    "sg:province": "OH",
    "wof:name": "Able",
    "wof:placetype": "venue"
  },
  "geometry": {"coordinates":[-83.114374,41.347351],"type":"Point"}
}
