{
  "type": "Feature",
  "properties": {
    "addr:full": "1945 W State St Alliance OH 44601",
    "addr:housenumber": "1945",
    "addr:postcode": "44601",
    "addr:street": "W State St",
    "iso:country": "US",
    "sg:address": "1945 W State St",
    "sg:city": "Alliance",
    "sg:classifiers": [
      {
        "category": "Autos \u0026 Motor Vehicles",
        "subcategory": "Auto Supplies",
        "type": "Retail Goods"
      }
    ],
    "sg:phone": "+1 330 821 9491",
    "sg:postcode": "44601",
    "sg:province": "OH",
    "sg:tags": [
      "tire"
    ],
    "wof:name": "Terry's Tire Town",
    "wof:placetype": "venue"
  },
  "geometry": {"coordinates":[-81.140696,40.901983],"type":"Point"}
}
