{
  "type": "Feature",
  "properties": {
    "iso:country":"US",
    "sg:address":"1945 W State St",
    "sg:city":"Alliance",
    "sg:classifiers":[
        {
            "category":"Autos & Motor Vehicles",
            "subcategory":"Auto Supplies",
            "type":"Retail Goods"
        }
    ],
    "sg:phone":"+1 330 821 9491",
    "sg:postcode":"44601",
    "sg:province":"OH",
    "sg:tags":[
        "tire"
    ],
    "wof:name":"Terry's Tire Town",
    "wof:placetype":"venue"
},
  "geometry": {"coordinates":[-81.14069600000001,40.901983],"type":"Point"}
}