{
  "type": "Feature",
  "properties": {
    "iso:country":"US",
    "sg:address":"5791 Lake Circle Dr",
    "sg:city":"Fairfield",
    "sg:classifiers":[
        {
            "category":"Manufacturing",
            "subcategory":"Printing",
            "type":"Manufacturing & Wholesale Goods"
        }
    ],
    "sg:phone":"+1 513 829 0950",
    "sg:postcode":"45014",
    "sg:province":"OH",
    "sg:tags":[
        "publishing"
    ],
    "wof:name":"Dectire Publishing",
    "wof:placetype":"venue"
},
  "geometry": {"coordinates":[-84.59457500000001,39.323343],"type":"Point"}
}