{
  "type": "Feature",
  "properties": {
    "addr:full": "5791 Lake Circle Dr Fairfield OH 45014",
    "addr:housenumber": "5791",
    "addr:postcode": "45014",
    "addr:street": "Lake Circle Dr",
    "iso:country": "US",
    "sg:address": "5791 Lake Circle Dr",
    "sg:city": "Fairfield",
    "sg:classifiers": [
      {
        "category": "Manufacturing",
        "subcategory": "Printing",
        "type": "Manufacturing \u0026 Wholesale Goods"
      }
    ],
    "sg:phone": "+1 513 829 0950",
    "sg:postcode": "45014",
    "sg:province": "OH",
    "sg:tags": [
      "publishing"
    ],
    "wof:name": "Dectire Publishing",
    "wof:placetype": "venue"
  },
  "geometry": {"coordinates":[-84.594575,39.323343],"type":"Point"}
}
