{
  "type": "Feature",
  "properties": {
    "addr:full": "5210 Chillicothe Rd Chagrin Falls OH 44022",
    "addr:postcode": "5210;44022",
    "addr:street": "Chillicothe Rd",
    "iso:country": "US",
    "sg:address": "5210 Chillicothe Rd",
    "sg:city": "Chagrin Falls",
    "sg:classifiers": [
      {
        "category": "Restaurant",
        "type": "Food \u0026 Drink"
      }
    ],
    "sg:phone": "+1 440 338 1112",
    "sg:postcode": "44022",
    "sg:province": "OH",
    "sg:tags": [
      "pizza"
    ],
    "wof:name": "Augie's Pizza",
    "wof:placetype": "venue"
  },
  "geometry": {"coordinates":[-81.338097,41.430401],"type":"Point"}
}
