{
  "type": "Feature",
  "properties": {
    "iso:country":"US",
    "sg:address":"1195 Timbertop Dr",
    "sg:city":"Tallmadge",
    "sg:classifiers":[
        {
            "category":"Building & Trades",
            "subcategory":"Plumbing",
            "type":"Services"
        }
    ],
    "sg:phone":"+1 330 634 0942",
    "sg:postcode":"44278",
    "sg:province":"OH",
    "sg:tags":[
        "contractor"
    ],
    "wof:name":"Johnson Controls",
    "wof:placetype":"venue"
},
  "geometry": {"coordinates":[-81.396182,41.086877],"type":"Point"}
}