{
  "type": "Feature",
  "properties": {
    "iso:country":"US",
    "sg:address":"1774 Ramblewood Ave",
    "sg:city":"Columbus",
    "sg:classifiers":[
        {
            "category":"Insurance",
            "subcategory":"Insurance Agent",
            "type":"Services"
        }
    ],
    "sg:phone":"+1 614 451 9277",
    "sg:postcode":"43235",
    "sg:province":"OH",
    "wof:name":"Dennis Eric Conard",
    "wof:placetype":"venue"
},
  "geometry": {"coordinates":[-83.067385,40.070142],"type":"Point"}
}