{
  "type": "Feature",
  "properties": {
    "addr:full": "6050 E Livingston Ave Columbus OH 43232",
    "addr:housenumber": "6050",
    "addr:postcode": "43232",
    "addr:street": "E Livingston Ave",
    "iso:country": "US",
    "sg:address": "6050 E Livingston Ave",
    "sg:city": "Columbus",
    "sg:classifiers": [
      {
        "category": "Retail",
        "subcategory": "Auto Repair",
        "type": "Services"
      }
    ],
    "sg:phone": "+1 614 863 6611",
    "sg:postcode": "43232",
    "sg:province": "OH",
    "sg:tags": [
      "automotive",
      "general"
    ],
    "wof:name": "Boutselis Auto Care Inc",
    "wof:placetype": "venue"
  },
  "geometry": {"coordinates":[-82.833983,39.942233],"type":"Point"}
}
