{
  "type": "Feature",
  "properties": {
    "addr:full":"1410 Sunset Rd Cleveland OH 44124",
    "addr:housenumber":"1410",
    "addr:postcode":"44124",
    "addr:street":"Sunset Rd",
    "iso:country":"US",
    "sg:address":"1410 Sunset Rd",
    "sg:city":"Cleveland",
    "sg:classifiers":[
        {
            "category":"Building & Trades",
            "subcategory":"Construction",
            "type":"Services"
        }
    ],
    "sg:phone":"+1 440 446 9062",
    "sg:postcode":"44124",
    "sg:province":"OH",
    "sg:tags":[
        "contractor"
    ],
    "wof:name":"Imperial Waterproofing Inc",
    "wof:placetype":"venue"
},
  "geometry": {"coordinates":[-81.461766,41.52158],"type":"Point"}
}