{
  "type": "Feature",
  "properties": {
    "addr:full": "7223 Pinehill Rd Painesville OH 44077",
    "addr:housenumber": "7223",
    "addr:postcode": "44077",
    "addr:street": "Pinehill Rd",
    "iso:country": "US",
    "sg:address": "7223 Pinehill Rd",
    "sg:city": "Painesville",
    "sg:classifiers": [
      {
        "category": "Manufacturing",
        "subcategory": "Printing",
        "type": "Manufacturing \u0026 Wholesale Goods"
      }
    ],
    "sg:phone": "+1 440 352 1587",
    "sg:postcode": "44077",
    "sg:province": "OH",
    "sg:tags": [
      "publisher",
      "software"
    ],
    "wof:name": "RLC Control Systems",
    "wof:placetype": "venue"
  },
  "geometry": {"coordinates":[-81.255359,41.676072],"type":"Point"}
}
