{
  "type": "Feature",
  "properties": {
    "iso:country":"US",
    "sg:address":"4030 Mount Carmel Tobasco Rd",
    "sg:city":"Cincinnati",
    "sg:classifiers":[
        {
            "category":"Professional",
            "subcategory":"Lawyer & Legal Services",
            "type":"Services"
        }
    ],
    "sg:phone":"+1 513 528 7222",
    "sg:postcode":"45255",
    "sg:province":"OH",
    "sg:tags":[
        "attorney"
    ],
    "wof:name":"Gary Billig",
    "wof:placetype":"venue"
},
  "geometry": {"coordinates":[-84.298164,39.073878],"type":"Point"}
}