{
  "type": "Feature",
  "properties": {
    "addr:full": "1720 Indian Wood Cir Maumee OH 43537",
    "addr:housenumber": "1720",
    "addr:postcode": "43537",
    "addr:street": "Indian Wood Cir",
    "iso:country": "US",
    "sg:address": "1720 Indian Wood Cir",
    "sg:city": "Maumee",
    "sg:classifiers": [
      {
        "category": "Insurance",
        "subcategory": "Insurance Agent",
        "type": "Services"
      }
    ],
    "sg:phone": "+1 419 897 1400",
    "sg:postcode": "43537",
    "sg:province": "OH",
    "sg:tags": [
      "processing"
    ],
    "wof:name": "Stateline Tpa Inc",
    "wof:placetype": "venue"
  },
  "geometry": {"coordinates":[-83.684114,41.589567],"type":"Point"}
}
