{
  "type": "Feature",
  "properties": {
    "iso:country":"US",
    "sg:address":"420 W Main St",
    "sg:city":"Pomeroy",
    "sg:classifiers":[
        {
            "category":"Autos & Motor Vehicles",
            "subcategory":"Fuel & Gas Station",
            "type":"Retail Goods"
        }
    ],
    "sg:phone":"+1 740 992 1393",
    "sg:postcode":"45769",
    "sg:province":"OH",
    "sg:tags":[
        "oil"
    ],
    "wof:name":"Marathon Service Ctr",
    "wof:placetype":"venue"
},
  "geometry": {"coordinates":[-82.042371,39.019405],"type":"Point"}
}