{
  "type": "Feature",
  "properties": {
    "addr:full": "3670 S Meridian Rd Youngstown OH 44511",
    "addr:housenumber": "3670",
    "addr:postcode": "44511",
    "addr:street": "S Meridian Rd",
    "iso:country": "US",
    "sg:address": "3670 S Meridian Rd",
    "sg:city": "Youngstown",
    "sg:classifiers": [
      {
        "category": "Food \u0026 Beverages",
        "subcategory": "Groceries \u0026 Convenience Stores",
        "type": "Retail Goods"
      }
    ],
    "sg:phone": "+1 330 793 1231",
    "sg:postcode": "44511",
    "sg:province": "OH",
    "wof:name": "True North 107",
    "wof:placetype": "venue"
  },
  "geometry": {"coordinates":[-80.711143,41.063791],"type":"Point"}
}
