{
  "type": "Feature",
  "properties": {
    "addr:full": "11 W Main St Newark OH 43055",
    "addr:housenumber": "11",
    "addr:postcode": "43055",
    "addr:street": "W Main St",
    "iso:country": "US",
    "sg:address": "11 W Main St",
    "sg:city": "Newark",
    "sg:classifiers": [
      {
        "category": "Manufacturing",
        "subcategory": "Printing",
        "type": "Manufacturing \u0026 Wholesale Goods"
      }
    ],
    "sg:phone": "+1 740 345 9823",
    "sg:postcode": "43055",
    "sg:province": "OH",
    "sg:tags": [
      "offset"
    ],
    "wof:name": "A Printed Impression",
    "wof:placetype": "venue"
  },
  "geometry": {"coordinates":[-82.402793,40.05751],"type":"Point"}
}
