{
  "type": "Feature",
  "properties": {
    "iso:country":"US",
    "sg:address":"11 W Main St",
    "sg:city":"Newark",
    "sg:classifiers":[
        {
            "category":"Manufacturing",
            "subcategory":"Printing",
            "type":"Manufacturing & Wholesale Goods"
        }
    ],
    "sg:phone":"+1 740 345 9823",
    "sg:postcode":"43055",
    "sg:province":"OH",
    "sg:tags":[
        "offset"
    ],
    "wof:name":"A Printed Impression",
    "wof:placetype":"venue"
},
  "geometry": {"coordinates":[-82.402793,40.05751],"type":"Point"}
}