{
  "type": "Feature",
  "properties": {
    "addr:full": "782 Kings Run Dr Cincinnati OH 45232",
    "addr:housenumber": "782",
    "addr:postcode": "45232",
    "addr:street": "Kings Run Dr",
    "iso:country": "US",
    "sg:address": "782 Kings Run Dr",
    "sg:city": "Cincinnati",
    "sg:classifiers": [
      {
        "category": "Wholesale",
        "subcategory": "Machinery \u0026 Supplies",
        "type": "Manufacturing \u0026 Wholesale Goods"
      }
    ],
    "sg:phone": "+1 513 542 8597",
    "sg:postcode": "45232",
    "sg:province": "OH",
    "sg:tags": [
      "contractor"
    ],
    "wof:name": "Northside Construction Supply",
    "wof:placetype": "venue"
  },
  "geometry": {"coordinates":[-84.507982,39.173693],"type":"Point"}
}
