{
  "type": "Feature",
  "properties": {
    "addr:full":"5742 Westbourne Ave Columbus OH 43213",
    "addr:housenumber":"5742",
    "addr:postcode":"43213",
    "addr:street":"Westbourne Ave",
    "iso:country":"US",
    "sg:address":"5742 Westbourne Ave",
    "sg:city":"Columbus",
    "sg:classifiers":[
        {
            "category":"Wholesale",
            "subcategory":"Machinery & Supplies",
            "type":"Manufacturing & Wholesale Goods"
        }
    ],
    "sg:phone":"+1 614 575 2720",
    "sg:postcode":"43213",
    "sg:province":"OH",
    "sg:tags":[
        "wholesaler",
        "product",
        "industrial"
    ],
    "wof:name":"Action Supply Products  Inc",
    "wof:placetype":"venue"
},
  "geometry": {"coordinates":[-82.850627,39.984489],"type":"Point"}
}