{
  "type": "Feature",
  "properties": {
    "addr:full":"1624 Remelle Rd Monroeville OH 44847",
    "addr:housenumber":"1624",
    "addr:postcode":"44847",
    "addr:street":"Remelle Rd",
    "iso:country":"US",
    "sg:address":"1624 Remelle Rd",
    "sg:city":"Monroeville",
    "sg:classifiers":[
        {
            "category":"Building & Trades",
            "subcategory":"Construction",
            "type":"Services"
        }
    ],
    "sg:phone":"+1 419 663 0213",
    "sg:postcode":"44847",
    "sg:province":"OH",
    "sg:tags":[
        "house"
    ],
    "wof:name":"Helmstetter Home Improvement",
    "wof:placetype":"venue"
},
  "geometry": {"coordinates":[-82.66298,41.180888],"type":"Point"}
}