{
  "type": "Feature",
  "properties": {
    "iso:country":"US",
    "sg:address":"5853 Robertdale Rd",
    "sg:city":"Cleveland",
    "sg:classifiers":[
        {
            "category":"Building & Trades",
            "subcategory":"Landscaping Services",
            "type":"Services"
        }
    ],
    "sg:phone":"+1 440 232 2373",
    "sg:postcode":"44146",
    "sg:province":"OH",
    "sg:tags":[
        "tree"
    ],
    "wof:name":"Great Lakes Tree Svc Inc",
    "wof:placetype":"venue"
},
  "geometry": {"coordinates":[-81.492875,41.39704],"type":"Point"}
}