{
  "type": "Feature",
  "properties": {
    "addr:full":"3761 Washington Blvd Cleveland OH 44118",
    "addr:housenumber":"3761",
    "addr:postcode":"44118",
    "addr:street":"Washington Blvd",
    "iso:country":"US",
    "sg:address":"3761 Washington Blvd",
    "sg:city":"Cleveland",
    "sg:classifiers":[
        {
            "category":"Local Transit",
            "type":"Transportation"
        }
    ],
    "sg:phone":"+1 216 321 0004",
    "sg:postcode":"44118",
    "sg:province":"OH",
    "sg:tags":[
        "suburban"
    ],
    "wof:name":"Max Shnell Airport Transport",
    "wof:placetype":"venue"
},
  "geometry": {"coordinates":[-81.54517199999999,41.501022],"type":"Point"}
}