{
  "type": "Feature",
  "properties": {
    "iso:country":"US",
    "sg:address":"102 Otto St",
    "sg:city":"Ottoville",
    "sg:classifiers":[
        {
            "category":"Retail",
            "subcategory":"Auto Repair",
            "type":"Services"
        }
    ],
    "sg:phone":"+1 419 453 3074",
    "sg:postcode":"45876",
    "sg:province":"OH",
    "sg:tags":[
        "body",
        "automobile",
        "painting"
    ],
    "wof:name":"Siefker Body Shop",
    "wof:placetype":"venue"
},
  "geometry": {"coordinates":[-84.33717,40.932274],"type":"Point"}
}