{
  "type": "Feature",
  "properties": {
    "iso:country":"US",
    "sg:address":"6210 Brookpark Rd",
    "sg:city":"Cleveland",
    "sg:classifiers":[
        {
            "category":"Banks & Credit Unions",
            "subcategory":"Bank",
            "type":"Services"
        }
    ],
    "sg:phone":"+1 216 739 0663",
    "sg:postcode":"44129",
    "sg:province":"OH",
    "sg:tags":[
        "depository",
        "banking"
    ],
    "wof:name":"Cash Now",
    "wof:placetype":"venue"
},
  "geometry": {"coordinates":[-81.727321,41.418642],"type":"Point"}
}