{
  "type": "Feature",
  "properties": {
    "addr:full":"7 Main St E Sparta OH 43350",
    "addr:housenumber":"7",
    "addr:postcode":"43350",
    "addr:street":"Main St E",
    "iso:country":"US",
    "sg:address":"7 Main St E",
    "sg:city":"Sparta",
    "sg:classifiers":[
        {
            "category":"Professional",
            "type":"Services"
        }
    ],
    "sg:phone":"+1 419 768 4134",
    "sg:postcode":"43350",
    "sg:province":"OH",
    "sg:tags":[
        "establishment"
    ],
    "wof:name":"Bullock Enterprises",
    "wof:placetype":"venue"
},
  "geometry": {"coordinates":[-82.70009400000001,40.395049],"type":"Point"}
}