{
  "type": "Feature",
  "properties": {
    "iso:country":"US",
    "sg:address":"2115 S Main St",
    "sg:city":"Bellefontaine",
    "sg:classifiers":[
        {
            "category":"Professional",
            "subcategory":"Business Services",
            "type":"Services"
        }
    ],
    "sg:phone":"+1 937 292 7279",
    "sg:postcode":"43311",
    "sg:province":"OH",
    "sg:tags":[
        "packaging"
    ],
    "wof:name":"Pak Mail",
    "wof:placetype":"venue"
},
  "geometry": {"coordinates":[-83.761544,40.332029],"type":"Point"}
}