{
  "type": "Feature",
  "properties": {
    "iso:country":"US",
    "sg:address":"5000 Rockside Rd",
    "sg:city":"Cleveland",
    "sg:classifiers":[
        {
            "category":"Real Estate",
            "subcategory":"Real Estate Services",
            "type":"Services"
        }
    ],
    "sg:phone":"+1 216 901 3250",
    "sg:postcode":"44131",
    "sg:province":"OH",
    "sg:tags":[
        "agency",
        "title"
    ],
    "wof:name":"Affilated Title Agency Inc",
    "wof:placetype":"venue"
},
  "geometry": {"coordinates":[-81.65416399999999,41.396992],"type":"Point"}
}