{
  "type": "Feature",
  "properties": {
    "iso:country":"US",
    "sg:address":"30575 Bainbridge Rd",
    "sg:city":"Cleveland",
    "sg:classifiers":[
        {
            "category":"Banks & Credit Unions",
            "subcategory":"Investment Brokerage",
            "type":"Services"
        },
        {
            "category":"Banks & Credit Unions",
            "subcategory":"Financial Services",
            "type":"Services"
        }
    ],
    "sg:phone":"+1 440 349 8173",
    "sg:postcode":"44139",
    "sg:province":"OH",
    "sg:tags":[
        "investor"
    ],
    "wof:name":"Betsy Investments Co",
    "wof:placetype":"venue"
},
  "geometry": {"coordinates":[-81.464884,41.402964],"type":"Point"}
}