{
  "type": "Feature",
  "properties": {
    "iso:country":"US",
    "sg:address":"3600 Mink St SW",
    "sg:city":"Pataskala",
    "sg:classifiers":[
        {
            "category":"Freight",
            "type":"Transportation"
        }
    ],
    "sg:phone":"+1 740 927 4658",
    "sg:postcode":"43062",
    "sg:province":"OH",
    "sg:tags":[
        "operator",
        "local",
        "trucking"
    ],
    "wof:name":"Derwin J Morris",
    "wof:placetype":"venue"
},
  "geometry": {"coordinates":[-82.732303,40.036875],"type":"Point"}
}