{
  "type": "Feature",
  "properties": {
    "iso:country":"US",
    "sg:address":"5565 Westerville Rd",
    "sg:city":"Westerville",
    "sg:classifiers":[
        {
            "category":"Building & Trades",
            "subcategory":"Plumbing",
            "type":"Services"
        }
    ],
    "sg:phone":"+1 614 882 7435",
    "sg:postcode":"43081",
    "sg:province":"OH",
    "sg:tags":[
        "plumbing",
        "contractor"
    ],
    "wof:name":"Starr Mechanical Inc",
    "wof:placetype":"venue"
},
  "geometry": {"coordinates":[-82.928088,40.083928],"type":"Point"}
}