{
  "type": "Feature",
  "properties": {
    "iso:country":"US",
    "sg:address":"1202 Linn St",
    "sg:city":"Cincinnati",
    "sg:classifiers":[
        {
            "category":"Real Estate",
            "subcategory":"Real Estate Operator",
            "type":"Services"
        }
    ],
    "sg:phone":"+1 513 665 9777",
    "sg:postcode":"45203",
    "sg:province":"OH",
    "sg:tags":[
        "building",
        "apartment"
    ],
    "wof:name":"City West",
    "wof:placetype":"venue"
},
  "geometry": {"coordinates":[-84.527746,39.108468],"type":"Point"}
}