{
  "type": "Feature",
  "properties": {
    "iso:country":"US",
    "sg:address":"1059 Brooke Ave",
    "sg:city":"Cincinnati",
    "sg:classifiers":[
        {
            "category":"Banks & Credit Unions",
            "subcategory":"Financial Services",
            "type":"Services"
        }
    ],
    "sg:phone":"+1 513 624 0825",
    "sg:postcode":"45230",
    "sg:province":"OH",
    "sg:tags":[
        "information",
        "consumer"
    ],
    "sg:website":"http://www.bradlittle.com",
    "wof:name":"Brad Little Information Highway",
    "wof:placetype":"venue"
},
  "geometry": {"coordinates":[-84.379665,39.071175],"type":"Point"}
}