{
  "type": "Feature",
  "properties": {
    "addr:full":"44 W Main St Mansfield OH 44904",
    "addr:housenumber":"44",
    "addr:postcode":"44904",
    "addr:street":"W Main St",
    "iso:country":"US",
    "sg:address":"44 W Main St",
    "sg:city":"Mansfield",
    "sg:classifiers":[
        {
            "category":"Government",
            "subcategory":"Office",
            "type":"Public Place"
        }
    ],
    "sg:phone":"+1 419 884 1329",
    "sg:postcode":"44904",
    "sg:province":"OH",
    "sg:tags":[
        "policy"
    ],
    "wof:name":"Income Tax Department",
    "wof:placetype":"venue"
},
  "geometry": {"coordinates":[-82.58422899999999,40.67883],"type":"Point"}
}