{
  "type": "Feature",
  "properties": {
    "addr:full": "95 Arch St Akron OH 44304",
    "addr:housenumber": "95",
    "addr:postcode": "44304",
    "addr:street": "Arch St",
    "iso:country": "US",
    "sg:address": "95 Arch St",
    "sg:city": "Akron",
    "sg:classifiers": [
      {
        "category": "Health Services",
        "subcategory": "Doctor",
        "type": "Services"
      }
    ],
    "sg:phone": "+1 330 376 9797",
    "sg:postcode": "44304",
    "sg:province": "OH",
    "sg:tags": [
      "physician",
      "surgeon"
    ],
    "sg:website": "www.akronmfmspecialists.com",
    "wof:name": "Akron Children's Maternal-Ftl",
    "wof:placetype": "venue"
  },
  "geometry": {"coordinates":[-81.499685,41.080153],"type":"Point"}
}
