{
  "type": "Feature",
  "properties": {
    "addr:full":"3949 Broadway Ave NE Louisville OH 44641",
    "addr:housenumber":"3949",
    "addr:postcode":"44641",
    "addr:street":"Broadway Ave Ne",
    "iso:country":"US",
    "sg:address":"3949 Broadway Ave NE",
    "sg:city":"Louisville",
    "sg:classifiers":[
        {
            "category":"Professional",
            "subcategory":"Detective & Security Services",
            "type":"Services"
        }
    ],
    "sg:phone":"+1 330 456 6670",
    "sg:postcode":"44641",
    "sg:province":"OH",
    "sg:tags":[
        "guard",
        "patrol"
    ],
    "wof:name":"Surveillance Pros",
    "wof:placetype":"venue"
},
  "geometry": {"coordinates":[-81.29844300000001,40.832545],"type":"Point"}
}