{
  "type": "Feature",
  "properties": {
    "addr:full":"610 Court St Fremont OH 43420",
    "addr:housenumber":"610",
    "addr:postcode":"43420",
    "addr:street":"Court St",
    "iso:country":"US",
    "sg:address":"610 Court St",
    "sg:city":"Fremont",
    "sg:classifiers":[
        {
            "category":"Government",
            "subcategory":"Office",
            "type":"Public Place"
        }
    ],
    "sg:phone":"+1 419 333 9469",
    "sg:postcode":"43420",
    "sg:province":"OH",
    "wof:name":"Sandusky County Juvenile Comm",
    "wof:placetype":"venue"
},
  "geometry": {"coordinates":[-83.118404,41.347567],"type":"Point"}
}