{
  "type": "Feature",
  "properties": {
    "addr:full": "6501 Heisley Rd Mentor OH 44060",
    "addr:housenumber": "6501",
    "addr:postcode": "44060",
    "addr:street": "Heisley Rd",
    "iso:country": "US",
    "sg:address": "6501 Heisley Rd",
    "sg:city": "Mentor",
    "sg:classifiers": [
      {
        "category": "Retail",
        "subcategory": "Auto Repair",
        "type": "Services"
      }
    ],
    "sg:phone": "+1 440 255 8473",
    "sg:postcode": "44060",
    "sg:province": "OH",
    "sg:tags": [
      "repairing",
      "automobile"
    ],
    "wof:name": "Enger Auto Svc \u0026 Tire",
    "wof:placetype": "venue"
  },
  "geometry": {"coordinates":[-81.30635,41.693196],"type":"Point"}
}
