{
  "type": "Feature",
  "properties": {
    "addr:full": "13641 Cooperrider Rd SE Glenford OH 43739",
    "addr:housenumber": "13641",
    "addr:postcode": "43739",
    "addr:street": "Cooperrider Rd Se",
    "iso:country": "US",
    "sg:address": "13641 Cooperrider Rd SE",
    "sg:city": "Glenford",
    "sg:classifiers": [
      {
        "category": "Building \u0026 Trades",
        "subcategory": "Construction",
        "type": "Services"
      }
    ],
    "sg:phone": "+1 740 787 1689",
    "sg:postcode": "43739",
    "sg:province": "OH",
    "sg:tags": [
      "water",
      "restoration",
      "damage"
    ],
    "wof:name": "American Power Steam",
    "wof:placetype": "venue"
  },
  "geometry": {"coordinates":[-82.287469,39.94329],"type":"Point"}
}
