{
  "type": "Feature",
  "properties": {
    "addr:full":"3324 W 31st St Cleveland OH 44109",
    "addr:housenumber":"3324",
    "addr:postcode":"44109",
    "addr:street":"W 31St St",
    "iso:country":"US",
    "sg:address":"3324 W 31st St",
    "sg:city":"Cleveland",
    "sg:classifiers":[
        {
            "category":"Food & Beverages",
            "subcategory":"Groceries & Convenience Stores",
            "type":"Retail Goods"
        }
    ],
    "sg:phone":"+1 216 351 8341",
    "sg:postcode":"44109",
    "sg:province":"OH",
    "sg:tags":[
        "grocer"
    ],
    "wof:name":"D & J Food Mart",
    "wof:placetype":"venue"
},
  "geometry": {"coordinates":[-81.70312,41.465385],"type":"Point"}
}