{
  "type": "Feature",
  "properties": {
    "iso:country":"US",
    "sg:address":"1 N Union St",
    "sg:city":"Delaware",
    "sg:classifiers":[
        {
            "category":"Manufacturing",
            "subcategory":"Apparel",
            "type":"Manufacturing & Wholesale Goods"
        }
    ],
    "sg:phone":"+1 740 363 6349",
    "sg:postcode":"43015",
    "sg:province":"OH",
    "sg:tags":[
        "fur",
        "mfg"
    ],
    "wof:name":"Wildside",
    "wof:placetype":"venue"
},
  "geometry": {"coordinates":[-83.065862,40.300078],"type":"Point"}
}