{
  "type": "Feature",
  "properties": {
    "addr:full": "3913 Berry Leaf Ln Hilliard OH 43026",
    "addr:housenumber": "3913",
    "addr:postcode": "43026",
    "addr:street": "Berry Leaf Ln",
    "iso:country": "US",
    "sg:address": "3913 Berry Leaf Ln",
    "sg:city": "Hilliard",
    "sg:classifiers": [
      {
        "category": "Health Services",
        "subcategory": "Doctor",
        "type": "Services"
      }
    ],
    "sg:phone": "+1 614 876 5500",
    "sg:postcode": "43026",
    "sg:province": "OH",
    "sg:tags": [
      "dentist"
    ],
    "wof:name": "Hilliard Pediatric Dentistry",
    "wof:placetype": "venue"
  },
  "geometry": {"coordinates":[-83.148828,40.031461],"type":"Point"}
}
