{
  "type": "Feature",
  "properties": {
    "addr:full": "5221 303rd St Toledo OH 43611",
    "addr:housenumber": "5221",
    "addr:postcode": "43611",
    "addr:street": "303Rd St",
    "iso:country": "US",
    "sg:address": "5221 303rd St",
    "sg:city": "Toledo",
    "sg:classifiers": [
      {
        "category": "Retail",
        "subcategory": "Portrait Studio",
        "type": "Services"
      }
    ],
    "sg:phone": "+1 419 255 9687",
    "sg:postcode": "43611",
    "sg:province": "OH",
    "sg:tags": [
      "photographer"
    ],
    "wof:name": "All Yours Wedding Photography",
    "wof:placetype": "venue"
  },
  "geometry": {"coordinates":[-83.476695,41.719844],"type":"Point"}
}
