{
  "type": "Feature",
  "properties": {
    "iso:country":"US",
    "sg:address":"5221 303rd St",
    "sg:city":"Toledo",
    "sg:classifiers":[
        {
            "category":"Retail",
            "subcategory":"Portrait Studio",
            "type":"Services"
        }
    ],
    "sg:phone":"+1 419 255 9687",
    "sg:postcode":"43611",
    "sg:province":"OH",
    "sg:tags":[
        "photographer"
    ],
    "wof:name":"All Yours Wedding Photography",
    "wof:placetype":"venue"
},
  "geometry": {"coordinates":[-83.47669500000001,41.719844],"type":"Point"}
}