{
  "type": "Feature",
  "properties": {
    "addr:full": "3392 S Columbus Rd Wooster OH 44691",
    "addr:housenumber": "3392",
    "addr:postcode": "44691",
    "addr:street": "S Columbus Rd",
    "iso:country": "US",
    "sg:address": "3392 S Columbus Rd",
    "sg:city": "Wooster",
    "sg:classifiers": [
      {
        "category": "Sports \u0026 Exercise",
        "subcategory": "Bowling",
        "type": "Entertainment"
      }
    ],
    "sg:phone": "+1 330 262 2451",
    "sg:postcode": "44691",
    "sg:province": "OH",
    "sg:tags": [
      "center"
    ],
    "wof:name": "Triway Lanes",
    "wof:placetype": "venue"
  },
  "geometry": {"coordinates":[-81.991709,40.758273],"type":"Point"}
}
