{
  "type": "Feature",
  "properties": {
    "iso:country":"US",
    "sg:address":"302 E Jefferson St",
    "sg:city":"Republic",
    "sg:classifiers":[
        {
            "category":"Restaurant",
            "type":"Food & Drink"
        }
    ],
    "sg:menulink":"http://www.allmenus.com/oh/scipio/193764-noble-romans/menu/",
    "sg:phone":"+1 419 585 2000",
    "sg:postcode":"44867",
    "sg:province":"OH",
    "sg:tags":[
        "wrap",
        "italian",
        "american",
        "sandwich",
        "pizza"
    ],
    "wof:name":"Noble Roman's",
    "wof:placetype":"venue"
},
  "geometry": {"coordinates":[-83.014672,41.124686],"type":"Point"}
}