{
  "type": "Feature",
  "properties": {
    "addr:full": "5777 Mink St Mount Vernon OH 43050",
    "addr:housenumber": "5777",
    "addr:postcode": "43050",
    "addr:street": "Mink St",
    "iso:country": "US",
    "sg:address": "5777 Mink St",
    "sg:city": "Mount Vernon",
    "sg:classifiers": [
      {
        "category": "Freight",
        "type": "Transportation"
      }
    ],
    "sg:phone": "+1 740 392 2884",
    "sg:postcode": "43050",
    "sg:province": "OH",
    "sg:tags": [
      "local",
      "provides",
      "trucking"
    ],
    "wof:name": "Peters Trucking Inc",
    "wof:placetype": "venue"
  },
  "geometry": {"coordinates":[-82.570975,40.315566],"type":"Point"}
}
