{
  "type": "Feature",
  "properties": {
    "iso:country":"US",
    "sg:address":"2100 Alum Creek Dr",
    "sg:city":"Columbus",
    "sg:classifiers":[
        {
            "category":"Government",
            "subcategory":"Office",
            "type":"Public Place"
        }
    ],
    "sg:phone":"+1 614 645 8027",
    "sg:postcode":"43207",
    "sg:province":"OH",
    "sg:tags":[
        "management"
    ],
    "wof:name":"Public Service Dept",
    "wof:placetype":"venue"
},
  "geometry": {"coordinates":[-82.93228999999999,39.921791],"type":"Point"}
}