{
  "type": "Feature",
  "properties": {
    "iso:country":"US",
    "sg:address":"8400 Mayfield Rd",
    "sg:city":"Chesterland",
    "sg:classifiers":[
        {
            "category":"Shopping",
            "type":"Retail Goods"
        }
    ],
    "sg:phone":"+1 440 729 7123",
    "sg:postcode":"44026",
    "sg:province":"OH",
    "sg:tags":[
        "art",
        "gallery",
        "dealer"
    ],
    "wof:name":"Sofia Art & Photography",
    "wof:placetype":"venue"
},
  "geometry": {"coordinates":[-81.337963,41.522138],"type":"Point"}
}