{
  "type": "Feature",
  "properties": {
    "iso:country":"US",
    "sg:address":"3600 Fisher Rd",
    "sg:city":"Columbus",
    "sg:classifiers":[
        {
            "category":"Professional",
            "subcategory":"Employment Agencies",
            "type":"Services"
        }
    ],
    "sg:phone":"+1 614 274 7480",
    "sg:postcode":"43228",
    "sg:province":"OH",
    "sg:tags":[
        "help",
        "contractor"
    ],
    "wof:name":"Resource Staffing Inc",
    "wof:placetype":"venue"
},
  "geometry": {"coordinates":[-83.099091,39.967223],"type":"Point"}
}