{
  "type": "Feature",
  "properties": {
    "addr:full":"1520 Bunker Hill Rd Ashtabula OH 44004",
    "addr:housenumber":"1520",
    "addr:postcode":"44004",
    "addr:street":"Bunker Hill Rd",
    "iso:country":"US",
    "sg:address":"1520 Bunker Hill Rd",
    "sg:city":"Ashtabula",
    "sg:classifiers":[
        {
            "category":"Retail",
            "subcategory":"Auto Rental",
            "type":"Services"
        }
    ],
    "sg:phone":"+1 440 992 7772",
    "sg:postcode":"44004",
    "sg:province":"OH",
    "sg:tags":[
        "renting",
        "automobile"
    ],
    "wof:name":"Rent-A-Wreck",
    "wof:placetype":"venue"
},
  "geometry": {"coordinates":[-80.79963100000001,41.848005],"type":"Point"}
}