{
  "type": "Feature",
  "properties": {
    "addr:full": "1516 Timken Rd Wooster OH 44691",
    "addr:housenumber": "1516",
    "addr:postcode": "44691",
    "addr:street": "Timken Rd",
    "iso:country": "US",
    "sg:address": "1516 Timken Rd",
    "sg:city": "Wooster",
    "sg:classifiers": [
      {
        "category": "Home \u0026 Garden",
        "subcategory": "Building Materials",
        "type": "Retail Goods"
      }
    ],
    "sg:phone": "+1 330 262 7383",
    "sg:postcode": "44691",
    "sg:province": "OH",
    "sg:tags": [
      "mixed",
      "concrete"
    ],
    "wof:name": "Quality Block \u0026 Supply",
    "wof:placetype": "venue"
  },
  "geometry": {"coordinates":[-81.938161,40.786206],"type":"Point"}
}
