{
  "type": "Feature",
  "properties": {
    "iso:country":"US",
    "sg:address":"1516 Timken Rd",
    "sg:city":"Wooster",
    "sg:classifiers":[
        {
            "category":"Home & Garden",
            "subcategory":"Building Materials",
            "type":"Retail Goods"
        }
    ],
    "sg:phone":"+1 330 262 7383",
    "sg:postcode":"44691",
    "sg:province":"OH",
    "sg:tags":[
        "mixed",
        "concrete"
    ],
    "wof:name":"Quality Block & Supply",
    "wof:placetype":"venue"
},
  "geometry": {"coordinates":[-81.93816099999999,40.786206],"type":"Point"}
}