{
  "type": "Feature",
  "properties": {
    "addr:full": "130 W Exchange St Akron OH 44302",
    "addr:housenumber": "130",
    "addr:postcode": "44302",
    "addr:street": "W Exchange St",
    "iso:country": "US",
    "sg:address": "130 W Exchange St",
    "sg:city": "Akron",
    "sg:classifiers": [
      {
        "category": "Professional",
        "type": "Services"
      }
    ],
    "sg:phone": "+1 330 376 1903",
    "sg:postcode": "44302",
    "sg:province": "OH",
    "wof:name": "Roger M Weiss Do",
    "wof:placetype": "venue"
  },
  "geometry": {"coordinates":[-81.525937,41.077906],"type":"Point"}
}
