{
  "type": "Feature",
  "properties": {
    "iso:country":"US",
    "sg:address":"20840 Southgate Park Blvd",
    "sg:city":"Cleveland",
    "sg:classifiers":[
        {
            "category":"Restaurant",
            "type":"Food & Drink"
        }
    ],
    "sg:phone":"+1 216 587 3367",
    "sg:postcode":"44137",
    "sg:province":"OH",
    "wof:name":"Mr B's Lounge & Restaurant",
    "wof:placetype":"venue"
},
  "geometry": {"coordinates":[-81.528339,41.413795],"type":"Point"}
}