{
  "type": "Feature",
  "properties": {
    "addr:full": "20840 Southgate Park Blvd Cleveland OH 44137",
    "addr:housenumber": "20840",
    "addr:postcode": "44137",
    "addr:street": "Southgate Park Blvd",
    "iso:country": "US",
    "sg:address": "20840 Southgate Park Blvd",
    "sg:city": "Cleveland",
    "sg:classifiers": [
      {
        "category": "Restaurant",
        "type": "Food \u0026 Drink"
      }
    ],
    "sg:phone": "+1 216 587 3367",
    "sg:postcode": "44137",
    "sg:province": "OH",
    "wof:name": "Mr B's Lounge \u0026 Restaurant",
    "wof:placetype": "venue"
  },
  "geometry": {"coordinates":[-81.528339,41.413795],"type":"Point"}
}
