{
  "type": "Feature",
  "properties": {
    "addr:full":"148 W Main St Cortland OH 44410",
    "addr:housenumber":"148",
    "addr:postcode":"44410",
    "addr:street":"W Main St",
    "iso:country":"US",
    "sg:address":"148 W Main St",
    "sg:city":"Cortland",
    "sg:classifiers":[
        {
            "category":"Health Services",
            "subcategory":"Chiropractor",
            "type":"Services"
        }
    ],
    "sg:phone":"+1 330 638 7310",
    "sg:postcode":"44410",
    "sg:province":"OH",
    "sg:tags":[
        "chiropractic"
    ],
    "sg:website":"http://www.thomasmontgomery.ie",
    "wof:name":"Dr Thomas Montgomery",
    "wof:placetype":"venue"
},
  "geometry": {"coordinates":[-80.72654,41.330101],"type":"Point"}
}