{
  "type": "Feature",
  "properties": {
    "addr:full": "538 E South St Akron OH 44311",
    "addr:housenumber": "538 e",
    "addr:postcode": "44311",
    "addr:street": "South St",
    "iso:country": "US",
    "sg:address": "538 E South St",
    "sg:city": "Akron",
    "sg:classifiers": [
      {
        "category": "Professional",
        "subcategory": "Engineering",
        "type": "Services"
      }
    ],
    "sg:phone": "+1 330 643 2850",
    "sg:postcode": "44311",
    "sg:province": "OH",
    "sg:tags": [
      "executive"
    ],
    "wof:name": "Dept of Engineering",
    "wof:placetype": "venue"
  },
  "geometry": {"coordinates":[-81.509006,41.06175],"type":"Point"}
}
