{
  "type": "Feature",
  "properties": {
    "addr:full": "921 12th St NE Canton OH 44703",
    "addr:housenumber": "921",
    "addr:postcode": "44703",
    "addr:street": "12Th St Ne",
    "iso:country": "US",
    "sg:address": "921 12th St NE",
    "sg:city": "Canton",
    "sg:classifiers": [
      {
        "category": "Building \u0026 Trades",
        "subcategory": "Cleaning \u0026 Sanitation",
        "type": "Services"
      }
    ],
    "sg:phone": "+1 330 455 4923",
    "sg:postcode": "44703",
    "sg:province": "OH",
    "sg:tags": [
      "janitor"
    ],
    "wof:name": "Holly's Super Cleaning",
    "wof:placetype": "venue"
  },
  "geometry": {"coordinates":[-81.38139,40.809441],"type":"Point"}
}
