{
  "type": "Feature",
  "properties": {
    "iso:country":"US",
    "sg:address":"2150 N Reynolds Rd",
    "sg:city":"Toledo",
    "sg:classifiers":[
        {
            "category":"Utilities",
            "subcategory":"Mobile Phone",
            "type":"Services"
        }
    ],
    "sg:phone":"+1 419 534 2100",
    "sg:postcode":"43615",
    "sg:province":"OH",
    "sg:tags":[
        "telephone",
        "cellular"
    ],
    "wof:name":"M & B Wireless",
    "wof:placetype":"venue"
},
  "geometry": {"coordinates":[-83.66759999999999,41.661181],"type":"Point"}
}