{
  "type": "Feature",
  "properties": {
    "addr:full": "2150 N Reynolds Rd Toledo OH 43615",
    "addr:housenumber": "2150",
    "addr:postcode": "43615",
    "addr:street": "N Reynolds Rd",
    "iso:country": "US",
    "sg:address": "2150 N Reynolds Rd",
    "sg:city": "Toledo",
    "sg:classifiers": [
      {
        "category": "Utilities",
        "subcategory": "Mobile Phone",
        "type": "Services"
      }
    ],
    "sg:phone": "+1 419 534 2100",
    "sg:postcode": "43615",
    "sg:province": "OH",
    "sg:tags": [
      "telephone",
      "cellular"
    ],
    "wof:name": "M \u0026 B Wireless",
    "wof:placetype": "venue"
  },
  "geometry": {"coordinates":[-83.6676,41.661181],"type":"Point"}
}
