{
  "type": "Feature",
  "properties": {
    "addr:full": "3640 Whiteoak Dr Cincinnati OH 45247",
    "addr:housenumber": "3640",
    "addr:postcode": "45247",
    "addr:street": "Whiteoak Dr",
    "iso:country": "US",
    "sg:address": "3640 Whiteoak Dr",
    "sg:city": "Cincinnati",
    "sg:classifiers": [
      {
        "category": "Manufacturing",
        "subcategory": "Food",
        "type": "Manufacturing \u0026 Wholesale Goods"
      }
    ],
    "sg:phone": "+1 513 861 0672",
    "sg:postcode": "45247",
    "sg:province": "OH",
    "sg:tags": [
      "bakery",
      "prod",
      "cookie"
    ],
    "wof:name": "Virginia Bakery",
    "wof:placetype": "venue"
  },
  "geometry": {"coordinates":[-84.60186,39.202864],"type":"Point"}
}
