{
  "type": "Feature",
  "properties": {
    "iso:country":"US",
    "sg:address":"4070 Silsby Rd",
    "sg:city":"Cleveland",
    "sg:classifiers":[
        {
            "category":"Shopping",
            "subcategory":"Clothing, Apparel, & Fashions",
            "type":"Retail Goods"
        }
    ],
    "sg:phone":"+1 216 320 1466",
    "sg:postcode":"44118",
    "sg:province":"OH",
    "sg:tags":[
        "item",
        "boutique"
    ],
    "wof:name":"Myrline's Klassic Boutique",
    "wof:placetype":"venue"
},
  "geometry": {"coordinates":[-81.533022,41.497779],"type":"Point"}
}