{
  "type": "Feature",
  "properties": {
    "addr:full":"202 S Main St Marion OH 43302",
    "addr:housenumber":"202",
    "addr:postcode":"43302",
    "addr:street":"S Main St",
    "iso:country":"US",
    "sg:address":"202 S Main St",
    "sg:city":"Marion",
    "sg:classifiers":[
        {
            "category":"Local Transit",
            "type":"Transportation"
        }
    ],
    "sg:phone":"+1 740 387 0386",
    "sg:postcode":"43302",
    "sg:province":"OH",
    "sg:tags":[
        "ambulance"
    ],
    "wof:name":"Rural/Metro",
    "wof:placetype":"venue"
},
  "geometry": {"coordinates":[-83.128638,40.58662],"type":"Point"}
}