{
  "type": "Feature",
  "properties": {
    "iso:country":"US",
    "sg:address":"39 S Mulberry St",
    "sg:city":"Chillicothe",
    "sg:classifiers":[
        {
            "category":"Organizations",
            "subcategory":"Religious Organization",
            "type":"Services"
        }
    ],
    "sg:phone":"+1 740 775 6149",
    "sg:postcode":"45601",
    "sg:province":"OH",
    "wof:name":"Salem Community Church",
    "wof:placetype":"venue"
},
  "geometry": {"coordinates":[-82.9787,39.332739],"type":"Point"}
}