{
  "type": "Feature",
  "properties": {
    "iso:country":"US",
    "sg:address":"6101 Saint Clair Ave",
    "sg:city":"Cleveland",
    "sg:classifiers":[
        {
            "category":"Autos & Motor Vehicles",
            "subcategory":"Fuel & Gas Station",
            "type":"Retail Goods"
        }
    ],
    "sg:phone":"+1 216 361 9140",
    "sg:postcode":"44103",
    "sg:province":"OH",
    "sg:tags":[
        "oil"
    ],
    "wof:name":"Turk's Service Station",
    "wof:placetype":"venue"
},
  "geometry": {"coordinates":[-81.648049,41.524017],"type":"Point"}
}