{
  "type": "Feature",
  "properties": {
    "addr:full": "6101 Saint Clair Ave Cleveland OH 44103",
    "addr:housenumber": "6101",
    "addr:postcode": "44103",
    "addr:street": "Saint Clair Ave",
    "iso:country": "US",
    "sg:address": "6101 Saint Clair Ave",
    "sg:city": "Cleveland",
    "sg:classifiers": [
      {
        "category": "Autos \u0026 Motor Vehicles",
        "subcategory": "Fuel \u0026 Gas Station",
        "type": "Retail Goods"
      }
    ],
    "sg:phone": "+1 216 361 9140",
    "sg:postcode": "44103",
    "sg:province": "OH",
    "sg:tags": [
      "oil"
    ],
    "wof:name": "Turk's Service Station",
    "wof:placetype": "venue"
  },
  "geometry": {"coordinates":[-81.648049,41.524017],"type":"Point"}
}
