{
  "type": "Feature",
  "properties": {
    "addr:full":"233 Ohio St Marietta OH 45750",
    "addr:housenumber":"233",
    "addr:postcode":"45750",
    "addr:street":"Ohio St",
    "iso:country":"US",
    "sg:address":"233 Ohio St",
    "sg:city":"Marietta",
    "sg:classifiers":[
        {
            "category":"Manufacturing",
            "subcategory":"Tools & Machinery",
            "type":"Manufacturing & Wholesale Goods"
        }
    ],
    "sg:phone":"+1 740 374 7325",
    "sg:postcode":"45750",
    "sg:province":"OH",
    "sg:tags":[
        "ind",
        "general"
    ],
    "wof:name":"Weinstock Welding & Repair Svc",
    "wof:placetype":"venue"
},
  "geometry": {"coordinates":[-81.448787,39.410977],"type":"Point"}
}