{
  "type": "Feature",
  "properties": {
    "addr:full":"10046 Brewster Ln Powell OH 43065",
    "addr:housenumber":"10046",
    "addr:postcode":"43065",
    "addr:street":"Brewster Ln",
    "iso:country":"US",
    "sg:address":"10046 Brewster Ln",
    "sg:city":"Powell",
    "sg:classifiers":[
        {
            "category":"Wholesale",
            "subcategory":"Furniture",
            "type":"Manufacturing & Wholesale Goods"
        }
    ],
    "sg:phone":"+1 614 923 4600",
    "sg:postcode":"43065",
    "sg:province":"OH",
    "sg:tags":[
        "equipment",
        "library",
        "supply"
    ],
    "sg:website":"www.librarydesign.com",
    "wof:name":"Library Design Assoc Inc",
    "wof:placetype":"venue"
},
  "geometry": {"coordinates":[-83.09413499999999,40.152598],"type":"Point"}
}