{
  "type": "Feature",
  "properties": {
    "addr:full":"1509 N Cable Rd Lima OH 45805",
    "addr:housenumber":"1509",
    "addr:postcode":"45805",
    "addr:street":"N Cable Rd",
    "iso:country":"US",
    "sg:address":"1509 N Cable Rd",
    "sg:city":"Lima",
    "sg:classifiers":[
        {
            "category":"Restaurant",
            "type":"Food & Drink"
        }
    ],
    "sg:menulink":"http://www.allmenus.com/oh/lima/79179-pizza-hut/menu/",
    "sg:phone":"+1 419 227 2233",
    "sg:postcode":"45805",
    "sg:province":"OH",
    "sg:tags":[
        "american",
        "pizza"
    ],
    "wof:name":"Pizza Hut",
    "wof:placetype":"venue"
},
  "geometry": {"coordinates":[-84.147063,40.759671],"type":"Point"}
}