{
  "type": "Feature",
  "properties": {
    "iso:country":"US",
    "sg:address":"1050 Plumrose Dr",
    "sg:city":"Columbus",
    "sg:classifiers":[
        {
            "category":"Real Estate",
            "subcategory":"Real Estate Operator",
            "type":"Services"
        }
    ],
    "sg:phone":"+1 614 878 2574",
    "sg:postcode":"43228",
    "sg:province":"OH",
    "sg:tags":[
        "apartment"
    ],
    "wof:name":"Plumwood Apartments",
    "wof:placetype":"venue"
},
  "geometry": {"coordinates":[-83.136883,39.930328],"type":"Point"}
}