{
  "type": "Feature",
  "properties": {
    "iso:country":"US",
    "sg:address":"421 Hill Rd N",
    "sg:city":"Pickerington",
    "sg:classifiers":[
        {
            "category":"Banks & Credit Unions",
            "subcategory":"Bank",
            "type":"Services"
        }
    ],
    "sg:phone":"+1 614 837 1996",
    "sg:postcode":"43147",
    "sg:province":"OH",
    "sg:tags":[
        "state",
        "commercial"
    ],
    "wof:name":"Fifth Third Bank",
    "wof:placetype":"venue"
},
  "geometry": {"coordinates":[-82.758522,39.890305],"type":"Point"}
}