{
  "type": "Feature",
  "properties": {
    "addr:full": "421 Hill Rd N Pickerington OH 43147",
    "addr:housenumber": "421",
    "addr:postcode": "43147",
    "addr:street": "Hill Rd N",
    "iso:country": "US",
    "sg:address": "421 Hill Rd N",
    "sg:city": "Pickerington",
    "sg:classifiers": [
      {
        "category": "Banks \u0026 Credit Unions",
        "subcategory": "Bank",
        "type": "Services"
      }
    ],
    "sg:phone": "+1 614 837 1996",
    "sg:postcode": "43147",
    "sg:province": "OH",
    "sg:tags": [
      "state",
      "commercial"
    ],
    "wof:name": "Fifth Third Bank",
    "wof:placetype": "venue"
  },
  "geometry": {"coordinates":[-82.758522,39.890305],"type":"Point"}
}
