{
  "type": "Feature",
  "properties": {
    "iso:country":"US",
    "sg:address":"3199 W 14th St",
    "sg:city":"Cleveland",
    "sg:classifiers":[
        {
            "category":"Real Estate",
            "subcategory":"Real Estate Operator",
            "type":"Services"
        }
    ],
    "sg:phone":"+1 216 621 2381",
    "sg:postcode":"44109",
    "sg:province":"OH",
    "sg:tags":[
        "building",
        "apartment"
    ],
    "wof:name":"CB Apartment LLC",
    "wof:placetype":"venue"
},
  "geometry": {"coordinates":[-81.691178,41.466065],"type":"Point"}
}