{
  "type": "Feature",
  "properties": {
    "iso:country":"US",
    "sg:address":"14 Hiawatha Trl",
    "sg:city":"Springboro",
    "sg:classifiers":[
        {
            "category":"Shopping",
            "subcategory":"Computers & Home Electronics",
            "type":"Retail Goods"
        }
    ],
    "sg:phone":"+1 937 746 2121",
    "sg:postcode":"45066",
    "sg:province":"OH",
    "wof:name":"Radio Shack",
    "wof:placetype":"venue"
},
  "geometry": {"coordinates":[-84.257341,39.563555],"type":"Point"}
}