{
  "type": "Feature",
  "properties": {
    "addr:full": "7420 Industrial Pkwy Dr Lorain OH 44053",
    "addr:housenumber": "7420",
    "addr:postcode": "44053",
    "addr:street": "Industrial Pkwy Dr",
    "iso:country": "US",
    "sg:address": "7420 Industrial Pkwy Dr",
    "sg:city": "Lorain",
    "sg:classifiers": [
      {
        "category": "Wholesale",
        "subcategory": "Machinery \u0026 Supplies",
        "type": "Manufacturing \u0026 Wholesale Goods"
      }
    ],
    "sg:phone": "+1 440 960 6911",
    "sg:postcode": "44053",
    "sg:province": "OH",
    "sg:tags": [
      "machine",
      "tool",
      "industrial",
      "metalworking"
    ],
    "wof:name": "Absolute Machine Tools Inc",
    "wof:placetype": "venue"
  },
  "geometry": {"coordinates":[-82.276767,41.408922],"type":"Point"}
}
