{
  "type": "Feature",
  "properties": {
    "iso:country":"US",
    "sg:address":"7420 Industrial Pkwy Dr",
    "sg:city":"Lorain",
    "sg:classifiers":[
        {
            "category":"Wholesale",
            "subcategory":"Machinery & Supplies",
            "type":"Manufacturing & Wholesale Goods"
        }
    ],
    "sg:phone":"+1 440 960 6911",
    "sg:postcode":"44053",
    "sg:province":"OH",
    "sg:tags":[
        "machine",
        "tool",
        "industrial",
        "metalworking"
    ],
    "wof:name":"Absolute Machine Tools Inc",
    "wof:placetype":"venue"
},
  "geometry": {"coordinates":[-82.27676700000001,41.408922],"type":"Point"}
}