{
  "type": "Feature",
  "properties": {
    "addr:full": "12036 Spencerville-Delphos Rd Delphos OH 45833",
    "addr:housenumber": "12036",
    "addr:postcode": "45833",
    "addr:street": "Spencerville-Delphos Rd",
    "iso:country": "US",
    "sg:address": "12036 Spencerville-Delphos Rd",
    "sg:city": "Delphos",
    "sg:classifiers": [
      {
        "category": "Building \u0026 Trades",
        "subcategory": "Construction",
        "type": "Services"
      }
    ],
    "sg:phone": "+1 419 695 1689",
    "sg:postcode": "45833",
    "sg:province": "OH",
    "sg:tags": [
      "residential",
      "commercial"
    ],
    "wof:name": "Kaverman Construction",
    "wof:placetype": "venue"
  },
  "geometry": {"coordinates":[-84.359452,40.829926],"type":"Point"}
}
