{
  "type": "Feature",
  "properties": {
    "iso:country":"US",
    "sg:address":"4154 W Broad St",
    "sg:city":"Columbus",
    "sg:classifiers":[
        {
            "category":"Banks & Credit Unions",
            "subcategory":"Bank",
            "type":"Services"
        }
    ],
    "sg:phone":"+1 614 279 6500",
    "sg:postcode":"43204",
    "sg:province":"OH",
    "sg:tags":[
        "cashing",
        "check"
    ],
    "wof:name":"Advance Pay USA",
    "wof:placetype":"venue"
},
  "geometry": {"coordinates":[-83.110263,39.953134],"type":"Point"}
}