{
  "type": "Feature",
  "properties": {
    "iso:country":"US",
    "sg:address":"559 E Mound St",
    "sg:city":"Circleville",
    "sg:classifiers":[
        {
            "category":"Home & Garden",
            "subcategory":"Household Appliances",
            "type":"Retail Goods"
        }
    ],
    "sg:phone":"+1 740 474 1123",
    "sg:postcode":"43113",
    "sg:province":"OH",
    "sg:tags":[
        "cleaners",
        "vacuum"
    ],
    "wof:name":"Hydro Tech Cleaning Systems",
    "wof:placetype":"venue"
},
  "geometry": {"coordinates":[-82.935648,39.59652],"type":"Point"}
}