{
  "type": "Feature",
  "properties": {
    "addr:full": "4141 Colonel Glenn Hwy Dayton OH 45431",
    "addr:housenumber": "4141",
    "addr:postcode": "45431",
    "addr:street": "Colonel Glenn Hwy",
    "iso:country": "US",
    "sg:address": "4141 Colonel Glenn Hwy",
    "sg:city": "Dayton",
    "sg:classifiers": [
      {
        "category": "Banks \u0026 Credit Unions",
        "subcategory": "Investment Brokerage",
        "type": "Services"
      },
      {
        "category": "Insurance",
        "subcategory": "Insurance Agent",
        "type": "Services"
      }
    ],
    "sg:phone": "+1 937 429 4490",
    "sg:postcode": "45431",
    "sg:province": "OH",
    "sg:tags": [
      "consulting",
      "management",
      "financial",
      "consultant",
      "planning",
      "security"
    ],
    "wof:name": "First Command Financial Plan",
    "wof:placetype": "venue"
  },
  "geometry": {"coordinates":[-84.087578,39.773348],"type":"Point"}
}
