{
  "type": "Feature",
  "properties": {
    "addr:full":"1366 Rockefeller Rd Wickliffe OH 44092",
    "addr:housenumber":"1366",
    "addr:postcode":"44092",
    "addr:street":"Rockefeller Rd",
    "iso:country":"US",
    "sg:address":"1366 Rockefeller Rd",
    "sg:city":"Wickliffe",
    "sg:classifiers":[
        {
            "category":"Wholesale",
            "subcategory":"Stationery",
            "type":"Manufacturing & Wholesale Goods"
        }
    ],
    "sg:phone":"+1 440 347 9527",
    "sg:postcode":"44092",
    "sg:province":"OH",
    "sg:tags":[
        "product",
        "paper"
    ],
    "sg:website":"www.clarkproducts.com",
    "wof:name":"Clark Products Inc",
    "wof:placetype":"venue"
},
  "geometry": {"coordinates":[-81.475323,41.610245],"type":"Point"}
}