{
  "type": "Feature",
  "properties": {
    "addr:full":"5700 Lombardo Center Cleveland OH 44131",
    "addr:postcode":"5700;44131",
    "addr:street":"Cleveland",
    "iso:country":"US",
    "sg:address":"5700 Lombardo Center",
    "sg:city":"Cleveland",
    "sg:classifiers":[
        {
            "category":"Shopping",
            "type":"Retail Goods"
        }
    ],
    "sg:phone":"+1 216 643 7008",
    "sg:postcode":"44131",
    "sg:province":"OH",
    "sg:tags":[
        "merchandise"
    ],
    "wof:name":"Southwestern Bell Telephone LP",
    "wof:placetype":"venue"
},
  "geometry": {"coordinates":[-81.66324,41.400737],"type":"Point"}
}