{
  "type": "Feature",
  "properties": {
    "addr:full": "5553 High Arbor Dr Galloway OH 43119",
    "addr:housenumber": "5553",
    "addr:postcode": "43119",
    "addr:street": "High Arbor Dr",
    "iso:country": "US",
    "sg:address": "5553 High Arbor Dr",
    "sg:city": "Galloway",
    "sg:classifiers": [
      {
        "category": "Building \u0026 Trades",
        "subcategory": "Construction",
        "type": "Services"
      }
    ],
    "sg:phone": "+1 614 679 2509",
    "sg:postcode": "43119",
    "sg:province": "OH",
    "sg:tags": [
      "residential"
    ],
    "wof:name": "Lyons",
    "wof:placetype": "venue"
  },
  "geometry": {"coordinates":[-83.146747,39.944938],"type":"Point"}
}
