{
  "type": "Feature",
  "properties": {
    "iso:country":"US",
    "sg:address":"3408 State Rte 131",
    "sg:city":"Blanchester",
    "sg:phone":"+1 937 783 4920",
    "sg:postcode":"45133",
    "sg:province":"OH",
    "sg:tags":[
        "farm",
        "corn",
        "soybean"
    ],
    "wof:name":"Stahl Farms",
    "wof:placetype":"venue"
},
  "geometry": {"coordinates":[-83.752208,39.141415],"type":"Point"}
}