{
  "type": "Feature",
  "properties": {
    "addr:full": "13710 Cleveland Ave NW Uniontown OH 44685",
    "addr:housenumber": "13710",
    "addr:postcode": "44685",
    "addr:street": "Cleveland Ave Nw",
    "iso:country": "US",
    "sg:address": "13710 Cleveland Ave NW",
    "sg:city": "Uniontown",
    "sg:classifiers": [
      {
        "category": "Building \u0026 Trades",
        "subcategory": "Construction",
        "type": "Services"
      }
    ],
    "sg:phone": "+1 330 699 9430",
    "sg:postcode": "44685",
    "sg:province": "OH",
    "sg:tags": [
      "general",
      "contractor"
    ],
    "wof:name": "W S Design \u0026 Development Co",
    "wof:placetype": "venue"
  },
  "geometry": {"coordinates":[-81.406518,40.981128],"type":"Point"}
}
