{
  "type": "Feature",
  "properties": {
    "iso:country":"US",
    "sg:address":"13710 Cleveland Ave NW",
    "sg:city":"Uniontown",
    "sg:classifiers":[
        {
            "category":"Building & Trades",
            "subcategory":"Construction",
            "type":"Services"
        }
    ],
    "sg:phone":"+1 330 699 9430",
    "sg:postcode":"44685",
    "sg:province":"OH",
    "sg:tags":[
        "general",
        "contractor"
    ],
    "wof:name":"W S Design & Development Co",
    "wof:placetype":"venue"
},
  "geometry": {"coordinates":[-81.40651800000001,40.981128],"type":"Point"}
}