{
  "type": "Feature",
  "properties": {
    "addr:full": "7317 State Rte 47 W De Graff OH 43318",
    "addr:housenumber": "7317",
    "addr:postcode": "43318",
    "addr:street": "State Rte 47 W De Graff",
    "iso:country": "US",
    "sg:address": "7317 State Rte 47 W",
    "sg:city": "De Graff",
    "sg:classifiers": [
      {
        "category": "Shopping",
        "subcategory": "Department Store",
        "type": "Retail Goods"
      }
    ],
    "sg:phone": "+1 937 585 5222",
    "sg:postcode": "43318",
    "sg:province": "OH",
    "wof:name": "Winners Harvest Barn",
    "wof:placetype": "venue"
  },
  "geometry": {"coordinates":[-83.894932,40.353882],"type":"Point"}
}
