{
  "type": "Feature",
  "properties": {
    "iso:country":"US",
    "sg:address":"6607 Market St",
    "sg:city":"Youngstown",
    "sg:classifiers":[
        {
            "category":"Retail",
            "subcategory":"Repair Shop",
            "type":"Services"
        }
    ],
    "sg:phone":"+1 330 726 3995",
    "sg:postcode":"44512",
    "sg:province":"OH",
    "sg:tags":[
        "stereo",
        "car",
        "television",
        "re",
        "radio",
        "cb"
    ],
    "wof:name":"Docs Radio-Auto Alarms",
    "wof:placetype":"venue"
},
  "geometry": {"coordinates":[-80.66267499999999,41.031152],"type":"Point"}
}