{
  "type": "Feature",
  "properties": {
    "addr:full": "4645 Paradise Rd Seville OH 44273",
    "addr:housenumber": "4645",
    "addr:postcode": "44273",
    "addr:street": "Paradise Rd",
    "iso:country": "US",
    "sg:address": "4645 Paradise Rd",
    "sg:city": "Seville",
    "sg:classifiers": [
      {
        "category": "Local Transit",
        "type": "Transportation"
      }
    ],
    "sg:phone": "+1 330 722 2585",
    "sg:postcode": "44273",
    "sg:province": "OH",
    "sg:tags": [
      "passenger"
    ],
    "wof:name": "Shield Mobility Service Inc",
    "wof:placetype": "venue"
  },
  "geometry": {"coordinates":[-81.855645,41.078196],"type":"Point"}
}
