{
  "type": "Feature",
  "properties": {
    "iso:country":"US",
    "sg:address":"4645 Paradise Rd",
    "sg:city":"Seville",
    "sg:classifiers":[
        {
            "category":"Local Transit",
            "type":"Transportation"
        }
    ],
    "sg:phone":"+1 330 722 2585",
    "sg:postcode":"44273",
    "sg:province":"OH",
    "sg:tags":[
        "passenger"
    ],
    "wof:name":"Shield Mobility Service Inc",
    "wof:placetype":"venue"
},
  "geometry": {"coordinates":[-81.855645,41.078196],"type":"Point"}
}