{
  "type": "Feature",
  "properties": {
    "iso:country":"US",
    "sg:address":"2945 Maple Ave",
    "sg:city":"Zanesville",
    "sg:classifiers":[
        {
            "category":"Health Services",
            "subcategory":"Doctor",
            "type":"Services"
        }
    ],
    "sg:phone":"+1 740 454 2273",
    "sg:postcode":"43701",
    "sg:province":"OH",
    "sg:tags":[
        "dr"
    ],
    "wof:name":"Allergy Department",
    "wof:placetype":"venue"
},
  "geometry": {"coordinates":[-82.014714,39.97594],"type":"Point"}
}