{
  "type": "Feature",
  "properties": {
    "iso:country":"US",
    "sg:address":"3757 Upper Bellbrook Rd",
    "sg:city":"Bellbrook",
    "sg:classifiers":[
        {
            "category":"Education",
            "subcategory":"School",
            "type":"Public Place"
        }
    ],
    "sg:phone":"+1 937 848 3827",
    "sg:postcode":"45305",
    "sg:province":"OH",
    "wof:name":"Medallion School Partnerships",
    "wof:placetype":"venue"
},
  "geometry": {"coordinates":[-84.069491,39.651959],"type":"Point"}
}