{
  "type": "Feature",
  "properties": {
    "addr:full": "3201 Enterprise Pkwy Cleveland OH 44122",
    "addr:housenumber": "3201",
    "addr:postcode": "44122",
    "addr:street": "Enterprise Pkwy",
    "iso:country": "US",
    "sg:address": "3201 Enterprise Pkwy",
    "sg:city": "Cleveland",
    "sg:classifiers": [
      {
        "category": "Wholesale",
        "subcategory": "Machinery \u0026 Supplies",
        "type": "Manufacturing \u0026 Wholesale Goods"
      }
    ],
    "sg:phone": "+1 216 831 0560",
    "sg:postcode": "44122",
    "sg:province": "OH",
    "wof:name": "Metalworking Intl",
    "wof:placetype": "venue"
  },
  "geometry": {"coordinates":[-81.494658,41.470563],"type":"Point"}
}
