{
  "type": "Feature",
  "properties": {
    "iso:country":"US",
    "sg:address":"3201 Enterprise Pkwy",
    "sg:city":"Cleveland",
    "sg:classifiers":[
        {
            "category":"Wholesale",
            "subcategory":"Machinery & Supplies",
            "type":"Manufacturing & Wholesale Goods"
        }
    ],
    "sg:phone":"+1 216 831 0560",
    "sg:postcode":"44122",
    "sg:province":"OH",
    "wof:name":"Metalworking Intl",
    "wof:placetype":"venue"
},
  "geometry": {"coordinates":[-81.494658,41.470563],"type":"Point"}
}