{
  "type": "Feature",
  "properties": {
    "iso:country":"US",
    "sg:address":"2158 Tremont Center",
    "sg:city":"Columbus",
    "sg:classifiers":[
        {
            "category":"Shopping",
            "type":"Retail Goods"
        },
        {
            "category":"Shopping",
            "subcategory":"Gifts & Souvenirs",
            "type":"Retail Goods"
        }
    ],
    "sg:phone":"+1 614 486 6387",
    "sg:postcode":"43221",
    "sg:province":"OH",
    "sg:tags":[
        "cards",
        "sport",
        "baseball",
        "memorabilia"
    ],
    "wof:name":"Chuck & Barb's Baseball Cards",
    "wof:placetype":"venue"
},
  "geometry": {"coordinates":[-83.068099,40.014422],"type":"Point"}
}