{
  "type": "Feature",
  "properties": {
    "addr:full": "2158 Tremont Center Columbus OH 43221",
    "addr:housenumber": "2158",
    "addr:postcode": "43221",
    "addr:street": "Tremont Center",
    "iso:country": "US",
    "sg:address": "2158 Tremont Center",
    "sg:city": "Columbus",
    "sg:classifiers": [
      {
        "category": "Shopping",
        "type": "Retail Goods"
      },
      {
        "category": "Shopping",
        "subcategory": "Gifts \u0026 Souvenirs",
        "type": "Retail Goods"
      }
    ],
    "sg:phone": "+1 614 486 6387",
    "sg:postcode": "43221",
    "sg:province": "OH",
    "sg:tags": [
      "cards",
      "sport",
      "baseball",
      "memorabilia"
    ],
    "wof:name": "Chuck \u0026 Barb's Baseball Cards",
    "wof:placetype": "venue"
  },
  "geometry": {"coordinates":[-83.068099,40.014422],"type":"Point"}
}
