{
  "type": "Feature",
  "properties": {
    "iso:country":"US",
    "sg:address":"1966 McAllister Ave",
    "sg:city":"Columbus",
    "sg:classifiers":[
        {
            "category":"Retail",
            "subcategory":"Auto Repair",
            "type":"Services"
        }
    ],
    "sg:phone":"+1 614 252 0626",
    "sg:postcode":"43205",
    "sg:province":"OH",
    "sg:tags":[
        "repairing",
        "automobile"
    ],
    "wof:name":"Penington's Auto Svc",
    "wof:placetype":"venue"
},
  "geometry": {"coordinates":[-82.945909,39.956616],"type":"Point"}
}