{
  "type": "Feature",
  "properties": {
    "addr:full":"3449 Lefevre Rd Troy OH 45373",
    "addr:housenumber":"3449",
    "addr:postcode":"45373",
    "addr:street":"Lefevre Rd",
    "iso:country":"US",
    "sg:address":"3449 Lefevre Rd",
    "sg:city":"Troy",
    "sg:classifiers":[
        {
            "category":"Organizations",
            "subcategory":"Community Association",
            "type":"Services"
        }
    ],
    "sg:phone":"+1 937 339 0700",
    "sg:postcode":"45373",
    "sg:province":"OH",
    "sg:tags":[
        "club"
    ],
    "wof:name":"Amvets Post 88",
    "wof:placetype":"venue"
},
  "geometry": {"coordinates":[-84.139652,40.033213],"type":"Point"}
}