{
  "type": "Feature",
  "properties": {
    "iso:country":"US",
    "sg:address":"2300 Rte 40",
    "sg:city":"Tipp City",
    "sg:classifiers":[
        {
            "category":"Social Services",
            "subcategory":"Job Training",
            "type":"Services"
        }
    ],
    "sg:phone":"+1 937 890 0470",
    "sg:postcode":"45371",
    "sg:province":"OH",
    "sg:tags":[
        "retardation",
        "disabled",
        "mental",
        "dev"
    ],
    "wof:name":"Miami County Residential Inc",
    "wof:placetype":"venue"
},
  "geometry": {"coordinates":[-84.15414,39.887637],"type":"Point"}
}