{
  "type": "Feature",
  "properties": {
    "addr:full": "329 Liberty St Dillonvale OH 43917",
    "addr:housenumber": "329",
    "addr:postcode": "43917",
    "addr:street": "Liberty St",
    "iso:country": "US",
    "sg:address": "329 Liberty St",
    "sg:city": "Dillonvale",
    "sg:classifiers": [
      {
        "category": "Autos \u0026 Motor Vehicles",
        "subcategory": "Auto Supplies",
        "type": "Retail Goods"
      }
    ],
    "sg:phone": "+1 740 769 7504",
    "sg:postcode": "43917",
    "sg:province": "OH",
    "sg:tags": [
      "automobile",
      "parts"
    ],
    "wof:name": "Dillon Auto Parts",
    "wof:placetype": "venue"
  },
  "geometry": {"coordinates":[-80.779854,40.191897],"type":"Point"}
}
