{
  "type": "Feature",
  "properties": {
    "addr:full":"708 S Pennsylvania Ave Wellston OH 45692",
    "addr:housenumber":"708",
    "addr:postcode":"45692",
    "addr:street":"S Pennsylvania Ave",
    "iso:country":"US",
    "sg:address":"708 S Pennsylvania Ave",
    "sg:city":"Wellston",
    "sg:classifiers":[
        {
            "category":"Restaurant",
            "type":"Food & Drink"
        }
    ],
    "sg:menulink":"http://www.allmenus.com/oh/wellston/134778-subway/menu/",
    "sg:phone":"+1 740 384 6342",
    "sg:postcode":"45692",
    "sg:province":"OH",
    "sg:tags":[
        "american",
        "sandwich"
    ],
    "wof:name":"Subway",
    "wof:placetype":"venue"
},
  "geometry": {"coordinates":[-82.533602,39.117785],"type":"Point"}
}