{
  "type": "Feature",
  "properties": {
    "addr:full":"1959 Easton St NW North Canton OH 44720",
    "addr:housenumber":"1959",
    "addr:postcode":"44720",
    "addr:street":"Easton St Nw",
    "iso:country":"US",
    "sg:address":"1959 Easton St NW",
    "sg:city":"North Canton",
    "sg:classifiers":[
        {
            "category":"Education",
            "subcategory":"School",
            "type":"Public Place"
        }
    ],
    "sg:phone":"+1 330 497 0842",
    "sg:postcode":"44720",
    "sg:province":"OH",
    "sg:tags":[
        "academic",
        "special"
    ],
    "wof:name":"Sylvan Learning Ctr",
    "wof:placetype":"venue"
},
  "geometry": {"coordinates":[-81.367918,40.875138],"type":"Point"}
}