{
  "type": "Feature",
  "properties": {
    "addr:full":"46 Alpha Park Cleveland OH 44143",
    "addr:housenumber":"46",
    "addr:postcode":"44143",
    "addr:street":"Alpha",
    "iso:country":"US",
    "sg:address":"46 Alpha Park",
    "sg:city":"Cleveland",
    "sg:classifiers":[
        {
            "category":"Banks & Credit Unions",
            "subcategory":"Bank",
            "type":"Services"
        }
    ],
    "sg:phone":"+1 440 443 9995",
    "sg:postcode":"44143",
    "sg:province":"OH",
    "sg:tags":[
        "loan",
        "real estate"
    ],
    "wof:name":"Premier Mortgage",
    "wof:placetype":"venue"
},
  "geometry": {"coordinates":[-81.45137699999999,41.553349],"type":"Point"}
}