{
  "type": "Feature",
  "properties": {
    "iso:country":"US",
    "sg:address":"2383 S Main St",
    "sg:city":"Akron",
    "sg:classifiers":[
        {
            "category":"Shopping",
            "subcategory":"Computers & Home Electronics",
            "type":"Retail Goods"
        }
    ],
    "sg:phone":"+1 330 724 9422",
    "sg:postcode":"44319",
    "sg:province":"OH",
    "sg:tags":[
        "equipment",
        "dealer"
    ],
    "wof:name":"Innovative Computers",
    "wof:placetype":"venue"
},
  "geometry": {"coordinates":[-81.526303,41.022291],"type":"Point"}
}