{
  "type": "Feature",
  "properties": {
    "addr:full": "2383 S Main St Akron OH 44319",
    "addr:housenumber": "2383",
    "addr:postcode": "44319",
    "addr:street": "S Main St",
    "iso:country": "US",
    "sg:address": "2383 S Main St",
    "sg:city": "Akron",
    "sg:classifiers": [
      {
        "category": "Shopping",
        "subcategory": "Computers \u0026 Home Electronics",
        "type": "Retail Goods"
      }
    ],
    "sg:phone": "+1 330 724 9422",
    "sg:postcode": "44319",
    "sg:province": "OH",
    "sg:tags": [
      "equipment",
      "dealer"
    ],
    "wof:name": "Innovative Computers",
    "wof:placetype": "venue"
  },
  "geometry": {"coordinates":[-81.526303,41.022291],"type":"Point"}
}
