{
  "type": "Feature",
  "properties": {
    "addr:full":"5600 Lehman Rd Delphos OH 45833",
    "addr:housenumber":"5600",
    "addr:postcode":"45833",
    "addr:street":"Lehman Rd",
    "iso:country":"US",
    "sg:address":"5600 Lehman Rd",
    "sg:city":"Delphos",
    "sg:classifiers":[
        {
            "category":"Farming",
            "subcategory":"Livestock Farm",
            "type":"Manufacturing & Wholesale Goods"
        }
    ],
    "sg:phone":"+1 419 692 8132",
    "sg:postcode":"45833",
    "sg:province":"OH",
    "sg:tags":[
        "beef",
        "feedlot",
        "cattle"
    ],
    "wof:name":"Eugene Gable",
    "wof:placetype":"venue"
},
  "geometry": {"coordinates":[-84.310518,40.816337],"type":"Point"}
}