{
  "type": "Feature",
  "properties": {
    "iso:country":"US",
    "sg:address":"1129 Niles Rd SE",
    "sg:city":"Warren",
    "sg:classifiers":[
        {
            "category":"Real Estate",
            "subcategory":"Developer",
            "type":"Services"
        }
    ],
    "sg:phone":"+1 330 609 9992",
    "sg:postcode":"44484",
    "sg:province":"OH",
    "wof:name":"TLD Development",
    "wof:placetype":"venue"
},
  "geometry": {"coordinates":[-80.803962,41.230028],"type":"Point"}
}