{
  "type": "Feature",
  "properties": {
    "addr:full": "201 North St Caldwell OH 43724",
    "addr:housenumber": "201",
    "addr:postcode": "43724",
    "addr:street": "North St",
    "iso:country": "US",
    "sg:address": "201 North St",
    "sg:city": "Caldwell",
    "sg:classifiers": [
      {
        "category": "Education",
        "subcategory": "Special Training",
        "type": "Public Place"
      }
    ],
    "sg:phone": "+1 740 732 5056",
    "sg:postcode": "43724",
    "sg:province": "OH",
    "sg:tags": [
      "instruction",
      "music"
    ],
    "wof:name": "Hines \u0026 Hines",
    "wof:placetype": "venue"
  },
  "geometry": {"coordinates":[-81.514433,39.74769],"type":"Point"}
}
