{
  "type": "Feature",
  "properties": {
    "addr:full":"32607 Electric Blvd Avon Lake OH 44012",
    "addr:housenumber":"32607",
    "addr:postcode":"44012",
    "addr:street":"Electric Blvd",
    "iso:country":"US",
    "sg:address":"32607 Electric Blvd",
    "sg:city":"Avon Lake",
    "sg:classifiers":[
        {
            "category":"Organizations",
            "subcategory":"Religious Organization",
            "type":"Services"
        }
    ],
    "sg:phone":"+1 440 933 8828",
    "sg:postcode":"44012",
    "sg:province":"OH",
    "sg:tags":[
        "church"
    ],
    "sg:website":"www.cbcavonlake.org",
    "wof:name":"Calvary Baptist Church",
    "wof:placetype":"venue"
},
  "geometry": {"coordinates":[-82.011382,41.510415],"type":"Point"}
}