{
  "type": "Feature",
  "properties": {
    "iso:country":"US",
    "sg:address":"417 Wayne Ave",
    "sg:city":"Defiance",
    "sg:classifiers":[
        {
            "category":"Shopping",
            "subcategory":"Computers & Home Electronics",
            "type":"Retail Goods"
        }
    ],
    "sg:phone":"+1 419 782 3472",
    "sg:postcode":"43512",
    "sg:province":"OH",
    "sg:tags":[
        "equipment",
        "dealer"
    ],
    "sg:website":"www.metalink.net",
    "wof:name":"Metalink Technologies",
    "wof:placetype":"venue"
},
  "geometry": {"coordinates":[-84.361481,41.28515],"type":"Point"}
}