{
  "type": "Feature",
  "properties": {
    "addr:full": "113 N Ohio Ave Sidney OH 45365",
    "addr:housenumber": "113",
    "addr:postcode": "45365",
    "addr:street": "N Ohio Ave",
    "iso:country": "US",
    "sg:address": "113 N Ohio Ave",
    "sg:city": "Sidney",
    "sg:classifiers": [
      {
        "category": "Social Services",
        "type": "Services"
      }
    ],
    "sg:phone": "+1 937 492 6404",
    "sg:postcode": "45365",
    "sg:province": "OH",
    "sg:tags": [
      "counseling"
    ],
    "wof:name": "Debby Smith \u0026 Assoc LLC",
    "wof:placetype": "venue"
  },
  "geometry": {"coordinates":[-84.156788,40.286698],"type":"Point"}
}
