{
  "type": "Feature",
  "properties": {
    "addr:full":"2001 Ford Cir Milford OH 45150",
    "addr:housenumber":"2001",
    "addr:postcode":"45150",
    "addr:street":"Ford Cir",
    "iso:country":"US",
    "sg:address":"2001 Ford Cir",
    "sg:city":"Milford",
    "sg:classifiers":[
        {
            "category":"Wholesale",
            "subcategory":"Machinery & Supplies",
            "type":"Manufacturing & Wholesale Goods"
        },
        {
            "category":"Manufacturing",
            "subcategory":"Tools & Machinery",
            "type":"Manufacturing & Wholesale Goods"
        }
    ],
    "sg:phone":"+1 513 831 3877",
    "sg:postcode":"45150",
    "sg:province":"OH",
    "sg:tags":[
        "technical",
        "support",
        "sales",
        "equipment",
        "safety",
        "clothing"
    ],
    "sg:website":"www.crowcon.com",
    "wof:name":"Crowcon Detection Instruments",
    "wof:placetype":"venue"
},
  "geometry": {"coordinates":[-84.25117400000001,39.154652],"type":"Point"}
}