{
  "type": "Feature",
  "properties": {
    "addr:full": "30825 Aurora Rd Solon OH 44139",
    "addr:housenumber": "30825",
    "addr:postcode": "44139",
    "addr:street": "Aurora Rd",
    "iso:country": "US",
    "sg:address": "30825 Aurora Rd",
    "sg:city": "Solon",
    "sg:classifiers": [
      {
        "category": "Professional",
        "subcategory": "Accounting \u0026 Tax Preparation",
        "type": "Services"
      }
    ],
    "sg:phone": "+1 440 914 1213",
    "sg:postcode": "44139",
    "sg:province": "OH",
    "wof:name": "Paychex Inc",
    "wof:placetype": "venue"
  },
  "geometry": {"coordinates":[-81.465987,41.397468],"type":"Point"}
}
