{
  "type": "Feature",
  "properties": {
    "iso:country":"US",
    "sg:address":"306 Forest Ave",
    "sg:city":"Cincinnati",
    "sg:classifiers":[
        {
            "category":"Taxi",
            "type":"Transportation"
        }
    ],
    "sg:phone":"+1 513 861 1371",
    "sg:postcode":"45229",
    "sg:province":"OH",
    "wof:name":"Moores Taxi",
    "wof:placetype":"venue"
},
  "geometry": {"coordinates":[-84.502319,39.146397],"type":"Point"}
}