{
  "type": "Feature",
  "properties": {
    "iso:country":"US",
    "sg:address":"421 W Main St",
    "sg:city":"Woodville",
    "sg:classifiers":[
        {
            "category":"Personal",
            "type":"Services"
        }
    ],
    "sg:phone":"+1 419 849 2227",
    "sg:postcode":"43469",
    "sg:province":"OH",
    "sg:tags":[
        "therapist",
        "massage"
    ],
    "wof:name":"Natural Health Ctr-Woodville",
    "wof:placetype":"venue"
},
  "geometry": {"coordinates":[-83.367147,41.452036],"type":"Point"}
}