{
  "type": "Feature",
  "properties": {
    "addr:full":"21613 Smith Hulse Rd Circleville OH 43113",
    "addr:housenumber":"21613",
    "addr:postcode":"43113",
    "addr:street":"Smith Hulse Rd",
    "iso:country":"US",
    "sg:address":"21613 Smith Hulse Rd",
    "sg:city":"Circleville",
    "sg:classifiers":[
        {
            "category":"Real Estate",
            "subcategory":"Real Estate Operator",
            "type":"Services"
        }
    ],
    "sg:phone":"+1 740 474 7276",
    "sg:postcode":"43113",
    "sg:province":"OH",
    "sg:tags":[
        "property",
        "lessor"
    ],
    "wof:name":"Rolling H Farm",
    "wof:placetype":"venue"
},
  "geometry": {"coordinates":[-83.050521,39.618869],"type":"Point"}
}