{
  "type": "Feature",
  "properties": {
    "iso:country":"US",
    "sg:address":"3410 Glenmore Ave",
    "sg:city":"Cincinnati",
    "sg:classifiers":[
        {
            "category":"Personal",
            "subcategory":"Shoe Repair & Shine",
            "type":"Services"
        }
    ],
    "sg:phone":"+1 513 662 6007",
    "sg:postcode":"45211",
    "sg:province":"OH",
    "sg:tags":[
        "repairing",
        "parlor",
        "boot",
        "shoes"
    ],
    "wof:name":"Lands Shoe Repair",
    "wof:placetype":"venue"
},
  "geometry": {"coordinates":[-84.61268699999999,39.149514],"type":"Point"}
}