{
  "type": "Feature",
  "properties": {
    "iso:country":"US",
    "sg:address":"7597 Broadmoor Rd",
    "sg:city":"Perrysburg",
    "sg:classifiers":[
        {
            "category":"Manufacturing",
            "subcategory":"Retail Goods",
            "type":"Manufacturing & Wholesale Goods"
        }
    ],
    "sg:phone":"+1 419 662 5001",
    "sg:postcode":"43551",
    "sg:province":"OH",
    "sg:tags":[
        "manufacturer"
    ],
    "wof:name":"Aluminite Of Ohio Inc",
    "wof:placetype":"venue"
},
  "geometry": {"coordinates":[-83.538073,41.558397],"type":"Point"}
}