{
  "type": "Feature",
  "properties": {
    "iso:country":"US",
    "sg:address":"7204 Claasen Ave",
    "sg:city":"Cleveland",
    "sg:classifiers":[
        {
            "category":"Building & Trades",
            "subcategory":"Construction",
            "type":"Services"
        }
    ],
    "sg:phone":"+1 216 883 2178",
    "sg:postcode":"44105",
    "sg:province":"OH",
    "sg:tags":[
        "home",
        "improvement"
    ],
    "wof:name":"Specialty Services",
    "wof:placetype":"venue"
},
  "geometry": {"coordinates":[-81.638351,41.447128],"type":"Point"}
}