{
  "type": "Feature",
  "properties": {
    "addr:full": "2354 London Groveport Rd Grove City OH 43123",
    "addr:housenumber": "2354",
    "addr:postcode": "43123",
    "addr:street": "London Groveport Rd",
    "iso:country": "US",
    "sg:address": "2354 London Groveport Rd",
    "sg:city": "Grove City",
    "sg:classifiers": [
      {
        "category": "Shopping",
        "subcategory": "Bicycles \u0026 Sporting Goods",
        "type": "Retail Goods"
      }
    ],
    "sg:phone": "+1 614 871 8291",
    "sg:postcode": "43123",
    "sg:province": "OH",
    "sg:tags": [
      "repair"
    ],
    "wof:name": "Gunworks",
    "wof:placetype": "venue"
  },
  "geometry": {"coordinates":[-83.066648,39.836328],"type":"Point"}
}
