{
  "type": "Feature",
  "properties": {
    "addr:full": "3731 Isabella Ave Cincinnati OH 45209",
    "addr:housenumber": "3731",
    "addr:postcode": "45209",
    "addr:street": "Isabella Ave",
    "iso:country": "US",
    "sg:address": "3731 Isabella Ave",
    "sg:city": "Cincinnati",
    "sg:classifiers": [
      {
        "category": "Social Services",
        "subcategory": "Adult Care",
        "type": "Services"
      }
    ],
    "sg:phone": "+1 513 771 3322",
    "sg:postcode": "45209",
    "sg:province": "OH",
    "sg:tags": [
      "home",
      "group"
    ],
    "wof:name": "We-Care/Valley",
    "wof:placetype": "venue"
  },
  "geometry": {"coordinates":[-84.432771,39.146453],"type":"Point"}
}
