{
  "type": "Feature",
  "properties": {
    "addr:full": "15408 Madison Ave Cleveland OH 44107",
    "addr:housenumber": "15408",
    "addr:postcode": "44107",
    "addr:street": "Madison Ave",
    "iso:country": "US",
    "sg:address": "15408 Madison Ave",
    "sg:city": "Cleveland",
    "sg:classifiers": [
      {
        "category": "Recreation",
        "subcategory": "Arcade",
        "type": "Entertainment"
      }
    ],
    "sg:phone": "+1 216 221 5179",
    "sg:postcode": "44107",
    "sg:province": "OH",
    "sg:tags": [
      "casino"
    ],
    "wof:name": "Live Wire Gaming",
    "wof:placetype": "venue"
  },
  "geometry": {"coordinates":[-81.803753,41.477326],"type":"Point"}
}
