{
  "type": "Feature",
  "properties": {
    "iso:country":"US",
    "sg:address":"2114 Goshen Hill Rd SE",
    "sg:city":"New Philadelphia",
    "sg:classifiers":[
        {
            "category":"Building & Trades",
            "subcategory":"Plumbing",
            "type":"Services"
        }
    ],
    "sg:phone":"+1 330 339 2346",
    "sg:postcode":"44663",
    "sg:province":"OH",
    "sg:tags":[
        "contractor"
    ],
    "wof:name":"Garver Electric & Plumbing",
    "wof:placetype":"venue"
},
  "geometry": {"coordinates":[-81.429679,40.448998],"type":"Point"}
}