{
  "type": "Feature",
  "properties": {
    "addr:full": "2114 Goshen Hill Rd SE New Philadelphia OH 44663",
    "addr:housenumber": "2114",
    "addr:postcode": "44663",
    "addr:street": "Goshen Hill Rd Se New",
    "iso:country": "US",
    "sg:address": "2114 Goshen Hill Rd SE",
    "sg:city": "New Philadelphia",
    "sg:classifiers": [
      {
        "category": "Building \u0026 Trades",
        "subcategory": "Plumbing",
        "type": "Services"
      }
    ],
    "sg:phone": "+1 330 339 2346",
    "sg:postcode": "44663",
    "sg:province": "OH",
    "sg:tags": [
      "contractor"
    ],
    "wof:name": "Garver Electric \u0026 Plumbing",
    "wof:placetype": "venue"
  },
  "geometry": {"coordinates":[-81.429679,40.448998],"type":"Point"}
}
