{
  "type": "Feature",
  "properties": {
    "addr:full": "17 Court St Gallipolis OH 45631",
    "addr:housenumber": "17",
    "addr:postcode": "45631",
    "addr:street": "Court St",
    "iso:country": "US",
    "sg:address": "17 Court St",
    "sg:city": "Gallipolis",
    "sg:classifiers": [
      {
        "category": "Real Estate",
        "subcategory": "Real Estate Operator",
        "type": "Services"
      }
    ],
    "sg:phone": "+1 740 446 2381",
    "sg:postcode": "45631",
    "sg:province": "OH",
    "sg:tags": [
      "mobile",
      "home",
      "site",
      "community"
    ],
    "wof:name": "Green Terrace Mobile Home Comm",
    "wof:placetype": "venue"
  },
  "geometry": {"coordinates":[-82.20705,38.806148],"type":"Point"}
}
