{
  "type": "Feature",
  "properties": {
    "iso:country":"US",
    "sg:address":"7465 State Rte 366",
    "sg:city":"Huntsville",
    "sg:classifiers":[
        {
            "category":"Health Services",
            "subcategory":"Chiropractor",
            "type":"Services"
        }
    ],
    "sg:phone":"+1 937 843 5280",
    "sg:postcode":"43324",
    "sg:province":"OH",
    "wof:name":"Duane C Kreusch DC",
    "wof:placetype":"venue"
},
  "geometry": {"coordinates":[-83.857387,40.46981],"type":"Point"}
}