{
  "type": "Feature",
  "properties": {
    "addr:full":"4466 Free Pike Dayton OH 45416",
    "addr:housenumber":"4466",
    "addr:postcode":"45416",
    "addr:street":"Free Pike",
    "iso:country":"US",
    "sg:address":"4466 Free Pike",
    "sg:city":"Dayton",
    "sg:classifiers":[
        {
            "category":"Organizations",
            "subcategory":"Religious Organization",
            "type":"Services"
        }
    ],
    "sg:phone":"+1 937 275 5794",
    "sg:postcode":"45416",
    "sg:province":"OH",
    "sg:tags":[
        "church"
    ],
    "wof:name":"St Timothy Missionary Baptist",
    "wof:placetype":"venue"
},
  "geometry": {"coordinates":[-84.264319,39.797777],"type":"Point"}
}