{
  "type": "Feature",
  "properties": {
    "iso:country":"US",
    "sg:address":"182 High St NE",
    "sg:city":"Warren",
    "sg:classifiers":[
        {
            "category":"Real Estate",
            "subcategory":"Real Estate Operator",
            "type":"Services"
        }
    ],
    "sg:phone":"+1 330 394 4321",
    "sg:postcode":"44481",
    "sg:province":"OH",
    "sg:tags":[
        "building",
        "apartment"
    ],
    "wof:name":"Warner Housing Partnership",
    "wof:placetype":"venue"
},
  "geometry": {"coordinates":[-80.817369,41.237421],"type":"Point"}
}