{
  "type": "Feature",
  "properties": {
    "iso:country":"US",
    "sg:address":"5692 Far Hills Ave",
    "sg:city":"Dayton",
    "sg:classifiers":[
        {
            "category":"Health Services",
            "subcategory":"Doctor",
            "type":"Services"
        }
    ],
    "sg:phone":"+1 937 434 3916",
    "sg:postcode":"45429",
    "sg:province":"OH",
    "wof:name":"Smith G Richard DDS Inc",
    "wof:placetype":"venue"
},
  "geometry": {"coordinates":[-84.15773,39.659007],"type":"Point"}
}