{
  "type": "Feature",
  "properties": {
    "iso:country":"US",
    "sg:address":"2166 Riverside Dr",
    "sg:city":"Sidney",
    "sg:classifiers":[
        {
            "category":"Real Estate",
            "subcategory":"Real Estate Agent",
            "type":"Services"
        }
    ],
    "sg:phone":"+1 937 492 7264",
    "sg:postcode":"45365",
    "sg:province":"OH",
    "wof:name":"Jayne Watkins",
    "wof:placetype":"venue"
},
  "geometry": {"coordinates":[-84.129414,40.316643],"type":"Point"}
}