{
  "type": "Feature",
  "properties": {
    "addr:full": "2612 Ellet Ave Akron OH 44312",
    "addr:postcode": "2612;44312",
    "addr:street": "Ellet Ave",
    "iso:country": "US",
    "sg:address": "2612 Ellet Ave",
    "sg:city": "Akron",
    "sg:classifiers": [
      {
        "category": "Building \u0026 Trades",
        "subcategory": "Plumbing",
        "type": "Services"
      }
    ],
    "sg:phone": "+1 330 928 1603",
    "sg:postcode": "44312",
    "sg:province": "OH",
    "sg:tags": [
      "contractor"
    ],
    "wof:name": "Mikes Plumbing Inc",
    "wof:placetype": "venue"
  },
  "geometry": {"coordinates":[-81.435806,41.049485],"type":"Point"}
}
