{
  "type": "Feature",
  "properties": {
    "addr:full":"8220 Northcreek Dr Cincinnati OH 45236",
    "addr:postcode":"8220;45236",
    "addr:street":"Northcreek Dr",
    "iso:country":"US",
    "sg:address":"8220 Northcreek Dr",
    "sg:city":"Cincinnati",
    "sg:classifiers":[
        {
            "category":"Wholesale",
            "subcategory":"Metals & Minerals",
            "type":"Manufacturing & Wholesale Goods"
        }
    ],
    "sg:phone":"+1 513 794 0800",
    "sg:postcode":"45236",
    "sg:province":"OH",
    "sg:tags":[
        "product",
        "aluminum"
    ],
    "wof:name":"Alcoa",
    "wof:placetype":"venue"
},
  "geometry": {"coordinates":[-84.370542,39.207204],"type":"Point"}
}