{
  "type": "Feature",
  "properties": {
    "addr:full":"1030 N Tuscarawas Ave Dover OH 44622",
    "addr:housenumber":"1030",
    "addr:postcode":"44622",
    "addr:street":"N Tuscarawas Ave",
    "iso:country":"US",
    "sg:address":"1030 N Tuscarawas Ave",
    "sg:city":"Dover",
    "sg:classifiers":[
        {
            "category":"Restaurant",
            "type":"Food & Drink"
        }
    ],
    "sg:menulink":"http://www.allmenus.com/oh/dover/211407-kfc---kentucky-fried-chicken/menu/",
    "sg:phone":"+1 216 343 1155",
    "sg:postcode":"44622",
    "sg:province":"OH",
    "sg:tags":[
        "american",
        "chicken"
    ],
    "wof:name":"KFC - Kentucky Fried Chicken",
    "wof:placetype":"venue"
},
  "geometry": {"coordinates":[-81.48882,40.526666],"type":"Point"}
}