{
  "type": "Feature",
  "properties": {
    "iso:country":"US",
    "sg:address":"12006 Fenstermaker Rd",
    "sg:city":"Garrettsville",
    "sg:classifiers":[
        {
            "category":"Shopping",
            "subcategory":"Bicycles & Sporting Goods",
            "type":"Retail Goods"
        }
    ],
    "sg:phone":"+1 440 548 2442",
    "sg:postcode":"44231",
    "sg:province":"OH",
    "sg:tags":[
        "gun",
        "gunsmith"
    ],
    "wof:name":"Targething",
    "wof:placetype":"venue"
},
  "geometry": {"coordinates":[-81.01152999999999,41.321511],"type":"Point"}
}