{
  "type": "Feature",
  "properties": {
    "addr:full": "12006 Fenstermaker Rd Garrettsville OH 44231",
    "addr:housenumber": "12006",
    "addr:postcode": "44231",
    "addr:street": "Fenstermaker Rd",
    "iso:country": "US",
    "sg:address": "12006 Fenstermaker Rd",
    "sg:city": "Garrettsville",
    "sg:classifiers": [
      {
        "category": "Shopping",
        "subcategory": "Bicycles \u0026 Sporting Goods",
        "type": "Retail Goods"
      }
    ],
    "sg:phone": "+1 440 548 2442",
    "sg:postcode": "44231",
    "sg:province": "OH",
    "sg:tags": [
      "gun",
      "gunsmith"
    ],
    "wof:name": "Targething",
    "wof:placetype": "venue"
  },
  "geometry": {"coordinates":[-81.01153,41.321511],"type":"Point"}
}
