{
  "type": "Feature",
  "properties": {
    "addr:full": "4360 Flatfoot Rd Cable OH 43009",
    "addr:housenumber": "4360",
    "addr:postcode": "43009",
    "addr:street": "Flatfoot Rd",
    "iso:country": "US",
    "sg:address": "4360 Flatfoot Rd",
    "sg:city": "Cable",
    "sg:classifiers": [
      {
        "category": "Shopping",
        "subcategory": "Bicycles \u0026 Sporting Goods",
        "type": "Retail Goods"
      },
      {
        "category": "Manufacturing",
        "subcategory": "Printing",
        "type": "Manufacturing \u0026 Wholesale Goods"
      }
    ],
    "sg:phone": "+1 937 652 3407",
    "sg:postcode": "43009",
    "sg:province": "OH",
    "sg:tags": [
      "print",
      "screen",
      "gun",
      "gunsmith"
    ],
    "wof:name": "Superior Products",
    "wof:placetype": "venue"
  },
  "geometry": {"coordinates":[-83.661478,40.187225],"type":"Point"}
}
