{
  "type": "Feature",
  "properties": {
    "iso:country":"US",
    "sg:address":"4360 Flatfoot Rd",
    "sg:city":"Cable",
    "sg:classifiers":[
        {
            "category":"Shopping",
            "subcategory":"Bicycles & Sporting Goods",
            "type":"Retail Goods"
        },
        {
            "category":"Manufacturing",
            "subcategory":"Printing",
            "type":"Manufacturing & Wholesale Goods"
        }
    ],
    "sg:phone":"+1 937 652 3407",
    "sg:postcode":"43009",
    "sg:province":"OH",
    "sg:tags":[
        "print",
        "screen",
        "gun",
        "gunsmith"
    ],
    "wof:name":"Superior Products",
    "wof:placetype":"venue"
},
  "geometry": {"coordinates":[-83.661478,40.187225],"type":"Point"}
}