{
  "type": "Feature",
  "properties": {
    "iso:country":"US",
    "sg:address":"8215 Wonderland Rd",
    "sg:city":"Chandlersville",
    "sg:classifiers":[
        {
            "category":"Building & Trades",
            "subcategory":"Construction",
            "type":"Services"
        }
    ],
    "sg:phone":"+1 740 674 6000",
    "sg:postcode":"43727",
    "sg:province":"OH",
    "sg:tags":[
        "concrete",
        "contractor"
    ],
    "wof:name":"Laid Right Flooring",
    "wof:placetype":"venue"
},
  "geometry": {"coordinates":[-81.835689,39.878045],"type":"Point"}
}