{
  "type": "Feature",
  "properties": {
    "iso:country":"US",
    "sg:address":"1660 Bridgewood Ct",
    "sg:city":"Defiance",
    "sg:phone":"+1 419 784 0542",
    "sg:postcode":"43512",
    "sg:province":"OH",
    "sg:tags":[
        "farm",
        "corn"
    ],
    "wof:name":"Jeff Stykemain",
    "wof:placetype":"venue"
},
  "geometry": {"coordinates":[-84.400263,41.257485],"type":"Point"}
}