{
  "type": "Feature",
  "properties": {
    "iso:country":"US",
    "sg:address":"1700 Highland Rd",
    "sg:city":"Twinsburg",
    "sg:classifiers":[
        {
            "category":"Manufacturing",
            "subcategory":"Chemicals & Compounds",
            "type":"Manufacturing & Wholesale Goods"
        }
    ],
    "sg:phone":"+1 330 425 8472",
    "sg:postcode":"44087",
    "sg:province":"OH",
    "sg:tags":[
        "rubber"
    ],
    "sg:website":"www.qsr-inc.com",
    "wof:name":"Quality Synthetic Rubber",
    "wof:placetype":"venue"
},
  "geometry": {"coordinates":[-81.458292,41.297681],"type":"Point"}
}