{
  "type": "Feature",
  "properties": {
    "addr:full": "1700 Highland Rd Twinsburg OH 44087",
    "addr:housenumber": "1700",
    "addr:postcode": "44087",
    "addr:street": "Highland Rd",
    "iso:country": "US",
    "sg:address": "1700 Highland Rd",
    "sg:city": "Twinsburg",
    "sg:classifiers": [
      {
        "category": "Manufacturing",
        "subcategory": "Chemicals \u0026 Compounds",
        "type": "Manufacturing \u0026 Wholesale Goods"
      }
    ],
    "sg:phone": "+1 330 425 8472",
    "sg:postcode": "44087",
    "sg:province": "OH",
    "sg:tags": [
      "rubber"
    ],
    "sg:website": "www.qsr-inc.com",
    "wof:name": "Quality Synthetic Rubber",
    "wof:placetype": "venue"
  },
  "geometry": {"coordinates":[-81.458292,41.297681],"type":"Point"}
}
