{
  "type": "Feature",
  "properties": {
    "addr:full":"505 State Rte 78 Scn Malta OH 43758",
    "addr:housenumber":"505",
    "addr:postcode":"43758",
    "addr:street":"State Rte 78 Scn",
    "iso:country":"US",
    "sg:address":"505 State Rte 78 Scn",
    "sg:city":"Malta",
    "sg:classifiers":[
        {
            "category":"Organizations",
            "subcategory":"Religious Organization",
            "type":"Services"
        }
    ],
    "sg:phone":"+1 740 962 4956",
    "sg:postcode":"43758",
    "sg:province":"OH",
    "sg:tags":[
        "church"
    ],
    "wof:name":"Wolf Creek Church Of Christ",
    "wof:placetype":"venue"
},
  "geometry": {"coordinates":[-81.92825999999999,39.610171],"type":"Point"}
}