{
  "type": "Feature",
  "properties": {
    "iso:country":"US",
    "sg:address":"143 Boardman Canfield Rd",
    "sg:city":"Youngstown",
    "sg:classifiers":[
        {
            "category":"Shopping",
            "type":"Retail Goods"
        }
    ],
    "sg:phone":"+1 330 965 2221",
    "sg:postcode":"44512",
    "sg:province":"OH",
    "sg:tags":[
        "equipment",
        "industrial",
        "merchandise"
    ],
    "wof:name":"Mason Entp Group & Assoc LLC",
    "wof:placetype":"venue"
},
  "geometry": {"coordinates":[-80.666735,41.02433],"type":"Point"}
}