{
  "type": "Feature",
  "properties": {
    "iso:country":"US",
    "sg:address":"218 Mud Switch Rd",
    "sg:city":"Martinsville",
    "sg:classifiers":[
        {
            "category":"Professional",
            "type":"Services"
        }
    ],
    "sg:phone":"+1 937 685 9449",
    "sg:postcode":"45146",
    "sg:province":"OH",
    "wof:name":"Hayslip Guy & Son",
    "wof:placetype":"venue"
},
  "geometry": {"coordinates":[-83.82823999999999,39.293699],"type":"Point"}
}