{
  "type": "Feature",
  "properties": {
    "addr:full": "218 Mud Switch Rd Martinsville OH 45146",
    "addr:housenumber": "218",
    "addr:postcode": "45146",
    "addr:street": "Mud Switch Rd",
    "iso:country": "US",
    "sg:address": "218 Mud Switch Rd",
    "sg:city": "Martinsville",
    "sg:classifiers": [
      {
        "category": "Professional",
        "type": "Services"
      }
    ],
    "sg:phone": "+1 937 685 9449",
    "sg:postcode": "45146",
    "sg:province": "OH",
    "wof:name": "Hayslip Guy \u0026 Son",
    "wof:placetype": "venue"
  },
  "geometry": {"coordinates":[-83.82824,39.293699],"type":"Point"}
}
