{
  "type": "Feature",
  "properties": {
    "addr:full": "14650 Detroit Ave Cleveland OH 44107",
    "addr:housenumber": "14650",
    "addr:postcode": "44107",
    "addr:street": "Detroit Ave",
    "iso:country": "US",
    "sg:address": "14650 Detroit Ave",
    "sg:city": "Cleveland",
    "sg:classifiers": [
      {
        "category": "Personal",
        "type": "Services"
      }
    ],
    "sg:phone": "+1 216 226 7952",
    "sg:postcode": "44107",
    "sg:province": "OH",
    "sg:tags": [
      "control",
      "weight"
    ],
    "wof:name": "Physicians Weight Loss Ctr",
    "wof:placetype": "venue"
  },
  "geometry": {"coordinates":[-81.797861,41.485289],"type":"Point"}
}
