{
  "type": "Feature",
  "properties": {
    "addr:full": "3723 Oxford Millville Rd Oxford OH 45056",
    "addr:housenumber": "3723",
    "addr:postcode": "45056",
    "addr:street": "Oxford Millville Rd",
    "iso:country": "US",
    "sg:address": "3723 Oxford Millville Rd",
    "sg:city": "Oxford",
    "sg:classifiers": [
      {
        "category": "Building \u0026 Trades",
        "subcategory": "Construction",
        "type": "Services"
      }
    ],
    "sg:phone": "+1 513 523 6930",
    "sg:postcode": "45056",
    "sg:province": "OH",
    "sg:tags": [
      "material",
      "contractor"
    ],
    "wof:name": "Invisible Window",
    "wof:placetype": "venue"
  },
  "geometry": {"coordinates":[-84.714692,39.482052],"type":"Point"}
}
