{
  "type": "Feature",
  "properties": {
    "addr:full": "9510 Montgomery Rd Cincinnati OH 45242",
    "addr:housenumber": "9510",
    "addr:postcode": "45242",
    "addr:street": "Montgomery Rd",
    "iso:country": "US",
    "sg:address": "9510 Montgomery Rd",
    "sg:city": "Cincinnati",
    "sg:classifiers": [
      {
        "category": "Food \u0026 Beverages",
        "subcategory": "Candy",
        "type": "Retail Goods"
      },
      {
        "category": "Shopping",
        "subcategory": "Florist",
        "type": "Retail Goods"
      }
    ],
    "sg:phone": "+1 513 793 3377",
    "sg:postcode": "45242",
    "sg:province": "OH",
    "wof:name": "Springwater Sweets \u0026 Flowers",
    "wof:placetype": "venue"
  },
  "geometry": {"coordinates":[-84.353773,39.22862],"type":"Point"}
}
