{
  "type": "Feature",
  "properties": {
    "addr:full":"3440 Olentangy River Rd Columbus OH 43202",
    "addr:housenumber":"3440",
    "addr:postcode":"43202",
    "addr:street":"Olentangy River Rd",
    "iso:country":"US",
    "sg:address":"3440 Olentangy River Rd",
    "sg:city":"Columbus",
    "sg:classifiers":[
        {
            "category":"Social Services",
            "type":"Services"
        }
    ],
    "sg:phone":"+1 614 268 1042",
    "sg:postcode":"43202",
    "sg:province":"OH",
    "sg:tags":[
        "counselor",
        "marriage",
        "family"
    ],
    "wof:name":"Lara Palay",
    "wof:placetype":"venue"
},
  "geometry": {"coordinates":[-83.030182,40.030186],"type":"Point"}
}