{
  "type": "Feature",
  "properties": {
    "iso:country":"US",
    "sg:address":"10650 N Pisgah Ridge Rd NW",
    "sg:city":"Blue Rock",
    "sg:classifiers":[
        {
            "category":"Wholesale",
            "subcategory":"Electrical",
            "type":"Manufacturing & Wholesale Goods"
        }
    ],
    "sg:phone":"+1 740 962 5808",
    "sg:postcode":"43720",
    "sg:province":"OH",
    "sg:tags":[
        "alarm",
        "burglar",
        "system"
    ],
    "sg:website":"www.securetechsystems.com",
    "wof:name":"Secure-Tech Security Systems",
    "wof:placetype":"venue"
},
  "geometry": {"coordinates":[-81.880048,39.760627],"type":"Point"}
}