{
  "type": "Feature",
  "properties": {
    "addr:full": "10650 N Pisgah Ridge Rd NW Blue Rock OH 43720",
    "addr:housenumber": "10650",
    "addr:postcode": "43720",
    "addr:street": "N Pisgah Ridge Rd Nw",
    "iso:country": "US",
    "sg:address": "10650 N Pisgah Ridge Rd NW",
    "sg:city": "Blue Rock",
    "sg:classifiers": [
      {
        "category": "Wholesale",
        "subcategory": "Electrical",
        "type": "Manufacturing \u0026 Wholesale Goods"
      }
    ],
    "sg:phone": "+1 740 962 5808",
    "sg:postcode": "43720",
    "sg:province": "OH",
    "sg:tags": [
      "alarm",
      "burglar",
      "system"
    ],
    "sg:website": "www.securetechsystems.com",
    "wof:name": "Secure-Tech Security Systems",
    "wof:placetype": "venue"
  },
  "geometry": {"coordinates":[-81.880048,39.760627],"type":"Point"}
}
