{
  "type": "Feature",
  "properties": {
    "iso:country":"US",
    "sg:address":"7920 Ballash Rd",
    "sg:city":"Medina",
    "sg:classifiers":[
        {
            "category":"Wholesale",
            "subcategory":"Construction Materials",
            "type":"Manufacturing & Wholesale Goods"
        }
    ],
    "sg:phone":"+1 330 769 4245",
    "sg:postcode":"44256",
    "sg:province":"OH",
    "sg:tags":[
        "consulting",
        "management"
    ],
    "wof:name":"Real Log Homes",
    "wof:placetype":"venue"
},
  "geometry": {"coordinates":[-81.923711,41.055897],"type":"Point"}
}