{
  "type": "Feature",
  "properties": {
    "addr:full":"1875 Radio Rd Dayton OH 45403",
    "addr:housenumber":"1875",
    "addr:postcode":"45403",
    "addr:street":"Radio Rd",
    "iso:country":"US",
    "sg:address":"1875 Radio Rd",
    "sg:city":"Dayton",
    "sg:classifiers":[
        {
            "category":"Manufacturing",
            "subcategory":"Printing",
            "type":"Manufacturing & Wholesale Goods"
        }
    ],
    "sg:phone":"+1 937 259 6575",
    "sg:postcode":"45403",
    "sg:province":"OH",
    "sg:tags":[
        "publisher"
    ],
    "wof:name":"Young's Publishing",
    "wof:placetype":"venue"
},
  "geometry": {"coordinates":[-84.134148,39.772566],"type":"Point"}
}