{
  "type": "Feature",
  "properties": {
    "addr:full":"11565 Fay Rd Painesville OH 44077",
    "addr:housenumber":"11565",
    "addr:postcode":"44077",
    "addr:street":"Fay Rd",
    "iso:country":"US",
    "sg:address":"11565 Fay Rd",
    "sg:city":"Painesville",
    "sg:classifiers":[
        {
            "category":"Shopping",
            "subcategory":"Computers & Home Electronics",
            "type":"Retail Goods"
        }
    ],
    "sg:phone":"+1 440 350 0500",
    "sg:postcode":"44077",
    "sg:province":"OH",
    "sg:tags":[
        "publishing"
    ],
    "wof:name":"Publication Strategies",
    "wof:placetype":"venue"
},
  "geometry": {"coordinates":[-81.22334499999999,41.687236],"type":"Point"}
}