{
  "type": "Feature",
  "properties": {
    "iso:country":"US",
    "sg:address":"15135 Pearl Rd",
    "sg:city":"Cleveland",
    "sg:classifiers":[
        {
            "category":"Banks & Credit Unions",
            "subcategory":"Bank",
            "type":"Services"
        }
    ],
    "sg:phone":"+1 440 238 0140",
    "sg:postcode":"44136",
    "sg:province":"OH",
    "sg:tags":[
        "financing"
    ],
    "wof:name":"Citi Financial",
    "wof:placetype":"venue"
},
  "geometry": {"coordinates":[-81.835143,41.304197],"type":"Point"}
}