{
  "type": "Feature",
  "properties": {
    "addr:full": "23366 Commerce Park Rd Cleveland OH 44122",
    "addr:housenumber": "23366",
    "addr:postcode": "44122",
    "addr:street": "Commerce Park Rd",
    "iso:country": "US",
    "sg:address": "23366 Commerce Park Rd",
    "sg:city": "Cleveland",
    "sg:classifiers": [
      {
        "category": "Wholesale",
        "subcategory": "Electrical",
        "type": "Manufacturing \u0026 Wholesale Goods"
      }
    ],
    "sg:phone": "+1 216 464 0903",
    "sg:postcode": "44122",
    "sg:province": "OH",
    "sg:tags": [
      "elements",
      "electric",
      "heating"
    ],
    "wof:name": "Electro-Glass Heating Of Ohio",
    "wof:placetype": "venue"
  },
  "geometry": {"coordinates":[-81.506624,41.461958],"type":"Point"}
}
