{
  "type": "Feature",
  "properties": {
    "addr:full": "398 N Market St Shreve OH 44676",
    "addr:housenumber": "398",
    "addr:postcode": "44676",
    "addr:street": "N Market St",
    "iso:country": "US",
    "sg:address": "398 N Market St",
    "sg:city": "Shreve",
    "sg:classifiers": [
      {
        "category": "Travel",
        "subcategory": "Hotels \u0026 Motels",
        "type": "Entertainment"
      }
    ],
    "sg:phone": "+1 330 567 5930",
    "sg:postcode": "44676",
    "sg:province": "OH",
    "sg:tags": [
      "breakfast",
      "accommodation",
      "bed"
    ],
    "wof:name": "Moyer Place",
    "wof:placetype": "venue"
  },
  "geometry": {"coordinates":[-82.022325,40.683994],"type":"Point"}
}
