{
  "type": "Feature",
  "properties": {
    "iso:country":"US",
    "sg:address":"398 N Market St",
    "sg:city":"Shreve",
    "sg:classifiers":[
        {
            "category":"Travel",
            "subcategory":"Hotels & Motels",
            "type":"Entertainment"
        }
    ],
    "sg:phone":"+1 330 567 5930",
    "sg:postcode":"44676",
    "sg:province":"OH",
    "sg:tags":[
        "breakfast",
        "accommodation",
        "bed"
    ],
    "wof:name":"Moyer Place",
    "wof:placetype":"venue"
},
  "geometry": {"coordinates":[-82.022325,40.683994],"type":"Point"}
}