{
  "type": "Feature",
  "properties": {
    "iso:country":"US",
    "sg:address":"157 N Main St",
    "sg:city":"Bowling Green",
    "sg:classifiers":[
        {
            "category":"Retail",
            "subcategory":"Photofinishing",
            "type":"Services"
        }
    ],
    "sg:phone":"+1 419 353 4244",
    "sg:postcode":"43402",
    "sg:province":"OH",
    "sg:tags":[
        "laboratory",
        "suppl"
    ],
    "wof:name":"Studio 157",
    "wof:placetype":"venue"
},
  "geometry": {"coordinates":[-83.650486,41.375367],"type":"Point"}
}