{
  "type": "Feature",
  "properties": {
    "iso:country":"US",
    "sg:address":"148 E 2nd St",
    "sg:city":"Logan",
    "sg:classifiers":[
        {
            "category":"Real Estate",
            "subcategory":"Real Estate Agent",
            "type":"Services"
        }
    ],
    "sg:phone":"+1 740 385 7829",
    "sg:postcode":"43138",
    "sg:province":"OH",
    "wof:name":"Ruby Hartley",
    "wof:placetype":"venue"
},
  "geometry": {"coordinates":[-82.40636600000001,39.538962],"type":"Point"}
}