{
  "type": "Feature",
  "properties": {
    "addr:full":"422 S 9th St Cambridge OH 43725",
    "addr:housenumber":"422",
    "addr:postcode":"43725",
    "addr:street":"S 9Th St",
    "iso:country":"US",
    "sg:address":"422 S 9th St",
    "sg:city":"Cambridge",
    "sg:classifiers":[
        {
            "category":"Shopping",
            "subcategory":"Used Merchandise",
            "type":"Retail Goods"
        }
    ],
    "sg:phone":"+1 740 432 5855",
    "sg:postcode":"43725",
    "sg:province":"OH",
    "sg:tags":[
        "antique",
        "business"
    ],
    "wof:name":"Judy's Antiques",
    "wof:placetype":"venue"
},
  "geometry": {"coordinates":[-81.589398,40.020722],"type":"Point"}
}