{
  "type": "Feature",
  "properties": {
    "iso:country":"US",
    "sg:address":"7401 Market St",
    "sg:city":"Youngstown",
    "sg:classifiers":[
        {
            "category":"Shopping",
            "subcategory":"Clothing, Apparel, & Fashions",
            "type":"Retail Goods"
        }
    ],
    "sg:phone":"+1 330 726 7902",
    "sg:postcode":"44512",
    "sg:province":"OH",
    "sg:tags":[
        "furnishing"
    ],
    "sg:website":"www.expressfasion.com",
    "wof:name":"Express Mens",
    "wof:placetype":"venue"
},
  "geometry": {"coordinates":[-80.662655,41.022168],"type":"Point"}
}