{
  "type": "Feature",
  "properties": {
    "addr:full": "2164 E Aurora Rd Twinsburg OH 44087",
    "addr:housenumber": "2164",
    "addr:postcode": "44087",
    "addr:street": "E Aurora Rd",
    "iso:country": "US",
    "sg:address": "2164 E Aurora Rd",
    "sg:city": "Twinsburg",
    "sg:classifiers": [
      {
        "category": "Manufacturing",
        "subcategory": "Signs",
        "type": "Manufacturing \u0026 Wholesale Goods"
      }
    ],
    "sg:phone": "+1 330 425 2550",
    "sg:postcode": "44087",
    "sg:province": "OH",
    "wof:name": "K \u0026 M Intl",
    "wof:placetype": "venue"
  },
  "geometry": {"coordinates":[-81.471052,41.311311],"type":"Point"}
}
