{
  "type": "Feature",
  "properties": {
    "addr:full":"677 E Main St Geneva OH 44041",
    "addr:housenumber":"677",
    "addr:postcode":"44041",
    "addr:street":"E Main St",
    "iso:country":"US",
    "sg:address":"677 E Main St",
    "sg:city":"Geneva",
    "sg:classifiers":[
        {
            "category":"Real Estate",
            "subcategory":"Real Estate Agent",
            "type":"Services"
        }
    ],
    "sg:phone":"+1 440 466 1191",
    "sg:postcode":"44041",
    "sg:province":"OH",
    "wof:name":"Miller Realty Company Inc",
    "wof:placetype":"venue"
},
  "geometry": {"coordinates":[-80.935959,41.809103],"type":"Point"}
}