{
  "type": "Feature",
  "properties": {
    "addr:full": "11310 Williamson Rd Cincinnati OH 45241",
    "addr:housenumber": "11310",
    "addr:postcode": "45241",
    "addr:street": "Williamson Rd",
    "iso:country": "US",
    "sg:address": "11310 Williamson Rd",
    "sg:city": "Cincinnati",
    "sg:classifiers": [
      {
        "category": "Wholesale",
        "subcategory": "Construction Materials",
        "type": "Manufacturing \u0026 Wholesale Goods"
      }
    ],
    "sg:phone": "+1 513 489 2233",
    "sg:postcode": "45241",
    "sg:province": "OH",
    "sg:tags": [
      "glass"
    ],
    "wof:name": "Glenny Glass Co",
    "wof:placetype": "venue"
  },
  "geometry": {"coordinates":[-84.378864,39.272452],"type":"Point"}
}
