{
  "type": "Feature",
  "properties": {
    "iso:country":"US",
    "sg:address":"6262 Sawmill Rd",
    "sg:city":"Dublin",
    "sg:classifiers":[
        {
            "category":"Home & Garden",
            "subcategory":"Home Furnishings",
            "type":"Retail Goods"
        }
    ],
    "sg:phone":"+1 614 764 1656",
    "sg:postcode":"43017",
    "sg:province":"OH",
    "wof:name":"Pier 1",
    "wof:placetype":"venue"
},
  "geometry": {"coordinates":[-83.091573,40.094031],"type":"Point"}
}