{
  "type": "Feature",
  "properties": {
    "addr:full":"1638 Bancroft St Dayton OH 45408",
    "addr:housenumber":"1638",
    "addr:postcode":"45408",
    "addr:street":"Bancroft St",
    "iso:country":"US",
    "sg:address":"1638 Bancroft St",
    "sg:city":"Dayton",
    "sg:classifiers":[
        {
            "category":"Real Estate",
            "subcategory":"Real Estate Agent",
            "type":"Services"
        }
    ],
    "sg:phone":"+1 937 228 4989",
    "sg:postcode":"45408",
    "sg:province":"OH",
    "sg:tags":[
        "building",
        "apartment"
    ],
    "wof:name":"Bancroft Apartments",
    "wof:placetype":"venue"
},
  "geometry": {"coordinates":[-84.22209700000001,39.743191],"type":"Point"}
}