{
  "type": "Feature",
  "properties": {
    "addr:full":"8500 Hoon Dr Athens OH 45701",
    "addr:postcode":"8500;45701",
    "addr:street":"Hoon Dr",
    "iso:country":"US",
    "sg:address":"8500 Hoon Dr",
    "sg:city":"Athens",
    "sg:classifiers":[
        {
            "category":"Retail",
            "subcategory":"Animal Services",
            "type":"Services"
        }
    ],
    "sg:phone":"+1 740 592 6047",
    "sg:postcode":"45701",
    "sg:province":"OH",
    "sg:tags":[
        "shelter"
    ],
    "wof:name":"Athens County Humane Society",
    "wof:placetype":"venue"
},
  "geometry": {"coordinates":[-82.12642099999999,39.33155],"type":"Point"}
}