{
  "type": "Feature",
  "properties": {
    "addr:full": "2121 Abington Rd Cleveland OH 44106",
    "addr:housenumber": "2121",
    "addr:postcode": "44106",
    "addr:street": "Abington Rd",
    "iso:country": "US",
    "sg:address": "2121 Abington Rd",
    "sg:city": "Cleveland",
    "sg:classifiers": [
      {
        "category": "Education",
        "subcategory": "Vocational School",
        "type": "Public Place"
      }
    ],
    "sg:phone": "+1 216 368 2529",
    "sg:postcode": "44106",
    "sg:province": "OH",
    "sg:tags": [
      "nurse"
    ],
    "wof:name": "Case Western Reserve Univ",
    "wof:placetype": "venue"
  },
  "geometry": {"coordinates":[-81.60555,41.506401],"type":"Point"}
}
