{
  "type": "Feature",
  "properties": {
    "iso:country":"US",
    "sg:address":"64 High St",
    "sg:city":"Carroll",
    "sg:classifiers":[
        {
            "category":"Personal",
            "subcategory":"Beauty Salon",
            "type":"Services"
        }
    ],
    "sg:phone":"+1 740 756 9000",
    "sg:postcode":"43112",
    "sg:province":"OH",
    "sg:tags":[
        "shop"
    ],
    "wof:name":"Tranquil Moment Salon",
    "wof:placetype":"venue"
},
  "geometry": {"coordinates":[-82.70518,39.79872],"type":"Point"}
}