{
  "type": "Feature",
  "properties": {
    "iso:country":"US",
    "sg:address":"5145 Salem Ave",
    "sg:city":"Dayton",
    "sg:classifiers":[
        {
            "category":"Utilities",
            "subcategory":"Mobile Phone",
            "type":"Services"
        }
    ],
    "sg:phone":"+1 937 854 9795",
    "sg:postcode":"45426",
    "sg:province":"OH",
    "sg:tags":[
        "telephone",
        "cellular"
    ],
    "wof:name":"Envizon Wireless",
    "wof:placetype":"venue"
},
  "geometry": {"coordinates":[-84.27999800000001,39.818869],"type":"Point"}
}