{
  "type": "Feature",
  "properties": {
    "addr:full": "5145 Salem Ave Dayton OH 45426",
    "addr:housenumber": "5145",
    "addr:postcode": "45426",
    "addr:street": "Salem Ave",
    "iso:country": "US",
    "sg:address": "5145 Salem Ave",
    "sg:city": "Dayton",
    "sg:classifiers": [
      {
        "category": "Utilities",
        "subcategory": "Mobile Phone",
        "type": "Services"
      }
    ],
    "sg:phone": "+1 937 854 9795",
    "sg:postcode": "45426",
    "sg:province": "OH",
    "sg:tags": [
      "telephone",
      "cellular"
    ],
    "wof:name": "Envizon Wireless",
    "wof:placetype": "venue"
  },
  "geometry": {"coordinates":[-84.279998,39.818869],"type":"Point"}
}
