{
  "type": "Feature",
  "properties": {
    "iso:country":"US",
    "sg:address":"5432 Co Rd 27",
    "sg:city":"Stryker",
    "sg:classifiers":[
        {
            "category":"Building & Trades",
            "subcategory":"Plumbing",
            "type":"Services"
        }
    ],
    "sg:phone":"+1 419 682 5722",
    "sg:postcode":"43557",
    "sg:province":"OH",
    "sg:tags":[
        "conditioning",
        "air",
        "system",
        "contractor"
    ],
    "wof:name":"Light Power & Comfort Corp",
    "wof:placetype":"venue"
},
  "geometry": {"coordinates":[-84.380807,41.54889],"type":"Point"}
}