{
  "type": "Feature",
  "properties": {
    "addr:full": "5432 Co Rd 27 Stryker OH 43557",
    "addr:housenumber": "5432;27",
    "addr:postcode": "43557",
    "addr:street": "Co Rd",
    "iso:country": "US",
    "sg:address": "5432 Co Rd 27",
    "sg:city": "Stryker",
    "sg:classifiers": [
      {
        "category": "Building \u0026 Trades",
        "subcategory": "Plumbing",
        "type": "Services"
      }
    ],
    "sg:phone": "+1 419 682 5722",
    "sg:postcode": "43557",
    "sg:province": "OH",
    "sg:tags": [
      "conditioning",
      "air",
      "system",
      "contractor"
    ],
    "wof:name": "Light Power \u0026 Comfort Corp",
    "wof:placetype": "venue"
  },
  "geometry": {"coordinates":[-84.380807,41.54889],"type":"Point"}
}
