{
  "type": "Feature",
  "properties": {
    "addr:full": "3375 W State Rte 571 Troy OH 45373",
    "addr:housenumber": "3375",
    "addr:postcode": "45373",
    "addr:street": "W State Rte 571",
    "iso:country": "US",
    "sg:address": "3375 W State Rte 571",
    "sg:city": "Troy",
    "sg:classifiers": [
      {
        "category": "Shopping",
        "subcategory": "Florist",
        "type": "Retail Goods"
      }
    ],
    "sg:phone": "+1 937 698 5823",
    "sg:postcode": "45373",
    "sg:province": "OH",
    "wof:name": "Lee Floral Containers",
    "wof:placetype": "venue"
  },
  "geometry": {"coordinates":[-84.259211,39.96235],"type":"Point"}
}
