{
  "type": "Feature",
  "properties": {
    "addr:full": "1147 Lake St Kent OH 44240",
    "addr:housenumber": "1147",
    "addr:postcode": "44240",
    "addr:street": "Lake St",
    "iso:country": "US",
    "sg:address": "1147 Lake St",
    "sg:city": "Kent",
    "sg:classifiers": [
      {
        "category": "Organizations",
        "subcategory": "Community Association",
        "type": "Services"
      }
    ],
    "sg:phone": "+1 330 677 4444",
    "sg:postcode": "44240",
    "sg:province": "OH",
    "sg:tags": [
      "sorority",
      "fraternity"
    ],
    "wof:name": "Sports-N-Duds",
    "wof:placetype": "venue"
  },
  "geometry": {"coordinates":[-81.341877,41.162804],"type":"Point"}
}
