{
  "type": "Feature",
  "properties": {
    "addr:full": "10787 Engle Rd Vandalia OH 45377",
    "addr:housenumber": "10787",
    "addr:postcode": "45377",
    "addr:street": "Engle Rd",
    "iso:country": "US",
    "sg:address": "10787 Engle Rd",
    "sg:city": "Vandalia",
    "sg:classifiers": [
      {
        "category": "Freight",
        "type": "Transportation"
      }
    ],
    "sg:phone": "+1 937 890 2048",
    "sg:postcode": "45377",
    "sg:province": "OH",
    "sg:tags": [
      "special",
      "general"
    ],
    "wof:name": "A To Z Self Storage",
    "wof:placetype": "venue"
  },
  "geometry": {"coordinates":[-84.189484,39.908288],"type":"Point"}
}
