{
  "type": "Feature",
  "properties": {
    "iso:country":"US",
    "sg:address":"305 Dunn St",
    "sg:city":"Cincinnati",
    "sg:classifiers":[
        {
            "category":"Retail",
            "subcategory":"Auto Repair",
            "type":"Services"
        }
    ],
    "sg:phone":"+1 513 821 6004",
    "sg:postcode":"45215",
    "sg:province":"OH",
    "sg:tags":[
        "repairing",
        "automobile",
        "radiator",
        "general"
    ],
    "wof:name":"Valley Radiator Serv",
    "wof:placetype":"venue"
},
  "geometry": {"coordinates":[-84.45048,39.223183],"type":"Point"}
}