{
  "type": "Feature",
  "properties": {
    "addr:full":"264 W Main St Cortland OH 44410",
    "addr:housenumber":"264",
    "addr:postcode":"44410",
    "addr:street":"W Main St",
    "iso:country":"US",
    "sg:address":"264 W Main St",
    "sg:city":"Cortland",
    "sg:classifiers":[
        {
            "category":"Shopping",
            "subcategory":"Clothing, Apparel, & Fashions",
            "type":"Retail Goods"
        }
    ],
    "sg:phone":"+1 330 637 5493",
    "sg:postcode":"44410",
    "sg:province":"OH",
    "sg:tags":[
        "men's",
        "clothing",
        "boys'"
    ],
    "wof:name":"The Men's Shop",
    "wof:placetype":"venue"
},
  "geometry": {"coordinates":[-80.73003,41.33009],"type":"Point"}
}