{
  "type": "Feature",
  "properties": {
    "addr:full": "192 E State St Salem OH 44460",
    "addr:housenumber": "192",
    "addr:postcode": "44460",
    "addr:street": "E State St",
    "iso:country": "US",
    "sg:address": "192 E State St",
    "sg:city": "Salem",
    "sg:classifiers": [
      {
        "category": "Real Estate",
        "subcategory": "Real Estate Agent",
        "type": "Services"
      }
    ],
    "sg:phone": "+1 330 337 3455",
    "sg:postcode": "44460",
    "sg:province": "OH",
    "wof:name": "Herron \u0026 Assoc Inc",
    "wof:placetype": "venue"
  },
  "geometry": {"coordinates":[-80.855905,40.901028],"type":"Point"}
}
