{
  "type": "Feature",
  "properties": {
    "iso:country":"US",
    "sg:address":"192 E State St",
    "sg:city":"Salem",
    "sg:classifiers":[
        {
            "category":"Real Estate",
            "subcategory":"Real Estate Agent",
            "type":"Services"
        }
    ],
    "sg:phone":"+1 330 337 3455",
    "sg:postcode":"44460",
    "sg:province":"OH",
    "wof:name":"Herron & Assoc Inc",
    "wof:placetype":"venue"
},
  "geometry": {"coordinates":[-80.855905,40.901028],"type":"Point"}
}