{
  "type": "Feature",
  "properties": {
    "iso:country":"US",
    "sg:address":"3754 Hamilton Cleves Rd",
    "sg:city":"Hamilton",
    "sg:classifiers":[
        {
            "category":"Restaurant",
            "type":"Food & Drink"
        }
    ],
    "sg:phone":"+1 513 738 3111",
    "sg:postcode":"45013",
    "sg:province":"OH",
    "wof:name":"Boston Butz Bbq & Pizza",
    "wof:placetype":"venue"
},
  "geometry": {"coordinates":[-84.634591,39.326473],"type":"Point"}
}