{
  "type": "Feature",
  "properties": {
    "iso:country":"US",
    "sg:address":"373 N Alcony Conover Rd",
    "sg:city":"Troy",
    "sg:classifiers":[
        {
            "category":"Local Transit",
            "type":"Transportation"
        }
    ],
    "sg:phone":"+1 937 857 0106",
    "sg:postcode":"45373",
    "sg:province":"OH",
    "sg:tags":[
        "passenger"
    ],
    "wof:name":"Tim Fleenor",
    "wof:placetype":"venue"
},
  "geometry": {"coordinates":[-84.055311,40.035323],"type":"Point"}
}