{
  "type": "Feature",
  "properties": {
    "iso:country":"US",
    "sg:address":"941 Bricker Blvd",
    "sg:city":"Columbus",
    "sg:classifiers":[
        {
            "category":"Recreation",
            "subcategory":"Marina",
            "type":"Entertainment"
        }
    ],
    "sg:phone":"+1 614 442 1863",
    "sg:postcode":"43221",
    "sg:province":"OH",
    "sg:tags":[
        "storage",
        "boat"
    ],
    "wof:name":"Sabo's Rv & Boat Storage",
    "wof:placetype":"venue"
},
  "geometry": {"coordinates":[-83.039951,40.023764],"type":"Point"}
}