{
  "type": "Feature",
  "properties": {
    "addr:full": "320 Chestnut St Greenville OH 45331",
    "addr:housenumber": "320",
    "addr:postcode": "45331",
    "addr:street": "Chestnut St",
    "iso:country": "US",
    "sg:address": "320 Chestnut St",
    "sg:city": "Greenville",
    "sg:classifiers": [
      {
        "category": "Home \u0026 Garden",
        "subcategory": "Building Materials",
        "type": "Retail Goods"
      }
    ],
    "sg:phone": "+1 937 547 1082",
    "sg:postcode": "45331",
    "sg:province": "OH",
    "sg:tags": [
      "garage",
      "door"
    ],
    "wof:name": "Greenville Door Sales Inc",
    "wof:placetype": "venue"
  },
  "geometry": {"coordinates":[-84.637805,40.097326],"type":"Point"}
}
