{
  "type": "Feature",
  "properties": {
    "iso:country":"US",
    "sg:address":"2824 Wilmington Pike",
    "sg:city":"Dayton",
    "sg:classifiers":[
        {
            "category":"Shopping",
            "subcategory":"Used Merchandise",
            "type":"Retail Goods"
        }
    ],
    "sg:phone":"+1 937 294 1973",
    "sg:postcode":"45419",
    "sg:province":"OH",
    "sg:tags":[
        "shop",
        "thrift"
    ],
    "wof:name":"St Francis Thrift Store",
    "wof:placetype":"venue"
},
  "geometry": {"coordinates":[-84.142254,39.706258],"type":"Point"}
}