{
  "type": "Feature",
  "properties": {
    "iso:country":"US",
    "sg:address":"20745 Germantown Dr",
    "sg:city":"Cleveland",
    "sg:classifiers":[
        {
            "category":"Building & Trades",
            "subcategory":"Construction",
            "type":"Services"
        }
    ],
    "sg:phone":"+1 440 331 2796",
    "sg:postcode":"44126",
    "sg:province":"OH",
    "sg:tags":[
        "house"
    ],
    "wof:name":"Walsh Remodeling",
    "wof:placetype":"venue"
},
  "geometry": {"coordinates":[-81.848625,41.438369],"type":"Point"}
}