{
  "type": "Feature",
  "properties": {
    "iso:country":"US",
    "sg:address":"765 S Prospect St",
    "sg:city":"Marion",
    "sg:classifiers":[
        {
            "category":"Building & Trades",
            "subcategory":"Construction",
            "type":"Services"
        }
    ],
    "sg:phone":"+1 740 387 0549",
    "sg:postcode":"43302",
    "sg:province":"OH",
    "sg:tags":[
        "house"
    ],
    "wof:name":"R P Construction",
    "wof:placetype":"venue"
},
  "geometry": {"coordinates":[-83.132041,40.575824],"type":"Point"}
}