{
  "type": "Feature",
  "properties": {
    "addr:full":"1970 Waldeck Ave Columbus OH 43201",
    "addr:housenumber":"1970",
    "addr:postcode":"43201",
    "addr:street":"Waldeck Ave",
    "iso:country":"US",
    "sg:address":"1970 Waldeck Ave",
    "sg:city":"Columbus",
    "sg:classifiers":[
        {
            "category":"Social Services",
            "subcategory":"Child Care",
            "type":"Services"
        }
    ],
    "sg:phone":"+1 614 262 1090",
    "sg:postcode":"43201",
    "sg:province":"OH",
    "wof:name":"Indianola Children's Ctr",
    "wof:placetype":"venue"
},
  "geometry": {"coordinates":[-83.00559800000001,40.002664],"type":"Point"}
}