{
  "type": "Feature",
  "properties": {
    "iso:country":"US",
    "sg:address":"1 W Main St",
    "sg:city":"New Concord",
    "sg:classifiers":[
        {
            "category":"Shopping",
            "type":"Retail Goods"
        }
    ],
    "sg:phone":"+1 740 826 4183",
    "sg:postcode":"43762",
    "sg:province":"OH",
    "sg:tags":[
        "miscellaneous",
        "store"
    ],
    "wof:name":"Cinema Shoppe",
    "wof:placetype":"venue"
},
  "geometry": {"coordinates":[-81.732911,39.993753],"type":"Point"}
}