{
  "type": "Feature",
  "properties": {
    "addr:full": "505 E Perkins Ave Sandusky OH 44870",
    "addr:housenumber": "505",
    "addr:postcode": "44870",
    "addr:street": "E Perkins Ave",
    "iso:country": "US",
    "sg:address": "505 E Perkins Ave",
    "sg:city": "Sandusky",
    "sg:classifiers": [
      {
        "category": "Home \u0026 Garden",
        "subcategory": "Home Furnishings",
        "type": "Retail Goods"
      }
    ],
    "sg:phone": "+1 419 626 3807",
    "sg:postcode": "44870",
    "sg:province": "OH",
    "sg:tags": [
      "equipment",
      "fireplace"
    ],
    "wof:name": "Roberts Specialty Shoppe",
    "wof:placetype": "venue"
  },
  "geometry": {"coordinates":[-82.692087,41.432756],"type":"Point"}
}
