{
  "type": "Feature",
  "properties": {
    "iso:country":"US",
    "sg:address":"505 E Perkins Ave",
    "sg:city":"Sandusky",
    "sg:classifiers":[
        {
            "category":"Home & Garden",
            "subcategory":"Home Furnishings",
            "type":"Retail Goods"
        }
    ],
    "sg:phone":"+1 419 626 3807",
    "sg:postcode":"44870",
    "sg:province":"OH",
    "sg:tags":[
        "equipment",
        "fireplace"
    ],
    "wof:name":"Roberts Specialty Shoppe",
    "wof:placetype":"venue"
},
  "geometry": {"coordinates":[-82.692087,41.432756],"type":"Point"}
}