{
  "type": "Feature",
  "properties": {
    "iso:country":"US",
    "sg:address":"2810 Lovers Ln",
    "sg:city":"Ravenna",
    "sg:classifiers":[
        {
            "category":"Building & Trades",
            "subcategory":"Landscaping Services",
            "type":"Services"
        }
    ],
    "sg:phone":"+1 330 388 2108",
    "sg:postcode":"44266",
    "sg:province":"OH",
    "sg:tags":[
        "landscape"
    ],
    "wof:name":"Better Image Landscaping A",
    "wof:placetype":"venue"
},
  "geometry": {"coordinates":[-81.292843,41.178509],"type":"Point"}
}