{
  "type": "Feature",
  "properties": {
    "addr:full":"10311 Dixon Rd Eaton OH 45320",
    "addr:housenumber":"10311",
    "addr:postcode":"45320",
    "addr:street":"Dixon Rd",
    "iso:country":"US",
    "sg:address":"10311 Dixon Rd",
    "sg:city":"Eaton",
    "sg:classifiers":[
        {
            "category":"Restaurant",
            "type":"Food & Drink"
        }
    ],
    "sg:phone":"+1 937 456 2462",
    "sg:postcode":"45320",
    "sg:province":"OH",
    "sg:tags":[
        "eating"
    ],
    "wof:name":"Bear Paw Enterprises",
    "wof:placetype":"venue"
},
  "geometry": {"coordinates":[-84.802516,39.729315],"type":"Point"}
}