{
  "type": "Feature",
  "properties": {
    "addr:full":"20030 Sidney-Plattsville Rd Sidney OH 45365",
    "addr:housenumber":"20030",
    "addr:postcode":"45365",
    "addr:street":"Sidney-Plattsville Rd",
    "iso:country":"US",
    "sg:address":"20030 Sidney-Plattsville Rd",
    "sg:city":"Sidney",
    "sg:classifiers":[
        {
            "category":"Home & Garden",
            "subcategory":"Garden Supply",
            "type":"Retail Goods"
        }
    ],
    "sg:phone":"+1 937 498 1186",
    "sg:postcode":"45365",
    "sg:province":"OH",
    "sg:tags":[
        "fertilizer",
        "farm"
    ],
    "wof:name":"Royster-Clark Inc",
    "wof:placetype":"venue"
},
  "geometry": {"coordinates":[-84.056999,40.230971],"type":"Point"}
}