{
  "type": "Feature",
  "properties": {
    "iso:country":"US",
    "sg:address":"33 W Kemper Rd",
    "sg:city":"Cincinnati",
    "sg:classifiers":[
        {
            "category":"Autos & Motor Vehicles",
            "subcategory":"Automobile Sales",
            "type":"Retail Goods"
        }
    ],
    "sg:phone":"+1 513 782 1041",
    "sg:postcode":"45246",
    "sg:province":"OH",
    "sg:tags":[
        "a",
        "repair",
        "used",
        "car",
        "general",
        "dealer"
    ],
    "wof:name":"G M Certified Used Vehicles",
    "wof:placetype":"venue"
},
  "geometry": {"coordinates":[-84.46967600000001,39.287759],"type":"Point"}
}