{
  "type": "Feature",
  "properties": {
    "addr:full": "6100 Oak Tree Blvd Cleveland OH 44131",
    "addr:housenumber": "6100",
    "addr:postcode": "44131",
    "addr:street": "Oak Tree Blvd",
    "iso:country": "US",
    "sg:address": "6100 Oak Tree Blvd",
    "sg:city": "Cleveland",
    "sg:classifiers": [
      {
        "category": "Insurance",
        "subcategory": "Insurance Agent",
        "type": "Services"
      }
    ],
    "sg:phone": "+1 216 986 0010",
    "sg:postcode": "44131",
    "sg:province": "OH",
    "wof:name": "Western \u0026 Southern Lf Insur Co",
    "wof:placetype": "venue"
  },
  "geometry": {"coordinates":[-81.661233,41.398296],"type":"Point"}
}
