{
  "type": "Feature",
  "properties": {
    "addr:full":"2365 Versailles Rd Russia OH 45363",
    "addr:housenumber":"2365",
    "addr:postcode":"45363",
    "addr:street":"Versailles Rd",
    "iso:country":"US",
    "sg:address":"2365 Versailles Rd",
    "sg:city":"Russia",
    "sg:classifiers":[
        {
            "category":"Professional",
            "type":"Services"
        }
    ],
    "sg:phone":"+1 937 526 5924",
    "sg:postcode":"45363",
    "sg:province":"OH",
    "wof:name":"Mrb",
    "wof:placetype":"venue"
},
  "geometry": {"coordinates":[-84.39364500000001,40.226536],"type":"Point"}
}