{
  "type": "Feature",
  "properties": {
    "addr:full": "7436 Vine St Cincinnati OH 45216",
    "addr:housenumber": "7436",
    "addr:postcode": "45216",
    "addr:street": "Vine St",
    "iso:country": "US",
    "sg:address": "7436 Vine St",
    "sg:city": "Cincinnati",
    "sg:classifiers": [
      {
        "category": "Health Services",
        "subcategory": "Doctor",
        "type": "Services"
      }
    ],
    "sg:phone": "+1 513 761 3307",
    "sg:postcode": "45216",
    "sg:province": "OH",
    "sg:tags": [
      "physician",
      "surgeon"
    ],
    "wof:name": "T C Mc Daniel DO",
    "wof:placetype": "venue"
  },
  "geometry": {"coordinates":[-84.475707,39.198726],"type":"Point"}
}
