{
  "type": "Feature",
  "properties": {
    "iso:country":"US",
    "sg:address":"37 N Limestone St",
    "sg:city":"Jamestown",
    "sg:classifiers":[
        {
            "category":"Government",
            "subcategory":"Post Office",
            "type":"Public Place"
        }
    ],
    "sg:phone":"+1 937 675 3111",
    "sg:postcode":"45335",
    "sg:province":"OH",
    "wof:name":"US Post Office",
    "wof:placetype":"venue"
},
  "geometry": {"coordinates":[-83.734578,39.660965],"type":"Point"}
}