{
  "type": "Feature",
  "properties": {
    "addr:full": "7347 California Ave Youngstown OH 44512",
    "addr:housenumber": "7347",
    "addr:postcode": "44512",
    "addr:street": "California Ave",
    "iso:country": "US",
    "sg:address": "7347 California Ave",
    "sg:city": "Youngstown",
    "sg:classifiers": [
      {
        "category": "Restaurant",
        "type": "Food \u0026 Drink"
      }
    ],
    "sg:phone": "+1 330 726 9934",
    "sg:postcode": "44512",
    "sg:province": "OH",
    "wof:name": "Bob Evans Farms Restaurant",
    "wof:placetype": "venue"
  },
  "geometry": {"coordinates":[-80.656343,41.022589],"type":"Point"}
}
