{
  "type": "Feature",
  "properties": {
    "iso:country":"US",
    "sg:address":"932 Jackson St",
    "sg:city":"Cincinnati",
    "sg:classifiers":[
        {
            "category":"Manufacturing",
            "subcategory":"Tobacco Products",
            "type":"Manufacturing & Wholesale Goods"
        }
    ],
    "sg:phone":"+1 513 733 1323",
    "sg:postcode":"45215",
    "sg:province":"OH",
    "sg:tags":[
        "cigarette",
        "mfg"
    ],
    "wof:name":"A K Cigarettes",
    "wof:placetype":"venue"
},
  "geometry": {"coordinates":[-84.458112,39.245476],"type":"Point"}
}