{
  "type": "Feature",
  "properties": {
    "addr:full": "932 Jackson St Cincinnati OH 45215",
    "addr:housenumber": "932",
    "addr:postcode": "45215",
    "addr:street": "Jackson St",
    "iso:country": "US",
    "sg:address": "932 Jackson St",
    "sg:city": "Cincinnati",
    "sg:classifiers": [
      {
        "category": "Manufacturing",
        "subcategory": "Tobacco Products",
        "type": "Manufacturing \u0026 Wholesale Goods"
      }
    ],
    "sg:phone": "+1 513 733 1323",
    "sg:postcode": "45215",
    "sg:province": "OH",
    "sg:tags": [
      "cigarette",
      "mfg"
    ],
    "wof:name": "A K Cigarettes",
    "wof:placetype": "venue"
  },
  "geometry": {"coordinates":[-84.458112,39.245476],"type":"Point"}
}
