{
  "type": "Feature",
  "properties": {
    "addr:full": "339 South St Piqua OH 45356",
    "addr:housenumber": "339",
    "addr:postcode": "45356",
    "addr:street": "South St",
    "iso:country": "US",
    "sg:address": "339 South St",
    "sg:city": "Piqua",
    "sg:classifiers": [
      {
        "category": "Education",
        "subcategory": "School",
        "type": "Public Place"
      }
    ],
    "sg:phone": "+1 937 773 2574",
    "sg:postcode": "45356",
    "sg:province": "OH",
    "wof:name": "South Street Elementary School",
    "wof:placetype": "venue"
  },
  "geometry": {"coordinates":[-84.243361,40.140602],"type":"Point"}
}
