{
  "type": "Feature",
  "properties": {
    "iso:country":"US",
    "sg:address":"339 South St",
    "sg:city":"Piqua",
    "sg:classifiers":[
        {
            "category":"Education",
            "subcategory":"School",
            "type":"Public Place"
        }
    ],
    "sg:phone":"+1 937 773 2574",
    "sg:postcode":"45356",
    "sg:province":"OH",
    "wof:name":"South Street Elementary School",
    "wof:placetype":"venue"
},
  "geometry": {"coordinates":[-84.24336099999999,40.140602],"type":"Point"}
}