{
  "type": "Feature",
  "properties": {
    "addr:full":"14606 Larchmere Blvd Cleveland OH 44120",
    "addr:postcode":"14606;44120",
    "addr:street":"Larchmere Blvd",
    "iso:country":"US",
    "sg:address":"14606 Larchmere Blvd",
    "sg:city":"Cleveland",
    "sg:classifiers":[
        {
            "category":"Restaurant",
            "type":"Food & Drink"
        }
    ],
    "sg:phone":"+1 216 397 7715",
    "sg:postcode":"44120",
    "sg:province":"OH",
    "sg:tags":[
        "eating"
    ],
    "wof:name":"Kitchen Trainer",
    "wof:placetype":"venue"
},
  "geometry": {"coordinates":[-81.57920900000001,41.485962],"type":"Point"}
}