{
  "type": "Feature",
  "properties": {
    "addr:full": "49 Heid Dr Dayton OH 45404",
    "addr:housenumber": "49",
    "addr:postcode": "45404",
    "addr:street": "Heid Dr",
    "iso:country": "US",
    "sg:address": "49 Heid Dr",
    "sg:city": "Dayton",
    "sg:classifiers": [
      {
        "category": "Wholesale",
        "subcategory": "Machinery \u0026 Supplies",
        "type": "Manufacturing \u0026 Wholesale Goods"
      }
    ],
    "sg:phone": "+1 937 233 6606",
    "sg:postcode": "45404",
    "sg:province": "OH",
    "sg:tags": [
      "equipment",
      "establishment"
    ],
    "wof:name": "Suntek Labs",
    "wof:placetype": "venue"
  },
  "geometry": {"coordinates":[-84.171296,39.796184],"type":"Point"}
}
