{
  "type": "Feature",
  "properties": {
    "iso:country":"US",
    "sg:address":"49 Heid Dr",
    "sg:city":"Dayton",
    "sg:classifiers":[
        {
            "category":"Wholesale",
            "subcategory":"Machinery & Supplies",
            "type":"Manufacturing & Wholesale Goods"
        }
    ],
    "sg:phone":"+1 937 233 6606",
    "sg:postcode":"45404",
    "sg:province":"OH",
    "sg:tags":[
        "equipment",
        "establishment"
    ],
    "wof:name":"Suntek Labs",
    "wof:placetype":"venue"
},
  "geometry": {"coordinates":[-84.171296,39.796184],"type":"Point"}
}