{
  "type": "Feature",
  "properties": {
    "iso:country":"US",
    "sg:address":"2074 Andover Rd",
    "sg:city":"Columbus",
    "sg:classifiers":[
        {
            "category":"Real Estate",
            "subcategory":"Real Estate Agent",
            "type":"Services"
        }
    ],
    "sg:phone":"+1 614 487 8717",
    "sg:postcode":"43221",
    "sg:province":"OH",
    "sg:tags":[
        "inspection"
    ],
    "wof:name":"Stutz & Assoc",
    "wof:placetype":"venue"
},
  "geometry": {"coordinates":[-83.056822,39.99947],"type":"Point"}
}