{
  "type": "Feature",
  "properties": {
    "addr:full":"4889 Princess Diana Ct Hilliard OH 43026",
    "addr:housenumber":"4889",
    "addr:postcode":"43026",
    "addr:street":"Princess Diana Ct",
    "iso:country":"US",
    "sg:address":"4889 Princess Diana Ct",
    "sg:city":"Hilliard",
    "sg:classifiers":[
        {
            "category":"Real Estate",
            "subcategory":"Real Estate Operator",
            "type":"Services"
        }
    ],
    "sg:phone":"+1 614 527 9190",
    "sg:postcode":"43026",
    "sg:province":"OH",
    "sg:tags":[
        "apartment"
    ],
    "wof:name":"Pingue Rentals",
    "wof:placetype":"venue"
},
  "geometry": {"coordinates":[-83.16105,40.051258],"type":"Point"}
}