{
  "type": "Feature",
  "properties": {
    "iso:country":"US",
    "sg:address":"1101 Tiffin Ave",
    "sg:city":"Findlay",
    "sg:classifiers":[
        {
            "category":"Shopping",
            "type":"Retail Goods"
        }
    ],
    "sg:phone":"+1 419 423 3737",
    "sg:postcode":"45840",
    "sg:province":"OH",
    "sg:tags":[
        "machine",
        "equipment",
        "business"
    ],
    "wof:name":"Perry Corporation",
    "wof:placetype":"venue"
},
  "geometry": {"coordinates":[-83.625192,41.050326],"type":"Point"}
}