{
  "type": "Feature",
  "properties": {
    "iso:country":"US",
    "sg:address":"1115 Cherry St",
    "sg:city":"Toledo",
    "sg:classifiers":[
        {
            "category":"Retail",
            "subcategory":"Auto Repair",
            "type":"Services"
        }
    ],
    "sg:phone":"+1 419 241 3487",
    "sg:postcode":"43608",
    "sg:province":"OH",
    "sg:tags":[
        "automotive"
    ],
    "wof:name":"City Auto Radiator Co",
    "wof:placetype":"venue"
},
  "geometry": {"coordinates":[-83.535699,41.661165],"type":"Point"}
}