{
  "type": "Feature",
  "properties": {
    "addr:full":"10420 Airport Hwy Swanton OH 43558",
    "addr:housenumber":"10420",
    "addr:postcode":"43558",
    "addr:street":"Airport Hwy",
    "iso:country":"US",
    "sg:address":"10420 Airport Hwy",
    "sg:city":"Swanton",
    "sg:classifiers":[
        {
            "category":"Retail",
            "subcategory":"Auto Rental",
            "type":"Services"
        }
    ],
    "sg:phone":"+1 419 867 1843",
    "sg:postcode":"43558",
    "sg:province":"OH",
    "sg:tags":[
        "renting",
        "automobile"
    ],
    "wof:name":"Enterprise Rent A Car",
    "wof:placetype":"venue"
},
  "geometry": {"coordinates":[-83.789141,41.60207],"type":"Point"}
}