{
  "type": "Feature",
  "properties": {
    "addr:full": "10418 Wildcat Pike La Rue OH 43332",
    "addr:housenumber": "10418",
    "addr:postcode": "43332",
    "addr:street": "Wildcat Pike La Rue Oh",
    "iso:country": "US",
    "sg:address": "10418 Wildcat Pike",
    "sg:city": "La Rue",
    "sg:classifiers": [
      {
        "category": "Building \u0026 Trades",
        "subcategory": "Construction",
        "type": "Services"
      }
    ],
    "sg:phone": "+1 740 499 3839",
    "sg:postcode": "43332",
    "sg:province": "OH",
    "sg:tags": [
      "house"
    ],
    "wof:name": "American Builders",
    "wof:placetype": "venue"
  },
  "geometry": {"coordinates":[-83.419552,40.621921],"type":"Point"}
}
