{
  "type": "Feature",
  "properties": {
    "addr:full": "312 Collins Blvd Orrville OH 44667",
    "addr:housenumber": "312",
    "addr:postcode": "44667",
    "addr:street": "Collins Blvd",
    "iso:country": "US",
    "sg:address": "312 Collins Blvd",
    "sg:city": "Orrville",
    "sg:classifiers": [
      {
        "category": "Manufacturing",
        "subcategory": "Chemicals \u0026 Compounds",
        "type": "Manufacturing \u0026 Wholesale Goods"
      }
    ],
    "sg:phone": "+1 330 684 2310",
    "sg:postcode": "44667",
    "sg:province": "OH",
    "sg:tags": [
      "salt",
      "mfg"
    ],
    "wof:name": "Morton International Inc",
    "wof:placetype": "venue"
  },
  "geometry": {"coordinates":[-81.761289,40.862657],"type":"Point"}
}
