{
  "type": "Feature",
  "properties": {
    "iso:country":"US",
    "sg:address":"840 S Vandemark Rd",
    "sg:city":"Sidney",
    "sg:classifiers":[
        {
            "category":"Building & Trades",
            "subcategory":"Electrical",
            "type":"Services"
        }
    ],
    "sg:phone":"+1 937 498 2357",
    "sg:postcode":"45365",
    "sg:province":"OH",
    "sg:tags":[
        "electric",
        "contractor"
    ],
    "sg:website":"www.sidneyelectric.com",
    "wof:name":"Sidney Electric Co",
    "wof:placetype":"venue"
},
  "geometry": {"coordinates":[-84.187736,40.276556],"type":"Point"}
}