{
  "type": "Feature",
  "properties": {
    "iso:country":"US",
    "sg:address":"10397 W Pleasant Valley Rd",
    "sg:city":"Cleveland",
    "sg:classifiers":[
        {
            "category":"Retail",
            "subcategory":"Veterinary Services",
            "type":"Services"
        }
    ],
    "sg:phone":"+1 440 842 0303",
    "sg:postcode":"44130",
    "sg:province":"OH",
    "wof:name":"William R Clark Inc",
    "wof:placetype":"venue"
},
  "geometry": {"coordinates":[-81.753884,41.363811],"type":"Point"}
}