{
  "type": "Feature",
  "properties": {
    "addr:full": "26022 Oregon Rd Perrysburg OH 43551",
    "addr:housenumber": "26022",
    "addr:postcode": "43551",
    "addr:street": "Oregon Rd",
    "iso:country": "US",
    "sg:address": "26022 Oregon Rd",
    "sg:city": "Perrysburg",
    "sg:classifiers": [
      {
        "category": "Building \u0026 Trades",
        "subcategory": "Electrical",
        "type": "Services"
      }
    ],
    "sg:phone": "+1 419 837 2111",
    "sg:postcode": "43551",
    "sg:province": "OH",
    "sg:tags": [
      "electric",
      "contractor"
    ],
    "wof:name": "Clark Electric",
    "wof:placetype": "venue"
  },
  "geometry": {"coordinates":[-83.538242,41.530021],"type":"Point"}
}
