{
  "type": "Feature",
  "properties": {
    "iso:country":"US",
    "sg:address":"26022 Oregon Rd",
    "sg:city":"Perrysburg",
    "sg:classifiers":[
        {
            "category":"Building & Trades",
            "subcategory":"Electrical",
            "type":"Services"
        }
    ],
    "sg:phone":"+1 419 837 2111",
    "sg:postcode":"43551",
    "sg:province":"OH",
    "sg:tags":[
        "electric",
        "contractor"
    ],
    "wof:name":"Clark Electric",
    "wof:placetype":"venue"
},
  "geometry": {"coordinates":[-83.538242,41.530021],"type":"Point"}
}