{
  "type": "Feature",
  "properties": {
    "addr:full": "1958 State Rte 125 Amelia OH 45102",
    "addr:housenumber": "1958",
    "addr:postcode": "45102",
    "addr:street": "State Rte 125",
    "iso:country": "US",
    "sg:address": "1958 State Rte 125",
    "sg:city": "Amelia",
    "sg:classifiers": [
      {
        "category": "Freight",
        "type": "Transportation"
      }
    ],
    "sg:phone": "+1 513 797 8515",
    "sg:postcode": "45102",
    "sg:province": "OH",
    "sg:tags": [
      "storage"
    ],
    "wof:name": "125 Storage",
    "wof:placetype": "venue"
  },
  "geometry": {"coordinates":[-84.187988,39.015949],"type":"Point"}
}
