{
  "type": "Feature",
  "properties": {
    "addr:full": "32402 Electric Blvd Avon Lake OH 44012",
    "addr:housenumber": "32402",
    "addr:postcode": "44012",
    "addr:street": "Electric Blvd",
    "iso:country": "US",
    "sg:address": "32402 Electric Blvd",
    "sg:city": "Avon Lake",
    "sg:classifiers": [
      {
        "category": "Organizations",
        "subcategory": "Community Association",
        "type": "Services"
      }
    ],
    "sg:phone": "+1 440 244 6376",
    "sg:postcode": "44012",
    "sg:province": "OH",
    "sg:tags": [
      "military"
    ],
    "wof:name": "Disabled American Veterans",
    "wof:placetype": "venue"
  },
  "geometry": {"coordinates":[-82.002318,41.510595],"type":"Point"}
}
