{
  "type": "Feature",
  "properties": {
    "iso:country":"US",
    "sg:address":"34675 Melinz Pkwy",
    "sg:city":"Willoughby",
    "sg:classifiers":[
        {
            "category":"Professional",
            "type":"Services"
        }
    ],
    "sg:phone":"+1 440 269 8046",
    "sg:postcode":"44095",
    "sg:province":"OH",
    "sg:tags":[
        "establishment"
    ],
    "wof:name":"Inogen",
    "wof:placetype":"venue"
},
  "geometry": {"coordinates":[-81.444164,41.636525],"type":"Point"}
}