{
  "type": "Feature",
  "properties": {
    "addr:full": "5919 Hamilton Ave Cincinnati OH 45224",
    "addr:housenumber": "5919",
    "addr:postcode": "45224",
    "addr:street": "Hamilton Ave",
    "iso:country": "US",
    "sg:address": "5919 Hamilton Ave",
    "sg:city": "Cincinnati",
    "sg:classifiers": [
      {
        "category": "Home \u0026 Garden",
        "subcategory": "Furniture",
        "type": "Retail Goods"
      }
    ],
    "sg:phone": "+1 513 541 1617",
    "sg:postcode": "45224",
    "sg:province": "OH",
    "sg:tags": [
      "floor",
      "covering"
    ],
    "wof:name": "Brill Cherry House",
    "wof:placetype": "venue"
  },
  "geometry": {"coordinates":[-84.547128,39.199342],"type":"Point"}
}
