{
  "type": "Feature",
  "properties": {
    "addr:full":"320 Galena Ave Zanesville OH 43701",
    "addr:housenumber":"320",
    "addr:postcode":"43701",
    "addr:street":"Galena Ave",
    "iso:country":"US",
    "sg:address":"320 Galena Ave",
    "sg:city":"Zanesville",
    "sg:classifiers":[
        {
            "category":"Arts & Performance",
            "subcategory":"Theater",
            "type":"Entertainment"
        }
    ],
    "sg:phone":"+1 740 588 0344",
    "sg:postcode":"43701",
    "sg:province":"OH",
    "sg:tags":[
        "live",
        "music"
    ],
    "wof:name":"Classic Good Times DJ Entrtn",
    "wof:placetype":"venue"
},
  "geometry": {"coordinates":[-82.038594,39.952523],"type":"Point"}
}