{
  "type": "Feature",
  "properties": {
    "addr:full": "9601 Community Rd Windham OH 44288",
    "addr:housenumber": "9601",
    "addr:postcode": "44288",
    "addr:street": "Community Rd",
    "iso:country": "US",
    "sg:address": "9601 Community Rd",
    "sg:city": "Windham",
    "sg:classifiers": [
      {
        "category": "Building \u0026 Trades",
        "subcategory": "Construction",
        "type": "Services"
      }
    ],
    "sg:phone": "+1 330 348 6344",
    "sg:postcode": "44288",
    "sg:province": "OH",
    "sg:tags": [
      "siding",
      "contractor"
    ],
    "wof:name": "Better Deals",
    "wof:placetype": "venue"
  },
  "geometry": {"coordinates":[-81.046949,41.237196],"type":"Point"}
}
