{
  "type": "Feature",
  "properties": {
    "iso:country":"US",
    "sg:address":"1300 N Locust St",
    "sg:city":"Ottawa",
    "sg:classifiers":[
        {
            "category":"Banks & Credit Unions",
            "subcategory":"Bank",
            "type":"Services"
        }
    ],
    "sg:phone":"+1 419 523 3013",
    "sg:postcode":"45875",
    "sg:province":"OH",
    "wof:name":"Fort Jennings State Bank",
    "wof:placetype":"venue"
},
  "geometry": {"coordinates":[-84.04414800000001,41.031899],"type":"Point"}
}