{
  "type": "Feature",
  "properties": {
    "addr:full": "1300 N Locust St Ottawa OH 45875",
    "addr:housenumber": "1300",
    "addr:postcode": "45875",
    "addr:street": "N Locust St",
    "iso:country": "US",
    "sg:address": "1300 N Locust St",
    "sg:city": "Ottawa",
    "sg:classifiers": [
      {
        "category": "Banks \u0026 Credit Unions",
        "subcategory": "Bank",
        "type": "Services"
      }
    ],
    "sg:phone": "+1 419 523 3013",
    "sg:postcode": "45875",
    "sg:province": "OH",
    "wof:name": "Fort Jennings State Bank",
    "wof:placetype": "venue"
  },
  "geometry": {"coordinates":[-84.044148,41.031899],"type":"Point"}
}
