{
  "type": "Feature",
  "properties": {
    "iso:country":"US",
    "sg:address":"10948 E Bayshore Rd",
    "sg:city":"Lakeside Marblhd",
    "sg:classifiers":[
        {
            "category":"Travel",
            "subcategory":"Hotels & Motels",
            "type":"Entertainment"
        }
    ],
    "sg:phone":"+1 419 798 4434",
    "sg:postcode":"43440",
    "sg:province":"OH",
    "sg:tags":[
        "resort"
    ],
    "sg:website":"www.baypointmarina.com",
    "wof:name":"Bay Point Marina",
    "wof:placetype":"venue"
},
  "geometry": {"coordinates":[-82.71721100000001,41.52323],"type":"Point"}
}