{
  "type": "Feature",
  "properties": {
    "addr:full": "6164 Co Hwy 165 Genoa OH 43430",
    "addr:housenumber": "6164",
    "addr:postcode": "43430",
    "addr:street": "Co Hwy 165",
    "iso:country": "US",
    "sg:address": "6164 Co Hwy 165",
    "sg:city": "Genoa",
    "sg:classifiers": [
      {
        "category": "Autos \u0026 Motor Vehicles",
        "subcategory": "Fuel \u0026 Gas Station",
        "type": "Retail Goods"
      }
    ],
    "sg:phone": "+1 419 855 4055",
    "sg:postcode": "43430",
    "sg:province": "OH",
    "sg:tags": [
      "station",
      "gasoline"
    ],
    "wof:name": "Sunoco",
    "wof:placetype": "venue"
  },
  "geometry": {"coordinates":[-83.361907,41.486407],"type":"Point"}
}
