{
  "type": "Feature",
  "properties": {
    "iso:country":"US",
    "sg:address":"6164 Co Hwy 165",
    "sg:city":"Genoa",
    "sg:classifiers":[
        {
            "category":"Autos & Motor Vehicles",
            "subcategory":"Fuel & Gas Station",
            "type":"Retail Goods"
        }
    ],
    "sg:phone":"+1 419 855 4055",
    "sg:postcode":"43430",
    "sg:province":"OH",
    "sg:tags":[
        "station",
        "gasoline"
    ],
    "wof:name":"Sunoco",
    "wof:placetype":"venue"
},
  "geometry": {"coordinates":[-83.361907,41.486407],"type":"Point"}
}