{
  "type": "Feature",
  "properties": {
    "addr:full": "987 Weisflock Rd Lynchburg OH 45142",
    "addr:housenumber": "987",
    "addr:postcode": "45142",
    "addr:street": "Weisflock Rd",
    "iso:country": "US",
    "sg:address": "987 Weisflock Rd",
    "sg:city": "Lynchburg",
    "sg:phone": "+1 937 364 6827",
    "sg:postcode": "45142",
    "sg:province": "OH",
    "sg:tags": [
      "farm",
      "corn",
      "soybean"
    ],
    "wof:name": "Kevin Beebe",
    "wof:placetype": "venue"
  },
  "geometry": {"coordinates":[-83.858971,39.251339],"type":"Point"}
}
