{
  "type": "Feature",
  "properties": {
    "addr:full": "6555 Warren-Sharon Rd Bristolville OH 44403",
    "addr:housenumber": "6555",
    "addr:postcode": "44403",
    "addr:street": "Warren-Sharon Rd",
    "iso:country": "US",
    "sg:address": "6555 Warren-Sharon Rd",
    "sg:city": "Bristolville",
    "sg:classifiers": [
      {
        "category": "Manufacturing",
        "subcategory": "Tools \u0026 Machinery",
        "type": "Manufacturing \u0026 Wholesale Goods"
      }
    ],
    "sg:phone": "+1 724 699 4951",
    "sg:postcode": "44403",
    "sg:province": "OH",
    "sg:tags": [
      "machine",
      "shop"
    ],
    "wof:name": "Brown's Machine Shop",
    "wof:placetype": "venue"
  },
  "geometry": {"coordinates":[-80.5841,41.235866],"type":"Point"}
}
