{
  "type": "Feature",
  "properties": {
    "addr:full":"8 N Main St Kenton OH 43326",
    "addr:housenumber":"8",
    "addr:postcode":"43326",
    "addr:street":"N Main St",
    "iso:country":"US",
    "sg:address":"8 N Main St",
    "sg:city":"Kenton",
    "sg:classifiers":[
        {
            "category":"Professional",
            "subcategory":"Accounting & Tax Preparation",
            "type":"Services"
        }
    ],
    "sg:phone":"+1 419 674 4465",
    "sg:postcode":"43326",
    "sg:province":"OH",
    "sg:tags":[
        "bookkeeping",
        "general"
    ],
    "wof:name":"Brooks Tax Office",
    "wof:placetype":"venue"
},
  "geometry": {"coordinates":[-83.60786299999999,40.648087],"type":"Point"}
}