{
  "type": "Feature",
  "properties": {
    "addr:full": "1348 Lexington Ave Mansfield OH 44907",
    "addr:housenumber": "1348",
    "addr:postcode": "44907",
    "addr:street": "Lexington Ave",
    "iso:country": "US",
    "sg:address": "1348 Lexington Ave",
    "sg:city": "Mansfield",
    "sg:classifiers": [
      {
        "category": "Personal",
        "subcategory": "Beauty Salon",
        "type": "Services"
      }
    ],
    "sg:phone": "+1 419 756 2237",
    "sg:postcode": "44907",
    "sg:province": "OH",
    "sg:tags": [
      "shop"
    ],
    "wof:name": "Duchess Hair Stylists",
    "wof:placetype": "venue"
  },
  "geometry": {"coordinates":[-82.54339,40.721537],"type":"Point"}
}
