{
  "type": "Feature",
  "properties": {
    "addr:full":"29550 Detroit Rd Westlake OH 44145",
    "addr:housenumber":"29550",
    "addr:postcode":"44145",
    "addr:street":"Detroit Rd",
    "iso:country":"US",
    "sg:address":"29550 Detroit Rd",
    "sg:city":"Westlake",
    "sg:classifiers":[
        {
            "category":"Banks & Credit Unions",
            "subcategory":"Financial Services",
            "type":"Services"
        }
    ],
    "sg:phone":"+1 440 892 5050",
    "sg:postcode":"44145",
    "sg:province":"OH",
    "sg:tags":[
        "company",
        "management",
        "investment"
    ],
    "wof:name":"Chimera Corporation",
    "wof:placetype":"venue"
},
  "geometry": {"coordinates":[-81.950469,41.463885],"type":"Point"}
}