{
  "type": "Feature",
  "properties": {
    "iso:country":"US",
    "sg:address":"5853 Everwood Rd",
    "sg:city":"Toledo",
    "sg:classifiers":[
        {
            "category":"Banks & Credit Unions",
            "subcategory":"Financial Services",
            "type":"Services"
        }
    ],
    "sg:phone":"+1 419 474 8477",
    "sg:postcode":"43613",
    "sg:province":"OH",
    "sg:tags":[
        "trust",
        "management"
    ],
    "wof:name":"Henley Family Living Trust",
    "wof:placetype":"venue"
},
  "geometry": {"coordinates":[-83.609212,41.724341],"type":"Point"}
}