{
  "type": "Feature",
  "properties": {
    "addr:full":"223 Blackmoor Dr Byesville OH 43723",
    "addr:housenumber":"223",
    "addr:postcode":"43723",
    "addr:street":"Blackmoor Dr",
    "iso:country":"US",
    "sg:address":"223 Blackmoor Dr",
    "sg:city":"Byesville",
    "sg:classifiers":[
        {
            "category":"Organizations",
            "subcategory":"Religious Organization",
            "type":"Services"
        }
    ],
    "sg:phone":"+1 740 685 9941",
    "sg:postcode":"43723",
    "sg:province":"OH",
    "wof:name":"Corporation of President of Th",
    "wof:placetype":"venue"
},
  "geometry": {"coordinates":[-81.545799,39.971022],"type":"Point"}
}