{
  "type": "Feature",
  "properties": {
    "addr:full": "7033 Mill Rd Brecksville OH 44141",
    "addr:housenumber": "7033",
    "addr:postcode": "44141",
    "addr:street": "Mill Rd",
    "iso:country": "US",
    "sg:address": "7033 Mill Rd",
    "sg:city": "Brecksville",
    "sg:classifiers": [
      {
        "category": "Recreation",
        "subcategory": "Amusement Park",
        "type": "Entertainment"
      },
      {
        "category": "Recreation",
        "type": "Entertainment"
      }
    ],
    "sg:phone": "+1 440 838 5138",
    "sg:postcode": "44141",
    "sg:province": "OH",
    "sg:tags": [
      "baseball",
      "good",
      "instruction",
      "batting"
    ],
    "wof:name": "Fielders Choice Baseball Inc",
    "wof:placetype": "venue"
  },
  "geometry": {"coordinates":[-81.631715,41.326792],"type":"Point"}
}
