{
  "type": "Feature",
  "properties": {
    "iso:country":"US",
    "sg:address":"801 3rd St",
    "sg:city":"Cincinnati",
    "sg:classifiers":[
        {
            "category":"Building & Trades",
            "subcategory":"Construction",
            "type":"Services"
        }
    ],
    "sg:phone":"+1 513 821 6841",
    "sg:postcode":"45215",
    "sg:province":"OH",
    "sg:tags":[
        "concrete",
        "contractor"
    ],
    "wof:name":"Gertz Construction Co",
    "wof:placetype":"venue"
},
  "geometry": {"coordinates":[-84.44001900000001,39.221079],"type":"Point"}
}