{
  "type": "Feature",
  "properties": {
    "iso:country":"US",
    "sg:address":"2168 Cloverleaf St E",
    "sg:city":"Columbus",
    "sg:classifiers":[
        {
            "category":"Local Transit",
            "type":"Transportation"
        }
    ],
    "sg:phone":"+1 614 501 3612",
    "sg:postcode":"43232",
    "sg:province":"OH",
    "sg:tags":[
        "handicapped"
    ],
    "wof:name":"G L Transportation",
    "wof:placetype":"venue"
},
  "geometry": {"coordinates":[-82.873057,39.932566],"type":"Point"}
}