{
  "type": "Feature",
  "properties": {
    "addr:full": "2006 Glendale Ave Toledo OH 43614",
    "addr:housenumber": "2006",
    "addr:postcode": "43614",
    "addr:street": "Glendale Ave",
    "iso:country": "US",
    "sg:address": "2006 Glendale Ave",
    "sg:city": "Toledo",
    "sg:classifiers": [
      {
        "category": "Building \u0026 Trades",
        "subcategory": "Landscaping Services",
        "type": "Services"
      }
    ],
    "sg:phone": "+1 419 917 4437",
    "sg:postcode": "43614",
    "sg:province": "OH",
    "sg:tags": [
      "tree"
    ],
    "wof:name": "American Arbor Tech Tree Svc",
    "wof:placetype": "venue"
  },
  "geometry": {"coordinates":[-83.593681,41.612451],"type":"Point"}
}
