{
  "type": "Feature",
  "properties": {
    "iso:country":"US",
    "sg:address":"556 Center St W",
    "sg:city":"Warren",
    "sg:classifiers":[
        {
            "category":"Organizations",
            "subcategory":"Religious Organization",
            "type":"Services"
        }
    ],
    "sg:phone":"+1 330 847 7735",
    "sg:postcode":"44481",
    "sg:province":"OH",
    "sg:tags":[
        "church"
    ],
    "wof:name":"Champion Baptist Church",
    "wof:placetype":"venue"
},
  "geometry": {"coordinates":[-80.866587,41.308471],"type":"Point"}
}