{
  "type": "Feature",
  "properties": {
    "addr:full": "602 Main St Cincinnati OH 45202",
    "addr:housenumber": "602",
    "addr:postcode": "45202",
    "addr:street": "Main St",
    "iso:country": "US",
    "sg:address": "602 Main St",
    "sg:city": "Cincinnati",
    "sg:classifiers": [
      {
        "category": "Wholesale",
        "subcategory": "Electrical",
        "type": "Manufacturing \u0026 Wholesale Goods"
      }
    ],
    "sg:phone": "+1 513 621 6677",
    "sg:postcode": "45202",
    "sg:province": "OH",
    "sg:tags": [
      "line",
      "video",
      "telecommunication",
      "for"
    ],
    "wof:name": "Cosmic Inventions Ltd",
    "wof:placetype": "venue"
  },
  "geometry": {"coordinates":[-84.510179,39.103548],"type":"Point"}
}
