{
  "type": "Feature",
  "properties": {
    "iso:country":"US",
    "sg:address":"3619 Walton Ave",
    "sg:city":"Cleveland",
    "sg:classifiers":[
        {
            "category":"Shopping",
            "subcategory":"Photographic Equipment",
            "type":"Retail Goods"
        }
    ],
    "sg:phone":"+1 216 961 9093",
    "sg:postcode":"44113",
    "sg:province":"OH",
    "sg:tags":[
        "supply"
    ],
    "wof:name":"Hildebrandt Photographic",
    "wof:placetype":"venue"
},
  "geometry": {"coordinates":[-81.709772,41.470899],"type":"Point"}
}