{
  "type": "Feature",
  "properties": {
    "addr:full":"203 Cleveland Ave NW Canton OH 44702",
    "addr:housenumber":"203",
    "addr:postcode":"44702",
    "addr:street":"Cleveland Ave Nw",
    "iso:country":"US",
    "sg:address":"203 Cleveland Ave NW",
    "sg:city":"Canton",
    "sg:classifiers":[
        {
            "category":"Professional",
            "subcategory":"Accounting & Tax Preparation",
            "type":"Services"
        }
    ],
    "sg:phone":"+1 330 452 5831",
    "sg:postcode":"44702",
    "sg:province":"OH",
    "sg:tags":[
        "bookkeeping",
        "general"
    ],
    "wof:name":"Quality Bookkeeping Svc",
    "wof:placetype":"venue"
},
  "geometry": {"coordinates":[-81.376125,40.800223],"type":"Point"}
}