{
  "type": "Feature",
  "properties": {
    "iso:country":"US",
    "sg:address":"13366 Walnut Trce",
    "sg:city":"Chardon",
    "sg:classifiers":[
        {
            "category":"Building & Trades",
            "subcategory":"Construction",
            "type":"Services"
        }
    ],
    "sg:phone":"+1 440 564 7446",
    "sg:postcode":"44024",
    "sg:province":"OH",
    "sg:tags":[
        "house"
    ],
    "wof:name":"S F Remodeling Inc",
    "wof:placetype":"venue"
},
  "geometry": {"coordinates":[-81.230338,41.503529],"type":"Point"}
}