{
  "type": "Feature",
  "properties": {
    "addr:full": "6404 Rosewood St Cincinnati OH 45216",
    "addr:housenumber": "6404",
    "addr:postcode": "45216",
    "addr:street": "Rosewood St",
    "iso:country": "US",
    "sg:address": "6404 Rosewood St",
    "sg:city": "Cincinnati",
    "sg:classifiers": [
      {
        "category": "Building \u0026 Trades",
        "subcategory": "Construction",
        "type": "Services"
      }
    ],
    "sg:phone": "+1 513 242 8715",
    "sg:postcode": "45216",
    "sg:province": "OH",
    "sg:tags": [
      "painter"
    ],
    "wof:name": "Mc Partlin's Painting \u0026 Paper",
    "wof:placetype": "venue"
  },
  "geometry": {"coordinates":[-84.489476,39.190701],"type":"Point"}
}
