{
  "type": "Feature",
  "properties": {
    "addr:full": "2040 Commerce Dr Sidney OH 45365",
    "addr:housenumber": "2040",
    "addr:postcode": "45365",
    "addr:street": "Commerce Dr",
    "iso:country": "US",
    "sg:address": "2040 Commerce Dr",
    "sg:city": "Sidney",
    "sg:classifiers": [
      {
        "category": "Manufacturing",
        "subcategory": "Tools \u0026 Machinery",
        "type": "Manufacturing \u0026 Wholesale Goods"
      }
    ],
    "sg:phone": "+1 937 492 8662",
    "sg:postcode": "45365",
    "sg:province": "OH",
    "sg:tags": [
      "machine",
      "shop"
    ],
    "sg:website": "www.aandbmachine.com",
    "wof:name": "A \u0026 B Machine Inc",
    "wof:placetype": "venue"
  },
  "geometry": {"coordinates":[-84.169755,40.307145],"type":"Point"}
}
