{
  "type": "Feature",
  "properties": {
    "iso:country":"US",
    "sg:address":"2040 Commerce Dr",
    "sg:city":"Sidney",
    "sg:classifiers":[
        {
            "category":"Manufacturing",
            "subcategory":"Tools & Machinery",
            "type":"Manufacturing & Wholesale Goods"
        }
    ],
    "sg:phone":"+1 937 492 8662",
    "sg:postcode":"45365",
    "sg:province":"OH",
    "sg:tags":[
        "machine",
        "shop"
    ],
    "sg:website":"www.aandbmachine.com",
    "wof:name":"A & B Machine Inc",
    "wof:placetype":"venue"
},
  "geometry": {"coordinates":[-84.16975499999999,40.307145],"type":"Point"}
}