{
  "type": "Feature",
  "properties": {
    "iso:country":"US",
    "sg:address":"3214 Beresford Ave",
    "sg:city":"Cincinnati",
    "sg:classifiers":[
        {
            "category":"Building & Trades",
            "subcategory":"Cleaning & Sanitation",
            "type":"Services"
        }
    ],
    "sg:phone":"+1 513 961 3394",
    "sg:postcode":"45206",
    "sg:province":"OH",
    "sg:tags":[
        "janitor"
    ],
    "wof:name":"LDM & Conn",
    "wof:placetype":"venue"
},
  "geometry": {"coordinates":[-84.483785,39.137734],"type":"Point"}
}