{
  "type": "Feature",
  "properties": {
    "addr:full": "3214 Beresford Ave Cincinnati OH 45206",
    "addr:housenumber": "3214",
    "addr:postcode": "45206",
    "addr:street": "Beresford Ave",
    "iso:country": "US",
    "sg:address": "3214 Beresford Ave",
    "sg:city": "Cincinnati",
    "sg:classifiers": [
      {
        "category": "Building \u0026 Trades",
        "subcategory": "Cleaning \u0026 Sanitation",
        "type": "Services"
      }
    ],
    "sg:phone": "+1 513 961 3394",
    "sg:postcode": "45206",
    "sg:province": "OH",
    "sg:tags": [
      "janitor"
    ],
    "wof:name": "LDM \u0026 Conn",
    "wof:placetype": "venue"
  },
  "geometry": {"coordinates":[-84.483785,39.137734],"type":"Point"}
}
