{
  "type": "Feature",
  "properties": {
    "iso:country":"US",
    "sg:address":"756 Ohio Pike",
    "sg:city":"Cincinnati",
    "sg:classifiers":[
        {
            "category":"Social Services",
            "subcategory":"Child Care",
            "type":"Services"
        }
    ],
    "sg:phone":"+1 513 752 2811",
    "sg:postcode":"45245",
    "sg:province":"OH",
    "sg:tags":[
        "day"
    ],
    "wof:name":"Kids First Acad",
    "wof:placetype":"venue"
},
  "geometry": {"coordinates":[-84.284599,39.064899],"type":"Point"}
}