{
  "type": "Feature",
  "properties": {
    "iso:country":"US",
    "sg:address":"9337 Stonington Rd",
    "sg:city":"Cleveland",
    "sg:classifiers":[
        {
            "category":"Manufacturing",
            "subcategory":"Printing",
            "type":"Manufacturing & Wholesale Goods"
        }
    ],
    "sg:phone":"+1 440 888 2966",
    "sg:postcode":"44130",
    "sg:province":"OH",
    "sg:tags":[
        "reporting",
        "publishing"
    ],
    "wof:name":"Composition Corner",
    "wof:placetype":"venue"
},
  "geometry": {"coordinates":[-81.75053800000001,41.394178],"type":"Point"}
}