{
  "type": "Feature",
  "properties": {
    "addr:full": "9337 Stonington Rd Cleveland OH 44130",
    "addr:housenumber": "9337",
    "addr:postcode": "44130",
    "addr:street": "Stonington Rd",
    "iso:country": "US",
    "sg:address": "9337 Stonington Rd",
    "sg:city": "Cleveland",
    "sg:classifiers": [
      {
        "category": "Manufacturing",
        "subcategory": "Printing",
        "type": "Manufacturing \u0026 Wholesale Goods"
      }
    ],
    "sg:phone": "+1 440 888 2966",
    "sg:postcode": "44130",
    "sg:province": "OH",
    "sg:tags": [
      "reporting",
      "publishing"
    ],
    "wof:name": "Composition Corner",
    "wof:placetype": "venue"
  },
  "geometry": {"coordinates":[-81.750538,41.394178],"type":"Point"}
}
