{
  "type": "Feature",
  "properties": {
    "iso:country":"US",
    "sg:address":"32142 Oak St",
    "sg:city":"Hanoverton",
    "sg:classifiers":[
        {
            "category":"Professional",
            "type":"Services"
        }
    ],
    "sg:phone":"+1 330 222 2014",
    "sg:postcode":"44423",
    "sg:province":"OH",
    "wof:name":"Ruritan National Corp",
    "wof:placetype":"venue"
},
  "geometry": {"coordinates":[-80.885987,40.796323],"type":"Point"}
}