{
  "type": "Feature",
  "properties": {
    "iso:country":"US",
    "sg:address":"1700 E 13th St",
    "sg:city":"Cleveland",
    "sg:classifiers":[
        {
            "category":"Professional",
            "subcategory":"Management & Consulting",
            "type":"Services"
        }
    ],
    "sg:phone":"+1 216 771 1147",
    "sg:postcode":"44114",
    "sg:province":"OH",
    "sg:tags":[
        "information",
        "traffic",
        "radio"
    ],
    "wof:name":"Metro Networks Communications",
    "wof:placetype":"venue"
},
  "geometry": {"coordinates":[-81.68372599999999,41.502916],"type":"Point"}
}