{
  "type": "Feature",
  "properties": {
    "iso:country":"US",
    "sg:address":"8336 Pitsburg-Laura Rd",
    "sg:city":"Arcanum",
    "sg:classifiers":[
        {
            "category":"Wholesale",
            "subcategory":"Farm Supplies",
            "type":"Manufacturing & Wholesale Goods"
        }
    ],
    "sg:phone":"+1 937 692 8108",
    "sg:postcode":"45304",
    "sg:province":"OH",
    "wof:name":"Garden Buddies",
    "wof:placetype":"venue"
},
  "geometry": {"coordinates":[-84.492221,39.99107],"type":"Point"}
}