{
  "type": "Feature",
  "properties": {
    "iso:country":"US",
    "sg:address":"502 Middle St",
    "sg:city":"Archbold",
    "sg:classifiers":[
        {
            "category":"Manufacturing",
            "subcategory":"Furniture",
            "type":"Manufacturing & Wholesale Goods"
        }
    ],
    "sg:phone":"+1 419 446 2711",
    "sg:postcode":"43502",
    "sg:province":"OH",
    "sg:tags":[
        "household"
    ],
    "sg:website":"www.sauderwoodworking.com",
    "wof:name":"Sauder Woodworking Co",
    "wof:placetype":"venue"
},
  "geometry": {"coordinates":[-84.302583,41.516944],"type":"Point"}
}