{
  "type": "Feature",
  "properties": {
    "iso:country":"US",
    "sg:address":"14882 Twp Rd 453",
    "sg:city":"Lakeville",
    "sg:classifiers":[
        {
            "category":"Professional",
            "subcategory":"Accounting & Tax Preparation",
            "type":"Services"
        }
    ],
    "sg:phone":"+1 330 378 9901",
    "sg:postcode":"44638",
    "sg:province":"OH",
    "sg:tags":[
        "accountant"
    ],
    "wof:name":"Michael R Kassinger CPA",
    "wof:placetype":"venue"
},
  "geometry": {"coordinates":[-82.157479,40.602661],"type":"Point"}
}