{
  "type": "Feature",
  "properties": {
    "iso:country":"US",
    "sg:address":"5870 Mayfield Rd",
    "sg:city":"Cleveland",
    "sg:classifiers":[
        {
            "category":"Shopping",
            "subcategory":"Discount & Variety Stores",
            "type":"Retail Goods"
        }
    ],
    "sg:phone":"+1 440 460 1723",
    "sg:postcode":"44124",
    "sg:province":"OH",
    "sg:tags":[
        "merchandise",
        "general"
    ],
    "wof:name":"Qq Dollar City Inc",
    "wof:placetype":"venue"
},
  "geometry": {"coordinates":[-81.468934,41.519967],"type":"Point"}
}