{
  "type": "Feature",
  "properties": {
    "addr:full": "5870 Mayfield Rd Cleveland OH 44124",
    "addr:housenumber": "5870",
    "addr:postcode": "44124",
    "addr:street": "Mayfield Rd",
    "iso:country": "US",
    "sg:address": "5870 Mayfield Rd",
    "sg:city": "Cleveland",
    "sg:classifiers": [
      {
        "category": "Shopping",
        "subcategory": "Discount \u0026 Variety Stores",
        "type": "Retail Goods"
      }
    ],
    "sg:phone": "+1 440 460 1723",
    "sg:postcode": "44124",
    "sg:province": "OH",
    "sg:tags": [
      "merchandise",
      "general"
    ],
    "wof:name": "Qq Dollar City Inc",
    "wof:placetype": "venue"
  },
  "geometry": {"coordinates":[-81.468934,41.519967],"type":"Point"}
}
