{
  "type": "Feature",
  "properties": {
    "addr:full": "408 Main St Delta OH 43515",
    "addr:housenumber": "408",
    "addr:postcode": "43515",
    "addr:street": "Main St",
    "iso:country": "US",
    "sg:address": "408 Main St",
    "sg:city": "Delta",
    "sg:classifiers": [
      {
        "category": "Real Estate",
        "subcategory": "Real Estate Agent",
        "type": "Services"
      }
    ],
    "sg:phone": "+1 419 822 4660",
    "sg:postcode": "43515",
    "sg:province": "OH",
    "wof:name": "Danberry Co",
    "wof:placetype": "venue"
  },
  "geometry": {"coordinates":[-84.003579,41.573916],"type":"Point"}
}
