{
  "type": "Feature",
  "properties": {
    "addr:full":"4201 W Hillcrest Ave Dayton OH 45406",
    "addr:housenumber":"4201",
    "addr:postcode":"45406",
    "addr:street":"W Hillcrest Ave",
    "iso:country":"US",
    "sg:address":"4201 W Hillcrest Ave",
    "sg:city":"Dayton",
    "sg:classifiers":[
        {
            "category":"Organizations",
            "subcategory":"Religious Organization",
            "type":"Services"
        }
    ],
    "sg:phone":"+1 937 278 8453",
    "sg:postcode":"45406",
    "sg:province":"OH",
    "sg:tags":[
        "church"
    ],
    "wof:name":"Hillcrest Avenue Seventh Day",
    "wof:placetype":"venue"
},
  "geometry": {"coordinates":[-84.25276599999999,39.790651],"type":"Point"}
}