{
  "type": "Feature",
  "properties": {
    "iso:country":"US",
    "sg:address":"600 Shorb Ave NW",
    "sg:city":"Canton",
    "sg:classifiers":[
        {
            "category":"Retail",
            "subcategory":"Auto Repair",
            "type":"Services"
        }
    ],
    "sg:phone":"+1 330 453 2050",
    "sg:postcode":"44703",
    "sg:province":"OH",
    "sg:tags":[
        "repairing",
        "automobile"
    ],
    "wof:name":"All Brake Specialist",
    "wof:placetype":"venue"
},
  "geometry": {"coordinates":[-81.380624,40.804201],"type":"Point"}
}