{
  "type": "Feature",
  "properties": {
    "iso:country":"US",
    "sg:address":"7406 W Central Ave",
    "sg:city":"Toledo",
    "sg:classifiers":[
        {
            "category":"Professional",
            "type":"Services"
        }
    ],
    "sg:phone":"+1 419 843 7596",
    "sg:postcode":"43617",
    "sg:province":"OH",
    "sg:tags":[
        "establishment"
    ],
    "wof:name":"Deepan India",
    "wof:placetype":"venue"
},
  "geometry": {"coordinates":[-83.722202,41.673952],"type":"Point"}
}