{
  "type": "Feature",
  "properties": {
    "iso:country":"US",
    "sg:address":"4295 Warren-Sharon Rd",
    "sg:city":"Vienna",
    "sg:classifiers":[
        {
            "category":"Organizations",
            "subcategory":"Religious Organization",
            "type":"Services"
        }
    ],
    "sg:phone":"+1 330 394 1986",
    "sg:postcode":"44473",
    "sg:province":"OH",
    "sg:tags":[
        "church"
    ],
    "wof:name":"Vienna Presbyterian Church",
    "wof:placetype":"venue"
},
  "geometry": {"coordinates":[-80.668496,41.237884],"type":"Point"}
}