{
  "type": "Feature",
  "properties": {
    "iso:country":"US",
    "sg:address":"2878 E Main St",
    "sg:city":"Columbus",
    "sg:classifiers":[
        {
            "category":"Manufacturing",
            "subcategory":"Printing",
            "type":"Manufacturing & Wholesale Goods"
        }
    ],
    "sg:phone":"+1 614 231 9585",
    "sg:postcode":"43209",
    "sg:province":"OH",
    "sg:tags":[
        "publisher"
    ],
    "sg:website":"www.furfishgame.com",
    "wof:name":"A R Harding Publishing Co",
    "wof:placetype":"venue"
},
  "geometry": {"coordinates":[-82.921863,39.956848],"type":"Point"}
}