{
  "type": "Feature",
  "properties": {
    "addr:full":"1085 Joyce Ave Columbus OH 43219",
    "addr:housenumber":"1085",
    "addr:postcode":"43219",
    "addr:street":"Joyce Ave",
    "iso:country":"US",
    "sg:address":"1085 Joyce Ave",
    "sg:city":"Columbus",
    "sg:classifiers":[
        {
            "category":"Railroad",
            "type":"Transportation"
        }
    ],
    "sg:phone":"+1 614 251 2600",
    "sg:postcode":"43219",
    "sg:province":"OH",
    "wof:name":"Norfolk Southern Railway Co",
    "wof:placetype":"venue"
},
  "geometry": {"coordinates":[-82.96690700000001,39.985729],"type":"Point"}
}