{
  "type": "Feature",
  "properties": {
    "iso:country":"US",
    "sg:address":"2735 W Alex Bell Rd",
    "sg:city":"Kettering",
    "sg:classifiers":[
        {
            "category":"Personal",
            "subcategory":"Beauty Salon",
            "type":"Services"
        }
    ],
    "sg:phone":"+1 937 298 3401",
    "sg:postcode":"45449",
    "sg:province":"OH",
    "sg:website":"www.greatclips.com",
    "wof:name":"Great Clips",
    "wof:placetype":"venue"
},
  "geometry": {"coordinates":[-84.236513,39.674718],"type":"Point"}
}