{
  "type": "Feature",
  "properties": {
    "addr:full": "703 Harding Way W Galion OH 44833",
    "addr:housenumber": "703",
    "addr:postcode": "44833",
    "addr:street": "Harding Way W",
    "iso:country": "US",
    "sg:address": "703 Harding Way W",
    "sg:city": "Galion",
    "sg:classifiers": [
      {
        "category": "Real Estate",
        "subcategory": "Real Estate Agent",
        "type": "Services"
      }
    ],
    "sg:phone": "+1 419 468 4602",
    "sg:postcode": "44833",
    "sg:province": "OH",
    "sg:website": "www.mileyrealty.com",
    "wof:name": "Craig A Miley Realty \u0026 Auction",
    "wof:placetype": "venue"
  },
  "geometry": {"coordinates":[-82.802364,40.734004],"type":"Point"}
}
