{
  "type": "Feature",
  "properties": {
    "iso:country":"US",
    "sg:address":"6980 E Livingston Ave",
    "sg:city":"Reynoldsburg",
    "sg:classifiers":[
        {
            "category":"Freight",
            "type":"Transportation"
        }
    ],
    "sg:phone":"+1 614 863 9487",
    "sg:postcode":"43068",
    "sg:province":"OH",
    "sg:tags":[
        "operator",
        "local",
        "trucking"
    ],
    "wof:name":"J W R Trucking LLC",
    "wof:placetype":"venue"
},
  "geometry": {"coordinates":[-82.810484,39.945999],"type":"Point"}
}