{
  "type": "Feature",
  "properties": {
    "addr:full": "4179 McLean Dr Cincinnati OH 45255",
    "addr:housenumber": "4179",
    "addr:postcode": "45255",
    "addr:street": "Mclean Dr",
    "iso:country": "US",
    "sg:address": "4179 McLean Dr",
    "sg:city": "Cincinnati",
    "sg:classifiers": [
      {
        "category": "Building \u0026 Trades",
        "subcategory": "Construction",
        "type": "Services"
      }
    ],
    "sg:phone": "+1 513 528 9714",
    "sg:postcode": "45255",
    "sg:province": "OH",
    "sg:tags": [
      "general",
      "contractor"
    ],
    "wof:name": "Greg Bolender Builder",
    "wof:placetype": "venue"
  },
  "geometry": {"coordinates":[-84.306784,39.082211],"type":"Point"}
}
