{
  "type": "Feature",
  "properties": {
    "addr:full": "888 Sturbridge Dr Medina OH 44256",
    "addr:housenumber": "888",
    "addr:postcode": "44256",
    "addr:street": "Sturbridge Dr",
    "iso:country": "US",
    "sg:address": "888 Sturbridge Dr",
    "sg:city": "Medina",
    "sg:classifiers": [
      {
        "category": "Professional",
        "type": "Services"
      }
    ],
    "sg:phone": "+1 330 721 9805",
    "sg:postcode": "44256",
    "sg:province": "OH",
    "wof:name": "John Powers",
    "wof:placetype": "venue"
  },
  "geometry": {"coordinates":[-81.844354,41.120381],"type":"Point"}
}
