{
  "type": "Feature",
  "properties": {
    "iso:country":"US",
    "sg:address":"6569 Vallevista Dr",
    "sg:city":"Cleveland",
    "sg:classifiers":[
        {
            "category":"Manufacturing",
            "subcategory":"Printing",
            "type":"Manufacturing & Wholesale Goods"
        }
    ],
    "sg:phone":"+1 440 442 3440",
    "sg:postcode":"44124",
    "sg:province":"OH",
    "sg:tags":[
        "commercial"
    ],
    "wof:name":"Elegant Details",
    "wof:placetype":"venue"
},
  "geometry": {"coordinates":[-81.440201,41.527734],"type":"Point"}
}