{
  "type": "Feature",
  "properties": {
    "iso:country":"US",
    "sg:address":"114 E Park St",
    "sg:city":"Chardon",
    "sg:classifiers":[
        {
            "category":"Real Estate",
            "subcategory":"Real Estate Agent",
            "type":"Services"
        }
    ],
    "sg:phone":"+1 440 286 1722",
    "sg:postcode":"44024",
    "sg:province":"OH",
    "wof:name":"D & T Enterprises",
    "wof:placetype":"venue"
},
  "geometry": {"coordinates":[-81.202866,41.582589],"type":"Point"}
}