{
  "type": "Feature",
  "properties": {
    "addr:full": "2475 Lee Blvd Cleveland OH 44118",
    "addr:housenumber": "2475",
    "addr:postcode": "44118",
    "addr:street": "Lee Blvd",
    "iso:country": "US",
    "sg:address": "2475 Lee Blvd",
    "sg:city": "Cleveland",
    "sg:classifiers": [
      {
        "category": "Museum",
        "type": "Entertainment"
      }
    ],
    "sg:phone": "+1 216 321 9350",
    "sg:postcode": "44118",
    "sg:province": "OH",
    "sg:tags": [
      "organization",
      "arts",
      "information"
    ],
    "wof:name": "Roots Of American Music",
    "wof:placetype": "venue"
  },
  "geometry": {"coordinates":[-81.569137,41.516155],"type":"Point"}
}
