{
  "type": "Feature",
  "properties": {
    "iso:country":"US",
    "sg:address":"7150 Hart St",
    "sg:city":"Mentor",
    "sg:classifiers":[
        {
            "category":"Autos & Motor Vehicles",
            "subcategory":"Auto Supplies",
            "type":"Retail Goods"
        },
        {
            "category":"Wholesale",
            "subcategory":"Auto Parts",
            "type":"Manufacturing & Wholesale Goods"
        }
    ],
    "sg:phone":"+1 440 205 2455",
    "sg:postcode":"44060",
    "sg:province":"OH",
    "sg:tags":[
        "automobile"
    ],
    "wof:name":"Kovachy Express",
    "wof:placetype":"venue"
},
  "geometry": {"coordinates":[-81.33819800000001,41.677355],"type":"Point"}
}