{
  "type": "Feature",
  "properties": {
    "iso:country":"US",
    "sg:address":"324 N Maple St",
    "sg:city":"Bowling Green",
    "sg:classifiers":[
        {
            "category":"Government",
            "subcategory":"Office",
            "type":"Public Place"
        },
        {
            "category":"Utilities",
            "subcategory":"Water",
            "type":"Services"
        }
    ],
    "sg:phone":"+1 419 354 6277",
    "sg:postcode":"43402",
    "sg:province":"OH",
    "sg:tags":[
        "govt",
        "city",
        "company",
        "sewage"
    ],
    "wof:name":"Bowling Green Utility-Sewer",
    "wof:placetype":"venue"
},
  "geometry": {"coordinates":[-83.65600999999999,41.377559],"type":"Point"}
}