{
  "type": "Feature",
  "properties": {
    "addr:full":"3550 Lander Rd Ste 200 Cleveland OH 44124",
    "addr:housenumber":"3550",
    "addr:postcode":"44124",
    "addr:street":"Lander Rd Ste 200",
    "iso:country":"US",
    "sg:address":"3550 Lander Rd Ste 200",
    "sg:city":"Cleveland",
    "sg:classifiers":[
        {
            "category":"Banks & Credit Unions",
            "subcategory":"Investment Brokerage",
            "type":"Services"
        }
    ],
    "sg:phone":"+1 216 464 6901",
    "sg:postcode":"44124",
    "sg:province":"OH",
    "sg:tags":[
        "investing"
    ],
    "sg:website":"www.nationalcity.com",
    "wof:name":"Sterling A National City Company",
    "wof:placetype":"venue"
},
  "geometry": {"coordinates":[-81.463303,41.4636],"type":"Point"}
}