{
  "type": "Feature",
  "properties": {
    "iso:country":"US",
    "sg:address":"2625 E 55th St",
    "sg:city":"Cleveland",
    "sg:classifiers":[
        {
            "category":"Autos & Motor Vehicles",
            "subcategory":"Fuel & Gas Station",
            "type":"Retail Goods"
        }
    ],
    "sg:phone":"+1 216 431 2728",
    "sg:postcode":"44104",
    "sg:province":"OH",
    "sg:tags":[
        "oil"
    ],
    "wof:name":"55th-Kinsman Shell",
    "wof:placetype":"venue"
},
  "geometry": {"coordinates":[-81.65149099999999,41.486153],"type":"Point"}
}