{
  "type": "Feature",
  "properties": {
    "addr:full":"29635 Lakeland Blvd Wickliffe OH 44092",
    "addr:housenumber":"29635",
    "addr:postcode":"44092",
    "addr:street":"Lakeland Blvd",
    "iso:country":"US",
    "sg:address":"29635 Lakeland Blvd",
    "sg:city":"Wickliffe",
    "sg:classifiers":[
        {
            "category":"Building & Trades",
            "subcategory":"Electrical",
            "type":"Services"
        }
    ],
    "sg:phone":"+1 440 944 6619",
    "sg:postcode":"44092",
    "sg:province":"OH",
    "sg:tags":[
        "electric",
        "contractor"
    ],
    "wof:name":"Ace Electric",
    "wof:placetype":"venue"
},
  "geometry": {"coordinates":[-81.48168699999999,41.611884],"type":"Point"}
}