{
  "type": "Feature",
  "properties": {
    "addr:full":"406 Beall Ave Wooster OH 44691",
    "addr:housenumber":"406",
    "addr:postcode":"44691",
    "addr:street":"Beall Ave",
    "iso:country":"US",
    "sg:address":"406 Beall Ave",
    "sg:city":"Wooster",
    "sg:classifiers":[
        {
            "category":"Shopping",
            "subcategory":"Musical Instruments",
            "type":"Retail Goods"
        }
    ],
    "sg:phone":"+1 330 262 8855",
    "sg:postcode":"44691",
    "sg:province":"OH",
    "wof:name":"Larry's Music Ctr Inc",
    "wof:placetype":"venue"
},
  "geometry": {"coordinates":[-81.93447999999999,40.803306],"type":"Point"}
}