{
  "type": "Feature",
  "properties": {
    "addr:full":"655 Metro Pl S Dublin OH 43017",
    "addr:housenumber":"655",
    "addr:postcode":"43017",
    "addr:street":"Metro Pl",
    "iso:country":"US",
    "sg:address":"655 Metro Pl S",
    "sg:city":"Dublin",
    "sg:classifiers":[
        {
            "category":"Banks & Credit Unions",
            "subcategory":"Investment Brokerage",
            "type":"Services"
        }
    ],
    "sg:phone":"+1 614 717 7283",
    "sg:postcode":"43017",
    "sg:province":"OH",
    "sg:tags":[
        "consultant",
        "planning",
        "financial"
    ],
    "sg:website":"www.americanexpressfinancialadvisors.com",
    "wof:name":"American Express Financial Adv",
    "wof:placetype":"venue"
},
  "geometry": {"coordinates":[-83.12620200000001,40.093382],"type":"Point"}
}