{
  "type": "Feature",
  "properties": {
    "iso:country":"US",
    "sg:address":"6100 Ridgewood Ave",
    "sg:city":"Cleveland",
    "sg:classifiers":[
        {
            "category":"Manufacturing",
            "subcategory":"Printing",
            "type":"Manufacturing & Wholesale Goods"
        }
    ],
    "sg:phone":"+1 216 447 9959",
    "sg:postcode":"44129",
    "sg:province":"OH",
    "sg:tags":[
        "publisher",
        "book"
    ],
    "wof:name":"Bluebook Building & Cnstr",
    "wof:placetype":"venue"
},
  "geometry": {"coordinates":[-81.730126,41.41132],"type":"Point"}
}