{
  "type": "Feature",
  "properties": {
    "addr:full": "6100 Ridgewood Ave Cleveland OH 44129",
    "addr:housenumber": "6100",
    "addr:postcode": "44129",
    "addr:street": "Ridgewood Ave",
    "iso:country": "US",
    "sg:address": "6100 Ridgewood Ave",
    "sg:city": "Cleveland",
    "sg:classifiers": [
      {
        "category": "Manufacturing",
        "subcategory": "Printing",
        "type": "Manufacturing \u0026 Wholesale Goods"
      }
    ],
    "sg:phone": "+1 216 447 9959",
    "sg:postcode": "44129",
    "sg:province": "OH",
    "sg:tags": [
      "publisher",
      "book"
    ],
    "wof:name": "Bluebook Building \u0026 Cnstr",
    "wof:placetype": "venue"
  },
  "geometry": {"coordinates":[-81.730126,41.41132],"type":"Point"}
}
