{
  "type": "Feature",
  "properties": {
    "addr:full":"515 Prospect St Salem OH 44460",
    "addr:housenumber":"515",
    "addr:postcode":"44460",
    "addr:street":"Prospect St",
    "iso:country":"US",
    "sg:address":"515 Prospect St",
    "sg:city":"Salem",
    "sg:classifiers":[
        {
            "category":"Autos & Motor Vehicles",
            "subcategory":"Automobile Sales",
            "type":"Retail Goods"
        }
    ],
    "sg:phone":"+1 330 332 1583",
    "sg:postcode":"44460",
    "sg:province":"OH",
    "sg:tags":[
        "truck"
    ],
    "wof:name":"Davidson Sales & Svc",
    "wof:placetype":"venue"
},
  "geometry": {"coordinates":[-80.863062,40.8962],"type":"Point"}
}