{
  "type": "Feature",
  "properties": {
    "addr:full":"13367 Calhoun Ct Pickerington OH 43147",
    "addr:housenumber":"13367",
    "addr:postcode":"43147",
    "addr:street":"Calhoun Ct",
    "iso:country":"US",
    "sg:address":"13367 Calhoun Ct",
    "sg:city":"Pickerington",
    "sg:classifiers":[
        {
            "category":"Professional",
            "type":"Services"
        }
    ],
    "sg:phone":"+1 614 861 1690",
    "sg:postcode":"43147",
    "sg:province":"OH",
    "wof:name":"L Warton Inc",
    "wof:placetype":"venue"
},
  "geometry": {"coordinates":[-82.721648,39.928139],"type":"Point"}
}