{
  "type": "Feature",
  "properties": {
    "addr:full":"407 E Lutz Rd Archbold OH 43502",
    "addr:housenumber":"407",
    "addr:postcode":"43502",
    "addr:street":"E Lutz Rd",
    "iso:country":"US",
    "sg:address":"407 E Lutz Rd",
    "sg:city":"Archbold",
    "sg:classifiers":[
        {
            "category":"Health Services",
            "subcategory":"Nursing And Care Facility",
            "type":"Services"
        }
    ],
    "sg:phone":"+1 419 445 3075",
    "sg:postcode":"43502",
    "sg:province":"OH",
    "sg:tags":[
        "home",
        "convalescent"
    ],
    "wof:name":"Fairlawn Haven",
    "wof:placetype":"venue"
},
  "geometry": {"coordinates":[-84.300985,41.528704],"type":"Point"}
}