{
  "type": "Feature",
  "properties": {
    "iso:country":"US",
    "sg:address":"300 Nordson Dr",
    "sg:city":"Amherst",
    "sg:classifiers":[
        {
            "category":"Manufacturing",
            "subcategory":"Tools & Machinery",
            "type":"Manufacturing & Wholesale Goods"
        }
    ],
    "sg:phone":"+1 440 985 4226",
    "sg:postcode":"44001",
    "sg:province":"OH",
    "sg:tags":[
        "ind",
        "general"
    ],
    "sg:website":"www.nordson.com",
    "wof:name":"Nordson Corp Container Systems",
    "wof:placetype":"venue"
},
  "geometry": {"coordinates":[-82.213567,41.392732],"type":"Point"}
}