{
  "type": "Feature",
  "properties": {
    "addr:full": "13170 York Rd Cleveland OH 44133",
    "addr:housenumber": "13170",
    "addr:postcode": "44133",
    "addr:street": "York Rd",
    "iso:country": "US",
    "sg:address": "13170 York Rd",
    "sg:city": "Cleveland",
    "sg:classifiers": [
      {
        "category": "Real Estate",
        "subcategory": "Real Estate Agent",
        "type": "Services"
      }
    ],
    "sg:phone": "+1 440 237 3222",
    "sg:postcode": "44133",
    "sg:province": "OH",
    "sg:tags": [
      "inspection"
    ],
    "wof:name": "House Check Inspection Svc",
    "wof:placetype": "venue"
  },
  "geometry": {"coordinates":[-81.756207,41.318944],"type":"Point"}
}
