{
  "type": "Feature",
  "properties": {
    "iso:country":"US",
    "sg:address":"1900 W Market St",
    "sg:city":"Akron",
    "sg:classifiers":[
        {
            "category":"Banks & Credit Unions",
            "subcategory":"Bank",
            "type":"Services"
        }
    ],
    "sg:phone":"+1 330 864 1805",
    "sg:postcode":"44313",
    "sg:province":"OH",
    "sg:tags":[
        "loan",
        "broker"
    ],
    "wof:name":"Continental Mortgage Services",
    "wof:placetype":"venue"
},
  "geometry": {"coordinates":[-81.576213,41.11249],"type":"Point"}
}