{
  "type": "Feature",
  "properties": {
    "iso:country":"US",
    "sg:address":"1469 Alphada Ave",
    "sg:city":"Akron",
    "sg:classifiers":[
        {
            "category":"Restaurant",
            "type":"Food & Drink"
        }
    ],
    "sg:phone":"+1 330 798 0833",
    "sg:postcode":"44310",
    "sg:province":"OH",
    "wof:name":"Chinatown",
    "wof:placetype":"venue"
},
  "geometry": {"coordinates":[-81.467406,41.104186],"type":"Point"}
}