{
  "type": "Feature",
  "properties": {
    "iso:country":"US",
    "sg:address":"319 N 1st St",
    "sg:city":"Cambridge",
    "sg:classifiers":[
        {
            "category":"Freight",
            "type":"Transportation"
        }
    ],
    "sg:phone":"+1 740 432 4899",
    "sg:postcode":"43725",
    "sg:province":"OH",
    "sg:tags":[
        "mini",
        "storage"
    ],
    "wof:name":"Northwest Mini Storage",
    "wof:placetype":"venue"
},
  "geometry": {"coordinates":[-81.601894,40.028176],"type":"Point"}
}