{
  "type": "Feature",
  "properties": {
    "addr:full": "6290 Cloverly Dr Solon OH 44139",
    "addr:housenumber": "6290",
    "addr:postcode": "44139",
    "addr:street": "Cloverly Dr",
    "iso:country": "US",
    "sg:address": "6290 Cloverly Dr",
    "sg:city": "Solon",
    "sg:classifiers": [
      {
        "category": "Professional",
        "subcategory": "Management \u0026 Consulting",
        "type": "Services"
      }
    ],
    "sg:phone": "+1 440 349 3609",
    "sg:postcode": "44139",
    "sg:province": "OH",
    "sg:tags": [
      "retail",
      "direct",
      "sales"
    ],
    "wof:name": "Melaleuca",
    "wof:placetype": "venue"
  },
  "geometry": {"coordinates":[-81.414983,41.388393],"type":"Point"}
}
