{
  "type": "Feature",
  "properties": {
    "addr:full": "683 E 200th St Cleveland OH 44119",
    "addr:housenumber": "683",
    "addr:postcode": "44119",
    "addr:street": "E 200Th St",
    "iso:country": "US",
    "sg:address": "683 E 200th St",
    "sg:city": "Cleveland",
    "sg:classifiers": [
      {
        "category": "Retail",
        "subcategory": "Repair Shop",
        "type": "Services"
      },
      {
        "category": "Building \u0026 Trades",
        "subcategory": "Plumbing",
        "type": "Services"
      }
    ],
    "sg:phone": "+1 216 486 6000",
    "sg:postcode": "44119",
    "sg:province": "OH",
    "sg:tags": [
      "stress",
      "system",
      "contractor",
      "environmental",
      "conditioning",
      "air",
      "simulation"
    ],
    "wof:name": "Capital Environmental Inc",
    "wof:placetype": "venue"
  },
  "geometry": {"coordinates":[-81.540097,41.587719],"type":"Point"}
}
