{
  "type": "Feature",
  "properties": {
    "addr:full": "2000 Lincoln Way E Massillon OH 44646",
    "addr:housenumber": "2000",
    "addr:postcode": "44646",
    "addr:street": "Lincoln Way E",
    "iso:country": "US",
    "sg:address": "2000 Lincoln Way E",
    "sg:city": "Massillon",
    "sg:classifiers": [
      {
        "category": "Restaurant",
        "type": "Food \u0026 Drink"
      }
    ],
    "sg:menulink": "http://www.allmenus.com/oh/massillon/68778-marcos-pizza/menu/",
    "sg:phone": "+1 330 833 0300",
    "sg:postcode": "44646",
    "sg:province": "OH",
    "sg:tags": [
      "american",
      "pizza"
    ],
    "wof:name": "Marco's Pizza",
    "wof:placetype": "venue"
  },
  "geometry": {"coordinates":[-81.496528,40.798711],"type":"Point"}
}
