{
  "type": "Feature",
  "properties": {
    "iso:country":"US",
    "sg:address":"2000 Lincoln Way E",
    "sg:city":"Massillon",
    "sg:classifiers":[
        {
            "category":"Restaurant",
            "type":"Food & Drink"
        }
    ],
    "sg:menulink":"http://www.allmenus.com/oh/massillon/68778-marcos-pizza/menu/",
    "sg:phone":"+1 330 833 0300",
    "sg:postcode":"44646",
    "sg:province":"OH",
    "sg:tags":[
        "american",
        "pizza"
    ],
    "wof:name":"Marco's Pizza",
    "wof:placetype":"venue"
},
  "geometry": {"coordinates":[-81.496528,40.798711],"type":"Point"}
}