{
  "type": "Feature",
  "properties": {
    "addr:full": "101 West St Lagrange OH 44050",
    "addr:housenumber": "101",
    "addr:postcode": "44050",
    "addr:street": "West St",
    "iso:country": "US",
    "sg:address": "101 West St",
    "sg:city": "Lagrange",
    "sg:classifiers": [
      {
        "category": "Education",
        "subcategory": "Library",
        "type": "Public Place"
      }
    ],
    "sg:phone": "+1 440 355 6323",
    "sg:postcode": "44050",
    "sg:province": "OH",
    "wof:name": "Keystone LA Grange Library",
    "wof:placetype": "venue"
  },
  "geometry": {"coordinates":[-82.125208,41.23769],"type":"Point"}
}
