{
  "type": "Feature",
  "properties": {
    "iso:country":"US",
    "sg:address":"4331 Yearling Cir",
    "sg:city":"Columbus",
    "sg:classifiers":[
        {
            "category":"Real Estate",
            "subcategory":"Real Estate Operator",
            "type":"Services"
        }
    ],
    "sg:phone":"+1 614 235 9000",
    "sg:postcode":"43213",
    "sg:province":"OH",
    "sg:tags":[
        "apartment",
        "operates"
    ],
    "wof:name":"Yearling Properties Inc",
    "wof:placetype":"venue"
},
  "geometry": {"coordinates":[-82.884922,39.973117],"type":"Point"}
}