{
  "type": "Feature",
  "properties": {
    "addr:full": "1740 Home Ave Dayton OH 45402",
    "addr:housenumber": "1740",
    "addr:postcode": "45402",
    "addr:street": "Home Ave",
    "iso:country": "US",
    "sg:address": "1740 Home Ave",
    "sg:city": "Dayton",
    "sg:classifiers": [
      {
        "category": "Organizations",
        "subcategory": "Religious Organization",
        "type": "Services"
      }
    ],
    "sg:phone": "+1 937 223 3406",
    "sg:postcode": "45402",
    "sg:province": "OH",
    "sg:tags": [
      "clergy"
    ],
    "wof:name": "Church Tabernacle Of God",
    "wof:placetype": "venue"
  },
  "geometry": {"coordinates":[-84.2232,39.750847],"type":"Point"}
}
