{
  "type": "Feature",
  "properties": {
    "iso:country":"US",
    "sg:address":"1740 Home Ave",
    "sg:city":"Dayton",
    "sg:classifiers":[
        {
            "category":"Organizations",
            "subcategory":"Religious Organization",
            "type":"Services"
        }
    ],
    "sg:phone":"+1 937 223 3406",
    "sg:postcode":"45402",
    "sg:province":"OH",
    "sg:tags":[
        "clergy"
    ],
    "wof:name":"Church Tabernacle Of God",
    "wof:placetype":"venue"
},
  "geometry": {"coordinates":[-84.22320000000001,39.750847],"type":"Point"}
}