{
  "type": "Feature",
  "properties": {
    "addr:full": "9157 Montgomery Rd Cincinnati OH 45242",
    "addr:housenumber": "9157",
    "addr:postcode": "45242",
    "addr:street": "Montgomery Rd",
    "iso:country": "US",
    "sg:address": "9157 Montgomery Rd",
    "sg:city": "Cincinnati",
    "sg:classifiers": [
      {
        "category": "Health Services",
        "subcategory": "Doctor",
        "type": "Services"
      }
    ],
    "sg:phone": "+1 513 791 0725",
    "sg:postcode": "45242",
    "sg:province": "OH",
    "wof:name": "James E Bishop DDS Inc",
    "wof:placetype": "venue"
  },
  "geometry": {"coordinates":[-84.356777,39.221852],"type":"Point"}
}
