{
  "type": "Feature",
  "properties": {
    "addr:full": "4590 Knightsbridge Blvd Columbus OH 43214",
    "addr:housenumber": "4590",
    "addr:postcode": "43214",
    "addr:street": "Knightsbridge Blvd",
    "iso:country": "US",
    "sg:address": "4590 Knightsbridge Blvd",
    "sg:city": "Columbus",
    "sg:classifiers": [
      {
        "category": "Health Services",
        "subcategory": "Clinic",
        "type": "Services"
      }
    ],
    "sg:phone": "+1 614 451 6766",
    "sg:postcode": "43214",
    "sg:province": "OH",
    "wof:name": "Healthcare Center At The Forum",
    "wof:placetype": "venue"
  },
  "geometry": {"coordinates":[-83.04212,40.052718],"type":"Point"}
}
