{
  "type": "Feature",
  "properties": {
    "addr:full": "1008 N Main St Bellefontaine OH 43311",
    "addr:housenumber": "1008",
    "addr:postcode": "43311",
    "addr:street": "N Main St",
    "iso:country": "US",
    "sg:address": "1008 N Main St",
    "sg:city": "Bellefontaine",
    "sg:classifiers": [
      {
        "category": "Health Services",
        "subcategory": "Optometrist",
        "type": "Services"
      }
    ],
    "sg:phone": "+1 937 599 5315",
    "sg:postcode": "43311",
    "sg:province": "OH",
    "wof:name": "Gary Contner Od",
    "wof:placetype": "venue"
  },
  "geometry": {"coordinates":[-83.757603,40.372984],"type":"Point"}
}
