{
  "type": "Feature",
  "properties": {
    "addr:full": "35901 Chester Rd Avon OH 44011",
    "addr:housenumber": "35901",
    "addr:postcode": "44011",
    "addr:street": "Chester Rd",
    "iso:country": "US",
    "sg:address": "35901 Chester Rd",
    "sg:city": "Avon",
    "sg:classifiers": [
      {
        "category": "Retail",
        "subcategory": "Portrait Studio",
        "type": "Services"
      }
    ],
    "sg:phone": "+1 440 937 4485",
    "sg:postcode": "44011",
    "sg:province": "OH",
    "sg:tags": [
      "photographer"
    ],
    "wof:name": "Wal-Mart Portrait Studio",
    "wof:placetype": "venue"
  },
  "geometry": {"coordinates":[-82.008138,41.46773],"type":"Point"}
}
