{
  "type": "Feature",
  "properties": {
    "addr:full": "3704 12th St NW Canton OH 44708",
    "addr:housenumber": "3704",
    "addr:postcode": "44708",
    "addr:street": "12Th St Nw",
    "iso:country": "US",
    "sg:address": "3704 12th St NW",
    "sg:city": "Canton",
    "sg:classifiers": [
      {
        "category": "Wholesale",
        "subcategory": "Non-durable Goods",
        "type": "Manufacturing \u0026 Wholesale Goods"
      }
    ],
    "sg:phone": "+1 330 452 1080",
    "sg:postcode": "44708",
    "sg:province": "OH",
    "wof:name": "Mr Mulch",
    "wof:placetype": "venue"
  },
  "geometry": {"coordinates":[-81.422223,40.810646],"type":"Point"}
}
