{
  "type": "Feature",
  "properties": {
    "iso:country":"US",
    "sg:address":"3704 12th St NW",
    "sg:city":"Canton",
    "sg:classifiers":[
        {
            "category":"Wholesale",
            "subcategory":"Non-durable Goods",
            "type":"Manufacturing & Wholesale Goods"
        }
    ],
    "sg:phone":"+1 330 452 1080",
    "sg:postcode":"44708",
    "sg:province":"OH",
    "wof:name":"Mr Mulch",
    "wof:placetype":"venue"
},
  "geometry": {"coordinates":[-81.422223,40.810646],"type":"Point"}
}