{
  "type": "Feature",
  "properties": {
    "iso:country":"US",
    "sg:address":"4333 N Detroit Ave",
    "sg:city":"Toledo",
    "sg:classifiers":[
        {
            "category":"Manufacturing",
            "subcategory":"Metals",
            "type":"Manufacturing & Wholesale Goods"
        }
    ],
    "sg:phone":"+1 419 476 8555",
    "sg:postcode":"43612",
    "sg:province":"OH",
    "sg:tags":[
        "work"
    ],
    "sg:website":"www.marleaufence.com",
    "wof:name":"Marleau-Hercules Fence Co",
    "wof:placetype":"venue"
},
  "geometry": {"coordinates":[-83.549921,41.697316],"type":"Point"}
}