{
  "type": "Feature",
  "properties": {
    "iso:country":"US",
    "sg:address":"111 2nd St NW",
    "sg:city":"Canton",
    "sg:classifiers":[
        {
            "category":"Professional",
            "type":"Services"
        }
    ],
    "sg:phone":"+1 330 430 9516",
    "sg:postcode":"44702",
    "sg:province":"OH",
    "sg:tags":[
        "establishment"
    ],
    "wof:name":"An Act Of Kindness",
    "wof:placetype":"venue"
},
  "geometry": {"coordinates":[-81.375315,40.799399],"type":"Point"}
}