{
  "type": "Feature",
  "properties": {
    "addr:full":"119 E Main St St Clairsville OH 43950",
    "addr:housenumber":"119",
    "addr:postcode":"43950",
    "addr:street":"E Main St",
    "iso:country":"US",
    "sg:address":"119 E Main St",
    "sg:city":"St Clairsville",
    "sg:classifiers":[
        {
            "category":"Real Estate",
            "subcategory":"Real Estate Agent",
            "type":"Services"
        }
    ],
    "sg:phone":"+1 740 695 0516",
    "sg:postcode":"43950",
    "sg:province":"OH",
    "sg:website":"www.century21bethel.com",
    "wof:name":"Bethel Agency",
    "wof:placetype":"venue"
},
  "geometry": {"coordinates":[-80.90095700000001,40.080513],"type":"Point"}
}