{
  "type": "Feature",
  "properties": {
    "addr:full":"1788 Mill St Exd Austinburg OH 44010",
    "addr:housenumber":"1788",
    "addr:postcode":"44010",
    "addr:street":"Mill St Exd",
    "iso:country":"US",
    "sg:address":"1788 Mill St Exd",
    "sg:city":"Austinburg",
    "sg:classifiers":[
        {
            "category":"Wholesale",
            "subcategory":"Machinery & Supplies",
            "type":"Manufacturing & Wholesale Goods"
        }
    ],
    "sg:phone":"+1 440 275 3211",
    "sg:postcode":"44010",
    "sg:province":"OH",
    "sg:tags":[
        "equipment",
        "lapidary"
    ],
    "sg:website":"www.noemagems.com",
    "wof:name":"Noema Rock & Gem Shop",
    "wof:placetype":"venue"
},
  "geometry": {"coordinates":[-80.852828,41.774322],"type":"Point"}
}