{
  "type": "Feature",
  "properties": {
    "addr:full": "33 E Canal St Nelsonville OH 45764",
    "addr:housenumber": "33",
    "addr:postcode": "45764",
    "addr:street": "E Canal St",
    "iso:country": "US",
    "sg:address": "33 E Canal St",
    "sg:city": "Nelsonville",
    "sg:classifiers": [
      {
        "category": "Railroad",
        "type": "Transportation"
      }
    ],
    "sg:phone": "+1 740 753 9531",
    "sg:postcode": "45764",
    "sg:province": "OH",
    "wof:name": "Hocking Valley Scenic Railway",
    "wof:placetype": "venue"
  },
  "geometry": {"coordinates":[-82.231906,39.45846],"type":"Point"}
}
