{
  "type": "Feature",
  "properties": {
    "iso:country":"US",
    "sg:address":"1314 Burnett Dr",
    "sg:city":"Xenia",
    "sg:classifiers":[
        {
            "category":"Building & Trades",
            "subcategory":"Construction",
            "type":"Services"
        }
    ],
    "sg:phone":"+1 937 718 2298",
    "sg:postcode":"45385",
    "sg:province":"OH",
    "sg:tags":[
        "paving",
        "contractor"
    ],
    "wof:name":"API Asphalt Maintenance",
    "wof:placetype":"venue"
},
  "geometry": {"coordinates":[-83.91264,39.670214],"type":"Point"}
}