{
  "type": "Feature",
  "properties": {
    "addr:full": "1314 Burnett Dr Xenia OH 45385",
    "addr:housenumber": "1314",
    "addr:postcode": "45385",
    "addr:street": "Burnett Dr",
    "iso:country": "US",
    "sg:address": "1314 Burnett Dr",
    "sg:city": "Xenia",
    "sg:classifiers": [
      {
        "category": "Building \u0026 Trades",
        "subcategory": "Construction",
        "type": "Services"
      }
    ],
    "sg:phone": "+1 937 718 2298",
    "sg:postcode": "45385",
    "sg:province": "OH",
    "sg:tags": [
      "paving",
      "contractor"
    ],
    "wof:name": "API Asphalt Maintenance",
    "wof:placetype": "venue"
  },
  "geometry": {"coordinates":[-83.91264,39.670214],"type":"Point"}
}
