{
  "type": "Feature",
  "properties": {
    "addr:full": "5616 Cheviot Rd Cincinnati OH 45247",
    "addr:housenumber": "5616",
    "addr:postcode": "45247",
    "addr:street": "Cheviot Rd",
    "iso:country": "US",
    "sg:address": "5616 Cheviot Rd",
    "sg:city": "Cincinnati",
    "sg:classifiers": [
      {
        "category": "Shopping",
        "subcategory": "Gifts \u0026 Souvenirs",
        "type": "Retail Goods"
      }
    ],
    "sg:phone": "+1 513 385 2320",
    "sg:postcode": "45247",
    "sg:province": "OH",
    "sg:tags": [
      "basket",
      "parcel"
    ],
    "wof:name": "Howard \u0026 Son Market",
    "wof:placetype": "venue"
  },
  "geometry": {"coordinates":[-84.59901,39.192936],"type":"Point"}
}
