{
  "type": "Feature",
  "properties": {
    "addr:full":"5616 Cheviot Rd Cincinnati OH 45247",
    "addr:housenumber":"5616",
    "addr:postcode":"45247",
    "addr:street":"Cheviot Rd",
    "iso:country":"US",
    "sg:address":"5616 Cheviot Rd",
    "sg:city":"Cincinnati",
    "sg:classifiers":[
        {
            "category":"Shopping",
            "subcategory":"Gifts & Souvenirs",
            "type":"Retail Goods"
        }
    ],
    "sg:phone":"+1 513 385 2320",
    "sg:postcode":"45247",
    "sg:province":"OH",
    "sg:tags":[
        "basket",
        "parcel"
    ],
    "wof:name":"Howard & Son Market",
    "wof:placetype":"venue"
},
  "geometry": {"coordinates":[-84.59901000000001,39.192936],"type":"Point"}
}