{
  "type": "Feature",
  "properties": {
    "addr:full":"2167 Forest Oak Dr Akron OH 44312",
    "addr:housenumber":"2167",
    "addr:postcode":"44312",
    "addr:street":"Forest Oak Dr",
    "iso:country":"US",
    "sg:address":"2167 Forest Oak Dr",
    "sg:city":"Akron",
    "sg:classifiers":[
        {
            "category":"Manufacturing",
            "subcategory":"Tools & Machinery",
            "type":"Manufacturing & Wholesale Goods"
        }
    ],
    "sg:phone":"+1 330 733 2907",
    "sg:postcode":"44312",
    "sg:province":"OH",
    "sg:tags":[
        "instrument",
        "medical",
        "mfg"
    ],
    "wof:name":"Lababidi Enterprises Inc",
    "wof:placetype":"venue"
},
  "geometry": {"coordinates":[-81.449872,41.049837],"type":"Point"}
}