{
  "type": "Feature",
  "properties": {
    "addr:full": "304 N Cole St Lima OH 45805",
    "addr:housenumber": "304",
    "addr:postcode": "45805",
    "addr:street": "N Cole St",
    "iso:country": "US",
    "sg:address": "304 N Cole St",
    "sg:city": "Lima",
    "sg:classifiers": [
      {
        "category": "Organizations",
        "subcategory": "Religious Organization",
        "type": "Services"
      }
    ],
    "sg:phone": "+1 419 225 7668",
    "sg:postcode": "45805",
    "sg:province": "OH",
    "sg:tags": [
      "church"
    ],
    "wof:name": "Fellowship Missionary Baptist",
    "wof:placetype": "venue"
  },
  "geometry": {"coordinates":[-84.127613,40.743341],"type":"Point"}
}
