{
  "type": "Feature",
  "properties": {
    "iso:country":"US",
    "sg:address":"723 E Tallmadge Ave",
    "sg:city":"Akron",
    "sg:classifiers":[
        {
            "category":"Professional",
            "type":"Services"
        }
    ],
    "sg:phone":"+1 330 375 0515",
    "sg:postcode":"44310",
    "sg:province":"OH",
    "wof:name":"Great Tops",
    "wof:placetype":"venue"
},
  "geometry": {"coordinates":[-81.488795,41.102634],"type":"Point"}
}