{
  "type": "Feature",
  "properties": {
    "addr:full": "1076 Rarig Ave Columbus OH 43219",
    "addr:housenumber": "1076",
    "addr:postcode": "43219",
    "addr:street": "Rarig Ave",
    "iso:country": "US",
    "sg:address": "1076 Rarig Ave",
    "sg:city": "Columbus",
    "sg:classifiers": [
      {
        "category": "Building \u0026 Trades",
        "subcategory": "Construction",
        "type": "Services"
      }
    ],
    "sg:phone": "+1 614 252 1540",
    "sg:postcode": "43219",
    "sg:province": "OH",
    "sg:tags": [
      "contractor"
    ],
    "wof:name": "Target Building Svc",
    "wof:placetype": "venue"
  },
  "geometry": {"coordinates":[-82.922513,39.997786],"type":"Point"}
}
