{
  "type": "Feature",
  "properties": {
    "iso:country":"US",
    "sg:address":"407 N Walnut St",
    "sg:city":"Logan",
    "sg:classifiers":[
        {
            "category":"Real Estate",
            "subcategory":"Real Estate Agent",
            "type":"Services"
        }
    ],
    "sg:phone":"+1 740 385 2665",
    "sg:postcode":"43138",
    "sg:province":"OH",
    "wof:name":"Dennis Rentals",
    "wof:placetype":"venue"
},
  "geometry": {"coordinates":[-82.405338,39.542654],"type":"Point"}
}