{
  "type": "Feature",
  "properties": {
    "iso:country":"US",
    "sg:address":"616 Hebron Rd",
    "sg:city":"Newark",
    "sg:classifiers":[
        {
            "category":"Shopping",
            "subcategory":"Crafts & Fabrics",
            "type":"Retail Goods"
        }
    ],
    "sg:phone":"+1 740 522 6545",
    "sg:postcode":"43056",
    "sg:province":"OH",
    "sg:tags":[
        "yarn"
    ],
    "wof:name":"JAO Enterprises Inc",
    "wof:placetype":"venue"
},
  "geometry": {"coordinates":[-82.43216,40.035373],"type":"Point"}
}