{
  "type": "Feature",
  "properties": {
    "iso:country":"US",
    "sg:address":"14282 Mayfield Rd",
    "sg:city":"Huntsburg",
    "sg:classifiers":[
        {
            "category":"Building & Trades",
            "subcategory":"Construction",
            "type":"Services"
        }
    ],
    "sg:phone":"+1 440 635 5177",
    "sg:postcode":"44046",
    "sg:province":"OH",
    "sg:tags":[
        "demolition",
        "contractor"
    ],
    "wof:name":"Demolition & Removal Spec",
    "wof:placetype":"venue"
},
  "geometry": {"coordinates":[-81.137724,41.532252],"type":"Point"}
}