{
  "type": "Feature",
  "properties": {
    "addr:full": "14282 Mayfield Rd Huntsburg OH 44046",
    "addr:housenumber": "14282",
    "addr:postcode": "44046",
    "addr:street": "Mayfield Rd",
    "iso:country": "US",
    "sg:address": "14282 Mayfield Rd",
    "sg:city": "Huntsburg",
    "sg:classifiers": [
      {
        "category": "Building \u0026 Trades",
        "subcategory": "Construction",
        "type": "Services"
      }
    ],
    "sg:phone": "+1 440 635 5177",
    "sg:postcode": "44046",
    "sg:province": "OH",
    "sg:tags": [
      "demolition",
      "contractor"
    ],
    "wof:name": "Demolition \u0026 Removal Spec",
    "wof:placetype": "venue"
  },
  "geometry": {"coordinates":[-81.137724,41.532252],"type":"Point"}
}
