{
  "type": "Feature",
  "properties": {
    "iso:country":"US",
    "sg:address":"302 S Byrne Rd",
    "sg:city":"Toledo",
    "sg:classifiers":[
        {
            "category":"Professional",
            "subcategory":"Business Services",
            "type":"Services"
        }
    ],
    "sg:phone":"+1 419 531 4914",
    "sg:postcode":"43615",
    "sg:province":"OH",
    "sg:tags":[
        "record",
        "document"
    ],
    "wof:name":"Iron Mountain",
    "wof:placetype":"venue"
},
  "geometry": {"coordinates":[-83.626015,41.63319],"type":"Point"}
}