{
  "type": "Feature",
  "properties": {
    "addr:full":"2234 Newton St Akron OH 44305",
    "addr:housenumber":"2234",
    "addr:postcode":"44305",
    "addr:street":"Newton St",
    "iso:country":"US",
    "sg:address":"2234 Newton St",
    "sg:city":"Akron",
    "sg:classifiers":[
        {
            "category":"Retail",
            "subcategory":"Auto Repair",
            "type":"Services"
        }
    ],
    "sg:phone":"+1 330 784 8142",
    "sg:postcode":"44305",
    "sg:province":"OH",
    "sg:tags":[
        "automobile",
        "general"
    ],
    "wof:name":"Kelvington Auto Service Inc",
    "wof:placetype":"venue"
},
  "geometry": {"coordinates":[-81.442391,41.072368],"type":"Point"}
}