{
  "type": "Feature",
  "properties": {
    "addr:full":"1128 Clifton Ave Ashland OH 44805",
    "addr:housenumber":"1128",
    "addr:postcode":"44805",
    "addr:street":"Clifton Ave",
    "iso:country":"US",
    "sg:address":"1128 Clifton Ave",
    "sg:city":"Ashland",
    "sg:classifiers":[
        {
            "category":"Wholesale",
            "subcategory":"Machinery & Supplies",
            "type":"Manufacturing & Wholesale Goods"
        }
    ],
    "sg:phone":"+1 419 281 7605",
    "sg:postcode":"44805",
    "sg:province":"OH",
    "sg:tags":[
        "equipment",
        "industrial"
    ],
    "wof:name":"Today & Beyond",
    "wof:placetype":"venue"
},
  "geometry": {"coordinates":[-82.326975,40.879467],"type":"Point"}
}