{
  "type": "Feature",
  "properties": {
    "iso:country":"US",
    "sg:address":"229 Woodman Dr",
    "sg:city":"Dayton",
    "sg:classifiers":[
        {
            "category":"Shopping",
            "subcategory":"Florist",
            "type":"Retail Goods"
        }
    ],
    "sg:phone":"+1 937 252 5647",
    "sg:postcode":"45431",
    "sg:province":"OH",
    "wof:name":"Smith Ed Flowers & Gifts Inc",
    "wof:placetype":"venue"
},
  "geometry": {"coordinates":[-84.123373,39.768341],"type":"Point"}
}