{
  "type": "Feature",
  "properties": {
    "iso:country":"US",
    "sg:address":"515 Union Ave",
    "sg:city":"Dover",
    "sg:classifiers":[
        {
            "category":"Personal",
            "subcategory":"Barber",
            "type":"Services"
        }
    ],
    "sg:phone":"+1 330 364 2813",
    "sg:postcode":"44622",
    "sg:province":"OH",
    "wof:name":"Haire Design Studio One",
    "wof:placetype":"venue"
},
  "geometry": {"coordinates":[-81.46677,40.509962],"type":"Point"}
}