{
  "type": "Feature",
  "properties": {
    "addr:full": "1150 Bechtle Ave Springfield OH 45504",
    "addr:housenumber": "1150",
    "addr:postcode": "45504",
    "addr:street": "Bechtle Ave",
    "iso:country": "US",
    "sg:address": "1150 Bechtle Ave",
    "sg:city": "Springfield",
    "sg:classifiers": [
      {
        "category": "Bars \u0026 Pubs",
        "type": "Food \u0026 Drink"
      }
    ],
    "sg:phone": "+1 937 325 4414",
    "sg:postcode": "45504",
    "sg:province": "OH",
    "sg:tags": [
      "lounge",
      "drinking",
      "cocktail"
    ],
    "wof:name": "Che's Rustic Lounge",
    "wof:placetype": "venue"
  },
  "geometry": {"coordinates":[-83.83589,39.940569],"type":"Point"}
}
