{
  "type": "Feature",
  "properties": {
    "iso:country":"US",
    "sg:address":"1150 Bechtle Ave",
    "sg:city":"Springfield",
    "sg:classifiers":[
        {
            "category":"Bars & Pubs",
            "type":"Food & Drink"
        }
    ],
    "sg:phone":"+1 937 325 4414",
    "sg:postcode":"45504",
    "sg:province":"OH",
    "sg:tags":[
        "lounge",
        "drinking",
        "cocktail"
    ],
    "wof:name":"Che's Rustic Lounge",
    "wof:placetype":"venue"
},
  "geometry": {"coordinates":[-83.83589,39.940569],"type":"Point"}
}