{
  "type": "Feature",
  "properties": {
    "addr:full": "2255 W Broad St Columbus OH 43223",
    "addr:housenumber": "2255",
    "addr:postcode": "43223",
    "addr:street": "W Broad St",
    "iso:country": "US",
    "sg:address": "2255 W Broad St",
    "sg:city": "Columbus",
    "sg:classifiers": [
      {
        "category": "Real Estate",
        "subcategory": "Real Estate Agent",
        "type": "Services"
      }
    ],
    "sg:phone": "+1 614 276 5187",
    "sg:postcode": "43223",
    "sg:province": "OH",
    "wof:name": "Athen Properties",
    "wof:placetype": "venue"
  },
  "geometry": {"coordinates":[-83.059171,39.955652],"type":"Point"}
}
