{
  "type": "Feature",
  "properties": {
    "iso:country":"US",
    "sg:address":"1001 Lakeside Ave E",
    "sg:city":"Cleveland",
    "sg:classifiers":[
        {
            "category":"Travel",
            "subcategory":"Travel Agent",
            "type":"Entertainment"
        }
    ],
    "sg:phone":"+1 216 736 8575",
    "sg:postcode":"44114",
    "sg:province":"OH",
    "sg:tags":[
        "agency",
        "bureau"
    ],
    "wof:name":"Pie Travel",
    "wof:placetype":"venue"
},
  "geometry": {"coordinates":[-81.691285,41.50566],"type":"Point"}
}