{
  "type": "Feature",
  "properties": {
    "iso:country":"US",
    "sg:address":"23720 Deal Rd",
    "sg:city":"Gambier",
    "sg:phone":"+1 740 668 4195",
    "sg:postcode":"43022",
    "sg:province":"OH",
    "sg:tags":[
        "farm",
        "grain",
        "cash"
    ],
    "wof:name":"Veatch Farms",
    "wof:placetype":"venue"
},
  "geometry": {"coordinates":[-82.329166,40.291463],"type":"Point"}
}