{
  "type": "Feature",
  "properties": {
    "iso:country":"US",
    "sg:address":"4035 Marion-Marysville Rd",
    "sg:city":"Prospect",
    "sg:classifiers":[
        {
            "category":"Building & Trades",
            "subcategory":"Construction",
            "type":"Services"
        }
    ],
    "sg:phone":"+1 740 382 8324",
    "sg:postcode":"43342",
    "sg:province":"OH",
    "sg:tags":[
        "contractor",
        "co",
        "hanging"
    ],
    "wof:name":"A1 Lowes Doug Contracting",
    "wof:placetype":"venue"
},
  "geometry": {"coordinates":[-83.173886,40.508748],"type":"Point"}
}