{
  "type": "Feature",
  "properties": {
    "addr:full": "4035 Marion-Marysville Rd Prospect OH 43342",
    "addr:housenumber": "4035",
    "addr:postcode": "43342",
    "addr:street": "Marion-Marysville Rd",
    "iso:country": "US",
    "sg:address": "4035 Marion-Marysville Rd",
    "sg:city": "Prospect",
    "sg:classifiers": [
      {
        "category": "Building \u0026 Trades",
        "subcategory": "Construction",
        "type": "Services"
      }
    ],
    "sg:phone": "+1 740 382 8324",
    "sg:postcode": "43342",
    "sg:province": "OH",
    "sg:tags": [
      "contractor",
      "co",
      "hanging"
    ],
    "wof:name": "A1 Lowes Doug Contracting",
    "wof:placetype": "venue"
  },
  "geometry": {"coordinates":[-83.173886,40.508748],"type":"Point"}
}
