{
  "type": "Feature",
  "properties": {
    "addr:full": "1891 Sunbury Rd Columbus OH 43219",
    "addr:housenumber": "1891",
    "addr:postcode": "43219",
    "addr:street": "Sunbury Rd",
    "iso:country": "US",
    "sg:address": "1891 Sunbury Rd",
    "sg:city": "Columbus",
    "sg:classifiers": [
      {
        "category": "Social Services",
        "subcategory": "Adult Care",
        "type": "Services"
      }
    ],
    "sg:phone": "+1 614 475 9645",
    "sg:postcode": "43219",
    "sg:province": "OH",
    "sg:tags": [
      "home",
      "residential",
      "for",
      "mentally",
      "retarded"
    ],
    "wof:name": "The Ark",
    "wof:placetype": "venue"
  },
  "geometry": {"coordinates":[-82.935235,40.008884],"type":"Point"}
}
