{
  "type": "Feature",
  "properties": {
    "addr:full": "135 W Broadway St Dover OH 44622",
    "addr:housenumber": "135",
    "addr:postcode": "44622",
    "addr:street": "W Broadway St",
    "iso:country": "US",
    "sg:address": "135 W Broadway St",
    "sg:city": "Dover",
    "sg:classifiers": [
      {
        "category": "Autos \u0026 Motor Vehicles",
        "subcategory": "Automobile Sales",
        "type": "Retail Goods"
      }
    ],
    "sg:phone": "+1 330 343 7781",
    "sg:postcode": "44622",
    "sg:province": "OH",
    "sg:tags": [
      "used"
    ],
    "wof:name": "Nicholson Chuck Mazda",
    "wof:placetype": "venue"
  },
  "geometry": {"coordinates":[-81.472788,40.518838],"type":"Point"}
}
