{
  "type": "Feature",
  "properties": {
    "iso:country":"US",
    "sg:address":"2109 Ravine St",
    "sg:city":"Cincinnati",
    "sg:classifiers":[
        {
            "category":"Organizations",
            "subcategory":"Religious Organization",
            "type":"Services"
        }
    ],
    "sg:phone":"+1 513 621 6542",
    "sg:postcode":"45214",
    "sg:province":"OH",
    "sg:tags":[
        "church"
    ],
    "wof:name":"Mt Tabor Baptist Church",
    "wof:placetype":"venue"
},
  "geometry": {"coordinates":[-84.526113,39.122209],"type":"Point"}
}