{
  "type": "Feature",
  "properties": {
    "iso:country":"US",
    "sg:address":"11762 Marquart Rd",
    "sg:city":"New Carlisle",
    "sg:classifiers":[
        {
            "category":"Farming",
            "subcategory":"Farm",
            "type":"Manufacturing & Wholesale Goods"
        }
    ],
    "sg:phone":"+1 937 845 0320",
    "sg:postcode":"45344",
    "sg:province":"OH",
    "sg:tags":[
        "crop",
        "general"
    ],
    "wof:name":"Mike Bonham",
    "wof:placetype":"venue"
},
  "geometry": {"coordinates":[-84.025023,39.986183],"type":"Point"}
}