{
  "type": "Feature",
  "properties": {
    "addr:full": "11762 Marquart Rd New Carlisle OH 45344",
    "addr:housenumber": "11762",
    "addr:postcode": "45344",
    "addr:street": "Marquart Rd",
    "iso:country": "US",
    "sg:address": "11762 Marquart Rd",
    "sg:city": "New Carlisle",
    "sg:classifiers": [
      {
        "category": "Farming",
        "subcategory": "Farm",
        "type": "Manufacturing \u0026 Wholesale Goods"
      }
    ],
    "sg:phone": "+1 937 845 0320",
    "sg:postcode": "45344",
    "sg:province": "OH",
    "sg:tags": [
      "crop",
      "general"
    ],
    "wof:name": "Mike Bonham",
    "wof:placetype": "venue"
  },
  "geometry": {"coordinates":[-84.025023,39.986183],"type":"Point"}
}
