{
  "type": "Feature",
  "properties": {
    "iso:country":"US",
    "sg:address":"4911 Spruce Hill Dr NW",
    "sg:city":"Canton",
    "sg:classifiers":[
        {
            "category":"Personal",
            "type":"Services"
        }
    ],
    "sg:phone":"+1 330 244 9515",
    "sg:postcode":"44718",
    "sg:province":"OH",
    "sg:tags":[
        "therapist",
        "massage"
    ],
    "wof:name":"Essential Touch Massotherapy",
    "wof:placetype":"venue"
},
  "geometry": {"coordinates":[-81.44683,40.852552],"type":"Point"}
}