{
  "type": "Feature",
  "properties": {
    "addr:full":"3510 S Union Ave Alliance OH 44601",
    "addr:housenumber":"3510",
    "addr:postcode":"44601",
    "addr:street":"S Union Ave",
    "iso:country":"US",
    "sg:address":"3510 S Union Ave",
    "sg:city":"Alliance",
    "sg:classifiers":[
        {
            "category":"Organizations",
            "subcategory":"Membership Organization",
            "type":"Services"
        }
    ],
    "sg:phone":"+1 330 821 0844",
    "sg:postcode":"44601",
    "sg:province":"OH",
    "wof:name":"First Church Christ Scientist",
    "wof:placetype":"venue"
},
  "geometry": {"coordinates":[-81.105549,40.883466],"type":"Point"}
}