{
  "type": "Feature",
  "properties": {
    "addr:full": "4360 Newberry Dr Batavia OH 45103",
    "addr:housenumber": "4360",
    "addr:postcode": "45103",
    "addr:street": "Newberry Dr",
    "iso:country": "US",
    "sg:address": "4360 Newberry Dr",
    "sg:city": "Batavia",
    "sg:classifiers": [
      {
        "category": "Autos \u0026 Motor Vehicles",
        "subcategory": "Fuel \u0026 Gas Station",
        "type": "Retail Goods"
      }
    ],
    "sg:phone": "+1 513 752 9091",
    "sg:postcode": "45103",
    "sg:province": "OH",
    "sg:tags": [
      "station",
      "gasoline"
    ],
    "wof:name": "Thorntons Gas \u0026 Foodmart 67",
    "wof:placetype": "venue"
  },
  "geometry": {"coordinates":[-84.247001,39.089729],"type":"Point"}
}
