{
  "type": "Feature",
  "properties": {
    "addr:full": "1214 N Monroe Dr Xenia OH 45385",
    "addr:housenumber": "1214",
    "addr:postcode": "45385",
    "addr:street": "N Monroe Dr",
    "iso:country": "US",
    "sg:address": "1214 N Monroe Dr",
    "sg:city": "Xenia",
    "sg:classifiers": [
      {
        "category": "Health Services",
        "subcategory": "Optometrist",
        "type": "Services"
      }
    ],
    "sg:phone": "+1 937 376 8255",
    "sg:postcode": "45385",
    "sg:province": "OH",
    "wof:name": "Gaynier Eye Clinic",
    "wof:placetype": "venue"
  },
  "geometry": {"coordinates":[-83.928927,39.700704],"type":"Point"}
}
