{
  "type": "Feature",
  "properties": {
    "addr:full": "1761 Academy Pl Dayton OH 45406",
    "addr:housenumber": "1761",
    "addr:postcode": "45406",
    "addr:street": "Academy Pl",
    "iso:country": "US",
    "sg:address": "1761 Academy Pl",
    "sg:city": "Dayton",
    "sg:classifiers": [
      {
        "category": "Organizations",
        "subcategory": "Religious Organization",
        "type": "Services"
      }
    ],
    "sg:phone": "+1 937 279 2213",
    "sg:postcode": "45406",
    "sg:province": "OH",
    "sg:tags": [
      "clergy"
    ],
    "wof:name": "Joseph C Mc Queen",
    "wof:placetype": "venue"
  },
  "geometry": {"coordinates":[-84.232778,39.774736],"type":"Point"}
}
