{
  "type": "Feature",
  "properties": {
    "iso:country":"US",
    "sg:address":"615 Front St",
    "sg:city":"Toledo",
    "sg:classifiers":[
        {
            "category":"Sports & Exercise",
            "subcategory":"Gym",
            "type":"Entertainment"
        }
    ],
    "sg:phone":"+1 419 691 2584",
    "sg:postcode":"43605",
    "sg:province":"OH",
    "sg:tags":[
        "club",
        "health",
        "studio",
        "gymnasium"
    ],
    "wof:name":"International Boxing Club",
    "wof:placetype":"venue"
},
  "geometry": {"coordinates":[-83.52269699999999,41.649067],"type":"Point"}
}