{
  "type": "Feature",
  "properties": {
    "addr:full": "3030 N High St Columbus OH 43202",
    "addr:housenumber": "3030",
    "addr:postcode": "43202",
    "addr:street": "N High St",
    "iso:country": "US",
    "sg:address": "3030 N High St",
    "sg:city": "Columbus",
    "sg:classifiers": [
      {
        "category": "Shopping",
        "subcategory": "Bicycles \u0026 Sporting Goods",
        "type": "Retail Goods"
      }
    ],
    "sg:phone": "+1 614 267 7178",
    "sg:postcode": "43202",
    "sg:province": "OH",
    "sg:tags": [
      "repair"
    ],
    "wof:name": "Baer Wheels",
    "wof:placetype": "venue"
  },
  "geometry": {"coordinates":[-83.013659,40.023439],"type":"Point"}
}
