{
  "type": "Feature",
  "properties": {
    "iso:country":"US",
    "sg:address":"14984 Emerson Rd",
    "sg:city":"Dalton",
    "sg:classifiers":[
        {
            "category":"Farming",
            "subcategory":"Dairy Farm",
            "type":"Manufacturing & Wholesale Goods"
        }
    ],
    "sg:phone":"+1 330 857 3375",
    "sg:postcode":"44618",
    "sg:province":"OH",
    "sg:tags":[
        "real",
        "property",
        "lessor"
    ],
    "wof:name":"David Gerber Farm",
    "wof:placetype":"venue"
},
  "geometry": {"coordinates":[-81.717617,40.741142],"type":"Point"}
}