{
  "type": "Feature",
  "properties": {
    "addr:full":"8805 Buckeye Rd Cleveland OH 44104",
    "addr:housenumber":"8805",
    "addr:postcode":"44104",
    "addr:street":"Buckeye Rd",
    "iso:country":"US",
    "sg:address":"8805 Buckeye Rd",
    "sg:city":"Cleveland",
    "sg:classifiers":[
        {
            "category":"Autos & Motor Vehicles",
            "subcategory":"Fuel & Gas Station",
            "type":"Retail Goods"
        }
    ],
    "sg:phone":"+1 216 229 2029",
    "sg:postcode":"44104",
    "sg:province":"OH",
    "sg:tags":[
        "station",
        "gasoline"
    ],
    "wof:name":"8805 Buckeye Inc",
    "wof:placetype":"venue"
},
  "geometry": {"coordinates":[-81.62513300000001,41.486488],"type":"Point"}
}