{
  "type": "Feature",
  "properties": {
    "addr:full": "4740 State Rd Cleveland OH 44109",
    "addr:housenumber": "4740",
    "addr:postcode": "44109",
    "addr:street": "State Rd",
    "iso:country": "US",
    "sg:address": "4740 State Rd",
    "sg:city": "Cleveland",
    "sg:classifiers": [
      {
        "category": "Retail",
        "subcategory": "Auto Repair",
        "type": "Services"
      }
    ],
    "sg:phone": "+1 216 741 6300",
    "sg:postcode": "44109",
    "sg:province": "OH",
    "sg:tags": [
      "construction",
      "electrical"
    ],
    "wof:name": "Premier Electrical Contracting",
    "wof:placetype": "venue"
  },
  "geometry": {"coordinates":[-81.709854,41.425084],"type":"Point"}
}
