{
  "type": "Feature",
  "properties": {
    "iso:country":"US",
    "sg:address":"1392 Eriewood Dr",
    "sg:city":"Cleveland",
    "sg:classifiers":[
        {
            "category":"Professional",
            "subcategory":"Accounting & Tax Preparation",
            "type":"Services"
        }
    ],
    "sg:phone":"+1 440 333 3335",
    "sg:postcode":"44116",
    "sg:province":"OH",
    "sg:tags":[
        "bookkeeping",
        "general"
    ],
    "wof:name":"E-Counting Electronic Bkpg",
    "wof:placetype":"venue"
},
  "geometry": {"coordinates":[-81.85675500000001,41.474407],"type":"Point"}
}