{
  "type": "Feature",
  "properties": {
    "addr:full": "1392 Eriewood Dr Cleveland OH 44116",
    "addr:housenumber": "1392",
    "addr:postcode": "44116",
    "addr:street": "Eriewood Dr",
    "iso:country": "US",
    "sg:address": "1392 Eriewood Dr",
    "sg:city": "Cleveland",
    "sg:classifiers": [
      {
        "category": "Professional",
        "subcategory": "Accounting \u0026 Tax Preparation",
        "type": "Services"
      }
    ],
    "sg:phone": "+1 440 333 3335",
    "sg:postcode": "44116",
    "sg:province": "OH",
    "sg:tags": [
      "bookkeeping",
      "general"
    ],
    "wof:name": "E-Counting Electronic Bkpg",
    "wof:placetype": "venue"
  },
  "geometry": {"coordinates":[-81.856755,41.474407],"type":"Point"}
}
