{
  "type": "Feature",
  "properties": {
    "iso:country":"US",
    "sg:address":"3333 Co Rd 140",
    "sg:city":"Findlay",
    "sg:classifiers":[
        {
            "category":"Wholesale",
            "subcategory":"Auto Parts",
            "type":"Manufacturing & Wholesale Goods"
        }
    ],
    "sg:phone":"+1 419 299 3336",
    "sg:postcode":"45840",
    "sg:province":"OH",
    "sg:tags":[
        "automobile",
        "rebuilt",
        "used",
        "supply"
    ],
    "wof:name":"Findlay Auto Parts Inc",
    "wof:placetype":"venue"
},
  "geometry": {"coordinates":[-83.688407,41.122124],"type":"Point"}
}