{
  "type": "Feature",
  "properties": {
    "addr:full": "3333 Co Rd 140 Findlay OH 45840",
    "addr:housenumber": "3333",
    "addr:postcode": "45840",
    "addr:street": "Co Rd 140",
    "iso:country": "US",
    "sg:address": "3333 Co Rd 140",
    "sg:city": "Findlay",
    "sg:classifiers": [
      {
        "category": "Wholesale",
        "subcategory": "Auto Parts",
        "type": "Manufacturing \u0026 Wholesale Goods"
      }
    ],
    "sg:phone": "+1 419 299 3336",
    "sg:postcode": "45840",
    "sg:province": "OH",
    "sg:tags": [
      "automobile",
      "rebuilt",
      "used",
      "supply"
    ],
    "wof:name": "Findlay Auto Parts Inc",
    "wof:placetype": "venue"
  },
  "geometry": {"coordinates":[-83.688407,41.122124],"type":"Point"}
}
