{
  "type": "Feature",
  "properties": {
    "addr:full":"7545 Muirwood Ct Chagrin Falls OH 44023",
    "addr:housenumber":"7545",
    "addr:postcode":"44023",
    "addr:street":"Muirwood Ct",
    "iso:country":"US",
    "sg:address":"7545 Muirwood Ct",
    "sg:city":"Chagrin Falls",
    "sg:classifiers":[
        {
            "category":"Banks & Credit Unions",
            "subcategory":"Investment Brokerage",
            "type":"Services"
        }
    ],
    "sg:phone":"+1 440 543 6220",
    "sg:postcode":"44023",
    "sg:province":"OH",
    "sg:tags":[
        "advisory",
        "financial"
    ],
    "wof:name":"Northern Financial Group LTD",
    "wof:placetype":"venue"
},
  "geometry": {"coordinates":[-81.372685,41.417145],"type":"Point"}
}