{
  "type": "Feature",
  "properties": {
    "iso:country":"US",
    "sg:address":"508 S Cleveland Ave",
    "sg:city":"Mogadore",
    "sg:classifiers":[
        {
            "category":"Wholesale",
            "subcategory":"Auto Parts",
            "type":"Manufacturing & Wholesale Goods"
        }
    ],
    "sg:phone":"+1 330 628 9900",
    "sg:postcode":"44260",
    "sg:province":"OH",
    "sg:tags":[
        "automobile",
        "rebuilt"
    ],
    "wof:name":"Mars Auto & Truck Parts",
    "wof:placetype":"venue"
},
  "geometry": {"coordinates":[-81.39330200000001,41.037782],"type":"Point"}
}