{
  "type": "Feature",
  "properties": {
    "addr:full": "100 Highland Dr Medina OH 44256",
    "addr:housenumber": "100",
    "addr:postcode": "44256",
    "addr:street": "Highland Dr",
    "iso:country": "US",
    "sg:address": "100 Highland Dr",
    "sg:city": "Medina",
    "sg:classifiers": [
      {
        "category": "Professional",
        "subcategory": "Management \u0026 Consulting",
        "type": "Services"
      }
    ],
    "sg:phone": "+1 330 725 5608",
    "sg:postcode": "44256",
    "sg:province": "OH",
    "sg:tags": [
      "consultant",
      "resource",
      "human"
    ],
    "wof:name": "Premium Enterprises Inc",
    "wof:placetype": "venue"
  },
  "geometry": {"coordinates":[-81.865763,41.148871],"type":"Point"}
}
