{
  "type": "Feature",
  "properties": {
    "addr:full": "7185 W Chester Rd West Chester OH 45069",
    "addr:housenumber": "7185",
    "addr:postcode": "45069",
    "addr:street": "W Chester Rd",
    "iso:country": "US",
    "sg:address": "7185 W Chester Rd",
    "sg:city": "West Chester",
    "sg:classifiers": [
      {
        "category": "Professional",
        "subcategory": "Management \u0026 Consulting",
        "type": "Services"
      }
    ],
    "sg:phone": "+1 513 860 1300",
    "sg:postcode": "45069",
    "sg:province": "OH",
    "sg:tags": [
      "marketing",
      "consultant"
    ],
    "wof:name": "Cinron Marketing",
    "wof:placetype": "venue"
  },
  "geometry": {"coordinates":[-84.388218,39.321946],"type":"Point"}
}
