{
  "type": "Feature",
  "properties": {
    "iso:country":"US",
    "sg:address":"7185 W Chester Rd",
    "sg:city":"West Chester",
    "sg:classifiers":[
        {
            "category":"Professional",
            "subcategory":"Management & Consulting",
            "type":"Services"
        }
    ],
    "sg:phone":"+1 513 860 1300",
    "sg:postcode":"45069",
    "sg:province":"OH",
    "sg:tags":[
        "marketing",
        "consultant"
    ],
    "wof:name":"Cinron Marketing",
    "wof:placetype":"venue"
},
  "geometry": {"coordinates":[-84.38821799999999,39.321946],"type":"Point"}
}