{
  "type": "Feature",
  "properties": {
    "addr:full": "345 W William St Delaware OH 43015",
    "addr:housenumber": "345",
    "addr:postcode": "43015",
    "addr:street": "W William St",
    "iso:country": "US",
    "sg:address": "345 W William St",
    "sg:city": "Delaware",
    "sg:classifiers": [
      {
        "category": "Retail",
        "subcategory": "Repair Shop",
        "type": "Services"
      }
    ],
    "sg:phone": "+1 740 369 3093",
    "sg:postcode": "43015",
    "sg:province": "OH",
    "sg:tags": [
      "refinishing",
      "furniture"
    ],
    "sg:website": "www.leather-doctor.com",
    "wof:name": "Leather Doctor",
    "wof:placetype": "venue"
  },
  "geometry": {"coordinates":[-83.081943,40.299371],"type":"Point"}
}
