{
  "type": "Feature",
  "properties": {
    "addr:full": "10675 Center Rd Blue Rock OH 43720",
    "addr:housenumber": "10675",
    "addr:postcode": "43720",
    "addr:street": "Center Rd",
    "iso:country": "US",
    "sg:address": "10675 Center Rd",
    "sg:city": "Blue Rock",
    "sg:classifiers": [
      {
        "category": "Farming",
        "subcategory": "Livestock Farm",
        "type": "Manufacturing \u0026 Wholesale Goods"
      }
    ],
    "sg:phone": "+1 740 697 7868",
    "sg:postcode": "43720",
    "sg:province": "OH",
    "sg:tags": [
      "beef",
      "feedlot",
      "cattle"
    ],
    "wof:name": "Donald \u0026 Wilma Fisher",
    "wof:placetype": "venue"
  },
  "geometry": {"coordinates":[-82.000732,39.770424],"type":"Point"}
}
