{
  "type": "Feature",
  "properties": {
    "iso:country":"US",
    "sg:address":"3900 Kinross Lakes Pkwy",
    "sg:city":"Richfield",
    "sg:classifiers":[
        {
            "category":"Manufacturing",
            "subcategory":"Tools & Machinery",
            "type":"Manufacturing & Wholesale Goods"
        }
    ],
    "sg:phone":"+1 330 659 1600",
    "sg:postcode":"44286",
    "sg:province":"OH",
    "sg:tags":[
        "equipment",
        "optical",
        "disk",
        "supply"
    ],
    "sg:website":"www.proquest.com",
    "wof:name":"Pro Quest Publishing Svc",
    "wof:placetype":"venue"
},
  "geometry": {"coordinates":[-81.630223,41.223918],"type":"Point"}
}