{
  "type": "Feature",
  "properties": {
    "addr:full": "5425 Maureen Dr NW Canton OH 44718",
    "addr:housenumber": "5425",
    "addr:postcode": "44718",
    "addr:street": "Maureen Dr Nw",
    "iso:country": "US",
    "sg:address": "5425 Maureen Dr NW",
    "sg:city": "Canton",
    "sg:classifiers": [
      {
        "category": "Building \u0026 Trades",
        "subcategory": "Construction",
        "type": "Services"
      }
    ],
    "sg:phone": "+1 330 492 8843",
    "sg:postcode": "44718",
    "sg:province": "OH",
    "sg:tags": [
      "painter"
    ],
    "wof:name": "Akro Painting \u0026 Wood Inc",
    "wof:placetype": "venue"
  },
  "geometry": {"coordinates":[-81.451447,40.849957],"type":"Point"}
}
