{
  "type": "Feature",
  "properties": {
    "iso:country":"US",
    "sg:address":"201 E High St",
    "sg:city":"Bryan",
    "sg:classifiers":[
        {
            "category":"Social Services",
            "type":"Services"
        }
    ],
    "sg:phone":"+1 419 636 8395",
    "sg:postcode":"43506",
    "sg:province":"OH",
    "sg:tags":[
        "assault",
        "abuse",
        "sexual",
        "crisis"
    ],
    "wof:name":"Women & Family Svc",
    "wof:placetype":"venue"
},
  "geometry": {"coordinates":[-84.549055,41.474609],"type":"Point"}
}