{
  "type": "Feature",
  "properties": {
    "iso:country":"US",
    "sg:address":"4477 E 49th St",
    "sg:city":"Cleveland",
    "sg:classifiers":[
        {
            "category":"Manufacturing",
            "subcategory":"Motor Vehicles & Parts",
            "type":"Manufacturing & Wholesale Goods"
        }
    ],
    "sg:phone":"+1 216 441 0120",
    "sg:postcode":"44125",
    "sg:province":"OH",
    "sg:tags":[
        "locomotive"
    ],
    "sg:website":"www.ge.com",
    "wof:name":"G E Transportation",
    "wof:placetype":"venue"
},
  "geometry": {"coordinates":[-81.656629,41.436256],"type":"Point"}
}