{
  "type": "Feature",
  "properties": {
    "addr:full": "206 E Cuyahoga Falls Ave Akron OH 44310",
    "addr:housenumber": "206",
    "addr:postcode": "44310",
    "addr:street": "E Cuyahoga Falls Ave",
    "iso:country": "US",
    "sg:address": "206 E Cuyahoga Falls Ave",
    "sg:city": "Akron",
    "sg:classifiers": [
      {
        "category": "Shopping",
        "type": "Retail Goods"
      }
    ],
    "sg:phone": "+1 330 928 8610",
    "sg:postcode": "44310",
    "sg:province": "OH",
    "sg:tags": [
      "typewriter"
    ],
    "wof:name": "North Akron Typewriter \u0026 Elect",
    "wof:placetype": "venue"
  },
  "geometry": {"coordinates":[-81.508708,41.108478],"type":"Point"}
}
