{
  "type": "Feature",
  "properties": {
    "addr:full":"4412 Linden Ave Dayton OH 45432",
    "addr:housenumber":"4412",
    "addr:postcode":"45432",
    "addr:street":"Linden Ave",
    "iso:country":"US",
    "sg:address":"4412 Linden Ave",
    "sg:city":"Dayton",
    "sg:classifiers":[
        {
            "category":"Restaurant",
            "type":"Food & Drink"
        }
    ],
    "sg:phone":"+1 937 253 9988",
    "sg:postcode":"45432",
    "sg:province":"OH",
    "sg:tags":[
        "delicatessen"
    ],
    "wof:name":"Linden Marathon",
    "wof:placetype":"venue"
},
  "geometry": {"coordinates":[-84.117009,39.743974],"type":"Point"}
}