{
  "type": "Feature",
  "properties": {
    "iso:country":"US",
    "sg:address":"1259 US Hwy 50",
    "sg:city":"Milford",
    "sg:classifiers":[
        {
            "category":"Home & Garden",
            "subcategory":"Building Materials",
            "type":"Retail Goods"
        }
    ],
    "sg:phone":"+1 513 831 2274",
    "sg:postcode":"45150",
    "sg:province":"OH",
    "sg:tags":[
        "glass",
        "window",
        "plate"
    ],
    "wof:name":"Timrek & Assoc Inc",
    "wof:placetype":"venue"
},
  "geometry": {"coordinates":[-84.233814,39.135326],"type":"Point"}
}