{
  "type": "Feature",
  "properties": {
    "addr:full": "1259 US Hwy 50 Milford OH 45150",
    "addr:housenumber": "1259",
    "addr:postcode": "45150",
    "addr:street": "Us Hwy 50",
    "iso:country": "US",
    "sg:address": "1259 US Hwy 50",
    "sg:city": "Milford",
    "sg:classifiers": [
      {
        "category": "Home \u0026 Garden",
        "subcategory": "Building Materials",
        "type": "Retail Goods"
      }
    ],
    "sg:phone": "+1 513 831 2274",
    "sg:postcode": "45150",
    "sg:province": "OH",
    "sg:tags": [
      "glass",
      "window",
      "plate"
    ],
    "wof:name": "Timrek \u0026 Assoc Inc",
    "wof:placetype": "venue"
  },
  "geometry": {"coordinates":[-84.233814,39.135326],"type":"Point"}
}
