{
  "type": "Feature",
  "properties": {
    "addr:full": "710 N Chapel St Louisville OH 44641",
    "addr:housenumber": "710",
    "addr:postcode": "44641",
    "addr:street": "N Chapel St",
    "iso:country": "US",
    "sg:address": "710 N Chapel St",
    "sg:city": "Louisville",
    "sg:classifiers": [
      {
        "category": "Wholesale",
        "subcategory": "Hardware",
        "type": "Manufacturing \u0026 Wholesale Goods"
      }
    ],
    "sg:phone": "+1 330 875 3327",
    "sg:postcode": "44641",
    "sg:province": "OH",
    "sg:tags": [
      "plumbing"
    ],
    "wof:name": "Carter Plumbing Electric \u0026 Htg",
    "wof:placetype": "venue"
  },
  "geometry": {"coordinates":[-81.259349,40.841556],"type":"Point"}
}
