{
  "type": "Feature",
  "properties": {
    "iso:country":"US",
    "sg:address":"3880 Linden Ave",
    "sg:city":"Dayton",
    "sg:classifiers":[
        {
            "category":"Shopping",
            "subcategory":"Used Merchandise",
            "type":"Retail Goods"
        }
    ],
    "sg:phone":"+1 937 825 4444",
    "sg:postcode":"45432",
    "sg:province":"OH",
    "sg:tags":[
        "shop",
        "consignment"
    ],
    "wof:name":"Village Discount Outlet",
    "wof:placetype":"venue"
},
  "geometry": {"coordinates":[-84.127443,39.747166],"type":"Point"}
}