{
  "type": "Feature",
  "properties": {
    "iso:country":"US",
    "sg:address":"11867 Reitz Rd",
    "sg:city":"Perrysburg",
    "sg:classifiers":[
        {
            "category":"Professional",
            "type":"Services"
        }
    ],
    "sg:phone":"+1 419 874 7468",
    "sg:postcode":"43551",
    "sg:province":"OH",
    "wof:name":"Rolland Emch Jr",
    "wof:placetype":"venue"
},
  "geometry": {"coordinates":[-83.62299899999999,41.492581],"type":"Point"}
}