{
  "type": "Feature",
  "properties": {
    "iso:country":"US",
    "sg:address":"2071 Celestial Dr NE",
    "sg:city":"Warren",
    "sg:classifiers":[
        {
            "category":"Travel",
            "subcategory":"Hotels & Motels",
            "type":"Entertainment"
        }
    ],
    "sg:phone":"+1 330 369 4100",
    "sg:postcode":"44484",
    "sg:province":"OH",
    "sg:tags":[
        "lodging"
    ],
    "sg:website":"http://www.travelodge.com",
    "wof:name":"Travelodge",
    "wof:placetype":"venue"
},
  "geometry": {"coordinates":[-80.71409199999999,41.258848],"type":"Point"}
}