{
  "type": "Feature",
  "properties": {
    "addr:full": "207 Vine St Archbold OH 43502",
    "addr:housenumber": "207",
    "addr:postcode": "43502",
    "addr:street": "Vine St",
    "iso:country": "US",
    "sg:address": "207 Vine St",
    "sg:city": "Archbold",
    "sg:classifiers": [
      {
        "category": "Social Services",
        "type": "Services"
      }
    ],
    "sg:phone": "+1 419 445 1552",
    "sg:postcode": "43502",
    "sg:province": "OH",
    "sg:tags": [
      "counseling"
    ],
    "wof:name": "Shalom Wellness Ctr",
    "wof:placetype": "venue"
  },
  "geometry": {"coordinates":[-84.305093,41.523565],"type":"Point"}
}
