{
  "type": "Feature",
  "properties": {
    "addr:full": "2261 Stringtown Rd Grove City OH 43123",
    "addr:housenumber": "2261",
    "addr:postcode": "43123",
    "addr:street": "Stringtown Rd",
    "iso:country": "US",
    "sg:address": "2261 Stringtown Rd",
    "sg:city": "Grove City",
    "sg:classifiers": [
      {
        "category": "Restaurant",
        "type": "Food \u0026 Drink"
      }
    ],
    "sg:phone": "+1 614 539 4540",
    "sg:postcode": "43123",
    "sg:province": "OH",
    "wof:name": "Casa Fiesta",
    "wof:placetype": "venue"
  },
  "geometry": {"coordinates":[-83.063226,39.878742],"type":"Point"}
}
