{
  "type": "Feature",
  "properties": {
    "addr:full":"27 E Main St Tipp City OH 45371",
    "addr:housenumber":"27",
    "addr:postcode":"45371",
    "addr:street":"E Main St",
    "iso:country":"US",
    "sg:address":"27 E Main St",
    "sg:city":"Tipp City",
    "sg:classifiers":[
        {
            "category":"Shopping",
            "subcategory":"Used Merchandise",
            "type":"Retail Goods"
        }
    ],
    "sg:phone":"+1 937 667 8861",
    "sg:postcode":"45371",
    "sg:province":"OH",
    "sg:tags":[
        "antique"
    ],
    "wof:name":"Angel's Antiques",
    "wof:placetype":"venue"
},
  "geometry": {"coordinates":[-84.17025,39.961326],"type":"Point"}
}