{
  "type": "Feature",
  "properties": {
    "iso:country":"US",
    "sg:address":"7225 Old Oak Blvd",
    "sg:city":"Cleveland",
    "sg:classifiers":[
        {
            "category":"Health Services",
            "subcategory":"Doctor",
            "type":"Services"
        }
    ],
    "sg:phone":"+1 440 826 9221",
    "sg:postcode":"44130",
    "sg:province":"OH",
    "sg:tags":[
        "physician",
        "surgeon"
    ],
    "wof:name":"Southwest Neurology Inc",
    "wof:placetype":"venue"
},
  "geometry": {"coordinates":[-81.833382,41.359457],"type":"Point"}
}