{
  "type": "Feature",
  "properties": {
    "iso:country":"US",
    "sg:address":"4392 Santa Michelle Ct",
    "sg:city":"Columbus",
    "sg:classifiers":[
        {
            "category":"Restaurant",
            "type":"Food & Drink"
        }
    ],
    "sg:phone":"+1 614 409 2580",
    "sg:postcode":"43207",
    "sg:province":"OH",
    "sg:tags":[
        "cake",
        "wedding"
    ],
    "wof:name":"Cake Dots Wedding Cakes",
    "wof:placetype":"venue"
},
  "geometry": {"coordinates":[-82.984604,39.872685],"type":"Point"}
}