{
  "type": "Feature",
  "properties": {
    "addr:full":"1124 N Memorial Dr Lancaster OH 43130",
    "addr:housenumber":"1124",
    "addr:postcode":"43130",
    "addr:street":"N Memorial Dr",
    "iso:country":"US",
    "sg:address":"1124 N Memorial Dr",
    "sg:city":"Lancaster",
    "sg:classifiers":[
        {
            "category":"Banks & Credit Unions",
            "subcategory":"Bank",
            "type":"Services"
        }
    ],
    "sg:phone":"+1 740 653 1650",
    "sg:postcode":"43130",
    "sg:province":"OH",
    "sg:tags":[
        "financing"
    ],
    "wof:name":"Citi Financial",
    "wof:placetype":"venue"
},
  "geometry": {"coordinates":[-82.609426,39.726174],"type":"Point"}
}