{
  "type": "Feature",
  "properties": {
    "addr:full":"18683 Marne Rd NE Nashport OH 43830",
    "addr:housenumber":"18683",
    "addr:postcode":"43830",
    "addr:street":"Marne Rd Ne",
    "iso:country":"US",
    "sg:address":"18683 Marne Rd NE",
    "sg:city":"Nashport",
    "sg:classifiers":[
        {
            "category":"Freight",
            "type":"Transportation"
        }
    ],
    "sg:phone":"+1 740 763 2822",
    "sg:postcode":"43830",
    "sg:province":"OH",
    "sg:tags":[
        "operator",
        "local",
        "trucking"
    ],
    "wof:name":"Shaws Trucking",
    "wof:placetype":"venue"
},
  "geometry": {"coordinates":[-82.205292,40.09271],"type":"Point"}
}