{
  "type": "Feature",
  "properties": {
    "iso:country":"US",
    "sg:address":"1088 E Weber Rd",
    "sg:city":"Columbus",
    "sg:classifiers":[
        {
            "category":"Organizations",
            "subcategory":"Religious Organization",
            "type":"Services"
        }
    ],
    "sg:phone":"+1 614 262 2626",
    "sg:postcode":"43211",
    "sg:province":"OH",
    "sg:tags":[
        "church"
    ],
    "wof:name":"Way Of Holiness Churches Inc",
    "wof:placetype":"venue"
},
  "geometry": {"coordinates":[-82.983437,40.023649],"type":"Point"}
}