{
  "type": "Feature",
  "properties": {
    "addr:full": "224 Cedar Hill Rd Lancaster OH 43130",
    "addr:housenumber": "224",
    "addr:postcode": "43130",
    "addr:street": "Cedar Hill Rd",
    "iso:country": "US",
    "sg:address": "224 Cedar Hill Rd",
    "sg:city": "Lancaster",
    "sg:classifiers": [
      {
        "category": "Wholesale",
        "subcategory": "Scrap",
        "type": "Manufacturing \u0026 Wholesale Goods"
      }
    ],
    "sg:phone": "+1 740 653 8765",
    "sg:postcode": "43130",
    "sg:province": "OH",
    "sg:tags": [
      "metal",
      "iron"
    ],
    "sg:website": "www.sierrametals.com",
    "wof:name": "Sierra Metals",
    "wof:placetype": "venue"
  },
  "geometry": {"coordinates":[-82.61541,39.71331],"type":"Point"}
}
