{
  "type": "Feature",
  "properties": {
    "iso:country":"US",
    "sg:address":"336 N Columbus St",
    "sg:city":"Lancaster",
    "sg:classifiers":[
        {
            "category":"Real Estate",
            "subcategory":"Real Estate Agent",
            "type":"Services"
        }
    ],
    "sg:phone":"+1 740 687 0222",
    "sg:postcode":"43130",
    "sg:province":"OH",
    "wof:name":"Wacker Realty",
    "wof:placetype":"venue"
},
  "geometry": {"coordinates":[-82.60438600000001,39.716439],"type":"Point"}
}