{
  "type": "Feature",
  "properties": {
    "addr:full": "336 N Columbus St Lancaster OH 43130",
    "addr:housenumber": "336",
    "addr:postcode": "43130",
    "addr:street": "N Columbus St",
    "iso:country": "US",
    "sg:address": "336 N Columbus St",
    "sg:city": "Lancaster",
    "sg:classifiers": [
      {
        "category": "Real Estate",
        "subcategory": "Real Estate Agent",
        "type": "Services"
      }
    ],
    "sg:phone": "+1 740 687 0222",
    "sg:postcode": "43130",
    "sg:province": "OH",
    "wof:name": "Wacker Realty",
    "wof:placetype": "venue"
  },
  "geometry": {"coordinates":[-82.604386,39.716439],"type":"Point"}
}
