{
  "type": "Feature",
  "properties": {
    "addr:full": "4289 State Rte 122 Franklin OH 45005",
    "addr:housenumber": "4289",
    "addr:postcode": "45005",
    "addr:street": "State Rte 122",
    "iso:country": "US",
    "sg:address": "4289 State Rte 122",
    "sg:city": "Franklin",
    "sg:classifiers": [
      {
        "category": "Organizations",
        "subcategory": "Religious Organization",
        "type": "Services"
      }
    ],
    "sg:phone": "+1 937 746 1653",
    "sg:postcode": "45005",
    "sg:province": "OH",
    "wof:name": "Eastview Baptist Church",
    "wof:placetype": "venue"
  },
  "geometry": {"coordinates":[-84.286214,39.492828],"type":"Point"}
}
