{
  "type": "Feature",
  "properties": {
    "addr:full": "716 Woodlawn Ave Sandusky OH 44870",
    "addr:housenumber": "716",
    "addr:postcode": "44870",
    "addr:street": "Woodlawn Ave",
    "iso:country": "US",
    "sg:address": "716 Woodlawn Ave",
    "sg:city": "Sandusky",
    "sg:classifiers": [
      {
        "category": "Retail",
        "subcategory": "Repair Shop",
        "type": "Services"
      }
    ],
    "sg:phone": "+1 419 625 4949",
    "sg:postcode": "44870",
    "sg:province": "OH",
    "sg:tags": [
      "repairing",
      "lawn",
      "mower"
    ],
    "wof:name": "Nort Small Engines",
    "wof:placetype": "venue"
  },
  "geometry": {"coordinates":[-82.68419,41.42347],"type":"Point"}
}
