{
  "type": "Feature",
  "properties": {
    "iso:country":"US",
    "sg:address":"14615 Co Rd 66A",
    "sg:city":"Saint Marys",
    "sg:phone":"+1 419 394 8020",
    "sg:postcode":"45885",
    "sg:province":"OH",
    "sg:tags":[
        "farm",
        "corn",
        "soybean"
    ],
    "wof:name":"Edward Yahl",
    "wof:placetype":"venue"
},
  "geometry": {"coordinates":[-84.37753499999999,40.572223],"type":"Point"}
}