{
  "type": "Feature",
  "properties": {
    "addr:full": "14615 Co Rd 66A Saint Marys OH 45885",
    "addr:housenumber": "14615;66a",
    "addr:postcode": "45885",
    "addr:street": "Co Rd",
    "iso:country": "US",
    "sg:address": "14615 Co Rd 66A",
    "sg:city": "Saint Marys",
    "sg:phone": "+1 419 394 8020",
    "sg:postcode": "45885",
    "sg:province": "OH",
    "sg:tags": [
      "farm",
      "corn",
      "soybean"
    ],
    "wof:name": "Edward Yahl",
    "wof:placetype": "venue"
  },
  "geometry": {"coordinates":[-84.377535,40.572223],"type":"Point"}
}
