{
  "type": "Feature",
  "properties": {
    "addr:full": "425 Walnut St Cincinnati OH 45202",
    "addr:housenumber": "425",
    "addr:postcode": "45202",
    "addr:street": "Walnut St",
    "iso:country": "US",
    "sg:address": "425 Walnut St",
    "sg:city": "Cincinnati",
    "sg:classifiers": [
      {
        "category": "Government",
        "subcategory": "Office",
        "type": "Public Place"
      }
    ],
    "sg:phone": "+1 513 852 2826",
    "sg:postcode": "45202",
    "sg:province": "OH",
    "sg:tags": [
      "state"
    ],
    "wof:name": "Governor's Economic Devel Ofc",
    "wof:placetype": "venue"
  },
  "geometry": {"coordinates":[-84.511373,39.100998],"type":"Point"}
}
