{
  "type": "Feature",
  "properties": {
    "iso:country":"US",
    "sg:address":"425 Walnut St",
    "sg:city":"Cincinnati",
    "sg:classifiers":[
        {
            "category":"Government",
            "subcategory":"Office",
            "type":"Public Place"
        }
    ],
    "sg:phone":"+1 513 852 2826",
    "sg:postcode":"45202",
    "sg:province":"OH",
    "sg:tags":[
        "state"
    ],
    "wof:name":"Governor's Economic Devel Ofc",
    "wof:placetype":"venue"
},
  "geometry": {"coordinates":[-84.51137300000001,39.100998],"type":"Point"}
}