{
  "type": "Feature",
  "properties": {
    "addr:full": "5630 Bridgetown Rd Cincinnati OH 45248",
    "addr:housenumber": "5630",
    "addr:postcode": "45248",
    "addr:street": "Bridgetown Rd",
    "iso:country": "US",
    "sg:address": "5630 Bridgetown Rd",
    "sg:city": "Cincinnati",
    "sg:classifiers": [
      {
        "category": "Health Services",
        "subcategory": "Doctor",
        "type": "Services"
      }
    ],
    "sg:phone": "+1 513 574 7511",
    "sg:postcode": "45248",
    "sg:province": "OH",
    "sg:tags": [
      "dentist"
    ],
    "wof:name": "Bridgetown Family Dentistry",
    "wof:placetype": "venue"
  },
  "geometry": {"coordinates":[-84.633695,39.158593],"type":"Point"}
}
