{
  "type": "Feature",
  "properties": {
    "iso:country":"US",
    "sg:address":"5630 Bridgetown Rd",
    "sg:city":"Cincinnati",
    "sg:classifiers":[
        {
            "category":"Health Services",
            "subcategory":"Doctor",
            "type":"Services"
        }
    ],
    "sg:phone":"+1 513 574 7511",
    "sg:postcode":"45248",
    "sg:province":"OH",
    "sg:tags":[
        "dentist"
    ],
    "wof:name":"Bridgetown Family Dentistry",
    "wof:placetype":"venue"
},
  "geometry": {"coordinates":[-84.633695,39.158593],"type":"Point"}
}