{
  "type": "Feature",
  "properties": {
    "addr:full": "6600 Busch Blvd Columbus OH 43229",
    "addr:postcode": "6600;43229",
    "addr:street": "Busch Blvd",
    "iso:country": "US",
    "sg:address": "6600 Busch Blvd",
    "sg:city": "Columbus",
    "sg:classifiers": [
      {
        "category": "Banks \u0026 Credit Unions",
        "subcategory": "Bank",
        "type": "Services"
      }
    ],
    "sg:phone": "+1 614 431 2515",
    "sg:postcode": "43229",
    "sg:province": "OH",
    "sg:tags": [
      "personal",
      "mortgage"
    ],
    "wof:name": "Home Buyers Mortgage Co",
    "wof:placetype": "venue"
  },
  "geometry": {"coordinates":[-82.993342,40.099044],"type":"Point"}
}
