{
  "type": "Feature",
  "properties": {
    "iso:country":"US",
    "sg:address":"6600 Busch Blvd",
    "sg:city":"Columbus",
    "sg:classifiers":[
        {
            "category":"Banks & Credit Unions",
            "subcategory":"Bank",
            "type":"Services"
        }
    ],
    "sg:phone":"+1 614 431 2515",
    "sg:postcode":"43229",
    "sg:province":"OH",
    "sg:tags":[
        "personal",
        "mortgage"
    ],
    "wof:name":"Home Buyers Mortgage Co",
    "wof:placetype":"venue"
},
  "geometry": {"coordinates":[-82.993342,40.099044],"type":"Point"}
}