{
  "type": "Feature",
  "properties": {
    "addr:full": "2301 W Jefferson Kiousville Rd West Jefferson OH 43162",
    "addr:housenumber": "2301",
    "addr:postcode": "43162",
    "addr:street": "W Jefferson Kiousville Rd",
    "iso:country": "US",
    "sg:address": "2301 W Jefferson Kiousville Rd",
    "sg:city": "West Jefferson",
    "sg:phone": "+1 614 879 8698",
    "sg:postcode": "43162",
    "sg:province": "OH",
    "sg:tags": [
      "farm",
      "corn"
    ],
    "wof:name": "Dorothy Weser Farm",
    "wof:placetype": "venue"
  },
  "geometry": {"coordinates":[-83.285795,39.898333],"type":"Point"}
}
