{
  "type": "Feature",
  "properties": {
    "addr:full": "8665 Lake in the Woods Trl Chagrin Falls OH 44023",
    "addr:housenumber": "8665",
    "addr:postcode": "44023",
    "addr:street": "Lake In The Woods Trl",
    "iso:country": "US",
    "sg:address": "8665 Lake in the Woods Trl",
    "sg:city": "Chagrin Falls",
    "sg:classifiers": [
      {
        "category": "Wholesale",
        "subcategory": "Machinery \u0026 Supplies",
        "type": "Manufacturing \u0026 Wholesale Goods"
      }
    ],
    "sg:phone": "+1 440 543 5940",
    "sg:postcode": "44023",
    "sg:province": "OH",
    "sg:tags": [
      "distribution",
      "industrial",
      "coating"
    ],
    "wof:name": "Viking Products Company",
    "wof:placetype": "venue"
  },
  "geometry": {"coordinates":[-81.332323,41.421297],"type":"Point"}
}
