{
  "type": "Feature",
  "properties": {
    "iso:country":"US",
    "sg:address":"1107 E Dayton Yellow Springs Rd",
    "sg:city":"Fairborn",
    "sg:classifiers":[
        {
            "category":"Restaurant",
            "type":"Food & Drink"
        }
    ],
    "sg:menulink":"http://www.allmenus.com/oh/bath/141812-waffle-house/menu/",
    "sg:phone":"+1 937 318 2514",
    "sg:postcode":"45324",
    "sg:province":"OH",
    "sg:tags":[
        "american"
    ],
    "wof:name":"Waffle House",
    "wof:placetype":"venue"
},
  "geometry": {"coordinates":[-83.99884400000001,39.783357],"type":"Point"}
}