{
  "type": "Feature",
  "properties": {
    "addr:full":"1009 Lake Ave Ashtabula OH 44004",
    "addr:housenumber":"1009",
    "addr:postcode":"44004",
    "addr:street":"Lake Ave",
    "iso:country":"US",
    "sg:address":"1009 Lake Ave",
    "sg:city":"Ashtabula",
    "sg:classifiers":[
        {
            "category":"Real Estate",
            "subcategory":"Real Estate Agent",
            "type":"Services"
        }
    ],
    "sg:phone":"+1 440 964 7142",
    "sg:postcode":"44004",
    "sg:province":"OH",
    "sg:website":"www.harborrealtyohio.com",
    "wof:name":"Harbor Realty",
    "wof:placetype":"venue"
},
  "geometry": {"coordinates":[-80.80561,41.890917],"type":"Point"}
}