{
  "type": "Feature",
  "properties": {
    "addr:full": "6935 Oakes Rd Cleveland OH 44141",
    "addr:housenumber": "6935",
    "addr:postcode": "44141",
    "addr:street": "Oakes Rd",
    "iso:country": "US",
    "sg:address": "6935 Oakes Rd",
    "sg:city": "Cleveland",
    "sg:classifiers": [
      {
        "category": "Professional",
        "subcategory": "Computer Services",
        "type": "Services"
      }
    ],
    "sg:phone": "+1 440 546 1516",
    "sg:postcode": "44141",
    "sg:province": "OH",
    "sg:tags": [
      "graphics"
    ],
    "wof:name": "Graphics Engineering Inc",
    "wof:placetype": "venue"
  },
  "geometry": {"coordinates":[-81.627932,41.30767],"type":"Point"}
}
