{
  "type": "Feature",
  "properties": {
    "addr:full":"4616 Black Run Rd Chillicothe OH 45601",
    "addr:housenumber":"4616",
    "addr:postcode":"45601",
    "addr:street":"Black Run Rd",
    "iso:country":"US",
    "sg:address":"4616 Black Run Rd",
    "sg:city":"Chillicothe",
    "sg:classifiers":[
        {
            "category":"Building & Trades",
            "subcategory":"Cleaning & Sanitation",
            "type":"Services"
        }
    ],
    "sg:phone":"+1 740 626 2107",
    "sg:postcode":"45601",
    "sg:province":"OH",
    "sg:tags":[
        "janitor"
    ],
    "wof:name":"Superior Cleaning",
    "wof:placetype":"venue"
},
  "geometry": {"coordinates":[-83.120508,39.280492],"type":"Point"}
}