{
  "type": "Feature",
  "properties": {
    "iso:country":"US",
    "sg:address":"1216 Kelly Ave",
    "sg:city":"Akron",
    "sg:classifiers":[
        {
            "category":"Professional",
            "subcategory":"Computer Services",
            "type":"Services"
        }
    ],
    "sg:phone":"+1 330 785 9467",
    "sg:postcode":"44306",
    "sg:province":"OH",
    "sg:tags":[
        "consultant",
        "designer"
    ],
    "wof:name":"Summit It Solutions",
    "wof:placetype":"venue"
},
  "geometry": {"coordinates":[-81.482007,41.038311],"type":"Point"}
}