{
  "type": "Feature",
  "properties": {
    "addr:full":"403 S Broadway St Geneva OH 44041",
    "addr:housenumber":"403",
    "addr:postcode":"44041",
    "addr:street":"S Broadway St",
    "iso:country":"US",
    "sg:address":"403 S Broadway St",
    "sg:city":"Geneva",
    "sg:classifiers":[
        {
            "category":"Manufacturing",
            "subcategory":"Food",
            "type":"Manufacturing & Wholesale Goods"
        }
    ],
    "sg:phone":"+1 440 466 5560",
    "sg:postcode":"44041",
    "sg:province":"OH",
    "sg:tags":[
        "mfg"
    ],
    "wof:name":"Old Mill Winery Inc",
    "wof:placetype":"venue"
},
  "geometry": {"coordinates":[-80.947397,41.799947],"type":"Point"}
}