{
  "type": "Feature",
  "properties": {
    "addr:full": "225 Court St Elyria OH 44035",
    "addr:housenumber": "225",
    "addr:postcode": "44035",
    "addr:street": "Court St",
    "iso:country": "US",
    "sg:address": "225 Court St",
    "sg:city": "Elyria",
    "sg:classifiers": [
      {
        "category": "Government",
        "subcategory": "Police Station",
        "type": "Public Place"
      }
    ],
    "sg:phone": "+1 440 329 5536",
    "sg:postcode": "44035",
    "sg:province": "OH",
    "sg:tags": [
      "sheriff"
    ],
    "sg:website": "www.loraincounty.com/clerk/",
    "wof:name": "Lorain County Civil \u0026 Criminal",
    "wof:placetype": "venue"
  },
  "geometry": {"coordinates":[-82.107998,41.365497],"type":"Point"}
}
