{
  "type": "Feature",
  "properties": {
    "iso:country":"US",
    "sg:address":"8118 Shiloh-Norwalk Rd",
    "sg:city":"Shiloh",
    "sg:classifiers":[
        {
            "category":"Manufacturing",
            "subcategory":"Motor Vehicles & Parts",
            "type":"Manufacturing & Wholesale Goods"
        }
    ],
    "sg:phone":"+1 419 896 2854",
    "sg:postcode":"44878",
    "sg:province":"OH",
    "sg:tags":[
        "equipment",
        "railroad",
        "mfg"
    ],
    "wof:name":"Plymouth Locomotive Service Co",
    "wof:placetype":"venue"
},
  "geometry": {"coordinates":[-82.60670399999999,40.974877],"type":"Point"}
}