{
  "type": "Feature",
  "properties": {
    "addr:full": "8118 Shiloh-Norwalk Rd Shiloh OH 44878",
    "addr:housenumber": "8118",
    "addr:postcode": "44878",
    "addr:street": "Shiloh-Norwalk Rd",
    "iso:country": "US",
    "sg:address": "8118 Shiloh-Norwalk Rd",
    "sg:city": "Shiloh",
    "sg:classifiers": [
      {
        "category": "Manufacturing",
        "subcategory": "Motor Vehicles \u0026 Parts",
        "type": "Manufacturing \u0026 Wholesale Goods"
      }
    ],
    "sg:phone": "+1 419 896 2854",
    "sg:postcode": "44878",
    "sg:province": "OH",
    "sg:tags": [
      "equipment",
      "railroad",
      "mfg"
    ],
    "wof:name": "Plymouth Locomotive Service Co",
    "wof:placetype": "venue"
  },
  "geometry": {"coordinates":[-82.606704,40.974877],"type":"Point"}
}
