{
  "type": "Feature",
  "properties": {
    "iso:country":"US",
    "sg:address":"20980 Saint Clair Ave",
    "sg:city":"Euclid",
    "sg:classifiers":[
        {
            "category":"Retail",
            "subcategory":"Auto Repair",
            "type":"Services"
        }
    ],
    "sg:phone":"+1 216 481 4333",
    "sg:postcode":"44117",
    "sg:province":"OH",
    "sg:tags":[
        "body",
        "automotive"
    ],
    "wof:name":"Papps Body Shop",
    "wof:placetype":"venue"
},
  "geometry": {"coordinates":[-81.53197900000001,41.583166],"type":"Point"}
}