{
  "type": "Feature",
  "properties": {
    "addr:full": "1360 State Rte 14 Columbiana OH 44408",
    "addr:housenumber": "1360",
    "addr:postcode": "44408",
    "addr:street": "State Rte 14",
    "iso:country": "US",
    "sg:address": "1360 State Rte 14",
    "sg:city": "Columbiana",
    "sg:classifiers": [
      {
        "category": "Autos \u0026 Motor Vehicles",
        "subcategory": "Automobile Sales",
        "type": "Retail Goods"
      }
    ],
    "sg:phone": "+1 330 482 9651",
    "sg:postcode": "44408",
    "sg:province": "OH",
    "sg:tags": [
      "repair",
      "used",
      "gen"
    ],
    "wof:name": "Dynamic Auto Body",
    "wof:placetype": "venue"
  },
  "geometry": {"coordinates":[-80.663388,40.886095],"type":"Point"}
}
