{
  "type": "Feature",
  "properties": {
    "iso:country":"US",
    "sg:address":"2 S Miami St",
    "sg:city":"West Milton",
    "sg:classifiers":[
        {
            "category":"Restaurant",
            "type":"Food & Drink"
        }
    ],
    "sg:phone":"+1 937 698 6549",
    "sg:postcode":"45383",
    "sg:province":"OH",
    "sg:tags":[
        "shop",
        "coffee",
        "eating"
    ],
    "wof:name":"Java Mama's",
    "wof:placetype":"venue"
},
  "geometry": {"coordinates":[-84.32781,39.962486],"type":"Point"}
}