{
  "type": "Feature",
  "properties": {
    "addr:full":"602 Taywood Rd Englewood OH 45322",
    "addr:housenumber":"602",
    "addr:postcode":"45322",
    "addr:street":"Taywood Rd",
    "iso:country":"US",
    "sg:address":"602 Taywood Rd",
    "sg:city":"Englewood",
    "sg:classifiers":[
        {
            "category":"Restaurant",
            "type":"Food & Drink"
        }
    ],
    "sg:menulink":"http://www.allmenus.com/oh/englewood/214797-ponderosa-steak-house/menu/",
    "sg:phone":"+1 937 836 8830",
    "sg:postcode":"45322",
    "sg:province":"OH",
    "sg:tags":[
        "american",
        "steakhouse"
    ],
    "wof:name":"Ponderosa Steak House",
    "wof:placetype":"venue"
},
  "geometry": {"coordinates":[-84.29163,39.866844],"type":"Point"}
}