{
  "type": "Feature",
  "properties": {
    "addr:full":"520 Market St East Liverpool OH 43920",
    "addr:housenumber":"520",
    "addr:postcode":"43920",
    "addr:street":"Market St",
    "iso:country":"US",
    "sg:address":"520 Market St",
    "sg:city":"East Liverpool",
    "sg:classifiers":[
        {
            "category":"Shopping",
            "subcategory":"Clothing, Apparel, & Fashions",
            "type":"Retail Goods"
        }
    ],
    "sg:phone":"+1 330 385 1835",
    "sg:postcode":"43920",
    "sg:province":"OH",
    "sg:tags":[
        "ready",
        "sportswear"
    ],
    "wof:name":"Arrows Paul Pants Shop Inc",
    "wof:placetype":"venue"
},
  "geometry": {"coordinates":[-80.579555,40.61973],"type":"Point"}
}