{
  "type": "Feature",
  "properties": {
    "iso:country":"US",
    "sg:address":"1212 Parsons Ave",
    "sg:city":"Columbus",
    "sg:classifiers":[
        {
            "category":"Autos & Motor Vehicles",
            "subcategory":"Automobile Sales",
            "type":"Retail Goods"
        },
        {
            "category":"Building & Trades",
            "subcategory":"Construction",
            "type":"Services"
        }
    ],
    "sg:phone":"+1 614 443 5483",
    "sg:postcode":"43206",
    "sg:province":"OH",
    "sg:tags":[
        "repair",
        "dealer",
        "car",
        "contractor"
    ],
    "wof:name":"Gregory's Used Cars",
    "wof:placetype":"venue"
},
  "geometry": {"coordinates":[-82.983316,39.938686],"type":"Point"}
}