{
  "type": "Feature",
  "properties": {
    "iso:country":"US",
    "sg:address":"142 N 9th St",
    "sg:city":"Cambridge",
    "sg:classifiers":[
        {
            "category":"Social Services",
            "type":"Services"
        }
    ],
    "sg:phone":"+1 740 432 3558",
    "sg:postcode":"43725",
    "sg:province":"OH",
    "sg:tags":[
        "organization",
        "welfare"
    ],
    "sg:website":"www.redcross.org",
    "wof:name":"American Red Cross",
    "wof:placetype":"venue"
},
  "geometry": {"coordinates":[-81.588106,40.025926],"type":"Point"}
}