{
  "type": "Feature",
  "properties": {
    "iso:country":"US",
    "sg:address":"2608 Bethel Rd",
    "sg:city":"Columbus",
    "sg:classifiers":[
        {
            "category":"Restaurant",
            "type":"Food & Drink"
        }
    ],
    "sg:phone":"+1 614 538 8967",
    "sg:postcode":"43220",
    "sg:province":"OH",
    "sg:tags":[
        "eating"
    ],
    "wof:name":"Hoggys Bar & Grill",
    "wof:placetype":"venue"
},
  "geometry": {"coordinates":[-83.089713,40.064811],"type":"Point"}
}