{
  "type": "Feature",
  "properties": {
    "addr:full": "2608 Bethel Rd Columbus OH 43220",
    "addr:housenumber": "2608",
    "addr:postcode": "43220",
    "addr:street": "Bethel Rd",
    "iso:country": "US",
    "sg:address": "2608 Bethel Rd",
    "sg:city": "Columbus",
    "sg:classifiers": [
      {
        "category": "Restaurant",
        "type": "Food \u0026 Drink"
      }
    ],
    "sg:phone": "+1 614 538 8967",
    "sg:postcode": "43220",
    "sg:province": "OH",
    "sg:tags": [
      "eating"
    ],
    "wof:name": "Hoggys Bar \u0026 Grill",
    "wof:placetype": "venue"
  },
  "geometry": {"coordinates":[-83.089713,40.064811],"type":"Point"}
}
