{
  "type": "Feature",
  "properties": {
    "addr:full": "3594 Orchard Way Powell OH 43065",
    "addr:housenumber": "3594",
    "addr:postcode": "43065",
    "addr:street": "Orchard Way",
    "iso:country": "US",
    "sg:address": "3594 Orchard Way",
    "sg:city": "Powell",
    "sg:classifiers": [
      {
        "category": "Real Estate",
        "subcategory": "Real Estate Operator",
        "type": "Services"
      }
    ],
    "sg:phone": "+1 740 881 4450",
    "sg:postcode": "43065",
    "sg:province": "OH",
    "sg:tags": [
      "condominium"
    ],
    "wof:name": "Orchards At Big Bear Farm",
    "wof:placetype": "venue"
  },
  "geometry": {"coordinates":[-83.09619,40.16716],"type":"Point"}
}
