{
  "type": "Feature",
  "properties": {
    "addr:full": "3500 N High St Columbus OH 43214",
    "addr:housenumber": "3500",
    "addr:postcode": "43214",
    "addr:street": "N High St",
    "iso:country": "US",
    "sg:address": "3500 N High St",
    "sg:city": "Columbus",
    "sg:classifiers": [
      {
        "category": "Sports \u0026 Exercise",
        "subcategory": "Gym",
        "type": "Entertainment"
      }
    ],
    "sg:phone": "+1 614 263 0636",
    "sg:postcode": "43214",
    "sg:province": "OH",
    "sg:tags": [
      "club",
      "health",
      "studio",
      "gymnasium"
    ],
    "wof:name": "Curves For Women",
    "wof:placetype": "venue"
  },
  "geometry": {"coordinates":[-83.016482,40.034232],"type":"Point"}
}
