{
  "type": "Feature",
  "properties": {
    "addr:full": "7010 Fairfield Business Dr Fairfield OH 45014",
    "addr:housenumber": "7010",
    "addr:postcode": "45014",
    "addr:street": "Fairfield Business Dr",
    "iso:country": "US",
    "sg:address": "7010 Fairfield Business Dr",
    "sg:city": "Fairfield",
    "sg:classifiers": [
      {
        "category": "Home \u0026 Garden",
        "subcategory": "Furniture",
        "type": "Retail Goods"
      }
    ],
    "sg:phone": "+1 513 860 9988",
    "sg:postcode": "45014",
    "sg:province": "OH",
    "sg:tags": [
      "mfg"
    ],
    "wof:name": "The Original Mattress Factory",
    "wof:placetype": "venue"
  },
  "geometry": {"coordinates":[-84.489088,39.316261],"type":"Point"}
}
