{
  "type": "Feature",
  "properties": {
    "iso:country":"US",
    "sg:address":"309 N Main St",
    "sg:city":"Bellefontaine",
    "sg:classifiers":[
        {
            "category":"Food & Beverages",
            "subcategory":"Groceries & Convenience Stores",
            "type":"Retail Goods"
        }
    ],
    "sg:phone":"+1 937 592 7726",
    "sg:postcode":"43311",
    "sg:province":"OH",
    "sg:tags":[
        "grocer"
    ],
    "wof:name":"Community Markets",
    "wof:placetype":"venue"
},
  "geometry": {"coordinates":[-83.75946999999999,40.364168],"type":"Point"}
}