{
  "type": "Feature",
  "properties": {
    "addr:full": "309 N Main St Bellefontaine OH 43311",
    "addr:housenumber": "309",
    "addr:postcode": "43311",
    "addr:street": "N Main St",
    "iso:country": "US",
    "sg:address": "309 N Main St",
    "sg:city": "Bellefontaine",
    "sg:classifiers": [
      {
        "category": "Food \u0026 Beverages",
        "subcategory": "Groceries \u0026 Convenience Stores",
        "type": "Retail Goods"
      }
    ],
    "sg:phone": "+1 937 592 7726",
    "sg:postcode": "43311",
    "sg:province": "OH",
    "sg:tags": [
      "grocer"
    ],
    "wof:name": "Community Markets",
    "wof:placetype": "venue"
  },
  "geometry": {"coordinates":[-83.75947,40.364168],"type":"Point"}
}
