{
  "type": "Feature",
  "properties": {
    "iso:country":"US",
    "sg:address":"537 S Broadway St",
    "sg:city":"Greenville",
    "sg:classifiers":[
        {
            "category":"Real Estate",
            "subcategory":"Real Estate Agent",
            "type":"Services"
        }
    ],
    "sg:phone":"+1 937 548 6235",
    "sg:postcode":"45331",
    "sg:province":"OH",
    "wof:name":"Paramount Properties",
    "wof:placetype":"venue"
},
  "geometry": {"coordinates":[-84.63120600000001,40.100487],"type":"Point"}
}