{
  "type": "Feature",
  "properties": {
    "addr:full": "537 S Broadway St Greenville OH 45331",
    "addr:housenumber": "537",
    "addr:postcode": "45331",
    "addr:street": "S Broadway St",
    "iso:country": "US",
    "sg:address": "537 S Broadway St",
    "sg:city": "Greenville",
    "sg:classifiers": [
      {
        "category": "Real Estate",
        "subcategory": "Real Estate Agent",
        "type": "Services"
      }
    ],
    "sg:phone": "+1 937 548 6235",
    "sg:postcode": "45331",
    "sg:province": "OH",
    "wof:name": "Paramount Properties",
    "wof:placetype": "venue"
  },
  "geometry": {"coordinates":[-84.631206,40.100487],"type":"Point"}
}
