{
  "type": "Feature",
  "properties": {
    "addr:full": "35 W Main St Amelia OH 45102",
    "addr:housenumber": "35",
    "addr:postcode": "45102",
    "addr:street": "W Main St",
    "iso:country": "US",
    "sg:address": "35 W Main St",
    "sg:city": "Amelia",
    "sg:classifiers": [
      {
        "category": "Home \u0026 Garden",
        "subcategory": "Household Appliances",
        "type": "Retail Goods"
      }
    ],
    "sg:phone": "+1 513 753 4500",
    "sg:postcode": "45102",
    "sg:province": "OH",
    "sg:tags": [
      "machine",
      "sewing"
    ],
    "wof:name": "Luke's Sewing Ctr",
    "wof:placetype": "venue"
  },
  "geometry": {"coordinates":[-84.217561,39.027854],"type":"Point"}
}
