{
  "type": "Feature",
  "properties": {
    "addr:full": "23746 Lorain Ave North Olmsted OH 44070",
    "addr:housenumber": "23746",
    "addr:postcode": "44070",
    "addr:street": "Lorain Ave",
    "iso:country": "US",
    "sg:address": "23746 Lorain Ave",
    "sg:city": "North Olmsted",
    "sg:classifiers": [
      {
        "category": "Wholesale",
        "subcategory": "Painting Supplies",
        "type": "Manufacturing \u0026 Wholesale Goods"
      }
    ],
    "sg:phone": "+1 440 777 1286",
    "sg:postcode": "44070",
    "sg:province": "OH",
    "sg:tags": [
      "paint"
    ],
    "wof:name": "Pro Tech Lake Polymer Products",
    "wof:placetype": "venue"
  },
  "geometry": {"coordinates":[-81.878307,41.441766],"type":"Point"}
}
