{
  "type": "Feature",
  "properties": {
    "iso:country":"US",
    "sg:address":"1159 N Hamilton Rd",
    "sg:city":"Columbus",
    "sg:classifiers":[
        {
            "category":"Banks & Credit Unions",
            "subcategory":"Investment Brokerage",
            "type":"Services"
        }
    ],
    "sg:phone":"+1 614 471 3912",
    "sg:postcode":"43230",
    "sg:province":"OH",
    "sg:tags":[
        "security"
    ],
    "wof:name":"Edward Jones 17941",
    "wof:placetype":"venue"
},
  "geometry": {"coordinates":[-82.86824799999999,39.999061],"type":"Point"}
}