{
  "type": "Feature",
  "properties": {
    "iso:country":"US",
    "sg:address":"124 N Maple St",
    "sg:city":"Union City",
    "sg:classifiers":[
        {
            "category":"Building & Trades",
            "subcategory":"Construction",
            "type":"Services"
        }
    ],
    "sg:phone":"+1 937 902 3910",
    "sg:postcode":"45390",
    "sg:province":"OH",
    "sg:tags":[
        "home",
        "improvement"
    ],
    "wof:name":"Krimm Construction Mobile Svc",
    "wof:placetype":"venue"
},
  "geometry": {"coordinates":[-84.79620799999999,40.202027],"type":"Point"}
}