{
  "type": "Feature",
  "properties": {
    "addr:full": "124 N Maple St Union City OH 45390",
    "addr:housenumber": "124",
    "addr:postcode": "45390",
    "addr:street": "N Maple St",
    "iso:country": "US",
    "sg:address": "124 N Maple St",
    "sg:city": "Union City",
    "sg:classifiers": [
      {
        "category": "Building \u0026 Trades",
        "subcategory": "Construction",
        "type": "Services"
      }
    ],
    "sg:phone": "+1 937 902 3910",
    "sg:postcode": "45390",
    "sg:province": "OH",
    "sg:tags": [
      "home",
      "improvement"
    ],
    "wof:name": "Krimm Construction Mobile Svc",
    "wof:placetype": "venue"
  },
  "geometry": {"coordinates":[-84.796208,40.202027],"type":"Point"}
}
