{
  "type": "Feature",
  "properties": {
    "addr:full":"1340 Neubrecht Rd Lima OH 45801",
    "addr:housenumber":"1340",
    "addr:postcode":"45801",
    "addr:street":"Neubrecht Rd",
    "iso:country":"US",
    "sg:address":"1340 Neubrecht Rd",
    "sg:city":"Lima",
    "sg:classifiers":[
        {
            "category":"Manufacturing",
            "subcategory":"Metals",
            "type":"Manufacturing & Wholesale Goods"
        }
    ],
    "sg:phone":"+1 419 227 1100",
    "sg:postcode":"45801",
    "sg:province":"OH",
    "sg:tags":[
        "coating",
        "specialty"
    ],
    "sg:website":"www.metokote.com",
    "wof:name":"Metokote Corp",
    "wof:placetype":"venue"
},
  "geometry": {"coordinates":[-84.07986,40.760894],"type":"Point"}
}