{
  "type": "Feature",
  "properties": {
    "addr:full": "5161 Warner Rd Cleveland OH 44125",
    "addr:housenumber": "5161",
    "addr:postcode": "44125",
    "addr:street": "Warner Rd",
    "iso:country": "US",
    "sg:address": "5161 Warner Rd",
    "sg:city": "Cleveland",
    "sg:classifiers": [
      {
        "category": "Retail",
        "subcategory": "Auto Repair",
        "type": "Services"
      }
    ],
    "sg:phone": "+1 216 341 4042",
    "sg:postcode": "44125",
    "sg:province": "OH",
    "sg:tags": [
      "truck"
    ],
    "wof:name": "Linda's Repair \u0026 Trucking",
    "wof:placetype": "venue"
  },
  "geometry": {"coordinates":[-81.633278,41.430881],"type":"Point"}
}
