{
  "type": "Feature",
  "properties": {
    "addr:full":"500 N Main St Findlay OH 45840",
    "addr:housenumber":"500",
    "addr:postcode":"45840",
    "addr:street":"N Main St",
    "iso:country":"US",
    "sg:address":"500 N Main St",
    "sg:city":"Findlay",
    "sg:classifiers":[
        {
            "category":"Social Services",
            "type":"Services"
        }
    ],
    "sg:phone":"+1 419 423 3292",
    "sg:postcode":"45840",
    "sg:province":"OH",
    "sg:tags":[
        "professional",
        "counselor"
    ],
    "wof:name":"Sophia Center Inc",
    "wof:placetype":"venue"
},
  "geometry": {"coordinates":[-83.65012299999999,41.048078],"type":"Point"}
}