{
  "type": "Feature",
  "properties": {
    "addr:full":"703 Valley Rd Salem OH 44460",
    "addr:housenumber":"703",
    "addr:postcode":"44460",
    "addr:street":"Valley Rd",
    "iso:country":"US",
    "sg:address":"703 Valley Rd",
    "sg:city":"Salem",
    "sg:classifiers":[
        {
            "category":"Retail",
            "subcategory":"Veterinary Services",
            "type":"Services"
        }
    ],
    "sg:phone":"+1 330 537 3899",
    "sg:postcode":"44460",
    "sg:province":"OH",
    "wof:name":"NOVA",
    "wof:placetype":"venue"
},
  "geometry": {"coordinates":[-80.95250900000001,40.892479],"type":"Point"}
}