{
  "type": "Feature",
  "properties": {
    "iso:country":"US",
    "sg:address":"520 Enterprise Dr",
    "sg:city":"Westerville",
    "sg:classifiers":[
        {
            "category":"Communications",
            "subcategory":"Film & Video Production",
            "type":"Services"
        }
    ],
    "sg:phone":"+1 614 888 4888",
    "sg:postcode":"43081",
    "sg:province":"OH",
    "sg:tags":[
        "taping"
    ],
    "wof:name":"Production Partners Corp",
    "wof:placetype":"venue"
},
  "geometry": {"coordinates":[-83.009184,40.155855],"type":"Point"}
}