{
  "type": "Feature",
  "properties": {
    "addr:full":"3744 Surfside Cir Aurora OH 44202",
    "addr:housenumber":"3744",
    "addr:postcode":"44202",
    "addr:street":"Surfside Cir",
    "iso:country":"US",
    "sg:address":"3744 Surfside Cir",
    "sg:city":"Aurora",
    "sg:classifiers":[
        {
            "category":"Wholesale",
            "subcategory":"Medical Equipment & Supplies",
            "type":"Manufacturing & Wholesale Goods"
        }
    ],
    "sg:phone":"+1 330 562 5031",
    "sg:postcode":"44202",
    "sg:province":"OH",
    "sg:tags":[
        "x",
        "apparatus"
    ],
    "sg:website":"www.privatepracticexray.com",
    "wof:name":"Private Practice X-Ray",
    "wof:placetype":"venue"
},
  "geometry": {"coordinates":[-81.395996,41.330741],"type":"Point"}
}