{
  "type": "Feature",
  "properties": {
    "addr:full": "904 Union Rd Monroe OH 45036",
    "addr:housenumber": "904",
    "addr:postcode": "45036",
    "addr:street": "Union Rd",
    "iso:country": "US",
    "sg:address": "904 Union Rd",
    "sg:city": "Monroe",
    "sg:classifiers": [
      {
        "category": "Organizations",
        "subcategory": "Religious Organization",
        "type": "Services"
      }
    ],
    "sg:phone": "+1 513 423 7040",
    "sg:postcode": "45036",
    "sg:province": "OH",
    "sg:tags": [
      "church"
    ],
    "sg:website": "www.solidrockchurch.org",
    "wof:name": "Solid Rock Church",
    "wof:placetype": "venue"
  },
  "geometry": {"coordinates":[-84.319806,39.4366],"type":"Point"}
}
