{
  "type": "Feature",
  "properties": {
    "addr:full":"3619 Wallwerth Dr Toledo OH 43612",
    "addr:housenumber":"3619",
    "addr:postcode":"43612",
    "addr:street":"Wallwerth Dr",
    "iso:country":"US",
    "sg:address":"3619 Wallwerth Dr",
    "sg:city":"Toledo",
    "sg:classifiers":[
        {
            "category":"Arts & Performance",
            "subcategory":"Theater",
            "type":"Entertainment"
        }
    ],
    "sg:phone":"+1 419 478 8888",
    "sg:postcode":"43612",
    "sg:province":"OH",
    "sg:tags":[
        "clown"
    ],
    "wof:name":"Bring On The Clowns",
    "wof:placetype":"venue"
},
  "geometry": {"coordinates":[-83.58349200000001,41.687296],"type":"Point"}
}