{
  "type": "Feature",
  "properties": {
    "addr:full":"85 Stone Ridge Ln Middletown OH 45044",
    "addr:housenumber":"85",
    "addr:postcode":"45044",
    "addr:street":"Stone Ridge Ln",
    "iso:country":"US",
    "sg:address":"85 Stone Ridge Ln",
    "sg:city":"Middletown",
    "sg:classifiers":[
        {
            "category":"Shopping",
            "subcategory":"Used Merchandise",
            "type":"Retail Goods"
        }
    ],
    "sg:phone":"+1 513 539 2773",
    "sg:postcode":"45044",
    "sg:province":"OH",
    "wof:name":"Kivinskis Antique Shop",
    "wof:placetype":"venue"
},
  "geometry": {"coordinates":[-84.408874,39.449262],"type":"Point"}
}