{
  "type": "Feature",
  "properties": {
    "addr:full":"1709 Bellefontaine Ave Marion OH 43302",
    "addr:housenumber":"1709",
    "addr:postcode":"43302",
    "addr:street":"Bellefontaine Ave",
    "iso:country":"US",
    "sg:address":"1709 Bellefontaine Ave",
    "sg:city":"Marion",
    "sg:classifiers":[
        {
            "category":"Organizations",
            "subcategory":"Religious Organization",
            "type":"Services"
        }
    ],
    "sg:phone":"+1 740 382 6311",
    "sg:postcode":"43302",
    "sg:province":"OH",
    "sg:tags":[
        "church"
    ],
    "wof:name":"Ch Of Christ Christian Union",
    "wof:placetype":"venue"
},
  "geometry": {"coordinates":[-83.162761,40.563006],"type":"Point"}
}