{
  "type": "Feature",
  "properties": {
    "addr:full":"2411 Far Hills Ave Dayton OH 45419",
    "addr:housenumber":"2411",
    "addr:postcode":"45419",
    "addr:street":"Far Hills Ave",
    "iso:country":"US",
    "sg:address":"2411 Far Hills Ave",
    "sg:city":"Dayton",
    "sg:classifiers":[
        {
            "category":"Shopping",
            "subcategory":"Jewelry",
            "type":"Retail Goods"
        }
    ],
    "sg:phone":"+1 937 293 0043",
    "sg:postcode":"45419",
    "sg:province":"OH",
    "sg:tags":[
        "store"
    ],
    "wof:name":"Rife Jewelers",
    "wof:placetype":"venue"
},
  "geometry": {"coordinates":[-84.17108,39.709048],"type":"Point"}
}