{
  "type": "Feature",
  "properties": {
    "addr:full":"237 State Rd Ashtabula OH 44004",
    "addr:housenumber":"237",
    "addr:postcode":"44004",
    "addr:street":"State Rd",
    "iso:country":"US",
    "sg:address":"237 State Rd",
    "sg:city":"Ashtabula",
    "sg:classifiers":[
        {
            "category":"Building & Trades",
            "subcategory":"Construction",
            "type":"Services"
        }
    ],
    "sg:phone":"+1 440 993 1397",
    "sg:postcode":"44004",
    "sg:province":"OH",
    "sg:tags":[
        "general",
        "contractor"
    ],
    "wof:name":"Mears/Meadors Excavating",
    "wof:placetype":"venue"
},
  "geometry": {"coordinates":[-80.772496,41.90455],"type":"Point"}
}