{
  "type": "Feature",
  "properties": {
    "iso:country":"US",
    "sg:address":"411 N State St",
    "sg:city":"Painesville",
    "sg:classifiers":[
        {
            "category":"Building & Trades",
            "subcategory":"Construction",
            "type":"Services"
        }
    ],
    "sg:phone":"+1 440 358 9852",
    "sg:postcode":"44077",
    "sg:province":"OH",
    "sg:tags":[
        "contractor"
    ],
    "wof:name":"Mooney & Moses Of Ohio",
    "wof:placetype":"venue"
},
  "geometry": {"coordinates":[-81.245569,41.73269],"type":"Point"}
}