{
  "type": "Feature",
  "properties": {
    "addr:full": "411 N State St Painesville OH 44077",
    "addr:housenumber": "411",
    "addr:postcode": "44077",
    "addr:street": "N State St",
    "iso:country": "US",
    "sg:address": "411 N State St",
    "sg:city": "Painesville",
    "sg:classifiers": [
      {
        "category": "Building \u0026 Trades",
        "subcategory": "Construction",
        "type": "Services"
      }
    ],
    "sg:phone": "+1 440 358 9852",
    "sg:postcode": "44077",
    "sg:province": "OH",
    "sg:tags": [
      "contractor"
    ],
    "wof:name": "Mooney \u0026 Moses Of Ohio",
    "wof:placetype": "venue"
  },
  "geometry": {"coordinates":[-81.245569,41.73269],"type":"Point"}
}
