{
  "type": "Feature",
  "properties": {
    "iso:country":"US",
    "sg:address":"150 W Western Reserve Rd",
    "sg:city":"Youngstown",
    "sg:classifiers":[
        {
            "category":"Retail",
            "subcategory":"Car Wash",
            "type":"Services"
        }
    ],
    "sg:phone":"+1 330 726 2786",
    "sg:postcode":"44514",
    "sg:province":"OH",
    "sg:tags":[
        "polishing",
        "washing"
    ],
    "wof:name":"JJA Car Wash Inc",
    "wof:placetype":"venue"
},
  "geometry": {"coordinates":[-80.669651,40.988025],"type":"Point"}
}