{
  "type": "Feature",
  "properties": {
    "addr:full": "212 W Chillicothe Ave Bellefontaine OH 43311",
    "addr:housenumber": "212",
    "addr:postcode": "43311",
    "addr:street": "W Chillicothe Ave",
    "iso:country": "US",
    "sg:address": "212 W Chillicothe Ave",
    "sg:city": "Bellefontaine",
    "sg:classifiers": [
      {
        "category": "Professional",
        "type": "Services"
      }
    ],
    "sg:phone": "+1 937 592 9558",
    "sg:postcode": "43311",
    "sg:province": "OH",
    "sg:tags": [
      "establishment"
    ],
    "wof:name": "RJB \u0026 Assoc Inc",
    "wof:placetype": "venue"
  },
  "geometry": {"coordinates":[-83.76353,40.359939],"type":"Point"}
}
