{
  "type": "Feature",
  "properties": {
    "addr:full": "16920 Detroit Ave Lakewood OH 44107",
    "addr:housenumber": "16920",
    "addr:postcode": "44107",
    "addr:street": "Detroit Ave",
    "iso:country": "US",
    "sg:address": "16920 Detroit Ave",
    "sg:city": "Lakewood",
    "sg:classifiers": [
      {
        "category": "Manufacturing",
        "subcategory": "Paper Products",
        "type": "Manufacturing \u0026 Wholesale Goods"
      }
    ],
    "sg:phone": "+1 216 226 6900",
    "sg:postcode": "44107",
    "sg:province": "OH",
    "sg:tags": [
      "retail",
      "internet"
    ],
    "wof:name": "Designers Cad and Graphic Sup",
    "wof:placetype": "venue"
  },
  "geometry": {"coordinates":[-81.815544,41.485456],"type":"Point"}
}
