{
  "type": "Feature",
  "properties": {
    "addr:full": "1592 State Rte 213 Steubenville OH 43952",
    "addr:housenumber": "1592",
    "addr:postcode": "43952",
    "addr:street": "State Rte 213",
    "iso:country": "US",
    "sg:address": "1592 State Rte 213",
    "sg:city": "Steubenville",
    "sg:classifiers": [
      {
        "category": "Food \u0026 Beverages",
        "subcategory": "Groceries \u0026 Convenience Stores",
        "type": "Retail Goods"
      }
    ],
    "sg:phone": "+1 740 282 8281",
    "sg:postcode": "43952",
    "sg:province": "OH",
    "wof:name": "Lewis Country Mart",
    "wof:placetype": "venue"
  },
  "geometry": {"coordinates":[-80.64967,40.397662],"type":"Point"}
}
