{
  "type": "Feature",
  "properties": {
    "iso:country":"US",
    "sg:address":"1592 State Rte 213",
    "sg:city":"Steubenville",
    "sg:classifiers":[
        {
            "category":"Food & Beverages",
            "subcategory":"Groceries & Convenience Stores",
            "type":"Retail Goods"
        }
    ],
    "sg:phone":"+1 740 282 8281",
    "sg:postcode":"43952",
    "sg:province":"OH",
    "wof:name":"Lewis Country Mart",
    "wof:placetype":"venue"
},
  "geometry": {"coordinates":[-80.64967,40.397662],"type":"Point"}
}