{
  "type": "Feature",
  "properties": {
    "addr:full":"191 E 194th St Cleveland OH 44119",
    "addr:housenumber":"191",
    "addr:postcode":"44119",
    "addr:street":"E 194Th St",
    "iso:country":"US",
    "sg:address":"191 E 194th St",
    "sg:city":"Cleveland",
    "sg:classifiers":[
        {
            "category":"Banks & Credit Unions",
            "subcategory":"Bank",
            "type":"Services"
        }
    ],
    "sg:phone":"+1 216 531 5974",
    "sg:postcode":"44119",
    "sg:province":"OH",
    "sg:tags":[
        "loan",
        "broker",
        "mortgage"
    ],
    "wof:name":"Allied Home Mrtg Capitl Corp",
    "wof:placetype":"venue"
},
  "geometry": {"coordinates":[-81.54585899999999,41.600788],"type":"Point"}
}