{
  "type": "Feature",
  "properties": {
    "addr:full":"400 Scott St Crestline OH 44827",
    "addr:housenumber":"400",
    "addr:postcode":"44827",
    "addr:street":"Scott St",
    "iso:country":"US",
    "sg:address":"400 Scott St",
    "sg:city":"Crestline",
    "sg:classifiers":[
        {
            "category":"Organizations",
            "subcategory":"Community Association",
            "type":"Services"
        }
    ],
    "sg:phone":"+1 419 683 3446",
    "sg:postcode":"44827",
    "sg:province":"OH",
    "sg:tags":[
        "fraternal"
    ],
    "wof:name":"Knights Of Columbus",
    "wof:placetype":"venue"
},
  "geometry": {"coordinates":[-82.731944,40.78552],"type":"Point"}
}