{
  "type": "Feature",
  "properties": {
    "addr:full":"4026 Dressler Rd NW Canton OH 44718",
    "addr:postcode":"4026;44718",
    "addr:street":"Dressler Rd Nw",
    "iso:country":"US",
    "sg:address":"4026 Dressler Rd NW",
    "sg:city":"Canton",
    "sg:classifiers":[
        {
            "category":"Banks & Credit Unions",
            "subcategory":"Bank",
            "type":"Services"
        }
    ],
    "sg:phone":"+1 330 478 1000",
    "sg:postcode":"44718",
    "sg:province":"OH",
    "wof:name":"Ohio Legacy Bank",
    "wof:placetype":"venue"
},
  "geometry": {"coordinates":[-81.433993,40.838288],"type":"Point"}
}