{
  "type": "Feature",
  "properties": {
    "iso:country":"US",
    "sg:address":"670 US Hwy 42 SE",
    "sg:city":"London",
    "sg:classifiers":[
        {
            "category":"Insurance",
            "subcategory":"Insurance Agent",
            "type":"Services"
        }
    ],
    "sg:phone":"+1 740 852 3331",
    "sg:postcode":"43140",
    "sg:province":"OH",
    "wof:name":"Ambrix & Co Assoc",
    "wof:placetype":"venue"
},
  "geometry": {"coordinates":[-83.40990600000001,39.92867],"type":"Point"}
}