{
  "type": "Feature",
  "properties": {
    "addr:full": "670 US Hwy 42 SE London OH 43140",
    "addr:housenumber": "670",
    "addr:postcode": "43140",
    "addr:street": "Us Hwy 42 Se",
    "iso:country": "US",
    "sg:address": "670 US Hwy 42 SE",
    "sg:city": "London",
    "sg:classifiers": [
      {
        "category": "Insurance",
        "subcategory": "Insurance Agent",
        "type": "Services"
      }
    ],
    "sg:phone": "+1 740 852 3331",
    "sg:postcode": "43140",
    "sg:province": "OH",
    "wof:name": "Ambrix \u0026 Co Assoc",
    "wof:placetype": "venue"
  },
  "geometry": {"coordinates":[-83.409906,39.92867],"type":"Point"}
}
