{
  "type": "Feature",
  "properties": {
    "addr:full": "36301 Euclid Ave Willoughby OH 44094",
    "addr:postcode": "36301;44094",
    "addr:street": "Euclid Ave",
    "iso:country": "US",
    "sg:address": "36301 Euclid Ave",
    "sg:city": "Willoughby",
    "sg:classifiers": [
      {
        "category": "Shopping",
        "subcategory": "Shoes",
        "type": "Retail Goods"
      }
    ],
    "sg:phone": "+1 440 975 9834",
    "sg:postcode": "44094",
    "sg:province": "OH",
    "sg:tags": [
      "family"
    ],
    "wof:name": "Terrys Shoes",
    "wof:placetype": "venue"
  },
  "geometry": {"coordinates":[-81.421506,41.628976],"type":"Point"}
}
