{
  "type": "Feature",
  "properties": {
    "addr:full": "325 Lexington-Ontario Rd Mansfield OH 44903",
    "addr:housenumber": "325",
    "addr:postcode": "44903",
    "addr:street": "Lexington-Ontario Rd",
    "iso:country": "US",
    "sg:address": "325 Lexington-Ontario Rd",
    "sg:city": "Mansfield",
    "sg:classifiers": [
      {
        "category": "Banks \u0026 Credit Unions",
        "subcategory": "Bank",
        "type": "Services"
      }
    ],
    "sg:phone": "+1 419 529 4112",
    "sg:postcode": "44903",
    "sg:province": "OH",
    "sg:tags": [
      "state",
      "commercial"
    ],
    "wof:name": "Richland Bank",
    "wof:placetype": "venue"
  },
  "geometry": {"coordinates":[-82.639285,40.751155],"type":"Point"}
}
