{
  "type": "Feature",
  "properties": {
    "addr:full": "1355 N Lexington-Springmill Rd Mansfield OH 44906",
    "addr:housenumber": "1355",
    "addr:postcode": "44906",
    "addr:street": "N Lexington-Springmill Rd",
    "iso:country": "US",
    "sg:address": "1355 N Lexington-Springmill Rd",
    "sg:city": "Mansfield",
    "sg:classifiers": [
      {
        "category": "Shopping",
        "subcategory": "Department Store",
        "type": "Retail Goods"
      }
    ],
    "sg:phone": "+1 419 747 8310",
    "sg:postcode": "44906",
    "sg:province": "OH",
    "sg:tags": [
      "eating",
      "gr"
    ],
    "wof:name": "Meijer 126",
    "wof:placetype": "venue"
  },
  "geometry": {"coordinates":[-82.590154,40.79023],"type":"Point"}
}
