{
  "type": "Feature",
  "properties": {
    "addr:full": "800 Portland Way N Galion OH 44833",
    "addr:housenumber": "800",
    "addr:postcode": "44833",
    "addr:street": "Portland Way N",
    "iso:country": "US",
    "sg:address": "800 Portland Way N",
    "sg:city": "Galion",
    "sg:classifiers": [
      {
        "category": "Health Services",
        "subcategory": "Doctor",
        "type": "Services"
      }
    ],
    "sg:phone": "+1 419 207 8018",
    "sg:postcode": "44833",
    "sg:province": "OH",
    "sg:tags": [
      "physician",
      "surgeon"
    ],
    "wof:name": "Ashland Surgical Assoc Inc",
    "wof:placetype": "venue"
  },
  "geometry": {"coordinates":[-82.798924,40.745884],"type":"Point"}
}
