{
  "type": "Feature",
  "properties": {
    "addr:full": "3109 Mayfield Rd Cleveland OH 44118",
    "addr:housenumber": "3109",
    "addr:postcode": "44118",
    "addr:street": "Mayfield Rd",
    "iso:country": "US",
    "sg:address": "3109 Mayfield Rd",
    "sg:city": "Cleveland",
    "sg:classifiers": [
      {
        "category": "Organizations",
        "subcategory": "Professional Association",
        "type": "Services"
      }
    ],
    "sg:phone": "+1 216 397 7322",
    "sg:postcode": "44118",
    "sg:province": "OH",
    "sg:tags": [
      "chambers",
      "commerce"
    ],
    "wof:name": "Heights Regional Chamber-Cmmrc",
    "wof:placetype": "venue"
  },
  "geometry": {"coordinates":[-81.56671,41.516707],"type":"Point"}
}
