{
  "type": "Feature",
  "properties": {
    "iso:country":"US",
    "sg:address":"3019 Navarre Ave",
    "sg:city":"Oregon",
    "sg:classifiers":[
        {
            "category":"Health Services",
            "subcategory":"Clinic",
            "type":"Services"
        }
    ],
    "sg:phone":"+1 419 698 8733",
    "sg:postcode":"43616",
    "sg:province":"OH",
    "sg:tags":[
        "home"
    ],
    "wof:name":"Health Services Connections",
    "wof:placetype":"venue"
},
  "geometry": {"coordinates":[-83.472464,41.636995],"type":"Point"}
}