{
  "type": "Feature",
  "properties": {
    "iso:country":"US",
    "sg:address":"1111 Superior Ave E",
    "sg:city":"Cleveland",
    "sg:classifiers":[
        {
            "category":"Government",
            "subcategory":"Office",
            "type":"Public Place"
        }
    ],
    "sg:phone":"+1 216 263 3455",
    "sg:postcode":"44114",
    "sg:province":"OH",
    "sg:tags":[
        "consultant",
        "trade",
        "program",
        "economic",
        "international",
        "administrative"
    ],
    "sg:website":"http://www.ftc.gov",
    "wof:name":"Federal Trade Commission (Inc)",
    "wof:placetype":"venue"
},
  "geometry": {"coordinates":[-81.68694000000001,41.503054],"type":"Point"}
}