{
  "type": "Feature",
  "properties": {
    "addr:full":"1201 Omniplex Dr Cincinnati OH 45240",
    "addr:housenumber":"1201",
    "addr:postcode":"45240",
    "addr:street":"Omniplex Dr",
    "iso:country":"US",
    "sg:address":"1201 Omniplex Dr",
    "sg:city":"Cincinnati",
    "sg:classifiers":[
        {
            "category":"Autos & Motor Vehicles",
            "subcategory":"Fuel & Gas Station",
            "type":"Retail Goods"
        }
    ],
    "sg:phone":"+1 513 671 4107",
    "sg:postcode":"45240",
    "sg:province":"OH",
    "sg:tags":[
        "convenience",
        "station",
        "store"
    ],
    "wof:name":"B P Exploration & Oil Inc",
    "wof:placetype":"venue"
},
  "geometry": {"coordinates":[-84.527129,39.301745],"type":"Point"}
}