{
  "type": "Feature",
  "properties": {
    "iso:country":"US",
    "sg:address":"815 Crocker Rd",
    "sg:city":"Cleveland",
    "sg:classifiers":[
        {
            "category":"Building & Trades",
            "subcategory":"Equipment Rental",
            "type":"Services"
        }
    ],
    "sg:phone":"+1 440 617 8866",
    "sg:postcode":"44145",
    "sg:province":"OH",
    "sg:tags":[
        "leasing"
    ],
    "wof:name":"Wells Fargo Equipment Finance",
    "wof:placetype":"venue"
},
  "geometry": {"coordinates":[-81.95077499999999,41.470828],"type":"Point"}
}