{
  "type": "Feature",
  "properties": {
    "iso:country":"US",
    "sg:address":"2106 Integrity Dr S",
    "sg:city":"Columbus",
    "sg:classifiers":[
        {
            "category":"Home & Garden",
            "subcategory":"Carpets & Floor Coverings",
            "type":"Retail Goods"
        }
    ],
    "sg:phone":"+1 614 443 9033",
    "sg:postcode":"43209",
    "sg:province":"OH",
    "sg:tags":[
        "dealer",
        "rug"
    ],
    "wof:name":"Carolyn's Wholesale Carpets",
    "wof:placetype":"venue"
},
  "geometry": {"coordinates":[-82.941418,39.933697],"type":"Point"}
}