{
  "type": "Feature",
  "properties": {
    "addr:full": "2106 Integrity Dr S Columbus OH 43209",
    "addr:housenumber": "2106",
    "addr:postcode": "43209",
    "addr:street": "Integrity Dr S",
    "iso:country": "US",
    "sg:address": "2106 Integrity Dr S",
    "sg:city": "Columbus",
    "sg:classifiers": [
      {
        "category": "Home \u0026 Garden",
        "subcategory": "Carpets \u0026 Floor Coverings",
        "type": "Retail Goods"
      }
    ],
    "sg:phone": "+1 614 443 9033",
    "sg:postcode": "43209",
    "sg:province": "OH",
    "sg:tags": [
      "dealer",
      "rug"
    ],
    "wof:name": "Carolyn's Wholesale Carpets",
    "wof:placetype": "venue"
  },
  "geometry": {"coordinates":[-82.941418,39.933697],"type":"Point"}
}
