{
  "type": "Feature",
  "properties": {
    "addr:full":"20045 Pitts Rd Wellington OH 44090",
    "addr:housenumber":"20045",
    "addr:postcode":"44090",
    "addr:street":"Pitts Rd",
    "iso:country":"US",
    "sg:address":"20045 Pitts Rd",
    "sg:city":"Wellington",
    "sg:classifiers":[
        {
            "category":"Building & Trades",
            "subcategory":"Construction",
            "type":"Services"
        }
    ],
    "sg:phone":"+1 440 647 6544",
    "sg:postcode":"44090",
    "sg:province":"OH",
    "sg:tags":[
        "contractor"
    ],
    "wof:name":"Pro Image Side",
    "wof:placetype":"venue"
},
  "geometry": {"coordinates":[-82.242362,41.185808],"type":"Point"}
}