{
  "type": "Feature",
  "properties": {
    "iso:country":"US",
    "sg:address":"3403 East Pike",
    "sg:city":"Zanesville",
    "sg:classifiers":[
        {
            "category":"Freight",
            "type":"Transportation"
        }
    ],
    "sg:phone":"+1 740 454 8568",
    "sg:postcode":"43701",
    "sg:province":"OH",
    "sg:tags":[
        "carrier",
        "motor"
    ],
    "sg:website":"www.myyellow.com",
    "wof:name":"Yellow Transportation Inc",
    "wof:placetype":"venue"
},
  "geometry": {"coordinates":[-81.938022,39.954056],"type":"Point"}
}