{
  "type": "Feature",
  "properties": {
    "addr:full": "4949 Galaxy Pkwy Cleveland OH 44128",
    "addr:housenumber": "4949",
    "addr:postcode": "44128",
    "addr:street": "Galaxy Pkwy",
    "iso:country": "US",
    "sg:address": "4949 Galaxy Pkwy",
    "sg:city": "Cleveland",
    "sg:classifiers": [
      {
        "category": "Insurance",
        "subcategory": "Insurance Agent",
        "type": "Services"
      }
    ],
    "sg:phone": "+1 216 292 0086",
    "sg:postcode": "44128",
    "sg:province": "OH",
    "wof:name": "Hope Financial Group",
    "wof:placetype": "venue"
  },
  "geometry": {"coordinates":[-81.501429,41.424961],"type":"Point"}
}
