{
  "type": "Feature",
  "properties": {
    "addr:full": "15 Bellemonte St Middletown OH 45042",
    "addr:housenumber": "15",
    "addr:postcode": "45042",
    "addr:street": "Bellemonte St",
    "iso:country": "US",
    "sg:address": "15 Bellemonte St",
    "sg:city": "Middletown",
    "sg:classifiers": [
      {
        "category": "Autos \u0026 Motor Vehicles",
        "subcategory": "Auto Supplies",
        "type": "Retail Goods"
      }
    ],
    "sg:phone": "+1 513 422 1113",
    "sg:postcode": "45042",
    "sg:province": "OH",
    "sg:tags": [
      "automobile",
      "stereo",
      "radio"
    ],
    "wof:name": "D \u0026 E Electronics",
    "wof:placetype": "venue"
  },
  "geometry": {"coordinates":[-84.380968,39.513276],"type":"Point"}
}
