{
  "type": "Feature",
  "properties": {
    "addr:full":"20745 Germantown Dr Cleveland OH 44126",
    "addr:housenumber":"20745",
    "addr:postcode":"44126",
    "addr:street":"Germantown Dr",
    "iso:country":"US",
    "sg:address":"20745 Germantown Dr",
    "sg:city":"Cleveland",
    "sg:classifiers":[
        {
            "category":"Professional",
            "subcategory":"Research",
            "type":"Services"
        }
    ],
    "sg:phone":"+1 440 331 2925",
    "sg:postcode":"44126",
    "sg:province":"OH",
    "sg:tags":[
        "medical"
    ],
    "wof:name":"Carad Inc",
    "wof:placetype":"venue"
},
  "geometry": {"coordinates":[-81.848625,41.438369],"type":"Point"}
}