{
  "type": "Feature",
  "properties": {
    "addr:full": "9394 N Shore Dr Hillsboro OH 45133",
    "addr:housenumber": "9394",
    "addr:postcode": "45133",
    "addr:street": "N Shore Dr",
    "iso:country": "US",
    "sg:address": "9394 N Shore Dr",
    "sg:city": "Hillsboro",
    "sg:phone": "+1 937 393 2568",
    "sg:postcode": "45133",
    "sg:province": "OH",
    "sg:tags": [
      "farm",
      "corn",
      "wheat",
      "soybean"
    ],
    "wof:name": "Dan Hiestand",
    "wof:placetype": "venue"
  },
  "geometry": {"coordinates":[-83.537759,39.187591],"type":"Point"}
}
