{
  "type": "Feature",
  "properties": {
    "addr:full": "1355 E 2nd St Franklin OH 45005",
    "addr:housenumber": "1355",
    "addr:postcode": "45005",
    "addr:street": "E 2Nd St",
    "iso:country": "US",
    "sg:address": "1355 E 2nd St",
    "sg:city": "Franklin",
    "sg:classifiers": [
      {
        "category": "Organizations",
        "subcategory": "Professional Association",
        "type": "Services"
      }
    ],
    "sg:phone": "+1 937 746 5400",
    "sg:postcode": "45005",
    "sg:province": "OH",
    "wof:name": "Masonic Lodge",
    "wof:placetype": "venue"
  },
  "geometry": {"coordinates":[-84.279784,39.563711],"type":"Point"}
}
