{
  "type": "Feature",
  "properties": {
    "iso:country":"US",
    "sg:address":"1355 E 2nd St",
    "sg:city":"Franklin",
    "sg:classifiers":[
        {
            "category":"Organizations",
            "subcategory":"Professional Association",
            "type":"Services"
        }
    ],
    "sg:phone":"+1 937 746 5400",
    "sg:postcode":"45005",
    "sg:province":"OH",
    "wof:name":"Masonic Lodge",
    "wof:placetype":"venue"
},
  "geometry": {"coordinates":[-84.27978400000001,39.563711],"type":"Point"}
}