{
  "type": "Feature",
  "properties": {
    "addr:full": "8490 East Pike Norwich OH 43767",
    "addr:housenumber": "8490",
    "addr:postcode": "43767",
    "addr:street": "East Pike",
    "iso:country": "US",
    "sg:address": "8490 East Pike",
    "sg:city": "Norwich",
    "sg:classifiers": [
      {
        "category": "Professional",
        "type": "Services"
      }
    ],
    "sg:phone": "+1 740 872 3273",
    "sg:postcode": "43767",
    "sg:province": "OH",
    "sg:tags": [
      "establishment"
    ],
    "wof:name": "Hartley Co",
    "wof:placetype": "venue"
  },
  "geometry": {"coordinates":[-81.830701,39.974603],"type":"Point"}
}
