{
  "type": "Feature",
  "properties": {
    "addr:full":"5842 Firethorne Dr Toledo OH 43615",
    "addr:housenumber":"5842",
    "addr:postcode":"43615",
    "addr:street":"Firethorne Dr",
    "iso:country":"US",
    "sg:address":"5842 Firethorne Dr",
    "sg:city":"Toledo",
    "sg:classifiers":[
        {
            "category":"Organizations",
            "subcategory":"Religious Organization",
            "type":"Services"
        }
    ],
    "sg:phone":"+1 419 474 5338",
    "sg:postcode":"43615",
    "sg:province":"OH",
    "sg:tags":[
        "clergy"
    ],
    "wof:name":"N Madison",
    "wof:placetype":"venue"
},
  "geometry": {"coordinates":[-83.68125499999999,41.620717],"type":"Point"}
}