{
  "type": "Feature",
  "properties": {
    "addr:full":"318 Iowa Ave SE Girard OH 44420",
    "addr:housenumber":"318",
    "addr:postcode":"44420",
    "addr:street":"Iowa Ave Se",
    "iso:country":"US",
    "sg:address":"318 Iowa Ave SE",
    "sg:city":"Girard",
    "sg:classifiers":[
        {
            "category":"Professional",
            "subcategory":"Lawyer & Legal Services",
            "type":"Services"
        }
    ],
    "sg:phone":"+1 330 530 1620",
    "sg:postcode":"44420",
    "sg:province":"OH",
    "sg:tags":[
        "attorney"
    ],
    "wof:name":"Lisa K Robinson",
    "wof:placetype":"venue"
},
  "geometry": {"coordinates":[-80.68436699999999,41.146737],"type":"Point"}
}