{
  "type": "Feature",
  "properties": {
    "addr:full": "3590 Smith Rd Fremont OH 43420",
    "addr:housenumber": "3590",
    "addr:postcode": "43420",
    "addr:street": "Smith Rd",
    "iso:country": "US",
    "sg:address": "3590 Smith Rd",
    "sg:city": "Fremont",
    "sg:classifiers": [
      {
        "category": "Wholesale",
        "subcategory": "Construction Materials",
        "type": "Manufacturing \u0026 Wholesale Goods"
      }
    ],
    "sg:phone": "+1 419 639 9930",
    "sg:postcode": "43420",
    "sg:province": "OH",
    "wof:name": "D A Miller Cement Finishing",
    "wof:placetype": "venue"
  },
  "geometry": {"coordinates":[-83.091829,41.282956],"type":"Point"}
}
