{
  "type": "Feature",
  "properties": {
    "addr:full":"502 Marion Manor Woods Newark OH 43055",
    "addr:housenumber":"502",
    "addr:postcode":"43055",
    "addr:street":"Marion Manor",
    "iso:country":"US",
    "sg:address":"502 Marion Manor Woods",
    "sg:city":"Newark",
    "sg:classifiers":[
        {
            "category":"Local Transit",
            "type":"Transportation"
        }
    ],
    "sg:phone":"+1 740 344 3349",
    "sg:postcode":"43055",
    "sg:province":"OH",
    "sg:tags":[
        "line"
    ],
    "wof:name":"Dart Transit",
    "wof:placetype":"venue"
},
  "geometry": {"coordinates":[-82.443853,40.060618],"type":"Point"}
}