{
  "type": "Feature",
  "properties": {
    "iso:country":"US",
    "sg:address":"1517 Harding Hwy",
    "sg:city":"Lima",
    "sg:classifiers":[
        {
            "category":"Communications",
            "type":"Services"
        }
    ],
    "sg:phone":"+1 419 221 1766",
    "sg:postcode":"45804",
    "sg:province":"OH",
    "wof:name":"R G Sound & Communication Inc",
    "wof:placetype":"venue"
},
  "geometry": {"coordinates":[-84.077332,40.730757],"type":"Point"}
}