{
  "type": "Feature",
  "properties": {
    "addr:full": "1517 Harding Hwy Lima OH 45804",
    "addr:housenumber": "1517",
    "addr:postcode": "45804",
    "addr:street": "Harding Hwy",
    "iso:country": "US",
    "sg:address": "1517 Harding Hwy",
    "sg:city": "Lima",
    "sg:classifiers": [
      {
        "category": "Communications",
        "type": "Services"
      }
    ],
    "sg:phone": "+1 419 221 1766",
    "sg:postcode": "45804",
    "sg:province": "OH",
    "wof:name": "R G Sound \u0026 Communication Inc",
    "wof:placetype": "venue"
  },
  "geometry": {"coordinates":[-84.077332,40.730757],"type":"Point"}
}
