{
  "type": "Feature",
  "properties": {
    "addr:full": "500 Baum St Cincinnati OH 45202",
    "addr:housenumber": "500",
    "addr:postcode": "45202",
    "addr:street": "Baum St",
    "iso:country": "US",
    "sg:address": "500 Baum St",
    "sg:city": "Cincinnati",
    "sg:classifiers": [
      {
        "category": "Building \u0026 Trades",
        "subcategory": "Cleaning \u0026 Sanitation",
        "type": "Services"
      }
    ],
    "sg:phone": "+1 513 984 5242",
    "sg:postcode": "45202",
    "sg:province": "OH",
    "sg:tags": [
      "house"
    ],
    "wof:name": "Amsterdam Cleaning Svc",
    "wof:placetype": "venue"
  },
  "geometry": {"coordinates":[-84.498544,39.104527],"type":"Point"}
}
