{
  "type": "Feature",
  "properties": {
    "addr:full": "49 S Lisbon St Carrollton OH 44615",
    "addr:housenumber": "49",
    "addr:postcode": "44615",
    "addr:street": "S Lisbon St",
    "iso:country": "US",
    "sg:address": "49 S Lisbon St",
    "sg:city": "Carrollton",
    "sg:classifiers": [
      {
        "category": "Organizations",
        "subcategory": "Non-profit Organization",
        "type": "Services"
      }
    ],
    "sg:phone": "+1 330 627 2463",
    "sg:postcode": "44615",
    "sg:province": "OH",
    "sg:tags": [
      "human"
    ],
    "wof:name": "Habitat For Humanity",
    "wof:placetype": "venue"
  },
  "geometry": {"coordinates":[-81.086368,40.572662],"type":"Point"}
}
