{
  "type": "Feature",
  "properties": {
    "iso:country":"US",
    "sg:address":"49 S Lisbon St",
    "sg:city":"Carrollton",
    "sg:classifiers":[
        {
            "category":"Organizations",
            "subcategory":"Non-profit Organization",
            "type":"Services"
        }
    ],
    "sg:phone":"+1 330 627 2463",
    "sg:postcode":"44615",
    "sg:province":"OH",
    "sg:tags":[
        "human"
    ],
    "wof:name":"Habitat For Humanity",
    "wof:placetype":"venue"
},
  "geometry": {"coordinates":[-81.08636799999999,40.572662],"type":"Point"}
}