{
  "type": "Feature",
  "properties": {
    "addr:full": "5534 State Rte 167 Pierpont OH 44082",
    "addr:housenumber": "5534",
    "addr:postcode": "44082",
    "addr:street": "State Rte 167",
    "iso:country": "US",
    "sg:address": "5534 State Rte 167",
    "sg:city": "Pierpont",
    "sg:classifiers": [
      {
        "category": "Home \u0026 Garden",
        "subcategory": "Household Appliances",
        "type": "Retail Goods"
      }
    ],
    "sg:phone": "+1 440 577 1256",
    "sg:postcode": "44082",
    "sg:province": "OH",
    "sg:tags": [
      "machine",
      "sewing"
    ],
    "wof:name": "Case Sewing Ctr",
    "wof:placetype": "venue"
  },
  "geometry": {"coordinates":[-80.5721,41.75163],"type":"Point"}
}
