{
  "type": "Feature",
  "properties": {
    "iso:country":"US",
    "sg:address":"5534 State Rte 167",
    "sg:city":"Pierpont",
    "sg:classifiers":[
        {
            "category":"Home & Garden",
            "subcategory":"Household Appliances",
            "type":"Retail Goods"
        }
    ],
    "sg:phone":"+1 440 577 1256",
    "sg:postcode":"44082",
    "sg:province":"OH",
    "sg:tags":[
        "machine",
        "sewing"
    ],
    "wof:name":"Case Sewing Ctr",
    "wof:placetype":"venue"
},
  "geometry": {"coordinates":[-80.57210000000001,41.75163],"type":"Point"}
}