{
  "type": "Feature",
  "properties": {
    "addr:full":"35490 Lorain Rd North Ridgeville OH 44039",
    "addr:housenumber":"35490",
    "addr:postcode":"44039",
    "addr:street":"Lorain Rd",
    "iso:country":"US",
    "sg:address":"35490 Lorain Rd",
    "sg:city":"North Ridgeville",
    "sg:classifiers":[
        {
            "category":"Home & Garden",
            "subcategory":"Building Materials",
            "type":"Retail Goods"
        }
    ],
    "sg:phone":"+1 440 327 4526",
    "sg:postcode":"44039",
    "sg:province":"OH",
    "sg:tags":[
        "paint"
    ],
    "wof:name":"Discount Painting & Decorating",
    "wof:placetype":"venue"
},
  "geometry": {"coordinates":[-82.012539,41.357875],"type":"Point"}
}