{
  "type": "Feature",
  "properties": {
    "iso:country":"US",
    "sg:address":"16773 Chagrin Blvd",
    "sg:city":"Cleveland",
    "sg:classifiers":[
        {
            "category":"Restaurant",
            "type":"Food & Drink"
        }
    ],
    "sg:menulink":"http://www.allmenus.com/oh/shaker-heights/150831-boston-market/menu/",
    "sg:phone":"+1 216 991 0300",
    "sg:postcode":"44120",
    "sg:province":"OH",
    "sg:tags":[
        "barbecue",
        "american",
        "soup"
    ],
    "wof:name":"Boston Market",
    "wof:placetype":"venue"
},
  "geometry": {"coordinates":[-81.56229399999999,41.464499],"type":"Point"}
}