{
  "type": "Feature",
  "properties": {
    "iso:country":"US",
    "sg:address":"3016 W Lakeshore Dr",
    "sg:city":"Port Clinton",
    "sg:classifiers":[
        {
            "category":"Recreation",
            "subcategory":"Marina",
            "type":"Entertainment"
        }
    ],
    "sg:phone":"+1 419 732 0981",
    "sg:postcode":"43452",
    "sg:province":"OH",
    "sg:tags":[
        "repairing",
        "boat"
    ],
    "wof:name":"Fiberglass & Wood Repair",
    "wof:placetype":"venue"
},
  "geometry": {"coordinates":[-82.991348,41.52079],"type":"Point"}
}