{
  "type": "Feature",
  "properties": {
    "addr:full":"13515 W 130th St North Royalton OH 44133",
    "addr:housenumber":"13515",
    "addr:postcode":"44133",
    "addr:street":"W 130Th St",
    "iso:country":"US",
    "sg:address":"13515 W 130th St",
    "sg:city":"North Royalton",
    "sg:classifiers":[
        {
            "category":"Real Estate",
            "subcategory":"Real Estate Agent",
            "type":"Services"
        }
    ],
    "sg:phone":"+1 440 237 2900",
    "sg:postcode":"44133",
    "sg:province":"OH",
    "wof:name":"Century 21",
    "wof:placetype":"venue"
},
  "geometry": {"coordinates":[-81.78523199999999,41.319771],"type":"Point"}
}