{
  "type": "Feature",
  "properties": {
    "addr:full":"1623 Marlowe Ave Cincinnati OH 45224",
    "addr:housenumber":"1623",
    "addr:postcode":"45224",
    "addr:street":"Marlowe Ave",
    "iso:country":"US",
    "sg:address":"1623 Marlowe Ave",
    "sg:city":"Cincinnati",
    "sg:classifiers":[
        {
            "category":"Organizations",
            "subcategory":"Non-profit Organization",
            "type":"Services"
        }
    ],
    "sg:phone":"+1 513 681 0326",
    "sg:postcode":"45224",
    "sg:province":"OH",
    "sg:tags":[
        "social"
    ],
    "wof:name":"Marlowe House",
    "wof:placetype":"venue"
},
  "geometry": {"coordinates":[-84.548393,39.199876],"type":"Point"}
}