{
  "type": "Feature",
  "properties": {
    "addr:full": "9355 State Rte 119 Anna OH 45302",
    "addr:housenumber": "9355",
    "addr:postcode": "45302",
    "addr:street": "State Rte 119",
    "iso:country": "US",
    "sg:address": "9355 State Rte 119",
    "sg:city": "Anna",
    "sg:classifiers": [
      {
        "category": "Government",
        "subcategory": "Office",
        "type": "Public Place"
      }
    ],
    "sg:phone": "+1 937 394 3217",
    "sg:postcode": "45302",
    "sg:province": "OH",
    "sg:tags": [
      "educational",
      "program",
      "administrative"
    ],
    "wof:name": "Shelby Co Sbh Unit",
    "wof:placetype": "venue"
  },
  "geometry": {"coordinates":[-84.248456,40.394848],"type":"Point"}
}
