{
  "type": "Feature",
  "properties": {
    "addr:full": "6078 Brown Rd Oxford OH 45056",
    "addr:housenumber": "6078",
    "addr:postcode": "45056",
    "addr:street": "Brown Rd",
    "iso:country": "US",
    "sg:address": "6078 Brown Rd",
    "sg:city": "Oxford",
    "sg:classifiers": [
      {
        "category": "Building \u0026 Trades",
        "subcategory": "Landscaping Services",
        "type": "Services"
      }
    ],
    "sg:phone": "+1 513 524 8800",
    "sg:postcode": "45056",
    "sg:province": "OH",
    "sg:tags": [
      "landscape",
      "contractor"
    ],
    "wof:name": "Land Framers Inc",
    "wof:placetype": "venue"
  },
  "geometry": {"coordinates":[-84.75181,39.538061],"type":"Point"}
}
