{
  "type": "Feature",
  "properties": {
    "iso:country":"US",
    "sg:address":"6078 Brown Rd",
    "sg:city":"Oxford",
    "sg:classifiers":[
        {
            "category":"Building & Trades",
            "subcategory":"Landscaping Services",
            "type":"Services"
        }
    ],
    "sg:phone":"+1 513 524 8800",
    "sg:postcode":"45056",
    "sg:province":"OH",
    "sg:tags":[
        "landscape",
        "contractor"
    ],
    "wof:name":"Land Framers Inc",
    "wof:placetype":"venue"
},
  "geometry": {"coordinates":[-84.75181000000001,39.538061],"type":"Point"}
}