{
  "type": "Feature",
  "properties": {
    "addr:full": "2033 Sutton Ave Apt 2 Cincinnati OH 45230",
    "addr:housenumber": "2033;2",
    "addr:postcode": "45230",
    "addr:street": "Sutton Ave Apt",
    "iso:country": "US",
    "sg:address": "2033 Sutton Ave Apt 2",
    "sg:city": "Cincinnati",
    "sg:classifiers": [
      {
        "category": "Autos \u0026 Motor Vehicles",
        "subcategory": "Auto Supplies",
        "type": "Retail Goods"
      },
      {
        "category": "Manufacturing",
        "subcategory": "Electronics",
        "type": "Manufacturing \u0026 Wholesale Goods"
      }
    ],
    "sg:phone": "+1 513 232 9363",
    "sg:postcode": "45230",
    "sg:province": "OH",
    "sg:tags": [
      "consultant",
      "robotics",
      "automation"
    ],
    "wof:name": "Robert Ribariu",
    "wof:placetype": "venue"
  },
  "geometry": {"coordinates":[-84.389618,39.091808],"type":"Point"}
}
