{
  "type": "Feature",
  "properties": {
    "iso:country":"US",
    "sg:address":"221 W Pete Rose Way",
    "sg:city":"Cincinnati",
    "sg:classifiers":[
        {
            "category":"Wholesale",
            "subcategory":"Fruits & Vegetables",
            "type":"Manufacturing & Wholesale Goods"
        }
    ],
    "sg:phone":"+1 513 721 5813",
    "sg:postcode":"45202",
    "sg:province":"OH",
    "wof:name":"Fries Brothers Fruit & Vgtbls",
    "wof:placetype":"venue"
},
  "geometry": {"coordinates":[-84.516513,39.096397],"type":"Point"}
}