{
  "type": "Feature",
  "properties": {
    "addr:full": "221 W Pete Rose Way Cincinnati OH 45202",
    "addr:housenumber": "221",
    "addr:postcode": "45202",
    "addr:street": "W Pete Rose Way",
    "iso:country": "US",
    "sg:address": "221 W Pete Rose Way",
    "sg:city": "Cincinnati",
    "sg:classifiers": [
      {
        "category": "Wholesale",
        "subcategory": "Fruits \u0026 Vegetables",
        "type": "Manufacturing \u0026 Wholesale Goods"
      }
    ],
    "sg:phone": "+1 513 721 5813",
    "sg:postcode": "45202",
    "sg:province": "OH",
    "wof:name": "Fries Brothers Fruit \u0026 Vgtbls",
    "wof:placetype": "venue"
  },
  "geometry": {"coordinates":[-84.516513,39.096397],"type":"Point"}
}
