{
  "type": "Feature",
  "properties": {
    "addr:full":"4012 E Harbor Rd Port Clinton OH 43452",
    "addr:housenumber":"4012 e",
    "addr:postcode":"43452",
    "addr:street":"Harbor Rd",
    "iso:country":"US",
    "sg:address":"4012 E Harbor Rd",
    "sg:city":"Port Clinton",
    "sg:classifiers":[
        {
            "category":"Professional",
            "subcategory":"Advertising",
            "type":"Services"
        }
    ],
    "sg:phone":"+1 419 732 0688",
    "sg:postcode":"43452",
    "sg:province":"OH",
    "sg:tags":[
        "mailing",
        "shipping"
    ],
    "wof:name":"UPS Store",
    "wof:placetype":"venue"
},
  "geometry": {"coordinates":[-82.854952,41.525078],"type":"Point"}
}