{
  "type": "Feature",
  "properties": {
    "addr:full": "5256 Maplesburg Dr Monclova OH 43542",
    "addr:housenumber": "5256",
    "addr:postcode": "43542",
    "addr:street": "Maplesburg Dr",
    "iso:country": "US",
    "sg:address": "5256 Maplesburg Dr",
    "sg:city": "Monclova",
    "sg:classifiers": [
      {
        "category": "Home \u0026 Garden",
        "subcategory": "Hardware",
        "type": "Retail Goods"
      }
    ],
    "sg:phone": "+1 419 877 0340",
    "sg:postcode": "43542",
    "sg:province": "OH",
    "wof:name": "J and B Tools Inc",
    "wof:placetype": "venue"
  },
  "geometry": {"coordinates":[-83.775206,41.545212],"type":"Point"}
}
