{
  "type": "Feature",
  "properties": {
    "addr:full": "1462 S High St Columbus OH 43207",
    "addr:housenumber": "1462",
    "addr:postcode": "43207",
    "addr:street": "S High St",
    "iso:country": "US",
    "sg:address": "1462 S High St",
    "sg:city": "Columbus",
    "sg:classifiers": [
      {
        "category": "Professional",
        "type": "Services"
      }
    ],
    "sg:phone": "+1 614 443 1111",
    "sg:postcode": "43207",
    "sg:province": "OH",
    "sg:tags": [
      "establishment"
    ],
    "wof:name": "F P Productions Inc",
    "wof:placetype": "venue"
  },
  "geometry": {"coordinates":[-82.995781,39.93156],"type":"Point"}
}
