{
  "type": "Feature",
  "properties": {
    "iso:country":"US",
    "sg:address":"7152 Reading Rd",
    "sg:city":"Cincinnati",
    "sg:classifiers":[
        {
            "category":"Home & Garden",
            "subcategory":"Hardware",
            "type":"Retail Goods"
        }
    ],
    "sg:phone":"+1 513 731 2580",
    "sg:postcode":"45237",
    "sg:province":"OH",
    "wof:name":"Smalls Pro Hardware-Hillcrest",
    "wof:placetype":"venue"
},
  "geometry": {"coordinates":[-84.462046,39.190914],"type":"Point"}
}