{
  "type": "Feature",
  "properties": {
    "addr:full":"101 Curl Dr Columbus OH 43210",
    "addr:housenumber":"101",
    "addr:postcode":"43210",
    "addr:street":"Curl Dr",
    "iso:country":"US",
    "sg:address":"101 Curl Dr",
    "sg:city":"Columbus",
    "sg:classifiers":[
        {
            "category":"Professional",
            "type":"Services"
        }
    ],
    "sg:phone":"+1 614 688 0917",
    "sg:postcode":"43210",
    "sg:province":"OH",
    "sg:tags":[
        "establishment"
    ],
    "wof:name":"Wang Sho-Ling",
    "wof:placetype":"venue"
},
  "geometry": {"coordinates":[-83.010471,40.005353],"type":"Point"}
}