{
  "type": "Feature",
  "properties": {
    "addr:full": "10004 US Rte 250 Milan OH 44846",
    "addr:housenumber": "10004",
    "addr:postcode": "44846",
    "addr:street": "Us Rte 250",
    "iso:country": "US",
    "sg:address": "10004 US Rte 250",
    "sg:city": "Milan",
    "sg:classifiers": [
      {
        "category": "Retail",
        "subcategory": "Auto Repair",
        "type": "Services"
      }
    ],
    "sg:phone": "+1 800 800 2727",
    "sg:postcode": "44846",
    "sg:province": "OH",
    "sg:tags": [
      "glass",
      "replacement"
    ],
    "wof:name": "Safelite Autoglass",
    "wof:placetype": "venue"
  },
  "geometry": {"coordinates":[-82.626039,41.336155],"type":"Point"}
}
