{
  "type": "Feature",
  "properties": {
    "iso:country":"US",
    "sg:address":"10004 US Rte 250",
    "sg:city":"Milan",
    "sg:classifiers":[
        {
            "category":"Retail",
            "subcategory":"Auto Repair",
            "type":"Services"
        }
    ],
    "sg:phone":"+1 800 800 2727",
    "sg:postcode":"44846",
    "sg:province":"OH",
    "sg:tags":[
        "glass",
        "replacement"
    ],
    "wof:name":"Safelite Autoglass",
    "wof:placetype":"venue"
},
  "geometry": {"coordinates":[-82.62603900000001,41.336155],"type":"Point"}
}