{
  "type": "Feature",
  "properties": {
    "addr:full":"11904 Detroit Ave Cleveland OH 44107",
    "addr:housenumber":"11904",
    "addr:postcode":"44107",
    "addr:street":"Detroit Ave",
    "iso:country":"US",
    "sg:address":"11904 Detroit Ave",
    "sg:city":"Cleveland",
    "sg:classifiers":[
        {
            "category":"Bars & Pubs",
            "type":"Food & Drink"
        }
    ],
    "sg:phone":"+1 216 521 4906",
    "sg:postcode":"44107",
    "sg:province":"OH",
    "sg:tags":[
        "drinking"
    ],
    "wof:name":"Five O'Clock Bar",
    "wof:placetype":"venue"
},
  "geometry": {"coordinates":[-81.772532,41.484043],"type":"Point"}
}