{
  "type": "Feature",
  "properties": {
    "iso:country":"US",
    "sg:address":"347 N Union St",
    "sg:city":"Delaware",
    "sg:classifiers":[
        {
            "category":"Building & Trades",
            "subcategory":"Construction",
            "type":"Services"
        }
    ],
    "sg:phone":"+1 740 369 5424",
    "sg:postcode":"43015",
    "sg:province":"OH",
    "sg:tags":[
        "nonresidential"
    ],
    "wof:name":"Keefers Building & Remodeling",
    "wof:placetype":"venue"
},
  "geometry": {"coordinates":[-83.065133,40.309508],"type":"Point"}
}