{
  "type": "Feature",
  "properties": {
    "addr:full":"207 S Court St Circleville OH 43113",
    "addr:housenumber":"207",
    "addr:postcode":"43113",
    "addr:street":"S Court St",
    "iso:country":"US",
    "sg:address":"207 S Court St",
    "sg:city":"Circleville",
    "sg:classifiers":[
        {
            "category":"Government",
            "subcategory":"Office",
            "type":"Public Place"
        }
    ],
    "sg:phone":"+1 740 474 5233",
    "sg:postcode":"43113",
    "sg:province":"OH",
    "sg:tags":[
        "county"
    ],
    "wof:name":"Pickaway County Clerk Of Court",
    "wof:placetype":"venue"
},
  "geometry": {"coordinates":[-82.945708,39.600804],"type":"Point"}
}