{
  "type": "Feature",
  "properties": {
    "iso:country":"US",
    "sg:address":"4059 Commerce Ave",
    "sg:city":"Cleveland",
    "sg:classifiers":[
        {
            "category":"Professional",
            "subcategory":"Art Services",
            "type":"Services"
        }
    ],
    "sg:phone":"+1 216 881 0141",
    "sg:postcode":"44103",
    "sg:province":"OH",
    "sg:tags":[
        "photographer"
    ],
    "wof:name":"Robert Heine Photography",
    "wof:placetype":"venue"
},
  "geometry": {"coordinates":[-81.656464,41.50787],"type":"Point"}
}