{
  "type": "Feature",
  "properties": {
    "iso:country":"US",
    "sg:address":"1910 Chippewa Dr",
    "sg:city":"Circleville",
    "sg:classifiers":[
        {
            "category":"Freight",
            "type":"Transportation"
        }
    ],
    "sg:phone":"+1 740 474 6246",
    "sg:postcode":"43113",
    "sg:province":"OH",
    "sg:tags":[
        "operator",
        "local",
        "trucking"
    ],
    "wof:name":"Triple D Trans Ltd",
    "wof:placetype":"venue"
},
  "geometry": {"coordinates":[-82.951984,39.571571],"type":"Point"}
}