{
  "type": "Feature",
  "properties": {
    "addr:full":"1771 Arlin Pl Fairborn OH 45324",
    "addr:housenumber":"1771",
    "addr:postcode":"45324",
    "addr:street":"Arlin Pl",
    "iso:country":"US",
    "sg:address":"1771 Arlin Pl",
    "sg:city":"Fairborn",
    "sg:classifiers":[
        {
            "category":"Shopping",
            "type":"Retail Goods"
        }
    ],
    "sg:phone":"+1 937 879 5824",
    "sg:postcode":"45324",
    "sg:province":"OH",
    "sg:tags":[
        "merchandise"
    ],
    "wof:name":"Phillips Discount Outlet",
    "wof:placetype":"venue"
},
  "geometry": {"coordinates":[-84.03297000000001,39.794201],"type":"Point"}
}