{
  "type": "Feature",
  "properties": {
    "iso:country":"US",
    "sg:address":"4014 E 116th St",
    "sg:city":"Cleveland",
    "sg:classifiers":[
        {
            "category":"Manufacturing",
            "subcategory":"Watercraft",
            "type":"Manufacturing & Wholesale Goods"
        }
    ],
    "sg:phone":"+1 216 732 9925",
    "sg:postcode":"44105",
    "sg:province":"OH",
    "sg:tags":[
        "kayak",
        "machine",
        "rowing",
        "mfg",
        "canoe"
    ],
    "wof:name":"Epi",
    "wof:placetype":"venue"
},
  "geometry": {"coordinates":[-81.602934,41.449981],"type":"Point"}
}