{
  "type": "Feature",
  "properties": {
    "addr:full": "4217 Hills and Dales Rd NW Canton OH 44708",
    "addr:housenumber": "4217",
    "addr:postcode": "44708",
    "addr:street": "Hills And Dales Rd Nw",
    "iso:country": "US",
    "sg:address": "4217 Hills and Dales Rd NW",
    "sg:city": "Canton",
    "sg:classifiers": [
      {
        "category": "Professional",
        "subcategory": "Accounting \u0026 Tax Preparation",
        "type": "Services"
      }
    ],
    "sg:phone": "+1 330 477 9933",
    "sg:postcode": "44708",
    "sg:province": "OH",
    "sg:tags": [
      "return",
      "filing"
    ],
    "wof:name": "Associated Tax Serv Inc",
    "wof:placetype": "venue"
  },
  "geometry": {"coordinates":[-81.422234,40.832915],"type":"Point"}
}
