{
  "type": "Feature",
  "properties": {
    "iso:country":"US",
    "sg:address":"4217 Hills and Dales Rd NW",
    "sg:city":"Canton",
    "sg:classifiers":[
        {
            "category":"Professional",
            "subcategory":"Accounting & Tax Preparation",
            "type":"Services"
        }
    ],
    "sg:phone":"+1 330 477 9933",
    "sg:postcode":"44708",
    "sg:province":"OH",
    "sg:tags":[
        "return",
        "filing"
    ],
    "wof:name":"Associated Tax Serv Inc",
    "wof:placetype":"venue"
},
  "geometry": {"coordinates":[-81.422234,40.832915],"type":"Point"}
}