{
  "type": "Feature",
  "properties": {
    "iso:country":"US",
    "sg:address":"5001 Monroe St",
    "sg:city":"Toledo",
    "sg:classifiers":[
        {
            "category":"Shopping",
            "subcategory":"Clothing, Apparel, & Fashions",
            "type":"Retail Goods"
        }
    ],
    "sg:phone":"+1 419 475 6950",
    "sg:postcode":"43606",
    "sg:province":"OH",
    "sg:tags":[
        "mfg"
    ],
    "wof:name":"Bebe Stores Inc",
    "wof:placetype":"venue"
},
  "geometry": {"coordinates":[-83.642016,41.697742],"type":"Point"}
}