{
  "type": "Feature",
  "properties": {
    "addr:full": "612 Market Ave S Canton OH 44702",
    "addr:housenumber": "612",
    "addr:postcode": "44702",
    "addr:street": "Market Ave S",
    "iso:country": "US",
    "sg:address": "612 Market Ave S",
    "sg:city": "Canton",
    "sg:classifiers": [
      {
        "category": "Professional",
        "subcategory": "Computer Services",
        "type": "Services"
      }
    ],
    "sg:phone": "+1 330 455 4000",
    "sg:postcode": "44702",
    "sg:province": "OH",
    "sg:tags": [
      "internet"
    ],
    "wof:name": "Skylan LTD",
    "wof:placetype": "venue"
  },
  "geometry": {"coordinates":[-81.376125,40.79429],"type":"Point"}
}
