{
  "type": "Feature",
  "properties": {
    "iso:country":"US",
    "sg:address":"9134 Mentor Ave",
    "sg:city":"Mentor",
    "sg:classifiers":[
        {
            "category":"Shopping",
            "subcategory":"Department Store",
            "type":"Retail Goods"
        }
    ],
    "sg:phone":"+1 440 974 6166",
    "sg:postcode":"44060",
    "sg:province":"OH",
    "sg:tags":[
        "shop"
    ],
    "wof:name":"Deals-Nthing Over A Dollar LLC",
    "wof:placetype":"venue"
},
  "geometry": {"coordinates":[-81.313599,41.675932],"type":"Point"}
}