{
  "type": "Feature",
  "properties": {
    "iso:country":"US",
    "sg:address":"919 Military Dr",
    "sg:city":"Galloway",
    "sg:classifiers":[
        {
            "category":"Professional",
            "type":"Services"
        }
    ],
    "sg:phone":"+1 614 922 0363",
    "sg:postcode":"43119",
    "sg:province":"OH",
    "wof:name":"Denise Davis",
    "wof:placetype":"venue"
},
  "geometry": {"coordinates":[-83.226195,39.966986],"type":"Point"}
}