{
  "type": "Feature",
  "properties": {
    "addr:full":"9345 Columbia Rd Cleveland OH 44138",
    "addr:housenumber":"9345",
    "addr:postcode":"44138",
    "addr:street":"Columbia Rd",
    "iso:country":"US",
    "sg:address":"9345 Columbia Rd",
    "sg:city":"Cleveland",
    "sg:classifiers":[
        {
            "category":"Home & Garden",
            "subcategory":"Garden Supply",
            "type":"Retail Goods"
        }
    ],
    "sg:phone":"+1 440 235 4220",
    "sg:postcode":"44138",
    "sg:province":"OH",
    "sg:tags":[
        "bonsai",
        "plant"
    ],
    "wof:name":"Container Gardens",
    "wof:placetype":"venue"
},
  "geometry": {"coordinates":[-81.903977,41.358295],"type":"Point"}
}