{
  "type": "Feature",
  "properties": {
    "addr:full": "10403 W Salem Rd West Salem OH 44287",
    "addr:housenumber": "10403",
    "addr:postcode": "44287",
    "addr:street": "W Salem Rd",
    "iso:country": "US",
    "sg:address": "10403 W Salem Rd",
    "sg:city": "West Salem",
    "sg:phone": "+1 419 846 3761",
    "sg:postcode": "44287",
    "sg:province": "OH",
    "sg:tags": [
      "farm",
      "corn",
      "wheat",
      "soybean"
    ],
    "wof:name": "Foltz Farms",
    "wof:placetype": "venue"
  },
  "geometry": {"coordinates":[-82.067628,40.990911],"type":"Point"}
}
