{
  "type": "Feature",
  "properties": {
    "addr:full": "9500 E Johnstown Rd New Albany OH 43054",
    "addr:housenumber": "9500",
    "addr:postcode": "43054",
    "addr:street": "E Johnstown Rd",
    "iso:country": "US",
    "sg:address": "9500 E Johnstown Rd",
    "sg:city": "New Albany",
    "sg:classifiers": [
      {
        "category": "Government",
        "subcategory": "Office",
        "type": "Public Place"
      },
      {
        "category": "Government",
        "subcategory": "Fire Station",
        "type": "Public Place"
      }
    ],
    "sg:phone": "+1 614 855 2222",
    "sg:postcode": "43054",
    "sg:province": "OH",
    "sg:tags": [
      "department",
      "township"
    ],
    "sg:website": "www.plaintownshipnaoh.com",
    "wof:name": "Plain Township Fire Department",
    "wof:placetype": "venue"
  },
  "geometry": {"coordinates":[-82.803228,40.085326],"type":"Point"}
}
