{
  "type": "Feature",
  "properties": {
    "addr:full": "101 E Spring St St Marys OH 45885",
    "addr:housenumber": "101",
    "addr:postcode": "45885",
    "addr:street": "E Spring St",
    "iso:country": "US",
    "sg:address": "101 E Spring St",
    "sg:city": "St Marys",
    "sg:classifiers": [
      {
        "category": "Shopping",
        "type": "Retail Goods"
      }
    ],
    "sg:phone": "+1 419 394 9192",
    "sg:postcode": "45885",
    "sg:province": "OH",
    "sg:tags": [
      "candle"
    ],
    "wof:name": "Scentsible Pleasures",
    "wof:placetype": "venue"
  },
  "geometry": {"coordinates":[-84.386397,40.543959],"type":"Point"}
}
