{
  "type": "Feature",
  "properties": {
    "addr:full": "5892 Windwood Ct Mason OH 45040",
    "addr:housenumber": "5892",
    "addr:postcode": "45040",
    "addr:street": "Windwood Ct",
    "iso:country": "US",
    "sg:address": "5892 Windwood Ct",
    "sg:city": "Mason",
    "sg:classifiers": [
      {
        "category": "Professional",
        "subcategory": "Management \u0026 Consulting",
        "type": "Services"
      }
    ],
    "sg:phone": "+1 513 459 8000",
    "sg:postcode": "45040",
    "sg:province": "OH",
    "sg:tags": [
      "consultant",
      "security",
      "system"
    ],
    "wof:name": "Piracy Prevention Systems Inc",
    "wof:placetype": "venue"
  },
  "geometry": {"coordinates":[-84.3286,39.318973],"type":"Point"}
}
