{
  "type": "Feature",
  "properties": {
    "iso:country":"US",
    "sg:address":"4359 E Pine Lake Rd",
    "sg:city":"New Springfield",
    "sg:classifiers":[
        {
            "category":"Professional",
            "subcategory":"Management & Consulting",
            "type":"Services"
        }
    ],
    "sg:phone":"+1 330 542 9135",
    "sg:postcode":"44443",
    "sg:province":"OH",
    "sg:tags":[
        "retail",
        "direct",
        "sales"
    ],
    "wof:name":"Michael Rutana",
    "wof:placetype":"venue"
},
  "geometry": {"coordinates":[-80.576481,40.929218],"type":"Point"}
}