{
  "type": "Feature",
  "properties": {
    "addr:full": "10391 State Rte 15 Ottawa OH 45875",
    "addr:housenumber": "10391",
    "addr:postcode": "45875",
    "addr:street": "State Rte 15",
    "iso:country": "US",
    "sg:address": "10391 State Rte 15",
    "sg:city": "Ottawa",
    "sg:classifiers": [
      {
        "category": "Manufacturing",
        "subcategory": "Glass \u0026 Minerals",
        "type": "Manufacturing \u0026 Wholesale Goods"
      }
    ],
    "sg:phone": "+1 419 523 4376",
    "sg:postcode": "45875",
    "sg:province": "OH",
    "sg:tags": [
      "ready"
    ],
    "sg:website": "www.kandlreadymix.com",
    "wof:name": "K \u0026 L Ready-Mix",
    "wof:placetype": "venue"
  },
  "geometry": {"coordinates":[-84.061196,41.03808],"type":"Point"}
}
