{
  "type": "Feature",
  "properties": {
    "iso:country":"US",
    "sg:address":"10391 State Rte 15",
    "sg:city":"Ottawa",
    "sg:classifiers":[
        {
            "category":"Manufacturing",
            "subcategory":"Glass & Minerals",
            "type":"Manufacturing & Wholesale Goods"
        }
    ],
    "sg:phone":"+1 419 523 4376",
    "sg:postcode":"45875",
    "sg:province":"OH",
    "sg:tags":[
        "ready"
    ],
    "sg:website":"www.kandlreadymix.com",
    "wof:name":"K & L Ready-Mix",
    "wof:placetype":"venue"
},
  "geometry": {"coordinates":[-84.061196,41.03808],"type":"Point"}
}