{
  "type": "Feature",
  "properties": {
    "addr:full": "5571 Beechmont Ave Cincinnati OH 45230",
    "addr:housenumber": "5571",
    "addr:postcode": "45230",
    "addr:street": "Beechmont Ave",
    "iso:country": "US",
    "sg:address": "5571 Beechmont Ave",
    "sg:city": "Cincinnati",
    "sg:classifiers": [
      {
        "category": "Organizations",
        "subcategory": "Religious Organization",
        "type": "Services"
      }
    ],
    "sg:phone": "+1 513 231 7382",
    "sg:postcode": "45230",
    "sg:province": "OH",
    "sg:tags": [
      "clergy"
    ],
    "wof:name": "Russell Ballard",
    "wof:placetype": "venue"
  },
  "geometry": {"coordinates":[-84.388681,39.10335],"type":"Point"}
}
