{
  "type": "Feature",
  "properties": {
    "addr:full":"3528 Tuscarawas St W Canton OH 44708",
    "addr:postcode":"3528;44708",
    "addr:street":"Tuscarawas St W",
    "iso:country":"US",
    "sg:address":"3528 Tuscarawas St W",
    "sg:city":"Canton",
    "sg:classifiers":[
        {
            "category":"Banks & Credit Unions",
            "subcategory":"Bank",
            "type":"Services"
        }
    ],
    "sg:phone":"+1 330 452 9804",
    "sg:postcode":"44708",
    "sg:province":"OH",
    "sg:tags":[
        "national",
        "commercial"
    ],
    "wof:name":"Charter One",
    "wof:placetype":"venue"
},
  "geometry": {"coordinates":[-81.415425,40.797582],"type":"Point"}
}