{
  "type": "Feature",
  "properties": {
    "addr:full":"126 Boardman Poland Rd Youngstown OH 44514",
    "addr:housenumber":"126",
    "addr:postcode":"44514",
    "addr:street":"Boardman Poland Rd",
    "iso:country":"US",
    "sg:address":"126 Boardman Poland Rd",
    "sg:city":"Youngstown",
    "sg:classifiers":[
        {
            "category":"Government",
            "subcategory":"Office",
            "type":"Public Place"
        }
    ],
    "sg:phone":"+1 330 726 3386",
    "sg:postcode":"44514",
    "sg:province":"OH",
    "wof:name":"Us Animal Plant/Health Inspctn",
    "wof:placetype":"venue"
},
  "geometry": {"coordinates":[-80.65682,41.02441],"type":"Point"}
}