{
  "type": "Feature",
  "properties": {
    "iso:country":"US",
    "sg:address":"120 S 3rd St",
    "sg:city":"Steubenville",
    "sg:classifiers":[
        {
            "category":"Museum",
            "type":"Entertainment"
        }
    ],
    "sg:phone":"+1 740 283 1787",
    "sg:postcode":"43952",
    "sg:province":"OH",
    "wof:name":"Old Fort Steuben",
    "wof:placetype":"venue"
},
  "geometry": {"coordinates":[-80.614476,40.357847],"type":"Point"}
}