{
  "type": "Feature",
  "properties": {
    "addr:full": "994 Coshocton Rd Mount Vernon OH 43050",
    "addr:housenumber": "994",
    "addr:postcode": "43050",
    "addr:street": "Coshocton Rd",
    "iso:country": "US",
    "sg:address": "994 Coshocton Rd",
    "sg:city": "Mount Vernon",
    "sg:classifiers": [
      {
        "category": "Restaurant",
        "type": "Food \u0026 Drink"
      }
    ],
    "sg:phone": "+1 740 397 3407",
    "sg:postcode": "43050",
    "sg:province": "OH",
    "sg:tags": [
      "fast"
    ],
    "wof:name": "Wendys",
    "wof:placetype": "venue"
  },
  "geometry": {"coordinates":[-82.453666,40.400519],"type":"Point"}
}
