{
  "type": "Feature",
  "properties": {
    "addr:full": "115 Allen Ln SW New Philadelphia OH 44663",
    "addr:housenumber": "115",
    "addr:postcode": "44663",
    "addr:street": "Allen Ln Sw",
    "iso:country": "US",
    "sg:address": "115 Allen Ln SW",
    "sg:city": "New Philadelphia",
    "sg:classifiers": [
      {
        "category": "Shopping",
        "subcategory": "Used Merchandise",
        "type": "Retail Goods"
      }
    ],
    "sg:phone": "+1 330 365 2026",
    "sg:postcode": "44663",
    "sg:province": "OH",
    "sg:tags": [
      "shop",
      "thrift"
    ],
    "wof:name": "Hospice Browse Buy Resale Str",
    "wof:placetype": "venue"
  },
  "geometry": {"coordinates":[-81.446588,40.48894],"type":"Point"}
}
