{
  "type": "Feature",
  "properties": {
    "iso:country":"US",
    "sg:address":"2266 W Manor Ave",
    "sg:city":"Youngstown",
    "sg:classifiers":[
        {
            "category":"Organizations",
            "subcategory":"Community Association",
            "type":"Services"
        }
    ],
    "sg:phone":"+1 330 755 3810",
    "sg:postcode":"44514",
    "sg:province":"OH",
    "wof:name":"Kiwanis CLB Estside Youngstown",
    "wof:placetype":"venue"
},
  "geometry": {"coordinates":[-80.604428,41.042877],"type":"Point"}
}