{
  "type": "Feature",
  "properties": {
    "addr:full":"410 Birchard Ave Fremont OH 43420",
    "addr:housenumber":"410",
    "addr:postcode":"43420",
    "addr:street":"Birchard Ave",
    "iso:country":"US",
    "sg:address":"410 Birchard Ave",
    "sg:city":"Fremont",
    "sg:classifiers":[
        {
            "category":"Health Services",
            "subcategory":"Doctor",
            "type":"Services"
        }
    ],
    "sg:phone":"+1 419 334 8855",
    "sg:postcode":"43420",
    "sg:province":"OH",
    "sg:tags":[
        "dentist"
    ],
    "wof:name":"Community Health Svc Dental",
    "wof:placetype":"venue"
},
  "geometry": {"coordinates":[-83.114954,41.344441],"type":"Point"}
}