{
  "type": "Feature",
  "properties": {
    "iso:country":"US",
    "sg:address":"115 E Gambier St",
    "sg:city":"Mount Vernon",
    "sg:classifiers":[
        {
            "category":"Travel",
            "subcategory":"Hotels & Motels",
            "type":"Entertainment"
        }
    ],
    "sg:phone":"+1 740 397 8638",
    "sg:postcode":"43050",
    "sg:province":"OH",
    "sg:tags":[
        "jewelry",
        "mfg",
        "metal",
        "ne",
        "precious",
        "operation"
    ],
    "wof:name":"Russell-Cooper House Inc",
    "wof:placetype":"venue"
},
  "geometry": {"coordinates":[-82.482673,40.391663],"type":"Point"}
}