{
  "type": "Feature",
  "properties": {
    "iso:country":"US",
    "sg:address":"793 W State St",
    "sg:city":"Columbus",
    "sg:classifiers":[
        {
            "category":"Insurance",
            "subcategory":"Health Insurance",
            "type":"Services"
        }
    ],
    "sg:phone":"+1 614 225 8024",
    "sg:postcode":"43222",
    "sg:province":"OH",
    "sg:tags":[
        "hospital",
        "medical",
        "plan"
    ],
    "wof:name":"Healthresponse",
    "wof:placetype":"venue"
},
  "geometry": {"coordinates":[-83.022406,39.957496],"type":"Point"}
}