{
  "type": "Feature",
  "properties": {
    "addr:full":"800 Gallia St Portsmouth OH 45662",
    "addr:housenumber":"800",
    "addr:postcode":"45662",
    "addr:street":"Gallia St",
    "iso:country":"US",
    "sg:address":"800 Gallia St",
    "sg:city":"Portsmouth",
    "sg:classifiers":[
        {
            "category":"Communications",
            "subcategory":"Television Station",
            "type":"Services"
        }
    ],
    "sg:phone":"+1 740 353 3391",
    "sg:postcode":"45662",
    "sg:province":"OH",
    "sg:tags":[
        "broadcasting"
    ],
    "wof:name":"Whcp TV",
    "wof:placetype":"venue"
},
  "geometry": {"coordinates":[-82.996557,38.734103],"type":"Point"}
}