{
  "type": "Feature",
  "properties": {
    "addr:full": "RR 93 Canal Fulton OH 44614",
    "addr:housenumber": "93",
    "addr:postcode": "44614",
    "addr:street": "Rr",
    "iso:country": "US",
    "sg:address": "RR 93",
    "sg:city": "Canal Fulton",
    "sg:classifiers": [
      {
        "category": "Park",
        "type": "Public Place"
      }
    ],
    "sg:phone": "+1 330 854 4242",
    "sg:postcode": "44614",
    "sg:province": "OH",
    "sg:website": "www.clayspark.com",
    "wof:name": "Clay's Park Resort",
    "wof:placetype": "venue"
  },
  "geometry": {"coordinates":[-81.580299,40.888401],"type":"Point"}
}
