{
  "type": "Feature",
  "properties": {
    "iso:country":"US",
    "sg:address":"6100 Memorial Dr",
    "sg:city":"Dublin",
    "sg:classifiers":[
        {
            "category":"Real Estate",
            "subcategory":"Real Estate Agent",
            "type":"Services"
        }
    ],
    "sg:phone":"+1 614 764 2211",
    "sg:postcode":"43017",
    "sg:province":"OH",
    "sg:tags":[
        "management"
    ],
    "sg:website":"www.hessenauer.com",
    "wof:name":"Hessenauer Corp Realtors",
    "wof:placetype":"venue"
},
  "geometry": {"coordinates":[-83.149503,40.134623],"type":"Point"}
}