{
  "type": "Feature",
  "properties": {
    "addr:full": "2280 E Dorothy Ln Dayton OH 45420",
    "addr:housenumber": "2280",
    "addr:postcode": "45420",
    "addr:street": "E Dorothy Ln",
    "iso:country": "US",
    "sg:address": "2280 E Dorothy Ln",
    "sg:city": "Dayton",
    "sg:classifiers": [
      {
        "category": "Restaurant",
        "type": "Food \u0026 Drink"
      }
    ],
    "sg:menulink": "http://www.allmenus.com/oh/kettering/122374-quiznos-sub/menu/",
    "sg:phone": "+1 937 293 7353",
    "sg:postcode": "45420",
    "sg:province": "OH",
    "sg:tags": [
      "wrap",
      "american",
      "sandwich"
    ],
    "wof:name": "Quiznos Sub",
    "wof:placetype": "venue"
  },
  "geometry": {"coordinates":[-84.121925,39.702187],"type":"Point"}
}
