{
  "type": "Feature",
  "properties": {
    "iso:country":"US",
    "sg:address":"2280 E Dorothy Ln",
    "sg:city":"Dayton",
    "sg:classifiers":[
        {
            "category":"Restaurant",
            "type":"Food & Drink"
        }
    ],
    "sg:menulink":"http://www.allmenus.com/oh/kettering/122374-quiznos-sub/menu/",
    "sg:phone":"+1 937 293 7353",
    "sg:postcode":"45420",
    "sg:province":"OH",
    "sg:tags":[
        "wrap",
        "american",
        "sandwich"
    ],
    "wof:name":"Quiznos Sub",
    "wof:placetype":"venue"
},
  "geometry": {"coordinates":[-84.121925,39.702187],"type":"Point"}
}