{
  "type": "Feature",
  "properties": {
    "addr:full": "1036 Hunters Chase Grafton OH 44044",
    "addr:housenumber": "1036",
    "addr:postcode": "44044",
    "addr:street": "Hunters Chase",
    "iso:country": "US",
    "sg:address": "1036 Hunters Chase",
    "sg:city": "Grafton",
    "sg:classifiers": [
      {
        "category": "Real Estate",
        "subcategory": "Real Estate Agent",
        "type": "Services"
      }
    ],
    "sg:phone": "+1 440 926 7208",
    "sg:postcode": "44044",
    "sg:province": "OH",
    "wof:name": "Chase Real Estate Inc",
    "wof:placetype": "venue"
  },
  "geometry": {"coordinates":[-82.061554,41.289208],"type":"Point"}
}
