{
  "type": "Feature",
  "properties": {
    "addr:full":"1327 W Main St Wilmington OH 45177",
    "addr:housenumber":"1327",
    "addr:postcode":"45177",
    "addr:street":"W Main St",
    "iso:country":"US",
    "sg:address":"1327 W Main St",
    "sg:city":"Wilmington",
    "sg:classifiers":[
        {
            "category":"Home & Garden",
            "subcategory":"Building Materials",
            "type":"Retail Goods"
        }
    ],
    "sg:phone":"+1 937 382 5866",
    "sg:postcode":"45177",
    "sg:province":"OH",
    "sg:tags":[
        "plate",
        "window",
        "contractor",
        "auto",
        "glass"
    ],
    "wof:name":"Wilmington Glass Co",
    "wof:placetype":"venue"
},
  "geometry": {"coordinates":[-83.850224,39.445367],"type":"Point"}
}