{
  "type": "Feature",
  "properties": {
    "iso:country":"US",
    "sg:address":"4141 US Hwy 127",
    "sg:city":"Greenville",
    "sg:classifiers":[
        {
            "category":"Building & Trades",
            "subcategory":"Construction",
            "type":"Services"
        }
    ],
    "sg:phone":"+1 937 548 3134",
    "sg:postcode":"45331",
    "sg:province":"OH",
    "sg:tags":[
        "concrete",
        "general",
        "commercial",
        "new",
        "contractor"
    ],
    "wof:name":"T R Lucas Co Inc",
    "wof:placetype":"venue"
},
  "geometry": {"coordinates":[-84.631083,40.043783],"type":"Point"}
}