{
  "type": "Feature",
  "properties": {
    "addr:full":"1765 Merriman Rd Akron OH 44313",
    "addr:housenumber":"1765",
    "addr:postcode":"44313",
    "addr:street":"Merriman Rd",
    "iso:country":"US",
    "sg:address":"1765 Merriman Rd",
    "sg:city":"Akron",
    "sg:classifiers":[
        {
            "category":"Real Estate",
            "subcategory":"Real Estate Agent",
            "type":"Services"
        }
    ],
    "sg:phone":"+1 330 836 0721",
    "sg:postcode":"44313",
    "sg:province":"OH",
    "sg:tags":[
        "property",
        "management"
    ],
    "wof:name":"Riverview Management Company",
    "wof:placetype":"venue"
},
  "geometry": {"coordinates":[-81.548592,41.133286],"type":"Point"}
}