{
  "type": "Feature",
  "properties": {
    "iso:country":"US",
    "sg:address":"214 S Main St",
    "sg:city":"Fostoria",
    "sg:classifiers":[
        {
            "category":"Autos & Motor Vehicles",
            "subcategory":"Auto Supplies",
            "type":"Retail Goods"
        }
    ],
    "sg:phone":"+1 419 435 6664",
    "sg:postcode":"44830",
    "sg:province":"OH",
    "sg:tags":[
        "tire"
    ],
    "wof:name":"Expert Tire",
    "wof:placetype":"venue"
},
  "geometry": {"coordinates":[-83.413994,41.156465],"type":"Point"}
}