{
  "type": "Feature",
  "properties": {
    "addr:full":"2810 Banwick Rd Columbus OH 43232",
    "addr:housenumber":"2810",
    "addr:postcode":"43232",
    "addr:street":"Banwick Rd",
    "iso:country":"US",
    "sg:address":"2810 Banwick Rd",
    "sg:city":"Columbus",
    "sg:classifiers":[
        {
            "category":"Home & Garden",
            "subcategory":"Building Materials",
            "type":"Retail Goods"
        }
    ],
    "sg:phone":"+1 614 237 4101",
    "sg:postcode":"43232",
    "sg:province":"OH",
    "sg:tags":[
        "granite"
    ],
    "wof:name":"Buckeye Marble And Granite",
    "wof:placetype":"venue"
},
  "geometry": {"coordinates":[-82.92128099999999,39.925971],"type":"Point"}
}