{
  "type": "Feature",
  "properties": {
    "iso:country":"US",
    "sg:address":"4450 Eastgate Blvd",
    "sg:city":"Cincinnati",
    "sg:classifiers":[
        {
            "category":"Health Services",
            "subcategory":"Health Practitioner",
            "type":"Services"
        }
    ],
    "sg:phone":"+1 513 947 0123",
    "sg:postcode":"45245",
    "sg:province":"OH",
    "sg:tags":[
        "therapist",
        "physical"
    ],
    "wof:name":"Oxford Physical Therapy",
    "wof:placetype":"venue"
},
  "geometry": {"coordinates":[-84.27450899999999,39.098168],"type":"Point"}
}