{
  "type": "Feature",
  "properties": {
    "addr:full": "4450 Eastgate Blvd Cincinnati OH 45245",
    "addr:housenumber": "4450",
    "addr:postcode": "45245",
    "addr:street": "Eastgate Blvd",
    "iso:country": "US",
    "sg:address": "4450 Eastgate Blvd",
    "sg:city": "Cincinnati",
    "sg:classifiers": [
      {
        "category": "Health Services",
        "subcategory": "Health Practitioner",
        "type": "Services"
      }
    ],
    "sg:phone": "+1 513 947 0123",
    "sg:postcode": "45245",
    "sg:province": "OH",
    "sg:tags": [
      "therapist",
      "physical"
    ],
    "wof:name": "Oxford Physical Therapy",
    "wof:placetype": "venue"
  },
  "geometry": {"coordinates":[-84.274509,39.098168],"type":"Point"}
}
