{
  "type": "Feature",
  "properties": {
    "addr:full": "8831 State Rte 785 Hillsboro OH 45133",
    "addr:housenumber": "8831",
    "addr:postcode": "45133",
    "addr:street": "State Rte 785",
    "iso:country": "US",
    "sg:address": "8831 State Rte 785",
    "sg:city": "Hillsboro",
    "sg:classifiers": [
      {
        "category": "Social Services",
        "type": "Services"
      }
    ],
    "sg:phone": "+1 937 764 1590",
    "sg:postcode": "45133",
    "sg:province": "OH",
    "sg:tags": [
      "organization",
      "welfare"
    ],
    "wof:name": "Highland County Community",
    "wof:placetype": "venue"
  },
  "geometry": {"coordinates":[-83.558421,39.049415],"type":"Point"}
}
