{
  "type": "Feature",
  "properties": {
    "addr:full": "301 W Main St St Henry OH 45883",
    "addr:housenumber": "301",
    "addr:postcode": "45883",
    "addr:street": "W Main St St",
    "iso:country": "US",
    "sg:address": "301 W Main St",
    "sg:city": "St Henry",
    "sg:classifiers": [
      {
        "category": "Autos \u0026 Motor Vehicles",
        "subcategory": "Fuel \u0026 Gas Station",
        "type": "Retail Goods"
      },
      {
        "category": "Retail",
        "subcategory": "Auto Repair",
        "type": "Services"
      }
    ],
    "sg:phone": "+1 419 678 4166",
    "sg:postcode": "45883",
    "sg:province": "OH",
    "sg:tags": [
      "repairing",
      "automobile",
      "station",
      "gasoline"
    ],
    "wof:name": "Ron's Service",
    "wof:placetype": "venue"
  },
  "geometry": {"coordinates":[-84.643366,40.417803],"type":"Point"}
}
