{
  "type": "Feature",
  "properties": {
    "addr:full": "16891 Farmington Rd West Farmington OH 44491",
    "addr:housenumber": "16891",
    "addr:postcode": "44491",
    "addr:street": "Farmington Rd",
    "iso:country": "US",
    "sg:address": "16891 Farmington Rd",
    "sg:city": "West Farmington",
    "sg:classifiers": [
      {
        "category": "Shopping",
        "subcategory": "Catalog Store",
        "type": "Retail Goods"
      }
    ],
    "sg:phone": "+1 440 548 8799",
    "sg:postcode": "44491",
    "sg:province": "OH",
    "sg:tags": [
      "mail",
      "clocks",
      "watch",
      "order",
      "internet"
    ],
    "wof:name": "Andy H Weaver Inc",
    "wof:placetype": "venue"
  },
  "geometry": {"coordinates":[-81.054884,41.370495],"type":"Point"}
}
