{
  "type": "Feature",
  "properties": {
    "addr:full": "11623 Market St North Lima OH 44452",
    "addr:housenumber": "11623",
    "addr:postcode": "44452",
    "addr:street": "Market St",
    "iso:country": "US",
    "sg:address": "11623 Market St",
    "sg:city": "North Lima",
    "sg:classifiers": [
      {
        "category": "Banks \u0026 Credit Unions",
        "subcategory": "Bank",
        "type": "Services"
      }
    ],
    "sg:phone": "+1 330 747 6088",
    "sg:postcode": "44452",
    "sg:province": "OH",
    "sg:website": "www.skyfi.com",
    "wof:name": "Sky Bank",
    "wof:placetype": "venue"
  },
  "geometry": {"coordinates":[-80.658434,40.948294],"type":"Point"}
}
