{
  "type": "Feature",
  "properties": {
    "addr:full":"231 W 7th St East Liverpool OH 43920",
    "addr:housenumber":"231",
    "addr:postcode":"43920",
    "addr:street":"W 7Th St",
    "iso:country":"US",
    "sg:address":"231 W 7th St",
    "sg:city":"East Liverpool",
    "sg:classifiers":[
        {
            "category":"Health Services",
            "subcategory":"Doctor",
            "type":"Services"
        }
    ],
    "sg:phone":"+1 330 385 2496",
    "sg:postcode":"43920",
    "sg:province":"OH",
    "sg:tags":[
        "physician",
        "surgeon"
    ],
    "wof:name":"Ann K Poriath MD",
    "wof:placetype":"venue"
},
  "geometry": {"coordinates":[-80.581828,40.622078],"type":"Point"}
}