{
  "type": "Feature",
  "properties": {
    "iso:country":"US",
    "sg:address":"250 E Market St",
    "sg:city":"Akron",
    "sg:classifiers":[
        {
            "category":"Professional",
            "type":"Services"
        }
    ],
    "sg:phone":"+1 330 762 7681",
    "sg:postcode":"44308",
    "sg:province":"OH",
    "wof:name":"United Services For All",
    "wof:placetype":"venue"
},
  "geometry": {"coordinates":[-81.507897,41.081632],"type":"Point"}
}