{
  "type": "Feature",
  "properties": {
    "addr:full": "101 E Ohio Ave Rittman OH 44270",
    "addr:housenumber": "101",
    "addr:postcode": "44270",
    "addr:street": "E Ohio Ave",
    "iso:country": "US",
    "sg:address": "101 E Ohio Ave",
    "sg:city": "Rittman",
    "sg:classifiers": [
      {
        "category": "Food \u0026 Beverages",
        "subcategory": "Groceries \u0026 Convenience Stores",
        "type": "Retail Goods"
      }
    ],
    "sg:phone": "+1 330 927 9221",
    "sg:postcode": "44270",
    "sg:province": "OH",
    "wof:name": "Rittman Quick Food Mart",
    "wof:placetype": "venue"
  },
  "geometry": {"coordinates":[-81.777648,40.972865],"type":"Point"}
}
