{
  "type": "Feature",
  "properties": {
    "iso:country":"US",
    "sg:address":"101 E Ohio Ave",
    "sg:city":"Rittman",
    "sg:classifiers":[
        {
            "category":"Food & Beverages",
            "subcategory":"Groceries & Convenience Stores",
            "type":"Retail Goods"
        }
    ],
    "sg:phone":"+1 330 927 9221",
    "sg:postcode":"44270",
    "sg:province":"OH",
    "wof:name":"Rittman Quick Food Mart",
    "wof:placetype":"venue"
},
  "geometry": {"coordinates":[-81.777648,40.972865],"type":"Point"}
}