{
  "type": "Feature",
  "properties": {
    "addr:full":"5091 Co Rd 33A Saint Marys OH 45885",
    "addr:housenumber":"5091;33a",
    "addr:postcode":"45885",
    "addr:street":"Co Rd",
    "iso:country":"US",
    "sg:address":"5091 Co Rd 33A",
    "sg:city":"Saint Marys",
    "sg:classifiers":[
        {
            "category":"Farming",
            "subcategory":"Farm & Veterinary Services",
            "type":"Manufacturing & Wholesale Goods"
        }
    ],
    "sg:phone":"+1 419 394 5432",
    "sg:postcode":"45885",
    "sg:province":"OH",
    "sg:tags":[
        "livestock"
    ],
    "wof:name":"Wilker Poultry Farm",
    "wof:placetype":"venue"
},
  "geometry": {"coordinates":[-84.356443,40.54801],"type":"Point"}
}