{
  "type": "Feature",
  "properties": {
    "iso:country":"US",
    "sg:address":"1025 US Hwy 52",
    "sg:city":"Aberdeen",
    "sg:classifiers":[
        {
            "category":"Restaurant",
            "type":"Food & Drink"
        }
    ],
    "sg:phone":"+1 937 795 2245",
    "sg:postcode":"45101",
    "sg:province":"OH",
    "wof:name":"Brown's Family Restaurant",
    "wof:placetype":"venue"
},
  "geometry": {"coordinates":[-83.765382,38.658046],"type":"Point"}
}