{
  "type": "Feature",
  "properties": {
    "addr:full": "4276 Stonebridge Dr Springfield OH 45504",
    "addr:housenumber": "4276",
    "addr:postcode": "45504",
    "addr:street": "Stonebridge Dr",
    "iso:country": "US",
    "sg:address": "4276 Stonebridge Dr",
    "sg:city": "Springfield",
    "sg:classifiers": [
      {
        "category": "Shopping",
        "type": "Retail Goods"
      }
    ],
    "sg:phone": "+1 937 399 5312",
    "sg:postcode": "45504",
    "sg:province": "OH",
    "sg:tags": [
      "cosmetic",
      "perfume"
    ],
    "sg:website": "www.marykay.com",
    "wof:name": "Mary Kay Cosmetics",
    "wof:placetype": "venue"
  },
  "geometry": {"coordinates":[-83.860944,39.985129],"type":"Point"}
}
