{
  "type": "Feature",
  "properties": {
    "addr:full":"4422 Carver Woods Dr Cincinnati OH 45242",
    "addr:housenumber":"4422",
    "addr:postcode":"45242",
    "addr:street":"Carver Woods Dr",
    "iso:country":"US",
    "sg:address":"4422 Carver Woods Dr",
    "sg:city":"Cincinnati",
    "sg:classifiers":[
        {
            "category":"Professional",
            "subcategory":"Computer Services",
            "type":"Services"
        }
    ],
    "sg:phone":"+1 513 793 8000",
    "sg:postcode":"45242",
    "sg:province":"OH",
    "sg:tags":[
        "consultant"
    ],
    "wof:name":"Accunet Inc",
    "wof:placetype":"venue"
},
  "geometry": {"coordinates":[-84.38666499999999,39.245271],"type":"Point"}
}