{
  "type": "Feature",
  "properties": {
    "addr:full": "2647 Ramsay Rd Cleveland OH 44122",
    "addr:housenumber": "2647",
    "addr:postcode": "44122",
    "addr:street": "Ramsay Rd",
    "iso:country": "US",
    "sg:address": "2647 Ramsay Rd",
    "sg:city": "Cleveland",
    "sg:classifiers": [
      {
        "category": "Professional",
        "subcategory": "Management \u0026 Consulting",
        "type": "Services"
      }
    ],
    "sg:phone": "+1 216 896 9501",
    "sg:postcode": "44122",
    "sg:province": "OH",
    "sg:tags": [
      "personnel",
      "consultant"
    ],
    "wof:name": "Star Personnel",
    "wof:placetype": "venue"
  },
  "geometry": {"coordinates":[-81.495631,41.487634],"type":"Point"}
}
