{
  "type": "Feature",
  "properties": {
    "addr:full": "46167 Pine Hollow Rd Rogers OH 44455",
    "addr:housenumber": "46167",
    "addr:postcode": "44455",
    "addr:street": "Pine Hollow Rd",
    "iso:country": "US",
    "sg:address": "46167 Pine Hollow Rd",
    "sg:city": "Rogers",
    "sg:classifiers": [
      {
        "category": "Retail",
        "subcategory": "Animal Services",
        "type": "Services"
      }
    ],
    "sg:phone": "+1 330 227 3982",
    "sg:postcode": "44455",
    "sg:province": "OH",
    "wof:name": "Trudys Pet Bow-Tique",
    "wof:placetype": "venue"
  },
  "geometry": {"coordinates":[-80.628819,40.78176],"type":"Point"}
}
