{
  "type": "Feature",
  "properties": {
    "addr:full": "7118 Concord Rd Eaton OH 45320",
    "addr:housenumber": "7118",
    "addr:postcode": "45320",
    "addr:street": "Concord Rd",
    "iso:country": "US",
    "sg:address": "7118 Concord Rd",
    "sg:city": "Eaton",
    "sg:classifiers": [
      {
        "category": "Farming",
        "subcategory": "Dairy Farm",
        "type": "Manufacturing \u0026 Wholesale Goods"
      }
    ],
    "sg:phone": "+1 937 456 6038",
    "sg:postcode": "45320",
    "sg:province": "OH",
    "sg:tags": [
      "feedlot",
      "grain",
      "cash",
      "beef",
      "cattle"
    ],
    "wof:name": "Four Mile Farm",
    "wof:placetype": "venue"
  },
  "geometry": {"coordinates":[-84.75601,39.714221],"type":"Point"}
}
