{
  "type": "Feature",
  "properties": {
    "addr:full": "755 Richmond Rd Cleveland OH 44143",
    "addr:housenumber": "755",
    "addr:postcode": "44143",
    "addr:street": "Richmond Rd",
    "iso:country": "US",
    "sg:address": "755 Richmond Rd",
    "sg:city": "Cleveland",
    "sg:classifiers": [
      {
        "category": "Retail",
        "subcategory": "Auto Repair",
        "type": "Services"
      }
    ],
    "sg:phone": "+1 440 449 3334",
    "sg:postcode": "44143",
    "sg:province": "OH",
    "sg:tags": [
      "body",
      "automobile",
      "painting"
    ],
    "wof:name": "Longstreet Auto Body \u0026 Sales",
    "wof:placetype": "venue"
  },
  "geometry": {"coordinates":[-81.497094,41.539546],"type":"Point"}
}
