{
  "type": "Feature",
  "properties": {
    "addr:full":"6150 Oak Tree Blvd Cleveland OH 44131",
    "addr:housenumber":"6150",
    "addr:postcode":"44131",
    "addr:street":"Oak Tree Blvd",
    "iso:country":"US",
    "sg:address":"6150 Oak Tree Blvd",
    "sg:city":"Cleveland",
    "sg:classifiers":[
        {
            "category":"Insurance",
            "subcategory":"Insurance Agent",
            "type":"Services"
        }
    ],
    "sg:phone":"+1 216 447 9187",
    "sg:postcode":"44131",
    "sg:province":"OH",
    "wof:name":"Reliant Claims Office",
    "wof:placetype":"venue"
},
  "geometry": {"coordinates":[-81.66019300000001,41.395503],"type":"Point"}
}