{
  "type": "Feature",
  "properties": {
    "addr:full":"98 Beck Ave Akron OH 44302",
    "addr:housenumber":"98",
    "addr:postcode":"44302",
    "addr:street":"Beck Ave",
    "iso:country":"US",
    "sg:address":"98 Beck Ave",
    "sg:city":"Akron",
    "sg:classifiers":[
        {
            "category":"Shopping",
            "subcategory":"Used Merchandise",
            "type":"Retail Goods"
        }
    ],
    "sg:phone":"+1 330 376 4965",
    "sg:postcode":"44302",
    "sg:province":"OH",
    "wof:name":"Darwin Bearley Antiques",
    "wof:placetype":"venue"
},
  "geometry": {"coordinates":[-81.540192,41.091053],"type":"Point"}
}