{
  "type": "Feature",
  "properties": {
    "addr:full":"701 Yankee Rd Middletown OH 45044",
    "addr:housenumber":"701",
    "addr:postcode":"45044",
    "addr:street":"Yankee Rd",
    "iso:country":"US",
    "sg:address":"701 Yankee Rd",
    "sg:city":"Middletown",
    "sg:classifiers":[
        {
            "category":"Building & Trades",
            "subcategory":"Plumbing",
            "type":"Services"
        }
    ],
    "sg:phone":"+1 513 894 5851",
    "sg:postcode":"45044",
    "sg:province":"OH",
    "sg:tags":[
        "sheet",
        "work",
        "metal",
        "contractor"
    ],
    "wof:name":"Valley Sheet Metal Works Inc",
    "wof:placetype":"venue"
},
  "geometry": {"coordinates":[-84.407674,39.50814],"type":"Point"}
}