{
  "type": "Feature",
  "properties": {
    "addr:full":"260 S Garber Dr Tipp City OH 45371",
    "addr:housenumber":"260",
    "addr:postcode":"45371",
    "addr:street":"S Garber Dr",
    "iso:country":"US",
    "sg:address":"260 S Garber Dr",
    "sg:city":"Tipp City",
    "sg:classifiers":[
        {
            "category":"Government",
            "subcategory":"Office",
            "type":"Public Place"
        }
    ],
    "sg:phone":"+1 937 667 6305",
    "sg:postcode":"45371",
    "sg:province":"OH",
    "sg:tags":[
        "govt",
        "city"
    ],
    "wof:name":"Tipp City Utility Svc",
    "wof:placetype":"venue"
},
  "geometry": {"coordinates":[-84.187669,39.95946],"type":"Point"}
}