{
  "type": "Feature",
  "properties": {
    "addr:full": "300 Shore Dr Lake Milton OH 44429",
    "addr:housenumber": "300",
    "addr:postcode": "44429",
    "addr:street": "Shore Dr",
    "iso:country": "US",
    "sg:address": "300 Shore Dr",
    "sg:city": "Lake Milton",
    "sg:classifiers": [
      {
        "category": "Building \u0026 Trades",
        "subcategory": "Construction",
        "type": "Services"
      }
    ],
    "sg:phone": "+1 330 654 3979",
    "sg:postcode": "44429",
    "sg:province": "OH",
    "sg:tags": [
      "house"
    ],
    "wof:name": "Durig Construction",
    "wof:placetype": "venue"
  },
  "geometry": {"coordinates":[-80.988166,41.095576],"type":"Point"}
}
