{
  "type": "Feature",
  "properties": {
    "addr:full":"2500 Mentzer Rd Convoy OH 45832",
    "addr:postcode":"2500;45832",
    "addr:street":"Mentzer Rd",
    "iso:country":"US",
    "sg:address":"2500 Mentzer Rd",
    "sg:city":"Convoy",
    "sg:phone":"+1 419 749 2432",
    "sg:postcode":"45832",
    "sg:province":"OH",
    "sg:tags":[
        "farm",
        "wheat"
    ],
    "wof:name":"Ray Riley",
    "wof:placetype":"venue"
},
  "geometry": {"coordinates":[-84.76497999999999,40.931767],"type":"Point"}
}