{
  "type": "Feature",
  "properties": {
    "iso:country":"US",
    "sg:address":"5416 Detroit Ave",
    "sg:city":"Cleveland",
    "sg:classifiers":[
        {
            "category":"Manufacturing",
            "subcategory":"Tools & Machinery",
            "type":"Manufacturing & Wholesale Goods"
        }
    ],
    "sg:phone":"+1 216 631 3572",
    "sg:postcode":"44102",
    "sg:province":"OH",
    "sg:tags":[
        "die",
        "industrial",
        "maker",
        "mfg"
    ],
    "wof:name":"I & C Tool & Die Company",
    "wof:placetype":"venue"
},
  "geometry": {"coordinates":[-81.724825,41.485572],"type":"Point"}
}