{
  "type": "Feature",
  "properties": {
    "addr:full": "5416 Detroit Ave Cleveland OH 44102",
    "addr:housenumber": "5416",
    "addr:postcode": "44102",
    "addr:street": "Detroit Ave",
    "iso:country": "US",
    "sg:address": "5416 Detroit Ave",
    "sg:city": "Cleveland",
    "sg:classifiers": [
      {
        "category": "Manufacturing",
        "subcategory": "Tools \u0026 Machinery",
        "type": "Manufacturing \u0026 Wholesale Goods"
      }
    ],
    "sg:phone": "+1 216 631 3572",
    "sg:postcode": "44102",
    "sg:province": "OH",
    "sg:tags": [
      "die",
      "industrial",
      "maker",
      "mfg"
    ],
    "wof:name": "I \u0026 C Tool \u0026 Die Company",
    "wof:placetype": "venue"
  },
  "geometry": {"coordinates":[-81.724825,41.485572],"type":"Point"}
}
