{
  "type": "Feature",
  "properties": {
    "iso:country":"US",
    "sg:address":"1707 Westwood Ave",
    "sg:city":"Cincinnati",
    "sg:classifiers":[
        {
            "category":"Real Estate",
            "subcategory":"Real Estate Agent",
            "type":"Services"
        }
    ],
    "sg:phone":"+1 513 557 3602",
    "sg:postcode":"45214",
    "sg:province":"OH",
    "sg:tags":[
        "cooperative"
    ],
    "wof:name":"Cooperative Janitoral Svc",
    "wof:placetype":"venue"
},
  "geometry": {"coordinates":[-84.556298,39.125152],"type":"Point"}
}