{
  "type": "Feature",
  "properties": {
    "iso:country":"US",
    "sg:address":"771 S 30th St",
    "sg:city":"Heath",
    "sg:classifiers":[
        {
            "category":"Shopping",
            "type":"Retail Goods"
        },
        {
            "category":"Wholesale",
            "subcategory":"Electrical",
            "type":"Manufacturing & Wholesale Goods"
        }
    ],
    "sg:phone":"+1 740 788 8455",
    "sg:postcode":"43056",
    "sg:province":"OH",
    "sg:tags":[
        "electronic",
        "telephone",
        "cellular"
    ],
    "wof:name":"Cellular Connection",
    "wof:placetype":"venue"
},
  "geometry": {"coordinates":[-82.443395,40.030931],"type":"Point"}
}