{
  "type": "Feature",
  "properties": {
    "iso:country":"US",
    "sg:address":"52 Chamberlain St",
    "sg:city":"Delaware",
    "sg:classifiers":[
        {
            "category":"Professional",
            "type":"Services"
        }
    ],
    "sg:phone":"+1 740 363 7630",
    "sg:postcode":"43015",
    "sg:province":"OH",
    "wof:name":"James Clark",
    "wof:placetype":"venue"
},
  "geometry": {"coordinates":[-83.053966,40.304295],"type":"Point"}
}