{
  "type": "Feature",
  "properties": {
    "iso:country":"US",
    "sg:address":"55 E Fir St",
    "sg:city":"New London",
    "sg:classifiers":[
        {
            "category":"Manufacturing",
            "subcategory":"Tools & Machinery",
            "type":"Manufacturing & Wholesale Goods"
        }
    ],
    "sg:phone":"+1 419 929 9013",
    "sg:postcode":"44851",
    "sg:province":"OH",
    "sg:tags":[
        "machine",
        "shop",
        "industrial",
        "mfg"
    ],
    "wof:name":"Mainline Manufacturing",
    "wof:placetype":"venue"
},
  "geometry": {"coordinates":[-82.396815,41.091411],"type":"Point"}
}