{
  "type": "Feature",
  "properties": {
    "addr:full": "55 E Fir St New London OH 44851",
    "addr:housenumber": "55",
    "addr:postcode": "44851",
    "addr:street": "E Fir St",
    "iso:country": "US",
    "sg:address": "55 E Fir St",
    "sg:city": "New London",
    "sg:classifiers": [
      {
        "category": "Manufacturing",
        "subcategory": "Tools \u0026 Machinery",
        "type": "Manufacturing \u0026 Wholesale Goods"
      }
    ],
    "sg:phone": "+1 419 929 9013",
    "sg:postcode": "44851",
    "sg:province": "OH",
    "sg:tags": [
      "machine",
      "shop",
      "industrial",
      "mfg"
    ],
    "wof:name": "Mainline Manufacturing",
    "wof:placetype": "venue"
  },
  "geometry": {"coordinates":[-82.396815,41.091411],"type":"Point"}
}
