{
  "type": "Feature",
  "properties": {
    "addr:full":"6900 Stillmore Dr Englewood OH 45322",
    "addr:housenumber":"6900",
    "addr:postcode":"45322",
    "addr:street":"Stillmore Dr",
    "iso:country":"US",
    "sg:address":"6900 Stillmore Dr",
    "sg:city":"Englewood",
    "sg:classifiers":[
        {
            "category":"Organizations",
            "subcategory":"Religious Organization",
            "type":"Services"
        }
    ],
    "sg:phone":"+1 937 836 3919",
    "sg:postcode":"45322",
    "sg:province":"OH",
    "sg:tags":[
        "clergy"
    ],
    "wof:name":"Donald E Boesel",
    "wof:placetype":"venue"
},
  "geometry": {"coordinates":[-84.296278,39.84757],"type":"Point"}
}