{
  "type": "Feature",
  "properties": {
    "iso:country":"US",
    "sg:address":"2773 Nationwide Pkwy",
    "sg:city":"Brunswick",
    "sg:classifiers":[
        {
            "category":"Wholesale",
            "subcategory":"Hardware",
            "type":"Manufacturing & Wholesale Goods"
        }
    ],
    "sg:phone":"+1 330 558 0030",
    "sg:postcode":"44212",
    "sg:province":"OH",
    "sg:tags":[
        "plumbing",
        "supply"
    ],
    "wof:name":"Curnayn Sales Inc",
    "wof:placetype":"venue"
},
  "geometry": {"coordinates":[-81.786307,41.244524],"type":"Point"}
}