{
  "type": "Feature",
  "properties": {
    "addr:full": "2773 Nationwide Pkwy Brunswick OH 44212",
    "addr:housenumber": "2773",
    "addr:postcode": "44212",
    "addr:street": "Nationwide Pkwy",
    "iso:country": "US",
    "sg:address": "2773 Nationwide Pkwy",
    "sg:city": "Brunswick",
    "sg:classifiers": [
      {
        "category": "Wholesale",
        "subcategory": "Hardware",
        "type": "Manufacturing \u0026 Wholesale Goods"
      }
    ],
    "sg:phone": "+1 330 558 0030",
    "sg:postcode": "44212",
    "sg:province": "OH",
    "sg:tags": [
      "plumbing",
      "supply"
    ],
    "wof:name": "Curnayn Sales Inc",
    "wof:placetype": "venue"
  },
  "geometry": {"coordinates":[-81.786307,41.244524],"type":"Point"}
}
