{
  "type": "Feature",
  "properties": {
    "iso:country":"US",
    "sg:address":"6934 Pine Valley Ln",
    "sg:city":"Westerville",
    "sg:classifiers":[
        {
            "category":"Restaurant",
            "type":"Food & Drink"
        }
    ],
    "sg:phone":"+1 614 882 1787",
    "sg:postcode":"43082",
    "sg:province":"OH",
    "sg:tags":[
        "eating"
    ],
    "wof:name":"Gros Investments Inc",
    "wof:placetype":"venue"
},
  "geometry": {"coordinates":[-82.945983,40.162541],"type":"Point"}
}