{
  "type": "Feature",
  "properties": {
    "addr:full":"7640 Oldfield Rd Crestline OH 44827",
    "addr:housenumber":"7640",
    "addr:postcode":"44827",
    "addr:street":"Oldfield Rd",
    "iso:country":"US",
    "sg:address":"7640 Oldfield Rd",
    "sg:city":"Crestline",
    "sg:classifiers":[
        {
            "category":"Building & Trades",
            "subcategory":"Construction",
            "type":"Services"
        }
    ],
    "sg:phone":"+1 419 683 4378",
    "sg:postcode":"44827",
    "sg:province":"OH",
    "sg:tags":[
        "contractor"
    ],
    "wof:name":"Kelco Builders",
    "wof:placetype":"venue"
},
  "geometry": {"coordinates":[-82.75475900000001,40.799212],"type":"Point"}
}