{
  "type": "Feature",
  "properties": {
    "addr:full": "13334 Lorain Ave Cleveland OH 44111",
    "addr:housenumber": "13334",
    "addr:postcode": "44111",
    "addr:street": "Lorain Ave",
    "iso:country": "US",
    "sg:address": "13334 Lorain Ave",
    "sg:city": "Cleveland",
    "sg:classifiers": [
      {
        "category": "Bars \u0026 Pubs",
        "type": "Food \u0026 Drink"
      },
      {
        "category": "Restaurant",
        "type": "Food \u0026 Drink"
      }
    ],
    "sg:phone": "+1 216 941 6972",
    "sg:postcode": "44111",
    "sg:province": "OH",
    "sg:tags": [
      "eating"
    ],
    "wof:name": "Blarney Stone",
    "wof:placetype": "venue"
  },
  "geometry": {"coordinates":[-81.782828,41.457511],"type":"Point"}
}
