{
  "type": "Feature",
  "properties": {
    "addr:full":"16638 Southland Rd Botkins OH 45306",
    "addr:housenumber":"16638",
    "addr:postcode":"45306",
    "addr:street":"Southland Rd",
    "iso:country":"US",
    "sg:address":"16638 Southland Rd",
    "sg:city":"Botkins",
    "sg:classifiers":[
        {
            "category":"Farming",
            "subcategory":"Dairy Farm",
            "type":"Manufacturing & Wholesale Goods"
        }
    ],
    "sg:phone":"+1 937 693 7515",
    "sg:postcode":"45306",
    "sg:province":"OH",
    "wof:name":"Ronald Marchal",
    "wof:placetype":"venue"
},
  "geometry": {"coordinates":[-84.118765,40.482984],"type":"Point"}
}