{
  "type": "Feature",
  "properties": {
    "addr:full": "35100 Detroit Rd Avon OH 44011",
    "addr:postcode": "35100;44011",
    "addr:street": "Detroit Rd",
    "iso:country": "US",
    "sg:address": "35100 Detroit Rd",
    "sg:city": "Avon",
    "sg:classifiers": [
      {
        "category": "Building \u0026 Trades",
        "subcategory": "Electrical",
        "type": "Services"
      }
    ],
    "sg:phone": "+1 440 937 6697",
    "sg:postcode": "44011",
    "sg:province": "OH",
    "sg:tags": [
      "electric",
      "contractor"
    ],
    "wof:name": "A J Nagel Electric",
    "wof:placetype": "venue"
  },
  "geometry": {"coordinates":[-82.006687,41.455467],"type":"Point"}
}
