{
  "type": "Feature",
  "properties": {
    "addr:full": "69 N South St Wilmington OH 45177",
    "addr:housenumber": "69",
    "addr:postcode": "45177",
    "addr:street": "N South St",
    "iso:country": "US",
    "sg:address": "69 N South St",
    "sg:city": "Wilmington",
    "sg:classifiers": [
      {
        "category": "Government",
        "subcategory": "Office",
        "type": "Public Place"
      }
    ],
    "sg:phone": "+1 937 383 2067",
    "sg:postcode": "45177",
    "sg:province": "OH",
    "sg:tags": [
      "village"
    ],
    "wof:name": "Wilmington Director Of Law",
    "wof:placetype": "venue"
  },
  "geometry": {"coordinates":[-83.828638,39.445549],"type":"Point"}
}
