{
  "type": "Feature",
  "properties": {
    "addr:full": "1006 27th St NE Canton OH 44714",
    "addr:housenumber": "1006",
    "addr:postcode": "44714",
    "addr:street": "27Th St Ne",
    "iso:country": "US",
    "sg:address": "1006 27th St NE",
    "sg:city": "Canton",
    "sg:classifiers": [
      {
        "category": "Shopping",
        "subcategory": "Used Merchandise",
        "type": "Retail Goods"
      }
    ],
    "sg:phone": "+1 330 453 1929",
    "sg:postcode": "44714",
    "sg:province": "OH",
    "wof:name": "Antiques \u0026 Things",
    "wof:placetype": "venue"
  },
  "geometry": {"coordinates":[-81.362711,40.826551],"type":"Point"}
}
