{
  "type": "Feature",
  "properties": {
    "addr:full":"2482 Owlcrest Dr Cincinnati OH 45231",
    "addr:housenumber":"2482",
    "addr:postcode":"45231",
    "addr:street":"Owlcrest Dr",
    "iso:country":"US",
    "sg:address":"2482 Owlcrest Dr",
    "sg:city":"Cincinnati",
    "sg:classifiers":[
        {
            "category":"Wholesale",
            "subcategory":"Electrical",
            "type":"Manufacturing & Wholesale Goods"
        }
    ],
    "sg:phone":"+1 513 742 1845",
    "sg:postcode":"45231",
    "sg:province":"OH",
    "sg:tags":[
        "alarm",
        "burglar",
        "system"
    ],
    "wof:name":"Active Protective Systems",
    "wof:placetype":"venue"
},
  "geometry": {"coordinates":[-84.568253,39.295427],"type":"Point"}
}