{
  "type": "Feature",
  "properties": {
    "addr:full": "37360 French Creek Rd Avon OH 44011",
    "addr:housenumber": "37360",
    "addr:postcode": "44011",
    "addr:street": "French Creek Rd",
    "iso:country": "US",
    "sg:address": "37360 French Creek Rd",
    "sg:city": "Avon",
    "sg:classifiers": [
      {
        "category": "Building \u0026 Trades",
        "subcategory": "Equipment Rental",
        "type": "Services"
      }
    ],
    "sg:phone": "+1 440 934 3736",
    "sg:postcode": "44011",
    "sg:province": "OH",
    "sg:tags": [
      "yard"
    ],
    "wof:name": "Taylor Rental",
    "wof:placetype": "venue"
  },
  "geometry": {"coordinates":[-82.048202,41.452179],"type":"Point"}
}
