{
  "type": "Feature",
  "properties": {
    "iso:country":"US",
    "sg:address":"1622 Indiana Ave",
    "sg:city":"Toledo",
    "sg:classifiers":[
        {
            "category":"Government",
            "subcategory":"Office",
            "type":"Public Place"
        }
    ],
    "sg:phone":"+1 419 255 7221",
    "sg:postcode":"43607",
    "sg:province":"OH",
    "sg:tags":[
        "housing",
        "program"
    ],
    "wof:name":"Kovenient Home Living Inc",
    "wof:placetype":"venue"
},
  "geometry": {"coordinates":[-83.579812,41.650401],"type":"Point"}
}