{
  "type": "Feature",
  "properties": {
    "addr:full": "953 Mount Olive Rd Washington Ct Hs OH 43160",
    "addr:housenumber": "953",
    "addr:postcode": "43160",
    "addr:street": "Mount Olive Rd",
    "iso:country": "US",
    "sg:address": "953 Mount Olive Rd",
    "sg:city": "Washington Ct Hs",
    "sg:classifiers": [
      {
        "category": "Retail",
        "subcategory": "Portrait Studio",
        "type": "Services"
      }
    ],
    "sg:phone": "+1 740 335 7468",
    "sg:postcode": "43160",
    "sg:province": "OH",
    "sg:tags": [
      "photographer"
    ],
    "wof:name": "Photographic Art By Christina",
    "wof:placetype": "venue"
  },
  "geometry": {"coordinates":[-83.494022,39.539453],"type":"Point"}
}
