{
  "type": "Feature",
  "properties": {
    "iso:country":"US",
    "sg:address":"3600 Slaven Rd",
    "sg:city":"Cincinnati",
    "sg:classifiers":[
        {
            "category":"Building & Trades",
            "subcategory":"Construction",
            "type":"Services"
        }
    ],
    "sg:phone":"+1 513 752 7626",
    "sg:postcode":"45245",
    "sg:province":"OH",
    "sg:tags":[
        "house"
    ],
    "wof:name":"Jim Morarity Construction",
    "wof:placetype":"venue"
},
  "geometry": {"coordinates":[-84.28782699999999,39.042096],"type":"Point"}
}