{
  "type": "Feature",
  "properties": {
    "addr:full": "3600 Slaven Rd Cincinnati OH 45245",
    "addr:postcode": "3600;45245",
    "addr:street": "Slaven Rd",
    "iso:country": "US",
    "sg:address": "3600 Slaven Rd",
    "sg:city": "Cincinnati",
    "sg:classifiers": [
      {
        "category": "Building \u0026 Trades",
        "subcategory": "Construction",
        "type": "Services"
      }
    ],
    "sg:phone": "+1 513 752 7626",
    "sg:postcode": "45245",
    "sg:province": "OH",
    "sg:tags": [
      "house"
    ],
    "wof:name": "Jim Morarity Construction",
    "wof:placetype": "venue"
  },
  "geometry": {"coordinates":[-84.287827,39.042096],"type":"Point"}
}
