{
  "type": "Feature",
  "properties": {
    "iso:country":"US",
    "sg:address":"1415 E 222nd St",
    "sg:city":"Cleveland",
    "sg:classifiers":[
        {
            "category":"Shopping",
            "subcategory":"Stationery & Office Supplies",
            "type":"Retail Goods"
        }
    ],
    "sg:phone":"+1 216 531 5311",
    "sg:postcode":"44117",
    "sg:province":"OH",
    "sg:website":"www.euclidoffice.com",
    "wof:name":"Euclid Office Supply Inc",
    "wof:placetype":"venue"
},
  "geometry": {"coordinates":[-81.526595,41.578551],"type":"Point"}
}