{
  "type": "Feature",
  "properties": {
    "addr:full": "1950 W State St Alliance OH 44601",
    "addr:housenumber": "1950",
    "addr:postcode": "44601",
    "addr:street": "W State St",
    "iso:country": "US",
    "sg:address": "1950 W State St",
    "sg:city": "Alliance",
    "sg:classifiers": [
      {
        "category": "Banks \u0026 Credit Unions",
        "subcategory": "Investment Brokerage",
        "type": "Services"
      }
    ],
    "sg:phone": "+1 330 823 1663",
    "sg:postcode": "44601",
    "sg:province": "OH",
    "sg:tags": [
      "advisory",
      "financial"
    ],
    "wof:name": "Buckeye Financial Svc - Allnc",
    "wof:placetype": "venue"
  },
  "geometry": {"coordinates":[-81.140571,40.901832],"type":"Point"}
}
