{
  "type": "Feature",
  "properties": {
    "addr:full": "306 Market St Steubenville OH 43952",
    "addr:housenumber": "306",
    "addr:postcode": "43952",
    "addr:street": "Market St",
    "iso:country": "US",
    "sg:address": "306 Market St",
    "sg:city": "Steubenville",
    "sg:classifiers": [
      {
        "category": "Government",
        "subcategory": "Office",
        "type": "Public Place"
      }
    ],
    "sg:phone": "+1 740 283 6068",
    "sg:postcode": "43952",
    "sg:province": "OH",
    "sg:tags": [
      "city",
      "taxation"
    ],
    "wof:name": "Steubenville Income Tax Dept",
    "wof:placetype": "venue"
  },
  "geometry": {"coordinates":[-80.614201,40.359624],"type":"Point"}
}
