{
  "type": "Feature",
  "properties": {
    "addr:full": "4424 Ethel Rd S Columbus OH 43207",
    "addr:housenumber": "4424",
    "addr:postcode": "43207",
    "addr:street": "Ethel Rd",
    "iso:country": "US",
    "sg:address": "4424 Ethel Rd S",
    "sg:city": "Columbus",
    "sg:classifiers": [
      {
        "category": "Building \u0026 Trades",
        "subcategory": "Construction",
        "type": "Services"
      }
    ],
    "sg:phone": "+1 614 492 1172",
    "sg:postcode": "43207",
    "sg:province": "OH",
    "sg:tags": [
      "hanging",
      "contractor"
    ],
    "wof:name": "Kidwells Kustom Painting",
    "wof:placetype": "venue"
  },
  "geometry": {"coordinates":[-82.93806,39.880241],"type":"Point"}
}
