{
  "type": "Feature",
  "properties": {
    "addr:full":"1571 Doten Ave Columbus OH 43212",
    "addr:housenumber":"1571",
    "addr:postcode":"43212",
    "addr:street":"Doten Ave",
    "iso:country":"US",
    "sg:address":"1571 Doten Ave",
    "sg:city":"Columbus",
    "sg:classifiers":[
        {
            "category":"Organizations",
            "subcategory":"Community Association",
            "type":"Services"
        }
    ],
    "sg:phone":"+1 614 421 1385",
    "sg:postcode":"43212",
    "sg:province":"OH",
    "wof:name":"Alpha PSI Vet Frat",
    "wof:placetype":"venue"
},
  "geometry": {"coordinates":[-83.037755,39.990555],"type":"Point"}
}