{
  "type": "Feature",
  "properties": {
    "iso:country":"US",
    "sg:address":"96 Overlook Dr",
    "sg:city":"Chesapeake",
    "sg:classifiers":[
        {
            "category":"Wholesale",
            "subcategory":"Machinery & Supplies",
            "type":"Manufacturing & Wholesale Goods"
        }
    ],
    "sg:phone":"+1 740 867 4909",
    "sg:postcode":"45619",
    "sg:province":"OH",
    "sg:tags":[
        "farm",
        "equipment"
    ],
    "wof:name":"Wilson's Farm Implement",
    "wof:placetype":"venue"
},
  "geometry": {"coordinates":[-82.436286,38.436095],"type":"Point"}
}