{
  "type": "Feature",
  "properties": {
    "iso:country":"US",
    "sg:address":"11309 Bailey Rd",
    "sg:city":"Vermilion",
    "sg:classifiers":[
        {
            "category":"Shopping",
            "subcategory":"Gifts & Souvenirs",
            "type":"Retail Goods"
        }
    ],
    "sg:phone":"+1 440 967 4052",
    "sg:postcode":"44089",
    "sg:province":"OH",
    "wof:name":"One Of A Kind Ceramics",
    "wof:placetype":"venue"
},
  "geometry": {"coordinates":[-82.424537,41.35787],"type":"Point"}
}