{
  "type": "Feature",
  "properties": {
    "addr:full":"115 Staunton St Piqua OH 45356",
    "addr:housenumber":"115",
    "addr:postcode":"45356",
    "addr:street":"Staunton St",
    "iso:country":"US",
    "sg:address":"115 Staunton St",
    "sg:city":"Piqua",
    "sg:classifiers":[
        {
            "category":"Organizations",
            "subcategory":"Religious Organization",
            "type":"Services"
        }
    ],
    "sg:phone":"+1 937 778 0980",
    "sg:postcode":"45356",
    "sg:province":"OH",
    "sg:tags":[
        "church"
    ],
    "wof:name":"Central Baptist Church",
    "wof:placetype":"venue"
},
  "geometry": {"coordinates":[-84.232399,40.145532],"type":"Point"}
}