{
  "type": "Feature",
  "properties": {
    "iso:country":"US",
    "sg:address":"3171 Moffet Rd",
    "sg:city":"Lucas",
    "sg:phone":"+1 419 892 2809",
    "sg:postcode":"44843",
    "sg:province":"OH",
    "sg:tags":[
        "farm",
        "field",
        "crop"
    ],
    "wof:name":"Marie Au",
    "wof:placetype":"venue"
},
  "geometry": {"coordinates":[-82.41604599999999,40.668725],"type":"Point"}
}