{
  "type": "Feature",
  "properties": {
    "addr:full": "3171 Moffet Rd Lucas OH 44843",
    "addr:housenumber": "3171",
    "addr:postcode": "44843",
    "addr:street": "Moffet Rd",
    "iso:country": "US",
    "sg:address": "3171 Moffet Rd",
    "sg:city": "Lucas",
    "sg:phone": "+1 419 892 2809",
    "sg:postcode": "44843",
    "sg:province": "OH",
    "sg:tags": [
      "farm",
      "field",
      "crop"
    ],
    "wof:name": "Marie Au",
    "wof:placetype": "venue"
  },
  "geometry": {"coordinates":[-82.416046,40.668725],"type":"Point"}
}
