{
  "type": "Feature",
  "properties": {
    "addr:full": "1023 Lynbrook St SE North Canton OH 44720",
    "addr:housenumber": "1023",
    "addr:postcode": "44720",
    "addr:street": "Lynbrook St Se",
    "iso:country": "US",
    "sg:address": "1023 Lynbrook St SE",
    "sg:city": "North Canton",
    "sg:classifiers": [
      {
        "category": "Building \u0026 Trades",
        "subcategory": "Cleaning \u0026 Sanitation",
        "type": "Services"
      }
    ],
    "sg:phone": "+1 330 922 0202",
    "sg:postcode": "44720",
    "sg:province": "OH",
    "sg:tags": [
      "janitor"
    ],
    "wof:name": "A Todd Cleaning Svc",
    "wof:placetype": "venue"
  },
  "geometry": {"coordinates":[-81.386935,40.865679],"type":"Point"}
}
