{
  "type": "Feature",
  "properties": {
    "iso:country":"US",
    "sg:address":"1023 Lynbrook St SE",
    "sg:city":"North Canton",
    "sg:classifiers":[
        {
            "category":"Building & Trades",
            "subcategory":"Cleaning & Sanitation",
            "type":"Services"
        }
    ],
    "sg:phone":"+1 330 922 0202",
    "sg:postcode":"44720",
    "sg:province":"OH",
    "sg:tags":[
        "janitor"
    ],
    "wof:name":"A Todd Cleaning Svc",
    "wof:placetype":"venue"
},
  "geometry": {"coordinates":[-81.38693499999999,40.865679],"type":"Point"}
}