{
  "type": "Feature",
  "properties": {
    "addr:full": "232 W Plane St Bethel OH 45106",
    "addr:housenumber": "232",
    "addr:postcode": "45106",
    "addr:street": "W Plane St",
    "iso:country": "US",
    "sg:address": "232 W Plane St",
    "sg:city": "Bethel",
    "sg:classifiers": [
      {
        "category": "Government",
        "subcategory": "Office",
        "type": "Public Place"
      }
    ],
    "sg:phone": "+1 513 734 7636",
    "sg:postcode": "45106",
    "sg:province": "OH",
    "sg:tags": [
      "armed",
      "force",
      "recruiting"
    ],
    "wof:name": "US Army Recruiting",
    "wof:placetype": "venue"
  },
  "geometry": {"coordinates":[-84.080098,38.96359],"type":"Point"}
}
