{
  "type": "Feature",
  "properties": {
    "addr:full": "7776 Montgomery Rd Cincinnati OH 45236",
    "addr:housenumber": "7776",
    "addr:postcode": "45236",
    "addr:street": "Montgomery Rd",
    "iso:country": "US",
    "sg:address": "7776 Montgomery Rd",
    "sg:city": "Cincinnati",
    "sg:classifiers": [
      {
        "category": "Autos \u0026 Motor Vehicles",
        "subcategory": "Auto Supplies",
        "type": "Retail Goods"
      },
      {
        "category": "Retail",
        "subcategory": "Auto Repair",
        "type": "Services"
      }
    ],
    "sg:phone": "+1 513 793 1711",
    "sg:postcode": "45236",
    "sg:province": "OH",
    "sg:tags": [
      "oil",
      "automotive",
      "automobile",
      "lube",
      "equipment-service",
      "air conditioning",
      "tune"
    ],
    "sg:website": "http://www.jiffylube.com",
    "wof:name": "Jiffy Lube",
    "wof:placetype": "venue"
  },
  "geometry": {"coordinates":[-84.382365,39.198246],"type":"Point"}
}
