{
  "type": "Feature",
  "properties": {
    "addr:full":"101 S Wayne St Fort Recovery OH 45846",
    "addr:housenumber":"101",
    "addr:postcode":"45846",
    "addr:street":"S Wayne St",
    "iso:country":"US",
    "sg:address":"101 S Wayne St",
    "sg:city":"Fort Recovery",
    "sg:classifiers":[
        {
            "category":"Home & Garden",
            "subcategory":"Household Appliances",
            "type":"Retail Goods"
        }
    ],
    "sg:phone":"+1 419 375 4866",
    "sg:postcode":"45846",
    "sg:province":"OH",
    "wof:name":"Brockman Appliances",
    "wof:placetype":"venue"
},
  "geometry": {"coordinates":[-84.779735,40.41241],"type":"Point"}
}