{
  "type": "Feature",
  "properties": {
    "addr:full": "9900 Washington St Chagrin Falls OH 44023",
    "addr:housenumber": "9900",
    "addr:postcode": "44023",
    "addr:street": "Washington St",
    "iso:country": "US",
    "sg:address": "9900 Washington St",
    "sg:city": "Chagrin Falls",
    "sg:classifiers": [
      {
        "category": "Restaurant",
        "type": "Food \u0026 Drink"
      }
    ],
    "sg:phone": "+1 440 543 7359",
    "sg:postcode": "44023",
    "sg:province": "OH",
    "sg:tags": [
      "barbeque"
    ],
    "sg:website": "www.thefireplaceconnection.net",
    "wof:name": "The Fireplace Connection Llc",
    "wof:placetype": "venue"
  },
  "geometry": {"coordinates":[-81.289298,41.3928],"type":"Point"}
}
