{
  "type": "Feature",
  "properties": {
    "addr:full": "4025 Lisa Dr Tipp City OH 45371",
    "addr:housenumber": "4025",
    "addr:postcode": "45371",
    "addr:street": "Lisa Dr",
    "iso:country": "US",
    "sg:address": "4025 Lisa Dr",
    "sg:city": "Tipp City",
    "sg:classifiers": [
      {
        "category": "Wholesale",
        "subcategory": "Non-durable Goods",
        "type": "Manufacturing \u0026 Wholesale Goods"
      }
    ],
    "sg:phone": "+1 937 256 1600",
    "sg:postcode": "45371",
    "sg:province": "OH",
    "sg:tags": [
      "advertising"
    ],
    "wof:name": "KIDD International Design",
    "wof:placetype": "venue"
  },
  "geometry": {"coordinates":[-84.143676,39.889878],"type":"Point"}
}
