{
  "type": "Feature",
  "properties": {
    "addr:full":"1267 Dueber Ave SW Canton OH 44706",
    "addr:housenumber":"1267",
    "addr:postcode":"44706",
    "addr:street":"Dueber Ave Sw",
    "iso:country":"US",
    "sg:address":"1267 Dueber Ave SW",
    "sg:city":"Canton",
    "sg:classifiers":[
        {
            "category":"Retail",
            "subcategory":"Repair Shop",
            "type":"Services"
        }
    ],
    "sg:phone":"+1 330 453 8077",
    "sg:postcode":"44706",
    "sg:province":"OH",
    "sg:tags":[
        "small",
        "appliance",
        "electric"
    ],
    "wof:name":"Appliance Parts Co",
    "wof:placetype":"venue"
},
  "geometry": {"coordinates":[-81.39461300000001,40.788409],"type":"Point"}
}