{
  "type": "Feature",
  "properties": {
    "iso:country":"US",
    "sg:address":"2818 Twp Rd 56",
    "sg:city":"Bellefontaine",
    "sg:classifiers":[
        {
            "category":"Building & Trades",
            "subcategory":"Construction",
            "type":"Services"
        }
    ],
    "sg:phone":"+1 937 599 5228",
    "sg:postcode":"43311",
    "sg:province":"OH",
    "sg:tags":[
        "excavation",
        "contractor"
    ],
    "wof:name":"Frederick Thomas Excavating",
    "wof:placetype":"venue"
},
  "geometry": {"coordinates":[-83.769455,40.3959],"type":"Point"}
}