{
  "type": "Feature",
  "properties": {
    "iso:country":"US",
    "sg:address":"1133 Lyn Rd",
    "sg:city":"Bowling Green",
    "sg:classifiers":[
        {
            "category":"Insurance",
            "subcategory":"Insurance Agent",
            "type":"Services"
        }
    ],
    "sg:phone":"+1 419 255 4713",
    "sg:postcode":"43402",
    "sg:province":"OH",
    "wof:name":"McD Real Estate Inc",
    "wof:placetype":"venue"
},
  "geometry": {"coordinates":[-83.670559,41.369338],"type":"Point"}
}