{
  "type": "Feature",
  "properties": {
    "addr:full":"339 N Columbus St Lancaster OH 43130",
    "addr:housenumber":"339",
    "addr:postcode":"43130",
    "addr:street":"N Columbus St",
    "iso:country":"US",
    "sg:address":"339 N Columbus St",
    "sg:city":"Lancaster",
    "sg:classifiers":[
        {
            "category":"Shopping",
            "type":"Retail Goods"
        }
    ],
    "sg:phone":"+1 740 654 9300",
    "sg:postcode":"43130",
    "sg:province":"OH",
    "sg:tags":[
        "picture",
        "frame"
    ],
    "wof:name":"Frame Shop",
    "wof:placetype":"venue"
},
  "geometry": {"coordinates":[-82.60453699999999,39.716419],"type":"Point"}
}