{
  "type": "Feature",
  "properties": {
    "addr:full": "7401 Benderson Dr Westerville OH 43082",
    "addr:housenumber": "7401",
    "addr:postcode": "43082",
    "addr:street": "Benderson Dr",
    "iso:country": "US",
    "sg:address": "7401 Benderson Dr",
    "sg:city": "Westerville",
    "sg:classifiers": [
      {
        "category": "Freight",
        "type": "Transportation"
      }
    ],
    "sg:phone": "+1 614 899 9325",
    "sg:postcode": "43082",
    "sg:province": "OH",
    "wof:name": "UTI World Wide",
    "wof:placetype": "venue"
  },
  "geometry": {"coordinates":[-82.893149,40.148776],"type":"Point"}
}
