{
  "type": "Feature",
  "properties": {
    "iso:country":"US",
    "sg:address":"7401 Benderson Dr",
    "sg:city":"Westerville",
    "sg:classifiers":[
        {
            "category":"Freight",
            "type":"Transportation"
        }
    ],
    "sg:phone":"+1 614 899 9325",
    "sg:postcode":"43082",
    "sg:province":"OH",
    "wof:name":"UTI World Wide",
    "wof:placetype":"venue"
},
  "geometry": {"coordinates":[-82.89314899999999,40.148776],"type":"Point"}
}