{
  "type": "Feature",
  "properties": {
    "addr:full": "1479 W 112th St Cleveland OH 44102",
    "addr:housenumber": "1479",
    "addr:postcode": "44102",
    "addr:street": "W 112Th St",
    "iso:country": "US",
    "sg:address": "1479 W 112th St",
    "sg:city": "Cleveland",
    "sg:classifiers": [
      {
        "category": "Retail",
        "subcategory": "Car Wash",
        "type": "Services"
      }
    ],
    "sg:phone": "+1 216 226 3062",
    "sg:postcode": "44102",
    "sg:province": "OH",
    "sg:tags": [
      "automobile",
      "detail",
      "clean"
    ],
    "wof:name": "Car Detailing Shop",
    "wof:placetype": "venue"
  },
  "geometry": {"coordinates":[-81.764846,41.47984],"type":"Point"}
}
