{
  "type": "Feature",
  "properties": {
    "iso:country":"US",
    "sg:address":"1584 Harding Hwy W",
    "sg:city":"Marion",
    "sg:classifiers":[
        {
            "category":"Freight",
            "type":"Transportation"
        },
        {
            "category":"Utilities",
            "subcategory":"Refuse",
            "type":"Services"
        }
    ],
    "sg:phone":"+1 740 375 6358",
    "sg:postcode":"43302",
    "sg:province":"OH",
    "sg:tags":[
        "operator",
        "local",
        "garbage",
        "collection",
        "trucking"
    ],
    "wof:name":"K C Rubbish Hauling",
    "wof:placetype":"venue"
},
  "geometry": {"coordinates":[-83.182361,40.610832],"type":"Point"}
}