{
  "type": "Feature",
  "properties": {
    "iso:country":"US",
    "sg:address":"4560 Willow Pkwy",
    "sg:city":"Cleveland",
    "sg:classifiers":[
        {
            "category":"Wholesale",
            "subcategory":"Machinery & Supplies",
            "type":"Manufacturing & Wholesale Goods"
        },
        {
            "category":"Building & Trades",
            "subcategory":"Construction",
            "type":"Services"
        }
    ],
    "sg:phone":"+1 216 883 7649",
    "sg:postcode":"44125",
    "sg:province":"OH",
    "sg:tags":[
        "deck",
        "equipment",
        "restoration",
        "cleaning",
        "establishment",
        "patio"
    ],
    "wof:name":"Jordan Power Equipment Co",
    "wof:placetype":"venue"
},
  "geometry": {"coordinates":[-81.650858,41.435575],"type":"Point"}
}