{
  "type": "Feature",
  "properties": {
    "addr:full": "4560 Willow Pkwy Cleveland OH 44125",
    "addr:housenumber": "4560",
    "addr:postcode": "44125",
    "addr:street": "Willow Pkwy",
    "iso:country": "US",
    "sg:address": "4560 Willow Pkwy",
    "sg:city": "Cleveland",
    "sg:classifiers": [
      {
        "category": "Wholesale",
        "subcategory": "Machinery \u0026 Supplies",
        "type": "Manufacturing \u0026 Wholesale Goods"
      },
      {
        "category": "Building \u0026 Trades",
        "subcategory": "Construction",
        "type": "Services"
      }
    ],
    "sg:phone": "+1 216 883 7649",
    "sg:postcode": "44125",
    "sg:province": "OH",
    "sg:tags": [
      "deck",
      "equipment",
      "restoration",
      "cleaning",
      "establishment",
      "patio"
    ],
    "wof:name": "Jordan Power Equipment Co",
    "wof:placetype": "venue"
  },
  "geometry": {"coordinates":[-81.650858,41.435575],"type":"Point"}
}
