{
  "type": "Feature",
  "properties": {
    "iso:country":"US",
    "sg:address":"1015 Central Ave",
    "sg:city":"Middletown",
    "sg:classifiers":[
        {
            "category":"Professional",
            "type":"Services"
        }
    ],
    "sg:phone":"+1 513 424 2259",
    "sg:postcode":"45044",
    "sg:province":"OH",
    "sg:tags":[
        "establishment"
    ],
    "wof:name":"Rumford Productions",
    "wof:placetype":"venue"
},
  "geometry": {"coordinates":[-84.403792,39.516614],"type":"Point"}
}