{
  "type": "Feature",
  "properties": {
    "iso:country":"US",
    "sg:address":"4170 Belden Village St NW",
    "sg:city":"Canton",
    "sg:classifiers":[
        {
            "category":"Shopping",
            "subcategory":"Gifts & Souvenirs",
            "type":"Retail Goods"
        }
    ],
    "sg:phone":"+1 330 494 9355",
    "sg:postcode":"44718",
    "sg:province":"OH",
    "wof:name":"Carlton Cards Retail Inc",
    "wof:placetype":"venue"
},
  "geometry": {"coordinates":[-81.423607,40.855043],"type":"Point"}
}