{
  "type": "Feature",
  "properties": {
    "iso:country":"US",
    "sg:address":"4726 Creek Rd",
    "sg:city":"Cincinnati",
    "sg:classifiers":[
        {
            "category":"Wholesale",
            "subcategory":"Stationery",
            "type":"Manufacturing & Wholesale Goods"
        }
    ],
    "sg:phone":"+1 513 791 3676",
    "sg:postcode":"45242",
    "sg:province":"OH",
    "sg:tags":[
        "business",
        "form",
        "system"
    ],
    "wof:name":"OEI Business Forms",
    "wof:placetype":"venue"
},
  "geometry": {"coordinates":[-84.377213,39.258437],"type":"Point"}
}