{
  "type": "Feature",
  "properties": {
    "iso:country":"US",
    "sg:address":"22081 State Rte 51",
    "sg:city":"Genoa",
    "sg:classifiers":[
        {
            "category":"Shopping",
            "subcategory":"Discount & Variety Stores",
            "type":"Retail Goods"
        }
    ],
    "sg:phone":"+1 419 855 1080",
    "sg:postcode":"43430",
    "sg:province":"OH",
    "wof:name":"Dollar General",
    "wof:placetype":"venue"
},
  "geometry": {"coordinates":[-83.359572,41.531962],"type":"Point"}
}