{
  "type": "Feature",
  "properties": {
    "iso:country":"US",
    "sg:address":"2219 W Windsor Rd",
    "sg:city":"Orwell",
    "sg:classifiers":[
        {
            "category":"Professional",
            "subcategory":"Accounting & Tax Preparation",
            "type":"Services"
        }
    ],
    "sg:phone":"+1 440 437 8838",
    "sg:postcode":"44076",
    "sg:province":"OH",
    "sg:tags":[
        "return",
        "filing"
    ],
    "wof:name":"Herbster's Tax Svc",
    "wof:placetype":"venue"
},
  "geometry": {"coordinates":[-80.81992099999999,41.556847],"type":"Point"}
}