{
  "type": "Feature",
  "properties": {
    "addr:full": "2219 W Windsor Rd Orwell OH 44076",
    "addr:housenumber": "2219",
    "addr:postcode": "44076",
    "addr:street": "W Windsor Rd",
    "iso:country": "US",
    "sg:address": "2219 W Windsor Rd",
    "sg:city": "Orwell",
    "sg:classifiers": [
      {
        "category": "Professional",
        "subcategory": "Accounting \u0026 Tax Preparation",
        "type": "Services"
      }
    ],
    "sg:phone": "+1 440 437 8838",
    "sg:postcode": "44076",
    "sg:province": "OH",
    "sg:tags": [
      "return",
      "filing"
    ],
    "wof:name": "Herbster's Tax Svc",
    "wof:placetype": "venue"
  },
  "geometry": {"coordinates":[-80.819921,41.556847],"type":"Point"}
}
