{
  "type": "Feature",
  "properties": {
    "addr:full": "18235 Quinn Rd Chagrin Falls OH 44023",
    "addr:housenumber": "18235",
    "addr:postcode": "44023",
    "addr:street": "Quinn Rd",
    "iso:country": "US",
    "sg:address": "18235 Quinn Rd",
    "sg:city": "Chagrin Falls",
    "sg:classifiers": [
      {
        "category": "Restaurant",
        "type": "Food \u0026 Drink"
      }
    ],
    "sg:phone": "+1 440 834 1111",
    "sg:postcode": "44023",
    "sg:province": "OH",
    "sg:tags": [
      "barbecue"
    ],
    "wof:name": "Blazin Bill's",
    "wof:placetype": "venue"
  },
  "geometry": {"coordinates":[-81.289625,41.36628],"type":"Point"}
}
