{
  "type": "Feature",
  "properties": {
    "addr:full": "1353 E 260th St Cleveland OH 44132",
    "addr:housenumber": "1353",
    "addr:postcode": "44132",
    "addr:street": "E 260Th St",
    "iso:country": "US",
    "sg:address": "1353 E 260th St",
    "sg:city": "Cleveland",
    "sg:classifiers": [
      {
        "category": "Wholesale",
        "subcategory": "Electrical",
        "type": "Manufacturing \u0026 Wholesale Goods"
      }
    ],
    "sg:phone": "+1 216 731 4000",
    "sg:postcode": "44132",
    "sg:province": "OH",
    "sg:tags": [
      "control",
      "security",
      "system"
    ],
    "wof:name": "Premier Security",
    "wof:placetype": "venue"
  },
  "geometry": {"coordinates":[-81.50276,41.593554],"type":"Point"}
}
