{
  "type": "Feature",
  "properties": {
    "addr:full": "5535 Dressler Rd NW North Canton OH 44720",
    "addr:postcode": "5535;44720",
    "addr:street": "Dressler Rd Nw",
    "iso:country": "US",
    "sg:address": "5535 Dressler Rd NW",
    "sg:city": "North Canton",
    "sg:classifiers": [
      {
        "category": "Sports \u0026 Exercise",
        "subcategory": "Gym",
        "type": "Entertainment"
      }
    ],
    "sg:phone": "+1 330 499 9500",
    "sg:postcode": "44720",
    "sg:province": "OH",
    "sg:tags": [
      "club",
      "health",
      "studio",
      "gymnasium"
    ],
    "wof:name": "Taebo Training Ctr",
    "wof:placetype": "venue"
  },
  "geometry": {"coordinates":[-81.432588,40.860116],"type":"Point"}
}
