{
  "type": "Feature",
  "properties": {
    "iso:country":"US",
    "sg:address":"22 Gordon Rd",
    "sg:city":"Springfield",
    "sg:classifiers":[
        {
            "category":"Building & Trades",
            "subcategory":"Landscaping Services",
            "type":"Services"
        }
    ],
    "sg:phone":"+1 937 324 1241",
    "sg:postcode":"45504",
    "sg:province":"OH",
    "sg:tags":[
        "lawn",
        "maintenance",
        "grounds"
    ],
    "wof:name":"Mowerdown Lawn Svc",
    "wof:placetype":"venue"
},
  "geometry": {"coordinates":[-83.89959500000001,39.926503],"type":"Point"}
}