{
  "type": "Feature",
  "properties": {
    "addr:full": "22 Gordon Rd Springfield OH 45504",
    "addr:housenumber": "22",
    "addr:postcode": "45504",
    "addr:street": "Gordon Rd",
    "iso:country": "US",
    "sg:address": "22 Gordon Rd",
    "sg:city": "Springfield",
    "sg:classifiers": [
      {
        "category": "Building \u0026 Trades",
        "subcategory": "Landscaping Services",
        "type": "Services"
      }
    ],
    "sg:phone": "+1 937 324 1241",
    "sg:postcode": "45504",
    "sg:province": "OH",
    "sg:tags": [
      "lawn",
      "maintenance",
      "grounds"
    ],
    "wof:name": "Mowerdown Lawn Svc",
    "wof:placetype": "venue"
  },
  "geometry": {"coordinates":[-83.899595,39.926503],"type":"Point"}
}
