{
  "type": "Feature",
  "properties": {
    "addr:full":"3800 Lee Rd Cleveland OH 44128",
    "addr:housenumber":"3800",
    "addr:postcode":"44128",
    "addr:street":"Lee Rd",
    "iso:country":"US",
    "sg:address":"3800 Lee Rd",
    "sg:city":"Cleveland",
    "sg:classifiers":[
        {
            "category":"Retail",
            "subcategory":"Auto Repair",
            "type":"Services"
        }
    ],
    "sg:phone":"+1 216 921 1756",
    "sg:postcode":"44128",
    "sg:province":"OH",
    "sg:tags":[
        "repairing",
        "automobile"
    ],
    "wof:name":"Pete's Auto Body",
    "wof:placetype":"venue"
},
  "geometry": {"coordinates":[-81.56496199999999,41.456492],"type":"Point"}
}