{
  "type": "Feature",
  "properties": {
    "addr:full": "957 Pavillion St Cincinnati OH 45202",
    "addr:housenumber": "957",
    "addr:postcode": "45202",
    "addr:street": "Pavillion St",
    "iso:country": "US",
    "sg:address": "957 Pavillion St",
    "sg:city": "Cincinnati",
    "sg:classifiers": [
      {
        "category": "Professional",
        "subcategory": "Management \u0026 Consulting",
        "type": "Services"
      }
    ],
    "sg:phone": "+1 513 421 2763",
    "sg:postcode": "45202",
    "sg:province": "OH",
    "sg:tags": [
      "consultant",
      "business"
    ],
    "wof:name": "Bluestone Creative",
    "wof:placetype": "venue"
  },
  "geometry": {"coordinates":[-84.496183,39.107572],"type":"Point"}
}
