{
  "type": "Feature",
  "properties": {
    "addr:full":"203 Cline St Norwalk OH 44857",
    "addr:housenumber":"203",
    "addr:postcode":"44857",
    "addr:street":"Cline St",
    "iso:country":"US",
    "sg:address":"203 Cline St",
    "sg:city":"Norwalk",
    "sg:classifiers":[
        {
            "category":"Restaurant",
            "type":"Food & Drink"
        }
    ],
    "sg:menulink":"http://www.allmenus.com/oh/norwalk/114093-sugarcreek-restaurant/menu/",
    "sg:phone":"+1 419 663 3555",
    "sg:postcode":"44857",
    "sg:province":"OH",
    "sg:tags":[
        "american"
    ],
    "wof:name":"Sugarcreek Restaurant",
    "wof:placetype":"venue"
},
  "geometry": {"coordinates":[-82.612314,41.257799],"type":"Point"}
}