{
  "type": "Feature",
  "properties": {
    "addr:full": "404 Maple St Warsaw OH 43844",
    "addr:housenumber": "404",
    "addr:postcode": "43844",
    "addr:street": "Maple St",
    "iso:country": "US",
    "sg:address": "404 Maple St",
    "sg:city": "Warsaw",
    "sg:classifiers": [
      {
        "category": "Utilities",
        "subcategory": "Refuse",
        "type": "Services"
      }
    ],
    "sg:phone": "+1 740 824 3827",
    "sg:postcode": "43844",
    "sg:province": "OH",
    "sg:tags": [
      "garbage",
      "collection"
    ],
    "wof:name": "Skip's Refuse Svc",
    "wof:placetype": "venue"
  },
  "geometry": {"coordinates":[-82.003995,40.338999],"type":"Point"}
}
