{
  "type": "Feature",
  "properties": {
    "iso:country":"US",
    "sg:address":"910 N 2nd St",
    "sg:city":"Coldwater",
    "sg:classifiers":[
        {
            "category":"Home & Garden",
            "subcategory":"Garden Supply",
            "type":"Retail Goods"
        }
    ],
    "sg:phone":"+1 419 678 2698",
    "sg:postcode":"45828",
    "sg:province":"OH",
    "sg:tags":[
        "motorcycle",
        "boat"
    ],
    "wof:name":"Raffels Engine Service",
    "wof:placetype":"venue"
},
  "geometry": {"coordinates":[-84.62881299999999,40.489432],"type":"Point"}
}