{
  "type": "Feature",
  "properties": {
    "addr:full":"405 Beaumont Dr Akron OH 44333",
    "addr:housenumber":"405",
    "addr:postcode":"44333",
    "addr:street":"Beaumont Dr",
    "iso:country":"US",
    "sg:address":"405 Beaumont Dr",
    "sg:city":"Akron",
    "sg:classifiers":[
        {
            "category":"Food & Beverages",
            "subcategory":"Groceries & Convenience Stores",
            "type":"Retail Goods"
        }
    ],
    "sg:phone":"+1 330 666 2785",
    "sg:postcode":"44333",
    "sg:province":"OH",
    "wof:name":"Laurenwest Market Solutns",
    "wof:placetype":"venue"
},
  "geometry": {"coordinates":[-81.62718,41.125338],"type":"Point"}
}