{
  "type": "Feature",
  "properties": {
    "iso:country":"US",
    "sg:address":"30753 Lake Logan Rd",
    "sg:city":"Logan",
    "sg:classifiers":[
        {
            "category":"Home & Garden",
            "subcategory":"Furniture",
            "type":"Retail Goods"
        }
    ],
    "sg:phone":"+1 740 385 3183",
    "sg:postcode":"43138",
    "sg:province":"OH",
    "sg:tags":[
        "household",
        "appliance"
    ],
    "wof:name":"Frazier's Home Furnishings",
    "wof:placetype":"venue"
},
  "geometry": {"coordinates":[-82.449194,39.540626],"type":"Point"}
}