{
  "type": "Feature",
  "properties": {
    "addr:full":"49435 Lighthouse Rd Racine OH 45771",
    "addr:housenumber":"49435",
    "addr:postcode":"45771",
    "addr:street":"Lighthouse Rd",
    "iso:country":"US",
    "sg:address":"49435 Lighthouse Rd",
    "sg:city":"Racine",
    "sg:phone":"+1 740 247 3421",
    "sg:postcode":"45771",
    "sg:province":"OH",
    "sg:tags":[
        "farm"
    ],
    "wof:name":"Morris Farm",
    "wof:placetype":"venue"
},
  "geometry": {"coordinates":[-81.924362,38.8925],"type":"Point"}
}