{
  "type": "Feature",
  "properties": {
    "addr:full":"6828 Market St Youngstown OH 44512",
    "addr:housenumber":"6828",
    "addr:postcode":"44512",
    "addr:street":"Market St",
    "iso:country":"US",
    "sg:address":"6828 Market St",
    "sg:city":"Youngstown",
    "sg:classifiers":[
        {
            "category":"Shopping",
            "subcategory":"Clothing, Apparel, & Fashions",
            "type":"Retail Goods"
        }
    ],
    "sg:phone":"+1 330 758 0973",
    "sg:postcode":"44512",
    "sg:province":"OH",
    "wof:name":"Eagle Uniforms Inc",
    "wof:placetype":"venue"
},
  "geometry": {"coordinates":[-80.662825,41.029422],"type":"Point"}
}