{
  "type": "Feature",
  "properties": {
    "iso:country":"US",
    "sg:address":"14991 Madison Rd",
    "sg:city":"Middlefield",
    "sg:classifiers":[
        {
            "category":"Personal",
            "subcategory":"Beauty Salon",
            "type":"Services"
        }
    ],
    "sg:phone":"+1 440 632 0757",
    "sg:postcode":"44062",
    "sg:province":"OH",
    "sg:tags":[
        "shop",
        "barber"
    ],
    "wof:name":"Hair X-Plosion",
    "wof:placetype":"venue"
},
  "geometry": {"coordinates":[-81.051212,41.46066],"type":"Point"}
}