{
  "type": "Feature",
  "properties": {
    "addr:full":"305 Linden Ave Zanesville OH 43701",
    "addr:housenumber":"305",
    "addr:postcode":"43701",
    "addr:street":"Linden Ave",
    "iso:country":"US",
    "sg:address":"305 Linden Ave",
    "sg:city":"Zanesville",
    "sg:classifiers":[
        {
            "category":"Wholesale",
            "subcategory":"Hardware",
            "type":"Manufacturing & Wholesale Goods"
        }
    ],
    "sg:phone":"+1 740 450 2972",
    "sg:postcode":"43701",
    "sg:province":"OH",
    "sg:tags":[
        "plumbing"
    ],
    "wof:name":"Zanesville Winnelson Co",
    "wof:placetype":"venue"
},
  "geometry": {"coordinates":[-82.014172,39.941865],"type":"Point"}
}