{
  "type": "Feature",
  "properties": {
    "iso:country":"US",
    "sg:address":"22 E Sunset Dr",
    "sg:city":"Rittman",
    "sg:classifiers":[
        {
            "category":"Personal",
            "subcategory":"Barber",
            "type":"Services"
        }
    ],
    "sg:phone":"+1 330 925 6971",
    "sg:postcode":"44270",
    "sg:province":"OH",
    "wof:name":"Bill's Hair Design",
    "wof:placetype":"venue"
},
  "geometry": {"coordinates":[-81.781523,40.97795],"type":"Point"}
}