{
  "type": "Feature",
  "properties": {
    "addr:full": "694 E 200th St Cleveland OH 44119",
    "addr:housenumber": "694",
    "addr:postcode": "44119",
    "addr:street": "E 200Th St",
    "iso:country": "US",
    "sg:address": "694 E 200th St",
    "sg:city": "Cleveland",
    "sg:classifiers": [
      {
        "category": "Professional",
        "type": "Services"
      }
    ],
    "sg:phone": "+1 216 486 9054",
    "sg:postcode": "44119",
    "sg:province": "OH",
    "wof:name": "Aerodesic Dome LLC",
    "wof:placetype": "venue"
  },
  "geometry": {"coordinates":[-81.540265,41.588967],"type":"Point"}
}
