{
  "type": "Feature",
  "properties": {
    "addr:full":"30 Graceland Blvd Columbus OH 43214",
    "addr:housenumber":"30",
    "addr:postcode":"43214",
    "addr:street":"Graceland Blvd",
    "iso:country":"US",
    "sg:address":"30 Graceland Blvd",
    "sg:city":"Columbus",
    "sg:classifiers":[
        {
            "category":"Restaurant",
            "type":"Food & Drink"
        }
    ],
    "sg:phone":"+1 614 433 0750",
    "sg:postcode":"43214",
    "sg:province":"OH",
    "sg:tags":[
        "eating"
    ],
    "wof:name":"Taco Bell",
    "wof:placetype":"venue"
},
  "geometry": {"coordinates":[-83.023478,40.066002],"type":"Point"}
}