{
  "type": "Feature",
  "properties": {
    "addr:full": "851 Broadview Dr Fairfield OH 45014",
    "addr:housenumber": "851",
    "addr:postcode": "45014",
    "addr:street": "Broadview Dr",
    "iso:country": "US",
    "sg:address": "851 Broadview Dr",
    "sg:city": "Fairfield",
    "sg:classifiers": [
      {
        "category": "Real Estate",
        "subcategory": "Real Estate Operator",
        "type": "Services"
      }
    ],
    "sg:phone": "+1 513 829 3696",
    "sg:postcode": "45014",
    "sg:province": "OH",
    "sg:tags": [
      "building",
      "nonresidential"
    ],
    "wof:name": "BBC Venture Properties LLC",
    "wof:placetype": "venue"
  },
  "geometry": {"coordinates":[-84.552526,39.331788],"type":"Point"}
}
