{
  "type": "Feature",
  "properties": {
    "addr:full": "2666 Winchell Rd Aurora OH 44202",
    "addr:housenumber": "2666",
    "addr:postcode": "44202",
    "addr:street": "Winchell Rd",
    "iso:country": "US",
    "sg:address": "2666 Winchell Rd",
    "sg:city": "Aurora",
    "sg:classifiers": [
      {
        "category": "Professional",
        "type": "Services"
      }
    ],
    "sg:phone": "+1 330 562 9874",
    "sg:postcode": "44202",
    "sg:province": "OH",
    "wof:name": "Heil Windemere Storage \u0026 Movin",
    "wof:placetype": "venue"
  },
  "geometry": {"coordinates":[-81.298225,41.337231],"type":"Point"}
}
