{
  "type": "Feature",
  "properties": {
    "iso:country":"US",
    "sg:address":"2666 Winchell Rd",
    "sg:city":"Aurora",
    "sg:classifiers":[
        {
            "category":"Professional",
            "type":"Services"
        }
    ],
    "sg:phone":"+1 330 562 9874",
    "sg:postcode":"44202",
    "sg:province":"OH",
    "wof:name":"Heil Windemere Storage & Movin",
    "wof:placetype":"venue"
},
  "geometry": {"coordinates":[-81.298225,41.337231],"type":"Point"}
}