{
  "type": "Feature",
  "properties": {
    "iso:country":"US",
    "sg:address":"3038 Mount Pleasant St NW",
    "sg:city":"Canton",
    "sg:classifiers":[
        {
            "category":"Building & Trades",
            "subcategory":"Construction",
            "type":"Services"
        }
    ],
    "sg:phone":"+1 330 499 9578",
    "sg:postcode":"44720",
    "sg:province":"OH",
    "sg:tags":[
        "excavation",
        "contractor"
    ],
    "wof:name":"Bob Thurman Excavating Inc",
    "wof:placetype":"venue"
},
  "geometry": {"coordinates":[-81.403997,40.907766],"type":"Point"}
}