{
  "type": "Feature",
  "properties": {
    "iso:country":"US",
    "sg:address":"8248 Kenwood Rd",
    "sg:city":"Cincinnati",
    "sg:classifiers":[
        {
            "category":"Building & Trades",
            "subcategory":"Electrical",
            "type":"Services"
        }
    ],
    "sg:phone":"+1 513 791 5451",
    "sg:postcode":"45236",
    "sg:province":"OH",
    "sg:tags":[
        "electrical",
        "contractor"
    ],
    "wof:name":"Bills Electric",
    "wof:placetype":"venue"
},
  "geometry": {"coordinates":[-84.379441,39.207556],"type":"Point"}
}