{
  "type": "Feature",
  "properties": {
    "addr:full": "2154 Hayes Ave Fremont OH 43420",
    "addr:housenumber": "2154",
    "addr:postcode": "43420",
    "addr:street": "Hayes Ave",
    "iso:country": "US",
    "sg:address": "2154 Hayes Ave",
    "sg:city": "Fremont",
    "sg:classifiers": [
      {
        "category": "Health Services",
        "subcategory": "Chiropractor",
        "type": "Services"
      }
    ],
    "sg:phone": "+1 419 332 7666",
    "sg:postcode": "43420",
    "sg:province": "OH",
    "wof:name": "Nitschke Chiropractic",
    "wof:placetype": "venue"
  },
  "geometry": {"coordinates":[-83.144751,41.342198],"type":"Point"}
}
