{
  "type": "Feature",
  "properties": {
    "addr:full": "10389 Black Fox Trl Piqua OH 45356",
    "addr:housenumber": "10389",
    "addr:postcode": "45356",
    "addr:street": "Black Fox Trl",
    "iso:country": "US",
    "sg:address": "10389 Black Fox Trl",
    "sg:city": "Piqua",
    "sg:classifiers": [
      {
        "category": "Building \u0026 Trades",
        "subcategory": "Landscaping Services",
        "type": "Services"
      }
    ],
    "sg:phone": "+1 937 615 9890",
    "sg:postcode": "45356",
    "sg:province": "OH",
    "wof:name": "All About Landscaping",
    "wof:placetype": "venue"
  },
  "geometry": {"coordinates":[-84.235427,40.205307],"type":"Point"}
}
