{
  "type": "Feature",
  "properties": {
    "iso:country":"US",
    "sg:address":"10389 Black Fox Trl",
    "sg:city":"Piqua",
    "sg:classifiers":[
        {
            "category":"Building & Trades",
            "subcategory":"Landscaping Services",
            "type":"Services"
        }
    ],
    "sg:phone":"+1 937 615 9890",
    "sg:postcode":"45356",
    "sg:province":"OH",
    "wof:name":"All About Landscaping",
    "wof:placetype":"venue"
},
  "geometry": {"coordinates":[-84.235427,40.205307],"type":"Point"}
}