{
  "type": "Feature",
  "properties": {
    "addr:full": "706 Convers Ave Zanesville OH 43701",
    "addr:housenumber": "706",
    "addr:postcode": "43701",
    "addr:street": "Convers Ave",
    "iso:country": "US",
    "sg:address": "706 Convers Ave",
    "sg:city": "Zanesville",
    "sg:classifiers": [
      {
        "category": "Professional",
        "subcategory": "Computer Services",
        "type": "Services"
      }
    ],
    "sg:phone": "+1 740 454 8272",
    "sg:postcode": "43701",
    "sg:province": "OH",
    "sg:tags": [
      "hardware",
      "provider",
      "internet",
      "software"
    ],
    "sg:website": "www.inf-inet.com",
    "wof:name": "Inf-Inet Business Solutions",
    "wof:placetype": "venue"
  },
  "geometry": {"coordinates":[-82.012103,39.950469],"type":"Point"}
}
