{
  "type": "Feature",
  "properties": {
    "addr:full":"604 Cross St Belpre OH 45714",
    "addr:housenumber":"604",
    "addr:postcode":"45714",
    "addr:street":"Cross St",
    "iso:country":"US",
    "sg:address":"604 Cross St",
    "sg:city":"Belpre",
    "sg:classifiers":[
        {
            "category":"Social Services",
            "type":"Services"
        }
    ],
    "sg:phone":"+1 740 423 6811",
    "sg:postcode":"45714",
    "sg:province":"OH",
    "sg:tags":[
        "counselor",
        "marriage",
        "family"
    ],
    "wof:name":"Heartstar Hypnotherapy",
    "wof:placetype":"venue"
},
  "geometry": {"coordinates":[-81.60610699999999,39.278007],"type":"Point"}
}