{
  "type": "Feature",
  "properties": {
    "iso:country":"US",
    "sg:address":"6683 Hamilton Scipio Rd",
    "sg:city":"Okeana",
    "sg:classifiers":[
        {
            "category":"Building & Trades",
            "subcategory":"Landscaping Services",
            "type":"Services"
        }
    ],
    "sg:phone":"+1 513 756 0317",
    "sg:postcode":"45053",
    "sg:province":"IN",
    "wof:name":"Louis Lot Maintenance",
    "wof:placetype":"venue"
},
  "geometry": {"coordinates":[-84.772504,39.391332],"type":"Point"}
}