{
  "type": "Feature",
  "properties": {
    "iso:country":"US",
    "sg:address":"214 S Damascus St",
    "sg:city":"Liberty Center",
    "sg:classifiers":[
        {
            "category":"Arts & Performance",
            "subcategory":"Theater",
            "type":"Entertainment"
        }
    ],
    "sg:phone":"+1 419 533 2480",
    "sg:postcode":"43532",
    "sg:province":"OH",
    "sg:tags":[
        "live",
        "music"
    ],
    "wof:name":"W & W Sounds In Motion Dj's",
    "wof:placetype":"venue"
},
  "geometry": {"coordinates":[-84.00887400000001,41.439183],"type":"Point"}
}