{
  "type": "Feature",
  "properties": {
    "addr:full": "214 S Damascus St Liberty Center OH 43532",
    "addr:housenumber": "214",
    "addr:postcode": "43532",
    "addr:street": "S Damascus St",
    "iso:country": "US",
    "sg:address": "214 S Damascus St",
    "sg:city": "Liberty Center",
    "sg:classifiers": [
      {
        "category": "Arts \u0026 Performance",
        "subcategory": "Theater",
        "type": "Entertainment"
      }
    ],
    "sg:phone": "+1 419 533 2480",
    "sg:postcode": "43532",
    "sg:province": "OH",
    "sg:tags": [
      "live",
      "music"
    ],
    "wof:name": "W \u0026 W Sounds In Motion Dj's",
    "wof:placetype": "venue"
  },
  "geometry": {"coordinates":[-84.008874,41.439183],"type":"Point"}
}
