{
  "type": "Feature",
  "properties": {
    "addr:full": "1120 Canton Rd Akron OH 44312",
    "addr:housenumber": "1120",
    "addr:postcode": "44312",
    "addr:street": "Canton Rd",
    "iso:country": "US",
    "sg:address": "1120 Canton Rd",
    "sg:city": "Akron",
    "sg:classifiers": [
      {
        "category": "Wholesale",
        "subcategory": "Hardware",
        "type": "Manufacturing \u0026 Wholesale Goods"
      }
    ],
    "sg:phone": "+1 330 733 9993",
    "sg:postcode": "44312",
    "sg:province": "OH",
    "sg:tags": [
      "refrigeration"
    ],
    "wof:name": "Thermo King Sales \u0026 Service",
    "wof:placetype": "venue"
  },
  "geometry": {"coordinates":[-81.430608,41.034898],"type":"Point"}
}
