{
  "type": "Feature",
  "properties": {
    "addr:full":"2131 Stringtown Rd Grove City OH 43123",
    "addr:housenumber":"2131",
    "addr:postcode":"43123",
    "addr:street":"Stringtown Rd",
    "iso:country":"US",
    "sg:address":"2131 Stringtown Rd",
    "sg:city":"Grove City",
    "sg:classifiers":[
        {
            "category":"Retail",
            "subcategory":"Auto Repair",
            "type":"Services"
        }
    ],
    "sg:phone":"+1 614 871 4020",
    "sg:postcode":"43123",
    "sg:province":"OH",
    "sg:tags":[
        "repairing",
        "automobile"
    ],
    "wof:name":"Tuffy Auto Svc Ctr",
    "wof:placetype":"venue"
},
  "geometry": {"coordinates":[-83.06162399999999,39.878622],"type":"Point"}
}