{
  "type": "Feature",
  "properties": {
    "addr:full": "1345 Mockingbird Dr Kent OH 44240",
    "addr:housenumber": "1345",
    "addr:postcode": "44240",
    "addr:street": "Mockingbird Dr",
    "iso:country": "US",
    "sg:address": "1345 Mockingbird Dr",
    "sg:city": "Kent",
    "sg:classifiers": [
      {
        "category": "Shopping",
        "subcategory": "Computers \u0026 Home Electronics",
        "type": "Retail Goods"
      }
    ],
    "sg:phone": "+1 330 678 8942",
    "sg:postcode": "44240",
    "sg:province": "OH",
    "wof:name": "Financial Analytics",
    "wof:placetype": "venue"
  },
  "geometry": {"coordinates":[-81.344397,41.200267],"type":"Point"}
}
