{
  "type": "Feature",
  "properties": {
    "addr:full":"3681 Kennybrook Bluff Columbus OH 43220",
    "addr:housenumber":"3681",
    "addr:postcode":"43220",
    "addr:street":"Kennybrook Bluff",
    "iso:country":"US",
    "sg:address":"3681 Kennybrook Bluff",
    "sg:city":"Columbus",
    "sg:classifiers":[
        {
            "category":"Real Estate",
            "subcategory":"Real Estate Operator",
            "type":"Services"
        }
    ],
    "sg:phone":"+1 614 889 7557",
    "sg:postcode":"43220",
    "sg:province":"OH",
    "sg:tags":[
        "mall",
        "shopping",
        "center"
    ],
    "wof:name":"Sawmar",
    "wof:placetype":"venue"
},
  "geometry": {"coordinates":[-83.047409,40.033381],"type":"Point"}
}