{
  "type": "Feature",
  "properties": {
    "iso:country":"US",
    "sg:address":"1472 E State St",
    "sg:city":"Fremont",
    "sg:classifiers":[
        {
            "category":"Home & Garden",
            "subcategory":"Household Appliances",
            "type":"Retail Goods"
        }
    ],
    "sg:phone":"+1 419 332 2747",
    "sg:postcode":"43420",
    "sg:province":"OH",
    "wof:name":"Fremont Vacuum",
    "wof:placetype":"venue"
},
  "geometry": {"coordinates":[-83.09350000000001,41.342043],"type":"Point"}
}