{
  "type": "Feature",
  "properties": {
    "addr:full": "1472 E State St Fremont OH 43420",
    "addr:housenumber": "1472",
    "addr:postcode": "43420",
    "addr:street": "E State St",
    "iso:country": "US",
    "sg:address": "1472 E State St",
    "sg:city": "Fremont",
    "sg:classifiers": [
      {
        "category": "Home \u0026 Garden",
        "subcategory": "Household Appliances",
        "type": "Retail Goods"
      }
    ],
    "sg:phone": "+1 419 332 2747",
    "sg:postcode": "43420",
    "sg:province": "OH",
    "wof:name": "Fremont Vacuum",
    "wof:placetype": "venue"
  },
  "geometry": {"coordinates":[-83.0935,41.342043],"type":"Point"}
}
