{
  "type": "Feature",
  "properties": {
    "addr:full": "1515 S Byrne Rd Toledo OH 43614",
    "addr:housenumber": "1515",
    "addr:postcode": "43614",
    "addr:street": "S Byrne Rd",
    "iso:country": "US",
    "sg:address": "1515 S Byrne Rd",
    "sg:city": "Toledo",
    "sg:classifiers": [
      {
        "category": "Cinema",
        "subcategory": "Movie Rental",
        "type": "Entertainment"
      }
    ],
    "sg:phone": "+1 419 381 1711",
    "sg:postcode": "43614",
    "sg:province": "OH",
    "sg:tags": [
      "company",
      "video"
    ],
    "wof:name": "Video Connection",
    "wof:placetype": "venue"
  },
  "geometry": {"coordinates":[-83.625682,41.60906],"type":"Point"}
}
