{
  "type": "Feature",
  "properties": {
    "iso:country":"US",
    "sg:address":"1843 Huy Rd",
    "sg:city":"Columbus",
    "sg:classifiers":[
        {
            "category":"Personal",
            "subcategory":"Barber",
            "type":"Services"
        }
    ],
    "sg:phone":"+1 614 262 3714",
    "sg:postcode":"43224",
    "sg:province":"OH",
    "wof:name":"Huy Road Barber Shop-North",
    "wof:placetype":"venue"
},
  "geometry": {"coordinates":[-82.965487,40.035131],"type":"Point"}
}