{
  "type": "Feature",
  "properties": {
    "addr:full":"1930 E 43rd St Ashtabula OH 44004",
    "addr:housenumber":"1930",
    "addr:postcode":"44004",
    "addr:street":"E 43Rd St",
    "iso:country":"US",
    "sg:address":"1930 E 43rd St",
    "sg:city":"Ashtabula",
    "sg:classifiers":[
        {
            "category":"Real Estate",
            "subcategory":"Real Estate Agent",
            "type":"Services"
        }
    ],
    "sg:phone":"+1 440 964 3454",
    "sg:postcode":"44004",
    "sg:province":"OH",
    "sg:tags":[
        "inspection"
    ],
    "wof:name":"Ashtabula Pest Control",
    "wof:placetype":"venue"
},
  "geometry": {"coordinates":[-80.77211200000001,41.86698],"type":"Point"}
}