{
  "type": "Feature",
  "properties": {
    "addr:full":"206 N Crown Hill Rd Orrville OH 44667",
    "addr:housenumber":"206",
    "addr:postcode":"44667",
    "addr:street":"N Crown Hill Rd",
    "iso:country":"US",
    "sg:address":"206 N Crown Hill Rd",
    "sg:city":"Orrville",
    "sg:classifiers":[
        {
            "category":"Wholesale",
            "subcategory":"Toys & Hobbies",
            "type":"Manufacturing & Wholesale Goods"
        }
    ],
    "sg:phone":"+1 330 682 6218",
    "sg:postcode":"44667",
    "sg:province":"OH",
    "wof:name":"Jj Crafts",
    "wof:placetype":"venue"
},
  "geometry": {"coordinates":[-81.784407,40.844241],"type":"Point"}
}