{
  "type": "Feature",
  "properties": {
    "iso:country":"US",
    "sg:address":"4999 Scothills Dr",
    "sg:city":"Englewood",
    "sg:classifiers":[
        {
            "category":"Shopping",
            "subcategory":"Clothing, Apparel, & Fashions",
            "type":"Retail Goods"
        }
    ],
    "sg:phone":"+1 937 832 8487",
    "sg:postcode":"45322",
    "sg:province":"OH",
    "sg:tags":[
        "designer"
    ],
    "wof:name":"J Styles Design Center",
    "wof:placetype":"venue"
},
  "geometry": {"coordinates":[-84.304745,39.845991],"type":"Point"}
}