{
  "type": "Feature",
  "properties": {
    "addr:full":"15801 Akron Canfield Rd Berlin Center OH 44401",
    "addr:housenumber":"15801",
    "addr:postcode":"44401",
    "addr:street":"Akron Canfield Rd",
    "iso:country":"US",
    "sg:address":"15801 Akron Canfield Rd",
    "sg:city":"Berlin Center",
    "sg:classifiers":[
        {
            "category":"Government",
            "subcategory":"Fire Station",
            "type":"Public Place"
        }
    ],
    "sg:phone":"+1 330 547 2222",
    "sg:postcode":"44401",
    "sg:province":"OH",
    "sg:tags":[
        "department"
    ],
    "wof:name":"Fire Department",
    "wof:placetype":"venue"
},
  "geometry": {"coordinates":[-80.949468,41.024515],"type":"Point"}
}