{
  "type": "Feature",
  "properties": {
    "addr:full": "4012 E Harbor Rd Port Clinton OH 43452",
    "addr:housenumber": "4012 e",
    "addr:postcode": "43452",
    "addr:street": "Harbor Rd",
    "iso:country": "US",
    "sg:address": "4012 E Harbor Rd",
    "sg:city": "Port Clinton",
    "sg:classifiers": [
      {
        "category": "Shopping",
        "subcategory": "Bicycles \u0026 Sporting Goods",
        "type": "Retail Goods"
      }
    ],
    "sg:phone": "+1 419 732 3957",
    "sg:postcode": "43452",
    "sg:province": "OH",
    "wof:name": "Cotton Dock",
    "wof:placetype": "venue"
  },
  "geometry": {"coordinates":[-82.854952,41.525078],"type":"Point"}
}
