{
  "type": "Feature",
  "properties": {
    "iso:country":"US",
    "sg:address":"1381 Oakwood Ave",
    "sg:city":"Napoleon",
    "sg:classifiers":[
        {
            "category":"Organizations",
            "subcategory":"Community Association",
            "type":"Services"
        }
    ],
    "sg:phone":"+1 419 592 5591",
    "sg:postcode":"43545",
    "sg:province":"OH",
    "sg:tags":[
        "fraternal"
    ],
    "wof:name":"Loyal Order Of Moose",
    "wof:placetype":"venue"
},
  "geometry": {"coordinates":[-84.122916,41.401126],"type":"Point"}
}