{
  "type": "Feature",
  "properties": {
    "addr:full":"1349 W 2nd St Lorain OH 44052",
    "addr:housenumber":"1349",
    "addr:postcode":"44052",
    "addr:street":"W 2Nd St",
    "iso:country":"US",
    "sg:address":"1349 W 2nd St",
    "sg:city":"Lorain",
    "sg:classifiers":[
        {
            "category":"Professional",
            "type":"Services"
        }
    ],
    "sg:phone":"+1 440 246 2322",
    "sg:postcode":"44052",
    "sg:province":"OH",
    "wof:name":"Safeharbors General Contrs LLC",
    "wof:placetype":"venue"
},
  "geometry": {"coordinates":[-82.19106499999999,41.464951],"type":"Point"}
}