{
  "type": "Feature",
  "properties": {
    "addr:full": "30350 Bruce Industrial Pkwy Cleveland OH 44139",
    "addr:housenumber": "30350",
    "addr:postcode": "44139",
    "addr:street": "Bruce Industrial Pkwy",
    "iso:country": "US",
    "sg:address": "30350 Bruce Industrial Pkwy",
    "sg:city": "Cleveland",
    "sg:classifiers": [
      {
        "category": "Manufacturing",
        "subcategory": "Metals",
        "type": "Manufacturing \u0026 Wholesale Goods"
      }
    ],
    "sg:phone": "+1 440 248 2710",
    "sg:postcode": "44139",
    "sg:province": "OH",
    "sg:tags": [
      "screw",
      "nut",
      "bolt"
    ],
    "sg:website": "www.ftsinc.cc",
    "wof:name": "Fastener Tool \u0026 Supply Inc",
    "wof:placetype": "venue"
  },
  "geometry": {"coordinates":[-81.464793,41.377461],"type":"Point"}
}
