{
  "type": "Feature",
  "properties": {
    "iso:country":"US",
    "sg:address":"30350 Bruce Industrial Pkwy",
    "sg:city":"Cleveland",
    "sg:classifiers":[
        {
            "category":"Manufacturing",
            "subcategory":"Metals",
            "type":"Manufacturing & Wholesale Goods"
        }
    ],
    "sg:phone":"+1 440 248 2710",
    "sg:postcode":"44139",
    "sg:province":"OH",
    "sg:tags":[
        "screw",
        "nut",
        "bolt"
    ],
    "sg:website":"www.ftsinc.cc",
    "wof:name":"Fastener Tool & Supply Inc",
    "wof:placetype":"venue"
},
  "geometry": {"coordinates":[-81.464793,41.377461],"type":"Point"}
}