{
  "type": "Feature",
  "properties": {
    "addr:full": "32 S Main St Johnstown OH 43031",
    "addr:housenumber": "32",
    "addr:postcode": "43031",
    "addr:street": "S Main St",
    "iso:country": "US",
    "sg:address": "32 S Main St",
    "sg:city": "Johnstown",
    "sg:classifiers": [
      {
        "category": "Sports \u0026 Exercise",
        "subcategory": "Gym",
        "type": "Entertainment"
      }
    ],
    "sg:phone": "+1 740 967 0799",
    "sg:postcode": "43031",
    "sg:province": "OH",
    "sg:tags": [
      "gymnasium"
    ],
    "wof:name": "Muscle Factory",
    "wof:placetype": "venue"
  },
  "geometry": {"coordinates":[-82.684289,40.153388],"type":"Point"}
}
