{
  "type": "Feature",
  "properties": {
    "addr:full": "6175 Highland Rd Cleveland OH 44143",
    "addr:housenumber": "6175",
    "addr:postcode": "44143",
    "addr:street": "Highland Rd",
    "iso:country": "US",
    "sg:address": "6175 Highland Rd",
    "sg:city": "Cleveland",
    "sg:classifiers": [
      {
        "category": "Building \u0026 Trades",
        "subcategory": "Plumbing",
        "type": "Services"
      }
    ],
    "sg:phone": "+1 440 442 5711",
    "sg:postcode": "44143",
    "sg:province": "OH",
    "sg:tags": [
      "contractor"
    ],
    "wof:name": "Kowalcyk Mechanical Co",
    "wof:placetype": "venue"
  },
  "geometry": {"coordinates":[-81.452386,41.552462],"type":"Point"}
}
