{
  "type": "Feature",
  "properties": {
    "addr:full":"721 Boardman Poland Rd Youngstown OH 44512",
    "addr:housenumber":"721",
    "addr:postcode":"44512",
    "addr:street":"Boardman Poland Rd",
    "iso:country":"US",
    "sg:address":"721 Boardman Poland Rd",
    "sg:city":"Youngstown",
    "sg:classifiers":[
        {
            "category":"Health Services",
            "subcategory":"Hospital",
            "type":"Services"
        }
    ],
    "sg:phone":"+1 330 629 2009",
    "sg:postcode":"44512",
    "sg:province":"OH",
    "sg:tags":[
        "treatment",
        "psychiatric",
        "facility"
    ],
    "wof:name":"Wellesley Corp",
    "wof:placetype":"venue"
},
  "geometry": {"coordinates":[-80.650829,41.024252],"type":"Point"}
}