{
  "type": "Feature",
  "properties": {
    "iso:country":"US",
    "sg:address":"1970 Scranton Rd",
    "sg:city":"Cleveland",
    "sg:classifiers":[
        {
            "category":"Building & Trades",
            "subcategory":"Construction",
            "type":"Services"
        }
    ],
    "sg:phone":"+1 216 589 0048",
    "sg:postcode":"44113",
    "sg:province":"OH",
    "sg:tags":[
        "painter"
    ],
    "wof:name":"Gerinmo Painting Co",
    "wof:placetype":"venue"
},
  "geometry": {"coordinates":[-81.694596,41.489444],"type":"Point"}
}