{
  "type": "Feature",
  "properties": {
    "addr:full":"160 High St NW Warren OH 44481",
    "addr:housenumber":"160",
    "addr:postcode":"44481",
    "addr:street":"High St Nw",
    "iso:country":"US",
    "sg:address":"160 High St NW",
    "sg:city":"Warren",
    "sg:classifiers":[
        {
            "category":"Government",
            "subcategory":"Office",
            "type":"Public Place"
        }
    ],
    "sg:phone":"+1 330 675 2420",
    "sg:postcode":"44481",
    "sg:province":"OH",
    "sg:tags":[
        "county",
        "taxation",
        "executive"
    ],
    "wof:name":"Trumbull County Auditors Off",
    "wof:placetype":"venue"
},
  "geometry": {"coordinates":[-80.818634,41.23755],"type":"Point"}
}