{
  "type": "Feature",
  "properties": {
    "addr:full":"501 S High St Columbus OH 43215",
    "addr:housenumber":"501",
    "addr:postcode":"43215",
    "addr:street":"S High St",
    "iso:country":"US",
    "sg:address":"501 S High St",
    "sg:city":"Columbus",
    "sg:classifiers":[
        {
            "category":"Professional",
            "subcategory":"Lawyer & Legal Services",
            "type":"Services"
        }
    ],
    "sg:phone":"+1 614 469 0180",
    "sg:postcode":"43215",
    "sg:province":"OH",
    "sg:tags":[
        "attorney"
    ],
    "wof:name":"Myron Shwartz",
    "wof:placetype":"venue"
},
  "geometry": {"coordinates":[-82.99869700000001,39.951793],"type":"Point"}
}