{
  "type": "Feature",
  "properties": {
    "iso:country":"US",
    "sg:address":"503 Sheridan St",
    "sg:city":"Zanesville",
    "sg:classifiers":[
        {
            "category":"Building & Trades",
            "subcategory":"Landscaping Services",
            "type":"Services"
        }
    ],
    "sg:phone":"+1 740 455 6444",
    "sg:postcode":"43701",
    "sg:province":"OH",
    "sg:tags":[
        "tree"
    ],
    "wof:name":"Krofft Complete Tree Service",
    "wof:placetype":"venue"
},
  "geometry": {"coordinates":[-82.009317,39.956096],"type":"Point"}
}