{
  "type": "Feature",
  "properties": {
    "addr:full":"574 Dover Center Rd Cleveland OH 44140",
    "addr:housenumber":"574",
    "addr:postcode":"44140",
    "addr:street":"Dover Center Rd",
    "iso:country":"US",
    "sg:address":"574 Dover Center Rd",
    "sg:city":"Cleveland",
    "sg:classifiers":[
        {
            "category":"Banks & Credit Unions",
            "subcategory":"Investment Brokerage",
            "type":"Services"
        }
    ],
    "sg:phone":"+1 440 808 0139",
    "sg:postcode":"44140",
    "sg:province":"OH",
    "sg:tags":[
        "stock",
        "bond"
    ],
    "wof:name":"Edward Jones Co",
    "wof:placetype":"venue"
},
  "geometry": {"coordinates":[-81.92112299999999,41.479232],"type":"Point"}
}