{
  "type": "Feature",
  "properties": {
    "addr:full": "2119 Brightwood Rd SE New Philadelphia OH 44663",
    "addr:housenumber": "2119",
    "addr:postcode": "44663",
    "addr:street": "Brightwood Rd Se New",
    "iso:country": "US",
    "sg:address": "2119 Brightwood Rd SE",
    "sg:city": "New Philadelphia",
    "sg:classifiers": [
      {
        "category": "Shopping",
        "subcategory": "Used Merchandise",
        "type": "Retail Goods"
      },
      {
        "category": "Shopping",
        "subcategory": "Clothing, Apparel, \u0026 Fashions",
        "type": "Retail Goods"
      }
    ],
    "sg:phone": "+1 330 339 8151",
    "sg:postcode": "44663",
    "sg:province": "OH",
    "sg:tags": [
      "shop",
      "consignment",
      "wear"
    ],
    "wof:name": "Kid's Place",
    "wof:placetype": "venue"
  },
  "geometry": {"coordinates":[-81.389748,40.444806],"type":"Point"}
}
