{
  "type": "Feature",
  "properties": {
    "iso:country":"US",
    "sg:address":"2119 Brightwood Rd SE",
    "sg:city":"New Philadelphia",
    "sg:classifiers":[
        {
            "category":"Shopping",
            "subcategory":"Used Merchandise",
            "type":"Retail Goods"
        },
        {
            "category":"Shopping",
            "subcategory":"Clothing, Apparel, & Fashions",
            "type":"Retail Goods"
        }
    ],
    "sg:phone":"+1 330 339 8151",
    "sg:postcode":"44663",
    "sg:province":"OH",
    "sg:tags":[
        "shop",
        "consignment",
        "wear"
    ],
    "wof:name":"Kid's Place",
    "wof:placetype":"venue"
},
  "geometry": {"coordinates":[-81.389748,40.444806],"type":"Point"}
}