{
  "type": "Feature",
  "properties": {
    "addr:full": "3313 W 140th St Cleveland OH 44111",
    "addr:housenumber": "3313",
    "addr:postcode": "44111",
    "addr:street": "W 140Th St",
    "iso:country": "US",
    "sg:address": "3313 W 140th St",
    "sg:city": "Cleveland",
    "sg:classifiers": [
      {
        "category": "Home \u0026 Garden",
        "subcategory": "Furniture",
        "type": "Retail Goods"
      }
    ],
    "sg:phone": "+1 216 374 3986",
    "sg:postcode": "44111",
    "sg:province": "OH",
    "wof:name": "Northeast Factory Furniture",
    "wof:placetype": "venue"
  },
  "geometry": {"coordinates":[-81.789934,41.462602],"type":"Point"}
}
