{
  "type": "Feature",
  "properties": {
    "iso:country":"US",
    "sg:address":"3313 W 140th St",
    "sg:city":"Cleveland",
    "sg:classifiers":[
        {
            "category":"Home & Garden",
            "subcategory":"Furniture",
            "type":"Retail Goods"
        }
    ],
    "sg:phone":"+1 216 374 3986",
    "sg:postcode":"44111",
    "sg:province":"OH",
    "wof:name":"Northeast Factory Furniture",
    "wof:placetype":"venue"
},
  "geometry": {"coordinates":[-81.789934,41.462602],"type":"Point"}
}