{
  "type": "Feature",
  "properties": {
    "iso:country":"US",
    "sg:address":"1631 Paula Dr",
    "sg:city":"Columbus",
    "sg:classifiers":[
        {
            "category":"Sports & Exercise",
            "subcategory":"Golf",
            "type":"Entertainment"
        }
    ],
    "sg:phone":"+1 614 442 8600",
    "sg:postcode":"43220",
    "sg:province":"OH",
    "sg:tags":[
        "course"
    ],
    "wof:name":"Sanfillipo's Golf Svc",
    "wof:placetype":"venue"
},
  "geometry": {"coordinates":[-83.063298,40.060071],"type":"Point"}
}