{
  "type": "Feature",
  "properties": {
    "addr:full":"506 Meadow Ln Wooster OH 44691",
    "addr:housenumber":"506",
    "addr:postcode":"44691",
    "addr:street":"Meadow Ln",
    "iso:country":"US",
    "sg:address":"506 Meadow Ln",
    "sg:city":"Wooster",
    "sg:classifiers":[
        {
            "category":"Banks & Credit Unions",
            "subcategory":"Financial Services",
            "type":"Services"
        }
    ],
    "sg:phone":"+1 330 263 1381",
    "sg:postcode":"44691",
    "sg:province":"OH",
    "sg:tags":[
        "company",
        "holding"
    ],
    "wof:name":"River View Industrial Wood",
    "wof:placetype":"venue"
},
  "geometry": {"coordinates":[-81.95026,40.821837],"type":"Point"}
}