{
  "type": "Feature",
  "properties": {
    "addr:full":"1900 Tamarack Rd Newark OH 43055",
    "addr:housenumber":"1900",
    "addr:postcode":"43055",
    "addr:street":"Tamarack Rd",
    "iso:country":"US",
    "sg:address":"1900 Tamarack Rd",
    "sg:city":"Newark",
    "sg:classifiers":[
        {
            "category":"Professional",
            "subcategory":"Management & Consulting",
            "type":"Services"
        }
    ],
    "sg:phone":"+1 740 522 2193",
    "sg:postcode":"43055",
    "sg:province":"OH",
    "sg:tags":[
        "fuel"
    ],
    "wof:name":"Calgary Management",
    "wof:placetype":"venue"
},
  "geometry": {"coordinates":[-82.464386,40.038516],"type":"Point"}
}