{
  "type": "Feature",
  "properties": {
    "addr:full": "300 E Sharon Rd Cincinnati OH 45246",
    "addr:housenumber": "300",
    "addr:postcode": "45246",
    "addr:street": "E Sharon Rd",
    "iso:country": "US",
    "sg:address": "300 E Sharon Rd",
    "sg:city": "Cincinnati",
    "sg:classifiers": [
      {
        "category": "Autos \u0026 Motor Vehicles",
        "subcategory": "Fuel \u0026 Gas Station",
        "type": "Retail Goods"
      }
    ],
    "sg:phone": "+1 513 771 1931",
    "sg:postcode": "45246",
    "sg:province": "OH",
    "sg:tags": [
      "oil"
    ],
    "wof:name": "Couch's Marathon",
    "wof:placetype": "venue"
  },
  "geometry": {"coordinates":[-84.45794,39.272009],"type":"Point"}
}
