{
  "type": "Feature",
  "properties": {
    "addr:full": "1042 Taggart St NW Massillon OH 44646",
    "addr:housenumber": "1042",
    "addr:postcode": "44646",
    "addr:street": "Taggart St Nw",
    "iso:country": "US",
    "sg:address": "1042 Taggart St NW",
    "sg:city": "Massillon",
    "sg:classifiers": [
      {
        "category": "Building \u0026 Trades",
        "subcategory": "Construction",
        "type": "Services"
      }
    ],
    "sg:phone": "+1 330 837 0359",
    "sg:postcode": "44646",
    "sg:province": "OH",
    "sg:tags": [
      "house"
    ],
    "wof:name": "Bl Distributing",
    "wof:placetype": "venue"
  },
  "geometry": {"coordinates":[-81.509211,40.824354],"type":"Point"}
}
