{
  "type": "Feature",
  "properties": {
    "iso:country":"US",
    "sg:address":"1042 Taggart St NW",
    "sg:city":"Massillon",
    "sg:classifiers":[
        {
            "category":"Building & Trades",
            "subcategory":"Construction",
            "type":"Services"
        }
    ],
    "sg:phone":"+1 330 837 0359",
    "sg:postcode":"44646",
    "sg:province":"OH",
    "sg:tags":[
        "house"
    ],
    "wof:name":"Bl Distributing",
    "wof:placetype":"venue"
},
  "geometry": {"coordinates":[-81.50921099999999,40.824354],"type":"Point"}
}