{
  "type": "Feature",
  "properties": {
    "addr:full": "2749 Edmondson Rd Cincinnati OH 45209",
    "addr:housenumber": "2749",
    "addr:postcode": "45209",
    "addr:street": "Edmondson Rd",
    "iso:country": "US",
    "sg:address": "2749 Edmondson Rd",
    "sg:city": "Cincinnati",
    "sg:classifiers": [
      {
        "category": "Shopping",
        "subcategory": "Jewelry",
        "type": "Retail Goods"
      }
    ],
    "sg:phone": "+1 513 631 3444",
    "sg:postcode": "45209",
    "sg:province": "OH",
    "sg:tags": [
      "jeweler"
    ],
    "wof:name": "Ultra Diamonds",
    "wof:placetype": "venue"
  },
  "geometry": {"coordinates":[-84.445541,39.149682],"type":"Point"}
}
