{
  "type": "Feature",
  "properties": {
    "iso:country":"US",
    "sg:address":"9445 Mentor Ave",
    "sg:city":"Mentor",
    "sg:classifiers":[
        {
            "category":"Restaurant",
            "type":"Food & Drink"
        }
    ],
    "sg:phone":"+1 216 831 4344",
    "sg:postcode":"44060",
    "sg:province":"OH",
    "sg:tags":[
        "eating"
    ],
    "wof:name":"California Salads & Catering",
    "wof:placetype":"venue"
},
  "geometry": {"coordinates":[-81.30250700000001,41.679892],"type":"Point"}
}