{
  "type": "Feature",
  "properties": {
    "addr:full":"151 N 3 Bs and K Rd Sunbury OH 43074",
    "addr:housenumber":"151;3",
    "addr:postcode":"43074",
    "addr:street":"N;And K Rd",
    "iso:country":"US",
    "sg:address":"151 N 3 Bs and K Rd",
    "sg:city":"Sunbury",
    "sg:classifiers":[
        {
            "category":"Building & Trades",
            "subcategory":"Construction",
            "type":"Services"
        }
    ],
    "sg:phone":"+1 740 296 7395",
    "sg:postcode":"43074",
    "sg:province":"OH",
    "sg:tags":[
        "hanging",
        "contractor"
    ],
    "wof:name":"Octopus Enterprises",
    "wof:placetype":"venue"
},
  "geometry": {"coordinates":[-82.938807,40.269281],"type":"Point"}
}