{
  "type": "Feature",
  "properties": {
    "addr:full":"4111 Henritze Ave Cleveland OH 44109",
    "addr:housenumber":"4111",
    "addr:postcode":"44109",
    "addr:street":"Henritze Ave",
    "iso:country":"US",
    "sg:address":"4111 Henritze Ave",
    "sg:city":"Cleveland",
    "sg:classifiers":[
        {
            "category":"Local Transit",
            "type":"Transportation"
        }
    ],
    "sg:phone":"+1 216 661 5466",
    "sg:postcode":"44109",
    "sg:province":"OH",
    "sg:tags":[
        "limousine"
    ],
    "wof:name":"Black Tie Limousine & Bus Svc",
    "wof:placetype":"venue"
},
  "geometry": {"coordinates":[-81.716364,41.438981],"type":"Point"}
}