{
  "type": "Feature",
  "properties": {
    "addr:full": "7711 Diley Rd Canal Winchester OH 43110",
    "addr:postcode": "7711;43110",
    "addr:street": "Diley Rd",
    "iso:country": "US",
    "sg:address": "7711 Diley Rd",
    "sg:city": "Canal Winchester",
    "sg:classifiers": [
      {
        "category": "Manufacturing",
        "subcategory": "Furniture",
        "type": "Manufacturing \u0026 Wholesale Goods"
      }
    ],
    "sg:phone": "+1 614 833 9596",
    "sg:postcode": "43110",
    "sg:province": "OH",
    "sg:tags": [
      "mfg",
      "wood",
      "n"
    ],
    "sg:website": "www.kelloggcabinets.com",
    "wof:name": "Kellogg Cabinets Inc",
    "wof:placetype": "venue"
  },
  "geometry": {"coordinates":[-82.781483,39.845925],"type":"Point"}
}
