{
  "type": "Feature",
  "properties": {
    "iso:country":"US",
    "sg:address":"7711 Diley Rd",
    "sg:city":"Canal Winchester",
    "sg:classifiers":[
        {
            "category":"Manufacturing",
            "subcategory":"Furniture",
            "type":"Manufacturing & Wholesale Goods"
        }
    ],
    "sg:phone":"+1 614 833 9596",
    "sg:postcode":"43110",
    "sg:province":"OH",
    "sg:tags":[
        "mfg",
        "wood",
        "n"
    ],
    "sg:website":"www.kelloggcabinets.com",
    "wof:name":"Kellogg Cabinets Inc",
    "wof:placetype":"venue"
},
  "geometry": {"coordinates":[-82.78148299999999,39.845925],"type":"Point"}
}