{
  "type": "Feature",
  "properties": {
    "addr:full":"3802 Sullivant Ave Columbus OH 43228",
    "addr:housenumber":"3802",
    "addr:postcode":"43228",
    "addr:street":"Sullivant Ave",
    "iso:country":"US",
    "sg:address":"3802 Sullivant Ave",
    "sg:city":"Columbus",
    "sg:classifiers":[
        {
            "category":"Building & Trades",
            "subcategory":"Electrical",
            "type":"Services"
        }
    ],
    "sg:phone":"+1 614 276 1423",
    "sg:postcode":"43228",
    "sg:province":"OH",
    "sg:tags":[
        "electric",
        "contractor"
    ],
    "wof:name":"CTH Electric Co",
    "wof:placetype":"venue"
},
  "geometry": {"coordinates":[-83.09867300000001,39.942529],"type":"Point"}
}