{
  "type": "Feature",
  "properties": {
    "addr:full":"12509 Gruss Ave Cleveland OH 44108",
    "addr:housenumber":"12509",
    "addr:postcode":"44108",
    "addr:street":"Gruss Ave",
    "iso:country":"US",
    "sg:address":"12509 Gruss Ave",
    "sg:city":"Cleveland",
    "sg:classifiers":[
        {
            "category":"Shopping",
            "subcategory":"Florist",
            "type":"Retail Goods"
        }
    ],
    "sg:phone":"+1 216 851 0018",
    "sg:postcode":"44108",
    "sg:province":"OH",
    "wof:name":"Anitas Floral Arrangements",
    "wof:placetype":"venue"
},
  "geometry": {"coordinates":[-81.59743400000001,41.546023],"type":"Point"}
}