{
  "type": "Feature",
  "properties": {
    "iso:country":"US",
    "sg:address":"151 Olive St",
    "sg:city":"Elyria",
    "sg:classifiers":[
        {
            "category":"Wholesale",
            "subcategory":"Machinery & Supplies",
            "type":"Manufacturing & Wholesale Goods"
        }
    ],
    "sg:phone":"+1 440 365 1741",
    "sg:postcode":"44035",
    "sg:province":"OH",
    "sg:tags":[
        "equipment",
        "industrial"
    ],
    "sg:website":"www.wolfenden.biz",
    "wof:name":"Wolfenden Industries Inc",
    "wof:placetype":"venue"
},
  "geometry": {"coordinates":[-82.085767,41.373371],"type":"Point"}
}