{
  "type": "Feature",
  "properties": {
    "addr:full": "151 Olive St Elyria OH 44035",
    "addr:housenumber": "151",
    "addr:postcode": "44035",
    "addr:street": "Olive St",
    "iso:country": "US",
    "sg:address": "151 Olive St",
    "sg:city": "Elyria",
    "sg:classifiers": [
      {
        "category": "Wholesale",
        "subcategory": "Machinery \u0026 Supplies",
        "type": "Manufacturing \u0026 Wholesale Goods"
      }
    ],
    "sg:phone": "+1 440 365 1741",
    "sg:postcode": "44035",
    "sg:province": "OH",
    "sg:tags": [
      "equipment",
      "industrial"
    ],
    "sg:website": "www.wolfenden.biz",
    "wof:name": "Wolfenden Industries Inc",
    "wof:placetype": "venue"
  },
  "geometry": {"coordinates":[-82.085767,41.373371],"type":"Point"}
}
