{
  "type": "Feature",
  "properties": {
    "addr:full": "104 N Detroit St Xenia OH 45385",
    "addr:housenumber": "104",
    "addr:postcode": "45385",
    "addr:street": "N Detroit St",
    "iso:country": "US",
    "sg:address": "104 N Detroit St",
    "sg:city": "Xenia",
    "sg:classifiers": [
      {
        "category": "Restaurant",
        "type": "Food \u0026 Drink"
      }
    ],
    "sg:phone": "+1 937 376 4587",
    "sg:postcode": "45385",
    "sg:province": "OH",
    "wof:name": "Tracy's Coffee Cafe",
    "wof:placetype": "venue"
  },
  "geometry": {"coordinates":[-83.929688,39.686473],"type":"Point"}
}
