{
  "type": "Feature",
  "properties": {
    "iso:country":"US",
    "sg:address":"104 N Detroit St",
    "sg:city":"Xenia",
    "sg:classifiers":[
        {
            "category":"Restaurant",
            "type":"Food & Drink"
        }
    ],
    "sg:phone":"+1 937 376 4587",
    "sg:postcode":"45385",
    "sg:province":"OH",
    "wof:name":"Tracy's Coffee Cafe",
    "wof:placetype":"venue"
},
  "geometry": {"coordinates":[-83.929688,39.686473],"type":"Point"}
}