{
  "type": "Feature",
  "properties": {
    "iso:country":"US",
    "sg:address":"8292 Lake Shore Blvd",
    "sg:city":"Mentor",
    "sg:classifiers":[
        {
            "category":"Shopping",
            "subcategory":"Bicycles & Sporting Goods",
            "type":"Retail Goods"
        }
    ],
    "sg:phone":"+1 440 257 7046",
    "sg:postcode":"44060",
    "sg:province":"OH",
    "sg:tags":[
        "tackle",
        "equipment",
        "bait",
        "fishing"
    ],
    "wof:name":"Minnow Bucket",
    "wof:placetype":"venue"
},
  "geometry": {"coordinates":[-81.34276,41.720475],"type":"Point"}
}