{
  "type": "Feature",
  "properties": {
    "addr:full": "6525 Chapel Rd Madison OH 44057",
    "addr:housenumber": "6525",
    "addr:postcode": "44057",
    "addr:street": "Chapel Rd",
    "iso:country": "US",
    "sg:address": "6525 Chapel Rd",
    "sg:city": "Madison",
    "sg:classifiers": [
      {
        "category": "Health Services",
        "subcategory": "Doctor",
        "type": "Services"
      }
    ],
    "sg:phone": "+1 440 428 2324",
    "sg:postcode": "44057",
    "sg:province": "OH",
    "sg:tags": [
      "dentist"
    ],
    "wof:name": "Ronald J Lipin DDS",
    "wof:placetype": "venue"
  },
  "geometry": {"coordinates":[-81.048977,41.81981],"type":"Point"}
}
