{
  "type": "Feature",
  "properties": {
    "addr:full":"8340 Yankee St Dayton OH 45458",
    "addr:housenumber":"8340",
    "addr:postcode":"45458",
    "addr:street":"Yankee St",
    "iso:country":"US",
    "sg:address":"8340 Yankee St",
    "sg:city":"Dayton",
    "sg:classifiers":[
        {
            "category":"Banks & Credit Unions",
            "subcategory":"Bank",
            "type":"Services"
        }
    ],
    "sg:phone":"+1 937 428 6000",
    "sg:postcode":"45458",
    "sg:province":"OH",
    "sg:tags":[
        "mortgage"
    ],
    "wof:name":"W E Mortgage Services  Inc",
    "wof:placetype":"venue"
},
  "geometry": {"coordinates":[-84.199898,39.627594],"type":"Point"}
}