{
  "type": "Feature",
  "properties": {
    "iso:country":"US",
    "sg:address":"3525 Riverside Dr",
    "sg:city":"Dayton",
    "sg:classifiers":[
        {
            "category":"Personal",
            "type":"Services"
        }
    ],
    "sg:phone":"+1 937 276 5626",
    "sg:postcode":"45405",
    "sg:province":"OH",
    "sg:tags":[
        "therapist",
        "massage"
    ],
    "wof:name":"Peggy Weller",
    "wof:placetype":"venue"
},
  "geometry": {"coordinates":[-84.207465,39.798355],"type":"Point"}
}