{
  "type": "Feature",
  "properties": {
    "iso:country":"US",
    "sg:address":"5500 Ridge Rd",
    "sg:city":"Cleveland",
    "sg:classifiers":[
        {
            "category":"Health Services",
            "subcategory":"Doctor",
            "type":"Services"
        }
    ],
    "sg:phone":"+1 440 884 7181",
    "sg:postcode":"44129",
    "sg:province":"OH",
    "sg:tags":[
        "ophthalmology"
    ],
    "wof:name":"Medical and Surgical Assoc",
    "wof:placetype":"venue"
},
  "geometry": {"coordinates":[-81.734484,41.412105],"type":"Point"}
}