{
  "type": "Feature",
  "properties": {
    "iso:country":"US",
    "sg:address":"106 S College St",
    "sg:city":"Yellow Springs",
    "sg:classifiers":[
        {
            "category":"Building & Trades",
            "subcategory":"Construction",
            "type":"Services"
        }
    ],
    "sg:phone":"+1 937 478 3150",
    "sg:postcode":"45356",
    "sg:province":"OH",
    "sg:tags":[
        "general",
        "contractor"
    ],
    "wof:name":"Gregor Construction",
    "wof:placetype":"venue"
},
  "geometry": {"coordinates":[-84.249151,40.146127],"type":"Point"}
}