{
  "type": "Feature",
  "properties": {
    "addr:full": "5950 S Ridge Rd Madison OH 44057",
    "addr:housenumber": "5950",
    "addr:postcode": "44057",
    "addr:street": "S Ridge Rd",
    "iso:country": "US",
    "sg:address": "5950 S Ridge Rd",
    "sg:city": "Madison",
    "sg:classifiers": [
      {
        "category": "Manufacturing",
        "subcategory": "Lumber",
        "type": "Manufacturing \u0026 Wholesale Goods"
      }
    ],
    "sg:phone": "+1 440 428 3706",
    "sg:postcode": "44057",
    "sg:province": "OH",
    "sg:tags": [
      "product",
      "forest",
      "gathering"
    ],
    "wof:name": "Matt Ungers",
    "wof:placetype": "venue"
  },
  "geometry": {"coordinates":[-81.090732,41.763888],"type":"Point"}
}
