{
  "type": "Feature",
  "properties": {
    "iso:country":"US",
    "sg:address":"10 Stower Ln",
    "sg:city":"Norwalk",
    "sg:classifiers":[
        {
            "category":"Personal",
            "subcategory":"Tanning Parlor",
            "type":"Services"
        }
    ],
    "sg:phone":"+1 419 668 5363",
    "sg:postcode":"44857",
    "sg:province":"OH",
    "sg:tags":[
        "salon"
    ],
    "wof:name":"Simply U",
    "wof:placetype":"venue"
},
  "geometry": {"coordinates":[-82.608757,41.267121],"type":"Point"}
}