{
  "type": "Feature",
  "properties": {
    "addr:full": "2031 S Rockhill Ave Alliance OH 44601",
    "addr:housenumber": "2031",
    "addr:postcode": "44601",
    "addr:street": "S Rockhill Ave",
    "iso:country": "US",
    "sg:address": "2031 S Rockhill Ave",
    "sg:city": "Alliance",
    "sg:classifiers": [
      {
        "category": "Restaurant",
        "type": "Food \u0026 Drink"
      }
    ],
    "sg:phone": "+1 330 821 2887",
    "sg:postcode": "44601",
    "sg:province": "OH",
    "wof:name": "Doug's Classic 57 Drive In",
    "wof:placetype": "venue"
  },
  "geometry": {"coordinates":[-81.115609,40.90169],"type":"Point"}
}
