{
  "type": "Feature",
  "properties": {
    "addr:full": "1346 Dellwood Ave Columbus OH 43227",
    "addr:housenumber": "1346",
    "addr:postcode": "43227",
    "addr:street": "Dellwood Ave",
    "iso:country": "US",
    "sg:address": "1346 Dellwood Ave",
    "sg:city": "Columbus",
    "sg:classifiers": [
      {
        "category": "Social Services",
        "type": "Services"
      }
    ],
    "sg:phone": "+1 614 262 6482",
    "sg:postcode": "43227",
    "sg:province": "OH",
    "sg:tags": [
      "organization",
      "welfare"
    ],
    "wof:name": "Project Exodus",
    "wof:placetype": "venue"
  },
  "geometry": {"coordinates":[-82.892271,39.946344],"type":"Point"}
}
