{
  "type": "Feature",
  "properties": {
    "addr:full":"3779 Sullivant Ave Columbus OH 43228",
    "addr:housenumber":"3779",
    "addr:postcode":"43228",
    "addr:street":"Sullivant Ave",
    "iso:country":"US",
    "sg:address":"3779 Sullivant Ave",
    "sg:city":"Columbus",
    "sg:classifiers":[
        {
            "category":"Manufacturing",
            "subcategory":"Printing",
            "type":"Manufacturing & Wholesale Goods"
        }
    ],
    "sg:phone":"+1 614 276 8366",
    "sg:postcode":"43228",
    "sg:province":"OH",
    "sg:tags":[
        "printer"
    ],
    "wof:name":"PRO Printing",
    "wof:placetype":"venue"
},
  "geometry": {"coordinates":[-83.097661,39.942415],"type":"Point"}
}