{
  "type": "Feature",
  "properties": {
    "iso:country":"US",
    "sg:address":"1358 Cherry Bottom Rd",
    "sg:city":"Columbus",
    "sg:classifiers":[
        {
            "category":"Professional",
            "subcategory":"Business Services",
            "type":"Services"
        }
    ],
    "sg:phone":"+1 614 475 1500",
    "sg:postcode":"43230",
    "sg:province":"OH",
    "sg:tags":[
        "auctioneer"
    ],
    "wof:name":"Got Stuff",
    "wof:placetype":"venue"
},
  "geometry": {"coordinates":[-82.87556,40.037339],"type":"Point"}
}