{
  "type": "Feature",
  "properties": {
    "iso:country":"US",
    "sg:address":"5732 Westbourne Ave",
    "sg:city":"Columbus",
    "sg:classifiers":[
        {
            "category":"Building & Trades",
            "subcategory":"Electrical",
            "type":"Services"
        }
    ],
    "sg:phone":"+1 614 367 9834",
    "sg:postcode":"43213",
    "sg:province":"OH",
    "sg:tags":[
        "communications",
        "contractor"
    ],
    "sg:website":"www.selecttech.com",
    "wof:name":"Etech Inc",
    "wof:placetype":"venue"
},
  "geometry": {"coordinates":[-82.850341,39.984471],"type":"Point"}
}