{
  "type": "Feature",
  "properties": {
    "addr:full":"4141 Rockside Rd Cleveland OH 44131",
    "addr:housenumber":"4141",
    "addr:postcode":"44131",
    "addr:street":"Rockside Rd",
    "iso:country":"US",
    "sg:address":"4141 Rockside Rd",
    "sg:city":"Cleveland",
    "sg:classifiers":[
        {
            "category":"Professional",
            "subcategory":"Accounting & Tax Preparation",
            "type":"Services"
        }
    ],
    "sg:phone":"+1 216 524 2920",
    "sg:postcode":"44131",
    "sg:province":"OH",
    "sg:tags":[
        "payroll"
    ],
    "wof:name":"Paydaze Inc",
    "wof:placetype":"venue"
},
  "geometry": {"coordinates":[-81.663586,41.400076],"type":"Point"}
}