{
  "type": "Feature",
  "properties": {
    "addr:full":"7187 Rd 209 Oakwood OH 45873",
    "addr:housenumber":"7187",
    "addr:postcode":"45873",
    "addr:street":"Rd 209",
    "iso:country":"US",
    "sg:address":"7187 Rd 209",
    "sg:city":"Oakwood",
    "sg:classifiers":[
        {
            "category":"Building & Trades",
            "subcategory":"Construction",
            "type":"Services"
        }
    ],
    "sg:phone":"+1 419 594 2987",
    "sg:postcode":"45873",
    "sg:province":"OH",
    "sg:tags":[
        "excavation",
        "contractor"
    ],
    "wof:name":"T & K Excavating",
    "wof:placetype":"venue"
},
  "geometry": {"coordinates":[-84.36127500000001,41.08487],"type":"Point"}
}