{
  "type": "Feature",
  "properties": {
    "addr:full": "229 W 7th St Cincinnati OH 45202",
    "addr:housenumber": "229",
    "addr:postcode": "45202",
    "addr:street": "W 7Th St",
    "iso:country": "US",
    "sg:address": "229 W 7th St",
    "sg:city": "Cincinnati",
    "sg:classifiers": [
      {
        "category": "Professional",
        "subcategory": "Business Services",
        "type": "Services"
      }
    ],
    "sg:phone": "+1 513 784 5900",
    "sg:postcode": "45202",
    "sg:province": "OH",
    "sg:tags": [
      "telemarketing"
    ],
    "wof:name": "Convergys Corp",
    "wof:placetype": "venue"
  },
  "geometry": {"coordinates":[-84.516958,39.103129],"type":"Point"}
}
