{
  "type": "Feature",
  "properties": {
    "addr:full":"19 N Garden St Norwalk OH 44857",
    "addr:housenumber":"19",
    "addr:postcode":"44857",
    "addr:street":"N Garden St",
    "iso:country":"US",
    "sg:address":"19 N Garden St",
    "sg:city":"Norwalk",
    "sg:phone":"+1 419 668 0322",
    "sg:postcode":"44857",
    "sg:province":"OH",
    "sg:tags":[
        "farm",
        "corn",
        "wheat",
        "soybean"
    ],
    "wof:name":"Laura Bundschuh",
    "wof:placetype":"venue"
},
  "geometry": {"coordinates":[-82.60771099999999,41.247229],"type":"Point"}
}