{
  "type": "Feature",
  "properties": {
    "addr:full": "3006 Harrison Ave Cincinnati OH 45211",
    "addr:housenumber": "3006",
    "addr:postcode": "45211",
    "addr:street": "Harrison Ave",
    "iso:country": "US",
    "sg:address": "3006 Harrison Ave",
    "sg:city": "Cincinnati",
    "sg:classifiers": [
      {
        "category": "Retail",
        "subcategory": "Laundry \u0026 Dry Cleaning",
        "type": "Services"
      }
    ],
    "sg:phone": "+1 513 661 3230",
    "sg:postcode": "45211",
    "sg:province": "OH",
    "sg:tags": [
      "cleaners"
    ],
    "wof:name": "Sontag Cleaners Inc",
    "wof:placetype": "venue"
  },
  "geometry": {"coordinates":[-84.597757,39.147896],"type":"Point"}
}
