{
  "type": "Feature",
  "properties": {
    "iso:country":"US",
    "sg:address":"8150 Market Ave N",
    "sg:city":"Canton",
    "sg:classifiers":[
        {
            "category":"Freight",
            "type":"Transportation"
        },
        {
            "category":"Building & Trades",
            "subcategory":"Construction",
            "type":"Services"
        }
    ],
    "sg:phone":"+1 330 499 4002",
    "sg:postcode":"44721",
    "sg:province":"OH",
    "sg:tags":[
        "home",
        "commercial",
        "storage",
        "family",
        "contractor"
    ],
    "wof:name":"Stark Mini Storage",
    "wof:placetype":"venue"
},
  "geometry": {"coordinates":[-81.362184,40.905635],"type":"Point"}
}