{
  "type": "Feature",
  "properties": {
    "iso:country":"US",
    "sg:address":"691 Fleming Rd",
    "sg:city":"Cincinnati",
    "sg:classifiers":[
        {
            "category":"Place Of Worship",
            "subcategory":"Church",
            "type":"Public Place"
        },
        {
            "category":"Place Of Worship",
            "type":"Public Place"
        }
    ],
    "sg:phone":"+1 513 522 2780",
    "sg:postcode":"45231",
    "sg:province":"OH",
    "sg:tags":[
        "testament",
        "christ-new",
        "churches-church",
        "christ"
    ],
    "sg:website":"http://www.flemingroaducc.org",
    "wof:name":"Fleming Road United Church Of Christ",
    "wof:placetype":"venue"
},
  "geometry": {"coordinates":[-84.505129,39.236266],"type":"Point"}
}