{
  "type": "Feature",
  "properties": {
    "iso:country":"US",
    "sg:address":"30 N Main St",
    "sg:city":"Kenton",
    "sg:classifiers":[
        {
            "category":"Shopping",
            "subcategory":"Books",
            "type":"Retail Goods"
        }
    ],
    "sg:phone":"+1 419 673 0983",
    "sg:postcode":"43326",
    "sg:province":"OH",
    "wof:name":"Todd & Betty Augsburger",
    "wof:placetype":"venue"
},
  "geometry": {"coordinates":[-83.607872,40.647862],"type":"Point"}
}