{
  "type": "Feature",
  "properties": {
    "addr:full": "23067 Rd 110 Oakwood OH 45873",
    "addr:housenumber": "23067",
    "addr:postcode": "45873",
    "addr:street": "Rd 110",
    "iso:country": "US",
    "sg:address": "23067 Rd 110",
    "sg:city": "Oakwood",
    "sg:classifiers": [
      {
        "category": "Personal",
        "subcategory": "Beauty Salon",
        "type": "Services"
      }
    ],
    "sg:phone": "+1 419 594 3301",
    "sg:postcode": "45873",
    "sg:province": "OH",
    "wof:name": "Rain Bow Hair Care",
    "wof:placetype": "venue"
  },
  "geometry": {"coordinates":[-84.365417,41.107087],"type":"Point"}
}
