{
  "type": "Feature",
  "properties": {
    "addr:full":"4660 Duke Dr Mason OH 45040",
    "addr:housenumber":"4660",
    "addr:postcode":"45040",
    "addr:street":"Duke Dr",
    "iso:country":"US",
    "sg:address":"4660 Duke Dr",
    "sg:city":"Mason",
    "sg:classifiers":[
        {
            "category":"Professional",
            "subcategory":"Computer Services",
            "type":"Services"
        }
    ],
    "sg:phone":"+1 513 492 5800",
    "sg:postcode":"45040",
    "sg:province":"OH",
    "sg:tags":[
        "development",
        "application",
        "software"
    ],
    "wof:name":"Domin-8 Entp Solutions LLC",
    "wof:placetype":"venue"
},
  "geometry": {"coordinates":[-84.309916,39.301167],"type":"Point"}
}