{
  "type": "Feature",
  "properties": {
    "addr:full": "200 Industrial Pkwy Chagrin Falls OH 44022",
    "addr:housenumber": "200",
    "addr:postcode": "44022",
    "addr:street": "Industrial Pkwy",
    "iso:country": "US",
    "sg:address": "200 Industrial Pkwy",
    "sg:city": "Chagrin Falls",
    "sg:classifiers": [
      {
        "category": "Personal",
        "type": "Services"
      }
    ],
    "sg:phone": "+1 440 247 7772",
    "sg:postcode": "44022",
    "sg:province": "OH",
    "sg:tags": [
      "therapist",
      "massage"
    ],
    "wof:name": "John E's Massage Works",
    "wof:placetype": "venue"
  },
  "geometry": {"coordinates":[-81.371363,41.424742],"type":"Point"}
}
