{
  "type": "Feature",
  "properties": {
    "addr:full": "2575 W Hume Rd Lima OH 45806",
    "addr:housenumber": "2575",
    "addr:postcode": "45806",
    "addr:street": "W Hume Rd",
    "iso:country": "US",
    "sg:address": "2575 W Hume Rd",
    "sg:city": "Lima",
    "sg:classifiers": [
      {
        "category": "Building \u0026 Trades",
        "subcategory": "Construction",
        "type": "Services"
      }
    ],
    "sg:phone": "+1 419 645 6555",
    "sg:postcode": "45806",
    "sg:province": "OH",
    "sg:tags": [
      "contractor"
    ],
    "wof:name": "Jerry Rolston",
    "wof:placetype": "venue"
  },
  "geometry": {"coordinates":[-84.147953,40.664543],"type":"Point"}
}
