{
  "type": "Feature",
  "properties": {
    "iso:country":"US",
    "sg:address":"702 George St",
    "sg:city":"Van Wert",
    "sg:classifiers":[
        {
            "category":"Building & Trades",
            "subcategory":"Landscaping Services",
            "type":"Services"
        }
    ],
    "sg:phone":"+1 419 238 2949",
    "sg:postcode":"45891",
    "sg:province":"OH",
    "sg:tags":[
        "tree"
    ],
    "wof:name":"Van WERT Tree Svc",
    "wof:placetype":"venue"
},
  "geometry": {"coordinates":[-84.592118,40.86892],"type":"Point"}
}