{
  "type": "Feature",
  "properties": {
    "iso:country":"US",
    "sg:address":"2177 Slack Rd",
    "sg:city":"Saint Paris",
    "sg:classifiers":[
        {
            "category":"Building & Trades",
            "subcategory":"Construction",
            "type":"Services"
        }
    ],
    "sg:phone":"+1 937 857 9390",
    "sg:postcode":"43072",
    "sg:province":"OH",
    "sg:tags":[
        "house"
    ],
    "wof:name":"Weddell Remodeling",
    "wof:placetype":"venue"
},
  "geometry": {"coordinates":[-84.010301,40.092942],"type":"Point"}
}