{
  "type": "Feature",
  "properties": {
    "addr:full":"4400 Marburg Ave Cincinnati OH 45209",
    "addr:housenumber":"4400",
    "addr:postcode":"45209",
    "addr:street":"Marburg Ave",
    "iso:country":"US",
    "sg:address":"4400 Marburg Ave",
    "sg:city":"Cincinnati",
    "sg:classifiers":[
        {
            "category":"Wholesale",
            "subcategory":"Furniture",
            "type":"Manufacturing & Wholesale Goods"
        }
    ],
    "sg:phone":"+1 513 321 8813",
    "sg:postcode":"45209",
    "sg:province":"OH",
    "wof:name":"Inner Applications",
    "wof:placetype":"venue"
},
  "geometry": {"coordinates":[-84.42543999999999,39.155581],"type":"Point"}
}