{
  "type": "Feature",
  "properties": {
    "addr:full": "33614 Saint Sharbel Dr Avon OH 44011",
    "addr:housenumber": "33614",
    "addr:postcode": "44011",
    "addr:street": "Saint Sharbel Dr",
    "iso:country": "US",
    "sg:address": "33614 Saint Sharbel Dr",
    "sg:city": "Avon",
    "sg:classifiers": [
      {
        "category": "Health Services",
        "subcategory": "Doctor",
        "type": "Services"
      }
    ],
    "sg:phone": "+1 216 671 5452",
    "sg:postcode": "44011",
    "sg:province": "OH",
    "sg:tags": [
      "dentist"
    ],
    "wof:name": "Lakewood Dental Care",
    "wof:placetype": "venue"
  },
  "geometry": {"coordinates":[-81.992412,41.425947],"type":"Point"}
}
