{
  "type": "Feature",
  "properties": {
    "addr:full":"4682 Webster Rd Centerburg OH 43011",
    "addr:housenumber":"4682",
    "addr:postcode":"43011",
    "addr:street":"Webster Rd",
    "iso:country":"US",
    "sg:address":"4682 Webster Rd",
    "sg:city":"Centerburg",
    "sg:classifiers":[
        {
            "category":"Building & Trades",
            "subcategory":"Electrical",
            "type":"Services"
        }
    ],
    "sg:phone":"+1 740 625 7611",
    "sg:postcode":"43011",
    "sg:province":"OH",
    "sg:tags":[
        "electrical",
        "contractor"
    ],
    "wof:name":"Electric Moon Home Services",
    "wof:placetype":"venue"
},
  "geometry": {"coordinates":[-82.638921,40.303165],"type":"Point"}
}