{
  "type": "Feature",
  "properties": {
    "iso:country":"US",
    "sg:address":"6820 Wooster Pike",
    "sg:city":"Cincinnati",
    "sg:classifiers":[
        {
            "category":"Retail",
            "subcategory":"Portrait Studio",
            "type":"Services"
        }
    ],
    "sg:phone":"+1 513 271 3113",
    "sg:postcode":"45227",
    "sg:province":"OH",
    "sg:tags":[
        "photography"
    ],
    "sg:website":"www.robertflischel.com",
    "wof:name":"Robert A Flischel Photography",
    "wof:placetype":"venue"
},
  "geometry": {"coordinates":[-84.375277,39.145251],"type":"Point"}
}