{
  "type": "Feature",
  "properties": {
    "addr:full": "2544 Forest Home Ave Dayton OH 45404",
    "addr:housenumber": "2544",
    "addr:postcode": "45404",
    "addr:street": "Forest Home Ave",
    "iso:country": "US",
    "sg:address": "2544 Forest Home Ave",
    "sg:city": "Dayton",
    "sg:classifiers": [
      {
        "category": "Organizations",
        "subcategory": "Religious Organization",
        "type": "Services"
      }
    ],
    "sg:phone": "+1 937 890 3624",
    "sg:postcode": "45404",
    "sg:province": "OH",
    "sg:tags": [
      "church"
    ],
    "wof:name": "Victory Heights Church Of God",
    "wof:placetype": "venue"
  },
  "geometry": {"coordinates":[-84.140026,39.796167],"type":"Point"}
}
