{
  "type": "Feature",
  "properties": {
    "addr:full": "909 S Scioto St Circleville OH 43113",
    "addr:housenumber": "909",
    "addr:postcode": "43113",
    "addr:street": "S Scioto St",
    "iso:country": "US",
    "sg:address": "909 S Scioto St",
    "sg:city": "Circleville",
    "sg:classifiers": [
      {
        "category": "Freight",
        "type": "Transportation"
      }
    ],
    "sg:phone": "+1 740 474 6575",
    "sg:postcode": "43113",
    "sg:province": "OH",
    "sg:tags": [
      "soil",
      "trucking",
      "preparation",
      "p",
      "operator",
      "local"
    ],
    "wof:name": "F C Russell Lime \u0026 Fertilizer",
    "wof:placetype": "venue"
  },
  "geometry": {"coordinates":[-82.952639,39.593329],"type":"Point"}
}
