{
  "type": "Feature",
  "properties": {
    "addr:full":"171 Kenmore Ave SE Warren OH 44483",
    "addr:housenumber":"171",
    "addr:postcode":"44483",
    "addr:street":"Kenmore Ave Se",
    "iso:country":"US",
    "sg:address":"171 Kenmore Ave SE",
    "sg:city":"Warren",
    "sg:classifiers":[
        {
            "category":"Shopping",
            "subcategory":"Florist",
            "type":"Retail Goods"
        }
    ],
    "sg:phone":"+1 330 394 3915",
    "sg:postcode":"44483",
    "sg:province":"OH",
    "wof:name":"Laura Flowers",
    "wof:placetype":"venue"
},
  "geometry": {"coordinates":[-80.78801,41.235218],"type":"Point"}
}