{
  "type": "Feature",
  "properties": {
    "iso:country":"US",
    "sg:address":"255 Mc Cormick Pl",
    "sg:city":"Cincinnati",
    "sg:classifiers":[
        {
            "category":"Professional",
            "type":"Services"
        }
    ],
    "sg:phone":"+1 513 421 3671",
    "sg:postcode":"45219",
    "sg:province":"OH",
    "sg:tags":[
        "establishment"
    ],
    "wof:name":"Cincinnati Kayaks Downtown",
    "wof:placetype":"venue"
},
  "geometry": {"coordinates":[-84.50752900000001,39.124592],"type":"Point"}
}