{
  "type": "Feature",
  "properties": {
    "iso:country":"US",
    "sg:address":"10616 Sheehan Rd",
    "sg:city":"Centerville",
    "sg:classifiers":[
        {
            "category":"Professional",
            "subcategory":"Secretarial Services",
            "type":"Services"
        }
    ],
    "sg:phone":"+1 937 885 7667",
    "sg:postcode":"45458",
    "sg:province":"OH",
    "sg:tags":[
        "reporting",
        "court"
    ],
    "wof:name":"Terri's Office",
    "wof:placetype":"venue"
},
  "geometry": {"coordinates":[-84.186117,39.58444],"type":"Point"}
}