{
  "type": "Feature",
  "properties": {
    "addr:full": "10616 Sheehan Rd Centerville OH 45458",
    "addr:housenumber": "10616",
    "addr:postcode": "45458",
    "addr:street": "Sheehan Rd",
    "iso:country": "US",
    "sg:address": "10616 Sheehan Rd",
    "sg:city": "Centerville",
    "sg:classifiers": [
      {
        "category": "Professional",
        "subcategory": "Secretarial Services",
        "type": "Services"
      }
    ],
    "sg:phone": "+1 937 885 7667",
    "sg:postcode": "45458",
    "sg:province": "OH",
    "sg:tags": [
      "reporting",
      "court"
    ],
    "wof:name": "Terri's Office",
    "wof:placetype": "venue"
  },
  "geometry": {"coordinates":[-84.186117,39.58444],"type":"Point"}
}
