{
  "type": "Feature",
  "properties": {
    "iso:country":"US",
    "sg:address":"417 N Main St",
    "sg:city":"Bluffton",
    "sg:classifiers":[
        {
            "category":"Personal",
            "subcategory":"Beauty Salon",
            "type":"Services"
        }
    ],
    "sg:phone":"+1 419 358 0001",
    "sg:postcode":"45817",
    "sg:province":"OH",
    "sg:tags":[
        "manicuring"
    ],
    "wof:name":"Nails By Joan",
    "wof:placetype":"venue"
},
  "geometry": {"coordinates":[-83.888156,40.896255],"type":"Point"}
}