{
  "type": "Feature",
  "properties": {
    "iso:country":"US",
    "sg:address":"5870 Cook Rd",
    "sg:city":"Milford",
    "sg:classifiers":[
        {
            "category":"Home & Garden",
            "subcategory":"Building Materials",
            "type":"Retail Goods"
        },
        {
            "category":"Building & Trades",
            "subcategory":"Construction",
            "type":"Services"
        }
    ],
    "sg:phone":"+1 513 965 9800",
    "sg:postcode":"45150",
    "sg:province":"OH",
    "sg:tags":[
        "lumber",
        "laying",
        "floor",
        "contractor"
    ],
    "wof:name":"First Impressions Hardwood Flo",
    "wof:placetype":"venue"
},
  "geometry": {"coordinates":[-84.24870799999999,39.193029],"type":"Point"}
}