{
  "type": "Feature",
  "properties": {
    "addr:full": "12765 State Rte 34 Bryan OH 43506",
    "addr:housenumber": "12765",
    "addr:postcode": "43506",
    "addr:street": "State Rte 34",
    "iso:country": "US",
    "sg:address": "12765 State Rte 34",
    "sg:city": "Bryan",
    "sg:classifiers": [
      {
        "category": "Retail",
        "subcategory": "Veterinary Services",
        "type": "Services"
      }
    ],
    "sg:phone": "+1 419 636 7124",
    "sg:postcode": "43506",
    "sg:province": "OH",
    "sg:tags": [
      "hospital",
      "animal"
    ],
    "wof:name": "Bryan Area Animal Hospital",
    "wof:placetype": "venue"
  },
  "geometry": {"coordinates":[-84.578824,41.478844],"type":"Point"}
}
