{
  "type": "Feature",
  "properties": {
    "iso:country":"US",
    "sg:address":"417 Monroe St",
    "sg:city":"East Liverpool",
    "sg:classifiers":[
        {
            "category":"Building & Trades",
            "subcategory":"Construction",
            "type":"Services"
        }
    ],
    "sg:phone":"+1 330 386 0365",
    "sg:postcode":"43920",
    "sg:province":"OH",
    "sg:tags":[
        "contractor"
    ],
    "wof:name":"Seilkop Contractor",
    "wof:placetype":"venue"
},
  "geometry": {"coordinates":[-80.585548,40.620941],"type":"Point"}
}