{
  "type": "Feature",
  "properties": {
    "addr:full":"5627 Kugler Mill Rd Cincinnati OH 45236",
    "addr:housenumber":"5627",
    "addr:postcode":"45236",
    "addr:street":"Kugler Mill Rd",
    "iso:country":"US",
    "sg:address":"5627 Kugler Mill Rd",
    "sg:city":"Cincinnati",
    "sg:classifiers":[
        {
            "category":"Wholesale",
            "subcategory":"Stationery",
            "type":"Manufacturing & Wholesale Goods"
        }
    ],
    "sg:phone":"+1 513 793 2529",
    "sg:postcode":"45236",
    "sg:province":"OH",
    "sg:tags":[
        "packaging",
        "material"
    ],
    "wof:name":"Sealright Inc",
    "wof:placetype":"venue"
},
  "geometry": {"coordinates":[-84.37501899999999,39.2105],"type":"Point"}
}