{
  "type": "Feature",
  "properties": {
    "iso:country":"US",
    "sg:address":"5000 Madison Ave",
    "sg:city":"Hamilton",
    "sg:classifiers":[
        {
            "category":"Restaurant",
            "type":"Food & Drink"
        }
    ],
    "sg:phone":"+1 513 887 5096",
    "sg:postcode":"45015",
    "sg:province":"OH",
    "wof:name":"Hamilton City Sch Cafeteria",
    "wof:placetype":"venue"
},
  "geometry": {"coordinates":[-84.555331,39.353996],"type":"Point"}
}