{
  "type": "Feature",
  "properties": {
    "addr:full":"6395 Stonebridge St Columbus OH 43229",
    "addr:housenumber":"6395",
    "addr:postcode":"43229",
    "addr:street":"Stonebridge St",
    "iso:country":"US",
    "sg:address":"6395 Stonebridge St",
    "sg:city":"Columbus",
    "sg:classifiers":[
        {
            "category":"Real Estate",
            "subcategory":"Real Estate Operator",
            "type":"Services"
        }
    ],
    "sg:phone":"+1 614 891 2829",
    "sg:postcode":"43229",
    "sg:province":"OH",
    "sg:tags":[
        "property",
        "lessor"
    ],
    "wof:name":"Larry Dodds Farm",
    "wof:placetype":"venue"
},
  "geometry": {"coordinates":[-82.96027100000001,40.098638],"type":"Point"}
}