{
  "type": "Feature",
  "properties": {
    "addr:full":"100 E Wilson Bridge Rd Worthington OH 43085",
    "addr:housenumber":"100",
    "addr:postcode":"43085",
    "addr:street":"E Wilson Bridge Rd",
    "iso:country":"US",
    "sg:address":"100 E Wilson Bridge Rd",
    "sg:city":"Worthington",
    "sg:classifiers":[
        {
            "category":"Building & Trades",
            "subcategory":"Construction",
            "type":"Services"
        }
    ],
    "sg:phone":"+1 614 540 2300",
    "sg:postcode":"43085",
    "sg:province":"OH",
    "sg:tags":[
        "home",
        "builder"
    ],
    "wof:name":"Jimenez Builders",
    "wof:placetype":"venue"
},
  "geometry": {"coordinates":[-83.013334,40.109727],"type":"Point"}
}