{
  "type": "Feature",
  "properties": {
    "iso:country":"US",
    "sg:address":"2926 State Road #132",
    "sg:city":"Cuyahoga Falls",
    "sg:classifiers":[
        {
            "category":"Professional",
            "subcategory":"Computer Services",
            "type":"Services"
        }
    ],
    "sg:phone":"+1 440 255 3235",
    "sg:postcode":"44223",
    "sg:province":"OH",
    "sg:website":"http://www.flexhire.com/",
    "wof:name":"Flexhire",
    "wof:placetype":"venue"
},
  "geometry": {"coordinates":[-81.508674,41.152297],"type":"Point"}
}