{
  "type": "Feature",
  "properties": {
    "addr:full": "314 Township Road 391 Toronto OH 43964",
    "addr:housenumber": "314",
    "addr:postcode": "43964",
    "addr:street": "Township Road 391",
    "iso:country": "US",
    "sg:address": "314 Township Road 391",
    "sg:city": "Toronto",
    "sg:classifiers": [
      {
        "category": "Farming",
        "subcategory": "Nursery",
        "type": "Manufacturing \u0026 Wholesale Goods"
      }
    ],
    "sg:phone": "+1 740 544 5640",
    "sg:postcode": "43964",
    "sg:province": "OH",
    "sg:tags": [
      "tree",
      "grower",
      "nursery-wholesale",
      "nurseries-plants"
    ],
    "wof:name": "James E Flowers",
    "wof:placetype": "venue"
  },
  "geometry": {"coordinates":[-80.639618,40.441094],"type":"Point"}
}
