{
  "type": "Feature",
  "properties": {
    "iso:country":"US",
    "sg:address":"314 Township Road 391",
    "sg:city":"Toronto",
    "sg:classifiers":[
        {
            "category":"Farming",
            "subcategory":"Nursery",
            "type":"Manufacturing & Wholesale Goods"
        }
    ],
    "sg:phone":"+1 740 544 5640",
    "sg:postcode":"43964",
    "sg:province":"OH",
    "sg:tags":[
        "tree",
        "grower",
        "nursery-wholesale",
        "nurseries-plants"
    ],
    "wof:name":"James E Flowers",
    "wof:placetype":"venue"
},
  "geometry": {"coordinates":[-80.639618,40.441094],"type":"Point"}
}