{
  "type": "Feature",
  "properties": {
    "addr:full":"1592 Granville Pike Lancaster OH 43130",
    "addr:housenumber":"1592",
    "addr:postcode":"43130",
    "addr:street":"Granville Pike",
    "iso:country":"US",
    "sg:address":"1592 Granville Pike",
    "sg:city":"Lancaster",
    "sg:classifiers":[
        {
            "category":"Health Services",
            "subcategory":"Hospital",
            "type":"Services"
        }
    ],
    "sg:phone":"+1 740 687 0835",
    "sg:postcode":"43130",
    "sg:province":"OH",
    "sg:tags":[
        "mental"
    ],
    "wof:name":"New Horizons Youth & Family",
    "wof:placetype":"venue"
},
  "geometry": {"coordinates":[-82.586423,39.743427],"type":"Point"}
}