{
  "type": "Feature",
  "properties": {
    "iso:country":"US",
    "sg:address":"240 S Sandusky Ave",
    "sg:city":"Bucyrus",
    "sg:classifiers":[
        {
            "category":"Insurance",
            "subcategory":"Insurance Agent",
            "type":"Services"
        }
    ],
    "sg:phone":"+1 419 562 6992",
    "sg:postcode":"44820",
    "sg:province":"OH",
    "wof:name":"Prudential Insurance Co",
    "wof:placetype":"venue"
},
  "geometry": {"coordinates":[-82.975514,40.80714],"type":"Point"}
}