{
  "type": "Feature",
  "properties": {
    "iso:country":"US",
    "sg:address":"8049 Mount Vernon Rd",
    "sg:city":"Saint Louisville",
    "sg:classifiers":[
        {
            "category":"Building & Trades",
            "subcategory":"Construction",
            "type":"Services"
        }
    ],
    "sg:phone":"+1 740 745 5323",
    "sg:postcode":"43071",
    "sg:province":"OH",
    "sg:tags":[
        "excavation",
        "contractor"
    ],
    "wof:name":"Law Excavating Inc",
    "wof:placetype":"venue"
},
  "geometry": {"coordinates":[-82.420494,40.170752],"type":"Point"}
}