{
  "type": "Feature",
  "properties": {
    "addr:full":"8049 Mount Vernon Rd Saint Louisville OH 43071",
    "addr:housenumber":"8049",
    "addr:postcode":"43071",
    "addr:street":"Mount Vernon Rd",
    "iso:country":"US",
    "sg:address":"8049 Mount Vernon Rd",
    "sg:city":"Saint Louisville",
    "sg:classifiers":[
        {
            "category":"Building & Trades",
            "subcategory":"Construction",
            "type":"Services"
        }
    ],
    "sg:phone":"+1 740 745 5323",
    "sg:postcode":"43071",
    "sg:province":"OH",
    "sg:tags":[
        "excavation",
        "contractor"
    ],
    "wof:name":"Law Excavating Inc",
    "wof:placetype":"venue"
},
  "geometry": {"coordinates":[-82.42049400000001,40.170752],"type":"Point"}
}