{
  "type": "Feature",
  "properties": {
    "iso:country":"US",
    "sg:address":"182 W Broad St",
    "sg:city":"Pataskala",
    "sg:classifiers":[
        {
            "category":"Banks & Credit Unions",
            "subcategory":"Bank",
            "type":"Services"
        }
    ],
    "sg:phone":"+1 740 927 0082",
    "sg:postcode":"43062",
    "sg:province":"OH",
    "sg:tags":[
        "savings",
        "loan",
        "association"
    ],
    "wof:name":"First Federal Savings & Loan",
    "wof:placetype":"venue"
},
  "geometry": {"coordinates":[-82.67865999999999,40.00257],"type":"Point"}
}