{
  "type": "Feature",
  "properties": {
    "iso:country":"US",
    "sg:address":"6209 Riverside Dr",
    "sg:city":"Dublin",
    "sg:classifiers":[
        {
            "category":"Banks & Credit Unions",
            "subcategory":"Financial Services",
            "type":"Services"
        }
    ],
    "sg:phone":"+1 614 761 3518",
    "sg:postcode":"43017",
    "sg:province":"OH",
    "sg:tags":[
        "company",
        "holding"
    ],
    "wof:name":"D K Holdings",
    "wof:placetype":"venue"
},
  "geometry": {"coordinates":[-83.108521,40.091984],"type":"Point"}
}