{
  "type": "Feature",
  "properties": {
    "addr:full": "630 Market St Steubenville OH 43952",
    "addr:housenumber": "630",
    "addr:postcode": "43952",
    "addr:street": "Market St",
    "iso:country": "US",
    "sg:address": "630 Market St",
    "sg:city": "Steubenville",
    "sg:classifiers": [
      {
        "category": "Insurance",
        "subcategory": "Health Insurance",
        "type": "Services"
      }
    ],
    "sg:phone": "+1 740 283 3640",
    "sg:postcode": "43952",
    "sg:province": "OH",
    "sg:tags": [
      "surgical",
      "hospitalization",
      "plan"
    ],
    "wof:name": "Bridge Benefits Inc",
    "wof:placetype": "venue"
  },
  "geometry": {"coordinates":[-80.619474,40.36123],"type":"Point"}
}
