{
  "type": "Feature",
  "properties": {
    "iso:country":"US",
    "sg:address":"18412 Saint Clair Ave",
    "sg:city":"Cleveland",
    "sg:classifiers":[
        {
            "category":"Restaurant",
            "type":"Food & Drink"
        }
    ],
    "sg:phone":"+1 216 486 4860",
    "sg:postcode":"44110",
    "sg:province":"OH",
    "sg:tags":[
        "eating"
    ],
    "wof:name":"Romitos Pizza & Ribs",
    "wof:placetype":"venue"
},
  "geometry": {"coordinates":[-81.550462,41.571976],"type":"Point"}
}