{
  "type": "Feature",
  "properties": {
    "addr:full": "18412 Saint Clair Ave Cleveland OH 44110",
    "addr:housenumber": "18412",
    "addr:postcode": "44110",
    "addr:street": "Saint Clair Ave",
    "iso:country": "US",
    "sg:address": "18412 Saint Clair Ave",
    "sg:city": "Cleveland",
    "sg:classifiers": [
      {
        "category": "Restaurant",
        "type": "Food \u0026 Drink"
      }
    ],
    "sg:phone": "+1 216 486 4860",
    "sg:postcode": "44110",
    "sg:province": "OH",
    "sg:tags": [
      "eating"
    ],
    "wof:name": "Romitos Pizza \u0026 Ribs",
    "wof:placetype": "venue"
  },
  "geometry": {"coordinates":[-81.550462,41.571976],"type":"Point"}
}
