{
  "type": "Feature",
  "properties": {
    "addr:full": "35535 Euclid Ave Willoughby OH 44094",
    "addr:housenumber": "35535",
    "addr:postcode": "44094",
    "addr:street": "Euclid Ave",
    "iso:country": "US",
    "sg:address": "35535 Euclid Ave",
    "sg:city": "Willoughby",
    "sg:classifiers": [
      {
        "category": "Shopping",
        "type": "Retail Goods"
      }
    ],
    "sg:phone": "+1 440 942 9016",
    "sg:postcode": "44094",
    "sg:province": "OH",
    "sg:tags": [
      "pet",
      "shop",
      "merchandise"
    ],
    "wof:name": "Pet Paradise",
    "wof:placetype": "venue"
  },
  "geometry": {"coordinates":[-81.433345,41.626305],"type":"Point"}
}
