{
  "type": "Feature",
  "properties": {
    "addr:full":"1289 Ashland Rd Mansfield OH 44905",
    "addr:housenumber":"1289",
    "addr:postcode":"44905",
    "addr:street":"Ashland Rd",
    "iso:country":"US",
    "sg:address":"1289 Ashland Rd",
    "sg:city":"Mansfield",
    "sg:classifiers":[
        {
            "category":"Restaurant",
            "type":"Food & Drink"
        }
    ],
    "sg:menulink":"http://www.allmenus.com/oh/madison/245186-fatdaddys-house-of-bones/menu/",
    "sg:phone":"+1 419 589 6555",
    "sg:postcode":"44905",
    "sg:province":"OH",
    "sg:tags":[
        "barbecue",
        "american"
    ],
    "wof:name":"Fatdaddy's House Of Bones ",
    "wof:placetype":"venue"
},
  "geometry": {"coordinates":[-82.468592,40.780282],"type":"Point"}
}