{
  "type": "Feature",
  "properties": {
    "addr:full": "603 N Washington St Van Wert OH 45891",
    "addr:housenumber": "603",
    "addr:postcode": "45891",
    "addr:street": "N Washington St",
    "iso:country": "US",
    "sg:address": "603 N Washington St",
    "sg:city": "Van Wert",
    "sg:classifiers": [
      {
        "category": "Wholesale",
        "subcategory": "Durable Goods \u0026 Equipment",
        "type": "Manufacturing \u0026 Wholesale Goods"
      }
    ],
    "sg:phone": "+1 419 238 4597",
    "sg:postcode": "45891",
    "sg:province": "OH",
    "wof:name": "Time Well Spent Antiques",
    "wof:placetype": "venue"
  },
  "geometry": {"coordinates":[-84.583168,40.875656],"type":"Point"}
}
