{
  "type": "Feature",
  "properties": {
    "addr:full": "3940 Foxtail Trl Copley OH 44321",
    "addr:housenumber": "3940",
    "addr:postcode": "44321",
    "addr:street": "Foxtail Trl",
    "iso:country": "US",
    "sg:address": "3940 Foxtail Trl",
    "sg:city": "Copley",
    "sg:classifiers": [
      {
        "category": "Professional",
        "type": "Services"
      }
    ],
    "sg:phone": "+1 330 670 5207",
    "sg:postcode": "44321",
    "sg:province": "OH",
    "sg:tags": [
      "establishment"
    ],
    "wof:name": "Oncor",
    "wof:placetype": "venue"
  },
  "geometry": {"coordinates":[-81.660303,41.107607],"type":"Point"}
}
