{
  "type": "Feature",
  "properties": {
    "addr:full":"8353 Mentor Ave Mentor OH 44060",
    "addr:housenumber":"8353",
    "addr:postcode":"44060",
    "addr:street":"Mentor Ave",
    "iso:country":"US",
    "sg:address":"8353 Mentor Ave",
    "sg:city":"Mentor",
    "sg:classifiers":[
        {
            "category":"Home & Garden",
            "subcategory":"Home Furnishings",
            "type":"Retail Goods"
        }
    ],
    "sg:phone":"+1 440 255 5103",
    "sg:postcode":"44060",
    "sg:province":"OH",
    "sg:tags":[
        "curtain",
        "made",
        "drapery"
    ],
    "sg:website":"www.budgetblinds.com",
    "wof:name":"Budget Blinds",
    "wof:placetype":"venue"
},
  "geometry": {"coordinates":[-81.340858,41.66627],"type":"Point"}
}