{
  "type": "Feature",
  "properties": {
    "iso:country":"US",
    "sg:address":"11896 Greyfriars Cir",
    "sg:city":"Cleveland",
    "sg:classifiers":[
        {
            "category":"Wholesale",
            "subcategory":"Electrical",
            "type":"Manufacturing & Wholesale Goods"
        }
    ],
    "sg:phone":"+1 440 582 8788",
    "sg:postcode":"44133",
    "sg:province":"OH",
    "sg:tags":[
        "alarm",
        "burglar",
        "system"
    ],
    "wof:name":"Sutton Security Systems Inc",
    "wof:placetype":"venue"
},
  "geometry": {"coordinates":[-81.771236,41.281552],"type":"Point"}
}