{
  "type": "Feature",
  "properties": {
    "addr:full": "105 E Auglaize St Wapakoneta OH 45895",
    "addr:housenumber": "105",
    "addr:postcode": "45895",
    "addr:street": "E Auglaize St",
    "iso:country": "US",
    "sg:address": "105 E Auglaize St",
    "sg:city": "Wapakoneta",
    "sg:classifiers": [
      {
        "category": "Shopping",
        "subcategory": "Gifts \u0026 Souvenirs",
        "type": "Retail Goods"
      }
    ],
    "sg:phone": "+1 419 739 9454",
    "sg:postcode": "45895",
    "sg:province": "OH",
    "wof:name": "Whispering Willow",
    "wof:placetype": "venue"
  },
  "geometry": {"coordinates":[-84.192366,40.570448],"type":"Point"}
}
