{
  "type": "Feature",
  "properties": {
    "addr:full":"2360 Norwood Ave Cincinnati OH 45212",
    "addr:housenumber":"2360",
    "addr:postcode":"45212",
    "addr:street":"Norwood Ave",
    "iso:country":"US",
    "sg:address":"2360 Norwood Ave",
    "sg:city":"Cincinnati",
    "sg:classifiers":[
        {
            "category":"Organizations",
            "subcategory":"Labor Organization",
            "type":"Services"
        }
    ],
    "sg:phone":"+1 513 407 2653",
    "sg:postcode":"45212",
    "sg:province":"OH",
    "wof:name":"IUEAFL-Cio",
    "wof:placetype":"venue"
},
  "geometry": {"coordinates":[-84.446563,39.164237],"type":"Point"}
}