{
  "type": "Feature",
  "properties": {
    "addr:full": "8485 Herbert Rd Canfield OH 44406",
    "addr:housenumber": "8485",
    "addr:postcode": "44406",
    "addr:street": "Herbert Rd",
    "iso:country": "US",
    "sg:address": "8485 Herbert Rd",
    "sg:city": "Canfield",
    "sg:classifiers": [
      {
        "category": "Freight",
        "type": "Transportation"
      }
    ],
    "sg:phone": "+1 330 716 0651",
    "sg:postcode": "44406",
    "sg:province": "OH",
    "sg:tags": [
      "general"
    ],
    "wof:name": "Allstore Self Storage",
    "wof:placetype": "venue"
  },
  "geometry": {"coordinates":[-80.808665,41.046654],"type":"Point"}
}
