{
  "type": "Feature",
  "properties": {
    "iso:country":"US",
    "sg:address":"26963 Lorain Rd",
    "sg:city":"North Olmsted",
    "sg:classifiers":[
        {
            "category":"Bakery",
            "type":"Food & Drink"
        },
        {
            "category":"Coffee & Tea",
            "type":"Food & Drink"
        },
        {
            "category":"Bagels",
            "type":"Food & Drink"
        },
        {
            "category":"Donuts",
            "type":"Food & Drink"
        }
    ],
    "sg:menulink":"http://www.allmenus.com/oh/north-olmsted/143953-dunkin-donuts/menu/",
    "sg:phone":"+1 440 734 2272",
    "sg:postcode":"44070",
    "sg:province":"OH",
    "sg:tags":[
        "american",
        "diner",
        "pastry"
    ],
    "wof:name":"Dunkin' Donuts",
    "wof:placetype":"venue"
},
  "geometry": {"coordinates":[-81.920332,41.417419],"type":"Point"}
}