{
  "type": "Feature",
  "properties": {
    "addr:full": "51790 Main St Jerusalem OH 43747",
    "addr:housenumber": "51790",
    "addr:postcode": "43747",
    "addr:street": "Main St",
    "iso:country": "US",
    "sg:address": "51790 Main St",
    "sg:city": "Jerusalem",
    "sg:classifiers": [
      {
        "category": "Building \u0026 Trades",
        "subcategory": "Construction",
        "type": "Services"
      }
    ],
    "sg:phone": "+1 740 926 1738",
    "sg:postcode": "43747",
    "sg:province": "OH",
    "sg:tags": [
      "excavation",
      "contractor"
    ],
    "wof:name": "Consolidated Services",
    "wof:placetype": "venue"
  },
  "geometry": {"coordinates":[-81.096452,39.851756],"type":"Point"}
}
