{
  "type": "Feature",
  "properties": {
    "addr:full":"905 Carnegie Ave Akron OH 44314",
    "addr:housenumber":"905",
    "addr:postcode":"44314",
    "addr:street":"Carnegie Ave",
    "iso:country":"US",
    "sg:address":"905 Carnegie Ave",
    "sg:city":"Akron",
    "sg:classifiers":[
        {
            "category":"Retail",
            "subcategory":"Laundry & Dry Cleaning",
            "type":"Services"
        }
    ],
    "sg:phone":"+1 330 745 4050",
    "sg:postcode":"44314",
    "sg:province":"OH",
    "sg:tags":[
        "cleaners",
        "rug",
        "carpet"
    ],
    "wof:name":"All American Carpet Cleaning",
    "wof:placetype":"venue"
},
  "geometry": {"coordinates":[-81.560992,41.024865],"type":"Point"}
}