{
  "type": "Feature",
  "properties": {
    "iso:country":"US",
    "sg:address":"301 Harding Way E",
    "sg:city":"Galion",
    "sg:classifiers":[
        {
            "category":"Government",
            "subcategory":"Fire Station",
            "type":"Public Place"
        }
    ],
    "sg:phone":"+1 419 468 6763",
    "sg:postcode":"44833",
    "sg:province":"OH",
    "sg:tags":[
        "protection"
    ],
    "wof:name":"Fire Dept",
    "wof:placetype":"venue"
},
  "geometry": {"coordinates":[-82.785966,40.733824],"type":"Point"}
}