{
  "type": "Feature",
  "properties": {
    "addr:full":"5551 State Rte 193 Kingsville OH 44048",
    "addr:housenumber":"5551",
    "addr:postcode":"44048",
    "addr:street":"State Rte 193",
    "iso:country":"US",
    "sg:address":"5551 State Rte 193",
    "sg:city":"Kingsville",
    "sg:classifiers":[
        {
            "category":"Autos & Motor Vehicles",
            "subcategory":"Fuel & Gas Station",
            "type":"Retail Goods"
        }
    ],
    "sg:phone":"+1 440 224 2035",
    "sg:postcode":"44048",
    "sg:province":"OH",
    "sg:tags":[
        "plaza",
        "truck",
        "stops"
    ],
    "wof:name":"Kingsville Travel Ctr Inc",
    "wof:placetype":"venue"
},
  "geometry": {"coordinates":[-80.666505,41.877603],"type":"Point"}
}