{
  "type": "Feature",
  "properties": {
    "iso:country":"US",
    "sg:address":"5940 Loudon St",
    "sg:city":"Johnstown",
    "sg:classifiers":[
        {
            "category":"Sports & Exercise",
            "subcategory":"Golf",
            "type":"Entertainment"
        }
    ],
    "sg:phone":"+1 740 587 1890",
    "sg:postcode":"43031",
    "sg:province":"OH",
    "sg:tags":[
        "course"
    ],
    "wof:name":"Links At Echosprings",
    "wof:placetype":"venue"
},
  "geometry": {"coordinates":[-82.56358299999999,40.140306],"type":"Point"}
}