{
  "type": "Feature",
  "properties": {
    "iso:country":"US",
    "sg:address":"27643 River Dr",
    "sg:city":"Circleville",
    "sg:classifiers":[
        {
            "category":"Farming",
            "subcategory":"Farm",
            "type":"Manufacturing & Wholesale Goods"
        }
    ],
    "sg:phone":"+1 740 474 4156",
    "sg:postcode":"43113",
    "sg:province":"OH",
    "sg:tags":[
        "crop",
        "general"
    ],
    "wof:name":"Larry Grissom",
    "wof:placetype":"venue"
},
  "geometry": {"coordinates":[-82.987067,39.523908],"type":"Point"}
}