{
  "type": "Feature",
  "properties": {
    "addr:full": "101 N Main St Celina OH 45822",
    "addr:housenumber": "101",
    "addr:postcode": "45822",
    "addr:street": "N Main St",
    "iso:country": "US",
    "sg:address": "101 N Main St",
    "sg:city": "Celina",
    "sg:classifiers": [
      {
        "category": "Government",
        "subcategory": "Office",
        "type": "Public Place"
      }
    ],
    "sg:phone": "+1 419 586 2215",
    "sg:postcode": "45822",
    "sg:province": "OH",
    "sg:tags": [
      "board",
      "election"
    ],
    "wof:name": "Board of Elections",
    "wof:placetype": "venue"
  },
  "geometry": {"coordinates":[-84.570799,40.549516],"type":"Point"}
}
