{
  "type": "Feature",
  "properties": {
    "iso:country":"US",
    "sg:address":"8115 Monclova Rd",
    "sg:city":"Monclova",
    "sg:classifiers":[
        {
            "category":"Restaurant",
            "type":"Food & Drink"
        }
    ],
    "sg:phone":"+1 419 861 1336",
    "sg:postcode":"43542",
    "sg:province":"OH",
    "sg:tags":[
        "banquet",
        "rooms"
    ],
    "sg:website":"www.monclovacommctr.org",
    "wof:name":"Monclova Community Ctr",
    "wof:placetype":"venue"
},
  "geometry": {"coordinates":[-83.73590799999999,41.558697],"type":"Point"}
}