{
  "type": "Feature",
  "properties": {
    "addr:full": "8115 Monclova Rd Monclova OH 43542",
    "addr:housenumber": "8115",
    "addr:postcode": "43542",
    "addr:street": "Monclova Rd",
    "iso:country": "US",
    "sg:address": "8115 Monclova Rd",
    "sg:city": "Monclova",
    "sg:classifiers": [
      {
        "category": "Restaurant",
        "type": "Food \u0026 Drink"
      }
    ],
    "sg:phone": "+1 419 861 1336",
    "sg:postcode": "43542",
    "sg:province": "OH",
    "sg:tags": [
      "banquet",
      "rooms"
    ],
    "sg:website": "www.monclovacommctr.org",
    "wof:name": "Monclova Community Ctr",
    "wof:placetype": "venue"
  },
  "geometry": {"coordinates":[-83.735908,41.558697],"type":"Point"}
}
