{
  "type": "Feature",
  "properties": {
    "addr:full": "1824 Rombach Ave Wilmington OH 45177",
    "addr:housenumber": "1824",
    "addr:postcode": "45177",
    "addr:street": "Rombach Ave",
    "iso:country": "US",
    "sg:address": "1824 Rombach Ave",
    "sg:city": "Wilmington",
    "sg:classifiers": [
      {
        "category": "Autos \u0026 Motor Vehicles",
        "subcategory": "Auto Supplies",
        "type": "Retail Goods"
      },
      {
        "category": "Retail",
        "subcategory": "Auto Repair",
        "type": "Services"
      }
    ],
    "sg:phone": "+1 937 382 0958",
    "sg:postcode": "45177",
    "sg:province": "OH",
    "sg:tags": [
      "repairing",
      "automobile"
    ],
    "sg:website": "www.tirediscounter.com",
    "wof:name": "Tire Discounters Inc",
    "wof:placetype": "venue"
  },
  "geometry": {"coordinates":[-83.794518,39.45116],"type":"Point"}
}
