{
  "type": "Feature",
  "properties": {
    "addr:full": "4975 Troy Rd Springfield OH 45502",
    "addr:housenumber": "4975",
    "addr:postcode": "45502",
    "addr:street": "Troy Rd",
    "iso:country": "US",
    "sg:address": "4975 Troy Rd",
    "sg:city": "Springfield",
    "sg:classifiers": [
      {
        "category": "Building \u0026 Trades",
        "subcategory": "Construction",
        "type": "Services"
      },
      {
        "category": "Shopping",
        "subcategory": "Bicycles \u0026 Sporting Goods",
        "type": "Retail Goods"
      }
    ],
    "sg:phone": "+1 937 964 1269",
    "sg:postcode": "45502",
    "sg:province": "OH",
    "sg:tags": [
      "contractor",
      "dry wall",
      "repair"
    ],
    "wof:name": "Mike's Bikes",
    "wof:placetype": "venue"
  },
  "geometry": {"coordinates":[-83.881861,39.986669],"type":"Point"}
}
