{
  "type": "Feature",
  "properties": {
    "iso:country":"US",
    "sg:address":"3171 Magnolia Rd NW",
    "sg:city":"Magnolia",
    "sg:classifiers":[
        {
            "category":"Building & Trades",
            "subcategory":"Construction",
            "type":"Services"
        },
        {
            "category":"Wholesale",
            "subcategory":"Metals & Minerals",
            "type":"Manufacturing & Wholesale Goods"
        }
    ],
    "sg:phone":"+1 330 866 2481",
    "sg:postcode":"44643",
    "sg:province":"OH",
    "sg:tags":[
        "fabricator",
        "center"
    ],
    "sg:website":"www.whitacreengineering.com",
    "wof:name":"Whitacre Engineering Co Inc",
    "wof:placetype":"venue"
},
  "geometry": {"coordinates":[-81.292451,40.63335],"type":"Point"}
}