{
  "type": "Feature",
  "properties": {
    "addr:full": "3171 Magnolia Rd NW Magnolia OH 44643",
    "addr:housenumber": "3171",
    "addr:postcode": "44643",
    "addr:street": "Magnolia Rd Nw",
    "iso:country": "US",
    "sg:address": "3171 Magnolia Rd NW",
    "sg:city": "Magnolia",
    "sg:classifiers": [
      {
        "category": "Building \u0026 Trades",
        "subcategory": "Construction",
        "type": "Services"
      },
      {
        "category": "Wholesale",
        "subcategory": "Metals \u0026 Minerals",
        "type": "Manufacturing \u0026 Wholesale Goods"
      }
    ],
    "sg:phone": "+1 330 866 2481",
    "sg:postcode": "44643",
    "sg:province": "OH",
    "sg:tags": [
      "fabricator",
      "center"
    ],
    "sg:website": "www.whitacreengineering.com",
    "wof:name": "Whitacre Engineering Co Inc",
    "wof:placetype": "venue"
  },
  "geometry": {"coordinates":[-81.292451,40.63335],"type":"Point"}
}
