{
  "type": "Feature",
  "properties": {
    "iso:country":"US",
    "sg:address":"530 Lowell St",
    "sg:city":"Elyria",
    "sg:classifiers":[
        {
            "category":"Manufacturing",
            "subcategory":"Tools & Machinery",
            "type":"Manufacturing & Wholesale Goods"
        }
    ],
    "sg:phone":"+1 440 323 7632",
    "sg:postcode":"44035",
    "sg:province":"OH",
    "sg:tags":[
        "industrial",
        "mfg"
    ],
    "wof:name":"Silver Machine Inc",
    "wof:placetype":"venue"
},
  "geometry": {"coordinates":[-82.124555,41.375007],"type":"Point"}
}