{
  "type": "Feature",
  "properties": {
    "addr:full": "3311 Tremont Rd Columbus OH 43221",
    "addr:housenumber": "3311",
    "addr:postcode": "43221",
    "addr:street": "Tremont Rd",
    "iso:country": "US",
    "sg:address": "3311 Tremont Rd",
    "sg:city": "Columbus",
    "sg:classifiers": [
      {
        "category": "Health Services",
        "subcategory": "Doctor",
        "type": "Services"
      }
    ],
    "sg:phone": "+1 614 457 4806",
    "sg:postcode": "43221",
    "sg:province": "OH",
    "sg:tags": [
      "physician",
      "family",
      "practice",
      "surgeons",
      "medicine",
      "surgeon"
    ],
    "wof:name": "Northwest Family Physicians",
    "wof:placetype": "venue"
  },
  "geometry": {"coordinates":[-83.058006,40.02454],"type":"Point"}
}
