{
  "type": "Feature",
  "properties": {
    "iso:country":"US",
    "sg:address":"218 N Fulton St",
    "sg:city":"Wauseon",
    "sg:classifiers":[
        {
            "category":"Food & Beverages",
            "subcategory":"Groceries & Convenience Stores",
            "type":"Retail Goods"
        }
    ],
    "sg:phone":"+1 419 337 1817",
    "sg:postcode":"43567",
    "sg:province":"OH",
    "wof:name":"Sterling Food Store 101",
    "wof:placetype":"venue"
},
  "geometry": {"coordinates":[-84.141472,41.54923],"type":"Point"}
}