{
  "type": "Feature",
  "properties": {
    "addr:full": "111 S Main St Marysville OH 43040",
    "addr:housenumber": "111",
    "addr:postcode": "43040",
    "addr:street": "S Main St",
    "iso:country": "US",
    "sg:address": "111 S Main St",
    "sg:city": "Marysville",
    "sg:classifiers": [
      {
        "category": "Professional",
        "subcategory": "Accounting \u0026 Tax Preparation",
        "type": "Services"
      }
    ],
    "sg:phone": "+1 937 642 9380",
    "sg:postcode": "43040",
    "sg:province": "OH",
    "sg:tags": [
      "return",
      "filing"
    ],
    "wof:name": "H \u0026 R Block Tax Svc",
    "wof:placetype": "venue"
  },
  "geometry": {"coordinates":[-83.367009,40.236307],"type":"Point"}
}
