{
  "type": "Feature",
  "properties": {
    "iso:country":"US",
    "sg:address":"560 Blue Jay Dr",
    "sg:city":"Vandalia",
    "sg:classifiers":[
        {
            "category":"Manufacturing",
            "subcategory":"Retail Goods",
            "type":"Manufacturing & Wholesale Goods"
        }
    ],
    "sg:phone":"+1 937 264 0813",
    "sg:postcode":"45377",
    "sg:province":"OH",
    "sg:tags":[
        "product",
        "mfg"
    ],
    "wof:name":"Jay Blue Candles",
    "wof:placetype":"venue"
},
  "geometry": {"coordinates":[-84.190534,39.882026],"type":"Point"}
}