{
  "type": "Feature",
  "properties": {
    "addr:full": "560 Blue Jay Dr Vandalia OH 45377",
    "addr:housenumber": "560",
    "addr:postcode": "45377",
    "addr:street": "Blue Jay Dr",
    "iso:country": "US",
    "sg:address": "560 Blue Jay Dr",
    "sg:city": "Vandalia",
    "sg:classifiers": [
      {
        "category": "Manufacturing",
        "subcategory": "Retail Goods",
        "type": "Manufacturing \u0026 Wholesale Goods"
      }
    ],
    "sg:phone": "+1 937 264 0813",
    "sg:postcode": "45377",
    "sg:province": "OH",
    "sg:tags": [
      "product",
      "mfg"
    ],
    "wof:name": "Jay Blue Candles",
    "wof:placetype": "venue"
  },
  "geometry": {"coordinates":[-84.190534,39.882026],"type":"Point"}
}
