{
  "type": "Feature",
  "properties": {
    "addr:full": "7343 Greenfarms Dr Cincinnati OH 45224",
    "addr:housenumber": "7343",
    "addr:postcode": "45224",
    "addr:street": "Greenfarms Dr",
    "iso:country": "US",
    "sg:address": "7343 Greenfarms Dr",
    "sg:city": "Cincinnati",
    "sg:classifiers": [
      {
        "category": "Real Estate",
        "subcategory": "Real Estate Agent",
        "type": "Services"
      }
    ],
    "sg:phone": "+1 513 522 1835",
    "sg:postcode": "45224",
    "sg:province": "OH",
    "wof:name": "Sibcy Cline Realtors",
    "wof:placetype": "venue"
  },
  "geometry": {"coordinates":[-84.52424,39.211672],"type":"Point"}
}
