{
  "type": "Feature",
  "properties": {
    "addr:full":"5055 Orangelawn Dr Cincinnati OH 45238",
    "addr:housenumber":"5055",
    "addr:postcode":"45238",
    "addr:street":"Orangelawn Dr",
    "iso:country":"US",
    "sg:address":"5055 Orangelawn Dr",
    "sg:city":"Cincinnati",
    "sg:classifiers":[
        {
            "category":"Wholesale",
            "subcategory":"Medical Equipment & Supplies",
            "type":"Manufacturing & Wholesale Goods"
        }
    ],
    "sg:phone":"+1 513 922 2700",
    "sg:postcode":"45238",
    "sg:province":"OH",
    "sg:tags":[
        "medication",
        "sales"
    ],
    "wof:name":"Generations Rx Inc",
    "wof:placetype":"venue"
},
  "geometry": {"coordinates":[-84.614634,39.088696],"type":"Point"}
}