{
  "type": "Feature",
  "properties": {
    "iso:country":"US",
    "sg:address":"388 Mc Clurg Rd",
    "sg:city":"Youngstown",
    "sg:phone":"+1 330 726 4100",
    "sg:postcode":"44512",
    "sg:province":"OH",
    "sg:tags":[
        "food",
        "wholesale",
        "commercial",
        "equipment"
    ],
    "wof:name":"Hobart Sales & Service",
    "wof:placetype":"venue"
},
  "geometry": {"coordinates":[-80.645528,40.99532],"type":"Point"}
}