{
  "type": "Feature",
  "properties": {
    "addr:full": "8516 Cleveland Ave NW North Canton OH 44720",
    "addr:housenumber": "8516",
    "addr:postcode": "44720",
    "addr:street": "Cleveland Ave Nw",
    "iso:country": "US",
    "sg:address": "8516 Cleveland Ave NW",
    "sg:city": "North Canton",
    "sg:classifiers": [
      {
        "category": "Shopping",
        "subcategory": "Bicycles \u0026 Sporting Goods",
        "type": "Retail Goods"
      }
    ],
    "sg:phone": "+1 330 499 4558",
    "sg:postcode": "44720",
    "sg:province": "OH",
    "sg:tags": [
      "tackle",
      "fishing"
    ],
    "wof:name": "Kame's Sport Ctr",
    "wof:placetype": "venue"
  },
  "geometry": {"coordinates":[-81.405576,40.90808],"type":"Point"}
}
