{
  "type": "Feature",
  "properties": {
    "addr:full": "5133 Telegraph Rd Toledo OH 43612",
    "addr:housenumber": "5133",
    "addr:postcode": "43612",
    "addr:street": "Telegraph Rd",
    "iso:country": "US",
    "sg:address": "5133 Telegraph Rd",
    "sg:city": "Toledo",
    "sg:classifiers": [
      {
        "category": "Sports \u0026 Exercise",
        "subcategory": "Bowling",
        "type": "Entertainment"
      }
    ],
    "sg:phone": "+1 419 476 7775",
    "sg:postcode": "43612",
    "sg:province": "OH",
    "sg:tags": [
      "drinking",
      "center"
    ],
    "wof:name": "New Glass Bowl Lanes",
    "wof:placetype": "venue"
  },
  "geometry": {"coordinates":[-83.546523,41.711341],"type":"Point"}
}
