{
  "type": "Feature",
  "properties": {
    "iso:country":"US",
    "sg:address":"1110 Brookpark Rd",
    "sg:city":"Cleveland",
    "sg:classifiers":[
        {
            "category":"Manufacturing",
            "subcategory":"Tools & Machinery",
            "type":"Manufacturing & Wholesale Goods"
        }
    ],
    "sg:phone":"+1 216 661 5750",
    "sg:postcode":"44109",
    "sg:province":"OH",
    "sg:tags":[
        "machine",
        "mfg",
        "die",
        "access",
        "fa",
        "maker"
    ],
    "wof:name":"Capital Tool Company",
    "wof:placetype":"venue"
},
  "geometry": {"coordinates":[-81.687156,41.419444],"type":"Point"}
}