{
  "type": "Feature",
  "properties": {
    "addr:full": "3869 Darrow Rd Stow OH 44224",
    "addr:housenumber": "3869",
    "addr:postcode": "44224",
    "addr:street": "Darrow Rd",
    "iso:country": "US",
    "sg:address": "3869 Darrow Rd",
    "sg:city": "Stow",
    "sg:classifiers": [
      {
        "category": "Health Services",
        "subcategory": "Medical Lab",
        "type": "Services"
      }
    ],
    "sg:phone": "+1 330 688 4531",
    "sg:postcode": "44224",
    "sg:province": "OH",
    "sg:tags": [
      "laboratory"
    ],
    "wof:name": "Labcare",
    "wof:placetype": "venue"
  },
  "geometry": {"coordinates":[-81.440301,41.168889],"type":"Point"}
}
