{
  "type": "Feature",
  "properties": {
    "iso:country":"US",
    "sg:address":"101 E College Ave",
    "sg:city":"Westerville",
    "sg:classifiers":[
        {
            "category":"Insurance",
            "subcategory":"Insurance Agent",
            "type":"Services"
        }
    ],
    "sg:phone":"+1 614 882 7218",
    "sg:postcode":"43081",
    "sg:province":"OH",
    "wof:name":"Thomas Belpedio",
    "wof:placetype":"venue"
},
  "geometry": {"coordinates":[-82.927424,40.126277],"type":"Point"}
}