{
  "type": "Feature",
  "properties": {
    "addr:full":"2000 Western Ave Chillicothe OH 45601",
    "addr:housenumber":"2000",
    "addr:postcode":"45601",
    "addr:street":"Western Ave",
    "iso:country":"US",
    "sg:address":"2000 Western Ave",
    "sg:city":"Chillicothe",
    "sg:classifiers":[
        {
            "category":"Wholesale",
            "subcategory":"Fruits & Vegetables",
            "type":"Manufacturing & Wholesale Goods"
        }
    ],
    "sg:phone":"+1 740 772 1400",
    "sg:postcode":"45601",
    "sg:province":"OH",
    "wof:name":"North-South Produce",
    "wof:placetype":"venue"
},
  "geometry": {"coordinates":[-83.030411,39.339412],"type":"Point"}
}