{
  "type": "Feature",
  "properties": {
    "iso:country":"US",
    "sg:address":"230 Crystal Ave",
    "sg:city":"Findlay",
    "sg:classifiers":[
        {
            "category":"Manufacturing",
            "subcategory":"Metals",
            "type":"Manufacturing & Wholesale Goods"
        }
    ],
    "sg:phone":"+1 419 422 9632",
    "sg:postcode":"45840",
    "sg:province":"OH",
    "sg:tags":[
        "s",
        "industrial",
        "structural"
    ],
    "wof:name":"Sausser Steel Company",
    "wof:placetype":"venue"
},
  "geometry": {"coordinates":[-83.64500700000001,41.049132],"type":"Point"}
}