{
  "type": "Feature",
  "properties": {
    "addr:full": "230 Crystal Ave Findlay OH 45840",
    "addr:housenumber": "230",
    "addr:postcode": "45840",
    "addr:street": "Crystal Ave",
    "iso:country": "US",
    "sg:address": "230 Crystal Ave",
    "sg:city": "Findlay",
    "sg:classifiers": [
      {
        "category": "Manufacturing",
        "subcategory": "Metals",
        "type": "Manufacturing \u0026 Wholesale Goods"
      }
    ],
    "sg:phone": "+1 419 422 9632",
    "sg:postcode": "45840",
    "sg:province": "OH",
    "sg:tags": [
      "s",
      "industrial",
      "structural"
    ],
    "wof:name": "Sausser Steel Company",
    "wof:placetype": "venue"
  },
  "geometry": {"coordinates":[-83.645007,41.049132],"type":"Point"}
}
