{
  "type": "Feature",
  "properties": {
    "addr:full": "239 Drexel Pl Pickerington OH 43147",
    "addr:housenumber": "239",
    "addr:postcode": "43147",
    "addr:street": "Drexel Pl",
    "iso:country": "US",
    "sg:address": "239 Drexel Pl",
    "sg:city": "Pickerington",
    "sg:classifiers": [
      {
        "category": "Shopping",
        "subcategory": "Computers \u0026 Home Electronics",
        "type": "Retail Goods"
      }
    ],
    "sg:phone": "+1 614 833 2854",
    "sg:postcode": "43147",
    "sg:province": "OH",
    "sg:tags": [
      "antenna"
    ],
    "wof:name": "New Vision Antenna",
    "wof:placetype": "venue"
  },
  "geometry": {"coordinates":[-82.753127,39.889101],"type":"Point"}
}
