{
  "type": "Feature",
  "properties": {
    "addr:full": "1985 Oakland Park Ave Columbus OH 43224",
    "addr:housenumber": "1985",
    "addr:postcode": "43224",
    "addr:street": "Oakland Park Ave",
    "iso:country": "US",
    "sg:address": "1985 Oakland Park Ave",
    "sg:city": "Columbus",
    "sg:classifiers": [
      {
        "category": "Building \u0026 Trades",
        "subcategory": "Construction",
        "type": "Services"
      }
    ],
    "sg:phone": "+1 614 263 9378",
    "sg:postcode": "43224",
    "sg:province": "OH",
    "sg:tags": [
      "insulation",
      "heat",
      "contractor"
    ],
    "wof:name": "Gale Insulation",
    "wof:placetype": "venue"
  },
  "geometry": {"coordinates":[-82.959113,40.031018],"type":"Point"}
}
