{
  "type": "Feature",
  "properties": {
    "iso:country":"US",
    "sg:address":"147 N Main St",
    "sg:city":"Bluffton",
    "sg:classifiers":[
        {
            "category":"Real Estate",
            "subcategory":"Real Estate Agent",
            "type":"Services"
        }
    ],
    "sg:phone":"+1 419 358 7653",
    "sg:postcode":"45817",
    "sg:province":"OH",
    "wof:name":"Smiths Realty Professional",
    "wof:placetype":"venue"
},
  "geometry": {"coordinates":[-83.890351,40.89462],"type":"Point"}
}