{
  "type": "Feature",
  "properties": {
    "addr:full": "2967 Northern Woods Ln Columbus OH 43231",
    "addr:housenumber": "2967",
    "addr:postcode": "43231",
    "addr:street": "Northern Woods Ln",
    "iso:country": "US",
    "sg:address": "2967 Northern Woods Ln",
    "sg:city": "Columbus",
    "sg:classifiers": [
      {
        "category": "Insurance",
        "subcategory": "Insurance Agent",
        "type": "Services"
      }
    ],
    "sg:phone": "+1 614 890 0167",
    "sg:postcode": "43231",
    "sg:province": "OH",
    "wof:name": "Willer Insurance",
    "wof:placetype": "venue"
  },
  "geometry": {"coordinates":[-82.940356,40.083172],"type":"Point"}
}
