{
  "type": "Feature",
  "properties": {
    "iso:country":"US",
    "sg:address":"199 Portsmouth St",
    "sg:city":"Jackson",
    "sg:classifiers":[
        {
            "category":"Government",
            "subcategory":"Office",
            "type":"Public Place"
        }
    ],
    "sg:phone":"+1 740 286 4415",
    "sg:postcode":"45640",
    "sg:province":"OH",
    "sg:tags":[
        "village"
    ],
    "wof:name":"Jackson Chief Clerk's Office",
    "wof:placetype":"venue"
},
  "geometry": {"coordinates":[-82.640534,39.050894],"type":"Point"}
}