{
  "type": "Feature",
  "properties": {
    "addr:full":"5700 Wallings Rd Cleveland OH 44133",
    "addr:housenumber":"5700",
    "addr:postcode":"44133",
    "addr:street":"Wallings Rd",
    "iso:country":"US",
    "sg:address":"5700 Wallings Rd",
    "sg:city":"Cleveland",
    "sg:classifiers":[
        {
            "category":"Shopping",
            "subcategory":"Books",
            "type":"Retail Goods"
        }
    ],
    "sg:phone":"+1 440 230 1555",
    "sg:postcode":"44133",
    "sg:province":"OH",
    "sg:tags":[
        "comic"
    ],
    "wof:name":"Amazing Comics & Cards",
    "wof:placetype":"venue"
},
  "geometry": {"coordinates":[-81.726634,41.330303],"type":"Point"}
}