{
  "type": "Feature",
  "properties": {
    "addr:full": "657 Antioch Rd Oak Hill OH 45656",
    "addr:housenumber": "657",
    "addr:postcode": "45656",
    "addr:street": "Antioch Rd",
    "iso:country": "US",
    "sg:address": "657 Antioch Rd",
    "sg:city": "Oak Hill",
    "sg:classifiers": [
      {
        "category": "Manufacturing",
        "subcategory": "Lumber",
        "type": "Manufacturing \u0026 Wholesale Goods"
      }
    ],
    "sg:phone": "+1 740 682 6411",
    "sg:postcode": "45656",
    "sg:province": "OH",
    "sg:tags": [
      "logging"
    ],
    "wof:name": "Smith Farron",
    "wof:placetype": "venue"
  },
  "geometry": {"coordinates":[-82.584337,38.909609],"type":"Point"}
}
