{
  "type": "Feature",
  "properties": {
    "iso:country":"US",
    "sg:address":"618 Maple Ave",
    "sg:city":"Tiltonsville",
    "sg:classifiers":[
        {
            "category":"Building & Trades",
            "subcategory":"Construction",
            "type":"Services"
        }
    ],
    "sg:phone":"+1 740 859 4102",
    "sg:postcode":"43963",
    "sg:province":"OH",
    "sg:tags":[
        "contractor"
    ],
    "wof:name":"Dino J Lollini",
    "wof:placetype":"venue"
},
  "geometry": {"coordinates":[-80.695234,40.179024],"type":"Point"}
}