{
  "type": "Feature",
  "properties": {
    "addr:full":"315 E College St Oberlin OH 44074",
    "addr:housenumber":"315",
    "addr:postcode":"44074",
    "addr:street":"E College St",
    "iso:country":"US",
    "sg:address":"315 E College St",
    "sg:city":"Oberlin",
    "sg:classifiers":[
        {
            "category":"Building & Trades",
            "subcategory":"Construction",
            "type":"Services"
        }
    ],
    "sg:phone":"+1 440 774 8183",
    "sg:postcode":"44074",
    "sg:province":"OH",
    "sg:tags":[
        "contractor"
    ],
    "wof:name":"Brick Drive Co",
    "wof:placetype":"venue"
},
  "geometry": {"coordinates":[-82.205431,41.291421],"type":"Point"}
}