{
  "type": "Feature",
  "properties": {
    "addr:full": "744 Clarendon Rd Troy OH 45373",
    "addr:housenumber": "744",
    "addr:postcode": "45373",
    "addr:street": "Clarendon Rd",
    "iso:country": "US",
    "sg:address": "744 Clarendon Rd",
    "sg:city": "Troy",
    "sg:classifiers": [
      {
        "category": "Real Estate",
        "subcategory": "Real Estate Agent",
        "type": "Services"
      }
    ],
    "sg:phone": "+1 937 335 2133",
    "sg:postcode": "45373",
    "sg:province": "OH",
    "wof:name": "Saxton Management Service Inc",
    "wof:placetype": "venue"
  },
  "geometry": {"coordinates":[-84.229843,40.056196],"type":"Point"}
}
