{
  "type": "Feature",
  "properties": {
    "addr:full":"1810 Cranberry Rd Saint Henry OH 45883",
    "addr:housenumber":"1810",
    "addr:postcode":"45883",
    "addr:street":"Cranberry Rd",
    "iso:country":"US",
    "sg:address":"1810 Cranberry Rd",
    "sg:city":"Saint Henry",
    "sg:phone":"+1 419 925 4791",
    "sg:postcode":"45883",
    "sg:province":"OH",
    "sg:tags":[
        "farm",
        "corn",
        "dairy",
        "soybean"
    ],
    "wof:name":"Thomas Knapke",
    "wof:placetype":"venue"
},
  "geometry": {"coordinates":[-84.581174,40.397463],"type":"Point"}
}