{
  "type": "Feature",
  "properties": {
    "addr:full": "5646 Wayside Ave Cincinnati OH 45230",
    "addr:housenumber": "5646",
    "addr:postcode": "45230",
    "addr:street": "Wayside Ave",
    "iso:country": "US",
    "sg:address": "5646 Wayside Ave",
    "sg:city": "Cincinnati",
    "sg:classifiers": [
      {
        "category": "Building \u0026 Trades",
        "subcategory": "Construction",
        "type": "Services"
      }
    ],
    "sg:phone": "+1 513 232 9500",
    "sg:postcode": "45230",
    "sg:province": "OH",
    "sg:tags": [
      "masonry",
      "contractor",
      "comm",
      "brick",
      "general"
    ],
    "wof:name": "Gary Wahoff Inc",
    "wof:placetype": "venue"
  },
  "geometry": {"coordinates":[-84.408543,39.083309],"type":"Point"}
}
