{
  "type": "Feature",
  "properties": {
    "addr:full": "5222 E 119th St Cleveland OH 44125",
    "addr:housenumber": "5222",
    "addr:postcode": "44125",
    "addr:street": "E 119Th St",
    "iso:country": "US",
    "sg:address": "5222 E 119th St",
    "sg:city": "Cleveland",
    "sg:classifiers": [
      {
        "category": "Shopping",
        "subcategory": "Stationery \u0026 Office Supplies",
        "type": "Retail Goods"
      }
    ],
    "sg:phone": "+1 440 250 9112",
    "sg:postcode": "44125",
    "sg:province": "OH",
    "sg:tags": [
      "rubber",
      "stamp",
      "plastic"
    ],
    "wof:name": "Creative Block",
    "wof:placetype": "venue"
  },
  "geometry": {"coordinates":[-81.601141,41.419646],"type":"Point"}
}
