{
  "type": "Feature",
  "properties": {
    "iso:country":"US",
    "sg:address":"5222 E 119th St",
    "sg:city":"Cleveland",
    "sg:classifiers":[
        {
            "category":"Shopping",
            "subcategory":"Stationery & Office Supplies",
            "type":"Retail Goods"
        }
    ],
    "sg:phone":"+1 440 250 9112",
    "sg:postcode":"44125",
    "sg:province":"OH",
    "sg:tags":[
        "rubber",
        "stamp",
        "plastic"
    ],
    "wof:name":"Creative Block",
    "wof:placetype":"venue"
},
  "geometry": {"coordinates":[-81.601141,41.419646],"type":"Point"}
}