{
  "type": "Feature",
  "properties": {
    "addr:full": "6955 Worthington Galena Rd Columbus OH 43085",
    "addr:housenumber": "6955",
    "addr:postcode": "43085",
    "addr:street": "Worthington Galena Rd",
    "iso:country": "US",
    "sg:address": "6955 Worthington Galena Rd",
    "sg:city": "Columbus",
    "sg:classifiers": [
      {
        "category": "Building \u0026 Trades",
        "subcategory": "Construction",
        "type": "Services"
      }
    ],
    "sg:phone": "+1 614 885 7944",
    "sg:postcode": "43085",
    "sg:province": "OH",
    "sg:tags": [
      "specializing",
      "general",
      "build",
      "contractor",
      "tenant",
      "out"
    ],
    "wof:name": "Commercial Office Specialists",
    "wof:placetype": "venue"
  },
  "geometry": {"coordinates":[-83.002199,40.105923],"type":"Point"}
}
