{
  "type": "Feature",
  "properties": {
    "addr:full":"3408 Saint James Pl Sandusky OH 44870",
    "addr:housenumber":"3408",
    "addr:postcode":"44870",
    "addr:street":"Saint James Pl",
    "iso:country":"US",
    "sg:address":"3408 Saint James Pl",
    "sg:city":"Sandusky",
    "sg:classifiers":[
        {
            "category":"Professional",
            "type":"Services"
        }
    ],
    "sg:phone":"+1 419 621 7791",
    "sg:postcode":"44870",
    "sg:province":"OH",
    "sg:tags":[
        "establishment"
    ],
    "wof:name":"S K Henterprisesinc",
    "wof:placetype":"venue"
},
  "geometry": {"coordinates":[-82.658016,41.410468],"type":"Point"}
}