{
  "type": "Feature",
  "properties": {
    "addr:full": "1045 Waugh Dr Hubbard OH 44425",
    "addr:housenumber": "1045",
    "addr:postcode": "44425",
    "addr:street": "Waugh Dr",
    "iso:country": "US",
    "sg:address": "1045 Waugh Dr",
    "sg:city": "Hubbard",
    "sg:classifiers": [
      {
        "category": "Building \u0026 Trades",
        "subcategory": "Construction",
        "type": "Services"
      }
    ],
    "sg:phone": "+1 330 534 1709",
    "sg:postcode": "44425",
    "sg:province": "OH",
    "sg:tags": [
      "sewer",
      "contractor"
    ],
    "wof:name": "C \u0026 C Sewer \u0026 Drain Svc",
    "wof:placetype": "venue"
  },
  "geometry": {"coordinates":[-80.551591,41.165173],"type":"Point"}
}
