{
  "type": "Feature",
  "properties": {
    "iso:country":"US",
    "sg:address":"1045 Waugh Dr",
    "sg:city":"Hubbard",
    "sg:classifiers":[
        {
            "category":"Building & Trades",
            "subcategory":"Construction",
            "type":"Services"
        }
    ],
    "sg:phone":"+1 330 534 1709",
    "sg:postcode":"44425",
    "sg:province":"OH",
    "sg:tags":[
        "sewer",
        "contractor"
    ],
    "wof:name":"C & C Sewer & Drain Svc",
    "wof:placetype":"venue"
},
  "geometry": {"coordinates":[-80.551591,41.165173],"type":"Point"}
}