{
  "type": "Feature",
  "properties": {
    "iso:country":"US",
    "sg:address":"39462 Center Ridge Rd",
    "sg:city":"North Ridgeville",
    "sg:classifiers":[
        {
            "category":"Personal",
            "subcategory":"Beauty Salon",
            "type":"Services"
        }
    ],
    "sg:phone":"+1 440 353 1919",
    "sg:postcode":"44039",
    "sg:province":"OH",
    "wof:name":"Indigo Salon",
    "wof:placetype":"venue"
},
  "geometry": {"coordinates":[-82.067667,41.380483],"type":"Point"}
}