{
  "type": "Feature",
  "properties": {
    "iso:country":"US",
    "sg:address":"1455 Dalton Ave",
    "sg:city":"Cincinnati",
    "sg:classifiers":[
        {
            "category":"Shopping",
            "subcategory":"Computers & Home Electronics",
            "type":"Retail Goods"
        }
    ],
    "sg:phone":"+1 513 541 3202",
    "sg:postcode":"45214",
    "sg:province":"OH",
    "wof:name":"Global Link",
    "wof:placetype":"venue"
},
  "geometry": {"coordinates":[-84.536152,39.112328],"type":"Point"}
}