{
  "type": "Feature",
  "properties": {
    "iso:country":"US",
    "sg:address":"7205 W Central Ave",
    "sg:city":"Toledo",
    "sg:classifiers":[
        {
            "category":"Banks & Credit Unions",
            "subcategory":"Investment Brokerage",
            "type":"Services"
        },
        {
            "category":"Professional",
            "subcategory":"Management & Consulting",
            "type":"Services"
        }
    ],
    "sg:phone":"+1 419 841 8521",
    "sg:postcode":"43617",
    "sg:province":"OH",
    "sg:tags":[
        "consultant",
        "planning",
        "financial"
    ],
    "sg:website":"www.austinassociates.com",
    "wof:name":"Austin Associates Inc",
    "wof:placetype":"venue"
},
  "geometry": {"coordinates":[-83.715704,41.673672],"type":"Point"}
}