{
  "type": "Feature",
  "properties": {
    "iso:country":"US",
    "sg:address":"7791 Cooper Rd",
    "sg:city":"Cincinnati",
    "sg:classifiers":[
        {
            "category":"Manufacturing",
            "subcategory":"Printing",
            "type":"Manufacturing & Wholesale Goods"
        }
    ],
    "sg:phone":"+1 513 793 2030",
    "sg:postcode":"45242",
    "sg:province":"OH",
    "sg:tags":[
        "lithographic",
        "commercial"
    ],
    "wof:name":"Village Print Shop",
    "wof:placetype":"venue"
},
  "geometry": {"coordinates":[-84.35509500000001,39.226496],"type":"Point"}
}