{
  "type": "Feature",
  "properties": {
    "iso:country":"US",
    "sg:address":"19413 US Hwy 23",
    "sg:city":"Circleville",
    "sg:classifiers":[
        {
            "category":"Sports & Exercise",
            "subcategory":"Race Track",
            "type":"Entertainment"
        }
    ],
    "sg:phone":"+1 740 477 1626",
    "sg:postcode":"43113",
    "sg:province":"OH",
    "wof:name":"Circleville Raceway Park Inc",
    "wof:placetype":"venue"
},
  "geometry": {"coordinates":[-82.958437,39.652922],"type":"Point"}
}