{
  "type": "Feature",
  "properties": {
    "addr:full": "19413 US Hwy 23 Circleville OH 43113",
    "addr:housenumber": "19413",
    "addr:postcode": "43113",
    "addr:street": "Us Hwy 23",
    "iso:country": "US",
    "sg:address": "19413 US Hwy 23",
    "sg:city": "Circleville",
    "sg:classifiers": [
      {
        "category": "Sports \u0026 Exercise",
        "subcategory": "Race Track",
        "type": "Entertainment"
      }
    ],
    "sg:phone": "+1 740 477 1626",
    "sg:postcode": "43113",
    "sg:province": "OH",
    "wof:name": "Circleville Raceway Park Inc",
    "wof:placetype": "venue"
  },
  "geometry": {"coordinates":[-82.958437,39.652922],"type":"Point"}
}
