{
  "type": "Feature",
  "properties": {
    "addr:full": "6635 Brigham Sq Centerville OH 45459",
    "addr:housenumber": "6635",
    "addr:postcode": "45459",
    "addr:street": "Brigham Sq",
    "iso:country": "US",
    "sg:address": "6635 Brigham Sq",
    "sg:city": "Centerville",
    "sg:classifiers": [
      {
        "category": "Manufacturing",
        "subcategory": "Paper Products",
        "type": "Manufacturing \u0026 Wholesale Goods"
      },
      {
        "category": "Utilities",
        "subcategory": "Refuse",
        "type": "Services"
      }
    ],
    "sg:phone": "+1 937 312 9380",
    "sg:postcode": "45459",
    "sg:province": "OH",
    "sg:tags": [
      "pet",
      "mill",
      "waste",
      "pulp",
      "removal"
    ],
    "wof:name": "Clean Green",
    "wof:placetype": "venue"
  },
  "geometry": {"coordinates":[-84.124276,39.64735],"type":"Point"}
}
