{
  "type": "Feature",
  "properties": {
    "addr:full":"4930 Cornell Rd Cincinnati OH 45242",
    "addr:housenumber":"4930",
    "addr:postcode":"45242",
    "addr:street":"Cornell Rd",
    "iso:country":"US",
    "sg:address":"4930 Cornell Rd",
    "sg:city":"Cincinnati",
    "sg:classifiers":[
        {
            "category":"Organizations",
            "subcategory":"Non-profit Organization",
            "type":"Services"
        }
    ],
    "sg:phone":"+1 513 489 1025",
    "sg:postcode":"45242",
    "sg:province":"OH",
    "sg:website":"www.grgsc.org",
    "wof:name":"Girl Scouts-Great Rivers Inc",
    "wof:placetype":"venue"
},
  "geometry": {"coordinates":[-84.369844,39.269328],"type":"Point"}
}