{
  "type": "Feature",
  "properties": {
    "iso:country":"US",
    "sg:address":"7238 Ohio Ave",
    "sg:city":"Cincinnati",
    "sg:classifiers":[
        {
            "category":"Bars & Pubs",
            "type":"Food & Drink"
        }
    ],
    "sg:phone":"+1 513 984 4544",
    "sg:postcode":"45236",
    "sg:province":"OH",
    "sg:tags":[
        "drinking"
    ],
    "wof:name":"H & H Lounge Inc",
    "wof:placetype":"venue"
},
  "geometry": {"coordinates":[-84.40407999999999,39.201268],"type":"Point"}
}