{
  "type": "Feature",
  "properties": {
    "addr:full": "7238 Ohio Ave Cincinnati OH 45236",
    "addr:housenumber": "7238",
    "addr:postcode": "45236",
    "addr:street": "Ohio Ave",
    "iso:country": "US",
    "sg:address": "7238 Ohio Ave",
    "sg:city": "Cincinnati",
    "sg:classifiers": [
      {
        "category": "Bars \u0026 Pubs",
        "type": "Food \u0026 Drink"
      }
    ],
    "sg:phone": "+1 513 984 4544",
    "sg:postcode": "45236",
    "sg:province": "OH",
    "sg:tags": [
      "drinking"
    ],
    "wof:name": "H \u0026 H Lounge Inc",
    "wof:placetype": "venue"
  },
  "geometry": {"coordinates":[-84.40408,39.201268],"type":"Point"}
}
