{
  "type": "Feature",
  "properties": {
    "iso:country":"US",
    "sg:address":"13828 Saint Clair Ave",
    "sg:city":"Cleveland",
    "sg:classifiers":[
        {
            "category":"Organizations",
            "subcategory":"Community Association",
            "type":"Services"
        }
    ],
    "sg:phone":"+1 216 851 1108",
    "sg:postcode":"44110",
    "sg:province":"OH",
    "wof:name":"Club Afrique",
    "wof:placetype":"venue"
},
  "geometry": {"coordinates":[-81.585641,41.548744],"type":"Point"}
}