{
  "type": "Feature",
  "properties": {
    "addr:full": "33625 Pin Oak Pkwy Avon Lake OH 44012",
    "addr:housenumber": "33625",
    "addr:postcode": "44012",
    "addr:street": "Pin Oak Pkwy Avon",
    "iso:country": "US",
    "sg:address": "33625 Pin Oak Pkwy",
    "sg:city": "Avon Lake",
    "sg:classifiers": [
      {
        "category": "Wholesale",
        "subcategory": "Farm Supplies",
        "type": "Manufacturing \u0026 Wholesale Goods"
      }
    ],
    "sg:phone": "+1 440 933 5477",
    "sg:postcode": "44012",
    "sg:province": "OH",
    "sg:tags": [
      "equipment",
      "greenhouse"
    ],
    "wof:name": "Reb Plastics Inc",
    "wof:placetype": "venue"
  },
  "geometry": {"coordinates":[-82.044425,41.481348],"type":"Point"}
}
