{
  "type": "Feature",
  "properties": {
    "addr:full": "4200 Kent Rd Stow OH 44224",
    "addr:housenumber": "4200",
    "addr:postcode": "44224",
    "addr:street": "Kent Rd",
    "iso:country": "US",
    "sg:address": "4200 Kent Rd",
    "sg:city": "Stow",
    "sg:classifiers": [
      {
        "category": "Retail",
        "subcategory": "Photofinishing",
        "type": "Services"
      }
    ],
    "sg:phone": "+1 330 688 7367",
    "sg:postcode": "44224",
    "sg:province": "OH",
    "sg:tags": [
      "laboratory"
    ],
    "wof:name": "Qualex Inc",
    "wof:placetype": "venue"
  },
  "geometry": {"coordinates":[-81.407933,41.156956],"type":"Point"}
}
