{
  "type": "Feature",
  "properties": {
    "addr:full": "11002 State Rte 47 Versailles OH 45380",
    "addr:housenumber": "11002",
    "addr:postcode": "45380",
    "addr:street": "State Rte 47",
    "iso:country": "US",
    "sg:address": "11002 State Rte 47",
    "sg:city": "Versailles",
    "sg:classifiers": [
      {
        "category": "Wholesale",
        "subcategory": "Drugs",
        "type": "Manufacturing \u0026 Wholesale Goods"
      }
    ],
    "sg:phone": "+1 937 526 3081",
    "sg:postcode": "45380",
    "sg:province": "OH",
    "wof:name": "Marlene Wooten",
    "wof:placetype": "venue"
  },
  "geometry": {"coordinates":[-84.462129,40.24107],"type":"Point"}
}
