{
  "type": "Feature",
  "properties": {
    "iso:country":"US",
    "sg:address":"11002 State Rte 47",
    "sg:city":"Versailles",
    "sg:classifiers":[
        {
            "category":"Wholesale",
            "subcategory":"Drugs",
            "type":"Manufacturing & Wholesale Goods"
        }
    ],
    "sg:phone":"+1 937 526 3081",
    "sg:postcode":"45380",
    "sg:province":"OH",
    "wof:name":"Marlene Wooten",
    "wof:placetype":"venue"
},
  "geometry": {"coordinates":[-84.462129,40.24107],"type":"Point"}
}