{
  "type": "Feature",
  "properties": {
    "iso:country":"US",
    "sg:address":"10569 Sharon Dr",
    "sg:city":"Cleveland",
    "sg:phone":"+1 440 884 1127",
    "sg:postcode":"44130",
    "sg:province":"OH",
    "sg:tags":[
        "equipment",
        "commercial"
    ],
    "wof:name":"Carolina Food Systems",
    "wof:placetype":"venue"
},
  "geometry": {"coordinates":[-81.76075899999999,41.409426],"type":"Point"}
}