{
  "type": "Feature",
  "properties": {
    "iso:country":"US",
    "sg:address":"3869 Broadway",
    "sg:city":"Grove City",
    "sg:classifiers":[
        {
            "category":"Insurance",
            "subcategory":"Insurance Agent",
            "type":"Services"
        }
    ],
    "sg:phone":"+1 614 875 6969",
    "sg:postcode":"43123",
    "sg:province":"OH",
    "wof:name":"Boggs Insurance Agency",
    "wof:placetype":"venue"
},
  "geometry": {"coordinates":[-83.091454,39.88487],"type":"Point"}
}