{
  "type": "Feature",
  "properties": {
    "iso:country":"US",
    "sg:address":"916 N Summit St",
    "sg:city":"Toledo",
    "sg:classifiers":[
        {
            "category":"Manufacturing",
            "subcategory":"Tools & Machinery",
            "type":"Manufacturing & Wholesale Goods"
        }
    ],
    "sg:phone":"+1 419 241 9248",
    "sg:postcode":"43604",
    "sg:province":"OH",
    "sg:tags":[
        "equipment",
        "engineering",
        "computer",
        "repair"
    ],
    "sg:website":"www.ohiotechresources.com",
    "wof:name":"Technology Resources Inc",
    "wof:placetype":"venue"
},
  "geometry": {"coordinates":[-83.526943,41.65635],"type":"Point"}
}