{
  "type": "Feature",
  "properties": {
    "addr:full": "29755 Somerset Rd Perrysburg OH 43551",
    "addr:housenumber": "29755",
    "addr:postcode": "43551",
    "addr:street": "Somerset Rd",
    "iso:country": "US",
    "sg:address": "29755 Somerset Rd",
    "sg:city": "Perrysburg",
    "sg:classifiers": [
      {
        "category": "Real Estate",
        "subcategory": "Real Estate Operator",
        "type": "Services"
      }
    ],
    "sg:phone": "+1 419 874 5201",
    "sg:postcode": "43551",
    "sg:province": "OH",
    "sg:tags": [
      "building",
      "commercial"
    ],
    "wof:name": "Thunderbird Enterprises Inc",
    "wof:placetype": "venue"
  },
  "geometry": {"coordinates":[-83.598289,41.582775],"type":"Point"}
}
