{
  "type": "Feature",
  "properties": {
    "iso:country":"US",
    "sg:address":"490 N Main St",
    "sg:city":"Marysville",
    "sg:classifiers":[
        {
            "category":"Autos & Motor Vehicles",
            "subcategory":"Fuel & Gas Station",
            "type":"Retail Goods"
        }
    ],
    "sg:phone":"+1 937 642 2067",
    "sg:postcode":"43040",
    "sg:province":"OH",
    "sg:tags":[
        "repair",
        "station",
        "gasoline",
        "general"
    ],
    "wof:name":"BP",
    "wof:placetype":"venue"
},
  "geometry": {"coordinates":[-83.366338,40.24118],"type":"Point"}
}