{
  "type": "Feature",
  "properties": {
    "addr:full": "490 N Main St Marysville OH 43040",
    "addr:housenumber": "490",
    "addr:postcode": "43040",
    "addr:street": "N Main St",
    "iso:country": "US",
    "sg:address": "490 N Main St",
    "sg:city": "Marysville",
    "sg:classifiers": [
      {
        "category": "Autos \u0026 Motor Vehicles",
        "subcategory": "Fuel \u0026 Gas Station",
        "type": "Retail Goods"
      }
    ],
    "sg:phone": "+1 937 642 2067",
    "sg:postcode": "43040",
    "sg:province": "OH",
    "sg:tags": [
      "repair",
      "station",
      "gasoline",
      "general"
    ],
    "wof:name": "BP",
    "wof:placetype": "venue"
  },
  "geometry": {"coordinates":[-83.366338,40.24118],"type":"Point"}
}
