{
  "type": "Feature",
  "properties": {
    "addr:full": "258 Tenney St Amherst OH 44001",
    "addr:housenumber": "258",
    "addr:postcode": "44001",
    "addr:street": "Tenney St",
    "iso:country": "US",
    "sg:address": "258 Tenney St",
    "sg:city": "Amherst",
    "sg:classifiers": [
      {
        "category": "Shopping",
        "type": "Retail Goods"
      },
      {
        "category": "Retail",
        "subcategory": "Animal Services",
        "type": "Services"
      }
    ],
    "sg:phone": "+1 440 988 2006",
    "sg:postcode": "44001",
    "sg:province": "OH",
    "sg:tags": [
      "pet",
      "boarding",
      "merchandise",
      "sitting"
    ],
    "wof:name": "Mary's Bird World",
    "wof:placetype": "venue"
  },
  "geometry": {"coordinates":[-82.224389,41.39719],"type":"Point"}
}
