{
  "type": "Feature",
  "properties": {
    "iso:country":"US",
    "sg:address":"5775 Zarley St",
    "sg:city":"New Albany",
    "sg:classifiers":[
        {
            "category":"Freight",
            "type":"Transportation"
        }
    ],
    "sg:phone":"+1 614 933 9250",
    "sg:postcode":"43054",
    "sg:province":"OH",
    "sg:tags":[
        "warehouse",
        "tobacco"
    ],
    "wof:name":"Buckeye Tobacco Wholesale",
    "wof:placetype":"venue"
},
  "geometry": {"coordinates":[-82.794906,40.087019],"type":"Point"}
}