{
  "type": "Feature",
  "properties": {
    "iso:country":"US",
    "sg:address":"200 Tuscarawas St W",
    "sg:city":"Canton",
    "sg:classifiers":[
        {
            "category":"Government",
            "subcategory":"Office",
            "type":"Public Place"
        }
    ],
    "sg:phone":"+1 330 451 7371",
    "sg:postcode":"44702",
    "sg:province":"OH",
    "wof:name":"Stark County Administrator",
    "wof:placetype":"venue"
},
  "geometry": {"coordinates":[-81.376543,40.798809],"type":"Point"}
}