{
  "type": "Feature",
  "properties": {
    "addr:full":"1666 W Exchange St Akron OH 44313",
    "addr:housenumber":"1666",
    "addr:postcode":"44313",
    "addr:street":"W Exchange St",
    "iso:country":"US",
    "sg:address":"1666 W Exchange St",
    "sg:city":"Akron",
    "sg:classifiers":[
        {
            "category":"Restaurant",
            "type":"Food & Drink"
        }
    ],
    "sg:phone":"+1 330 836 6666",
    "sg:postcode":"44313",
    "sg:province":"OH",
    "wof:name":"Yoconos Restaurant",
    "wof:placetype":"venue"
},
  "geometry": {"coordinates":[-81.56714100000001,41.10749],"type":"Point"}
}