{
  "type": "Feature",
  "properties": {
    "iso:country":"US",
    "sg:address":"6301 Kellogg Rd",
    "sg:city":"Cincinnati",
    "sg:classifiers":[
        {
            "category":"Recreation",
            "type":"Entertainment"
        }
    ],
    "sg:phone":"+1 513 231 3189",
    "sg:postcode":"45230",
    "sg:province":"OH",
    "sg:tags":[
        "stable"
    ],
    "wof:name":"Ryan Stables",
    "wof:placetype":"venue"
},
  "geometry": {"coordinates":[-84.414416,39.05469],"type":"Point"}
}