{
  "type": "Feature",
  "properties": {
    "addr:full":"2765 Northland Plaza Dr Columbus OH 43231",
    "addr:housenumber":"2765",
    "addr:postcode":"43231",
    "addr:street":"Northland Plaza Dr",
    "iso:country":"US",
    "sg:address":"2765 Northland Plaza Dr",
    "sg:city":"Columbus",
    "sg:classifiers":[
        {
            "category":"Food & Beverages",
            "subcategory":"Specialty",
            "type":"Retail Goods"
        },
        {
            "category":"Food & Beverages",
            "subcategory":"Fruits & Vegetables",
            "type":"Retail Goods"
        },
        {
            "category":"Shopping",
            "subcategory":"Pharmacy",
            "type":"Retail Goods"
        }
    ],
    "sg:phone":"+1 614 891 3711",
    "sg:postcode":"43231",
    "sg:province":"OH",
    "sg:tags":[
        "product",
        "wellness",
        "vitamin",
        "diet",
        "supplement",
        "health",
        "herb"
    ],
    "sg:website":"http://www.gnc.com",
    "wof:name":"GNC",
    "wof:placetype":"venue"
},
  "geometry": {"coordinates":[-82.949184,40.082315],"type":"Point"}
}