{
  "type": "Feature",
  "properties": {
    "addr:full":"7964 Holyrood Ct Dublin OH 43017",
    "addr:housenumber":"7964",
    "addr:postcode":"43017",
    "addr:street":"Holyrood Ct",
    "iso:country":"US",
    "sg:address":"7964 Holyrood Ct",
    "sg:city":"Dublin",
    "sg:classifiers":[
        {
            "category":"Health Services",
            "subcategory":"Clinic",
            "type":"Services"
        }
    ],
    "sg:phone":"+1 614 718 9241",
    "sg:postcode":"43017",
    "sg:province":"OH",
    "wof:name":"Papnet",
    "wof:placetype":"venue"
},
  "geometry": {"coordinates":[-83.152451,40.13132],"type":"Point"}
}