{
  "type": "Feature",
  "properties": {
    "iso:country":"US",
    "sg:address":"401 W Trenton Ave",
    "sg:city":"Findlay",
    "sg:classifiers":[
        {
            "category":"Manufacturing",
            "subcategory":"Printing",
            "type":"Manufacturing & Wholesale Goods"
        }
    ],
    "sg:phone":"+1 419 423 0271",
    "sg:postcode":"45840",
    "sg:province":"OH",
    "sg:tags":[
        "nonprofit",
        "printer",
        "envelope"
    ],
    "wof:name":"Hubbard Press Ohio Corp",
    "wof:placetype":"venue"
},
  "geometry": {"coordinates":[-83.65831300000001,41.058774],"type":"Point"}
}