{
  "type": "Feature",
  "properties": {
    "addr:full":"1378 E Livingston Ave Columbus OH 43205",
    "addr:housenumber":"1378",
    "addr:postcode":"43205",
    "addr:street":"E Livingston Ave",
    "iso:country":"US",
    "sg:address":"1378 E Livingston Ave",
    "sg:city":"Columbus",
    "sg:classifiers":[
        {
            "category":"Building & Trades",
            "subcategory":"Construction",
            "type":"Services"
        }
    ],
    "sg:phone":"+1 614 252 1234",
    "sg:postcode":"43205",
    "sg:province":"OH",
    "sg:tags":[
        "repair",
        "addition",
        "general",
        "new",
        "sing",
        "contractor",
        "remodeling"
    ],
    "wof:name":"Michael Boyd Enterprises",
    "wof:placetype":"venue"
},
  "geometry": {"coordinates":[-82.961387,39.949261],"type":"Point"}
}