{
  "type": "Feature",
  "properties": {
    "iso:country":"US",
    "sg:address":"717 Maple Grove Ave",
    "sg:city":"Newark",
    "sg:classifiers":[
        {
            "category":"Wholesale",
            "subcategory":"Construction Materials",
            "type":"Manufacturing & Wholesale Goods"
        },
        {
            "category":"Manufacturing",
            "subcategory":"Metals",
            "type":"Manufacturing & Wholesale Goods"
        }
    ],
    "sg:phone":"+1 740 344 9037",
    "sg:postcode":"43055",
    "sg:province":"OH",
    "sg:tags":[
        "gates",
        "metalwork",
        "architectural",
        "mfg"
    ],
    "wof:name":"Custom Made Gates LLC",
    "wof:placetype":"venue"
},
  "geometry": {"coordinates":[-82.429089,40.049031],"type":"Point"}
}