{
  "type": "Feature",
  "properties": {
    "addr:full": "7961 Windridge Dr Broadview Heights OH 44147",
    "addr:housenumber": "7961",
    "addr:postcode": "44147",
    "addr:street": "Windridge Dr",
    "iso:country": "US",
    "sg:address": "7961 Windridge Dr",
    "sg:city": "Broadview Heights",
    "sg:classifiers": [
      {
        "category": "Home \u0026 Garden",
        "subcategory": "Home Furnishings",
        "type": "Retail Goods"
      }
    ],
    "sg:phone": "+1 440 546 9183",
    "sg:postcode": "44147",
    "sg:province": "OH",
    "sg:tags": [
      "curtain",
      "made",
      "drapery"
    ],
    "wof:name": "Rose K Draperies",
    "wof:placetype": "venue"
  },
  "geometry": {"coordinates":[-81.674467,41.329175],"type":"Point"}
}
