{
  "type": "Feature",
  "properties": {
    "addr:full": "440 High St Fairport Harbor OH 44077",
    "addr:housenumber": "440",
    "addr:postcode": "44077",
    "addr:street": "High St",
    "iso:country": "US",
    "sg:address": "440 High St",
    "sg:city": "Fairport Harbor",
    "sg:classifiers": [
      {
        "category": "Professional",
        "subcategory": "Accounting \u0026 Tax Preparation",
        "type": "Services"
      }
    ],
    "sg:phone": "+1 440 354 4248",
    "sg:postcode": "44077",
    "sg:province": "OH",
    "sg:tags": [
      "return",
      "filing"
    ],
    "wof:name": "Robert J Meyers",
    "wof:placetype": "venue"
  },
  "geometry": {"coordinates":[-81.276982,41.752956],"type":"Point"}
}
