{
  "type": "Feature",
  "properties": {
    "addr:full": "16495 Florence Chapel Pike Circleville OH 43113",
    "addr:housenumber": "16495",
    "addr:postcode": "43113",
    "addr:street": "Florence Chapel Pike",
    "iso:country": "US",
    "sg:address": "16495 Florence Chapel Pike",
    "sg:city": "Circleville",
    "sg:classifiers": [
      {
        "category": "Building \u0026 Trades",
        "subcategory": "Construction",
        "type": "Services"
      }
    ],
    "sg:phone": "+1 740 477 8580",
    "sg:postcode": "43113",
    "sg:province": "OH",
    "sg:tags": [
      "house",
      "builder",
      "home"
    ],
    "wof:name": "Cline Builders Inc",
    "wof:placetype": "venue"
  },
  "geometry": {"coordinates":[-83.086402,39.703083],"type":"Point"}
}
