{
  "type": "Feature",
  "properties": {
    "addr:full":"7388 Southpointe Dr Cincinnati OH 45233",
    "addr:housenumber":"7388",
    "addr:postcode":"45233",
    "addr:street":"Southpointe Dr",
    "iso:country":"US",
    "sg:address":"7388 Southpointe Dr",
    "sg:city":"Cincinnati",
    "sg:classifiers":[
        {
            "category":"Building & Trades",
            "subcategory":"Construction",
            "type":"Services"
        }
    ],
    "sg:phone":"+1 513 574 5030",
    "sg:postcode":"45233",
    "sg:province":"OH",
    "sg:tags":[
        "tile",
        "installation",
        "marble",
        "contractor"
    ],
    "wof:name":"KUHL Tile & Marble",
    "wof:placetype":"venue"
},
  "geometry": {"coordinates":[-84.69235999999999,39.128605],"type":"Point"}
}