{
  "type": "Feature",
  "properties": {
    "addr:full": "7718 Theota Ave Cleveland OH 44129",
    "addr:postcode": "7718;44129",
    "addr:street": "Theota Ave",
    "iso:country": "US",
    "sg:address": "7718 Theota Ave",
    "sg:city": "Cleveland",
    "sg:classifiers": [
      {
        "category": "Building \u0026 Trades",
        "subcategory": "Pest Control",
        "type": "Services"
      }
    ],
    "sg:phone": "+1 440 582 5108",
    "sg:postcode": "44129",
    "sg:province": "OH",
    "sg:tags": [
      "trapper",
      "animal"
    ],
    "wof:name": "Wild In Country",
    "wof:placetype": "venue"
  },
  "geometry": {"coordinates":[-81.736024,41.413307],"type":"Point"}
}
