{
  "type": "Feature",
  "properties": {
    "addr:full":"221 Prince of Wales Dr Columbus OH 43230",
    "addr:housenumber":"221",
    "addr:postcode":"43230",
    "addr:street":"Prince Of Wales Dr",
    "iso:country":"US",
    "sg:address":"221 Prince of Wales Dr",
    "sg:city":"Columbus",
    "sg:classifiers":[
        {
            "category":"Retail",
            "subcategory":"Auto Repair",
            "type":"Services"
        }
    ],
    "sg:phone":"+1 614 794 0445",
    "sg:postcode":"43230",
    "sg:province":"OH",
    "sg:tags":[
        "general"
    ],
    "wof:name":"All Tune & Lube",
    "wof:placetype":"venue"
},
  "geometry": {"coordinates":[-82.89345899999999,40.022655],"type":"Point"}
}