{
  "type": "Feature",
  "properties": {
    "addr:full":"8019 Moody Rd Centerburg OH 43011",
    "addr:housenumber":"8019",
    "addr:postcode":"43011",
    "addr:street":"Moody Rd",
    "iso:country":"US",
    "sg:address":"8019 Moody Rd",
    "sg:city":"Centerburg",
    "sg:classifiers":[
        {
            "category":"Retail",
            "subcategory":"Repair Shop",
            "type":"Services"
        }
    ],
    "sg:phone":"+1 740 965 2711",
    "sg:postcode":"43011",
    "sg:province":"OH",
    "sg:tags":[
        "taxidermist"
    ],
    "wof:name":"Tail Feathers Taxidermy",
    "wof:placetype":"venue"
},
  "geometry": {"coordinates":[-82.75931799999999,40.319386],"type":"Point"}
}