{
  "type": "Feature",
  "properties": {
    "addr:full":"1870 E Mansfield St Bucyrus OH 44820",
    "addr:housenumber":"1870",
    "addr:postcode":"44820",
    "addr:street":"E Mansfield St",
    "iso:country":"US",
    "sg:address":"1870 E Mansfield St",
    "sg:city":"Bucyrus",
    "sg:classifiers":[
        {
            "category":"Manufacturing",
            "subcategory":"Jewelry",
            "type":"Manufacturing & Wholesale Goods"
        }
    ],
    "sg:phone":"+1 419 562 0466",
    "sg:postcode":"44820",
    "sg:province":"OH",
    "sg:website":"www.regoonline.com",
    "wof:name":"Rego Manufacturing",
    "wof:placetype":"venue"
},
  "geometry": {"coordinates":[-82.95036,40.812546],"type":"Point"}
}