{
  "type": "Feature",
  "properties": {
    "addr:full":"6184 Royalton Rd North Royalton OH 44133",
    "addr:housenumber":"6184",
    "addr:postcode":"44133",
    "addr:street":"Royalton Rd",
    "iso:country":"US",
    "sg:address":"6184 Royalton Rd",
    "sg:city":"North Royalton",
    "sg:classifiers":[
        {
            "category":"Wholesale",
            "subcategory":"Hardware",
            "type":"Manufacturing & Wholesale Goods"
        }
    ],
    "sg:phone":"+1 440 582 2593",
    "sg:postcode":"44133",
    "sg:province":"OH",
    "sg:tags":[
        "tool",
        "hand"
    ],
    "wof:name":"Ester Abrasives",
    "wof:placetype":"venue"
},
  "geometry": {"coordinates":[-81.727349,41.313812],"type":"Point"}
}