{
  "type": "Feature",
  "properties": {
    "iso:country":"US",
    "sg:address":"113 Washington St",
    "sg:city":"Canal Winchester",
    "sg:classifiers":[
        {
            "category":"Building & Trades",
            "subcategory":"Construction",
            "type":"Services"
        }
    ],
    "sg:phone":"+1 614 837 5990",
    "sg:postcode":"43110",
    "sg:province":"OH",
    "sg:tags":[
        "contractor"
    ],
    "wof:name":"Monarch Exteriors",
    "wof:placetype":"venue"
},
  "geometry": {"coordinates":[-82.810162,39.838148],"type":"Point"}
}