{
  "type": "Feature",
  "properties": {
    "addr:full":"4201 W 8th St Cincinnati OH 45205",
    "addr:housenumber":"4201",
    "addr:postcode":"45205",
    "addr:street":"W 8Th St",
    "iso:country":"US",
    "sg:address":"4201 W 8th St",
    "sg:city":"Cincinnati",
    "sg:classifiers":[
        {
            "category":"Autos & Motor Vehicles",
            "subcategory":"Fuel & Gas Station",
            "type":"Retail Goods"
        }
    ],
    "sg:phone":"+1 513 921 7448",
    "sg:postcode":"45205",
    "sg:province":"OH",
    "sg:tags":[
        "station",
        "oil"
    ],
    "wof:name":"Bob's Marathon",
    "wof:placetype":"venue"
},
  "geometry": {"coordinates":[-84.589371,39.107486],"type":"Point"}
}