{
  "type": "Feature",
  "properties": {
    "addr:full":"537 Aaron Ave Jackson OH 45640",
    "addr:housenumber":"537",
    "addr:postcode":"45640",
    "addr:street":"Aaron Ave",
    "iso:country":"US",
    "sg:address":"537 Aaron Ave",
    "sg:city":"Jackson",
    "sg:classifiers":[
        {
            "category":"Organizations",
            "subcategory":"Non-profit Organization",
            "type":"Services"
        }
    ],
    "sg:phone":"+1 740 286 1377",
    "sg:postcode":"45640",
    "sg:province":"OH",
    "sg:tags":[
        "social"
    ],
    "wof:name":"Knights of Clmbus Spreme Cncil",
    "wof:placetype":"venue"
},
  "geometry": {"coordinates":[-82.574286,39.076563],"type":"Point"}
}