{
  "type": "Feature",
  "properties": {
    "addr:full":"1630 E 361st St Willoughby OH 44095",
    "addr:housenumber":"1630",
    "addr:postcode":"44095",
    "addr:street":"E 361St St",
    "iso:country":"US",
    "sg:address":"1630 E 361st St",
    "sg:city":"Willoughby",
    "sg:classifiers":[
        {
            "category":"Manufacturing",
            "subcategory":"Tools & Machinery",
            "type":"Manufacturing & Wholesale Goods"
        }
    ],
    "sg:phone":"+1 440 953 8088",
    "sg:postcode":"44095",
    "sg:province":"OH",
    "sg:tags":[
        "machine",
        "shop",
        "job"
    ],
    "wof:name":"Arlo Precision Inc",
    "wof:placetype":"venue"
},
  "geometry": {"coordinates":[-81.430986,41.63761],"type":"Point"}
}