{
  "type": "Feature",
  "properties": {
    "addr:full": "937 Main St Hamilton IN 45013",
    "addr:housenumber": "937",
    "addr:postcode": "45013",
    "addr:street": "Main St",
    "iso:country": "US",
    "sg:address": "937 Main St",
    "sg:city": "Hamilton",
    "sg:classifiers": [
      {
        "category": "Retail",
        "subcategory": "Car Wash",
        "type": "Services"
      }
    ],
    "sg:phone": "+1 513 856 9384",
    "sg:postcode": "45013",
    "sg:province": "IN",
    "sg:tags": [
      "polishing",
      "washing"
    ],
    "wof:name": "Hamiltons Premium Car Care",
    "wof:placetype": "venue"
  },
  "geometry": {"coordinates":[-84.579061,39.411229],"type":"Point"}
}
