{
  "type": "Feature",
  "properties": {
    "iso:country":"US",
    "sg:address":"3249 Oakwood Dr",
    "sg:city":"Cuyahoga Falls",
    "sg:classifiers":[
        {
            "category":"Health Services",
            "subcategory":"Medical Lab",
            "type":"Services"
        }
    ],
    "sg:phone":"+1 330 945 4551",
    "sg:postcode":"44221",
    "sg:province":"OH",
    "sg:tags":[
        "laboratory"
    ],
    "wof:name":"Suburban Dental Lab",
    "wof:placetype":"venue"
},
  "geometry": {"coordinates":[-81.48952300000001,41.158739],"type":"Point"}
}