{
  "type": "Feature",
  "properties": {
    "addr:full": "3249 Oakwood Dr Cuyahoga Falls OH 44221",
    "addr:housenumber": "3249",
    "addr:postcode": "44221",
    "addr:street": "Oakwood Dr",
    "iso:country": "US",
    "sg:address": "3249 Oakwood Dr",
    "sg:city": "Cuyahoga Falls",
    "sg:classifiers": [
      {
        "category": "Health Services",
        "subcategory": "Medical Lab",
        "type": "Services"
      }
    ],
    "sg:phone": "+1 330 945 4551",
    "sg:postcode": "44221",
    "sg:province": "OH",
    "sg:tags": [
      "laboratory"
    ],
    "wof:name": "Suburban Dental Lab",
    "wof:placetype": "venue"
  },
  "geometry": {"coordinates":[-81.489523,41.158739],"type":"Point"}
}
