{
  "type": "Feature",
  "properties": {
    "iso:country":"US",
    "sg:address":"539 Parsons Ave",
    "sg:city":"Chillicothe",
    "sg:classifiers":[
        {
            "category":"Organizations",
            "subcategory":"Religious Organization",
            "type":"Services"
        }
    ],
    "sg:phone":"+1 740 779 6497",
    "sg:postcode":"45601",
    "sg:province":"OH",
    "sg:tags":[
        "clergy"
    ],
    "wof:name":"Larry Grant",
    "wof:placetype":"venue"
},
  "geometry": {"coordinates":[-82.99906,39.324101],"type":"Point"}
}