{
  "type": "Feature",
  "properties": {
    "addr:full": "5044 Corbin Dr Cleveland OH 44128",
    "addr:housenumber": "5044",
    "addr:postcode": "44128",
    "addr:street": "Corbin Dr",
    "iso:country": "US",
    "sg:address": "5044 Corbin Dr",
    "sg:city": "Cleveland",
    "sg:classifiers": [
      {
        "category": "Professional",
        "type": "Services"
      }
    ],
    "sg:phone": "+1 216 581 6288",
    "sg:postcode": "44128",
    "sg:province": "OH",
    "wof:name": "American Fleet Locator",
    "wof:placetype": "venue"
  },
  "geometry": {"coordinates":[-81.514889,41.421943],"type":"Point"}
}
