{
  "type": "Feature",
  "properties": {
    "addr:full":"3801 Olentangy River Rd Delaware OH 43015",
    "addr:housenumber":"3801",
    "addr:postcode":"43015",
    "addr:street":"Olentangy River Rd",
    "iso:country":"US",
    "sg:address":"3801 Olentangy River Rd",
    "sg:city":"Delaware",
    "sg:classifiers":[
        {
            "category":"Professional",
            "subcategory":"Management & Consulting",
            "type":"Services"
        }
    ],
    "sg:phone":"+1 740 363 2141",
    "sg:postcode":"43015",
    "sg:province":"OH",
    "sg:tags":[
        "counselor",
        "public",
        "relations"
    ],
    "sg:website":"www.bradritter.com",
    "wof:name":"Brad Ritter Communications",
    "wof:placetype":"venue"
},
  "geometry": {"coordinates":[-83.06079099999999,40.250605],"type":"Point"}
}