{
  "type": "Feature",
  "properties": {
    "addr:full": "495 E Canal St Nelsonville OH 45764",
    "addr:housenumber": "495",
    "addr:postcode": "45764",
    "addr:street": "E Canal St",
    "iso:country": "US",
    "sg:address": "495 E Canal St",
    "sg:city": "Nelsonville",
    "sg:classifiers": [
      {
        "category": "Health Services",
        "subcategory": "Health Practitioner",
        "type": "Services"
      }
    ],
    "sg:phone": "+1 740 753 9414",
    "sg:postcode": "45764",
    "sg:province": "OH",
    "sg:tags": [
      "psychologist"
    ],
    "wof:name": "Sleep Care America",
    "wof:placetype": "venue"
  },
  "geometry": {"coordinates":[-82.225626,39.454328],"type":"Point"}
}
