{
  "type": "Feature",
  "properties": {
    "iso:country":"US",
    "sg:address":"56 Mill St",
    "sg:city":"Carroll",
    "sg:classifiers":[
        {
            "category":"Building & Trades",
            "subcategory":"Construction",
            "type":"Services"
        }
    ],
    "sg:phone":"+1 740 756 7733",
    "sg:postcode":"43112",
    "sg:province":"OH",
    "sg:tags":[
        "excavation",
        "excavating",
        "contractor"
    ],
    "wof:name":"J Benson Excavating",
    "wof:placetype":"venue"
},
  "geometry": {"coordinates":[-82.705731,39.800098],"type":"Point"}
}