{
  "type": "Feature",
  "properties": {
    "addr:full":"15700 Euclid Ave Cleveland OH 44112",
    "addr:housenumber":"15700",
    "addr:postcode":"44112",
    "addr:street":"Euclid Ave",
    "iso:country":"US",
    "sg:address":"15700 Euclid Ave",
    "sg:city":"Cleveland",
    "sg:classifiers":[
        {
            "category":"Professional",
            "subcategory":"Detective & Security Services",
            "type":"Services"
        }
    ],
    "sg:phone":"+1 216 761 2054",
    "sg:postcode":"44112",
    "sg:province":"OH",
    "wof:name":"Harrison Investigations",
    "wof:placetype":"venue"
},
  "geometry": {"coordinates":[-81.570583,41.54107],"type":"Point"}
}