{
  "type": "Feature",
  "properties": {
    "iso:country":"US",
    "sg:address":"26 E High St",
    "sg:city":"London",
    "sg:classifiers":[
        {
            "category":"Personal",
            "type":"Services"
        }
    ],
    "sg:phone":"+1 740 845 4968",
    "sg:postcode":"43140",
    "sg:province":"OH",
    "sg:tags":[
        "therapist",
        "massage"
    ],
    "wof:name":"Relaxation 4 You",
    "wof:placetype":"venue"
},
  "geometry": {"coordinates":[-83.448578,39.886348],"type":"Point"}
}