{
  "type": "Feature",
  "properties": {
    "iso:country":"US",
    "sg:address":"104 E Franklin St",
    "sg:city":"Circleville",
    "sg:classifiers":[
        {
            "category":"Government",
            "subcategory":"Office",
            "type":"Public Place"
        }
    ],
    "sg:phone":"+1 740 477 8282",
    "sg:postcode":"43113",
    "sg:province":"OH",
    "sg:tags":[
        "village"
    ],
    "wof:name":"Circleville Building Dept",
    "wof:placetype":"venue"
},
  "geometry": {"coordinates":[-82.94548899999999,39.600875],"type":"Point"}
}