{
  "type": "Feature",
  "properties": {
    "addr:full":"3520 State Rte 98 Bucyrus OH 44820",
    "addr:housenumber":"3520",
    "addr:postcode":"44820",
    "addr:street":"State Rte 98",
    "iso:country":"US",
    "sg:address":"3520 State Rte 98",
    "sg:city":"Bucyrus",
    "sg:classifiers":[
        {
            "category":"Real Estate",
            "subcategory":"Real Estate Operator",
            "type":"Services"
        }
    ],
    "sg:phone":"+1 419 562 3094",
    "sg:postcode":"44820",
    "sg:province":"OH",
    "sg:tags":[
        "property",
        "lessor"
    ],
    "wof:name":"James Meister",
    "wof:placetype":"venue"
},
  "geometry": {"coordinates":[-82.94571000000001,40.828174],"type":"Point"}
}