{
  "type": "Feature",
  "properties": {
    "addr:full":"2474 Dresden Ave East Liverpool OH 43920",
    "addr:housenumber":"2474",
    "addr:postcode":"43920",
    "addr:street":"Dresden Ave",
    "iso:country":"US",
    "sg:address":"2474 Dresden Ave",
    "sg:city":"East Liverpool",
    "sg:classifiers":[
        {
            "category":"Shopping",
            "subcategory":"Gifts & Souvenirs",
            "type":"Retail Goods"
        }
    ],
    "sg:phone":"+1 330 386 4716",
    "sg:postcode":"43920",
    "sg:province":"OH",
    "sg:tags":[
        "shop"
    ],
    "wof:name":"Pearl China Inc",
    "wof:placetype":"venue"
},
  "geometry": {"coordinates":[-80.586241,40.643422],"type":"Point"}
}