{
  "type": "Feature",
  "properties": {
    "addr:full": "130 S Erie Hwy Hamilton OH 45011",
    "addr:housenumber": "130",
    "addr:postcode": "45011",
    "addr:street": "S Erie Hwy",
    "iso:country": "US",
    "sg:address": "130 S Erie Hwy",
    "sg:city": "Hamilton",
    "sg:classifiers": [
      {
        "category": "Restaurant",
        "type": "Food \u0026 Drink"
      }
    ],
    "sg:menulink": "http://www.allmenus.com/oh/hamilton/278232-hydes-restaurant/menu/",
    "sg:phone": "+1 513 892 1287",
    "sg:postcode": "45011",
    "sg:province": "OH",
    "sg:tags": [
      "american"
    ],
    "wof:name": "Hyde's Restaurant",
    "wof:placetype": "venue"
  },
  "geometry": {"coordinates":[-84.54779,39.393539],"type":"Point"}
}
