{
  "type": "Feature",
  "properties": {
    "iso:country":"US",
    "sg:address":"130 S Erie Hwy",
    "sg:city":"Hamilton",
    "sg:classifiers":[
        {
            "category":"Restaurant",
            "type":"Food & Drink"
        }
    ],
    "sg:menulink":"http://www.allmenus.com/oh/hamilton/278232-hydes-restaurant/menu/",
    "sg:phone":"+1 513 892 1287",
    "sg:postcode":"45011",
    "sg:province":"OH",
    "sg:tags":[
        "american"
    ],
    "wof:name":"Hyde's Restaurant",
    "wof:placetype":"venue"
},
  "geometry": {"coordinates":[-84.54779000000001,39.393539],"type":"Point"}
}