{
  "type": "Feature",
  "properties": {
    "addr:full": "300 Progress Rd Dayton OH 45449",
    "addr:housenumber": "300",
    "addr:postcode": "45449",
    "addr:street": "Progress Rd",
    "iso:country": "US",
    "sg:address": "300 Progress Rd",
    "sg:city": "Dayton",
    "sg:classifiers": [
      {
        "category": "Manufacturing",
        "subcategory": "Tools \u0026 Machinery",
        "type": "Manufacturing \u0026 Wholesale Goods"
      }
    ],
    "sg:phone": "+1 937 859 8273",
    "sg:postcode": "45449",
    "sg:province": "OH",
    "sg:tags": [
      "industry",
      "special"
    ],
    "sg:website": "www.mmprecision.com",
    "wof:name": "Gleason-M \u0026 M Precision Systs",
    "wof:placetype": "venue"
  },
  "geometry": {"coordinates":[-84.24363,39.65397],"type":"Point"}
}
