{
  "type": "Feature",
  "properties": {
    "iso:country":"US",
    "sg:address":"300 Progress Rd",
    "sg:city":"Dayton",
    "sg:classifiers":[
        {
            "category":"Manufacturing",
            "subcategory":"Tools & Machinery",
            "type":"Manufacturing & Wholesale Goods"
        }
    ],
    "sg:phone":"+1 937 859 8273",
    "sg:postcode":"45449",
    "sg:province":"OH",
    "sg:tags":[
        "industry",
        "special"
    ],
    "sg:website":"www.mmprecision.com",
    "wof:name":"Gleason-M & M Precision Systs",
    "wof:placetype":"venue"
},
  "geometry": {"coordinates":[-84.24363,39.65397],"type":"Point"}
}