{
  "type": "Feature",
  "properties": {
    "iso:country":"US",
    "sg:address":"191 Community Dr",
    "sg:city":"Urbana",
    "sg:classifiers":[
        {
            "category":"Health Services",
            "subcategory":"Health Practitioner",
            "type":"Services"
        }
    ],
    "sg:phone":"+1 937 484 6152",
    "sg:postcode":"43078",
    "sg:province":"OH",
    "sg:tags":[
        "therapist",
        "physical"
    ],
    "wof:name":"Mercy Memorial Hospital Physcl",
    "wof:placetype":"venue"
},
  "geometry": {"coordinates":[-83.724514,40.107989],"type":"Point"}
}