{
  "type": "Feature",
  "properties": {
    "addr:full":"3824 Roslyn Ave Dayton OH 45429",
    "addr:housenumber":"3824",
    "addr:postcode":"45429",
    "addr:street":"Roslyn Ave",
    "iso:country":"US",
    "sg:address":"3824 Roslyn Ave",
    "sg:city":"Dayton",
    "sg:classifiers":[
        {
            "category":"Banks & Credit Unions",
            "subcategory":"Financial Services",
            "type":"Services"
        }
    ],
    "sg:phone":"+1 937 293 8604",
    "sg:postcode":"45429",
    "sg:province":"OH",
    "sg:tags":[
        "trust",
        "management"
    ],
    "wof:name":"Hale Tammy & Terry Trustees",
    "wof:placetype":"venue"
},
  "geometry": {"coordinates":[-84.139537,39.691503],"type":"Point"}
}