{
  "type": "Feature",
  "properties": {
    "addr:full":"476 Rigrish Rd Portsmouth OH 45662",
    "addr:housenumber":"476",
    "addr:postcode":"45662",
    "addr:street":"Rigrish Rd",
    "iso:country":"US",
    "sg:address":"476 Rigrish Rd",
    "sg:city":"Portsmouth",
    "sg:classifiers":[
        {
            "category":"Farming",
            "subcategory":"Livestock Farm",
            "type":"Manufacturing & Wholesale Goods"
        }
    ],
    "sg:phone":"+1 740 776 7976",
    "sg:postcode":"45662",
    "sg:province":"OH",
    "sg:tags":[
        "animal",
        "general"
    ],
    "wof:name":"Melvin Bernthold",
    "wof:placetype":"venue"
},
  "geometry": {"coordinates":[-82.85597799999999,38.773504],"type":"Point"}
}