{
  "type": "Feature",
  "properties": {
    "addr:full":"2500 Stillwater Rd Houston OH 45333",
    "addr:housenumber":"2500",
    "addr:postcode":"45333",
    "addr:street":"Stillwater Rd",
    "iso:country":"US",
    "sg:address":"2500 Stillwater Rd",
    "sg:city":"Houston",
    "sg:classifiers":[
        {
            "category":"Farming",
            "subcategory":"Dairy Farm",
            "type":"Manufacturing & Wholesale Goods"
        }
    ],
    "sg:phone":"+1 937 778 1641",
    "sg:postcode":"45333",
    "sg:province":"OH",
    "wof:name":"Paul L Delaet",
    "wof:placetype":"venue"
},
  "geometry": {"coordinates":[-84.339944,40.235123],"type":"Point"}
}