{
  "type": "Feature",
  "properties": {
    "addr:full":"3581 Co Rd 140 Findlay OH 45840",
    "addr:housenumber":"3581",
    "addr:postcode":"45840",
    "addr:street":"Co Rd 140",
    "iso:country":"US",
    "sg:address":"3581 Co Rd 140",
    "sg:city":"Findlay",
    "sg:classifiers":[
        {
            "category":"Retail",
            "subcategory":"Laundry & Dry Cleaning",
            "type":"Services"
        }
    ],
    "sg:phone":"+1 419 299 3500",
    "sg:postcode":"45840",
    "sg:province":"OH",
    "sg:tags":[
        "cleaners",
        "rug",
        "carpet"
    ],
    "wof:name":"Premier Plus",
    "wof:placetype":"venue"
},
  "geometry": {"coordinates":[-83.688357,41.11678],"type":"Point"}
}