{
  "type": "Feature",
  "properties": {
    "addr:full":"1978 Greensburg Rd Canton OH 44720",
    "addr:housenumber":"1978",
    "addr:postcode":"44720",
    "addr:street":"Greensburg Rd",
    "iso:country":"US",
    "sg:address":"1978 Greensburg Rd",
    "sg:city":"Canton",
    "sg:classifiers":[
        {
            "category":"Shopping",
            "subcategory":"Computers & Home Electronics",
            "type":"Retail Goods"
        }
    ],
    "sg:phone":"+1 330 899 9009",
    "sg:postcode":"44720",
    "sg:province":"OH",
    "sg:tags":[
        "equipment",
        "satellite",
        "system"
    ],
    "wof:name":"All Star Satellite",
    "wof:placetype":"venue"
},
  "geometry": {"coordinates":[-81.47614299999999,40.932643],"type":"Point"}
}