{
  "type": "Feature",
  "properties": {
    "iso:country":"US",
    "sg:address":"5078 Warrensville Center Rd",
    "sg:city":"Cleveland",
    "sg:classifiers":[
        {
            "category":"Shopping",
            "subcategory":"Gifts & Souvenirs",
            "type":"Retail Goods"
        }
    ],
    "sg:phone":"+1 216 663 1091",
    "sg:postcode":"44137",
    "sg:province":"OH",
    "sg:tags":[
        "party",
        "supply"
    ],
    "wof:name":"Babes Beverage",
    "wof:placetype":"venue"
},
  "geometry": {"coordinates":[-81.53745,41.422197],"type":"Point"}
}