{
  "type": "Feature",
  "properties": {
    "iso:country":"US",
    "sg:address":"6431 Twp Rd 93",
    "sg:city":"New Riegel",
    "sg:phone":"+1 419 595 2151",
    "sg:postcode":"44853",
    "sg:province":"OH",
    "sg:tags":[
        "farm",
        "corn",
        "wheat",
        "soybean"
    ],
    "wof:name":"Thomas Boes",
    "wof:placetype":"venue"
},
  "geometry": {"coordinates":[-83.324375,41.029786],"type":"Point"}
}