{
  "type": "Feature",
  "properties": {
    "addr:full": "8523 Hickory Hill Dr Youngstown OH 44514",
    "addr:housenumber": "8523",
    "addr:postcode": "44514",
    "addr:street": "Hickory Hill Dr",
    "iso:country": "US",
    "sg:address": "8523 Hickory Hill Dr",
    "sg:city": "Youngstown",
    "sg:classifiers": [
      {
        "category": "Shopping",
        "subcategory": "Catalog Store",
        "type": "Retail Goods"
      }
    ],
    "sg:phone": "+1 330 757 1663",
    "sg:postcode": "44514",
    "sg:province": "OH",
    "sg:tags": [
      "house",
      "mail"
    ],
    "wof:name": "James D Leonelli",
    "wof:placetype": "venue"
  },
  "geometry": {"coordinates":[-80.627516,40.99121],"type":"Point"}
}
