{
  "type": "Feature",
  "properties": {
    "addr:full": "1867 Goleta Ave Youngstown OH 44504",
    "addr:housenumber": "1867",
    "addr:postcode": "44504",
    "addr:street": "Goleta Ave",
    "iso:country": "US",
    "sg:address": "1867 Goleta Ave",
    "sg:city": "Youngstown",
    "sg:classifiers": [
      {
        "category": "Retail",
        "subcategory": "Laundry \u0026 Dry Cleaning",
        "type": "Services"
      }
    ],
    "sg:phone": "+1 330 746 5624",
    "sg:postcode": "44504",
    "sg:province": "OH",
    "sg:tags": [
      "cleaner",
      "rug",
      "carpet"
    ],
    "wof:name": "A Final Solution",
    "wof:placetype": "venue"
  },
  "geometry": {"coordinates":[-80.655645,41.127559],"type":"Point"}
}
