{
  "type": "Feature",
  "properties": {
    "addr:full":"1587 Boettler Rd Uniontown OH 44685",
    "addr:housenumber":"1587",
    "addr:postcode":"44685",
    "addr:street":"Boettler Rd",
    "iso:country":"US",
    "sg:address":"1587 Boettler Rd",
    "sg:city":"Uniontown",
    "sg:classifiers":[
        {
            "category":"Health Services",
            "subcategory":"Doctor",
            "type":"Services"
        }
    ],
    "sg:phone":"+1 330 864 8008",
    "sg:postcode":"44685",
    "sg:province":"OH",
    "sg:tags":[
        "physician",
        "surgeon"
    ],
    "wof:name":"Urology Inc",
    "wof:placetype":"venue"
},
  "geometry": {"coordinates":[-81.470309,40.95943],"type":"Point"}
}