{
  "type": "Feature",
  "properties": {
    "iso:country":"US",
    "sg:address":"150 University Ave",
    "sg:city":"Akron",
    "sg:classifiers":[
        {
            "category":"Education",
            "subcategory":"College",
            "type":"Public Place"
        }
    ],
    "sg:phone":"+1 330 972 7331",
    "sg:postcode":"44308",
    "sg:province":"OH",
    "wof:name":"University of Akron School Law",
    "wof:placetype":"venue"
},
  "geometry": {"coordinates":[-81.515816,41.077788],"type":"Point"}
}