{
  "type": "Feature",
  "properties": {
    "addr:full": "28045 Clemens Rd Westlake OH 44145",
    "addr:housenumber": "28045",
    "addr:postcode": "44145",
    "addr:street": "Clemens Rd",
    "iso:country": "US",
    "sg:address": "28045 Clemens Rd",
    "sg:city": "Westlake",
    "sg:classifiers": [
      {
        "category": "Airport",
        "type": "Transportation"
      }
    ],
    "sg:phone": "+1 440 899 3100",
    "sg:postcode": "44145",
    "sg:province": "OH",
    "wof:name": "Wheels Up Ltd",
    "wof:placetype": "venue"
  },
  "geometry": {"coordinates":[-81.941627,41.470289],"type":"Point"}
}
