{
  "type": "Feature",
  "properties": {
    "iso:country":"US",
    "sg:address":"4343 Carmont Ave SW",
    "sg:city":"Navarre",
    "sg:classifiers":[
        {
            "category":"Retail",
            "subcategory":"Auto Repair",
            "type":"Services"
        }
    ],
    "sg:phone":"+1 330 879 9990",
    "sg:postcode":"44662",
    "sg:province":"OH",
    "sg:tags":[
        "repairing",
        "automobile"
    ],
    "wof:name":"Bill's Automotive",
    "wof:placetype":"venue"
},
  "geometry": {"coordinates":[-81.54709699999999,40.749448],"type":"Point"}
}