{
  "type": "Feature",
  "properties": {
    "iso:country":"US",
    "sg:address":"220 N Clinton St",
    "sg:city":"Defiance",
    "sg:classifiers":[
        {
            "category":"Wholesale",
            "subcategory":"Dairy",
            "type":"Manufacturing & Wholesale Goods"
        }
    ],
    "sg:phone":"+1 419 782 9116",
    "sg:postcode":"43512",
    "sg:province":"OH",
    "sg:tags":[
        "product"
    ],
    "sg:website":"www.arpsdairy.com",
    "wof:name":"Arps Dairy Inc",
    "wof:placetype":"venue"
},
  "geometry": {"coordinates":[-84.360865,41.291366],"type":"Point"}
}