{
  "type": "Feature",
  "properties": {
    "addr:full": "220 N Clinton St Defiance OH 43512",
    "addr:housenumber": "220",
    "addr:postcode": "43512",
    "addr:street": "N Clinton St",
    "iso:country": "US",
    "sg:address": "220 N Clinton St",
    "sg:city": "Defiance",
    "sg:classifiers": [
      {
        "category": "Wholesale",
        "subcategory": "Dairy",
        "type": "Manufacturing \u0026 Wholesale Goods"
      }
    ],
    "sg:phone": "+1 419 782 9116",
    "sg:postcode": "43512",
    "sg:province": "OH",
    "sg:tags": [
      "product"
    ],
    "sg:website": "www.arpsdairy.com",
    "wof:name": "Arps Dairy Inc",
    "wof:placetype": "venue"
  },
  "geometry": {"coordinates":[-84.360865,41.291366],"type":"Point"}
}
