{
  "type": "Feature",
  "properties": {
    "addr:full":"985 Dellwood Dr Troy OH 45373",
    "addr:housenumber":"985",
    "addr:postcode":"45373",
    "addr:street":"Dellwood Dr",
    "iso:country":"US",
    "sg:address":"985 Dellwood Dr",
    "sg:city":"Troy",
    "sg:classifiers":[
        {
            "category":"Organizations",
            "subcategory":"Religious Organization",
            "type":"Services"
        }
    ],
    "sg:phone":"+1 937 335 7311",
    "sg:postcode":"45373",
    "sg:province":"OH",
    "sg:tags":[
        "church"
    ],
    "wof:name":"Bible Missionary Church",
    "wof:placetype":"venue"
},
  "geometry": {"coordinates":[-84.190028,40.049314],"type":"Point"}
}