{
  "type": "Feature",
  "properties": {
    "addr:full": "3793 Bay Path Dr Akron OH 44319",
    "addr:housenumber": "3793",
    "addr:postcode": "44319",
    "addr:street": "Bay Path Dr",
    "iso:country": "US",
    "sg:address": "3793 Bay Path Dr",
    "sg:city": "Akron",
    "sg:classifiers": [
      {
        "category": "Professional",
        "subcategory": "Computer Services",
        "type": "Services"
      }
    ],
    "sg:phone": "+1 330 644 4613",
    "sg:postcode": "44319",
    "sg:province": "OH",
    "sg:tags": [
      "internet"
    ],
    "wof:name": "Internet Service Consultant",
    "wof:placetype": "venue"
  },
  "geometry": {"coordinates":[-81.541925,40.991897],"type":"Point"}
}
