{
  "type": "Feature",
  "properties": {
    "iso:country":"US",
    "sg:address":"3145 S Canal St",
    "sg:city":"Newton Falls",
    "sg:classifiers":[
        {
            "category":"Farming",
            "subcategory":"Farm",
            "type":"Manufacturing & Wholesale Goods"
        }
    ],
    "sg:phone":"+1 330 872 5987",
    "sg:postcode":"44444",
    "sg:province":"OH",
    "sg:tags":[
        "crop",
        "general"
    ],
    "wof:name":"Clark Farms",
    "wof:placetype":"venue"
},
  "geometry": {"coordinates":[-80.988587,41.162321],"type":"Point"}
}