{
  "type": "Feature",
  "properties": {
    "addr:full":"11648 Lorain Ave Cleveland OH 44111",
    "addr:housenumber":"11648",
    "addr:postcode":"44111",
    "addr:street":"Lorain Ave",
    "iso:country":"US",
    "sg:address":"11648 Lorain Ave",
    "sg:city":"Cleveland",
    "sg:classifiers":[
        {
            "category":"Professional",
            "subcategory":"Employment Agencies",
            "type":"Services"
        }
    ],
    "sg:phone":"+1 216 941 2222",
    "sg:postcode":"44111",
    "sg:province":"OH",
    "sg:tags":[
        "help",
        "contractor"
    ],
    "sg:website":"www.areatemps.com",
    "wof:name":"Area Temps",
    "wof:placetype":"venue"
},
  "geometry": {"coordinates":[-81.768491,41.462134],"type":"Point"}
}