{
  "type": "Feature",
  "properties": {
    "addr:full":"7495 State Rd Cincinnati OH 45255",
    "addr:housenumber":"7495",
    "addr:postcode":"45255",
    "addr:street":"State Rd",
    "iso:country":"US",
    "sg:address":"7495 State Rd",
    "sg:city":"Cincinnati",
    "sg:classifiers":[
        {
            "category":"Health Services",
            "subcategory":"Doctor",
            "type":"Services"
        }
    ],
    "sg:phone":"+1 513 636 4751",
    "sg:postcode":"45255",
    "sg:province":"OH",
    "sg:tags":[
        "physician",
        "surgeon"
    ],
    "wof:name":"Abrahamson Pediatric Eye Inst",
    "wof:placetype":"venue"
},
  "geometry": {"coordinates":[-84.346847,39.084128],"type":"Point"}
}