{
  "type": "Feature",
  "properties": {
    "addr:full":"5991 S Sunbury Rd Westerville OH 43081",
    "addr:housenumber":"5991",
    "addr:postcode":"43081",
    "addr:street":"S Sunbury Rd",
    "iso:country":"US",
    "sg:address":"5991 S Sunbury Rd",
    "sg:city":"Westerville",
    "sg:classifiers":[
        {
            "category":"Banks & Credit Unions",
            "subcategory":"Bank",
            "type":"Services"
        }
    ],
    "sg:phone":"+1 614 898 4963",
    "sg:postcode":"43081",
    "sg:province":"OH",
    "wof:name":"Fifth Third Bank",
    "wof:placetype":"venue"
},
  "geometry": {"coordinates":[-82.895736,40.083131],"type":"Point"}
}