{
  "type": "Feature",
  "properties": {
    "iso:country":"US",
    "sg:address":"505 E Ohio Ave",
    "sg:city":"Mount Vernon",
    "sg:classifiers":[
        {
            "category":"Building & Trades",
            "subcategory":"Construction",
            "type":"Services"
        }
    ],
    "sg:phone":"+1 740 392 6801",
    "sg:postcode":"43050",
    "sg:province":"OH",
    "sg:tags":[
        "house"
    ],
    "wof:name":"Joes Home Repairs",
    "wof:placetype":"venue"
},
  "geometry": {"coordinates":[-82.478675,40.390541],"type":"Point"}
}