{
  "type": "Feature",
  "properties": {
    "addr:full":"3533 Epley Ln Cincinnati OH 45247",
    "addr:housenumber":"3533",
    "addr:postcode":"45247",
    "addr:street":"Epley Ln",
    "iso:country":"US",
    "sg:address":"3533 Epley Ln",
    "sg:city":"Cincinnati",
    "sg:classifiers":[
        {
            "category":"Building & Trades",
            "subcategory":"Construction",
            "type":"Services"
        }
    ],
    "sg:phone":"+1 513 385 5160",
    "sg:postcode":"45247",
    "sg:province":"OH",
    "sg:tags":[
        "general",
        "contractor"
    ],
    "wof:name":"Tri State Framing Inc",
    "wof:placetype":"venue"
},
  "geometry": {"coordinates":[-84.600863,39.191324],"type":"Point"}
}