{
  "type": "Feature",
  "properties": {
    "iso:country":"US",
    "sg:address":"733 N Court St",
    "sg:city":"Medina",
    "sg:classifiers":[
        {
            "category":"Personal",
            "subcategory":"Beauty Salon",
            "type":"Services"
        }
    ],
    "sg:phone":"+1 330 721 4545",
    "sg:postcode":"44256",
    "sg:province":"OH",
    "wof:name":"Salon Rootz",
    "wof:placetype":"venue"
},
  "geometry": {"coordinates":[-81.86376,41.148002],"type":"Point"}
}