{
  "type": "Feature",
  "properties": {
    "addr:full":"5567 Mayfield Rd Cleveland OH 44124",
    "addr:housenumber":"5567",
    "addr:postcode":"44124",
    "addr:street":"Mayfield Rd",
    "iso:country":"US",
    "sg:address":"5567 Mayfield Rd",
    "sg:city":"Cleveland",
    "sg:classifiers":[
        {
            "category":"Professional",
            "subcategory":"Credit Reporting & Collection",
            "type":"Services"
        }
    ],
    "sg:phone":"+1 440 442 6722",
    "sg:postcode":"44124",
    "sg:province":"OH",
    "sg:tags":[
        "agency"
    ],
    "wof:name":"Diversified Credit Svc",
    "wof:placetype":"venue"
},
  "geometry": {"coordinates":[-81.47829400000001,41.520054],"type":"Point"}
}