{
  "type": "Feature",
  "properties": {
    "addr:full": "10710 Kenwood Rd Cincinnati OH 45242",
    "addr:housenumber": "10710",
    "addr:postcode": "45242",
    "addr:street": "Kenwood Rd",
    "iso:country": "US",
    "sg:address": "10710 Kenwood Rd",
    "sg:city": "Cincinnati",
    "sg:classifiers": [
      {
        "category": "Banks \u0026 Credit Unions",
        "subcategory": "Investment Brokerage",
        "type": "Services"
      }
    ],
    "sg:phone": "+1 513 231 8211",
    "sg:postcode": "45242",
    "sg:province": "OH",
    "sg:tags": [
      "consultant",
      "planning",
      "financial"
    ],
    "wof:name": "Corporate Planning Systems",
    "wof:placetype": "venue"
  },
  "geometry": {"coordinates":[-84.374378,39.25753],"type":"Point"}
}
