{
  "type": "Feature",
  "properties": {
    "addr:full": "428 N Main St Niles OH 44446",
    "addr:housenumber": "428",
    "addr:postcode": "44446",
    "addr:street": "N Main St",
    "iso:country": "US",
    "sg:address": "428 N Main St",
    "sg:city": "Niles",
    "sg:classifiers": [
      {
        "category": "Restaurant",
        "type": "Food \u0026 Drink"
      }
    ],
    "sg:menulink": "http://www.allmenus.com/oh/weathersfield/195271-mcdonalds/menu/",
    "sg:postcode": "44446",
    "sg:province": "OH",
    "sg:tags": [
      "burger",
      "american"
    ],
    "wof:name": "McDonald's",
    "wof:placetype": "venue"
  },
  "geometry": {"coordinates":[-80.765017,41.185344],"type":"Point"}
}
