{
  "type": "Feature",
  "properties": {
    "iso:country":"US",
    "sg:address":"1030 Miami Rd",
    "sg:city":"Piqua",
    "sg:classifiers":[
        {
            "category":"Building & Trades",
            "subcategory":"Construction",
            "type":"Services"
        }
    ],
    "sg:phone":"+1 937 773 8258",
    "sg:postcode":"45356",
    "sg:province":"OH",
    "sg:tags":[
        "house",
        "electrical",
        "contractor"
    ],
    "wof:name":"Stewart Construction & Rmdlg",
    "wof:placetype":"venue"
},
  "geometry": {"coordinates":[-84.236173,40.156334],"type":"Point"}
}