{
  "type": "Feature",
  "properties": {
    "iso:country":"US",
    "sg:address":"6987 State Rte 43",
    "sg:city":"Kent",
    "sg:classifiers":[
        {
            "category":"Retail",
            "subcategory":"Auto Repair",
            "type":"Services"
        }
    ],
    "sg:phone":"+1 330 678 4632",
    "sg:postcode":"44240",
    "sg:province":"OH",
    "sg:tags":[
        "repairing",
        "automobile"
    ],
    "wof:name":"Mars Motors",
    "wof:placetype":"venue"
},
  "geometry": {"coordinates":[-81.351213,41.174126],"type":"Point"}
}