{
  "type": "Feature",
  "properties": {
    "addr:full": "45959 W Captina Hwy Alledonia OH 43902",
    "addr:housenumber": "45959",
    "addr:postcode": "43902",
    "addr:street": "W Captina Hwy",
    "iso:country": "US",
    "sg:address": "45959 W Captina Hwy",
    "sg:city": "Alledonia",
    "sg:classifiers": [
      {
        "category": "Freight",
        "type": "Transportation"
      }
    ],
    "sg:phone": "+1 740 926 2026",
    "sg:postcode": "43902",
    "sg:province": "OH",
    "sg:tags": [
      "trucking"
    ],
    "wof:name": "Saffell Trucking",
    "wof:placetype": "venue"
  },
  "geometry": {"coordinates":[-80.979134,39.907396],"type":"Point"}
}
