{
  "type": "Feature",
  "properties": {
    "addr:full": "237 E Front St Youngstown OH 44503",
    "addr:housenumber": "237",
    "addr:postcode": "44503",
    "addr:street": "E Front St",
    "iso:country": "US",
    "sg:address": "237 E Front St",
    "sg:city": "Youngstown",
    "sg:classifiers": [
      {
        "category": "Real Estate",
        "subcategory": "Real Estate Agent",
        "type": "Services"
      }
    ],
    "sg:phone": "+1 330 759 3871",
    "sg:postcode": "44503",
    "sg:province": "OH",
    "sg:tags": [
      "finding",
      "apartment",
      "rental"
    ],
    "wof:name": "Eagle Holding Co",
    "wof:placetype": "venue"
  },
  "geometry": {"coordinates":[-80.646953,41.096683],"type":"Point"}
}
