{
  "type": "Feature",
  "properties": {
    "addr:full":"1165 Colony Dr Westerville OH 43081",
    "addr:housenumber":"1165",
    "addr:postcode":"43081",
    "addr:street":"Colony Dr",
    "iso:country":"US",
    "sg:address":"1165 Colony Dr",
    "sg:city":"Westerville",
    "sg:classifiers":[
        {
            "category":"Real Estate",
            "subcategory":"Real Estate Operator",
            "type":"Services"
        }
    ],
    "sg:phone":"+1 614 890 6152",
    "sg:postcode":"43081",
    "sg:province":"OH",
    "sg:tags":[
        "apartment"
    ],
    "wof:name":"Columbus Colony Housing 1",
    "wof:placetype":"venue"
},
  "geometry": {"coordinates":[-82.891757,40.097564],"type":"Point"}
}