{
  "type": "Feature",
  "properties": {
    "addr:full":"4811 Douglas Rd Toledo OH 43613",
    "addr:housenumber":"4811",
    "addr:postcode":"43613",
    "addr:street":"Douglas Rd",
    "iso:country":"US",
    "sg:address":"4811 Douglas Rd",
    "sg:city":"Toledo",
    "sg:classifiers":[
        {
            "category":"Real Estate",
            "subcategory":"Real Estate Operator",
            "type":"Services"
        }
    ],
    "sg:phone":"+1 419 472 6087",
    "sg:postcode":"43613",
    "sg:province":"OH",
    "sg:tags":[
        "apartment"
    ],
    "wof:name":"Douglas Square Apartments",
    "wof:placetype":"venue"
},
  "geometry": {"coordinates":[-83.60416499999999,41.703653],"type":"Point"}
}