{
  "type": "Feature",
  "properties": {
    "iso:country":"US",
    "sg:address":"616 Valley St",
    "sg:city":"Minerva",
    "sg:classifiers":[
        {
            "category":"Shopping",
            "subcategory":"Crafts & Fabrics",
            "type":"Retail Goods"
        }
    ],
    "sg:phone":"+1 330 868 6937",
    "sg:postcode":"44657",
    "sg:province":"OH",
    "sg:tags":[
        "sewing"
    ],
    "wof:name":"Calico Grandmas",
    "wof:placetype":"venue"
},
  "geometry": {"coordinates":[-81.108643,40.721912],"type":"Point"}
}