{
  "type": "Feature",
  "properties": {
    "iso:country":"US",
    "sg:address":"1015 Seabrook Way",
    "sg:city":"Cincinnati",
    "sg:classifiers":[
        {
            "category":"Wholesale",
            "subcategory":"Metals & Minerals",
            "type":"Manufacturing & Wholesale Goods"
        }
    ],
    "sg:phone":"+1 513 943 1290",
    "sg:postcode":"45245",
    "sg:province":"OH",
    "sg:tags":[
        "steel",
        "warehouse"
    ],
    "wof:name":"Slice Of Stainless",
    "wof:placetype":"venue"
},
  "geometry": {"coordinates":[-84.258668,39.067532],"type":"Point"}
}