{
  "type": "Feature",
  "properties": {
    "addr:full": "1015 Seabrook Way Cincinnati OH 45245",
    "addr:housenumber": "1015",
    "addr:postcode": "45245",
    "addr:street": "Seabrook Way",
    "iso:country": "US",
    "sg:address": "1015 Seabrook Way",
    "sg:city": "Cincinnati",
    "sg:classifiers": [
      {
        "category": "Wholesale",
        "subcategory": "Metals \u0026 Minerals",
        "type": "Manufacturing \u0026 Wholesale Goods"
      }
    ],
    "sg:phone": "+1 513 943 1290",
    "sg:postcode": "45245",
    "sg:province": "OH",
    "sg:tags": [
      "steel",
      "warehouse"
    ],
    "wof:name": "Slice Of Stainless",
    "wof:placetype": "venue"
  },
  "geometry": {"coordinates":[-84.258668,39.067532],"type":"Point"}
}
