{
  "type": "Feature",
  "properties": {
    "addr:full": "518 3rd Ave Chesapeake OH 45619",
    "addr:housenumber": "518",
    "addr:postcode": "45619",
    "addr:street": "3Rd Ave",
    "iso:country": "US",
    "sg:address": "518 3rd Ave",
    "sg:city": "Chesapeake",
    "sg:classifiers": [
      {
        "category": "Recreation",
        "type": "Entertainment"
      }
    ],
    "sg:phone": "+1 740 867 5020",
    "sg:postcode": "45619",
    "sg:province": "OH",
    "sg:tags": [
      "club",
      "membership"
    ],
    "wof:name": "Vance Club USA",
    "wof:placetype": "venue"
  },
  "geometry": {"coordinates":[-82.458784,38.427628],"type":"Point"}
}
