{
  "type": "Feature",
  "properties": {
    "addr:full": "1323 33rd St NE Canton OH 44714",
    "addr:housenumber": "1323",
    "addr:postcode": "44714",
    "addr:street": "33Rd St Ne",
    "iso:country": "US",
    "sg:address": "1323 33rd St NE",
    "sg:city": "Canton",
    "sg:classifiers": [
      {
        "category": "Retail",
        "subcategory": "Portrait Studio",
        "type": "Services"
      }
    ],
    "sg:phone": "+1 330 454 7915",
    "sg:postcode": "44714",
    "sg:province": "OH",
    "sg:tags": [
      "photographer"
    ],
    "wof:name": "Marty's Custom Photography",
    "wof:placetype": "venue"
  },
  "geometry": {"coordinates":[-81.356517,40.833487],"type":"Point"}
}
