{
  "type": "Feature",
  "properties": {
    "addr:full": "7105 Bessemer Ave Cleveland OH 44127",
    "addr:housenumber": "7105",
    "addr:postcode": "44127",
    "addr:street": "Bessemer Ave",
    "iso:country": "US",
    "sg:address": "7105 Bessemer Ave",
    "sg:city": "Cleveland",
    "sg:classifiers": [
      {
        "category": "Manufacturing",
        "subcategory": "Metals",
        "type": "Manufacturing \u0026 Wholesale Goods"
      }
    ],
    "sg:phone": "+1 216 441 0057",
    "sg:postcode": "44127",
    "sg:province": "OH",
    "sg:tags": [
      "equipment",
      "mfg",
      "machinery",
      "forging"
    ],
    "wof:name": "Presrite Bessemer",
    "wof:placetype": "venue"
  },
  "geometry": {"coordinates":[-81.636676,41.468334],"type":"Point"}
}
