{
  "type": "Feature",
  "properties": {
    "iso:country":"US",
    "sg:address":"7469 Worthington Galena Rd",
    "sg:city":"Columbus",
    "sg:classifiers":[
        {
            "category":"Home & Garden",
            "subcategory":"Carpets & Floor Coverings",
            "type":"Retail Goods"
        }
    ],
    "sg:phone":"+1 614 846 0214",
    "sg:postcode":"43085",
    "sg:province":"OH",
    "sg:tags":[
        "contractor"
    ],
    "wof:name":"Best Tile Distrs of Pittsburgh",
    "wof:placetype":"venue"
},
  "geometry": {"coordinates":[-82.991281,40.115409],"type":"Point"}
}