{
  "type": "Feature",
  "properties": {
    "addr:full":"181 Schofield Dr Columbus OH 43213",
    "addr:housenumber":"181",
    "addr:postcode":"43213",
    "addr:street":"Schofield Dr",
    "iso:country":"US",
    "sg:address":"181 Schofield Dr",
    "sg:city":"Columbus",
    "sg:classifiers":[
        {
            "category":"Manufacturing",
            "subcategory":"Furniture",
            "type":"Manufacturing & Wholesale Goods"
        }
    ],
    "sg:phone":"+1 614 367 1072",
    "sg:postcode":"43213",
    "sg:province":"OH",
    "sg:tags":[
        "mfg",
        "design",
        "closet",
        "custom"
    ],
    "wof:name":"Office Factory The",
    "wof:placetype":"venue"
},
  "geometry": {"coordinates":[-82.879907,39.977842],"type":"Point"}
}