{
  "type": "Feature",
  "properties": {
    "addr:full": "62 N Maple St Germantown OH 45327",
    "addr:housenumber": "62",
    "addr:postcode": "45327",
    "addr:street": "N Maple St",
    "iso:country": "US",
    "sg:address": "62 N Maple St",
    "sg:city": "Germantown",
    "sg:classifiers": [
      {
        "category": "Professional",
        "subcategory": "Business Services",
        "type": "Services"
      }
    ],
    "sg:phone": "+1 937 855 2621",
    "sg:postcode": "45327",
    "sg:province": "OH",
    "sg:tags": [
      "interior",
      "consultant",
      "design",
      "decorator"
    ],
    "wof:name": "C J's Interior Trim",
    "wof:placetype": "venue"
  },
  "geometry": {"coordinates":[-84.375974,39.625772],"type":"Point"}
}
