{
  "type": "Feature",
  "properties": {
    "addr:full":"10325 Brecksville Rd Brecksville OH 44141",
    "addr:housenumber":"10325",
    "addr:postcode":"44141",
    "addr:street":"Brecksville Rd",
    "iso:country":"US",
    "sg:address":"10325 Brecksville Rd",
    "sg:city":"Brecksville",
    "sg:classifiers":[
        {
            "category":"Retail",
            "subcategory":"Repair Shop",
            "type":"Services"
        },
        {
            "category":"Manufacturing",
            "subcategory":"Tools & Machinery",
            "type":"Manufacturing & Wholesale Goods"
        }
    ],
    "sg:phone":"+1 440 546 7553",
    "sg:postcode":"44141",
    "sg:province":"OH",
    "sg:tags":[
        "machine",
        "driven",
        "industrial",
        "computer",
        "sales"
    ],
    "wof:name":"Ohio HI-Speed Machine Inc",
    "wof:placetype":"venue"
},
  "geometry": {"coordinates":[-81.627105,41.281432],"type":"Point"}
}