{
  "type": "Feature",
  "properties": {
    "addr:full": "8277 Audubon St NW Massillon OH 44646",
    "addr:housenumber": "8277",
    "addr:postcode": "44646",
    "addr:street": "Audubon St Nw",
    "iso:country": "US",
    "sg:address": "8277 Audubon St NW",
    "sg:city": "Massillon",
    "sg:classifiers": [
      {
        "category": "Communications",
        "type": "Services"
      }
    ],
    "sg:phone": "+1 330 492 6468",
    "sg:postcode": "44646",
    "sg:province": "OH",
    "sg:tags": [
      "web",
      "design"
    ],
    "wof:name": "Visual Arts Spectrum",
    "wof:placetype": "venue"
  },
  "geometry": {"coordinates":[-81.504895,40.843882],"type":"Point"}
}
