{
  "type": "Feature",
  "properties": {
    "addr:full":"135 Northfield Rd Cleveland OH 44146",
    "addr:housenumber":"135",
    "addr:postcode":"44146",
    "addr:street":"Northfield Rd",
    "iso:country":"US",
    "sg:address":"135 Northfield Rd",
    "sg:city":"Cleveland",
    "sg:classifiers":[
        {
            "category":"Wholesale",
            "subcategory":"Electrical",
            "type":"Manufacturing & Wholesale Goods"
        }
    ],
    "sg:phone":"+1 440 232 7090",
    "sg:postcode":"44146",
    "sg:province":"OH",
    "sg:tags":[
        "electric",
        "motor"
    ],
    "wof:name":"Al's Electric Motor Svc",
    "wof:placetype":"venue"
},
  "geometry": {"coordinates":[-81.52680100000001,41.377759],"type":"Point"}
}