{
  "type": "Feature",
  "properties": {
    "addr:full":"7629 Pearl Rd Cleveland OH 44130",
    "addr:housenumber":"7629",
    "addr:postcode":"44130",
    "addr:street":"Pearl Rd",
    "iso:country":"US",
    "sg:address":"7629 Pearl Rd",
    "sg:city":"Cleveland",
    "sg:classifiers":[
        {
            "category":"Retail",
            "subcategory":"Car Wash",
            "type":"Services"
        }
    ],
    "sg:phone":"+1 440 243 1402",
    "sg:postcode":"44130",
    "sg:province":"OH",
    "sg:tags":[
        "carwash"
    ],
    "wof:name":"Sunnyside Detail Center",
    "wof:placetype":"venue"
},
  "geometry": {"coordinates":[-81.81558200000001,41.35901],"type":"Point"}
}