{
  "type": "Feature",
  "properties": {
    "addr:full": "318 N Main St Lima OH 45801",
    "addr:housenumber": "318",
    "addr:postcode": "45801",
    "addr:street": "N Main St",
    "iso:country": "US",
    "sg:address": "318 N Main St",
    "sg:city": "Lima",
    "sg:classifiers": [
      {
        "category": "Bars \u0026 Pubs",
        "type": "Food \u0026 Drink"
      }
    ],
    "sg:phone": "+1 419 523 6399",
    "sg:postcode": "45801",
    "sg:province": "OH",
    "sg:tags": [
      "drinking"
    ],
    "wof:name": "Silver Shamrock Irish Pub LLC",
    "wof:placetype": "venue"
  },
  "geometry": {"coordinates":[-84.10491,40.743796],"type":"Point"}
}
