{
  "type": "Feature",
  "properties": {
    "iso:country":"US",
    "sg:address":"318 N Main St",
    "sg:city":"Lima",
    "sg:classifiers":[
        {
            "category":"Bars & Pubs",
            "type":"Food & Drink"
        }
    ],
    "sg:phone":"+1 419 523 6399",
    "sg:postcode":"45801",
    "sg:province":"OH",
    "sg:tags":[
        "drinking"
    ],
    "wof:name":"Silver Shamrock Irish Pub LLC",
    "wof:placetype":"venue"
},
  "geometry": {"coordinates":[-84.10491,40.743796],"type":"Point"}
}