{
  "type": "Feature",
  "properties": {
    "iso:country":"US",
    "sg:address":"110 W Point Pl",
    "sg:city":"Mount Orab",
    "sg:classifiers":[
        {
            "category":"Restaurant",
            "type":"Food & Drink"
        }
    ],
    "sg:phone":"+1 937 444 0203",
    "sg:postcode":"45154",
    "sg:province":"OH",
    "sg:tags":[
        "eating"
    ],
    "wof:name":"Skyline Chili",
    "wof:placetype":"venue"
},
  "geometry": {"coordinates":[-83.91474700000001,39.015893],"type":"Point"}
}