{
  "type": "Feature",
  "properties": {
    "addr:full": "110 W Point Pl Mount Orab OH 45154",
    "addr:housenumber": "110",
    "addr:postcode": "45154",
    "addr:street": "W Point Pl",
    "iso:country": "US",
    "sg:address": "110 W Point Pl",
    "sg:city": "Mount Orab",
    "sg:classifiers": [
      {
        "category": "Restaurant",
        "type": "Food \u0026 Drink"
      }
    ],
    "sg:phone": "+1 937 444 0203",
    "sg:postcode": "45154",
    "sg:province": "OH",
    "sg:tags": [
      "eating"
    ],
    "wof:name": "Skyline Chili",
    "wof:placetype": "venue"
  },
  "geometry": {"coordinates":[-83.914747,39.015893],"type":"Point"}
}
