{
  "type": "Feature",
  "properties": {
    "iso:country":"US",
    "sg:address":"8179 Princeton Glendale Rd",
    "sg:city":"Hamilton",
    "sg:classifiers":[
        {
            "category":"Health Services",
            "subcategory":"Optometrist",
            "type":"Services"
        }
    ],
    "sg:phone":"+1 513 860 5525",
    "sg:postcode":"45011",
    "sg:province":"OH",
    "wof:name":"West Chester Eye Care",
    "wof:placetype":"venue"
},
  "geometry": {"coordinates":[-84.46139700000001,39.352513],"type":"Point"}
}