{
  "type": "Feature",
  "properties": {
    "addr:full":"3315 Catherine Dr Vienna OH 44473",
    "addr:housenumber":"3315",
    "addr:postcode":"44473",
    "addr:street":"Catherine Dr",
    "iso:country":"US",
    "sg:address":"3315 Catherine Dr",
    "sg:city":"Vienna",
    "sg:classifiers":[
        {
            "category":"Wholesale",
            "subcategory":"Machinery & Supplies",
            "type":"Manufacturing & Wholesale Goods"
        }
    ],
    "sg:phone":"+1 330 539 5339",
    "sg:postcode":"44473",
    "sg:province":"OH",
    "wof:name":"Sollberger Stone Industries",
    "wof:placetype":"venue"
},
  "geometry": {"coordinates":[-80.700647,41.214385],"type":"Point"}
}