{
  "type": "Feature",
  "properties": {
    "addr:full": "10496 Mitchell Rd Columbia Station OH 44028",
    "addr:housenumber": "10496",
    "addr:postcode": "44028",
    "addr:street": "Mitchell Rd",
    "iso:country": "US",
    "sg:address": "10496 Mitchell Rd",
    "sg:city": "Columbia Station",
    "sg:classifiers": [
      {
        "category": "Building \u0026 Trades",
        "subcategory": "Construction",
        "type": "Services"
      }
    ],
    "sg:phone": "+1 440 236 6654",
    "sg:postcode": "44028",
    "sg:province": "OH",
    "sg:tags": [
      "nonresidential"
    ],
    "wof:name": "L \u0026 R Home Improvements",
    "wof:placetype": "venue"
  },
  "geometry": {"coordinates":[-81.956984,41.346318],"type":"Point"}
}
