{
  "type": "Feature",
  "properties": {
    "addr:full":"385 Randolph Rd Mogadore OH 44260",
    "addr:housenumber":"385",
    "addr:postcode":"44260",
    "addr:street":"Randolph Rd",
    "iso:country":"US",
    "sg:address":"385 Randolph Rd",
    "sg:city":"Mogadore",
    "sg:classifiers":[
        {
            "category":"Organizations",
            "subcategory":"Community Association",
            "type":"Services"
        }
    ],
    "sg:phone":"+1 330 628 9140",
    "sg:postcode":"44260",
    "sg:province":"OH",
    "sg:tags":[
        "military"
    ],
    "sg:website":"www.vfw.org",
    "wof:name":"Veterans Of Foreign Wars",
    "wof:placetype":"venue"
},
  "geometry": {"coordinates":[-81.37856499999999,41.050835],"type":"Point"}
}