{
  "type": "Feature",
  "properties": {
    "iso:country":"US",
    "sg:address":"766 Linden Ave",
    "sg:city":"Zanesville",
    "sg:classifiers":[
        {
            "category":"Professional",
            "subcategory":"Business Services",
            "type":"Services"
        },
        {
            "category":"Building & Trades",
            "subcategory":"Construction",
            "type":"Services"
        }
    ],
    "sg:phone":"+1 740 452 8588",
    "sg:postcode":"43701",
    "sg:province":"OH",
    "sg:tags":[
        "designer",
        "dealer",
        "pool",
        "swimming"
    ],
    "wof:name":"Dean's Pool & Spa Svc & Supply",
    "wof:placetype":"venue"
},
  "geometry": {"coordinates":[-82.009999,39.947567],"type":"Point"}
}