{
  "type": "Feature",
  "properties": {
    "addr:full":"2295 Morse Rd Columbus OH 43229",
    "addr:housenumber":"2295",
    "addr:postcode":"43229",
    "addr:street":"Morse Rd",
    "iso:country":"US",
    "sg:address":"2295 Morse Rd",
    "sg:city":"Columbus",
    "sg:classifiers":[
        {
            "category":"Food & Beverages",
            "subcategory":"Groceries & Convenience Stores",
            "type":"Retail Goods"
        }
    ],
    "sg:phone":"+1 614 478 7384",
    "sg:postcode":"43229",
    "sg:province":"OH",
    "sg:tags":[
        "grocer"
    ],
    "wof:name":"Zam Zam Grocery Inc",
    "wof:placetype":"venue"
},
  "geometry": {"coordinates":[-82.96112599999999,40.059914],"type":"Point"}
}