{
  "type": "Feature",
  "properties": {
    "addr:full":"2618 Massillon Rd Akron OH 44312",
    "addr:postcode":"2618;44312",
    "addr:street":"Massillon Rd",
    "iso:country":"US",
    "sg:address":"2618 Massillon Rd",
    "sg:city":"Akron",
    "sg:classifiers":[
        {
            "category":"Retail",
            "subcategory":"Animal Services",
            "type":"Services"
        }
    ],
    "sg:phone":"+1 330 645 1323",
    "sg:postcode":"44312",
    "sg:province":"OH",
    "wof:name":"Happy Pets Dog Grooming",
    "wof:placetype":"venue"
},
  "geometry": {"coordinates":[-81.46347799999999,40.990877],"type":"Point"}
}