{
  "type": "Feature",
  "properties": {
    "addr:full": "3195 E 65th St Cleveland OH 44127",
    "addr:housenumber": "3195",
    "addr:postcode": "44127",
    "addr:street": "E 65Th St",
    "iso:country": "US",
    "sg:address": "3195 E 65th St",
    "sg:city": "Cleveland",
    "sg:classifiers": [
      {
        "category": "Manufacturing",
        "subcategory": "Metals",
        "type": "Manufacturing \u0026 Wholesale Goods"
      }
    ],
    "sg:phone": "+1 216 883 4530",
    "sg:postcode": "44127",
    "sg:province": "OH",
    "sg:tags": [
      "polishing",
      "abrasive",
      "buffing",
      "finisher"
    ],
    "wof:name": "Portage Polishing \u0026 Buffing Co",
    "wof:placetype": "venue"
  },
  "geometry": {"coordinates":[-81.645063,41.473068],"type":"Point"}
}
