{
  "type": "Feature",
  "properties": {
    "iso:country":"US",
    "sg:address":"216 W Sugar St",
    "sg:city":"Cridersville",
    "sg:classifiers":[
        {
            "category":"Personal",
            "subcategory":"Tanning Parlor",
            "type":"Services"
        }
    ],
    "sg:phone":"+1 419 649 5331",
    "sg:postcode":"45806",
    "sg:province":"OH",
    "sg:tags":[
        "salon"
    ],
    "wof:name":"Bangs The Hair Place",
    "wof:placetype":"venue"
},
  "geometry": {"coordinates":[-84.14667,40.655279],"type":"Point"}
}