{
  "type": "Feature",
  "properties": {
    "iso:country":"US",
    "sg:address":"220 Walnut",
    "sg:city":"Marysville",
    "sg:classifiers":[
        {
            "category":"Education",
            "subcategory":"School",
            "type":"Public Place"
        }
    ],
    "sg:phone":"+1 937 642 1726",
    "sg:postcode":"43040",
    "sg:province":"OH",
    "sg:tags":[
        "religious"
    ],
    "sg:website":"www.trinitymarysville.org",
    "wof:name":"Trinity Lutheran School",
    "wof:placetype":"venue"
},
  "geometry": {"coordinates":[-83.364501,40.234924],"type":"Point"}
}