{
  "type": "Feature",
  "properties": {
    "addr:full":"1629 Schrock Rd Columbus OH 43229",
    "addr:housenumber":"1629",
    "addr:postcode":"43229",
    "addr:street":"Schrock Rd",
    "iso:country":"US",
    "sg:address":"1629 Schrock Rd",
    "sg:city":"Columbus",
    "sg:classifiers":[
        {
            "category":"Restaurant",
            "type":"Food & Drink"
        }
    ],
    "sg:menulink":"http://www.allmenus.com/oh/columbus/134209-subway/menu/",
    "sg:phone":"+1 614 818 9762",
    "sg:postcode":"43229",
    "sg:province":"OH",
    "sg:tags":[
        "american",
        "sandwich"
    ],
    "wof:name":"Subway",
    "wof:placetype":"venue"
},
  "geometry": {"coordinates":[-82.973032,40.105314],"type":"Point"}
}