{
  "type": "Feature",
  "properties": {
    "iso:country":"US",
    "sg:address":"165 Wayne Park Dr",
    "sg:city":"Napoleon",
    "sg:classifiers":[
        {
            "category":"Manufacturing",
            "subcategory":"Tools & Machinery",
            "type":"Manufacturing & Wholesale Goods"
        }
    ],
    "sg:phone":"+1 419 592 0329",
    "sg:postcode":"43545",
    "sg:province":"OH",
    "sg:tags":[
        "equipment",
        "material",
        "handling",
        "mfg"
    ],
    "wof:name":"Skates & Company",
    "wof:placetype":"venue"
},
  "geometry": {"coordinates":[-84.153268,41.367163],"type":"Point"}
}