{
  "type": "Feature",
  "properties": {
    "addr:full": "165 Wayne Park Dr Napoleon OH 43545",
    "addr:housenumber": "165",
    "addr:postcode": "43545",
    "addr:street": "Wayne Park Dr",
    "iso:country": "US",
    "sg:address": "165 Wayne Park Dr",
    "sg:city": "Napoleon",
    "sg:classifiers": [
      {
        "category": "Manufacturing",
        "subcategory": "Tools \u0026 Machinery",
        "type": "Manufacturing \u0026 Wholesale Goods"
      }
    ],
    "sg:phone": "+1 419 592 0329",
    "sg:postcode": "43545",
    "sg:province": "OH",
    "sg:tags": [
      "equipment",
      "material",
      "handling",
      "mfg"
    ],
    "wof:name": "Skates \u0026 Company",
    "wof:placetype": "venue"
  },
  "geometry": {"coordinates":[-84.153268,41.367163],"type":"Point"}
}
