{
  "type": "Feature",
  "properties": {
    "addr:full": "125 William Howard Taft Rd Cincinnati OH 45219",
    "addr:housenumber": "125",
    "addr:postcode": "45219",
    "addr:street": "William Howard Taft Rd",
    "iso:country": "US",
    "sg:address": "125 William Howard Taft Rd",
    "sg:city": "Cincinnati",
    "sg:classifiers": [
      {
        "category": "Wholesale",
        "subcategory": "Painting Supplies",
        "type": "Manufacturing \u0026 Wholesale Goods"
      },
      {
        "category": "Shopping",
        "subcategory": "Crafts \u0026 Fabrics",
        "type": "Retail Goods"
      }
    ],
    "sg:phone": "+1 513 861 0189",
    "sg:postcode": "45219",
    "sg:province": "OH",
    "sg:tags": [
      "goods-wholesale",
      "art",
      "manufacturer"
    ],
    "wof:name": "Young Enterprises, Inc",
    "wof:placetype": "venue"
  },
  "geometry": {"coordinates":[-84.508065,39.127987],"type":"Point"}
}
