{
  "type": "Feature",
  "properties": {
    "iso:country":"US",
    "sg:address":"524 Uhl St",
    "sg:city":"Millersburg",
    "sg:classifiers":[
        {
            "category":"Organizations",
            "subcategory":"Religious Organization",
            "type":"Services"
        }
    ],
    "sg:phone":"+1 330 674 0515",
    "sg:postcode":"44654",
    "sg:province":"OH",
    "sg:tags":[
        "church"
    ],
    "wof:name":"Trinity Christian Fellowship",
    "wof:placetype":"venue"
},
  "geometry": {"coordinates":[-81.917154,40.557813],"type":"Point"}
}