{
  "type": "Feature",
  "properties": {
    "addr:full": "1435 Baronial Plaza Dr Toledo OH 43615",
    "addr:housenumber": "1435",
    "addr:postcode": "43615",
    "addr:street": "Baronial Plaza Dr",
    "iso:country": "US",
    "sg:address": "1435 Baronial Plaza Dr",
    "sg:city": "Toledo",
    "sg:classifiers": [
      {
        "category": "Restaurant",
        "type": "Food \u0026 Drink"
      }
    ],
    "sg:phone": "+1 419 866 8877",
    "sg:postcode": "43615",
    "sg:province": "OH",
    "sg:tags": [
      "eating"
    ],
    "sg:website": "www.joescrabshack.com",
    "wof:name": "Joe's Crab Shack",
    "wof:placetype": "venue"
  },
  "geometry": {"coordinates":[-83.674223,41.615424],"type":"Point"}
}
