{
  "type": "Feature",
  "properties": {
    "addr:full": "122 Lownsdale Ave Akron OH 44313",
    "addr:housenumber": "122",
    "addr:postcode": "44313",
    "addr:street": "Lownsdale Ave",
    "iso:country": "US",
    "sg:address": "122 Lownsdale Ave",
    "sg:city": "Akron",
    "sg:classifiers": [
      {
        "category": "Manufacturing",
        "subcategory": "Chemicals \u0026 Compounds",
        "type": "Manufacturing \u0026 Wholesale Goods"
      }
    ],
    "sg:phone": "+1 330 836 2455",
    "sg:postcode": "44313",
    "sg:province": "OH",
    "sg:tags": [
      "rubber"
    ],
    "wof:name": "Shincor Silicones Inc",
    "wof:placetype": "venue"
  },
  "geometry": {"coordinates":[-81.587122,41.11419],"type":"Point"}
}
