{
  "type": "Feature",
  "properties": {
    "addr:full": "7817 Hills and Dales Rd NE Massillon OH 44646",
    "addr:housenumber": "7817",
    "addr:postcode": "44646",
    "addr:street": "Hills And Dales Rd Ne",
    "iso:country": "US",
    "sg:address": "7817 Hills and Dales Rd NE",
    "sg:city": "Massillon",
    "sg:classifiers": [
      {
        "category": "Shopping",
        "subcategory": "Gifts \u0026 Souvenirs",
        "type": "Retail Goods"
      }
    ],
    "sg:phone": "+1 330 832 2647",
    "sg:postcode": "44646",
    "sg:province": "OH",
    "wof:name": "Especially For You",
    "wof:placetype": "venue"
  },
  "geometry": {"coordinates":[-81.493813,40.824003],"type":"Point"}
}
