{
  "type": "Feature",
  "properties": {
    "iso:country":"US",
    "sg:address":"7817 Hills and Dales Rd NE",
    "sg:city":"Massillon",
    "sg:classifiers":[
        {
            "category":"Shopping",
            "subcategory":"Gifts & Souvenirs",
            "type":"Retail Goods"
        }
    ],
    "sg:phone":"+1 330 832 2647",
    "sg:postcode":"44646",
    "sg:province":"OH",
    "wof:name":"Especially For You",
    "wof:placetype":"venue"
},
  "geometry": {"coordinates":[-81.493813,40.824003],"type":"Point"}
}