{
  "type": "Feature",
  "properties": {
    "addr:full":"1919 Fauver Ave Dayton OH 45420",
    "addr:housenumber":"1919",
    "addr:postcode":"45420",
    "addr:street":"Fauver Ave",
    "iso:country":"US",
    "sg:address":"1919 Fauver Ave",
    "sg:city":"Dayton",
    "sg:classifiers":[
        {
            "category":"Banks & Credit Unions",
            "subcategory":"Financial Services",
            "type":"Services"
        }
    ],
    "sg:phone":"+1 937 256 1429",
    "sg:postcode":"45420",
    "sg:province":"OH",
    "sg:tags":[
        "trust",
        "management"
    ],
    "wof:name":"Gale E Harmeling Al Et",
    "wof:placetype":"venue"
},
  "geometry": {"coordinates":[-84.14149399999999,39.739924],"type":"Point"}
}