{
  "type": "Feature",
  "properties": {
    "iso:country":"US",
    "sg:address":"5822 Middlebranch Ave NE",
    "sg:city":"Canton",
    "sg:classifiers":[
        {
            "category":"Health Services",
            "subcategory":"Health Practitioner",
            "type":"Services"
        }
    ],
    "sg:phone":"+1 330 492 1193",
    "sg:postcode":"44721",
    "sg:province":"OH",
    "sg:tags":[
        "therapist",
        "physical"
    ],
    "wof:name":"Pr 2 Physical Therapy",
    "wof:placetype":"venue"
},
  "geometry": {"coordinates":[-81.335144,40.865938],"type":"Point"}
}