{
  "type": "Feature",
  "properties": {
    "addr:full": "12625 Western Rd Kidron OH 44606",
    "addr:housenumber": "12625",
    "addr:postcode": "44606",
    "addr:street": "Western Rd",
    "iso:country": "US",
    "sg:address": "12625 Western Rd",
    "sg:city": "Kidron",
    "sg:classifiers": [
      {
        "category": "Professional",
        "type": "Services"
      }
    ],
    "sg:phone": "+1 330 857 3781",
    "sg:postcode": "44606",
    "sg:province": "OH",
    "sg:tags": [
      "establishment"
    ],
    "wof:name": "Harrison Refrigertaion Inc",
    "wof:placetype": "venue"
  },
  "geometry": {"coordinates":[-81.751503,40.722807],"type":"Point"}
}
