{
  "type": "Feature",
  "properties": {
    "iso:country":"US",
    "sg:address":"200 1st St",
    "sg:city":"Findlay",
    "sg:classifiers":[
        {
            "category":"Shopping",
            "subcategory":"Gifts & Souvenirs",
            "type":"Retail Goods"
        }
    ],
    "sg:phone":"+1 419 424 0045",
    "sg:postcode":"45840",
    "sg:province":"OH",
    "sg:tags":[
        "shop"
    ],
    "wof:name":"Art Works",
    "wof:placetype":"venue"
},
  "geometry": {"coordinates":[-83.648966,41.029153],"type":"Point"}
}