{
  "type": "Feature",
  "properties": {
    "addr:full": "200 1st St Findlay OH 45840",
    "addr:housenumber": "200",
    "addr:postcode": "45840",
    "addr:street": "1St St",
    "iso:country": "US",
    "sg:address": "200 1st St",
    "sg:city": "Findlay",
    "sg:classifiers": [
      {
        "category": "Shopping",
        "subcategory": "Gifts \u0026 Souvenirs",
        "type": "Retail Goods"
      }
    ],
    "sg:phone": "+1 419 424 0045",
    "sg:postcode": "45840",
    "sg:province": "OH",
    "sg:tags": [
      "shop"
    ],
    "wof:name": "Art Works",
    "wof:placetype": "venue"
  },
  "geometry": {"coordinates":[-83.648966,41.029153],"type":"Point"}
}
