{
  "type": "Feature",
  "properties": {
    "addr:full":"11335 Stoneledge Dr Chardon OH 44024",
    "addr:housenumber":"11335",
    "addr:postcode":"44024",
    "addr:street":"Stoneledge Dr",
    "iso:country":"US",
    "sg:address":"11335 Stoneledge Dr",
    "sg:city":"Chardon",
    "sg:classifiers":[
        {
            "category":"Building & Trades",
            "subcategory":"Electrical",
            "type":"Services"
        }
    ],
    "sg:phone":"+1 440 286 4859",
    "sg:postcode":"44024",
    "sg:province":"OH",
    "sg:tags":[
        "electric",
        "contractor"
    ],
    "wof:name":"DDS Electric Inc",
    "wof:placetype":"venue"
},
  "geometry": {"coordinates":[-81.115831,41.56419],"type":"Point"}
}