{
  "type": "Feature",
  "properties": {
    "addr:full": "1739 Mahoning Ave Youngstown OH 44509",
    "addr:housenumber": "1739",
    "addr:postcode": "44509",
    "addr:street": "Mahoning Ave",
    "iso:country": "US",
    "sg:address": "1739 Mahoning Ave",
    "sg:city": "Youngstown",
    "sg:classifiers": [
      {
        "category": "Building \u0026 Trades",
        "subcategory": "Construction",
        "type": "Services"
      }
    ],
    "sg:phone": "+1 330 793 7787",
    "sg:postcode": "44509",
    "sg:province": "OH",
    "sg:tags": [
      "maker",
      "cabinet"
    ],
    "wof:name": "Michael's Cabinet Shop",
    "wof:placetype": "venue"
  },
  "geometry": {"coordinates":[-80.687395,41.102292],"type":"Point"}
}
