{
  "type": "Feature",
  "properties": {
    "iso:country":"US",
    "sg:address":"645 Georgetown Ave",
    "sg:city":"Elyria",
    "sg:classifiers":[
        {
            "category":"Government",
            "subcategory":"Office",
            "type":"Public Place"
        }
    ],
    "sg:phone":"+1 440 365 5250",
    "sg:postcode":"44035",
    "sg:province":"OH",
    "sg:tags":[
        "legislative",
        "body"
    ],
    "wof:name":"Senate  United States",
    "wof:placetype":"venue"
},
  "geometry": {"coordinates":[-82.07162700000001,41.393547],"type":"Point"}
}