{
  "type": "Feature",
  "properties": {
    "addr:full":"18500 Detroit Ave Cleveland OH 44107",
    "addr:housenumber":"18500",
    "addr:postcode":"44107",
    "addr:street":"Detroit Ave",
    "iso:country":"US",
    "sg:address":"18500 Detroit Ave",
    "sg:city":"Cleveland",
    "sg:classifiers":[
        {
            "category":"Restaurant",
            "type":"Food & Drink"
        }
    ],
    "sg:phone":"+1 216 521 1529",
    "sg:postcode":"44107",
    "sg:province":"OH",
    "sg:tags":[
        "drinking",
        "eating"
    ],
    "wof:name":"Riverwood Cafe",
    "wof:placetype":"venue"
},
  "geometry": {"coordinates":[-81.827398,41.48159],"type":"Point"}
}