{
  "type": "Feature",
  "properties": {
    "addr:full": "819 Yale St Akron OH 44311",
    "addr:housenumber": "819",
    "addr:postcode": "44311",
    "addr:street": "Yale St",
    "iso:country": "US",
    "sg:address": "819 Yale St",
    "sg:city": "Akron",
    "sg:classifiers": [
      {
        "category": "Professional",
        "type": "Services"
      }
    ],
    "sg:phone": "+1 330 374 7893",
    "sg:postcode": "44311",
    "sg:province": "OH",
    "wof:name": "Marsha Ann Morgan",
    "wof:placetype": "venue"
  },
  "geometry": {"coordinates":[-81.530262,41.06317],"type":"Point"}
}
