{
  "type": "Feature",
  "properties": {
    "addr:full":"818 Ohio Pike Cincinnati OH 45245",
    "addr:housenumber":"818",
    "addr:postcode":"45245",
    "addr:street":"Ohio Pike",
    "iso:country":"US",
    "sg:address":"818 Ohio Pike",
    "sg:city":"Cincinnati",
    "sg:classifiers":[
        {
            "category":"Manufacturing",
            "subcategory":"Metals",
            "type":"Manufacturing & Wholesale Goods"
        }
    ],
    "sg:phone":"+1 513 752 8119",
    "sg:postcode":"45245",
    "sg:province":"OH",
    "sg:tags":[
        "steel"
    ],
    "wof:name":"Able Steel Rule Die Co",
    "wof:placetype":"venue"
},
  "geometry": {"coordinates":[-84.281226,39.064821],"type":"Point"}
}