{
  "type": "Feature",
  "properties": {
    "addr:full": "6797 N High St Worthington OH 43085",
    "addr:housenumber": "6797",
    "addr:postcode": "43085",
    "addr:street": "N High St",
    "iso:country": "US",
    "sg:address": "6797 N High St",
    "sg:city": "Worthington",
    "sg:classifiers": [
      {
        "category": "Banks \u0026 Credit Unions",
        "subcategory": "Investment Brokerage",
        "type": "Services"
      }
    ],
    "sg:phone": "+1 614 430 8744",
    "sg:postcode": "43085",
    "sg:province": "OH",
    "sg:tags": [
      "advisory",
      "financial"
    ],
    "wof:name": "Financial Navigators",
    "wof:placetype": "venue"
  },
  "geometry": {"coordinates":[-83.017267,40.102781],"type":"Point"}
}
