{
  "type": "Feature",
  "properties": {
    "addr:full": "3030 Alexander Ave SW Canton OH 44706",
    "addr:housenumber": "3030",
    "addr:postcode": "44706",
    "addr:street": "Alexander Ave Sw",
    "iso:country": "US",
    "sg:address": "3030 Alexander Ave SW",
    "sg:city": "Canton",
    "sg:classifiers": [
      {
        "category": "Home \u0026 Garden",
        "subcategory": "Furniture",
        "type": "Retail Goods"
      }
    ],
    "sg:phone": "+1 330 833 2055",
    "sg:postcode": "44706",
    "sg:province": "OH",
    "wof:name": "B \u0026 B Diversified Products",
    "wof:placetype": "venue"
  },
  "geometry": {"coordinates":[-81.465508,40.76165],"type":"Point"}
}
