{
  "type": "Feature",
  "properties": {
    "addr:full": "7956 Market St Youngstown OH 44512",
    "addr:housenumber": "7956",
    "addr:postcode": "44512",
    "addr:street": "Market St",
    "iso:country": "US",
    "sg:address": "7956 Market St",
    "sg:city": "Youngstown",
    "sg:classifiers": [
      {
        "category": "Real Estate",
        "subcategory": "Real Estate Services",
        "type": "Services"
      },
      {
        "category": "Real Estate",
        "subcategory": "Real Estate Operator",
        "type": "Services"
      }
    ],
    "sg:phone": "+1 330 758 4449",
    "sg:postcode": "44512",
    "sg:province": "OH",
    "sg:tags": [
      "vacancy",
      "apartment",
      "rental",
      "listing"
    ],
    "sg:website": "http://www.simco-apts.com",
    "wof:name": "Cambridge Square Apts \u0026 Marquette Manor",
    "wof:placetype": "venue"
  },
  "geometry": {"coordinates":[-80.662723,41.006738],"type":"Point"}
}
