{
  "type": "Feature",
  "properties": {
    "addr:full": "10468 Northfield Rd Northfield OH 44067",
    "addr:housenumber": "10468",
    "addr:postcode": "44067",
    "addr:street": "Northfield Rd",
    "iso:country": "US",
    "sg:address": "10468 Northfield Rd",
    "sg:city": "Northfield",
    "sg:classifiers": [
      {
        "category": "Shopping",
        "subcategory": "Tobacco",
        "type": "Retail Goods"
      }
    ],
    "sg:phone": "+1 330 467 1480",
    "sg:postcode": "44067",
    "sg:province": "OH",
    "sg:tags": [
      "cigarette",
      "cigar",
      "dealer"
    ],
    "wof:name": "Lou's Discount Smoke Haven",
    "wof:placetype": "venue"
  },
  "geometry": {"coordinates":[-81.528689,41.343649],"type":"Point"}
}
