{
  "type": "Feature",
  "properties": {
    "iso:country":"US",
    "sg:address":"7489 Twin Acorn Ct",
    "sg:city":"Lewis Center",
    "sg:classifiers":[
        {
            "category":"Professional",
            "type":"Services"
        }
    ],
    "sg:phone":"+1 740 657 8025",
    "sg:postcode":"43035",
    "sg:province":"OH",
    "wof:name":"Lorie Fearing",
    "wof:placetype":"venue"
},
  "geometry": {"coordinates":[-82.982607,40.168491],"type":"Point"}
}