{
  "type": "Feature",
  "properties": {
    "addr:full": "3038 N Reynolds Rd Toledo OH 43615",
    "addr:housenumber": "3038",
    "addr:postcode": "43615",
    "addr:street": "N Reynolds Rd",
    "iso:country": "US",
    "sg:address": "3038 N Reynolds Rd",
    "sg:city": "Toledo",
    "sg:classifiers": [
      {
        "category": "Wholesale",
        "subcategory": "Machinery \u0026 Supplies",
        "type": "Manufacturing \u0026 Wholesale Goods"
      }
    ],
    "sg:phone": "+1 419 531 7101",
    "sg:postcode": "43615",
    "sg:province": "OH",
    "sg:tags": [
      "equipment",
      "industrial"
    ],
    "wof:name": "Columbus Equipment Company",
    "wof:placetype": "venue"
  },
  "geometry": {"coordinates":[-83.673389,41.676448],"type":"Point"}
}
