{
  "type": "Feature",
  "properties": {
    "iso:country":"US",
    "sg:address":"3038 N Reynolds Rd",
    "sg:city":"Toledo",
    "sg:classifiers":[
        {
            "category":"Wholesale",
            "subcategory":"Machinery & Supplies",
            "type":"Manufacturing & Wholesale Goods"
        }
    ],
    "sg:phone":"+1 419 531 7101",
    "sg:postcode":"43615",
    "sg:province":"OH",
    "sg:tags":[
        "equipment",
        "industrial"
    ],
    "wof:name":"Columbus Equipment Company",
    "wof:placetype":"venue"
},
  "geometry": {"coordinates":[-83.673389,41.676448],"type":"Point"}
}