{
  "type": "Feature",
  "properties": {
    "iso:country":"US",
    "sg:address":"2215 Nottingham St NW",
    "sg:city":"Massillon",
    "sg:classifiers":[
        {
            "category":"Wholesale",
            "subcategory":"Auto Parts",
            "type":"Manufacturing & Wholesale Goods"
        }
    ],
    "sg:phone":"+1 330 353 0729",
    "sg:postcode":"44646",
    "sg:province":"OH",
    "wof:name":"Wheel Booker The",
    "wof:placetype":"venue"
},
  "geometry": {"coordinates":[-81.490619,40.819829],"type":"Point"}
}