{
  "type": "Feature",
  "properties": {
    "addr:full": "2215 Nottingham St NW Massillon OH 44646",
    "addr:housenumber": "2215",
    "addr:postcode": "44646",
    "addr:street": "Nottingham St Nw",
    "iso:country": "US",
    "sg:address": "2215 Nottingham St NW",
    "sg:city": "Massillon",
    "sg:classifiers": [
      {
        "category": "Wholesale",
        "subcategory": "Auto Parts",
        "type": "Manufacturing \u0026 Wholesale Goods"
      }
    ],
    "sg:phone": "+1 330 353 0729",
    "sg:postcode": "44646",
    "sg:province": "OH",
    "wof:name": "Wheel Booker The",
    "wof:placetype": "venue"
  },
  "geometry": {"coordinates":[-81.490619,40.819829],"type":"Point"}
}
