{
  "type": "Feature",
  "properties": {
    "iso:country":"US",
    "sg:address":"689 Lyons Rd",
    "sg:city":"Dayton",
    "sg:classifiers":[
        {
            "category":"Personal",
            "subcategory":"Beauty Salon",
            "type":"Services"
        }
    ],
    "sg:phone":"+1 937 433 2833",
    "sg:postcode":"45459",
    "sg:province":"OH",
    "wof:name":"Tina's Creations",
    "wof:placetype":"venue"
},
  "geometry": {"coordinates":[-84.188956,39.630781],"type":"Point"}
}