{
  "type": "Feature",
  "properties": {
    "addr:full": "112 E Mansfield St Bucyrus OH 44820",
    "addr:housenumber": "112",
    "addr:postcode": "44820",
    "addr:street": "E Mansfield St",
    "iso:country": "US",
    "sg:address": "112 E Mansfield St",
    "sg:city": "Bucyrus",
    "sg:classifiers": [
      {
        "category": "Government",
        "subcategory": "Office",
        "type": "Public Place"
      }
    ],
    "sg:phone": "+1 419 562 5876",
    "sg:postcode": "44820",
    "sg:province": "OH",
    "sg:tags": [
      "executive"
    ],
    "wof:name": "Board of Comissioners Office",
    "wof:placetype": "venue"
  },
  "geometry": {"coordinates":[-82.974819,40.808746],"type":"Point"}
}
