{
  "type": "Feature",
  "properties": {
    "addr:full": "999 Rosetree Ln Cincinnati OH 45230",
    "addr:housenumber": "999",
    "addr:postcode": "45230",
    "addr:street": "Rosetree Ln",
    "iso:country": "US",
    "sg:address": "999 Rosetree Ln",
    "sg:city": "Cincinnati",
    "sg:classifiers": [
      {
        "category": "Building \u0026 Trades",
        "subcategory": "Plumbing",
        "type": "Services"
      }
    ],
    "sg:phone": "+1 513 232 0975",
    "sg:postcode": "45230",
    "sg:province": "OH",
    "sg:tags": [
      "contractor"
    ],
    "wof:name": "Buchanan Heating \u0026 Cooling",
    "wof:placetype": "venue"
  },
  "geometry": {"coordinates":[-84.366556,39.067974],"type":"Point"}
}
