{
  "type": "Feature",
  "properties": {
    "addr:full": "4922 Stickney Ave Toledo OH 43612",
    "addr:housenumber": "4922",
    "addr:postcode": "43612",
    "addr:street": "Stickney Ave",
    "iso:country": "US",
    "sg:address": "4922 Stickney Ave",
    "sg:city": "Toledo",
    "sg:classifiers": [
      {
        "category": "Manufacturing",
        "subcategory": "Tools \u0026 Machinery",
        "type": "Manufacturing \u0026 Wholesale Goods"
      }
    ],
    "sg:phone": "+1 419 726 2611",
    "sg:postcode": "43612",
    "sg:province": "OH",
    "sg:tags": [
      "die",
      "maker"
    ],
    "wof:name": "Right Tool \u0026 Die Inc",
    "wof:placetype": "venue"
  },
  "geometry": {"coordinates":[-83.527483,41.705922],"type":"Point"}
}
