{
  "type": "Feature",
  "properties": {
    "iso:country":"US",
    "sg:address":"4922 Stickney Ave",
    "sg:city":"Toledo",
    "sg:classifiers":[
        {
            "category":"Manufacturing",
            "subcategory":"Tools & Machinery",
            "type":"Manufacturing & Wholesale Goods"
        }
    ],
    "sg:phone":"+1 419 726 2611",
    "sg:postcode":"43612",
    "sg:province":"OH",
    "sg:tags":[
        "die",
        "maker"
    ],
    "wof:name":"Right Tool & Die Inc",
    "wof:placetype":"venue"
},
  "geometry": {"coordinates":[-83.527483,41.705922],"type":"Point"}
}