{
  "type": "Feature",
  "properties": {
    "iso:country":"US",
    "sg:address":"3215 Superior Ave E",
    "sg:city":"Cleveland",
    "sg:classifiers":[
        {
            "category":"Manufacturing",
            "subcategory":"Tools & Machinery",
            "type":"Manufacturing & Wholesale Goods"
        }
    ],
    "sg:phone":"+1 216 687 0459",
    "sg:postcode":"44114",
    "sg:province":"OH",
    "sg:tags":[
        "machine",
        "shop",
        "job"
    ],
    "sg:website":"www.ksmachineinc.com",
    "wof:name":"K S Machine Inc",
    "wof:placetype":"venue"
},
  "geometry": {"coordinates":[-81.667967,41.511617],"type":"Point"}
}