{
  "type": "Feature",
  "properties": {
    "addr:full":"108 Franklin Ave Cambridge OH 43725",
    "addr:housenumber":"108",
    "addr:postcode":"43725",
    "addr:street":"Franklin Ave",
    "iso:country":"US",
    "sg:address":"108 Franklin Ave",
    "sg:city":"Cambridge",
    "sg:classifiers":[
        {
            "category":"Organizations",
            "subcategory":"Membership Organization",
            "type":"Services"
        }
    ],
    "sg:phone":"+1 740 439 1903",
    "sg:postcode":"43725",
    "sg:province":"OH",
    "sg:tags":[
        "society",
        "humane"
    ],
    "wof:name":"Humane Society Of Guernsey",
    "wof:placetype":"venue"
},
  "geometry": {"coordinates":[-81.59675,40.02182],"type":"Point"}
}