{
  "type": "Feature",
  "properties": {
    "addr:full":"37 N Main St Fort Loramie OH 45845",
    "addr:housenumber":"37",
    "addr:postcode":"45845",
    "addr:street":"N Main St",
    "iso:country":"US",
    "sg:address":"37 N Main St",
    "sg:city":"Fort Loramie",
    "sg:classifiers":[
        {
            "category":"Museum",
            "type":"Entertainment"
        }
    ],
    "sg:phone":"+1 937 295 3855",
    "sg:postcode":"45845",
    "sg:province":"OH",
    "wof:name":"Fort Loramie Historical Assoc",
    "wof:placetype":"venue"
},
  "geometry": {"coordinates":[-84.374381,40.351145],"type":"Point"}
}