{
  "type": "Feature",
  "properties": {
    "iso:country":"US",
    "sg:address":"5685 Lake Rd E",
    "sg:city":"Geneva",
    "sg:classifiers":[
        {
            "category":"Organizations",
            "subcategory":"Membership Organization",
            "type":"Services"
        }
    ],
    "sg:phone":"+1 440 466 7337",
    "sg:postcode":"44041",
    "sg:province":"OH",
    "sg:tags":[
        "historical"
    ],
    "wof:name":"Ashtabula County Historical",
    "wof:placetype":"venue"
},
  "geometry": {"coordinates":[-80.952489,41.860364],"type":"Point"}
}