{
  "type": "Feature",
  "properties": {
    "iso:country":"US",
    "sg:address":"483 E 108th St",
    "sg:city":"Cleveland",
    "sg:classifiers":[
        {
            "category":"Shopping",
            "subcategory":"Clothing, Apparel, & Fashions",
            "type":"Retail Goods"
        }
    ],
    "sg:phone":"+1 216 249 4309",
    "sg:postcode":"44108",
    "sg:province":"OH",
    "wof:name":"Nell's Closet",
    "wof:placetype":"venue"
},
  "geometry": {"coordinates":[-81.61086,41.543516],"type":"Point"}
}