{
  "type": "Feature",
  "properties": {
    "iso:country":"US",
    "sg:address":"7560 Mc Ewen Rd",
    "sg:city":"Dayton",
    "sg:classifiers":[
        {
            "category":"Shopping",
            "type":"Retail Goods"
        }
    ],
    "sg:phone":"+1 937 438 0388",
    "sg:postcode":"45459",
    "sg:province":"OH",
    "sg:tags":[
        "equipment",
        "care",
        "health",
        "home"
    ],
    "sg:website":"www.ahom.com",
    "wof:name":"American Home Patient Inc",
    "wof:placetype":"venue"
},
  "geometry": {"coordinates":[-84.187856,39.631969],"type":"Point"}
}