{
  "type": "Feature",
  "properties": {
    "addr:full":"4 W Main St Troy OH 45373",
    "addr:housenumber":"4",
    "addr:postcode":"45373",
    "addr:street":"W Main St",
    "iso:country":"US",
    "sg:address":"4 W Main St",
    "sg:city":"Troy",
    "sg:classifiers":[
        {
            "category":"Shopping",
            "subcategory":"Stationery & Office Supplies",
            "type":"Retail Goods"
        }
    ],
    "sg:phone":"+1 937 335 2117",
    "sg:postcode":"45373",
    "sg:province":"OH",
    "wof:name":"Brower Stationers",
    "wof:placetype":"venue"
},
  "geometry": {"coordinates":[-84.203676,40.039693],"type":"Point"}
}