{
  "type": "Feature",
  "properties": {
    "addr:full": "801 3rd St Brilliant OH 43913",
    "addr:housenumber": "801",
    "addr:postcode": "43913",
    "addr:street": "3Rd St",
    "iso:country": "US",
    "sg:address": "801 3rd St",
    "sg:city": "Brilliant",
    "sg:classifiers": [
      {
        "category": "Government",
        "subcategory": "Post Office",
        "type": "Public Place"
      }
    ],
    "sg:phone": "+1 740 598 4906",
    "sg:postcode": "43913",
    "sg:province": "OH",
    "sg:tags": [
      "postal",
      "us"
    ],
    "wof:name": "US Post Office",
    "wof:placetype": "venue"
  },
  "geometry": {"coordinates":[-80.630547,40.264015],"type":"Point"}
}
