{
  "type": "Feature",
  "properties": {
    "iso:country":"US",
    "sg:address":"222 Ravenshollow Dr",
    "sg:city":"Cuyahoga Falls",
    "sg:classifiers":[
        {
            "category":"Communications",
            "type":"Services"
        }
    ],
    "sg:phone":"+1 330 945 6561",
    "sg:postcode":"44223",
    "sg:province":"OH",
    "sg:tags":[
        "communication"
    ],
    "wof:name":"Renner Communications",
    "wof:placetype":"venue"
},
  "geometry": {"coordinates":[-81.516518,41.170914],"type":"Point"}
}