{
  "type": "Feature",
  "properties": {
    "addr:full":"7655 Mentor Ave Mentor OH 44060",
    "addr:housenumber":"7655",
    "addr:postcode":"44060",
    "addr:street":"Mentor Ave",
    "iso:country":"US",
    "sg:address":"7655 Mentor Ave",
    "sg:city":"Mentor",
    "sg:classifiers":[
        {
            "category":"Personal",
            "type":"Services"
        }
    ],
    "sg:phone":"+1 440 283 0255",
    "sg:postcode":"44060",
    "sg:province":"OH",
    "sg:tags":[
        "therapist",
        "massage"
    ],
    "wof:name":"Dominic's Massotherapy",
    "wof:placetype":"venue"
},
  "geometry": {"coordinates":[-81.366592,41.659236],"type":"Point"}
}