{
  "type": "Feature",
  "properties": {
    "addr:full": "198 W Main St Shelby OH 44875",
    "addr:housenumber": "198",
    "addr:postcode": "44875",
    "addr:street": "W Main St",
    "iso:country": "US",
    "sg:address": "198 W Main St",
    "sg:city": "Shelby",
    "sg:classifiers": [
      {
        "category": "Building \u0026 Trades",
        "subcategory": "Construction",
        "type": "Services"
      }
    ],
    "sg:phone": "+1 419 347 8760",
    "sg:postcode": "44875",
    "sg:province": "OH",
    "sg:tags": [
      "house"
    ],
    "wof:name": "Calver Construction",
    "wof:placetype": "venue"
  },
  "geometry": {"coordinates":[-82.673379,40.88124],"type":"Point"}
}
