{
  "type": "Feature",
  "properties": {
    "addr:full": "835 Riegel Ridge Rd Jackson OH 45640",
    "addr:housenumber": "835",
    "addr:postcode": "45640",
    "addr:street": "Riegel Ridge Rd",
    "iso:country": "US",
    "sg:address": "835 Riegel Ridge Rd",
    "sg:city": "Jackson",
    "sg:classifiers": [
      {
        "category": "Government",
        "subcategory": "Fire Station",
        "type": "Public Place"
      }
    ],
    "sg:phone": "+1 740 820 3195",
    "sg:postcode": "45640",
    "sg:province": "OH",
    "sg:tags": [
      "protection"
    ],
    "wof:name": "Hamilton Twnsp Vol Fire/Rescue",
    "wof:placetype": "venue"
  },
  "geometry": {"coordinates":[-82.750585,38.936227],"type":"Point"}
}
