{
  "type": "Feature",
  "properties": {
    "iso:country":"US",
    "sg:address":"3960 E 93rd St",
    "sg:city":"Cleveland",
    "sg:classifiers":[
        {
            "category":"Manufacturing",
            "subcategory":"Chemicals & Compounds",
            "type":"Manufacturing & Wholesale Goods"
        }
    ],
    "sg:phone":"+1 216 341 0500",
    "sg:postcode":"44105",
    "sg:province":"OH",
    "sg:tags":[
        "industrial",
        "organic",
        "mfg"
    ],
    "sg:website":"www.klenztone.com",
    "wof:name":"K & E Chemical Co Inc",
    "wof:placetype":"venue"
},
  "geometry": {"coordinates":[-81.621347,41.450348],"type":"Point"}
}