{
  "type": "Feature",
  "properties": {
    "addr:full": "3960 E 93rd St Cleveland OH 44105",
    "addr:housenumber": "3960",
    "addr:postcode": "44105",
    "addr:street": "E 93Rd St",
    "iso:country": "US",
    "sg:address": "3960 E 93rd St",
    "sg:city": "Cleveland",
    "sg:classifiers": [
      {
        "category": "Manufacturing",
        "subcategory": "Chemicals \u0026 Compounds",
        "type": "Manufacturing \u0026 Wholesale Goods"
      }
    ],
    "sg:phone": "+1 216 341 0500",
    "sg:postcode": "44105",
    "sg:province": "OH",
    "sg:tags": [
      "industrial",
      "organic",
      "mfg"
    ],
    "sg:website": "www.klenztone.com",
    "wof:name": "K \u0026 E Chemical Co Inc",
    "wof:placetype": "venue"
  },
  "geometry": {"coordinates":[-81.621347,41.450348],"type":"Point"}
}
