{
  "type": "Feature",
  "properties": {
    "addr:full":"1951 S Gettysburg Ave Dayton OH 45418",
    "addr:housenumber":"1951",
    "addr:postcode":"45418",
    "addr:street":"S Gettysburg Ave",
    "iso:country":"US",
    "sg:address":"1951 S Gettysburg Ave",
    "sg:city":"Dayton",
    "sg:classifiers":[
        {
            "category":"Government",
            "subcategory":"Office",
            "type":"Public Place"
        }
    ],
    "sg:phone":"+1 937 496 7300",
    "sg:postcode":"45418",
    "sg:province":"OH",
    "sg:tags":[
        "executive"
    ],
    "wof:name":"Monday Cmnty Correctional Inst",
    "wof:placetype":"venue"
},
  "geometry": {"coordinates":[-84.252622,39.728958],"type":"Point"}
}