{
  "type": "Feature",
  "properties": {
    "addr:full": "164 Trl End Oregon OH 43616",
    "addr:postcode": "43616",
    "addr:street": "164 Trl End",
    "iso:country": "US",
    "sg:address": "164 Trl End",
    "sg:city": "Oregon",
    "sg:classifiers": [
      {
        "category": "Organizations",
        "subcategory": "Professional Association",
        "type": "Services"
      }
    ],
    "sg:phone": "+1 419 693 9139",
    "sg:postcode": "43616",
    "sg:province": "OH",
    "sg:tags": [
      "sales"
    ],
    "wof:name": "Cynor Home Buyers LTD",
    "wof:placetype": "venue"
  },
  "geometry": {"coordinates":[-83.480929,41.646152],"type":"Point"}
}
