{
  "type": "Feature",
  "properties": {
    "addr:full": "132 S Main St Sardinia OH 45171",
    "addr:housenumber": "132",
    "addr:postcode": "45171",
    "addr:street": "S Main St",
    "iso:country": "US",
    "sg:address": "132 S Main St",
    "sg:city": "Sardinia",
    "sg:classifiers": [
      {
        "category": "Shopping",
        "subcategory": "Bicycles \u0026 Sporting Goods",
        "type": "Retail Goods"
      }
    ],
    "sg:phone": "+1 937 446 3476",
    "sg:postcode": "45171",
    "sg:province": "OH",
    "wof:name": "Kevin's Bike Sales \u0026 Svc",
    "wof:placetype": "venue"
  },
  "geometry": {"coordinates":[-83.808995,39.006517],"type":"Point"}
}
