{
  "type": "Feature",
  "properties": {
    "iso:country":"US",
    "sg:address":"132 S Main St",
    "sg:city":"Sardinia",
    "sg:classifiers":[
        {
            "category":"Shopping",
            "subcategory":"Bicycles & Sporting Goods",
            "type":"Retail Goods"
        }
    ],
    "sg:phone":"+1 937 446 3476",
    "sg:postcode":"45171",
    "sg:province":"OH",
    "wof:name":"Kevin's Bike Sales & Svc",
    "wof:placetype":"venue"
},
  "geometry": {"coordinates":[-83.808995,39.006517],"type":"Point"}
}