{
  "type": "Feature",
  "properties": {
    "addr:full": "2575 Elida Rd Lima OH 45805",
    "addr:housenumber": "2575",
    "addr:postcode": "45805",
    "addr:street": "Elida Rd",
    "iso:country": "US",
    "sg:address": "2575 Elida Rd",
    "sg:city": "Lima",
    "sg:classifiers": [
      {
        "category": "Restaurant",
        "type": "Food \u0026 Drink"
      }
    ],
    "sg:menulink": "http://www.allmenus.com/oh/american/100872-captain-ds-seafood/menu/",
    "sg:phone": "+1 419 331 8888",
    "sg:postcode": "45805",
    "sg:province": "OH",
    "sg:tags": [
      "seafood",
      "american"
    ],
    "wof:name": "Captain D's Seafood",
    "wof:placetype": "venue"
  },
  "geometry": {"coordinates":[-84.152464,40.764312],"type":"Point"}
}
