{
  "type": "Feature",
  "properties": {
    "iso:country":"US",
    "sg:address":"2575 Elida Rd",
    "sg:city":"Lima",
    "sg:classifiers":[
        {
            "category":"Restaurant",
            "type":"Food & Drink"
        }
    ],
    "sg:menulink":"http://www.allmenus.com/oh/american/100872-captain-ds-seafood/menu/",
    "sg:phone":"+1 419 331 8888",
    "sg:postcode":"45805",
    "sg:province":"OH",
    "sg:tags":[
        "seafood",
        "american"
    ],
    "wof:name":"Captain D's Seafood",
    "wof:placetype":"venue"
},
  "geometry": {"coordinates":[-84.15246399999999,40.764312],"type":"Point"}
}