{
  "type": "Feature",
  "properties": {
    "addr:full":"3458 Reading Rd Cincinnati OH 45229",
    "addr:housenumber":"3458",
    "addr:postcode":"45229",
    "addr:street":"Reading Rd",
    "iso:country":"US",
    "sg:address":"3458 Reading Rd",
    "sg:city":"Cincinnati",
    "sg:classifiers":[
        {
            "category":"Social Services",
            "type":"Services"
        }
    ],
    "sg:phone":"+1 513 281 9955",
    "sg:postcode":"45229",
    "sg:province":"OH",
    "sg:tags":[
        "organization",
        "welfare"
    ],
    "sg:website":"www.gcul.org",
    "wof:name":"Urban League Of Cincinnati",
    "wof:placetype":"venue"
},
  "geometry": {"coordinates":[-84.49162200000001,39.14306],"type":"Point"}
}