{
  "type": "Feature",
  "properties": {
    "addr:full":"133 Dewolf St Wellington OH 44090",
    "addr:housenumber":"133",
    "addr:postcode":"44090",
    "addr:street":"Dewolf St",
    "iso:country":"US",
    "sg:address":"133 Dewolf St",
    "sg:city":"Wellington",
    "sg:classifiers":[
        {
            "category":"Freight",
            "type":"Transportation"
        }
    ],
    "sg:phone":"+1 440 647 0171",
    "sg:postcode":"44090",
    "sg:province":"OH",
    "wof:name":"Will Do Packaging LLC",
    "wof:placetype":"venue"
},
  "geometry": {"coordinates":[-82.214882,41.170589],"type":"Point"}
}