{
  "type": "Feature",
  "properties": {
    "iso:country":"US",
    "sg:address":"128 Alexandersville Rd",
    "sg:city":"Miamisburg",
    "sg:classifiers":[
        {
            "category":"Retail",
            "subcategory":"Auto Repair",
            "type":"Services"
        }
    ],
    "sg:phone":"+1 937 866 7032",
    "sg:postcode":"45342",
    "sg:province":"OH",
    "sg:tags":[
        "transmission"
    ],
    "sg:website":"www.aamco.com",
    "wof:name":"AAMCO Transmissions",
    "wof:placetype":"venue"
},
  "geometry": {"coordinates":[-84.243701,39.638757],"type":"Point"}
}