{
  "type": "Feature",
  "properties": {
    "addr:full":"9249 Oxford Trl Brecksville OH 44141",
    "addr:housenumber":"9249",
    "addr:postcode":"44141",
    "addr:street":"Oxford Trl",
    "iso:country":"US",
    "sg:address":"9249 Oxford Trl",
    "sg:city":"Brecksville",
    "sg:classifiers":[
        {
            "category":"Insurance",
            "subcategory":"Insurance Agent",
            "type":"Services"
        }
    ],
    "sg:phone":"+1 440 526 5390",
    "sg:postcode":"44141",
    "sg:province":"OH",
    "wof:name":"FCD Financial",
    "wof:placetype":"venue"
},
  "geometry": {"coordinates":[-81.66794299999999,41.313884],"type":"Point"}
}