{
  "type": "Feature",
  "properties": {
    "iso:country":"US",
    "sg:address":"313 Medina Rd",
    "sg:city":"Medina",
    "sg:classifiers":[
        {
            "category":"Recreation",
            "type":"Entertainment"
        }
    ],
    "sg:phone":"+1 330 239 0616",
    "sg:postcode":"44256",
    "sg:province":"OH",
    "wof:name":"Pinnacle Soccer Inc",
    "wof:placetype":"venue"
},
  "geometry": {"coordinates":[-81.698047,41.136073],"type":"Point"}
}