{
  "type": "Feature",
  "properties": {
    "iso:country":"US",
    "sg:address":"7207 Vine St",
    "sg:city":"Cincinnati",
    "sg:classifiers":[
        {
            "category":"Building & Trades",
            "subcategory":"Electrical",
            "type":"Services"
        }
    ],
    "sg:phone":"+1 513 761 4097",
    "sg:postcode":"45216",
    "sg:province":"OH",
    "sg:tags":[
        "electric",
        "contractor"
    ],
    "wof:name":"Stacy Electric-Heating & AC",
    "wof:placetype":"venue"
},
  "geometry": {"coordinates":[-84.478657,39.195814],"type":"Point"}
}