{
  "type": "Feature",
  "properties": {
    "addr:full": "2843 Timber Creek Dr N Cortland OH 44410",
    "addr:housenumber": "2843",
    "addr:postcode": "44410",
    "addr:street": "Timber Creek Dr N",
    "iso:country": "US",
    "sg:address": "2843 Timber Creek Dr N",
    "sg:city": "Cortland",
    "sg:classifiers": [
      {
        "category": "Wholesale",
        "subcategory": "Non-durable Goods",
        "type": "Manufacturing \u0026 Wholesale Goods"
      }
    ],
    "sg:phone": "+1 330 637 5701",
    "sg:postcode": "44410",
    "sg:province": "OH",
    "wof:name": "Louis Kaszonyi Inc",
    "wof:placetype": "venue"
  },
  "geometry": {"coordinates":[-80.749674,41.294157],"type":"Point"}
}
