{
  "type": "Feature",
  "properties": {
    "addr:full": "2135 Vermilion Rd Vermilion OH 44089",
    "addr:housenumber": "2135",
    "addr:postcode": "44089",
    "addr:street": "Vermilion Rd",
    "iso:country": "US",
    "sg:address": "2135 Vermilion Rd",
    "sg:city": "Vermilion",
    "sg:classifiers": [
      {
        "category": "Building \u0026 Trades",
        "subcategory": "Construction",
        "type": "Services"
      }
    ],
    "sg:phone": "+1 440 967 6822",
    "sg:postcode": "44089",
    "sg:province": "OH",
    "sg:tags": [
      "excavation",
      "contractor"
    ],
    "wof:name": "Bartlett Leasing",
    "wof:placetype": "venue"
  },
  "geometry": {"coordinates":[-82.322878,41.391677],"type":"Point"}
}
