{
  "type": "Feature",
  "properties": {
    "addr:full": "5002 Seaman St Oregon OH 43616",
    "addr:housenumber": "5002",
    "addr:postcode": "43616",
    "addr:street": "Seaman St",
    "iso:country": "US",
    "sg:address": "5002 Seaman St",
    "sg:city": "Oregon",
    "sg:classifiers": [
      {
        "category": "Government",
        "subcategory": "Fire Station",
        "type": "Public Place"
      }
    ],
    "sg:phone": "+1 419 698 7021",
    "sg:postcode": "43616",
    "sg:province": "OH",
    "sg:tags": [
      "department"
    ],
    "wof:name": "Oregon Fire Department",
    "wof:placetype": "venue"
  },
  "geometry": {"coordinates":[-83.426101,41.652305],"type":"Point"}
}
