{
  "type": "Feature",
  "properties": {
    "addr:full": "525 Chestnut Ave Sidney OH 45365",
    "addr:housenumber": "525",
    "addr:postcode": "45365",
    "addr:street": "Chestnut Ave",
    "iso:country": "US",
    "sg:address": "525 Chestnut Ave",
    "sg:city": "Sidney",
    "sg:classifiers": [
      {
        "category": "Building \u0026 Trades",
        "subcategory": "Construction",
        "type": "Services"
      }
    ],
    "sg:phone": "+1 937 492 0322",
    "sg:postcode": "45365",
    "sg:province": "OH",
    "sg:tags": [
      "house"
    ],
    "wof:name": "Heckman Construction",
    "wof:placetype": "venue"
  },
  "geometry": {"coordinates":[-84.161463,40.279654],"type":"Point"}
}
