{
  "type": "Feature",
  "properties": {
    "addr:full": "4528 Aicholtz Rd Cincinnati OH 45245",
    "addr:housenumber": "4528",
    "addr:postcode": "45245",
    "addr:street": "Aicholtz Rd",
    "iso:country": "US",
    "sg:address": "4528 Aicholtz Rd",
    "sg:city": "Cincinnati",
    "sg:classifiers": [
      {
        "category": "Home \u0026 Garden",
        "subcategory": "Carpets \u0026 Floor Coverings",
        "type": "Retail Goods"
      }
    ],
    "sg:phone": "+1 513 528 1650",
    "sg:postcode": "45245",
    "sg:province": "OH",
    "wof:name": "Martin Floors Inc",
    "wof:placetype": "venue"
  },
  "geometry": {"coordinates":[-84.286979,39.099797],"type":"Point"}
}
