{
  "type": "Feature",
  "properties": {
    "iso:country":"US",
    "sg:address":"4528 Aicholtz Rd",
    "sg:city":"Cincinnati",
    "sg:classifiers":[
        {
            "category":"Home & Garden",
            "subcategory":"Carpets & Floor Coverings",
            "type":"Retail Goods"
        }
    ],
    "sg:phone":"+1 513 528 1650",
    "sg:postcode":"45245",
    "sg:province":"OH",
    "wof:name":"Martin Floors Inc",
    "wof:placetype":"venue"
},
  "geometry": {"coordinates":[-84.286979,39.099797],"type":"Point"}
}