{
  "type": "Feature",
  "properties": {
    "addr:full": "7559 Gardenside Dr Dayton OH 45414",
    "addr:housenumber": "7559",
    "addr:postcode": "45414",
    "addr:street": "Gardenside Dr",
    "iso:country": "US",
    "sg:address": "7559 Gardenside Dr",
    "sg:city": "Dayton",
    "sg:classifiers": [
      {
        "category": "Building \u0026 Trades",
        "subcategory": "Landscaping Services",
        "type": "Services"
      }
    ],
    "sg:phone": "+1 937 264 1570",
    "sg:postcode": "45414",
    "sg:province": "OH",
    "wof:name": "Boesys Lawn \u0026 Landscaping LLC",
    "wof:placetype": "venue"
  },
  "geometry": {"coordinates":[-84.211604,39.854698],"type":"Point"}
}
