{
  "type": "Feature",
  "properties": {
    "addr:full":"1427 W North St Springfield OH 45504",
    "addr:housenumber":"1427",
    "addr:postcode":"45504",
    "addr:street":"W North St",
    "iso:country":"US",
    "sg:address":"1427 W North St",
    "sg:city":"Springfield",
    "sg:classifiers":[
        {
            "category":"Retail",
            "subcategory":"Auto Repair",
            "type":"Services"
        }
    ],
    "sg:phone":"+1 937 324 8541",
    "sg:postcode":"45504",
    "sg:province":"OH",
    "sg:tags":[
        "body",
        "automobile",
        "painting"
    ],
    "wof:name":"Hobbs Body Shop",
    "wof:placetype":"venue"
},
  "geometry": {"coordinates":[-83.833387,39.928442],"type":"Point"}
}