{
  "type": "Feature",
  "properties": {
    "addr:full":"4432 Hopkins Rd Youngstown OH 44511",
    "addr:housenumber":"4432",
    "addr:postcode":"44511",
    "addr:street":"Hopkins Rd",
    "iso:country":"US",
    "sg:address":"4432 Hopkins Rd",
    "sg:city":"Youngstown",
    "sg:classifiers":[
        {
            "category":"Wholesale",
            "subcategory":"Electrical",
            "type":"Manufacturing & Wholesale Goods"
        }
    ],
    "sg:phone":"+1 330 788 8722",
    "sg:postcode":"44511",
    "sg:province":"OH",
    "sg:tags":[
        "burglar",
        "alarm",
        "system",
        "install",
        "security",
        "retail"
    ],
    "wof:name":"Best Alarm Co Inc",
    "wof:placetype":"venue"
},
  "geometry": {"coordinates":[-80.69275,41.057834],"type":"Point"}
}