{
  "type": "Feature",
  "properties": {
    "addr:full": "412 Crestwood Ave Wadsworth OH 44281",
    "addr:housenumber": "412",
    "addr:postcode": "44281",
    "addr:street": "Crestwood Ave",
    "iso:country": "US",
    "sg:address": "412 Crestwood Ave",
    "sg:city": "Wadsworth",
    "sg:classifiers": [
      {
        "category": "Organizations",
        "subcategory": "Religious Organization",
        "type": "Services"
      }
    ],
    "sg:phone": "+1 330 336 4230",
    "sg:postcode": "44281",
    "sg:province": "OH",
    "sg:tags": [
      "clergy"
    ],
    "wof:name": "James L Singleton",
    "wof:placetype": "venue"
  },
  "geometry": {"coordinates":[-81.724003,41.032206],"type":"Point"}
}
