{
  "type": "Feature",
  "properties": {
    "iso:country":"US",
    "sg:address":"412 Crestwood Ave",
    "sg:city":"Wadsworth",
    "sg:classifiers":[
        {
            "category":"Organizations",
            "subcategory":"Religious Organization",
            "type":"Services"
        }
    ],
    "sg:phone":"+1 330 336 4230",
    "sg:postcode":"44281",
    "sg:province":"OH",
    "sg:tags":[
        "clergy"
    ],
    "wof:name":"James L Singleton",
    "wof:placetype":"venue"
},
  "geometry": {"coordinates":[-81.724003,41.032206],"type":"Point"}
}