{
  "type": "Feature",
  "properties": {
    "addr:full":"5626 Frantz Rd Dublin OH 43017",
    "addr:housenumber":"5626",
    "addr:postcode":"43017",
    "addr:street":"Frantz Rd",
    "iso:country":"US",
    "sg:address":"5626 Frantz Rd",
    "sg:city":"Dublin",
    "sg:classifiers":[
        {
            "category":"Professional",
            "subcategory":"Credit Reporting & Collection",
            "type":"Services"
        }
    ],
    "sg:phone":"+1 614 791 4646",
    "sg:postcode":"43017",
    "sg:province":"OH",
    "sg:tags":[
        "agency"
    ],
    "sg:website":"www.transworldsystems.com",
    "wof:name":"Transworld Systems",
    "wof:placetype":"venue"
},
  "geometry": {"coordinates":[-83.12223899999999,40.083252],"type":"Point"}
}