{
  "type": "Feature",
  "properties": {
    "addr:full": "13071 Old Dayton Rd New Lebanon OH 45345",
    "addr:housenumber": "13071",
    "addr:postcode": "45345",
    "addr:street": "Old Dayton Rd",
    "iso:country": "US",
    "sg:address": "13071 Old Dayton Rd",
    "sg:city": "New Lebanon",
    "sg:classifiers": [
      {
        "category": "Building \u0026 Trades",
        "subcategory": "Plumbing",
        "type": "Services"
      }
    ],
    "sg:phone": "+1 937 833 5606",
    "sg:postcode": "45345",
    "sg:province": "OH",
    "sg:tags": [
      "contractor"
    ],
    "wof:name": "Free Flo LLC",
    "wof:placetype": "venue"
  },
  "geometry": {"coordinates":[-84.441631,39.759726],"type":"Point"}
}
