{
  "type": "Feature",
  "properties": {
    "addr:full": "8346 Chesney Ln Cincinnati OH 45249",
    "addr:housenumber": "8346",
    "addr:postcode": "45249",
    "addr:street": "Chesney Ln",
    "iso:country": "US",
    "sg:address": "8346 Chesney Ln",
    "sg:city": "Cincinnati",
    "sg:classifiers": [
      {
        "category": "Real Estate",
        "subcategory": "Real Estate Agent",
        "type": "Services"
      }
    ],
    "sg:phone": "+1 513 247 0993",
    "sg:postcode": "45249",
    "sg:province": "OH",
    "wof:name": "Robinson Womack",
    "wof:placetype": "venue"
  },
  "geometry": {"coordinates":[-84.334121,39.273188],"type":"Point"}
}
