{
  "type": "Feature",
  "properties": {
    "iso:country":"US",
    "sg:address":"8062 Hickory Hill Ln",
    "sg:city":"Cincinnati",
    "sg:classifiers":[
        {
            "category":"Professional",
            "subcategory":"Management & Consulting",
            "type":"Services"
        }
    ],
    "sg:phone":"+1 513 779 7296",
    "sg:postcode":"45241",
    "sg:province":"OH",
    "sg:tags":[
        "consultant",
        "resource",
        "human"
    ],
    "sg:website":"www.hrpiinc.com",
    "wof:name":"H R Partners Intl Inc",
    "wof:placetype":"venue"
},
  "geometry": {"coordinates":[-84.361709,39.306147],"type":"Point"}
}