{
  "type": "Feature",
  "properties": {
    "addr:full": "19550 Monterey Ave Cleveland OH 44119",
    "addr:housenumber": "19550",
    "addr:postcode": "44119",
    "addr:street": "Monterey Ave",
    "iso:country": "US",
    "sg:address": "19550 Monterey Ave",
    "sg:city": "Cleveland",
    "sg:classifiers": [
      {
        "category": "Building \u0026 Trades",
        "subcategory": "Construction",
        "type": "Services"
      }
    ],
    "sg:phone": "+1 216 481 6506",
    "sg:postcode": "44119",
    "sg:province": "OH",
    "sg:tags": [
      "residential"
    ],
    "wof:name": "Raggets Unlimited",
    "wof:placetype": "venue"
  },
  "geometry": {"coordinates":[-81.54147,41.590867],"type":"Point"}
}
