{
  "type": "Feature",
  "properties": {
    "iso:country":"US",
    "sg:address":"208 High St",
    "sg:city":"Flushing",
    "sg:classifiers":[
        {
            "category":"Government",
            "subcategory":"Post Office",
            "type":"Public Place"
        }
    ],
    "sg:phone":"+1 740 968 3212",
    "sg:postcode":"43977",
    "sg:province":"OH",
    "wof:name":"US Post Office",
    "wof:placetype":"venue"
},
  "geometry": {"coordinates":[-81.06768099999999,40.149291],"type":"Point"}
}