{
  "type": "Feature",
  "properties": {
    "iso:country":"US",
    "sg:address":"215 E Main St",
    "sg:city":"Wilmington",
    "sg:classifiers":[
        {
            "category":"Restaurant",
            "type":"Food & Drink"
        }
    ],
    "sg:phone":"+1 937 383 3888",
    "sg:postcode":"45177",
    "sg:province":"OH",
    "wof:name":"East West Intl Buffett",
    "wof:placetype":"venue"
},
  "geometry": {"coordinates":[-83.823965,39.4453],"type":"Point"}
}