{
  "type": "Feature",
  "properties": {
    "addr:full": "215 E Main St Wilmington OH 45177",
    "addr:housenumber": "215",
    "addr:postcode": "45177",
    "addr:street": "E Main St",
    "iso:country": "US",
    "sg:address": "215 E Main St",
    "sg:city": "Wilmington",
    "sg:classifiers": [
      {
        "category": "Restaurant",
        "type": "Food \u0026 Drink"
      }
    ],
    "sg:phone": "+1 937 383 3888",
    "sg:postcode": "45177",
    "sg:province": "OH",
    "wof:name": "East West Intl Buffett",
    "wof:placetype": "venue"
  },
  "geometry": {"coordinates":[-83.823965,39.4453],"type":"Point"}
}
