{
  "type": "Feature",
  "properties": {
    "iso:country":"US",
    "sg:address":"2114 Central Ave",
    "sg:city":"Middletown",
    "sg:classifiers":[
        {
            "category":"Professional",
            "subcategory":"Accounting & Tax Preparation",
            "type":"Services"
        }
    ],
    "sg:phone":"+1 513 422 1649",
    "sg:postcode":"45044",
    "sg:province":"OH",
    "sg:tags":[
        "accountant"
    ],
    "wof:name":"Jeffrey F Jackson CPA",
    "wof:placetype":"venue"
},
  "geometry": {"coordinates":[-84.386612,39.512428],"type":"Point"}
}