{
  "type": "Feature",
  "properties": {
    "addr:full": "2114 Central Ave Middletown OH 45044",
    "addr:housenumber": "2114",
    "addr:postcode": "45044",
    "addr:street": "Central Ave",
    "iso:country": "US",
    "sg:address": "2114 Central Ave",
    "sg:city": "Middletown",
    "sg:classifiers": [
      {
        "category": "Professional",
        "subcategory": "Accounting \u0026 Tax Preparation",
        "type": "Services"
      }
    ],
    "sg:phone": "+1 513 422 1649",
    "sg:postcode": "45044",
    "sg:province": "OH",
    "sg:tags": [
      "accountant"
    ],
    "wof:name": "Jeffrey F Jackson CPA",
    "wof:placetype": "venue"
  },
  "geometry": {"coordinates":[-84.386612,39.512428],"type":"Point"}
}
