{
  "type": "Feature",
  "properties": {
    "addr:full": "1721 Whetstone St Bucyrus OH 44820",
    "addr:housenumber": "1721",
    "addr:postcode": "44820",
    "addr:street": "Whetstone St",
    "iso:country": "US",
    "sg:address": "1721 Whetstone St",
    "sg:city": "Bucyrus",
    "sg:classifiers": [
      {
        "category": "Health Services",
        "subcategory": "Nursing And Care Facility",
        "type": "Services"
      },
      {
        "category": "Social Services",
        "type": "Services"
      }
    ],
    "sg:phone": "+1 419 562 4927",
    "sg:postcode": "44820",
    "sg:province": "OH",
    "sg:tags": [
      "intermediate",
      "retirement",
      "community",
      "home"
    ],
    "sg:website": "www.alcco.com",
    "wof:name": "ALC-Carlisle House",
    "wof:placetype": "venue"
  },
  "geometry": {"coordinates":[-82.958898,40.788205],"type":"Point"}
}
