{
  "type": "Feature",
  "properties": {
    "addr:full":"5671 Sheehan Ct Dublin OH 43016",
    "addr:housenumber":"5671",
    "addr:postcode":"43016",
    "addr:street":"Sheehan Ct",
    "iso:country":"US",
    "sg:address":"5671 Sheehan Ct",
    "sg:city":"Dublin",
    "sg:classifiers":[
        {
            "category":"Shopping",
            "subcategory":"Clothing, Apparel, & Fashions",
            "type":"Retail Goods"
        }
    ],
    "sg:phone":"+1 614 766 4730",
    "sg:postcode":"43016",
    "sg:province":"OH",
    "sg:tags":[
        "dressmaker"
    ],
    "wof:name":"S-N Designs Custom Tailoring",
    "wof:placetype":"venue"
},
  "geometry": {"coordinates":[-83.11941899999999,40.068812],"type":"Point"}
}