{
  "type": "Feature",
  "properties": {
    "addr:full":"1325 Twp Rd 653 Ashland OH 44805",
    "addr:housenumber":"1325;653",
    "addr:postcode":"44805",
    "addr:street":"Twp Rd",
    "iso:country":"US",
    "sg:address":"1325 Twp Rd 653",
    "sg:city":"Ashland",
    "sg:phone":"+1 419 289 2725",
    "sg:postcode":"44805",
    "sg:province":"OH",
    "sg:tags":[
        "farm",
        "soybean"
    ],
    "wof:name":"Zager Farm",
    "wof:placetype":"venue"
},
  "geometry": {"coordinates":[-82.249887,40.872229],"type":"Point"}
}