{
  "type": "Feature",
  "properties": {
    "iso:country":"US",
    "sg:address":"30325 Bainbridge Rd",
    "sg:city":"Cleveland",
    "sg:classifiers":[
        {
            "category":"Utilities",
            "subcategory":"Telephone",
            "type":"Services"
        }
    ],
    "sg:phone":"+1 440 498 8027",
    "sg:postcode":"44139",
    "sg:province":"OH",
    "sg:tags":[
        "distance",
        "long",
        "communications"
    ],
    "wof:name":"Acetel",
    "wof:placetype":"venue"
},
  "geometry": {"coordinates":[-81.463454,41.402011],"type":"Point"}
}