{
  "type": "Feature",
  "properties": {
    "addr:full":"61 Bond St Lucas OH 44843",
    "addr:housenumber":"61",
    "addr:postcode":"44843",
    "addr:street":"Bond St",
    "iso:country":"US",
    "sg:address":"61 Bond St",
    "sg:city":"Lucas",
    "sg:classifiers":[
        {
            "category":"Professional",
            "subcategory":"Computer Services",
            "type":"Services"
        }
    ],
    "sg:phone":"+1 419 892 2482",
    "sg:postcode":"44843",
    "sg:province":"OH",
    "sg:tags":[
        "consultant",
        "designer"
    ],
    "wof:name":"Partec Systems",
    "wof:placetype":"venue"
},
  "geometry": {"coordinates":[-82.415993,40.704944],"type":"Point"}
}