{
  "type": "Feature",
  "properties": {
    "iso:country":"US",
    "sg:address":"9289 Crestwood Dr",
    "sg:city":"Cleveland",
    "sg:classifiers":[
        {
            "category":"Real Estate",
            "subcategory":"Surveying",
            "type":"Services"
        }
    ],
    "sg:phone":"+1 440 886 0217",
    "sg:postcode":"44130",
    "sg:province":"OH",
    "sg:tags":[
        "surveyor"
    ],
    "wof:name":"Ingleright Engineering",
    "wof:placetype":"venue"
},
  "geometry": {"coordinates":[-81.75084200000001,41.390258],"type":"Point"}
}