{
  "type": "Feature",
  "properties": {
    "addr:full": "5817 Monroe St Sylvania OH 43560",
    "addr:housenumber": "5817",
    "addr:postcode": "43560",
    "addr:street": "Monroe St",
    "iso:country": "US",
    "sg:address": "5817 Monroe St",
    "sg:city": "Sylvania",
    "sg:classifiers": [
      {
        "category": "Restaurant",
        "type": "Food \u0026 Drink"
      }
    ],
    "sg:phone": "+1 419 885 0151",
    "sg:postcode": "43560",
    "sg:province": "OH",
    "sg:tags": [
      "eating"
    ],
    "wof:name": "Gourmet Garden",
    "wof:placetype": "venue"
  },
  "geometry": {"coordinates":[-83.681568,41.712112],"type":"Point"}
}
