{
  "type": "Feature",
  "properties": {
    "iso:country":"US",
    "sg:address":"6100 Tod Ave SW",
    "sg:city":"Warren",
    "sg:classifiers":[
        {
            "category":"Travel",
            "subcategory":"Travel Agent",
            "type":"Entertainment"
        }
    ],
    "sg:phone":"+1 330 824 8725",
    "sg:postcode":"44481",
    "sg:province":"OH",
    "sg:tags":[
        "agency",
        "bureau"
    ],
    "wof:name":"Pal Tours & Cruises",
    "wof:placetype":"venue"
},
  "geometry": {"coordinates":[-80.857463,41.174151],"type":"Point"}
}