{
  "type": "Feature",
  "properties": {
    "addr:full": "10217 Runnymede Ave Cleveland OH 44125",
    "addr:housenumber": "10217",
    "addr:postcode": "44125",
    "addr:street": "Runnymede Ave",
    "iso:country": "US",
    "sg:address": "10217 Runnymede Ave",
    "sg:city": "Cleveland",
    "sg:classifiers": [
      {
        "category": "Autos \u0026 Motor Vehicles",
        "subcategory": "Fuel \u0026 Gas Station",
        "type": "Retail Goods"
      }
    ],
    "sg:phone": "+1 216 271 2319",
    "sg:postcode": "44125",
    "sg:province": "OH",
    "sg:tags": [
      "station",
      "gasoline"
    ],
    "wof:name": "B P Maintenance",
    "wof:placetype": "venue"
  },
  "geometry": {"coordinates":[-81.611606,41.4281],"type":"Point"}
}
