{
  "type": "Feature",
  "properties": {
    "iso:country":"US",
    "sg:address":"2866 Penny Ln",
    "sg:city":"Youngstown",
    "sg:classifiers":[
        {
            "category":"Shopping",
            "subcategory":"Gifts & Souvenirs",
            "type":"Retail Goods"
        }
    ],
    "sg:phone":"+1 330 799 8603",
    "sg:postcode":"44515",
    "sg:province":"OH",
    "wof:name":"Magnificent Specialties",
    "wof:placetype":"venue"
},
  "geometry": {"coordinates":[-80.749742,41.072956],"type":"Point"}
}