{
  "type": "Feature",
  "properties": {
    "iso:country":"US",
    "sg:address":"1561 Milford Ave",
    "sg:city":"Marysville",
    "sg:classifiers":[
        {
            "category":"Organizations",
            "subcategory":"Community Association",
            "type":"Services"
        }
    ],
    "sg:phone":"+1 937 644 5505",
    "sg:postcode":"43040",
    "sg:province":"OH",
    "sg:tags":[
        "fraternal"
    ],
    "wof:name":"Loyal Order Of Moose",
    "wof:placetype":"venue"
},
  "geometry": {"coordinates":[-83.388738,40.216168],"type":"Point"}
}