{
  "type": "Feature",
  "properties": {
    "addr:full":"3204 Heatherdowns Blvd Toledo OH 43614",
    "addr:housenumber":"3204",
    "addr:postcode":"43614",
    "addr:street":"Heatherdowns Blvd",
    "iso:country":"US",
    "sg:address":"3204 Heatherdowns Blvd",
    "sg:city":"Toledo",
    "sg:classifiers":[
        {
            "category":"Building & Trades",
            "subcategory":"Construction",
            "type":"Services"
        }
    ],
    "sg:phone":"+1 419 382 0681",
    "sg:postcode":"43614",
    "sg:province":"OH",
    "sg:tags":[
        "company"
    ],
    "wof:name":"Moawad Construction-Samir Mwd",
    "wof:placetype":"venue"
},
  "geometry": {"coordinates":[-83.62060200000001,41.605319],"type":"Point"}
}