{
  "type": "Feature",
  "properties": {
    "addr:full": "11440 N Palmyra Rd North Jackson OH 44451",
    "addr:housenumber": "11440",
    "addr:postcode": "44451",
    "addr:street": "N Palmyra Rd",
    "iso:country": "US",
    "sg:address": "11440 N Palmyra Rd",
    "sg:city": "North Jackson",
    "sg:classifiers": [
      {
        "category": "Farming",
        "subcategory": "Dairy Farm",
        "type": "Manufacturing \u0026 Wholesale Goods"
      }
    ],
    "sg:phone": "+1 330 538 3359",
    "sg:postcode": "44451",
    "sg:province": "OH",
    "wof:name": "Campbell Ward",
    "wof:placetype": "venue"
  },
  "geometry": {"coordinates":[-80.860463,41.054963],"type":"Point"}
}
