{
  "type": "Feature",
  "properties": {
    "addr:full":"38 Eswin St Cincinnati OH 45218",
    "addr:housenumber":"38",
    "addr:postcode":"45218",
    "addr:street":"Eswin St",
    "iso:country":"US",
    "sg:address":"38 Eswin St",
    "sg:city":"Cincinnati",
    "sg:classifiers":[
        {
            "category":"Shopping",
            "subcategory":"Florist",
            "type":"Retail Goods"
        }
    ],
    "sg:phone":"+1 513 742 1400",
    "sg:postcode":"45218",
    "sg:province":"OH",
    "wof:name":"Jan Ellers Florist",
    "wof:placetype":"venue"
},
  "geometry": {"coordinates":[-84.522791,39.269818],"type":"Point"}
}