{
  "type": "Feature",
  "properties": {
    "iso:country":"US",
    "sg:address":"2431 Queenston Rd",
    "sg:city":"Cleveland",
    "sg:classifiers":[
        {
            "category":"Shopping",
            "type":"Retail Goods"
        }
    ],
    "sg:phone":"+1 216 932 4918",
    "sg:postcode":"44118",
    "sg:province":"OH",
    "sg:tags":[
        "merchandise",
        "business"
    ],
    "wof:name":"Mary Kay",
    "wof:placetype":"venue"
},
  "geometry": {"coordinates":[-81.554519,41.491227],"type":"Point"}
}