{
  "type": "Feature",
  "properties": {
    "iso:country":"US",
    "sg:address":"20680 N Park Blvd",
    "sg:city":"Cleveland",
    "sg:classifiers":[
        {
            "category":"Bars & Pubs",
            "type":"Food & Drink"
        },
        {
            "category":"Food & Beverages",
            "subcategory":"Groceries & Convenience Stores",
            "type":"Retail Goods"
        },
        {
            "category":"Restaurant",
            "type":"Food & Drink"
        },
        {
            "category":"Professional",
            "type":"Services"
        },
        {
            "category":"Fast Food",
            "type":"Food & Drink"
        }
    ],
    "sg:phone":"+1 216 321 7272",
    "sg:postcode":"44118",
    "sg:province":"OH",
    "sg:tags":[
        "shop",
        "sandwich",
        "seafood",
        "take",
        "caterer",
        "pasta",
        "pizza",
        "italian"
    ],
    "sg:website":"http://www.pizzazzpizza.com",
    "wof:name":"Pizzazz On the Circle",
    "wof:placetype":"venue"
},
  "geometry": {"coordinates":[-81.535428,41.487172],"type":"Point"}
}