{
  "type": "Feature",
  "properties": {
    "addr:full": "1044 S High St Columbus OH 43206",
    "addr:housenumber": "1044",
    "addr:postcode": "43206",
    "addr:street": "S High St",
    "iso:country": "US",
    "sg:address": "1044 S High St",
    "sg:city": "Columbus",
    "sg:classifiers": [
      {
        "category": "Shopping",
        "subcategory": "Tobacco",
        "type": "Retail Goods"
      }
    ],
    "sg:phone": "+1 614 443 5323",
    "sg:postcode": "43206",
    "sg:province": "OH",
    "sg:tags": [
      "store"
    ],
    "wof:name": "Burning Leaf",
    "wof:placetype": "venue"
  },
  "geometry": {"coordinates":[-82.996268,39.940098],"type":"Point"}
}
