{
  "type": "Feature",
  "properties": {
    "iso:country":"US",
    "sg:address":"107 Tara Ct",
    "sg:city":"Lima",
    "sg:classifiers":[
        {
            "category":"Manufacturing",
            "subcategory":"Printing",
            "type":"Manufacturing & Wholesale Goods"
        }
    ],
    "sg:phone":"+1 419 222 3769",
    "sg:postcode":"45805",
    "sg:province":"OH",
    "sg:tags":[
        "book"
    ],
    "wof:name":"Sj Publishing Inc",
    "wof:placetype":"venue"
},
  "geometry": {"coordinates":[-84.141935,40.767853],"type":"Point"}
}