{
  "type": "Feature",
  "properties": {
    "iso:country":"US",
    "sg:address":"1722 Seymour Ave",
    "sg:city":"Cincinnati",
    "sg:classifiers":[
        {
            "category":"Shopping",
            "subcategory":"Shoes",
            "type":"Retail Goods"
        }
    ],
    "sg:phone":"+1 513 631 0157",
    "sg:postcode":"45237",
    "sg:province":"OH",
    "wof:name":"Knapp Safety Shoe Co",
    "wof:placetype":"venue"
},
  "geometry": {"coordinates":[-84.463791,39.189769],"type":"Point"}
}