{
  "type": "Feature",
  "properties": {
    "iso:country":"US",
    "sg:address":"194 Big Run Rd",
    "sg:city":"Delaware",
    "sg:classifiers":[
        {
            "category":"Museum",
            "type":"Entertainment"
        }
    ],
    "sg:phone":"+1 614 761 2008",
    "sg:postcode":"43015",
    "sg:province":"OH",
    "sg:tags":[
        "gallery"
    ],
    "wof:name":"Deck The Walls",
    "wof:placetype":"venue"
},
  "geometry": {"coordinates":[-82.975269,40.269788],"type":"Point"}
}