{
  "type": "Feature",
  "properties": {
    "iso:country":"US",
    "sg:address":"5670 Cecil Rd",
    "sg:city":"Sidney",
    "sg:classifiers":[
        {
            "category":"Manufacturing",
            "subcategory":"Metals",
            "type":"Manufacturing & Wholesale Goods"
        },
        {
            "category":"Manufacturing",
            "subcategory":"Tools & Machinery",
            "type":"Manufacturing & Wholesale Goods"
        }
    ],
    "sg:phone":"+1 937 492 0977",
    "sg:postcode":"45365",
    "sg:province":"OH",
    "sg:tags":[
        "machine",
        "shop"
    ],
    "wof:name":"Sidney Can & Tool LLC",
    "wof:placetype":"venue"
},
  "geometry": {"coordinates":[-84.302171,40.280354],"type":"Point"}
}