{
  "type": "Feature",
  "properties": {
    "addr:full": "5670 Cecil Rd Sidney OH 45365",
    "addr:housenumber": "5670",
    "addr:postcode": "45365",
    "addr:street": "Cecil Rd",
    "iso:country": "US",
    "sg:address": "5670 Cecil Rd",
    "sg:city": "Sidney",
    "sg:classifiers": [
      {
        "category": "Manufacturing",
        "subcategory": "Metals",
        "type": "Manufacturing \u0026 Wholesale Goods"
      },
      {
        "category": "Manufacturing",
        "subcategory": "Tools \u0026 Machinery",
        "type": "Manufacturing \u0026 Wholesale Goods"
      }
    ],
    "sg:phone": "+1 937 492 0977",
    "sg:postcode": "45365",
    "sg:province": "OH",
    "sg:tags": [
      "machine",
      "shop"
    ],
    "wof:name": "Sidney Can \u0026 Tool LLC",
    "wof:placetype": "venue"
  },
  "geometry": {"coordinates":[-84.302171,40.280354],"type":"Point"}
}
