{
  "type": "Feature",
  "properties": {
    "iso:country":"US",
    "sg:address":"470 Annadale Ave",
    "sg:city":"Mansfield",
    "sg:classifiers":[
        {
            "category":"Building & Trades",
            "subcategory":"Cleaning & Sanitation",
            "type":"Services"
        }
    ],
    "sg:phone":"+1 419 755 1963",
    "sg:postcode":"44905",
    "sg:province":"OH",
    "sg:tags":[
        "janitor"
    ],
    "wof:name":"Euts Cleaning Svc",
    "wof:placetype":"venue"
},
  "geometry": {"coordinates":[-82.4996,40.78362],"type":"Point"}
}