{
  "type": "Feature",
  "properties": {
    "addr:full": "2749 Morse Rd Columbus OH 43231",
    "addr:housenumber": "2749",
    "addr:postcode": "43231",
    "addr:street": "Morse Rd",
    "iso:country": "US",
    "sg:address": "2749 Morse Rd",
    "sg:city": "Columbus",
    "sg:classifiers": [
      {
        "category": "Autos \u0026 Motor Vehicles",
        "subcategory": "Automobile Sales",
        "type": "Retail Goods"
      }
    ],
    "sg:phone": "+1 614 478 5800",
    "sg:postcode": "43231",
    "sg:province": "OH",
    "sg:tags": [
      "used"
    ],
    "wof:name": "Safe Auto Sales Inc",
    "wof:placetype": "venue"
  },
  "geometry": {"coordinates":[-82.946006,40.059098],"type":"Point"}
}
