{
  "type": "Feature",
  "properties": {
    "iso:country":"US",
    "sg:address":"2749 Morse Rd",
    "sg:city":"Columbus",
    "sg:classifiers":[
        {
            "category":"Autos & Motor Vehicles",
            "subcategory":"Automobile Sales",
            "type":"Retail Goods"
        }
    ],
    "sg:phone":"+1 614 478 5800",
    "sg:postcode":"43231",
    "sg:province":"OH",
    "sg:tags":[
        "used"
    ],
    "wof:name":"Safe Auto Sales Inc",
    "wof:placetype":"venue"
},
  "geometry": {"coordinates":[-82.946006,40.059098],"type":"Point"}
}