{
  "type": "Feature",
  "properties": {
    "addr:full":"529 N High St Hillsboro OH 45133",
    "addr:housenumber":"529",
    "addr:postcode":"45133",
    "addr:street":"N High St",
    "iso:country":"US",
    "sg:address":"529 N High St",
    "sg:city":"Hillsboro",
    "sg:classifiers":[
        {
            "category":"Utilities",
            "subcategory":"Mobile Phone",
            "type":"Services"
        },
        {
            "category":"Shopping",
            "type":"Retail Goods"
        }
    ],
    "sg:phone":"+1 937 393 0088",
    "sg:postcode":"45133",
    "sg:province":"OH",
    "sg:tags":[
        "communication",
        "merchandise",
        "radiotelephone",
        "cellular",
        "telephone"
    ],
    "wof:name":"Executive Cellular Network Inc",
    "wof:placetype":"venue"
},
  "geometry": {"coordinates":[-83.610091,39.208274],"type":"Point"}
}