{
  "type": "Feature",
  "properties": {
    "addr:full":"6094 Bridgetown Rd Cincinnati OH 45248",
    "addr:housenumber":"6094",
    "addr:postcode":"45248",
    "addr:street":"Bridgetown Rd",
    "iso:country":"US",
    "sg:address":"6094 Bridgetown Rd",
    "sg:city":"Cincinnati",
    "sg:classifiers":[
        {
            "category":"Food & Beverages",
            "subcategory":"Groceries & Convenience Stores",
            "type":"Retail Goods"
        }
    ],
    "sg:phone":"+1 513 941 9080",
    "sg:postcode":"45248",
    "sg:province":"OH",
    "wof:name":"Jeff's",
    "wof:placetype":"venue"
},
  "geometry": {"coordinates":[-84.647813,39.158662],"type":"Point"}
}