{
  "type": "Feature",
  "properties": {
    "addr:full":"630 Newdale Dr Bryan OH 43506",
    "addr:housenumber":"630",
    "addr:postcode":"43506",
    "addr:street":"Newdale Dr",
    "iso:country":"US",
    "sg:address":"630 Newdale Dr",
    "sg:city":"Bryan",
    "sg:classifiers":[
        {
            "category":"Government",
            "subcategory":"Office",
            "type":"Public Place"
        }
    ],
    "sg:phone":"+1 419 636 1414",
    "sg:postcode":"43506",
    "sg:province":"OH",
    "sg:tags":[
        "national",
        "security"
    ],
    "wof:name":"US Army Reserve",
    "wof:placetype":"venue"
},
  "geometry": {"coordinates":[-84.569525,41.466726],"type":"Point"}
}