{
  "type": "Feature",
  "properties": {
    "addr:full":"317 Forest Meadows Dr Medina OH 44256",
    "addr:housenumber":"317",
    "addr:postcode":"44256",
    "addr:street":"Forest Meadows Dr",
    "iso:country":"US",
    "sg:address":"317 Forest Meadows Dr",
    "sg:city":"Medina",
    "sg:classifiers":[
        {
            "category":"Real Estate",
            "subcategory":"Real Estate Agent",
            "type":"Services"
        }
    ],
    "sg:phone":"+1 330 725 5341",
    "sg:postcode":"44256",
    "sg:province":"OH",
    "wof:name":"Abell Enterprises",
    "wof:placetype":"venue"
},
  "geometry": {"coordinates":[-81.859754,41.151361],"type":"Point"}
}