{
  "type": "Feature",
  "properties": {
    "addr:full":"978 Proehl Dr Barberton OH 44203",
    "addr:housenumber":"978",
    "addr:postcode":"44203",
    "addr:street":"Proehl Dr",
    "iso:country":"US",
    "sg:address":"978 Proehl Dr",
    "sg:city":"Barberton",
    "sg:classifiers":[
        {
            "category":"Travel",
            "subcategory":"Travel Agent",
            "type":"Entertainment"
        }
    ],
    "sg:phone":"+1 330 645 0173",
    "sg:postcode":"44203",
    "sg:province":"OH",
    "sg:tags":[
        "agency",
        "bureau"
    ],
    "wof:name":"Agape Travel Svc",
    "wof:placetype":"venue"
},
  "geometry": {"coordinates":[-81.559541,41.008477],"type":"Point"}
}