{
  "type": "Feature",
  "properties": {
    "addr:full": "3051 Shady Ln Cleveland OH 44131",
    "addr:housenumber": "3051",
    "addr:postcode": "44131",
    "addr:street": "Shady Ln",
    "iso:country": "US",
    "sg:address": "3051 Shady Ln",
    "sg:city": "Cleveland",
    "sg:classifiers": [
      {
        "category": "Recreation",
        "type": "Entertainment"
      }
    ],
    "sg:phone": "+1 216 491 1290",
    "sg:postcode": "44131",
    "sg:province": "OH",
    "sg:tags": [
      "club",
      "membership"
    ],
    "wof:name": "Shaker Recreation",
    "wof:placetype": "venue"
  },
  "geometry": {"coordinates":[-81.669084,41.374779],"type":"Point"}
}
