{
  "type": "Feature",
  "properties": {
    "iso:country":"US",
    "sg:address":"3563 State Rte 83",
    "sg:city":"Millersburg",
    "sg:classifiers":[
        {
            "category":"Wholesale",
            "subcategory":"Computers",
            "type":"Manufacturing & Wholesale Goods"
        }
    ],
    "sg:phone":"+1 330 674 7370",
    "sg:postcode":"44654",
    "sg:province":"OH",
    "sg:tags":[
        "sales"
    ],
    "wof:name":"National Merchandise Co",
    "wof:placetype":"venue"
},
  "geometry": {"coordinates":[-81.911214,40.509093],"type":"Point"}
}