{
  "type": "Feature",
  "properties": {
    "addr:full": "970 Windham Ct Youngstown OH 44512",
    "addr:housenumber": "970",
    "addr:postcode": "44512",
    "addr:street": "Windham Ct",
    "iso:country": "US",
    "sg:address": "970 Windham Ct",
    "sg:city": "Youngstown",
    "sg:classifiers": [
      {
        "category": "Insurance",
        "subcategory": "Insurance Agent",
        "type": "Services"
      }
    ],
    "sg:phone": "+1 330 726 8858",
    "sg:postcode": "44512",
    "sg:province": "OH",
    "wof:name": "American Express",
    "wof:placetype": "venue"
  },
  "geometry": {"coordinates":[-80.635322,41.028483],"type":"Point"}
}
