{
  "type": "Feature",
  "properties": {
    "addr:full":"4624 Warrensville Center Rd Cleveland OH 44128",
    "addr:housenumber":"4624",
    "addr:postcode":"44128",
    "addr:street":"Warrensville Center Rd",
    "iso:country":"US",
    "sg:address":"4624 Warrensville Center Rd",
    "sg:city":"Cleveland",
    "sg:classifiers":[
        {
            "category":"Personal",
            "subcategory":"Beauty Salon",
            "type":"Services"
        }
    ],
    "sg:phone":"+1 216 662 8831",
    "sg:postcode":"44128",
    "sg:province":"OH",
    "sg:tags":[
        "shop"
    ],
    "wof:name":"Abracadabra Hair & Nail Salon",
    "wof:placetype":"venue"
},
  "geometry": {"coordinates":[-81.536135,41.431412],"type":"Point"}
}