{
  "type": "Feature",
  "properties": {
    "addr:full":"4645 Morse Centre Rd Columbus OH 43229",
    "addr:housenumber":"4645",
    "addr:postcode":"43229",
    "addr:street":"Morse Centre Rd",
    "iso:country":"US",
    "sg:address":"4645 Morse Centre Rd",
    "sg:city":"Columbus",
    "sg:classifiers":[
        {
            "category":"Shopping",
            "subcategory":"Discount & Variety Stores",
            "type":"Retail Goods"
        }
    ],
    "sg:phone":"+1 614 433 0727",
    "sg:postcode":"43229",
    "sg:province":"OH",
    "wof:name":"Big Lots",
    "wof:placetype":"venue"
},
  "geometry": {"coordinates":[-82.962594,40.060517],"type":"Point"}
}