{
  "type": "Feature",
  "properties": {
    "addr:full":"2206 Lagrange St Toledo OH 43608",
    "addr:housenumber":"2206",
    "addr:postcode":"43608",
    "addr:street":"Lagrange St",
    "iso:country":"US",
    "sg:address":"2206 Lagrange St",
    "sg:city":"Toledo",
    "sg:classifiers":[
        {
            "category":"Shopping",
            "type":"Retail Goods"
        },
        {
            "category":"Manufacturing",
            "subcategory":"Apparel",
            "type":"Manufacturing & Wholesale Goods"
        }
    ],
    "sg:phone":"+1 419 241 1181",
    "sg:postcode":"43608",
    "sg:province":"OH",
    "sg:tags":[
        "product",
        "merchandise",
        "canvas",
        "related"
    ],
    "wof:name":"Action Canvas & Boat Covers",
    "wof:placetype":"venue"
},
  "geometry": {"coordinates":[-83.53688099999999,41.670551],"type":"Point"}
}