{
  "type": "Feature",
  "properties": {
    "addr:full":"7920 Mapleway Dr Cleveland OH 44138",
    "addr:housenumber":"7920",
    "addr:postcode":"44138",
    "addr:street":"Mapleway Dr",
    "iso:country":"US",
    "sg:address":"7920 Mapleway Dr",
    "sg:city":"Cleveland",
    "sg:classifiers":[
        {
            "category":"Wholesale",
            "subcategory":"Stationery",
            "type":"Manufacturing & Wholesale Goods"
        },
        {
            "category":"Manufacturing",
            "subcategory":"Paper Products",
            "type":"Manufacturing & Wholesale Goods"
        }
    ],
    "sg:phone":"+1 440 235 7200",
    "sg:postcode":"44138",
    "sg:province":"OH",
    "sg:tags":[
        "mfg"
    ],
    "sg:website":"www.blueridgepaper.com",
    "wof:name":"Blue Ridge Paper Products Inc",
    "wof:placetype":"venue"
},
  "geometry": {"coordinates":[-81.90957,41.374841],"type":"Point"}
}