{
  "type": "Feature",
  "properties": {
    "addr:full": "8128 Kirtland Chardon Rd Willoughby OH 44094",
    "addr:housenumber": "8128",
    "addr:postcode": "44094",
    "addr:street": "Kirtland Chardon Rd",
    "iso:country": "US",
    "sg:address": "8128 Kirtland Chardon Rd",
    "sg:city": "Willoughby",
    "sg:classifiers": [
      {
        "category": "Professional",
        "subcategory": "Accounting \u0026 Tax Preparation",
        "type": "Services"
      }
    ],
    "sg:phone": "+1 440 256 3105",
    "sg:postcode": "44094",
    "sg:province": "OH",
    "sg:tags": [
      "accountant"
    ],
    "wof:name": "David L Kirek CPA",
    "wof:placetype": "venue"
  },
  "geometry": {"coordinates":[-81.349858,41.621825],"type":"Point"}
}
