{
  "type": "Feature",
  "properties": {
    "addr:full": "129 Prospect Ave S Hartville OH 44632",
    "addr:housenumber": "129",
    "addr:postcode": "44632",
    "addr:street": "Prospect Ave S",
    "iso:country": "US",
    "sg:address": "129 Prospect Ave S",
    "sg:city": "Hartville",
    "sg:classifiers": [
      {
        "category": "Professional",
        "subcategory": "Business Services",
        "type": "Services"
      }
    ],
    "sg:phone": "+1 330 877 4400",
    "sg:postcode": "44632",
    "sg:province": "OH",
    "sg:tags": [
      "florist"
    ],
    "wof:name": "Just Not Normal",
    "wof:placetype": "venue"
  },
  "geometry": {"coordinates":[-81.332335,40.963218],"type":"Point"}
}
