{
  "type": "Feature",
  "properties": {
    "addr:full": "1466 Alpine Dr Columbus OH 43229",
    "addr:housenumber": "1466",
    "addr:postcode": "43229",
    "addr:street": "Alpine Dr",
    "iso:country": "US",
    "sg:address": "1466 Alpine Dr",
    "sg:city": "Columbus",
    "sg:classifiers": [
      {
        "category": "Health Services",
        "subcategory": "Doctor",
        "type": "Services"
      }
    ],
    "sg:phone": "+1 614 885 9083",
    "sg:postcode": "43229",
    "sg:province": "OH",
    "sg:tags": [
      "clinic"
    ],
    "wof:name": "Obregon Health Ctr Inc",
    "wof:placetype": "venue"
  },
  "geometry": {"coordinates":[-82.978675,40.093201],"type":"Point"}
}
