{
  "type": "Feature",
  "properties": {
    "addr:full":"5123 Tuttle Crossing Blvd Dublin OH 43016",
    "addr:housenumber":"5123",
    "addr:postcode":"43016",
    "addr:street":"Tuttle Crossing Blvd",
    "iso:country":"US",
    "sg:address":"5123 Tuttle Crossing Blvd",
    "sg:city":"Dublin",
    "sg:classifiers":[
        {
            "category":"Shopping",
            "subcategory":"Clothing, Apparel, & Fashions",
            "type":"Retail Goods"
        }
    ],
    "sg:phone":"+1 614 760 1237",
    "sg:postcode":"43016",
    "sg:province":"OH",
    "sg:tags":[
        "alteration"
    ],
    "wof:name":"Lazarus-Macy's Alteration Svc",
    "wof:placetype":"venue"
},
  "geometry": {"coordinates":[-83.12731100000001,40.076766],"type":"Point"}
}