{
  "type": "Feature",
  "properties": {
    "iso:country":"US",
    "sg:address":"1700 E Market St",
    "sg:city":"Warren",
    "sg:classifiers":[
        {
            "category":"Health Services",
            "subcategory":"Doctor",
            "type":"Services"
        }
    ],
    "sg:phone":"+1 330 394 8844",
    "sg:postcode":"44483",
    "sg:province":"OH",
    "sg:tags":[
        "physician",
        "surgeon"
    ],
    "wof:name":"M Rammohan Inc",
    "wof:placetype":"venue"
},
  "geometry": {"coordinates":[-80.794741,41.236526],"type":"Point"}
}