{
  "type": "Feature",
  "properties": {
    "addr:full":"9 Corporation Center Cleveland OH 44147",
    "addr:housenumber":"9",
    "addr:postcode":"44147",
    "addr:street":"Corporation Center",
    "iso:country":"US",
    "sg:address":"9 Corporation Center",
    "sg:city":"Cleveland",
    "sg:classifiers":[
        {
            "category":"Building & Trades",
            "subcategory":"Construction",
            "type":"Services"
        }
    ],
    "sg:phone":"+1 440 838 4515",
    "sg:postcode":"44147",
    "sg:province":"OH",
    "sg:tags":[
        "home",
        "builder"
    ],
    "wof:name":"Homes In Ohio",
    "wof:placetype":"venue"
},
  "geometry": {"coordinates":[-81.672899,41.294058],"type":"Point"}
}