{
  "type": "Feature",
  "properties": {
    "addr:full":"4763 W 32nd St Cleveland OH 44109",
    "addr:housenumber":"4763",
    "addr:postcode":"44109",
    "addr:street":"W 32Nd St",
    "iso:country":"US",
    "sg:address":"4763 W 32nd St",
    "sg:city":"Cleveland",
    "sg:classifiers":[
        {
            "category":"Wholesale",
            "subcategory":"Machinery & Supplies",
            "type":"Manufacturing & Wholesale Goods"
        }
    ],
    "sg:phone":"+1 216 741 1414",
    "sg:postcode":"44109",
    "sg:province":"OH",
    "sg:tags":[
        "machine",
        "tool",
        "cutting"
    ],
    "wof:name":"Johnson Tool Inc",
    "wof:placetype":"venue"
},
  "geometry": {"coordinates":[-81.70656700000001,41.425158],"type":"Point"}
}