{
  "type": "Feature",
  "properties": {
    "addr:full": "123 Franklin St Winchester OH 45680",
    "addr:housenumber": "123",
    "addr:postcode": "45680",
    "addr:street": "Franklin St",
    "iso:country": "US",
    "sg:address": "123 Franklin St",
    "sg:city": "Winchester",
    "sg:classifiers": [
      {
        "category": "Home \u0026 Garden",
        "subcategory": "Household Appliances",
        "type": "Retail Goods"
      }
    ],
    "sg:phone": "+1 937 584 5411",
    "sg:postcode": "45680",
    "sg:province": "OH",
    "wof:name": "Johnson TV \u0026 Appliance",
    "wof:placetype": "venue"
  },
  "geometry": {"coordinates":[-82.576134,38.417238],"type":"Point"}
}
