{
  "type": "Feature",
  "properties": {
    "iso:country":"US",
    "sg:address":"474 W Main St",
    "sg:city":"Apple Creek",
    "sg:classifiers":[
        {
            "category":"Building & Trades",
            "subcategory":"Plumbing",
            "type":"Services"
        }
    ],
    "sg:phone":"+1 330 698 8471",
    "sg:postcode":"44606",
    "sg:province":"OH",
    "sg:tags":[
        "conditioning",
        "air",
        "system",
        "contractor"
    ],
    "wof:name":"Howell Heating",
    "wof:placetype":"venue"
},
  "geometry": {"coordinates":[-81.841728,40.753823],"type":"Point"}
}