{
  "type": "Feature",
  "properties": {
    "addr:full":"14415 Pearl Rd Cleveland OH 44136",
    "addr:housenumber":"14415",
    "addr:postcode":"44136",
    "addr:street":"Pearl Rd",
    "iso:country":"US",
    "sg:address":"14415 Pearl Rd",
    "sg:city":"Cleveland",
    "sg:classifiers":[
        {
            "category":"Banks & Credit Unions",
            "subcategory":"Bank",
            "type":"Services"
        }
    ],
    "sg:phone":"+1 440 878 8000",
    "sg:postcode":"44136",
    "sg:province":"OH",
    "sg:tags":[
        "loan",
        "real estate"
    ],
    "sg:website":"www.fullspectrumlending.com",
    "wof:name":"Full Spectrum Lending",
    "wof:placetype":"venue"
},
  "geometry": {"coordinates":[-81.835154,41.311394],"type":"Point"}
}