{
  "type": "Feature",
  "properties": {
    "iso:country":"US",
    "sg:address":"12855 Beaver Creek Rd",
    "sg:city":"Salem",
    "sg:classifiers":[
        {
            "category":"Real Estate",
            "subcategory":"Developer",
            "type":"Services"
        }
    ],
    "sg:phone":"+1 330 533 8865",
    "sg:postcode":"44460",
    "sg:province":"OH",
    "wof:name":"J Monroe Developing Inc",
    "wof:placetype":"venue"
},
  "geometry": {"coordinates":[-80.809147,40.932004],"type":"Point"}
}