{
  "type": "Feature",
  "properties": {
    "addr:full": "1398 Sweitzer St Greenville OH 45331",
    "addr:housenumber": "1398",
    "addr:postcode": "45331",
    "addr:street": "Sweitzer St",
    "iso:country": "US",
    "sg:address": "1398 Sweitzer St",
    "sg:city": "Greenville",
    "sg:classifiers": [
      {
        "category": "Utilities",
        "subcategory": "Electric",
        "type": "Services"
      }
    ],
    "sg:phone": "+1 937 548 2161",
    "sg:postcode": "45331",
    "sg:province": "OH",
    "sg:tags": [
      "company"
    ],
    "wof:name": "Dayton Power \u0026 Light Co",
    "wof:placetype": "venue"
  },
  "geometry": {"coordinates":[-84.633751,40.079667],"type":"Point"}
}
