{
  "type": "Feature",
  "properties": {
    "addr:full": "3355 Deer Creek Trl Richfield OH 44286",
    "addr:housenumber": "3355",
    "addr:postcode": "44286",
    "addr:street": "Deer Creek Trl",
    "iso:country": "US",
    "sg:address": "3355 Deer Creek Trl",
    "sg:city": "Richfield",
    "sg:phone": "+1 330 659 7379",
    "sg:postcode": "44286",
    "sg:province": "OH",
    "sg:tags": [
      "equipment",
      "commercial"
    ],
    "wof:name": "Datavision Inc",
    "wof:placetype": "venue"
  },
  "geometry": {"coordinates":[-81.645038,41.265037],"type":"Point"}
}
