{
  "type": "Feature",
  "properties": {
    "addr:full": "3721 Lee Rd Cleveland OH 44120",
    "addr:housenumber": "3721",
    "addr:postcode": "44120",
    "addr:street": "Lee Rd",
    "iso:country": "US",
    "sg:address": "3721 Lee Rd",
    "sg:city": "Cleveland",
    "sg:classifiers": [
      {
        "category": "Wholesale",
        "subcategory": "Machinery \u0026 Supplies",
        "type": "Manufacturing \u0026 Wholesale Goods"
      }
    ],
    "sg:phone": "+1 216 991 6466",
    "sg:postcode": "44120",
    "sg:province": "OH",
    "sg:tags": [
      "welding"
    ],
    "wof:name": "Addifix",
    "wof:placetype": "venue"
  },
  "geometry": {"coordinates":[-81.56483,41.458584],"type":"Point"}
}
