{
  "type": "Feature",
  "properties": {
    "iso:country":"US",
    "sg:address":"3721 Lee Rd",
    "sg:city":"Cleveland",
    "sg:classifiers":[
        {
            "category":"Wholesale",
            "subcategory":"Machinery & Supplies",
            "type":"Manufacturing & Wholesale Goods"
        }
    ],
    "sg:phone":"+1 216 991 6466",
    "sg:postcode":"44120",
    "sg:province":"OH",
    "sg:tags":[
        "welding"
    ],
    "wof:name":"Addifix",
    "wof:placetype":"venue"
},
  "geometry": {"coordinates":[-81.56483,41.458584],"type":"Point"}
}