{
  "type": "Feature",
  "properties": {
    "addr:full":"24755 Chagrin Blvd Cleveland OH 44122",
    "addr:housenumber":"24755",
    "addr:postcode":"44122",
    "addr:street":"Chagrin Blvd",
    "iso:country":"US",
    "sg:address":"24755 Chagrin Blvd",
    "sg:city":"Cleveland",
    "sg:classifiers":[
        {
            "category":"Wholesale",
            "subcategory":"Medical Equipment & Supplies",
            "type":"Manufacturing & Wholesale Goods"
        }
    ],
    "sg:phone":"+1 216 587 7260",
    "sg:postcode":"44122",
    "sg:province":"OH",
    "sg:tags":[
        "physician",
        "surgeon"
    ],
    "wof:name":"Professional Medical Equipment",
    "wof:placetype":"venue"
},
  "geometry": {"coordinates":[-81.50116,41.464533],"type":"Point"}
}