{
  "type": "Feature",
  "properties": {
    "addr:full": "4934 Turney Rd Cleveland OH 44125",
    "addr:housenumber": "4934",
    "addr:postcode": "44125",
    "addr:street": "Turney Rd",
    "iso:country": "US",
    "sg:address": "4934 Turney Rd",
    "sg:city": "Cleveland",
    "sg:classifiers": [
      {
        "category": "Shopping",
        "subcategory": "Department Store",
        "type": "Retail Goods"
      }
    ],
    "sg:phone": "+1 216 429 2074",
    "sg:postcode": "44125",
    "sg:province": "OH",
    "wof:name": "Dollar Paradise",
    "wof:placetype": "venue"
  },
  "geometry": {"coordinates":[-81.612679,41.426188],"type":"Point"}
}
