{
  "type": "Feature",
  "properties": {
    "iso:country":"US",
    "sg:address":"935 E Columbus St",
    "sg:city":"Kenton",
    "sg:classifiers":[
        {
            "category":"Banks & Credit Unions",
            "subcategory":"Bank",
            "type":"Services"
        }
    ],
    "sg:phone":"+1 419 674 4162",
    "sg:postcode":"43326",
    "sg:province":"OH",
    "sg:website":"www.lnbbank.com",
    "wof:name":"Liberty National Bank",
    "wof:placetype":"venue"
},
  "geometry": {"coordinates":[-83.591831,40.651709],"type":"Point"}
}