{
  "type": "Feature",
  "properties": {
    "iso:country":"US",
    "sg:address":"565 Metro Pl S",
    "sg:city":"Dublin",
    "sg:classifiers":[
        {
            "category":"Professional",
            "subcategory":"Business Services",
            "type":"Services"
        }
    ],
    "sg:phone":"+1 614 280 1600",
    "sg:postcode":"43017",
    "sg:province":"OH",
    "sg:tags":[
        "telemarketing"
    ],
    "sg:website":"www.influentinc.com",
    "wof:name":"Interactive Teleservices Corp",
    "wof:placetype":"venue"
},
  "geometry": {"coordinates":[-83.129255,40.093329],"type":"Point"}
}