{
  "type": "Feature",
  "properties": {
    "addr:full": "565 Metro Pl S Dublin OH 43017",
    "addr:housenumber": "565",
    "addr:postcode": "43017",
    "addr:street": "Metro Pl",
    "iso:country": "US",
    "sg:address": "565 Metro Pl S",
    "sg:city": "Dublin",
    "sg:classifiers": [
      {
        "category": "Professional",
        "subcategory": "Business Services",
        "type": "Services"
      }
    ],
    "sg:phone": "+1 614 280 1600",
    "sg:postcode": "43017",
    "sg:province": "OH",
    "sg:tags": [
      "telemarketing"
    ],
    "sg:website": "www.influentinc.com",
    "wof:name": "Interactive Teleservices Corp",
    "wof:placetype": "venue"
  },
  "geometry": {"coordinates":[-83.129255,40.093329],"type":"Point"}
}
