{
  "type": "Feature",
  "properties": {
    "iso:country":"US",
    "sg:address":"1604 Wedgewood Way",
    "sg:city":"Wooster",
    "sg:classifiers":[
        {
            "category":"Shopping",
            "type":"Retail Goods"
        }
    ],
    "sg:phone":"+1 330 345 8411",
    "sg:postcode":"44691",
    "sg:province":"OH",
    "sg:tags":[
        "plastic"
    ],
    "wof:name":"Jarden Plastic Solutions",
    "wof:placetype":"venue"
},
  "geometry": {"coordinates":[-81.916068,40.837332],"type":"Point"}
}