{
  "type": "Feature",
  "properties": {
    "iso:country":"US",
    "sg:address":"90 Smith Rd",
    "sg:city":"South Webster",
    "sg:classifiers":[
        {
            "category":"Manufacturing",
            "subcategory":"Glass & Minerals",
            "type":"Manufacturing & Wholesale Goods"
        }
    ],
    "sg:phone":"+1 740 778 2634",
    "sg:postcode":"45682",
    "sg:province":"OH",
    "sg:tags":[
        "refractory",
        "mfg"
    ],
    "wof:name":"Vesuvius USA Corporation",
    "wof:placetype":"venue"
},
  "geometry": {"coordinates":[-82.730889,38.85284],"type":"Point"}
}