{
  "type": "Feature",
  "properties": {
    "addr:full":"3615 Lockbourne Rd Columbus OH 43207",
    "addr:housenumber":"3615",
    "addr:postcode":"43207",
    "addr:street":"Lockbourne Rd",
    "iso:country":"US",
    "sg:address":"3615 Lockbourne Rd",
    "sg:city":"Columbus",
    "sg:classifiers":[
        {
            "category":"Retail",
            "subcategory":"Repair Shop",
            "type":"Services"
        }
    ],
    "sg:phone":"+1 614 492 0691",
    "sg:postcode":"43207",
    "sg:province":"OH",
    "sg:tags":[
        "related"
    ],
    "wof:name":"Holcomb's Repair",
    "wof:placetype":"venue"
},
  "geometry": {"coordinates":[-82.968277,39.886999],"type":"Point"}
}