{
  "type": "Feature",
  "properties": {
    "addr:full": "105 Mc Knight Dr Middletown OH 45044",
    "addr:housenumber": "105",
    "addr:postcode": "45044",
    "addr:street": "Mc Knight Dr",
    "iso:country": "US",
    "sg:address": "105 Mc Knight Dr",
    "sg:city": "Middletown",
    "sg:classifiers": [
      {
        "category": "Health Services",
        "subcategory": "Doctor",
        "type": "Services"
      }
    ],
    "sg:phone": "+1 513 705 4766",
    "sg:postcode": "45044",
    "sg:province": "OH",
    "sg:tags": [
      "physician",
      "surgeon"
    ],
    "wof:name": "Arthur Arand MD",
    "wof:placetype": "venue"
  },
  "geometry": {"coordinates":[-84.37622,39.51],"type":"Point"}
}
