{
  "type": "Feature",
  "properties": {
    "addr:full": "77 Smithsonian St Girard OH 44420",
    "addr:housenumber": "77",
    "addr:postcode": "44420",
    "addr:street": "Smithsonian St",
    "iso:country": "US",
    "sg:address": "77 Smithsonian St",
    "sg:city": "Girard",
    "sg:classifiers": [
      {
        "category": "Building \u0026 Trades",
        "subcategory": "Construction",
        "type": "Services"
      }
    ],
    "sg:phone": "+1 330 545 3330",
    "sg:postcode": "44420",
    "sg:province": "OH",
    "sg:tags": [
      "house"
    ],
    "wof:name": "Andrew Pizzulo Construction",
    "wof:placetype": "venue"
  },
  "geometry": {"coordinates":[-80.702707,41.164065],"type":"Point"}
}
