{
  "type": "Feature",
  "properties": {
    "addr:full": "54 S Main St Dayton OH 45402",
    "addr:housenumber": "54",
    "addr:postcode": "45402",
    "addr:street": "S Main St",
    "iso:country": "US",
    "sg:address": "54 S Main St",
    "sg:city": "Dayton",
    "sg:classifiers": [
      {
        "category": "Real Estate",
        "subcategory": "Developer",
        "type": "Services"
      }
    ],
    "sg:phone": "+1 937 384 0708",
    "sg:postcode": "45402",
    "sg:province": "OH",
    "wof:name": "DPG Group Inc",
    "wof:placetype": "venue"
  },
  "geometry": {"coordinates":[-84.191356,39.758148],"type":"Point"}
}
