{
  "type": "Feature",
  "properties": {
    "addr:full":"1 Court House Plz Bryan OH 43567",
    "addr:housenumber":"1",
    "addr:postcode":"43567",
    "addr:street":"Court House Plz",
    "iso:country":"US",
    "sg:address":"1 Court House Plz",
    "sg:city":"Bryan",
    "sg:classifiers":[
        {
            "category":"Government",
            "subcategory":"Office",
            "type":"Public Place"
        }
    ],
    "sg:phone":"+1 419 636 3259",
    "sg:postcode":"43567",
    "sg:province":"OH",
    "wof:name":"Williams County Recorder",
    "wof:placetype":"venue"
},
  "geometry": {"coordinates":[-84.345468,41.279019],"type":"Point"}
}