{
  "type": "Feature",
  "properties": {
    "addr:full":"164 Mc Craw Dr Englewood OH 45322",
    "addr:housenumber":"164",
    "addr:postcode":"45322",
    "addr:street":"Mc Craw Dr",
    "iso:country":"US",
    "sg:address":"164 Mc Craw Dr",
    "sg:city":"Englewood",
    "sg:classifiers":[
        {
            "category":"Shopping",
            "subcategory":"Discount & Variety Stores",
            "type":"Retail Goods"
        }
    ],
    "sg:phone":"+1 937 832 9888",
    "sg:postcode":"45322",
    "sg:province":"OH",
    "sg:tags":[
        "merchandise",
        "general"
    ],
    "wof:name":"Reliable Imaging Sales & Svc",
    "wof:placetype":"venue"
},
  "geometry": {"coordinates":[-84.317033,39.901335],"type":"Point"}
}