{
  "type": "Feature",
  "properties": {
    "iso:country":"US",
    "sg:address":"11 E Washington St",
    "sg:city":"Athens",
    "sg:classifiers":[
        {
            "category":"Banks & Credit Unions",
            "subcategory":"Investment Brokerage",
            "type":"Services"
        }
    ],
    "sg:phone":"+1 740 594 5079",
    "sg:postcode":"45701",
    "sg:province":"OH",
    "sg:tags":[
        "security"
    ],
    "wof:name":"Edward Jones Investments",
    "wof:placetype":"venue"
},
  "geometry": {"coordinates":[-82.101069,39.329104],"type":"Point"}
}