{
  "type": "Feature",
  "properties": {
    "iso:country":"US",
    "sg:address":"102 W High St",
    "sg:city":"Springfield",
    "sg:classifiers":[
        {
            "category":"Organizations",
            "subcategory":"Religious Organization",
            "type":"Services"
        }
    ],
    "sg:phone":"+1 937 323 7597",
    "sg:postcode":"45502",
    "sg:province":"OH",
    "sg:tags":[
        "church"
    ],
    "wof:name":"Central United Methodist Chr",
    "wof:placetype":"venue"
},
  "geometry": {"coordinates":[-83.814362,39.923635],"type":"Point"}
}