{
  "type": "Feature",
  "properties": {
    "addr:full":"6740 Huntley Rd Columbus OH 43229",
    "addr:postcode":"6740;43229",
    "addr:street":"Huntley Rd",
    "iso:country":"US",
    "sg:address":"6740 Huntley Rd",
    "sg:city":"Columbus",
    "sg:classifiers":[
        {
            "category":"Health Services",
            "subcategory":"Medical Lab",
            "type":"Services"
        }
    ],
    "sg:phone":"+1 614 888 8378",
    "sg:postcode":"43229",
    "sg:province":"OH",
    "sg:tags":[
        "detection",
        "equipment",
        "drug"
    ],
    "wof:name":"On Site",
    "wof:placetype":"venue"
},
  "geometry": {"coordinates":[-82.998479,40.103729],"type":"Point"}
}