{
  "type": "Feature",
  "properties": {
    "addr:full": "25975 Emery Rd Cleveland OH 44128",
    "addr:housenumber": "25975",
    "addr:postcode": "44128",
    "addr:street": "Emery Rd",
    "iso:country": "US",
    "sg:address": "25975 Emery Rd",
    "sg:city": "Cleveland",
    "sg:classifiers": [
      {
        "category": "Wholesale",
        "subcategory": "Hardware",
        "type": "Manufacturing \u0026 Wholesale Goods"
      }
    ],
    "sg:phone": "+1 216 378 9088",
    "sg:postcode": "44128",
    "sg:province": "OH",
    "sg:tags": [
      "nut",
      "bolt"
    ],
    "wof:name": "Circle Bolt \u0026 Nut Co",
    "wof:placetype": "venue"
  },
  "geometry": {"coordinates":[-81.495454,41.435183],"type":"Point"}
}
