{
  "type": "Feature",
  "properties": {
    "addr:full": "2419 Vendome Dr Columbus OH 43219",
    "addr:housenumber": "2419",
    "addr:postcode": "43219",
    "addr:street": "Vendome Dr",
    "iso:country": "US",
    "sg:address": "2419 Vendome Dr",
    "sg:city": "Columbus",
    "sg:classifiers": [
      {
        "category": "Freight",
        "type": "Transportation"
      }
    ],
    "sg:phone": "+1 614 252 7242",
    "sg:postcode": "43219",
    "sg:province": "OH",
    "sg:tags": [
      "operator",
      "local",
      "trucking"
    ],
    "wof:name": "C/K Trucking Co",
    "wof:placetype": "venue"
  },
  "geometry": {"coordinates":[-82.939679,40.00219],"type":"Point"}
}
