{
  "type": "Feature",
  "properties": {
    "addr:full": "1133 N Ottokee St Wauseon OH 43567",
    "addr:housenumber": "1133",
    "addr:postcode": "43567",
    "addr:street": "N Ottokee St",
    "iso:country": "US",
    "sg:address": "1133 N Ottokee St",
    "sg:city": "Wauseon",
    "sg:classifiers": [
      {
        "category": "Organizations",
        "subcategory": "Community Association",
        "type": "Services"
      }
    ],
    "sg:phone": "+1 419 335 1301",
    "sg:postcode": "43567",
    "sg:province": "OH",
    "wof:name": "V F W Post 7424",
    "wof:placetype": "venue"
  },
  "geometry": {"coordinates":[-84.146966,41.563254],"type":"Point"}
}
