{
  "type": "Feature",
  "properties": {
    "iso:country":"US",
    "sg:address":"7350 Foust Rd",
    "sg:city":"Columbus Grove",
    "sg:phone":"+1 419 643 2045",
    "sg:postcode":"45830",
    "sg:province":"OH",
    "sg:tags":[
        "farm",
        "repair",
        "corn",
        "wheat",
        "soybean"
    ],
    "wof:name":"Kiene Farm Repair",
    "wof:placetype":"venue"
},
  "geometry": {"coordinates":[-83.98539,40.843819],"type":"Point"}
}