{
  "type": "Feature",
  "properties": {
    "iso:country":"US",
    "sg:address":"2509 W Sylvania Ave",
    "sg:city":"Toledo",
    "sg:classifiers":[
        {
            "category":"Professional",
            "subcategory":"Accounting & Tax Preparation",
            "type":"Services"
        }
    ],
    "sg:phone":"+1 419 475 3020",
    "sg:postcode":"43613",
    "sg:province":"OH",
    "sg:tags":[
        "accountant"
    ],
    "wof:name":"Arthur Allen CPA",
    "wof:placetype":"venue"
},
  "geometry": {"coordinates":[-83.606317,41.692034],"type":"Point"}
}