{
  "type": "Feature",
  "properties": {
    "iso:country":"US",
    "sg:address":"3115 Center Rd",
    "sg:city":"Brunswick",
    "sg:classifiers":[
        {
            "category":"Restaurant",
            "type":"Food & Drink"
        }
    ],
    "sg:menulink":"http://www.allmenus.com/oh/brunswick/195169-mcdonalds/menu/",
    "sg:postcode":"44212",
    "sg:province":"OH",
    "sg:tags":[
        "burger",
        "american"
    ],
    "wof:name":"McDonald's",
    "wof:placetype":"venue"
},
  "geometry": {"coordinates":[-81.80274300000001,41.238322],"type":"Point"}
}