{
  "type": "Feature",
  "properties": {
    "addr:full": "3115 Center Rd Brunswick OH 44212",
    "addr:housenumber": "3115",
    "addr:postcode": "44212",
    "addr:street": "Center Rd",
    "iso:country": "US",
    "sg:address": "3115 Center Rd",
    "sg:city": "Brunswick",
    "sg:classifiers": [
      {
        "category": "Restaurant",
        "type": "Food \u0026 Drink"
      }
    ],
    "sg:menulink": "http://www.allmenus.com/oh/brunswick/195169-mcdonalds/menu/",
    "sg:postcode": "44212",
    "sg:province": "OH",
    "sg:tags": [
      "burger",
      "american"
    ],
    "wof:name": "McDonald's",
    "wof:placetype": "venue"
  },
  "geometry": {"coordinates":[-81.802743,41.238322],"type":"Point"}
}
