{
  "type": "Feature",
  "properties": {
    "iso:country":"US",
    "sg:address":"6845 German Rd",
    "sg:city":"Crestline",
    "sg:classifiers":[
        {
            "category":"Organizations",
            "subcategory":"Labor Organization",
            "type":"Services"
        }
    ],
    "sg:phone":"+1 419 683 0515",
    "sg:postcode":"44827",
    "sg:province":"OH",
    "wof:name":"Brotherhood Railroad Signalmen",
    "wof:placetype":"venue"
},
  "geometry": {"coordinates":[-82.78525500000001,40.850274],"type":"Point"}
}