{
  "type": "Feature",
  "properties": {
    "addr:full": "42 S Main St Utica OH 43080",
    "addr:housenumber": "42",
    "addr:postcode": "43080",
    "addr:street": "S Main St",
    "iso:country": "US",
    "sg:address": "42 S Main St",
    "sg:city": "Utica",
    "sg:classifiers": [
      {
        "category": "Home \u0026 Garden",
        "subcategory": "Carpets \u0026 Floor Coverings",
        "type": "Retail Goods"
      }
    ],
    "sg:phone": "+1 740 892 3643",
    "sg:postcode": "43080",
    "sg:province": "OH",
    "sg:tags": [
      "dealer",
      "rug"
    ],
    "wof:name": "Tri Phase Floor Coverings",
    "wof:placetype": "venue"
  },
  "geometry": {"coordinates":[-82.452647,40.233611],"type":"Point"}
}
