{
  "type": "Feature",
  "properties": {
    "addr:full": "1138 N Main St Bellefontaine OH 43311",
    "addr:housenumber": "1138",
    "addr:postcode": "43311",
    "addr:street": "N Main St",
    "iso:country": "US",
    "sg:address": "1138 N Main St",
    "sg:city": "Bellefontaine",
    "sg:classifiers": [
      {
        "category": "Autos \u0026 Motor Vehicles",
        "subcategory": "Fuel \u0026 Gas Station",
        "type": "Retail Goods"
      }
    ],
    "sg:phone": "+1 937 599 1524",
    "sg:postcode": "43311",
    "sg:province": "OH",
    "sg:tags": [
      "grocery",
      "station",
      "gasoline"
    ],
    "wof:name": "Shell Food Mart",
    "wof:placetype": "venue"
  },
  "geometry": {"coordinates":[-83.755482,40.378584],"type":"Point"}
}
