{
  "type": "Feature",
  "properties": {
    "addr:full":"729 Lincoln Way E Massillon OH 44646",
    "addr:housenumber":"729",
    "addr:postcode":"44646",
    "addr:street":"Lincoln Way E",
    "iso:country":"US",
    "sg:address":"729 Lincoln Way E",
    "sg:city":"Massillon",
    "sg:classifiers":[
        {
            "category":"Banks & Credit Unions",
            "subcategory":"Bank",
            "type":"Services"
        }
    ],
    "sg:phone":"+1 330 832 9900",
    "sg:postcode":"44646",
    "sg:province":"OH",
    "sg:tags":[
        "broker",
        "mortgage"
    ],
    "wof:name":"All American Home Lending Inc",
    "wof:placetype":"venue"
},
  "geometry": {"coordinates":[-81.514042,40.798977],"type":"Point"}
}