{
  "type": "Feature",
  "properties": {
    "addr:full": "25000 Euclid Ave Cleveland OH 44117",
    "addr:housenumber": "25000",
    "addr:postcode": "44117",
    "addr:street": "Euclid Ave",
    "iso:country": "US",
    "sg:address": "25000 Euclid Ave",
    "sg:city": "Cleveland",
    "sg:classifiers": [
      {
        "category": "Professional",
        "subcategory": "Management \u0026 Consulting",
        "type": "Services"
      }
    ],
    "sg:phone": "+1 216 261 3337",
    "sg:postcode": "44117",
    "sg:province": "OH",
    "sg:tags": [
      "consultant",
      "business"
    ],
    "wof:name": "Envision Enterprises",
    "wof:placetype": "venue"
  },
  "geometry": {"coordinates":[-81.507516,41.583934],"type":"Point"}
}
