{
  "type": "Feature",
  "properties": {
    "iso:country":"US",
    "sg:address":"5714 Wilson Ave",
    "sg:city":"Portsmouth",
    "sg:classifiers":[
        {
            "category":"Building & Trades",
            "subcategory":"Construction",
            "type":"Services"
        }
    ],
    "sg:phone":"+1 740 776 2111",
    "sg:postcode":"45662",
    "sg:province":"OH",
    "sg:tags":[
        "general",
        "contractor"
    ],
    "wof:name":"Danny Yates",
    "wof:placetype":"venue"
},
  "geometry": {"coordinates":[-82.88865300000001,38.763068],"type":"Point"}
}