{
  "type": "Feature",
  "properties": {
    "addr:full": "5714 Wilson Ave Portsmouth OH 45662",
    "addr:housenumber": "5714",
    "addr:postcode": "45662",
    "addr:street": "Wilson Ave",
    "iso:country": "US",
    "sg:address": "5714 Wilson Ave",
    "sg:city": "Portsmouth",
    "sg:classifiers": [
      {
        "category": "Building \u0026 Trades",
        "subcategory": "Construction",
        "type": "Services"
      }
    ],
    "sg:phone": "+1 740 776 2111",
    "sg:postcode": "45662",
    "sg:province": "OH",
    "sg:tags": [
      "general",
      "contractor"
    ],
    "wof:name": "Danny Yates",
    "wof:placetype": "venue"
  },
  "geometry": {"coordinates":[-82.888653,38.763068],"type":"Point"}
}
