{
  "type": "Feature",
  "properties": {
    "iso:country":"US",
    "sg:address":"580 Walnut St",
    "sg:city":"Cincinnati",
    "sg:classifiers":[
        {
            "category":"Food & Beverages",
            "subcategory":"Groceries & Convenience Stores",
            "type":"Retail Goods"
        }
    ],
    "sg:phone":"+1 513 287 8659",
    "sg:postcode":"45202",
    "sg:province":"OH",
    "sg:tags":[
        "cards",
        "independent",
        "gift"
    ],
    "wof:name":"Straus 19",
    "wof:placetype":"venue"
},
  "geometry": {"coordinates":[-84.511525,39.10221],"type":"Point"}
}