{
  "type": "Feature",
  "properties": {
    "addr:full": "1645 Biers Run Rd Chillicothe OH 45601",
    "addr:housenumber": "1645",
    "addr:postcode": "45601",
    "addr:street": "Biers Run Rd",
    "iso:country": "US",
    "sg:address": "1645 Biers Run Rd",
    "sg:city": "Chillicothe",
    "sg:classifiers": [
      {
        "category": "Farming",
        "subcategory": "Farm",
        "type": "Manufacturing \u0026 Wholesale Goods"
      }
    ],
    "sg:phone": "+1 740 998 6339",
    "sg:postcode": "45601",
    "sg:province": "OH",
    "sg:tags": [
      "crop",
      "general"
    ],
    "wof:name": "Fore Star Farm",
    "wof:placetype": "venue"
  },
  "geometry": {"coordinates":[-83.111532,39.410412],"type":"Point"}
}
