{
  "type": "Feature",
  "properties": {
    "iso:country":"US",
    "sg:address":"917 E Lincoln Way",
    "sg:city":"Minerva",
    "sg:classifiers":[
        {
            "category":"Sports & Exercise",
            "subcategory":"Bowling",
            "type":"Entertainment"
        }
    ],
    "sg:phone":"+1 330 868 5210",
    "sg:postcode":"44657",
    "sg:province":"OH",
    "sg:tags":[
        "alley"
    ],
    "wof:name":"Minerva Bowl",
    "wof:placetype":"venue"
},
  "geometry": {"coordinates":[-81.090024,40.736944],"type":"Point"}
}