{
  "type": "Feature",
  "properties": {
    "iso:country":"US",
    "sg:address":"1146 Prospect Ave S",
    "sg:city":"Hartville",
    "sg:classifiers":[
        {
            "category":"Real Estate",
            "subcategory":"Real Estate Agent",
            "type":"Services"
        }
    ],
    "sg:phone":"+1 330 877 9151",
    "sg:postcode":"44632",
    "sg:province":"OH",
    "wof:name":"Realty Media Inc",
    "wof:placetype":"venue"
},
  "geometry": {"coordinates":[-81.33429,40.94903],"type":"Point"}
}