{
  "type": "Feature",
  "properties": {
    "addr:full":"2264 S Hamilton Rd Columbus OH 43232",
    "addr:housenumber":"2264",
    "addr:postcode":"43232",
    "addr:street":"S Hamilton Rd",
    "iso:country":"US",
    "sg:address":"2264 S Hamilton Rd",
    "sg:city":"Columbus",
    "sg:classifiers":[
        {
            "category":"Shopping",
            "subcategory":"Shoes",
            "type":"Retail Goods"
        }
    ],
    "sg:phone":"+1 614 888 2668",
    "sg:postcode":"43232",
    "sg:province":"OH",
    "sg:tags":[
        "footwear"
    ],
    "wof:name":"Z Z Boots",
    "wof:placetype":"venue"
},
  "geometry": {"coordinates":[-82.879221,39.929907],"type":"Point"}
}