{
  "type": "Feature",
  "properties": {
    "addr:full": "5230 Bethel Center Mall Columbus OH 43220",
    "addr:housenumber": "5230",
    "addr:postcode": "43220",
    "addr:street": "Bethel Center Mall",
    "iso:country": "US",
    "sg:address": "5230 Bethel Center Mall",
    "sg:city": "Columbus",
    "sg:classifiers": [
      {
        "category": "Wholesale",
        "subcategory": "Drugs",
        "type": "Manufacturing \u0026 Wholesale Goods"
      }
    ],
    "sg:phone": "+1 614 457 2912",
    "sg:postcode": "43220",
    "sg:province": "OH",
    "sg:tags": [
      "broker"
    ],
    "wof:name": "Canada Drug Svc",
    "wof:placetype": "venue"
  },
  "geometry": {"coordinates":[-83.058168,40.064129],"type":"Point"}
}
