{
  "type": "Feature",
  "properties": {
    "iso:country":"US",
    "sg:address":"5230 Bethel Center Mall",
    "sg:city":"Columbus",
    "sg:classifiers":[
        {
            "category":"Wholesale",
            "subcategory":"Drugs",
            "type":"Manufacturing & Wholesale Goods"
        }
    ],
    "sg:phone":"+1 614 457 2912",
    "sg:postcode":"43220",
    "sg:province":"OH",
    "sg:tags":[
        "broker"
    ],
    "wof:name":"Canada Drug Svc",
    "wof:placetype":"venue"
},
  "geometry": {"coordinates":[-83.05816799999999,40.064129],"type":"Point"}
}