{
  "type": "Feature",
  "properties": {
    "addr:full": "3385 US Hwy 6 Fremont OH 43420",
    "addr:housenumber": "3385",
    "addr:postcode": "43420",
    "addr:street": "Us Hwy 6",
    "iso:country": "US",
    "sg:address": "3385 US Hwy 6",
    "sg:city": "Fremont",
    "sg:classifiers": [
      {
        "category": "Home \u0026 Garden",
        "subcategory": "Garden Supply",
        "type": "Retail Goods"
      }
    ],
    "sg:phone": "+1 419 547 8149",
    "sg:postcode": "43420",
    "sg:province": "OH",
    "sg:tags": [
      "equipment"
    ],
    "wof:name": "Action Power Sales \u0026 Service",
    "wof:placetype": "venue"
  },
  "geometry": {"coordinates":[-83.170129,41.34199],"type":"Point"}
}
