{
  "type": "Feature",
  "properties": {
    "iso:country":"US",
    "sg:address":"1150 Harrison Ave",
    "sg:city":"Harrison",
    "sg:classifiers":[
        {
            "category":"Banks & Credit Unions",
            "subcategory":"Bank",
            "type":"Services"
        }
    ],
    "sg:phone":"+1 513 202 1777",
    "sg:postcode":"45030",
    "sg:province":"IN",
    "sg:tags":[
        "loan",
        "broker"
    ],
    "wof:name":"Foundation Financial Group",
    "wof:placetype":"venue"
},
  "geometry": {"coordinates":[-84.808835,39.260836],"type":"Point"}
}