{
  "type": "Feature",
  "properties": {
    "addr:full": "314 N Columbus St Lancaster OH 43130",
    "addr:housenumber": "314",
    "addr:postcode": "43130",
    "addr:street": "N Columbus St",
    "iso:country": "US",
    "sg:address": "314 N Columbus St",
    "sg:city": "Lancaster",
    "sg:classifiers": [
      {
        "category": "Professional",
        "subcategory": "Art Services",
        "type": "Services"
      }
    ],
    "sg:phone": "+1 740 654 5000",
    "sg:postcode": "43130",
    "sg:province": "OH",
    "sg:tags": [
      "graphic",
      "designer"
    ],
    "wof:name": "Astrografics LTD",
    "wof:placetype": "venue"
  },
  "geometry": {"coordinates":[-82.604376,39.716723],"type":"Point"}
}
