{
  "type": "Feature",
  "properties": {
    "addr:full": "4761 Industry Dr Fairfield OH 45014",
    "addr:housenumber": "4761",
    "addr:postcode": "45014",
    "addr:street": "Industry Dr",
    "iso:country": "US",
    "sg:address": "4761 Industry Dr",
    "sg:city": "Fairfield",
    "sg:classifiers": [
      {
        "category": "Building \u0026 Trades",
        "subcategory": "Cleaning \u0026 Sanitation",
        "type": "Services"
      }
    ],
    "sg:phone": "+1 513 939 3143",
    "sg:postcode": "45014",
    "sg:province": "OH",
    "wof:name": "Kings Kare Inc",
    "wof:placetype": "venue"
  },
  "geometry": {"coordinates":[-84.533295,39.3437],"type":"Point"}
}
