{
  "type": "Feature",
  "properties": {
    "addr:full":"5717 Bridgetown Rd Cincinnati OH 45248",
    "addr:housenumber":"5717",
    "addr:postcode":"45248",
    "addr:street":"Bridgetown Rd",
    "iso:country":"US",
    "sg:address":"5717 Bridgetown Rd",
    "sg:city":"Cincinnati",
    "sg:classifiers":[
        {
            "category":"Retail",
            "subcategory":"Repair Shop",
            "type":"Services"
        }
    ],
    "sg:phone":"+1 513 574 7639",
    "sg:postcode":"45248",
    "sg:province":"OH",
    "sg:tags":[
        "appliance"
    ],
    "wof:name":"Ralph Adams Appliance Svc",
    "wof:placetype":"venue"
},
  "geometry": {"coordinates":[-84.637603,39.159436],"type":"Point"}
}