{
  "type": "Feature",
  "properties": {
    "addr:full":"288 Canton Rd Wintersville OH 43953",
    "addr:housenumber":"288",
    "addr:postcode":"43953",
    "addr:street":"Canton Rd",
    "iso:country":"US",
    "sg:address":"288 Canton Rd",
    "sg:city":"Wintersville",
    "sg:classifiers":[
        {
            "category":"Shopping",
            "subcategory":"Department Store",
            "type":"Retail Goods"
        }
    ],
    "sg:phone":"+1 740 264 7090",
    "sg:postcode":"43953",
    "sg:province":"OH",
    "wof:name":"Dollar General",
    "wof:placetype":"venue"
},
  "geometry": {"coordinates":[-80.707913,40.380827],"type":"Point"}
}