{
  "type": "Feature",
  "properties": {
    "addr:full":"1295 N Martin Williston Rd Genoa OH 43430",
    "addr:housenumber":"1295",
    "addr:postcode":"43430",
    "addr:street":"N Martin Williston Rd",
    "iso:country":"US",
    "sg:address":"1295 N Martin Williston Rd",
    "sg:city":"Genoa",
    "sg:classifiers":[
        {
            "category":"Freight",
            "type":"Transportation"
        }
    ],
    "sg:phone":"+1 419 855 4484",
    "sg:postcode":"43430",
    "sg:province":"OH",
    "sg:tags":[
        "operator",
        "local",
        "trucking"
    ],
    "wof:name":"Twd Trucking",
    "wof:placetype":"venue"
},
  "geometry": {"coordinates":[-83.339217,41.53235],"type":"Point"}
}