{
  "type": "Feature",
  "properties": {
    "iso:country":"US",
    "sg:address":"12525 Airport Hwy",
    "sg:city":"Swanton",
    "sg:classifiers":[
        {
            "category":"Retail",
            "subcategory":"Auto Repair",
            "type":"Services"
        }
    ],
    "sg:phone":"+1 419 825 5655",
    "sg:postcode":"43558",
    "sg:province":"OH",
    "sg:tags":[
        "body",
        "shop",
        "travel",
        "trailer"
    ],
    "wof:name":"Walters Travel Trailers",
    "wof:placetype":"venue"
},
  "geometry": {"coordinates":[-83.846863,41.58354],"type":"Point"}
}