{
  "type": "Feature",
  "properties": {
    "iso:country":"US",
    "sg:address":"214 S Main St",
    "sg:city":"Findlay",
    "sg:classifiers":[
        {
            "category":"Home & Garden",
            "subcategory":"Household Appliances",
            "type":"Retail Goods"
        }
    ],
    "sg:phone":"+1 419 422 6954",
    "sg:postcode":"45840",
    "sg:province":"OH",
    "wof:name":"Bindels Appliance LLC",
    "wof:placetype":"venue"
},
  "geometry": {"coordinates":[-83.650301,41.039774],"type":"Point"}
}