{
  "type": "Feature",
  "properties": {
    "addr:full": "214 S Main St Findlay OH 45840",
    "addr:housenumber": "214",
    "addr:postcode": "45840",
    "addr:street": "S Main St",
    "iso:country": "US",
    "sg:address": "214 S Main St",
    "sg:city": "Findlay",
    "sg:classifiers": [
      {
        "category": "Home \u0026 Garden",
        "subcategory": "Household Appliances",
        "type": "Retail Goods"
      }
    ],
    "sg:phone": "+1 419 422 6954",
    "sg:postcode": "45840",
    "sg:province": "OH",
    "wof:name": "Bindels Appliance LLC",
    "wof:placetype": "venue"
  },
  "geometry": {"coordinates":[-83.650301,41.039774],"type":"Point"}
}
