{
  "type": "Feature",
  "properties": {
    "iso:country":"US",
    "sg:address":"440 E 3rd St",
    "sg:city":"Dover",
    "sg:classifiers":[
        {
            "category":"Professional",
            "subcategory":"Engineering",
            "type":"Services"
        }
    ],
    "sg:phone":"+1 330 343 6120",
    "sg:postcode":"44622",
    "sg:province":"OH",
    "sg:tags":[
        "engineer"
    ],
    "wof:name":"Michael T Perkowski PE",
    "wof:placetype":"venue"
},
  "geometry": {"coordinates":[-81.470935,40.526468],"type":"Point"}
}