{
  "type": "Feature",
  "properties": {
    "iso:country":"US",
    "sg:address":"7805 W Ridgewood Dr",
    "sg:city":"Cleveland",
    "sg:classifiers":[
        {
            "category":"Personal",
            "subcategory":"Beauty Salon",
            "type":"Services"
        }
    ],
    "sg:phone":"+1 440 843 9100",
    "sg:postcode":"44129",
    "sg:province":"OH",
    "sg:tags":[
        "shop"
    ],
    "wof:name":"Hair By Maxelles Inc",
    "wof:placetype":"venue"
},
  "geometry": {"coordinates":[-81.739936,41.384452],"type":"Point"}
}