{
  "type": "Feature",
  "properties": {
    "addr:full":"3344 Central Pkwy Cincinnati OH 45225",
    "addr:housenumber":"3344",
    "addr:postcode":"45225",
    "addr:street":"Central Pkwy",
    "iso:country":"US",
    "sg:address":"3344 Central Pkwy",
    "sg:city":"Cincinnati",
    "sg:classifiers":[
        {
            "category":"Wholesale",
            "subcategory":"Machinery & Supplies",
            "type":"Manufacturing & Wholesale Goods"
        }
    ],
    "sg:phone":"+1 513 559 1345",
    "sg:postcode":"45225",
    "sg:province":"OH",
    "sg:tags":[
        "casket"
    ],
    "wof:name":"United Casket",
    "wof:placetype":"venue"
},
  "geometry": {"coordinates":[-84.532026,39.142063],"type":"Point"}
}