{
  "type": "Feature",
  "properties": {
    "addr:full":"1206 N Main St Canton OH 44720",
    "addr:housenumber":"1206",
    "addr:postcode":"44720",
    "addr:street":"N Main St",
    "iso:country":"US",
    "sg:address":"1206 N Main St",
    "sg:city":"Canton",
    "sg:classifiers":[
        {
            "category":"Insurance",
            "subcategory":"Insurance Agent",
            "type":"Services"
        }
    ],
    "sg:phone":"+1 330 497 8800",
    "sg:postcode":"44720",
    "sg:province":"OH",
    "wof:name":"Allstate",
    "wof:placetype":"venue"
},
  "geometry": {"coordinates":[-81.405603,40.889475],"type":"Point"}
}