{
  "type": "Feature",
  "properties": {
    "iso:country":"US",
    "sg:address":"2400 Interstate Cir",
    "sg:city":"Mansfield",
    "sg:classifiers":[
        {
            "category":"Restaurant",
            "type":"Food & Drink"
        }
    ],
    "sg:phone":"+1 419 756 2022",
    "sg:postcode":"44903",
    "sg:province":"OH",
    "sg:tags":[
        "eating"
    ],
    "wof:name":"Joes Restaurant",
    "wof:placetype":"venue"
},
  "geometry": {"coordinates":[-82.514291,40.694902],"type":"Point"}
}