{
  "type": "Feature",
  "properties": {
    "iso:country":"US",
    "sg:address":"3650 W National Rd",
    "sg:city":"Springfield",
    "sg:classifiers":[
        {
            "category":"Government",
            "subcategory":"Fire Station",
            "type":"Public Place"
        }
    ],
    "sg:phone":"+1 937 322 8507",
    "sg:postcode":"45504",
    "sg:province":"OH",
    "sg:tags":[
        "department",
        "volunteer"
    ],
    "wof:name":"Springfield Twnsp Fire Dept 3",
    "wof:placetype":"venue"
},
  "geometry": {"coordinates":[-83.87804199999999,39.92576],"type":"Point"}
}