{
  "type": "Feature",
  "properties": {
    "iso:country":"US",
    "sg:address":"2501 E 61st St",
    "sg:city":"Cleveland",
    "sg:classifiers":[
        {
            "category":"Education",
            "subcategory":"School",
            "type":"Public Place"
        }
    ],
    "sg:phone":"+1 216 361 0708",
    "sg:postcode":"44104",
    "sg:province":"OH",
    "wof:name":"Dike Montessori School",
    "wof:placetype":"venue"
},
  "geometry": {"coordinates":[-81.647937,41.490762],"type":"Point"}
}