{
  "type": "Feature",
  "properties": {
    "addr:full": "7965 Washington Wood Dr Dayton OH 45459",
    "addr:housenumber": "7965",
    "addr:postcode": "45459",
    "addr:street": "Washington Wood Dr",
    "iso:country": "US",
    "sg:address": "7965 Washington Wood Dr",
    "sg:city": "Dayton",
    "sg:classifiers": [
      {
        "category": "Professional",
        "subcategory": "Lawyer \u0026 Legal Services",
        "type": "Services"
      }
    ],
    "sg:phone": "+1 937 439 1177",
    "sg:postcode": "45459",
    "sg:province": "OH",
    "sg:tags": [
      "attorney"
    ],
    "wof:name": "William K James",
    "wof:placetype": "venue"
  },
  "geometry": {"coordinates":[-84.179279,39.629874],"type":"Point"}
}
