{
  "type": "Feature",
  "properties": {
    "addr:full": "14701 Detroit Ave Cleveland OH 44107",
    "addr:housenumber": "14701",
    "addr:postcode": "44107",
    "addr:street": "Detroit Ave",
    "iso:country": "US",
    "sg:address": "14701 Detroit Ave",
    "sg:city": "Cleveland",
    "sg:classifiers": [
      {
        "category": "Professional",
        "type": "Services"
      }
    ],
    "sg:phone": "+1 216 228 6633",
    "sg:postcode": "44107",
    "sg:province": "OH",
    "sg:tags": [
      "establishment"
    ],
    "wof:name": "Farley Lester Intl",
    "wof:placetype": "venue"
  },
  "geometry": {"coordinates":[-81.7995,41.485115],"type":"Point"}
}
