{
  "type": "Feature",
  "properties": {
    "addr:full": "8540 Twp Rd 308 Millersburg OH 44654",
    "addr:postcode": "8540;44654",
    "addr:street": "Twp Rd 308",
    "iso:country": "US",
    "sg:address": "8540 Twp Rd 308",
    "sg:city": "Millersburg",
    "sg:classifiers": [
      {
        "category": "Banks \u0026 Credit Unions",
        "subcategory": "Bank",
        "type": "Services"
      }
    ],
    "sg:phone": "+1 330 674 7816",
    "sg:postcode": "44654",
    "sg:province": "OH",
    "wof:name": "West Holmes School Empl Cu Inc",
    "wof:placetype": "venue"
  },
  "geometry": {"coordinates":[-81.932503,40.543258],"type":"Point"}
}
