{
  "type": "Feature",
  "properties": {
    "addr:full": "12024 Brown Moder Rd Marysville OH 43040",
    "addr:housenumber": "12024",
    "addr:postcode": "43040",
    "addr:street": "Brown Moder Rd",
    "iso:country": "US",
    "sg:address": "12024 Brown Moder Rd",
    "sg:city": "Marysville",
    "sg:classifiers": [
      {
        "category": "Banks \u0026 Credit Unions",
        "subcategory": "Financial Services",
        "type": "Services"
      }
    ],
    "sg:phone": "+1 937 642 4174",
    "sg:postcode": "43040",
    "sg:province": "OH",
    "sg:tags": [
      "trust",
      "management"
    ],
    "wof:name": "Brown Family Trust",
    "wof:placetype": "venue"
  },
  "geometry": {"coordinates":[-83.321428,40.181443],"type":"Point"}
}
