{
  "type": "Feature",
  "properties": {
    "addr:full": "10 W 2nd St Dayton OH 45402",
    "addr:housenumber": "10",
    "addr:postcode": "45402",
    "addr:street": "W 2Nd St",
    "iso:country": "US",
    "sg:address": "10 W 2nd St",
    "sg:city": "Dayton",
    "sg:classifiers": [
      {
        "category": "Real Estate",
        "subcategory": "Architect",
        "type": "Services"
      }
    ],
    "sg:phone": "+1 937 223 6500",
    "sg:postcode": "45402",
    "sg:province": "OH",
    "sg:website": "www.lorenzwilliams.com",
    "wof:name": "Lorenz \u0026 Williams Inc",
    "wof:placetype": "venue"
  },
  "geometry": {"coordinates":[-84.193857,39.7606],"type":"Point"}
}
