{
  "type": "Feature",
  "properties": {
    "iso:country":"US",
    "sg:address":"10 W 2nd St",
    "sg:city":"Dayton",
    "sg:classifiers":[
        {
            "category":"Real Estate",
            "subcategory":"Architect",
            "type":"Services"
        }
    ],
    "sg:phone":"+1 937 223 6500",
    "sg:postcode":"45402",
    "sg:province":"OH",
    "sg:website":"www.lorenzwilliams.com",
    "wof:name":"Lorenz & Williams Inc",
    "wof:placetype":"venue"
},
  "geometry": {"coordinates":[-84.19385699999999,39.7606],"type":"Point"}
}