{
  "type": "Feature",
  "properties": {
    "iso:country":"US",
    "sg:address":"1959 Harmon Ave",
    "sg:city":"Columbus",
    "sg:classifiers":[
        {
            "category":"Retail",
            "subcategory":"Auto Repair",
            "type":"Services"
        }
    ],
    "sg:phone":"+1 614 449 8009",
    "sg:postcode":"43223",
    "sg:province":"OH",
    "sg:tags":[
        "repairing",
        "automobile",
        "body",
        "painting"
    ],
    "wof:name":"Charlie's Body Shop",
    "wof:placetype":"venue"
},
  "geometry": {"coordinates":[-83.016221,39.920676],"type":"Point"}
}