{
  "type": "Feature",
  "properties": {
    "addr:full":"13940 Navarre Rd SW Beach City OH 44608",
    "addr:housenumber":"13940",
    "addr:postcode":"44608",
    "addr:street":"Navarre Rd Sw",
    "iso:country":"US",
    "sg:address":"13940 Navarre Rd SW",
    "sg:city":"Beach City",
    "sg:classifiers":[
        {
            "category":"Freight",
            "type":"Transportation"
        }
    ],
    "sg:phone":"+1 330 359 5271",
    "sg:postcode":"44608",
    "sg:province":"OH",
    "sg:tags":[
        "operator",
        "local",
        "trucking"
    ],
    "wof:name":"Vern Shetler Trucking Ltd",
    "wof:placetype":"venue"
},
  "geometry": {"coordinates":[-81.63019799999999,40.658353],"type":"Point"}
}