{
  "type": "Feature",
  "properties": {
    "addr:full": "893 N High St Worthington OH 43085",
    "addr:housenumber": "893",
    "addr:postcode": "43085",
    "addr:street": "N High St",
    "iso:country": "US",
    "sg:address": "893 N High St",
    "sg:city": "Worthington",
    "sg:classifiers": [
      {
        "category": "Professional",
        "subcategory": "Computer Services",
        "type": "Services"
      }
    ],
    "sg:phone": "+1 614 846 1689",
    "sg:postcode": "43085",
    "sg:province": "OH",
    "wof:name": "PC Guys Consulting Svc",
    "wof:placetype": "venue"
  },
  "geometry": {"coordinates":[-83.017941,40.092374],"type":"Point"}
}
