{
  "type": "Feature",
  "properties": {
    "iso:country":"US",
    "sg:address":"14220 Southard Rd",
    "sg:city":"Marysville",
    "sg:classifiers":[
        {
            "category":"Building & Trades",
            "subcategory":"Construction",
            "type":"Services"
        }
    ],
    "sg:phone":"+1 937 644 9873",
    "sg:postcode":"43040",
    "sg:province":"OH",
    "sg:tags":[
        "house"
    ],
    "wof:name":"Humble & Sons Drywall",
    "wof:placetype":"venue"
},
  "geometry": {"coordinates":[-83.394786,40.206857],"type":"Point"}
}