{
  "type": "Feature",
  "properties": {
    "iso:country":"US",
    "sg:address":"427 Boardman Poland Rd",
    "sg:city":"Youngstown",
    "sg:classifiers":[
        {
            "category":"Shopping",
            "subcategory":"Stationery & Office Supplies",
            "type":"Retail Goods"
        }
    ],
    "sg:phone":"+1 330 629 2001",
    "sg:postcode":"44512",
    "sg:province":"OH",
    "wof:name":"Office Max",
    "wof:placetype":"venue"
},
  "geometry": {"coordinates":[-80.645709,41.024227],"type":"Point"}
}