{
  "type": "Feature",
  "properties": {
    "addr:full": "13501 Claiborne Rd Cleveland OH 44112",
    "addr:housenumber": "13501",
    "addr:postcode": "44112",
    "addr:street": "Claiborne Rd",
    "iso:country": "US",
    "sg:address": "13501 Claiborne Rd",
    "sg:city": "Cleveland",
    "sg:classifiers": [
      {
        "category": "Shopping",
        "type": "Retail Goods"
      }
    ],
    "sg:phone": "+1 216 761 5121",
    "sg:postcode": "44112",
    "sg:province": "OH",
    "sg:tags": [
      "cosmetic",
      "perfume"
    ],
    "wof:name": "Haya Bath \u0026 Body Novelties",
    "wof:placetype": "venue"
  },
  "geometry": {"coordinates":[-81.588756,41.536422],"type":"Point"}
}
