{
  "type": "Feature",
  "properties": {
    "iso:country":"US",
    "sg:address":"1801 E 9th St",
    "sg:city":"Cleveland",
    "sg:classifiers":[
        {
            "category":"Real Estate",
            "subcategory":"Real Estate Agent",
            "type":"Services"
        }
    ],
    "sg:phone":"+1 216 241 6120",
    "sg:postcode":"44114",
    "sg:province":"OH",
    "wof:name":"C L Pete Smythe",
    "wof:placetype":"venue"
},
  "geometry": {"coordinates":[-81.68791400000001,41.501762],"type":"Point"}
}