{
  "type": "Feature",
  "properties": {
    "iso:country":"US",
    "sg:address":"5 S 5th St",
    "sg:city":"Martins Ferry",
    "sg:classifiers":[
        {
            "category":"Restaurant",
            "type":"Food & Drink"
        }
    ],
    "sg:phone":"+1 740 633 2605",
    "sg:postcode":"43935",
    "sg:province":"OH",
    "wof:name":"Country Gold Inc",
    "wof:placetype":"venue"
},
  "geometry": {"coordinates":[-80.725493,40.096021],"type":"Point"}
}