{
  "type": "Feature",
  "properties": {
    "iso:country":"US",
    "sg:address":"2440 N Dayton Xenia Rd",
    "sg:city":"Dayton",
    "sg:classifiers":[
        {
            "category":"Personal",
            "subcategory":"Beauty Salon",
            "type":"Services"
        }
    ],
    "sg:phone":"+1 937 431 1623",
    "sg:postcode":"45434",
    "sg:province":"OH",
    "wof:name":"Unmi's Beauty Salon",
    "wof:placetype":"venue"
},
  "geometry": {"coordinates":[-84.024632,39.716337],"type":"Point"}
}