{
  "type": "Feature",
  "properties": {
    "addr:full":"3894 State St NW North Canton OH 44720",
    "addr:housenumber":"3894",
    "addr:postcode":"44720",
    "addr:street":"State St Nw",
    "iso:country":"US",
    "sg:address":"3894 State St NW",
    "sg:city":"North Canton",
    "sg:classifiers":[
        {
            "category":"Retail",
            "subcategory":"Auto Repair",
            "type":"Services"
        }
    ],
    "sg:phone":"+1 330 499 8889",
    "sg:postcode":"44720",
    "sg:province":"OH",
    "sg:tags":[
        "repairing",
        "automobile"
    ],
    "wof:name":"Burkhardt's Automotive",
    "wof:placetype":"venue"
},
  "geometry": {"coordinates":[-81.41717199999999,40.928412],"type":"Point"}
}