{
  "type": "Feature",
  "properties": {
    "addr:full": "404 3rd St Marietta OH 45750",
    "addr:housenumber": "404",
    "addr:postcode": "45750",
    "addr:street": "3Rd St",
    "iso:country": "US",
    "sg:address": "404 3rd St",
    "sg:city": "Marietta",
    "sg:classifiers": [
      {
        "category": "Wholesale",
        "subcategory": "Sporting Goods",
        "type": "Manufacturing \u0026 Wholesale Goods"
      }
    ],
    "sg:phone": "+1 740 374 8584",
    "sg:postcode": "45750",
    "sg:province": "OH",
    "wof:name": "Pedal Shop",
    "wof:placetype": "venue"
  },
  "geometry": {"coordinates":[-81.457183,39.420064],"type":"Point"}
}
