{
  "type": "Feature",
  "properties": {
    "iso:country":"US",
    "sg:address":"201 E 4th St",
    "sg:city":"Cincinnati",
    "sg:classifiers":[
        {
            "category":"Professional",
            "subcategory":"Accounting & Tax Preparation",
            "type":"Services"
        }
    ],
    "sg:phone":"+1 513 651 4000",
    "sg:postcode":"45202",
    "sg:province":"OH",
    "sg:tags":[
        "accountant"
    ],
    "wof:name":"Coopers & Lybrand",
    "wof:placetype":"venue"
},
  "geometry": {"coordinates":[-84.508546,39.100561],"type":"Point"}
}