{
  "type": "Feature",
  "properties": {
    "iso:country":"US",
    "sg:address":"1010 W Washington St",
    "sg:city":"Sandusky",
    "sg:classifiers":[
        {
            "category":"Taxi",
            "type":"Transportation"
        }
    ],
    "sg:phone":"+1 419 621 1016",
    "sg:postcode":"44870",
    "sg:province":"OH",
    "sg:tags":[
        "taxicab"
    ],
    "wof:name":"Dependable Shuttle Svc",
    "wof:placetype":"venue"
},
  "geometry": {"coordinates":[-82.71887,41.452213],"type":"Point"}
}