{
  "type": "Feature",
  "properties": {
    "addr:full": "4006 Vermaas Ave Toledo OH 43612",
    "addr:housenumber": "4006",
    "addr:postcode": "43612",
    "addr:street": "Vermaas Ave",
    "iso:country": "US",
    "sg:address": "4006 Vermaas Ave",
    "sg:city": "Toledo",
    "sg:classifiers": [
      {
        "category": "Wholesale",
        "subcategory": "Medical Equipment \u0026 Supplies",
        "type": "Manufacturing \u0026 Wholesale Goods"
      }
    ],
    "sg:phone": "+1 419 478 0099",
    "sg:postcode": "43612",
    "sg:province": "OH",
    "wof:name": "Cousins Medical Supply Inc",
    "wof:placetype": "venue"
  },
  "geometry": {"coordinates":[-83.560205,41.695259],"type":"Point"}
}
