{
  "type": "Feature",
  "properties": {
    "iso:country":"US",
    "sg:address":"4006 Vermaas Ave",
    "sg:city":"Toledo",
    "sg:classifiers":[
        {
            "category":"Wholesale",
            "subcategory":"Medical Equipment & Supplies",
            "type":"Manufacturing & Wholesale Goods"
        }
    ],
    "sg:phone":"+1 419 478 0099",
    "sg:postcode":"43612",
    "sg:province":"OH",
    "wof:name":"Cousins Medical Supply Inc",
    "wof:placetype":"venue"
},
  "geometry": {"coordinates":[-83.560205,41.695259],"type":"Point"}
}