{
  "type": "Feature",
  "properties": {
    "addr:full": "110 Distribution Dr Fairfield OH 45014",
    "addr:housenumber": "110",
    "addr:postcode": "45014",
    "addr:street": "Distribution Dr",
    "iso:country": "US",
    "sg:address": "110 Distribution Dr",
    "sg:city": "Fairfield",
    "sg:classifiers": [
      {
        "category": "Wholesale",
        "subcategory": "Groceries",
        "type": "Manufacturing \u0026 Wholesale Goods"
      },
      {
        "category": "Food \u0026 Beverages",
        "subcategory": "Supermarket",
        "type": "Retail Goods"
      }
    ],
    "sg:phone": "+1 513 881 4560",
    "sg:postcode": "45014",
    "sg:province": "OH",
    "sg:tags": [
      "frozen",
      "super",
      "store",
      "foods-wholesale"
    ],
    "wof:name": "Pierre Foods",
    "wof:placetype": "venue"
  },
  "geometry": {"coordinates":[-84.505086,39.335764],"type":"Point"}
}
