{
  "type": "Feature",
  "properties": {
    "iso:country":"US",
    "sg:address":"110 Distribution Dr",
    "sg:city":"Fairfield",
    "sg:classifiers":[
        {
            "category":"Wholesale",
            "subcategory":"Groceries",
            "type":"Manufacturing & Wholesale Goods"
        },
        {
            "category":"Food & Beverages",
            "subcategory":"Supermarket",
            "type":"Retail Goods"
        }
    ],
    "sg:phone":"+1 513 881 4560",
    "sg:postcode":"45014",
    "sg:province":"OH",
    "sg:tags":[
        "frozen",
        "super",
        "store",
        "foods-wholesale"
    ],
    "wof:name":"Pierre Foods",
    "wof:placetype":"venue"
},
  "geometry": {"coordinates":[-84.50508600000001,39.335764],"type":"Point"}
}