{
  "type": "Feature",
  "properties": {
    "addr:full": "1201 S Houk Rd Delaware OH 43015",
    "addr:housenumber": "1201",
    "addr:postcode": "43015",
    "addr:street": "S Houk Rd",
    "iso:country": "US",
    "sg:address": "1201 S Houk Rd",
    "sg:city": "Delaware",
    "sg:classifiers": [
      {
        "category": "Manufacturing",
        "subcategory": "Metals",
        "type": "Manufacturing \u0026 Wholesale Goods"
      }
    ],
    "sg:phone": "+1 740 362 1035",
    "sg:postcode": "43015",
    "sg:province": "OH",
    "sg:tags": [
      "barrels",
      "drum"
    ],
    "wof:name": "Greif Brothers Corp Research",
    "wof:placetype": "venue"
  },
  "geometry": {"coordinates":[-83.113497,40.286287],"type":"Point"}
}
