{
  "type": "Feature",
  "properties": {
    "addr:full":"101 E High St Oxford IN 45056",
    "addr:housenumber":"101",
    "addr:postcode":"45056",
    "addr:street":"E High St",
    "iso:country":"US",
    "sg:address":"101 E High St",
    "sg:city":"Oxford",
    "sg:classifiers":[
        {
            "category":"Government",
            "subcategory":"Office",
            "type":"Public Place"
        }
    ],
    "sg:phone":"+1 513 524 5202",
    "sg:postcode":"45056",
    "sg:province":"IN",
    "sg:tags":[
        "city",
        "taxation"
    ],
    "wof:name":"Oxford City Finance Dept",
    "wof:placetype":"venue"
},
  "geometry": {"coordinates":[-84.73924,39.510448],"type":"Point"}
}