{
  "type": "Feature",
  "properties": {
    "addr:full": "496 N Orchard Rd NE Bolivar OH 44612",
    "addr:housenumber": "496",
    "addr:postcode": "44612",
    "addr:street": "N Orchard Rd Ne Bolivar",
    "iso:country": "US",
    "sg:address": "496 N Orchard Rd NE",
    "sg:city": "Bolivar",
    "sg:classifiers": [
      {
        "category": "Social Services",
        "subcategory": "Child Care",
        "type": "Services"
      }
    ],
    "sg:phone": "+1 330 874 8687",
    "sg:postcode": "44612",
    "sg:province": "OH",
    "sg:tags": [
      "day"
    ],
    "wof:name": "Through The Years Child Center",
    "wof:placetype": "venue"
  },
  "geometry": {"coordinates":[-81.44131,40.642772],"type":"Point"}
}
