{
  "type": "Feature",
  "properties": {
    "addr:full": "218 Eastown Dr Wapakoneta OH 45895",
    "addr:housenumber": "218",
    "addr:postcode": "45895",
    "addr:street": "Eastown Dr",
    "iso:country": "US",
    "sg:address": "218 Eastown Dr",
    "sg:city": "Wapakoneta",
    "sg:classifiers": [
      {
        "category": "Real Estate",
        "subcategory": "Real Estate Agent",
        "type": "Services"
      }
    ],
    "sg:phone": "+1 419 738 9450",
    "sg:postcode": "45895",
    "sg:province": "OH",
    "wof:name": "Wapakoneta Village Apts",
    "wof:placetype": "venue"
  },
  "geometry": {"coordinates":[-84.176409,40.566199],"type":"Point"}
}
