{
  "type": "Feature",
  "properties": {
    "addr:full": "412 N Leavitt Rd Amherst OH 44001",
    "addr:housenumber": "412",
    "addr:postcode": "44001",
    "addr:street": "N Leavitt Rd",
    "iso:country": "US",
    "sg:address": "412 N Leavitt Rd",
    "sg:city": "Amherst",
    "sg:classifiers": [
      {
        "category": "Professional",
        "subcategory": "Accounting \u0026 Tax Preparation",
        "type": "Services"
      }
    ],
    "sg:phone": "+1 440 988 2877",
    "sg:postcode": "44001",
    "sg:province": "OH",
    "sg:tags": [
      "accountant"
    ],
    "sg:website": "www.peck-cpa.com",
    "wof:name": "Peck \u0026 Peck Public Accountants",
    "wof:placetype": "venue"
  },
  "geometry": {"coordinates":[-82.209293,41.408548],"type":"Point"}
}
