{
  "type": "Feature",
  "properties": {
    "addr:full": "40 S James Rd Columbus OH 43213",
    "addr:housenumber": "40",
    "addr:postcode": "43213",
    "addr:street": "S James Rd",
    "iso:country": "US",
    "sg:address": "40 S James Rd",
    "sg:city": "Columbus",
    "sg:classifiers": [
      {
        "category": "Professional",
        "subcategory": "Accounting \u0026 Tax Preparation",
        "type": "Services"
      }
    ],
    "sg:phone": "+1 614 235 4500",
    "sg:postcode": "43213",
    "sg:province": "OH",
    "sg:tags": [
      "return",
      "filing"
    ],
    "wof:name": "B \u0026 B Enterprises",
    "wof:placetype": "venue"
  },
  "geometry": {"coordinates":[-82.913716,39.968387],"type":"Point"}
}
