{
  "type": "Feature",
  "properties": {
    "addr:full":"40 S James Rd Columbus OH 43213",
    "addr:housenumber":"40",
    "addr:postcode":"43213",
    "addr:street":"S James Rd",
    "iso:country":"US",
    "sg:address":"40 S James Rd",
    "sg:city":"Columbus",
    "sg:classifiers":[
        {
            "category":"Professional",
            "subcategory":"Accounting & Tax Preparation",
            "type":"Services"
        }
    ],
    "sg:phone":"+1 614 235 4500",
    "sg:postcode":"43213",
    "sg:province":"OH",
    "sg:tags":[
        "return",
        "filing"
    ],
    "wof:name":"B & B Enterprises",
    "wof:placetype":"venue"
},
  "geometry": {"coordinates":[-82.91371599999999,39.968387],"type":"Point"}
}