{
  "type": "Feature",
  "properties": {
    "iso:country":"US",
    "sg:address":"4404 Saint Clair Ave",
    "sg:city":"Cleveland",
    "sg:classifiers":[
        {
            "category":"Manufacturing",
            "subcategory":"Metals",
            "type":"Manufacturing & Wholesale Goods"
        }
    ],
    "sg:phone":"+1 216 391 2132",
    "sg:postcode":"44103",
    "sg:province":"OH",
    "sg:tags":[
        "chrome",
        "plating",
        "hard"
    ],
    "wof:name":"Durable Plating Co",
    "wof:placetype":"venue"
},
  "geometry": {"coordinates":[-81.661422,41.517635],"type":"Point"}
}