{
  "type": "Feature",
  "properties": {
    "addr:full": "438 Dodge St Kent OH 44240",
    "addr:housenumber": "438",
    "addr:postcode": "44240",
    "addr:street": "Dodge St",
    "iso:country": "US",
    "sg:address": "438 Dodge St",
    "sg:city": "Kent",
    "sg:classifiers": [
      {
        "category": "Organizations",
        "subcategory": "Religious Organization",
        "type": "Services"
      }
    ],
    "sg:phone": "+1 330 678 3973",
    "sg:postcode": "44240",
    "sg:province": "OH",
    "sg:tags": [
      "church"
    ],
    "wof:name": "New Beginning Church Of God",
    "wof:placetype": "venue"
  },
  "geometry": {"coordinates":[-81.366305,41.143557],"type":"Point"}
}
