{
  "type": "Feature",
  "properties": {
    "addr:full":"3742 April Ln Columbus OH 43227",
    "addr:housenumber":"3742",
    "addr:postcode":"43227",
    "addr:street":"April Ln",
    "iso:country":"US",
    "sg:address":"3742 April Ln",
    "sg:city":"Columbus",
    "sg:classifiers":[
        {
            "category":"Professional",
            "subcategory":"Business Services",
            "type":"Services"
        }
    ],
    "sg:phone":"+1 614 235 0902",
    "sg:postcode":"43227",
    "sg:province":"OH",
    "wof:name":"Mortgage Maintenance Co LLC",
    "wof:placetype":"venue"
},
  "geometry": {"coordinates":[-82.89283399999999,39.942418],"type":"Point"}
}