{
  "type": "Feature",
  "properties": {
    "iso:country":"US",
    "sg:address":"12840 Wren-Landeck Rd",
    "sg:city":"Van Wert",
    "sg:classifiers":[
        {
            "category":"Farming",
            "subcategory":"Farm",
            "type":"Manufacturing & Wholesale Goods"
        }
    ],
    "sg:phone":"+1 419 965 2517",
    "sg:postcode":"45874",
    "sg:province":"OH",
    "sg:tags":[
        "crop",
        "general"
    ],
    "wof:name":"Joe Hertel",
    "wof:placetype":"venue"
},
  "geometry": {"coordinates":[-84.580994,40.800656],"type":"Point"}
}