{
  "type": "Feature",
  "properties": {
    "addr:full": "12840 Wren-Landeck Rd Van Wert OH 45874",
    "addr:housenumber": "12840",
    "addr:postcode": "45874",
    "addr:street": "Wren-Landeck Rd",
    "iso:country": "US",
    "sg:address": "12840 Wren-Landeck Rd",
    "sg:city": "Van Wert",
    "sg:classifiers": [
      {
        "category": "Farming",
        "subcategory": "Farm",
        "type": "Manufacturing \u0026 Wholesale Goods"
      }
    ],
    "sg:phone": "+1 419 965 2517",
    "sg:postcode": "45874",
    "sg:province": "OH",
    "sg:tags": [
      "crop",
      "general"
    ],
    "wof:name": "Joe Hertel",
    "wof:placetype": "venue"
  },
  "geometry": {"coordinates":[-84.580994,40.800656],"type":"Point"}
}
