{
  "type": "Feature",
  "properties": {
    "iso:country":"US",
    "sg:address":"112 2nd St SW",
    "sg:city":"Carrollton",
    "sg:classifiers":[
        {
            "category":"Banks & Credit Unions",
            "subcategory":"Bank",
            "type":"Services"
        }
    ],
    "sg:phone":"+1 330 627 3737",
    "sg:postcode":"44615",
    "sg:province":"OH",
    "sg:tags":[
        "loan",
        "real estate"
    ],
    "wof:name":"Jericho Mortgage Co",
    "wof:placetype":"venue"
},
  "geometry": {"coordinates":[-81.08833799999999,40.572915],"type":"Point"}
}