{
  "type": "Feature",
  "properties": {
    "addr:full": "112 2nd St SW Carrollton OH 44615",
    "addr:housenumber": "112",
    "addr:postcode": "44615",
    "addr:street": "2Nd St Sw",
    "iso:country": "US",
    "sg:address": "112 2nd St SW",
    "sg:city": "Carrollton",
    "sg:classifiers": [
      {
        "category": "Banks \u0026 Credit Unions",
        "subcategory": "Bank",
        "type": "Services"
      }
    ],
    "sg:phone": "+1 330 627 3737",
    "sg:postcode": "44615",
    "sg:province": "OH",
    "sg:tags": [
      "loan",
      "real estate"
    ],
    "wof:name": "Jericho Mortgage Co",
    "wof:placetype": "venue"
  },
  "geometry": {"coordinates":[-81.088338,40.572915],"type":"Point"}
}
