{
  "type": "Feature",
  "properties": {
    "addr:full": "142 Wetherby Ln Westerville OH 43081",
    "addr:housenumber": "142",
    "addr:postcode": "43081",
    "addr:street": "Wetherby Ln",
    "iso:country": "US",
    "sg:address": "142 Wetherby Ln",
    "sg:city": "Westerville",
    "sg:classifiers": [
      {
        "category": "Building \u0026 Trades",
        "subcategory": "Equipment Rental",
        "type": "Services"
      },
      {
        "category": "Banks \u0026 Credit Unions",
        "subcategory": "Bank",
        "type": "Services"
      }
    ],
    "sg:phone": "+1 614 891 9200",
    "sg:postcode": "43081",
    "sg:province": "OH",
    "sg:tags": [
      "machine",
      "leasing",
      "or",
      "teller",
      "automated"
    ],
    "sg:website": "www.atmad.com",
    "wof:name": "Automated Transaction Mgmt",
    "wof:placetype": "venue"
  },
  "geometry": {"coordinates":[-82.932087,40.111143],"type":"Point"}
}
