{
  "type": "Feature",
  "properties": {
    "iso:country":"US",
    "sg:address":"142 Wetherby Ln",
    "sg:city":"Westerville",
    "sg:classifiers":[
        {
            "category":"Building & Trades",
            "subcategory":"Equipment Rental",
            "type":"Services"
        },
        {
            "category":"Banks & Credit Unions",
            "subcategory":"Bank",
            "type":"Services"
        }
    ],
    "sg:phone":"+1 614 891 9200",
    "sg:postcode":"43081",
    "sg:province":"OH",
    "sg:tags":[
        "machine",
        "leasing",
        "or",
        "teller",
        "automated"
    ],
    "sg:website":"www.atmad.com",
    "wof:name":"Automated Transaction Mgmt",
    "wof:placetype":"venue"
},
  "geometry": {"coordinates":[-82.932087,40.111143],"type":"Point"}
}