{
  "type": "Feature",
  "properties": {
    "addr:full": "7757 Greenville-Celina Rd Greenville OH 45331",
    "addr:housenumber": "7757",
    "addr:postcode": "45331",
    "addr:street": "Greenville-Celina Rd",
    "iso:country": "US",
    "sg:address": "7757 Greenville-Celina Rd",
    "sg:city": "Greenville",
    "sg:classifiers": [
      {
        "category": "Organizations",
        "subcategory": "Religious Organization",
        "type": "Services"
      }
    ],
    "sg:phone": "+1 937 547 1952",
    "sg:postcode": "45331",
    "sg:province": "OH",
    "sg:tags": [
      "church"
    ],
    "sg:website": "www.biblefellowship.com",
    "wof:name": "Bible Fellowship Church",
    "wof:placetype": "venue"
  },
  "geometry": {"coordinates":[-84.61398,40.142502],"type":"Point"}
}
