{
  "type": "Feature",
  "properties": {
    "addr:full": "7360 Chaparral Rd Columbus OH 43235",
    "addr:housenumber": "7360",
    "addr:postcode": "43235",
    "addr:street": "Chaparral Rd",
    "iso:country": "US",
    "sg:address": "7360 Chaparral Rd",
    "sg:city": "Columbus",
    "sg:classifiers": [
      {
        "category": "Banks \u0026 Credit Unions",
        "subcategory": "Financial Services",
        "type": "Services"
      }
    ],
    "sg:phone": "+1 614 799 8868",
    "sg:postcode": "43235",
    "sg:province": "OH",
    "sg:tags": [
      "company",
      "holding"
    ],
    "wof:name": "Jayzer Inc",
    "wof:placetype": "venue"
  },
  "geometry": {"coordinates":[-83.084612,40.105909],"type":"Point"}
}
