{
  "type": "Feature",
  "properties": {
    "iso:country":"US",
    "sg:address":"737 Bolivar Rd",
    "sg:city":"Cleveland",
    "sg:classifiers":[
        {
            "category":"Professional",
            "subcategory":"Management & Consulting",
            "type":"Services"
        }
    ],
    "sg:phone":"+1 216 363 3400",
    "sg:postcode":"44115",
    "sg:province":"OH",
    "sg:tags":[
        "profit",
        "organization",
        "public",
        "relations",
        "man"
    ],
    "wof:name":"Jumpstart",
    "wof:placetype":"venue"
},
  "geometry": {"coordinates":[-81.68585,41.49734],"type":"Point"}
}