{
  "type": "Feature",
  "properties": {
    "addr:full": "1600 Walcutt Rd Columbus OH 43228",
    "addr:housenumber": "1600",
    "addr:postcode": "43228",
    "addr:street": "Walcutt Rd",
    "iso:country": "US",
    "sg:address": "1600 Walcutt Rd",
    "sg:city": "Columbus",
    "sg:classifiers": [
      {
        "category": "Wholesale",
        "subcategory": "Machinery \u0026 Supplies",
        "type": "Manufacturing \u0026 Wholesale Goods"
      }
    ],
    "sg:phone": "+1 614 486 6726",
    "sg:postcode": "43228",
    "sg:province": "OH",
    "sg:tags": [
      "equipment",
      "industrial",
      "supplies-wholesale"
    ],
    "wof:name": "Fischel Technologies",
    "wof:placetype": "venue"
  },
  "geometry": {"coordinates":[-83.137947,39.983688],"type":"Point"}
}
