{
  "type": "Feature",
  "properties": {
    "addr:full":"6705 Linder Ln Cincinnati OH 45244",
    "addr:postcode":"6705;45244",
    "addr:street":"Linder Ln",
    "iso:country":"US",
    "sg:address":"6705 Linder Ln",
    "sg:city":"Cincinnati",
    "sg:classifiers":[
        {
            "category":"Professional",
            "subcategory":"Engineering",
            "type":"Services"
        }
    ],
    "sg:phone":"+1 513 271 2850",
    "sg:postcode":"45244",
    "sg:province":"OH",
    "sg:tags":[
        "engineer"
    ],
    "wof:name":"Burnside & Assoc",
    "wof:placetype":"venue"
},
  "geometry": {"coordinates":[-84.371084,39.114551],"type":"Point"}
}