{
  "type": "Feature",
  "properties": {
    "iso:country":"US",
    "sg:address":"250 Mc Cullough St",
    "sg:city":"Cincinnati",
    "sg:classifiers":[
        {
            "category":"Social Services",
            "type":"Services"
        }
    ],
    "sg:phone":"+1 513 531 9001",
    "sg:postcode":"45226",
    "sg:province":"OH",
    "sg:tags":[
        "organization",
        "welfare"
    ],
    "sg:website":"www.preventblindness.org",
    "wof:name":"Prevent Blindness Ohio",
    "wof:placetype":"venue"
},
  "geometry": {"coordinates":[-84.43458800000001,39.108607],"type":"Point"}
}