{
  "type": "Feature",
  "properties": {
    "iso:country":"US",
    "sg:address":"222 S 2nd St",
    "sg:city":"Hamilton",
    "sg:classifiers":[
        {
            "category":"Utilities",
            "subcategory":"Telephone",
            "type":"Services"
        }
    ],
    "sg:phone":"+1 513 863 9985",
    "sg:postcode":"45011",
    "sg:province":"OH",
    "sg:tags":[
        "communications"
    ],
    "wof:name":"Cincinnati Bell Telephone Co",
    "wof:placetype":"venue"
},
  "geometry": {"coordinates":[-84.562488,39.398538],"type":"Point"}
}