{
  "type": "Feature",
  "properties": {
    "addr:full":"180 W High St London OH 43140",
    "addr:housenumber":"180",
    "addr:postcode":"43140",
    "addr:street":"W High St",
    "iso:country":"US",
    "sg:address":"180 W High St",
    "sg:city":"London",
    "sg:classifiers":[
        {
            "category":"Restaurant",
            "type":"Food & Drink"
        }
    ],
    "sg:phone":"+1 740 852 9509",
    "sg:postcode":"43140",
    "sg:province":"OH",
    "sg:tags":[
        "eating"
    ],
    "wof:name":"In Dixie Drive",
    "wof:placetype":"venue"
},
  "geometry": {"coordinates":[-83.453878,39.882745],"type":"Point"}
}