{
  "type": "Feature",
  "properties": {
    "addr:full": "1066 Ridge St Columbus OH 43215",
    "addr:housenumber": "1066",
    "addr:postcode": "43215",
    "addr:street": "Ridge St",
    "iso:country": "US",
    "sg:address": "1066 Ridge St",
    "sg:city": "Columbus",
    "sg:classifiers": [
      {
        "category": "Building \u0026 Trades",
        "subcategory": "Construction",
        "type": "Services"
      }
    ],
    "sg:phone": "+1 614 485 0550",
    "sg:postcode": "43215",
    "sg:province": "OH",
    "sg:tags": [
      "resurfacing",
      "laying",
      "refinishing",
      "floor"
    ],
    "wof:name": "Carpet King Floor Coverings",
    "wof:placetype": "venue"
  },
  "geometry": {"coordinates":[-83.044973,39.971755],"type":"Point"}
}
