{
  "type": "Feature",
  "properties": {
    "iso:country":"US",
    "sg:address":"946 E Main St",
    "sg:city":"Chillicothe",
    "sg:classifiers":[
        {
            "category":"Health Services",
            "subcategory":"Clinic",
            "type":"Services"
        }
    ],
    "sg:phone":"+1 740 779 9390",
    "sg:postcode":"45601",
    "sg:province":"OH",
    "sg:tags":[
        "home"
    ],
    "wof:name":"Lincare",
    "wof:placetype":"venue"
},
  "geometry": {"coordinates":[-82.954308,39.337478],"type":"Point"}
}