{
  "type": "Feature",
  "properties": {
    "addr:full":"655 Fox Run Rd Findlay OH 45840",
    "addr:housenumber":"655",
    "addr:postcode":"45840",
    "addr:street":"Fox Run Rd",
    "iso:country":"US",
    "sg:address":"655 Fox Run Rd",
    "sg:city":"Findlay",
    "sg:classifiers":[
        {
            "category":"Professional",
            "subcategory":"Accounting & Tax Preparation",
            "type":"Services"
        }
    ],
    "sg:phone":"+1 419 420 0711",
    "sg:postcode":"45840",
    "sg:province":"OH",
    "wof:name":"Fruth & Co",
    "wof:placetype":"venue"
},
  "geometry": {"coordinates":[-83.602839,41.046074],"type":"Point"}
}