{
  "type": "Feature",
  "properties": {
    "addr:full": "455 Hill St Coshocton OH 43812",
    "addr:housenumber": "455",
    "addr:postcode": "43812",
    "addr:street": "Hill St",
    "iso:country": "US",
    "sg:address": "455 Hill St",
    "sg:city": "Coshocton",
    "sg:classifiers": [
      {
        "category": "Real Estate",
        "subcategory": "Real Estate Agent",
        "type": "Services"
      }
    ],
    "sg:phone": "+1 740 622 1329",
    "sg:postcode": "43812",
    "sg:province": "OH",
    "wof:name": "McCru Real Estate Ltd",
    "wof:placetype": "venue"
  },
  "geometry": {"coordinates":[-81.878223,40.279725],"type":"Point"}
}
