{
  "type": "Feature",
  "properties": {
    "addr:full": "5534 Airway Rd Dayton OH 45431",
    "addr:housenumber": "5534",
    "addr:postcode": "45431",
    "addr:street": "Airway Rd",
    "iso:country": "US",
    "sg:address": "5534 Airway Rd",
    "sg:city": "Dayton",
    "sg:classifiers": [
      {
        "category": "Personal",
        "subcategory": "Barber",
        "type": "Services"
      }
    ],
    "sg:phone": "+1 937 781 9703",
    "sg:postcode": "45431",
    "sg:province": "OH",
    "wof:name": "R \u0026 R Barbers",
    "wof:placetype": "venue"
  },
  "geometry": {"coordinates":[-84.114361,39.771761],"type":"Point"}
}
