{
  "type": "Feature",
  "properties": {
    "addr:full": "240 Park Ave W Mansfield OH 44902",
    "addr:housenumber": "240",
    "addr:postcode": "44902",
    "addr:street": "Park Ave W",
    "iso:country": "US",
    "sg:address": "240 Park Ave W",
    "sg:city": "Mansfield",
    "sg:classifiers": [
      {
        "category": "Real Estate",
        "subcategory": "Architect",
        "type": "Services"
      }
    ],
    "sg:phone": "+1 419 524 5050",
    "sg:postcode": "44902",
    "sg:province": "OH",
    "wof:name": "Seckel Group LTD",
    "wof:placetype": "venue"
  },
  "geometry": {"coordinates":[-82.526029,40.758874],"type":"Point"}
}
