{
  "type": "Feature",
  "properties": {
    "addr:full": "28380 Nagel Rd Defiance OH 43512",
    "addr:housenumber": "28380",
    "addr:postcode": "43512",
    "addr:street": "Nagel Rd",
    "iso:country": "US",
    "sg:address": "28380 Nagel Rd",
    "sg:city": "Defiance",
    "sg:phone": "+1 419 267 5157",
    "sg:postcode": "43512",
    "sg:province": "OH",
    "sg:tags": [
      "farm",
      "corn",
      "soybean"
    ],
    "wof:name": "Wilbur Behnfeldt",
    "wof:placetype": "venue"
  },
  "geometry": {"coordinates":[-84.277574,41.413185],"type":"Point"}
}
