{
  "type": "Feature",
  "properties": {
    "iso:country":"US",
    "sg:address":"8640 Factory Shops Blvd",
    "sg:city":"Jeffersonville",
    "sg:classifiers":[
        {
            "category":"Shopping",
            "subcategory":"Clothing, Apparel, & Fashions",
            "type":"Retail Goods"
        }
    ],
    "sg:phone":"+1 740 948 2100",
    "sg:postcode":"43128",
    "sg:province":"OH",
    "sg:tags":[
        "infant",
        "wear"
    ],
    "sg:website":"www.oshkoshbgosh.com",
    "wof:name":"Osh Kosh B'Gosh",
    "wof:placetype":"venue"
},
  "geometry": {"coordinates":[-83.601789,39.617191],"type":"Point"}
}