{
  "type": "Feature",
  "properties": {
    "addr:full": "20611 Barker Rd Marysville OH 43040",
    "addr:housenumber": "20611",
    "addr:postcode": "43040",
    "addr:street": "Barker Rd",
    "iso:country": "US",
    "sg:address": "20611 Barker Rd",
    "sg:city": "Marysville",
    "sg:classifiers": [
      {
        "category": "Retail",
        "subcategory": "Laundry \u0026 Dry Cleaning",
        "type": "Services"
      }
    ],
    "sg:phone": "+1 937 644 2464",
    "sg:postcode": "43040",
    "sg:province": "OH",
    "sg:tags": [
      "cleaners",
      "rug",
      "carpet"
    ],
    "sg:website": "www.baneclene.com",
    "wof:name": "Bane-Clene Way",
    "wof:placetype": "venue"
  },
  "geometry": {"coordinates":[-83.430374,40.259711],"type":"Point"}
}
