{
  "type": "Feature",
  "properties": {
    "addr:full": "545 Foliage Ln Springboro OH 45066",
    "addr:housenumber": "545",
    "addr:postcode": "45066",
    "addr:street": "Foliage Ln",
    "iso:country": "US",
    "sg:address": "545 Foliage Ln",
    "sg:city": "Springboro",
    "sg:classifiers": [
      {
        "category": "Wholesale",
        "subcategory": "Metals \u0026 Minerals",
        "type": "Manufacturing \u0026 Wholesale Goods"
      }
    ],
    "sg:phone": "+1 937 748 9220",
    "sg:postcode": "45066",
    "sg:province": "OH",
    "sg:tags": [
      "building",
      "material"
    ],
    "wof:name": "Nucor Building Systems",
    "wof:placetype": "venue"
  },
  "geometry": {"coordinates":[-84.24231,39.572225],"type":"Point"}
}
