{
  "type": "Feature",
  "properties": {
    "iso:country":"US",
    "sg:address":"545 Foliage Ln",
    "sg:city":"Springboro",
    "sg:classifiers":[
        {
            "category":"Wholesale",
            "subcategory":"Metals & Minerals",
            "type":"Manufacturing & Wholesale Goods"
        }
    ],
    "sg:phone":"+1 937 748 9220",
    "sg:postcode":"45066",
    "sg:province":"OH",
    "sg:tags":[
        "building",
        "material"
    ],
    "wof:name":"Nucor Building Systems",
    "wof:placetype":"venue"
},
  "geometry": {"coordinates":[-84.24231,39.572225],"type":"Point"}
}