{
  "type": "Feature",
  "properties": {
    "addr:full": "395 Industrial Dr Franklin OH 45005",
    "addr:housenumber": "395",
    "addr:postcode": "45005",
    "addr:street": "Industrial Dr",
    "iso:country": "US",
    "sg:address": "395 Industrial Dr",
    "sg:city": "Franklin",
    "sg:classifiers": [
      {
        "category": "Manufacturing",
        "subcategory": "Tools \u0026 Machinery",
        "type": "Manufacturing \u0026 Wholesale Goods"
      }
    ],
    "sg:phone": "+1 937 746 3086",
    "sg:postcode": "45005",
    "sg:province": "OH",
    "sg:tags": [
      "machine",
      "shop"
    ],
    "wof:name": "SRS Manufacturing Corp",
    "wof:placetype": "venue"
  },
  "geometry": {"coordinates":[-84.30192,39.535478],"type":"Point"}
}
