{
  "type": "Feature",
  "properties": {
    "iso:country":"US",
    "sg:address":"395 Industrial Dr",
    "sg:city":"Franklin",
    "sg:classifiers":[
        {
            "category":"Manufacturing",
            "subcategory":"Tools & Machinery",
            "type":"Manufacturing & Wholesale Goods"
        }
    ],
    "sg:phone":"+1 937 746 3086",
    "sg:postcode":"45005",
    "sg:province":"OH",
    "sg:tags":[
        "machine",
        "shop"
    ],
    "wof:name":"SRS Manufacturing Corp",
    "wof:placetype":"venue"
},
  "geometry": {"coordinates":[-84.30192,39.535478],"type":"Point"}
}