{
  "type": "Feature",
  "properties": {
    "iso:country":"US",
    "sg:address":"1328 Winchester West Rd",
    "sg:city":"Bucyrus",
    "sg:classifiers":[
        {
            "category":"Farming",
            "subcategory":"Livestock Farm",
            "type":"Manufacturing & Wholesale Goods"
        }
    ],
    "sg:phone":"+1 419 562 4248",
    "sg:postcode":"44820",
    "sg:province":"OH",
    "sg:tags":[
        "feedlot",
        "hog",
        "corn",
        "or",
        "soybean"
    ],
    "wof:name":"Sulser Ken",
    "wof:placetype":"venue"
},
  "geometry": {"coordinates":[-82.95882400000001,40.794202],"type":"Point"}
}