{
  "type": "Feature",
  "properties": {
    "addr:full": "1328 Winchester West Rd Bucyrus OH 44820",
    "addr:housenumber": "1328",
    "addr:postcode": "44820",
    "addr:street": "Winchester West Rd",
    "iso:country": "US",
    "sg:address": "1328 Winchester West Rd",
    "sg:city": "Bucyrus",
    "sg:classifiers": [
      {
        "category": "Farming",
        "subcategory": "Livestock Farm",
        "type": "Manufacturing \u0026 Wholesale Goods"
      }
    ],
    "sg:phone": "+1 419 562 4248",
    "sg:postcode": "44820",
    "sg:province": "OH",
    "sg:tags": [
      "feedlot",
      "hog",
      "corn",
      "or",
      "soybean"
    ],
    "wof:name": "Sulser Ken",
    "wof:placetype": "venue"
  },
  "geometry": {"coordinates":[-82.958824,40.794202],"type":"Point"}
}
