{
  "type": "Feature",
  "properties": {
    "addr:full":"1531 Dream Ct Reynoldsburg OH 43068",
    "addr:housenumber":"1531",
    "addr:postcode":"43068",
    "addr:street":"Dream Ct",
    "iso:country":"US",
    "sg:address":"1531 Dream Ct",
    "sg:city":"Reynoldsburg",
    "sg:classifiers":[
        {
            "category":"Social Services",
            "subcategory":"Child Care",
            "type":"Services"
        }
    ],
    "sg:phone":"+1 614 575 1384",
    "sg:postcode":"43068",
    "sg:province":"OH",
    "wof:name":"Mrs Monica's Child Care",
    "wof:placetype":"venue"
},
  "geometry": {"coordinates":[-82.787724,39.952236],"type":"Point"}
}