{
  "type": "Feature",
  "properties": {
    "iso:country":"US",
    "sg:address":"7148 US Hwy 24",
    "sg:city":"Antwerp",
    "sg:classifiers":[
        {
            "category":"Professional",
            "type":"Services"
        }
    ],
    "sg:phone":"+1 419 258 2821",
    "sg:postcode":"45813",
    "sg:province":"OH",
    "sg:tags":[
        "to",
        "range",
        "wide",
        "business",
        "area"
    ],
    "wof:name":"Krick & Associates",
    "wof:placetype":"venue"
},
  "geometry": {"coordinates":[-84.68880799999999,41.20397],"type":"Point"}
}