{
  "type": "Feature",
  "properties": {
    "addr:full": "7148 US Hwy 24 Antwerp OH 45813",
    "addr:housenumber": "7148",
    "addr:postcode": "45813",
    "addr:street": "Us Hwy 24",
    "iso:country": "US",
    "sg:address": "7148 US Hwy 24",
    "sg:city": "Antwerp",
    "sg:classifiers": [
      {
        "category": "Professional",
        "type": "Services"
      }
    ],
    "sg:phone": "+1 419 258 2821",
    "sg:postcode": "45813",
    "sg:province": "OH",
    "sg:tags": [
      "to",
      "range",
      "wide",
      "business",
      "area"
    ],
    "wof:name": "Krick \u0026 Associates",
    "wof:placetype": "venue"
  },
  "geometry": {"coordinates":[-84.688808,41.20397],"type":"Point"}
}
