{
  "type": "Feature",
  "properties": {
    "addr:full": "100 Mall Dr Steubenville OH 43952",
    "addr:housenumber": "100",
    "addr:postcode": "43952",
    "addr:street": "Mall Dr",
    "iso:country": "US",
    "sg:address": "100 Mall Dr",
    "sg:city": "Steubenville",
    "sg:classifiers": [
      {
        "category": "Bakery",
        "type": "Food \u0026 Drink"
      }
    ],
    "sg:menulink": "http://www.allmenus.com/oh/steubenville/220153-auntie-annes-pretzels/menu/",
    "sg:phone": "+1 740 266 6550",
    "sg:postcode": "43952",
    "sg:province": "OH",
    "sg:tags": [
      "american",
      "pastry"
    ],
    "wof:name": "Auntie Anne's Pretzels",
    "wof:placetype": "venue"
  },
  "geometry": {"coordinates":[-80.675002,40.367764],"type":"Point"}
}
