{
  "type": "Feature",
  "properties": {
    "addr:full": "3727 Co Hwy 96 Carey OH 43316",
    "addr:housenumber": "3727",
    "addr:postcode": "43316",
    "addr:street": "Co Hwy 96",
    "iso:country": "US",
    "sg:address": "3727 Co Hwy 96",
    "sg:city": "Carey",
    "sg:classifiers": [
      {
        "category": "Freight",
        "type": "Transportation"
      }
    ],
    "sg:phone": "+1 419 396 1400",
    "sg:postcode": "43316",
    "sg:province": "OH",
    "sg:tags": [
      "commercial",
      "storage"
    ],
    "wof:name": "Carey Self Storage",
    "wof:placetype": "venue"
  },
  "geometry": {"coordinates":[-83.400933,40.936962],"type":"Point"}
}
