{
  "type": "Feature",
  "properties": {
    "addr:full": "10645 Springfield Pike Cincinnati OH 45215",
    "addr:housenumber": "10645",
    "addr:postcode": "45215",
    "addr:street": "Springfield Pike",
    "iso:country": "US",
    "sg:address": "10645 Springfield Pike",
    "sg:city": "Cincinnati",
    "sg:classifiers": [
      {
        "category": "Real Estate",
        "subcategory": "Real Estate Operator",
        "type": "Services"
      }
    ],
    "sg:phone": "+1 513 772 7140",
    "sg:postcode": "45215",
    "sg:province": "OH",
    "sg:tags": [
      "apartment"
    ],
    "wof:name": "Commons",
    "wof:placetype": "venue"
  },
  "geometry": {"coordinates":[-84.469563,39.265035],"type":"Point"}
}
