{
  "type": "Feature",
  "properties": {
    "addr:full": "101 S Main St Piqua OH 45356",
    "addr:housenumber": "101",
    "addr:postcode": "45356",
    "addr:street": "S Main St",
    "iso:country": "US",
    "sg:address": "101 S Main St",
    "sg:city": "Piqua",
    "sg:classifiers": [
      {
        "category": "Wholesale",
        "subcategory": "Farm Supplies",
        "type": "Manufacturing \u0026 Wholesale Goods"
      }
    ],
    "sg:phone": "+1 937 773 0215",
    "sg:postcode": "45356",
    "sg:province": "OH",
    "sg:tags": [
      "feed"
    ],
    "wof:name": "Piqua Feed Seed \u0026 Supply Co",
    "wof:placetype": "venue"
  },
  "geometry": {"coordinates":[-84.23946,40.146015],"type":"Point"}
}
