{
  "type": "Feature",
  "properties": {
    "addr:full": "9011 Freeway Dr Macedonia OH 44056",
    "addr:postcode": "9011;44056",
    "addr:street": "Freeway Dr",
    "iso:country": "US",
    "sg:address": "9011 Freeway Dr",
    "sg:city": "Macedonia",
    "sg:classifiers": [
      {
        "category": "Wholesale",
        "subcategory": "Machinery \u0026 Supplies",
        "type": "Manufacturing \u0026 Wholesale Goods"
      }
    ],
    "sg:phone": "+1 330 468 2700",
    "sg:postcode": "44056",
    "sg:province": "OH",
    "sg:tags": [
      "equipment",
      "establishment"
    ],
    "sg:website": "www.ironmountain.com",
    "wof:name": "Iron Mountain Secure Shredding",
    "wof:placetype": "venue"
  },
  "geometry": {"coordinates":[-81.511259,41.313857],"type":"Point"}
}
