{
  "type": "Feature",
  "properties": {
    "addr:full":"712 E 34th St Lorain OH 44055",
    "addr:housenumber":"712",
    "addr:postcode":"44055",
    "addr:street":"E 34Th St",
    "iso:country":"US",
    "sg:address":"712 E 34th St",
    "sg:city":"Lorain",
    "sg:classifiers":[
        {
            "category":"Real Estate",
            "subcategory":"Real Estate Agent",
            "type":"Services"
        }
    ],
    "sg:phone":"+1 440 233 8776",
    "sg:postcode":"44055",
    "sg:province":"OH",
    "wof:name":"Schreiber & Associates",
    "wof:placetype":"venue"
},
  "geometry": {"coordinates":[-82.157729,41.439488],"type":"Point"}
}