{
  "type": "Feature",
  "properties": {
    "iso:country":"US",
    "sg:address":"7620 Olentangy River Rd",
    "sg:city":"Columbus",
    "sg:classifiers":[
        {
            "category":"Health Services",
            "subcategory":"Doctor",
            "type":"Services"
        },
        {
            "category":"Health Services",
            "subcategory":"Clinic",
            "type":"Services"
        },
        {
            "category":"Insurance",
            "subcategory":"Health Insurance",
            "type":"Services"
        }
    ],
    "sg:phone":"+1 614 846 6554",
    "sg:postcode":"43235",
    "sg:province":"OH",
    "sg:tags":[
        "physician",
        "medical",
        "surgeon"
    ],
    "wof:name":"National Healthcare Access Inc",
    "wof:placetype":"venue"
},
  "geometry": {"coordinates":[-83.035701,40.122155],"type":"Point"}
}