{
  "type": "Feature",
  "properties": {
    "iso:country":"US",
    "sg:address":"9510 Millbrook Dr",
    "sg:city":"Cincinnati",
    "sg:classifiers":[
        {
            "category":"Building & Trades",
            "subcategory":"Landscaping Services",
            "type":"Services"
        }
    ],
    "sg:phone":"+1 513 931 2203",
    "sg:postcode":"45231",
    "sg:province":"OH",
    "sg:tags":[
        "landscape"
    ],
    "wof:name":"Twin Blades Landscaping Ltd",
    "wof:placetype":"venue"
},
  "geometry": {"coordinates":[-84.508573,39.241007],"type":"Point"}
}