{
  "type": "Feature",
  "properties": {
    "addr:full":"448 Anthony St Ottawa OH 45875",
    "addr:housenumber":"448",
    "addr:postcode":"45875",
    "addr:street":"Anthony St",
    "iso:country":"US",
    "sg:address":"448 Anthony St",
    "sg:city":"Ottawa",
    "sg:phone":"+1 419 538 6443",
    "sg:postcode":"45875",
    "sg:province":"OH",
    "sg:tags":[
        "wheat",
        "farm",
        "corn",
        "cash",
        "grain",
        "soybean"
    ],
    "wof:name":"Larry Karoff",
    "wof:placetype":"venue"
},
  "geometry": {"coordinates":[-84.082927,41.036087],"type":"Point"}
}