{
  "type": "Feature",
  "properties": {
    "iso:country":"US",
    "sg:address":"2251 Pine Ridge Dr",
    "sg:city":"Wickliffe",
    "sg:classifiers":[
        {
            "category":"Arts & Performance",
            "subcategory":"Theater",
            "type":"Entertainment"
        }
    ],
    "sg:phone":"+1 440 943 5480",
    "sg:postcode":"44092",
    "sg:province":"OH",
    "sg:tags":[
        "bureau"
    ],
    "wof:name":"J B Promotions",
    "wof:placetype":"venue"
},
  "geometry": {"coordinates":[-81.44955899999999,41.605419],"type":"Point"}
}