{
  "type": "Feature",
  "properties": {
    "iso:country":"US",
    "sg:address":"9670 Valley View Rd",
    "sg:city":"Macedonia",
    "sg:classifiers":[
        {
            "category":"Organizations",
            "subcategory":"Religious Organization",
            "type":"Services"
        }
    ],
    "sg:phone":"+1 330 467 9433",
    "sg:postcode":"44056",
    "sg:province":"OH",
    "sg:tags":[
        "church"
    ],
    "wof:name":"Macedonia Church Of Nazarene",
    "wof:placetype":"venue"
},
  "geometry": {"coordinates":[-81.50022199999999,41.306866],"type":"Point"}
}