{
  "type": "Feature",
  "properties": {
    "addr:full": "6094 Harrison Ave Cincinnati OH 45247",
    "addr:housenumber": "6094",
    "addr:postcode": "45247",
    "addr:street": "Harrison Ave",
    "iso:country": "US",
    "sg:address": "6094 Harrison Ave",
    "sg:city": "Cincinnati",
    "sg:classifiers": [
      {
        "category": "Retail",
        "subcategory": "Auto Repair",
        "type": "Services"
      }
    ],
    "sg:phone": "+1 513 574 6611",
    "sg:postcode": "45247",
    "sg:province": "OH",
    "sg:tags": [
      "general"
    ],
    "wof:name": "Waddle Brothers Garage Inc",
    "wof:placetype": "venue"
  },
  "geometry": {"coordinates":[-84.647392,39.180719],"type":"Point"}
}
