{
  "type": "Feature",
  "properties": {
    "addr:full":"4307 Roosevelt Blvd Middletown OH 45044",
    "addr:housenumber":"4307",
    "addr:postcode":"45044",
    "addr:street":"Roosevelt Blvd",
    "iso:country":"US",
    "sg:address":"4307 Roosevelt Blvd",
    "sg:city":"Middletown",
    "sg:phone":"+1 513 258 0099",
    "sg:postcode":"45044",
    "sg:province":"OH",
    "sg:website":"http://www.voodootattooohio.com",
    "wof:name":"Voodoo Tattoo",
    "wof:placetype":"venue"
},
  "geometry": {"coordinates":[-84.356674,39.499549],"type":"Point"}
}