{
  "type": "Feature",
  "properties": {
    "iso:country":"US",
    "sg:address":"47 2nd St NE",
    "sg:city":"Massillon",
    "sg:classifiers":[
        {
            "category":"Organizations",
            "subcategory":"Religious Organization",
            "type":"Services"
        }
    ],
    "sg:phone":"+1 330 832 7455",
    "sg:postcode":"44646",
    "sg:province":"OH",
    "wof:name":"Central Presbyterian Church",
    "wof:placetype":"venue"
},
  "geometry": {"coordinates":[-81.520663,40.797671],"type":"Point"}
}