{
  "type": "Feature",
  "properties": {
    "addr:full":"20 Mill St Belpre OH 45760",
    "addr:housenumber":"20",
    "addr:postcode":"45760",
    "addr:street":"Mill",
    "iso:country":"US",
    "sg:address":"20 Mill St",
    "sg:city":"Belpre",
    "sg:classifiers":[
        {
            "category":"Building & Trades",
            "subcategory":"Construction",
            "type":"Services"
        }
    ],
    "sg:phone":"+1 740 423 8982",
    "sg:postcode":"45760",
    "sg:province":"OH",
    "sg:tags":[
        "pipe",
        "line",
        "contractor"
    ],
    "sg:website":"www.lapipeline.com",
    "wof:name":"L A Pipeline Construction Co",
    "wof:placetype":"venue"
},
  "geometry": {"coordinates":[-82.04823399999999,39.001677],"type":"Point"}
}