{
  "type": "Feature",
  "properties": {
    "iso:country":"US",
    "sg:address":"1441 Stanley Ave",
    "sg:city":"Dayton",
    "sg:classifiers":[
        {
            "category":"Wholesale",
            "subcategory":"Hardware",
            "type":"Manufacturing & Wholesale Goods"
        }
    ],
    "sg:phone":"+1 937 223 4621",
    "sg:postcode":"45404",
    "sg:province":"OH",
    "sg:tags":[
        "fastener"
    ],
    "wof:name":"Dayton Winfastener",
    "wof:placetype":"venue"
},
  "geometry": {"coordinates":[-84.196316,39.783149],"type":"Point"}
}