{
  "type": "Feature",
  "properties": {
    "addr:full":"10045 Columbus Rd NE Louisville OH 44641",
    "addr:housenumber":"10045",
    "addr:postcode":"44641",
    "addr:street":"Columbus Rd Ne",
    "iso:country":"US",
    "sg:address":"10045 Columbus Rd NE",
    "sg:city":"Louisville",
    "sg:phone":"+1 330 823 4362",
    "sg:postcode":"44641",
    "sg:province":"OH",
    "sg:tags":[
        "farm",
        "corn",
        "wheat",
        "soybean"
    ],
    "wof:name":"Larry Strouble",
    "wof:placetype":"venue"
},
  "geometry": {"coordinates":[-81.20261000000001,40.917635],"type":"Point"}
}