{
  "type": "Feature",
  "properties": {
    "addr:full": "67 Industrial Pkwy Versailles OH 45380",
    "addr:housenumber": "67",
    "addr:postcode": "45380",
    "addr:street": "Industrial Pkwy",
    "iso:country": "US",
    "sg:address": "67 Industrial Pkwy",
    "sg:city": "Versailles",
    "sg:classifiers": [
      {
        "category": "Building \u0026 Trades",
        "subcategory": "Electrical",
        "type": "Services"
      }
    ],
    "sg:phone": "+1 937 526 5520",
    "sg:postcode": "45380",
    "sg:province": "OH",
    "sg:tags": [
      "telecommunication",
      "contractor"
    ],
    "sg:website": "www.cotainternational.com",
    "wof:name": "Cota International Inc",
    "wof:placetype": "venue"
  },
  "geometry": {"coordinates":[-84.485369,40.235483],"type":"Point"}
}
