{
  "type": "Feature",
  "properties": {
    "iso:country":"US",
    "sg:address":"208 N Scioto St",
    "sg:city":"Circleville",
    "sg:classifiers":[
        {
            "category":"Banks & Credit Unions",
            "subcategory":"Bank",
            "type":"Services"
        }
    ],
    "sg:phone":"+1 740 474 5999",
    "sg:postcode":"43113",
    "sg:province":"OH",
    "sg:tags":[
        "mortgage",
        "loan",
        "broker",
        "real estate"
    ],
    "sg:website":"www.directionmortgage.com",
    "wof:name":"Direction Mortgage",
    "wof:placetype":"venue"
},
  "geometry": {"coordinates":[-82.946645,39.604744],"type":"Point"}
}