{
  "type": "Feature",
  "properties": {
    "iso:country":"US",
    "sg:address":"871 McKay Ct",
    "sg:city":"Youngstown",
    "sg:classifiers":[
        {
            "category":"Restaurant",
            "type":"Food & Drink"
        }
    ],
    "sg:phone":"+1 330 793 0707",
    "sg:postcode":"44512",
    "sg:province":"OH",
    "sg:tags":[
        "lounge"
    ],
    "wof:name":"Antones Restaurant and Lounge",
    "wof:placetype":"venue"
},
  "geometry": {"coordinates":[-80.63880399999999,41.023326],"type":"Point"}
}