{
  "type": "Feature",
  "properties": {
    "iso:country":"US",
    "sg:address":"22960 State Rte 73",
    "sg:city":"West Portsmouth",
    "sg:classifiers":[
        {
            "category":"Autos & Motor Vehicles",
            "subcategory":"Automobile Sales",
            "type":"Retail Goods"
        }
    ],
    "sg:phone":"+1 740 858 5255",
    "sg:postcode":"45663",
    "sg:province":"OH",
    "sg:tags":[
        "car",
        "dealer"
    ],
    "wof:name":"Goode's Ent Inc Sales & Parts",
    "wof:placetype":"venue"
},
  "geometry": {"coordinates":[-83.016825,38.767501],"type":"Point"}
}