{
  "type": "Feature",
  "properties": {
    "iso:country":"US",
    "sg:address":"1524 W River Rd N",
    "sg:city":"Elyria",
    "sg:classifiers":[
        {
            "category":"Restaurant",
            "type":"Food & Drink"
        }
    ],
    "sg:menulink":"http://www.allmenus.com/oh/elyria/223061-eat-n-park/menu/",
    "sg:phone":"+1 440 324 3286",
    "sg:postcode":"44035",
    "sg:province":"OH",
    "sg:tags":[
        "american",
        "diner"
    ],
    "wof:name":"Eat N' Park",
    "wof:placetype":"venue"
},
  "geometry": {"coordinates":[-82.10641,41.394058],"type":"Point"}
}