{
  "type": "Feature",
  "properties": {
    "addr:full":"10313 Lorain Ave Cleveland OH 44111",
    "addr:housenumber":"10313",
    "addr:postcode":"44111",
    "addr:street":"Lorain Ave",
    "iso:country":"US",
    "sg:address":"10313 Lorain Ave",
    "sg:city":"Cleveland",
    "sg:classifiers":[
        {
            "category":"Organizations",
            "subcategory":"Professional Association",
            "type":"Services"
        }
    ],
    "sg:phone":"+1 216 941 9262",
    "sg:postcode":"44111",
    "sg:province":"OH",
    "sg:tags":[
        "provides",
        "community"
    ],
    "wof:name":"Westown Community Development",
    "wof:placetype":"venue"
},
  "geometry": {"coordinates":[-81.75588399999999,41.466137],"type":"Point"}
}