{
  "type": "Feature",
  "properties": {
    "addr:full":"6219 Pearl Rd Cleveland OH 44130",
    "addr:housenumber":"6219",
    "addr:postcode":"44130",
    "addr:street":"Pearl Rd",
    "iso:country":"US",
    "sg:address":"6219 Pearl Rd",
    "sg:city":"Cleveland",
    "sg:classifiers":[
        {
            "category":"Restaurant",
            "type":"Food & Drink"
        }
    ],
    "sg:phone":"+1 440 885 3663",
    "sg:postcode":"44130",
    "sg:province":"OH",
    "sg:tags":[
        "eating"
    ],
    "wof:name":"Victorios Family Restaurant",
    "wof:placetype":"venue"
},
  "geometry": {"coordinates":[-81.759266,41.392538],"type":"Point"}
}