{
  "type": "Feature",
  "properties": {
    "addr:full":"4012 Burbank Rd Wooster OH 44691",
    "addr:housenumber":"4012",
    "addr:postcode":"44691",
    "addr:street":"Burbank Rd",
    "iso:country":"US",
    "sg:address":"4012 Burbank Rd",
    "sg:city":"Wooster",
    "sg:classifiers":[
        {
            "category":"Restaurant",
            "type":"Food & Drink"
        }
    ],
    "sg:phone":"+1 330 345 3533",
    "sg:postcode":"44691",
    "sg:province":"OH",
    "sg:tags":[
        "eating"
    ],
    "wof:name":"Burger King",
    "wof:placetype":"venue"
},
  "geometry": {"coordinates":[-81.94634600000001,40.84948],"type":"Point"}
}