{
  "type": "Feature",
  "properties": {
    "addr:full":"606 Phillips Ave Toledo OH 43612",
    "addr:housenumber":"606",
    "addr:postcode":"43612",
    "addr:street":"Phillips Ave",
    "iso:country":"US",
    "sg:address":"606 Phillips Ave",
    "sg:city":"Toledo",
    "sg:classifiers":[
        {
            "category":"Building & Trades",
            "subcategory":"Construction",
            "type":"Services"
        }
    ],
    "sg:phone":"+1 419 255 2925",
    "sg:postcode":"43612",
    "sg:province":"OH",
    "sg:tags":[
        "resurfacing",
        "laying",
        "refinishing",
        "floor"
    ],
    "wof:name":"Emerald Floor Maintence LLC",
    "wof:placetype":"venue"
},
  "geometry": {"coordinates":[-83.55829,41.690612],"type":"Point"}
}