{
  "type": "Feature",
  "properties": {
    "addr:full": "2694 Akron Rd Wooster OH 44691",
    "addr:housenumber": "2694",
    "addr:postcode": "44691",
    "addr:street": "Akron Rd",
    "iso:country": "US",
    "sg:address": "2694 Akron Rd",
    "sg:city": "Wooster",
    "sg:classifiers": [
      {
        "category": "Home \u0026 Garden",
        "subcategory": "Furniture",
        "type": "Retail Goods"
      }
    ],
    "sg:phone": "+1 330 264 3137",
    "sg:postcode": "44691",
    "sg:province": "OH",
    "wof:name": "Sleep Systems",
    "wof:placetype": "venue"
  },
  "geometry": {"coordinates":[-81.908114,40.831398],"type":"Point"}
}
