{
  "type": "Feature",
  "properties": {
    "addr:full": "24481 Detroit Rd Westlake OH 44145",
    "addr:housenumber": "24481",
    "addr:postcode": "44145",
    "addr:street": "Detroit Rd",
    "iso:country": "US",
    "sg:address": "24481 Detroit Rd",
    "sg:city": "Westlake",
    "sg:classifiers": [
      {
        "category": "Restaurant",
        "type": "Food \u0026 Drink"
      }
    ],
    "sg:phone": "+1 440 835 3559",
    "sg:postcode": "44145",
    "sg:province": "OH",
    "sg:website": "http://www.saucybistro.com",
    "wof:name": "Saucy Bistro",
    "wof:placetype": "venue"
  },
  "geometry": {"coordinates":[-81.891624,41.470864],"type":"Point"}
}
