{
  "type": "Feature",
  "properties": {
    "iso:country":"US",
    "sg:address":"806 Sharon Dr",
    "sg:city":"Cleveland",
    "sg:classifiers":[
        {
            "category":"Professional",
            "subcategory":"Advertising",
            "type":"Services"
        }
    ],
    "sg:phone":"+1 440 899 1336",
    "sg:postcode":"44145",
    "sg:province":"OH",
    "sg:tags":[
        "counselor"
    ],
    "wof:name":"Wichmann Group Advertising",
    "wof:placetype":"venue"
},
  "geometry": {"coordinates":[-81.891147,41.473177],"type":"Point"}
}