{
  "type": "Feature",
  "properties": {
    "addr:full": "3878 Co Rd 80 Alger OH 45812",
    "addr:housenumber": "3878",
    "addr:postcode": "45812",
    "addr:street": "Co Rd 80",
    "iso:country": "US",
    "sg:address": "3878 Co Rd 80",
    "sg:city": "Alger",
    "sg:classifiers": [
      {
        "category": "Health Services",
        "subcategory": "Clinic",
        "type": "Services"
      }
    ],
    "sg:phone": "+1 419 757 7794",
    "sg:postcode": "45812",
    "sg:province": "OH",
    "sg:tags": [
      "home",
      "care"
    ],
    "wof:name": "Voc Works",
    "wof:placetype": "venue"
  },
  "geometry": {"coordinates":[-83.806675,40.718535],"type":"Point"}
}
