{
  "type": "Feature",
  "properties": {
    "iso:country":"US",
    "sg:address":"921 Elysian Ave",
    "sg:city":"Toledo",
    "sg:classifiers":[
        {
            "category":"Shopping",
            "subcategory":"Discount & Variety Stores",
            "type":"Retail Goods"
        },
        {
            "category":"Shopping",
            "subcategory":"Hobbies, Toys, & Games",
            "type":"Retail Goods"
        }
    ],
    "sg:phone":"+1 419 539 7478",
    "sg:postcode":"43607",
    "sg:province":"OH",
    "wof:name":"Mable's What Not Shop",
    "wof:placetype":"venue"
},
  "geometry": {"coordinates":[-83.611032,41.650845],"type":"Point"}
}