{
  "type": "Feature",
  "properties": {
    "addr:full":"30 N Kimberly Ave Youngstown OH 44515",
    "addr:housenumber":"30",
    "addr:postcode":"44515",
    "addr:street":"N Kimberly Ave",
    "iso:country":"US",
    "sg:address":"30 N Kimberly Ave",
    "sg:city":"Youngstown",
    "sg:classifiers":[
        {
            "category":"Wholesale",
            "subcategory":"Electrical",
            "type":"Manufacturing & Wholesale Goods"
        }
    ],
    "sg:phone":"+1 330 793 0200",
    "sg:postcode":"44515",
    "sg:province":"OH",
    "sg:tags":[
        "equipment",
        "radio"
    ],
    "wof:name":"Car Tunes Inc",
    "wof:placetype":"venue"
},
  "geometry": {"coordinates":[-80.757932,41.100713],"type":"Point"}
}