{
  "type": "Feature",
  "properties": {
    "addr:full":"1548 Creekside Rd Amelia OH 45102",
    "addr:housenumber":"1548",
    "addr:postcode":"45102",
    "addr:street":"Creekside Rd",
    "iso:country":"US",
    "sg:address":"1548 Creekside Rd",
    "sg:city":"Amelia",
    "sg:classifiers":[
        {
            "category":"Restaurant",
            "type":"Food & Drink"
        }
    ],
    "sg:phone":"+1 513 943 7761",
    "sg:postcode":"45102",
    "sg:province":"OH",
    "sg:tags":[
        "eating"
    ],
    "wof:name":"Flying J Inc",
    "wof:placetype":"venue"
},
  "geometry": {"coordinates":[-84.221203,39.035805],"type":"Point"}
}