{
  "type": "Feature",
  "properties": {
    "addr:full":"938 S Main St Canton OH 44720",
    "addr:housenumber":"938",
    "addr:postcode":"44720",
    "addr:street":"S Main St",
    "iso:country":"US",
    "sg:address":"938 S Main St",
    "sg:city":"Canton",
    "sg:classifiers":[
        {
            "category":"Shopping",
            "subcategory":"Shoes",
            "type":"Retail Goods"
        }
    ],
    "sg:phone":"+1 330 494 0566",
    "sg:postcode":"44720",
    "sg:province":"OH",
    "wof:name":"Pachmayer Enterprises Inc",
    "wof:placetype":"venue"
},
  "geometry": {"coordinates":[-81.39916599999999,40.869223],"type":"Point"}
}