{
  "type": "Feature",
  "properties": {
    "iso:country":"US",
    "sg:address":"230 Xenia Ave",
    "sg:city":"Dayton",
    "sg:classifiers":[
        {
            "category":"Real Estate",
            "subcategory":"Real Estate Agent",
            "type":"Services"
        }
    ],
    "sg:phone":"+1 937 256 5502",
    "sg:postcode":"45410",
    "sg:province":"OH",
    "wof:name":"Worth Rentals",
    "wof:placetype":"venue"
},
  "geometry": {"coordinates":[-84.174144,39.752508],"type":"Point"}
}