{
  "type": "Feature",
  "properties": {
    "addr:full":"2323 W 5th Ave Columbus OH 43204",
    "addr:housenumber":"2323",
    "addr:postcode":"43204",
    "addr:street":"W 5Th Ave",
    "iso:country":"US",
    "sg:address":"2323 W 5th Ave",
    "sg:city":"Columbus",
    "sg:classifiers":[
        {
            "category":"Communications",
            "subcategory":"Radio Station",
            "type":"Services"
        }
    ],
    "sg:phone":"+1 614 486 6101",
    "sg:postcode":"43204",
    "sg:province":"OH",
    "sg:tags":[
        "broadcast"
    ],
    "wof:name":"Newsradio 610 Wtvn",
    "wof:placetype":"venue"
},
  "geometry": {"coordinates":[-83.069204,39.988542],"type":"Point"}
}