{
  "type": "Feature",
  "properties": {
    "addr:full":"7237 W Chester Rd West Chester OH 45069",
    "addr:housenumber":"7237",
    "addr:postcode":"45069",
    "addr:street":"W Chester Rd",
    "iso:country":"US",
    "sg:address":"7237 W Chester Rd",
    "sg:city":"West Chester",
    "sg:classifiers":[
        {
            "category":"Real Estate",
            "subcategory":"Real Estate Agent",
            "type":"Services"
        }
    ],
    "sg:phone":"+1 513 755 3800",
    "sg:postcode":"45069",
    "sg:province":"OH",
    "wof:name":"Beckmark Inc",
    "wof:placetype":"venue"
},
  "geometry": {"coordinates":[-84.383931,39.320604],"type":"Point"}
}