{
  "type": "Feature",
  "properties": {
    "addr:full": "1018 Robinson Rd Wooster OH 44691",
    "addr:housenumber": "1018",
    "addr:postcode": "44691",
    "addr:street": "Robinson Rd",
    "iso:country": "US",
    "sg:address": "1018 Robinson Rd",
    "sg:city": "Wooster",
    "sg:classifiers": [
      {
        "category": "Professional",
        "type": "Services"
      }
    ],
    "sg:phone": "+1 330 264 9451",
    "sg:postcode": "44691",
    "sg:province": "OH",
    "wof:name": "Celebrations In A Box",
    "wof:placetype": "venue"
  },
  "geometry": {"coordinates":[-81.928967,40.787544],"type":"Point"}
}
