{
  "type": "Feature",
  "properties": {
    "addr:full": "4073 E 82nd St Cleveland OH 44105",
    "addr:housenumber": "4073",
    "addr:postcode": "44105",
    "addr:street": "E 82Nd St",
    "iso:country": "US",
    "sg:address": "4073 E 82nd St",
    "sg:city": "Cleveland",
    "sg:classifiers": [
      {
        "category": "Home \u0026 Garden",
        "subcategory": "Building Materials",
        "type": "Retail Goods"
      },
      {
        "category": "Building \u0026 Trades",
        "subcategory": "Construction",
        "type": "Services"
      }
    ],
    "sg:phone": "+1 216 271 2420",
    "sg:postcode": "44105",
    "sg:province": "OH",
    "sg:tags": [
      "insulation",
      "contractor"
    ],
    "wof:name": "Fiberglass Roof Insulation Co.",
    "wof:placetype": "venue"
  },
  "geometry": {"coordinates":[-81.627991,41.447989],"type":"Point"}
}
