{
  "type": "Feature",
  "properties": {
    "iso:country":"US",
    "sg:address":"1360 S Cleveland Massillon Rd",
    "sg:city":"Copley",
    "sg:classifiers":[
        {
            "category":"Home & Garden",
            "subcategory":"Furniture",
            "type":"Retail Goods"
        }
    ],
    "sg:phone":"+1 330 666 9959",
    "sg:postcode":"44321",
    "sg:province":"OH",
    "wof:name":"Amish Acres LLC",
    "wof:placetype":"venue"
},
  "geometry": {"coordinates":[-81.644685,41.101126],"type":"Point"}
}