{
  "type": "Feature",
  "properties": {
    "addr:full": "1360 S Cleveland Massillon Rd Copley OH 44321",
    "addr:housenumber": "1360",
    "addr:postcode": "44321",
    "addr:street": "S Cleveland Massillon Rd",
    "iso:country": "US",
    "sg:address": "1360 S Cleveland Massillon Rd",
    "sg:city": "Copley",
    "sg:classifiers": [
      {
        "category": "Home \u0026 Garden",
        "subcategory": "Furniture",
        "type": "Retail Goods"
      }
    ],
    "sg:phone": "+1 330 666 9959",
    "sg:postcode": "44321",
    "sg:province": "OH",
    "wof:name": "Amish Acres LLC",
    "wof:placetype": "venue"
  },
  "geometry": {"coordinates":[-81.644685,41.101126],"type":"Point"}
}
