{
  "type": "Feature",
  "properties": {
    "addr:full": "1860 E Perry St Port Clinton OH 43452",
    "addr:housenumber": "1860",
    "addr:postcode": "43452",
    "addr:street": "E Perry St",
    "iso:country": "US",
    "sg:address": "1860 E Perry St",
    "sg:city": "Port Clinton",
    "sg:classifiers": [
      {
        "category": "Social Services",
        "type": "Services"
      }
    ],
    "sg:phone": "+1 419 734 6299",
    "sg:postcode": "43452",
    "sg:province": "OH",
    "sg:tags": [
      "probation"
    ],
    "wof:name": "Ottawa County Probation",
    "wof:placetype": "venue"
  },
  "geometry": {"coordinates":[-82.911715,41.514779],"type":"Point"}
}
