{
  "type": "Feature",
  "properties": {
    "iso:country":"US",
    "sg:address":"1120 S Norwalk Rd W",
    "sg:city":"Norwalk",
    "sg:classifiers":[
        {
            "category":"Retail",
            "subcategory":"Auto Repair",
            "type":"Services"
        }
    ],
    "sg:phone":"+1 419 668 6902",
    "sg:postcode":"44857",
    "sg:province":"OH",
    "sg:tags":[
        "repairing",
        "automobile"
    ],
    "wof:name":"Snyder Automotive",
    "wof:placetype":"venue"
},
  "geometry": {"coordinates":[-82.629328,41.221303],"type":"Point"}
}