{
  "type": "Feature",
  "properties": {
    "addr:full": "14271 Broad St SW Pataskala OH 43062",
    "addr:housenumber": "14271",
    "addr:postcode": "43062",
    "addr:street": "Broad St Sw",
    "iso:country": "US",
    "sg:address": "14271 Broad St SW",
    "sg:city": "Pataskala",
    "sg:classifiers": [
      {
        "category": "Freight",
        "type": "Transportation"
      }
    ],
    "sg:phone": "+1 740 927 0483",
    "sg:postcode": "43062",
    "sg:province": "OH",
    "sg:tags": [
      "operator",
      "trucking"
    ],
    "wof:name": "Eli Matalon Trnsp Trckg",
    "wof:placetype": "venue"
  },
  "geometry": {"coordinates":[-82.75217,39.990209],"type":"Point"}
}
