{
  "type": "Feature",
  "properties": {
    "iso:country":"US",
    "sg:address":"14271 Broad St SW",
    "sg:city":"Pataskala",
    "sg:classifiers":[
        {
            "category":"Freight",
            "type":"Transportation"
        }
    ],
    "sg:phone":"+1 740 927 0483",
    "sg:postcode":"43062",
    "sg:province":"OH",
    "sg:tags":[
        "operator",
        "trucking"
    ],
    "wof:name":"Eli Matalon Trnsp Trckg",
    "wof:placetype":"venue"
},
  "geometry": {"coordinates":[-82.75217000000001,39.990209],"type":"Point"}
}