{
  "type": "Feature",
  "properties": {
    "iso:country":"US",
    "sg:address":"2150 Woodward Ave",
    "sg:city":"Columbus",
    "sg:classifiers":[
        {
            "category":"Government",
            "subcategory":"Office",
            "type":"Public Place"
        }
    ],
    "sg:phone":"+1 614 258 6513",
    "sg:postcode":"43219",
    "sg:province":"OH",
    "sg:tags":[
        "development"
    ],
    "wof:name":"Hebron Community Dev Corp",
    "wof:placetype":"venue"
},
  "geometry": {"coordinates":[-82.94683499999999,39.99211],"type":"Point"}
}