{
  "type": "Feature",
  "properties": {
    "addr:full":"3 N Main St Marshallville OH 44645",
    "addr:housenumber":"3",
    "addr:postcode":"44645",
    "addr:street":"N Main St",
    "iso:country":"US",
    "sg:address":"3 N Main St",
    "sg:city":"Marshallville",
    "sg:classifiers":[
        {
            "category":"Professional",
            "subcategory":"Business Services",
            "type":"Services"
        },
        {
            "category":"Government",
            "subcategory":"Post Office",
            "type":"Public Place"
        }
    ],
    "sg:phone":"+1 330 855 3681",
    "sg:postcode":"44645",
    "sg:province":"OH",
    "sg:tags":[
        "mail",
        "shipping"
    ],
    "sg:website":"http://www.usps.gov",
    "wof:name":"USPS - United States Post Office",
    "wof:placetype":"venue"
},
  "geometry": {"coordinates":[-81.73367,40.900991],"type":"Point"}
}