{
  "type": "Feature",
  "properties": {
    "iso:country":"US",
    "sg:address":"3356 Vagabond Ln",
    "sg:city":"Dayton",
    "sg:classifiers":[
        {
            "category":"Building & Trades",
            "subcategory":"Construction",
            "type":"Services"
        }
    ],
    "sg:phone":"+1 937 236 3214",
    "sg:postcode":"45424",
    "sg:province":"OH",
    "sg:tags":[
        "house"
    ],
    "wof:name":"Jab Parker Construction Inc",
    "wof:placetype":"venue"
},
  "geometry": {"coordinates":[-84.122168,39.798488],"type":"Point"}
}