{
  "type": "Feature",
  "properties": {
    "iso:country":"US",
    "sg:address":"6445 State Rte 446",
    "sg:city":"Canfield",
    "sg:classifiers":[
        {
            "category":"Building & Trades",
            "subcategory":"Construction",
            "type":"Services"
        }
    ],
    "sg:phone":"+1 330 533 3897",
    "sg:postcode":"44406",
    "sg:province":"OH",
    "sg:tags":[
        "contractor"
    ],
    "wof:name":"Victor Rucci Construction",
    "wof:placetype":"venue"
},
  "geometry": {"coordinates":[-80.769834,41.016619],"type":"Point"}
}