{
  "type": "Feature",
  "properties": {
    "iso:country":"US",
    "sg:address":"11001 Union Ave",
    "sg:city":"Cleveland",
    "sg:classifiers":[
        {
            "category":"Freight",
            "type":"Transportation"
        },
        {
            "category":"Home & Garden",
            "subcategory":"Building Materials",
            "type":"Retail Goods"
        }
    ],
    "sg:phone":"+1 216 341 3130",
    "sg:postcode":"44105",
    "sg:province":"OH",
    "sg:tags":[
        "warehouse",
        "plumbing",
        "fixture",
        "supply"
    ],
    "sg:website":"www.clevelandplumbingsupply.com",
    "wof:name":"Cleveland Plumbing Supply Co",
    "wof:placetype":"venue"
},
  "geometry": {"coordinates":[-81.60691199999999,41.463625],"type":"Point"}
}