{
  "type": "Feature",
  "properties": {
    "addr:full": "11001 Union Ave Cleveland OH 44105",
    "addr:housenumber": "11001",
    "addr:postcode": "44105",
    "addr:street": "Union Ave",
    "iso:country": "US",
    "sg:address": "11001 Union Ave",
    "sg:city": "Cleveland",
    "sg:classifiers": [
      {
        "category": "Freight",
        "type": "Transportation"
      },
      {
        "category": "Home \u0026 Garden",
        "subcategory": "Building Materials",
        "type": "Retail Goods"
      }
    ],
    "sg:phone": "+1 216 341 3130",
    "sg:postcode": "44105",
    "sg:province": "OH",
    "sg:tags": [
      "warehouse",
      "plumbing",
      "fixture",
      "supply"
    ],
    "sg:website": "www.clevelandplumbingsupply.com",
    "wof:name": "Cleveland Plumbing Supply Co",
    "wof:placetype": "venue"
  },
  "geometry": {"coordinates":[-81.606912,41.463625],"type":"Point"}
}
