{
  "type": "Feature",
  "properties": {
    "iso:country":"US",
    "sg:address":"7900 Depot Rd",
    "sg:city":"Ashtabula",
    "sg:classifiers":[
        {
            "category":"Organizations",
            "subcategory":"Religious Organization",
            "type":"Services"
        }
    ],
    "sg:phone":"+1 440 969 1562",
    "sg:postcode":"44004",
    "sg:province":"OH",
    "sg:tags":[
        "church"
    ],
    "wof:name":"Saybrook United Methodist Chr",
    "wof:placetype":"venue"
},
  "geometry": {"coordinates":[-80.870728,41.825917],"type":"Point"}
}