{
  "type": "Feature",
  "properties": {
    "addr:full": "10988 Welton Rd NE Bolivar OH 44612",
    "addr:housenumber": "10988",
    "addr:postcode": "44612",
    "addr:street": "Welton Rd Ne Bolivar",
    "iso:country": "US",
    "sg:address": "10988 Welton Rd NE",
    "sg:city": "Bolivar",
    "sg:classifiers": [
      {
        "category": "Building \u0026 Trades",
        "subcategory": "Construction",
        "type": "Services"
      }
    ],
    "sg:phone": "+1 330 874 3516",
    "sg:postcode": "44612",
    "sg:province": "OH",
    "sg:tags": [
      "house"
    ],
    "wof:name": "Reliable Home Improvements",
    "wof:placetype": "venue"
  },
  "geometry": {"coordinates":[-81.412985,40.642354],"type":"Point"}
}
