{
  "type": "Feature",
  "properties": {
    "iso:country":"US",
    "sg:address":"10988 Welton Rd NE",
    "sg:city":"Bolivar",
    "sg:classifiers":[
        {
            "category":"Building & Trades",
            "subcategory":"Construction",
            "type":"Services"
        }
    ],
    "sg:phone":"+1 330 874 3516",
    "sg:postcode":"44612",
    "sg:province":"OH",
    "sg:tags":[
        "house"
    ],
    "wof:name":"Reliable Home Improvements",
    "wof:placetype":"venue"
},
  "geometry": {"coordinates":[-81.41298500000001,40.642354],"type":"Point"}
}