{
  "type": "Feature",
  "properties": {
    "iso:country":"US",
    "sg:address":"6000 Freedom Square Dr",
    "sg:city":"Cleveland",
    "sg:classifiers":[
        {
            "category":"Professional",
            "subcategory":"Computer Services",
            "type":"Services"
        }
    ],
    "sg:phone":"+1 216 654 1800",
    "sg:postcode":"44131",
    "sg:province":"OH",
    "wof:name":"Satyam Computer Svc LTD",
    "wof:placetype":"venue"
},
  "geometry": {"coordinates":[-81.659509,41.399322],"type":"Point"}
}