{
  "type": "Feature",
  "properties": {
    "addr:full":"122 Donald Dr Fairfield OH 45014",
    "addr:housenumber":"122",
    "addr:postcode":"45014",
    "addr:street":"Donald Dr",
    "iso:country":"US",
    "sg:address":"122 Donald Dr",
    "sg:city":"Fairfield",
    "sg:classifiers":[
        {
            "category":"Building & Trades",
            "subcategory":"Construction",
            "type":"Services"
        }
    ],
    "sg:phone":"+1 513 829 1980",
    "sg:postcode":"45014",
    "sg:province":"OH",
    "sg:tags":[
        "specializing",
        "new",
        "general",
        "contractor"
    ],
    "wof:name":"Darien Homes Inc",
    "wof:placetype":"venue"
},
  "geometry": {"coordinates":[-84.537243,39.344027],"type":"Point"}
}