{
  "type": "Feature",
  "properties": {
    "iso:country":"US",
    "sg:address":"4185 E Main St",
    "sg:city":"Columbus",
    "sg:classifiers":[
        {
            "category":"Professional",
            "subcategory":"Lawyer & Legal Services",
            "type":"Services"
        }
    ],
    "sg:phone":"+1 614 338 1800",
    "sg:postcode":"43213",
    "sg:province":"OH",
    "sg:tags":[
        "attorney"
    ],
    "wof:name":"Todd W Barstow",
    "wof:placetype":"venue"
},
  "geometry": {"coordinates":[-82.88875,39.955816],"type":"Point"}
}