{
  "type": "Feature",
  "properties": {
    "iso:country":"US",
    "sg:address":"815 Adair Ave",
    "sg:city":"Zanesville",
    "sg:classifiers":[
        {
            "category":"Personal",
            "subcategory":"Beauty Salon",
            "type":"Services"
        }
    ],
    "sg:phone":"+1 740 454 4495",
    "sg:postcode":"43701",
    "sg:province":"OH",
    "sg:tags":[
        "manicuring"
    ],
    "wof:name":"Creeks Girls",
    "wof:placetype":"venue"
},
  "geometry": {"coordinates":[-82.014866,39.953415],"type":"Point"}
}