{
  "type": "Feature",
  "properties": {
    "iso:country":"US",
    "sg:address":"427 E Broadway St",
    "sg:city":"Toledo",
    "sg:classifiers":[
        {
            "category":"Shopping",
            "subcategory":"Florist",
            "type":"Retail Goods"
        }
    ],
    "sg:phone":"+1 419 691 5747",
    "sg:postcode":"43605",
    "sg:province":"OH",
    "wof:name":"Hirzel Brothers Florist",
    "wof:placetype":"venue"
},
  "geometry": {"coordinates":[-83.51579099999999,41.64342],"type":"Point"}
}