{
  "type": "Feature",
  "properties": {
    "addr:full": "427 E Broadway St Toledo OH 43605",
    "addr:housenumber": "427",
    "addr:postcode": "43605",
    "addr:street": "E Broadway St",
    "iso:country": "US",
    "sg:address": "427 E Broadway St",
    "sg:city": "Toledo",
    "sg:classifiers": [
      {
        "category": "Shopping",
        "subcategory": "Florist",
        "type": "Retail Goods"
      }
    ],
    "sg:phone": "+1 419 691 5747",
    "sg:postcode": "43605",
    "sg:province": "OH",
    "wof:name": "Hirzel Brothers Florist",
    "wof:placetype": "venue"
  },
  "geometry": {"coordinates":[-83.515791,41.64342],"type":"Point"}
}
