{
  "type": "Feature",
  "properties": {
    "iso:country":"US",
    "sg:address":"2773 Manchester Ave NW",
    "sg:city":"North Lawrence",
    "sg:classifiers":[
        {
            "category":"Home & Garden",
            "subcategory":"Furniture",
            "type":"Retail Goods"
        }
    ],
    "sg:phone":"+1 330 832 2309",
    "sg:postcode":"44666",
    "sg:province":"OH",
    "sg:tags":[
        "custom"
    ],
    "wof:name":"Mothers Work",
    "wof:placetype":"venue"
},
  "geometry": {"coordinates":[-81.60112599999999,40.819081],"type":"Point"}
}