{
  "type": "Feature",
  "properties": {
    "addr:full": "3914 Miami Rd Cincinnati OH 45227",
    "addr:housenumber": "3914",
    "addr:postcode": "45227",
    "addr:street": "Miami Rd",
    "iso:country": "US",
    "sg:address": "3914 Miami Rd",
    "sg:city": "Cincinnati",
    "sg:classifiers": [
      {
        "category": "Professional",
        "subcategory": "Accounting \u0026 Tax Preparation",
        "type": "Services"
      }
    ],
    "sg:phone": "+1 513 272 6217",
    "sg:postcode": "45227",
    "sg:province": "OH",
    "sg:tags": [
      "accountant"
    ],
    "wof:name": "Michael Ferguson \u0026 Assoc",
    "wof:placetype": "venue"
  },
  "geometry": {"coordinates":[-84.373766,39.145442],"type":"Point"}
}
