{
  "type": "Feature",
  "properties": {
    "addr:full": "1348 Cherry Bark Ct Newark OH 43056",
    "addr:housenumber": "1348",
    "addr:postcode": "43056",
    "addr:street": "Cherry Bark Ct",
    "iso:country": "US",
    "sg:address": "1348 Cherry Bark Ct",
    "sg:city": "Newark",
    "sg:classifiers": [
      {
        "category": "Building \u0026 Trades",
        "subcategory": "Construction",
        "type": "Services"
      }
    ],
    "sg:phone": "+1 740 366 2709",
    "sg:postcode": "43056",
    "sg:province": "OH",
    "sg:tags": [
      "carpentry",
      "contractor"
    ],
    "wof:name": "Pettit Carpenter Service",
    "wof:placetype": "venue"
  },
  "geometry": {"coordinates":[-82.430788,40.017804],"type":"Point"}
}
