{
  "type": "Feature",
  "properties": {
    "addr:full": "3245 E Livingston Ave Columbus OH 43227",
    "addr:housenumber": "3245",
    "addr:postcode": "43227",
    "addr:street": "E Livingston Ave",
    "iso:country": "US",
    "sg:address": "3245 E Livingston Ave",
    "sg:city": "Columbus",
    "sg:classifiers": [
      {
        "category": "Insurance",
        "subcategory": "Insurance Agent",
        "type": "Services"
      }
    ],
    "sg:phone": "+1 614 559 3500",
    "sg:postcode": "43227",
    "sg:province": "OH",
    "wof:name": "Highchek Ltd",
    "wof:placetype": "venue"
  },
  "geometry": {"coordinates":[-82.90866,39.946515],"type":"Point"}
}
