{
  "type": "Feature",
  "properties": {
    "addr:full":"7711 W Lake Blvd Kent OH 44240",
    "addr:housenumber":"7711",
    "addr:postcode":"44240",
    "addr:street":"W Lake Blvd",
    "iso:country":"US",
    "sg:address":"7711 W Lake Blvd",
    "sg:city":"Kent",
    "sg:classifiers":[
        {
            "category":"Wholesale",
            "subcategory":"Home Furnishings",
            "type":"Manufacturing & Wholesale Goods"
        }
    ],
    "sg:phone":"+1 330 673 1399",
    "sg:postcode":"44240",
    "sg:province":"OH",
    "sg:tags":[
        "consulting",
        "kitchenware"
    ],
    "wof:name":"Herbert Enterprises Inc",
    "wof:placetype":"venue"
},
  "geometry": {"coordinates":[-81.348161,41.199707],"type":"Point"}
}