{
  "type": "Feature",
  "properties": {
    "addr:full":"130 W State St Alliance OH 44601",
    "addr:housenumber":"130",
    "addr:postcode":"44601",
    "addr:street":"W State St",
    "iso:country":"US",
    "sg:address":"130 W State St",
    "sg:city":"Alliance",
    "sg:classifiers":[
        {
            "category":"Retail",
            "subcategory":"Car Wash",
            "type":"Services"
        }
    ],
    "sg:phone":"+1 330 823 8578",
    "sg:postcode":"44601",
    "sg:province":"OH",
    "sg:tags":[
        "automobile",
        "detail",
        "clean"
    ],
    "wof:name":"Nicky's Car Care",
    "wof:placetype":"venue"
},
  "geometry": {"coordinates":[-81.107975,40.901639],"type":"Point"}
}