{
  "type": "Feature",
  "properties": {
    "addr:full": "1065 Western Ave Chillicothe OH 45601",
    "addr:housenumber": "1065",
    "addr:postcode": "45601",
    "addr:street": "Western Ave",
    "iso:country": "US",
    "sg:address": "1065 Western Ave",
    "sg:city": "Chillicothe",
    "sg:classifiers": [
      {
        "category": "Restaurant",
        "type": "Food \u0026 Drink"
      }
    ],
    "sg:menulink": "http://www.allmenus.com/oh/scioto/42840-bob-evans/menu/",
    "sg:phone": "+1 740 773 0728",
    "sg:postcode": "45601",
    "sg:province": "OH",
    "sg:tags": [
      "american"
    ],
    "wof:name": "Bob Evans",
    "wof:placetype": "venue"
  },
  "geometry": {"coordinates":[-83.012313,39.333026],"type":"Point"}
}
