{
  "type": "Feature",
  "properties": {
    "addr:full": "494 Dow Ave Columbus OH 43211",
    "addr:housenumber": "494",
    "addr:postcode": "43211",
    "addr:street": "Dow Ave",
    "iso:country": "US",
    "sg:address": "494 Dow Ave",
    "sg:city": "Columbus",
    "sg:classifiers": [
      {
        "category": "Manufacturing",
        "subcategory": "Tools \u0026 Machinery",
        "type": "Manufacturing \u0026 Wholesale Goods"
      }
    ],
    "sg:phone": "+1 614 294 6137",
    "sg:postcode": "43211",
    "sg:province": "OH",
    "sg:tags": [
      "machine",
      "shop",
      "job"
    ],
    "wof:name": "Kyron Tool \u0026 Machine Co Inc",
    "wof:placetype": "venue"
  },
  "geometry": {"coordinates":[-82.991893,39.992406],"type":"Point"}
}
