{
  "type": "Feature",
  "properties": {
    "addr:full":"3782 Edison St NW Uniontown OH 44685",
    "addr:housenumber":"3782",
    "addr:postcode":"44685",
    "addr:street":"Edison St Nw",
    "iso:country":"US",
    "sg:address":"3782 Edison St NW",
    "sg:city":"Uniontown",
    "sg:classifiers":[
        {
            "category":"Professional",
            "subcategory":"Accounting & Tax Preparation",
            "type":"Services"
        }
    ],
    "sg:phone":"+1 330 699 9662",
    "sg:postcode":"44685",
    "sg:province":"OH",
    "sg:tags":[
        "return",
        "filing"
    ],
    "wof:name":"Taxes Made Simple",
    "wof:placetype":"venue"
},
  "geometry": {"coordinates":[-81.414439,40.976052],"type":"Point"}
}