{
  "type": "Feature",
  "properties": {
    "addr:full":"600 Bellbrook Ave Xenia OH 45385",
    "addr:housenumber":"600",
    "addr:postcode":"45385",
    "addr:street":"Bellbrook Ave",
    "iso:country":"US",
    "sg:address":"600 Bellbrook Ave",
    "sg:city":"Xenia",
    "sg:classifiers":[
        {
            "category":"Manufacturing",
            "subcategory":"Electronics",
            "type":"Manufacturing & Wholesale Goods"
        }
    ],
    "sg:phone":"+1 937 372 7579",
    "sg:postcode":"45385",
    "sg:province":"OH",
    "sg:tags":[
        "mfg",
        "tv",
        "research",
        "radio",
        "comm",
        "physical"
    ],
    "wof:name":"Eis",
    "wof:placetype":"venue"
},
  "geometry": {"coordinates":[-83.944182,39.679456],"type":"Point"}
}