{
  "type": "Feature",
  "properties": {
    "addr:full":"8804 W Central Ave Sylvania OH 43560",
    "addr:housenumber":"8804",
    "addr:postcode":"43560",
    "addr:street":"W Central Ave",
    "iso:country":"US",
    "sg:address":"8804 W Central Ave",
    "sg:city":"Sylvania",
    "sg:classifiers":[
        {
            "category":"Freight",
            "type":"Transportation"
        }
    ],
    "sg:phone":"+1 419 829 7627",
    "sg:postcode":"43560",
    "sg:province":"OH",
    "sg:tags":[
        "operator",
        "trucking"
    ],
    "wof:name":"Enterprise Transportation Co",
    "wof:placetype":"venue"
},
  "geometry": {"coordinates":[-83.749247,41.673666],"type":"Point"}
}