{
  "type": "Feature",
  "properties": {
    "addr:full":"5241 Southwyck Blvd Toledo OH 43614",
    "addr:housenumber":"5241",
    "addr:postcode":"43614",
    "addr:street":"Southwyck Blvd",
    "iso:country":"US",
    "sg:address":"5241 Southwyck Blvd",
    "sg:city":"Toledo",
    "sg:classifiers":[
        {
            "category":"Professional",
            "subcategory":"Employment Agencies",
            "type":"Services"
        }
    ],
    "sg:phone":"+1 419 868 6932",
    "sg:postcode":"43614",
    "sg:province":"OH",
    "sg:tags":[
        "help",
        "supply"
    ],
    "wof:name":"Unlimited Medstaff of Georgia",
    "wof:placetype":"venue"
},
  "geometry": {"coordinates":[-83.667537,41.60009],"type":"Point"}
}