{
  "type": "Feature",
  "properties": {
    "addr:full":"820 Wallace Ave Milford OH 45150",
    "addr:housenumber":"820",
    "addr:postcode":"45150",
    "addr:street":"Wallace Ave",
    "iso:country":"US",
    "sg:address":"820 Wallace Ave",
    "sg:city":"Milford",
    "sg:classifiers":[
        {
            "category":"Professional",
            "subcategory":"Business Services",
            "type":"Services"
        }
    ],
    "sg:phone":"+1 513 248 1916",
    "sg:postcode":"45150",
    "sg:province":"OH",
    "sg:tags":[
        "plant",
        "design",
        "maintenance"
    ],
    "wof:name":"Plant Co",
    "wof:placetype":"venue"
},
  "geometry": {"coordinates":[-84.287398,39.176105],"type":"Point"}
}