{
  "type": "Feature",
  "properties": {
    "addr:full": "14379 Rock Creek Rd Chardon OH 44024",
    "addr:housenumber": "14379",
    "addr:postcode": "44024",
    "addr:street": "Rock Creek Rd",
    "iso:country": "US",
    "sg:address": "14379 Rock Creek Rd",
    "sg:city": "Chardon",
    "sg:classifiers": [
      {
        "category": "Building \u0026 Trades",
        "subcategory": "Construction",
        "type": "Services"
      }
    ],
    "sg:phone": "+1 440 286 6724",
    "sg:postcode": "44024",
    "sg:province": "OH",
    "sg:tags": [
      "home",
      "builder"
    ],
    "wof:name": "Craft Builders Inc",
    "wof:placetype": "venue"
  },
  "geometry": {"coordinates":[-81.129612,41.618],"type":"Point"}
}
