{
  "type": "Feature",
  "properties": {
    "addr:full":"1791 W Holtzmuller Rd West Manchester OH 45382",
    "addr:housenumber":"1791",
    "addr:postcode":"45382",
    "addr:street":"W Holtzmuller Rd",
    "iso:country":"US",
    "sg:address":"1791 W Holtzmuller Rd",
    "sg:city":"West Manchester",
    "sg:classifiers":[
        {
            "category":"Farming",
            "subcategory":"Livestock Farm",
            "type":"Manufacturing & Wholesale Goods"
        }
    ],
    "sg:phone":"+1 937 273 8100",
    "sg:postcode":"45382",
    "sg:province":"OH",
    "sg:tags":[
        "beef",
        "feedlot",
        "cattle"
    ],
    "wof:name":"Doug Fark",
    "wof:placetype":"venue"
},
  "geometry": {"coordinates":[-84.66010799999999,39.90935],"type":"Point"}
}