{
  "type": "Feature",
  "properties": {
    "iso:country":"US",
    "sg:address":"520 S Main St",
    "sg:city":"Akron",
    "sg:classifiers":[
        {
            "category":"Wholesale",
            "subcategory":"Office Equipment",
            "type":"Manufacturing & Wholesale Goods"
        }
    ],
    "sg:phone":"+1 330 453 9343",
    "sg:postcode":"44311",
    "sg:province":"OH",
    "sg:tags":[
        "supply"
    ],
    "wof:name":"Roach Reid Office Systems",
    "wof:placetype":"venue"
},
  "geometry": {"coordinates":[-81.52443100000001,41.073244],"type":"Point"}
}