{
  "type": "Feature",
  "properties": {
    "addr:full":"9263 Ravenna Rd Twinsburg OH 44087",
    "addr:housenumber":"9263",
    "addr:postcode":"44087",
    "addr:street":"Ravenna Rd",
    "iso:country":"US",
    "sg:address":"9263 Ravenna Rd",
    "sg:city":"Twinsburg",
    "sg:classifiers":[
        {
            "category":"Professional",
            "subcategory":"Management & Consulting",
            "type":"Services"
        }
    ],
    "sg:phone":"+1 330 379 3282",
    "sg:postcode":"44087",
    "sg:province":"OH",
    "sg:tags":[
        "communications",
        "consultant"
    ],
    "wof:name":"Procom Technologies Inc",
    "wof:placetype":"venue"
},
  "geometry": {"coordinates":[-81.423089,41.305079],"type":"Point"}
}