{
  "type": "Feature",
  "properties": {
    "iso:country":"US",
    "sg:address":"4070 S Firestone Rd",
    "sg:city":"Shreve",
    "sg:classifiers":[
        {
            "category":"Manufacturing",
            "subcategory":"Apparel",
            "type":"Manufacturing & Wholesale Goods"
        }
    ],
    "sg:phone":"+1 330 264 9817",
    "sg:postcode":"44676",
    "sg:province":"OH",
    "sg:tags":[
        "dress",
        "mfg"
    ],
    "wof:name":"Making Memories",
    "wof:placetype":"venue"
},
  "geometry": {"coordinates":[-82.062426,40.750299],"type":"Point"}
}