{
  "type": "Feature",
  "properties": {
    "addr:full":"6951 Alan Schwarzwalder St Columbus OH 43217",
    "addr:housenumber":"6951",
    "addr:postcode":"43217",
    "addr:street":"Alan Schwarzwalder St",
    "iso:country":"US",
    "sg:address":"6951 Alan Schwarzwalder St",
    "sg:city":"Columbus",
    "sg:classifiers":[
        {
            "category":"Wholesale",
            "subcategory":"Machinery & Supplies",
            "type":"Manufacturing & Wholesale Goods"
        }
    ],
    "sg:phone":"+1 614 497 1500",
    "sg:postcode":"43217",
    "sg:province":"OH",
    "sg:tags":[
        "industrial"
    ],
    "wof:name":"Timken Company",
    "wof:placetype":"venue"
},
  "geometry": {"coordinates":[-82.93767099999999,39.825701],"type":"Point"}
}