{
  "type": "Feature",
  "properties": {
    "addr:full": "13804 Riley Rd Milan OH 44846",
    "addr:housenumber": "13804",
    "addr:postcode": "44846",
    "addr:street": "Riley Rd",
    "iso:country": "US",
    "sg:address": "13804 Riley Rd",
    "sg:city": "Milan",
    "sg:classifiers": [
      {
        "category": "Wholesale",
        "subcategory": "Tobacco Products",
        "type": "Manufacturing \u0026 Wholesale Goods"
      }
    ],
    "sg:phone": "+1 419 499 9994",
    "sg:postcode": "44846",
    "sg:province": "OH",
    "wof:name": "EBY-Brown Company LP",
    "wof:placetype": "venue"
  },
  "geometry": {"coordinates":[-82.598425,41.301387],"type":"Point"}
}
