{
  "type": "Feature",
  "properties": {
    "iso:country":"US",
    "sg:address":"13804 Riley Rd",
    "sg:city":"Milan",
    "sg:classifiers":[
        {
            "category":"Wholesale",
            "subcategory":"Tobacco Products",
            "type":"Manufacturing & Wholesale Goods"
        }
    ],
    "sg:phone":"+1 419 499 9994",
    "sg:postcode":"44846",
    "sg:province":"OH",
    "wof:name":"EBY-Brown Company LP",
    "wof:placetype":"venue"
},
  "geometry": {"coordinates":[-82.59842500000001,41.301387],"type":"Point"}
}