{
  "type": "Feature",
  "properties": {
    "iso:country":"US",
    "sg:address":"885 S Twp Rd 15",
    "sg:city":"Tiffin",
    "sg:phone":"+1 419 447 9184",
    "sg:postcode":"44883",
    "sg:province":"OH",
    "sg:tags":[
        "farm",
        "corn",
        "soybean"
    ],
    "wof:name":"Thomas Warnement",
    "wof:placetype":"venue"
},
  "geometry": {"coordinates":[-83.131018,41.109916],"type":"Point"}
}