{
  "type": "Feature",
  "properties": {
    "iso:country":"US",
    "sg:address":"36840 Detroit Rd",
    "sg:city":"Avon",
    "sg:classifiers":[
        {
            "category":"Shopping",
            "subcategory":"Gifts & Souvenirs",
            "type":"Retail Goods"
        }
    ],
    "sg:phone":"+1 440 934 3457",
    "sg:postcode":"44011",
    "sg:province":"OH",
    "sg:tags":[
        "shop"
    ],
    "wof:name":"Details Gifts For The Heart",
    "wof:placetype":"venue"
},
  "geometry": {"coordinates":[-82.035051,41.45176],"type":"Point"}
}