{
  "type": "Feature",
  "properties": {
    "iso:country":"US",
    "sg:address":"24 Morris St",
    "sg:city":"Shelby",
    "sg:classifiers":[
        {
            "category":"Health Services",
            "subcategory":"Doctor",
            "type":"Services"
        }
    ],
    "sg:phone":"+1 419 347 4040",
    "sg:postcode":"44875",
    "sg:province":"OH",
    "sg:tags":[
        "family"
    ],
    "wof:name":"Demers Marion C MD",
    "wof:placetype":"venue"
},
  "geometry": {"coordinates":[-82.67346499999999,40.882181],"type":"Point"}
}