{
  "type": "Feature",
  "properties": {
    "addr:full": "5105 Som Center Rd Willoughby OH 44094",
    "addr:housenumber": "5105",
    "addr:postcode": "44094",
    "addr:street": "Som Center Rd",
    "iso:country": "US",
    "sg:address": "5105 Som Center Rd",
    "sg:city": "Willoughby",
    "sg:classifiers": [
      {
        "category": "Health Services",
        "subcategory": "Doctor",
        "type": "Services"
      }
    ],
    "sg:phone": "+1 440 975 1494",
    "sg:postcode": "44094",
    "sg:province": "OH",
    "sg:tags": [
      "clinic"
    ],
    "wof:name": "Ohio Renal Care Group",
    "wof:placetype": "venue"
  },
  "geometry": {"coordinates":[-81.440036,41.624849],"type":"Point"}
}
