{
  "type": "Feature",
  "properties": {
    "iso:country":"US",
    "sg:address":"1500 Polaris Pkwy",
    "sg:city":"Columbus",
    "sg:classifiers":[
        {
            "category":"Bakery",
            "type":"Food & Drink"
        }
    ],
    "sg:menulink":"http://www.allmenus.com/oh/columbus-city/220135-auntie-annes-pretzels/menu/",
    "sg:phone":"+1 614 844 5350",
    "sg:postcode":"43240",
    "sg:province":"OH",
    "sg:tags":[
        "american",
        "pastry"
    ],
    "wof:name":"Auntie Anne's Pretzels",
    "wof:placetype":"venue"
},
  "geometry": {"coordinates":[-82.977676,40.141704],"type":"Point"}
}