{
  "type": "Feature",
  "properties": {
    "addr:full":"1265 S Cleveland Massillon Rd Copley OH 44321",
    "addr:housenumber":"1265",
    "addr:postcode":"44321",
    "addr:street":"S Cleveland Massillon Rd",
    "iso:country":"US",
    "sg:address":"1265 S Cleveland Massillon Rd",
    "sg:city":"Copley",
    "sg:classifiers":[
        {
            "category":"Shopping",
            "subcategory":"Used Merchandise",
            "type":"Retail Goods"
        }
    ],
    "sg:phone":"+1 330 666 1958",
    "sg:postcode":"44321",
    "sg:province":"OH",
    "sg:tags":[
        "antique"
    ],
    "wof:name":"Wizard Of Odds II",
    "wof:placetype":"venue"
},
  "geometry": {"coordinates":[-81.64453,41.106183],"type":"Point"}
}