{
  "type": "Feature",
  "properties": {
    "addr:full":"110 W Main St Dayton OH 45426",
    "addr:housenumber":"110",
    "addr:postcode":"45426",
    "addr:street":"W Main St",
    "iso:country":"US",
    "sg:address":"110 W Main St",
    "sg:city":"Dayton",
    "sg:classifiers":[
        {
            "category":"Retail",
            "subcategory":"Funeral Services",
            "type":"Services"
        }
    ],
    "sg:phone":"+1 937 837 1272",
    "sg:postcode":"45426",
    "sg:province":"OH",
    "sg:tags":[
        "director",
        "home"
    ],
    "wof:name":"Rogers Funeral Homes Inc",
    "wof:placetype":"venue"
},
  "geometry": {"coordinates":[-84.315022,39.797301],"type":"Point"}
}