{
  "type": "Feature",
  "properties": {
    "addr:full": "7255 Old Oak Blvd Cleveland OH 44130",
    "addr:housenumber": "7255",
    "addr:postcode": "44130",
    "addr:street": "Old Oak Blvd",
    "iso:country": "US",
    "sg:address": "7255 Old Oak Blvd",
    "sg:city": "Cleveland",
    "sg:classifiers": [
      {
        "category": "Health Services",
        "subcategory": "Doctor",
        "type": "Services"
      }
    ],
    "sg:phone": "+1 440 239 3700",
    "sg:postcode": "44130",
    "sg:province": "OH",
    "sg:tags": [
      "physician",
      "surgeon"
    ],
    "wof:name": "North Ohio Heart Ctr Inc",
    "wof:placetype": "venue"
  },
  "geometry": {"coordinates":[-81.833524,41.360471],"type":"Point"}
}
