{
  "type": "Feature",
  "properties": {
    "addr:full": "3828 N Ridge Rd Perry OH 44081",
    "addr:housenumber": "3828",
    "addr:postcode": "44081",
    "addr:street": "N Ridge Rd",
    "iso:country": "US",
    "sg:address": "3828 N Ridge Rd",
    "sg:city": "Perry",
    "sg:classifiers": [
      {
        "category": "Autos \u0026 Motor Vehicles",
        "subcategory": "Automobile Sales",
        "type": "Retail Goods"
      }
    ],
    "sg:phone": "+1 440 259 4484",
    "sg:postcode": "44081",
    "sg:province": "OH",
    "sg:tags": [
      "car",
      "dealer"
    ],
    "wof:name": "Phil's Auto Brite",
    "wof:placetype": "venue"
  },
  "geometry": {"coordinates":[-81.149638,41.779161],"type":"Point"}
}
