{
  "type": "Feature",
  "properties": {
    "addr:full": "1300 Hill Rd N Pickerington OH 43147",
    "addr:housenumber": "1300",
    "addr:postcode": "43147",
    "addr:street": "Hill Rd N",
    "iso:country": "US",
    "sg:address": "1300 Hill Rd N",
    "sg:city": "Pickerington",
    "sg:classifiers": [
      {
        "category": "Health Services",
        "subcategory": "Nursing And Care Facility",
        "type": "Services"
      }
    ],
    "sg:phone": "+1 614 856 4689",
    "sg:postcode": "43147",
    "sg:province": "OH",
    "sg:tags": [
      "home",
      "convalescent"
    ],
    "wof:name": "N C Kindred",
    "wof:placetype": "venue"
  },
  "geometry": {"coordinates":[-82.780162,39.915222],"type":"Point"}
}
