{
  "type": "Feature",
  "properties": {
    "addr:full":"16017 Neladale Rd Cleveland OH 44112",
    "addr:postcode":"16017;44112",
    "addr:street":"Neladale Rd",
    "iso:country":"US",
    "sg:address":"16017 Neladale Rd",
    "sg:city":"Cleveland",
    "sg:classifiers":[
        {
            "category":"Building & Trades",
            "subcategory":"Landscaping Services",
            "type":"Services"
        }
    ],
    "sg:phone":"+1 216 310 0817",
    "sg:postcode":"44112",
    "sg:province":"OH",
    "sg:tags":[
        "landscape"
    ],
    "wof:name":"Jesses Landscaping",
    "wof:placetype":"venue"
},
  "geometry": {"coordinates":[-81.56260399999999,41.539075],"type":"Point"}
}