{
  "type": "Feature",
  "properties": {
    "iso:country":"US",
    "sg:address":"4738 Troy Rd",
    "sg:city":"Springfield",
    "sg:classifiers":[
        {
            "category":"Building & Trades",
            "subcategory":"Construction",
            "type":"Services"
        }
    ],
    "sg:phone":"+1 937 964 1995",
    "sg:postcode":"45502",
    "sg:province":"OH",
    "sg:tags":[
        "handyman"
    ],
    "wof:name":"Doorboy Handyman Div",
    "wof:placetype":"venue"
},
  "geometry": {"coordinates":[-83.885834,39.987201],"type":"Point"}
}