{
  "type": "Feature",
  "properties": {
    "addr:full": "502 Eric Wolber Dr Ada OH 45810",
    "addr:housenumber": "502",
    "addr:postcode": "45810",
    "addr:street": "Eric Wolber Dr",
    "iso:country": "US",
    "sg:address": "502 Eric Wolber Dr",
    "sg:city": "Ada",
    "sg:classifiers": [
      {
        "category": "Manufacturing",
        "subcategory": "Rubber \u0026 Plastics",
        "type": "Manufacturing \u0026 Wholesale Goods"
      }
    ],
    "sg:phone": "+1 419 634 0460",
    "sg:postcode": "45810",
    "sg:province": "OH",
    "wof:name": "Associated Plastics Corp",
    "wof:placetype": "venue"
  },
  "geometry": {"coordinates":[-83.815615,40.771831],"type":"Point"}
}
