{
  "type": "Feature",
  "properties": {
    "iso:country":"US",
    "sg:address":"502 Eric Wolber Dr",
    "sg:city":"Ada",
    "sg:classifiers":[
        {
            "category":"Manufacturing",
            "subcategory":"Rubber & Plastics",
            "type":"Manufacturing & Wholesale Goods"
        }
    ],
    "sg:phone":"+1 419 634 0460",
    "sg:postcode":"45810",
    "sg:province":"OH",
    "wof:name":"Associated Plastics Corp",
    "wof:placetype":"venue"
},
  "geometry": {"coordinates":[-83.81561499999999,40.771831],"type":"Point"}
}