{
  "type": "Feature",
  "properties": {
    "iso:country":"US",
    "sg:address":"11590 Century Blvd",
    "sg:city":"Cincinnati",
    "sg:classifiers":[
        {
            "category":"Real Estate",
            "subcategory":"Real Estate Operator",
            "type":"Services"
        }
    ],
    "sg:phone":"+1 513 671 7010",
    "sg:postcode":"45246",
    "sg:province":"OH",
    "sg:tags":[
        "building",
        "parks"
    ],
    "sg:website":"www.trammelcrow.com",
    "wof:name":"Trammell Crow Co",
    "wof:placetype":"venue"
},
  "geometry": {"coordinates":[-84.453407,39.28622],"type":"Point"}
}