{
  "type": "Feature",
  "properties": {
    "addr:full": "11 Broadway Ave Bedford OH 44146",
    "addr:housenumber": "11",
    "addr:postcode": "44146",
    "addr:street": "Broadway Ave",
    "iso:country": "US",
    "sg:address": "11 Broadway Ave",
    "sg:city": "Bedford",
    "sg:classifiers": [
      {
        "category": "Autos \u0026 Motor Vehicles",
        "subcategory": "Automobile Sales",
        "type": "Retail Goods"
      }
    ],
    "sg:phone": "+1 440 439 2323",
    "sg:postcode": "44146",
    "sg:province": "OH",
    "sg:tags": [
      "new",
      "lease",
      "used",
      "car"
    ],
    "wof:name": "Mazda Saab of Bedford",
    "wof:placetype": "venue"
  },
  "geometry": {"coordinates":[-81.554774,41.404278],"type":"Point"}
}
