{
  "type": "Feature",
  "properties": {
    "iso:country":"US",
    "sg:address":"11 Broadway Ave",
    "sg:city":"Bedford",
    "sg:classifiers":[
        {
            "category":"Autos & Motor Vehicles",
            "subcategory":"Automobile Sales",
            "type":"Retail Goods"
        }
    ],
    "sg:phone":"+1 440 439 2323",
    "sg:postcode":"44146",
    "sg:province":"OH",
    "sg:tags":[
        "new",
        "lease",
        "used",
        "car"
    ],
    "wof:name":"Mazda Saab of Bedford",
    "wof:placetype":"venue"
},
  "geometry": {"coordinates":[-81.55477399999999,41.404278],"type":"Point"}
}