{
  "type": "Feature",
  "properties": {
    "iso:country":"US",
    "sg:address":"4478 New Cumberland Rd NE",
    "sg:city":"Mineral City",
    "sg:classifiers":[
        {
            "category":"Manufacturing",
            "subcategory":"Metals",
            "type":"Manufacturing & Wholesale Goods"
        }
    ],
    "sg:phone":"+1 330 602 1382",
    "sg:postcode":"44656",
    "sg:province":"OH",
    "sg:tags":[
        "product",
        "mfg",
        "forging"
    ],
    "wof:name":"Canton Flexable Mfg Systems",
    "wof:placetype":"venue"
},
  "geometry": {"coordinates":[-81.303656,40.556957],"type":"Point"}
}