{
  "type": "Feature",
  "properties": {
    "addr:full": "4478 New Cumberland Rd NE Mineral City OH 44656",
    "addr:housenumber": "4478",
    "addr:postcode": "44656",
    "addr:street": "New Cumberland Rd Ne",
    "iso:country": "US",
    "sg:address": "4478 New Cumberland Rd NE",
    "sg:city": "Mineral City",
    "sg:classifiers": [
      {
        "category": "Manufacturing",
        "subcategory": "Metals",
        "type": "Manufacturing \u0026 Wholesale Goods"
      }
    ],
    "sg:phone": "+1 330 602 1382",
    "sg:postcode": "44656",
    "sg:province": "OH",
    "sg:tags": [
      "product",
      "mfg",
      "forging"
    ],
    "wof:name": "Canton Flexable Mfg Systems",
    "wof:placetype": "venue"
  },
  "geometry": {"coordinates":[-81.303656,40.556957],"type":"Point"}
}
