{
  "type": "Feature",
  "properties": {
    "addr:full":"813 Glenwood Rd Rossford OH 43460",
    "addr:housenumber":"813",
    "addr:postcode":"43460",
    "addr:street":"Glenwood Rd",
    "iso:country":"US",
    "sg:address":"813 Glenwood Rd",
    "sg:city":"Rossford",
    "sg:classifiers":[
        {
            "category":"Real Estate",
            "subcategory":"Real Estate Operator",
            "type":"Services"
        }
    ],
    "sg:phone":"+1 419 666 5320",
    "sg:postcode":"43460",
    "sg:province":"OH",
    "sg:tags":[
        "building",
        "apartment"
    ],
    "wof:name":"Camelot East Apartments",
    "wof:placetype":"venue"
},
  "geometry": {"coordinates":[-83.55765599999999,41.590416],"type":"Point"}
}