{
  "type": "Feature",
  "properties": {
    "addr:full":"4411 Carroll-Southern Rd NW Carroll OH 43112",
    "addr:housenumber":"4411",
    "addr:postcode":"43112",
    "addr:street":"Carroll-Southern Rd Nw",
    "iso:country":"US",
    "sg:address":"4411 Carroll-Southern Rd NW",
    "sg:city":"Carroll",
    "sg:classifiers":[
        {
            "category":"Building & Trades",
            "subcategory":"Construction",
            "type":"Services"
        }
    ],
    "sg:phone":"+1 740 756 7665",
    "sg:postcode":"43112",
    "sg:province":"OH",
    "sg:tags":[
        "house"
    ],
    "wof:name":"Mc Cook Construction",
    "wof:placetype":"venue"
},
  "geometry": {"coordinates":[-82.702523,39.793559],"type":"Point"}
}