{
  "type": "Feature",
  "properties": {
    "iso:country":"US",
    "sg:address":"4596 Ridge Rd",
    "sg:city":"Cleveland",
    "sg:classifiers":[
        {
            "category":"Manufacturing",
            "subcategory":"Tools & Machinery",
            "type":"Manufacturing & Wholesale Goods"
        }
    ],
    "sg:phone":"+1 216 741 0475",
    "sg:postcode":"44144",
    "sg:province":"OH",
    "sg:tags":[
        "machine",
        "mfg"
    ],
    "wof:name":"J D C Tool",
    "wof:placetype":"venue"
},
  "geometry": {"coordinates":[-81.735383,41.4336],"type":"Point"}
}