{
  "type": "Feature",
  "properties": {
    "iso:country":"US",
    "sg:address":"13735 Diagonal Rd",
    "sg:city":"Lagrange",
    "sg:classifiers":[
        {
            "category":"Building & Trades",
            "subcategory":"Construction",
            "type":"Services"
        }
    ],
    "sg:phone":"+1 440 458 6801",
    "sg:postcode":"44050",
    "sg:province":"OH",
    "sg:tags":[
        "general",
        "contractor"
    ],
    "wof:name":"Stans Excavating",
    "wof:placetype":"venue"
},
  "geometry": {"coordinates":[-82.15674300000001,41.275187],"type":"Point"}
}