{
  "type": "Feature",
  "properties": {
    "addr:full": "13735 Diagonal Rd Lagrange OH 44050",
    "addr:housenumber": "13735",
    "addr:postcode": "44050",
    "addr:street": "Diagonal Rd",
    "iso:country": "US",
    "sg:address": "13735 Diagonal Rd",
    "sg:city": "Lagrange",
    "sg:classifiers": [
      {
        "category": "Building \u0026 Trades",
        "subcategory": "Construction",
        "type": "Services"
      }
    ],
    "sg:phone": "+1 440 458 6801",
    "sg:postcode": "44050",
    "sg:province": "OH",
    "sg:tags": [
      "general",
      "contractor"
    ],
    "wof:name": "Stans Excavating",
    "wof:placetype": "venue"
  },
  "geometry": {"coordinates":[-82.156743,41.275187],"type":"Point"}
}
