{
  "type": "Feature",
  "properties": {
    "addr:full":"14120 Rd 15-M Columbus Grove OH 45830",
    "addr:housenumber":"14120;15-m",
    "addr:postcode":"45830",
    "addr:street":"Rd;Columbus Grove",
    "iso:country":"US",
    "sg:address":"14120 Rd 15-M",
    "sg:city":"Columbus Grove",
    "sg:classifiers":[
        {
            "category":"Arts & Performance",
            "subcategory":"Theater",
            "type":"Entertainment"
        }
    ],
    "sg:phone":"+1 419 532 2098",
    "sg:postcode":"45830",
    "sg:province":"OH",
    "sg:tags":[
        "entertainer",
        "business"
    ],
    "wof:name":"Blackie & Buffy's DJ Svc",
    "wof:placetype":"venue"
},
  "geometry": {"coordinates":[-84.159341,40.975029],"type":"Point"}
}