{
  "type": "Feature",
  "properties": {
    "iso:country":"US",
    "sg:address":"4039 Deer Park Ave",
    "sg:city":"Cincinnati",
    "sg:classifiers":[
        {
            "category":"Retail",
            "subcategory":"Auto Repair",
            "type":"Services"
        }
    ],
    "sg:phone":"+1 513 792 9444",
    "sg:postcode":"45236",
    "sg:province":"OH",
    "sg:tags":[
        "body",
        "automobile",
        "painting"
    ],
    "wof:name":"Noland's Unique Paint & Body",
    "wof:placetype":"venue"
},
  "geometry": {"coordinates":[-84.400443,39.197498],"type":"Point"}
}