{
  "type": "Feature",
  "properties": {
    "addr:full": "5704 Decker Rd North Olmsted OH 44070",
    "addr:housenumber": "5704",
    "addr:postcode": "44070",
    "addr:street": "Decker Rd",
    "iso:country": "US",
    "sg:address": "5704 Decker Rd",
    "sg:city": "North Olmsted",
    "sg:classifiers": [
      {
        "category": "Shopping",
        "type": "Retail Goods"
      },
      {
        "category": "Retail",
        "subcategory": "Animal Services",
        "type": "Services"
      }
    ],
    "sg:phone": "+1 440 570 0137",
    "sg:postcode": "44070",
    "sg:province": "OH",
    "sg:tags": [
      "pet",
      "merchandise"
    ],
    "wof:name": "Just 4 Paws Pet Sitting",
    "wof:placetype": "venue"
  },
  "geometry": {"coordinates":[-81.930059,41.408901],"type":"Point"}
}
