{
  "type": "Feature",
  "properties": {
    "addr:full": "13000 Athens Ave Cleveland OH 44107",
    "addr:postcode": "13000;44107",
    "addr:street": "Athens Ave",
    "iso:country": "US",
    "sg:address": "13000 Athens Ave",
    "sg:city": "Cleveland",
    "sg:classifiers": [
      {
        "category": "Wholesale",
        "subcategory": "Construction Materials",
        "type": "Manufacturing \u0026 Wholesale Goods"
      }
    ],
    "sg:phone": "+1 216 228 2124",
    "sg:postcode": "44107",
    "sg:province": "OH",
    "sg:tags": [
      "sand",
      "gravel"
    ],
    "wof:name": "Sand Products Corporation",
    "wof:placetype": "venue"
  },
  "geometry": {"coordinates":[-81.782308,41.473926],"type":"Point"}
}
