{
  "type": "Feature",
  "properties": {
    "addr:full":"N Medina St Medina OH 44256",
    "addr:postcode":"44256",
    "addr:street":"N Medina St",
    "iso:country":"US",
    "sg:address":"N Medina St",
    "sg:city":"Medina",
    "sg:classifiers":[
        {
            "category":"Restaurant",
            "type":"Food & Drink"
        }
    ],
    "sg:menulink":"http://www.allmenus.com/oh/medina-city/238945-pizzazios/menu/",
    "sg:phone":"+1 330 725 8200",
    "sg:postcode":"44256",
    "sg:province":"OH",
    "sg:tags":[
        "american",
        "pizza"
    ],
    "wof:name":"Pizzazio's",
    "wof:placetype":"venue"
},
  "geometry": {"coordinates":[-81.872936,41.140591],"type":"Point"}
}