{
  "type": "Feature",
  "properties": {
    "addr:full": "5158 Duff Dr Cincinnati OH 45246",
    "addr:housenumber": "5158",
    "addr:postcode": "45246",
    "addr:street": "Duff Dr",
    "iso:country": "US",
    "sg:address": "5158 Duff Dr",
    "sg:city": "Cincinnati",
    "sg:classifiers": [
      {
        "category": "Professional",
        "subcategory": "Employment Agencies",
        "type": "Services"
      }
    ],
    "sg:phone": "+1 513 682 5900",
    "sg:postcode": "45246",
    "sg:province": "OH",
    "sg:tags": [
      "help",
      "contractor"
    ],
    "wof:name": "CIMA Inc",
    "wof:placetype": "venue"
  },
  "geometry": {"coordinates":[-84.457468,39.309268],"type":"Point"}
}
