{
  "type": "Feature",
  "properties": {
    "addr:full": "7250 Miami Ave Cincinnati OH 45243",
    "addr:housenumber": "7250",
    "addr:postcode": "45243",
    "addr:street": "Miami Ave",
    "iso:country": "US",
    "sg:address": "7250 Miami Ave",
    "sg:city": "Cincinnati",
    "sg:classifiers": [
      {
        "category": "Retail",
        "subcategory": "Veterinary Services",
        "type": "Services"
      }
    ],
    "sg:phone": "+1 513 202 3943",
    "sg:postcode": "45243",
    "sg:province": "OH",
    "sg:tags": [
      "pet",
      "hospital",
      "veterinarian",
      "clinic"
    ],
    "sg:website": "http://www.yext.com/p/superpages/madeira-veterinary-hospital-cincinnati-ohio.html",
    "wof:name": "Madeira Veterinary Hospital",
    "wof:placetype": "venue"
  },
  "geometry": {"coordinates":[-84.362859,39.192616],"type":"Point"}
}
