{
  "type": "Feature",
  "properties": {
    "iso:country":"US",
    "sg:address":"1240 Bailey Anderson Rd",
    "sg:city":"Leavittsburg",
    "sg:classifiers":[
        {
            "category":"Manufacturing",
            "subcategory":"Printing",
            "type":"Manufacturing & Wholesale Goods"
        }
    ],
    "sg:phone":"+1 330 898 3299",
    "sg:postcode":"44430",
    "sg:province":"OH",
    "sg:tags":[
        "lithographic",
        "commercial"
    ],
    "wof:name":"Bell Printing Co",
    "wof:placetype":"venue"
},
  "geometry": {"coordinates":[-80.93186,41.250598],"type":"Point"}
}