{
  "type": "Feature",
  "properties": {
    "addr:full": "1240 Bailey Anderson Rd Leavittsburg OH 44430",
    "addr:housenumber": "1240",
    "addr:postcode": "44430",
    "addr:street": "Bailey Anderson Rd",
    "iso:country": "US",
    "sg:address": "1240 Bailey Anderson Rd",
    "sg:city": "Leavittsburg",
    "sg:classifiers": [
      {
        "category": "Manufacturing",
        "subcategory": "Printing",
        "type": "Manufacturing \u0026 Wholesale Goods"
      }
    ],
    "sg:phone": "+1 330 898 3299",
    "sg:postcode": "44430",
    "sg:province": "OH",
    "sg:tags": [
      "lithographic",
      "commercial"
    ],
    "wof:name": "Bell Printing Co",
    "wof:placetype": "venue"
  },
  "geometry": {"coordinates":[-80.93186,41.250598],"type":"Point"}
}
