{
  "type": "Feature",
  "properties": {
    "addr:full": "116 E High St Mt Vernon OH 43050",
    "addr:housenumber": "116",
    "addr:postcode": "43050",
    "addr:street": "E High St",
    "iso:country": "US",
    "sg:address": "116 E High St",
    "sg:city": "Mt Vernon",
    "sg:classifiers": [
      {
        "category": "Social Services",
        "type": "Services"
      }
    ],
    "sg:phone": "+1 740 393 6799",
    "sg:postcode": "43050",
    "sg:province": "OH",
    "sg:tags": [
      "probation"
    ],
    "wof:name": "Juvenile Probation Officers",
    "wof:placetype": "venue"
  },
  "geometry": {"coordinates":[-82.483878,40.393399],"type":"Point"}
}
