{
  "type": "Feature",
  "properties": {
    "iso:country":"US",
    "sg:address":"8555 Amish Pike",
    "sg:city":"Plain City",
    "sg:classifiers":[
        {
            "category":"Building & Trades",
            "subcategory":"Construction",
            "type":"Services"
        }
    ],
    "sg:phone":"+1 614 873 1106",
    "sg:postcode":"43064",
    "sg:province":"OH",
    "sg:tags":[
        "excavation",
        "contractor"
    ],
    "wof:name":"Wayne S Excavating",
    "wof:placetype":"venue"
},
  "geometry": {"coordinates":[-83.343414,40.064863],"type":"Point"}
}