{
  "type": "Feature",
  "properties": {
    "addr:full": "8555 Amish Pike Plain City OH 43064",
    "addr:housenumber": "8555",
    "addr:postcode": "43064",
    "addr:street": "Amish Pike",
    "iso:country": "US",
    "sg:address": "8555 Amish Pike",
    "sg:city": "Plain City",
    "sg:classifiers": [
      {
        "category": "Building \u0026 Trades",
        "subcategory": "Construction",
        "type": "Services"
      }
    ],
    "sg:phone": "+1 614 873 1106",
    "sg:postcode": "43064",
    "sg:province": "OH",
    "sg:tags": [
      "excavation",
      "contractor"
    ],
    "wof:name": "Wayne S Excavating",
    "wof:placetype": "venue"
  },
  "geometry": {"coordinates":[-83.343414,40.064863],"type":"Point"}
}
