{
  "type": "Feature",
  "properties": {
    "addr:full": "302 N 4th St Toronto OH 43964",
    "addr:housenumber": "302",
    "addr:postcode": "43964",
    "addr:street": "N 4Th St",
    "iso:country": "US",
    "sg:address": "302 N 4th St",
    "sg:city": "Toronto",
    "sg:classifiers": [
      {
        "category": "Shopping",
        "subcategory": "Pharmacy",
        "type": "Retail Goods"
      }
    ],
    "sg:phone": "+1 740 537 2100",
    "sg:postcode": "43964",
    "sg:province": "OH",
    "wof:name": "Toronto Pharmacy",
    "wof:placetype": "venue"
  },
  "geometry": {"coordinates":[-80.600791,40.467065],"type":"Point"}
}
