{
  "type": "Feature",
  "properties": {
    "iso:country":"US",
    "sg:address":"3654 E 114th St",
    "sg:city":"Cleveland",
    "sg:classifiers":[
        {
            "category":"Restaurant",
            "type":"Food & Drink"
        }
    ],
    "sg:phone":"+1 216 491 0811",
    "sg:postcode":"44105",
    "sg:province":"OH",
    "sg:tags":[
        "caterer"
    ],
    "wof:name":"Debra Nashe Catering",
    "wof:placetype":"venue"
},
  "geometry": {"coordinates":[-81.604095,41.460486],"type":"Point"}
}