{
  "type": "Feature",
  "properties": {
    "addr:full": "5763 Butler Warren Rd Middletown OH 45040",
    "addr:housenumber": "5763",
    "addr:postcode": "45040",
    "addr:street": "Butler Warren Rd",
    "iso:country": "US",
    "sg:address": "5763 Butler Warren Rd",
    "sg:city": "Middletown",
    "sg:classifiers": [
      {
        "category": "Building \u0026 Trades",
        "subcategory": "Plumbing",
        "type": "Services"
      }
    ],
    "sg:phone": "+1 513 779 1482",
    "sg:postcode": "45040",
    "sg:province": "OH",
    "sg:tags": [
      "contractor"
    ],
    "wof:name": "Conveyor Controls",
    "wof:placetype": "venue"
  },
  "geometry": {"coordinates":[-84.34726,39.357907],"type":"Point"}
}
