{
  "type": "Feature",
  "properties": {
    "addr:full": "1752 Oak Dr Fremont OH 43420",
    "addr:housenumber": "1752",
    "addr:postcode": "43420",
    "addr:street": "Oak Dr",
    "iso:country": "US",
    "sg:address": "1752 Oak Dr",
    "sg:city": "Fremont",
    "sg:classifiers": [
      {
        "category": "Shopping",
        "subcategory": "Bicycles \u0026 Sporting Goods",
        "type": "Retail Goods"
      }
    ],
    "sg:phone": "+1 419 332 5362",
    "sg:postcode": "43420",
    "sg:province": "OH",
    "wof:name": "Brian Wammes",
    "wof:placetype": "venue"
  },
  "geometry": {"coordinates":[-83.104379,41.321604],"type":"Point"}
}
