{
  "type": "Feature",
  "properties": {
    "iso:country":"US",
    "sg:address":"7707 Hough Ave",
    "sg:city":"Cleveland",
    "sg:classifiers":[
        {
            "category":"Freight",
            "type":"Transportation"
        }
    ],
    "sg:phone":"+1 216 229 0644",
    "sg:postcode":"44103",
    "sg:province":"OH",
    "wof:name":"Perry's Transportation",
    "wof:placetype":"venue"
},
  "geometry": {"coordinates":[-81.634721,41.509383],"type":"Point"}
}