{
  "type": "Feature",
  "properties": {
    "iso:country":"US",
    "sg:address":"118 S Main St",
    "sg:city":"Amsterdam",
    "sg:classifiers":[
        {
            "category":"Personal",
            "subcategory":"Beauty Salon",
            "type":"Services"
        }
    ],
    "sg:phone":"+1 740 543 3891",
    "sg:postcode":"43903",
    "sg:province":"OH",
    "wof:name":"Charlotte's Cut & Curl",
    "wof:placetype":"venue"
},
  "geometry": {"coordinates":[-80.923753,40.472995],"type":"Point"}
}