{
  "type": "Feature",
  "properties": {
    "addr:full":"1184 Fairview Ave Columbus OH 43212",
    "addr:housenumber":"1184",
    "addr:postcode":"43212",
    "addr:street":"Fairview Ave",
    "iso:country":"US",
    "sg:address":"1184 Fairview Ave",
    "sg:city":"Columbus",
    "sg:classifiers":[
        {
            "category":"Real Estate",
            "subcategory":"Real Estate Agent",
            "type":"Services"
        }
    ],
    "sg:phone":"+1 614 486 4081",
    "sg:postcode":"43212",
    "sg:province":"OH",
    "wof:name":"Shaudys Rentals",
    "wof:placetype":"venue"
},
  "geometry": {"coordinates":[-83.04799199999999,39.980318],"type":"Point"}
}