{
  "type": "Feature",
  "properties": {
    "addr:full":"9952 Twp Rd 26-2 West Unity OH 43570",
    "addr:housenumber":"26-2",
    "addr:postcode":"9952;43570",
    "addr:street":"Twp Rd;West",
    "iso:country":"US",
    "sg:address":"9952 Twp Rd 26-2",
    "sg:city":"West Unity",
    "sg:phone":"+1 419 924 2094",
    "sg:postcode":"43570",
    "sg:province":"OH",
    "sg:tags":[
        "farm",
        "corn",
        "soybean"
    ],
    "wof:name":"Theodore Kreiner",
    "wof:placetype":"venue"
},
  "geometry": {"coordinates":[-84.37168,41.616479],"type":"Point"}
}