{
  "type": "Feature",
  "properties": {
    "addr:full": "102 S Main St De Graff OH 43318",
    "addr:housenumber": "102",
    "addr:postcode": "43318",
    "addr:street": "S Main St",
    "iso:country": "US",
    "sg:address": "102 S Main St",
    "sg:city": "De Graff",
    "sg:classifiers": [
      {
        "category": "Restaurant",
        "type": "Food \u0026 Drink"
      }
    ],
    "sg:phone": "+1 937 585 5881",
    "sg:postcode": "43318",
    "sg:province": "OH",
    "sg:tags": [
      "shop",
      "coffee"
    ],
    "wof:name": "Ruby G's",
    "wof:placetype": "venue"
  },
  "geometry": {"coordinates":[-83.914819,40.309379],"type":"Point"}
}
