{
  "type": "Feature",
  "properties": {
    "addr:full": "615 Fulton St Port Clinton OH 43452",
    "addr:housenumber": "615",
    "addr:postcode": "43452",
    "addr:street": "Fulton St",
    "iso:country": "US",
    "sg:address": "615 Fulton St",
    "sg:city": "Port Clinton",
    "sg:classifiers": [
      {
        "category": "Organizations",
        "subcategory": "Professional Association",
        "type": "Services"
      }
    ],
    "sg:phone": "+1 419 734 5787",
    "sg:postcode": "43452",
    "sg:province": "OH",
    "wof:name": "Ottawa County Care Net",
    "wof:placetype": "venue"
  },
  "geometry": {"coordinates":[-82.933702,41.506295],"type":"Point"}
}
