{
  "type": "Feature",
  "properties": {
    "addr:full": "323 Parktrail Ln Cincinnati OH 45238",
    "addr:housenumber": "323",
    "addr:postcode": "45238",
    "addr:street": "Parktrail Ln",
    "iso:country": "US",
    "sg:address": "323 Parktrail Ln",
    "sg:city": "Cincinnati",
    "sg:classifiers": [
      {
        "category": "Professional",
        "type": "Services"
      }
    ],
    "sg:phone": "+1 513 921 3325",
    "sg:postcode": "45238",
    "sg:province": "OH",
    "sg:tags": [
      "establishment"
    ],
    "wof:name": "Stenna Corp",
    "wof:placetype": "venue"
  },
  "geometry": {"coordinates":[-84.590822,39.090862],"type":"Point"}
}
