{
  "type": "Feature",
  "properties": {
    "iso:country":"US",
    "sg:address":"164 S Watt St",
    "sg:city":"Chillicothe",
    "sg:classifiers":[
        {
            "category":"Organizations",
            "subcategory":"Religious Organization",
            "type":"Services"
        }
    ],
    "sg:phone":"+1 740 998 2223",
    "sg:postcode":"45601",
    "sg:province":"OH",
    "sg:tags":[
        "christian",
        "ministry"
    ],
    "wof:name":"Philadelphia Fellowship",
    "wof:placetype":"venue"
},
  "geometry": {"coordinates":[-82.962699,39.332077],"type":"Point"}
}