{
  "type": "Feature",
  "properties": {
    "iso:country":"US",
    "sg:address":"11687 Lebanon Rd",
    "sg:city":"Cincinnati",
    "sg:classifiers":[
        {
            "category":"Professional",
            "subcategory":"Engineering",
            "type":"Services"
        }
    ],
    "sg:phone":"+1 513 860 1070",
    "sg:postcode":"45241",
    "sg:province":"OH",
    "sg:tags":[
        "engineer"
    ],
    "sg:website":"www.fmsmengineers.com",
    "wof:name":"Fuller Mossbarger Scott & May",
    "wof:placetype":"venue"
},
  "geometry": {"coordinates":[-84.399952,39.283906],"type":"Point"}
}