{
  "type": "Feature",
  "properties": {
    "iso:country":"US",
    "sg:address":"145 S Main St",
    "sg:city":"Springboro",
    "sg:classifiers":[
        {
            "category":"Insurance",
            "subcategory":"Insurance Agent",
            "type":"Services"
        }
    ],
    "sg:phone":"+1 937 748 2987",
    "sg:postcode":"45066",
    "sg:province":"OH",
    "wof:name":"Springsboro Insurance Agency",
    "wof:placetype":"venue"
},
  "geometry": {"coordinates":[-84.233244,39.554866],"type":"Point"}
}