{
  "type": "Feature",
  "properties": {
    "iso:country":"US",
    "sg:address":"77 Granville St",
    "sg:city":"Columbus",
    "sg:classifiers":[
        {
            "category":"Restaurant",
            "type":"Food & Drink"
        }
    ],
    "sg:phone":"+1 614 475 4138",
    "sg:postcode":"43230",
    "sg:province":"OH",
    "sg:tags":[
        "eating"
    ],
    "wof:name":"Wendys",
    "wof:placetype":"venue"
},
  "geometry": {"coordinates":[-82.879451,40.0188],"type":"Point"}
}