{
  "type": "Feature",
  "properties": {
    "addr:full": "77 Granville St Columbus OH 43230",
    "addr:housenumber": "77",
    "addr:postcode": "43230",
    "addr:street": "Granville St",
    "iso:country": "US",
    "sg:address": "77 Granville St",
    "sg:city": "Columbus",
    "sg:classifiers": [
      {
        "category": "Restaurant",
        "type": "Food \u0026 Drink"
      }
    ],
    "sg:phone": "+1 614 475 4138",
    "sg:postcode": "43230",
    "sg:province": "OH",
    "sg:tags": [
      "eating"
    ],
    "wof:name": "Wendys",
    "wof:placetype": "venue"
  },
  "geometry": {"coordinates":[-82.879451,40.0188],"type":"Point"}
}
