{
  "type": "Feature",
  "properties": {
    "addr:full":"441 Vine St Cincinnati OH 45202",
    "addr:housenumber":"441",
    "addr:postcode":"45202",
    "addr:street":"Vine St",
    "iso:country":"US",
    "sg:address":"441 Vine St",
    "sg:city":"Cincinnati",
    "sg:classifiers":[
        {
            "category":"Utilities",
            "subcategory":"Mobile Phone",
            "type":"Services"
        },
        {
            "category":"Shopping",
            "subcategory":"Mobile Phones",
            "type":"Retail Goods"
        },
        {
            "category":"Utilities",
            "subcategory":"Telephone",
            "type":"Services"
        },
        {
            "category":"Professional",
            "subcategory":"Computer Services",
            "type":"Services"
        }
    ],
    "sg:phone":"+1 513 684 0213",
    "sg:postcode":"45202",
    "sg:province":"OH",
    "sg:tags":[
        "telecommunication",
        "supply",
        "communication",
        "system",
        "wireless",
        "equipment",
        "cellular"
    ],
    "sg:website":"http://clickserve.dartsearch.net/link/click?lid=43000000308049899",
    "wof:name":"T-Mobile",
    "wof:placetype":"venue"
},
  "geometry": {"coordinates":[-84.51279100000001,39.10042],"type":"Point"}
}