{
  "type": "Feature",
  "properties": {
    "iso:country":"US",
    "sg:address":"1524 Oak Harbor Rd",
    "sg:city":"Fremont",
    "sg:classifiers":[
        {
            "category":"Building & Trades",
            "subcategory":"Plumbing",
            "type":"Services"
        }
    ],
    "sg:phone":"+1 419 483 4249",
    "sg:postcode":"43420",
    "sg:province":"OH",
    "sg:tags":[
        "fire",
        "protection",
        "contractor"
    ],
    "sg:website":"www.comunale.com",
    "wof:name":"S A Comunale Co Inc",
    "wof:placetype":"venue"
},
  "geometry": {"coordinates":[-83.13655199999999,41.363518],"type":"Point"}
}