{
  "type": "Feature",
  "properties": {
    "addr:full": "1524 Oak Harbor Rd Fremont OH 43420",
    "addr:housenumber": "1524",
    "addr:postcode": "43420",
    "addr:street": "Oak Harbor Rd",
    "iso:country": "US",
    "sg:address": "1524 Oak Harbor Rd",
    "sg:city": "Fremont",
    "sg:classifiers": [
      {
        "category": "Building \u0026 Trades",
        "subcategory": "Plumbing",
        "type": "Services"
      }
    ],
    "sg:phone": "+1 419 483 4249",
    "sg:postcode": "43420",
    "sg:province": "OH",
    "sg:tags": [
      "fire",
      "protection",
      "contractor"
    ],
    "sg:website": "www.comunale.com",
    "wof:name": "S A Comunale Co Inc",
    "wof:placetype": "venue"
  },
  "geometry": {"coordinates":[-83.136552,41.363518],"type":"Point"}
}
