{
  "type": "Feature",
  "properties": {
    "addr:full":"6530 Urbana Rd Springfield OH 45502",
    "addr:housenumber":"6530",
    "addr:postcode":"45502",
    "addr:street":"Urbana Rd",
    "iso:country":"US",
    "sg:address":"6530 Urbana Rd",
    "sg:city":"Springfield",
    "sg:classifiers":[
        {
            "category":"Freight",
            "type":"Transportation"
        }
    ],
    "sg:phone":"+1 937 390 7500",
    "sg:postcode":"45502",
    "sg:province":"OH",
    "sg:tags":[
        "general"
    ],
    "wof:name":"Spgfld Self Storage",
    "wof:placetype":"venue"
},
  "geometry": {"coordinates":[-83.789584,40.015999],"type":"Point"}
}