{
  "type": "Feature",
  "properties": {
    "addr:full":"20906 Drake Rd Strongsville OH 44149",
    "addr:housenumber":"20906",
    "addr:postcode":"44149",
    "addr:street":"Drake Rd",
    "iso:country":"US",
    "sg:address":"20906 Drake Rd",
    "sg:city":"Strongsville",
    "sg:classifiers":[
        {
            "category":"Restaurant",
            "type":"Food & Drink"
        }
    ],
    "sg:phone":"+1 440 238 8278",
    "sg:postcode":"44149",
    "sg:province":"OH",
    "wof:name":"King Dragon",
    "wof:placetype":"venue"
},
  "geometry": {"coordinates":[-81.85720000000001,41.290251],"type":"Point"}
}