{
  "type": "Feature",
  "properties": {
    "addr:full": "1704 Redbush Ave Dayton OH 45420",
    "addr:housenumber": "1704",
    "addr:postcode": "45420",
    "addr:street": "Redbush Ave",
    "iso:country": "US",
    "sg:address": "1704 Redbush Ave",
    "sg:city": "Dayton",
    "sg:classifiers": [
      {
        "category": "Building \u0026 Trades",
        "subcategory": "Construction",
        "type": "Services"
      }
    ],
    "sg:phone": "+1 937 253 1739",
    "sg:postcode": "45420",
    "sg:province": "OH",
    "sg:tags": [
      "nonresidential"
    ],
    "wof:name": "Cotters Inc",
    "wof:placetype": "venue"
  },
  "geometry": {"coordinates":[-84.135192,39.714095],"type":"Point"}
}
