{
  "type": "Feature",
  "properties": {
    "addr:full":"1699 W Market St Akron OH 44313",
    "addr:housenumber":"1699",
    "addr:postcode":"44313",
    "addr:street":"W Market St",
    "iso:country":"US",
    "sg:address":"1699 W Market St",
    "sg:city":"Akron",
    "sg:classifiers":[
        {
            "category":"Shopping",
            "type":"Retail Goods"
        }
    ],
    "sg:phone":"+1 330 865 6200",
    "sg:postcode":"44313",
    "sg:province":"OH",
    "sg:tags":[
        "pet",
        "shop"
    ],
    "wof:name":"One Of A Kind Pets",
    "wof:placetype":"venue"
},
  "geometry": {"coordinates":[-81.569869,41.10993],"type":"Point"}
}