{
  "type": "Feature",
  "properties": {
    "addr:full": "1200 Chambers Rd Columbus OH 43212",
    "addr:housenumber": "1200",
    "addr:postcode": "43212",
    "addr:street": "Chambers Rd",
    "iso:country": "US",
    "sg:address": "1200 Chambers Rd",
    "sg:city": "Columbus",
    "sg:classifiers": [
      {
        "category": "Real Estate",
        "subcategory": "Architect",
        "type": "Services"
      }
    ],
    "sg:phone": "+1 614 487 8077",
    "sg:postcode": "43212",
    "sg:province": "OH",
    "sg:tags": [
      "architectural"
    ],
    "wof:name": "M L Architects and Planners",
    "wof:placetype": "venue"
  },
  "geometry": {"coordinates":[-83.042363,39.993739],"type":"Point"}
}
