{
  "type": "Feature",
  "properties": {
    "iso:country":"US",
    "sg:address":"1800 Harding Hwy",
    "sg:city":"Lima",
    "sg:classifiers":[
        {
            "category":"Travel",
            "subcategory":"Hotels & Motels",
            "type":"Entertainment"
        }
    ],
    "sg:phone":"+1 419 228 0456",
    "sg:postcode":"45804",
    "sg:province":"OH",
    "sg:tags":[
        "operation"
    ],
    "wof:name":"Motel 6",
    "wof:placetype":"venue"
},
  "geometry": {"coordinates":[-84.07257199999999,40.730639],"type":"Point"}
}