{
  "type": "Feature",
  "properties": {
    "iso:country":"US",
    "sg:address":"700 Springmill St",
    "sg:city":"Mansfield",
    "sg:classifiers":[
        {
            "category":"Manufacturing",
            "subcategory":"Metals",
            "type":"Manufacturing & Wholesale Goods"
        }
    ],
    "sg:phone":"+1 419 522 0751",
    "sg:postcode":"44903",
    "sg:province":"OH",
    "sg:tags":[
        "product",
        "stampings",
        "stamping",
        "mfg"
    ],
    "wof:name":"Taylor Metal Products Company",
    "wof:placetype":"venue"
},
  "geometry": {"coordinates":[-82.528575,40.772267],"type":"Point"}
}