{
  "type": "Feature",
  "properties": {
    "addr:full": "700 Springmill St Mansfield OH 44903",
    "addr:housenumber": "700",
    "addr:postcode": "44903",
    "addr:street": "Springmill St",
    "iso:country": "US",
    "sg:address": "700 Springmill St",
    "sg:city": "Mansfield",
    "sg:classifiers": [
      {
        "category": "Manufacturing",
        "subcategory": "Metals",
        "type": "Manufacturing \u0026 Wholesale Goods"
      }
    ],
    "sg:phone": "+1 419 522 0751",
    "sg:postcode": "44903",
    "sg:province": "OH",
    "sg:tags": [
      "product",
      "stampings",
      "stamping",
      "mfg"
    ],
    "wof:name": "Taylor Metal Products Company",
    "wof:placetype": "venue"
  },
  "geometry": {"coordinates":[-82.528575,40.772267],"type":"Point"}
}
