{
  "type": "Feature",
  "properties": {
    "addr:full": "310 Watt St Circleville OH 43113",
    "addr:housenumber": "310",
    "addr:postcode": "43113",
    "addr:street": "Watt St",
    "iso:country": "US",
    "sg:address": "310 Watt St",
    "sg:city": "Circleville",
    "sg:classifiers": [
      {
        "category": "Professional",
        "type": "Services"
      }
    ],
    "sg:phone": "+1 740 474 7940",
    "sg:postcode": "43113",
    "sg:province": "OH",
    "wof:name": "Evans Edward",
    "wof:placetype": "venue"
  },
  "geometry": {"coordinates":[-82.939836,39.601657],"type":"Point"}
}
