{
  "type": "Feature",
  "properties": {
    "addr:full":"2445 Brooklyn Rd Columbus OH 43231",
    "addr:housenumber":"2445",
    "addr:postcode":"43231",
    "addr:street":"Brooklyn Rd",
    "iso:country":"US",
    "sg:address":"2445 Brooklyn Rd",
    "sg:city":"Columbus",
    "sg:classifiers":[
        {
            "category":"Banks & Credit Unions",
            "subcategory":"Financial Services",
            "type":"Services"
        }
    ],
    "sg:phone":"+1 614 475 2126",
    "sg:postcode":"43231",
    "sg:province":"OH",
    "sg:tags":[
        "trust",
        "management"
    ],
    "wof:name":"Paul F Barr Trust",
    "wof:placetype":"venue"
},
  "geometry": {"coordinates":[-82.954458,40.061419],"type":"Point"}
}