{
  "type": "Feature",
  "properties": {
    "addr:full": "3425 Glenmore Ave Cincinnati OH 45211",
    "addr:housenumber": "3425",
    "addr:postcode": "45211",
    "addr:street": "Glenmore Ave",
    "iso:country": "US",
    "sg:address": "3425 Glenmore Ave",
    "sg:city": "Cincinnati",
    "sg:classifiers": [
      {
        "category": "Health Services",
        "subcategory": "Doctor",
        "type": "Services"
      }
    ],
    "sg:phone": "+1 513 481 8000",
    "sg:postcode": "45211",
    "sg:province": "OH",
    "wof:name": "Tmthy M Reddy Ddsms Orthdntist",
    "wof:placetype": "venue"
  },
  "geometry": {"coordinates":[-84.61269,39.151032],"type":"Point"}
}
