{
  "type": "Feature",
  "properties": {
    "addr:full":"72 Frebis Ave Columbus OH 43206",
    "addr:housenumber":"72",
    "addr:postcode":"43206",
    "addr:street":"Frebis Ave",
    "iso:country":"US",
    "sg:address":"72 Frebis Ave",
    "sg:city":"Columbus",
    "sg:classifiers":[
        {
            "category":"Building & Trades",
            "subcategory":"Construction",
            "type":"Services"
        }
    ],
    "sg:phone":"+1 614 443 6364",
    "sg:postcode":"43206",
    "sg:province":"OH",
    "sg:tags":[
        "house"
    ],
    "wof:name":"PQ Remodeling",
    "wof:placetype":"venue"
},
  "geometry": {"coordinates":[-82.99348500000001,39.935993],"type":"Point"}
}