{
  "type": "Feature",
  "properties": {
    "addr:full":"8911 Little Mountain Rd Mentor OH 44060",
    "addr:housenumber":"8911",
    "addr:postcode":"44060",
    "addr:street":"Little Mountain Rd",
    "iso:country":"US",
    "sg:address":"8911 Little Mountain Rd",
    "sg:city":"Mentor",
    "sg:classifiers":[
        {
            "category":"Wholesale",
            "subcategory":"Fruits & Vegetables",
            "type":"Manufacturing & Wholesale Goods"
        }
    ],
    "sg:phone":"+1 440 255 3508",
    "sg:postcode":"44060",
    "sg:province":"OH",
    "wof:name":"Miller Quality Produce Inc",
    "wof:placetype":"venue"
},
  "geometry": {"coordinates":[-81.32417599999999,41.647602],"type":"Point"}
}