{
  "type": "Feature",
  "properties": {
    "addr:full": "1015 E Park Cir Girard OH 44420",
    "addr:housenumber": "1015",
    "addr:postcode": "44420",
    "addr:street": "E Park Cir",
    "iso:country": "US",
    "sg:address": "1015 E Park Cir",
    "sg:city": "Girard",
    "sg:classifiers": [
      {
        "category": "Wholesale",
        "subcategory": "Apparel",
        "type": "Manufacturing \u0026 Wholesale Goods"
      }
    ],
    "sg:phone": "+1 330 545 8476",
    "sg:postcode": "44420",
    "sg:province": "OH",
    "sg:tags": [
      "piece"
    ],
    "wof:name": "American Textile Buyers Assn",
    "wof:placetype": "venue"
  },
  "geometry": {"coordinates":[-80.681329,41.151024],"type":"Point"}
}
