{
  "type": "Feature",
  "properties": {
    "iso:country":"US",
    "sg:address":"10483 State Rte 500",
    "sg:city":"Paulding",
    "sg:classifiers":[
        {
            "category":"Shopping",
            "subcategory":"Discount & Variety Stores",
            "type":"Retail Goods"
        }
    ],
    "sg:phone":"+1 419 399 2656",
    "sg:postcode":"45879",
    "sg:province":"OH",
    "sg:tags":[
        "merchandise",
        "general"
    ],
    "wof:name":"Wilhelm Mobile Hm Sales & Park",
    "wof:placetype":"venue"
},
  "geometry": {"coordinates":[-84.62217,41.123407],"type":"Point"}
}