{
  "type": "Feature",
  "properties": {
    "addr:full":"18612 Thorpe Rd Chagrin Falls OH 44023",
    "addr:housenumber":"18612",
    "addr:postcode":"44023",
    "addr:street":"Thorpe Rd",
    "iso:country":"US",
    "sg:address":"18612 Thorpe Rd",
    "sg:city":"Chagrin Falls",
    "sg:classifiers":[
        {
            "category":"Shopping",
            "subcategory":"Clothing, Apparel, & Fashions",
            "type":"Retail Goods"
        }
    ],
    "sg:phone":"+1 440 543 6554",
    "sg:postcode":"44023",
    "sg:province":"OH",
    "wof:name":"Nellys Tailoring",
    "wof:placetype":"venue"
},
  "geometry": {"coordinates":[-81.26060200000001,41.362993],"type":"Point"}
}