{
  "type": "Feature",
  "properties": {
    "addr:full":"6899 E Broad St Columbus OH 43213",
    "addr:housenumber":"6899",
    "addr:postcode":"43213",
    "addr:street":"E Broad St",
    "iso:country":"US",
    "sg:address":"6899 E Broad St",
    "sg:city":"Columbus",
    "sg:classifiers":[
        {
            "category":"Sports & Exercise",
            "subcategory":"Gym",
            "type":"Entertainment"
        }
    ],
    "sg:phone":"+1 614 522 0012",
    "sg:postcode":"43213",
    "sg:province":"OH",
    "sg:tags":[
        "club",
        "health",
        "studio",
        "gymnasium"
    ],
    "wof:name":"Curves For Women",
    "wof:placetype":"venue"
},
  "geometry": {"coordinates":[-82.814234,39.982625],"type":"Point"}
}