{
  "type": "Feature",
  "properties": {
    "addr:full": "11894 Clinton Rd Doylestown OH 44230",
    "addr:housenumber": "11894",
    "addr:postcode": "44230",
    "addr:street": "Clinton Rd",
    "iso:country": "US",
    "sg:address": "11894 Clinton Rd",
    "sg:city": "Doylestown",
    "sg:classifiers": [
      {
        "category": "Professional",
        "type": "Services"
      }
    ],
    "sg:phone": "+1 330 658 4351",
    "sg:postcode": "44230",
    "sg:province": "OH",
    "wof:name": "Jon D Anderson Family Limited",
    "wof:placetype": "venue"
  },
  "geometry": {"coordinates":[-81.661164,40.943248],"type":"Point"}
}
