{
  "type": "Feature",
  "properties": {
    "addr:full":"765 Radio Dr Lewis Center OH 43035",
    "addr:housenumber":"765",
    "addr:postcode":"43035",
    "addr:street":"Radio Dr",
    "iso:country":"US",
    "sg:address":"765 Radio Dr",
    "sg:city":"Lewis Center",
    "sg:classifiers":[
        {
            "category":"Real Estate",
            "subcategory":"Real Estate Agent",
            "type":"Services"
        }
    ],
    "sg:phone":"+1 740 548 0689",
    "sg:postcode":"43035",
    "sg:province":"OH",
    "wof:name":"Triangle Real Estate Svc",
    "wof:placetype":"venue"
},
  "geometry": {"coordinates":[-83.010628,40.158471],"type":"Point"}
}