{
  "type": "Feature",
  "properties": {
    "addr:full": "6180 Halle Dr Cleveland OH 44125",
    "addr:housenumber": "6180",
    "addr:postcode": "44125",
    "addr:street": "Halle Dr",
    "iso:country": "US",
    "sg:address": "6180 Halle Dr",
    "sg:city": "Cleveland",
    "sg:classifiers": [
      {
        "category": "Building \u0026 Trades",
        "subcategory": "Construction",
        "type": "Services"
      }
    ],
    "sg:phone": "+1 216 573 0355",
    "sg:postcode": "44125",
    "sg:province": "OH",
    "sg:tags": [
      "nonresidential"
    ],
    "wof:name": "Tradesmen International",
    "wof:placetype": "venue"
  },
  "geometry": {"coordinates":[-81.617021,41.391631],"type":"Point"}
}
