{
  "type": "Feature",
  "properties": {
    "addr:full":"210 Marybill Dr Troy OH 45373",
    "addr:housenumber":"210",
    "addr:postcode":"45373",
    "addr:street":"Marybill Dr",
    "iso:country":"US",
    "sg:address":"210 Marybill Dr",
    "sg:city":"Troy",
    "sg:classifiers":[
        {
            "category":"Government",
            "subcategory":"Office",
            "type":"Public Place"
        }
    ],
    "sg:phone":"+1 937 440 9911",
    "sg:postcode":"45373",
    "sg:province":"OH",
    "wof:name":"Miami County Dispatch",
    "wof:placetype":"venue"
},
  "geometry": {"coordinates":[-84.24293400000001,40.066308],"type":"Point"}
}