{
  "type": "Feature",
  "properties": {
    "iso:country":"US",
    "sg:address":"4027 Colonel Glenn Hwy",
    "sg:city":"Dayton",
    "sg:classifiers":[
        {
            "category":"Organizations",
            "subcategory":"Non-profit Organization",
            "type":"Services"
        }
    ],
    "sg:phone":"+1 937 427 4710",
    "sg:postcode":"45431",
    "sg:province":"OH",
    "sg:tags":[
        "fund",
        "counselor",
        "raising"
    ],
    "wof:name":"Doyle Group",
    "wof:placetype":"venue"
},
  "geometry": {"coordinates":[-84.084897,39.773747],"type":"Point"}
}