{
  "type": "Feature",
  "properties": {
    "addr:full": "4140 State Rte 44 Rootstown OH 44272",
    "addr:housenumber": "4140",
    "addr:postcode": "44272",
    "addr:street": "State Rte 44",
    "iso:country": "US",
    "sg:address": "4140 State Rte 44",
    "sg:city": "Rootstown",
    "sg:classifiers": [
      {
        "category": "Education",
        "subcategory": "School",
        "type": "Public Place"
      }
    ],
    "sg:phone": "+1 330 325 9911",
    "sg:postcode": "44272",
    "sg:province": "OH",
    "sg:tags": [
      "local",
      "district"
    ],
    "wof:name": "Rootstown Local Sch District",
    "wof:placetype": "venue"
  },
  "geometry": {"coordinates":[-81.242488,41.101434],"type":"Point"}
}
