{
  "type": "Feature",
  "properties": {
    "addr:full":"8 Prestige Plaza Dr Miamisburg OH 45342",
    "addr:housenumber":"8",
    "addr:postcode":"45342",
    "addr:street":"Prestige Plaza Dr",
    "iso:country":"US",
    "sg:address":"8 Prestige Plaza Dr",
    "sg:city":"Miamisburg",
    "sg:classifiers":[
        {
            "category":"Shopping",
            "subcategory":"Clothing, Apparel, & Fashions",
            "type":"Retail Goods"
        }
    ],
    "sg:phone":"+1 937 291 9200",
    "sg:postcode":"45342",
    "sg:province":"OH",
    "sg:tags":[
        "bridal"
    ],
    "wof:name":"Sharnett Bridal & Formal",
    "wof:placetype":"venue"
},
  "geometry": {"coordinates":[-84.225478,39.635912],"type":"Point"}
}