{
  "type": "Feature",
  "properties": {
    "addr:full": "687 Perkinswood Blvd SE Warren OH 44483",
    "addr:housenumber": "687",
    "addr:postcode": "44483",
    "addr:street": "Perkinswood Blvd Se",
    "iso:country": "US",
    "sg:address": "687 Perkinswood Blvd SE",
    "sg:city": "Warren",
    "sg:classifiers": [
      {
        "category": "Manufacturing",
        "subcategory": "Signs",
        "type": "Manufacturing \u0026 Wholesale Goods"
      }
    ],
    "sg:phone": "+1 330 393 4653",
    "sg:postcode": "44483",
    "sg:province": "OH",
    "sg:tags": [
      "specialty",
      "mfg"
    ],
    "wof:name": "Cape Cod Signs",
    "wof:placetype": "venue"
  },
  "geometry": {"coordinates":[-80.784774,41.231776],"type":"Point"}
}
