{
  "type": "Feature",
  "properties": {
    "iso:country":"US",
    "sg:address":"500 Reading Rd",
    "sg:city":"Cincinnati",
    "sg:classifiers":[
        {
            "category":"Shopping",
            "subcategory":"Bicycles & Sporting Goods",
            "type":"Retail Goods"
        }
    ],
    "sg:phone":"+1 513 333 0191",
    "sg:postcode":"45202",
    "sg:province":"OH",
    "sg:tags":[
        "equipment",
        "exercise"
    ],
    "wof:name":"Pendleton Pilates",
    "wof:placetype":"venue"
},
  "geometry": {"coordinates":[-84.504346,39.110295],"type":"Point"}
}