{
  "type": "Feature",
  "properties": {
    "addr:full": "3917 Belmont Ave Youngstown OH 44505",
    "addr:housenumber": "3917",
    "addr:postcode": "44505",
    "addr:street": "Belmont Ave",
    "iso:country": "US",
    "sg:address": "3917 Belmont Ave",
    "sg:city": "Youngstown",
    "sg:classifiers": [
      {
        "category": "Restaurant",
        "type": "Food \u0026 Drink"
      }
    ],
    "sg:phone": "+1 330 759 5480",
    "sg:postcode": "44505",
    "sg:province": "OH",
    "sg:tags": [
      "eating"
    ],
    "sg:website": "www.youngstowncrabco.com",
    "wof:name": "Youngstown Crab Company",
    "wof:placetype": "venue"
  },
  "geometry": {"coordinates":[-80.664961,41.152418],"type":"Point"}
}
