{
  "type": "Feature",
  "properties": {
    "addr:full": "26912 Center Ridge Rd Cleveland OH 44145",
    "addr:housenumber": "26912",
    "addr:postcode": "44145",
    "addr:street": "Center Ridge Rd",
    "iso:country": "US",
    "sg:address": "26912 Center Ridge Rd",
    "sg:city": "Cleveland",
    "sg:classifiers": [
      {
        "category": "Personal",
        "subcategory": "Beauty Salon",
        "type": "Services"
      }
    ],
    "sg:phone": "+1 440 892 0800",
    "sg:postcode": "44145",
    "sg:province": "OH",
    "sg:tags": [
      "treatment",
      "skin"
    ],
    "wof:name": "Skin Restoration \u0026 Permanent",
    "wof:placetype": "venue"
  },
  "geometry": {"coordinates":[-81.918506,41.450942],"type":"Point"}
}
