{
  "type": "Feature",
  "properties": {
    "iso:country":"US",
    "sg:address":"26912 Center Ridge Rd",
    "sg:city":"Cleveland",
    "sg:classifiers":[
        {
            "category":"Personal",
            "subcategory":"Beauty Salon",
            "type":"Services"
        }
    ],
    "sg:phone":"+1 440 892 0800",
    "sg:postcode":"44145",
    "sg:province":"OH",
    "sg:tags":[
        "treatment",
        "skin"
    ],
    "wof:name":"Skin Restoration & Permanent",
    "wof:placetype":"venue"
},
  "geometry": {"coordinates":[-81.918506,41.450942],"type":"Point"}
}