{
  "type": "Feature",
  "properties": {
    "addr:full":"5989 Canal Rd Cleveland OH 44125",
    "addr:housenumber":"5989",
    "addr:postcode":"44125",
    "addr:street":"Canal Rd",
    "iso:country":"US",
    "sg:address":"5989 Canal Rd",
    "sg:city":"Cleveland",
    "sg:classifiers":[
        {
            "category":"Restaurant",
            "type":"Food & Drink"
        }
    ],
    "sg:menulink":"http://www.allmenus.com/oh/valley-view/28934-champs/menu/",
    "sg:phone":"+1 216 328 0083",
    "sg:postcode":"44125",
    "sg:province":"OH",
    "sg:tags":[
        "american"
    ],
    "wof:name":"Champs",
    "wof:placetype":"venue"
},
  "geometry": {"coordinates":[-81.626045,41.39932],"type":"Point"}
}