{
  "type": "Feature",
  "properties": {
    "addr:full": "7 Rowe Ct Hamilton OH 45015",
    "addr:housenumber": "7",
    "addr:postcode": "45015",
    "addr:street": "Rowe Ct",
    "iso:country": "US",
    "sg:address": "7 Rowe Ct",
    "sg:city": "Hamilton",
    "sg:classifiers": [
      {
        "category": "Manufacturing",
        "subcategory": "Tools \u0026 Machinery",
        "type": "Manufacturing \u0026 Wholesale Goods"
      }
    ],
    "sg:phone": "+1 513 874 7236",
    "sg:postcode": "45015",
    "sg:province": "OH",
    "sg:tags": [
      "manufacture",
      "pattern",
      "industrial"
    ],
    "wof:name": "Bren-Ko Patterns Inc",
    "wof:placetype": "venue"
  },
  "geometry": {"coordinates":[-84.510553,39.337576],"type":"Point"}
}
