{
  "type": "Feature",
  "properties": {
    "iso:country":"US",
    "sg:address":"22061 Rye Rd",
    "sg:city":"Cleveland",
    "sg:classifiers":[
        {
            "category":"Professional",
            "type":"Services"
        }
    ],
    "sg:phone":"+1 216 752 6650",
    "sg:postcode":"44122",
    "sg:province":"OH",
    "wof:name":"Jason E & Bernice Lutsker",
    "wof:placetype":"venue"
},
  "geometry": {"coordinates":[-81.520349,41.474857],"type":"Point"}
}