{
  "type": "Feature",
  "properties": {
    "addr:full":"11120 Rd R Columbus Grove OH 45830",
    "addr:housenumber":"11120",
    "addr:postcode":"45830",
    "addr:street":"Rd;Columbus Grove",
    "iso:country":"US",
    "sg:address":"11120 Rd R",
    "sg:city":"Columbus Grove",
    "sg:phone":"+1 419 659 2915",
    "sg:postcode":"45830",
    "sg:province":"OH",
    "sg:tags":[
        "farm",
        "corn",
        "soybean"
    ],
    "wof:name":"Keith Hartoon",
    "wof:placetype":"venue"
},
  "geometry": {"coordinates":[-84.075885,40.919351],"type":"Point"}
}