{
  "type": "Feature",
  "properties": {
    "addr:full": "7218 Justin Way Mentor OH 44060",
    "addr:housenumber": "7218",
    "addr:postcode": "44060",
    "addr:street": "Justin Way",
    "iso:country": "US",
    "sg:address": "7218 Justin Way",
    "sg:city": "Mentor",
    "sg:classifiers": [
      {
        "category": "Manufacturing",
        "subcategory": "Metals",
        "type": "Manufacturing \u0026 Wholesale Goods"
      },
      {
        "category": "Wholesale",
        "subcategory": "Hardware",
        "type": "Manufacturing \u0026 Wholesale Goods"
      }
    ],
    "sg:phone": "+1 440 255 9600",
    "sg:postcode": "44060",
    "sg:province": "OH",
    "sg:tags": [
      "fastener"
    ],
    "sg:website": "www.distributorsales.com",
    "wof:name": "Distributor Sales",
    "wof:placetype": "venue"
  },
  "geometry": {"coordinates":[-81.357635,41.678689],"type":"Point"}
}
