{
  "type": "Feature",
  "properties": {
    "addr:full": "135 E Ohio Ave Sebring OH 44672",
    "addr:housenumber": "135",
    "addr:postcode": "44672",
    "addr:street": "E Ohio Ave",
    "iso:country": "US",
    "sg:address": "135 E Ohio Ave",
    "sg:city": "Sebring",
    "sg:classifiers": [
      {
        "category": "Government",
        "subcategory": "Police Station",
        "type": "Public Place"
      }
    ],
    "sg:phone": "+1 330 938 6114",
    "sg:postcode": "44672",
    "sg:province": "OH",
    "sg:tags": [
      "protection"
    ],
    "wof:name": "Police Department",
    "wof:placetype": "venue"
  },
  "geometry": {"coordinates":[-81.018422,40.923322],"type":"Point"}
}
