{
  "type": "Feature",
  "properties": {
    "iso:country":"US",
    "sg:address":"1892 Logan-Lancaster Rd",
    "sg:city":"Lancaster",
    "sg:classifiers":[
        {
            "category":"Home & Garden",
            "subcategory":"Building Materials",
            "type":"Retail Goods"
        }
    ],
    "sg:phone":"+1 740 653 7198",
    "sg:postcode":"43130",
    "sg:province":"OH",
    "sg:tags":[
        "plumbing",
        "fixture",
        "supply"
    ],
    "wof:name":"Carter Plumbing Electric & Htg",
    "wof:placetype":"venue"
},
  "geometry": {"coordinates":[-82.584794,39.696415],"type":"Point"}
}