{
  "type": "Feature",
  "properties": {
    "iso:country":"US",
    "sg:address":"1333 Home Ave",
    "sg:city":"Akron",
    "sg:classifiers":[
        {
            "category":"Professional",
            "subcategory":"Testing Lab",
            "type":"Services"
        }
    ],
    "sg:phone":"+1 330 945 7500",
    "sg:postcode":"44310",
    "sg:province":"OH",
    "sg:tags":[
        "asbestos"
    ],
    "sg:website":"www.acrtinc.com",
    "wof:name":"ACRT Environmental Specs",
    "wof:placetype":"venue"
},
  "geometry": {"coordinates":[-81.487179,41.107532],"type":"Point"}
}