{
  "type": "Feature",
  "properties": {
    "addr:full":"9925 Royalton Rd Cleveland OH 44133",
    "addr:housenumber":"9925",
    "addr:postcode":"44133",
    "addr:street":"Royalton Rd",
    "iso:country":"US",
    "sg:address":"9925 Royalton Rd",
    "sg:city":"Cleveland",
    "sg:classifiers":[
        {
            "category":"Autos & Motor Vehicles",
            "subcategory":"Auto Supplies",
            "type":"Retail Goods"
        }
    ],
    "sg:phone":"+1 440 582 8270",
    "sg:postcode":"44133",
    "sg:province":"OH",
    "sg:tags":[
        "tire"
    ],
    "wof:name":"Express Auto Tire & Svc",
    "wof:placetype":"venue"
},
  "geometry": {"coordinates":[-81.763008,41.313917],"type":"Point"}
}