{
  "type": "Feature",
  "properties": {
    "iso:country":"US",
    "sg:address":"10210 Adams Ave",
    "sg:city":"Cleveland",
    "sg:classifiers":[
        {
            "category":"Organizations",
            "subcategory":"Religious Organization",
            "type":"Services"
        }
    ],
    "sg:phone":"+1 216 541 6182",
    "sg:postcode":"44108",
    "sg:province":"OH",
    "sg:tags":[
        "clergy"
    ],
    "wof:name":"J D Walker Jr",
    "wof:placetype":"venue"
},
  "geometry": {"coordinates":[-81.615627,41.529963],"type":"Point"}
}