{
  "type": "Feature",
  "properties": {
    "addr:full":"321 Hopeland St Dayton OH 45408",
    "addr:housenumber":"321",
    "addr:postcode":"45408",
    "addr:street":"Hopeland St",
    "iso:country":"US",
    "sg:address":"321 Hopeland St",
    "sg:city":"Dayton",
    "sg:classifiers":[
        {
            "category":"Wholesale",
            "subcategory":"Stationery",
            "type":"Manufacturing & Wholesale Goods"
        }
    ],
    "sg:phone":"+1 937 223 3958",
    "sg:postcode":"45408",
    "sg:province":"OH",
    "sg:tags":[
        "paper",
        "fold",
        "converted",
        "mfg"
    ],
    "sg:website":"www.imperialpk.com",
    "wof:name":"Imperial Packaging Corp",
    "wof:placetype":"venue"
},
  "geometry": {"coordinates":[-84.19980099999999,39.74358],"type":"Point"}
}