{
  "type": "Feature",
  "properties": {
    "addr:full":"10266 Northfield Rd Northfield OH 44067",
    "addr:housenumber":"10266",
    "addr:postcode":"44067",
    "addr:street":"Northfield Rd",
    "iso:country":"US",
    "sg:address":"10266 Northfield Rd",
    "sg:city":"Northfield",
    "sg:classifiers":[
        {
            "category":"Retail",
            "subcategory":"Auto Repair",
            "type":"Services"
        }
    ],
    "sg:phone":"+1 330 467 3555",
    "sg:postcode":"44067",
    "sg:province":"OH",
    "sg:tags":[
        "body",
        "glass",
        "painting",
        "automobile"
    ],
    "wof:name":"Northfield Collision Serv",
    "wof:placetype":"venue"
},
  "geometry": {"coordinates":[-81.53090400000001,41.336332],"type":"Point"}
}