{
  "type": "Feature",
  "properties": {
    "addr:full":"26400 Broadway Ave Cleveland OH 44146",
    "addr:housenumber":"26400",
    "addr:postcode":"44146",
    "addr:street":"Broadway Ave",
    "iso:country":"US",
    "sg:address":"26400 Broadway Ave",
    "sg:city":"Cleveland",
    "sg:classifiers":[
        {
            "category":"Food & Beverages",
            "subcategory":"Groceries & Convenience Stores",
            "type":"Retail Goods"
        }
    ],
    "sg:phone":"+1 216 661 9808",
    "sg:postcode":"44146",
    "sg:province":"OH",
    "sg:tags":[
        "product"
    ],
    "wof:name":"Snyders Of Hanover",
    "wof:placetype":"venue"
},
  "geometry": {"coordinates":[-81.48909500000001,41.349834],"type":"Point"}
}