{
  "type": "Feature",
  "properties": {
    "addr:full": "1207 Central Ave Middletown OH 45044",
    "addr:housenumber": "1207",
    "addr:postcode": "45044",
    "addr:street": "Central Ave",
    "iso:country": "US",
    "sg:address": "1207 Central Ave",
    "sg:city": "Middletown",
    "sg:classifiers": [
      {
        "category": "Home \u0026 Garden",
        "subcategory": "Building Materials",
        "type": "Retail Goods"
      }
    ],
    "sg:phone": "+1 513 705 6028",
    "sg:postcode": "45044",
    "sg:province": "OH",
    "sg:tags": [
      "glass",
      "window",
      "plate"
    ],
    "wof:name": "Integrity Auto Glass",
    "wof:placetype": "venue"
  },
  "geometry": {"coordinates":[-84.401133,39.515529],"type":"Point"}
}
