{
  "type": "Feature",
  "properties": {
    "addr:full": "2115 E Dorothy Ln Dayton OH 45420",
    "addr:housenumber": "2115",
    "addr:postcode": "45420",
    "addr:street": "E Dorothy Ln",
    "iso:country": "US",
    "sg:address": "2115 E Dorothy Ln",
    "sg:city": "Dayton",
    "sg:classifiers": [
      {
        "category": "Food \u0026 Beverages",
        "subcategory": "Groceries \u0026 Convenience Stores",
        "type": "Retail Goods"
      },
      {
        "category": "Shopping",
        "subcategory": "Pharmacy",
        "type": "Retail Goods"
      }
    ],
    "sg:phone": "+1 937 299 7475",
    "sg:postcode": "45420",
    "sg:province": "OH",
    "sg:tags": [
      "grocer"
    ],
    "wof:name": "Kroger",
    "wof:placetype": "venue"
  },
  "geometry": {"coordinates":[-84.127532,39.703012],"type":"Point"}
}
