{
  "type": "Feature",
  "properties": {
    "iso:country":"US",
    "sg:address":"302 N Court St",
    "sg:city":"Medina",
    "sg:classifiers":[
        {
            "category":"Travel",
            "subcategory":"Hotels & Motels",
            "type":"Entertainment"
        }
    ],
    "sg:phone":"+1 330 725 4535",
    "sg:postcode":"44256",
    "sg:province":"OH",
    "wof:name":"Towne Motel Of Medina Inc",
    "wof:placetype":"venue"
},
  "geometry": {"coordinates":[-81.86392499999999,41.142125],"type":"Point"}
}