{
  "type": "Feature",
  "properties": {
    "iso:country":"US",
    "sg:address":"787 Lexington Ave",
    "sg:city":"Mansfield",
    "sg:classifiers":[
        {
            "category":"Personal",
            "type":"Services"
        }
    ],
    "sg:phone":"+1 419 565 5084",
    "sg:postcode":"44907",
    "sg:province":"OH",
    "sg:tags":[
        "therapist",
        "massage"
    ],
    "wof:name":"Valerie J Stone",
    "wof:placetype":"venue"
},
  "geometry": {"coordinates":[-82.53224299999999,40.735639],"type":"Point"}
}