{
  "type": "Feature",
  "properties": {
    "addr:full":"2541 Hilliard Rome Rd Hilliard OH 43026",
    "addr:housenumber":"2541",
    "addr:postcode":"43026",
    "addr:street":"Hilliard Rome Rd",
    "iso:country":"US",
    "sg:address":"2541 Hilliard Rome Rd",
    "sg:city":"Hilliard",
    "sg:classifiers":[
        {
            "category":"Banks & Credit Unions",
            "subcategory":"Bank",
            "type":"Services"
        }
    ],
    "sg:phone":"+1 614 921 8694",
    "sg:postcode":"43026",
    "sg:province":"OH",
    "sg:tags":[
        "cashing",
        "check"
    ],
    "wof:name":"Advance America",
    "wof:placetype":"venue"
},
  "geometry": {"coordinates":[-83.15342800000001,40.000166],"type":"Point"}
}