{
  "type": "Feature",
  "properties": {
    "addr:full": "421 Prentice Rd NW Warren OH 44481",
    "addr:housenumber": "421",
    "addr:postcode": "44481",
    "addr:street": "Prentice Rd Nw",
    "iso:country": "US",
    "sg:address": "421 Prentice Rd NW",
    "sg:city": "Warren",
    "sg:classifiers": [
      {
        "category": "Building \u0026 Trades",
        "subcategory": "Construction",
        "type": "Services"
      }
    ],
    "sg:phone": "+1 330 847 0952",
    "sg:postcode": "44481",
    "sg:province": "OH",
    "sg:tags": [
      "excavation",
      "concrete",
      "contractor"
    ],
    "wof:name": "J \u0026 J Concrete",
    "wof:placetype": "venue"
  },
  "geometry": {"coordinates":[-80.869582,41.333991],"type":"Point"}
}
