{
  "type": "Feature",
  "properties": {
    "addr:full": "2838 Hampshire Rd Cleveland OH 44118",
    "addr:housenumber": "2838",
    "addr:postcode": "44118",
    "addr:street": "Hampshire Rd",
    "iso:country": "US",
    "sg:address": "2838 Hampshire Rd",
    "sg:city": "Cleveland",
    "sg:classifiers": [
      {
        "category": "Professional",
        "type": "Services"
      }
    ],
    "sg:phone": "+1 216 932 8872",
    "sg:postcode": "44118",
    "sg:province": "OH",
    "wof:name": "Winslow H Crocker III",
    "wof:placetype": "venue"
  },
  "geometry": {"coordinates":[-81.579292,41.510808],"type":"Point"}
}
