{
  "type": "Feature",
  "properties": {
    "addr:full": "319 S 2nd St Miamisburg OH 45342",
    "addr:housenumber": "319",
    "addr:postcode": "45342",
    "addr:street": "S 2Nd St",
    "iso:country": "US",
    "sg:address": "319 S 2nd St",
    "sg:city": "Miamisburg",
    "sg:classifiers": [
      {
        "category": "Restaurant",
        "type": "Food \u0026 Drink"
      }
    ],
    "sg:phone": "+1 937 866 5968",
    "sg:postcode": "45342",
    "sg:province": "OH",
    "sg:website": "www.peerlessmillinn.net",
    "wof:name": "Peerless Mill Inn",
    "wof:placetype": "venue"
  },
  "geometry": {"coordinates":[-84.287851,39.639341],"type":"Point"}
}
