{
  "type": "Feature",
  "properties": {
    "iso:country":"US",
    "sg:address":"238 W 6th Ave",
    "sg:city":"Lancaster",
    "sg:classifiers":[
        {
            "category":"Education",
            "subcategory":"Vocational School",
            "type":"Public Place"
        }
    ],
    "sg:phone":"+1 740 652 1990",
    "sg:postcode":"43130",
    "sg:province":"OH",
    "sg:tags":[
        "training",
        "computer"
    ],
    "wof:name":"S G Training Ctr",
    "wof:placetype":"venue"
},
  "geometry": {"coordinates":[-82.60451,39.7199],"type":"Point"}
}