{
  "type": "Feature",
  "properties": {
    "addr:full": "1805 E Main St Columbus OH 43205",
    "addr:housenumber": "1805",
    "addr:postcode": "43205",
    "addr:street": "E Main St",
    "iso:country": "US",
    "sg:address": "1805 E Main St",
    "sg:city": "Columbus",
    "sg:classifiers": [
      {
        "category": "Health Services",
        "subcategory": "Clinic",
        "type": "Services"
      }
    ],
    "sg:phone": "+1 614 253 3300",
    "sg:postcode": "43205",
    "sg:province": "OH",
    "sg:tags": [
      "kidney",
      "dialysis",
      "center"
    ],
    "wof:name": "America Renal Associates",
    "wof:placetype": "venue"
  },
  "geometry": {"coordinates":[-82.949885,39.957373],"type":"Point"}
}
