{
  "type": "Feature",
  "properties": {
    "iso:country":"US",
    "sg:address":"1805 E Main St",
    "sg:city":"Columbus",
    "sg:classifiers":[
        {
            "category":"Health Services",
            "subcategory":"Clinic",
            "type":"Services"
        }
    ],
    "sg:phone":"+1 614 253 3300",
    "sg:postcode":"43205",
    "sg:province":"OH",
    "sg:tags":[
        "kidney",
        "dialysis",
        "center"
    ],
    "wof:name":"America Renal Associates",
    "wof:placetype":"venue"
},
  "geometry": {"coordinates":[-82.94988499999999,39.957373],"type":"Point"}
}