{
  "type": "Feature",
  "properties": {
    "addr:full": "1762 State Rte 131 Fayetteville OH 45118",
    "addr:housenumber": "1762",
    "addr:postcode": "45118",
    "addr:street": "State Rte 131",
    "iso:country": "US",
    "sg:address": "1762 State Rte 131",
    "sg:city": "Fayetteville",
    "sg:classifiers": [
      {
        "category": "Manufacturing",
        "subcategory": "Tools \u0026 Machinery",
        "type": "Manufacturing \u0026 Wholesale Goods"
      }
    ],
    "sg:phone": "+1 513 875 3388",
    "sg:postcode": "45118",
    "sg:province": "OH",
    "sg:tags": [
      "generator"
    ],
    "wof:name": "B J Generator Repair",
    "wof:placetype": "venue"
  },
  "geometry": {"coordinates":[-83.997871,39.173914],"type":"Point"}
}
