{
  "type": "Feature",
  "properties": {
    "addr:full": "5303 Glenway Ave Cincinnati OH 45238",
    "addr:housenumber": "5303",
    "addr:postcode": "45238",
    "addr:street": "Glenway Ave",
    "iso:country": "US",
    "sg:address": "5303 Glenway Ave",
    "sg:city": "Cincinnati",
    "sg:classifiers": [
      {
        "category": "Shopping",
        "type": "Retail Goods"
      }
    ],
    "sg:phone": "+1 513 923 4999",
    "sg:postcode": "45238",
    "sg:province": "OH",
    "sg:tags": [
      "hearing",
      "equipment",
      "supply",
      "impaired"
    ],
    "wof:name": "Beltone Hearing Aid Ctr",
    "wof:placetype": "venue"
  },
  "geometry": {"coordinates":[-84.604624,39.126315],"type":"Point"}
}
