{
  "type": "Feature",
  "properties": {
    "addr:full": "101 N Ohio Ave Fremont OH 43420",
    "addr:housenumber": "101",
    "addr:postcode": "43420",
    "addr:street": "N Ohio Ave",
    "iso:country": "US",
    "sg:address": "101 N Ohio Ave",
    "sg:city": "Fremont",
    "sg:classifiers": [
      {
        "category": "Personal",
        "subcategory": "Beauty Salon",
        "type": "Services"
      }
    ],
    "sg:phone": "+1 419 334 3243",
    "sg:postcode": "43420",
    "sg:province": "OH",
    "wof:name": "Hair Today",
    "wof:placetype": "venue"
  },
  "geometry": {"coordinates":[-83.106689,41.346934],"type":"Point"}
}
