{
  "type": "Feature",
  "properties": {
    "addr:full": "26900 Cedar Rd Cleveland OH 44122",
    "addr:housenumber": "26900",
    "addr:postcode": "44122",
    "addr:street": "Cedar Rd",
    "iso:country": "US",
    "sg:address": "26900 Cedar Rd",
    "sg:city": "Cleveland",
    "sg:classifiers": [
      {
        "category": "Health Services",
        "subcategory": "Medical Lab",
        "type": "Services"
      }
    ],
    "sg:phone": "+1 216 765 0241",
    "sg:postcode": "44122",
    "sg:province": "OH",
    "sg:tags": [
      "laboratory"
    ],
    "wof:name": "Quest Diagnostics Inc",
    "wof:placetype": "venue"
  },
  "geometry": {"coordinates":[-81.487867,41.501148],"type":"Point"}
}
