{
  "type": "Feature",
  "properties": {
    "addr:full": "6503 Marsol Rd Cleveland OH 44124",
    "addr:housenumber": "6503",
    "addr:postcode": "44124",
    "addr:street": "Marsol Rd",
    "iso:country": "US",
    "sg:address": "6503 Marsol Rd",
    "sg:city": "Cleveland",
    "sg:classifiers": [
      {
        "category": "Shopping",
        "subcategory": "Hobbies, Toys, \u0026 Games",
        "type": "Retail Goods"
      }
    ],
    "sg:phone": "+1 440 461 0641",
    "sg:postcode": "44124",
    "sg:province": "OH",
    "sg:tags": [
      "craft"
    ],
    "wof:name": "Edina Glozshteyn Crafts",
    "wof:placetype": "venue"
  },
  "geometry": {"coordinates":[-81.438863,41.515175],"type":"Point"}
}
