{
  "type": "Feature",
  "properties": {
    "iso:country":"US",
    "sg:address":"6503 Marsol Rd",
    "sg:city":"Cleveland",
    "sg:classifiers":[
        {
            "category":"Shopping",
            "subcategory":"Hobbies, Toys, & Games",
            "type":"Retail Goods"
        }
    ],
    "sg:phone":"+1 440 461 0641",
    "sg:postcode":"44124",
    "sg:province":"OH",
    "sg:tags":[
        "craft"
    ],
    "wof:name":"Edina Glozshteyn Crafts",
    "wof:placetype":"venue"
},
  "geometry": {"coordinates":[-81.438863,41.515175],"type":"Point"}
}