{
  "type": "Feature",
  "properties": {
    "addr:full":"6544 N River Rd Waterville OH 43566",
    "addr:housenumber":"6544",
    "addr:postcode":"43566",
    "addr:street":"N River Rd",
    "iso:country":"US",
    "sg:address":"6544 N River Rd",
    "sg:city":"Waterville",
    "sg:classifiers":[
        {
            "category":"Autos & Motor Vehicles",
            "subcategory":"Automobile Sales",
            "type":"Retail Goods"
        },
        {
            "category":"Freight",
            "type":"Transportation"
        }
    ],
    "sg:phone":"+1 419 878 2121",
    "sg:postcode":"43566",
    "sg:province":"OH",
    "sg:tags":[
        "operator",
        "car",
        "dealer",
        "trucking"
    ],
    "wof:name":"Nu Concept Auto Carriers",
    "wof:placetype":"venue"
},
  "geometry": {"coordinates":[-83.714286,41.521167],"type":"Point"}
}