{
  "type": "Feature",
  "properties": {
    "addr:full": "10000 Root Rd Columbia Station OH 44028",
    "addr:postcode": "10000;44028",
    "addr:street": "Root Rd",
    "iso:country": "US",
    "sg:address": "10000 Root Rd",
    "sg:city": "Columbia Station",
    "sg:classifiers": [
      {
        "category": "Building \u0026 Trades",
        "subcategory": "Construction",
        "type": "Services"
      }
    ],
    "sg:phone": "+1 440 748 2700",
    "sg:postcode": "44028",
    "sg:province": "OH",
    "sg:tags": [
      "painter"
    ],
    "wof:name": "Precision Painting \u0026 Wllcvrng",
    "wof:placetype": "venue"
  },
  "geometry": {"coordinates":[-81.971446,41.343787],"type":"Point"}
}
