{
  "type": "Feature",
  "properties": {
    "addr:full": "414 Colegate Dr Marietta OH 45750",
    "addr:housenumber": "414",
    "addr:postcode": "45750",
    "addr:street": "Colegate Dr",
    "iso:country": "US",
    "sg:address": "414 Colegate Dr",
    "sg:city": "Marietta",
    "sg:classifiers": [
      {
        "category": "Organizations",
        "subcategory": "Non-profit Organization",
        "type": "Services"
      }
    ],
    "sg:phone": "+1 740 373 2227",
    "sg:postcode": "45750",
    "sg:province": "OH",
    "wof:name": "Elks BPOE Four Seventy Seven",
    "wof:placetype": "venue"
  },
  "geometry": {"coordinates":[-81.436193,39.425019],"type":"Point"}
}
