{
  "type": "Feature",
  "properties": {
    "iso:country":"US",
    "sg:address":"248 Plain St",
    "sg:city":"Magnolia",
    "sg:classifiers":[
        {
            "category":"Wholesale",
            "subcategory":"Electrical",
            "type":"Manufacturing & Wholesale Goods"
        },
        {
            "category":"Manufacturing",
            "subcategory":"Tools & Machinery",
            "type":"Manufacturing & Wholesale Goods"
        }
    ],
    "sg:phone":"+1 330 866 2544",
    "sg:postcode":"44643",
    "sg:province":"OH",
    "sg:tags":[
        "transmission",
        "equipment",
        "speed",
        "power",
        "mfg"
    ],
    "sg:website":"www.seweurodrive.com",
    "wof:name":"Sew-Eurodrive Inc",
    "wof:placetype":"venue"
},
  "geometry": {"coordinates":[-81.296476,40.65025],"type":"Point"}
}