{
  "type": "Feature",
  "properties": {
    "addr:full": "248 Plain St Magnolia OH 44643",
    "addr:housenumber": "248",
    "addr:postcode": "44643",
    "addr:street": "Plain St",
    "iso:country": "US",
    "sg:address": "248 Plain St",
    "sg:city": "Magnolia",
    "sg:classifiers": [
      {
        "category": "Wholesale",
        "subcategory": "Electrical",
        "type": "Manufacturing \u0026 Wholesale Goods"
      },
      {
        "category": "Manufacturing",
        "subcategory": "Tools \u0026 Machinery",
        "type": "Manufacturing \u0026 Wholesale Goods"
      }
    ],
    "sg:phone": "+1 330 866 2544",
    "sg:postcode": "44643",
    "sg:province": "OH",
    "sg:tags": [
      "transmission",
      "equipment",
      "speed",
      "power",
      "mfg"
    ],
    "sg:website": "www.seweurodrive.com",
    "wof:name": "Sew-Eurodrive Inc",
    "wof:placetype": "venue"
  },
  "geometry": {"coordinates":[-81.296476,40.65025],"type":"Point"}
}
