{
  "type": "Feature",
  "properties": {
    "iso:country":"US",
    "sg:address":"7910 Beechmont Ave",
    "sg:city":"Cincinnati",
    "sg:classifiers":[
        {
            "category":"Health Services",
            "subcategory":"Health Practitioner",
            "type":"Services"
        }
    ],
    "sg:phone":"+1 513 474 8600",
    "sg:postcode":"45255",
    "sg:province":"OH",
    "sg:tags":[
        "therapist",
        "physical"
    ],
    "wof:name":"Sports Therapy Inc",
    "wof:placetype":"venue"
},
  "geometry": {"coordinates":[-84.33735,39.072748],"type":"Point"}
}