{
  "type": "Feature",
  "properties": {
    "addr:full":"3285 Chadbourne Rd Cleveland OH 44120",
    "addr:housenumber":"3285",
    "addr:postcode":"44120",
    "addr:street":"Chadbourne Rd",
    "iso:country":"US",
    "sg:address":"3285 Chadbourne Rd",
    "sg:city":"Cleveland",
    "sg:classifiers":[
        {
            "category":"Building & Trades",
            "subcategory":"Cleaning & Sanitation",
            "type":"Services"
        }
    ],
    "sg:phone":"+1 216 561 1951",
    "sg:postcode":"44120",
    "sg:province":"OH",
    "sg:tags":[
        "janitor"
    ],
    "wof:name":"T & S Cleaning Inc",
    "wof:placetype":"venue"
},
  "geometry": {"coordinates":[-81.572239,41.470346],"type":"Point"}
}