{
  "type": "Feature",
  "properties": {
    "addr:full": "2211 State Rte 165 East Palestine OH 44413",
    "addr:housenumber": "2211",
    "addr:postcode": "44413",
    "addr:street": "State Rte 165 East",
    "iso:country": "US",
    "sg:address": "2211 State Rte 165",
    "sg:city": "East Palestine",
    "sg:classifiers": [
      {
        "category": "Building \u0026 Trades",
        "subcategory": "Cleaning \u0026 Sanitation",
        "type": "Services"
      }
    ],
    "sg:phone": "+1 330 426 4467",
    "sg:postcode": "44413",
    "sg:province": "OH",
    "sg:tags": [
      "landscaping",
      "commercial",
      "janitorial"
    ],
    "wof:name": "Ulbrichs Landscaping",
    "wof:placetype": "venue"
  },
  "geometry": {"coordinates":[-80.548926,40.857282],"type":"Point"}
}
