{
  "type": "Feature",
  "properties": {
    "addr:full":"5770 State Rte 762 Ashville OH 43146",
    "addr:housenumber":"5770",
    "addr:postcode":"43146",
    "addr:street":"State Rte 762",
    "iso:country":"US",
    "sg:address":"5770 State Rte 762",
    "sg:city":"Ashville",
    "sg:classifiers":[
        {
            "category":"Professional",
            "type":"Services"
        }
    ],
    "sg:phone":"+1 740 983 2053",
    "sg:postcode":"43146",
    "sg:province":"OH",
    "wof:name":"Wendy Taylor",
    "wof:placetype":"venue"
},
  "geometry": {"coordinates":[-83.050376,39.76921],"type":"Point"}
}