{
  "type": "Feature",
  "properties": {
    "iso:country":"US",
    "sg:address":"1596 Bloomingdale Ave",
    "sg:city":"Cincinnati",
    "sg:classifiers":[
        {
            "category":"Professional",
            "subcategory":"Art Services",
            "type":"Services"
        }
    ],
    "sg:phone":"+1 513 871 3346",
    "sg:postcode":"45230",
    "sg:province":"OH",
    "sg:tags":[
        "graphic",
        "designer"
    ],
    "sg:website":"www.imprintdesign.com",
    "wof:name":"Imprint Design Inc",
    "wof:placetype":"venue"
},
  "geometry": {"coordinates":[-84.396016,39.083836],"type":"Point"}
}