{
  "type": "Feature",
  "properties": {
    "addr:full":"3829 Main St Perry OH 44081",
    "addr:housenumber":"3829",
    "addr:postcode":"44081",
    "addr:street":"Main St",
    "iso:country":"US",
    "sg:address":"3829 Main St",
    "sg:city":"Perry",
    "sg:classifiers":[
        {
            "category":"School Buses",
            "type":"Transportation"
        }
    ],
    "sg:phone":"+1 440 259 3005",
    "sg:postcode":"44081",
    "sg:province":"OH",
    "wof:name":"Perry Transportation Dept",
    "wof:placetype":"venue"
},
  "geometry": {"coordinates":[-81.159278,41.764575],"type":"Point"}
}