{
  "type": "Feature",
  "properties": {
    "addr:full":"13519 Euclid Ave Cleveland OH 44112",
    "addr:housenumber":"13519",
    "addr:postcode":"44112",
    "addr:street":"Euclid Ave",
    "iso:country":"US",
    "sg:address":"13519 Euclid Ave",
    "sg:city":"Cleveland",
    "sg:classifiers":[
        {
            "category":"Shopping",
            "subcategory":"Shoes",
            "type":"Retail Goods"
        }
    ],
    "sg:phone":"+1 216 681 8005",
    "sg:postcode":"44112",
    "sg:province":"OH",
    "wof:name":"Payless Shoe Source",
    "wof:placetype":"venue"
},
  "geometry": {"coordinates":[-81.58811799999999,41.524539],"type":"Point"}
}