{
  "type": "Feature",
  "properties": {
    "addr:full":"28331 Center Ridge Rd Cleveland OH 44145",
    "addr:housenumber":"28331",
    "addr:postcode":"44145",
    "addr:street":"Center Ridge Rd",
    "iso:country":"US",
    "sg:address":"28331 Center Ridge Rd",
    "sg:city":"Cleveland",
    "sg:classifiers":[
        {
            "category":"Real Estate",
            "subcategory":"Real Estate Operator",
            "type":"Services"
        }
    ],
    "sg:phone":"+1 440 871 8866",
    "sg:postcode":"44145",
    "sg:province":"OH",
    "sg:tags":[
        "building",
        "apartment"
    ],
    "wof:name":"Timber Ridge Apartments",
    "wof:placetype":"venue"
},
  "geometry": {"coordinates":[-81.935649,41.441562],"type":"Point"}
}