{
  "type": "Feature",
  "properties": {
    "iso:country":"US",
    "sg:address":"6501 Barberton Ave",
    "sg:city":"Cleveland",
    "sg:classifiers":[
        {
            "category":"Wholesale",
            "subcategory":"Construction Materials",
            "type":"Manufacturing & Wholesale Goods"
        }
    ],
    "sg:phone":"+1 216 961 8449",
    "sg:postcode":"44102",
    "sg:province":"OH",
    "sg:tags":[
        "granite"
    ],
    "wof:name":"Jesri Modern Store",
    "wof:placetype":"venue"
},
  "geometry": {"coordinates":[-81.733821,41.458043],"type":"Point"}
}