{
  "type": "Feature",
  "properties": {
    "iso:country":"US",
    "sg:address":"266 E 2nd St",
    "sg:city":"Girard",
    "sg:classifiers":[
        {
            "category":"Building & Trades",
            "subcategory":"Electrical",
            "type":"Services"
        }
    ],
    "sg:phone":"+1 330 545 6652",
    "sg:postcode":"44420",
    "sg:province":"OH",
    "sg:tags":[
        "electrical",
        "contractor"
    ],
    "wof:name":"Mikes Electric",
    "wof:placetype":"venue"
},
  "geometry": {"coordinates":[-80.69296300000001,41.152323],"type":"Point"}
}