{
  "type": "Feature",
  "properties": {
    "addr:full": "266 E 2nd St Girard OH 44420",
    "addr:housenumber": "266",
    "addr:postcode": "44420",
    "addr:street": "E 2Nd St",
    "iso:country": "US",
    "sg:address": "266 E 2nd St",
    "sg:city": "Girard",
    "sg:classifiers": [
      {
        "category": "Building \u0026 Trades",
        "subcategory": "Electrical",
        "type": "Services"
      }
    ],
    "sg:phone": "+1 330 545 6652",
    "sg:postcode": "44420",
    "sg:province": "OH",
    "sg:tags": [
      "electrical",
      "contractor"
    ],
    "wof:name": "Mikes Electric",
    "wof:placetype": "venue"
  },
  "geometry": {"coordinates":[-80.692963,41.152323],"type":"Point"}
}
