{
  "type": "Feature",
  "properties": {
    "addr:full":"19552 State Rte 180 Laurelville OH 43135",
    "addr:housenumber":"19552",
    "addr:postcode":"43135",
    "addr:street":"State Rte 180",
    "iso:country":"US",
    "sg:address":"19552 State Rte 180",
    "sg:city":"Laurelville",
    "sg:classifiers":[
        {
            "category":"Food & Beverages",
            "subcategory":"Groceries & Convenience Stores",
            "type":"Retail Goods"
        }
    ],
    "sg:phone":"+1 740 332 0630",
    "sg:postcode":"43135",
    "sg:province":"OH",
    "sg:tags":[
        "grocer"
    ],
    "wof:name":"South Perry Carry Out",
    "wof:placetype":"venue"
},
  "geometry": {"coordinates":[-82.669764,39.496841],"type":"Point"}
}