{
  "type": "Feature",
  "properties": {
    "addr:full":"1517 Thomas St Ironton OH 45638",
    "addr:housenumber":"1517",
    "addr:postcode":"45638",
    "addr:street":"Thomas St",
    "iso:country":"US",
    "sg:address":"1517 Thomas St",
    "sg:city":"Ironton",
    "sg:classifiers":[
        {
            "category":"Professional",
            "type":"Services"
        }
    ],
    "sg:phone":"+1 740 532 2223",
    "sg:postcode":"45638",
    "sg:province":"OH",
    "wof:name":"Sandra Wooten",
    "wof:placetype":"venue"
},
  "geometry": {"coordinates":[-82.701537,38.550818],"type":"Point"}
}