{
  "type": "Feature",
  "properties": {
    "addr:full":"217 Zimmerman St New Carlisle OH 45344",
    "addr:housenumber":"217",
    "addr:postcode":"45344",
    "addr:street":"Zimmerman St",
    "iso:country":"US",
    "sg:address":"217 Zimmerman St",
    "sg:city":"New Carlisle",
    "sg:classifiers":[
        {
            "category":"Organizations",
            "subcategory":"Community Association",
            "type":"Services"
        }
    ],
    "sg:phone":"+1 937 845 0743",
    "sg:postcode":"45344",
    "sg:province":"OH",
    "wof:name":"Sertoma International",
    "wof:placetype":"venue"
},
  "geometry": {"coordinates":[-84.036636,39.939887],"type":"Point"}
}