{
  "type": "Feature",
  "properties": {
    "addr:full":"725 S Vandemark Rd Sidney OH 45365",
    "addr:housenumber":"725",
    "addr:postcode":"45365",
    "addr:street":"S Vandemark Rd",
    "iso:country":"US",
    "sg:address":"725 S Vandemark Rd",
    "sg:city":"Sidney",
    "sg:classifiers":[
        {
            "category":"Railroad",
            "type":"Transportation"
        }
    ],
    "sg:phone":"+1 937 492 5228",
    "sg:postcode":"45365",
    "sg:province":"OH",
    "wof:name":"Conrail",
    "wof:placetype":"venue"
},
  "geometry": {"coordinates":[-84.187927,40.279481],"type":"Point"}
}