{
  "type": "Feature",
  "properties": {
    "addr:full": "20801 Miles Rd Cleveland OH 44128",
    "addr:housenumber": "20801",
    "addr:postcode": "44128",
    "addr:street": "Miles Rd",
    "iso:country": "US",
    "sg:address": "20801 Miles Rd",
    "sg:city": "Cleveland",
    "sg:classifiers": [
      {
        "category": "Professional",
        "subcategory": "Printing \u0026 Photocopies",
        "type": "Services"
      },
      {
        "category": "Manufacturing",
        "subcategory": "Printing",
        "type": "Manufacturing \u0026 Wholesale Goods"
      }
    ],
    "sg:phone": "+1 216 587 0077",
    "sg:postcode": "44128",
    "sg:province": "OH",
    "sg:tags": [
      "lithographic",
      "commercial",
      "duplicating",
      "copying"
    ],
    "wof:name": "Unigraphics Printing \u0026 Copy",
    "wof:placetype": "venue"
  },
  "geometry": {"coordinates":[-81.531465,41.428662],"type":"Point"}
}
