{
  "type": "Feature",
  "properties": {
    "addr:full":"1243 Tennessee Ave Cincinnati OH 45229",
    "addr:housenumber":"1243",
    "addr:postcode":"45229",
    "addr:street":"Tennessee Ave",
    "iso:country":"US",
    "sg:address":"1243 Tennessee Ave",
    "sg:city":"Cincinnati",
    "sg:classifiers":[
        {
            "category":"Wholesale",
            "subcategory":"Stationery",
            "type":"Manufacturing & Wholesale Goods"
        }
    ],
    "sg:phone":"+1 513 641 3661",
    "sg:postcode":"45229",
    "sg:province":"OH",
    "sg:tags":[
        "mfr",
        "marking",
        "devices"
    ],
    "wof:name":"Sayre Joseph J & Son Co Inc",
    "wof:placetype":"venue"
},
  "geometry": {"coordinates":[-84.476011,39.168224],"type":"Point"}
}