{
  "type": "Feature",
  "properties": {
    "addr:full": "52 Rainbow Ave Sunbury OH 43074",
    "addr:housenumber": "52",
    "addr:postcode": "43074",
    "addr:street": "Rainbow Ave",
    "iso:country": "US",
    "sg:address": "52 Rainbow Ave",
    "sg:city": "Sunbury",
    "sg:classifiers": [
      {
        "category": "Wholesale",
        "subcategory": "Meat",
        "type": "Manufacturing \u0026 Wholesale Goods"
      }
    ],
    "sg:phone": "+1 614 906 2810",
    "sg:postcode": "43074",
    "sg:province": "OH",
    "sg:tags": [
      "mfg",
      "prepared"
    ],
    "wof:name": "Virgils Jerky Plus",
    "wof:placetype": "venue"
  },
  "geometry": {"coordinates":[-82.856108,40.24648],"type":"Point"}
}
