{
  "type": "Feature",
  "properties": {
    "iso:country":"US",
    "sg:address":"52 Rainbow Ave",
    "sg:city":"Sunbury",
    "sg:classifiers":[
        {
            "category":"Wholesale",
            "subcategory":"Meat",
            "type":"Manufacturing & Wholesale Goods"
        }
    ],
    "sg:phone":"+1 614 906 2810",
    "sg:postcode":"43074",
    "sg:province":"OH",
    "sg:tags":[
        "mfg",
        "prepared"
    ],
    "wof:name":"Virgils Jerky Plus",
    "wof:placetype":"venue"
},
  "geometry": {"coordinates":[-82.85610800000001,40.24648],"type":"Point"}
}