{
  "type": "Feature",
  "properties": {
    "iso:country":"US",
    "sg:address":"1070 Oberlin Dr",
    "sg:city":"Columbus",
    "sg:classifiers":[
        {
            "category":"Professional",
            "type":"Services"
        }
    ],
    "sg:phone":"+1 614 459 8133",
    "sg:postcode":"43221",
    "sg:province":"OH",
    "sg:tags":[
        "technical",
        "preparation",
        "manual"
    ],
    "wof:name":"Counterpoint",
    "wof:placetype":"venue"
},
  "geometry": {"coordinates":[-83.042721,40.025902],"type":"Point"}
}