{
  "type": "Feature",
  "properties": {
    "addr:full": "2175 Schlichter Dr Hamilton OH 45015",
    "addr:housenumber": "2175",
    "addr:postcode": "45015",
    "addr:street": "Schlichter Dr",
    "iso:country": "US",
    "sg:address": "2175 Schlichter Dr",
    "sg:city": "Hamilton",
    "sg:classifiers": [
      {
        "category": "Building \u0026 Trades",
        "subcategory": "Construction",
        "type": "Services"
      }
    ],
    "sg:phone": "+1 513 869 7660",
    "sg:postcode": "45015",
    "sg:province": "OH",
    "sg:tags": [
      "steel",
      "structure"
    ],
    "wof:name": "Rebar Express Cincinati LLC",
    "wof:placetype": "venue"
  },
  "geometry": {"coordinates":[-84.542858,39.36711],"type":"Point"}
}
