{
  "type": "Feature",
  "properties": {
    "iso:country":"US",
    "sg:address":"2175 Schlichter Dr",
    "sg:city":"Hamilton",
    "sg:classifiers":[
        {
            "category":"Building & Trades",
            "subcategory":"Construction",
            "type":"Services"
        }
    ],
    "sg:phone":"+1 513 869 7660",
    "sg:postcode":"45015",
    "sg:province":"OH",
    "sg:tags":[
        "steel",
        "structure"
    ],
    "wof:name":"Rebar Express Cincinati LLC",
    "wof:placetype":"venue"
},
  "geometry": {"coordinates":[-84.542858,39.36711],"type":"Point"}
}