{
  "type": "Feature",
  "properties": {
    "addr:full": "5549 Convoy Rd Convoy OH 45832",
    "addr:housenumber": "5549",
    "addr:postcode": "45832",
    "addr:street": "Convoy Rd",
    "iso:country": "US",
    "sg:address": "5549 Convoy Rd",
    "sg:city": "Convoy",
    "sg:classifiers": [
      {
        "category": "Banks \u0026 Credit Unions",
        "subcategory": "Financial Services",
        "type": "Services"
      }
    ],
    "sg:phone": "+1 419 749 2644",
    "sg:postcode": "45832",
    "sg:province": "OH",
    "sg:tags": [
      "investor"
    ],
    "wof:name": "Jasa Investments LLC",
    "wof:placetype": "venue"
  },
  "geometry": {"coordinates":[-84.718025,40.916969],"type":"Point"}
}
