{
  "type": "Feature",
  "properties": {
    "iso:country":"US",
    "sg:address":"2196 Ferris Rd",
    "sg:city":"Columbus",
    "sg:classifiers":[
        {
            "category":"Professional",
            "type":"Services"
        }
    ],
    "sg:phone":"+1 614 478 0515",
    "sg:postcode":"43224",
    "sg:province":"OH",
    "wof:name":"James Dean Hanck",
    "wof:placetype":"venue"
},
  "geometry": {"coordinates":[-82.95839100000001,40.050081],"type":"Point"}
}