{
  "type": "Feature",
  "properties": {
    "addr:full": "2196 Ferris Rd Columbus OH 43224",
    "addr:housenumber": "2196",
    "addr:postcode": "43224",
    "addr:street": "Ferris Rd",
    "iso:country": "US",
    "sg:address": "2196 Ferris Rd",
    "sg:city": "Columbus",
    "sg:classifiers": [
      {
        "category": "Professional",
        "type": "Services"
      }
    ],
    "sg:phone": "+1 614 478 0515",
    "sg:postcode": "43224",
    "sg:province": "OH",
    "wof:name": "James Dean Hanck",
    "wof:placetype": "venue"
  },
  "geometry": {"coordinates":[-82.958391,40.050081],"type":"Point"}
}
