{
  "type": "Feature",
  "properties": {
    "iso:country":"US",
    "sg:address":"310 N Cleveland Massillon Rd",
    "sg:city":"Akron",
    "sg:classifiers":[
        {
            "category":"Professional",
            "subcategory":"Lawyer & Legal Services",
            "type":"Services"
        }
    ],
    "sg:phone":"+1 330 666 6900",
    "sg:postcode":"44333",
    "sg:province":"OH",
    "sg:tags":[
        "attorney"
    ],
    "wof:name":"John P Lazar",
    "wof:placetype":"venue"
},
  "geometry": {"coordinates":[-81.637327,41.143728],"type":"Point"}
}