{
  "type": "Feature",
  "properties": {
    "iso:country":"US",
    "sg:address":"14204 Aspinwall Ave",
    "sg:city":"Cleveland",
    "sg:classifiers":[
        {
            "category":"Personal",
            "subcategory":"Beauty Salon",
            "type":"Services"
        }
    ],
    "sg:phone":"+1 216 249 1400",
    "sg:postcode":"44110",
    "sg:province":"OH",
    "wof:name":"Diverse Styles Barber Salon",
    "wof:placetype":"venue"
},
  "geometry": {"coordinates":[-81.58336199999999,41.557853],"type":"Point"}
}