{
  "type": "Feature",
  "properties": {
    "addr:full": "505 London Rd Delaware OH 43015",
    "addr:housenumber": "505",
    "addr:postcode": "43015",
    "addr:street": "London Rd",
    "iso:country": "US",
    "sg:address": "505 London Rd",
    "sg:city": "Delaware",
    "sg:classifiers": [
      {
        "category": "Professional",
        "subcategory": "Accounting \u0026 Tax Preparation",
        "type": "Services"
      }
    ],
    "sg:phone": "+1 740 363 4500",
    "sg:postcode": "43015",
    "sg:province": "OH",
    "sg:tags": [
      "billing"
    ],
    "wof:name": "Consolidated Billing Systems",
    "wof:placetype": "venue"
  },
  "geometry": {"coordinates":[-83.085529,40.28646],"type":"Point"}
}
