{
  "type": "Feature",
  "properties": {
    "addr:full": "1100 Perry St Orrville OH 44667",
    "addr:housenumber": "1100",
    "addr:postcode": "44667",
    "addr:street": "Perry St",
    "iso:country": "US",
    "sg:address": "1100 Perry St",
    "sg:city": "Orrville",
    "sg:classifiers": [
      {
        "category": "Government",
        "subcategory": "Office",
        "type": "Public Place"
      }
    ],
    "sg:phone": "+1 330 684 5100",
    "sg:postcode": "44667",
    "sg:province": "OH",
    "sg:tags": [
      "village"
    ],
    "wof:name": "Orrville City Electric Dept",
    "wof:placetype": "venue"
  },
  "geometry": {"coordinates":[-81.766202,40.850467],"type":"Point"}
}
