{
  "type": "Feature",
  "properties": {
    "iso:country":"US",
    "sg:address":"9743 Carey Rd",
    "sg:city":"West Liberty",
    "sg:classifiers":[
        {
            "category":"Farming",
            "subcategory":"Livestock Farm",
            "type":"Manufacturing & Wholesale Goods"
        }
    ],
    "sg:phone":"+1 937 465 3309",
    "sg:postcode":"43357",
    "sg:province":"OH",
    "sg:tags":[
        "beef",
        "feedlot",
        "cattle"
    ],
    "wof:name":"Wilbur Wren",
    "wof:placetype":"venue"
},
  "geometry": {"coordinates":[-83.803751,40.250575],"type":"Point"}
}