{
  "type": "Feature",
  "properties": {
    "addr:full": "1601 Oakmont Ln Sandusky OH 44870",
    "addr:housenumber": "1601",
    "addr:postcode": "44870",
    "addr:street": "Oakmont Ln",
    "iso:country": "US",
    "sg:address": "1601 Oakmont Ln",
    "sg:city": "Sandusky",
    "sg:classifiers": [
      {
        "category": "Organizations",
        "subcategory": "Religious Organization",
        "type": "Services"
      }
    ],
    "sg:phone": "+1 419 626 5295",
    "sg:postcode": "44870",
    "sg:province": "OH",
    "sg:tags": [
      "clergy"
    ],
    "wof:name": "Herman Robinson",
    "wof:placetype": "venue"
  },
  "geometry": {"coordinates":[-82.684393,41.445938],"type":"Point"}
}
