{
  "type": "Feature",
  "properties": {
    "iso:country":"US",
    "sg:address":"2787 Martin Rd",
    "sg:city":"Dublin",
    "sg:classifiers":[
        {
            "category":"Restaurant",
            "type":"Food & Drink"
        }
    ],
    "sg:menulink":"http://www.allmenus.com/oh/columbus/134392-subway/menu/",
    "sg:phone":"+1 614 793 2813",
    "sg:postcode":"43017",
    "sg:province":"OH",
    "sg:tags":[
        "american",
        "sandwich"
    ],
    "wof:name":"Subway",
    "wof:placetype":"venue"
},
  "geometry": {"coordinates":[-83.090863,40.094391],"type":"Point"}
}