{
  "type": "Feature",
  "properties": {
    "addr:full": "2787 Martin Rd Dublin OH 43017",
    "addr:housenumber": "2787",
    "addr:postcode": "43017",
    "addr:street": "Martin Rd",
    "iso:country": "US",
    "sg:address": "2787 Martin Rd",
    "sg:city": "Dublin",
    "sg:classifiers": [
      {
        "category": "Restaurant",
        "type": "Food \u0026 Drink"
      }
    ],
    "sg:menulink": "http://www.allmenus.com/oh/columbus/134392-subway/menu/",
    "sg:phone": "+1 614 793 2813",
    "sg:postcode": "43017",
    "sg:province": "OH",
    "sg:tags": [
      "american",
      "sandwich"
    ],
    "wof:name": "Subway",
    "wof:placetype": "venue"
  },
  "geometry": {"coordinates":[-83.090863,40.094391],"type":"Point"}
}
