{
  "type": "Feature",
  "properties": {
    "addr:full": "2105 N Teralta Cir Cincinnati OH 45211",
    "addr:housenumber": "2105",
    "addr:postcode": "45211",
    "addr:street": "N Teralta Cir",
    "iso:country": "US",
    "sg:address": "2105 N Teralta Cir",
    "sg:city": "Cincinnati",
    "sg:classifiers": [
      {
        "category": "Building \u0026 Trades",
        "subcategory": "Construction",
        "type": "Services"
      }
    ],
    "sg:phone": "+1 513 662 4353",
    "sg:postcode": "45211",
    "sg:province": "OH",
    "sg:tags": [
      "carpentry",
      "contractor"
    ],
    "wof:name": "Pw Contracting",
    "wof:placetype": "venue"
  },
  "geometry": {"coordinates":[-84.567882,39.137489],"type":"Point"}
}
