{
  "type": "Feature",
  "properties": {
    "addr:full":"208 Springboro Pike Dayton OH 45439",
    "addr:housenumber":"208",
    "addr:postcode":"45439",
    "addr:street":"Springboro Pike",
    "iso:country":"US",
    "sg:address":"208 Springboro Pike",
    "sg:city":"Dayton",
    "sg:classifiers":[
        {
            "category":"Professional",
            "subcategory":"Employment Agencies",
            "type":"Services"
        }
    ],
    "sg:phone":"+1 937 439 2702",
    "sg:postcode":"45439",
    "sg:province":"OH",
    "sg:tags":[
        "help",
        "contractor"
    ],
    "wof:name":"Extrahelp Staffing Svc",
    "wof:placetype":"venue"
},
  "geometry": {"coordinates":[-84.221081,39.682874],"type":"Point"}
}