{
  "type": "Feature",
  "properties": {
    "iso:country":"US",
    "sg:address":"1432 Tuscarawas St E",
    "sg:city":"Canton",
    "sg:classifiers":[
        {
            "category":"Organizations",
            "subcategory":"Non-profit Organization",
            "type":"Services"
        }
    ],
    "sg:phone":"+1 330 456 3565",
    "sg:postcode":"44707",
    "sg:province":"OH",
    "sg:website":"www.commtreatment.org",
    "wof:name":"Comm Treatmnt & Correction Ct",
    "wof:placetype":"venue"
},
  "geometry": {"coordinates":[-81.360491,40.795521],"type":"Point"}
}