{
  "type": "Feature",
  "properties": {
    "addr:full":"10678 Carnation Way Hillsboro OH 45133",
    "addr:housenumber":"10678",
    "addr:postcode":"45133",
    "addr:street":"Carnation Way",
    "iso:country":"US",
    "sg:address":"10678 Carnation Way",
    "sg:city":"Hillsboro",
    "sg:classifiers":[
        {
            "category":"Building & Trades",
            "subcategory":"Construction",
            "type":"Services"
        }
    ],
    "sg:phone":"+1 937 393 2586",
    "sg:postcode":"45133",
    "sg:province":"OH",
    "sg:tags":[
        "residential"
    ],
    "wof:name":"W/J Mobile Home Svc",
    "wof:placetype":"venue"
},
  "geometry": {"coordinates":[-83.499309,39.191558],"type":"Point"}
}