{
  "type": "Feature",
  "properties": {
    "addr:full": "2965 Columbus St Grove City OH 43123",
    "addr:housenumber": "2965",
    "addr:postcode": "43123",
    "addr:street": "Columbus St",
    "iso:country": "US",
    "sg:address": "2965 Columbus St",
    "sg:city": "Grove City",
    "sg:classifiers": [
      {
        "category": "Professional",
        "subcategory": "Accounting \u0026 Tax Preparation",
        "type": "Services"
      }
    ],
    "sg:phone": "+1 614 539 7070",
    "sg:postcode": "43123",
    "sg:province": "OH",
    "sg:tags": [
      "return",
      "filing"
    ],
    "wof:name": "AMS Accounting \u0026 Tax",
    "wof:placetype": "venue"
  },
  "geometry": {"coordinates":[-83.08392,39.881496],"type":"Point"}
}
