{
  "type": "Feature",
  "properties": {
    "iso:country":"US",
    "sg:address":"2965 Columbus St",
    "sg:city":"Grove City",
    "sg:classifiers":[
        {
            "category":"Professional",
            "subcategory":"Accounting & Tax Preparation",
            "type":"Services"
        }
    ],
    "sg:phone":"+1 614 539 7070",
    "sg:postcode":"43123",
    "sg:province":"OH",
    "sg:tags":[
        "return",
        "filing"
    ],
    "wof:name":"AMS Accounting & Tax",
    "wof:placetype":"venue"
},
  "geometry": {"coordinates":[-83.08392000000001,39.881496],"type":"Point"}
}