{
  "type": "Feature",
  "properties": {
    "iso:country":"US",
    "sg:address":"2220 Superior Via",
    "sg:city":"Cleveland",
    "sg:classifiers":[
        {
            "category":"Banks & Credit Unions",
            "subcategory":"Bank",
            "type":"Services"
        }
    ],
    "sg:phone":"+1 216 622 0454",
    "sg:postcode":"44113",
    "sg:province":"OH",
    "sg:tags":[
        "loan",
        "real estate"
    ],
    "wof:name":"American Home Loans",
    "wof:placetype":"venue"
},
  "geometry": {"coordinates":[-81.706085,41.493029],"type":"Point"}
}