{
  "type": "Feature",
  "properties": {
    "addr:full":"842 Abbe Rd N Sheffield Lake OH 44054",
    "addr:housenumber":"842",
    "addr:postcode":"44054",
    "addr:street":"Abbe Rd N",
    "iso:country":"US",
    "sg:address":"842 Abbe Rd N",
    "sg:city":"Sheffield Lake",
    "sg:classifiers":[
        {
            "category":"Building & Trades",
            "subcategory":"Landscaping Services",
            "type":"Services"
        }
    ],
    "sg:phone":"+1 440 949 9333",
    "sg:postcode":"44054",
    "sg:province":"OH",
    "sg:tags":[
        "ornamental",
        "fertilizing",
        "tree",
        "lawn",
        "shrub"
    ],
    "wof:name":"Weed Pro Ltd",
    "wof:placetype":"venue"
},
  "geometry": {"coordinates":[-82.07572399999999,41.488111],"type":"Point"}
}