{
  "type": "Feature",
  "properties": {
    "iso:country":"US",
    "sg:address":"24350 Garden Dr",
    "sg:city":"Euclid",
    "sg:classifiers":[
        {
            "category":"Shopping",
            "subcategory":"Computers & Home Electronics",
            "type":"Retail Goods"
        }
    ],
    "sg:phone":"+1 216 289 4220",
    "sg:postcode":"44123",
    "sg:province":"OH",
    "sg:tags":[
        "software"
    ],
    "wof:name":"Dawson & Dawson Enterprises",
    "wof:placetype":"venue"
},
  "geometry": {"coordinates":[-81.51312,41.598375],"type":"Point"}
}