{
  "type": "Feature",
  "properties": {
    "iso:country":"US",
    "sg:address":"1565 Mitchell Rd",
    "sg:city":"North Baltimore",
    "sg:classifiers":[
        {
            "category":"Farming",
            "subcategory":"Farm",
            "type":"Manufacturing & Wholesale Goods"
        }
    ],
    "sg:phone":"+1 419 257 3356",
    "sg:postcode":"45872",
    "sg:province":"OH",
    "sg:tags":[
        "crop",
        "general"
    ],
    "wof:name":"Don Seiler",
    "wof:placetype":"venue"
},
  "geometry": {"coordinates":[-83.68809299999999,41.174479],"type":"Point"}
}