{
  "type": "Feature",
  "properties": {
    "addr:full": "1565 Mitchell Rd North Baltimore OH 45872",
    "addr:housenumber": "1565",
    "addr:postcode": "45872",
    "addr:street": "Mitchell Rd",
    "iso:country": "US",
    "sg:address": "1565 Mitchell Rd",
    "sg:city": "North Baltimore",
    "sg:classifiers": [
      {
        "category": "Farming",
        "subcategory": "Farm",
        "type": "Manufacturing \u0026 Wholesale Goods"
      }
    ],
    "sg:phone": "+1 419 257 3356",
    "sg:postcode": "45872",
    "sg:province": "OH",
    "sg:tags": [
      "crop",
      "general"
    ],
    "wof:name": "Don Seiler",
    "wof:placetype": "venue"
  },
  "geometry": {"coordinates":[-83.688093,41.174479],"type":"Point"}
}
