{
  "type": "Feature",
  "properties": {
    "addr:full": "125 Smith Ave NW Canton OH 44708",
    "addr:housenumber": "125",
    "addr:postcode": "44708",
    "addr:street": "Smith Ave Nw",
    "iso:country": "US",
    "sg:address": "125 Smith Ave NW",
    "sg:city": "Canton",
    "sg:classifiers": [
      {
        "category": "Retail",
        "subcategory": "Auto Repair",
        "type": "Services"
      }
    ],
    "sg:phone": "+1 330 454 0244",
    "sg:postcode": "44708",
    "sg:province": "OH",
    "sg:tags": [
      "repairing",
      "automobile"
    ],
    "wof:name": "Randy's Automotive",
    "wof:placetype": "venue"
  },
  "geometry": {"coordinates":[-81.399446,40.800806],"type":"Point"}
}
