{
  "type": "Feature",
  "properties": {
    "iso:country":"US",
    "sg:address":"3774 Clay Bank Dr",
    "sg:city":"Hilliard",
    "sg:classifiers":[
        {
            "category":"Building & Trades",
            "subcategory":"Construction",
            "type":"Services"
        }
    ],
    "sg:phone":"+1 614 771 1777",
    "sg:postcode":"43026",
    "sg:province":"OH",
    "sg:tags":[
        "house",
        "carpenter"
    ],
    "wof:name":"Loscocco & Company Inc",
    "wof:placetype":"venue"
},
  "geometry": {"coordinates":[-83.119352,40.048524],"type":"Point"}
}