{
  "type": "Feature",
  "properties": {
    "iso:country":"US",
    "sg:address":"13840 Emerson Rd",
    "sg:city":"Dalton",
    "sg:classifiers":[
        {
            "category":"Wholesale",
            "subcategory":"Construction Materials",
            "type":"Manufacturing & Wholesale Goods"
        }
    ],
    "sg:phone":"+1 330 466 5942",
    "sg:postcode":"44618",
    "sg:province":"OH",
    "sg:tags":[
        "fence"
    ],
    "wof:name":"Kidron Vinyl",
    "wof:placetype":"venue"
},
  "geometry": {"coordinates":[-81.73273399999999,40.741143],"type":"Point"}
}