{
  "type": "Feature",
  "properties": {
    "addr:full": "13840 Emerson Rd Dalton OH 44618",
    "addr:housenumber": "13840",
    "addr:postcode": "44618",
    "addr:street": "Emerson Rd",
    "iso:country": "US",
    "sg:address": "13840 Emerson Rd",
    "sg:city": "Dalton",
    "sg:classifiers": [
      {
        "category": "Wholesale",
        "subcategory": "Construction Materials",
        "type": "Manufacturing \u0026 Wholesale Goods"
      }
    ],
    "sg:phone": "+1 330 466 5942",
    "sg:postcode": "44618",
    "sg:province": "OH",
    "sg:tags": [
      "fence"
    ],
    "wof:name": "Kidron Vinyl",
    "wof:placetype": "venue"
  },
  "geometry": {"coordinates":[-81.732734,40.741143],"type":"Point"}
}
