{
  "type": "Feature",
  "properties": {
    "addr:full":"805 Defiance St Wapakoneta OH 45895",
    "addr:housenumber":"805",
    "addr:postcode":"45895",
    "addr:street":"Defiance St",
    "iso:country":"US",
    "sg:address":"805 Defiance St",
    "sg:city":"Wapakoneta",
    "sg:classifiers":[
        {
            "category":"Food & Beverages",
            "subcategory":"Groceries & Convenience Stores",
            "type":"Retail Goods"
        },
        {
            "category":"Shopping",
            "subcategory":"Pharmacy",
            "type":"Retail Goods"
        }
    ],
    "sg:phone":"+1 419 738 4108",
    "sg:postcode":"45895",
    "sg:province":"OH",
    "sg:tags":[
        "grocer",
        "eating"
    ],
    "wof:name":"Community Market Inc",
    "wof:placetype":"venue"
},
  "geometry": {"coordinates":[-84.20236800000001,40.578427],"type":"Point"}
}