{
  "type": "Feature",
  "properties": {
    "iso:country":"US",
    "sg:address":"2023 Belmont Ave",
    "sg:city":"Youngstown",
    "sg:classifiers":[
        {
            "category":"Health Services",
            "subcategory":"Doctor",
            "type":"Services"
        }
    ],
    "sg:phone":"+1 330 743 9655",
    "sg:postcode":"44505",
    "sg:province":"OH",
    "sg:tags":[
        "dentist"
    ],
    "wof:name":"James O Corbett DDS",
    "wof:placetype":"venue"
},
  "geometry": {"coordinates":[-80.664636,41.12839],"type":"Point"}
}