{
  "type": "Feature",
  "properties": {
    "iso:country":"US",
    "sg:address":"22900 State Rte 34",
    "sg:city":"Archbold",
    "sg:classifiers":[
        {
            "category":"Education",
            "subcategory":"Junior College",
            "type":"Public Place"
        }
    ],
    "sg:phone":"+1 419 267 3331",
    "sg:postcode":"43502",
    "sg:province":"OH",
    "sg:tags":[
        "technical",
        "institute"
    ],
    "sg:website":"www.fourcounty.net",
    "wof:name":"Four County Career Ctr",
    "wof:placetype":"venue"
},
  "geometry": {"coordinates":[-84.303802,41.451279],"type":"Point"}
}