{
  "type": "Feature",
  "properties": {
    "addr:full": "47 Westchester Dr Youngstown OH 44515",
    "addr:housenumber": "47",
    "addr:postcode": "44515",
    "addr:street": "Westchester Dr",
    "iso:country": "US",
    "sg:address": "47 Westchester Dr",
    "sg:city": "Youngstown",
    "sg:classifiers": [
      {
        "category": "Banks \u0026 Credit Unions",
        "subcategory": "Investment Brokerage",
        "type": "Services"
      }
    ],
    "sg:phone": "+1 330 792 9011",
    "sg:postcode": "44515",
    "sg:province": "OH",
    "sg:tags": [
      "consultant",
      "planning",
      "financial"
    ],
    "wof:name": "Hannon \u0026 Assoc Financial Svc",
    "wof:placetype": "venue"
  },
  "geometry": {"coordinates":[-80.748481,41.097896],"type":"Point"}
}
