{
  "type": "Feature",
  "properties": {
    "iso:country":"US",
    "sg:address":"47 Westchester Dr",
    "sg:city":"Youngstown",
    "sg:classifiers":[
        {
            "category":"Banks & Credit Unions",
            "subcategory":"Investment Brokerage",
            "type":"Services"
        }
    ],
    "sg:phone":"+1 330 792 9011",
    "sg:postcode":"44515",
    "sg:province":"OH",
    "sg:tags":[
        "consultant",
        "planning",
        "financial"
    ],
    "wof:name":"Hannon & Assoc Financial Svc",
    "wof:placetype":"venue"
},
  "geometry": {"coordinates":[-80.748481,41.097896],"type":"Point"}
}