{
  "type": "Feature",
  "properties": {
    "iso:country":"US",
    "sg:address":"2520 S Reynolds Rd",
    "sg:city":"Toledo",
    "sg:classifiers":[
        {
            "category":"Home & Garden",
            "subcategory":"Garden Supply",
            "type":"Retail Goods"
        }
    ],
    "sg:phone":"+1 419 865 8897",
    "sg:postcode":"43614",
    "sg:province":"OH",
    "wof:name":"Franks Nursery & Crafts 36",
    "wof:placetype":"venue"
},
  "geometry": {"coordinates":[-83.664755,41.594235],"type":"Point"}
}