{
  "type": "Feature",
  "properties": {
    "addr:full": "180 Mill St Columbus OH 43230",
    "addr:housenumber": "180",
    "addr:postcode": "43230",
    "addr:street": "Mill St",
    "iso:country": "US",
    "sg:address": "180 Mill St",
    "sg:city": "Columbus",
    "sg:classifiers": [
      {
        "category": "Autos \u0026 Motor Vehicles",
        "subcategory": "Automobile Sales",
        "type": "Retail Goods"
      }
    ],
    "sg:phone": "+1 614 475 7148",
    "sg:postcode": "43230",
    "sg:province": "OH",
    "sg:tags": [
      "car",
      "used",
      "dealer"
    ],
    "wof:name": "Gahanna Auto Sales Inc",
    "wof:placetype": "venue"
  },
  "geometry": {"coordinates":[-82.87758,40.024821],"type":"Point"}
}
