{
  "type": "Feature",
  "properties": {
    "addr:full":"3366 E 55th St Cleveland OH 44127",
    "addr:housenumber":"3366",
    "addr:postcode":"44127",
    "addr:street":"E 55Th St",
    "iso:country":"US",
    "sg:address":"3366 E 55th St",
    "sg:city":"Cleveland",
    "sg:classifiers":[
        {
            "category":"Health Services",
            "subcategory":"Chiropractor",
            "type":"Services"
        }
    ],
    "sg:phone":"+1 216 271 1133",
    "sg:postcode":"44127",
    "sg:province":"OH",
    "wof:name":"Broadway Chiropractic Clinic",
    "wof:placetype":"venue"
},
  "geometry": {"coordinates":[-81.65156500000001,41.466859],"type":"Point"}
}