{
  "type": "Feature",
  "properties": {
    "iso:country":"US",
    "sg:address":"9501 W Central Ave",
    "sg:city":"Sylvania",
    "sg:classifiers":[
        {
            "category":"Sports & Exercise",
            "subcategory":"Golf",
            "type":"Entertainment"
        }
    ],
    "sg:phone":"+1 419 829 2891",
    "sg:postcode":"43560",
    "sg:province":"OH",
    "sg:tags":[
        "course"
    ],
    "sg:website":"www.spuytenduyval.com",
    "wof:name":"Spuyten Duyval Golf Club",
    "wof:placetype":"venue"
},
  "geometry": {"coordinates":[-83.772415,41.673395],"type":"Point"}
}