{
  "type": "Feature",
  "properties": {
    "iso:country":"US",
    "sg:address":"1197 W 5th Ave",
    "sg:city":"Columbus",
    "sg:classifiers":[
        {
            "category":"Banks & Credit Unions",
            "subcategory":"Bank",
            "type":"Services"
        }
    ],
    "sg:phone":"+1 614 485 0400",
    "sg:postcode":"43212",
    "sg:province":"OH",
    "sg:tags":[
        "cashing",
        "check"
    ],
    "wof:name":"Always Payday",
    "wof:placetype":"venue"
},
  "geometry": {"coordinates":[-83.038618,39.988416],"type":"Point"}
}