{
  "type": "Feature",
  "properties": {
    "addr:full": "5444 Carlton Rd Medina OH 44256",
    "addr:housenumber": "5444",
    "addr:postcode": "44256",
    "addr:street": "Carlton Rd",
    "iso:country": "US",
    "sg:address": "5444 Carlton Rd",
    "sg:city": "Medina",
    "sg:classifiers": [
      {
        "category": "Manufacturing",
        "subcategory": "Tools \u0026 Machinery",
        "type": "Manufacturing \u0026 Wholesale Goods"
      }
    ],
    "sg:phone": "+1 330 725 8917",
    "sg:postcode": "44256",
    "sg:province": "OH",
    "sg:tags": [
      "industrial",
      "mfg"
    ],
    "wof:name": "Palkers Machining",
    "wof:placetype": "venue"
  },
  "geometry": {"coordinates":[-81.930332,41.125053],"type":"Point"}
}
