{
  "type": "Feature",
  "properties": {
    "addr:full":"303 East St Liberty Center OH 43532",
    "addr:housenumber":"303",
    "addr:postcode":"43532",
    "addr:street":"East St",
    "iso:country":"US",
    "sg:address":"303 East St",
    "sg:city":"Liberty Center",
    "sg:classifiers":[
        {
            "category":"Personal",
            "subcategory":"Beauty Salon",
            "type":"Services"
        }
    ],
    "sg:phone":"+1 419 533 2461",
    "sg:postcode":"43532",
    "sg:province":"OH",
    "wof:name":"Bonnie's Beauty Shoppe",
    "wof:placetype":"venue"
},
  "geometry": {"coordinates":[-84.008387,41.445226],"type":"Point"}
}