{
  "type": "Feature",
  "properties": {
    "addr:full":"616 S Yearling Rd Columbus OH 43213",
    "addr:housenumber":"616",
    "addr:postcode":"43213",
    "addr:street":"S Yearling Rd",
    "iso:country":"US",
    "sg:address":"616 S Yearling Rd",
    "sg:city":"Columbus",
    "sg:classifiers":[
        {
            "category":"Personal",
            "subcategory":"Beauty Salon",
            "type":"Services"
        }
    ],
    "sg:phone":"+1 614 231 4677",
    "sg:postcode":"43213",
    "sg:province":"OH",
    "wof:name":"Styles Of Excellence Inc",
    "wof:placetype":"venue"
},
  "geometry": {"coordinates":[-82.88578099999999,39.961594],"type":"Point"}
}