{
  "type": "Feature",
  "properties": {
    "addr:full": "3525 Blackmore Rd Perry OH 44081",
    "addr:housenumber": "3525",
    "addr:postcode": "44081",
    "addr:street": "Blackmore Rd",
    "iso:country": "US",
    "sg:address": "3525 Blackmore Rd",
    "sg:city": "Perry",
    "sg:classifiers": [
      {
        "category": "Wholesale",
        "subcategory": "Plants",
        "type": "Manufacturing \u0026 Wholesale Goods"
      },
      {
        "category": "Farming",
        "subcategory": "Farm",
        "type": "Manufacturing \u0026 Wholesale Goods"
      }
    ],
    "sg:phone": "+1 440 259 5757",
    "sg:postcode": "44081",
    "sg:province": "OH",
    "sg:tags": [
      "food",
      "covered",
      "nursery",
      "tree",
      "crop"
    ],
    "wof:name": "Moretti Nursery Inc",
    "wof:placetype": "venue"
  },
  "geometry": {"coordinates":[-81.176702,41.779241],"type":"Point"}
}
