{
  "type": "Feature",
  "properties": {
    "iso:country":"US",
    "sg:address":"3525 Blackmore Rd",
    "sg:city":"Perry",
    "sg:classifiers":[
        {
            "category":"Wholesale",
            "subcategory":"Plants",
            "type":"Manufacturing & Wholesale Goods"
        },
        {
            "category":"Farming",
            "subcategory":"Farm",
            "type":"Manufacturing & Wholesale Goods"
        }
    ],
    "sg:phone":"+1 440 259 5757",
    "sg:postcode":"44081",
    "sg:province":"OH",
    "sg:tags":[
        "food",
        "covered",
        "nursery",
        "tree",
        "crop"
    ],
    "wof:name":"Moretti Nursery Inc",
    "wof:placetype":"venue"
},
  "geometry": {"coordinates":[-81.17670200000001,41.779241],"type":"Point"}
}