{
  "type": "Feature",
  "properties": {
    "addr:full":"180 N 5th St Batavia OH 45103",
    "addr:housenumber":"180",
    "addr:postcode":"45103",
    "addr:street":"N 5Th St",
    "iso:country":"US",
    "sg:address":"180 N 5th St",
    "sg:city":"Batavia",
    "sg:classifiers":[
        {
            "category":"Organizations",
            "subcategory":"Religious Organization",
            "type":"Services"
        }
    ],
    "sg:phone":"+1 513 732 2027",
    "sg:postcode":"45103",
    "sg:province":"OH",
    "sg:tags":[
        "church"
    ],
    "wof:name":"Batavia Faith United Methodist",
    "wof:placetype":"venue"
},
  "geometry": {"coordinates":[-84.172721,39.075932],"type":"Point"}
}