{
  "type": "Feature",
  "properties": {
    "iso:country":"US",
    "sg:address":"542 Turkey Foot Rd",
    "sg:city":"Wheelersburg",
    "sg:classifiers":[
        {
            "category":"Shopping",
            "subcategory":"Computers & Home Electronics",
            "type":"Retail Goods"
        }
    ],
    "sg:phone":"+1 740 574 9860",
    "sg:postcode":"45694",
    "sg:province":"OH",
    "wof:name":"Hyperkat",
    "wof:placetype":"venue"
},
  "geometry": {"coordinates":[-82.780849,38.764629],"type":"Point"}
}