{
  "type": "Feature",
  "properties": {
    "addr:full":"47 Lexington Blvd Madison OH 44057",
    "addr:housenumber":"47",
    "addr:postcode":"44057",
    "addr:street":"Lexington Blvd",
    "iso:country":"US",
    "sg:address":"47 Lexington Blvd",
    "sg:city":"Madison",
    "sg:classifiers":[
        {
            "category":"Professional",
            "type":"Services"
        }
    ],
    "sg:phone":"+1 440 428 0725",
    "sg:postcode":"44057",
    "sg:province":"OH",
    "wof:name":"Stephen Gray",
    "wof:placetype":"venue"
},
  "geometry": {"coordinates":[-81.049009,41.779885],"type":"Point"}
}