{
  "type": "Feature",
  "properties": {
    "addr:full":"5956 State Rd Cleveland OH 44134",
    "addr:housenumber":"5956",
    "addr:postcode":"44134",
    "addr:street":"State Rd",
    "iso:country":"US",
    "sg:address":"5956 State Rd",
    "sg:city":"Cleveland",
    "sg:classifiers":[
        {
            "category":"Restaurant",
            "type":"Food & Drink"
        }
    ],
    "sg:phone":"+1 440 886 5533",
    "sg:postcode":"44134",
    "sg:province":"OH",
    "sg:tags":[
        "eating"
    ],
    "wof:name":"Napoleons Pizza Inc",
    "wof:placetype":"venue"
},
  "geometry": {"coordinates":[-81.710482,41.400612],"type":"Point"}
}