{
  "type": "Feature",
  "properties": {
    "iso:country":"US",
    "sg:address":"160 Parkwood Ave",
    "sg:city":"Avon Lake",
    "sg:classifiers":[
        {
            "category":"Restaurant",
            "type":"Food & Drink"
        }
    ],
    "sg:phone":"+1 440 933 5971",
    "sg:postcode":"44012",
    "sg:province":"OH",
    "sg:tags":[
        "eating"
    ],
    "wof:name":"Five Alarm Pizza Inc",
    "wof:placetype":"venue"
},
  "geometry": {"coordinates":[-82.028934,41.507939],"type":"Point"}
}