{
  "type": "Feature",
  "properties": {
    "iso:country":"US",
    "sg:address":"8014 W Western Reserve Rd",
    "sg:city":"Canfield",
    "sg:classifiers":[
        {
            "category":"Wholesale",
            "subcategory":"Scrap",
            "type":"Manufacturing & Wholesale Goods"
        }
    ],
    "sg:phone":"+1 330 717 5369",
    "sg:postcode":"44406",
    "sg:province":"OH",
    "sg:tags":[
        "waste"
    ],
    "wof:name":"Monarch Disposal",
    "wof:placetype":"venue"
},
  "geometry": {"coordinates":[-80.801016,40.988338],"type":"Point"}
}