{
  "type": "Feature",
  "properties": {
    "addr:full": "8014 W Western Reserve Rd Canfield OH 44406",
    "addr:housenumber": "8014",
    "addr:postcode": "44406",
    "addr:street": "W Western Reserve Rd",
    "iso:country": "US",
    "sg:address": "8014 W Western Reserve Rd",
    "sg:city": "Canfield",
    "sg:classifiers": [
      {
        "category": "Wholesale",
        "subcategory": "Scrap",
        "type": "Manufacturing \u0026 Wholesale Goods"
      }
    ],
    "sg:phone": "+1 330 717 5369",
    "sg:postcode": "44406",
    "sg:province": "OH",
    "sg:tags": [
      "waste"
    ],
    "wof:name": "Monarch Disposal",
    "wof:placetype": "venue"
  },
  "geometry": {"coordinates":[-80.801016,40.988338],"type":"Point"}
}
