{
  "type": "Feature",
  "properties": {
    "iso:country":"US",
    "sg:address":"2600 Victory Pkwy",
    "sg:city":"Cincinnati",
    "sg:classifiers":[
        {
            "category":"Social Services",
            "type":"Services"
        }
    ],
    "sg:phone":"+1 513 961 3677",
    "sg:postcode":"45206",
    "sg:province":"OH",
    "sg:tags":[
        "organization",
        "welfare"
    ],
    "wof:name":"Beech Acres",
    "wof:placetype":"venue"
},
  "geometry": {"coordinates":[-84.48424799999999,39.128164],"type":"Point"}
}