{
  "type": "Feature",
  "properties": {
    "iso:country":"US",
    "sg:address":"2149 Columbus Ave",
    "sg:city":"Ashtabula",
    "sg:classifiers":[
        {
            "category":"Retail",
            "subcategory":"Repair Shop",
            "type":"Services"
        }
    ],
    "sg:phone":"+1 440 992 5870",
    "sg:postcode":"44004",
    "sg:province":"OH",
    "sg:tags":[
        "television",
        "radio"
    ],
    "wof:name":"Spangler Electric Repair",
    "wof:placetype":"venue"
},
  "geometry": {"coordinates":[-80.785951,41.887137],"type":"Point"}
}