{
  "type": "Feature",
  "properties": {
    "iso:country":"US",
    "sg:address":"131 E Center St",
    "sg:city":"Marion",
    "sg:classifiers":[
        {
            "category":"Manufacturing",
            "subcategory":"Apparel",
            "type":"Manufacturing & Wholesale Goods"
        }
    ],
    "sg:phone":"+1 740 387 7101",
    "sg:postcode":"43302",
    "sg:province":"OH",
    "sg:tags":[
        "clothes",
        "accessory"
    ],
    "wof:name":"Keefer's Clothier",
    "wof:placetype":"venue"
},
  "geometry": {"coordinates":[-83.12799099999999,40.588598],"type":"Point"}
}