{
  "type": "Feature",
  "properties": {
    "iso:country":"US",
    "sg:address":"50 E 39th St",
    "sg:city":"Shadyside",
    "sg:classifiers":[
        {
            "category":"Government",
            "subcategory":"Police Station",
            "type":"Public Place"
        }
    ],
    "sg:phone":"+1 740 676 4024",
    "sg:postcode":"43947",
    "sg:province":"OH",
    "sg:tags":[
        "protection"
    ],
    "wof:name":"Jeffrey T Loeffler",
    "wof:placetype":"venue"
},
  "geometry": {"coordinates":[-80.74825800000001,39.972086],"type":"Point"}
}