{
  "type": "Feature",
  "properties": {
    "iso:country":"US",
    "sg:address":"1100 Dover Rd",
    "sg:city":"Wooster",
    "sg:classifiers":[
        {
            "category":"Communications",
            "subcategory":"Radio Station",
            "type":"Services"
        }
    ],
    "sg:phone":"+1 330 264 1862",
    "sg:postcode":"44691",
    "sg:province":"OH",
    "sg:tags":[
        "company",
        "broadcasting"
    ],
    "wof:name":"Wooster Radio Site",
    "wof:placetype":"venue"
},
  "geometry": {"coordinates":[-81.927009,40.775684],"type":"Point"}
}