{
  "type": "Feature",
  "properties": {
    "iso:country":"US",
    "sg:address":"8934 Brecksville Rd",
    "sg:city":"Brecksville",
    "sg:classifiers":[
        {
            "category":"Insurance",
            "subcategory":"Insurance Agent",
            "type":"Services"
        }
    ],
    "sg:phone":"+1 440 546 1662",
    "sg:postcode":"44141",
    "sg:province":"OH",
    "wof:name":"Code 3 Risk Management",
    "wof:placetype":"venue"
},
  "geometry": {"coordinates":[-81.626925,41.319941],"type":"Point"}
}