{
  "type": "Feature",
  "properties": {
    "iso:country":"US",
    "sg:address":"3614 Warsaw Ave",
    "sg:city":"Cincinnati",
    "sg:classifiers":[
        {
            "category":"Manufacturing",
            "subcategory":"Printing",
            "type":"Manufacturing & Wholesale Goods"
        }
    ],
    "sg:phone":"+1 513 251 8483",
    "sg:postcode":"45205",
    "sg:province":"OH",
    "sg:tags":[
        "printer"
    ],
    "wof:name":"S & H Printing Co",
    "wof:placetype":"venue"
},
  "geometry": {"coordinates":[-84.571427,39.110585],"type":"Point"}
}