{
  "type": "Feature",
  "properties": {
    "addr:full":"2069 Webster St Dayton OH 45404",
    "addr:housenumber":"2069",
    "addr:postcode":"45404",
    "addr:street":"Webster St",
    "iso:country":"US",
    "sg:address":"2069 Webster St",
    "sg:city":"Dayton",
    "sg:classifiers":[
        {
            "category":"Wholesale",
            "subcategory":"Hardware",
            "type":"Manufacturing & Wholesale Goods"
        },
        {
            "category":"Manufacturing",
            "subcategory":"Metals",
            "type":"Manufacturing & Wholesale Goods"
        }
    ],
    "sg:phone":"+1 937 223 4135",
    "sg:postcode":"45404",
    "sg:province":"OH",
    "sg:tags":[
        "tool",
        "blade",
        "machine",
        "cutting",
        "handsaw",
        "saw"
    ],
    "wof:name":"Kneiss Saw & Tool Supply",
    "wof:placetype":"venue"
},
  "geometry": {"coordinates":[-84.18159900000001,39.790633],"type":"Point"}
}