{
  "type": "Feature",
  "properties": {
    "iso:country":"US",
    "sg:address":"155 5th St NE",
    "sg:city":"Barberton",
    "sg:classifiers":[
        {
            "category":"Health Services",
            "subcategory":"Doctor",
            "type":"Services"
        }
    ],
    "sg:phone":"+1 330 848 7830",
    "sg:postcode":"44203",
    "sg:province":"OH",
    "sg:tags":[
        "physician",
        "surgeon"
    ],
    "wof:name":"Emergency Medicine Physicians",
    "wof:placetype":"venue"
},
  "geometry": {"coordinates":[-81.58971699999999,41.01544],"type":"Point"}
}