{
  "type": "Feature",
  "properties": {
    "addr:full":"5612 Werner Church Rd NE Canton OH 44721",
    "addr:housenumber":"5612",
    "addr:postcode":"44721",
    "addr:street":"Werner Church Rd Ne",
    "iso:country":"US",
    "sg:address":"5612 Werner Church Rd NE",
    "sg:city":"Canton",
    "sg:classifiers":[
        {
            "category":"Retail",
            "subcategory":"Repair Shop",
            "type":"Services"
        }
    ],
    "sg:phone":"+1 330 877 1516",
    "sg:postcode":"44721",
    "sg:province":"OH",
    "sg:tags":[
        "refinishing",
        "furniture"
    ],
    "wof:name":"Justice's Finishing Line",
    "wof:placetype":"venue"
},
  "geometry": {"coordinates":[-81.29937700000001,40.897817],"type":"Point"}
}