{
  "type": "Feature",
  "properties": {
    "addr:full": "1517 Hess St Columbus OH 43212",
    "addr:housenumber": "1517",
    "addr:postcode": "43212",
    "addr:street": "Hess St",
    "iso:country": "US",
    "sg:address": "1517 Hess St",
    "sg:city": "Columbus",
    "sg:classifiers": [
      {
        "category": "Communications",
        "subcategory": "Film \u0026 Video Production",
        "type": "Services"
      }
    ],
    "sg:phone": "+1 614 291 5352",
    "sg:postcode": "43212",
    "sg:province": "OH",
    "sg:tags": [
      "taping"
    ],
    "wof:name": "Planetary Media LLC",
    "wof:placetype": "venue"
  },
  "geometry": {"coordinates":[-83.031596,39.990769],"type":"Point"}
}
