{
  "type": "Feature",
  "properties": {
    "addr:full":"901 Finney Trl Cincinnati OH 45224",
    "addr:housenumber":"901",
    "addr:postcode":"45224",
    "addr:street":"Finney Trl",
    "iso:country":"US",
    "sg:address":"901 Finney Trl",
    "sg:city":"Cincinnati",
    "sg:classifiers":[
        {
            "category":"Social Services",
            "subcategory":"Child Care",
            "type":"Services"
        }
    ],
    "sg:phone":"+1 513 632 7114",
    "sg:postcode":"45224",
    "sg:province":"OH",
    "sg:tags":[
        "day"
    ],
    "wof:name":"7 Hill Neigoborhood Houses",
    "wof:placetype":"venue"
},
  "geometry": {"coordinates":[-84.520326,39.210496],"type":"Point"}
}