{
  "type": "Feature",
  "properties": {
    "addr:full":"606 N Perry St Napoleon OH 43545",
    "addr:housenumber":"606",
    "addr:postcode":"43545",
    "addr:street":"N Perry St",
    "iso:country":"US",
    "sg:address":"606 N Perry St",
    "sg:city":"Napoleon",
    "sg:classifiers":[
        {
            "category":"Organizations",
            "subcategory":"Religious Organization",
            "type":"Services"
        }
    ],
    "sg:phone":"+1 419 599 0213",
    "sg:postcode":"43545",
    "sg:province":"OH",
    "sg:tags":[
        "church"
    ],
    "wof:name":"Lutheran Church Missouri Synod",
    "wof:placetype":"venue"
},
  "geometry": {"coordinates":[-84.12460299999999,41.39105],"type":"Point"}
}