{
  "type": "Feature",
  "properties": {
    "addr:full": "7800 W US Hwy 36 Saint Paris OH 43072",
    "addr:housenumber": "7800",
    "addr:postcode": "43072",
    "addr:street": "W Us Hwy 36 Saint",
    "iso:country": "US",
    "sg:address": "7800 W US Hwy 36",
    "sg:city": "Saint Paris",
    "sg:classifiers": [
      {
        "category": "Education",
        "subcategory": "School",
        "type": "Public Place"
      }
    ],
    "sg:phone": "+1 937 663 4127",
    "sg:postcode": "43072",
    "sg:province": "OH",
    "wof:name": "Graham High School",
    "wof:placetype": "venue"
  },
  "geometry": {"coordinates":[-83.910172,40.121282],"type":"Point"}
}
