{
  "type": "Feature",
  "properties": {
    "addr:full": "2074 W Market St Akron OH 44313",
    "addr:housenumber": "2074",
    "addr:postcode": "44313",
    "addr:street": "W Market St",
    "iso:country": "US",
    "sg:address": "2074 W Market St",
    "sg:city": "Akron",
    "sg:classifiers": [
      {
        "category": "Real Estate",
        "subcategory": "Real Estate Operator",
        "type": "Services"
      },
      {
        "category": "Organizations",
        "subcategory": "Community Association",
        "type": "Services"
      }
    ],
    "sg:phone": "+1 330 836 3337",
    "sg:postcode": "44313",
    "sg:province": "OH",
    "sg:tags": [
      "building",
      "club",
      "membership",
      "apartment"
    ],
    "wof:name": "Fairlawn Park Garden \u0026 Civic C",
    "wof:placetype": "venue"
  },
  "geometry": {"coordinates":[-81.582829,41.115279],"type":"Point"}
}
