{
  "type": "Feature",
  "properties": {
    "iso:country":"US",
    "sg:address":"2074 W Market St",
    "sg:city":"Akron",
    "sg:classifiers":[
        {
            "category":"Real Estate",
            "subcategory":"Real Estate Operator",
            "type":"Services"
        },
        {
            "category":"Organizations",
            "subcategory":"Community Association",
            "type":"Services"
        }
    ],
    "sg:phone":"+1 330 836 3337",
    "sg:postcode":"44313",
    "sg:province":"OH",
    "sg:tags":[
        "building",
        "club",
        "membership",
        "apartment"
    ],
    "wof:name":"Fairlawn Park Garden & Civic C",
    "wof:placetype":"venue"
},
  "geometry": {"coordinates":[-81.582829,41.115279],"type":"Point"}
}