{
  "type": "Feature",
  "properties": {
    "addr:full":"6029 Renaissance Pl Toledo OH 43623",
    "addr:housenumber":"6029",
    "addr:postcode":"43623",
    "addr:street":"Renaissance Pl",
    "iso:country":"US",
    "sg:address":"6029 Renaissance Pl",
    "sg:city":"Toledo",
    "sg:classifiers":[
        {
            "category":"Insurance",
            "subcategory":"Insurance Agent",
            "type":"Services"
        }
    ],
    "sg:phone":"+1 419 824 2071",
    "sg:postcode":"43623",
    "sg:province":"OH",
    "wof:name":"Nationwide Insurance",
    "wof:placetype":"venue"
},
  "geometry": {"coordinates":[-83.686477,41.69646],"type":"Point"}
}