{
  "type": "Feature",
  "properties": {
    "addr:full":"1 Kenilworth Ct Cincinnati OH 45246",
    "addr:housenumber":"1",
    "addr:postcode":"45246",
    "addr:street":"Kenilworth Ct",
    "iso:country":"US",
    "sg:address":"1 Kenilworth Ct",
    "sg:city":"Cincinnati",
    "sg:classifiers":[
        {
            "category":"Real Estate",
            "subcategory":"Real Estate Operator",
            "type":"Services"
        }
    ],
    "sg:phone":"+1 513 771 9365",
    "sg:postcode":"45246",
    "sg:province":"OH",
    "sg:tags":[
        "building",
        "apartment"
    ],
    "wof:name":"Colonley Springdale",
    "wof:placetype":"venue"
},
  "geometry": {"coordinates":[-84.480344,39.279157],"type":"Point"}
}