{
  "type": "Feature",
  "properties": {
    "iso:country":"US",
    "sg:address":"27201 Tremaine Dr",
    "sg:city":"Euclid",
    "sg:classifiers":[
        {
            "category":"Freight",
            "type":"Transportation"
        }
    ],
    "sg:phone":"+1 216 965 5414",
    "sg:postcode":"44132",
    "sg:province":"OH",
    "sg:tags":[
        "hire",
        "for",
        "general"
    ],
    "wof:name":"Capricorn Entp Trckg Co LLC",
    "wof:placetype":"venue"
},
  "geometry": {"coordinates":[-81.491934,41.591961],"type":"Point"}
}