{
  "type": "Feature",
  "properties": {
    "addr:full": "250 Richmond Rd Cleveland OH 44143",
    "addr:housenumber": "250",
    "addr:postcode": "44143",
    "addr:street": "Richmond Rd",
    "iso:country": "US",
    "sg:address": "250 Richmond Rd",
    "sg:city": "Cleveland",
    "sg:classifiers": [
      {
        "category": "Social Services",
        "type": "Services"
      }
    ],
    "sg:phone": "+1 216 261 8005",
    "sg:postcode": "44143",
    "sg:province": "OH",
    "sg:tags": [
      "counselor",
      "marriage",
      "family"
    ],
    "wof:name": "New Perspectives Counseling",
    "wof:placetype": "venue"
  },
  "geometry": {"coordinates":[-81.494653,41.574266],"type":"Point"}
}
