{
  "type": "Feature",
  "properties": {
    "addr:full":"738 Wheeling Ave Cambridge OH 43725",
    "addr:housenumber":"738",
    "addr:postcode":"43725",
    "addr:street":"Wheeling Ave",
    "iso:country":"US",
    "sg:address":"738 Wheeling Ave",
    "sg:city":"Cambridge",
    "sg:classifiers":[
        {
            "category":"Sports & Exercise",
            "subcategory":"Gym",
            "type":"Entertainment"
        }
    ],
    "sg:phone":"+1 740 432 7075",
    "sg:postcode":"43725",
    "sg:province":"OH",
    "sg:tags":[
        "spa",
        "health"
    ],
    "wof:name":"Loft Day Spa",
    "wof:placetype":"venue"
},
  "geometry": {"coordinates":[-81.591533,40.024726],"type":"Point"}
}