{
  "type": "Feature",
  "properties": {
    "addr:full": "3224 Payne Ave Cleveland OH 44114",
    "addr:housenumber": "3224",
    "addr:postcode": "44114",
    "addr:street": "Payne Ave",
    "iso:country": "US",
    "sg:address": "3224 Payne Ave",
    "sg:city": "Cleveland",
    "sg:classifiers": [
      {
        "category": "Place Of Worship",
        "type": "Public Place"
      }
    ],
    "sg:phone": "+1 216 621 1412",
    "sg:postcode": "44114",
    "sg:province": "OH",
    "sg:tags": [
      "church"
    ],
    "wof:name": "Cleve Chinese Christian Church",
    "wof:placetype": "venue"
  },
  "geometry": {"coordinates":[-81.666005,41.508656],"type":"Point"}
}
