{
  "type": "Feature",
  "properties": {
    "addr:full":"16221 Windsor Dr Cleveland OH 44136",
    "addr:housenumber":"16221",
    "addr:postcode":"44136",
    "addr:street":"Windsor Dr",
    "iso:country":"US",
    "sg:address":"16221 Windsor Dr",
    "sg:city":"Cleveland",
    "sg:classifiers":[
        {
            "category":"Building & Trades",
            "subcategory":"Construction",
            "type":"Services"
        }
    ],
    "sg:phone":"+1 440 572 3865",
    "sg:postcode":"44136",
    "sg:province":"OH",
    "wof:name":"Arthur Construction Co",
    "wof:placetype":"venue"
},
  "geometry": {"coordinates":[-81.81235100000001,41.29985],"type":"Point"}
}