{
  "type": "Feature",
  "properties": {
    "addr:full":"578 Witham Ct Columbus OH 43230",
    "addr:housenumber":"578",
    "addr:postcode":"43230",
    "addr:street":"Witham Ct",
    "iso:country":"US",
    "sg:address":"578 Witham Ct",
    "sg:city":"Columbus",
    "sg:classifiers":[
        {
            "category":"Organizations",
            "subcategory":"Non-profit Organization",
            "type":"Services"
        }
    ],
    "sg:phone":"+1 614 337 0664",
    "sg:postcode":"43230",
    "sg:province":"OH",
    "wof:name":"Davidson Gore Family Reunion",
    "wof:placetype":"venue"
},
  "geometry": {"coordinates":[-82.892906,40.034453],"type":"Point"}
}