{
  "type": "Feature",
  "properties": {
    "iso:country":"US",
    "sg:address":"5243 Washington Rd",
    "sg:city":"Albany",
    "sg:classifiers":[
        {
            "category":"Health Services",
            "subcategory":"Chiropractor",
            "type":"Services"
        }
    ],
    "sg:phone":"+1 740 698 3181",
    "sg:postcode":"45710",
    "sg:province":"OH",
    "wof:name":"Albany Chiropractic",
    "wof:placetype":"venue"
},
  "geometry": {"coordinates":[-82.20523799999999,39.22526],"type":"Point"}
}