{
  "type": "Feature",
  "properties": {
    "addr:full": "5243 Washington Rd Albany OH 45710",
    "addr:housenumber": "5243",
    "addr:postcode": "45710",
    "addr:street": "Washington Rd",
    "iso:country": "US",
    "sg:address": "5243 Washington Rd",
    "sg:city": "Albany",
    "sg:classifiers": [
      {
        "category": "Health Services",
        "subcategory": "Chiropractor",
        "type": "Services"
      }
    ],
    "sg:phone": "+1 740 698 3181",
    "sg:postcode": "45710",
    "sg:province": "OH",
    "wof:name": "Albany Chiropractic",
    "wof:placetype": "venue"
  },
  "geometry": {"coordinates":[-82.205238,39.22526],"type":"Point"}
}
