{
  "type": "Feature",
  "properties": {
    "addr:full": "1060 State Rte 18 Bellevue OH 44811",
    "addr:housenumber": "1060",
    "addr:postcode": "44811",
    "addr:street": "State Rte 18",
    "iso:country": "US",
    "sg:address": "1060 State Rte 18",
    "sg:city": "Bellevue",
    "sg:classifiers": [
      {
        "category": "Building \u0026 Trades",
        "subcategory": "Landscaping Services",
        "type": "Services"
      }
    ],
    "sg:phone": "+1 419 483 9313",
    "sg:postcode": "44811",
    "sg:province": "OH",
    "sg:tags": [
      "tree"
    ],
    "wof:name": "Jarrett Tree Svc",
    "wof:placetype": "venue"
  },
  "geometry": {"coordinates":[-82.826004,41.272171],"type":"Point"}
}
