{
  "type": "Feature",
  "properties": {
    "iso:country":"US",
    "sg:address":"9880 Shepard Rd",
    "sg:city":"Macedonia",
    "sg:classifiers":[
        {
            "category":"Social Services",
            "subcategory":"Child Care",
            "type":"Services"
        }
    ],
    "sg:phone":"+1 330 468 1827",
    "sg:postcode":"44056",
    "sg:province":"OH",
    "wof:name":"All Star Day Care Center",
    "wof:placetype":"venue"
},
  "geometry": {"coordinates":[-81.489114,41.344288],"type":"Point"}
}