{
  "type": "Feature",
  "properties": {
    "iso:country":"US",
    "sg:address":"502 Rawson Ave",
    "sg:city":"Fremont",
    "sg:classifiers":[
        {
            "category":"Building & Trades",
            "subcategory":"Landscaping Services",
            "type":"Services"
        }
    ],
    "sg:phone":"+1 419 332 5198",
    "sg:postcode":"43420",
    "sg:province":"OH",
    "sg:tags":[
        "lawn",
        "maintenance",
        "grounds"
    ],
    "wof:name":"Lee's Grounds Maintenance",
    "wof:placetype":"venue"
},
  "geometry": {"coordinates":[-83.120314,41.353373],"type":"Point"}
}