{
  "type": "Feature",
  "properties": {
    "iso:country":"US",
    "sg:address":"1480 Dayton-Brandt Rd",
    "sg:city":"Troy",
    "sg:classifiers":[
        {
            "category":"Building & Trades",
            "subcategory":"Construction",
            "type":"Services"
        }
    ],
    "sg:phone":"+1 937 845 3830",
    "sg:postcode":"45373",
    "sg:province":"OH",
    "sg:tags":[
        "roofing",
        "contractor"
    ],
    "wof:name":"Right Turn USA Inc",
    "wof:placetype":"venue"
},
  "geometry": {"coordinates":[-84.043688,40.006889],"type":"Point"}
}