{
  "type": "Feature",
  "properties": {
    "addr:full": "315 York St Springfield OH 45505",
    "addr:housenumber": "315",
    "addr:postcode": "45505",
    "addr:street": "York St",
    "iso:country": "US",
    "sg:address": "315 York St",
    "sg:city": "Springfield",
    "sg:classifiers": [
      {
        "category": "Manufacturing",
        "subcategory": "Building Materials",
        "type": "Manufacturing \u0026 Wholesale Goods"
      }
    ],
    "sg:phone": "+1 937 324 5689",
    "sg:postcode": "45505",
    "sg:province": "OH",
    "sg:tags": [
      "mfg",
      "wood",
      "cabinet",
      "kitchen",
      "carpentry"
    ],
    "wof:name": "Kramer Mill",
    "wof:placetype": "venue"
  },
  "geometry": {"coordinates":[-83.799436,39.919207],"type":"Point"}
}
