{
  "type": "Feature",
  "properties": {
    "addr:full": "560 Fairview Dr Franklin OH 45005",
    "addr:housenumber": "560",
    "addr:postcode": "45005",
    "addr:street": "Fairview Dr",
    "iso:country": "US",
    "sg:address": "560 Fairview Dr",
    "sg:city": "Franklin",
    "sg:classifiers": [
      {
        "category": "Retail",
        "subcategory": "Auto Repair",
        "type": "Services"
      }
    ],
    "sg:phone": "+1 937 746 3790",
    "sg:postcode": "45005",
    "sg:province": "OH",
    "sg:tags": [
      "automotive"
    ],
    "wof:name": "Good Vibes",
    "wof:placetype": "venue"
  },
  "geometry": {"coordinates":[-84.315646,39.584843],"type":"Point"}
}
