{
  "type": "Feature",
  "properties": {
    "iso:country":"US",
    "sg:address":"6215 Heisley Rd",
    "sg:city":"Mentor",
    "sg:classifiers":[
        {
            "category":"Manufacturing",
            "subcategory":"Motor Vehicles & Parts",
            "type":"Manufacturing & Wholesale Goods"
        }
    ],
    "sg:phone":"+1 440 392 0734",
    "sg:postcode":"44060",
    "sg:province":"OH",
    "sg:tags":[
        "body",
        "mfg"
    ],
    "wof:name":"Raison Race Cars & Components",
    "wof:placetype":"venue"
},
  "geometry": {"coordinates":[-81.307259,41.703765],"type":"Point"}
}