{
  "type": "Feature",
  "properties": {
    "addr:full": "6215 Heisley Rd Mentor OH 44060",
    "addr:housenumber": "6215",
    "addr:postcode": "44060",
    "addr:street": "Heisley Rd",
    "iso:country": "US",
    "sg:address": "6215 Heisley Rd",
    "sg:city": "Mentor",
    "sg:classifiers": [
      {
        "category": "Manufacturing",
        "subcategory": "Motor Vehicles \u0026 Parts",
        "type": "Manufacturing \u0026 Wholesale Goods"
      }
    ],
    "sg:phone": "+1 440 392 0734",
    "sg:postcode": "44060",
    "sg:province": "OH",
    "sg:tags": [
      "body",
      "mfg"
    ],
    "wof:name": "Raison Race Cars \u0026 Components",
    "wof:placetype": "venue"
  },
  "geometry": {"coordinates":[-81.307259,41.703765],"type":"Point"}
}
