{
  "type": "Feature",
  "properties": {
    "addr:full": "18000 US Hwy 23 Circleville OH 43113",
    "addr:postcode": "18000;43113",
    "addr:street": "Us Hwy 23",
    "iso:country": "US",
    "sg:address": "18000 US Hwy 23",
    "sg:city": "Circleville",
    "sg:classifiers": [
      {
        "category": "Autos \u0026 Motor Vehicles",
        "subcategory": "Automobile Sales",
        "type": "Retail Goods"
      }
    ],
    "sg:phone": "+1 740 474 4849",
    "sg:postcode": "43113",
    "sg:province": "OH",
    "sg:tags": [
      "car",
      "used",
      "dealer"
    ],
    "wof:name": "Mike's Auto Connection",
    "wof:placetype": "venue"
  },
  "geometry": {"coordinates":[-82.965522,39.669385],"type":"Point"}
}
