{
  "type": "Feature",
  "properties": {
    "iso:country":"US",
    "sg:address":"365 Agler Rd",
    "sg:city":"Columbus",
    "sg:classifiers":[
        {
            "category":"Restaurant",
            "type":"Food & Drink"
        }
    ],
    "sg:phone":"+1 614 475 6840",
    "sg:postcode":"43230",
    "sg:province":"OH",
    "sg:tags":[
        "shop",
        "coffee"
    ],
    "wof:name":"Tim Hortons",
    "wof:placetype":"venue"
},
  "geometry": {"coordinates":[-82.88629,40.019131],"type":"Point"}
}