{
  "type": "Feature",
  "properties": {
    "addr:full":"800 Mohawk Dr Mc Dermott OH 45648",
    "addr:housenumber":"800",
    "addr:postcode":"45648",
    "addr:street":"Mohawk Dr",
    "iso:country":"US",
    "sg:address":"800 Mohawk Dr",
    "sg:city":"Mc Dermott",
    "sg:classifiers":[
        {
            "category":"Education",
            "subcategory":"School",
            "type":"Public Place"
        }
    ],
    "sg:phone":"+1 740 259 5558",
    "sg:postcode":"45648",
    "sg:province":"OH",
    "wof:name":"Northwest Board Of Education",
    "wof:placetype":"venue"
},
  "geometry": {"coordinates":[-83.082166,38.879277],"type":"Point"}
}