{
  "type": "Feature",
  "properties": {
    "addr:full": "11 Lincoln Way W Massillon OH 44647",
    "addr:housenumber": "11",
    "addr:postcode": "44647",
    "addr:street": "Lincoln Way W",
    "iso:country": "US",
    "sg:address": "11 Lincoln Way W",
    "sg:city": "Massillon",
    "sg:classifiers": [
      {
        "category": "Real Estate",
        "subcategory": "Real Estate Services",
        "type": "Services"
      }
    ],
    "sg:phone": "+1 330 832 5426",
    "sg:postcode": "44647",
    "sg:province": "OH",
    "sg:tags": [
      "company",
      "title"
    ],
    "wof:name": "Glick Title Agency LLC",
    "wof:placetype": "venue"
  },
  "geometry": {"coordinates":[-81.523552,40.796284],"type":"Point"}
}
