{
  "type": "Feature",
  "properties": {
    "iso:country":"US",
    "sg:address":"112 Hamilton Ave",
    "sg:city":"Cleveland",
    "sg:classifiers":[
        {
            "category":"Government",
            "subcategory":"Office",
            "type":"Public Place"
        }
    ],
    "sg:phone":"+1 216 443 7230",
    "sg:postcode":"44114",
    "sg:province":"OH",
    "sg:website":"www.cuyahogacounty.us",
    "wof:name":"Procurement & Divercity",
    "wof:placetype":"venue"
},
  "geometry": {"coordinates":[-81.695672,41.502446],"type":"Point"}
}