{
  "type": "Feature",
  "properties": {
    "addr:full": "927 E McMillan St Cincinnati OH 45206",
    "addr:housenumber": "927",
    "addr:postcode": "45206",
    "addr:street": "E Mcmillan St",
    "iso:country": "US",
    "sg:address": "927 E McMillan St",
    "sg:city": "Cincinnati",
    "sg:classifiers": [
      {
        "category": "Shopping",
        "subcategory": "Clothing, Apparel, \u0026 Fashions",
        "type": "Retail Goods"
      }
    ],
    "sg:phone": "+1 513 281 8006",
    "sg:postcode": "45206",
    "sg:province": "OH",
    "sg:tags": [
      "family"
    ],
    "wof:name": "Great Look Fashions",
    "wof:placetype": "venue"
  },
  "geometry": {"coordinates":[-84.488458,39.125757],"type":"Point"}
}
