{
  "type": "Feature",
  "properties": {
    "addr:full": "3766 E 147th St Cleveland OH 44128",
    "addr:housenumber": "3766",
    "addr:postcode": "44128",
    "addr:street": "E 147Th St",
    "iso:country": "US",
    "sg:address": "3766 E 147th St",
    "sg:city": "Cleveland",
    "sg:classifiers": [
      {
        "category": "Personal",
        "subcategory": "Beauty Salon",
        "type": "Services"
      }
    ],
    "sg:phone": "+1 216 751 9908",
    "sg:postcode": "44128",
    "sg:province": "OH",
    "wof:name": "East One Forty-Seven Hair Sln",
    "wof:placetype": "venue"
  },
  "geometry": {"coordinates":[-81.578617,41.453468],"type":"Point"}
}
