{
  "type": "Feature",
  "properties": {
    "addr:full":"2091 Oakdale Dr Marion OH 43302",
    "addr:housenumber":"2091",
    "addr:postcode":"43302",
    "addr:street":"Oakdale Dr",
    "iso:country":"US",
    "sg:address":"2091 Oakdale Dr",
    "sg:city":"Marion",
    "sg:classifiers":[
        {
            "category":"Organizations",
            "subcategory":"Religious Organization",
            "type":"Services"
        }
    ],
    "sg:phone":"+1 740 389 9703",
    "sg:postcode":"43302",
    "sg:province":"OH",
    "sg:tags":[
        "clergy"
    ],
    "wof:name":"Joseph Miller",
    "wof:placetype":"venue"
},
  "geometry": {"coordinates":[-83.08591,40.549457],"type":"Point"}
}