{
  "type": "Feature",
  "properties": {
    "addr:full": "3339 Monticello Blvd Cleveland OH 44118",
    "addr:housenumber": "3339",
    "addr:postcode": "44118",
    "addr:street": "Monticello Blvd",
    "iso:country": "US",
    "sg:address": "3339 Monticello Blvd",
    "sg:city": "Cleveland",
    "sg:classifiers": [
      {
        "category": "Professional",
        "type": "Services"
      }
    ],
    "sg:phone": "+1 216 321 3558",
    "sg:postcode": "44118",
    "sg:province": "OH",
    "wof:name": "Pishnery \u0026 Pishnry",
    "wof:placetype": "venue"
  },
  "geometry": {"coordinates":[-81.561711,41.524508],"type":"Point"}
}
