{
  "type": "Feature",
  "properties": {
    "iso:country":"US",
    "sg:address":"1148 Walnut St",
    "sg:city":"Coshocton",
    "sg:classifiers":[
        {
            "category":"Wholesale",
            "subcategory":"Non-durable Goods",
            "type":"Manufacturing & Wholesale Goods"
        }
    ],
    "sg:phone":"+1 740 622 3113",
    "sg:postcode":"43812",
    "sg:province":"OH",
    "sg:tags":[
        "advertising"
    ],
    "sg:website":"www.noveltyadv.com",
    "wof:name":"Novelty Advertising Co",
    "wof:placetype":"venue"
},
  "geometry": {"coordinates":[-81.852492,40.27183],"type":"Point"}
}