{
  "type": "Feature",
  "properties": {
    "addr:full": "15780 Rd 3 Pandora OH 45877",
    "addr:housenumber": "15780",
    "addr:postcode": "45877",
    "addr:street": "Rd 3",
    "iso:country": "US",
    "sg:address": "15780 Rd 3",
    "sg:city": "Pandora",
    "sg:classifiers": [
      {
        "category": "Farming",
        "subcategory": "Farm",
        "type": "Manufacturing \u0026 Wholesale Goods"
      }
    ],
    "sg:phone": "+1 419 384 3973",
    "sg:postcode": "45877",
    "sg:province": "OH",
    "sg:tags": [
      "crop",
      "general"
    ],
    "wof:name": "Oliver Schutz",
    "wof:placetype": "venue"
  },
  "geometry": {"coordinates":[-83.91893,40.952524],"type":"Point"}
}
