{
  "type": "Feature",
  "properties": {
    "addr:full": "619 Industrial Pkwy Newark OH 43056",
    "addr:housenumber": "619",
    "addr:postcode": "43056",
    "addr:street": "Industrial Pkwy",
    "iso:country": "US",
    "sg:address": "619 Industrial Pkwy",
    "sg:city": "Newark",
    "sg:classifiers": [
      {
        "category": "Insurance",
        "subcategory": "Insurance Agent",
        "type": "Services"
      }
    ],
    "sg:phone": "+1 740 522 3108",
    "sg:postcode": "43056",
    "sg:province": "OH",
    "sg:tags": [
      "agency"
    ],
    "wof:name": "William E Mills Insurance LLC",
    "wof:placetype": "venue"
  },
  "geometry": {"coordinates":[-82.427494,40.036321],"type":"Point"}
}
