{
  "type": "Feature",
  "properties": {
    "addr:full":"222 S Broad St Lancaster OH 43130",
    "addr:housenumber":"222",
    "addr:postcode":"43130",
    "addr:street":"S Broad St",
    "iso:country":"US",
    "sg:address":"222 S Broad St",
    "sg:city":"Lancaster",
    "sg:classifiers":[
        {
            "category":"Real Estate",
            "subcategory":"Real Estate Agent",
            "type":"Services"
        }
    ],
    "sg:phone":"+1 740 687 1234",
    "sg:postcode":"43130",
    "sg:province":"OH",
    "sg:tags":[
        "appraiser"
    ],
    "wof:name":"Singer Appraisal & Consulting",
    "wof:placetype":"venue"
},
  "geometry": {"coordinates":[-82.60194,39.712159],"type":"Point"}
}