{
  "type": "Feature",
  "properties": {
    "addr:full":"2740 Eastland Mall Columbus OH 43232",
    "addr:housenumber":"2740",
    "addr:postcode":"43232",
    "addr:street":"Eastland Mall",
    "iso:country":"US",
    "sg:address":"2740 Eastland Mall",
    "sg:city":"Columbus",
    "sg:classifiers":[
        {
            "category":"Professional",
            "type":"Services"
        }
    ],
    "sg:phone":"+1 614 864 5134",
    "sg:postcode":"43232",
    "sg:province":"OH",
    "wof:name":"Digital Memories",
    "wof:placetype":"venue"
},
  "geometry": {"coordinates":[-82.887655,39.91641],"type":"Point"}
}