{
  "type": "Feature",
  "properties": {
    "iso:country":"US",
    "sg:address":"403 N 3rd St",
    "sg:city":"Coshocton",
    "sg:classifiers":[
        {
            "category":"Utilities",
            "subcategory":"Refuse",
            "type":"Services"
        }
    ],
    "sg:phone":"+1 740 622 9348",
    "sg:postcode":"43812",
    "sg:province":"OH",
    "sg:tags":[
        "system"
    ],
    "wof:name":"Williams Recycling",
    "wof:placetype":"venue"
},
  "geometry": {"coordinates":[-81.866879,40.278029],"type":"Point"}
}