{
  "type": "Feature",
  "properties": {
    "iso:country":"US",
    "sg:address":"12500 Co Rd 2",
    "sg:city":"West Mansfield",
    "sg:classifiers":[
        {
            "category":"Building & Trades",
            "subcategory":"Construction",
            "type":"Services"
        }
    ],
    "sg:phone":"+1 937 355 3361",
    "sg:postcode":"43358",
    "sg:province":"OH",
    "sg:tags":[
        "family",
        "farm",
        "corn",
        "contractor",
        "soybean",
        "home",
        "general",
        "remodeling"
    ],
    "wof:name":"M J Construction",
    "wof:placetype":"venue"
},
  "geometry": {"coordinates":[-83.540352,40.365987],"type":"Point"}
}