{
  "type": "Feature",
  "properties": {
    "addr:full":"996 W 3rd Ave Columbus OH 43212",
    "addr:housenumber":"996",
    "addr:postcode":"43212",
    "addr:street":"W 3Rd Ave",
    "iso:country":"US",
    "sg:address":"996 W 3rd Ave",
    "sg:city":"Columbus",
    "sg:classifiers":[
        {
            "category":"Real Estate",
            "subcategory":"Architect",
            "type":"Services"
        }
    ],
    "sg:phone":"+1 614 291 1400",
    "sg:postcode":"43212",
    "sg:province":"OH",
    "wof:name":"Nau & Bullock Architects LTD",
    "wof:placetype":"venue"
},
  "geometry": {"coordinates":[-83.031226,39.984588],"type":"Point"}
}