{
  "type": "Feature",
  "properties": {
    "addr:full": "111 S Elmwood Ave Medina OH 44256",
    "addr:housenumber": "111",
    "addr:postcode": "44256",
    "addr:street": "S Elmwood Ave",
    "iso:country": "US",
    "sg:address": "111 S Elmwood Ave",
    "sg:city": "Medina",
    "sg:classifiers": [
      {
        "category": "Utilities",
        "subcategory": "Telephone",
        "type": "Services"
      }
    ],
    "sg:phone": "+1 330 722 9496",
    "sg:postcode": "44256",
    "sg:province": "OH",
    "sg:tags": [
      "communications"
    ],
    "wof:name": "Verizon",
    "wof:placetype": "venue"
  },
  "geometry": {"coordinates":[-81.866106,41.139027],"type":"Point"}
}
