{
  "type": "Feature",
  "properties": {
    "addr:full": "1011 Ridge Rd Hinckley OH 44233",
    "addr:housenumber": "1011",
    "addr:postcode": "44233",
    "addr:street": "Ridge Rd",
    "iso:country": "US",
    "sg:address": "1011 Ridge Rd",
    "sg:city": "Hinckley",
    "sg:phone": "+1 330 278 7325",
    "sg:postcode": "44233",
    "sg:province": "OH",
    "sg:tags": [
      "farm",
      "field",
      "crop"
    ],
    "wof:name": "Pacyna Brothers Farm",
    "wof:placetype": "venue"
  },
  "geometry": {"coordinates":[-81.74488,41.241978],"type":"Point"}
}
