{
  "type": "Feature",
  "properties": {
    "addr:full": "1532 Enterprise Pkwy Twinsburg OH 44087",
    "addr:housenumber": "1532",
    "addr:postcode": "44087",
    "addr:street": "Enterprise Pkwy",
    "iso:country": "US",
    "sg:address": "1532 Enterprise Pkwy",
    "sg:city": "Twinsburg",
    "sg:classifiers": [
      {
        "category": "Professional",
        "subcategory": "Research",
        "type": "Services"
      }
    ],
    "sg:phone": "+1 330 425 8180",
    "sg:postcode": "44087",
    "sg:province": "OH",
    "sg:tags": [
      "laboratory"
    ],
    "wof:name": "Universal Biological Labs",
    "wof:placetype": "venue"
  },
  "geometry": {"coordinates":[-81.46367,41.291535],"type":"Point"}
}
