{
  "type": "Feature",
  "properties": {
    "addr:full":"2071 Langram Rd Port Clinton OH 43456",
    "addr:housenumber":"2071",
    "addr:postcode":"43456",
    "addr:street":"Langram Rd",
    "iso:country":"US",
    "sg:address":"2071 Langram Rd",
    "sg:city":"Port Clinton",
    "sg:classifiers":[
        {
            "category":"Recreation",
            "type":"Entertainment"
        }
    ],
    "sg:phone":"+1 419 285 2016",
    "sg:postcode":"43456",
    "sg:province":"OH",
    "sg:tags":[
        "bicycle"
    ],
    "wof:name":"Island Bike Rental",
    "wof:placetype":"venue"
},
  "geometry": {"coordinates":[-82.83718500000001,41.630848],"type":"Point"}
}