{
  "type": "Feature",
  "properties": {
    "addr:full":"2735 Spring Grove Ave Cincinnati OH 45225",
    "addr:housenumber":"2735",
    "addr:postcode":"45225",
    "addr:street":"Spring Grove Ave",
    "iso:country":"US",
    "sg:address":"2735 Spring Grove Ave",
    "sg:city":"Cincinnati",
    "sg:classifiers":[
        {
            "category":"Autos & Motor Vehicles",
            "subcategory":"Auto Supplies",
            "type":"Retail Goods"
        }
    ],
    "sg:phone":"+1 513 241 1079",
    "sg:postcode":"45225",
    "sg:province":"OH",
    "sg:tags":[
        "tire"
    ],
    "wof:name":"Dispatch Tire",
    "wof:placetype":"venue"
},
  "geometry": {"coordinates":[-84.537215,39.131781],"type":"Point"}
}