{
  "type": "Feature",
  "properties": {
    "iso:country":"US",
    "sg:address":"225 Stolle Ave",
    "sg:city":"Sidney",
    "sg:classifiers":[
        {
            "category":"Building & Trades",
            "subcategory":"Electrical",
            "type":"Services"
        }
    ],
    "sg:phone":"+1 937 492 4175",
    "sg:postcode":"45365",
    "sg:province":"OH",
    "sg:tags":[
        "electric",
        "contractor"
    ],
    "wof:name":"Duellman Rexel Elec Supplies",
    "wof:placetype":"venue"
},
  "geometry": {"coordinates":[-84.196493,40.287045],"type":"Point"}
}