{
  "type": "Feature",
  "properties": {
    "iso:country":"US",
    "sg:address":"900 E Bigelow Ave",
    "sg:city":"Findlay",
    "sg:classifiers":[
        {
            "category":"Banks & Credit Unions",
            "subcategory":"Investment Brokerage",
            "type":"Services"
        }
    ],
    "sg:phone":"+1 419 424 9839",
    "sg:postcode":"45840",
    "sg:province":"OH",
    "sg:tags":[
        "consultant",
        "financing"
    ],
    "wof:name":"Lake Finance",
    "wof:placetype":"venue"
},
  "geometry": {"coordinates":[-83.637669,41.073018],"type":"Point"}
}