{
  "type": "Feature",
  "properties": {
    "addr:full":"319 Colegate Dr Marietta OH 45750",
    "addr:housenumber":"319",
    "addr:postcode":"45750",
    "addr:street":"Colegate Dr",
    "iso:country":"US",
    "sg:address":"319 Colegate Dr",
    "sg:city":"Marietta",
    "sg:classifiers":[
        {
            "category":"Food & Beverages",
            "subcategory":"Groceries & Convenience Stores",
            "type":"Retail Goods"
        }
    ],
    "sg:phone":"+1 740 374 3663",
    "sg:postcode":"45750",
    "sg:province":"OH",
    "sg:tags":[
        "grocer"
    ],
    "wof:name":"Colegate Food Ctr",
    "wof:placetype":"venue"
},
  "geometry": {"coordinates":[-81.435408,39.422378],"type":"Point"}
}