{
  "type": "Feature",
  "properties": {
    "addr:full":"155 N Gebhart Church Rd Miamisburg OH 45342",
    "addr:housenumber":"155",
    "addr:postcode":"45342",
    "addr:street":"N Gebhart Church Rd",
    "iso:country":"US",
    "sg:address":"155 N Gebhart Church Rd",
    "sg:city":"Miamisburg",
    "sg:classifiers":[
        {
            "category":"Wholesale",
            "subcategory":"Machinery & Supplies",
            "type":"Manufacturing & Wholesale Goods"
        }
    ],
    "sg:phone":"+1 937 865 9733",
    "sg:postcode":"45342",
    "sg:province":"OH",
    "sg:tags":[
        "equipment",
        "industrial"
    ],
    "wof:name":"Industrial Air Science",
    "wof:placetype":"venue"
},
  "geometry": {"coordinates":[-84.25418999999999,39.642225],"type":"Point"}
}