{
  "type": "Feature",
  "properties": {
    "addr:full":"2137 Kingsglen Dr Grove City OH 43123",
    "addr:housenumber":"2137",
    "addr:postcode":"43123",
    "addr:street":"Kingsglen Dr",
    "iso:country":"US",
    "sg:address":"2137 Kingsglen Dr",
    "sg:city":"Grove City",
    "sg:classifiers":[
        {
            "category":"Building & Trades",
            "subcategory":"Construction",
            "type":"Services"
        }
    ],
    "sg:phone":"+1 614 871 5311",
    "sg:postcode":"43123",
    "sg:province":"OH",
    "sg:tags":[
        "contractor"
    ],
    "wof:name":"Duke Matthews Construction",
    "wof:placetype":"venue"
},
  "geometry": {"coordinates":[-83.04595399999999,39.911508],"type":"Point"}
}