{
  "type": "Feature",
  "properties": {
    "iso:country":"US",
    "sg:address":"306 Bush St",
    "sg:city":"Toledo",
    "sg:classifiers":[
        {
            "category":"Personal",
            "type":"Services"
        }
    ],
    "sg:phone":"+1 419 474 3995",
    "sg:postcode":"43604",
    "sg:province":"OH",
    "sg:tags":[
        "program",
        "physical",
        "exercise",
        "fitness"
    ],
    "wof:name":"YMCA",
    "wof:placetype":"venue"
},
  "geometry": {"coordinates":[-83.51772800000001,41.661459],"type":"Point"}
}