{
  "type": "Feature",
  "properties": {
    "addr:full":"1307 W 2nd Ave Columbus OH 43212",
    "addr:housenumber":"1307",
    "addr:postcode":"43212",
    "addr:street":"W 2Nd Ave",
    "iso:country":"US",
    "sg:address":"1307 W 2nd Ave",
    "sg:city":"Columbus",
    "sg:classifiers":[
        {
            "category":"Professional",
            "subcategory":"Accounting & Tax Preparation",
            "type":"Services"
        }
    ],
    "sg:phone":"+1 614 486 1935",
    "sg:postcode":"43212",
    "sg:province":"OH",
    "sg:tags":[
        "billing"
    ],
    "sg:website":"www.per-se.com",
    "wof:name":"Per Se Technologies",
    "wof:placetype":"venue"
},
  "geometry": {"coordinates":[-83.041635,39.983323],"type":"Point"}
}