{
  "type": "Feature",
  "properties": {
    "iso:country":"US",
    "sg:address":"1749 Cleveland Rd",
    "sg:city":"Wooster",
    "sg:classifiers":[
        {
            "category":"Health Services",
            "subcategory":"Doctor",
            "type":"Services"
        }
    ],
    "sg:phone":"+1 330 264 9699",
    "sg:postcode":"44691",
    "sg:province":"OH",
    "sg:tags":[
        "medical"
    ],
    "wof:name":"Mathur Arun K",
    "wof:placetype":"venue"
},
  "geometry": {"coordinates":[-81.935311,40.82041],"type":"Point"}
}