{
  "type": "Feature",
  "properties": {
    "addr:full":"160 Elevator Ave Painesville OH 44077",
    "addr:housenumber":"160",
    "addr:postcode":"44077",
    "addr:street":"Elevator Ave",
    "iso:country":"US",
    "sg:address":"160 Elevator Ave",
    "sg:city":"Painesville",
    "sg:classifiers":[
        {
            "category":"Manufacturing",
            "subcategory":"Printing",
            "type":"Manufacturing & Wholesale Goods"
        }
    ],
    "sg:phone":"+1 440 357 4424",
    "sg:postcode":"44077",
    "sg:province":"OH",
    "sg:tags":[
        "publisher"
    ],
    "wof:name":"Mc Groarty Enterprises",
    "wof:placetype":"venue"
},
  "geometry": {"coordinates":[-81.237064,41.714761],"type":"Point"}
}