{
  "type": "Feature",
  "properties": {
    "iso:country":"US",
    "sg:address":"5218 Oakbriar Cir NE",
    "sg:city":"Canton",
    "sg:classifiers":[
        {
            "category":"Banks & Credit Unions",
            "subcategory":"Bank",
            "type":"Services"
        }
    ],
    "sg:phone":"+1 330 491 1967",
    "sg:postcode":"44705",
    "sg:province":"OH",
    "sg:tags":[
        "loan",
        "broker"
    ],
    "wof:name":"Home Office",
    "wof:placetype":"venue"
},
  "geometry": {"coordinates":[-81.343225,40.85638],"type":"Point"}
}