{
  "type": "Feature",
  "properties": {
    "addr:full": "1488 Grandview Ave Columbus OH 43212",
    "addr:housenumber": "1488",
    "addr:postcode": "43212",
    "addr:street": "Grandview Ave",
    "iso:country": "US",
    "sg:address": "1488 Grandview Ave",
    "sg:city": "Columbus",
    "sg:classifiers": [
      {
        "category": "Health Services",
        "subcategory": "Health Practitioner",
        "type": "Services"
      }
    ],
    "sg:phone": "+1 614 486 4892",
    "sg:postcode": "43212",
    "sg:province": "OH",
    "sg:tags": [
      "therapist",
      "physical"
    ],
    "wof:name": "Grandview Ave Physical Therapy",
    "wof:placetype": "venue"
  },
  "geometry": {"coordinates":[-83.044428,39.988124],"type":"Point"}
}
