{
  "type": "Feature",
  "properties": {
    "addr:full": "8 Wesley Ave Heath OH 43056",
    "addr:housenumber": "8",
    "addr:postcode": "43056",
    "addr:street": "Wesley Ave",
    "iso:country": "US",
    "sg:address": "8 Wesley Ave",
    "sg:city": "Heath",
    "sg:classifiers": [
      {
        "category": "Building \u0026 Trades",
        "subcategory": "Cleaning \u0026 Sanitation",
        "type": "Services"
      },
      {
        "category": "Building \u0026 Trades",
        "subcategory": "Construction",
        "type": "Services"
      }
    ],
    "sg:phone": "+1 740 522 5666",
    "sg:postcode": "43056",
    "sg:province": "OH",
    "sg:tags": [
      "repair",
      "fireplace",
      "chimney",
      "contractor"
    ],
    "wof:name": "Colonial Chimney Sweeps",
    "wof:placetype": "venue"
  },
  "geometry": {"coordinates":[-82.464879,39.999684],"type":"Point"}
}
