{
  "type": "Feature",
  "properties": {
    "addr:full": "5926 Beach Rd Wadsworth OH 44281",
    "addr:housenumber": "5926",
    "addr:postcode": "44281",
    "addr:street": "Beach Rd",
    "iso:country": "US",
    "sg:address": "5926 Beach Rd",
    "sg:city": "Wadsworth",
    "sg:classifiers": [
      {
        "category": "Professional",
        "subcategory": "Business Services",
        "type": "Services"
      }
    ],
    "sg:phone": "+1 330 239 2585",
    "sg:postcode": "44281",
    "sg:province": "OH",
    "sg:tags": [
      "lecture",
      "bureau",
      "seminar"
    ],
    "wof:name": "Hairohio",
    "wof:placetype": "venue"
  },
  "geometry": {"coordinates":[-81.756105,41.115345],"type":"Point"}
}
