{
  "type": "Feature",
  "properties": {
    "iso:country":"US",
    "sg:address":"527 S Union St",
    "sg:city":"Bryan",
    "sg:classifiers":[
        {
            "category":"Retail",
            "subcategory":"Repair Shop",
            "type":"Services"
        },
        {
            "category":"Wholesale",
            "subcategory":"Electrical",
            "type":"Manufacturing & Wholesale Goods"
        }
    ],
    "sg:phone":"+1 419 636 3438",
    "sg:postcode":"43506",
    "sg:province":"OH",
    "sg:tags":[
        "electric",
        "motor"
    ],
    "wof:name":"Koontz-Wagner Electric Company",
    "wof:placetype":"venue"
},
  "geometry": {"coordinates":[-84.536508,41.470445],"type":"Point"}
}