{
  "type": "Feature",
  "properties": {
    "addr:full": "2524 Cleveland Ave SW Canton OH 44707",
    "addr:housenumber": "2524",
    "addr:postcode": "44707",
    "addr:street": "Cleveland Ave Sw",
    "iso:country": "US",
    "sg:address": "2524 Cleveland Ave SW",
    "sg:city": "Canton",
    "sg:classifiers": [
      {
        "category": "Real Estate",
        "subcategory": "Real Estate Agent",
        "type": "Services"
      }
    ],
    "sg:phone": "+1 330 484 4300",
    "sg:postcode": "44707",
    "sg:province": "OH",
    "wof:name": "Southway Mini Storage",
    "wof:placetype": "venue"
  },
  "geometry": {"coordinates":[-81.385559,40.77007],"type":"Point"}
}
