{
  "type": "Feature",
  "properties": {
    "addr:full": "695 Koebel Ave Columbus OH 43207",
    "addr:housenumber": "695",
    "addr:postcode": "43207",
    "addr:street": "Koebel Ave",
    "iso:country": "US",
    "sg:address": "695 Koebel Ave",
    "sg:city": "Columbus",
    "sg:classifiers": [
      {
        "category": "Manufacturing",
        "subcategory": "Printing",
        "type": "Manufacturing \u0026 Wholesale Goods"
      }
    ],
    "sg:phone": "+1 614 444 3171",
    "sg:postcode": "43207",
    "sg:province": "OH",
    "sg:tags": [
      "printer",
      "commercial",
      "typesetting"
    ],
    "wof:name": "Baise Quality Printing-Graphic",
    "wof:placetype": "venue"
  },
  "geometry": {"coordinates":[-82.980545,39.914229],"type":"Point"}
}
