{
  "type": "Feature",
  "properties": {
    "addr:full":"1730 Newberry St Cuyahoga Falls OH 44221",
    "addr:housenumber":"1730",
    "addr:postcode":"44221",
    "addr:street":"Newberry St",
    "iso:country":"US",
    "sg:address":"1730 Newberry St",
    "sg:city":"Cuyahoga Falls",
    "sg:classifiers":[
        {
            "category":"Professional",
            "type":"Services"
        }
    ],
    "sg:phone":"+1 330 618 4296",
    "sg:postcode":"44221",
    "sg:province":"OH",
    "wof:name":"Radiographic Quality Assurance",
    "wof:placetype":"venue"
},
  "geometry": {"coordinates":[-81.480019,41.129933],"type":"Point"}
}