{
  "type": "Feature",
  "properties": {
    "iso:country":"US",
    "sg:address":"1670 Fox Wood Trl",
    "sg:city":"Loveland",
    "sg:classifiers":[
        {
            "category":"Manufacturing",
            "subcategory":"Metals",
            "type":"Manufacturing & Wholesale Goods"
        }
    ],
    "sg:phone":"+1 513 241 6603",
    "sg:postcode":"45140",
    "sg:province":"OH",
    "sg:tags":[
        "fabrication",
        "structural"
    ],
    "wof:name":"Carew Tower Magic Shop In",
    "wof:placetype":"venue"
},
  "geometry": {"coordinates":[-84.246948,39.218535],"type":"Point"}
}