{
  "type": "Feature",
  "properties": {
    "addr:full": "1944 Lucille Dr Dayton OH 45404",
    "addr:housenumber": "1944",
    "addr:postcode": "45404",
    "addr:street": "Lucille Dr",
    "iso:country": "US",
    "sg:address": "1944 Lucille Dr",
    "sg:city": "Dayton",
    "sg:classifiers": [
      {
        "category": "Manufacturing",
        "subcategory": "Tools \u0026 Machinery",
        "type": "Manufacturing \u0026 Wholesale Goods"
      }
    ],
    "sg:phone": "+1 937 222 5022",
    "sg:postcode": "45404",
    "sg:province": "OH",
    "sg:tags": [
      "mfg"
    ],
    "wof:name": "Dana Ray Technologies",
    "wof:placetype": "venue"
  },
  "geometry": {"coordinates":[-84.18223,39.789531],"type":"Point"}
}
