{
  "type": "Feature",
  "properties": {
    "iso:country":"US",
    "sg:address":"1944 Lucille Dr",
    "sg:city":"Dayton",
    "sg:classifiers":[
        {
            "category":"Manufacturing",
            "subcategory":"Tools & Machinery",
            "type":"Manufacturing & Wholesale Goods"
        }
    ],
    "sg:phone":"+1 937 222 5022",
    "sg:postcode":"45404",
    "sg:province":"OH",
    "sg:tags":[
        "mfg"
    ],
    "wof:name":"Dana Ray Technologies",
    "wof:placetype":"venue"
},
  "geometry": {"coordinates":[-84.18223,39.789531],"type":"Point"}
}