{
  "type": "Feature",
  "properties": {
    "addr:full":"100 Jamaica Rd Franklin OH 45005",
    "addr:housenumber":"100",
    "addr:postcode":"45005",
    "addr:street":"Jamaica Rd",
    "iso:country":"US",
    "sg:address":"100 Jamaica Rd",
    "sg:city":"Franklin",
    "sg:classifiers":[
        {
            "category":"Education",
            "subcategory":"School",
            "type":"Public Place"
        }
    ],
    "sg:phone":"+1 937 746 8969",
    "sg:postcode":"45005",
    "sg:province":"OH",
    "wof:name":"Carlisle Intermediate School",
    "wof:placetype":"venue"
},
  "geometry": {"coordinates":[-84.32366399999999,39.587422],"type":"Point"}
}