{
  "type": "Feature",
  "properties": {
    "iso:country":"US",
    "sg:address":"2615 W Bancroft St",
    "sg:city":"Toledo",
    "sg:classifiers":[
        {
            "category":"Insurance",
            "subcategory":"Insurance Agent",
            "type":"Services"
        }
    ],
    "sg:phone":"+1 419 536 8231",
    "sg:postcode":"43607",
    "sg:province":"OH",
    "wof:name":"David R Spitznaugle Insurance",
    "wof:placetype":"venue"
},
  "geometry": {"coordinates":[-83.60750899999999,41.663113],"type":"Point"}
}