{
  "type": "Feature",
  "properties": {
    "addr:full":"428 N Wolf Creek St Brookville OH 45309",
    "addr:housenumber":"428",
    "addr:postcode":"45309",
    "addr:street":"N Wolf Creek St",
    "iso:country":"US",
    "sg:address":"428 N Wolf Creek St",
    "sg:city":"Brookville",
    "sg:classifiers":[
        {
            "category":"Home & Garden",
            "subcategory":"Hardware",
            "type":"Retail Goods"
        }
    ],
    "sg:phone":"+1 937 833 4026",
    "sg:postcode":"45309",
    "sg:province":"OH",
    "wof:name":"True Value Hardware",
    "wof:placetype":"venue"
},
  "geometry": {"coordinates":[-84.422392,39.839851],"type":"Point"}
}