{
  "type": "Feature",
  "properties": {
    "addr:full": "148 N Main St New Madison OH 45346",
    "addr:housenumber": "148",
    "addr:postcode": "45346",
    "addr:street": "N Main St",
    "iso:country": "US",
    "sg:address": "148 N Main St",
    "sg:city": "New Madison",
    "sg:classifiers": [
      {
        "category": "Personal",
        "type": "Services"
      }
    ],
    "sg:phone": "+1 937 996 1111",
    "sg:postcode": "45346",
    "sg:province": "OH",
    "sg:tags": [
      "therapist",
      "massage"
    ],
    "wof:name": "White Feather Medical Massage",
    "wof:placetype": "venue"
  },
  "geometry": {"coordinates":[-84.708275,39.969439],"type":"Point"}
}
