{
  "type": "Feature",
  "properties": {
    "addr:full": "7491 State Rte 45 Lisbon OH 44432",
    "addr:housenumber": "7491",
    "addr:postcode": "44432",
    "addr:street": "State Rte 45",
    "iso:country": "US",
    "sg:address": "7491 State Rte 45",
    "sg:city": "Lisbon",
    "sg:classifiers": [
      {
        "category": "Retail",
        "subcategory": "Auto Repair",
        "type": "Services"
      }
    ],
    "sg:phone": "+1 330 424 9751",
    "sg:postcode": "44432",
    "sg:province": "OH",
    "sg:tags": [
      "repairing",
      "automobile"
    ],
    "wof:name": "Faulk's Automotive Svc",
    "wof:placetype": "venue"
  },
  "geometry": {"coordinates":[-80.778591,40.791969],"type":"Point"}
}
