{
  "type": "Feature",
  "properties": {
    "addr:full": "4460 South Ave Toledo OH 43615",
    "addr:housenumber": "4460",
    "addr:postcode": "43615",
    "addr:street": "South Ave",
    "iso:country": "US",
    "sg:address": "4460 South Ave",
    "sg:city": "Toledo",
    "sg:classifiers": [
      {
        "category": "Organizations",
        "subcategory": "Religious Organization",
        "type": "Services"
      }
    ],
    "sg:phone": "+1 419 868 6086",
    "sg:postcode": "43615",
    "sg:province": "OH",
    "sg:tags": [
      "church"
    ],
    "wof:name": "Christian Fellowship Chr-God",
    "wof:placetype": "venue"
  },
  "geometry": {"coordinates":[-83.647381,41.631041],"type":"Point"}
}
