{
  "type": "Feature",
  "properties": {
    "addr:full":"2085 Kemper Hollow Rd Gallipolis OH 45631",
    "addr:housenumber":"2085",
    "addr:postcode":"45631",
    "addr:street":"Kemper Hollow Rd",
    "iso:country":"US",
    "sg:address":"2085 Kemper Hollow Rd",
    "sg:city":"Gallipolis",
    "sg:classifiers":[
        {
            "category":"Insurance",
            "subcategory":"Insurance Agent",
            "type":"Services"
        }
    ],
    "sg:phone":"+1 740 446 7659",
    "sg:postcode":"45631",
    "sg:province":"OH",
    "wof:name":"Kisner Home Inspections",
    "wof:placetype":"venue"
},
  "geometry": {"coordinates":[-82.228702,38.875309],"type":"Point"}
}