{
  "type": "Feature",
  "properties": {
    "addr:full": "709 N Main St Celina OH 45822",
    "addr:housenumber": "709",
    "addr:postcode": "45822",
    "addr:street": "N Main St",
    "iso:country": "US",
    "sg:address": "709 N Main St",
    "sg:city": "Celina",
    "sg:classifiers": [
      {
        "category": "Banks \u0026 Credit Unions",
        "subcategory": "Bank",
        "type": "Services"
      }
    ],
    "sg:phone": "+1 419 584 2300",
    "sg:postcode": "45822",
    "sg:province": "OH",
    "sg:tags": [
      "loan"
    ],
    "wof:name": "Citizens National Bank",
    "wof:placetype": "venue"
  },
  "geometry": {"coordinates":[-84.571273,40.557538],"type":"Point"}
}
