{
  "type": "Feature",
  "properties": {
    "addr:full":"4482 Broadview Rd Cleveland OH 44109",
    "addr:housenumber":"4482",
    "addr:postcode":"44109",
    "addr:street":"Broadview Rd",
    "iso:country":"US",
    "sg:address":"4482 Broadview Rd",
    "sg:city":"Cleveland",
    "sg:classifiers":[
        {
            "category":"Personal",
            "subcategory":"Barber",
            "type":"Services"
        }
    ],
    "sg:phone":"+1 216 398 4048",
    "sg:postcode":"44109",
    "sg:province":"OH",
    "wof:name":"Broadview Road Barber & Stylng",
    "wof:placetype":"venue"
},
  "geometry": {"coordinates":[-81.69724100000001,41.433433],"type":"Point"}
}