{
  "type": "Feature",
  "properties": {
    "addr:full": "113 S Defiance St Stryker OH 43557",
    "addr:housenumber": "113",
    "addr:postcode": "43557",
    "addr:street": "S Defiance St",
    "iso:country": "US",
    "sg:address": "113 S Defiance St",
    "sg:city": "Stryker",
    "sg:classifiers": [
      {
        "category": "Professional",
        "subcategory": "Art Services",
        "type": "Services"
      }
    ],
    "sg:phone": "+1 419 682 5472",
    "sg:postcode": "43557",
    "sg:province": "OH",
    "sg:tags": [
      "photographer"
    ],
    "wof:name": "Lisa Whitlock Photo Studio",
    "wof:placetype": "venue"
  },
  "geometry": {"coordinates":[-84.414279,41.503877],"type":"Point"}
}
