{
  "type": "Feature",
  "properties": {
    "addr:full":"601 S High St Columbus OH 43215",
    "addr:housenumber":"601",
    "addr:postcode":"43215",
    "addr:street":"S High St",
    "iso:country":"US",
    "sg:address":"601 S High St",
    "sg:city":"Columbus",
    "sg:classifiers":[
        {
            "category":"Professional",
            "subcategory":"Lawyer & Legal Services",
            "type":"Services"
        }
    ],
    "sg:phone":"+1 614 228 4992",
    "sg:postcode":"43215",
    "sg:province":"OH",
    "sg:tags":[
        "attorney"
    ],
    "wof:name":"Brian A Walker",
    "wof:placetype":"venue"
},
  "geometry": {"coordinates":[-82.99809500000001,39.949082],"type":"Point"}
}