{
  "type": "Feature",
  "properties": {
    "addr:full": "12804 Antioch Rd Leesburg OH 45135",
    "addr:housenumber": "12804",
    "addr:postcode": "45135",
    "addr:street": "Antioch Rd",
    "iso:country": "US",
    "sg:address": "12804 Antioch Rd",
    "sg:city": "Leesburg",
    "sg:classifiers": [
      {
        "category": "Professional",
        "type": "Services"
      }
    ],
    "sg:phone": "+1 937 780 6308",
    "sg:postcode": "45135",
    "sg:province": "OH",
    "sg:tags": [
      "physicist"
    ],
    "wof:name": "D G Dunsieth",
    "wof:placetype": "venue"
  },
  "geometry": {"coordinates":[-83.629864,39.355202],"type":"Point"}
}
