{
  "type": "Feature",
  "properties": {
    "addr:full":"1095 Clark Ave Cleveland OH 44109",
    "addr:housenumber":"1095",
    "addr:postcode":"44109",
    "addr:street":"Clark Ave",
    "iso:country":"US",
    "sg:address":"1095 Clark Ave",
    "sg:city":"Cleveland",
    "sg:classifiers":[
        {
            "category":"Retail",
            "subcategory":"Auto Repair",
            "type":"Services"
        }
    ],
    "sg:phone":"+1 216 344 9122",
    "sg:postcode":"44109",
    "sg:province":"OH",
    "sg:tags":[
        "repairing",
        "automobile"
    ],
    "wof:name":"Bobby's Automotive",
    "wof:placetype":"venue"
},
  "geometry": {"coordinates":[-81.681752,41.470206],"type":"Point"}
}