{
  "type": "Feature",
  "properties": {
    "addr:full": "1621 E Market St Akron OH 44305",
    "addr:housenumber": "1621",
    "addr:postcode": "44305",
    "addr:street": "E Market St",
    "iso:country": "US",
    "sg:address": "1621 E Market St",
    "sg:city": "Akron",
    "sg:classifiers": [
      {
        "category": "Manufacturing",
        "subcategory": "Food",
        "type": "Manufacturing \u0026 Wholesale Goods"
      }
    ],
    "sg:phone": "+1 330 733 9693",
    "sg:postcode": "44305",
    "sg:province": "OH",
    "sg:tags": [
      "ice",
      "mfg"
    ],
    "wof:name": "Serv-Ice Delivery Co",
    "wof:placetype": "venue"
  },
  "geometry": {"coordinates":[-81.469484,41.062605],"type":"Point"}
}
