{
  "type": "Feature",
  "properties": {
    "addr:full": "259 Greenmount Blvd Dayton OH 45419",
    "addr:housenumber": "259",
    "addr:postcode": "45419",
    "addr:street": "Greenmount Blvd",
    "iso:country": "US",
    "sg:address": "259 Greenmount Blvd",
    "sg:city": "Dayton",
    "sg:classifiers": [
      {
        "category": "Shopping",
        "subcategory": "Crafts \u0026 Fabrics",
        "type": "Retail Goods"
      }
    ],
    "sg:phone": "+1 937 293 9933",
    "sg:postcode": "45419",
    "sg:province": "OH",
    "sg:tags": [
      "material",
      "needlework"
    ],
    "wof:name": "Primrose Garden",
    "wof:placetype": "venue"
  },
  "geometry": {"coordinates":[-84.166949,39.718709],"type":"Point"}
}
