{
  "type": "Feature",
  "properties": {
    "iso:country":"US",
    "sg:address":"259 Greenmount Blvd",
    "sg:city":"Dayton",
    "sg:classifiers":[
        {
            "category":"Shopping",
            "subcategory":"Crafts & Fabrics",
            "type":"Retail Goods"
        }
    ],
    "sg:phone":"+1 937 293 9933",
    "sg:postcode":"45419",
    "sg:province":"OH",
    "sg:tags":[
        "material",
        "needlework"
    ],
    "wof:name":"Primrose Garden",
    "wof:placetype":"venue"
},
  "geometry": {"coordinates":[-84.166949,39.718709],"type":"Point"}
}