{
  "type": "Feature",
  "properties": {
    "addr:full": "872 Daily Rd Eaton OH 45320",
    "addr:housenumber": "872",
    "addr:postcode": "45320",
    "addr:street": "Daily Rd",
    "iso:country": "US",
    "sg:address": "872 Daily Rd",
    "sg:city": "Eaton",
    "sg:classifiers": [
      {
        "category": "Farming",
        "subcategory": "Livestock Farm",
        "type": "Manufacturing \u0026 Wholesale Goods"
      }
    ],
    "sg:phone": "+1 937 456 6452",
    "sg:postcode": "45320",
    "sg:province": "OH",
    "sg:tags": [
      "beef",
      "feedlot",
      "cattle"
    ],
    "wof:name": "Mike Hans Farm",
    "wof:placetype": "venue"
  },
  "geometry": {"coordinates":[-84.74156,39.762595],"type":"Point"}
}
