{
  "type": "Feature",
  "properties": {
    "addr:full":"4424 Genesee Ave Dayton OH 45406",
    "addr:housenumber":"4424",
    "addr:postcode":"45406",
    "addr:street":"Genesee Ave",
    "iso:country":"US",
    "sg:address":"4424 Genesee Ave",
    "sg:city":"Dayton",
    "sg:classifiers":[
        {
            "category":"Building & Trades",
            "subcategory":"Cleaning & Sanitation",
            "type":"Services"
        }
    ],
    "sg:phone":"+1 937 275 8144",
    "sg:postcode":"45406",
    "sg:province":"OH",
    "sg:tags":[
        "janitor"
    ],
    "wof:name":"Simply Cleaned & Shined",
    "wof:placetype":"venue"
},
  "geometry": {"coordinates":[-84.256912,39.784866],"type":"Point"}
}