{
  "type": "Feature",
  "properties": {
    "iso:country":"US",
    "sg:address":"3600 Shawnee Rd",
    "sg:city":"Lima",
    "sg:classifiers":[
        {
            "category":"Restaurant",
            "type":"Food & Drink"
        }
    ],
    "sg:phone":"+1 419 999 5542",
    "sg:postcode":"45806",
    "sg:province":"OH",
    "sg:tags":[
        "eating"
    ],
    "wof:name":"Short Stop Drive Thru",
    "wof:placetype":"venue"
},
  "geometry": {"coordinates":[-84.151152,40.686447],"type":"Point"}
}