{
  "type": "Feature",
  "properties": {
    "addr:full": "5166 Monroe St Toledo OH 43623",
    "addr:housenumber": "5166",
    "addr:postcode": "43623",
    "addr:street": "Monroe St",
    "iso:country": "US",
    "sg:address": "5166 Monroe St",
    "sg:city": "Toledo",
    "sg:classifiers": [
      {
        "category": "Retail",
        "subcategory": "Veterinary Services",
        "type": "Services"
      }
    ],
    "sg:phone": "+1 419 843 3137",
    "sg:postcode": "43623",
    "sg:province": "OH",
    "sg:tags": [
      "veterinarian"
    ],
    "wof:name": "Bird \u0026 Exotic Pet Wellness",
    "wof:placetype": "venue"
  },
  "geometry": {"coordinates":[-83.652719,41.701688],"type":"Point"}
}
