{
  "type": "Feature",
  "properties": {
    "addr:full":"3452 Bolender Rd Bethel OH 45106",
    "addr:housenumber":"3452",
    "addr:postcode":"45106",
    "addr:street":"Bolender Rd",
    "iso:country":"US",
    "sg:address":"3452 Bolender Rd",
    "sg:city":"Bethel",
    "sg:classifiers":[
        {
            "category":"Food & Beverages",
            "subcategory":"Meat & Fish",
            "type":"Retail Goods"
        }
    ],
    "sg:phone":"+1 513 876 2859",
    "sg:postcode":"45106",
    "sg:province":"OH",
    "wof:name":"Sunshine Acres Emu Farm",
    "wof:placetype":"venue"
},
  "geometry": {"coordinates":[-84.091667,38.857743],"type":"Point"}
}