{
  "type": "Feature",
  "properties": {
    "iso:country":"US",
    "sg:address":"6788 Lake Ave",
    "sg:city":"Elyria",
    "sg:classifiers":[
        {
            "category":"Insurance",
            "subcategory":"Insurance Agent",
            "type":"Services"
        }
    ],
    "sg:phone":"+1 440 324 3331",
    "sg:postcode":"44035",
    "sg:province":"OH",
    "wof:name":"Sandi Criswell Insur Agcy",
    "wof:placetype":"venue"
},
  "geometry": {"coordinates":[-82.131697,41.400835],"type":"Point"}
}