{
  "type": "Feature",
  "properties": {
    "addr:full":"1000 Urlin Ave Columbus OH 43212",
    "addr:housenumber":"1000",
    "addr:postcode":"43212",
    "addr:street":"Urlin Ave",
    "iso:country":"US",
    "sg:address":"1000 Urlin Ave",
    "sg:city":"Columbus",
    "sg:classifiers":[
        {
            "category":"Professional",
            "subcategory":"Management & Consulting",
            "type":"Services"
        }
    ],
    "sg:phone":"+1 614 488 4401",
    "sg:postcode":"43212",
    "sg:province":"OH",
    "sg:tags":[
        "consultant",
        "business"
    ],
    "wof:name":"Kampmeier Group LLC",
    "wof:placetype":"venue"
},
  "geometry": {"coordinates":[-83.050505,39.977796],"type":"Point"}
}