{
  "type": "Feature",
  "properties": {
    "iso:country":"US",
    "sg:address":"670 Enterprise Dr",
    "sg:city":"Lewis Center",
    "sg:classifiers":[
        {
            "category":"Professional",
            "type":"Services"
        }
    ],
    "sg:phone":"+1 614 540 3050",
    "sg:postcode":"43035",
    "sg:province":"OH",
    "sg:tags":[
        "establishment"
    ],
    "wof:name":"Integrity Online Columbus",
    "wof:placetype":"venue"
},
  "geometry": {"coordinates":[-83.008436,40.15381],"type":"Point"}
}