{
  "type": "Feature",
  "properties": {
    "addr:full": "144 Union St Tiffin OH 44883",
    "addr:housenumber": "144",
    "addr:postcode": "44883",
    "addr:street": "Union St",
    "iso:country": "US",
    "sg:address": "144 Union St",
    "sg:city": "Tiffin",
    "sg:classifiers": [
      {
        "category": "Social Services",
        "subcategory": "Child Care",
        "type": "Services"
      }
    ],
    "sg:phone": "+1 419 448 9640",
    "sg:postcode": "44883",
    "sg:province": "OH",
    "wof:name": "Daycare Provider",
    "wof:placetype": "venue"
  },
  "geometry": {"coordinates":[-83.182552,41.107637],"type":"Point"}
}
