{
  "type": "Feature",
  "properties": {
    "addr:full":"1428 Market Ave N Canton OH 44714",
    "addr:housenumber":"1428",
    "addr:postcode":"44714",
    "addr:street":"Market Ave N",
    "iso:country":"US",
    "sg:address":"1428 Market Ave N",
    "sg:city":"Canton",
    "sg:classifiers":[
        {
            "category":"Professional",
            "subcategory":"Lawyer & Legal Services",
            "type":"Services"
        }
    ],
    "sg:phone":"+1 330 452 7334",
    "sg:postcode":"44714",
    "sg:province":"OH",
    "sg:tags":[
        "attorney"
    ],
    "wof:name":"Richard R Kuhn",
    "wof:placetype":"venue"
},
  "geometry": {"coordinates":[-81.370555,40.813524],"type":"Point"}
}