{
  "type": "Feature",
  "properties": {
    "addr:full": "1501 Bowman St Mansfield OH 44903",
    "addr:housenumber": "1501",
    "addr:postcode": "44903",
    "addr:street": "Bowman St",
    "iso:country": "US",
    "sg:address": "1501 Bowman St",
    "sg:city": "Mansfield",
    "sg:classifiers": [
      {
        "category": "Wholesale",
        "subcategory": "Auto Parts",
        "type": "Manufacturing \u0026 Wholesale Goods"
      }
    ],
    "sg:phone": "+1 419 747 5050",
    "sg:postcode": "44903",
    "sg:province": "OH",
    "sg:tags": [
      "automobile",
      "rebuilt"
    ],
    "wof:name": "Bowman Auto Recycling",
    "wof:placetype": "venue"
  },
  "geometry": {"coordinates":[-82.539097,40.799924],"type":"Point"}
}
