{
  "type": "Feature",
  "properties": {
    "iso:country":"US",
    "sg:address":"1501 Bowman St",
    "sg:city":"Mansfield",
    "sg:classifiers":[
        {
            "category":"Wholesale",
            "subcategory":"Auto Parts",
            "type":"Manufacturing & Wholesale Goods"
        }
    ],
    "sg:phone":"+1 419 747 5050",
    "sg:postcode":"44903",
    "sg:province":"OH",
    "sg:tags":[
        "automobile",
        "rebuilt"
    ],
    "wof:name":"Bowman Auto Recycling",
    "wof:placetype":"venue"
},
  "geometry": {"coordinates":[-82.539097,40.799924],"type":"Point"}
}