{
  "type": "Feature",
  "properties": {
    "iso:country":"US",
    "sg:address":"1032 Shroyer Rd",
    "sg:city":"Dayton",
    "sg:classifiers":[
        {
            "category":"Personal",
            "type":"Services"
        }
    ],
    "sg:phone":"+1 937 290 0300",
    "sg:postcode":"45419",
    "sg:province":"OH",
    "sg:tags":[
        "miscellaneous"
    ],
    "wof:name":"Personal Trainers",
    "wof:placetype":"venue"
},
  "geometry": {"coordinates":[-84.16104300000001,39.720659],"type":"Point"}
}