{
  "type": "Feature",
  "properties": {
    "iso:country":"US",
    "sg:address":"3568 Columbia Pkwy",
    "sg:city":"Cincinnati",
    "sg:classifiers":[
        {
            "category":"Restaurant",
            "type":"Food & Drink"
        }
    ],
    "sg:phone":"+1 513 321 9545",
    "sg:postcode":"45226",
    "sg:province":"OH",
    "sg:tags":[
        "caterer"
    ],
    "wof:name":"Village Pantry Catering",
    "wof:placetype":"venue"
},
  "geometry": {"coordinates":[-84.43681599999999,39.115978],"type":"Point"}
}