{
  "type": "Feature",
  "properties": {
    "addr:full": "3568 Columbia Pkwy Cincinnati OH 45226",
    "addr:housenumber": "3568",
    "addr:postcode": "45226",
    "addr:street": "Columbia Pkwy",
    "iso:country": "US",
    "sg:address": "3568 Columbia Pkwy",
    "sg:city": "Cincinnati",
    "sg:classifiers": [
      {
        "category": "Restaurant",
        "type": "Food \u0026 Drink"
      }
    ],
    "sg:phone": "+1 513 321 9545",
    "sg:postcode": "45226",
    "sg:province": "OH",
    "sg:tags": [
      "caterer"
    ],
    "wof:name": "Village Pantry Catering",
    "wof:placetype": "venue"
  },
  "geometry": {"coordinates":[-84.436816,39.115978],"type":"Point"}
}
