{
  "type": "Feature",
  "properties": {
    "iso:country":"US",
    "sg:address":"5424 Airport Hwy",
    "sg:city":"Toledo",
    "sg:classifiers":[
        {
            "category":"Sports & Exercise",
            "subcategory":"Gym",
            "type":"Entertainment"
        }
    ],
    "sg:phone":"+1 419 866 8276",
    "sg:postcode":"43615",
    "sg:province":"OH",
    "sg:tags":[
        "club",
        "health",
        "studio",
        "gymnasium"
    ],
    "sg:website":"www.ballyfitness.com",
    "wof:name":"Bally Total Fitness",
    "wof:placetype":"venue"
},
  "geometry": {"coordinates":[-83.67138,41.616461],"type":"Point"}
}