{
  "type": "Feature",
  "properties": {
    "addr:full": "2100 W State St Fremont OH 43420",
    "addr:housenumber": "2100",
    "addr:postcode": "43420",
    "addr:street": "W State St",
    "iso:country": "US",
    "sg:address": "2100 W State St",
    "sg:city": "Fremont",
    "sg:classifiers": [
      {
        "category": "Restaurant",
        "type": "Food \u0026 Drink"
      }
    ],
    "sg:phone": "+1 419 334 3475",
    "sg:postcode": "43420",
    "sg:province": "OH",
    "wof:name": "El Rancho II",
    "wof:placetype": "venue"
  },
  "geometry": {"coordinates":[-83.141365,41.358836],"type":"Point"}
}
