{
  "type": "Feature",
  "properties": {
    "addr:full":"4219 Hamilton Ave Cincinnati OH 45223",
    "addr:housenumber":"4219",
    "addr:postcode":"45223",
    "addr:street":"Hamilton Ave",
    "iso:country":"US",
    "sg:address":"4219 Hamilton Ave",
    "sg:city":"Cincinnati",
    "sg:classifiers":[
        {
            "category":"Education",
            "subcategory":"Library",
            "type":"Public Place"
        }
    ],
    "sg:phone":"+1 513 369 4449",
    "sg:postcode":"45223",
    "sg:province":"OH",
    "sg:website":"http://www.mhrecovery.com",
    "wof:name":"Public Library",
    "wof:placetype":"venue"
},
  "geometry": {"coordinates":[-84.540291,39.164009],"type":"Point"}
}