{
  "type": "Feature",
  "properties": {
    "addr:full": "530 S Maple St Bowling Green OH 43402",
    "addr:housenumber": "530",
    "addr:postcode": "43402",
    "addr:street": "S Maple St",
    "iso:country": "US",
    "sg:address": "530 S Maple St",
    "sg:city": "Bowling Green",
    "sg:classifiers": [
      {
        "category": "Building \u0026 Trades",
        "subcategory": "Construction",
        "type": "Services"
      }
    ],
    "sg:phone": "+1 419 352 7581",
    "sg:postcode": "43402",
    "sg:province": "OH",
    "sg:tags": [
      "contractor"
    ],
    "wof:name": "Piedmont Corp",
    "wof:placetype": "venue"
  },
  "geometry": {"coordinates":[-83.656167,41.3682],"type":"Point"}
}
