{
  "type": "Feature",
  "properties": {
    "addr:full": "4015 Monticello Blvd Youngstown OH 44505",
    "addr:housenumber": "4015",
    "addr:postcode": "44505",
    "addr:street": "Monticello Blvd",
    "iso:country": "US",
    "sg:address": "4015 Monticello Blvd",
    "sg:city": "Youngstown",
    "sg:classifiers": [
      {
        "category": "Organizations",
        "subcategory": "Religious Organization",
        "type": "Services"
      }
    ],
    "sg:phone": "+1 330 759 3656",
    "sg:postcode": "44505",
    "sg:province": "OH",
    "sg:tags": [
      "monastery",
      "convent"
    ],
    "wof:name": "Sisters Of Humility Of Mary",
    "wof:placetype": "venue"
  },
  "geometry": {"coordinates":[-80.629588,41.157219],"type":"Point"}
}
