{
  "type": "Feature",
  "properties": {
    "addr:full":"250 North St Conneaut OH 44030",
    "addr:housenumber":"250",
    "addr:postcode":"44030",
    "addr:street":"North St",
    "iso:country":"US",
    "sg:address":"250 North St",
    "sg:city":"Conneaut",
    "sg:classifiers":[
        {
            "category":"Building & Trades",
            "subcategory":"Electrical",
            "type":"Services"
        }
    ],
    "sg:phone":"+1 440 593 2988",
    "sg:postcode":"44030",
    "sg:province":"OH",
    "sg:tags":[
        "electrician"
    ],
    "wof:name":"Bittner Electric",
    "wof:placetype":"venue"
},
  "geometry": {"coordinates":[-80.57176800000001,41.94319],"type":"Point"}
}