{
  "type": "Feature",
  "properties": {
    "iso:country":"US",
    "sg:address":"258 Miami St",
    "sg:city":"Waynesville",
    "sg:classifiers":[
        {
            "category":"Professional",
            "subcategory":"Lawyer & Legal Services",
            "type":"Services"
        }
    ],
    "sg:phone":"+1 513 897 7916",
    "sg:postcode":"45068",
    "sg:province":"OH",
    "sg:tags":[
        "attorney"
    ],
    "wof:name":"Waynesville Area Land Title",
    "wof:placetype":"venue"
},
  "geometry": {"coordinates":[-84.08718500000001,39.530019],"type":"Point"}
}