{
  "type": "Feature",
  "properties": {
    "addr:full": "258 Miami St Waynesville OH 45068",
    "addr:housenumber": "258",
    "addr:postcode": "45068",
    "addr:street": "Miami St",
    "iso:country": "US",
    "sg:address": "258 Miami St",
    "sg:city": "Waynesville",
    "sg:classifiers": [
      {
        "category": "Professional",
        "subcategory": "Lawyer \u0026 Legal Services",
        "type": "Services"
      }
    ],
    "sg:phone": "+1 513 897 7916",
    "sg:postcode": "45068",
    "sg:province": "OH",
    "sg:tags": [
      "attorney"
    ],
    "wof:name": "Waynesville Area Land Title",
    "wof:placetype": "venue"
  },
  "geometry": {"coordinates":[-84.087185,39.530019],"type":"Point"}
}
