{
  "type": "Feature",
  "properties": {
    "addr:full": "425 N Brice Rd Blacklick OH 43004",
    "addr:housenumber": "425",
    "addr:postcode": "43004",
    "addr:street": "N Brice Rd",
    "iso:country": "US",
    "sg:address": "425 N Brice Rd",
    "sg:city": "Blacklick",
    "sg:classifiers": [
      {
        "category": "Parking",
        "subcategory": "Lot",
        "type": "Transportation"
      },
      {
        "category": "Autos \u0026 Motor Vehicles",
        "subcategory": "Auto Supplies",
        "type": "Retail Goods"
      },
      {
        "category": "Parking",
        "subcategory": "Garage",
        "type": "Transportation"
      },
      {
        "category": "Manufacturing",
        "subcategory": "Building Materials",
        "type": "Manufacturing \u0026 Wholesale Goods"
      }
    ],
    "sg:phone": "+1 614 864 2222",
    "sg:postcode": "43004",
    "sg:province": "OH",
    "sg:tags": [
      "garages-construction",
      "gate",
      "booths-toll",
      "facilities-equipment",
      "accessory"
    ],
    "sg:website": "http://www.signaturecontrols.com",
    "wof:name": "Signature Control Systems",
    "wof:placetype": "venue"
  },
  "geometry": {"coordinates":[-82.817318,39.985485],"type":"Point"}
}
