{
  "type": "Feature",
  "properties": {
    "iso:country":"US",
    "sg:address":"425 N Brice Rd",
    "sg:city":"Blacklick",
    "sg:classifiers":[
        {
            "category":"Parking",
            "subcategory":"Lot",
            "type":"Transportation"
        },
        {
            "category":"Autos & Motor Vehicles",
            "subcategory":"Auto Supplies",
            "type":"Retail Goods"
        },
        {
            "category":"Parking",
            "subcategory":"Garage",
            "type":"Transportation"
        },
        {
            "category":"Manufacturing",
            "subcategory":"Building Materials",
            "type":"Manufacturing & Wholesale Goods"
        }
    ],
    "sg:phone":"+1 614 864 2222",
    "sg:postcode":"43004",
    "sg:province":"OH",
    "sg:tags":[
        "garages-construction",
        "gate",
        "booths-toll",
        "facilities-equipment",
        "accessory"
    ],
    "sg:website":"http://www.signaturecontrols.com",
    "wof:name":"Signature Control Systems",
    "wof:placetype":"venue"
},
  "geometry": {"coordinates":[-82.817318,39.985485],"type":"Point"}
}