{
  "type": "Feature",
  "properties": {
    "addr:full":"29425 Chagrin Blvd Cleveland OH 44122",
    "addr:housenumber":"29425",
    "addr:postcode":"44122",
    "addr:street":"Chagrin Blvd",
    "iso:country":"US",
    "sg:address":"29425 Chagrin Blvd",
    "sg:city":"Cleveland",
    "sg:classifiers":[
        {
            "category":"Social Services",
            "type":"Services"
        }
    ],
    "sg:phone":"+1 216 556 2624",
    "sg:postcode":"44122",
    "sg:province":"OH",
    "sg:tags":[
        "counselor",
        "human",
        "relations"
    ],
    "wof:name":"Organizational Consulting Grp",
    "wof:placetype":"venue"
},
  "geometry": {"coordinates":[-81.47402,41.462429],"type":"Point"}
}