{
  "type": "Feature",
  "properties": {
    "addr:full": "7679 Mentor Ave Mentor OH 44060",
    "addr:housenumber": "7679",
    "addr:postcode": "44060",
    "addr:street": "Mentor Ave",
    "iso:country": "US",
    "sg:address": "7679 Mentor Ave",
    "sg:city": "Mentor",
    "sg:classifiers": [
      {
        "category": "Building \u0026 Trades",
        "subcategory": "Plumbing",
        "type": "Services"
      }
    ],
    "sg:phone": "+1 440 953 7970",
    "sg:postcode": "44060",
    "sg:province": "OH",
    "sg:tags": [
      "plumbing",
      "contractor"
    ],
    "wof:name": "Campbell Plumbing \u0026 Heating",
    "wof:placetype": "venue"
  },
  "geometry": {"coordinates":[-81.367326,41.658769],"type":"Point"}
}
