{
  "type": "Feature",
  "properties": {
    "iso:country":"US",
    "sg:address":"7679 Mentor Ave",
    "sg:city":"Mentor",
    "sg:classifiers":[
        {
            "category":"Building & Trades",
            "subcategory":"Plumbing",
            "type":"Services"
        }
    ],
    "sg:phone":"+1 440 953 7970",
    "sg:postcode":"44060",
    "sg:province":"OH",
    "sg:tags":[
        "plumbing",
        "contractor"
    ],
    "wof:name":"Campbell Plumbing & Heating",
    "wof:placetype":"venue"
},
  "geometry": {"coordinates":[-81.36732600000001,41.658769],"type":"Point"}
}