{
  "type": "Feature",
  "properties": {
    "addr:full": "3262 Darien Ln Twinsburg OH 44087",
    "addr:housenumber": "3262",
    "addr:postcode": "44087",
    "addr:street": "Darien Ln",
    "iso:country": "US",
    "sg:address": "3262 Darien Ln",
    "sg:city": "Twinsburg",
    "sg:classifiers": [
      {
        "category": "Social Services",
        "subcategory": "Child Care",
        "type": "Services"
      }
    ],
    "sg:phone": "+1 330 405 1950",
    "sg:postcode": "44087",
    "sg:province": "OH",
    "sg:website": "www.escholars.net",
    "wof:name": "Norton Kordell \u0026 Rene",
    "wof:placetype": "venue"
  },
  "geometry": {"coordinates":[-81.425093,41.325956],"type":"Point"}
}
