{
  "type": "Feature",
  "properties": {
    "addr:full":"318 W Oak St Wauseon OH 43567",
    "addr:housenumber":"318",
    "addr:postcode":"43567",
    "addr:street":"W Oak St",
    "iso:country":"US",
    "sg:address":"318 W Oak St",
    "sg:city":"Wauseon",
    "sg:classifiers":[
        {
            "category":"Building & Trades",
            "subcategory":"Landscaping Services",
            "type":"Services"
        }
    ],
    "sg:phone":"+1 419 335 6617",
    "sg:postcode":"43567",
    "sg:province":"OH",
    "sg:tags":[
        "landscape",
        "contractor"
    ],
    "wof:name":"D Jones Lawn & Landscape",
    "wof:placetype":"venue"
},
  "geometry": {"coordinates":[-84.145906,41.550096],"type":"Point"}
}