{
  "type": "Feature",
  "properties": {
    "addr:full":"5800 Rager Rd Groveport OH 43125",
    "addr:postcode":"5800;43125",
    "addr:street":"Rager Rd",
    "iso:country":"US",
    "sg:address":"5800 Rager Rd",
    "sg:city":"Groveport",
    "sg:classifiers":[
        {
            "category":"Wholesale",
            "subcategory":"Plants",
            "type":"Manufacturing & Wholesale Goods"
        },
        {
            "category":"Home & Garden",
            "subcategory":"Building Materials",
            "type":"Retail Goods"
        },
        {
            "category":"Building & Trades",
            "subcategory":"Landscaping Services",
            "type":"Services"
        },
        {
            "category":"Manufacturing",
            "subcategory":"Paper Products",
            "type":"Manufacturing & Wholesale Goods"
        },
        {
            "category":"Farming",
            "subcategory":"Nursery",
            "type":"Manufacturing & Wholesale Goods"
        },
        {
            "category":"Home & Garden",
            "subcategory":"Garden Supply",
            "type":"Retail Goods"
        }
    ],
    "sg:phone":"+1 614 836 3700",
    "sg:postcode":"43125",
    "sg:province":"OH",
    "sg:tags":[
        "designer",
        "nurseries-plants",
        "consultant",
        "builder",
        "tree",
        "nursery-wholesale",
        "equipment",
        "landscape",
        "greenhouse",
        "bamboo",
        "grower"
    ],
    "sg:website":"http://www.dillsgreenhouse.net",
    "wof:name":"Dill's Greenhouse, Inc.",
    "wof:placetype":"venue"
},
  "geometry": {"coordinates":[-82.84343699999999,39.864269],"type":"Point"}
}