{
  "type": "Feature",
  "properties": {
    "addr:full":"34785 Sherwood Dr Solon OH 44139",
    "addr:housenumber":"34785",
    "addr:postcode":"44139",
    "addr:street":"Sherwood Dr",
    "iso:country":"US",
    "sg:address":"34785 Sherwood Dr",
    "sg:city":"Solon",
    "sg:classifiers":[
        {
            "category":"Farming",
            "subcategory":"Farm & Veterinary Services",
            "type":"Manufacturing & Wholesale Goods"
        }
    ],
    "sg:phone":"+1 440 248 1519",
    "sg:postcode":"44139",
    "sg:province":"OH",
    "sg:tags":[
        "field",
        "crop",
        "harvesting"
    ],
    "wof:name":"Sherwood Farms",
    "wof:placetype":"venue"
},
  "geometry": {"coordinates":[-81.43046200000001,41.406835],"type":"Point"}
}