{
  "type": "Feature",
  "properties": {
    "addr:full": "3519 Washington Ave Cincinnati OH 45229",
    "addr:housenumber": "3519",
    "addr:postcode": "45229",
    "addr:street": "Washington Ave",
    "iso:country": "US",
    "sg:address": "3519 Washington Ave",
    "sg:city": "Cincinnati",
    "sg:classifiers": [
      {
        "category": "Social Services",
        "subcategory": "Adult Care",
        "type": "Services"
      }
    ],
    "sg:phone": "+1 513 771 3322",
    "sg:postcode": "45229",
    "sg:province": "OH",
    "sg:tags": [
      "residential"
    ],
    "wof:name": "We-Care/Washington",
    "wof:placetype": "venue"
  },
  "geometry": {"coordinates":[-84.495276,39.145233],"type":"Point"}
}
