{
  "type": "Feature",
  "properties": {
    "iso:country":"US",
    "sg:address":"938 W Main St",
    "sg:city":"Hillsboro",
    "sg:classifiers":[
        {
            "category":"Professional",
            "subcategory":"Accounting & Tax Preparation",
            "type":"Services"
        }
    ],
    "sg:phone":"+1 937 393 2215",
    "sg:postcode":"45133",
    "sg:province":"OH",
    "sg:tags":[
        "billing"
    ],
    "wof:name":"Southern Ohio Professional Bus",
    "wof:placetype":"venue"
},
  "geometry": {"coordinates":[-83.634694,39.205063],"type":"Point"}
}