{
  "type": "Feature",
  "properties": {
    "addr:full":"1978 E Walnut St Columbus OH 43205",
    "addr:housenumber":"1978",
    "addr:postcode":"43205",
    "addr:street":"E Walnut St",
    "iso:country":"US",
    "sg:address":"1978 E Walnut St",
    "sg:city":"Columbus",
    "sg:classifiers":[
        {
            "category":"Building & Trades",
            "subcategory":"Construction",
            "type":"Services"
        }
    ],
    "sg:phone":"+1 614 252 3737",
    "sg:postcode":"43205",
    "sg:province":"OH",
    "sg:tags":[
        "plastering",
        "contractor"
    ],
    "sg:website":"www.pymerplastering.com",
    "wof:name":"Pymer Plastering Inc",
    "wof:placetype":"venue"
},
  "geometry": {"coordinates":[-82.952338,39.959549],"type":"Point"}
}