{
  "type": "Feature",
  "properties": {
    "addr:full": "9288 Twp Hwy 10 Nevada OH 44849",
    "addr:housenumber": "9288",
    "addr:postcode": "44849",
    "addr:street": "Twp Hwy 10",
    "iso:country": "US",
    "sg:address": "9288 Twp Hwy 10",
    "sg:city": "Nevada",
    "sg:classifiers": [
      {
        "category": "Farming",
        "subcategory": "Farm",
        "type": "Manufacturing \u0026 Wholesale Goods"
      }
    ],
    "sg:phone": "+1 740 482 2561",
    "sg:postcode": "44849",
    "sg:province": "OH",
    "sg:tags": [
      "crop",
      "general"
    ],
    "wof:name": "David Ritzler",
    "wof:placetype": "venue"
  },
  "geometry": {"coordinates":[-83.112376,40.854746],"type":"Point"}
}
