{
  "type": "Feature",
  "properties": {
    "iso:country":"US",
    "sg:address":"2180 North St NW",
    "sg:city":"Granville",
    "sg:classifiers":[
        {
            "category":"Building & Trades",
            "subcategory":"Construction",
            "type":"Services"
        }
    ],
    "sg:phone":"+1 740 587 1008",
    "sg:postcode":"43023",
    "sg:province":"OH",
    "sg:tags":[
        "repairing",
        "remodeling",
        "contractor"
    ],
    "wof:name":"Central Ohio Remodeling",
    "wof:placetype":"venue"
},
  "geometry": {"coordinates":[-82.52038899999999,40.088656],"type":"Point"}
}