{
  "type": "Feature",
  "properties": {
    "iso:country":"US",
    "sg:address":"905 Canterbury Rd",
    "sg:city":"Cleveland",
    "sg:classifiers":[
        {
            "category":"Wholesale",
            "subcategory":"Construction Materials",
            "type":"Manufacturing & Wholesale Goods"
        }
    ],
    "sg:phone":"+1 440 243 9020",
    "sg:postcode":"44145",
    "sg:province":"OH",
    "sg:tags":[
        "frame",
        "industrial",
        "door"
    ],
    "wof:name":"Renewal By Anderson",
    "wof:placetype":"venue"
},
  "geometry": {"coordinates":[-81.911442,41.471585],"type":"Point"}
}