{
  "type": "Feature",
  "properties": {
    "addr:full": "1080 Nimitzview Dr Ste 400 Cincinnati OH 45230",
    "addr:housenumber": "1080",
    "addr:postcode": "45230",
    "addr:street": "Nimitzview Dr Ste 400",
    "iso:country": "US",
    "sg:address": "1080 Nimitzview Dr Ste 400",
    "sg:city": "Cincinnati",
    "sg:classifiers": [
      {
        "category": "Professional",
        "subcategory": "Accounting \u0026 Tax Preparation",
        "type": "Services"
      }
    ],
    "sg:phone": "+1 513 624 6136",
    "sg:postcode": "45230",
    "sg:province": "OH",
    "sg:tags": [
      "accountant"
    ],
    "wof:name": "Zimmerman \u0026 Co Cpas Inc",
    "wof:placetype": "venue"
  },
  "geometry": {"coordinates":[-84.352997,39.069401],"type":"Point"}
}
