{
  "type": "Feature",
  "properties": {
    "addr:full": "342 S Hampton Rd Columbus OH 43213",
    "addr:housenumber": "342",
    "addr:postcode": "43213",
    "addr:street": "S Hampton Rd",
    "iso:country": "US",
    "sg:address": "342 S Hampton Rd",
    "sg:city": "Columbus",
    "sg:classifiers": [
      {
        "category": "Professional",
        "type": "Services"
      }
    ],
    "sg:phone": "+1 614 235 5855",
    "sg:postcode": "43213",
    "sg:province": "OH",
    "sg:tags": [
      "hair",
      "accessory",
      "supply"
    ],
    "wof:name": "Bettie A Niarchos",
    "wof:placetype": "venue"
  },
  "geometry": {"coordinates":[-82.909993,39.964598],"type":"Point"}
}
