{
  "type": "Feature",
  "properties": {
    "iso:country":"US",
    "sg:address":"217 E 3rd St",
    "sg:city":"Uhrichsville",
    "sg:classifiers":[
        {
            "category":"Organizations",
            "subcategory":"Religious Organization",
            "type":"Services"
        }
    ],
    "sg:phone":"+1 740 922 2752",
    "sg:postcode":"44683",
    "sg:province":"OH",
    "sg:tags":[
        "church"
    ],
    "wof:name":"Christian Fellowship",
    "wof:placetype":"venue"
},
  "geometry": {"coordinates":[-81.34372,40.391464],"type":"Point"}
}