{
  "type": "Feature",
  "properties": {
    "iso:country":"US",
    "sg:address":"1618 Bechtle Ave",
    "sg:city":"Springfield",
    "sg:classifiers":[
        {
            "category":"Personal",
            "type":"Services"
        }
    ],
    "sg:phone":"+1 937 325 3800",
    "sg:postcode":"45504",
    "sg:province":"OH",
    "sg:tags":[
        "control",
        "weight"
    ],
    "wof:name":"L A Weight Loss Ctr",
    "wof:placetype":"venue"
},
  "geometry": {"coordinates":[-83.835561,39.942535],"type":"Point"}
}