{
  "type": "Feature",
  "properties": {
    "addr:full":"6605 Angola Rd Holland OH 43528",
    "addr:housenumber":"6605",
    "addr:postcode":"43528",
    "addr:street":"Angola Rd",
    "iso:country":"US",
    "sg:address":"6605 Angola Rd",
    "sg:city":"Holland",
    "sg:classifiers":[
        {
            "category":"Organizations",
            "subcategory":"Religious Organization",
            "type":"Services"
        }
    ],
    "sg:phone":"+1 419 865 4640",
    "sg:postcode":"43528",
    "sg:province":"OH",
    "sg:tags":[
        "church"
    ],
    "sg:website":"www.hollandfmc.org",
    "wof:name":"Holland Free Methodist Church",
    "wof:placetype":"venue"
},
  "geometry": {"coordinates":[-83.70013,41.624569],"type":"Point"}
}