{
  "type": "Feature",
  "properties": {
    "addr:full": "5886 Cheviot Rd Cincinnati OH 45247",
    "addr:housenumber": "5886",
    "addr:postcode": "45247",
    "addr:street": "Cheviot Rd",
    "iso:country": "US",
    "sg:address": "5886 Cheviot Rd",
    "sg:city": "Cincinnati",
    "sg:classifiers": [
      {
        "category": "Health Services",
        "subcategory": "Doctor",
        "type": "Services"
      }
    ],
    "sg:phone": "+1 513 385 0718",
    "sg:postcode": "45247",
    "sg:province": "OH",
    "sg:tags": [
      "dentist"
    ],
    "wof:name": "Konrad Omeltschenko DDS",
    "wof:placetype": "venue"
  },
  "geometry": {"coordinates":[-84.600659,39.200409],"type":"Point"}
}
