{
  "type": "Feature",
  "properties": {
    "addr:full": "15 W 4th St Dayton OH 45402",
    "addr:housenumber": "15",
    "addr:postcode": "45402",
    "addr:street": "W 4Th St",
    "iso:country": "US",
    "sg:address": "15 W 4th St",
    "sg:city": "Dayton",
    "sg:classifiers": [
      {
        "category": "Health Services",
        "subcategory": "Clinic",
        "type": "Services"
      }
    ],
    "sg:phone": "+1 937 461 2437",
    "sg:postcode": "45402",
    "sg:province": "OH",
    "sg:tags": [
      "aids",
      "testing",
      "information"
    ],
    "sg:website": "www.arcohio.org",
    "wof:name": "AIDS Resource Ctr Ohio",
    "wof:placetype": "venue"
  },
  "geometry": {"coordinates":[-84.193071,39.757939],"type":"Point"}
}
