{
  "type": "Feature",
  "properties": {
    "addr:full": "2710 Sawbury Blvd Columbus OH 43235",
    "addr:housenumber": "2710",
    "addr:postcode": "43235",
    "addr:street": "Sawbury Blvd",
    "iso:country": "US",
    "sg:address": "2710 Sawbury Blvd",
    "sg:city": "Columbus",
    "sg:classifiers": [
      {
        "category": "Banks \u0026 Credit Unions",
        "subcategory": "Bank",
        "type": "Services"
      }
    ],
    "sg:phone": "+1 614 874 4004",
    "sg:postcode": "43235",
    "sg:province": "OH",
    "sg:tags": [
      "loan",
      "real estate"
    ],
    "wof:name": "Advantage Mortgage",
    "wof:placetype": "venue"
  },
  "geometry": {"coordinates":[-83.08892,40.114215],"type":"Point"}
}
