{
  "type": "Feature",
  "properties": {
    "iso:country":"US",
    "sg:address":"2710 Sawbury Blvd",
    "sg:city":"Columbus",
    "sg:classifiers":[
        {
            "category":"Banks & Credit Unions",
            "subcategory":"Bank",
            "type":"Services"
        }
    ],
    "sg:phone":"+1 614 874 4004",
    "sg:postcode":"43235",
    "sg:province":"OH",
    "sg:tags":[
        "loan",
        "real estate"
    ],
    "wof:name":"Advantage Mortgage",
    "wof:placetype":"venue"
},
  "geometry": {"coordinates":[-83.08892,40.114215],"type":"Point"}
}