{
  "type": "Feature",
  "properties": {
    "iso:country":"US",
    "sg:address":"5900 Sawmill Rd",
    "sg:city":"Dublin",
    "sg:classifiers":[
        {
            "category":"Banks & Credit Unions",
            "subcategory":"Bank",
            "type":"Services"
        }
    ],
    "sg:phone":"+1 614 760 0750",
    "sg:postcode":"43017",
    "sg:province":"OH",
    "sg:tags":[
        "correspondent",
        "banker",
        "mortgage"
    ],
    "wof:name":"American Fidelity Mortgage Svc",
    "wof:placetype":"venue"
},
  "geometry": {"coordinates":[-83.0919,40.088476],"type":"Point"}
}