{
  "type": "Feature",
  "properties": {
    "iso:country":"US",
    "sg:address":"1436 Triplett Blvd",
    "sg:city":"Akron",
    "sg:classifiers":[
        {
            "category":"Government",
            "subcategory":"Office",
            "type":"Public Place"
        }
    ],
    "sg:phone":"+1 330 375 2841",
    "sg:postcode":"44306",
    "sg:province":"OH",
    "sg:tags":[
        "park",
        "maintenance"
    ],
    "wof:name":"Parks Maintenance",
    "wof:placetype":"venue"
},
  "geometry": {"coordinates":[-81.472313,41.042545],"type":"Point"}
}