{
  "type": "Feature",
  "properties": {
    "iso:country":"US",
    "sg:address":"7110 State Rd",
    "sg:city":"Somerville",
    "sg:classifiers":[
        {
            "category":"Farming",
            "subcategory":"Dairy Farm",
            "type":"Manufacturing & Wholesale Goods"
        }
    ],
    "sg:phone":"+1 513 726 6560",
    "sg:postcode":"45064",
    "sg:province":"OH",
    "wof:name":"Thomas Bulach",
    "wof:placetype":"venue"
},
  "geometry": {"coordinates":[-84.60087,39.565525],"type":"Point"}
}