{
  "type": "Feature",
  "properties": {
    "iso:country":"US",
    "sg:address":"3050 Mack Rd",
    "sg:city":"Fairfield",
    "sg:classifiers":[
        {
            "category":"Health Services",
            "subcategory":"Health Practitioner",
            "type":"Services"
        },
        {
            "category":"Shopping",
            "subcategory":"Gifts & Souvenirs",
            "type":"Retail Goods"
        }
    ],
    "sg:phone":"+1 513 870 7878",
    "sg:postcode":"45014",
    "sg:province":"OH",
    "sg:tags":[
        "therapist",
        "physical"
    ],
    "sg:website":"www.emercy.com",
    "wof:name":"Mercy Health Partners Rehab",
    "wof:placetype":"venue"
},
  "geometry": {"coordinates":[-84.51765399999999,39.31128],"type":"Point"}
}