{
  "type": "Feature",
  "properties": {
    "addr:full": "2232 8th St NW Canton OH 44708",
    "addr:housenumber": "2232",
    "addr:postcode": "44708",
    "addr:street": "8Th St Nw",
    "iso:country": "US",
    "sg:address": "2232 8th St NW",
    "sg:city": "Canton",
    "sg:classifiers": [
      {
        "category": "Wholesale",
        "subcategory": "Toys \u0026 Hobbies",
        "type": "Manufacturing \u0026 Wholesale Goods"
      }
    ],
    "sg:phone": "+1 330 456 4754",
    "sg:postcode": "44708",
    "sg:province": "OH",
    "sg:tags": [
      "wholesaler"
    ],
    "wof:name": "SJA Wholesale",
    "wof:placetype": "venue"
  },
  "geometry": {"coordinates":[-81.398839,40.805578],"type":"Point"}
}
