{
  "type": "Feature",
  "properties": {
    "addr:full": "30479 State Rte 172 Hanoverton OH 44423",
    "addr:housenumber": "30479",
    "addr:postcode": "44423",
    "addr:street": "State Rte 172",
    "iso:country": "US",
    "sg:address": "30479 State Rte 172",
    "sg:city": "Hanoverton",
    "sg:classifiers": [
      {
        "category": "Restaurant",
        "type": "Food \u0026 Drink"
      }
    ],
    "sg:phone": "+1 330 223 1329",
    "sg:postcode": "44423",
    "sg:province": "OH",
    "sg:tags": [
      "eating"
    ],
    "wof:name": "Pinkys Lounge",
    "wof:placetype": "venue"
  },
  "geometry": {"coordinates":[-80.930764,40.795459],"type":"Point"}
}
