{
  "type": "Feature",
  "properties": {
    "iso:country":"US",
    "sg:address":"6670 State Rte 128",
    "sg:city":"Miamitown",
    "sg:classifiers":[
        {
            "category":"Organizations",
            "subcategory":"Religious Organization",
            "type":"Services"
        }
    ],
    "sg:phone":"+1 513 353 2226",
    "sg:postcode":"45041",
    "sg:province":"OH",
    "sg:tags":[
        "church"
    ],
    "sg:website":"www.miamitowncc.com",
    "wof:name":"Miamitown Church Of Christ",
    "wof:placetype":"venue"
},
  "geometry": {"coordinates":[-84.70471499999999,39.213472],"type":"Point"}
}