{
  "type": "Feature",
  "properties": {
    "addr:full":"1034 Bellefontaine Ave Lima OH 45804",
    "addr:housenumber":"1034",
    "addr:postcode":"45804",
    "addr:street":"Bellefontaine Ave",
    "iso:country":"US",
    "sg:address":"1034 Bellefontaine Ave",
    "sg:city":"Lima",
    "sg:classifiers":[
        {
            "category":"Autos & Motor Vehicles",
            "subcategory":"Auto Supplies",
            "type":"Retail Goods"
        }
    ],
    "sg:phone":"+1 419 228 1441",
    "sg:postcode":"45804",
    "sg:province":"OH",
    "sg:tags":[
        "automobile",
        "parts"
    ],
    "sg:website":"www.autozone.com",
    "wof:name":"Autozone",
    "wof:placetype":"venue"
},
  "geometry": {"coordinates":[-84.085909,40.734434],"type":"Point"}
}