{
  "type": "Feature",
  "properties": {
    "addr:full": "289 Elm St Youngstown OH 44503",
    "addr:housenumber": "289",
    "addr:postcode": "44503",
    "addr:street": "Elm St",
    "iso:country": "US",
    "sg:address": "289 Elm St",
    "sg:city": "Youngstown",
    "sg:classifiers": [
      {
        "category": "Health Services",
        "subcategory": "Doctor",
        "type": "Services"
      }
    ],
    "sg:phone": "+1 330 750 9444",
    "sg:postcode": "44503",
    "sg:province": "OH",
    "sg:tags": [
      "physician",
      "surgeon"
    ],
    "wof:name": "Charles E Wagner Jr Inc",
    "wof:placetype": "venue"
  },
  "geometry": {"coordinates":[-80.650875,41.103249],"type":"Point"}
}
