{
  "type": "Feature",
  "properties": {
    "addr:full": "52 N Diamond St Mansfield OH 44902",
    "addr:housenumber": "52",
    "addr:postcode": "44902",
    "addr:street": "N Diamond St",
    "iso:country": "US",
    "sg:address": "52 N Diamond St",
    "sg:city": "Mansfield",
    "sg:classifiers": [
      {
        "category": "Professional",
        "subcategory": "Engineering",
        "type": "Services"
      }
    ],
    "sg:phone": "+1 419 525 0093",
    "sg:postcode": "44902",
    "sg:province": "OH",
    "sg:tags": [
      "engineer"
    ],
    "sg:website": "www.kemccartney.com",
    "wof:name": "K E Mc Cartney \u0026 Associates",
    "wof:placetype": "venue"
  },
  "geometry": {"coordinates":[-82.513871,40.760219],"type":"Point"}
}
