{
  "type": "Feature",
  "properties": {
    "iso:country":"US",
    "sg:address":"52 N Diamond St",
    "sg:city":"Mansfield",
    "sg:classifiers":[
        {
            "category":"Professional",
            "subcategory":"Engineering",
            "type":"Services"
        }
    ],
    "sg:phone":"+1 419 525 0093",
    "sg:postcode":"44902",
    "sg:province":"OH",
    "sg:tags":[
        "engineer"
    ],
    "sg:website":"www.kemccartney.com",
    "wof:name":"K E Mc Cartney & Associates",
    "wof:placetype":"venue"
},
  "geometry": {"coordinates":[-82.51387099999999,40.760219],"type":"Point"}
}