{
  "type": "Feature",
  "properties": {
    "iso:country":"US",
    "sg:address":"8240 Stone Rd",
    "sg:city":"Medina",
    "sg:classifiers":[
        {
            "category":"Professional",
            "type":"Services"
        }
    ],
    "sg:phone":"+1 330 722 4019",
    "sg:postcode":"44256",
    "sg:province":"OH",
    "sg:tags":[
        "establishment"
    ],
    "wof:name":"Stawen",
    "wof:placetype":"venue"
},
  "geometry": {"coordinates":[-81.98355,41.15772],"type":"Point"}
}