{
  "type": "Feature",
  "properties": {
    "iso:country":"US",
    "sg:address":"1682 Michigan St",
    "sg:city":"Sidney",
    "sg:classifiers":[
        {
            "category":"Banks & Credit Unions",
            "subcategory":"Bank",
            "type":"Services"
        }
    ],
    "sg:phone":"+1 937 493 0244",
    "sg:postcode":"45365",
    "sg:province":"OH",
    "sg:tags":[
        "cashing",
        "check"
    ],
    "wof:name":"National Cash Advance",
    "wof:placetype":"venue"
},
  "geometry": {"coordinates":[-84.178877,40.287965],"type":"Point"}
}