{
  "type": "Feature",
  "properties": {
    "iso:country":"US",
    "sg:address":"1382 W 9th St",
    "sg:city":"Cleveland",
    "sg:classifiers":[
        {
            "category":"Restaurant",
            "type":"Food & Drink"
        }
    ],
    "sg:phone":"+1 440 250 8908",
    "sg:postcode":"44113",
    "sg:province":"OH",
    "sg:tags":[
        "eating"
    ],
    "wof:name":"Thanh Nhan",
    "wof:placetype":"venue"
},
  "geometry": {"coordinates":[-81.69895699999999,41.497097],"type":"Point"}
}