{
  "type": "Feature",
  "properties": {
    "addr:full":"1690 Lander Rd Cleveland OH 44124",
    "addr:housenumber":"1690",
    "addr:postcode":"44124",
    "addr:street":"Lander Rd",
    "iso:country":"US",
    "sg:address":"1690 Lander Rd",
    "sg:city":"Cleveland",
    "sg:classifiers":[
        {
            "category":"Social Services",
            "subcategory":"Child Care",
            "type":"Services"
        }
    ],
    "sg:phone":"+1 440 442 6444",
    "sg:postcode":"44124",
    "sg:province":"OH",
    "sg:tags":[
        "day"
    ],
    "wof:name":"Visions For Children",
    "wof:placetype":"venue"
},
  "geometry": {"coordinates":[-81.463319,41.515109],"type":"Point"}
}