{
  "type": "Feature",
  "properties": {
    "iso:country":"US",
    "sg:address":"125 Executive Dr",
    "sg:city":"Marion",
    "sg:classifiers":[
        {
            "category":"Health Services",
            "subcategory":"Doctor",
            "type":"Services"
        }
    ],
    "sg:phone":"+1 740 387 5200",
    "sg:postcode":"43302",
    "sg:province":"OH",
    "sg:tags":[
        "physician",
        "surgeon"
    ],
    "wof:name":"Marion Dermatology Ctr Inc",
    "wof:placetype":"venue"
},
  "geometry": {"coordinates":[-83.12497500000001,40.570495],"type":"Point"}
}