{
  "type": "Feature",
  "properties": {
    "iso:country":"US",
    "sg:address":"19105 Rashell Dr",
    "sg:city":"Bedford",
    "sg:classifiers":[
        {
            "category":"Insurance",
            "subcategory":"Insurance Agent",
            "type":"Services"
        }
    ],
    "sg:phone":"+1 216 765 1688",
    "sg:postcode":"44146",
    "sg:province":"OH",
    "wof:name":"Carl F Dill Insurance Age",
    "wof:placetype":"venue"
},
  "geometry": {"coordinates":[-81.53282,41.352642],"type":"Point"}
}