{
  "type": "Feature",
  "properties": {
    "addr:full":"7800 W Salem Rd West Salem OH 44287",
    "addr:housenumber":"7800",
    "addr:postcode":"44287",
    "addr:street":"W Salem Rd",
    "iso:country":"US",
    "sg:address":"7800 W Salem Rd",
    "sg:city":"West Salem",
    "sg:classifiers":[
        {
            "category":"Building & Trades",
            "subcategory":"Construction",
            "type":"Services"
        }
    ],
    "sg:phone":"+1 419 853 4496",
    "sg:postcode":"44287",
    "sg:province":"OH",
    "sg:tags":[
        "siding",
        "contractor"
    ],
    "wof:name":"S & S Precision Siding",
    "wof:placetype":"venue"
},
  "geometry": {"coordinates":[-82.063363,40.990841],"type":"Point"}
}