{
  "type": "Feature",
  "properties": {
    "addr:full":"755 Boardman Canfield Rd Youngstown OH 44512",
    "addr:housenumber":"755",
    "addr:postcode":"44512",
    "addr:street":"Boardman Canfield Rd",
    "iso:country":"US",
    "sg:address":"755 Boardman Canfield Rd",
    "sg:city":"Youngstown",
    "sg:classifiers":[
        {
            "category":"Health Services",
            "subcategory":"Doctor",
            "type":"Services"
        }
    ],
    "sg:phone":"+1 330 726 1766",
    "sg:postcode":"44512",
    "sg:province":"OH",
    "sg:tags":[
        "physician",
        "surgeon"
    ],
    "wof:name":"Circulatory Center",
    "wof:placetype":"venue"
},
  "geometry": {"coordinates":[-80.68386,41.024436],"type":"Point"}
}