{
  "type": "Feature",
  "properties": {
    "iso:country":"US",
    "sg:address":"514 McManness Ave",
    "sg:city":"Findlay",
    "sg:classifiers":[
        {
            "category":"Banks & Credit Unions",
            "subcategory":"Bank",
            "type":"Services"
        }
    ],
    "sg:phone":"+1 419 424 0625",
    "sg:postcode":"45840",
    "sg:province":"OH",
    "sg:tags":[
        "broker",
        "mortgage"
    ],
    "wof:name":"Chester & Co Inc",
    "wof:placetype":"venue"
},
  "geometry": {"coordinates":[-83.63269699999999,41.048095],"type":"Point"}
}