{
  "type": "Feature",
  "properties": {
    "addr:full": "514 McManness Ave Findlay OH 45840",
    "addr:housenumber": "514",
    "addr:postcode": "45840",
    "addr:street": "Mcmanness Ave",
    "iso:country": "US",
    "sg:address": "514 McManness Ave",
    "sg:city": "Findlay",
    "sg:classifiers": [
      {
        "category": "Banks \u0026 Credit Unions",
        "subcategory": "Bank",
        "type": "Services"
      }
    ],
    "sg:phone": "+1 419 424 0625",
    "sg:postcode": "45840",
    "sg:province": "OH",
    "sg:tags": [
      "broker",
      "mortgage"
    ],
    "wof:name": "Chester \u0026 Co Inc",
    "wof:placetype": "venue"
  },
  "geometry": {"coordinates":[-83.632697,41.048095],"type":"Point"}
}
