{
  "type": "Feature",
  "properties": {
    "iso:country":"US",
    "sg:address":"2600 W Jefferson Kiousville Rd",
    "sg:city":"West Jefferson",
    "sg:classifiers":[
        {
            "category":"Retail",
            "subcategory":"Repair Shop",
            "type":"Services"
        }
    ],
    "sg:phone":"+1 614 879 9700",
    "sg:postcode":"43162",
    "sg:province":"OH",
    "sg:tags":[
        "related"
    ],
    "wof:name":"Ken & Sons Gas & Water Repair",
    "wof:placetype":"venue"
},
  "geometry": {"coordinates":[-83.285329,39.896564],"type":"Point"}
}