{
  "type": "Feature",
  "properties": {
    "addr:full": "3406 Beechwood Ave Cleveland OH 44118",
    "addr:housenumber": "3406",
    "addr:postcode": "44118",
    "addr:street": "Beechwood Ave",
    "iso:country": "US",
    "sg:address": "3406 Beechwood Ave",
    "sg:city": "Cleveland",
    "sg:classifiers": [
      {
        "category": "Shopping",
        "subcategory": "Hobbies, Toys, \u0026 Games",
        "type": "Retail Goods"
      }
    ],
    "sg:phone": "+1 216 320 1234",
    "sg:postcode": "44118",
    "sg:province": "OH",
    "wof:name": "Creating Keepsakes Magazine",
    "wof:placetype": "venue"
  },
  "geometry": {"coordinates":[-81.556596,41.512362],"type":"Point"}
}
