{
  "type": "Feature",
  "properties": {
    "addr:full": "113 E Kiracofe Ave Elida OH 45807",
    "addr:housenumber": "113",
    "addr:postcode": "45807",
    "addr:street": "E Kiracofe Ave",
    "iso:country": "US",
    "sg:address": "113 E Kiracofe Ave",
    "sg:city": "Elida",
    "sg:classifiers": [
      {
        "category": "Insurance",
        "subcategory": "Insurance Agent",
        "type": "Services"
      }
    ],
    "sg:phone": "+1 419 339 1504",
    "sg:postcode": "45807",
    "sg:province": "OH",
    "wof:name": "Wolfenbarger Insurance",
    "wof:placetype": "venue"
  },
  "geometry": {"coordinates":[-84.201936,40.786458],"type":"Point"}
}
