{
  "type": "Feature",
  "properties": {
    "addr:full": "343 3rd St SW Sugarcreek OH 44681",
    "addr:housenumber": "343",
    "addr:postcode": "44681",
    "addr:street": "3Rd St Sw",
    "iso:country": "US",
    "sg:address": "343 3rd St SW",
    "sg:city": "Sugarcreek",
    "sg:classifiers": [
      {
        "category": "Food \u0026 Beverages",
        "subcategory": "Candy",
        "type": "Retail Goods"
      }
    ],
    "sg:phone": "+1 330 852 1109",
    "sg:postcode": "44681",
    "sg:province": "OH",
    "sg:tags": [
      "confectionery"
    ],
    "wof:name": "Candy Bouquet",
    "wof:placetype": "venue"
  },
  "geometry": {"coordinates":[-81.64514,40.501973],"type":"Point"}
}
