{
  "type": "Feature",
  "properties": {
    "addr:full": "100 Lake Forest Dr Hudson OH 44236",
    "addr:housenumber": "100",
    "addr:postcode": "44236",
    "addr:street": "Lake Forest Dr",
    "iso:country": "US",
    "sg:address": "100 Lake Forest Dr",
    "sg:city": "Hudson",
    "sg:classifiers": [
      {
        "category": "Recreation",
        "type": "Entertainment"
      },
      {
        "category": "Organizations",
        "subcategory": "Community Association",
        "type": "Services"
      }
    ],
    "sg:phone": "+1 330 656 3804",
    "sg:postcode": "44236",
    "sg:province": "OH",
    "sg:tags": [
      "club",
      "membership"
    ],
    "sg:website": "www.lakeforestcc.org",
    "wof:name": "Lake Forest Country Club Pro",
    "wof:placetype": "venue"
  },
  "geometry": {"coordinates":[-81.468994,41.248977],"type":"Point"}
}
