{
  "type": "Feature",
  "properties": {
    "addr:full": "2801 W Bancroft St Toledo OH 43606",
    "addr:housenumber": "2801",
    "addr:postcode": "43606",
    "addr:street": "W Bancroft St",
    "iso:country": "US",
    "sg:address": "2801 W Bancroft St",
    "sg:city": "Toledo",
    "sg:classifiers": [
      {
        "category": "Social Services",
        "subcategory": "Child Care",
        "type": "Services"
      }
    ],
    "sg:phone": "+1 419 530 1070",
    "sg:postcode": "43606",
    "sg:province": "OH",
    "sg:tags": [
      "day"
    ],
    "wof:name": "Apple Tree Nrsry School",
    "wof:placetype": "venue"
  },
  "geometry": {"coordinates":[-83.611671,41.663033],"type":"Point"}
}
