{
  "type": "Feature",
  "properties": {
    "addr:full": "2940 Maple Ave Zanesville OH 43701",
    "addr:housenumber": "2940",
    "addr:postcode": "43701",
    "addr:street": "Maple Ave",
    "iso:country": "US",
    "sg:address": "2940 Maple Ave",
    "sg:city": "Zanesville",
    "sg:classifiers": [
      {
        "category": "Restaurant",
        "type": "Food \u0026 Drink"
      }
    ],
    "sg:phone": "+1 740 452 2222",
    "sg:postcode": "43701",
    "sg:province": "OH",
    "wof:name": "Wally's Old Fashion Pizza",
    "wof:placetype": "venue"
  },
  "geometry": {"coordinates":[-82.014657,39.976095],"type":"Point"}
}
