{
  "type": "Feature",
  "properties": {
    "iso:country":"US",
    "sg:address":"515 Steubenville Rd SE",
    "sg:city":"Carrollton",
    "sg:classifiers":[
        {
            "category":"Organizations",
            "subcategory":"Religious Organization",
            "type":"Services"
        }
    ],
    "sg:phone":"+1 330 627 7525",
    "sg:postcode":"44615",
    "sg:province":"OH",
    "wof:name":"Jehovahs Witnesses",
    "wof:placetype":"venue"
},
  "geometry": {"coordinates":[-81.068008,40.564248],"type":"Point"}
}