{
  "type": "Feature",
  "properties": {
    "addr:full": "515 Steubenville Rd SE Carrollton OH 44615",
    "addr:housenumber": "515",
    "addr:postcode": "44615",
    "addr:street": "Steubenville Rd Se",
    "iso:country": "US",
    "sg:address": "515 Steubenville Rd SE",
    "sg:city": "Carrollton",
    "sg:classifiers": [
      {
        "category": "Organizations",
        "subcategory": "Religious Organization",
        "type": "Services"
      }
    ],
    "sg:phone": "+1 330 627 7525",
    "sg:postcode": "44615",
    "sg:province": "OH",
    "wof:name": "Jehovahs Witnesses",
    "wof:placetype": "venue"
  },
  "geometry": {"coordinates":[-81.068008,40.564248],"type":"Point"}
}
