{
  "type": "Feature",
  "properties": {
    "addr:full": "468 Karen Dr Chardon OH 44024",
    "addr:housenumber": "468",
    "addr:postcode": "44024",
    "addr:street": "Karen Dr",
    "iso:country": "US",
    "sg:address": "468 Karen Dr",
    "sg:city": "Chardon",
    "sg:classifiers": [
      {
        "category": "Building \u0026 Trades",
        "subcategory": "Construction",
        "type": "Services"
      }
    ],
    "sg:phone": "+1 440 285 2308",
    "sg:postcode": "44024",
    "sg:province": "OH",
    "sg:tags": [
      "home",
      "builder"
    ],
    "wof:name": "Watson Homes LLC",
    "wof:placetype": "venue"
  },
  "geometry": {"coordinates":[-81.196123,41.574273],"type":"Point"}
}
