{
  "type": "Feature",
  "properties": {
    "iso:country":"US",
    "sg:address":"16625 Royalton Rd",
    "sg:city":"Strongsville",
    "sg:classifiers":[
        {
            "category":"Restaurant",
            "type":"Food & Drink"
        }
    ],
    "sg:menulink":"http://www.allmenus.com/oh/strongsville/134218-subway/menu/",
    "sg:phone":"+1 440 238 8455",
    "sg:postcode":"44136",
    "sg:province":"OH",
    "sg:tags":[
        "american",
        "sandwich"
    ],
    "wof:name":"Subway",
    "wof:placetype":"venue"
},
  "geometry": {"coordinates":[-81.815833,41.312567],"type":"Point"}
}