{
  "type": "Feature",
  "properties": {
    "addr:full": "6606 Buckingham Pl Cincinnati OH 45227",
    "addr:housenumber": "6606",
    "addr:postcode": "45227",
    "addr:street": "Buckingham Pl",
    "iso:country": "US",
    "sg:address": "6606 Buckingham Pl",
    "sg:city": "Cincinnati",
    "sg:classifiers": [
      {
        "category": "Retail",
        "subcategory": "Repair Shop",
        "type": "Services"
      }
    ],
    "sg:phone": "+1 513 271 6175",
    "sg:postcode": "45227",
    "sg:province": "OH",
    "sg:tags": [
      "lock",
      "locksmith"
    ],
    "wof:name": "Ron's Lock \u0026 Key Svc",
    "wof:placetype": "venue"
  },
  "geometry": {"coordinates":[-84.38438,39.155976],"type":"Point"}
}
