{
  "type": "Feature",
  "properties": {
    "iso:country":"US",
    "sg:address":"4130 W Enon Dr",
    "sg:city":"Enon",
    "sg:classifiers":[
        {
            "category":"Freight",
            "type":"Transportation"
        }
    ],
    "sg:phone":"+1 937 864 0565",
    "sg:postcode":"45323",
    "sg:province":"OH",
    "sg:tags":[
        "operator",
        "trucking"
    ],
    "wof:name":"AAA Express",
    "wof:placetype":"venue"
},
  "geometry": {"coordinates":[-83.95111300000001,39.869573],"type":"Point"}
}