{
  "type": "Feature",
  "properties": {
    "addr:full": "4130 W Enon Dr Enon OH 45323",
    "addr:housenumber": "4130",
    "addr:postcode": "45323",
    "addr:street": "W Enon Dr",
    "iso:country": "US",
    "sg:address": "4130 W Enon Dr",
    "sg:city": "Enon",
    "sg:classifiers": [
      {
        "category": "Freight",
        "type": "Transportation"
      }
    ],
    "sg:phone": "+1 937 864 0565",
    "sg:postcode": "45323",
    "sg:province": "OH",
    "sg:tags": [
      "operator",
      "trucking"
    ],
    "wof:name": "AAA Express",
    "wof:placetype": "venue"
  },
  "geometry": {"coordinates":[-83.951113,39.869573],"type":"Point"}
}
