{
  "type": "Feature",
  "properties": {
    "addr:full":"8295 Twp Rd 95 Findlay OH 45840",
    "addr:housenumber":"95",
    "addr:postcode":"8295;45840",
    "addr:street":"Twp Rd",
    "iso:country":"US",
    "sg:address":"8295 Twp Rd 95",
    "sg:city":"Findlay",
    "sg:classifiers":[
        {
            "category":"Organizations",
            "subcategory":"Religious Organization",
            "type":"Services"
        }
    ],
    "sg:phone":"+1 419 422 5495",
    "sg:postcode":"45840",
    "sg:province":"OH",
    "sg:tags":[
        "church"
    ],
    "wof:name":"Van Buren Primitive Bapt Chr",
    "wof:placetype":"venue"
},
  "geometry": {"coordinates":[-83.713168,41.073051],"type":"Point"}
}