{
  "type": "Feature",
  "properties": {
    "addr:full": "71 Terrace St Struthers OH 44471",
    "addr:housenumber": "71",
    "addr:postcode": "44471",
    "addr:street": "Terrace St",
    "iso:country": "US",
    "sg:address": "71 Terrace St",
    "sg:city": "Struthers",
    "sg:classifiers": [
      {
        "category": "Professional",
        "subcategory": "Computer Services",
        "type": "Services"
      }
    ],
    "sg:phone": "+1 330 750 0286",
    "sg:postcode": "44471",
    "sg:province": "OH",
    "sg:tags": [
      "home",
      "consulting",
      "page",
      "dev",
      "internet"
    ],
    "wof:name": "Executive Web Management",
    "wof:placetype": "venue"
  },
  "geometry": {"coordinates":[-80.591271,41.056576],"type":"Point"}
}
