{
  "type": "Feature",
  "properties": {
    "addr:full": "1515 State Rte 28 Loveland OH 45140",
    "addr:housenumber": "1515",
    "addr:postcode": "45140",
    "addr:street": "State Rte 28",
    "iso:country": "US",
    "sg:address": "1515 State Rte 28",
    "sg:city": "Loveland",
    "sg:classifiers": [
      {
        "category": "Personal",
        "subcategory": "Beauty Salon",
        "type": "Services"
      }
    ],
    "sg:phone": "+1 513 575 9516",
    "sg:postcode": "45140",
    "sg:province": "OH",
    "sg:tags": [
      "shop"
    ],
    "wof:name": "Amenities Hair Salon",
    "wof:placetype": "venue"
  },
  "geometry": {"coordinates":[-84.201277,39.214543],"type":"Point"}
}
