{
  "type": "Feature",
  "properties": {
    "iso:country":"US",
    "sg:address":"464 N Wolf Creek St",
    "sg:city":"Brookville",
    "sg:classifiers":[
        {
            "category":"Building & Trades",
            "subcategory":"Construction",
            "type":"Services"
        }
    ],
    "sg:phone":"+1 937 222 3200",
    "sg:postcode":"45309",
    "sg:province":"OH",
    "sg:tags":[
        "contractor"
    ],
    "wof:name":"Bath Creations",
    "wof:placetype":"venue"
},
  "geometry": {"coordinates":[-84.42151200000001,39.839357],"type":"Point"}
}