{
  "type": "Feature",
  "properties": {
    "addr:full": "464 N Wolf Creek St Brookville OH 45309",
    "addr:housenumber": "464",
    "addr:postcode": "45309",
    "addr:street": "N Wolf Creek St",
    "iso:country": "US",
    "sg:address": "464 N Wolf Creek St",
    "sg:city": "Brookville",
    "sg:classifiers": [
      {
        "category": "Building \u0026 Trades",
        "subcategory": "Construction",
        "type": "Services"
      }
    ],
    "sg:phone": "+1 937 222 3200",
    "sg:postcode": "45309",
    "sg:province": "OH",
    "sg:tags": [
      "contractor"
    ],
    "wof:name": "Bath Creations",
    "wof:placetype": "venue"
  },
  "geometry": {"coordinates":[-84.421512,39.839357],"type":"Point"}
}
