{
  "type": "Feature",
  "properties": {
    "iso:country":"US",
    "sg:address":"3150 Springboro Rd",
    "sg:city":"Dayton",
    "sg:classifiers":[
        {
            "category":"Government",
            "subcategory":"Office",
            "type":"Public Place"
        }
    ],
    "sg:phone":"+1 937 225 2852",
    "sg:postcode":"45439",
    "sg:province":"OH",
    "sg:tags":[
        "federal",
        "record",
        "storage"
    ],
    "wof:name":"Great Lakes Regional Center",
    "wof:placetype":"venue"
},
  "geometry": {"coordinates":[-84.217586,39.70739],"type":"Point"}
}