{
  "type": "Feature",
  "properties": {
    "addr:full": "4300 Shire Cove Rd Hilliard OH 43026",
    "addr:housenumber": "4300",
    "addr:postcode": "43026",
    "addr:street": "Shire Cove Rd",
    "iso:country": "US",
    "sg:address": "4300 Shire Cove Rd",
    "sg:city": "Hilliard",
    "sg:classifiers": [
      {
        "category": "Professional",
        "subcategory": "Computer Services",
        "type": "Services"
      }
    ],
    "sg:phone": "+1 614 313 0473",
    "sg:postcode": "43026",
    "sg:province": "OH",
    "sg:tags": [
      "custom"
    ],
    "wof:name": "Host Visions",
    "wof:placetype": "venue"
  },
  "geometry": {"coordinates":[-83.107833,40.05957],"type":"Point"}
}
