{
  "type": "Feature",
  "properties": {
    "addr:full":"6239 Millerstown-Eris Rd Urbana OH 43078",
    "addr:housenumber":"6239",
    "addr:postcode":"43078",
    "addr:street":"Millerstown-Eris Rd",
    "iso:country":"US",
    "sg:address":"6239 Millerstown-Eris Rd",
    "sg:city":"Urbana",
    "sg:classifiers":[
        {
            "category":"Government",
            "subcategory":"Office",
            "type":"Public Place"
        }
    ],
    "sg:phone":"+1 937 663 5202",
    "sg:postcode":"43078",
    "sg:province":"OH",
    "sg:tags":[
        "executive"
    ],
    "wof:name":"Concord Township Champaign",
    "wof:placetype":"venue"
},
  "geometry": {"coordinates":[-83.874768,40.155711],"type":"Point"}
}