{
  "type": "Feature",
  "properties": {
    "addr:full":"1914 Oakland Ave Portsmouth OH 45662",
    "addr:housenumber":"1914",
    "addr:postcode":"45662",
    "addr:street":"Oakland Ave",
    "iso:country":"US",
    "sg:address":"1914 Oakland Ave",
    "sg:city":"Portsmouth",
    "sg:classifiers":[
        {
            "category":"Building & Trades",
            "subcategory":"Pest Control",
            "type":"Services"
        }
    ],
    "sg:phone":"+1 740 354 3779",
    "sg:postcode":"45662",
    "sg:province":"OH",
    "wof:name":"AAA Exterminating",
    "wof:placetype":"venue"
},
  "geometry": {"coordinates":[-82.98570599999999,38.747275],"type":"Point"}
}