{
  "type": "Feature",
  "properties": {
    "addr:full":"5705 Blackhawk Forest Dr Westerville OH 43082",
    "addr:housenumber":"5705",
    "addr:postcode":"43082",
    "addr:street":"Blackhawk Forest Dr",
    "iso:country":"US",
    "sg:address":"5705 Blackhawk Forest Dr",
    "sg:city":"Westerville",
    "sg:classifiers":[
        {
            "category":"Local Transit",
            "type":"Transportation"
        }
    ],
    "sg:phone":"+1 614 882 0280",
    "sg:postcode":"43082",
    "sg:province":"OH",
    "sg:tags":[
        "limousine"
    ],
    "wof:name":"A Bella Limousine",
    "wof:placetype":"venue"
},
  "geometry": {"coordinates":[-82.917421,40.17278],"type":"Point"}
}