{
  "type": "Feature",
  "properties": {
    "iso:country":"US",
    "sg:address":"8500 Union Ave",
    "sg:city":"Cleveland",
    "sg:classifiers":[
        {
            "category":"Building & Trades",
            "subcategory":"Construction",
            "type":"Services"
        }
    ],
    "sg:phone":"+1 216 883 3000",
    "sg:postcode":"44105",
    "sg:province":"OH",
    "sg:tags":[
        "steel",
        "erection",
        "structural"
    ],
    "wof:name":"CMS -Kilroy Steel",
    "wof:placetype":"venue"
},
  "geometry": {"coordinates":[-81.629689,41.463367],"type":"Point"}
}