{
  "type": "Feature",
  "properties": {
    "addr:full": "6480 Twp Rd 294 West Liberty OH 43357",
    "addr:housenumber": "294",
    "addr:postcode": "6480;43357",
    "addr:street": "Twp Rd;West",
    "iso:country": "US",
    "sg:address": "6480 Twp Rd 294",
    "sg:city": "West Liberty",
    "sg:classifiers": [
      {
        "category": "Banks \u0026 Credit Unions",
        "subcategory": "Investment Brokerage",
        "type": "Services"
      }
    ],
    "sg:phone": "+1 937 465 0011",
    "sg:postcode": "43357",
    "sg:province": "OH",
    "wof:name": "DBS Investment Group Inc",
    "wof:placetype": "venue"
  },
  "geometry": {"coordinates":[-83.866475,40.255171],"type":"Point"}
}
