{
  "type": "Feature",
  "properties": {
    "addr:full":"4626 12th St SW Canton OH 44710",
    "addr:housenumber":"4626",
    "addr:postcode":"44710",
    "addr:street":"12Th St Sw",
    "iso:country":"US",
    "sg:address":"4626 12th St SW",
    "sg:city":"Canton",
    "sg:classifiers":[
        {
            "category":"Building & Trades",
            "subcategory":"Construction",
            "type":"Services"
        }
    ],
    "sg:phone":"+1 330 479 9170",
    "sg:postcode":"44710",
    "sg:province":"OH",
    "sg:tags":[
        "house"
    ],
    "wof:name":"Martin Krueger Construction",
    "wof:placetype":"venue"
},
  "geometry": {"coordinates":[-81.431449,40.790686],"type":"Point"}
}