{
  "type": "Feature",
  "properties": {
    "iso:country":"US",
    "sg:address":"2110 Waterford Rd",
    "sg:city":"New Waterford",
    "sg:classifiers":[
        {
            "category":"Building & Trades",
            "subcategory":"Construction",
            "type":"Services"
        }
    ],
    "sg:phone":"+1 330 457 0683",
    "sg:postcode":"44445",
    "sg:province":"OH",
    "sg:tags":[
        "home",
        "family",
        "contractor"
    ],
    "wof:name":"Jones Construction",
    "wof:placetype":"venue"
},
  "geometry": {"coordinates":[-80.57471700000001,40.869557],"type":"Point"}
}