{
  "type": "Feature",
  "properties": {
    "addr:full": "1800 Marlboro Ave Obetz OH 43207",
    "addr:housenumber": "1800",
    "addr:postcode": "43207",
    "addr:street": "Marlboro Ave",
    "iso:country": "US",
    "sg:address": "1800 Marlboro Ave",
    "sg:city": "Obetz",
    "sg:classifiers": [
      {
        "category": "Personal",
        "subcategory": "Beauty Salon",
        "type": "Services"
      }
    ],
    "sg:phone": "+1 614 491 1717",
    "sg:postcode": "43207",
    "sg:province": "OH",
    "wof:name": "Chatter Box Beauty Salon",
    "wof:placetype": "venue"
  },
  "geometry": {"coordinates":[-82.953527,39.875841],"type":"Point"}
}
