{
  "type": "Feature",
  "properties": {
    "iso:country":"US",
    "sg:address":"1111 Superior Ave E",
    "sg:city":"Cleveland",
    "sg:classifiers":[
        {
            "category":"Real Estate",
            "subcategory":"Real Estate Agent",
            "type":"Services"
        }
    ],
    "sg:phone":"+1 216 241 3000",
    "sg:postcode":"44114",
    "sg:province":"OH",
    "wof:name":"Victor S Voinovich Co",
    "wof:placetype":"venue"
},
  "geometry": {"coordinates":[-81.687528,41.502644],"type":"Point"}
}