{
  "type": "Feature",
  "properties": {
    "addr:full": "4304 Old Scioto Trl Portsmouth OH 45662",
    "addr:housenumber": "4304",
    "addr:postcode": "45662",
    "addr:street": "Old Scioto Trl",
    "iso:country": "US",
    "sg:address": "4304 Old Scioto Trl",
    "sg:city": "Portsmouth",
    "sg:classifiers": [
      {
        "category": "Government",
        "subcategory": "Office",
        "type": "Public Place"
      }
    ],
    "sg:phone": "+1 614 354 8803",
    "sg:postcode": "45662",
    "sg:province": "OH",
    "sg:tags": [
      "program",
      "administrative"
    ],
    "wof:name": "Services For Visually Impaired",
    "wof:placetype": "venue"
  },
  "geometry": {"coordinates":[-82.983319,38.782028],"type":"Point"}
}
