{
  "type": "Feature",
  "properties": {
    "addr:full":"380 Waverly Ave Washington Ct Hs OH 43160",
    "addr:housenumber":"380",
    "addr:postcode":"43160",
    "addr:street":"Waverly Ave Washington Ct",
    "iso:country":"US",
    "sg:address":"380 Waverly Ave",
    "sg:city":"Washington Ct Hs",
    "sg:classifiers":[
        {
            "category":"Shopping",
            "type":"Retail Goods"
        }
    ],
    "sg:phone":"+1 740 333 7263",
    "sg:postcode":"43160",
    "sg:province":"OH",
    "sg:tags":[
        "picture",
        "frame"
    ],
    "wof:name":"Frazier Frames & Gallery",
    "wof:placetype":"venue"
},
  "geometry": {"coordinates":[-83.429948,39.519886],"type":"Point"}
}