{
  "type": "Feature",
  "properties": {
    "addr:full": "229 Turner Dr Chardon OH 44024",
    "addr:housenumber": "229",
    "addr:postcode": "44024",
    "addr:street": "Turner Dr",
    "iso:country": "US",
    "sg:address": "229 Turner Dr",
    "sg:city": "Chardon",
    "sg:classifiers": [
      {
        "category": "Building \u0026 Trades",
        "subcategory": "Construction",
        "type": "Services"
      }
    ],
    "sg:phone": "+1 440 286 4951",
    "sg:postcode": "44024",
    "sg:province": "OH",
    "sg:tags": [
      "carpentry",
      "contractor"
    ],
    "wof:name": "Custom Finish Carpentry",
    "wof:placetype": "venue"
  },
  "geometry": {"coordinates":[-81.170397,41.548069],"type":"Point"}
}
