{
  "type": "Feature",
  "properties": {
    "iso:country":"US",
    "sg:address":"1703 Macomber St",
    "sg:city":"Toledo",
    "sg:classifiers":[
        {
            "category":"Organizations",
            "subcategory":"Religious Organization",
            "type":"Services"
        }
    ],
    "sg:phone":"+1 419 475 4710",
    "sg:postcode":"43606",
    "sg:province":"OH",
    "sg:tags":[
        "church"
    ],
    "wof:name":"American Orthodox Church",
    "wof:placetype":"venue"
},
  "geometry": {"coordinates":[-83.58623900000001,41.665371],"type":"Point"}
}