{
  "type": "Feature",
  "properties": {
    "addr:full":"20614 Aurora Rd Cleveland OH 44146",
    "addr:housenumber":"20614",
    "addr:postcode":"44146",
    "addr:street":"Aurora Rd",
    "iso:country":"US",
    "sg:address":"20614 Aurora Rd",
    "sg:city":"Cleveland",
    "sg:classifiers":[
        {
            "category":"Retail",
            "subcategory":"Auto Repair",
            "type":"Services"
        }
    ],
    "sg:phone":"+1 216 518 0383",
    "sg:postcode":"44146",
    "sg:province":"OH",
    "sg:tags":[
        "body",
        "automobile",
        "painting"
    ],
    "wof:name":"Kumar Auto Body Works",
    "wof:placetype":"venue"
},
  "geometry": {"coordinates":[-81.53302100000001,41.426543],"type":"Point"}
}