{
  "type": "Feature",
  "properties": {
    "iso:country":"US",
    "sg:address":"1550 Welsh Hills Rd NE",
    "sg:city":"Granville",
    "sg:classifiers":[
        {
            "category":"Wholesale",
            "subcategory":"Chemicals & Plastics",
            "type":"Manufacturing & Wholesale Goods"
        }
    ],
    "sg:phone":"+1 740 587 2093",
    "sg:postcode":"43023",
    "sg:province":"OH",
    "wof:name":"Crecca & Associates",
    "wof:placetype":"venue"
},
  "geometry": {"coordinates":[-82.502937,40.080541],"type":"Point"}
}