{
  "type": "Feature",
  "properties": {
    "addr:full": "1550 Welsh Hills Rd NE Granville OH 43023",
    "addr:housenumber": "1550",
    "addr:postcode": "43023",
    "addr:street": "Welsh Hills Rd Ne",
    "iso:country": "US",
    "sg:address": "1550 Welsh Hills Rd NE",
    "sg:city": "Granville",
    "sg:classifiers": [
      {
        "category": "Wholesale",
        "subcategory": "Chemicals \u0026 Plastics",
        "type": "Manufacturing \u0026 Wholesale Goods"
      }
    ],
    "sg:phone": "+1 740 587 2093",
    "sg:postcode": "43023",
    "sg:province": "OH",
    "wof:name": "Crecca \u0026 Associates",
    "wof:placetype": "venue"
  },
  "geometry": {"coordinates":[-82.502937,40.080541],"type":"Point"}
}
