{
  "type": "Feature",
  "properties": {
    "addr:full": "1269 Marwood Dr Zanesville OH 43701",
    "addr:housenumber": "1269",
    "addr:postcode": "43701",
    "addr:street": "Marwood Dr",
    "iso:country": "US",
    "sg:address": "1269 Marwood Dr",
    "sg:city": "Zanesville",
    "sg:classifiers": [
      {
        "category": "Real Estate",
        "subcategory": "Real Estate Operator",
        "type": "Services"
      }
    ],
    "sg:phone": "+1 740 453 7189",
    "sg:postcode": "43701",
    "sg:province": "OH",
    "sg:tags": [
      "building",
      "nonresidential"
    ],
    "wof:name": "Pughs Properties",
    "wof:placetype": "venue"
  },
  "geometry": {"coordinates":[-82.019641,39.954326],"type":"Point"}
}
