{
  "type": "Feature",
  "properties": {
    "addr:full":"10417 Juniper Ct Strongsville OH 44136",
    "addr:housenumber":"10417",
    "addr:postcode":"44136",
    "addr:street":"Juniper Ct",
    "iso:country":"US",
    "sg:address":"10417 Juniper Ct",
    "sg:city":"Strongsville",
    "sg:classifiers":[
        {
            "category":"Professional",
            "type":"Services"
        }
    ],
    "sg:phone":"+1 440 572 4848",
    "sg:postcode":"44136",
    "sg:province":"OH",
    "wof:name":"Marc Moorman",
    "wof:placetype":"venue"
},
  "geometry": {"coordinates":[-81.79274700000001,41.335706],"type":"Point"}
}