{
  "type": "Feature",
  "properties": {
    "addr:full":"101 W Lima St Forest OH 45843",
    "addr:housenumber":"101",
    "addr:postcode":"45843",
    "addr:street":"W Lima St",
    "iso:country":"US",
    "sg:address":"101 W Lima St",
    "sg:city":"Forest",
    "sg:classifiers":[
        {
            "category":"Restaurant",
            "type":"Food & Drink"
        }
    ],
    "sg:phone":"+1 419 273 2831",
    "sg:postcode":"45843",
    "sg:province":"OH",
    "sg:tags":[
        "eating"
    ],
    "wof:name":"B & B Dairy Barn",
    "wof:placetype":"venue"
},
  "geometry": {"coordinates":[-83.513345,40.801758],"type":"Point"}
}