{
  "type": "Feature",
  "properties": {
    "iso:country":"US",
    "sg:address":"19640 Rd 16S",
    "sg:city":"Columbus Grove",
    "sg:classifiers":[
        {
            "category":"Retail",
            "subcategory":"Auto Repair",
            "type":"Services"
        }
    ],
    "sg:phone":"+1 419 646 3315",
    "sg:postcode":"45830",
    "sg:province":"OH",
    "sg:tags":[
        "truck"
    ],
    "wof:name":"Wilbur Williams Garage",
    "wof:placetype":"venue"
},
  "geometry": {"coordinates":[-84.171988,40.88971],"type":"Point"}
}