{
  "type": "Feature",
  "properties": {
    "iso:country":"US",
    "sg:address":"26800 Fargo Ave",
    "sg:city":"Cleveland",
    "sg:classifiers":[
        {
            "category":"Autos & Motor Vehicles",
            "subcategory":"Automobile Sales",
            "type":"Retail Goods"
        }
    ],
    "sg:phone":"+1 216 765 9601",
    "sg:postcode":"44146",
    "sg:province":"OH",
    "sg:tags":[
        "car",
        "dealer"
    ],
    "wof:name":"Shoey Enterprise",
    "wof:placetype":"venue"
},
  "geometry": {"coordinates":[-81.490889,41.418493],"type":"Point"}
}