{
  "type": "Feature",
  "properties": {
    "addr:full": "1633 Bradford St NW Warren OH 44485",
    "addr:housenumber": "1633",
    "addr:postcode": "44485",
    "addr:street": "Bradford St Nw",
    "iso:country": "US",
    "sg:address": "1633 Bradford St NW",
    "sg:city": "Warren",
    "sg:classifiers": [
      {
        "category": "Retail",
        "subcategory": "Repair Shop",
        "type": "Services"
      }
    ],
    "sg:phone": "+1 330 399 2479",
    "sg:postcode": "44485",
    "sg:province": "OH",
    "sg:tags": [
      "hardware"
    ],
    "wof:name": "Hinkles Home Electric",
    "wof:placetype": "venue"
  },
  "geometry": {"coordinates":[-80.844928,41.253394],"type":"Point"}
}
