{
  "type": "Feature",
  "properties": {
    "iso:country":"US",
    "sg:address":"420 E Broad St",
    "sg:city":"Pataskala",
    "sg:classifiers":[
        {
            "category":"Personal",
            "subcategory":"Beauty Salon",
            "type":"Services"
        }
    ],
    "sg:phone":"+1 740 964 6698",
    "sg:postcode":"43062",
    "sg:province":"OH",
    "sg:tags":[
        "manicuring"
    ],
    "wof:name":"Nails By Bry Jen",
    "wof:placetype":"venue"
},
  "geometry": {"coordinates":[-82.668368,40.004291],"type":"Point"}
}