{
  "type": "Feature",
  "properties": {
    "addr:full": "3341 Ninann Ct Cincinnati OH 45211",
    "addr:housenumber": "3341",
    "addr:postcode": "45211",
    "addr:street": "Ninann Ct",
    "iso:country": "US",
    "sg:address": "3341 Ninann Ct",
    "sg:city": "Cincinnati",
    "sg:classifiers": [
      {
        "category": "Professional",
        "type": "Services"
      }
    ],
    "sg:phone": "+1 513 661 5242",
    "sg:postcode": "45211",
    "sg:province": "OH",
    "wof:name": "Jag 864",
    "wof:placetype": "venue"
  },
  "geometry": {"coordinates":[-84.565963,39.144551],"type":"Point"}
}
