{
  "type": "Feature",
  "properties": {
    "addr:full": "993 S Main St Bowling Green OH 43402",
    "addr:housenumber": "993",
    "addr:postcode": "43402",
    "addr:street": "S Main St",
    "iso:country": "US",
    "sg:address": "993 S Main St",
    "sg:city": "Bowling Green",
    "sg:classifiers": [
      {
        "category": "Retail",
        "subcategory": "Self-service Laundry",
        "type": "Services"
      }
    ],
    "sg:phone": "+1 419 353 8826",
    "sg:postcode": "43402",
    "sg:province": "OH",
    "wof:name": "Southside Laundromat",
    "wof:placetype": "venue"
  },
  "geometry": {"coordinates":[-83.650361,41.359925],"type":"Point"}
}
