{
  "type": "Feature",
  "properties": {
    "addr:full":"8240 Beckett Park Dr Hamilton OH 45011",
    "addr:housenumber":"8240",
    "addr:postcode":"45011",
    "addr:street":"Beckett Park Dr",
    "iso:country":"US",
    "sg:address":"8240 Beckett Park Dr",
    "sg:city":"Hamilton",
    "sg:classifiers":[
        {
            "category":"Real Estate",
            "subcategory":"Real Estate Services",
            "type":"Services"
        }
    ],
    "sg:phone":"+1 513 942 2074",
    "sg:postcode":"45011",
    "sg:province":"OH",
    "sg:tags":[
        "company",
        "title"
    ],
    "wof:name":"Park Place Title",
    "wof:placetype":"venue"
},
  "geometry": {"coordinates":[-84.46243200000001,39.35096],"type":"Point"}
}