{
  "type": "Feature",
  "properties": {
    "addr:full": "171 Scott St NE Warren OH 44483",
    "addr:housenumber": "171",
    "addr:postcode": "44483",
    "addr:street": "Scott St Ne",
    "iso:country": "US",
    "sg:address": "171 Scott St NE",
    "sg:city": "Warren",
    "sg:classifiers": [
      {
        "category": "Government",
        "subcategory": "Office",
        "type": "Public Place"
      }
    ],
    "sg:phone": "+1 330 392 5362",
    "sg:postcode": "44483",
    "sg:province": "OH",
    "wof:name": "Trumbull Boys Group Home",
    "wof:placetype": "venue"
  },
  "geometry": {"coordinates":[-80.817761,41.240168],"type":"Point"}
}
