{
  "type": "Feature",
  "properties": {
    "addr:full":"5722 Telegraph Rd Toledo OH 43612",
    "addr:housenumber":"5722",
    "addr:postcode":"43612",
    "addr:street":"Telegraph Rd",
    "iso:country":"US",
    "sg:address":"5722 Telegraph Rd",
    "sg:city":"Toledo",
    "sg:classifiers":[
        {
            "category":"Real Estate",
            "subcategory":"Real Estate Operator",
            "type":"Services"
        }
    ],
    "sg:phone":"+1 419 476 1521",
    "sg:postcode":"43612",
    "sg:province":"OH",
    "sg:tags":[
        "mobile",
        "home",
        "community"
    ],
    "wof:name":"Carriage Way Home Park",
    "wof:placetype":"venue"
},
  "geometry": {"coordinates":[-83.547308,41.720513],"type":"Point"}
}