{
  "type": "Feature",
  "properties": {
    "addr:full":"4550 Este Ave Cincinnati OH 45232",
    "addr:postcode":"4550;45232",
    "addr:street":"Este Ave",
    "iso:country":"US",
    "sg:address":"4550 Este Ave",
    "sg:city":"Cincinnati",
    "sg:classifiers":[
        {
            "category":"Professional",
            "subcategory":"Research",
            "type":"Services"
        }
    ],
    "sg:phone":"+1 513 627 9621",
    "sg:postcode":"45232",
    "sg:province":"OH",
    "sg:tags":[
        "laboratory"
    ],
    "wof:name":"Procter & Gamble",
    "wof:placetype":"venue"
},
  "geometry": {"coordinates":[-84.512925,39.1715],"type":"Point"}
}