{
  "type": "Feature",
  "properties": {
    "iso:country":"US",
    "sg:address":"165 Park Ave W",
    "sg:city":"Mansfield",
    "sg:classifiers":[
        {
            "category":"Retail",
            "subcategory":"Laundry & Dry Cleaning",
            "type":"Services"
        }
    ],
    "sg:phone":"+1 419 524 2611",
    "sg:postcode":"44902",
    "sg:province":"OH",
    "sg:tags":[
        "drycleaning",
        "pressing",
        "garment"
    ],
    "wof:name":"Swan Cleaners",
    "wof:placetype":"venue"
},
  "geometry": {"coordinates":[-82.51925799999999,40.758636],"type":"Point"}
}