{
  "type": "Feature",
  "properties": {
    "addr:full": "165 Park Ave W Mansfield OH 44902",
    "addr:housenumber": "165",
    "addr:postcode": "44902",
    "addr:street": "Park Ave W",
    "iso:country": "US",
    "sg:address": "165 Park Ave W",
    "sg:city": "Mansfield",
    "sg:classifiers": [
      {
        "category": "Retail",
        "subcategory": "Laundry \u0026 Dry Cleaning",
        "type": "Services"
      }
    ],
    "sg:phone": "+1 419 524 2611",
    "sg:postcode": "44902",
    "sg:province": "OH",
    "sg:tags": [
      "drycleaning",
      "pressing",
      "garment"
    ],
    "wof:name": "Swan Cleaners",
    "wof:placetype": "venue"
  },
  "geometry": {"coordinates":[-82.519258,40.758636],"type":"Point"}
}
