{
  "type": "Feature",
  "properties": {
    "addr:full":"225 Ludlow St Hamilton OH 45011",
    "addr:housenumber":"225",
    "addr:postcode":"45011",
    "addr:street":"Ludlow St",
    "iso:country":"US",
    "sg:address":"225 Ludlow St",
    "sg:city":"Hamilton",
    "sg:classifiers":[
        {
            "category":"Organizations",
            "subcategory":"Religious Organization",
            "type":"Services"
        }
    ],
    "sg:phone":"+1 513 896 5683",
    "sg:postcode":"45011",
    "sg:province":"OH",
    "sg:website":"www.first-church-hamilton.org",
    "wof:name":"First United Methodist Church",
    "wof:placetype":"venue"
},
  "geometry": {"coordinates":[-84.56173200000001,39.397382],"type":"Point"}
}