{
  "type": "Feature",
  "properties": {
    "addr:full": "439 W Market St Akron OH 44303",
    "addr:housenumber": "439",
    "addr:postcode": "44303",
    "addr:street": "W Market St",
    "iso:country": "US",
    "sg:address": "439 W Market St",
    "sg:city": "Akron",
    "sg:classifiers": [
      {
        "category": "Professional",
        "subcategory": "Art Services",
        "type": "Services"
      }
    ],
    "sg:phone": "+1 330 535 2525",
    "sg:postcode": "44303",
    "sg:province": "OH",
    "sg:tags": [
      "graphic",
      "designer"
    ],
    "sg:website": "www.adgraphicsinc.com",
    "wof:name": "Advertising Graphics",
    "wof:placetype": "venue"
  },
  "geometry": {"coordinates":[-81.530822,41.091301],"type":"Point"}
}
