{
  "type": "Feature",
  "properties": {
    "addr:full":"1444 Lima Ave Findlay OH 45840",
    "addr:housenumber":"1444",
    "addr:postcode":"45840",
    "addr:street":"Lima Ave",
    "iso:country":"US",
    "sg:address":"1444 Lima Ave",
    "sg:city":"Findlay",
    "sg:classifiers":[
        {
            "category":"Government",
            "subcategory":"Office",
            "type":"Public Place"
        }
    ],
    "sg:phone":"+1 419 425 3313",
    "sg:postcode":"45840",
    "sg:province":"OH",
    "sg:tags":[
        "state",
        "program"
    ],
    "wof:name":"License Bureau",
    "wof:placetype":"venue"
},
  "geometry": {"coordinates":[-83.67477599999999,41.018374],"type":"Point"}
}