{
  "type": "Feature",
  "properties": {
    "addr:full": "6572 Beaver Creek Rd Celina OH 45822",
    "addr:housenumber": "6572",
    "addr:postcode": "45822",
    "addr:street": "Beaver Creek Rd",
    "iso:country": "US",
    "sg:address": "6572 Beaver Creek Rd",
    "sg:city": "Celina",
    "sg:classifiers": [
      {
        "category": "Banks \u0026 Credit Unions",
        "subcategory": "Financial Services",
        "type": "Services"
      }
    ],
    "sg:phone": "+1 419 268 9500",
    "sg:postcode": "45822",
    "sg:province": "OH",
    "sg:tags": [
      "investor"
    ],
    "wof:name": "Zuma Investments LLC",
    "wof:placetype": "venue"
  },
  "geometry": {"coordinates":[-84.543387,40.491653],"type":"Point"}
}
