{
  "type": "Feature",
  "properties": {
    "iso:country":"US",
    "sg:address":"3367 Hauck Rd",
    "sg:city":"Cincinnati",
    "sg:classifiers":[
        {
            "category":"Retail",
            "subcategory":"Auto Repair",
            "type":"Services"
        }
    ],
    "sg:phone":"+1 513 769 6686",
    "sg:postcode":"45241",
    "sg:province":"OH",
    "sg:tags":[
        "wrecker"
    ],
    "wof:name":"Nick's Towing Svc",
    "wof:placetype":"venue"
},
  "geometry": {"coordinates":[-84.410921,39.290583],"type":"Point"}
}