{
  "type": "Feature",
  "properties": {
    "addr:full": "5026 Hoffman Norton Rd Bristolville OH 44402",
    "addr:housenumber": "5026",
    "addr:postcode": "44402",
    "addr:street": "Hoffman Norton Rd",
    "iso:country": "US",
    "sg:address": "5026 Hoffman Norton Rd",
    "sg:city": "Bristolville",
    "sg:classifiers": [
      {
        "category": "Building \u0026 Trades",
        "subcategory": "Construction",
        "type": "Services"
      }
    ],
    "sg:phone": "+1 330 889 3122",
    "sg:postcode": "44402",
    "sg:province": "OH",
    "sg:tags": [
      "house"
    ],
    "wof:name": "Kurtz Quality Construction",
    "wof:placetype": "venue"
  },
  "geometry": {"coordinates":[-80.913062,41.359984],"type":"Point"}
}
