{
  "type": "Feature",
  "properties": {
    "addr:full":"7003 Memphis Ave Cleveland OH 44144",
    "addr:housenumber":"7003",
    "addr:postcode":"44144",
    "addr:street":"Memphis Ave",
    "iso:country":"US",
    "sg:address":"7003 Memphis Ave",
    "sg:city":"Cleveland",
    "sg:classifiers":[
        {
            "category":"Health Services",
            "subcategory":"Doctor",
            "type":"Services"
        }
    ],
    "sg:phone":"+1 216 749 4733",
    "sg:postcode":"44144",
    "sg:province":"OH",
    "sg:tags":[
        "physician",
        "surgeon"
    ],
    "wof:name":"Rogelia B Medidas Inc",
    "wof:placetype":"venue"
},
  "geometry": {"coordinates":[-81.73376,41.43989],"type":"Point"}
}