{
  "type": "Feature",
  "properties": {
    "addr:full":"204 E Boundary St Perrysburg OH 43551",
    "addr:housenumber":"204",
    "addr:postcode":"43551",
    "addr:street":"E Boundary St",
    "iso:country":"US",
    "sg:address":"204 E Boundary St",
    "sg:city":"Perrysburg",
    "sg:classifiers":[
        {
            "category":"Organizations",
            "subcategory":"Religious Organization",
            "type":"Services"
        },
        {
            "category":"Shopping",
            "subcategory":"Books",
            "type":"Retail Goods"
        }
    ],
    "sg:phone":"+1 419 874 0371",
    "sg:postcode":"43551",
    "sg:province":"OH",
    "sg:tags":[
        "dealer"
    ],
    "wof:name":"Christian Scence Reading Rooms",
    "wof:placetype":"venue"
},
  "geometry": {"coordinates":[-83.617203,41.562971],"type":"Point"}
}