{
  "type": "Feature",
  "properties": {
    "addr:full":"2355 Olentangy River Rd Columbus OH 43210",
    "addr:housenumber":"2355",
    "addr:postcode":"43210",
    "addr:street":"Olentangy River Rd",
    "iso:country":"US",
    "sg:address":"2355 Olentangy River Rd",
    "sg:city":"Columbus",
    "sg:classifiers":[
        {
            "category":"Museum",
            "type":"Entertainment"
        }
    ],
    "sg:phone":"+1 614 247 5959",
    "sg:postcode":"43210",
    "sg:province":"OH",
    "wof:name":"Jack Nicklaus Museum",
    "wof:placetype":"venue"
},
  "geometry": {"coordinates":[-83.02228599999999,40.011171],"type":"Point"}
}