{
  "type": "Feature",
  "properties": {
    "iso:country":"US",
    "sg:address":"200 E Emmitt Ave",
    "sg:city":"Waverly",
    "sg:classifiers":[
        {
            "category":"Real Estate",
            "subcategory":"Real Estate Agent",
            "type":"Services"
        }
    ],
    "sg:phone":"+1 740 947 7577",
    "sg:postcode":"45690",
    "sg:province":"OH",
    "wof:name":"Fran Francis Realtors",
    "wof:placetype":"venue"
},
  "geometry": {"coordinates":[-82.982934,39.128561],"type":"Point"}
}