{
  "type": "Feature",
  "properties": {
    "addr:full":"417 Euclid Ave Lorain OH 44052",
    "addr:housenumber":"417",
    "addr:postcode":"44052",
    "addr:street":"Euclid Ave",
    "iso:country":"US",
    "sg:address":"417 Euclid Ave",
    "sg:city":"Lorain",
    "sg:classifiers":[
        {
            "category":"Building & Trades",
            "subcategory":"Construction",
            "type":"Services"
        }
    ],
    "sg:phone":"+1 440 288 4224",
    "sg:postcode":"44052",
    "sg:province":"OH",
    "sg:tags":[
        "house"
    ],
    "wof:name":"North Coast Home Improvement",
    "wof:placetype":"venue"
},
  "geometry": {"coordinates":[-82.138679,41.478021],"type":"Point"}
}