{
  "type": "Feature",
  "properties": {
    "addr:full":"4947 W Alexis Rd Sylvania OH 43560",
    "addr:housenumber":"4947",
    "addr:postcode":"43560",
    "addr:street":"W Alexis Rd",
    "iso:country":"US",
    "sg:address":"4947 W Alexis Rd",
    "sg:city":"Sylvania",
    "sg:classifiers":[
        {
            "category":"Manufacturing",
            "subcategory":"Metals",
            "type":"Manufacturing & Wholesale Goods"
        }
    ],
    "sg:phone":"+1 419 474 3500",
    "sg:postcode":"43560",
    "sg:province":"OH",
    "sg:tags":[
        "mfg",
        "carpentry",
        "sheet",
        "metalwork",
        "contractor"
    ],
    "wof:name":"Buckeye Mfg & Awning Co",
    "wof:placetype":"venue"
},
  "geometry": {"coordinates":[-83.662828,41.718184],"type":"Point"}
}