{
  "type": "Feature",
  "properties": {
    "addr:full": "3979 Glenn Hwy Cambridge OH 43725",
    "addr:housenumber": "3979",
    "addr:postcode": "43725",
    "addr:street": "Glenn Hwy",
    "iso:country": "US",
    "sg:address": "3979 Glenn Hwy",
    "sg:city": "Cambridge",
    "sg:classifiers": [
      {
        "category": "Retail",
        "subcategory": "Veterinary Services",
        "type": "Services"
      }
    ],
    "sg:phone": "+1 740 439 1728",
    "sg:postcode": "43725",
    "sg:province": "OH",
    "wof:name": "Animal Clinic",
    "wof:placetype": "venue"
  },
  "geometry": {"coordinates":[-81.671927,40.003485],"type":"Point"}
}
