{
  "type": "Feature",
  "properties": {
    "iso:country":"US",
    "sg:address":"153 Mill St",
    "sg:city":"Gahanna",
    "sg:classifiers":[
        {
            "category":"Autos & Motor Vehicles",
            "subcategory":"Auto Supplies",
            "type":"Retail Goods"
        }
    ],
    "sg:phone":"+1 614 471 4700",
    "sg:postcode":"43230",
    "sg:province":"OH",
    "sg:tags":[
        "automobile",
        "parts"
    ],
    "wof:name":"Gahanna Automotive Supply",
    "wof:placetype":"venue"
},
  "geometry": {"coordinates":[-82.879513,40.022145],"type":"Point"}
}