{
  "type": "Feature",
  "properties": {
    "addr:full": "1336 Woodman Dr Dayton OH 45432",
    "addr:housenumber": "1336",
    "addr:postcode": "45432",
    "addr:street": "Woodman Dr",
    "iso:country": "US",
    "sg:address": "1336 Woodman Dr",
    "sg:city": "Dayton",
    "sg:classifiers": [
      {
        "category": "Insurance",
        "subcategory": "Insurance Agent",
        "type": "Services"
      }
    ],
    "sg:phone": "+1 937 259 0300",
    "sg:postcode": "45432",
    "sg:province": "OH",
    "wof:name": "Gillson Financial Group",
    "wof:placetype": "venue"
  },
  "geometry": {"coordinates":[-84.120844,39.743661],"type":"Point"}
}
