{
  "type": "Feature",
  "properties": {
    "addr:full": "642 Wheeling Ave Cambridge OH 43725",
    "addr:housenumber": "642",
    "addr:postcode": "43725",
    "addr:street": "Wheeling Ave",
    "iso:country": "US",
    "sg:address": "642 Wheeling Ave",
    "sg:city": "Cambridge",
    "sg:classifiers": [
      {
        "category": "Museum",
        "type": "Entertainment"
      }
    ],
    "sg:phone": "+1 740 432 7958",
    "sg:postcode": "43725",
    "sg:province": "OH",
    "sg:tags": [
      "organization",
      "arts",
      "information"
    ],
    "wof:name": "Cambridge Performing Arts Ctr",
    "wof:placetype": "venue"
  },
  "geometry": {"coordinates":[-81.592801,40.024757],"type":"Point"}
}
