{
  "type": "Feature",
  "properties": {
    "addr:full":"10210 Brecksville Rd Cleveland OH 44141",
    "addr:housenumber":"10210",
    "addr:postcode":"44141",
    "addr:street":"Brecksville Rd",
    "iso:country":"US",
    "sg:address":"10210 Brecksville Rd",
    "sg:city":"Cleveland",
    "sg:classifiers":[
        {
            "category":"Professional",
            "subcategory":"Computer Services",
            "type":"Services"
        }
    ],
    "sg:phone":"+1 440 717 9400",
    "sg:postcode":"44141",
    "sg:province":"OH",
    "sg:tags":[
        "consultant",
        "designer"
    ],
    "wof:name":"Exential LLC",
    "wof:placetype":"venue"
},
  "geometry": {"coordinates":[-81.62715900000001,41.279528],"type":"Point"}
}