{
  "type": "Feature",
  "properties": {
    "iso:country":"US",
    "sg:address":"29339 Euclid Ave",
    "sg:city":"Wickliffe",
    "sg:classifiers":[
        {
            "category":"Professional",
            "subcategory":"Accounting & Tax Preparation",
            "type":"Services"
        }
    ],
    "sg:phone":"+1 440 585 1090",
    "sg:postcode":"44092",
    "sg:province":"OH",
    "sg:tags":[
        "return",
        "filing"
    ],
    "wof:name":"Rap & Assoc Inc",
    "wof:placetype":"venue"
},
  "geometry": {"coordinates":[-81.47335699999999,41.606722],"type":"Point"}
}