{
  "type": "Feature",
  "properties": {
    "addr:full":"1405 Springfield Pike Cincinnati OH 45215",
    "addr:housenumber":"1405",
    "addr:postcode":"45215",
    "addr:street":"Springfield Pike",
    "iso:country":"US",
    "sg:address":"1405 Springfield Pike",
    "sg:city":"Cincinnati",
    "sg:classifiers":[
        {
            "category":"Professional",
            "subcategory":"Accounting & Tax Preparation",
            "type":"Services"
        }
    ],
    "sg:phone":"+1 513 679 2100",
    "sg:postcode":"45215",
    "sg:province":"OH",
    "sg:tags":[
        "accountant"
    ],
    "wof:name":"Reiser & Assoc",
    "wof:placetype":"venue"
},
  "geometry": {"coordinates":[-84.47143,39.240988],"type":"Point"}
}