{
  "type": "Feature",
  "properties": {
    "addr:full": "15711 Rd 18 Fort Jennings OH 45844",
    "addr:postcode": "15711;45844",
    "addr:street": "Rd 18 Fort",
    "iso:country": "US",
    "sg:address": "15711 Rd 18",
    "sg:city": "Fort Jennings",
    "sg:phone": "+1 419 532 2146",
    "sg:postcode": "45844",
    "sg:province": "OH",
    "sg:tags": [
      "farm",
      "grain",
      "cash"
    ],
    "wof:name": "Mark Kahle",
    "wof:placetype": "venue"
  },
  "geometry": {"coordinates":[-84.206663,40.950229],"type":"Point"}
}
