{
  "type": "Feature",
  "properties": {
    "iso:country":"US",
    "sg:address":"15711 Rd 18",
    "sg:city":"Fort Jennings",
    "sg:phone":"+1 419 532 2146",
    "sg:postcode":"45844",
    "sg:province":"OH",
    "sg:tags":[
        "farm",
        "grain",
        "cash"
    ],
    "wof:name":"Mark Kahle",
    "wof:placetype":"venue"
},
  "geometry": {"coordinates":[-84.20666300000001,40.950229],"type":"Point"}
}