{
  "type": "Feature",
  "properties": {
    "addr:full": "850 Creek Rd Columbiana OH 44408",
    "addr:housenumber": "850",
    "addr:postcode": "44408",
    "addr:street": "Creek Rd",
    "iso:country": "US",
    "sg:address": "850 Creek Rd",
    "sg:city": "Columbiana",
    "sg:classifiers": [
      {
        "category": "Real Estate",
        "subcategory": "Real Estate Agent",
        "type": "Services"
      }
    ],
    "sg:phone": "+1 330 482 1144",
    "sg:postcode": "44408",
    "sg:province": "OH",
    "wof:name": "Hanna Howard Real Estate",
    "wof:placetype": "venue"
  },
  "geometry": {"coordinates":[-80.641097,40.88992],"type":"Point"}
}
