{
  "type": "Feature",
  "properties": {
    "iso:country":"US",
    "sg:address":"7540 Harding Hwy",
    "sg:city":"Lima",
    "sg:classifiers":[
        {
            "category":"Recreation",
            "type":"Entertainment"
        }
    ],
    "sg:phone":"+1 419 222 4115",
    "sg:postcode":"45801",
    "sg:province":"OH",
    "sg:tags":[
        "stable"
    ],
    "wof:name":"J Bark",
    "wof:placetype":"venue"
},
  "geometry": {"coordinates":[-83.964356,40.73145],"type":"Point"}
}