{
  "type": "Feature",
  "properties": {
    "addr:full":"623 W State St Alliance OH 44601",
    "addr:housenumber":"623",
    "addr:postcode":"44601",
    "addr:street":"W State St",
    "iso:country":"US",
    "sg:address":"623 W State St",
    "sg:city":"Alliance",
    "sg:classifiers":[
        {
            "category":"Building & Trades",
            "subcategory":"Construction",
            "type":"Services"
        }
    ],
    "sg:phone":"+1 330 206 0020",
    "sg:postcode":"44601",
    "sg:province":"OH",
    "sg:tags":[
        "concrete",
        "contractor"
    ],
    "wof:name":"Vali Concrete Construction",
    "wof:placetype":"venue"
},
  "geometry": {"coordinates":[-81.112916,40.901826],"type":"Point"}
}