{
  "type": "Feature",
  "properties": {
    "addr:full":"157 E Morrison St Edgerton OH 43517",
    "addr:housenumber":"157",
    "addr:postcode":"43517",
    "addr:street":"E Morrison St",
    "iso:country":"US",
    "sg:address":"157 E Morrison St",
    "sg:city":"Edgerton",
    "sg:classifiers":[
        {
            "category":"Communications",
            "type":"Services"
        }
    ],
    "sg:phone":"+1 419 298 3237",
    "sg:postcode":"43517",
    "sg:province":"OH",
    "wof:name":"C & J Communications",
    "wof:placetype":"venue"
},
  "geometry": {"coordinates":[-84.74077800000001,41.448138],"type":"Point"}
}