{
  "type": "Feature",
  "properties": {
    "iso:country":"US",
    "sg:address":"4601 Eastgate Blvd",
    "sg:city":"Cincinnati",
    "sg:classifiers":[
        {
            "category":"Shopping",
            "subcategory":"Hobbies, Toys, & Games",
            "type":"Retail Goods"
        }
    ],
    "sg:phone":"+1 513 947 8485",
    "sg:postcode":"45245",
    "sg:province":"OH",
    "wof:name":"Dixies Dollhouse Inc",
    "wof:placetype":"venue"
},
  "geometry": {"coordinates":[-84.27309099999999,39.10214],"type":"Point"}
}