{
  "type": "Feature",
  "properties": {
    "iso:country":"US",
    "sg:address":"14200 Ridge Rd",
    "sg:city":"Cleveland",
    "sg:classifiers":[
        {
            "category":"Professional",
            "subcategory":"Computer Services",
            "type":"Services"
        }
    ],
    "sg:phone":"+1 440 230 5500",
    "sg:postcode":"44133",
    "sg:province":"OH",
    "sg:tags":[
        "home",
        "consulting",
        "page",
        "dev",
        "internet"
    ],
    "sg:website":"www.rxdds.com",
    "wof:name":"RXDDS",
    "wof:placetype":"venue"
},
  "geometry": {"coordinates":[-81.734707,41.312419],"type":"Point"}
}