{
  "type": "Feature",
  "properties": {
    "iso:country":"US",
    "sg:address":"823 Heatherstone Dr",
    "sg:city":"Cincinnati",
    "sg:classifiers":[
        {
            "category":"Communications",
            "subcategory":"Film & Video Production",
            "type":"Services"
        }
    ],
    "sg:phone":"+1 513 851 3869",
    "sg:postcode":"45240",
    "sg:province":"OH",
    "sg:tags":[
        "audio"
    ],
    "wof:name":"Wave Wind Productions",
    "wof:placetype":"venue"
},
  "geometry": {"coordinates":[-84.510013,39.29128],"type":"Point"}
}