{
  "type": "Feature",
  "properties": {
    "addr:full":"32 Goldie Rd Youngstown OH 44505",
    "addr:housenumber":"32",
    "addr:postcode":"44505",
    "addr:street":"Goldie Rd",
    "iso:country":"US",
    "sg:address":"32 Goldie Rd",
    "sg:city":"Youngstown",
    "sg:classifiers":[
        {
            "category":"Health Services",
            "subcategory":"Doctor",
            "type":"Services"
        }
    ],
    "sg:phone":"+1 330 759 7821",
    "sg:postcode":"44505",
    "sg:province":"OH",
    "sg:tags":[
        "dentist"
    ],
    "wof:name":"Heyman Family Dentistry",
    "wof:placetype":"venue"
},
  "geometry": {"coordinates":[-80.662396,41.145744],"type":"Point"}
}