{
  "type": "Feature",
  "properties": {
    "iso:country":"US",
    "sg:address":"615 Literary Rd",
    "sg:city":"Cleveland",
    "sg:classifiers":[
        {
            "category":"Real Estate",
            "subcategory":"Real Estate Operator",
            "type":"Services"
        }
    ],
    "sg:phone":"+1 216 357 3067",
    "sg:postcode":"44113",
    "sg:province":"OH",
    "sg:tags":[
        "building",
        "nonresidential"
    ],
    "wof:name":"Beckerson Properties Inc",
    "wof:placetype":"venue"
},
  "geometry": {"coordinates":[-81.685137,41.482485],"type":"Point"}
}