{
  "type": "Feature",
  "properties": {
    "addr:full":"1375 Copley Rd Akron OH 44320",
    "addr:housenumber":"1375",
    "addr:postcode":"44320",
    "addr:street":"Copley Rd",
    "iso:country":"US",
    "sg:address":"1375 Copley Rd",
    "sg:city":"Akron",
    "sg:classifiers":[
        {
            "category":"Food & Beverages",
            "subcategory":"Groceries & Convenience Stores",
            "type":"Retail Goods"
        }
    ],
    "sg:phone":"+1 330 835 3761",
    "sg:postcode":"44320",
    "sg:province":"OH",
    "sg:tags":[
        "grocer"
    ],
    "wof:name":"Save-A-Lot",
    "wof:placetype":"venue"
},
  "geometry": {"coordinates":[-81.570769,41.083823],"type":"Point"}
}