{
  "type": "Feature",
  "properties": {
    "addr:full":"430 Center St Martins Ferry OH 43935",
    "addr:housenumber":"430",
    "addr:postcode":"43935",
    "addr:street":"Center St Martins Ferry",
    "iso:country":"US",
    "sg:address":"430 Center St",
    "sg:city":"Martins Ferry",
    "sg:classifiers":[
        {
            "category":"Home & Garden",
            "subcategory":"Building Materials",
            "type":"Retail Goods"
        }
    ],
    "sg:phone":"+1 740 633 5284",
    "sg:postcode":"43935",
    "sg:province":"OH",
    "sg:tags":[
        "improvement",
        "bath",
        "including",
        "kitchen",
        "supply"
    ],
    "wof:name":"McIntosh Kitchen & Bath",
    "wof:placetype":"venue"
},
  "geometry": {"coordinates":[-80.717719,40.100532],"type":"Point"}
}