{
  "type": "Feature",
  "properties": {
    "addr:full": "147 Massillon Rd Akron OH 44312",
    "addr:housenumber": "147",
    "addr:postcode": "44312",
    "addr:street": "Massillon Rd",
    "iso:country": "US",
    "sg:address": "147 Massillon Rd",
    "sg:city": "Akron",
    "sg:classifiers": [
      {
        "category": "Home \u0026 Garden",
        "subcategory": "Building Materials",
        "type": "Retail Goods"
      }
    ],
    "sg:phone": "+1 330 784 8661",
    "sg:postcode": "44312",
    "sg:province": "OH",
    "sg:tags": [
      "windows"
    ],
    "wof:name": "Builtrite Windows",
    "wof:placetype": "venue"
  },
  "geometry": {"coordinates":[-81.462639,41.057813],"type":"Point"}
}
