{
  "type": "Feature",
  "properties": {
    "addr:full": "53 Coriell Rd Portsmouth OH 45662",
    "addr:housenumber": "53",
    "addr:postcode": "45662",
    "addr:street": "Coriell Rd",
    "iso:country": "US",
    "sg:address": "53 Coriell Rd",
    "sg:city": "Portsmouth",
    "sg:classifiers": [
      {
        "category": "Building \u0026 Trades",
        "subcategory": "Construction",
        "type": "Services"
      }
    ],
    "sg:phone": "+1 740 776 3452",
    "sg:postcode": "45662",
    "sg:province": "OH",
    "sg:tags": [
      "residential"
    ],
    "wof:name": "Ira Coriell Construction",
    "wof:placetype": "venue"
  },
  "geometry": {"coordinates":[-82.850728,38.795095],"type":"Point"}
}
