{
  "type": "Feature",
  "properties": {
    "iso:country":"US",
    "sg:address":"105 Old St",
    "sg:city":"Monroe",
    "sg:classifiers":[
        {
            "category":"Professional",
            "subcategory":"Advertising",
            "type":"Services"
        }
    ],
    "sg:phone":"+1 513 539 0008",
    "sg:postcode":"45050",
    "sg:province":"OH",
    "sg:tags":[
        "counselor"
    ],
    "wof:name":"Marketing Services Inc",
    "wof:placetype":"venue"
},
  "geometry": {"coordinates":[-84.361333,39.441303],"type":"Point"}
}