{
  "type": "Feature",
  "properties": {
    "addr:full":"10147 Royalton Rd Cleveland OH 44133",
    "addr:housenumber":"10147",
    "addr:postcode":"44133",
    "addr:street":"Royalton Rd",
    "iso:country":"US",
    "sg:address":"10147 Royalton Rd",
    "sg:city":"Cleveland",
    "sg:classifiers":[
        {
            "category":"Shopping",
            "type":"Retail Goods"
        }
    ],
    "sg:phone":"+1 440 582 2307",
    "sg:postcode":"44133",
    "sg:province":"OH",
    "sg:tags":[
        "plastic"
    ],
    "wof:name":"Kempco & James Plastic Equip",
    "wof:placetype":"venue"
},
  "geometry": {"coordinates":[-81.761245,41.313367],"type":"Point"}
}