{
  "type": "Feature",
  "properties": {
    "iso:country":"US",
    "sg:address":"2823 Eden Ave",
    "sg:city":"Cincinnati",
    "sg:classifiers":[
        {
            "category":"Recreation",
            "type":"Entertainment"
        }
    ],
    "sg:phone":"+1 513 221 0888",
    "sg:postcode":"45219",
    "sg:province":"OH",
    "sg:tags":[
        "hall",
        "auditorium"
    ],
    "wof:name":"Corryville Community Ctr",
    "wof:placetype":"venue"
},
  "geometry": {"coordinates":[-84.50608200000001,39.131708],"type":"Point"}
}