{
  "type": "Feature",
  "properties": {
    "addr:full": "2823 Eden Ave Cincinnati OH 45219",
    "addr:housenumber": "2823",
    "addr:postcode": "45219",
    "addr:street": "Eden Ave",
    "iso:country": "US",
    "sg:address": "2823 Eden Ave",
    "sg:city": "Cincinnati",
    "sg:classifiers": [
      {
        "category": "Recreation",
        "type": "Entertainment"
      }
    ],
    "sg:phone": "+1 513 221 0888",
    "sg:postcode": "45219",
    "sg:province": "OH",
    "sg:tags": [
      "hall",
      "auditorium"
    ],
    "wof:name": "Corryville Community Ctr",
    "wof:placetype": "venue"
  },
  "geometry": {"coordinates":[-84.506082,39.131708],"type":"Point"}
}
