{
  "type": "Feature",
  "properties": {
    "addr:full": "1260 York Ln Troy OH 45373",
    "addr:housenumber": "1260",
    "addr:postcode": "45373",
    "addr:street": "York Ln",
    "iso:country": "US",
    "sg:address": "1260 York Ln",
    "sg:city": "Troy",
    "sg:classifiers": [
      {
        "category": "Real Estate",
        "subcategory": "Real Estate Agent",
        "type": "Services"
      }
    ],
    "sg:phone": "+1 937 335 6271",
    "sg:postcode": "45373",
    "sg:province": "OH",
    "wof:name": "Dave Lusk Realty",
    "wof:placetype": "venue"
  },
  "geometry": {"coordinates":[-84.219727,40.048624],"type":"Point"}
}
