{
  "type": "Feature",
  "properties": {
    "addr:full":"4665 Cleveland Ave Columbus OH 43231",
    "addr:housenumber":"4665",
    "addr:postcode":"43231",
    "addr:street":"Cleveland Ave",
    "iso:country":"US",
    "sg:address":"4665 Cleveland Ave",
    "sg:city":"Columbus",
    "sg:classifiers":[
        {
            "category":"Professional",
            "subcategory":"Computer Services",
            "type":"Services"
        }
    ],
    "sg:phone":"+1 614 418 7780",
    "sg:postcode":"43231",
    "sg:province":"OH",
    "sg:tags":[
        "consultant",
        "designer"
    ],
    "wof:name":"Advanced Business Technologies",
    "wof:placetype":"venue"
},
  "geometry": {"coordinates":[-82.95268900000001,40.064385],"type":"Point"}
}