{
  "type": "Feature",
  "properties": {
    "iso:country":"US",
    "sg:address":"2819 E Dublin Granville Rd",
    "sg:city":"Columbus",
    "sg:classifiers":[
        {
            "category":"Real Estate",
            "subcategory":"Real Estate Operator",
            "type":"Services"
        }
    ],
    "sg:phone":"+1 614 898 9922",
    "sg:postcode":"43231",
    "sg:province":"OH",
    "sg:tags":[
        "building",
        "intermediate",
        "apartment",
        "care",
        "facility"
    ],
    "wof:name":"Woodside Village of Columbus",
    "wof:placetype":"venue"
},
  "geometry": {"coordinates":[-82.94166,40.083027],"type":"Point"}
}