{
  "type": "Feature",
  "properties": {
    "iso:country":"US",
    "sg:address":"875 Bickel Church Rd NE",
    "sg:city":"Baltimore",
    "sg:classifiers":[
        {
            "category":"Building & Trades",
            "subcategory":"Construction",
            "type":"Services"
        }
    ],
    "sg:phone":"+1 740 862 4223",
    "sg:postcode":"43105",
    "sg:province":"OH",
    "sg:tags":[
        "residential"
    ],
    "wof:name":"James Edward Davis",
    "wof:placetype":"venue"
},
  "geometry": {"coordinates":[-82.568864,39.870648],"type":"Point"}
}