{
  "type": "Feature",
  "properties": {
    "addr:full":"2433 Vera Ave Cincinnati OH 45237",
    "addr:housenumber":"2433",
    "addr:postcode":"45237",
    "addr:street":"Vera Ave",
    "iso:country":"US",
    "sg:address":"2433 Vera Ave",
    "sg:city":"Cincinnati",
    "sg:classifiers":[
        {
            "category":"Organizations",
            "subcategory":"Religious Organization",
            "type":"Services"
        }
    ],
    "sg:phone":"+1 513 396 7176",
    "sg:postcode":"45237",
    "sg:province":"OH",
    "sg:tags":[
        "clergy"
    ],
    "wof:name":"Raymond Shepard",
    "wof:placetype":"venue"
},
  "geometry": {"coordinates":[-84.44666599999999,39.191556],"type":"Point"}
}