{
  "type": "Feature",
  "properties": {
    "addr:full":"7601 Mentor Ave Mentor OH 44060",
    "addr:housenumber":"7601",
    "addr:postcode":"44060",
    "addr:street":"Mentor Ave",
    "iso:country":"US",
    "sg:address":"7601 Mentor Ave",
    "sg:city":"Mentor",
    "sg:classifiers":[
        {
            "category":"Travel",
            "subcategory":"Travel Agent",
            "type":"Entertainment"
        }
    ],
    "sg:phone":"+1 440 951 1242",
    "sg:postcode":"44060",
    "sg:province":"OH",
    "sg:tags":[
        "agency",
        "bureau"
    ],
    "wof:name":"Flight Time Travel",
    "wof:placetype":"venue"
},
  "geometry": {"coordinates":[-81.370126,41.657159],"type":"Point"}
}