{
  "type": "Feature",
  "properties": {
    "addr:full":"8025 Corporate Cir Cleveland OH 44133",
    "addr:housenumber":"8025",
    "addr:postcode":"44133",
    "addr:street":"Corporate Cir",
    "iso:country":"US",
    "sg:address":"8025 Corporate Cir",
    "sg:city":"Cleveland",
    "sg:classifiers":[
        {
            "category":"Insurance",
            "subcategory":"Insurance Agent",
            "type":"Services"
        }
    ],
    "sg:phone":"+1 440 887 0477",
    "sg:postcode":"44133",
    "sg:province":"OH",
    "wof:name":"Allstate Insurance Co",
    "wof:placetype":"venue"
},
  "geometry": {"coordinates":[-81.755747,41.349468],"type":"Point"}
}