{
  "type": "Feature",
  "properties": {
    "iso:country":"US",
    "sg:address":"28870 Chardon Rd",
    "sg:city":"Wickliffe",
    "sg:classifiers":[
        {
            "category":"Organizations",
            "subcategory":"Religious Organization",
            "type":"Services"
        }
    ],
    "sg:phone":"+1 440 944 5100",
    "sg:postcode":"44092",
    "sg:province":"OH",
    "sg:website":"www.calvaryagohio.org",
    "wof:name":"Calvary Assembly Of God",
    "wof:placetype":"venue"
},
  "geometry": {"coordinates":[-81.473167,41.584403],"type":"Point"}
}