{
  "type": "Feature",
  "properties": {
    "addr:full": "5690 W Liberty St Hubbard OH 44425",
    "addr:housenumber": "5690",
    "addr:postcode": "44425",
    "addr:street": "W Liberty St",
    "iso:country": "US",
    "sg:address": "5690 W Liberty St",
    "sg:city": "Hubbard",
    "sg:classifiers": [
      {
        "category": "Manufacturing",
        "subcategory": "Wood Products",
        "type": "Manufacturing \u0026 Wholesale Goods"
      },
      {
        "category": "Home \u0026 Garden",
        "subcategory": "Building Materials",
        "type": "Retail Goods"
      },
      {
        "category": "Manufacturing",
        "subcategory": "Lumber",
        "type": "Manufacturing \u0026 Wholesale Goods"
      }
    ],
    "sg:phone": "+1 330 759 7115",
    "sg:postcode": "44425",
    "sg:province": "OH",
    "sg:tags": [
      "lumber-wholesale",
      "lumber-used"
    ],
    "wof:name": "Hubbard Lumber",
    "wof:placetype": "venue"
  },
  "geometry": {"coordinates":[-80.614165,41.159469],"type":"Point"}
}
