{
  "type": "Feature",
  "properties": {
    "addr:full": "1060 Mount Vernon Ave Columbus OH 43203",
    "addr:housenumber": "1060",
    "addr:postcode": "43203",
    "addr:street": "Mount Vernon Ave",
    "iso:country": "US",
    "sg:address": "1060 Mount Vernon Ave",
    "sg:city": "Columbus",
    "sg:classifiers": [
      {
        "category": "Organizations",
        "subcategory": "Non-profit Organization",
        "type": "Services"
      }
    ],
    "sg:phone": "+1 614 251 1322",
    "sg:postcode": "43203",
    "sg:province": "OH",
    "wof:name": "Harambee",
    "wof:placetype": "venue"
  },
  "geometry": {"coordinates":[-82.974159,39.972045],"type":"Point"}
}
