{
  "type": "Feature",
  "properties": {
    "iso:country":"US",
    "sg:address":"47 E Hollister St",
    "sg:city":"Cincinnati",
    "sg:classifiers":[
        {
            "category":"Health Services",
            "subcategory":"Chiropractor",
            "type":"Services"
        }
    ],
    "sg:phone":"+1 513 744 9091",
    "sg:postcode":"45219",
    "sg:province":"OH",
    "wof:name":"Cork Family Chiropractic",
    "wof:placetype":"venue"
},
  "geometry": {"coordinates":[-84.510069,39.1256],"type":"Point"}
}