{
  "type": "Feature",
  "properties": {
    "addr:full": "364 Rice St Elmore OH 43416",
    "addr:housenumber": "364",
    "addr:postcode": "43416",
    "addr:street": "Rice St",
    "iso:country": "US",
    "sg:address": "364 Rice St",
    "sg:city": "Elmore",
    "sg:classifiers": [
      {
        "category": "Shopping",
        "subcategory": "Gifts \u0026 Souvenirs",
        "type": "Retail Goods"
      }
    ],
    "sg:phone": "+1 419 862 1401",
    "sg:postcode": "43416",
    "sg:province": "OH",
    "sg:tags": [
      "party",
      "supply"
    ],
    "wof:name": "Elf's Attic",
    "wof:placetype": "venue"
  },
  "geometry": {"coordinates":[-83.295147,41.475306],"type":"Point"}
}
