{
  "type": "Feature",
  "properties": {
    "iso:country":"US",
    "sg:address":"364 Rice St",
    "sg:city":"Elmore",
    "sg:classifiers":[
        {
            "category":"Shopping",
            "subcategory":"Gifts & Souvenirs",
            "type":"Retail Goods"
        }
    ],
    "sg:phone":"+1 419 862 1401",
    "sg:postcode":"43416",
    "sg:province":"OH",
    "sg:tags":[
        "party",
        "supply"
    ],
    "wof:name":"Elf's Attic",
    "wof:placetype":"venue"
},
  "geometry": {"coordinates":[-83.295147,41.475306],"type":"Point"}
}