{
  "type": "Feature",
  "properties": {
    "addr:full": "3535 Wales Ave NW Massillon OH 44646",
    "addr:housenumber": "3535",
    "addr:postcode": "44646",
    "addr:street": "Wales Ave Nw",
    "iso:country": "US",
    "sg:address": "3535 Wales Ave NW",
    "sg:city": "Massillon",
    "sg:classifiers": [
      {
        "category": "Retail",
        "subcategory": "Laundry \u0026 Dry Cleaning",
        "type": "Services"
      }
    ],
    "sg:phone": "+1 330 833 7891",
    "sg:postcode": "44646",
    "sg:province": "OH",
    "sg:tags": [
      "cleaners"
    ],
    "wof:name": "Blair's Cleaners",
    "wof:placetype": "venue"
  },
  "geometry": {"coordinates":[-81.502444,40.832568],"type":"Point"}
}
