{
  "type": "Feature",
  "properties": {
    "iso:country":"US",
    "sg:address":"3365 Silica Rd",
    "sg:city":"Sylvania",
    "sg:classifiers":[
        {
            "category":"Building & Trades",
            "subcategory":"Plumbing",
            "type":"Services"
        }
    ],
    "sg:phone":"+1 419 843 8800",
    "sg:postcode":"43560",
    "sg:province":"OH",
    "sg:tags":[
        "contractor"
    ],
    "wof:name":"Pauls Heating & Cooling",
    "wof:placetype":"venue"
},
  "geometry": {"coordinates":[-83.733001,41.682902],"type":"Point"}
}