{
  "type": "Feature",
  "properties": {
    "addr:full":"83 Madison St Port Clinton OH 43452",
    "addr:housenumber":"83",
    "addr:postcode":"43452",
    "addr:street":"Madison St",
    "iso:country":"US",
    "sg:address":"83 Madison St",
    "sg:city":"Port Clinton",
    "sg:classifiers":[
        {
            "category":"Shopping",
            "subcategory":"Bicycles & Sporting Goods",
            "type":"Retail Goods"
        }
    ],
    "sg:phone":"+1 419 734 9002",
    "sg:postcode":"43452",
    "sg:province":"OH",
    "sg:tags":[
        "boating",
        "rental",
        "fishing",
        "boat",
        "supply"
    ],
    "wof:name":"Fishermans Wharf",
    "wof:placetype":"venue"
},
  "geometry": {"coordinates":[-82.941186,41.513461],"type":"Point"}
}