{
  "type": "Feature",
  "properties": {
    "addr:full":"1320 Aiken Rd Piqua OH 45356",
    "addr:housenumber":"1320",
    "addr:postcode":"45356",
    "addr:street":"Aiken Rd",
    "iso:country":"US",
    "sg:address":"1320 Aiken Rd",
    "sg:city":"Piqua",
    "sg:classifiers":[
        {
            "category":"Professional",
            "subcategory":"Computer Services",
            "type":"Services"
        }
    ],
    "sg:phone":"+1 937 615 0648",
    "sg:postcode":"45356",
    "sg:province":"OH",
    "sg:tags":[
        "internet"
    ],
    "wof:name":"Pats Internet Svc",
    "wof:placetype":"venue"
},
  "geometry": {"coordinates":[-84.289978,40.218658],"type":"Point"}
}