{
  "type": "Feature",
  "properties": {
    "addr:full":"1220 Parsons Ave Columbus OH 43206",
    "addr:housenumber":"1220",
    "addr:postcode":"43206",
    "addr:street":"Parsons Ave",
    "iso:country":"US",
    "sg:address":"1220 Parsons Ave",
    "sg:city":"Columbus",
    "sg:classifiers":[
        {
            "category":"Wholesale",
            "subcategory":"Machinery & Supplies",
            "type":"Manufacturing & Wholesale Goods"
        },
        {
            "category":"Wholesale",
            "subcategory":"Farm Supplies",
            "type":"Manufacturing & Wholesale Goods"
        }
    ],
    "sg:phone":"+1 614 443 5522",
    "sg:postcode":"43206",
    "sg:province":"OH",
    "sg:tags":[
        "control",
        "exterminator",
        "pest",
        "equipment"
    ],
    "wof:name":"Mid Ohio Termite & Pest Cntrl",
    "wof:placetype":"venue"
},
  "geometry": {"coordinates":[-82.983307,39.938838],"type":"Point"}
}