{
  "type": "Feature",
  "properties": {
    "addr:full": "1112 Gallia St Portsmouth OH 45662",
    "addr:housenumber": "1112",
    "addr:postcode": "45662",
    "addr:street": "Gallia St",
    "iso:country": "US",
    "sg:address": "1112 Gallia St",
    "sg:city": "Portsmouth",
    "sg:classifiers": [
      {
        "category": "Organizations",
        "subcategory": "Non-profit Organization",
        "type": "Services"
      }
    ],
    "sg:phone": "+1 740 354 2273",
    "sg:postcode": "45662",
    "sg:province": "OH",
    "sg:tags": [
      "alternative",
      "abortion"
    ],
    "wof:name": "Cradle Pregnancy Care Ctr",
    "wof:placetype": "venue"
  },
  "geometry": {"coordinates":[-82.991245,38.734254],"type":"Point"}
}
