{
  "type": "Feature",
  "properties": {
    "iso:country":"US",
    "sg:address":"1102 S Market St",
    "sg:city":"Troy",
    "sg:classifiers":[
        {
            "category":"Retail",
            "subcategory":"Auto Repair",
            "type":"Services"
        }
    ],
    "sg:phone":"+1 937 339 6031",
    "sg:postcode":"45373",
    "sg:province":"OH",
    "sg:tags":[
        "repairing",
        "automobile"
    ],
    "wof:name":"Muffler Brothers",
    "wof:placetype":"venue"
},
  "geometry": {"coordinates":[-84.201331,40.021886],"type":"Point"}
}