{
  "type": "Feature",
  "properties": {
    "addr:full":"2109 Adelbert Rd Cleveland OH 44106",
    "addr:housenumber":"2109",
    "addr:postcode":"44106",
    "addr:street":"Adelbert Rd",
    "iso:country":"US",
    "sg:address":"2109 Adelbert Rd",
    "sg:city":"Cleveland",
    "sg:classifiers":[
        {
            "category":"Shopping",
            "subcategory":"Books",
            "type":"Retail Goods"
        }
    ],
    "sg:phone":"+1 216 368 3464",
    "sg:postcode":"44106",
    "sg:province":"OH",
    "sg:tags":[
        "equipment"
    ],
    "wof:name":"Health Science Bookstore",
    "wof:placetype":"venue"
},
  "geometry": {"coordinates":[-81.60670399999999,41.504723],"type":"Point"}
}