{
  "type": "Feature",
  "properties": {
    "iso:country":"US",
    "sg:address":"6039 Mayfield Rd",
    "sg:city":"Cleveland",
    "sg:classifiers":[
        {
            "category":"Retail",
            "subcategory":"Auto Repair",
            "type":"Services"
        }
    ],
    "sg:phone":"+1 440 995 1030",
    "sg:postcode":"44124",
    "sg:province":"OH",
    "sg:tags":[
        "repairing",
        "automobile"
    ],
    "wof:name":"Brake Pad Inc",
    "wof:placetype":"venue"
},
  "geometry": {"coordinates":[-81.46260100000001,41.520137],"type":"Point"}
}