{
  "type": "Feature",
  "properties": {
    "addr:full": "30 Gambier Cir Cincinnati OH 45218",
    "addr:housenumber": "30",
    "addr:postcode": "45218",
    "addr:street": "Gambier Cir",
    "iso:country": "US",
    "sg:address": "30 Gambier Cir",
    "sg:city": "Cincinnati",
    "sg:classifiers": [
      {
        "category": "Wholesale",
        "subcategory": "Scrap",
        "type": "Manufacturing \u0026 Wholesale Goods"
      }
    ],
    "sg:phone": "+1 513 851 7138",
    "sg:postcode": "45218",
    "sg:province": "OH",
    "sg:tags": [
      "material"
    ],
    "wof:name": "S\u0026M Scrap \u0026 Fabrication Inc",
    "wof:placetype": "venue"
  },
  "geometry": {"coordinates":[-84.516607,39.268675],"type":"Point"}
}
