{
  "type": "Feature",
  "properties": {
    "addr:full":"17870 Mayfield Rd Windsor OH 44099",
    "addr:housenumber":"17870",
    "addr:postcode":"44099",
    "addr:street":"Mayfield Rd",
    "iso:country":"US",
    "sg:address":"17870 Mayfield Rd",
    "sg:city":"Windsor",
    "sg:classifiers":[
        {
            "category":"Government",
            "subcategory":"Office",
            "type":"Public Place"
        }
    ],
    "sg:phone":"+1 440 636 9809",
    "sg:postcode":"44099",
    "sg:province":"OH",
    "sg:tags":[
        "county"
    ],
    "wof:name":"County Line Wood Products",
    "wof:placetype":"venue"
},
  "geometry": {"coordinates":[-81.00443199999999,41.535149],"type":"Point"}
}