{
  "type": "Feature",
  "properties": {
    "addr:full": "1435 State Rte 43 Mogadore OH 44260",
    "addr:housenumber": "1435",
    "addr:postcode": "44260",
    "addr:street": "State Rte 43",
    "iso:country": "US",
    "sg:address": "1435 State Rte 43",
    "sg:city": "Mogadore",
    "sg:classifiers": [
      {
        "category": "Food \u0026 Beverages",
        "subcategory": "Liquor \u0026 Beverages",
        "type": "Retail Goods"
      }
    ],
    "sg:phone": "+1 330 628 9782",
    "sg:postcode": "44260",
    "sg:province": "OH",
    "sg:tags": [
      "beer",
      "ale",
      "alcoholic"
    ],
    "wof:name": "Suffield Carry Out",
    "wof:placetype": "venue"
  },
  "geometry": {"coordinates":[-81.347403,41.033361],"type":"Point"}
}
