{
  "type": "Feature",
  "properties": {
    "addr:full": "7718 E Linden Ln Cleveland OH 44130",
    "addr:housenumber": "7718",
    "addr:postcode": "44130",
    "addr:street": "E Linden Ln",
    "iso:country": "US",
    "sg:address": "7718 E Linden Ln",
    "sg:city": "Cleveland",
    "sg:classifiers": [
      {
        "category": "Building \u0026 Trades",
        "subcategory": "Construction",
        "type": "Services"
      }
    ],
    "sg:phone": "+1 440 842 4498",
    "sg:postcode": "44130",
    "sg:province": "OH",
    "sg:tags": [
      "home",
      "contractor",
      "family",
      "roofing"
    ],
    "wof:name": "Thomas Brothers Construction",
    "wof:placetype": "venue"
  },
  "geometry": {"coordinates":[-81.773924,41.35334],"type":"Point"}
}
