{
  "type": "Feature",
  "properties": {
    "addr:full": "530 Lakeview Plaza Blvd Worthington OH 43085",
    "addr:housenumber": "530",
    "addr:postcode": "43085",
    "addr:street": "Lakeview Plaza Blvd",
    "iso:country": "US",
    "sg:address": "530 Lakeview Plaza Blvd",
    "sg:city": "Worthington",
    "sg:classifiers": [
      {
        "category": "Wholesale",
        "subcategory": "Farm Supplies",
        "type": "Manufacturing \u0026 Wholesale Goods"
      }
    ],
    "sg:phone": "+1 614 880 9076",
    "sg:postcode": "43085",
    "sg:province": "OH",
    "sg:tags": [
      "alfalfa",
      "product"
    ],
    "wof:name": "Batelle Special Support Site",
    "wof:placetype": "venue"
  },
  "geometry": {"coordinates":[-83.00186,40.113414],"type":"Point"}
}
