{
  "type": "Feature",
  "properties": {
    "iso:country":"US",
    "sg:address":"530 Lakeview Plaza Blvd",
    "sg:city":"Worthington",
    "sg:classifiers":[
        {
            "category":"Wholesale",
            "subcategory":"Farm Supplies",
            "type":"Manufacturing & Wholesale Goods"
        }
    ],
    "sg:phone":"+1 614 880 9076",
    "sg:postcode":"43085",
    "sg:province":"OH",
    "sg:tags":[
        "alfalfa",
        "product"
    ],
    "wof:name":"Batelle Special Support Site",
    "wof:placetype":"venue"
},
  "geometry": {"coordinates":[-83.00185999999999,40.113414],"type":"Point"}
}