{
  "type": "Feature",
  "properties": {
    "addr:full": "10044 Danville Rd Bloomingburg OH 43106",
    "addr:housenumber": "10044",
    "addr:postcode": "43106",
    "addr:street": "Danville Rd",
    "iso:country": "US",
    "sg:address": "10044 Danville Rd",
    "sg:city": "Bloomingburg",
    "sg:classifiers": [
      {
        "category": "Building \u0026 Trades",
        "subcategory": "Construction",
        "type": "Services"
      }
    ],
    "sg:phone": "+1 740 437 7267",
    "sg:postcode": "43106",
    "sg:province": "OH",
    "sg:tags": [
      "farm",
      "house",
      "corn",
      "soybean"
    ],
    "wof:name": "Miller Greg Farm",
    "wof:placetype": "venue"
  },
  "geometry": {"coordinates":[-83.404419,39.688098],"type":"Point"}
}
