{
  "type": "Feature",
  "properties": {
    "addr:full": "27016 Knickerbocker Rd Bay Village OH 44140",
    "addr:postcode": "27016;44140",
    "addr:street": "Knickerbocker Rd",
    "iso:country": "US",
    "sg:address": "27016 Knickerbocker Rd",
    "sg:city": "Bay Village",
    "sg:classifiers": [
      {
        "category": "Home \u0026 Garden",
        "subcategory": "Building Materials",
        "type": "Retail Goods"
      }
    ],
    "sg:phone": "+1 440 892 3580",
    "sg:postcode": "44140",
    "sg:province": "OH",
    "wof:name": "Bobs Cabinet Center",
    "wof:placetype": "venue"
  },
  "geometry": {"coordinates":[-81.919092,41.478249],"type":"Point"}
}
