{
  "type": "Feature",
  "properties": {
    "iso:country":"US",
    "sg:address":"27016 Knickerbocker Rd",
    "sg:city":"Bay Village",
    "sg:classifiers":[
        {
            "category":"Home & Garden",
            "subcategory":"Building Materials",
            "type":"Retail Goods"
        }
    ],
    "sg:phone":"+1 440 892 3580",
    "sg:postcode":"44140",
    "sg:province":"OH",
    "wof:name":"Bobs Cabinet Center",
    "wof:placetype":"venue"
},
  "geometry": {"coordinates":[-81.91909200000001,41.478249],"type":"Point"}
}