{
  "type": "Feature",
  "properties": {
    "addr:full":"3927 N Bend Rd Cincinnati OH 45211",
    "addr:housenumber":"3927",
    "addr:postcode":"45211",
    "addr:street":"N Bend Rd",
    "iso:country":"US",
    "sg:address":"3927 N Bend Rd",
    "sg:city":"Cincinnati",
    "sg:classifiers":[
        {
            "category":"Retail",
            "subcategory":"Portrait Studio",
            "type":"Services"
        }
    ],
    "sg:phone":"+1 513 661 3195",
    "sg:postcode":"45211",
    "sg:province":"OH",
    "sg:tags":[
        "photography"
    ],
    "sg:website":"www.dimagephoto.com",
    "wof:name":"Distinctive Image",
    "wof:placetype":"venue"
},
  "geometry": {"coordinates":[-84.60616899999999,39.158633],"type":"Point"}
}