{
  "type": "Feature",
  "properties": {
    "iso:country":"US",
    "sg:address":"947 Beechwood Dr",
    "sg:city":"Tallmadge",
    "sg:classifiers":[
        {
            "category":"Professional",
            "subcategory":"Business Services",
            "type":"Services"
        }
    ],
    "sg:phone":"+1 330 633 6582",
    "sg:postcode":"44278",
    "sg:province":"OH",
    "sg:tags":[
        "interior",
        "consultant",
        "design",
        "decorator"
    ],
    "wof:name":"Studio Space Design",
    "wof:placetype":"venue"
},
  "geometry": {"coordinates":[-81.402811,41.095626],"type":"Point"}
}