{
  "type": "Feature",
  "properties": {
    "addr:full": "4220 Prospect Ave Cleveland OH 44103",
    "addr:housenumber": "4220",
    "addr:postcode": "44103",
    "addr:street": "Prospect Ave",
    "iso:country": "US",
    "sg:address": "4220 Prospect Ave",
    "sg:city": "Cleveland",
    "sg:classifiers": [
      {
        "category": "Organizations",
        "subcategory": "Labor Organization",
        "type": "Services"
      }
    ],
    "sg:phone": "+1 216 432 1022",
    "sg:postcode": "44103",
    "sg:province": "OH",
    "sg:website": "www.local860.com",
    "wof:name": "Laborers International Union",
    "wof:placetype": "venue"
  },
  "geometry": {"coordinates":[-81.656753,41.502241],"type":"Point"}
}
