{
  "type": "Feature",
  "properties": {
    "addr:full":"2579 Mardella Dr Dayton OH 45434",
    "addr:housenumber":"2579",
    "addr:postcode":"45434",
    "addr:street":"Mardella Dr",
    "iso:country":"US",
    "sg:address":"2579 Mardella Dr",
    "sg:city":"Dayton",
    "sg:classifiers":[
        {
            "category":"Professional",
            "subcategory":"Business Services",
            "type":"Services"
        }
    ],
    "sg:phone":"+1 937 426 5936",
    "sg:postcode":"45434",
    "sg:province":"OH",
    "sg:tags":[
        "tile",
        "mfg"
    ],
    "wof:name":"Designs By Elizabeth Kitch",
    "wof:placetype":"venue"
},
  "geometry": {"coordinates":[-84.031552,39.716493],"type":"Point"}
}