{
  "type": "Feature",
  "properties": {
    "iso:country":"US",
    "sg:address":"4048 State Rte 108",
    "sg:city":"Leipsic",
    "sg:classifiers":[
        {
            "category":"Professional",
            "subcategory":"Business Services",
            "type":"Services"
        }
    ],
    "sg:phone":"+1 419 876 3500",
    "sg:postcode":"45856",
    "sg:province":"OH",
    "sg:tags":[
        "construction",
        "nonresidential"
    ],
    "wof:name":"Rusty Spade Construction The",
    "wof:placetype":"venue"
},
  "geometry": {"coordinates":[-84.13146,41.118877],"type":"Point"}
}