{
  "type": "Feature",
  "properties": {
    "addr:full": "500 E Royalton Rd Cleveland OH 44147",
    "addr:housenumber": "500",
    "addr:postcode": "44147",
    "addr:street": "E Royalton Rd",
    "iso:country": "US",
    "sg:address": "500 E Royalton Rd",
    "sg:city": "Cleveland",
    "sg:classifiers": [
      {
        "category": "Health Services",
        "subcategory": "Doctor",
        "type": "Services"
      }
    ],
    "sg:phone": "+1 440 526 6630",
    "sg:postcode": "44147",
    "sg:province": "OH",
    "sg:tags": [
      "physician",
      "surgeon"
    ],
    "wof:name": "Pediatricenter Of Cleveland Co",
    "wof:placetype": "venue"
  },
  "geometry": {"coordinates":[-81.683472,41.313734],"type":"Point"}
}
