{
  "type": "Feature",
  "properties": {
    "addr:full": "2969 Lewis Center Way Grove City OH 43123",
    "addr:housenumber": "2969",
    "addr:postcode": "43123",
    "addr:street": "Lewis Center Way",
    "iso:country": "US",
    "sg:address": "2969 Lewis Center Way",
    "sg:city": "Grove City",
    "sg:classifiers": [
      {
        "category": "Professional",
        "subcategory": "Management \u0026 Consulting",
        "type": "Services"
      }
    ],
    "sg:phone": "+1 614 277 0561",
    "sg:postcode": "43123",
    "sg:province": "OH",
    "sg:tags": [
      "personnel",
      "consultant"
    ],
    "wof:name": "Resource Staffing",
    "wof:placetype": "venue"
  },
  "geometry": {"coordinates":[-83.094606,39.896492],"type":"Point"}
}
