{
  "type": "Feature",
  "properties": {
    "iso:country":"US",
    "sg:address":"21625 Chagrin Blvd",
    "sg:city":"Cleveland",
    "sg:classifiers":[
        {
            "category":"Professional",
            "subcategory":"Lawyer & Legal Services",
            "type":"Services"
        }
    ],
    "sg:phone":"+1 216 752 0955",
    "sg:postcode":"44122",
    "sg:province":"OH",
    "sg:tags":[
        "attorney"
    ],
    "sg:website":"www.mezuzah.net",
    "wof:name":"Howard M Cohn Attorneys At Law",
    "wof:placetype":"venue"
},
  "geometry": {"coordinates":[-81.52124499999999,41.464576],"type":"Point"}
}