{
  "type": "Feature",
  "properties": {
    "iso:country":"US",
    "sg:address":"76 S Main St",
    "sg:city":"Akron",
    "sg:classifiers":[
        {
            "category":"Government",
            "subcategory":"Office",
            "type":"Public Place"
        }
    ],
    "sg:phone":"+1 330 374 0256",
    "sg:postcode":"44308",
    "sg:province":"OH",
    "sg:tags":[
        "federal",
        "security"
    ],
    "wof:name":"Us Army Nurse Corps Rep",
    "wof:placetype":"venue"
},
  "geometry": {"coordinates":[-81.517078,41.084663],"type":"Point"}
}