{
  "type": "Feature",
  "properties": {
    "iso:country":"US",
    "sg:address":"3250 W Market St",
    "sg:city":"Fairlawn",
    "sg:classifiers":[
        {
            "category":"Personal",
            "subcategory":"Beauty Salon",
            "type":"Services"
        }
    ],
    "sg:phone":"+1 330 867 3880",
    "sg:postcode":"44333",
    "sg:province":"OH",
    "wof:name":"Studio Hairworks",
    "wof:placetype":"venue"
},
  "geometry": {"coordinates":[-81.619372,41.132607],"type":"Point"}
}