{
  "type": "Feature",
  "properties": {
    "addr:full": "1801 N Michigan St Toledo OH 43611",
    "addr:housenumber": "1801",
    "addr:postcode": "43611",
    "addr:street": "N Michigan St",
    "iso:country": "US",
    "sg:address": "1801 N Michigan St",
    "sg:city": "Toledo",
    "sg:classifiers": [
      {
        "category": "Bars \u0026 Pubs",
        "type": "Food \u0026 Drink"
      }
    ],
    "sg:phone": "+1 419 727 0184",
    "sg:postcode": "43611",
    "sg:province": "OH",
    "wof:name": "Korner Bar",
    "wof:placetype": "venue"
  },
  "geometry": {"coordinates":[-83.515003,41.669281],"type":"Point"}
}
