{
  "type": "Feature",
  "properties": {
    "iso:country":"US",
    "sg:address":"1801 N Michigan St",
    "sg:city":"Toledo",
    "sg:classifiers":[
        {
            "category":"Bars & Pubs",
            "type":"Food & Drink"
        }
    ],
    "sg:phone":"+1 419 727 0184",
    "sg:postcode":"43611",
    "sg:province":"OH",
    "wof:name":"Korner Bar",
    "wof:placetype":"venue"
},
  "geometry": {"coordinates":[-83.51500299999999,41.669281],"type":"Point"}
}