{
  "type": "Feature",
  "properties": {
    "iso:country":"US",
    "sg:address":"10260 Chenowith Rd",
    "sg:city":"South Charleston",
    "sg:phone":"+1 937 462 8777",
    "sg:postcode":"45368",
    "sg:province":"OH",
    "sg:tags":[
        "farm",
        "general",
        "grain",
        "livestock",
        "cash"
    ],
    "wof:name":"Troxell Farms",
    "wof:placetype":"venue"
},
  "geometry": {"coordinates":[-83.615706,39.859615],"type":"Point"}
}