{
  "type": "Feature",
  "properties": {
    "addr:full": "10260 Chenowith Rd South Charleston OH 45368",
    "addr:housenumber": "10260",
    "addr:postcode": "45368",
    "addr:street": "Chenowith Rd",
    "iso:country": "US",
    "sg:address": "10260 Chenowith Rd",
    "sg:city": "South Charleston",
    "sg:phone": "+1 937 462 8777",
    "sg:postcode": "45368",
    "sg:province": "OH",
    "sg:tags": [
      "farm",
      "general",
      "grain",
      "livestock",
      "cash"
    ],
    "wof:name": "Troxell Farms",
    "wof:placetype": "venue"
  },
  "geometry": {"coordinates":[-83.615706,39.859615],"type":"Point"}
}
