{
  "type": "Feature",
  "properties": {
    "addr:full":"2246 Old State Rte 32 Batavia OH 45103",
    "addr:housenumber":"2246",
    "addr:postcode":"45103",
    "addr:street":"Old State Rte 32",
    "iso:country":"US",
    "sg:address":"2246 Old State Rte 32",
    "sg:city":"Batavia",
    "sg:classifiers":[
        {
            "category":"Shopping",
            "type":"Retail Goods"
        }
    ],
    "sg:phone":"+1 513 732 1847",
    "sg:postcode":"45103",
    "sg:province":"OH",
    "sg:tags":[
        "merchandise"
    ],
    "wof:name":"Able Awards",
    "wof:placetype":"venue"
},
  "geometry": {"coordinates":[-84.152945,39.077959],"type":"Point"}
}