{
  "type": "Feature",
  "properties": {
    "addr:full":"205 Key Blvd Pataskala OH 43062",
    "addr:housenumber":"205",
    "addr:postcode":"43062",
    "addr:street":"Key Blvd",
    "iso:country":"US",
    "sg:address":"205 Key Blvd",
    "sg:city":"Pataskala",
    "sg:classifiers":[
        {
            "category":"Building & Trades",
            "subcategory":"Construction",
            "type":"Services"
        }
    ],
    "sg:phone":"+1 740 927 8383",
    "sg:postcode":"43062",
    "sg:province":"OH",
    "sg:tags":[
        "house"
    ],
    "wof:name":"Key Homes",
    "wof:placetype":"venue"
},
  "geometry": {"coordinates":[-82.66763,39.99519],"type":"Point"}
}