{
  "type": "Feature",
  "properties": {
    "addr:full":"430 Blackstone St Washington Ct Hs OH 43160",
    "addr:housenumber":"430",
    "addr:postcode":"43160",
    "addr:street":"Blackstone St",
    "iso:country":"US",
    "sg:address":"430 Blackstone St",
    "sg:city":"Washington Ct Hs",
    "sg:classifiers":[
        {
            "category":"Building & Trades",
            "subcategory":"Plumbing",
            "type":"Services"
        }
    ],
    "sg:phone":"+1 740 335 2900",
    "sg:postcode":"43160",
    "sg:province":"OH",
    "sg:tags":[
        "conditioning",
        "air",
        "system",
        "contractor"
    ],
    "wof:name":"Humble Heating & Air Cond",
    "wof:placetype":"venue"
},
  "geometry": {"coordinates":[-83.430671,39.547794],"type":"Point"}
}