{
  "type": "Feature",
  "properties": {
    "iso:country":"US",
    "sg:address":"5729 Flowerdale Ave",
    "sg:city":"Cleveland",
    "sg:classifiers":[
        {
            "category":"Professional",
            "type":"Services"
        }
    ],
    "sg:phone":"+1 216 741 4929",
    "sg:postcode":"44144",
    "sg:province":"OH",
    "wof:name":"Jennifer L Sobrowski",
    "wof:placetype":"venue"
},
  "geometry": {"coordinates":[-81.7246,41.423557],"type":"Point"}
}