{
  "type": "Feature",
  "properties": {
    "iso:country":"US",
    "sg:address":"2350 S Clinton St",
    "sg:city":"Defiance",
    "sg:classifiers":[
        {
            "category":"Building & Trades",
            "subcategory":"Construction",
            "type":"Services"
        }
    ],
    "sg:phone":"+1 419 784 5899",
    "sg:postcode":"43512",
    "sg:province":"OH",
    "sg:tags":[
        "painter"
    ],
    "wof:name":"T & R Painting & Power Wash",
    "wof:placetype":"venue"
},
  "geometry": {"coordinates":[-84.39715099999999,41.254896],"type":"Point"}
}