{
  "type": "Feature",
  "properties": {
    "addr:full": "2350 S Clinton St Defiance OH 43512",
    "addr:housenumber": "2350",
    "addr:postcode": "43512",
    "addr:street": "S Clinton St",
    "iso:country": "US",
    "sg:address": "2350 S Clinton St",
    "sg:city": "Defiance",
    "sg:classifiers": [
      {
        "category": "Building \u0026 Trades",
        "subcategory": "Construction",
        "type": "Services"
      }
    ],
    "sg:phone": "+1 419 784 5899",
    "sg:postcode": "43512",
    "sg:province": "OH",
    "sg:tags": [
      "painter"
    ],
    "wof:name": "T \u0026 R Painting \u0026 Power Wash",
    "wof:placetype": "venue"
  },
  "geometry": {"coordinates":[-84.397151,41.254896],"type":"Point"}
}
