{
  "type": "Feature",
  "properties": {
    "addr:full": "30311 Clemens Rd Cleveland OH 44145",
    "addr:housenumber": "30311",
    "addr:postcode": "44145",
    "addr:street": "Clemens Rd",
    "iso:country": "US",
    "sg:address": "30311 Clemens Rd",
    "sg:city": "Cleveland",
    "sg:classifiers": [
      {
        "category": "Wholesale",
        "subcategory": "Durable Goods \u0026 Equipment",
        "type": "Manufacturing \u0026 Wholesale Goods"
      },
      {
        "category": "Wholesale",
        "subcategory": "Electrical",
        "type": "Manufacturing \u0026 Wholesale Goods"
      }
    ],
    "sg:phone": "+1 440 835 8698",
    "sg:postcode": "44145",
    "sg:province": "OH",
    "sg:tags": [
      "representative",
      "insulator",
      "manufacturer"
    ],
    "wof:name": "Norm Schwenk \u0026 Associates",
    "wof:placetype": "venue"
  },
  "geometry": {"coordinates":[-81.957166,41.470541],"type":"Point"}
}
