{
  "type": "Feature",
  "properties": {
    "iso:country":"US",
    "sg:address":"30311 Clemens Rd",
    "sg:city":"Cleveland",
    "sg:classifiers":[
        {
            "category":"Wholesale",
            "subcategory":"Durable Goods & Equipment",
            "type":"Manufacturing & Wholesale Goods"
        },
        {
            "category":"Wholesale",
            "subcategory":"Electrical",
            "type":"Manufacturing & Wholesale Goods"
        }
    ],
    "sg:phone":"+1 440 835 8698",
    "sg:postcode":"44145",
    "sg:province":"OH",
    "sg:tags":[
        "representative",
        "insulator",
        "manufacturer"
    ],
    "wof:name":"Norm Schwenk & Associates",
    "wof:placetype":"venue"
},
  "geometry": {"coordinates":[-81.957166,41.470541],"type":"Point"}
}