{
  "type": "Feature",
  "properties": {
    "addr:full": "721 S Main St Mount Vernon OH 43050",
    "addr:housenumber": "721",
    "addr:postcode": "43050",
    "addr:street": "S Main St",
    "iso:country": "US",
    "sg:address": "721 S Main St",
    "sg:city": "Mount Vernon",
    "sg:classifiers": [
      {
        "category": "Building \u0026 Trades",
        "subcategory": "Construction",
        "type": "Services"
      }
    ],
    "sg:phone": "+1 740 397 7956",
    "sg:postcode": "43050",
    "sg:province": "OH",
    "sg:tags": [
      "residential"
    ],
    "wof:name": "Southpark Partnership",
    "wof:placetype": "venue"
  },
  "geometry": {"coordinates":[-82.48653,40.382108],"type":"Point"}
}
