{
  "type": "Feature",
  "properties": {
    "addr:full": "12085 Elkridge Dr Cincinnati OH 45240",
    "addr:housenumber": "12085",
    "addr:postcode": "45240",
    "addr:street": "Elkridge Dr",
    "iso:country": "US",
    "sg:address": "12085 Elkridge Dr",
    "sg:city": "Cincinnati",
    "sg:classifiers": [
      {
        "category": "Manufacturing",
        "subcategory": "Metals",
        "type": "Manufacturing \u0026 Wholesale Goods"
      }
    ],
    "sg:phone": "+1 513 851 4700",
    "sg:postcode": "45240",
    "sg:province": "OH",
    "sg:tags": [
      "machine",
      "screw",
      "product"
    ],
    "wof:name": "Patterson Metal Specialists",
    "wof:placetype": "venue"
  },
  "geometry": {"coordinates":[-84.508523,39.303447],"type":"Point"}
}
