{
  "type": "Feature",
  "properties": {
    "iso:country":"US",
    "sg:address":"9555 Plainfield Rd",
    "sg:city":"Cincinnati",
    "sg:classifiers":[
        {
            "category":"Education",
            "subcategory":"College",
            "type":"Public Place"
        }
    ],
    "sg:phone":"+1 513 745 5600",
    "sg:postcode":"45236",
    "sg:province":"OH",
    "sg:tags":[
        "academic",
        "school"
    ],
    "sg:website":"www.rwc.uc.edu",
    "wof:name":"University Of Cincinnati",
    "wof:placetype":"venue"
},
  "geometry": {"coordinates":[-84.39652700000001,39.234505],"type":"Point"}
}