{
  "type": "Feature",
  "properties": {
    "iso:country":"US",
    "sg:address":"3535 Olentangy River Rd",
    "sg:city":"Columbus",
    "sg:classifiers":[
        {
            "category":"Health Services",
            "subcategory":"Medical Lab",
            "type":"Services"
        }
    ],
    "sg:phone":"+1 614 566 4945",
    "sg:postcode":"43214",
    "sg:province":"OH",
    "sg:tags":[
        "laboratory"
    ],
    "wof:name":"RMH Department of Pathology",
    "wof:placetype":"venue"
},
  "geometry": {"coordinates":[-83.030506,40.030631],"type":"Point"}
}