{
  "type": "Feature",
  "properties": {
    "iso:country":"US",
    "sg:address":"3615 Superior Ave E",
    "sg:city":"Cleveland",
    "sg:classifiers":[
        {
            "category":"Organizations",
            "subcategory":"Non-profit Organization",
            "type":"Services"
        }
    ],
    "sg:phone":"+1 216 431 6070",
    "sg:postcode":"44114",
    "sg:province":"OH",
    "sg:tags":[
        "human"
    ],
    "wof:name":"For The Children",
    "wof:placetype":"venue"
},
  "geometry": {"coordinates":[-81.664812,41.512866],"type":"Point"}
}