{
  "type": "Feature",
  "properties": {
    "addr:full": "3615 Superior Ave E Cleveland OH 44114",
    "addr:housenumber": "3615",
    "addr:postcode": "44114",
    "addr:street": "Superior Ave E",
    "iso:country": "US",
    "sg:address": "3615 Superior Ave E",
    "sg:city": "Cleveland",
    "sg:classifiers": [
      {
        "category": "Organizations",
        "subcategory": "Non-profit Organization",
        "type": "Services"
      }
    ],
    "sg:phone": "+1 216 431 6070",
    "sg:postcode": "44114",
    "sg:province": "OH",
    "sg:tags": [
      "human"
    ],
    "wof:name": "For The Children",
    "wof:placetype": "venue"
  },
  "geometry": {"coordinates":[-81.664812,41.512866],"type":"Point"}
}
