{
  "type": "Feature",
  "properties": {
    "addr:full": "93 W Franklin St Dayton OH 45459",
    "addr:housenumber": "93",
    "addr:postcode": "45459",
    "addr:street": "W Franklin St",
    "iso:country": "US",
    "sg:address": "93 W Franklin St",
    "sg:city": "Dayton",
    "sg:classifiers": [
      {
        "category": "Professional",
        "subcategory": "Management \u0026 Consulting",
        "type": "Services"
      }
    ],
    "sg:phone": "+1 937 433 8330",
    "sg:postcode": "45459",
    "sg:province": "OH",
    "sg:tags": [
      "marketing",
      "program"
    ],
    "wof:name": "Carlsbad Marketing \u0026 Comm",
    "wof:placetype": "venue"
  },
  "geometry": {"coordinates":[-84.163165,39.628357],"type":"Point"}
}
