{
  "type": "Feature",
  "properties": {
    "addr:full":"11865 Hamilton Ave Cincinnati OH 45231",
    "addr:housenumber":"11865",
    "addr:postcode":"45231",
    "addr:street":"Hamilton Ave",
    "iso:country":"US",
    "sg:address":"11865 Hamilton Ave",
    "sg:city":"Cincinnati",
    "sg:classifiers":[
        {
            "category":"Banks & Credit Unions",
            "subcategory":"Bank",
            "type":"Services"
        }
    ],
    "sg:phone":"+1 513 632 3134",
    "sg:postcode":"45231",
    "sg:province":"OH",
    "sg:tags":[
        "national",
        "commercial"
    ],
    "wof:name":"Firstar Bank",
    "wof:placetype":"venue"
},
  "geometry": {"coordinates":[-84.56405700000001,39.296215],"type":"Point"}
}