{
  "type": "Feature",
  "properties": {
    "addr:full": "121 W Main St West Jefferson OH 43162",
    "addr:housenumber": "121",
    "addr:postcode": "43162",
    "addr:street": "W Main St",
    "iso:country": "US",
    "sg:address": "121 W Main St",
    "sg:city": "West Jefferson",
    "sg:classifiers": [
      {
        "category": "Restaurant",
        "type": "Food \u0026 Drink"
      }
    ],
    "sg:menulink": "http://www.allmenus.com/oh/jefferson/19327-flyers-pizza--subs/menu/",
    "sg:phone": "+1 614 879 7777",
    "sg:postcode": "43162",
    "sg:province": "OH",
    "sg:tags": [
      "italian"
    ],
    "wof:name": "Flyers Pizza \u0026 Subs",
    "wof:placetype": "venue"
  },
  "geometry": {"coordinates":[-83.271759,39.944704],"type":"Point"}
}
