{
  "type": "Feature",
  "properties": {
    "addr:full": "3077 Kettering Blvd Kettering OH 45439",
    "addr:housenumber": "3077",
    "addr:postcode": "45439",
    "addr:street": "Kettering Blvd",
    "iso:country": "US",
    "sg:address": "3077 Kettering Blvd",
    "sg:city": "Kettering",
    "sg:classifiers": [
      {
        "category": "Insurance",
        "subcategory": "Insurance Agent",
        "type": "Services"
      }
    ],
    "sg:phone": "+1 937 435 4438",
    "sg:postcode": "45439",
    "sg:province": "OH",
    "wof:name": "Benefits Network Insurance",
    "wof:placetype": "venue"
  },
  "geometry": {"coordinates":[-84.202301,39.707437],"type":"Point"}
}
