{
  "type": "Feature",
  "properties": {
    "addr:full":"1100 Tiffin Ave Findlay OH 45840",
    "addr:housenumber":"1100",
    "addr:postcode":"45840",
    "addr:street":"Tiffin Ave",
    "iso:country":"US",
    "sg:address":"1100 Tiffin Ave",
    "sg:city":"Findlay",
    "sg:classifiers":[
        {
            "category":"Shopping",
            "subcategory":"Pharmacy",
            "type":"Retail Goods"
        }
    ],
    "sg:phone":"+1 419 422 1622",
    "sg:postcode":"45840",
    "sg:province":"OH",
    "wof:name":"Medicine Shoppe",
    "wof:placetype":"venue"
},
  "geometry": {"coordinates":[-83.625192,41.050326],"type":"Point"}
}