{
  "type": "Feature",
  "properties": {
    "addr:full":"26 N Jefferson St Dayton OH 45402",
    "addr:housenumber":"26",
    "addr:postcode":"45402",
    "addr:street":"N Jefferson St",
    "iso:country":"US",
    "sg:address":"26 N Jefferson St",
    "sg:city":"Dayton",
    "sg:classifiers":[
        {
            "category":"Banks & Credit Unions",
            "subcategory":"Financial Services",
            "type":"Services"
        }
    ],
    "sg:phone":"+1 732 329 6370",
    "sg:postcode":"45402",
    "sg:province":"OH",
    "sg:tags":[
        "company",
        "holding"
    ],
    "wof:name":"SBBL Land Holdings LLC",
    "wof:placetype":"venue"
},
  "geometry": {"coordinates":[-84.190274,39.760912],"type":"Point"}
}