{
  "type": "Feature",
  "properties": {
    "addr:full": "5134 Whipple Ave NW Canton OH 44718",
    "addr:housenumber": "5134",
    "addr:postcode": "44718",
    "addr:street": "Whipple Ave Nw",
    "iso:country": "US",
    "sg:address": "5134 Whipple Ave NW",
    "sg:city": "Canton",
    "sg:classifiers": [
      {
        "category": "Professional",
        "subcategory": "Advertising",
        "type": "Services"
      }
    ],
    "sg:phone": "+1 330 492 2679",
    "sg:postcode": "44718",
    "sg:province": "OH",
    "sg:tags": [
      "mailing",
      "shipping"
    ],
    "sg:website": "www.kinkos.com",
    "wof:name": "Fed Ex Kinko's Ofc \u0026 Print Ctr",
    "wof:placetype": "venue"
  },
  "geometry": {"coordinates":[-81.422711,40.857872],"type":"Point"}
}
