{
  "type": "Feature",
  "properties": {
    "addr:full":"3550 US Hwy 22 Circleville OH 43113",
    "addr:housenumber":"3550",
    "addr:postcode":"43113",
    "addr:street":"Us Hwy 22",
    "iso:country":"US",
    "sg:address":"3550 US Hwy 22",
    "sg:city":"Circleville",
    "sg:classifiers":[
        {
            "category":"Real Estate",
            "subcategory":"Real Estate Operator",
            "type":"Services"
        }
    ],
    "sg:phone":"+1 740 477 2736",
    "sg:postcode":"43113",
    "sg:province":"OH",
    "sg:tags":[
        "property",
        "lessor"
    ],
    "wof:name":"Diltz Farm",
    "wof:placetype":"venue"
},
  "geometry": {"coordinates":[-83.01799,39.588951],"type":"Point"}
}