{
  "type": "Feature",
  "properties": {
    "addr:full": "391 Centennial Dr Vienna OH 44473",
    "addr:housenumber": "391",
    "addr:postcode": "44473",
    "addr:street": "Centennial Dr",
    "iso:country": "US",
    "sg:address": "391 Centennial Dr",
    "sg:city": "Vienna",
    "sg:classifiers": [
      {
        "category": "Building \u0026 Trades",
        "subcategory": "Construction",
        "type": "Services"
      }
    ],
    "sg:phone": "+1 330 856 5577",
    "sg:postcode": "44473",
    "sg:province": "OH",
    "sg:tags": [
      "demolition",
      "contractor"
    ],
    "wof:name": "M \u0026 M Demolition Inc",
    "wof:placetype": "venue"
  },
  "geometry": {"coordinates":[-80.653013,41.234052],"type":"Point"}
}
