{
  "type": "Feature",
  "properties": {
    "addr:full": "10431 Cooper Rd NW Johnstown OH 43031",
    "addr:housenumber": "10431",
    "addr:postcode": "43031",
    "addr:street": "Cooper Rd Nw",
    "iso:country": "US",
    "sg:address": "10431 Cooper Rd NW",
    "sg:city": "Johnstown",
    "sg:classifiers": [
      {
        "category": "Building \u0026 Trades",
        "subcategory": "Construction",
        "type": "Services"
      }
    ],
    "sg:phone": "+1 740 404 1386",
    "sg:postcode": "43031",
    "sg:province": "OH",
    "sg:tags": [
      "excavating",
      "contractor"
    ],
    "wof:name": "B2 Services",
    "wof:placetype": "venue"
  },
  "geometry": {"coordinates":[-82.61741,40.199073],"type":"Point"}
}
