{
  "type": "Feature",
  "properties": {
    "iso:country":"US",
    "sg:address":"10431 Cooper Rd NW",
    "sg:city":"Johnstown",
    "sg:classifiers":[
        {
            "category":"Building & Trades",
            "subcategory":"Construction",
            "type":"Services"
        }
    ],
    "sg:phone":"+1 740 404 1386",
    "sg:postcode":"43031",
    "sg:province":"OH",
    "sg:tags":[
        "excavating",
        "contractor"
    ],
    "wof:name":"B2 Services",
    "wof:placetype":"venue"
},
  "geometry": {"coordinates":[-82.61741000000001,40.199073],"type":"Point"}
}