{
  "type": "Feature",
  "properties": {
    "addr:full":"120 N Main St Bellefontaine OH 43311",
    "addr:housenumber":"120",
    "addr:postcode":"43311",
    "addr:street":"N Main St",
    "iso:country":"US",
    "sg:address":"120 N Main St",
    "sg:city":"Bellefontaine",
    "sg:classifiers":[
        {
            "category":"Professional",
            "subcategory":"Employment Agencies",
            "type":"Services"
        }
    ],
    "sg:phone":"+1 937 592 7570",
    "sg:postcode":"43311",
    "sg:province":"OH",
    "sg:tags":[
        "consultant",
        "search",
        "executive"
    ],
    "wof:name":"Navy Recruiting District",
    "wof:placetype":"venue"
},
  "geometry": {"coordinates":[-83.759629,40.36122],"type":"Point"}
}