{
  "type": "Feature",
  "properties": {
    "addr:full":"3139 W Central Ave Toledo OH 43606",
    "addr:housenumber":"3139",
    "addr:postcode":"43606",
    "addr:street":"W Central Ave",
    "iso:country":"US",
    "sg:address":"3139 W Central Ave",
    "sg:city":"Toledo",
    "sg:classifiers":[
        {
            "category":"Food & Beverages",
            "subcategory":"Candy",
            "type":"Retail Goods"
        }
    ],
    "sg:phone":"+1 419 535 0608",
    "sg:postcode":"43606",
    "sg:province":"OH",
    "sg:tags":[
        "confectionery"
    ],
    "wof:name":"Christie's Candies & Mints",
    "wof:placetype":"venue"
},
  "geometry": {"coordinates":[-83.621211,41.677322],"type":"Point"}
}