{
  "type": "Feature",
  "properties": {
    "iso:country":"US",
    "sg:address":"22008 Lorain Rd",
    "sg:city":"Cleveland",
    "sg:classifiers":[
        {
            "category":"Retail",
            "subcategory":"Repair Shop",
            "type":"Services"
        },
        {
            "category":"Home & Garden",
            "subcategory":"Home Furnishings",
            "type":"Retail Goods"
        }
    ],
    "sg:phone":"+1 440 734 6161",
    "sg:postcode":"44126",
    "sg:province":"OH",
    "sg:tags":[
        "upholstery",
        "fabric"
    ],
    "wof:name":"Fabric Showcase",
    "wof:placetype":"venue"
},
  "geometry": {"coordinates":[-81.865647,41.441215],"type":"Point"}
}