{
  "type": "Feature",
  "properties": {
    "addr:full":"51 Hamburg Rd SW Lancaster OH 43130",
    "addr:housenumber":"51",
    "addr:postcode":"43130",
    "addr:street":"Hamburg Rd Sw",
    "iso:country":"US",
    "sg:address":"51 Hamburg Rd SW",
    "sg:city":"Lancaster",
    "sg:classifiers":[
        {
            "category":"Farming",
            "subcategory":"Farm",
            "type":"Manufacturing & Wholesale Goods"
        }
    ],
    "sg:phone":"+1 740 654 7406",
    "sg:postcode":"43130",
    "sg:province":"OH",
    "sg:tags":[
        "crop",
        "general"
    ],
    "wof:name":"Donald Guisinger",
    "wof:placetype":"venue"
},
  "geometry": {"coordinates":[-82.604697,39.69563],"type":"Point"}
}