{
  "type": "Feature",
  "properties": {
    "iso:country":"US",
    "sg:address":"6665 Huntley Rd",
    "sg:city":"Columbus",
    "sg:classifiers":[
        {
            "category":"Retail",
            "subcategory":"Auto Repair",
            "type":"Services"
        }
    ],
    "sg:phone":"+1 614 985 3093",
    "sg:postcode":"43229",
    "sg:province":"OH",
    "sg:tags":[
        "repairing",
        "automobile"
    ],
    "wof:name":"Pj Automotive",
    "wof:placetype":"venue"
},
  "geometry": {"coordinates":[-82.998671,40.10455],"type":"Point"}
}