{
  "type": "Feature",
  "properties": {
    "iso:country":"US",
    "sg:address":"309 N Main St",
    "sg:city":"New Lexington",
    "sg:classifiers":[
        {
            "category":"Organizations",
            "subcategory":"Religious Organization",
            "type":"Services"
        }
    ],
    "sg:phone":"+1 740 342 1348",
    "sg:postcode":"43764",
    "sg:province":"OH",
    "sg:tags":[
        "church"
    ],
    "wof:name":"St Rose Church Rectory",
    "wof:placetype":"venue"
},
  "geometry": {"coordinates":[-82.20894800000001,39.715073],"type":"Point"}
}