{
  "type": "Feature",
  "properties": {
    "addr:full": "309 N Main St New Lexington OH 43764",
    "addr:housenumber": "309",
    "addr:postcode": "43764",
    "addr:street": "N Main St",
    "iso:country": "US",
    "sg:address": "309 N Main St",
    "sg:city": "New Lexington",
    "sg:classifiers": [
      {
        "category": "Organizations",
        "subcategory": "Religious Organization",
        "type": "Services"
      }
    ],
    "sg:phone": "+1 740 342 1348",
    "sg:postcode": "43764",
    "sg:province": "OH",
    "sg:tags": [
      "church"
    ],
    "wof:name": "St Rose Church Rectory",
    "wof:placetype": "venue"
  },
  "geometry": {"coordinates":[-82.208948,39.715073],"type":"Point"}
}
