{
  "type": "Feature",
  "properties": {
    "addr:full": "3106 Warsaw Ave Cincinnati OH 45205",
    "addr:housenumber": "3106",
    "addr:postcode": "45205",
    "addr:street": "Warsaw Ave",
    "iso:country": "US",
    "sg:address": "3106 Warsaw Ave",
    "sg:city": "Cincinnati",
    "sg:classifiers": [
      {
        "category": "Food \u0026 Beverages",
        "subcategory": "Candy",
        "type": "Retail Goods"
      }
    ],
    "sg:phone": "+1 513 921 4700",
    "sg:postcode": "45205",
    "sg:province": "OH",
    "wof:name": "LL Candyzone",
    "wof:placetype": "venue"
  },
  "geometry": {"coordinates":[-84.562975,39.109973],"type":"Point"}
}
