{
  "type": "Feature",
  "properties": {
    "addr:full": "1297 Bethel Rd Columbus OH 43220",
    "addr:housenumber": "1297",
    "addr:postcode": "43220",
    "addr:street": "Bethel Rd",
    "iso:country": "US",
    "sg:address": "1297 Bethel Rd",
    "sg:city": "Columbus",
    "sg:classifiers": [
      {
        "category": "Personal",
        "subcategory": "Tanning Parlor",
        "type": "Services"
      }
    ],
    "sg:phone": "+1 614 459 3774",
    "sg:postcode": "43220",
    "sg:province": "OH",
    "sg:tags": [
      "salon"
    ],
    "wof:name": "Body Works Super Tanning Salon",
    "wof:placetype": "venue"
  },
  "geometry": {"coordinates":[-83.054293,40.063549],"type":"Point"}
}
