{
  "type": "Feature",
  "properties": {
    "iso:country":"US",
    "sg:address":"6100 Drake Rd",
    "sg:city":"Cincinnati",
    "sg:classifiers":[
        {
            "category":"Education",
            "subcategory":"School",
            "type":"Public Place"
        }
    ],
    "sg:phone":"+1 513 272 4703",
    "sg:postcode":"45243",
    "sg:province":"OH",
    "sg:tags":[
        "elementary"
    ],
    "sg:website":"www.ih.k12.oh.us",
    "wof:name":"Indian Hill Elementary School",
    "wof:placetype":"venue"
},
  "geometry": {"coordinates":[-84.345855,39.174736],"type":"Point"}
}