{
  "type": "Feature",
  "properties": {
    "addr:full": "527 Grove Ave Zanesville OH 43701",
    "addr:housenumber": "527",
    "addr:postcode": "43701",
    "addr:street": "Grove Ave",
    "iso:country": "US",
    "sg:address": "527 Grove Ave",
    "sg:city": "Zanesville",
    "sg:classifiers": [
      {
        "category": "Freight",
        "type": "Transportation"
      }
    ],
    "sg:phone": "+1 740 454 0115",
    "sg:postcode": "43701",
    "sg:province": "OH",
    "sg:tags": [
      "firm",
      "distance",
      "long",
      "trucking"
    ],
    "wof:name": "Roadway Express Inc",
    "wof:placetype": "venue"
  },
  "geometry": {"coordinates":[-82.016776,39.915986],"type":"Point"}
}
