{
  "type": "Feature",
  "properties": {
    "addr:full": "457 Carol Ln Elyria OH 44035",
    "addr:housenumber": "457",
    "addr:postcode": "44035",
    "addr:street": "Carol Ln",
    "iso:country": "US",
    "sg:address": "457 Carol Ln",
    "sg:city": "Elyria",
    "sg:classifiers": [
      {
        "category": "Wholesale",
        "subcategory": "Machinery \u0026 Supplies",
        "type": "Manufacturing \u0026 Wholesale Goods"
      }
    ],
    "sg:phone": "+1 440 365 5400",
    "sg:postcode": "44035",
    "sg:province": "OH",
    "sg:tags": [
      "bearing"
    ],
    "wof:name": "Koyo Corp Of USA",
    "wof:placetype": "venue"
  },
  "geometry": {"coordinates":[-82.079702,41.347664],"type":"Point"}
}
