{
  "type": "Feature",
  "properties": {
    "iso:country":"US",
    "sg:address":"457 Carol Ln",
    "sg:city":"Elyria",
    "sg:classifiers":[
        {
            "category":"Wholesale",
            "subcategory":"Machinery & Supplies",
            "type":"Manufacturing & Wholesale Goods"
        }
    ],
    "sg:phone":"+1 440 365 5400",
    "sg:postcode":"44035",
    "sg:province":"OH",
    "sg:tags":[
        "bearing"
    ],
    "wof:name":"Koyo Corp Of USA",
    "wof:placetype":"venue"
},
  "geometry": {"coordinates":[-82.079702,41.347664],"type":"Point"}
}