{
  "type": "Feature",
  "properties": {
    "addr:full":"11135 West St Whitehouse OH 43571",
    "addr:housenumber":"11135",
    "addr:postcode":"43571",
    "addr:street":"West St",
    "iso:country":"US",
    "sg:address":"11135 West St",
    "sg:city":"Whitehouse",
    "sg:classifiers":[
        {
            "category":"Building & Trades",
            "subcategory":"Landscaping Services",
            "type":"Services"
        }
    ],
    "sg:phone":"+1 419 877 9498",
    "sg:postcode":"43571",
    "sg:province":"OH",
    "wof:name":"Bucher Lawn Care",
    "wof:placetype":"venue"
},
  "geometry": {"coordinates":[-83.809259,41.518437],"type":"Point"}
}