{
  "type": "Feature",
  "properties": {
    "addr:full":"3862 E 143rd St Cleveland OH 44128",
    "addr:housenumber":"3862",
    "addr:postcode":"44128",
    "addr:street":"E 143Rd St",
    "iso:country":"US",
    "sg:address":"3862 E 143rd St",
    "sg:city":"Cleveland",
    "sg:classifiers":[
        {
            "category":"Building & Trades",
            "subcategory":"Landscaping Services",
            "type":"Services"
        }
    ],
    "sg:phone":"+1 216 921 7447",
    "sg:postcode":"44128",
    "sg:province":"OH",
    "sg:tags":[
        "landscape"
    ],
    "wof:name":"Stuart Landscaping",
    "wof:placetype":"venue"
},
  "geometry": {"coordinates":[-81.582376,41.456358],"type":"Point"}
}