{
  "type": "Feature",
  "properties": {
    "iso:country":"US",
    "sg:address":"2436 30th St NE",
    "sg:city":"Canton",
    "sg:classifiers":[
        {
            "category":"Government",
            "subcategory":"Office",
            "type":"Public Place"
        }
    ],
    "sg:phone":"+1 330 649 8100",
    "sg:postcode":"44705",
    "sg:province":"OH",
    "sg:tags":[
        "village"
    ],
    "wof:name":"Canton Sewer Dept",
    "wof:placetype":"venue"
},
  "geometry": {"coordinates":[-81.340864,40.830163],"type":"Point"}
}