{
  "type": "Feature",
  "properties": {
    "addr:full": "2436 30th St NE Canton OH 44705",
    "addr:housenumber": "2436",
    "addr:postcode": "44705",
    "addr:street": "30Th St Ne",
    "iso:country": "US",
    "sg:address": "2436 30th St NE",
    "sg:city": "Canton",
    "sg:classifiers": [
      {
        "category": "Government",
        "subcategory": "Office",
        "type": "Public Place"
      }
    ],
    "sg:phone": "+1 330 649 8100",
    "sg:postcode": "44705",
    "sg:province": "OH",
    "sg:tags": [
      "village"
    ],
    "wof:name": "Canton Sewer Dept",
    "wof:placetype": "venue"
  },
  "geometry": {"coordinates":[-81.340864,40.830163],"type":"Point"}
}
