{
  "type": "Feature",
  "properties": {
    "addr:full": "3013 Indianola Ave Columbus OH 43202",
    "addr:housenumber": "3013",
    "addr:postcode": "43202",
    "addr:street": "Indianola Ave",
    "iso:country": "US",
    "sg:address": "3013 Indianola Ave",
    "sg:city": "Columbus",
    "sg:classifiers": [
      {
        "category": "Retail",
        "subcategory": "Laundry \u0026 Dry Cleaning",
        "type": "Services"
      }
    ],
    "sg:phone": "+1 614 262 2535",
    "sg:postcode": "43202",
    "sg:province": "OH",
    "sg:tags": [
      "drycleaning",
      "plant",
      "coin",
      "power"
    ],
    "wof:name": "Imperial Cleaners",
    "wof:placetype": "venue"
  },
  "geometry": {"coordinates":[-83.001663,40.024465],"type":"Point"}
}
