{
  "type": "Feature",
  "properties": {
    "iso:country":"US",
    "sg:address":"5401 Hetzell St",
    "sg:city":"Cincinnati",
    "sg:classifiers":[
        {
            "category":"Building & Trades",
            "subcategory":"Landscaping Services",
            "type":"Services"
        }
    ],
    "sg:phone":"+1 513 271 2332",
    "sg:postcode":"45227",
    "sg:province":"OH",
    "sg:tags":[
        "landscape",
        "contractor"
    ],
    "sg:website":"www.wimberglandscaping.com",
    "wof:name":"Peter A Wimberg Co Inc",
    "wof:placetype":"venue"
},
  "geometry": {"coordinates":[-84.402117,39.157783],"type":"Point"}
}