{
  "type": "Feature",
  "properties": {
    "addr:full":"3658 E 52nd St Cleveland OH 44105",
    "addr:housenumber":"3658",
    "addr:postcode":"44105",
    "addr:street":"E 52Nd St",
    "iso:country":"US",
    "sg:address":"3658 E 52nd St",
    "sg:city":"Cleveland",
    "sg:classifiers":[
        {
            "category":"Bars & Pubs",
            "type":"Food & Drink"
        }
    ],
    "sg:phone":"+1 216 641 3671",
    "sg:postcode":"44105",
    "sg:province":"OH",
    "sg:tags":[
        "bar"
    ],
    "wof:name":"Johns Cafe Inc",
    "wof:placetype":"venue"
},
  "geometry": {"coordinates":[-81.654483,41.457087],"type":"Point"}
}