{
  "type": "Feature",
  "properties": {
    "addr:full":"432 Church St Swanton OH 43558",
    "addr:housenumber":"432",
    "addr:postcode":"43558",
    "addr:street":"Church St",
    "iso:country":"US",
    "sg:address":"432 Church St",
    "sg:city":"Swanton",
    "sg:classifiers":[
        {
            "category":"Government",
            "subcategory":"Fire Station",
            "type":"Public Place"
        }
    ],
    "sg:phone":"+1 419 825 1455",
    "sg:postcode":"43558",
    "sg:province":"OH",
    "sg:tags":[
        "department"
    ],
    "wof:name":"Fire Dept",
    "wof:placetype":"venue"
},
  "geometry": {"coordinates":[-83.88441400000001,41.592185],"type":"Point"}
}