{
  "type": "Feature",
  "properties": {
    "addr:full": "6950 Worthington Galena Rd Worthington OH 43085",
    "addr:housenumber": "6950",
    "addr:postcode": "43085",
    "addr:street": "Worthington Galena Rd",
    "iso:country": "US",
    "sg:address": "6950 Worthington Galena Rd",
    "sg:city": "Worthington",
    "sg:classifiers": [
      {
        "category": "Manufacturing",
        "subcategory": "Rubber \u0026 Plastics",
        "type": "Manufacturing \u0026 Wholesale Goods"
      }
    ],
    "sg:phone": "+1 614 888 9280",
    "sg:postcode": "43085",
    "sg:province": "OH",
    "sg:tags": [
      "product"
    ],
    "sg:website": "www.liqui-box.com",
    "wof:name": "Liqui-Box Corp",
    "wof:placetype": "venue"
  },
  "geometry": {"coordinates":[-83.00201,40.105899],"type":"Point"}
}
