{
  "type": "Feature",
  "properties": {
    "iso:country":"US",
    "sg:address":"6950 Worthington Galena Rd",
    "sg:city":"Worthington",
    "sg:classifiers":[
        {
            "category":"Manufacturing",
            "subcategory":"Rubber & Plastics",
            "type":"Manufacturing & Wholesale Goods"
        }
    ],
    "sg:phone":"+1 614 888 9280",
    "sg:postcode":"43085",
    "sg:province":"OH",
    "sg:tags":[
        "product"
    ],
    "sg:website":"www.liqui-box.com",
    "wof:name":"Liqui-Box Corp",
    "wof:placetype":"venue"
},
  "geometry": {"coordinates":[-83.00201,40.105899],"type":"Point"}
}