{
  "type": "Feature",
  "properties": {
    "addr:full": "706 Blaine Ave Akron OH 44310",
    "addr:housenumber": "706",
    "addr:postcode": "44310",
    "addr:street": "Blaine Ave",
    "iso:country": "US",
    "sg:address": "706 Blaine Ave",
    "sg:city": "Akron",
    "sg:classifiers": [
      {
        "category": "Retail",
        "subcategory": "Repair Shop",
        "type": "Services"
      }
    ],
    "sg:phone": "+1 330 253 1990",
    "sg:postcode": "44310",
    "sg:province": "OH",
    "sg:tags": [
      "equipment",
      "photographic"
    ],
    "wof:name": "H \u0026 L Repair",
    "wof:placetype": "venue"
  },
  "geometry": {"coordinates":[-81.512168,41.102206],"type":"Point"}
}
