{
  "type": "Feature",
  "properties": {
    "iso:country":"US",
    "sg:address":"706 Blaine Ave",
    "sg:city":"Akron",
    "sg:classifiers":[
        {
            "category":"Retail",
            "subcategory":"Repair Shop",
            "type":"Services"
        }
    ],
    "sg:phone":"+1 330 253 1990",
    "sg:postcode":"44310",
    "sg:province":"OH",
    "sg:tags":[
        "equipment",
        "photographic"
    ],
    "wof:name":"H & L Repair",
    "wof:placetype":"venue"
},
  "geometry": {"coordinates":[-81.512168,41.102206],"type":"Point"}
}