{
  "type": "Feature",
  "properties": {
    "addr:full": "2505 Washington Blvd Belpre OH 45714",
    "addr:housenumber": "2505",
    "addr:postcode": "45714",
    "addr:street": "Washington Blvd",
    "iso:country": "US",
    "sg:address": "2505 Washington Blvd",
    "sg:city": "Belpre",
    "sg:classifiers": [
      {
        "category": "Autos \u0026 Motor Vehicles",
        "subcategory": "Motorcycle Sales",
        "type": "Retail Goods"
      }
    ],
    "sg:phone": "+1 740 423 2123",
    "sg:postcode": "45714",
    "sg:province": "OH",
    "sg:tags": [
      "all",
      "terrain"
    ],
    "wof:name": "Buckeye Atv",
    "wof:placetype": "venue"
  },
  "geometry": {"coordinates":[-81.614007,39.279552],"type":"Point"}
}
