{
  "type": "Feature",
  "properties": {
    "iso:country":"US",
    "sg:address":"3049 Reeves Ave",
    "sg:city":"Lorain",
    "sg:classifiers":[
        {
            "category":"Professional",
            "type":"Services"
        }
    ],
    "sg:phone":"+1 440 282 2412",
    "sg:postcode":"44052",
    "sg:province":"OH",
    "wof:name":"Mark Goulding",
    "wof:placetype":"venue"
},
  "geometry": {"coordinates":[-82.20052699999999,41.441891],"type":"Point"}
}