{
  "type": "Feature",
  "properties": {
    "addr:full": "191 Sexton St Struthers OH 44471",
    "addr:housenumber": "191",
    "addr:postcode": "44471",
    "addr:street": "Sexton St",
    "iso:country": "US",
    "sg:address": "191 Sexton St",
    "sg:city": "Struthers",
    "sg:classifiers": [
      {
        "category": "Building \u0026 Trades",
        "subcategory": "Cleaning \u0026 Sanitation",
        "type": "Services"
      }
    ],
    "sg:phone": "+1 330 755 1577",
    "sg:postcode": "44471",
    "sg:province": "OH",
    "sg:tags": [
      "window"
    ],
    "wof:name": "Conzett Window Cleaning",
    "wof:placetype": "venue"
  },
  "geometry": {"coordinates":[-80.598812,41.05378],"type":"Point"}
}
