{
  "type": "Feature",
  "properties": {
    "addr:full": "339 Smith Dr Clayton OH 45315",
    "addr:housenumber": "339",
    "addr:postcode": "45315",
    "addr:street": "Smith Dr",
    "iso:country": "US",
    "sg:address": "339 Smith Dr",
    "sg:city": "Clayton",
    "sg:classifiers": [
      {
        "category": "Manufacturing",
        "subcategory": "Rubber \u0026 Plastics",
        "type": "Manufacturing \u0026 Wholesale Goods"
      }
    ],
    "sg:phone": "+1 937 836 0010",
    "sg:postcode": "45315",
    "sg:province": "OH",
    "wof:name": "Diamond Tool \u0026 Engineering",
    "wof:placetype": "venue"
  },
  "geometry": {"coordinates":[-84.324337,39.85683],"type":"Point"}
}
