{
  "type": "Feature",
  "properties": {
    "iso:country":"US",
    "sg:address":"339 Smith Dr",
    "sg:city":"Clayton",
    "sg:classifiers":[
        {
            "category":"Manufacturing",
            "subcategory":"Rubber & Plastics",
            "type":"Manufacturing & Wholesale Goods"
        }
    ],
    "sg:phone":"+1 937 836 0010",
    "sg:postcode":"45315",
    "sg:province":"OH",
    "wof:name":"Diamond Tool & Engineering",
    "wof:placetype":"venue"
},
  "geometry": {"coordinates":[-84.324337,39.85683],"type":"Point"}
}