{
  "type": "Feature",
  "properties": {
    "addr:full": "67 Lakeshore Dr W Hebron OH 43025",
    "addr:housenumber": "67",
    "addr:postcode": "43025",
    "addr:street": "Lakeshore Dr W",
    "iso:country": "US",
    "sg:address": "67 Lakeshore Dr W",
    "sg:city": "Hebron",
    "sg:classifiers": [
      {
        "category": "Building \u0026 Trades",
        "subcategory": "Plumbing",
        "type": "Services"
      }
    ],
    "sg:phone": "+1 614 519 9110",
    "sg:postcode": "43025",
    "sg:province": "OH",
    "sg:tags": [
      "plumbing",
      "contractor"
    ],
    "wof:name": "Brandywine Plumbing",
    "wof:placetype": "venue"
  },
  "geometry": {"coordinates":[-82.448431,39.936254],"type":"Point"}
}
