{
  "type": "Feature",
  "properties": {
    "iso:country":"US",
    "sg:address":"67 Lakeshore Dr W",
    "sg:city":"Hebron",
    "sg:classifiers":[
        {
            "category":"Building & Trades",
            "subcategory":"Plumbing",
            "type":"Services"
        }
    ],
    "sg:phone":"+1 614 519 9110",
    "sg:postcode":"43025",
    "sg:province":"OH",
    "sg:tags":[
        "plumbing",
        "contractor"
    ],
    "wof:name":"Brandywine Plumbing",
    "wof:placetype":"venue"
},
  "geometry": {"coordinates":[-82.448431,39.936254],"type":"Point"}
}