{
  "type": "Feature",
  "properties": {
    "iso:country":"US",
    "sg:address":"1610 Carrol Ct",
    "sg:city":"Lebanon",
    "sg:classifiers":[
        {
            "category":"Building & Trades",
            "subcategory":"Plumbing",
            "type":"Services"
        }
    ],
    "sg:phone":"+1 513 934 3884",
    "sg:postcode":"45036",
    "sg:province":"OH",
    "sg:tags":[
        "plumbing",
        "contractor"
    ],
    "wof:name":"Pete The Plumber",
    "wof:placetype":"venue"
},
  "geometry": {"coordinates":[-84.20622899999999,39.464163],"type":"Point"}
}