{
  "type": "Feature",
  "properties": {
    "addr:full": "1610 Carrol Ct Lebanon OH 45036",
    "addr:housenumber": "1610",
    "addr:postcode": "45036",
    "addr:street": "Carrol Ct",
    "iso:country": "US",
    "sg:address": "1610 Carrol Ct",
    "sg:city": "Lebanon",
    "sg:classifiers": [
      {
        "category": "Building \u0026 Trades",
        "subcategory": "Plumbing",
        "type": "Services"
      }
    ],
    "sg:phone": "+1 513 934 3884",
    "sg:postcode": "45036",
    "sg:province": "OH",
    "sg:tags": [
      "plumbing",
      "contractor"
    ],
    "wof:name": "Pete The Plumber",
    "wof:placetype": "venue"
  },
  "geometry": {"coordinates":[-84.206229,39.464163],"type":"Point"}
}
