{
  "type": "Feature",
  "properties": {
    "addr:full": "1820 State Rte 19 Bucyrus OH 44820",
    "addr:housenumber": "1820",
    "addr:postcode": "44820",
    "addr:street": "State Rte 19",
    "iso:country": "US",
    "sg:address": "1820 State Rte 19",
    "sg:city": "Bucyrus",
    "sg:classifiers": [
      {
        "category": "Recreation",
        "type": "Entertainment"
      }
    ],
    "sg:phone": "+1 419 562 5411",
    "sg:postcode": "44820",
    "sg:province": "OH",
    "sg:tags": [
      "hall",
      "auditorium"
    ],
    "wof:name": "Whetstone Township Hall",
    "wof:placetype": "venue"
  },
  "geometry": {"coordinates":[-82.907151,40.772596],"type":"Point"}
}
