{
  "type": "Feature",
  "properties": {
    "addr:full": "5743 Westbourne Ave Columbus OH 43213",
    "addr:housenumber": "5743",
    "addr:postcode": "43213",
    "addr:street": "Westbourne Ave",
    "iso:country": "US",
    "sg:address": "5743 Westbourne Ave",
    "sg:city": "Columbus",
    "sg:classifiers": [
      {
        "category": "Shopping",
        "type": "Retail Goods"
      }
    ],
    "sg:phone": "+1 614 322 0940",
    "sg:postcode": "43213",
    "sg:province": "OH",
    "sg:tags": [
      "merchandise"
    ],
    "wof:name": "Ohio Pool Equipment \u0026 Supply C",
    "wof:placetype": "venue"
  },
  "geometry": {"coordinates":[-82.850636,39.984339],"type":"Point"}
}
