{
  "type": "Feature",
  "properties": {
    "addr:full":"4130 Market St Bladensburg OH 43005",
    "addr:housenumber":"4130",
    "addr:postcode":"43005",
    "addr:street":"Market St",
    "iso:country":"US",
    "sg:address":"4130 Market St",
    "sg:city":"Bladensburg",
    "sg:classifiers":[
        {
            "category":"Mining & Drilling",
            "type":"Manufacturing & Wholesale Goods"
        }
    ],
    "sg:phone":"+1 740 668 5711",
    "sg:postcode":"43005",
    "sg:province":"OH",
    "sg:tags":[
        "oil",
        "gas",
        "producer"
    ],
    "wof:name":"Derrick Petroleum",
    "wof:placetype":"venue"
},
  "geometry": {"coordinates":[-82.28256399999999,40.285877],"type":"Point"}
}