{
  "type": "Feature",
  "properties": {
    "addr:full": "2625 E Harbor Rd Port Clinton OH 43452",
    "addr:housenumber": "2625 e",
    "addr:postcode": "43452",
    "addr:street": "Harbor Rd",
    "iso:country": "US",
    "sg:address": "2625 E Harbor Rd",
    "sg:city": "Port Clinton",
    "sg:classifiers": [
      {
        "category": "Autos \u0026 Motor Vehicles",
        "subcategory": "Boat Sales",
        "type": "Retail Goods"
      }
    ],
    "sg:phone": "+1 419 734 6161",
    "sg:postcode": "43452",
    "sg:province": "OH",
    "sg:tags": [
      "propeller"
    ],
    "wof:name": "Port Clinton Prop Repair Inc",
    "wof:placetype": "venue"
  },
  "geometry": {"coordinates":[-82.882387,41.518861],"type":"Point"}
}
