{
  "type": "Feature",
  "properties": {
    "addr:full": "2891 E Waterloo Rd Akron OH 44312",
    "addr:housenumber": "2891",
    "addr:postcode": "44312",
    "addr:street": "E Waterloo Rd",
    "iso:country": "US",
    "sg:address": "2891 E Waterloo Rd",
    "sg:city": "Akron",
    "sg:classifiers": [
      {
        "category": "Shopping",
        "subcategory": "Gifts \u0026 Souvenirs",
        "type": "Retail Goods"
      }
    ],
    "sg:phone": "+1 330 628 3195",
    "sg:postcode": "44312",
    "sg:province": "OH",
    "sg:tags": [
      "shop"
    ],
    "wof:name": "Karen's Hallmark Shop",
    "wof:placetype": "venue"
  },
  "geometry": {"coordinates":[-81.422328,41.030225],"type":"Point"}
}
