{
  "type": "Feature",
  "properties": {
    "iso:country":"US",
    "sg:address":"2891 E Waterloo Rd",
    "sg:city":"Akron",
    "sg:classifiers":[
        {
            "category":"Shopping",
            "subcategory":"Gifts & Souvenirs",
            "type":"Retail Goods"
        }
    ],
    "sg:phone":"+1 330 628 3195",
    "sg:postcode":"44312",
    "sg:province":"OH",
    "sg:tags":[
        "shop"
    ],
    "wof:name":"Karen's Hallmark Shop",
    "wof:placetype":"venue"
},
  "geometry": {"coordinates":[-81.42232799999999,41.030225],"type":"Point"}
}