{
  "type": "Feature",
  "properties": {
    "addr:full":"1795 Columbus Ave Washington Court House OH 43160",
    "addr:housenumber":"1795",
    "addr:postcode":"43160",
    "addr:street":"Columbus Ave",
    "iso:country":"US",
    "sg:address":"1795 Columbus Ave",
    "sg:city":"Washington Court House",
    "sg:classifiers":[
        {
            "category":"Shopping",
            "subcategory":"Pharmacy",
            "type":"Retail Goods"
        }
    ],
    "sg:phone":"+1 740 636 2534",
    "sg:postcode":"43160",
    "sg:province":"OH",
    "sg:tags":[
        "photofinishing",
        "laboratory"
    ],
    "wof:name":"CVS",
    "wof:placetype":"venue"
},
  "geometry": {"coordinates":[-83.42539499999999,39.547517],"type":"Point"}
}