{
  "type": "Feature",
  "properties": {
    "iso:country":"US",
    "sg:address":"959 Worthington Woods Loop Rd",
    "sg:city":"Worthington",
    "sg:classifiers":[
        {
            "category":"Real Estate",
            "subcategory":"Real Estate Agent",
            "type":"Services"
        }
    ],
    "sg:phone":"+1 614 436 4442",
    "sg:postcode":"43085",
    "sg:province":"OH",
    "sg:tags":[
        "management"
    ],
    "wof:name":"CMA Investments LLC",
    "wof:placetype":"venue"
},
  "geometry": {"coordinates":[-82.988978,40.118414],"type":"Point"}
}