{
  "type": "Feature",
  "properties": {
    "addr:full":"2944 Washington Blvd Cleveland OH 44118",
    "addr:housenumber":"2944",
    "addr:postcode":"44118",
    "addr:street":"Washington Blvd",
    "iso:country":"US",
    "sg:address":"2944 Washington Blvd",
    "sg:city":"Cleveland",
    "sg:classifiers":[
        {
            "category":"Wholesale",
            "subcategory":"Machinery & Supplies",
            "type":"Manufacturing & Wholesale Goods"
        }
    ],
    "sg:phone":"+1 216 321 6900",
    "sg:postcode":"44118",
    "sg:province":"OH",
    "sg:tags":[
        "equipment",
        "industrial"
    ],
    "wof:name":"Murata Wiedemann Inc",
    "wof:placetype":"venue"
},
  "geometry": {"coordinates":[-81.5754,41.504132],"type":"Point"}
}