{
  "type": "Feature",
  "properties": {
    "addr:full": "621 Broadway St Portsmouth OH 45662",
    "addr:housenumber": "621",
    "addr:postcode": "45662",
    "addr:street": "Broadway St",
    "iso:country": "US",
    "sg:address": "621 Broadway St",
    "sg:city": "Portsmouth",
    "sg:classifiers": [
      {
        "category": "Health Services",
        "subcategory": "Doctor",
        "type": "Services"
      }
    ],
    "sg:phone": "+1 740 353 3236",
    "sg:postcode": "45662",
    "sg:province": "OH",
    "sg:tags": [
      "clinic"
    ],
    "wof:name": "V A Community Based Outpatient",
    "wof:placetype": "venue"
  },
  "geometry": {"coordinates":[-82.97448,38.734893],"type":"Point"}
}
