{
  "type": "Feature",
  "properties": {
    "iso:country":"US",
    "sg:address":"6706 Sandalwood Dr",
    "sg:city":"Gates Mills",
    "sg:classifiers":[
        {
            "category":"Shopping",
            "type":"Retail Goods"
        }
    ],
    "sg:phone":"+1 440 449 6479",
    "sg:postcode":"44040",
    "sg:province":"OH",
    "sg:tags":[
        "merchandise"
    ],
    "wof:name":"MTA Enterprises",
    "wof:placetype":"venue"
},
  "geometry": {"coordinates":[-81.43879200000001,41.540478],"type":"Point"}
}