{
  "type": "Feature",
  "properties": {
    "addr:full": "17330 Broadway Ave Cleveland OH 44137",
    "addr:housenumber": "17330",
    "addr:postcode": "44137",
    "addr:street": "Broadway Ave",
    "iso:country": "US",
    "sg:address": "17330 Broadway Ave",
    "sg:city": "Cleveland",
    "sg:classifiers": [
      {
        "category": "Restaurant",
        "type": "Food \u0026 Drink"
      }
    ],
    "sg:phone": "+1 216 663 7733",
    "sg:postcode": "44137",
    "sg:province": "OH",
    "sg:tags": [
      "caterer"
    ],
    "sg:website": "www.mhcatering.com",
    "wof:name": "Maple Heights Catering",
    "wof:placetype": "venue"
  },
  "geometry": {"coordinates":[-81.557289,41.406128],"type":"Point"}
}
