{
  "type": "Feature",
  "properties": {
    "addr:full":"29 Canterbury Dr Athens OH 45701",
    "addr:housenumber":"29",
    "addr:postcode":"45701",
    "addr:street":"Canterbury Dr",
    "iso:country":"US",
    "sg:address":"29 Canterbury Dr",
    "sg:city":"Athens",
    "sg:classifiers":[
        {
            "category":"Manufacturing",
            "subcategory":"Printing",
            "type":"Manufacturing & Wholesale Goods"
        }
    ],
    "sg:phone":"+1 740 594 3957",
    "sg:postcode":"45701",
    "sg:province":"OH",
    "sg:tags":[
        "publisher",
        "publishing"
    ],
    "wof:name":"Double V Publishing Inc",
    "wof:placetype":"venue"
},
  "geometry": {"coordinates":[-82.099318,39.307345],"type":"Point"}
}