{
  "type": "Feature",
  "properties": {
    "addr:full": "38333 Chase Run Rd Albany OH 45710",
    "addr:housenumber": "38333",
    "addr:postcode": "45710",
    "addr:street": "Chase Run Rd",
    "iso:country": "US",
    "sg:address": "38333 Chase Run Rd",
    "sg:city": "Albany",
    "sg:classifiers": [
      {
        "category": "Home \u0026 Garden",
        "subcategory": "Furniture",
        "type": "Retail Goods"
      }
    ],
    "sg:phone": "+1 740 696 1100",
    "sg:postcode": "45710",
    "sg:province": "OH",
    "sg:tags": [
      "equipment",
      "kitchen",
      "cabinet"
    ],
    "sg:website": "www.kitchensolvers.com",
    "wof:name": "Kitchen Solvers",
    "wof:placetype": "venue"
  },
  "geometry": {"coordinates":[-82.073116,39.180194],"type":"Point"}
}
