{
  "type": "Feature",
  "properties": {
    "iso:country":"US",
    "sg:address":"324 Gay St",
    "sg:city":"Lancaster",
    "sg:classifiers":[
        {
            "category":"Organizations",
            "subcategory":"Religious Organization",
            "type":"Services"
        }
    ],
    "sg:phone":"+1 740 654 2874",
    "sg:postcode":"43130",
    "sg:province":"OH",
    "sg:tags":[
        "church"
    ],
    "wof:name":"St Mark Church",
    "wof:placetype":"venue"
},
  "geometry": {"coordinates":[-82.629711,39.712628],"type":"Point"}
}