{
  "type": "Feature",
  "properties": {
    "iso:country":"US",
    "sg:address":"800 Compton Rd",
    "sg:city":"Cincinnati",
    "sg:classifiers":[
        {
            "category":"Health Services",
            "subcategory":"Doctor",
            "type":"Services"
        }
    ],
    "sg:phone":"+1 513 522 3377",
    "sg:postcode":"45231",
    "sg:province":"OH",
    "sg:tags":[
        "dentist"
    ],
    "wof:name":"Spencer L Fried DDS",
    "wof:placetype":"venue"
},
  "geometry": {"coordinates":[-84.511915,39.233935],"type":"Point"}
}