{
  "type": "Feature",
  "properties": {
    "addr:full":"700 Morse Rd Columbus OH 43214",
    "addr:housenumber":"700",
    "addr:postcode":"43214",
    "addr:street":"Morse Rd",
    "iso:country":"US",
    "sg:address":"700 Morse Rd",
    "sg:city":"Columbus",
    "sg:classifiers":[
        {
            "category":"Communications",
            "type":"Services"
        }
    ],
    "sg:phone":"+1 614 848 4390",
    "sg:postcode":"43214",
    "sg:province":"OH",
    "wof:name":"Communications Workers",
    "wof:placetype":"venue"
},
  "geometry": {"coordinates":[-83.00001899999999,40.06176],"type":"Point"}
}