{
  "type": "Feature",
  "properties": {
    "addr:full":"6908 Hill Rd Berlin Heights OH 44814",
    "addr:housenumber":"6908",
    "addr:postcode":"44814",
    "addr:street":"Hill Rd",
    "iso:country":"US",
    "sg:address":"6908 Hill Rd",
    "sg:city":"Berlin Heights",
    "sg:classifiers":[
        {
            "category":"Building & Trades",
            "subcategory":"Landscaping Services",
            "type":"Services"
        }
    ],
    "sg:phone":"+1 419 588 2026",
    "sg:postcode":"44814",
    "sg:province":"OH",
    "sg:tags":[
        "tree"
    ],
    "wof:name":"Leimeister Cran & Tree Svc",
    "wof:placetype":"venue"
},
  "geometry": {"coordinates":[-82.493864,41.315762],"type":"Point"}
}