{
  "type": "Feature",
  "properties": {
    "addr:full": "11501 W Airport Svc Rd Swanton OH 43558",
    "addr:housenumber": "11501",
    "addr:postcode": "43558",
    "addr:street": "W Airport Svc Rd",
    "iso:country": "US",
    "sg:address": "11501 W Airport Svc Rd",
    "sg:city": "Swanton",
    "sg:classifiers": [
      {
        "category": "Airport",
        "type": "Transportation"
      }
    ],
    "sg:phone": "+1 419 867 0110",
    "sg:postcode": "43558",
    "sg:province": "OH",
    "wof:name": "Maintance Dept",
    "wof:placetype": "venue"
  },
  "geometry": {"coordinates":[-83.815023,41.590391],"type":"Point"}
}
