{
  "type": "Feature",
  "properties": {
    "addr:full": "4765 US Hwy 62 Berlin OH 44654",
    "addr:housenumber": "4765",
    "addr:postcode": "44654",
    "addr:street": "Us Hwy 62",
    "iso:country": "US",
    "sg:address": "4765 US Hwy 62",
    "sg:city": "Berlin",
    "sg:classifiers": [
      {
        "category": "Shopping",
        "subcategory": "Gifts \u0026 Souvenirs",
        "type": "Retail Goods"
      }
    ],
    "sg:phone": "+1 330 893 3990",
    "sg:postcode": "44654",
    "sg:province": "OH",
    "sg:tags": [
      "shop"
    ],
    "wof:name": "Kaufmans Kountry Accents",
    "wof:placetype": "venue"
  },
  "geometry": {"coordinates":[-81.793997,40.561373],"type":"Point"}
}
