{
  "type": "Feature",
  "properties": {
    "iso:country":"US",
    "sg:address":"4765 US Hwy 62",
    "sg:city":"Berlin",
    "sg:classifiers":[
        {
            "category":"Shopping",
            "subcategory":"Gifts & Souvenirs",
            "type":"Retail Goods"
        }
    ],
    "sg:phone":"+1 330 893 3990",
    "sg:postcode":"44654",
    "sg:province":"OH",
    "sg:tags":[
        "shop"
    ],
    "wof:name":"Kaufmans Kountry Accents",
    "wof:placetype":"venue"
},
  "geometry": {"coordinates":[-81.793997,40.561373],"type":"Point"}
}