{
  "type": "Feature",
  "properties": {
    "addr:full":"1441 Joyce Ave Columbus OH 43219",
    "addr:housenumber":"1441",
    "addr:postcode":"43219",
    "addr:street":"Joyce Ave",
    "iso:country":"US",
    "sg:address":"1441 Joyce Ave",
    "sg:city":"Columbus",
    "sg:classifiers":[
        {
            "category":"Autos & Motor Vehicles",
            "subcategory":"Automobile Sales",
            "type":"Retail Goods"
        },
        {
            "category":"Wholesale",
            "subcategory":"Scrap",
            "type":"Manufacturing & Wholesale Goods"
        },
        {
            "category":"Autos & Motor Vehicles",
            "subcategory":"Auto Supplies",
            "type":"Retail Goods"
        }
    ],
    "sg:phone":"+1 614 299 2197",
    "sg:postcode":"43219",
    "sg:province":"OH",
    "sg:tags":[
        "wrecking",
        "metal",
        "accessory",
        "part",
        "truck",
        "supplies-used",
        "rebuilt",
        "metals-wholesale",
        "salvage"
    ],
    "wof:name":"All City Auto Recycling",
    "wof:placetype":"venue"
},
  "geometry": {"coordinates":[-82.965891,39.996686],"type":"Point"}
}