{
  "type": "Feature",
  "properties": {
    "addr:full": "10395 Squires Ct Painesville OH 44077",
    "addr:housenumber": "10395",
    "addr:postcode": "44077",
    "addr:street": "Squires Ct",
    "iso:country": "US",
    "sg:address": "10395 Squires Ct",
    "sg:city": "Painesville",
    "sg:classifiers": [
      {
        "category": "Manufacturing",
        "subcategory": "Tools \u0026 Machinery",
        "type": "Manufacturing \u0026 Wholesale Goods"
      }
    ],
    "sg:phone": "+1 440 639 9801",
    "sg:postcode": "44077",
    "sg:province": "OH",
    "sg:tags": [
      "machine",
      "shop",
      "custom"
    ],
    "wof:name": "Accesories Tools",
    "wof:placetype": "venue"
  },
  "geometry": {"coordinates":[-81.265658,41.695189],"type":"Point"}
}
