{
  "type": "Feature",
  "properties": {
    "addr:full":"211 E Center St Bellevue OH 44811",
    "addr:housenumber":"211",
    "addr:postcode":"44811",
    "addr:street":"E Center St",
    "iso:country":"US",
    "sg:address":"211 E Center St",
    "sg:city":"Bellevue",
    "sg:classifiers":[
        {
            "category":"Wholesale",
            "subcategory":"Auto Parts",
            "type":"Manufacturing & Wholesale Goods"
        }
    ],
    "sg:phone":"+1 419 483 3479",
    "sg:postcode":"44811",
    "sg:province":"OH",
    "sg:tags":[
        "supply"
    ],
    "wof:name":"S & S Auto Supply",
    "wof:placetype":"venue"
},
  "geometry": {"coordinates":[-82.83857999999999,41.272276],"type":"Point"}
}