{
  "type": "Feature",
  "properties": {
    "iso:country":"US",
    "sg:address":"4214 Crispin Ct",
    "sg:city":"Grove City",
    "sg:classifiers":[
        {
            "category":"Building & Trades",
            "subcategory":"Construction",
            "type":"Services"
        }
    ],
    "sg:phone":"+1 614 801 9230",
    "sg:postcode":"43123",
    "sg:province":"OH",
    "sg:tags":[
        "masonry",
        "contractor"
    ],
    "wof:name":"Utmost Renovations",
    "wof:placetype":"venue"
},
  "geometry": {"coordinates":[-83.115268,39.884644],"type":"Point"}
}