{
  "type": "Feature",
  "properties": {
    "addr:full": "75 Rice Park Dr Avon Lake OH 44012",
    "addr:housenumber": "75",
    "addr:postcode": "44012",
    "addr:street": "Rice Park Dr",
    "iso:country": "US",
    "sg:address": "75 Rice Park Dr",
    "sg:city": "Avon Lake",
    "sg:classifiers": [
      {
        "category": "Shopping",
        "subcategory": "Computers \u0026 Home Electronics",
        "type": "Retail Goods"
      }
    ],
    "sg:phone": "+1 440 930 4770",
    "sg:postcode": "44012",
    "sg:province": "OH",
    "sg:tags": [
      "equipment",
      "electronic",
      "supply"
    ],
    "wof:name": "Double D Diversified",
    "wof:placetype": "venue"
  },
  "geometry": {"coordinates":[-82.009262,41.513786],"type":"Point"}
}
