{
  "type": "Feature",
  "properties": {
    "iso:country":"US",
    "sg:address":"75 Rice Park Dr",
    "sg:city":"Avon Lake",
    "sg:classifiers":[
        {
            "category":"Shopping",
            "subcategory":"Computers & Home Electronics",
            "type":"Retail Goods"
        }
    ],
    "sg:phone":"+1 440 930 4770",
    "sg:postcode":"44012",
    "sg:province":"OH",
    "sg:tags":[
        "equipment",
        "electronic",
        "supply"
    ],
    "wof:name":"Double D Diversified",
    "wof:placetype":"venue"
},
  "geometry": {"coordinates":[-82.009262,41.513786],"type":"Point"}
}