{
  "type": "Feature",
  "properties": {
    "addr:full": "8508 Beechmont Ave Cincinnati OH 45255",
    "addr:housenumber": "8508",
    "addr:postcode": "45255",
    "addr:street": "Beechmont Ave",
    "iso:country": "US",
    "sg:address": "8508 Beechmont Ave",
    "sg:city": "Cincinnati",
    "sg:classifiers": [
      {
        "category": "Wholesale",
        "subcategory": "Hardware",
        "type": "Manufacturing \u0026 Wholesale Goods"
      }
    ],
    "sg:phone": "+1 513 474 3077",
    "sg:postcode": "45255",
    "sg:province": "OH",
    "sg:tags": [
      "dust",
      "collecting",
      "system"
    ],
    "wof:name": "Ritchie Industrial Marketing",
    "wof:placetype": "venue"
  },
  "geometry": {"coordinates":[-84.317154,39.072183],"type":"Point"}
}
