{
  "type": "Feature",
  "properties": {
    "addr:full": "857 Jonathan St Amherst OH 44001",
    "addr:housenumber": "857",
    "addr:postcode": "44001",
    "addr:street": "Jonathan St",
    "iso:country": "US",
    "sg:address": "857 Jonathan St",
    "sg:city": "Amherst",
    "sg:classifiers": [
      {
        "category": "Communications",
        "subcategory": "Film \u0026 Video Production",
        "type": "Services"
      }
    ],
    "sg:phone": "+1 440 988 7400",
    "sg:postcode": "44001",
    "sg:province": "OH",
    "sg:tags": [
      "taping"
    ],
    "wof:name": "Melendez Video Svc",
    "wof:placetype": "venue"
  },
  "geometry": {"coordinates":[-82.245046,41.409544],"type":"Point"}
}
