{
  "type": "Feature",
  "properties": {
    "iso:country":"US",
    "sg:address":"248 Yacht Club Dr",
    "sg:city":"Fremont",
    "sg:classifiers":[
        {
            "category":"Real Estate",
            "subcategory":"Real Estate Operator",
            "type":"Services"
        }
    ],
    "sg:phone":"+1 419 332 1329",
    "sg:postcode":"43420",
    "sg:province":"OH",
    "sg:tags":[
        "building",
        "nonresidential"
    ],
    "wof:name":"Pt Properties of Fremont LLC",
    "wof:placetype":"venue"
},
  "geometry": {"coordinates":[-83.100252,41.3721],"type":"Point"}
}