{
  "type": "Feature",
  "properties": {
    "iso:country":"US",
    "sg:address":"12797 Mayfield Rd",
    "sg:city":"Chardon",
    "sg:classifiers":[
        {
            "category":"Restaurant",
            "type":"Food & Drink"
        }
    ],
    "sg:phone":"+1 440 285 4008",
    "sg:postcode":"44024",
    "sg:province":"OH",
    "sg:tags":[
        "eating"
    ],
    "wof:name":"Diamonds In Ruff",
    "wof:placetype":"venue"
},
  "geometry": {"coordinates":[-81.18895999999999,41.53307],"type":"Point"}
}