{
  "type": "Feature",
  "properties": {
    "addr:full":"850 State Rte 97 E Bellville OH 44813",
    "addr:housenumber":"850",
    "addr:postcode":"44813",
    "addr:street":"State Rte 97 E",
    "iso:country":"US",
    "sg:address":"850 State Rte 97 E",
    "sg:city":"Bellville",
    "sg:classifiers":[
        {
            "category":"Restaurant",
            "type":"Food & Drink"
        }
    ],
    "sg:phone":"+1 419 886 3505",
    "sg:postcode":"44813",
    "sg:province":"OH",
    "sg:website":"www.mcdonalds.com",
    "wof:name":"Mc Donald's",
    "wof:placetype":"venue"
},
  "geometry": {"coordinates":[-82.482356,40.609576],"type":"Point"}
}