{
  "type": "Feature",
  "properties": {
    "iso:country":"US",
    "sg:address":"280 Looney Rd",
    "sg:city":"Piqua",
    "sg:classifiers":[
        {
            "category":"Health Services",
            "subcategory":"Clinic",
            "type":"Services"
        }
    ],
    "sg:phone":"+1 937 440 7356",
    "sg:postcode":"45356",
    "sg:province":"OH",
    "sg:tags":[
        "outpatient",
        "center"
    ],
    "wof:name":"Outpatient Care Center/North",
    "wof:placetype":"venue"
},
  "geometry": {"coordinates":[-84.216921,40.149129],"type":"Point"}
}