{
  "type": "Feature",
  "properties": {
    "addr:full": "1655 W Market St Akron OH 44313",
    "addr:housenumber": "1655",
    "addr:postcode": "44313",
    "addr:street": "W Market St",
    "iso:country": "US",
    "sg:address": "1655 W Market St",
    "sg:city": "Akron",
    "sg:classifiers": [
      {
        "category": "Professional",
        "subcategory": "Accounting \u0026 Tax Preparation",
        "type": "Services"
      }
    ],
    "sg:phone": "+1 330 867 4733",
    "sg:postcode": "44313",
    "sg:province": "OH",
    "sg:tags": [
      "accountant"
    ],
    "sg:website": "www.seikel.com",
    "wof:name": "Seikel \u0026 Assoc Inc",
    "wof:placetype": "venue"
  },
  "geometry": {"coordinates":[-81.56875,41.109338],"type":"Point"}
}
