{
  "type": "Feature",
  "properties": {
    "iso:country":"US",
    "sg:address":"1655 W Market St",
    "sg:city":"Akron",
    "sg:classifiers":[
        {
            "category":"Professional",
            "subcategory":"Accounting & Tax Preparation",
            "type":"Services"
        }
    ],
    "sg:phone":"+1 330 867 4733",
    "sg:postcode":"44313",
    "sg:province":"OH",
    "sg:tags":[
        "accountant"
    ],
    "sg:website":"www.seikel.com",
    "wof:name":"Seikel & Assoc Inc",
    "wof:placetype":"venue"
},
  "geometry": {"coordinates":[-81.56875,41.109338],"type":"Point"}
}