{
  "type": "Feature",
  "properties": {
    "addr:full":"1845 Progress Ave Columbus OH 43207",
    "addr:housenumber":"1845",
    "addr:postcode":"43207",
    "addr:street":"Progress Ave",
    "iso:country":"US",
    "sg:address":"1845 Progress Ave",
    "sg:city":"Columbus",
    "sg:classifiers":[
        {
            "category":"Wholesale",
            "subcategory":"Stationery",
            "type":"Manufacturing & Wholesale Goods"
        }
    ],
    "sg:phone":"+1 614 443 0303",
    "sg:postcode":"43207",
    "sg:province":"OH",
    "sg:tags":[
        "product",
        "paper"
    ],
    "sg:website":"www.sterling-paper.com",
    "wof:name":"Sterling Paper Co",
    "wof:placetype":"venue"
},
  "geometry": {"coordinates":[-82.947739,39.927039],"type":"Point"}
}