{
  "type": "Feature",
  "properties": {
    "addr:full":"5781 Manchester Rd Akron OH 44319",
    "addr:housenumber":"5781",
    "addr:postcode":"44319",
    "addr:street":"Manchester Rd",
    "iso:country":"US",
    "sg:address":"5781 Manchester Rd",
    "sg:city":"Akron",
    "sg:classifiers":[
        {
            "category":"Social Services",
            "subcategory":"Child Care",
            "type":"Services"
        },
        {
            "category":"Organizations",
            "subcategory":"Religious Organization",
            "type":"Services"
        }
    ],
    "sg:phone":"+1 330 882 4416",
    "sg:postcode":"44319",
    "sg:province":"OH",
    "sg:tags":[
        "kindergarten",
        "academic",
        "school",
        "church"
    ],
    "wof:name":"Manchester Trinity Chapel",
    "wof:placetype":"venue"
},
  "geometry": {"coordinates":[-81.568229,40.945189],"type":"Point"}
}