{
  "type": "Feature",
  "properties": {
    "addr:full": "642 Sugar Ln Elyria OH 44035",
    "addr:housenumber": "642",
    "addr:postcode": "44035",
    "addr:street": "Sugar Ln",
    "iso:country": "US",
    "sg:address": "642 Sugar Ln",
    "sg:city": "Elyria",
    "sg:classifiers": [
      {
        "category": "Wholesale",
        "subcategory": "Petroleum",
        "type": "Manufacturing \u0026 Wholesale Goods"
      }
    ],
    "sg:phone": "+1 440 365 5234",
    "sg:postcode": "44035",
    "sg:province": "OH",
    "sg:tags": [
      "pipe",
      "line",
      "company"
    ],
    "wof:name": "Pipe Line Unique Svc",
    "wof:placetype": "venue"
  },
  "geometry": {"coordinates":[-82.072928,41.361337],"type":"Point"}
}
