{
  "type": "Feature",
  "properties": {
    "addr:full": "105 Virginia St Versailles OH 45380",
    "addr:housenumber": "105",
    "addr:postcode": "45380",
    "addr:street": "Virginia St",
    "iso:country": "US",
    "sg:address": "105 Virginia St",
    "sg:city": "Versailles",
    "sg:classifiers": [
      {
        "category": "Professional",
        "subcategory": "Computer Services",
        "type": "Services"
      }
    ],
    "sg:phone": "+1 937 526 9690",
    "sg:postcode": "45380",
    "sg:province": "OH",
    "sg:tags": [
      "repair"
    ],
    "wof:name": "Village Computers",
    "wof:placetype": "venue"
  },
  "geometry": {"coordinates":[-84.485658,40.219142],"type":"Point"}
}
