{
  "type": "Feature",
  "properties": {
    "addr:full": "106 State Rte 108 Miller City OH 45864",
    "addr:housenumber": "106",
    "addr:postcode": "45864",
    "addr:street": "State Rte 108 Miller",
    "iso:country": "US",
    "sg:address": "106 State Rte 108",
    "sg:city": "Miller City",
    "sg:classifiers": [
      {
        "category": "Building \u0026 Trades",
        "subcategory": "Construction",
        "type": "Services"
      }
    ],
    "sg:phone": "+1 419 876 3333",
    "sg:postcode": "45864",
    "sg:province": "OH",
    "sg:tags": [
      "general",
      "contractor"
    ],
    "wof:name": "Kahle \u0026 Verhoff Construction",
    "wof:placetype": "venue"
  },
  "geometry": {"coordinates":[-84.131253,41.10341],"type":"Point"}
}
