{
  "type": "Feature",
  "properties": {
    "addr:full":"614 Prospect St Elyria OH 44035",
    "addr:housenumber":"614",
    "addr:postcode":"44035",
    "addr:street":"Prospect St",
    "iso:country":"US",
    "sg:address":"614 Prospect St",
    "sg:city":"Elyria",
    "sg:classifiers":[
        {
            "category":"Food & Beverages",
            "subcategory":"Bakery",
            "type":"Retail Goods"
        }
    ],
    "sg:phone":"+1 440 322 6021",
    "sg:postcode":"44035",
    "sg:province":"OH",
    "sg:tags":[
        "baker"
    ],
    "wof:name":"Jeanie's Party Cakes & Supls",
    "wof:placetype":"venue"
},
  "geometry": {"coordinates":[-82.0886,41.362277],"type":"Point"}
}