{
  "type": "Feature",
  "properties": {
    "addr:full": "529 Barnett Ave Newcomerstown OH 43832",
    "addr:housenumber": "529",
    "addr:postcode": "43832",
    "addr:street": "Barnett Ave",
    "iso:country": "US",
    "sg:address": "529 Barnett Ave",
    "sg:city": "Newcomerstown",
    "sg:classifiers": [
      {
        "category": "Manufacturing",
        "subcategory": "Motor Vehicles \u0026 Parts",
        "type": "Manufacturing \u0026 Wholesale Goods"
      }
    ],
    "sg:phone": "+1 740 498 5678",
    "sg:postcode": "43832",
    "sg:province": "OH",
    "sg:tags": [
      "mfg"
    ],
    "wof:name": "Spring David",
    "wof:placetype": "venue"
  },
  "geometry": {"coordinates":[-81.618872,40.265482],"type":"Point"}
}
