{
  "type": "Feature",
  "properties": {
    "addr:full": "2266 Phillips Dr Cuyahoga Falls OH 44223",
    "addr:housenumber": "2266",
    "addr:postcode": "44223",
    "addr:street": "Phillips Dr",
    "iso:country": "US",
    "sg:address": "2266 Phillips Dr",
    "sg:city": "Cuyahoga Falls",
    "sg:classifiers": [
      {
        "category": "Organizations",
        "subcategory": "Religious Organization",
        "type": "Services"
      }
    ],
    "sg:phone": "+1 330 928 2648",
    "sg:postcode": "44223",
    "sg:province": "OH",
    "sg:tags": [
      "clergy"
    ],
    "wof:name": "Frnaklin Lorenz",
    "wof:placetype": "venue"
  },
  "geometry": {"coordinates":[-81.535577,41.158341],"type":"Point"}
}
