{
  "type": "Feature",
  "properties": {
    "iso:country":"US",
    "sg:address":"3439 US Hwy 224 W",
    "sg:city":"Willard",
    "sg:classifiers":[
        {
            "category":"Shopping",
            "subcategory":"Shoes",
            "type":"Retail Goods"
        }
    ],
    "sg:phone":"+1 419 933 4076",
    "sg:postcode":"44890",
    "sg:province":"OH",
    "wof:name":"Ellis Tuttle",
    "wof:placetype":"venue"
},
  "geometry": {"coordinates":[-82.707402,41.031907],"type":"Point"}
}