{
  "type": "Feature",
  "properties": {
    "addr:full": "3704 Lee Rd Cleveland OH 44120",
    "addr:housenumber": "3704",
    "addr:postcode": "44120",
    "addr:street": "Lee Rd",
    "iso:country": "US",
    "sg:address": "3704 Lee Rd",
    "sg:city": "Cleveland",
    "sg:classifiers": [
      {
        "category": "Personal",
        "subcategory": "Barber",
        "type": "Services"
      }
    ],
    "sg:phone": "+1 216 283 1313",
    "sg:postcode": "44120",
    "sg:province": "OH",
    "wof:name": "Barbara's Magic Shop",
    "wof:placetype": "venue"
  },
  "geometry": {"coordinates":[-81.564974,41.457751],"type":"Point"}
}
