{
  "type": "Feature",
  "properties": {
    "addr:full": "544 2nd St NW Carrollton OH 44615",
    "addr:housenumber": "544",
    "addr:postcode": "44615",
    "addr:street": "2Nd St Nw",
    "iso:country": "US",
    "sg:address": "544 2nd St NW",
    "sg:city": "Carrollton",
    "sg:classifiers": [
      {
        "category": "Utilities",
        "subcategory": "Refuse",
        "type": "Services"
      }
    ],
    "sg:phone": "+1 330 627 2559",
    "sg:postcode": "44615",
    "sg:province": "OH",
    "sg:tags": [
      "garbage",
      "collection"
    ],
    "wof:name": "Tippy's Hauling Svc",
    "wof:placetype": "venue"
  },
  "geometry": {"coordinates":[-81.091991,40.577157],"type":"Point"}
}
