{
  "type": "Feature",
  "properties": {
    "addr:full": "525 Mussey Ave Elyria OH 44035",
    "addr:housenumber": "525",
    "addr:postcode": "44035",
    "addr:street": "Mussey Ave",
    "iso:country": "US",
    "sg:address": "525 Mussey Ave",
    "sg:city": "Elyria",
    "sg:classifiers": [
      {
        "category": "Manufacturing",
        "subcategory": "Metals",
        "type": "Manufacturing \u0026 Wholesale Goods"
      }
    ],
    "sg:phone": "+1 440 322 3731",
    "sg:postcode": "44035",
    "sg:province": "OH",
    "sg:tags": [
      "steel",
      "mills"
    ],
    "wof:name": "Maverick Tube Corp",
    "wof:placetype": "venue"
  },
  "geometry": {"coordinates":[-82.11667,41.352913],"type":"Point"}
}
