{
  "type": "Feature",
  "properties": {
    "addr:full":"2323 Quebec Rd Cincinnati OH 45214",
    "addr:housenumber":"2323",
    "addr:postcode":"45214",
    "addr:street":"Quebec Rd",
    "iso:country":"US",
    "sg:address":"2323 Quebec Rd",
    "sg:city":"Cincinnati",
    "sg:classifiers":[
        {
            "category":"Building & Trades",
            "subcategory":"Electrical",
            "type":"Services"
        }
    ],
    "sg:phone":"+1 513 684 9170",
    "sg:postcode":"45214",
    "sg:province":"OH",
    "sg:tags":[
        "electric",
        "contractor"
    ],
    "wof:name":"Solar Solutions Elec Svc Inc",
    "wof:placetype":"venue"
},
  "geometry": {"coordinates":[-84.561871,39.125919],"type":"Point"}
}