{
  "type": "Feature",
  "properties": {
    "iso:country":"US",
    "sg:address":"1264 E 123rd St",
    "sg:city":"Cleveland",
    "sg:classifiers":[
        {
            "category":"Organizations",
            "subcategory":"Non-profit Organization",
            "type":"Services"
        }
    ],
    "sg:phone":"+1 216 268 3909",
    "sg:postcode":"44108",
    "sg:province":"OH",
    "sg:tags":[
        "charitable",
        "institution"
    ],
    "wof:name":"Catholic Charitites Svc",
    "wof:placetype":"venue"
},
  "geometry": {"coordinates":[-81.60101,41.523423],"type":"Point"}
}