{
  "type": "Feature",
  "properties": {
    "iso:country":"US",
    "sg:address":"80 1st Ave",
    "sg:city":"Cleveland",
    "sg:classifiers":[
        {
            "category":"Organizations",
            "subcategory":"Membership Organization",
            "type":"Services"
        }
    ],
    "sg:phone":"+1 440 891 5050",
    "sg:postcode":"44146",
    "sg:province":"OH",
    "sg:tags":[
        "athletic"
    ],
    "wof:name":"Cleveland Browns",
    "wof:placetype":"venue"
},
  "geometry": {"coordinates":[-81.528153,41.380197],"type":"Point"}
}