{
  "type": "Feature",
  "properties": {
    "addr:full":"332 Barrington Ridge Rd Painesville OH 44077",
    "addr:housenumber":"332",
    "addr:postcode":"44077",
    "addr:street":"Barrington Ridge Rd",
    "iso:country":"US",
    "sg:address":"332 Barrington Ridge Rd",
    "sg:city":"Painesville",
    "sg:classifiers":[
        {
            "category":"Wholesale",
            "subcategory":"Metals & Minerals",
            "type":"Manufacturing & Wholesale Goods"
        }
    ],
    "sg:phone":"+1 440 357 9708",
    "sg:postcode":"44077",
    "sg:province":"OH",
    "sg:tags":[
        "center"
    ],
    "wof:name":"Fluid Tite Castings Ltd",
    "wof:placetype":"venue"
},
  "geometry": {"coordinates":[-81.276149,41.688298],"type":"Point"}
}