{
  "type": "Feature",
  "properties": {
    "addr:full":"3279 Pebblebrook Ln Cincinnati OH 45251",
    "addr:housenumber":"3279",
    "addr:postcode":"45251",
    "addr:street":"Pebblebrook Ln",
    "iso:country":"US",
    "sg:address":"3279 Pebblebrook Ln",
    "sg:city":"Cincinnati",
    "sg:classifiers":[
        {
            "category":"Building & Trades",
            "subcategory":"Construction",
            "type":"Services"
        }
    ],
    "sg:phone":"+1 513 741 7523",
    "sg:postcode":"45251",
    "sg:province":"OH",
    "sg:tags":[
        "hanging",
        "contractor"
    ],
    "wof:name":"Elmer L Jones Painting Inc",
    "wof:placetype":"venue"
},
  "geometry": {"coordinates":[-84.587745,39.241529],"type":"Point"}
}