{
  "type": "Feature",
  "properties": {
    "iso:country":"US",
    "sg:address":"2366 Norwood Ave",
    "sg:city":"Cincinnati",
    "sg:classifiers":[
        {
            "category":"Building & Trades",
            "subcategory":"Plumbing",
            "type":"Services"
        }
    ],
    "sg:phone":"+1 513 351 0844",
    "sg:postcode":"45212",
    "sg:province":"OH",
    "sg:tags":[
        "heating",
        "contractor"
    ],
    "wof:name":"Viking HVAC",
    "wof:placetype":"venue"
},
  "geometry": {"coordinates":[-84.446682,39.164246],"type":"Point"}
}