{
  "type": "Feature",
  "properties": {
    "addr:full": "4352 W Sylvania Ave Toledo OH 43623",
    "addr:housenumber": "4352",
    "addr:postcode": "43623",
    "addr:street": "W Sylvania Ave",
    "iso:country": "US",
    "sg:address": "4352 W Sylvania Ave",
    "sg:city": "Toledo",
    "sg:classifiers": [
      {
        "category": "Shopping",
        "subcategory": "Clothing, Apparel, \u0026 Fashions",
        "type": "Retail Goods"
      }
    ],
    "sg:phone": "+1 419 843 4247",
    "sg:postcode": "43623",
    "sg:province": "OH",
    "sg:tags": [
      "wig",
      "toupee",
      "hairpiece"
    ],
    "wof:name": "Hair FX",
    "wof:placetype": "venue"
  },
  "geometry": {"coordinates":[-83.648068,41.691274],"type":"Point"}
}
