{
  "type": "Feature",
  "properties": {
    "addr:full":"1604 Parkman Rd NW Warren OH 44485",
    "addr:housenumber":"1604",
    "addr:postcode":"44485",
    "addr:street":"Parkman Rd Nw",
    "iso:country":"US",
    "sg:address":"1604 Parkman Rd NW",
    "sg:city":"Warren",
    "sg:classifiers":[
        {
            "category":"Restaurant",
            "type":"Food & Drink"
        }
    ],
    "sg:menulink":"http://www.allmenus.com/oh/warren/134203-subway/menu/",
    "sg:phone":"+1 330 395 1604",
    "sg:postcode":"44485",
    "sg:province":"OH",
    "sg:tags":[
        "american",
        "sandwich"
    ],
    "wof:name":"Subway",
    "wof:placetype":"venue"
},
  "geometry": {"coordinates":[-80.843149,41.244767],"type":"Point"}
}