{
  "type": "Feature",
  "properties": {
    "addr:full":"202 S Blackhoof St Wapakoneta OH 45895",
    "addr:housenumber":"202",
    "addr:postcode":"45895",
    "addr:street":"S Blackhoof St",
    "iso:country":"US",
    "sg:address":"202 S Blackhoof St",
    "sg:city":"Wapakoneta",
    "sg:classifiers":[
        {
            "category":"Education",
            "subcategory":"Special Training",
            "type":"Public Place"
        }
    ],
    "sg:phone":"+1 419 738 5606",
    "sg:postcode":"45895",
    "sg:province":"OH",
    "sg:tags":[
        "center"
    ],
    "wof:name":"Cammy's Learning Place",
    "wof:placetype":"venue"
},
  "geometry": {"coordinates":[-84.19613,40.568971],"type":"Point"}
}