{
  "type": "Feature",
  "properties": {
    "addr:full": "5570 Huron St Vermilion OH 44089",
    "addr:housenumber": "5570",
    "addr:postcode": "44089",
    "addr:street": "Huron St",
    "iso:country": "US",
    "sg:address": "5570 Huron St",
    "sg:city": "Vermilion",
    "sg:classifiers": [
      {
        "category": "Professional",
        "subcategory": "Business Services",
        "type": "Services"
      }
    ],
    "sg:phone": "+1 440 967 8500",
    "sg:postcode": "44089",
    "sg:province": "OH",
    "sg:tags": [
      "broker"
    ],
    "wof:name": "Business Latitudes",
    "wof:placetype": "venue"
  },
  "geometry": {"coordinates":[-82.365723,41.424285],"type":"Point"}
}
