{
  "type": "Feature",
  "properties": {
    "addr:full": "327 Town Line Rd Bryan OH 43506",
    "addr:housenumber": "327",
    "addr:postcode": "43506",
    "addr:street": "Town Line Rd",
    "iso:country": "US",
    "sg:address": "327 Town Line Rd",
    "sg:city": "Bryan",
    "sg:classifiers": [
      {
        "category": "Freight",
        "type": "Transportation"
      }
    ],
    "sg:phone": "+1 419 636 0382",
    "sg:postcode": "43506",
    "sg:province": "OH",
    "sg:tags": [
      "operator",
      "local",
      "trucking"
    ],
    "wof:name": "Vitek Trucking",
    "wof:placetype": "venue"
  },
  "geometry": {"coordinates":[-84.573828,41.471116],"type":"Point"}
}
