{
  "type": "Feature",
  "properties": {
    "iso:country":"US",
    "sg:address":"4140 Tuller Rd",
    "sg:city":"Dublin",
    "sg:classifiers":[
        {
            "category":"Wholesale",
            "subcategory":"Machinery & Supplies",
            "type":"Manufacturing & Wholesale Goods"
        },
        {
            "category":"Building & Trades",
            "subcategory":"Plumbing",
            "type":"Services"
        }
    ],
    "sg:phone":"+1 614 760 3473",
    "sg:postcode":"43017",
    "sg:province":"OH",
    "sg:tags":[
        "fire",
        "system",
        "installation",
        "sprinkler",
        "contractor"
    ],
    "wof:name":"Northstar Fire Protection",
    "wof:placetype":"venue"
},
  "geometry": {"coordinates":[-83.09256999999999,40.106909],"type":"Point"}
}