{
  "type": "Feature",
  "properties": {
    "addr:full": "471 Bastogne Dr Akron OH 44303",
    "addr:housenumber": "471",
    "addr:postcode": "44303",
    "addr:street": "Bastogne Dr",
    "iso:country": "US",
    "sg:address": "471 Bastogne Dr",
    "sg:city": "Akron",
    "sg:classifiers": [
      {
        "category": "Shopping",
        "subcategory": "Computers \u0026 Home Electronics",
        "type": "Retail Goods"
      }
    ],
    "sg:phone": "+1 330 873 9677",
    "sg:postcode": "44303",
    "sg:province": "OH",
    "sg:tags": [
      "parts",
      "supply"
    ],
    "wof:name": "Lasercom Systems",
    "wof:placetype": "venue"
  },
  "geometry": {"coordinates":[-81.533517,41.108272],"type":"Point"}
}
