{
  "type": "Feature",
  "properties": {
    "addr:full": "353 Claymore Blvd Cleveland OH 44143",
    "addr:housenumber": "353",
    "addr:postcode": "44143",
    "addr:street": "Claymore Blvd",
    "iso:country": "US",
    "sg:address": "353 Claymore Blvd",
    "sg:city": "Cleveland",
    "sg:classifiers": [
      {
        "category": "Building \u0026 Trades",
        "subcategory": "Equipment Rental",
        "type": "Services"
      }
    ],
    "sg:phone": "+1 216 387 1115",
    "sg:postcode": "44143",
    "sg:province": "OH",
    "wof:name": "Xitron",
    "wof:placetype": "venue"
  },
  "geometry": {"coordinates":[-81.506408,41.561076],"type":"Point"}
}
