{
  "type": "Feature",
  "properties": {
    "iso:country":"US",
    "sg:address":"353 Claymore Blvd",
    "sg:city":"Cleveland",
    "sg:classifiers":[
        {
            "category":"Building & Trades",
            "subcategory":"Equipment Rental",
            "type":"Services"
        }
    ],
    "sg:phone":"+1 216 387 1115",
    "sg:postcode":"44143",
    "sg:province":"OH",
    "wof:name":"Xitron",
    "wof:placetype":"venue"
},
  "geometry": {"coordinates":[-81.506408,41.561076],"type":"Point"}
}