{
  "type": "Feature",
  "properties": {
    "addr:full":"1541 W River Rd N Elyria OH 44035",
    "addr:housenumber":"1541",
    "addr:postcode":"44035",
    "addr:street":"W River Rd N",
    "iso:country":"US",
    "sg:address":"1541 W River Rd N",
    "sg:city":"Elyria",
    "sg:classifiers":[
        {
            "category":"Personal",
            "subcategory":"Beauty Salon",
            "type":"Services"
        }
    ],
    "sg:phone":"+1 440 324 4812",
    "sg:postcode":"44035",
    "sg:province":"OH",
    "sg:tags":[
        "manicuring"
    ],
    "wof:name":"R & K Nails",
    "wof:placetype":"venue"
},
  "geometry": {"coordinates":[-82.10665,41.395029],"type":"Point"}
}