{
  "type": "Feature",
  "properties": {
    "addr:full":"50733 Twp Rd 198 Clarington OH 43915",
    "addr:postcode":"50733;43915",
    "addr:street":"Twp Rd 198",
    "iso:country":"US",
    "sg:address":"50733 Twp Rd 198",
    "sg:city":"Clarington",
    "sg:classifiers":[
        {
            "category":"Farming",
            "subcategory":"Livestock Farm",
            "type":"Manufacturing & Wholesale Goods"
        }
    ],
    "sg:phone":"+1 740 458 1044",
    "sg:postcode":"43915",
    "sg:province":"OH",
    "sg:tags":[
        "beef",
        "feedlot",
        "cattle"
    ],
    "wof:name":"Frederick H Smith",
    "wof:placetype":"venue"
},
  "geometry": {"coordinates":[-80.912252,39.818313],"type":"Point"}
}