{
  "type": "Feature",
  "properties": {
    "addr:full": "3030 Wheeling Rd NE Lancaster OH 43130",
    "addr:housenumber": "3030",
    "addr:postcode": "43130",
    "addr:street": "Wheeling Rd Ne",
    "iso:country": "US",
    "sg:address": "3030 Wheeling Rd NE",
    "sg:city": "Lancaster",
    "sg:classifiers": [
      {
        "category": "Professional",
        "type": "Services"
      }
    ],
    "sg:phone": "+1 740 681 9155",
    "sg:postcode": "43130",
    "sg:province": "OH",
    "wof:name": "Randall W Knorr",
    "wof:placetype": "venue"
  },
  "geometry": {"coordinates":[-82.543292,39.729784],"type":"Point"}
}
