{
  "type": "Feature",
  "properties": {
    "iso:country":"US",
    "sg:address":"8169 State Rte 7",
    "sg:city":"Cheshire",
    "sg:classifiers":[
        {
            "category":"Freight",
            "type":"Transportation"
        }
    ],
    "sg:phone":"+1 740 367 7776",
    "sg:postcode":"45620",
    "sg:province":"OH",
    "sg:tags":[
        "operator",
        "local",
        "trucking"
    ],
    "wof:name":"Dan Swisher Trucking",
    "wof:placetype":"venue"
},
  "geometry": {"coordinates":[-82.106102,38.950793],"type":"Point"}
}