{
  "type": "Feature",
  "properties": {
    "addr:full": "6272 Grape Grove Rd Jamestown OH 45335",
    "addr:housenumber": "6272",
    "addr:postcode": "45335",
    "addr:street": "Grape Grove Rd",
    "iso:country": "US",
    "sg:address": "6272 Grape Grove Rd",
    "sg:city": "Jamestown",
    "sg:classifiers": [
      {
        "category": "Government",
        "subcategory": "Office",
        "type": "Public Place"
      }
    ],
    "sg:phone": "+1 937 675 5931",
    "sg:postcode": "45335",
    "sg:province": "OH",
    "sg:tags": [
      "legislative",
      "body"
    ],
    "wof:name": "Ross Township Trustees",
    "wof:placetype": "venue"
  },
  "geometry": {"coordinates":[-83.692448,39.717204],"type":"Point"}
}
