{
  "type": "Feature",
  "properties": {
    "addr:full": "1007 Valley Side Dr Maumee OH 43537",
    "addr:housenumber": "1007",
    "addr:postcode": "43537",
    "addr:street": "Valley Side Dr",
    "iso:country": "US",
    "sg:address": "1007 Valley Side Dr",
    "sg:city": "Maumee",
    "sg:classifiers": [
      {
        "category": "Utilities",
        "subcategory": "Cable",
        "type": "Services"
      }
    ],
    "sg:phone": "+1 419 897 9322",
    "sg:postcode": "43537",
    "sg:province": "OH",
    "sg:tags": [
      "television"
    ],
    "wof:name": "Rock Cable Services Inc",
    "wof:placetype": "venue"
  },
  "geometry": {"coordinates":[-83.621066,41.583692],"type":"Point"}
}
