{
  "type": "Feature",
  "properties": {
    "addr:full": "6000 Royalton Rd Cleveland OH 44133",
    "addr:housenumber": "6000",
    "addr:postcode": "44133",
    "addr:street": "Royalton Rd",
    "iso:country": "US",
    "sg:address": "6000 Royalton Rd",
    "sg:city": "Cleveland",
    "sg:classifiers": [
      {
        "category": "Food \u0026 Beverages",
        "subcategory": "Groceries \u0026 Convenience Stores",
        "type": "Retail Goods"
      }
    ],
    "sg:phone": "+1 440 237 3061",
    "sg:postcode": "44133",
    "sg:province": "OH",
    "sg:tags": [
      "grocer"
    ],
    "sg:website": "www.gianteagle.com",
    "wof:name": "Giant Eagle",
    "wof:placetype": "venue"
  },
  "geometry": {"coordinates":[-81.728061,41.313806],"type":"Point"}
}
