{
  "type": "Feature",
  "properties": {
    "addr:full": "3805 Marlane Dr Grove City OH 43123",
    "addr:housenumber": "3805",
    "addr:postcode": "43123",
    "addr:street": "Marlane Dr",
    "iso:country": "US",
    "sg:address": "3805 Marlane Dr",
    "sg:city": "Grove City",
    "sg:classifiers": [
      {
        "category": "Education",
        "subcategory": "School",
        "type": "Public Place"
      }
    ],
    "sg:phone": "+1 614 801 8850",
    "sg:postcode": "43123",
    "sg:province": "OH",
    "sg:website": "www.swcs.k12.oh.us",
    "wof:name": "Galloway Ridge Intermediate",
    "wof:placetype": "venue"
  },
  "geometry": {"coordinates":[-83.050567,39.880225],"type":"Point"}
}
