{
  "type": "Feature",
  "properties": {
    "addr:full": "8 W High St Ashley OH 43003",
    "addr:housenumber": "8",
    "addr:postcode": "43003",
    "addr:street": "W High St",
    "iso:country": "US",
    "sg:address": "8 W High St",
    "sg:city": "Ashley",
    "sg:classifiers": [
      {
        "category": "Restaurant",
        "type": "Food \u0026 Drink"
      }
    ],
    "sg:phone": "+1 740 747 2961",
    "sg:postcode": "43003",
    "sg:province": "OH",
    "wof:name": "Gibeye's Pizza \u0026 Pub",
    "wof:placetype": "venue"
  },
  "geometry": {"coordinates":[-82.957317,40.409261],"type":"Point"}
}
