{
  "type": "Feature",
  "properties": {
    "addr:full": "140 E Town St Columbus OH 43215",
    "addr:housenumber": "140",
    "addr:postcode": "43215",
    "addr:street": "E Town St",
    "iso:country": "US",
    "sg:address": "140 E Town St",
    "sg:city": "Columbus",
    "sg:classifiers": [
      {
        "category": "Real Estate",
        "subcategory": "Real Estate Operator",
        "type": "Services"
      }
    ],
    "sg:phone": "+1 614 224 8550",
    "sg:postcode": "43215",
    "sg:province": "OH",
    "sg:tags": [
      "building",
      "parks"
    ],
    "wof:name": "C B Richard Ellis",
    "wof:placetype": "venue"
  },
  "geometry": {"coordinates":[-82.996015,39.959328],"type":"Point"}
}
