{
  "type": "Feature",
  "properties": {
    "iso:country":"US",
    "sg:address":"111 Lylburn Rd",
    "sg:city":"Middletown",
    "sg:classifiers":[
        {
            "category":"Building & Trades",
            "subcategory":"Plumbing",
            "type":"Services"
        }
    ],
    "sg:phone":"+1 513 424 4554",
    "sg:postcode":"45044",
    "sg:province":"OH",
    "sg:tags":[
        "conditioning",
        "air",
        "system",
        "contractor"
    ],
    "wof:name":"Central Heating & Cooling",
    "wof:placetype":"venue"
},
  "geometry": {"coordinates":[-84.361047,39.507609],"type":"Point"}
}