{
  "type": "Feature",
  "properties": {
    "addr:full": "111 Lylburn Rd Middletown OH 45044",
    "addr:housenumber": "111",
    "addr:postcode": "45044",
    "addr:street": "Lylburn Rd",
    "iso:country": "US",
    "sg:address": "111 Lylburn Rd",
    "sg:city": "Middletown",
    "sg:classifiers": [
      {
        "category": "Building \u0026 Trades",
        "subcategory": "Plumbing",
        "type": "Services"
      }
    ],
    "sg:phone": "+1 513 424 4554",
    "sg:postcode": "45044",
    "sg:province": "OH",
    "sg:tags": [
      "conditioning",
      "air",
      "system",
      "contractor"
    ],
    "wof:name": "Central Heating \u0026 Cooling",
    "wof:placetype": "venue"
  },
  "geometry": {"coordinates":[-84.361047,39.507609],"type":"Point"}
}
