{
  "type": "Feature",
  "properties": {
    "iso:country":"US",
    "sg:address":"152 W Main St",
    "sg:city":"Amherst",
    "sg:classifiers":[
        {
            "category":"Education",
            "subcategory":"School",
            "type":"Public Place"
        }
    ],
    "sg:phone":"+1 440 986 7021",
    "sg:postcode":"44001",
    "sg:province":"OH",
    "sg:tags":[
        "middle"
    ],
    "wof:name":"South Amherst Middle School",
    "wof:placetype":"venue"
},
  "geometry": {"coordinates":[-82.24338899999999,41.357559],"type":"Point"}
}