{
  "type": "Feature",
  "properties": {
    "addr:full": "3204 Tremainsville Rd Toledo OH 43613",
    "addr:housenumber": "3204",
    "addr:postcode": "43613",
    "addr:street": "Tremainsville Rd",
    "iso:country": "US",
    "sg:address": "3204 Tremainsville Rd",
    "sg:city": "Toledo",
    "sg:classifiers": [
      {
        "category": "Banks \u0026 Credit Unions",
        "subcategory": "Bank",
        "type": "Services"
      }
    ],
    "sg:phone": "+1 419 473 1940",
    "sg:postcode": "43613",
    "sg:province": "OH",
    "wof:name": "Key Bank",
    "wof:placetype": "venue"
  },
  "geometry": {"coordinates":[-83.621224,41.720889],"type":"Point"}
}
