{
  "type": "Feature",
  "properties": {
    "iso:country":"US",
    "sg:address":"5441 Philothea Rd",
    "sg:city":"Saint Henry",
    "sg:phone":"+1 419 925 5112",
    "sg:postcode":"45883",
    "sg:province":"OH",
    "sg:tags":[
        "farm",
        "corn",
        "wheat",
        "soybean"
    ],
    "wof:name":"Wermert Farm",
    "wof:placetype":"venue"
},
  "geometry": {"coordinates":[-84.593046,40.443638],"type":"Point"}
}