{
  "type": "Feature",
  "properties": {
    "addr:full":"93 Public Sq Medina OH 44256",
    "addr:housenumber":"93",
    "addr:postcode":"44256",
    "addr:street":"Public Sq",
    "iso:country":"US",
    "sg:address":"93 Public Sq",
    "sg:city":"Medina",
    "sg:classifiers":[
        {
            "category":"Government",
            "subcategory":"Court House",
            "type":"Public Place"
        }
    ],
    "sg:phone":"+1 330 725 9736",
    "sg:postcode":"44256",
    "sg:province":"OH",
    "sg:tags":[
        "county"
    ],
    "wof:name":"Common Pleas Court No 2",
    "wof:placetype":"venue"
},
  "geometry": {"coordinates":[-81.86268800000001,41.1389],"type":"Point"}
}