{
  "type": "Feature",
  "properties": {
    "addr:full":"325 W 8th St Cincinnati OH 45202",
    "addr:housenumber":"325",
    "addr:postcode":"45202",
    "addr:street":"W 8Th St",
    "iso:country":"US",
    "sg:address":"325 W 8th St",
    "sg:city":"Cincinnati",
    "sg:classifiers":[
        {
            "category":"Organizations",
            "subcategory":"Religious Organization",
            "type":"Services"
        }
    ],
    "sg:phone":"+1 513 421 5354",
    "sg:postcode":"45202",
    "sg:province":"OH",
    "sg:website":"www.stpeterinchainscathedral.org",
    "wof:name":"St Peter In Chains Cathedral",
    "wof:placetype":"venue"
},
  "geometry": {"coordinates":[-84.52014200000001,39.10365],"type":"Point"}
}