{
  "type": "Feature",
  "properties": {
    "addr:full":"203 Potomac Ave Tallmadge OH 44278",
    "addr:housenumber":"203",
    "addr:postcode":"44278",
    "addr:street":"Potomac Ave",
    "iso:country":"US",
    "sg:address":"203 Potomac Ave",
    "sg:city":"Tallmadge",
    "sg:classifiers":[
        {
            "category":"Manufacturing",
            "subcategory":"Tools & Machinery",
            "type":"Manufacturing & Wholesale Goods"
        }
    ],
    "sg:phone":"+1 330 633 7225",
    "sg:postcode":"44278",
    "sg:province":"OH",
    "sg:tags":[
        "mold"
    ],
    "wof:name":"Feist Mold & Machine",
    "wof:placetype":"venue"
},
  "geometry": {"coordinates":[-81.461169,41.097329],"type":"Point"}
}