{
  "type": "Feature",
  "properties": {
    "addr:full":"120 E Mill St Akron OH 44308",
    "addr:housenumber":"120",
    "addr:postcode":"44308",
    "addr:street":"E Mill St",
    "iso:country":"US",
    "sg:address":"120 E Mill St",
    "sg:city":"Akron",
    "sg:classifiers":[
        {
            "category":"Professional",
            "subcategory":"Advertising",
            "type":"Services"
        }
    ],
    "sg:phone":"+1 330 376 3185",
    "sg:postcode":"44308",
    "sg:province":"OH",
    "wof:name":"Mediacast Advertising",
    "wof:placetype":"venue"
},
  "geometry": {"coordinates":[-81.51531799999999,41.08185],"type":"Point"}
}