{
  "type": "Feature",
  "properties": {
    "iso:country":"US",
    "sg:address":"130 Bellflower Rd NW",
    "sg:city":"Minerva",
    "sg:classifiers":[
        {
            "category":"Autos & Motor Vehicles",
            "subcategory":"Auto Supplies",
            "type":"Retail Goods"
        }
    ],
    "sg:phone":"+1 330 895 2756",
    "sg:postcode":"44657",
    "sg:province":"OH",
    "sg:tags":[
        "tire"
    ],
    "wof:name":"W S Tires Inc",
    "wof:placetype":"venue"
},
  "geometry": {"coordinates":[-81.10124399999999,40.667851],"type":"Point"}
}