{
  "type": "Feature",
  "properties": {
    "addr:full": "3471 Nichols Rd Medina OH 44256",
    "addr:housenumber": "3471",
    "addr:postcode": "44256",
    "addr:street": "Nichols Rd",
    "iso:country": "US",
    "sg:address": "3471 Nichols Rd",
    "sg:city": "Medina",
    "sg:classifiers": [
      {
        "category": "Banks \u0026 Credit Unions",
        "subcategory": "Bank",
        "type": "Services"
      }
    ],
    "sg:phone": "+1 330 725 0527",
    "sg:postcode": "44256",
    "sg:province": "OH",
    "sg:tags": [
      "federal",
      "reserve"
    ],
    "wof:name": "Federal Reserve Bank",
    "wof:placetype": "venue"
  },
  "geometry": {"coordinates":[-81.791087,41.179194],"type":"Point"}
}
