{
  "type": "Feature",
  "properties": {
    "addr:full":"5589 S Rudy Rd Tipp City OH 45371",
    "addr:housenumber":"5589",
    "addr:postcode":"45371",
    "addr:street":"S Rudy Rd",
    "iso:country":"US",
    "sg:address":"5589 S Rudy Rd",
    "sg:city":"Tipp City",
    "sg:classifiers":[
        {
            "category":"Home & Garden",
            "subcategory":"Building Materials",
            "type":"Retail Goods"
        }
    ],
    "sg:phone":"+1 937 667 2300",
    "sg:postcode":"45371",
    "sg:province":"OH",
    "sg:tags":[
        "door",
        "gate",
        "operating",
        "devices"
    ],
    "wof:name":"Door One",
    "wof:placetype":"venue"
},
  "geometry": {"coordinates":[-84.12080899999999,39.946935],"type":"Point"}
}