{
  "type": "Feature",
  "properties": {
    "addr:full":"35836 Center Ridge Rd North Ridgeville OH 44039",
    "addr:housenumber":"35836",
    "addr:postcode":"44039",
    "addr:street":"Center Ridge Rd",
    "iso:country":"US",
    "sg:address":"35836 Center Ridge Rd",
    "sg:city":"North Ridgeville",
    "sg:classifiers":[
        {
            "category":"Health Services",
            "subcategory":"Doctor",
            "type":"Services"
        }
    ],
    "sg:phone":"+1 440 327 9036",
    "sg:postcode":"44039",
    "sg:province":"OH",
    "sg:tags":[
        "dentist"
    ],
    "wof:name":"Casey L O'Conor DDS",
    "wof:placetype":"venue"
},
  "geometry": {"coordinates":[-82.018573,41.390291],"type":"Point"}
}