{
  "type": "Feature",
  "properties": {
    "addr:full": "868 Montford Rd Cleveland OH 44121",
    "addr:housenumber": "868",
    "addr:postcode": "44121",
    "addr:street": "Montford Rd",
    "iso:country": "US",
    "sg:address": "868 Montford Rd",
    "sg:city": "Cleveland",
    "sg:classifiers": [
      {
        "category": "Shopping",
        "subcategory": "Computers \u0026 Home Electronics",
        "type": "Retail Goods"
      }
    ],
    "sg:phone": "+1 216 382 8381",
    "sg:postcode": "44121",
    "sg:province": "OH",
    "sg:tags": [
      "software"
    ],
    "wof:name": "MDB Software Inc",
    "wof:placetype": "venue"
  },
  "geometry": {"coordinates":[-81.540017,41.536061],"type":"Point"}
}
