{
  "type": "Feature",
  "properties": {
    "iso:country":"US",
    "sg:address":"868 Montford Rd",
    "sg:city":"Cleveland",
    "sg:classifiers":[
        {
            "category":"Shopping",
            "subcategory":"Computers & Home Electronics",
            "type":"Retail Goods"
        }
    ],
    "sg:phone":"+1 216 382 8381",
    "sg:postcode":"44121",
    "sg:province":"OH",
    "sg:tags":[
        "software"
    ],
    "wof:name":"MDB Software Inc",
    "wof:placetype":"venue"
},
  "geometry": {"coordinates":[-81.540017,41.536061],"type":"Point"}
}