{
  "type": "Feature",
  "properties": {
    "addr:full": "4589 E Broad St Columbus OH 43213",
    "addr:housenumber": "4589",
    "addr:postcode": "43213",
    "addr:street": "E Broad St",
    "iso:country": "US",
    "sg:address": "4589 E Broad St",
    "sg:city": "Columbus",
    "sg:classifiers": [
      {
        "category": "Sports \u0026 Exercise",
        "subcategory": "Bowling",
        "type": "Entertainment"
      }
    ],
    "sg:phone": "+1 614 861 1600",
    "sg:postcode": "43213",
    "sg:province": "OH",
    "sg:tags": [
      "center",
      "alley"
    ],
    "wof:name": "Holiday Lanes Inc",
    "wof:placetype": "venue"
  },
  "geometry": {"coordinates":[-82.877546,39.975688],"type":"Point"}
}
