{
  "type": "Feature",
  "properties": {
    "iso:country":"US",
    "sg:address":"16775 Milton Ave",
    "sg:city":"Lake Milton",
    "sg:classifiers":[
        {
            "category":"Autos & Motor Vehicles",
            "subcategory":"Automobile Sales",
            "type":"Retail Goods"
        }
    ],
    "sg:phone":"+1 330 654 4527",
    "sg:postcode":"44429",
    "sg:province":"OH",
    "sg:tags":[
        "used"
    ],
    "wof:name":"Sports Unlimited Used Cars",
    "wof:placetype":"venue"
},
  "geometry": {"coordinates":[-80.970557,41.099248],"type":"Point"}
}