{
  "type": "Feature",
  "properties": {
    "addr:full": "10941 Mahoning Ave North Jackson OH 44451",
    "addr:housenumber": "10941",
    "addr:postcode": "44451",
    "addr:street": "Mahoning Ave North",
    "iso:country": "US",
    "sg:address": "10941 Mahoning Ave",
    "sg:city": "North Jackson",
    "sg:classifiers": [
      {
        "category": "Restaurant",
        "type": "Food \u0026 Drink"
      }
    ],
    "sg:phone": "+1 330 538 2263",
    "sg:postcode": "44451",
    "sg:province": "OH",
    "sg:tags": [
      "eating"
    ],
    "wof:name": "Dinos Restaurant \u0026 Pizza",
    "wof:placetype": "venue"
  },
  "geometry": {"coordinates":[-80.856235,41.100067],"type":"Point"}
}
