{
  "type": "Feature",
  "properties": {
    "iso:country":"US",
    "sg:address":"10941 Mahoning Ave",
    "sg:city":"North Jackson",
    "sg:classifiers":[
        {
            "category":"Restaurant",
            "type":"Food & Drink"
        }
    ],
    "sg:phone":"+1 330 538 2263",
    "sg:postcode":"44451",
    "sg:province":"OH",
    "sg:tags":[
        "eating"
    ],
    "wof:name":"Dinos Restaurant & Pizza",
    "wof:placetype":"venue"
},
  "geometry": {"coordinates":[-80.856235,41.100067],"type":"Point"}
}