{
  "type": "Feature",
  "properties": {
    "addr:full": "8188 Asbury Hills Dr Cincinnati OH 45255",
    "addr:housenumber": "8188",
    "addr:postcode": "45255",
    "addr:street": "Asbury Hills Dr",
    "iso:country": "US",
    "sg:address": "8188 Asbury Hills Dr",
    "sg:city": "Cincinnati",
    "sg:classifiers": [
      {
        "category": "Professional",
        "subcategory": "Business Services",
        "type": "Services"
      }
    ],
    "sg:phone": "+1 513 474 2639",
    "sg:postcode": "45255",
    "sg:province": "OH",
    "sg:tags": [
      "interior",
      "consultant",
      "design",
      "decorator"
    ],
    "wof:name": "Interiors By Judyth",
    "wof:placetype": "venue"
  },
  "geometry": {"coordinates":[-84.329433,39.061651],"type":"Point"}
}
