{
  "type": "Feature",
  "properties": {
    "iso:country":"US",
    "sg:address":"45 Cathedral Ln",
    "sg:city":"Cuyahoga Falls",
    "sg:classifiers":[
        {
            "category":"Real Estate",
            "subcategory":"Real Estate Operator",
            "type":"Services"
        }
    ],
    "sg:phone":"+1 330 929 4227",
    "sg:postcode":"44223",
    "sg:province":"OH",
    "sg:tags":[
        "building",
        "apartment"
    ],
    "wof:name":"Portage Trail Village",
    "wof:placetype":"venue"
},
  "geometry": {"coordinates":[-81.509608,41.144393],"type":"Point"}
}