{
  "type": "Feature",
  "properties": {
    "iso:country":"US",
    "sg:address":"330 N Chestnut St",
    "sg:city":"Ravenna",
    "sg:classifiers":[
        {
            "category":"Health Services",
            "subcategory":"Doctor",
            "type":"Services"
        }
    ],
    "sg:phone":"+1 330 296 7256",
    "sg:postcode":"44266",
    "sg:province":"OH",
    "sg:tags":[
        "physician",
        "surgeon"
    ],
    "wof:name":"Portage Regional Gastro",
    "wof:placetype":"venue"
},
  "geometry": {"coordinates":[-81.24282,41.161315],"type":"Point"}
}