{
  "type": "Feature",
  "properties": {
    "addr:full": "6161 Busch Blvd Columbus OH 43229",
    "addr:housenumber": "6161",
    "addr:postcode": "43229",
    "addr:street": "Busch Blvd",
    "iso:country": "US",
    "sg:address": "6161 Busch Blvd",
    "sg:city": "Columbus",
    "sg:classifiers": [
      {
        "category": "Wholesale",
        "subcategory": "Durable Goods \u0026 Equipment",
        "type": "Manufacturing \u0026 Wholesale Goods"
      }
    ],
    "sg:phone": "+1 614 847 9460",
    "sg:postcode": "43229",
    "sg:province": "OH",
    "sg:tags": [
      "instrument",
      "scientific",
      "apparatus"
    ],
    "wof:name": "Edax",
    "wof:placetype": "venue"
  },
  "geometry": {"coordinates":[-82.992685,40.090008],"type":"Point"}
}
