{
  "type": "Feature",
  "properties": {
    "iso:country":"US",
    "sg:address":"711 Wick Ave",
    "sg:city":"Youngstown",
    "sg:classifiers":[
        {
            "category":"Retail",
            "subcategory":"Funeral Services",
            "type":"Services"
        }
    ],
    "sg:phone":"+1 330 744 5019",
    "sg:postcode":"44505",
    "sg:province":"OH",
    "sg:tags":[
        "director"
    ],
    "wof:name":"Mc Vean & Hughes Inc Funeral",
    "wof:placetype":"venue"
},
  "geometry": {"coordinates":[-80.64116799999999,41.110735],"type":"Point"}
}