{
  "type": "Feature",
  "properties": {
    "addr:full": "8004 Blue Ash Rd Cincinnati OH 45236",
    "addr:housenumber": "8004",
    "addr:postcode": "45236",
    "addr:street": "Blue Ash Rd",
    "iso:country": "US",
    "sg:address": "8004 Blue Ash Rd",
    "sg:city": "Cincinnati",
    "sg:classifiers": [
      {
        "category": "Insurance",
        "subcategory": "Insurance Agent",
        "type": "Services"
      }
    ],
    "sg:phone": "+1 513 793 2161",
    "sg:postcode": "45236",
    "sg:province": "OH",
    "wof:name": "Caldwin Agency",
    "wof:placetype": "venue"
  },
  "geometry": {"coordinates":[-84.392131,39.206091],"type":"Point"}
}
