{
  "type": "Feature",
  "properties": {
    "addr:full": "3832 Yellow Creek Rd Akron OH 44333",
    "addr:housenumber": "3832",
    "addr:postcode": "44333",
    "addr:street": "Yellow Creek Rd",
    "iso:country": "US",
    "sg:address": "3832 Yellow Creek Rd",
    "sg:city": "Akron",
    "sg:classifiers": [
      {
        "category": "Manufacturing",
        "subcategory": "Paper Products",
        "type": "Manufacturing \u0026 Wholesale Goods"
      }
    ],
    "sg:phone": "+1 330 762 4832",
    "sg:postcode": "44333",
    "sg:province": "OH",
    "wof:name": "Preacs Corp",
    "wof:placetype": "venue"
  },
  "geometry": {"coordinates":[-81.642884,41.155634],"type":"Point"}
}
