{
  "type": "Feature",
  "properties": {
    "addr:full": "208 Mill St Milford OH 45150",
    "addr:housenumber": "208",
    "addr:postcode": "45150",
    "addr:street": "Mill St",
    "iso:country": "US",
    "sg:address": "208 Mill St",
    "sg:city": "Milford",
    "sg:classifiers": [
      {
        "category": "Autos \u0026 Motor Vehicles",
        "subcategory": "Automobile Sales",
        "type": "Retail Goods"
      }
    ],
    "sg:phone": "+1 513 831 8600",
    "sg:postcode": "45150",
    "sg:province": "OH",
    "sg:tags": [
      "car",
      "dealer"
    ],
    "wof:name": "Auto Gallery",
    "wof:placetype": "venue"
  },
  "geometry": {"coordinates":[-84.296847,39.171901],"type":"Point"}
}
