{
  "type": "Feature",
  "properties": {
    "addr:full":"21675 Center Ridge Rd Rocky River OH 44116",
    "addr:housenumber":"21675",
    "addr:postcode":"44116",
    "addr:street":"Center Ridge Rd",
    "iso:country":"US",
    "sg:address":"21675 Center Ridge Rd",
    "sg:city":"Rocky River",
    "sg:classifiers":[
        {
            "category":"Restaurant",
            "type":"Food & Drink"
        }
    ],
    "sg:menulink":"http://www.allmenus.com/oh/rocky-river/195063-mcdonalds/menu/",
    "sg:postcode":"44116",
    "sg:province":"OH",
    "sg:tags":[
        "burger",
        "american"
    ],
    "wof:name":"McDonald's",
    "wof:placetype":"venue"
},
  "geometry": {"coordinates":[-81.86019400000001,41.459015],"type":"Point"}
}