{
  "type": "Feature",
  "properties": {
    "addr:full": "2887 N Salem Warren Rd North Jackson OH 44451",
    "addr:housenumber": "2887",
    "addr:postcode": "44451",
    "addr:street": "N Salem Warren Rd",
    "iso:country": "US",
    "sg:address": "2887 N Salem Warren Rd",
    "sg:city": "North Jackson",
    "sg:classifiers": [
      {
        "category": "Manufacturing",
        "subcategory": "Retail Goods",
        "type": "Manufacturing \u0026 Wholesale Goods"
      }
    ],
    "sg:phone": "+1 330 538 9682",
    "sg:postcode": "44451",
    "sg:province": "OH",
    "sg:tags": [
      "manufacturer"
    ],
    "wof:name": "American Way Mfg Inc",
    "wof:placetype": "venue"
  },
  "geometry": {"coordinates":[-80.857124,41.132419],"type":"Point"}
}
