{
  "type": "Feature",
  "properties": {
    "iso:country":"US",
    "sg:address":"2887 N Salem Warren Rd",
    "sg:city":"North Jackson",
    "sg:classifiers":[
        {
            "category":"Manufacturing",
            "subcategory":"Retail Goods",
            "type":"Manufacturing & Wholesale Goods"
        }
    ],
    "sg:phone":"+1 330 538 9682",
    "sg:postcode":"44451",
    "sg:province":"OH",
    "sg:tags":[
        "manufacturer"
    ],
    "wof:name":"American Way Mfg Inc",
    "wof:placetype":"venue"
},
  "geometry": {"coordinates":[-80.857124,41.132419],"type":"Point"}
}