{
  "type": "Feature",
  "properties": {
    "addr:full": "3161 E 5th Ave Columbus OH 43219",
    "addr:housenumber": "3161",
    "addr:postcode": "43219",
    "addr:street": "E 5Th Ave",
    "iso:country": "US",
    "sg:address": "3161 E 5th Ave",
    "sg:city": "Columbus",
    "sg:classifiers": [
      {
        "category": "Organizations",
        "subcategory": "Religious Organization",
        "type": "Services"
      }
    ],
    "sg:phone": "+1 614 237 8619",
    "sg:postcode": "43219",
    "sg:province": "OH",
    "sg:tags": [
      "church"
    ],
    "wof:name": "Corinthian Baptist Church",
    "wof:placetype": "venue"
  },
  "geometry": {"coordinates":[-82.918323,39.984592],"type":"Point"}
}
