{
  "type": "Feature",
  "properties": {
    "iso:country":"US",
    "sg:address":"3660 Millvale Ave NE",
    "sg:city":"Canton",
    "sg:classifiers":[
        {
            "category":"Social Services",
            "type":"Services"
        }
    ],
    "sg:phone":"+1 330 452 4204",
    "sg:postcode":"44705",
    "sg:province":"OH",
    "sg:tags":[
        "organization",
        "welfare"
    ],
    "wof:name":"VOCA Corp",
    "wof:placetype":"venue"
},
  "geometry": {"coordinates":[-81.312879,40.832597],"type":"Point"}
}