{
  "type": "Feature",
  "properties": {
    "addr:full": "1095 N Court St Medina OH 44256",
    "addr:housenumber": "1095",
    "addr:postcode": "44256",
    "addr:street": "N Court St",
    "iso:country": "US",
    "sg:address": "1095 N Court St",
    "sg:city": "Medina",
    "sg:classifiers": [
      {
        "category": "Building \u0026 Trades",
        "subcategory": "Construction",
        "type": "Services"
      }
    ],
    "sg:phone": "+1 330 722 0600",
    "sg:postcode": "44256",
    "sg:province": "OH",
    "sg:tags": [
      "designer",
      "dealer",
      "pool",
      "swimming"
    ],
    "sg:website": "www.litehouse.com",
    "wof:name": "Litehouse Pools \u0026 Spas",
    "wof:placetype": "venue"
  },
  "geometry": {"coordinates":[-81.863069,41.152477],"type":"Point"}
}
