{
  "type": "Feature",
  "properties": {
    "iso:country":"US",
    "sg:address":"333 Lafayette Dr NW",
    "sg:city":"Canal Fulton",
    "sg:classifiers":[
        {
            "category":"Personal",
            "type":"Services"
        },
        {
            "category":"Sports & Exercise",
            "subcategory":"Golf",
            "type":"Entertainment"
        }
    ],
    "sg:phone":"+1 330 854 6999",
    "sg:postcode":"44614",
    "sg:province":"OH",
    "sg:tags":[
        "mini",
        "planning",
        "event",
        "party"
    ],
    "wof:name":"Sluggers & Putters Family Fun Sports Park",
    "wof:placetype":"venue"
},
  "geometry": {"coordinates":[-81.56759599999999,40.880402],"type":"Point"}
}