{
  "type": "Feature",
  "properties": {
    "addr:full": "926 Conners St Dayton OH 45408",
    "addr:housenumber": "926",
    "addr:postcode": "45408",
    "addr:street": "Conners St",
    "iso:country": "US",
    "sg:address": "926 Conners St",
    "sg:city": "Dayton",
    "sg:classifiers": [
      {
        "category": "Organizations",
        "subcategory": "Religious Organization",
        "type": "Services"
      }
    ],
    "sg:phone": "+1 937 226 7582",
    "sg:postcode": "45408",
    "sg:province": "OH",
    "sg:tags": [
      "church"
    ],
    "wof:name": "Church St Paul Missionary Bapt",
    "wof:placetype": "venue"
  },
  "geometry": {"coordinates":[-84.219511,39.743504],"type":"Point"}
}
