{
  "type": "Feature",
  "properties": {
    "iso:country":"US",
    "sg:address":"2181 Ambleside Dr",
    "sg:city":"Cleveland",
    "sg:classifiers":[
        {
            "category":"Banks & Credit Unions",
            "subcategory":"Bank",
            "type":"Services"
        }
    ],
    "sg:phone":"+1 216 515 0049",
    "sg:postcode":"44106",
    "sg:province":"OH",
    "sg:tags":[
        "national"
    ],
    "wof:name":"Huntington National Bank",
    "wof:placetype":"venue"
},
  "geometry": {"coordinates":[-81.603555,41.499245],"type":"Point"}
}