{
  "type": "Feature",
  "properties": {
    "addr:full":"3809 Wilmington Pike Dayton OH 45429",
    "addr:housenumber":"3809",
    "addr:postcode":"45429",
    "addr:street":"Wilmington Pike",
    "iso:country":"US",
    "sg:address":"3809 Wilmington Pike",
    "sg:city":"Dayton",
    "sg:classifiers":[
        {
            "category":"Health Services",
            "subcategory":"Doctor",
            "type":"Services"
        }
    ],
    "sg:phone":"+1 937 395 1111",
    "sg:postcode":"45429",
    "sg:province":"OH",
    "sg:tags":[
        "dentist"
    ],
    "wof:name":"Miami Valley Dental",
    "wof:placetype":"venue"
},
  "geometry": {"coordinates":[-84.13538200000001,39.691867],"type":"Point"}
}