{
  "type": "Feature",
  "properties": {
    "iso:country":"US",
    "sg:address":"2744 Lagrange St",
    "sg:city":"Toledo",
    "sg:classifiers":[
        {
            "category":"Retail",
            "subcategory":"Repair Shop",
            "type":"Services"
        }
    ],
    "sg:phone":"+1 419 244 2525",
    "sg:postcode":"43608",
    "sg:province":"OH",
    "sg:tags":[
        "scooter",
        "motorcycle",
        "motor"
    ],
    "wof:name":"Cycleman",
    "wof:placetype":"venue"
},
  "geometry": {"coordinates":[-83.538758,41.674835],"type":"Point"}
}