{
  "type": "Feature",
  "properties": {
    "iso:country":"US",
    "sg:address":"1108 Lawndale Dr",
    "sg:city":"Tallmadge",
    "sg:classifiers":[
        {
            "category":"Professional",
            "type":"Services"
        }
    ],
    "sg:phone":"+1 330 784 4990",
    "sg:postcode":"44278",
    "sg:province":"OH",
    "wof:name":"Energy Factory",
    "wof:placetype":"venue"
},
  "geometry": {"coordinates":[-81.424921,41.06996],"type":"Point"}
}