{
  "type": "Feature",
  "properties": {
    "iso:country":"US",
    "sg:address":"633 Main St",
    "sg:city":"Genoa",
    "sg:classifiers":[
        {
            "category":"Shopping",
            "subcategory":"Computers & Home Electronics",
            "type":"Retail Goods"
        }
    ],
    "sg:phone":"+1 419 855 2400",
    "sg:postcode":"43430",
    "sg:province":"OH",
    "wof:name":"Custom Computer Solutions",
    "wof:placetype":"venue"
},
  "geometry": {"coordinates":[-83.358577,41.519646],"type":"Point"}
}