{
  "type": "Feature",
  "properties": {
    "addr:full": "633 Main St Genoa OH 43430",
    "addr:housenumber": "633",
    "addr:postcode": "43430",
    "addr:street": "Main St",
    "iso:country": "US",
    "sg:address": "633 Main St",
    "sg:city": "Genoa",
    "sg:classifiers": [
      {
        "category": "Shopping",
        "subcategory": "Computers \u0026 Home Electronics",
        "type": "Retail Goods"
      }
    ],
    "sg:phone": "+1 419 855 2400",
    "sg:postcode": "43430",
    "sg:province": "OH",
    "wof:name": "Custom Computer Solutions",
    "wof:placetype": "venue"
  },
  "geometry": {"coordinates":[-83.358577,41.519646],"type":"Point"}
}
