{
  "type": "Feature",
  "properties": {
    "iso:country":"US",
    "sg:address":"306 Looney Rd",
    "sg:city":"Piqua",
    "sg:classifiers":[
        {
            "category":"Wholesale",
            "subcategory":"Durable Goods & Equipment",
            "type":"Manufacturing & Wholesale Goods"
        },
        {
            "category":"Shopping",
            "subcategory":"Gifts & Souvenirs",
            "type":"Retail Goods"
        }
    ],
    "sg:phone":"+1 937 615 9660",
    "sg:postcode":"45356",
    "sg:province":"OH",
    "sg:tags":[
        "party",
        "supply"
    ],
    "wof:name":"Special Occasions Party Supply",
    "wof:placetype":"venue"
},
  "geometry": {"coordinates":[-84.216815,40.15014],"type":"Point"}
}