{
  "type": "Feature",
  "properties": {
    "iso:country":"US",
    "sg:address":"5357 Dorr St",
    "sg:city":"Toledo",
    "sg:classifiers":[
        {
            "category":"Restaurant",
            "type":"Food & Drink"
        }
    ],
    "sg:phone":"+1 419 531 8255",
    "sg:postcode":"43615",
    "sg:province":"OH",
    "sg:website":"www.chubbyssportseatery.com",
    "wof:name":"Chubby's Sports Eatery",
    "wof:placetype":"venue"
},
  "geometry": {"coordinates":[-83.66928,41.653378],"type":"Point"}
}