{
  "type": "Feature",
  "properties": {
    "addr:full": "1290 W High Ave New Philadelphia OH 44663",
    "addr:housenumber": "1290",
    "addr:postcode": "44663",
    "addr:street": "W High Ave",
    "iso:country": "US",
    "sg:address": "1290 W High Ave",
    "sg:city": "New Philadelphia",
    "sg:classifiers": [
      {
        "category": "Restaurant",
        "type": "Food \u0026 Drink"
      }
    ],
    "sg:menulink": "http://www.allmenus.com/oh/new-philadelphia/102460-hog-heaven/menu/",
    "sg:phone": "+1 330 308 8040",
    "sg:postcode": "44663",
    "sg:province": "OH",
    "sg:tags": [
      "barbecue",
      "american"
    ],
    "wof:name": "Hog Heaven",
    "wof:placetype": "venue"
  },
  "geometry": {"coordinates":[-81.475043,40.493453],"type":"Point"}
}
