{
  "type": "Feature",
  "properties": {
    "addr:full":"237 Lake Ave Elyria OH 44035",
    "addr:housenumber":"237",
    "addr:postcode":"44035",
    "addr:street":"Lake Ave",
    "iso:country":"US",
    "sg:address":"237 Lake Ave",
    "sg:city":"Elyria",
    "sg:classifiers":[
        {
            "category":"Autos & Motor Vehicles",
            "subcategory":"Fuel & Gas Station",
            "type":"Retail Goods"
        }
    ],
    "sg:phone":"+1 440 323 9696",
    "sg:postcode":"44035",
    "sg:province":"OH",
    "sg:tags":[
        "oil",
        "dealer"
    ],
    "wof:name":"Clark Retail Enterprises Inc",
    "wof:placetype":"venue"
},
  "geometry": {"coordinates":[-82.11390900000001,41.37272],"type":"Point"}
}