{
  "type": "Feature",
  "properties": {
    "addr:full":"7761 Mercer Darke County Line Rd Maria Stein OH 45860",
    "addr:housenumber":"7761",
    "addr:postcode":"45860",
    "addr:street":"Mercer Darke County Line Rd",
    "iso:country":"US",
    "sg:address":"7761 Mercer Darke County Line Rd",
    "sg:city":"Maria Stein",
    "sg:classifiers":[
        {
            "category":"Farming",
            "subcategory":"Livestock Farm",
            "type":"Manufacturing & Wholesale Goods"
        }
    ],
    "sg:phone":"+1 419 582 4551",
    "sg:postcode":"45860",
    "sg:province":"OH",
    "sg:tags":[
        "hog",
        "or",
        "feedlot"
    ],
    "wof:name":"Schemmel  Norb",
    "wof:placetype":"venue"
},
  "geometry": {"coordinates":[-84.507724,40.354006],"type":"Point"}
}