{
  "type": "Feature",
  "properties": {
    "addr:full": "335 W 5th St Cincinnati OH 45202",
    "addr:housenumber": "335",
    "addr:postcode": "45202",
    "addr:street": "W 5Th St",
    "iso:country": "US",
    "sg:address": "335 W 5th St",
    "sg:city": "Cincinnati",
    "sg:classifiers": [
      {
        "category": "Professional",
        "subcategory": "Business Services",
        "type": "Services"
      }
    ],
    "sg:phone": "+1 513 579 1001",
    "sg:postcode": "45202",
    "sg:province": "OH",
    "sg:tags": [
      "interior",
      "consultant",
      "design",
      "decorator"
    ],
    "wof:name": "Spaces",
    "wof:placetype": "venue"
  },
  "geometry": {"coordinates":[-84.518947,39.100251],"type":"Point"}
}
