{
  "type": "Feature",
  "properties": {
    "addr:full": "17991 Englewood Dr Cleveland OH 44130",
    "addr:housenumber": "17991",
    "addr:postcode": "44130",
    "addr:street": "Englewood Dr",
    "iso:country": "US",
    "sg:address": "17991 Englewood Dr",
    "sg:city": "Cleveland",
    "sg:classifiers": [
      {
        "category": "Wholesale",
        "subcategory": "Machinery \u0026 Supplies",
        "type": "Manufacturing \u0026 Wholesale Goods"
      }
    ],
    "sg:phone": "+1 440 239 9920",
    "sg:postcode": "44130",
    "sg:province": "OH",
    "sg:tags": [
      "distributor",
      "dock",
      "leveler"
    ],
    "wof:name": "Rite-Hite Corp",
    "wof:placetype": "venue"
  },
  "geometry": {"coordinates":[-81.829362,41.380888],"type":"Point"}
}
