{
  "type": "Feature",
  "properties": {
    "addr:full": "33 Blucher St Toledo OH 43607",
    "addr:housenumber": "33",
    "addr:postcode": "43607",
    "addr:street": "Blucher St",
    "iso:country": "US",
    "sg:address": "33 Blucher St",
    "sg:city": "Toledo",
    "sg:classifiers": [
      {
        "category": "Wholesale",
        "subcategory": "Painting Supplies",
        "type": "Manufacturing \u0026 Wholesale Goods"
      }
    ],
    "sg:phone": "+1 419 243 5954",
    "sg:postcode": "43607",
    "sg:province": "OH",
    "sg:tags": [
      "paint"
    ],
    "wof:name": "Thomas Co",
    "wof:placetype": "venue"
  },
  "geometry": {"coordinates":[-83.564267,41.642663],"type":"Point"}
}
