{
  "type": "Feature",
  "properties": {
    "addr:full": "2766 Noe Bixby Rd Columbus OH 43232",
    "addr:housenumber": "2766",
    "addr:postcode": "43232",
    "addr:street": "Noe Bixby Rd",
    "iso:country": "US",
    "sg:address": "2766 Noe Bixby Rd",
    "sg:city": "Columbus",
    "sg:classifiers": [
      {
        "category": "Wholesale",
        "subcategory": "Electrical",
        "type": "Manufacturing \u0026 Wholesale Goods"
      }
    ],
    "sg:phone": "+1 614 501 9931",
    "sg:postcode": "43232",
    "sg:province": "OH",
    "sg:tags": [
      "electric",
      "motor"
    ],
    "wof:name": "P A Days Motor Land",
    "wof:placetype": "venue"
  },
  "geometry": {"coordinates":[-82.864968,39.920689],"type":"Point"}
}
