{
  "type": "Feature",
  "properties": {
    "iso:country":"US",
    "sg:address":"9090 Magnet Rd NE",
    "sg:city":"Minerva",
    "sg:classifiers":[
        {
            "category":"Building & Trades",
            "subcategory":"Landscaping Services",
            "type":"Services"
        }
    ],
    "sg:phone":"+1 330 895 2405",
    "sg:postcode":"44657",
    "sg:province":"OH",
    "wof:name":"Garretts Mowing LLC",
    "wof:placetype":"venue"
},
  "geometry": {"coordinates":[-81.083479,40.704568],"type":"Point"}
}