{
  "type": "Feature",
  "properties": {
    "addr:full": "3789 E 131st St Cleveland OH 44120",
    "addr:housenumber": "3789",
    "addr:postcode": "44120",
    "addr:street": "E 131St St",
    "iso:country": "US",
    "sg:address": "3789 E 131st St",
    "sg:city": "Cleveland",
    "sg:classifiers": [
      {
        "category": "Personal",
        "subcategory": "Barber",
        "type": "Services"
      }
    ],
    "sg:phone": "+1 216 752 3051",
    "sg:postcode": "44120",
    "sg:province": "OH",
    "wof:name": "Bennett Barber Shop",
    "wof:placetype": "venue"
  },
  "geometry": {"coordinates":[-81.591076,41.455286],"type":"Point"}
}
