{
  "type": "Feature",
  "properties": {
    "iso:country":"US",
    "sg:address":"3789 E 131st St",
    "sg:city":"Cleveland",
    "sg:classifiers":[
        {
            "category":"Personal",
            "subcategory":"Barber",
            "type":"Services"
        }
    ],
    "sg:phone":"+1 216 752 3051",
    "sg:postcode":"44120",
    "sg:province":"OH",
    "wof:name":"Bennett Barber Shop",
    "wof:placetype":"venue"
},
  "geometry": {"coordinates":[-81.591076,41.455286],"type":"Point"}
}