{
  "type": "Feature",
  "properties": {
    "iso:country":"US",
    "sg:address":"1304 McCormick Rd",
    "sg:city":"Gallipolis",
    "sg:classifiers":[
        {
            "category":"Shopping",
            "subcategory":"Gifts & Souvenirs",
            "type":"Retail Goods"
        }
    ],
    "sg:phone":"+1 740 441 9999",
    "sg:postcode":"45631",
    "sg:province":"OH",
    "wof:name":"Diecast and More",
    "wof:placetype":"venue"
},
  "geometry": {"coordinates":[-82.227909,38.827243],"type":"Point"}
}