{
  "type": "Feature",
  "properties": {
    "addr:full": "1304 McCormick Rd Gallipolis OH 45631",
    "addr:housenumber": "1304",
    "addr:postcode": "45631",
    "addr:street": "Mccormick Rd",
    "iso:country": "US",
    "sg:address": "1304 McCormick Rd",
    "sg:city": "Gallipolis",
    "sg:classifiers": [
      {
        "category": "Shopping",
        "subcategory": "Gifts \u0026 Souvenirs",
        "type": "Retail Goods"
      }
    ],
    "sg:phone": "+1 740 441 9999",
    "sg:postcode": "45631",
    "sg:province": "OH",
    "wof:name": "Diecast and More",
    "wof:placetype": "venue"
  },
  "geometry": {"coordinates":[-82.227909,38.827243],"type":"Point"}
}
