{
  "type": "Feature",
  "properties": {
    "addr:full":"4752 River Rd Cincinnati OH 45233",
    "addr:housenumber":"4752",
    "addr:postcode":"45233",
    "addr:street":"River Rd",
    "iso:country":"US",
    "sg:address":"4752 River Rd",
    "sg:city":"Cincinnati",
    "sg:classifiers":[
        {
            "category":"Organizations",
            "subcategory":"Membership Organization",
            "type":"Services"
        },
        {
            "category":"Manufacturing",
            "subcategory":"Toys & Sporting Goods",
            "type":"Manufacturing & Wholesale Goods"
        }
    ],
    "sg:phone":"+1 513 347 8100",
    "sg:postcode":"45233",
    "sg:province":"OH",
    "sg:tags":[
        "athletic",
        "equipment"
    ],
    "wof:name":"Pregame Athletics Inc",
    "wof:placetype":"venue"
},
  "geometry": {"coordinates":[-84.62871,39.078489],"type":"Point"}
}