{
  "type": "Feature",
  "properties": {
    "iso:country":"US",
    "sg:address":"4885 Jaysville-St Johns Rd",
    "sg:city":"Greenville",
    "sg:classifiers":[
        {
            "category":"Farming",
            "subcategory":"Livestock Farm",
            "type":"Manufacturing & Wholesale Goods"
        }
    ],
    "sg:phone":"+1 937 547 9560",
    "sg:postcode":"45331",
    "sg:province":"OH",
    "sg:tags":[
        "animal",
        "general"
    ],
    "wof:name":"Doug J Schmitmeyer",
    "wof:placetype":"venue"
},
  "geometry": {"coordinates":[-84.599029,40.051784],"type":"Point"}
}