{
  "type": "Feature",
  "properties": {
    "addr:full": "605 Springfield St Dayton OH 45403",
    "addr:housenumber": "605",
    "addr:postcode": "45403",
    "addr:street": "Springfield St",
    "iso:country": "US",
    "sg:address": "605 Springfield St",
    "sg:city": "Dayton",
    "sg:classifiers": [
      {
        "category": "Wholesale",
        "subcategory": "Office Equipment",
        "type": "Manufacturing \u0026 Wholesale Goods"
      },
      {
        "category": "Manufacturing",
        "subcategory": "Metals",
        "type": "Manufacturing \u0026 Wholesale Goods"
      }
    ],
    "sg:phone": "+1 937 253 8880",
    "sg:postcode": "45403",
    "sg:province": "OH",
    "sg:tags": [
      "vault",
      "product",
      "safe",
      "fabricated",
      "mfg"
    ],
    "wof:name": "Mc Intosh Safe Corp",
    "wof:placetype": "venue"
  },
  "geometry": {"coordinates":[-84.155111,39.768993],"type":"Point"}
}
