{
  "type": "Feature",
  "properties": {
    "addr:full":"605 Springfield St Dayton OH 45403",
    "addr:housenumber":"605",
    "addr:postcode":"45403",
    "addr:street":"Springfield St",
    "iso:country":"US",
    "sg:address":"605 Springfield St",
    "sg:city":"Dayton",
    "sg:classifiers":[
        {
            "category":"Wholesale",
            "subcategory":"Office Equipment",
            "type":"Manufacturing & Wholesale Goods"
        },
        {
            "category":"Manufacturing",
            "subcategory":"Metals",
            "type":"Manufacturing & Wholesale Goods"
        }
    ],
    "sg:phone":"+1 937 253 8880",
    "sg:postcode":"45403",
    "sg:province":"OH",
    "sg:tags":[
        "vault",
        "product",
        "safe",
        "fabricated",
        "mfg"
    ],
    "wof:name":"Mc Intosh Safe Corp",
    "wof:placetype":"venue"
},
  "geometry": {"coordinates":[-84.15511100000001,39.768993],"type":"Point"}
}