{
  "type": "Feature",
  "properties": {
    "iso:country":"US",
    "sg:address":"30050 Chagrin Blvd",
    "sg:city":"Cleveland",
    "sg:classifiers":[
        {
            "category":"Real Estate",
            "subcategory":"Real Estate Agent",
            "type":"Services"
        }
    ],
    "sg:phone":"+1 216 464 3580",
    "sg:postcode":"44124",
    "sg:province":"OH",
    "wof:name":"Greystone Group-Avery Ltd",
    "wof:placetype":"venue"
},
  "geometry": {"coordinates":[-81.456338,41.459931],"type":"Point"}
}