{
  "type": "Feature",
  "properties": {
    "iso:country":"US",
    "sg:address":"2 Summit Park Dr",
    "sg:city":"Cleveland",
    "sg:classifiers":[
        {
            "category":"Insurance",
            "subcategory":"Insurance Agent",
            "type":"Services"
        }
    ],
    "sg:phone":"+1 216 642 9211",
    "sg:postcode":"44131",
    "sg:province":"OH",
    "sg:tags":[
        "agency",
        "investment"
    ],
    "wof:name":"First Finacial Resources",
    "wof:placetype":"venue"
},
  "geometry": {"coordinates":[-81.655926,41.395674],"type":"Point"}
}