{
  "type": "Feature",
  "properties": {
    "addr:full": "8101 Chesterfield Ave Cleveland OH 44129",
    "addr:housenumber": "8101",
    "addr:postcode": "44129",
    "addr:street": "Chesterfield Ave",
    "iso:country": "US",
    "sg:address": "8101 Chesterfield Ave",
    "sg:city": "Cleveland",
    "sg:classifiers": [
      {
        "category": "Building \u0026 Trades",
        "subcategory": "Electrical",
        "type": "Services"
      }
    ],
    "sg:phone": "+1 440 884 7172",
    "sg:postcode": "44129",
    "sg:province": "OH",
    "sg:tags": [
      "communication",
      "system",
      "contractor"
    ],
    "wof:name": "Tele-Sound Network",
    "wof:placetype": "venue"
  },
  "geometry": {"coordinates":[-81.741557,41.412347],"type":"Point"}
}
