{
  "type": "Feature",
  "properties": {
    "addr:full": "444 Mahoning Ave NW Warren OH 44483",
    "addr:housenumber": "444",
    "addr:postcode": "44483",
    "addr:street": "Mahoning Ave Nw",
    "iso:country": "US",
    "sg:address": "444 Mahoning Ave NW",
    "sg:city": "Warren",
    "sg:classifiers": [
      {
        "category": "Education",
        "subcategory": "Library",
        "type": "Public Place"
      }
    ],
    "sg:phone": "+1 330 399 8807",
    "sg:postcode": "44483",
    "sg:province": "OH",
    "wof:name": "Warren-Trumbull Co Pub Library",
    "wof:placetype": "venue"
  },
  "geometry": {"coordinates":[-80.82285,41.239727],"type":"Point"}
}
