{
  "type": "Feature",
  "properties": {
    "addr:full": "6880 Sovereign Ct Dayton OH 45414",
    "addr:housenumber": "6880",
    "addr:postcode": "45414",
    "addr:street": "Sovereign Ct",
    "iso:country": "US",
    "sg:address": "6880 Sovereign Ct",
    "sg:city": "Dayton",
    "sg:classifiers": [
      {
        "category": "Banks \u0026 Credit Unions",
        "subcategory": "Investment Brokerage",
        "type": "Services"
      },
      {
        "category": "Professional",
        "subcategory": "Management \u0026 Consulting",
        "type": "Services"
      }
    ],
    "sg:phone": "+1 937 898 2438",
    "sg:postcode": "45414",
    "sg:province": "OH",
    "sg:tags": [
      "consultant",
      "banker",
      "business"
    ],
    "wof:name": "Lockhart Group Inc",
    "wof:placetype": "venue"
  },
  "geometry": {"coordinates":[-84.243887,39.846365],"type":"Point"}
}
