{
  "type": "Feature",
  "properties": {
    "addr:full":"254 S Abbe Rd Elyria OH 44035",
    "addr:housenumber":"254",
    "addr:postcode":"44035",
    "addr:street":"S Abbe Rd",
    "iso:country":"US",
    "sg:address":"254 S Abbe Rd",
    "sg:city":"Elyria",
    "sg:classifiers":[
        {
            "category":"Shopping",
            "type":"Retail Goods"
        }
    ],
    "sg:phone":"+1 440 366 6355",
    "sg:postcode":"44035",
    "sg:province":"OH",
    "sg:tags":[
        "trophy",
        "medal",
        "award"
    ],
    "wof:name":"Bayorek's Trophies Signs",
    "wof:placetype":"venue"
},
  "geometry": {"coordinates":[-82.077856,41.371878],"type":"Point"}
}