{
  "type": "Feature",
  "properties": {
    "iso:country":"US",
    "sg:address":"4984 S Main St",
    "sg:city":"Akron",
    "sg:classifiers":[
        {
            "category":"Professional",
            "subcategory":"Advertising",
            "type":"Services"
        }
    ],
    "sg:phone":"+1 330 645 1575",
    "sg:postcode":"44319",
    "sg:province":"OH",
    "sg:tags":[
        "mail",
        "marketing"
    ],
    "wof:name":"Capital Business Services",
    "wof:placetype":"venue"
},
  "geometry": {"coordinates":[-81.533129,40.954414],"type":"Point"}
}