{
  "type": "Feature",
  "properties": {
    "iso:country":"US",
    "sg:address":"1630 W 4th St",
    "sg:city":"Ashtabula",
    "sg:classifiers":[
        {
            "category":"Wholesale",
            "subcategory":"Machinery & Supplies",
            "type":"Manufacturing & Wholesale Goods"
        }
    ],
    "sg:phone":"+1 440 964 5436",
    "sg:postcode":"44004",
    "sg:province":"OH",
    "sg:tags":[
        "equipment",
        "transportation"
    ],
    "wof:name":"K A M Marine Parts & Stuff",
    "wof:placetype":"venue"
},
  "geometry": {"coordinates":[-80.80756599999999,41.897202],"type":"Point"}
}