{
  "type": "Feature",
  "properties": {
    "addr:full": "1630 W 4th St Ashtabula OH 44004",
    "addr:housenumber": "1630",
    "addr:postcode": "44004",
    "addr:street": "W 4Th St",
    "iso:country": "US",
    "sg:address": "1630 W 4th St",
    "sg:city": "Ashtabula",
    "sg:classifiers": [
      {
        "category": "Wholesale",
        "subcategory": "Machinery \u0026 Supplies",
        "type": "Manufacturing \u0026 Wholesale Goods"
      }
    ],
    "sg:phone": "+1 440 964 5436",
    "sg:postcode": "44004",
    "sg:province": "OH",
    "sg:tags": [
      "equipment",
      "transportation"
    ],
    "wof:name": "K A M Marine Parts \u0026 Stuff",
    "wof:placetype": "venue"
  },
  "geometry": {"coordinates":[-80.807566,41.897202],"type":"Point"}
}
