{
  "type": "Feature",
  "properties": {
    "addr:full":"1900 E Dublin Granville Rd Columbus OH 43229",
    "addr:housenumber":"1900",
    "addr:postcode":"43229",
    "addr:street":"E Dublin Granville Rd",
    "iso:country":"US",
    "sg:address":"1900 E Dublin Granville Rd",
    "sg:city":"Columbus",
    "sg:classifiers":[
        {
            "category":"Education",
            "subcategory":"College",
            "type":"Public Place"
        }
    ],
    "sg:phone":"+1 614 794 0803",
    "sg:postcode":"43229",
    "sg:province":"OH",
    "sg:tags":[
        "academic",
        "school"
    ],
    "wof:name":"Ashland University",
    "wof:placetype":"venue"
},
  "geometry": {"coordinates":[-82.966938,40.086883],"type":"Point"}
}