{
  "type": "Feature",
  "properties": {
    "iso:country":"US",
    "sg:address":"7805 Billman Rd",
    "sg:city":"Gambier",
    "sg:classifiers":[
        {
            "category":"Organizations",
            "subcategory":"Religious Organization",
            "type":"Services"
        }
    ],
    "sg:phone":"+1 740 427 4864",
    "sg:postcode":"43022",
    "sg:province":"OH",
    "sg:tags":[
        "clergy"
    ],
    "wof:name":"Robert Pelfrey",
    "wof:placetype":"venue"
},
  "geometry": {"coordinates":[-82.282133,40.339366],"type":"Point"}
}