{
  "type": "Feature",
  "properties": {
    "addr:full":"3870 Bell Rd Seville OH 44273",
    "addr:housenumber":"3870",
    "addr:postcode":"44273",
    "addr:street":"Bell Rd",
    "iso:country":"US",
    "sg:address":"3870 Bell Rd",
    "sg:city":"Seville",
    "sg:classifiers":[
        {
            "category":"Manufacturing",
            "subcategory":"Signs",
            "type":"Manufacturing & Wholesale Goods"
        }
    ],
    "sg:phone":"+1 330 769 4212",
    "sg:postcode":"44273",
    "sg:province":"OH",
    "sg:tags":[
        "advertising",
        "specialty"
    ],
    "wof:name":"Adam's Signs",
    "wof:placetype":"venue"
},
  "geometry": {"coordinates":[-81.83110600000001,40.990398],"type":"Point"}
}