{
  "type": "Feature",
  "properties": {
    "addr:full": "3000 Tuscarawas St W Canton OH 44708",
    "addr:housenumber": "3000",
    "addr:postcode": "44708",
    "addr:street": "Tuscarawas St W",
    "iso:country": "US",
    "sg:address": "3000 Tuscarawas St W",
    "sg:city": "Canton",
    "sg:classifiers": [
      {
        "category": "Autos \u0026 Motor Vehicles",
        "subcategory": "Automobile Sales",
        "type": "Retail Goods"
      }
    ],
    "sg:phone": "+1 330 458 0000",
    "sg:postcode": "44708",
    "sg:province": "OH",
    "sg:tags": [
      "car",
      "dealer"
    ],
    "sg:website": "www.jdbyrider.com",
    "wof:name": "J D Byrider Of Canton",
    "wof:placetype": "venue"
  },
  "geometry": {"coordinates":[-81.408123,40.798514],"type":"Point"}
}
