{
  "type": "Feature",
  "properties": {
    "addr:full": "987 E Ash St Piqua OH 45356",
    "addr:housenumber": "987",
    "addr:postcode": "45356",
    "addr:street": "E Ash St",
    "iso:country": "US",
    "sg:address": "987 E Ash St",
    "sg:city": "Piqua",
    "sg:classifiers": [
      {
        "category": "Bakery",
        "type": "Food \u0026 Drink"
      }
    ],
    "sg:menulink": "http://www.allmenus.com/oh/piqua/230547-great-american-cookies/menu/",
    "sg:phone": "+1 937 778 9292",
    "sg:postcode": "45356",
    "sg:province": "OH",
    "sg:tags": [
      "american",
      "pastry"
    ],
    "wof:name": "Great American Cookies",
    "wof:placetype": "venue"
  },
  "geometry": {"coordinates":[-84.217548,40.150875],"type":"Point"}
}
