{
  "type": "Feature",
  "properties": {
    "addr:full": "3506 Greenwich St Columbus OH 43224",
    "addr:housenumber": "3506",
    "addr:postcode": "43224",
    "addr:street": "Greenwich St",
    "iso:country": "US",
    "sg:address": "3506 Greenwich St",
    "sg:city": "Columbus",
    "sg:classifiers": [
      {
        "category": "Banks \u0026 Credit Unions",
        "subcategory": "Financial Services",
        "type": "Services"
      }
    ],
    "sg:phone": "+1 614 263 8380",
    "sg:postcode": "43224",
    "sg:province": "OH",
    "sg:tags": [
      "investor"
    ],
    "wof:name": "Mohamed M Osman",
    "wof:placetype": "venue"
  },
  "geometry": {"coordinates":[-82.966608,40.040177],"type":"Point"}
}
