{
  "type": "Feature",
  "properties": {
    "iso:country":"US",
    "sg:address":"3506 Greenwich St",
    "sg:city":"Columbus",
    "sg:classifiers":[
        {
            "category":"Banks & Credit Unions",
            "subcategory":"Financial Services",
            "type":"Services"
        }
    ],
    "sg:phone":"+1 614 263 8380",
    "sg:postcode":"43224",
    "sg:province":"OH",
    "sg:tags":[
        "investor"
    ],
    "wof:name":"Mohamed M Osman",
    "wof:placetype":"venue"
},
  "geometry": {"coordinates":[-82.966608,40.040177],"type":"Point"}
}