{
  "type": "Feature",
  "properties": {
    "iso:country":"US",
    "sg:address":"5481 N Bend Rd",
    "sg:city":"Cincinnati",
    "sg:classifiers":[
        {
            "category":"Manufacturing",
            "subcategory":"Rubber & Plastics",
            "type":"Manufacturing & Wholesale Goods"
        },
        {
            "category":"Autos & Motor Vehicles",
            "subcategory":"Auto Supplies",
            "type":"Retail Goods"
        },
        {
            "category":"Retail",
            "subcategory":"Auto Repair",
            "type":"Services"
        }
    ],
    "sg:phone":"+1 513 662 6696",
    "sg:postcode":"45247",
    "sg:province":"OH",
    "sg:tags":[
        "tires-wholesale",
        "tire",
        "retread",
        "recap",
        "manufacturer"
    ],
    "sg:website":"http://www.coopertire.com/html/",
    "wof:name":"Jim's Auto Clinic Inc",
    "wof:placetype":"venue"
},
  "geometry": {"coordinates":[-84.599648,39.190361],"type":"Point"}
}