{
  "type": "Feature",
  "properties": {
    "addr:full": "5481 N Bend Rd Cincinnati OH 45247",
    "addr:housenumber": "5481",
    "addr:postcode": "45247",
    "addr:street": "N Bend Rd",
    "iso:country": "US",
    "sg:address": "5481 N Bend Rd",
    "sg:city": "Cincinnati",
    "sg:classifiers": [
      {
        "category": "Manufacturing",
        "subcategory": "Rubber \u0026 Plastics",
        "type": "Manufacturing \u0026 Wholesale Goods"
      },
      {
        "category": "Autos \u0026 Motor Vehicles",
        "subcategory": "Auto Supplies",
        "type": "Retail Goods"
      },
      {
        "category": "Retail",
        "subcategory": "Auto Repair",
        "type": "Services"
      }
    ],
    "sg:phone": "+1 513 662 6696",
    "sg:postcode": "45247",
    "sg:province": "OH",
    "sg:tags": [
      "tires-wholesale",
      "tire",
      "retread",
      "recap",
      "manufacturer"
    ],
    "sg:website": "http://www.coopertire.com/html/",
    "wof:name": "Jim's Auto Clinic Inc",
    "wof:placetype": "venue"
  },
  "geometry": {"coordinates":[-84.599648,39.190361],"type":"Point"}
}
