{
  "type": "Feature",
  "properties": {
    "addr:full":"2676 Madison Rd Cincinnati OH 45208",
    "addr:housenumber":"2676",
    "addr:postcode":"45208",
    "addr:street":"Madison Rd",
    "iso:country":"US",
    "sg:address":"2676 Madison Rd",
    "sg:city":"Cincinnati",
    "sg:classifiers":[
        {
            "category":"Wholesale",
            "subcategory":"Non-durable Goods",
            "type":"Manufacturing & Wholesale Goods"
        }
    ],
    "sg:phone":"+1 513 871 7888",
    "sg:postcode":"45208",
    "sg:province":"OH",
    "wof:name":"Hyde Park K9 Kamp",
    "wof:placetype":"venue"
},
  "geometry": {"coordinates":[-84.443977,39.144809],"type":"Point"}
}