{
  "type": "Feature",
  "properties": {
    "iso:country":"US",
    "sg:address":"2020 Tiffin Ave",
    "sg:city":"Findlay",
    "sg:classifiers":[
        {
            "category":"Personal",
            "subcategory":"Beauty Salon",
            "type":"Services"
        }
    ],
    "sg:phone":"+1 419 425 0808",
    "sg:postcode":"45840",
    "sg:province":"OH",
    "wof:name":"Cost Cutters Family Hair Care",
    "wof:placetype":"venue"
},
  "geometry": {"coordinates":[-83.60561800000001,41.054199],"type":"Point"}
}