{
  "type": "Feature",
  "properties": {
    "addr:full":"11023 Finefrock Rd SW Massillon OH 44647",
    "addr:housenumber":"11023",
    "addr:postcode":"44647",
    "addr:street":"Finefrock Rd Sw",
    "iso:country":"US",
    "sg:address":"11023 Finefrock Rd SW",
    "sg:city":"Massillon",
    "sg:classifiers":[
        {
            "category":"Freight",
            "type":"Transportation"
        }
    ],
    "sg:phone":"+1 330 699 7182",
    "sg:postcode":"44647",
    "sg:province":"OH",
    "sg:tags":[
        "operator",
        "local",
        "trucking"
    ],
    "wof:name":"Db Trucking",
    "wof:placetype":"venue"
},
  "geometry": {"coordinates":[-81.574206,40.771439],"type":"Point"}
}