{
  "type": "Feature",
  "properties": {
    "addr:full": "1814 Lima Sandusky Rd Sandusky OH 44870",
    "addr:housenumber": "1814",
    "addr:postcode": "44870",
    "addr:street": "Lima Sandusky Rd",
    "iso:country": "US",
    "sg:address": "1814 Lima Sandusky Rd",
    "sg:city": "Sandusky",
    "sg:phone": "+1 419 684 5557",
    "sg:postcode": "44870",
    "sg:province": "OH",
    "sg:tags": [
      "farm",
      "corn",
      "soybean"
    ],
    "wof:name": "Fitz Farms",
    "wof:placetype": "venue"
  },
  "geometry": {"coordinates":[-82.797545,41.441316],"type":"Point"}
}
