{
  "type": "Feature",
  "properties": {
    "iso:country":"US",
    "sg:address":"938 E 123rd St",
    "sg:city":"Cleveland",
    "sg:classifiers":[
        {
            "category":"Travel",
            "subcategory":"Hotels & Motels",
            "type":"Entertainment"
        }
    ],
    "sg:phone":"+1 216 541 5912",
    "sg:postcode":"44108",
    "sg:province":"OH",
    "wof:name":"Trinity Suites",
    "wof:placetype":"venue"
},
  "geometry": {"coordinates":[-81.60184700000001,41.530936],"type":"Point"}
}