{
  "type": "Feature",
  "properties": {
    "addr:full": "924 Ontario St Sandusky OH 44870",
    "addr:housenumber": "924",
    "addr:postcode": "44870",
    "addr:street": "Ontario St",
    "iso:country": "US",
    "sg:address": "924 Ontario St",
    "sg:city": "Sandusky",
    "sg:classifiers": [
      {
        "category": "Education",
        "subcategory": "School",
        "type": "Public Place"
      }
    ],
    "sg:phone": "+1 419 627 8544",
    "sg:postcode": "44870",
    "sg:province": "OH",
    "wof:name": "Ontario Elementary School",
    "wof:placetype": "venue"
  },
  "geometry": {"coordinates":[-82.692652,41.449729],"type":"Point"}
}
