{
  "type": "Feature",
  "properties": {
    "addr:full": "18220 Euclid Ave Cleveland OH 44112",
    "addr:housenumber": "18220",
    "addr:postcode": "44112",
    "addr:street": "Euclid Ave",
    "iso:country": "US",
    "sg:address": "18220 Euclid Ave",
    "sg:city": "Cleveland",
    "sg:classifiers": [
      {
        "category": "Building \u0026 Trades",
        "subcategory": "Cleaning \u0026 Sanitation",
        "type": "Services"
      }
    ],
    "sg:phone": "+1 216 383 1621",
    "sg:postcode": "44112",
    "sg:province": "OH",
    "sg:tags": [
      "janitor"
    ],
    "wof:name": "David's Cleaning Svc",
    "wof:placetype": "venue"
  },
  "geometry": {"coordinates":[-81.550232,41.556775],"type":"Point"}
}
