{
  "type": "Feature",
  "properties": {
    "iso:country":"US",
    "sg:address":"18220 Euclid Ave",
    "sg:city":"Cleveland",
    "sg:classifiers":[
        {
            "category":"Building & Trades",
            "subcategory":"Cleaning & Sanitation",
            "type":"Services"
        }
    ],
    "sg:phone":"+1 216 383 1621",
    "sg:postcode":"44112",
    "sg:province":"OH",
    "sg:tags":[
        "janitor"
    ],
    "wof:name":"David's Cleaning Svc",
    "wof:placetype":"venue"
},
  "geometry": {"coordinates":[-81.55023199999999,41.556775],"type":"Point"}
}