{
  "type": "Feature",
  "properties": {
    "iso:country":"US",
    "sg:address":"807 S 3rd St",
    "sg:city":"Ironton",
    "sg:classifiers":[
        {
            "category":"Banks & Credit Unions",
            "subcategory":"Investment Brokerage",
            "type":"Services"
        }
    ],
    "sg:phone":"+1 740 533 2072",
    "sg:postcode":"45638",
    "sg:province":"OH",
    "sg:tags":[
        "consultant",
        "planning",
        "financial"
    ],
    "wof:name":"Creative Financial Solutions",
    "wof:placetype":"venue"
},
  "geometry": {"coordinates":[-82.680485,38.529121],"type":"Point"}
}