{
  "type": "Feature",
  "properties": {
    "iso:country":"US",
    "sg:address":"5005 Rockside Rd",
    "sg:city":"Cleveland",
    "sg:classifiers":[
        {
            "category":"Insurance",
            "subcategory":"Health Insurance",
            "type":"Services"
        }
    ],
    "sg:phone":"+1 216 328 9400",
    "sg:postcode":"44131",
    "sg:province":"OH",
    "wof:name":"Accident & Health Dept",
    "wof:placetype":"venue"
},
  "geometry": {"coordinates":[-81.65351,41.396943],"type":"Point"}
}