{
  "type": "Feature",
  "properties": {
    "iso:country":"US",
    "sg:address":"1320 Washington Ave",
    "sg:city":"Cleveland",
    "sg:classifiers":[
        {
            "category":"Health Services",
            "subcategory":"Hospital",
            "type":"Services"
        }
    ],
    "sg:phone":"+1 216 781 0550",
    "sg:postcode":"44113",
    "sg:province":"OH",
    "sg:tags":[
        "rehabilitation",
        "center"
    ],
    "wof:name":"Stella Mris Detoxification Ctr",
    "wof:placetype":"venue"
},
  "geometry": {"coordinates":[-81.706766,41.493442],"type":"Point"}
}