{
  "type": "Feature",
  "properties": {
    "addr:full":"7363 S Elyria Rd Shreve OH 44676",
    "addr:housenumber":"7363",
    "addr:postcode":"44676",
    "addr:street":"S Elyria Rd",
    "iso:country":"US",
    "sg:address":"7363 S Elyria Rd",
    "sg:city":"Shreve",
    "sg:classifiers":[
        {
            "category":"Building & Trades",
            "subcategory":"Pest Control",
            "type":"Services"
        }
    ],
    "sg:phone":"+1 330 567 0018",
    "sg:postcode":"44676",
    "sg:province":"OH",
    "wof:name":"Tag's Termite Control",
    "wof:placetype":"venue"
},
  "geometry": {"coordinates":[-82.048074,40.710501],"type":"Point"}
}