{
  "type": "Feature",
  "properties": {
    "iso:country":"US",
    "sg:address":"36445 Biltmore Pl",
    "sg:city":"Willoughby",
    "sg:phone":"+1 440 942 2242",
    "sg:postcode":"44094",
    "sg:province":"OH",
    "sg:tags":[
        "partition"
    ],
    "wof:name":"B-PAR Inc",
    "wof:placetype":"venue"
},
  "geometry": {"coordinates":[-81.425299,41.632649],"type":"Point"}
}