{
  "type": "Feature",
  "properties": {
    "iso:country":"US",
    "sg:address":"6217 Erie Ave",
    "sg:city":"Cincinnati",
    "sg:classifiers":[
        {
            "category":"Arts & Performance",
            "subcategory":"Theater",
            "type":"Entertainment"
        }
    ],
    "sg:phone":"+1 513 271 4320",
    "sg:postcode":"45227",
    "sg:province":"OH",
    "sg:tags":[
        "entertainer"
    ],
    "wof:name":"Magic Wanda",
    "wof:placetype":"venue"
},
  "geometry": {"coordinates":[-84.38908000000001,39.157609],"type":"Point"}
}