{
  "type": "Feature",
  "properties": {
    "addr:full":"559 Liberty Hl Ste 1 Cincinnati OH 45202",
    "addr:housenumber":"559;hl ste 1",
    "addr:postcode":"45202",
    "addr:street":"Liberty",
    "iso:country":"US",
    "sg:address":"559 Liberty Hl Ste 1",
    "sg:city":"Cincinnati",
    "sg:classifiers":[
        {
            "category":"Bars & Pubs",
            "subcategory":"Champagne Bar",
            "type":"Food & Drink"
        }
    ],
    "sg:phone":"+1 513 651 9444",
    "sg:postcode":"45202",
    "sg:province":"OH",
    "sg:tags":[
        "coal",
        "coke"
    ],
    "wof:name":"River Trading Company Ltd",
    "wof:placetype":"venue"
},
  "geometry": {"coordinates":[-84.505081,39.112259],"type":"Point"}
}