{
  "type": "Feature",
  "properties": {
    "iso:country":"US",
    "sg:address":"5786 Fulton Dr NW",
    "sg:city":"Canton",
    "sg:classifiers":[
        {
            "category":"Health Services",
            "subcategory":"Chiropractor",
            "type":"Services"
        }
    ],
    "sg:phone":"+1 330 966 0030",
    "sg:postcode":"44718",
    "sg:province":"OH",
    "wof:name":"Lake Cable Chiropractic Ctr",
    "wof:placetype":"venue"
},
  "geometry": {"coordinates":[-81.456368,40.856051],"type":"Point"}
}