{
  "type": "Feature",
  "properties": {
    "addr:full":"929 Kling St Akron OH 44311",
    "addr:housenumber":"929",
    "addr:postcode":"44311",
    "addr:street":"Kling St",
    "iso:country":"US",
    "sg:address":"929 Kling St",
    "sg:city":"Akron",
    "sg:classifiers":[
        {
            "category":"Manufacturing",
            "subcategory":"Metals",
            "type":"Manufacturing & Wholesale Goods"
        }
    ],
    "sg:phone":"+1 330 253 9147",
    "sg:postcode":"44311",
    "sg:province":"OH",
    "sg:tags":[
        "steel"
    ],
    "wof:name":"Service Iron & Steel Co",
    "wof:placetype":"venue"
},
  "geometry": {"coordinates":[-81.511487,41.057178],"type":"Point"}
}