{
  "type": "Feature",
  "properties": {
    "iso:country":"US",
    "sg:address":"377 N High St",
    "sg:city":"Cortland",
    "sg:classifiers":[
        {
            "category":"Building & Trades",
            "subcategory":"Construction",
            "type":"Services"
        }
    ],
    "sg:phone":"+1 330 638 5317",
    "sg:postcode":"44410",
    "sg:province":"OH",
    "sg:tags":[
        "house",
        "improvement",
        "home"
    ],
    "wof:name":"C & L Home Improvement",
    "wof:placetype":"venue"
},
  "geometry": {"coordinates":[-80.723957,41.33773],"type":"Point"}
}