{
  "type": "Feature",
  "properties": {
    "addr:full": "377 N High St Cortland OH 44410",
    "addr:housenumber": "377",
    "addr:postcode": "44410",
    "addr:street": "N High St",
    "iso:country": "US",
    "sg:address": "377 N High St",
    "sg:city": "Cortland",
    "sg:classifiers": [
      {
        "category": "Building \u0026 Trades",
        "subcategory": "Construction",
        "type": "Services"
      }
    ],
    "sg:phone": "+1 330 638 5317",
    "sg:postcode": "44410",
    "sg:province": "OH",
    "sg:tags": [
      "house",
      "improvement",
      "home"
    ],
    "wof:name": "C \u0026 L Home Improvement",
    "wof:placetype": "venue"
  },
  "geometry": {"coordinates":[-80.723957,41.33773],"type":"Point"}
}
