{
  "type": "Feature",
  "properties": {
    "addr:full": "3212 Madison Rd Cincinnati OH 45209",
    "addr:housenumber": "3212",
    "addr:postcode": "45209",
    "addr:street": "Madison Rd",
    "iso:country": "US",
    "sg:address": "3212 Madison Rd",
    "sg:city": "Cincinnati",
    "sg:classifiers": [
      {
        "category": "Food \u0026 Beverages",
        "subcategory": "Specialty",
        "type": "Retail Goods"
      }
    ],
    "sg:phone": "+1 513 533 4832",
    "sg:postcode": "45209",
    "sg:province": "OH",
    "sg:tags": [
      "tea",
      "coffee",
      "restaurant"
    ],
    "wof:name": "Essencha Tea House \u0026 Fine Teas",
    "wof:placetype": "venue"
  },
  "geometry": {"coordinates":[-84.426952,39.155066],"type":"Point"}
}
