{
  "type": "Feature",
  "properties": {
    "addr:full": "1705 Steiner St NW Canton OH 44720",
    "addr:housenumber": "1705",
    "addr:postcode": "44720",
    "addr:street": "Steiner St Nw",
    "iso:country": "US",
    "sg:address": "1705 Steiner St NW",
    "sg:city": "Canton",
    "sg:classifiers": [
      {
        "category": "Shopping",
        "subcategory": "Florist",
        "type": "Retail Goods"
      }
    ],
    "sg:phone": "+1 330 494 6529",
    "sg:postcode": "44720",
    "sg:province": "OH",
    "wof:name": "Flos Floral \u0026 Bows",
    "wof:placetype": "venue"
  },
  "geometry": {"coordinates":[-81.370821,40.887446],"type":"Point"}
}
