{
  "type": "Feature",
  "properties": {
    "iso:country":"US",
    "sg:address":"8260 Hitchcock Rd",
    "sg:city":"Youngstown",
    "sg:classifiers":[
        {
            "category":"Professional",
            "type":"Services"
        }
    ],
    "sg:phone":"+1 330 758 4071",
    "sg:postcode":"44512",
    "sg:province":"OH",
    "wof:name":"Bert P & Carolyne M Toth",
    "wof:placetype":"venue"
},
  "geometry": {"coordinates":[-80.676755,41.00483],"type":"Point"}
}