{
  "type": "Feature",
  "properties": {
    "addr:full":"150 N Water St Kent OH 44240",
    "addr:housenumber":"150",
    "addr:postcode":"44240",
    "addr:street":"N Water St",
    "iso:country":"US",
    "sg:address":"150 N Water St",
    "sg:city":"Kent",
    "sg:classifiers":[
        {
            "category":"Personal",
            "subcategory":"Barber",
            "type":"Services"
        }
    ],
    "sg:phone":"+1 330 673 4517",
    "sg:postcode":"44240",
    "sg:province":"OH",
    "wof:name":"Pennington's Barber Shop",
    "wof:placetype":"venue"
},
  "geometry": {"coordinates":[-81.358226,41.154301],"type":"Point"}
}