{
  "type": "Feature",
  "properties": {
    "addr:full": "11445 Blodgett Creek Trl Strongsville OH 44149",
    "addr:housenumber": "11445",
    "addr:postcode": "44149",
    "addr:street": "Blodgett Creek Trl",
    "iso:country": "US",
    "sg:address": "11445 Blodgett Creek Trl",
    "sg:city": "Strongsville",
    "sg:classifiers": [
      {
        "category": "Building \u0026 Trades",
        "subcategory": "Construction",
        "type": "Services"
      }
    ],
    "sg:phone": "+1 440 238 6209",
    "sg:postcode": "44149",
    "sg:province": "OH",
    "sg:tags": [
      "utility",
      "contractor"
    ],
    "wof:name": "Trace Services",
    "wof:placetype": "venue"
  },
  "geometry": {"coordinates":[-81.848182,41.332159],"type":"Point"}
}
