{
  "type": "Feature",
  "properties": {
    "iso:country":"US",
    "sg:address":"11445 Blodgett Creek Trl",
    "sg:city":"Strongsville",
    "sg:classifiers":[
        {
            "category":"Building & Trades",
            "subcategory":"Construction",
            "type":"Services"
        }
    ],
    "sg:phone":"+1 440 238 6209",
    "sg:postcode":"44149",
    "sg:province":"OH",
    "sg:tags":[
        "utility",
        "contractor"
    ],
    "wof:name":"Trace Services",
    "wof:placetype":"venue"
},
  "geometry": {"coordinates":[-81.84818199999999,41.332159],"type":"Point"}
}