{
  "type": "Feature",
  "properties": {
    "addr:full": "685 Harmon Plz Columbus OH 43223",
    "addr:housenumber": "685",
    "addr:postcode": "43223",
    "addr:street": "Harmon Plz",
    "iso:country": "US",
    "sg:address": "685 Harmon Plz",
    "sg:city": "Columbus",
    "sg:classifiers": [
      {
        "category": "Wholesale",
        "subcategory": "Vending Machines",
        "type": "Manufacturing \u0026 Wholesale Goods"
      }
    ],
    "sg:phone": "+1 614 449 0420",
    "sg:postcode": "43223",
    "sg:province": "OH",
    "sg:tags": [
      "operator"
    ],
    "wof:name": "Rmj Vending",
    "wof:placetype": "venue"
  },
  "geometry": {"coordinates":[-83.014426,39.929144],"type":"Point"}
}
