{
  "type": "Feature",
  "properties": {
    "addr:full":"913 N Keowee St Dayton OH 45404",
    "addr:housenumber":"913",
    "addr:postcode":"45404",
    "addr:street":"N Keowee St",
    "iso:country":"US",
    "sg:address":"913 N Keowee St",
    "sg:city":"Dayton",
    "sg:classifiers":[
        {
            "category":"Manufacturing",
            "subcategory":"Printing",
            "type":"Manufacturing & Wholesale Goods"
        }
    ],
    "sg:phone":"+1 937 228 2588",
    "sg:postcode":"45404",
    "sg:province":"OH",
    "sg:tags":[
        "printer"
    ],
    "wof:name":"Dayton Printmakers Co-Op",
    "wof:placetype":"venue"
},
  "geometry": {"coordinates":[-84.183994,39.777039],"type":"Point"}
}