{
  "type": "Feature",
  "properties": {
    "addr:full":"4840 Sinclair Rd Columbus OH 43229",
    "addr:housenumber":"4840",
    "addr:postcode":"43229",
    "addr:street":"Sinclair Rd",
    "iso:country":"US",
    "sg:address":"4840 Sinclair Rd",
    "sg:city":"Columbus",
    "sg:classifiers":[
        {
            "category":"Food & Beverages",
            "subcategory":"Groceries & Convenience Stores",
            "type":"Retail Goods"
        }
    ],
    "sg:phone":"+1 614 885 8104",
    "sg:postcode":"43229",
    "sg:province":"OH",
    "wof:name":"Pak Gas",
    "wof:placetype":"venue"
},
  "geometry": {"coordinates":[-82.998581,40.063463],"type":"Point"}
}