{
  "type": "Feature",
  "properties": {
    "iso:country":"US",
    "sg:address":"1120 E State St",
    "sg:city":"Alliance",
    "sg:classifiers":[
        {
            "category":"Personal",
            "subcategory":"Barber",
            "type":"Services"
        }
    ],
    "sg:phone":"+1 330 821 1020",
    "sg:postcode":"44601",
    "sg:province":"OH",
    "wof:name":"College Plaza Barber Shop",
    "wof:placetype":"venue"
},
  "geometry": {"coordinates":[-81.086949,40.901686],"type":"Point"}
}