{
  "type": "Feature",
  "properties": {
    "addr:full":"225 Greenville Rd St Marys OH 45885",
    "addr:housenumber":"225",
    "addr:postcode":"45885",
    "addr:street":"Greenville Rd",
    "iso:country":"US",
    "sg:address":"225 Greenville Rd",
    "sg:city":"St Marys",
    "sg:classifiers":[
        {
            "category":"Building & Trades",
            "subcategory":"Plumbing",
            "type":"Services"
        }
    ],
    "sg:phone":"+1 419 394 8121",
    "sg:postcode":"45885",
    "sg:province":"OH",
    "sg:tags":[
        "plumbing",
        "contractor"
    ],
    "wof:name":"Quality Plumbing & Heating",
    "wof:placetype":"venue"
},
  "geometry": {"coordinates":[-84.385255,40.534782],"type":"Point"}
}