{
  "type": "Feature",
  "properties": {
    "iso:country":"US",
    "sg:address":"1059 Grand Ave",
    "sg:city":"Madison",
    "sg:classifiers":[
        {
            "category":"Building & Trades",
            "subcategory":"Plumbing",
            "type":"Services"
        }
    ],
    "sg:phone":"+1 440 428 7676",
    "sg:postcode":"44057",
    "sg:province":"OH",
    "sg:tags":[
        "heating",
        "contractor"
    ],
    "wof:name":"Polar Heating & Cooling",
    "wof:placetype":"venue"
},
  "geometry": {"coordinates":[-81.016148,41.844492],"type":"Point"}
}