{
  "type": "Feature",
  "properties": {
    "addr:full": "4265 E Dublin Granville Rd Westerville OH 43081",
    "addr:housenumber": "4265",
    "addr:postcode": "43081",
    "addr:street": "E Dublin Granville Rd",
    "iso:country": "US",
    "sg:address": "4265 E Dublin Granville Rd",
    "sg:city": "Westerville",
    "sg:classifiers": [
      {
        "category": "Travel",
        "subcategory": "Campground",
        "type": "Entertainment"
      }
    ],
    "sg:phone": "+1 614 891 0700",
    "sg:postcode": "43081",
    "sg:province": "OH",
    "sg:tags": [
      "trailer"
    ],
    "wof:name": "Blendon Woods Metro Park",
    "wof:placetype": "venue"
  },
  "geometry": {"coordinates":[-82.883138,40.079796],"type":"Point"}
}
