{
  "type": "Feature",
  "properties": {
    "iso:country":"US",
    "sg:address":"7176 Hartcrest Ln",
    "sg:city":"Dayton",
    "sg:classifiers":[
        {
            "category":"Shopping",
            "type":"Retail Goods"
        }
    ],
    "sg:phone":"+1 937 435 4521",
    "sg:postcode":"45459",
    "sg:province":"OH",
    "sg:tags":[
        "product",
        "wood"
    ],
    "wof:name":"Grandpa's Wood Creations",
    "wof:placetype":"venue"
},
  "geometry": {"coordinates":[-84.142192,39.640102],"type":"Point"}
}