{
  "type": "Feature",
  "properties": {
    "addr:full":"500 Lena Dr Aurora OH 44202",
    "addr:housenumber":"500",
    "addr:postcode":"44202",
    "addr:street":"Lena Dr",
    "iso:country":"US",
    "sg:address":"500 Lena Dr",
    "sg:city":"Aurora",
    "sg:classifiers":[
        {
            "category":"Wholesale",
            "subcategory":"Durable Goods & Equipment",
            "type":"Manufacturing & Wholesale Goods"
        }
    ],
    "sg:phone":"+1 330 562 2125",
    "sg:postcode":"44202",
    "sg:province":"OH",
    "sg:tags":[
        "representative",
        "manufacturer"
    ],
    "wof:name":"Thermoform Plastics Inc",
    "wof:placetype":"venue"
},
  "geometry": {"coordinates":[-81.336361,41.283898],"type":"Point"}
}