{
  "type": "Feature",
  "properties": {
    "addr:full":"880 E State St Sharon OH 16146",
    "addr:housenumber":"880",
    "addr:postcode":"16146",
    "addr:street":"E State St",
    "iso:country":"US",
    "sg:address":"880 E State St",
    "sg:city":"Sharon",
    "sg:classifiers":[
        {
            "category":"Shopping",
            "subcategory":"Gifts & Souvenirs",
            "type":"Retail Goods"
        }
    ],
    "sg:phone":"+1   ",
    "sg:postcode":"16146",
    "sg:province":"OH",
    "wof:name":"Louisas Flowers & Gifts",
    "wof:placetype":"venue"
},
  "geometry": {"coordinates":[-80.491676,41.232961],"type":"Point"}
}