{
  "type": "Feature",
  "properties": {
    "iso:country":"US",
    "sg:address":"99 Park Ave E",
    "sg:city":"Mansfield",
    "sg:classifiers":[
        {
            "category":"Government",
            "subcategory":"Office",
            "type":"Public Place"
        }
    ],
    "sg:phone":"+1 419 774 5595",
    "sg:postcode":"44902",
    "sg:province":"OH",
    "wof:name":"Richland County Bar Assn",
    "wof:placetype":"venue"
},
  "geometry": {"coordinates":[-82.512038,40.758493],"type":"Point"}
}