{
  "type": "Feature",
  "properties": {
    "addr:full":"1427 Yale Dr Brunswick OH 44212",
    "addr:housenumber":"1427",
    "addr:postcode":"44212",
    "addr:street":"Yale Dr",
    "iso:country":"US",
    "sg:address":"1427 Yale Dr",
    "sg:city":"Brunswick",
    "sg:classifiers":[
        {
            "category":"Building & Trades",
            "subcategory":"Construction",
            "type":"Services"
        }
    ],
    "sg:phone":"+1 330 225 8033",
    "sg:postcode":"44212",
    "sg:province":"OH",
    "sg:tags":[
        "house"
    ],
    "wof:name":"Wolf Creek Log Homes Ltd",
    "wof:placetype":"venue"
},
  "geometry": {"coordinates":[-81.83308599999999,41.237098],"type":"Point"}
}