{
  "type": "Feature",
  "properties": {
    "iso:country":"US",
    "sg:address":"33462 Warwickshire Ln",
    "sg:city":"Solon",
    "sg:classifiers":[
        {
            "category":"Building & Trades",
            "subcategory":"Construction",
            "type":"Services"
        }
    ],
    "sg:phone":"+1 440 248 2979",
    "sg:postcode":"44139",
    "sg:province":"OH",
    "sg:tags":[
        "contractor"
    ],
    "wof:name":"Fusco Sandstone",
    "wof:placetype":"venue"
},
  "geometry": {"coordinates":[-81.444152,41.36708],"type":"Point"}
}