{
  "type": "Feature",
  "properties": {
    "addr:full": "33462 Warwickshire Ln Solon OH 44139",
    "addr:housenumber": "33462",
    "addr:postcode": "44139",
    "addr:street": "Warwickshire Ln",
    "iso:country": "US",
    "sg:address": "33462 Warwickshire Ln",
    "sg:city": "Solon",
    "sg:classifiers": [
      {
        "category": "Building \u0026 Trades",
        "subcategory": "Construction",
        "type": "Services"
      }
    ],
    "sg:phone": "+1 440 248 2979",
    "sg:postcode": "44139",
    "sg:province": "OH",
    "sg:tags": [
      "contractor"
    ],
    "wof:name": "Fusco Sandstone",
    "wof:placetype": "venue"
  },
  "geometry": {"coordinates":[-81.444152,41.36708],"type":"Point"}
}
