{
  "type": "Feature",
  "properties": {
    "iso:country":"US",
    "sg:address":"320 S Paint St",
    "sg:city":"Chillicothe",
    "sg:classifiers":[
        {
            "category":"Autos & Motor Vehicles",
            "subcategory":"Auto Supplies",
            "type":"Retail Goods"
        }
    ],
    "sg:phone":"+1 740 773 5481",
    "sg:postcode":"45601",
    "sg:province":"OH",
    "sg:tags":[
        "tire"
    ],
    "wof:name":"Jack's Tire & Auto Ctr",
    "wof:placetype":"venue"
},
  "geometry": {"coordinates":[-82.98048900000001,39.326428],"type":"Point"}
}