{
  "type": "Feature",
  "properties": {
    "addr:full": "320 S Paint St Chillicothe OH 45601",
    "addr:housenumber": "320",
    "addr:postcode": "45601",
    "addr:street": "S Paint St",
    "iso:country": "US",
    "sg:address": "320 S Paint St",
    "sg:city": "Chillicothe",
    "sg:classifiers": [
      {
        "category": "Autos \u0026 Motor Vehicles",
        "subcategory": "Auto Supplies",
        "type": "Retail Goods"
      }
    ],
    "sg:phone": "+1 740 773 5481",
    "sg:postcode": "45601",
    "sg:province": "OH",
    "sg:tags": [
      "tire"
    ],
    "wof:name": "Jack's Tire \u0026 Auto Ctr",
    "wof:placetype": "venue"
  },
  "geometry": {"coordinates":[-82.980489,39.326428],"type":"Point"}
}
