{
  "type": "Feature",
  "properties": {
    "addr:full": "8290 Harvest Wind Dr Westerville OH 43082",
    "addr:housenumber": "8290",
    "addr:postcode": "43082",
    "addr:street": "Harvest Wind Dr",
    "iso:country": "US",
    "sg:address": "8290 Harvest Wind Dr",
    "sg:city": "Westerville",
    "sg:classifiers": [
      {
        "category": "Manufacturing",
        "subcategory": "Electronics",
        "type": "Manufacturing \u0026 Wholesale Goods"
      }
    ],
    "sg:phone": "+1 614 895 1329",
    "sg:postcode": "43082",
    "sg:province": "OH",
    "sg:tags": [
      "equipment",
      "electronic",
      "supply"
    ],
    "wof:name": "Toshiba International Corp",
    "wof:placetype": "venue"
  },
  "geometry": {"coordinates":[-82.882838,40.154257],"type":"Point"}
}
