{
  "type": "Feature",
  "properties": {
    "addr:full":"3107 Mayfield Rd Cleveland OH 44118",
    "addr:housenumber":"3107",
    "addr:postcode":"44118",
    "addr:street":"Mayfield Rd",
    "iso:country":"US",
    "sg:address":"3107 Mayfield Rd",
    "sg:city":"Cleveland",
    "sg:classifiers":[
        {
            "category":"Shopping",
            "subcategory":"Used Merchandise",
            "type":"Retail Goods"
        }
    ],
    "sg:phone":"+1 216 932 6380",
    "sg:postcode":"44118",
    "sg:province":"OH",
    "wof:name":"American Antiques",
    "wof:placetype":"venue"
},
  "geometry": {"coordinates":[-81.566654,41.516735],"type":"Point"}
}