{
  "type": "Feature",
  "properties": {
    "iso:country":"US",
    "sg:address":"3231 Central Park W",
    "sg:city":"Toledo",
    "sg:classifiers":[
        {
            "category":"Organizations",
            "subcategory":"Non-profit Organization",
            "type":"Services"
        }
    ],
    "sg:phone":"+1 419 842 0800",
    "sg:postcode":"43617",
    "sg:province":"OH",
    "sg:website":"www.hcno.org",
    "wof:name":"Hospital Council Of Northwest",
    "wof:placetype":"venue"
},
  "geometry": {"coordinates":[-83.700556,41.676135],"type":"Point"}
}