{
  "type": "Feature",
  "properties": {
    "iso:country":"US",
    "sg:address":"535 E Smith Rd",
    "sg:city":"Medina",
    "sg:classifiers":[
        {
            "category":"Health Services",
            "subcategory":"Podiatrist",
            "type":"Services"
        }
    ],
    "sg:phone":"+1 330 725 7075",
    "sg:postcode":"44256",
    "sg:province":"OH",
    "sg:website":"www.agapepodiatry.com",
    "wof:name":"Agape Podiatry Group",
    "wof:placetype":"venue"
},
  "geometry": {"coordinates":[-81.85536399999999,41.13634],"type":"Point"}
}