{
  "type": "Feature",
  "properties": {
    "addr:full": "1024 Cement Ave Sandusky OH 44870",
    "addr:housenumber": "1024",
    "addr:postcode": "44870",
    "addr:street": "Cement Ave",
    "iso:country": "US",
    "sg:address": "1024 Cement Ave",
    "sg:city": "Sandusky",
    "sg:classifiers": [
      {
        "category": "Building \u0026 Trades",
        "subcategory": "Construction",
        "type": "Services"
      }
    ],
    "sg:phone": "+1 419 627 5881",
    "sg:postcode": "44870",
    "sg:province": "OH",
    "wof:name": "Street Maintenance",
    "wof:placetype": "venue"
  },
  "geometry": {"coordinates":[-82.749141,41.444609],"type":"Point"}
}
