{
  "type": "Feature",
  "properties": {
    "addr:full": "48 E Main St West Jefferson OH 43162",
    "addr:housenumber": "48",
    "addr:postcode": "43162",
    "addr:street": "E Main St",
    "iso:country": "US",
    "sg:address": "48 E Main St",
    "sg:city": "West Jefferson",
    "sg:classifiers": [
      {
        "category": "Professional",
        "subcategory": "Business Services",
        "type": "Services"
      }
    ],
    "sg:phone": "+1 614 879 7171",
    "sg:postcode": "43162",
    "sg:province": "OH",
    "sg:tags": [
      "merchandise"
    ],
    "wof:name": "Chevron Pool Co",
    "wof:placetype": "venue"
  },
  "geometry": {"coordinates":[-83.266163,39.945033],"type":"Point"}
}
