{
  "type": "Feature",
  "properties": {
    "iso:country":"US",
    "sg:address":"48 E Main St",
    "sg:city":"West Jefferson",
    "sg:classifiers":[
        {
            "category":"Professional",
            "subcategory":"Business Services",
            "type":"Services"
        }
    ],
    "sg:phone":"+1 614 879 7171",
    "sg:postcode":"43162",
    "sg:province":"OH",
    "sg:tags":[
        "merchandise"
    ],
    "wof:name":"Chevron Pool Co",
    "wof:placetype":"venue"
},
  "geometry": {"coordinates":[-83.26616300000001,39.945033],"type":"Point"}
}