{
  "type": "Feature",
  "properties": {
    "addr:full": "47 W Long St Columbus OH 43215",
    "addr:housenumber": "47",
    "addr:postcode": "43215",
    "addr:street": "W Long St",
    "iso:country": "US",
    "sg:address": "47 W Long St",
    "sg:city": "Columbus",
    "sg:classifiers": [
      {
        "category": "Professional",
        "subcategory": "Lawyer \u0026 Legal Services",
        "type": "Services"
      }
    ],
    "sg:phone": "+1 614 221 1771",
    "sg:postcode": "43215",
    "sg:province": "OH",
    "sg:tags": [
      "attorney"
    ],
    "wof:name": "Robert Liss",
    "wof:placetype": "venue"
  },
  "geometry": {"coordinates":[-83.002476,39.964729],"type":"Point"}
}
