{
  "type": "Feature",
  "properties": {
    "addr:full":"8526 Usher Rd Cleveland OH 44138",
    "addr:housenumber":"8526",
    "addr:postcode":"44138",
    "addr:street":"Usher Rd",
    "iso:country":"US",
    "sg:address":"8526 Usher Rd",
    "sg:city":"Cleveland",
    "sg:classifiers":[
        {
            "category":"Organizations",
            "subcategory":"Religious Organization",
            "type":"Services"
        }
    ],
    "sg:phone":"+1 440 235 4558",
    "sg:postcode":"44138",
    "sg:province":"OH",
    "sg:tags":[
        "church"
    ],
    "wof:name":"St Innocent Orthodox Church",
    "wof:placetype":"venue"
},
  "geometry": {"coordinates":[-81.90992199999999,41.366876],"type":"Point"}
}