{
  "type": "Feature",
  "properties": {
    "addr:full":"6448 Meadowbrook Cir Columbus OH 43085",
    "addr:housenumber":"6448",
    "addr:postcode":"43085",
    "addr:street":"Meadowbrook Cir",
    "iso:country":"US",
    "sg:address":"6448 Meadowbrook Cir",
    "sg:city":"Columbus",
    "sg:classifiers":[
        {
            "category":"Professional",
            "type":"Services"
        }
    ],
    "sg:phone":"+1 614 436 0382",
    "sg:postcode":"43085",
    "sg:province":"OH",
    "wof:name":"A1 Intl Corp",
    "wof:placetype":"venue"
},
  "geometry": {"coordinates":[-83.049252,40.098423],"type":"Point"}
}