{
  "type": "Feature",
  "properties": {
    "iso:country":"US",
    "sg:address":"1115 Milton St",
    "sg:city":"Akron",
    "sg:classifiers":[
        {
            "category":"Organizations",
            "subcategory":"Religious Organization",
            "type":"Services"
        }
    ],
    "sg:phone":"+1 330 724 4657",
    "sg:postcode":"44306",
    "sg:province":"OH",
    "wof:name":"New Cvanent Sanctuary Appraise",
    "wof:placetype":"venue"
},
  "geometry": {"coordinates":[-81.49023200000001,41.054291],"type":"Point"}
}