{
  "type": "Feature",
  "properties": {
    "addr:full": "723 Treasury Dr Dayton OH 45429",
    "addr:housenumber": "723",
    "addr:postcode": "45429",
    "addr:street": "Treasury Dr",
    "iso:country": "US",
    "sg:address": "723 Treasury Dr",
    "sg:city": "Dayton",
    "sg:classifiers": [
      {
        "category": "Health Services",
        "subcategory": "Clinic",
        "type": "Services"
      }
    ],
    "sg:phone": "+1 937 643 1540",
    "sg:postcode": "45429",
    "sg:province": "OH",
    "wof:name": "Supplemental Health Care",
    "wof:placetype": "venue"
  },
  "geometry": {"coordinates":[-84.155464,39.695234],"type":"Point"}
}
