{
  "type": "Feature",
  "properties": {
    "iso:country":"US",
    "sg:address":"723 Treasury Dr",
    "sg:city":"Dayton",
    "sg:classifiers":[
        {
            "category":"Health Services",
            "subcategory":"Clinic",
            "type":"Services"
        }
    ],
    "sg:phone":"+1 937 643 1540",
    "sg:postcode":"45429",
    "sg:province":"OH",
    "wof:name":"Supplemental Health Care",
    "wof:placetype":"venue"
},
  "geometry": {"coordinates":[-84.15546399999999,39.695234],"type":"Point"}
}