{
  "type": "Feature",
  "properties": {
    "iso:country":"US",
    "sg:address":"6647 Foster Ave",
    "sg:city":"Cincinnati",
    "sg:classifiers":[
        {
            "category":"Retail",
            "subcategory":"Laundry & Dry Cleaning",
            "type":"Services"
        }
    ],
    "sg:phone":"+1 513 232 9663",
    "sg:postcode":"45230",
    "sg:province":"OH",
    "sg:tags":[
        "cleaner",
        "rug",
        "carpet"
    ],
    "sg:website":"www.chemdry.com",
    "wof:name":"Anderson Chem-Dry",
    "wof:placetype":"venue"
},
  "geometry": {"coordinates":[-84.376161,39.076006],"type":"Point"}
}