{
  "type": "Feature",
  "properties": {
    "addr:full": "983 Quarry Park Dr Reynoldsburg OH 43068",
    "addr:housenumber": "983",
    "addr:postcode": "43068",
    "addr:street": "Quarry Park Dr",
    "iso:country": "US",
    "sg:address": "983 Quarry Park Dr",
    "sg:city": "Reynoldsburg",
    "sg:classifiers": [
      {
        "category": "Arts \u0026 Performance",
        "subcategory": "Theater",
        "type": "Entertainment"
      }
    ],
    "sg:phone": "+1 614 575 0069",
    "sg:postcode": "43068",
    "sg:province": "OH",
    "sg:tags": [
      "telegram",
      "singing"
    ],
    "wof:name": "Ladies Of Desire",
    "wof:placetype": "venue"
  },
  "geometry": {"coordinates":[-82.785738,39.966511],"type":"Point"}
}
