{
  "type": "Feature",
  "properties": {
    "iso:country":"US",
    "sg:address":"983 Quarry Park Dr",
    "sg:city":"Reynoldsburg",
    "sg:classifiers":[
        {
            "category":"Arts & Performance",
            "subcategory":"Theater",
            "type":"Entertainment"
        }
    ],
    "sg:phone":"+1 614 575 0069",
    "sg:postcode":"43068",
    "sg:province":"OH",
    "sg:tags":[
        "telegram",
        "singing"
    ],
    "wof:name":"Ladies Of Desire",
    "wof:placetype":"venue"
},
  "geometry": {"coordinates":[-82.78573799999999,39.966511],"type":"Point"}
}