{
  "type": "Feature",
  "properties": {
    "iso:country":"US",
    "sg:address":"5833 Turney Rd",
    "sg:city":"Cleveland",
    "sg:classifiers":[
        {
            "category":"Food & Beverages",
            "subcategory":"Bakery",
            "type":"Retail Goods"
        }
    ],
    "sg:phone":"+1 216 663 1270",
    "sg:postcode":"44125",
    "sg:province":"OH",
    "wof:name":"Kathleens Cakes & Bakery Shop",
    "wof:placetype":"venue"
},
  "geometry": {"coordinates":[-81.596163,41.403347],"type":"Point"}
}