{
  "type": "Feature",
  "properties": {
    "iso:country":"US",
    "sg:address":"338 N Ohio Ave",
    "sg:city":"Fremont",
    "sg:classifiers":[
        {
            "category":"Retail",
            "subcategory":"Laundry & Dry Cleaning",
            "type":"Services"
        }
    ],
    "sg:phone":"+1 419 332 2966",
    "sg:postcode":"43420",
    "sg:province":"OH",
    "sg:tags":[
        "commercial"
    ],
    "wof:name":"Fremont Ldry Dry Clrs Lin Sup",
    "wof:placetype":"venue"
},
  "geometry": {"coordinates":[-83.105198,41.348635],"type":"Point"}
}