{
  "type": "Feature",
  "properties": {
    "addr:full": "52 Public Sq Medina OH 44256",
    "addr:housenumber": "52",
    "addr:postcode": "44256",
    "addr:street": "Public Sq",
    "iso:country": "US",
    "sg:address": "52 Public Sq",
    "sg:city": "Medina",
    "sg:classifiers": [
      {
        "category": "Professional",
        "subcategory": "Lawyer \u0026 Legal Services",
        "type": "Services"
      }
    ],
    "sg:phone": "+1 330 722 2144",
    "sg:postcode": "44256",
    "sg:province": "OH",
    "sg:tags": [
      "attorney"
    ],
    "wof:name": "Robert M Hanwell",
    "wof:placetype": "venue"
  },
  "geometry": {"coordinates":[-81.863131,41.137956],"type":"Point"}
}
