{
  "type": "Feature",
  "properties": {
    "iso:country":"US",
    "sg:address":"295 Wetmore Ave SE",
    "sg:city":"Massillon",
    "sg:classifiers":[
        {
            "category":"Manufacturing",
            "subcategory":"Metals",
            "type":"Manufacturing & Wholesale Goods"
        },
        {
            "category":"Manufacturing",
            "subcategory":"Tools & Machinery",
            "type":"Manufacturing & Wholesale Goods"
        }
    ],
    "sg:phone":"+1 330 830 4210",
    "sg:postcode":"44646",
    "sg:province":"OH",
    "sg:tags":[
        "industrial",
        "sheet",
        "mfg",
        "fabricator",
        "fabrication",
        "structural"
    ],
    "wof:name":"National Precision Fabricators",
    "wof:placetype":"venue"
},
  "geometry": {"coordinates":[-81.517388,40.791652],"type":"Point"}
}