{
  "type": "Feature",
  "properties": {
    "addr:full": "295 Wetmore Ave SE Massillon OH 44646",
    "addr:housenumber": "295",
    "addr:postcode": "44646",
    "addr:street": "Wetmore Ave Se",
    "iso:country": "US",
    "sg:address": "295 Wetmore Ave SE",
    "sg:city": "Massillon",
    "sg:classifiers": [
      {
        "category": "Manufacturing",
        "subcategory": "Metals",
        "type": "Manufacturing \u0026 Wholesale Goods"
      },
      {
        "category": "Manufacturing",
        "subcategory": "Tools \u0026 Machinery",
        "type": "Manufacturing \u0026 Wholesale Goods"
      }
    ],
    "sg:phone": "+1 330 830 4210",
    "sg:postcode": "44646",
    "sg:province": "OH",
    "sg:tags": [
      "industrial",
      "sheet",
      "mfg",
      "fabricator",
      "fabrication",
      "structural"
    ],
    "wof:name": "National Precision Fabricators",
    "wof:placetype": "venue"
  },
  "geometry": {"coordinates":[-81.517388,40.791652],"type":"Point"}
}
