{
  "type": "Feature",
  "properties": {
    "addr:full": "5181 Natorp Blvd Ste 202 Mason OH 45040",
    "addr:housenumber": "5181",
    "addr:postcode": "45040",
    "addr:street": "Natorp Blvd Ste 202",
    "iso:country": "US",
    "sg:address": "5181 Natorp Blvd Ste 202",
    "sg:city": "Mason",
    "sg:classifiers": [
      {
        "category": "Professional",
        "subcategory": "Lawyer \u0026 Legal Services",
        "type": "Services"
      }
    ],
    "sg:phone": "+1 513 489 0829",
    "sg:postcode": "45040",
    "sg:province": "OH",
    "sg:tags": [
      "attorney",
      "law",
      "collection"
    ],
    "wof:name": "Mason, Schilling \u0026 Mason Co., L.P.A.",
    "wof:placetype": "venue"
  },
  "geometry": {"coordinates":[-84.317221,39.300909],"type":"Point"}
}
