{
  "type": "Feature",
  "properties": {
    "addr:full": "234 1st St Piqua OH 45356",
    "addr:housenumber": "234",
    "addr:postcode": "45356",
    "addr:street": "1St St",
    "iso:country": "US",
    "sg:address": "234 1st St",
    "sg:city": "Piqua",
    "sg:classifiers": [
      {
        "category": "Professional",
        "subcategory": "Management \u0026 Consulting",
        "type": "Services"
      }
    ],
    "sg:phone": "+1 937 773 7481",
    "sg:postcode": "45356",
    "sg:province": "OH",
    "sg:tags": [
      "consultant",
      "business"
    ],
    "wof:name": "Scarbrough Management",
    "wof:placetype": "venue"
  },
  "geometry": {"coordinates":[-84.232575,40.144442],"type":"Point"}
}
