{
  "type": "Feature",
  "properties": {
    "addr:full": "1666 el Dorado Blvd Brunswick OH 44212",
    "addr:housenumber": "1666",
    "addr:postcode": "44212",
    "addr:street": "El Dorado Blvd",
    "iso:country": "US",
    "sg:address": "1666 el Dorado Blvd",
    "sg:city": "Brunswick",
    "sg:classifiers": [
      {
        "category": "Building \u0026 Trades",
        "subcategory": "Construction",
        "type": "Services"
      }
    ],
    "sg:phone": "+1 330 225 3585",
    "sg:postcode": "44212",
    "sg:province": "OH",
    "sg:tags": [
      "general",
      "contractor"
    ],
    "sg:website": "www.cannonsline.com",
    "wof:name": "Cannon Sline",
    "wof:placetype": "venue"
  },
  "geometry": {"coordinates":[-81.810976,41.229968],"type":"Point"}
}
