{
  "type": "Feature",
  "properties": {
    "iso:country":"US",
    "sg:address":"7613 Reading Rd",
    "sg:city":"Cincinnati",
    "sg:classifiers":[
        {
            "category":"Professional",
            "subcategory":"Accounting & Tax Preparation",
            "type":"Services"
        }
    ],
    "sg:phone":"+1 513 821 4112",
    "sg:postcode":"45237",
    "sg:province":"OH",
    "sg:tags":[
        "accountant"
    ],
    "wof:name":"Lawrence G Zalants CPA",
    "wof:placetype":"venue"
},
  "geometry": {"coordinates":[-84.456649,39.200838],"type":"Point"}
}