{
  "type": "Feature",
  "properties": {
    "addr:full":"5005 Rockside Rd Cleveland OH 44131",
    "addr:housenumber":"5005",
    "addr:postcode":"44131",
    "addr:street":"Rockside Rd",
    "iso:country":"US",
    "sg:address":"5005 Rockside Rd",
    "sg:city":"Cleveland",
    "sg:classifiers":[
        {
            "category":"Health Services",
            "subcategory":"Doctor",
            "type":"Services"
        }
    ],
    "sg:phone":"+1 440 446 1698",
    "sg:postcode":"44131",
    "sg:province":"OH",
    "sg:tags":[
        "physician",
        "surgeon"
    ],
    "wof:name":"Western Reserve Plastic Srgry",
    "wof:placetype":"venue"
},
  "geometry": {"coordinates":[-81.65351,41.396943],"type":"Point"}
}