{
  "type": "Feature",
  "properties": {
    "addr:full":"305 Illinois Ave Mc Donald OH 44437",
    "addr:housenumber":"305",
    "addr:postcode":"44437",
    "addr:street":"Illinois Ave Mc",
    "iso:country":"US",
    "sg:address":"305 Illinois Ave",
    "sg:city":"Mc Donald",
    "sg:classifiers":[
        {
            "category":"Building & Trades",
            "subcategory":"Construction",
            "type":"Services"
        }
    ],
    "sg:phone":"+1 330 530 5210",
    "sg:postcode":"44437",
    "sg:province":"OH",
    "sg:tags":[
        "house"
    ],
    "wof:name":"A&G Builders Unlimited LLC",
    "wof:placetype":"venue"
},
  "geometry": {"coordinates":[-80.7264,41.16522],"type":"Point"}
}