{
  "type": "Feature",
  "properties": {
    "iso:country":"US",
    "sg:address":"6465 Monroe St",
    "sg:city":"Sylvania",
    "sg:classifiers":[
        {
            "category":"Insurance",
            "subcategory":"Insurance Agent",
            "type":"Services"
        }
    ],
    "sg:phone":"+1 419 885 0660",
    "sg:postcode":"43560",
    "sg:province":"OH",
    "wof:name":"Labadie Insurance Agency",
    "wof:placetype":"venue"
},
  "geometry": {"coordinates":[-83.702986,41.715531],"type":"Point"}
}