{
  "type": "Feature",
  "properties": {
    "addr:full":"13 N South St Wilmington OH 45177",
    "addr:housenumber":"13",
    "addr:postcode":"45177",
    "addr:street":"N South St",
    "iso:country":"US",
    "sg:address":"13 N South St",
    "sg:city":"Wilmington",
    "sg:classifiers":[
        {
            "category":"Travel",
            "subcategory":"Travel Agent",
            "type":"Entertainment"
        }
    ],
    "sg:phone":"+1 937 382 1965",
    "sg:postcode":"45177",
    "sg:province":"OH",
    "sg:tags":[
        "information",
        "tourist"
    ],
    "wof:name":"Clinton County CVB",
    "wof:placetype":"venue"
},
  "geometry": {"coordinates":[-83.828586,39.446384],"type":"Point"}
}