{
  "type": "Feature",
  "properties": {
    "iso:country":"US",
    "sg:address":"2721 S Union Ave",
    "sg:city":"Alliance",
    "sg:classifiers":[
        {
            "category":"Professional",
            "type":"Services"
        }
    ],
    "sg:phone":"+1 330 823 6021",
    "sg:postcode":"44601",
    "sg:province":"OH",
    "wof:name":"Richard Fecik",
    "wof:placetype":"venue"
},
  "geometry": {"coordinates":[-81.105797,40.894738],"type":"Point"}
}