{
  "type": "Feature",
  "properties": {
    "addr:full": "2721 S Union Ave Alliance OH 44601",
    "addr:housenumber": "2721",
    "addr:postcode": "44601",
    "addr:street": "S Union Ave",
    "iso:country": "US",
    "sg:address": "2721 S Union Ave",
    "sg:city": "Alliance",
    "sg:classifiers": [
      {
        "category": "Professional",
        "type": "Services"
      }
    ],
    "sg:phone": "+1 330 823 6021",
    "sg:postcode": "44601",
    "sg:province": "OH",
    "wof:name": "Richard Fecik",
    "wof:placetype": "venue"
  },
  "geometry": {"coordinates":[-81.105797,40.894738],"type":"Point"}
}
