{
  "type": "Feature",
  "properties": {
    "iso:country":"US",
    "sg:address":"31550 Chieftain Dr",
    "sg:city":"Logan",
    "sg:classifiers":[
        {
            "category":"Banks & Credit Unions",
            "subcategory":"Bank",
            "type":"Services"
        }
    ],
    "sg:phone":"+1 740 385 0995",
    "sg:postcode":"43138",
    "sg:province":"OH",
    "sg:tags":[
        "national",
        "commercial"
    ],
    "wof:name":"Citizens Bank Tne",
    "wof:placetype":"venue"
},
  "geometry": {"coordinates":[-82.43765999999999,39.547332],"type":"Point"}
}