{
  "type": "Feature",
  "properties": {
    "addr:full": "31550 Chieftain Dr Logan OH 43138",
    "addr:housenumber": "31550",
    "addr:postcode": "43138",
    "addr:street": "Chieftain Dr",
    "iso:country": "US",
    "sg:address": "31550 Chieftain Dr",
    "sg:city": "Logan",
    "sg:classifiers": [
      {
        "category": "Banks \u0026 Credit Unions",
        "subcategory": "Bank",
        "type": "Services"
      }
    ],
    "sg:phone": "+1 740 385 0995",
    "sg:postcode": "43138",
    "sg:province": "OH",
    "sg:tags": [
      "national",
      "commercial"
    ],
    "wof:name": "Citizens Bank Tne",
    "wof:placetype": "venue"
  },
  "geometry": {"coordinates":[-82.43766,39.547332],"type":"Point"}
}
