{
  "type": "Feature",
  "properties": {
    "addr:full":"777 Dearborn Park Ln Worthington OH 43085",
    "addr:housenumber":"777",
    "addr:postcode":"43085",
    "addr:street":"Dearborn Park Ln",
    "iso:country":"US",
    "sg:address":"777 Dearborn Park Ln",
    "sg:city":"Worthington",
    "sg:classifiers":[
        {
            "category":"Organizations",
            "subcategory":"Labor Organization",
            "type":"Services"
        }
    ],
    "sg:phone":"+1 614 888 6784",
    "sg:postcode":"43085",
    "sg:province":"OH",
    "sg:website":"www.uswa.org",
    "wof:name":"United Steelworkers Of America",
    "wof:placetype":"venue"
},
  "geometry": {"coordinates":[-82.996359,40.116078],"type":"Point"}
}