{
  "type": "Feature",
  "properties": {
    "addr:full":"1135 W Alexis Rd Toledo OH 43612",
    "addr:housenumber":"1135",
    "addr:postcode":"43612",
    "addr:street":"W Alexis Rd",
    "iso:country":"US",
    "sg:address":"1135 W Alexis Rd",
    "sg:city":"Toledo",
    "sg:classifiers":[
        {
            "category":"Restaurant",
            "type":"Food & Drink"
        }
    ],
    "sg:phone":"+1 419 478 3023",
    "sg:postcode":"43612",
    "sg:province":"OH",
    "sg:tags":[
        "eating"
    ],
    "wof:name":"Ideal Hot Dog",
    "wof:placetype":"venue"
},
  "geometry": {"coordinates":[-83.568411,41.721478],"type":"Point"}
}