{
  "type": "Feature",
  "properties": {
    "addr:full": "6230 Busch Blvd Columbus OH 43229",
    "addr:postcode": "6230;43229",
    "addr:street": "Busch Blvd",
    "iso:country": "US",
    "sg:address": "6230 Busch Blvd",
    "sg:city": "Columbus",
    "sg:classifiers": [
      {
        "category": "Building \u0026 Trades",
        "subcategory": "Construction",
        "type": "Services"
      }
    ],
    "sg:phone": "+1 614 438 0099",
    "sg:postcode": "43229",
    "sg:province": "OH",
    "sg:tags": [
      "general",
      "contractor"
    ],
    "wof:name": "GFC Commercial Construction",
    "wof:placetype": "venue"
  },
  "geometry": {"coordinates":[-82.992589,40.090293],"type":"Point"}
}
