{
  "type": "Feature",
  "properties": {
    "iso:country":"US",
    "sg:address":"2271 Beechwood Ave",
    "sg:city":"Alliance",
    "sg:classifiers":[
        {
            "category":"Shopping",
            "type":"Retail Goods"
        }
    ],
    "sg:phone":"+1 330 823 0729",
    "sg:postcode":"44601",
    "sg:province":"OH",
    "sg:tags":[
        "picture",
        "frame"
    ],
    "wof:name":"Barb's Frames & Floral Designs",
    "wof:placetype":"venue"
},
  "geometry": {"coordinates":[-81.13416700000001,40.897185],"type":"Point"}
}