{
  "type": "Feature",
  "properties": {
    "addr:full": "515 Station Ave Cincinnati OH 45215",
    "addr:housenumber": "515",
    "addr:postcode": "45215",
    "addr:street": "Station Ave",
    "iso:country": "US",
    "sg:address": "515 Station Ave",
    "sg:city": "Cincinnati",
    "sg:classifiers": [
      {
        "category": "Manufacturing",
        "subcategory": "Paper Products",
        "type": "Manufacturing \u0026 Wholesale Goods"
      }
    ],
    "sg:phone": "+1 513 948 9951",
    "sg:postcode": "45215",
    "sg:province": "OH",
    "sg:website": "www.cindus.com",
    "wof:name": "Cindus Corp",
    "wof:placetype": "venue"
  },
  "geometry": {"coordinates":[-84.457402,39.217047],"type":"Point"}
}
