{
  "type": "Feature",
  "properties": {
    "addr:full":"8011 Lake Ave Cleveland OH 44102",
    "addr:housenumber":"8011",
    "addr:postcode":"44102",
    "addr:street":"Lake Ave",
    "iso:country":"US",
    "sg:address":"8011 Lake Ave",
    "sg:city":"Cleveland",
    "sg:classifiers":[
        {
            "category":"Organizations",
            "subcategory":"Religious Organization",
            "type":"Services"
        }
    ],
    "sg:phone":"+1 216 334 1431",
    "sg:postcode":"44102",
    "sg:province":"OH",
    "wof:name":"Cleveland Christian Homes",
    "wof:placetype":"venue"
},
  "geometry": {"coordinates":[-81.741508,41.483567],"type":"Point"}
}