{
  "type": "Feature",
  "properties": {
    "addr:full":"3900 Ben Hur Ave Willoughby OH 44094",
    "addr:housenumber":"3900",
    "addr:postcode":"44094",
    "addr:street":"Ben Hur Ave",
    "iso:country":"US",
    "sg:address":"3900 Ben Hur Ave",
    "sg:city":"Willoughby",
    "sg:classifiers":[
        {
            "category":"Building & Trades",
            "subcategory":"Construction",
            "type":"Services"
        }
    ],
    "sg:phone":"+1 440 951 6022",
    "sg:postcode":"44094",
    "sg:province":"OH",
    "sg:tags":[
        "general",
        "contractor"
    ],
    "wof:name":"Sound Solutions Contr Svc",
    "wof:placetype":"venue"
},
  "geometry": {"coordinates":[-81.417872,41.644379],"type":"Point"}
}