{
  "type": "Feature",
  "properties": {
    "addr:full": "5676 Rockefeller Center Blvd Dublin OH 43016",
    "addr:housenumber": "5676",
    "addr:postcode": "43016",
    "addr:street": "Center Blvd",
    "iso:country": "US",
    "sg:address": "5676 Rockefeller Center Blvd",
    "sg:city": "Dublin",
    "sg:classifiers": [
      {
        "category": "Wholesale",
        "subcategory": "Auto Parts",
        "type": "Manufacturing \u0026 Wholesale Goods"
      }
    ],
    "sg:phone": "+1 614 761 1932",
    "sg:postcode": "43016",
    "sg:province": "OH",
    "sg:tags": [
      "automobile",
      "supply"
    ],
    "wof:name": "Three M Co",
    "wof:placetype": "venue"
  },
  "geometry": {"coordinates":[-83.126773,40.068679],"type":"Point"}
}
