{
  "type": "Feature",
  "properties": {
    "addr:full": "901 Coover Rd Delaware OH 43015",
    "addr:housenumber": "901",
    "addr:postcode": "43015",
    "addr:street": "Coover Rd",
    "iso:country": "US",
    "sg:address": "901 Coover Rd",
    "sg:city": "Delaware",
    "sg:classifiers": [
      {
        "category": "Education",
        "subcategory": "School",
        "type": "Public Place"
      }
    ],
    "sg:phone": "+1 740 363 1349",
    "sg:postcode": "43015",
    "sg:province": "OH",
    "sg:website": "www.buckeyevalley.k12.oh.us",
    "wof:name": "Buckeye Valley High School",
    "wof:placetype": "venue"
  },
  "geometry": {"coordinates":[-83.098717,40.3509],"type":"Point"}
}
