{
  "type": "Feature",
  "properties": {
    "addr:full": "1013 S Ohio Ave Columbus OH 43206",
    "addr:housenumber": "1013",
    "addr:postcode": "43206",
    "addr:street": "S Ohio Ave",
    "iso:country": "US",
    "sg:address": "1013 S Ohio Ave",
    "sg:city": "Columbus",
    "sg:classifiers": [
      {
        "category": "Organizations",
        "subcategory": "Religious Organization",
        "type": "Services"
      }
    ],
    "sg:phone": "+1 614 252 5975",
    "sg:postcode": "43206",
    "sg:province": "OH",
    "sg:tags": [
      "church"
    ],
    "wof:name": "Ohio Ave United Methodist Chr",
    "wof:placetype": "venue"
  },
  "geometry": {"coordinates":[-82.971972,39.944249],"type":"Point"}
}
