{
  "type": "Feature",
  "properties": {
    "iso:country":"US",
    "sg:address":"1275 Kriswood Ln",
    "sg:city":"Columbus",
    "sg:classifiers":[
        {
            "category":"Utilities",
            "subcategory":"Telephone",
            "type":"Services"
        }
    ],
    "sg:phone":"+1 614 275 4551",
    "sg:postcode":"43228",
    "sg:province":"OH",
    "sg:tags":[
        "company"
    ],
    "wof:name":"Excel Telecommunication Inc",
    "wof:placetype":"venue"
},
  "geometry": {"coordinates":[-83.115487,39.927537],"type":"Point"}
}