{
  "type": "Feature",
  "properties": {
    "addr:full": "35 E 5th Ave Columbus OH 43201",
    "addr:housenumber": "35",
    "addr:postcode": "43201",
    "addr:street": "E 5Th Ave",
    "iso:country": "US",
    "sg:address": "35 E 5th Ave",
    "sg:city": "Columbus",
    "sg:classifiers": [
      {
        "category": "Personal",
        "subcategory": "Tattoo Parlor",
        "type": "Services"
      }
    ],
    "sg:phone": "+1 614 291 8977",
    "sg:postcode": "43201",
    "sg:province": "OH",
    "sg:tags": [
      "tattooing"
    ],
    "wof:name": "Sector 7G",
    "wof:placetype": "venue"
  },
  "geometry": {"coordinates":[-83.004638,39.987003],"type":"Point"}
}
