{
  "type": "Feature",
  "properties": {
    "iso:country":"US",
    "sg:address":"5100 Darrow Rd",
    "sg:city":"Hudson",
    "sg:classifiers":[
        {
            "category":"Professional",
            "type":"Services"
        }
    ],
    "sg:phone":"+1 330 653 5227",
    "sg:postcode":"44236",
    "sg:province":"OH",
    "sg:tags":[
        "establishment"
    ],
    "sg:website":"www.pointovue.com",
    "wof:name":"J M Erbaugh Co",
    "wof:placetype":"venue"
},
  "geometry": {"coordinates":[-81.440489,41.206356],"type":"Point"}
}