{
  "type": "Feature",
  "properties": {
    "iso:country":"US",
    "sg:address":"1105 W Schrock Rd",
    "sg:city":"Columbus",
    "sg:classifiers":[
        {
            "category":"Social Services",
            "subcategory":"Job Training",
            "type":"Services"
        }
    ],
    "sg:phone":"+1 614 885 9806",
    "sg:postcode":"43229",
    "sg:province":"OH",
    "sg:tags":[
        "rehabilitation"
    ],
    "wof:name":"CRA Managed Care Inc",
    "wof:placetype":"venue"
},
  "geometry": {"coordinates":[-82.982364,40.105387],"type":"Point"}
}