{
  "type": "Feature",
  "properties": {
    "addr:full": "1797 Columbia Rd Cleveland OH 44145",
    "addr:housenumber": "1797",
    "addr:postcode": "44145",
    "addr:street": "Columbia Rd",
    "iso:country": "US",
    "sg:address": "1797 Columbia Rd",
    "sg:city": "Cleveland",
    "sg:classifiers": [
      {
        "category": "Professional",
        "subcategory": "Advertising",
        "type": "Services"
      }
    ],
    "sg:phone": "+1 440 808 9000",
    "sg:postcode": "44145",
    "sg:province": "OH",
    "sg:tags": [
      "publisher"
    ],
    "sg:website": "www.fmsyndrome.com",
    "wof:name": "Natural Products Ctr",
    "wof:placetype": "venue"
  },
  "geometry": {"coordinates":[-81.901954,41.46111],"type":"Point"}
}
