{
  "type": "Feature",
  "properties": {
    "addr:full": "1013 Bechtle Ave Springfield OH 45504",
    "addr:housenumber": "1013",
    "addr:postcode": "45504",
    "addr:street": "Bechtle Ave",
    "iso:country": "US",
    "sg:address": "1013 Bechtle Ave",
    "sg:city": "Springfield",
    "sg:classifiers": [
      {
        "category": "Wholesale",
        "subcategory": "Machinery \u0026 Supplies",
        "type": "Manufacturing \u0026 Wholesale Goods"
      }
    ],
    "sg:phone": "+1 937 322 9185",
    "sg:postcode": "45504",
    "sg:province": "OH",
    "sg:tags": [
      "shop",
      "equipment",
      "salon",
      "barber",
      "beauty"
    ],
    "wof:name": "Sally Beauty Supply 539",
    "wof:placetype": "venue"
  },
  "geometry": {"coordinates":[-83.835334,39.938157],"type":"Point"}
}
