{
  "type": "Feature",
  "properties": {
    "addr:full":"35 S Kennebec Ave Mc Connelsville OH 43756",
    "addr:housenumber":"35",
    "addr:postcode":"43756",
    "addr:street":"S Kennebec Ave Mc",
    "iso:country":"US",
    "sg:address":"35 S Kennebec Ave",
    "sg:city":"Mc Connelsville",
    "sg:classifiers":[
        {
            "category":"Restaurant",
            "type":"Food & Drink"
        },
        {
            "category":"Bars & Pubs",
            "type":"Food & Drink"
        }
    ],
    "sg:phone":"+1 740 962 6310",
    "sg:postcode":"43756",
    "sg:province":"OH",
    "sg:tags":[
        "tavern"
    ],
    "wof:name":"Chatterbox Tavern Inc",
    "wof:placetype":"venue"
},
  "geometry": {"coordinates":[-81.85321,39.648445],"type":"Point"}
}