{
  "type": "Feature",
  "properties": {
    "addr:full": "2422 Lake Ave Ashtabula OH 44004",
    "addr:housenumber": "2422",
    "addr:postcode": "44004",
    "addr:street": "Lake Ave",
    "iso:country": "US",
    "sg:address": "2422 Lake Ave",
    "sg:city": "Ashtabula",
    "sg:classifiers": [
      {
        "category": "Health Services",
        "subcategory": "Doctor",
        "type": "Services"
      }
    ],
    "sg:phone": "+1 440 997 6960",
    "sg:postcode": "44004",
    "sg:province": "OH",
    "sg:tags": [
      "medical"
    ],
    "wof:name": "Ashtabula County Medical Ctr",
    "wof:placetype": "venue"
  },
  "geometry": {"coordinates":[-80.79658,41.880845],"type":"Point"}
}
