{
  "type": "Feature",
  "properties": {
    "addr:full":"1907 Powers St Cincinnati OH 45223",
    "addr:housenumber":"1907",
    "addr:postcode":"45223",
    "addr:street":"Powers St",
    "iso:country":"US",
    "sg:address":"1907 Powers St",
    "sg:city":"Cincinnati",
    "sg:classifiers":[
        {
            "category":"Manufacturing",
            "subcategory":"Metals",
            "type":"Manufacturing & Wholesale Goods"
        }
    ],
    "sg:phone":"+1 513 681 2020",
    "sg:postcode":"45223",
    "sg:province":"OH",
    "sg:tags":[
        "stampings",
        "mfg"
    ],
    "wof:name":"Metal Images Incorporated",
    "wof:placetype":"venue"
},
  "geometry": {"coordinates":[-84.55223700000001,39.157419],"type":"Point"}
}