{
  "type": "Feature",
  "properties": {
    "addr:full": "15321 Munn Rd Newbury OH 44065",
    "addr:housenumber": "15321",
    "addr:postcode": "44065",
    "addr:street": "Munn Rd",
    "iso:country": "US",
    "sg:address": "15321 Munn Rd",
    "sg:city": "Newbury",
    "sg:classifiers": [
      {
        "category": "Wholesale",
        "subcategory": "Farm Supplies",
        "type": "Manufacturing \u0026 Wholesale Goods"
      }
    ],
    "sg:phone": "+1 440 564 5496",
    "sg:postcode": "44065",
    "sg:province": "OH",
    "sg:tags": [
      "livestock"
    ],
    "wof:name": "Rolling Medows Farms",
    "wof:placetype": "venue"
  },
  "geometry": {"coordinates":[-81.273459,41.463241],"type":"Point"}
}
