{
  "type": "Feature",
  "properties": {
    "addr:full":"3233 Parsons Ave Columbus OH 43207",
    "addr:housenumber":"3233",
    "addr:postcode":"43207",
    "addr:street":"Parsons Ave",
    "iso:country":"US",
    "sg:address":"3233 Parsons Ave",
    "sg:city":"Columbus",
    "sg:classifiers":[
        {
            "category":"Home & Garden",
            "subcategory":"Household Appliances",
            "type":"Retail Goods"
        },
        {
            "category":"Building & Trades",
            "subcategory":"Construction",
            "type":"Services"
        }
    ],
    "sg:phone":"+1 614 497 3619",
    "sg:postcode":"43207",
    "sg:province":"OH",
    "sg:tags":[
        "system",
        "specialty",
        "pump",
        "heating",
        "heat",
        "contractor",
        "air conditioning"
    ],
    "wof:name":"Rite Temperature Heating & Air Conditioning",
    "wof:placetype":"venue"
},
  "geometry": {"coordinates":[-82.986588,39.895969],"type":"Point"}
}