{
  "type": "Feature",
  "properties": {
    "addr:full": "760 Warehouse Rd Toledo OH 43615",
    "addr:housenumber": "760",
    "addr:postcode": "43615",
    "addr:street": "Warehouse Rd",
    "iso:country": "US",
    "sg:address": "760 Warehouse Rd",
    "sg:city": "Toledo",
    "sg:classifiers": [
      {
        "category": "Professional",
        "subcategory": "Business Services",
        "type": "Services"
      },
      {
        "category": "Manufacturing",
        "subcategory": "Apparel",
        "type": "Manufacturing \u0026 Wholesale Goods"
      }
    ],
    "sg:phone": "+1 419 865 6450",
    "sg:postcode": "43615",
    "sg:province": "OH",
    "sg:tags": [
      "embroidery"
    ],
    "wof:name": "Holmes Embroidery",
    "wof:placetype": "venue"
  },
  "geometry": {"coordinates":[-83.653751,41.625114],"type":"Point"}
}
