{
  "type": "Feature",
  "properties": {
    "addr:full":"2305 Garey Rd NE Junction City OH 43748",
    "addr:housenumber":"2305",
    "addr:postcode":"43748",
    "addr:street":"Garey Rd Ne",
    "iso:country":"US",
    "sg:address":"2305 Garey Rd NE",
    "sg:city":"Junction City",
    "sg:phone":"+1 740 987 3105",
    "sg:postcode":"43748",
    "sg:province":"OH",
    "sg:tags":[
        "farm",
        "corn"
    ],
    "wof:name":"Gilligan Farm",
    "wof:placetype":"venue"
},
  "geometry": {"coordinates":[-82.28203499999999,39.734389],"type":"Point"}
}