{
  "type": "Feature",
  "properties": {
    "addr:full":"3889 Powell Rd Powell OH 43065",
    "addr:housenumber":"3889",
    "addr:postcode":"43065",
    "addr:street":"Powell Rd",
    "iso:country":"US",
    "sg:address":"3889 Powell Rd",
    "sg:city":"Powell",
    "sg:classifiers":[
        {
            "category":"Restaurant",
            "type":"Food & Drink"
        }
    ],
    "sg:menulink":"http://www.allmenus.com/oh/liberty/79117-pizza-hut/menu/",
    "sg:phone":"+1 614 895 1111",
    "sg:postcode":"43065",
    "sg:province":"OH",
    "sg:tags":[
        "american",
        "pizza"
    ],
    "wof:name":"Pizza Hut",
    "wof:placetype":"venue"
},
  "geometry": {"coordinates":[-83.09266700000001,40.157883],"type":"Point"}
}