{
  "type": "Feature",
  "properties": {
    "iso:country":"US",
    "sg:address":"1740 Langdon Farm Rd",
    "sg:city":"Cincinnati",
    "sg:classifiers":[
        {
            "category":"Education",
            "subcategory":"Library",
            "type":"Public Place"
        }
    ],
    "sg:phone":"+1 513 369 4445",
    "sg:postcode":"45237",
    "sg:province":"OH",
    "sg:website":"http://www.mhrecovery.com",
    "wof:name":"Public Library",
    "wof:placetype":"venue"
},
  "geometry": {"coordinates":[-84.464426,39.184352],"type":"Point"}
}