{
  "type": "Feature",
  "properties": {
    "addr:full": "7900 W Chester Rd West Chester OH 45069",
    "addr:housenumber": "7900",
    "addr:postcode": "45069",
    "addr:street": "W Chester Rd",
    "iso:country": "US",
    "sg:address": "7900 W Chester Rd",
    "sg:city": "West Chester",
    "sg:classifiers": [
      {
        "category": "Home \u0026 Garden",
        "subcategory": "Hardware",
        "type": "Retail Goods"
      }
    ],
    "sg:phone": "+1 513 759 0436",
    "sg:postcode": "45069",
    "sg:province": "OH",
    "sg:website": "www.sears.com",
    "wof:name": "Sears Hardware Store",
    "wof:placetype": "venue"
  },
  "geometry": {"coordinates":[-84.364829,39.317933],"type":"Point"}
}
