{
  "type": "Feature",
  "properties": {
    "iso:country":"US",
    "sg:address":"855 W 5th Ave",
    "sg:city":"Columbus",
    "sg:classifiers":[
        {
            "category":"Professional",
            "subcategory":"Computer Services",
            "type":"Services"
        }
    ],
    "sg:phone":"+1 614 294 6078",
    "sg:postcode":"43212",
    "sg:province":"OH",
    "sg:tags":[
        "processing",
        "datum"
    ],
    "sg:website":"www.dyserv.com",
    "wof:name":"Dyserv Inc",
    "wof:placetype":"venue"
},
  "geometry": {"coordinates":[-83.028598,39.987911],"type":"Point"}
}