{
  "type": "Feature",
  "properties": {
    "iso:country":"US",
    "sg:address":"104 S Market St",
    "sg:city":"Minerva",
    "sg:classifiers":[
        {
            "category":"Bars & Pubs",
            "type":"Food & Drink"
        }
    ],
    "sg:phone":"+1 330 868 7966",
    "sg:postcode":"44657",
    "sg:province":"OH",
    "sg:tags":[
        "drinking"
    ],
    "wof:name":"Bings Lounge",
    "wof:placetype":"venue"
},
  "geometry": {"coordinates":[-81.10351,40.727881],"type":"Point"}
}