{
  "type": "Feature",
  "properties": {
    "iso:country":"US",
    "sg:address":"1818 Pearl Rd",
    "sg:city":"Brunswick",
    "sg:classifiers":[
        {
            "category":"Insurance",
            "subcategory":"Insurance Agent",
            "type":"Services"
        }
    ],
    "sg:phone":"+1 330 225 1145",
    "sg:postcode":"44212",
    "sg:province":"OH",
    "wof:name":"Joyce Insurance",
    "wof:placetype":"venue"
},
  "geometry": {"coordinates":[-81.841517,41.226208],"type":"Point"}
}