{
  "type": "Feature",
  "properties": {
    "addr:full": "2052 W 95th St Cleveland OH 44102",
    "addr:housenumber": "2052",
    "addr:postcode": "44102",
    "addr:street": "W 95Th St",
    "iso:country": "US",
    "sg:address": "2052 W 95th St",
    "sg:city": "Cleveland",
    "sg:classifiers": [
      {
        "category": "Wholesale",
        "subcategory": "Auto Parts",
        "type": "Manufacturing \u0026 Wholesale Goods"
      }
    ],
    "sg:phone": "+1 216 651 3896",
    "sg:postcode": "44102",
    "sg:province": "OH",
    "sg:tags": [
      "trade"
    ],
    "wof:name": "Mason Diesel Service Inc",
    "wof:placetype": "venue"
  },
  "geometry": {"coordinates":[-81.748614,41.475867],"type":"Point"}
}
