{
  "type": "Feature",
  "properties": {
    "addr:full":"721 US Hwy 52 Stout OH 45684",
    "addr:housenumber":"721",
    "addr:postcode":"45684",
    "addr:street":"Us Hwy 52",
    "iso:country":"US",
    "sg:address":"721 US Hwy 52",
    "sg:city":"Stout",
    "sg:classifiers":[
        {
            "category":"Food & Beverages",
            "subcategory":"Groceries & Convenience Stores",
            "type":"Retail Goods"
        }
    ],
    "sg:phone":"+1 740 858 4939",
    "sg:postcode":"45684",
    "sg:province":"OH",
    "wof:name":"Shawnee Grocery LTD",
    "wof:placetype":"venue"
},
  "geometry": {"coordinates":[-83.260214,38.627641],"type":"Point"}
}