{
  "type": "Feature",
  "properties": {
    "addr:full": "19050 Ridgeview Trl Chagrin Falls OH 44023",
    "addr:housenumber": "19050",
    "addr:postcode": "44023",
    "addr:street": "Ridgeview Trl",
    "iso:country": "US",
    "sg:address": "19050 Ridgeview Trl",
    "sg:city": "Chagrin Falls",
    "sg:classifiers": [
      {
        "category": "Shopping",
        "subcategory": "Computers \u0026 Home Electronics",
        "type": "Retail Goods"
      }
    ],
    "sg:phone": "+1 440 708 0580",
    "sg:postcode": "44023",
    "sg:province": "OH",
    "wof:name": "Total Micro Technology Inc",
    "wof:placetype": "venue"
  },
  "geometry": {"coordinates":[-81.344203,41.350212],"type":"Point"}
}
