{
  "type": "Feature",
  "properties": {
    "iso:country":"US",
    "sg:address":"19050 Ridgeview Trl",
    "sg:city":"Chagrin Falls",
    "sg:classifiers":[
        {
            "category":"Shopping",
            "subcategory":"Computers & Home Electronics",
            "type":"Retail Goods"
        }
    ],
    "sg:phone":"+1 440 708 0580",
    "sg:postcode":"44023",
    "sg:province":"OH",
    "wof:name":"Total Micro Technology Inc",
    "wof:placetype":"venue"
},
  "geometry": {"coordinates":[-81.34420299999999,41.350212],"type":"Point"}
}