{
  "type": "Feature",
  "properties": {
    "iso:country":"US",
    "sg:address":"2852 Westerville Rd",
    "sg:city":"Columbus",
    "sg:classifiers":[
        {
            "category":"Retail",
            "subcategory":"Repair Shop",
            "type":"Services"
        }
    ],
    "sg:phone":"+1 614 476 9180",
    "sg:postcode":"43224",
    "sg:province":"OH",
    "sg:tags":[
        "related"
    ],
    "wof:name":"Fix N Go",
    "wof:placetype":"venue"
},
  "geometry": {"coordinates":[-82.960823,40.025964],"type":"Point"}
}