{
  "type": "Feature",
  "properties": {
    "addr:full": "20650 Lakeland Blvd Cleveland OH 44119",
    "addr:housenumber": "20650",
    "addr:postcode": "44119",
    "addr:street": "Lakeland Blvd",
    "iso:country": "US",
    "sg:address": "20650 Lakeland Blvd",
    "sg:city": "Cleveland",
    "sg:classifiers": [
      {
        "category": "Manufacturing",
        "subcategory": "Tools \u0026 Machinery",
        "type": "Manufacturing \u0026 Wholesale Goods"
      }
    ],
    "sg:phone": "+1 216 531 2773",
    "sg:postcode": "44119",
    "sg:province": "OH",
    "sg:tags": [
      "equipment",
      "orthopedic",
      "mfg"
    ],
    "wof:name": "Orthotic and Prostetic Spc",
    "wof:placetype": "venue"
  },
  "geometry": {"coordinates":[-81.534225,41.58328],"type":"Point"}
}
