{
  "type": "Feature",
  "properties": {
    "iso:country":"US",
    "sg:address":"319 Main St",
    "sg:city":"Bridgeport",
    "sg:classifiers":[
        {
            "category":"Personal",
            "subcategory":"Barber",
            "type":"Services"
        }
    ],
    "sg:phone":"+1 740 633 6223",
    "sg:postcode":"43912",
    "sg:province":"OH",
    "wof:name":"Bill's Barber Shop",
    "wof:placetype":"venue"
},
  "geometry": {"coordinates":[-80.744074,40.072393],"type":"Point"}
}