{
  "type": "Feature",
  "properties": {
    "addr:full":"545 Pine Ave SE Warren OH 44483",
    "addr:housenumber":"545",
    "addr:postcode":"44483",
    "addr:street":"Pine Ave Se",
    "iso:country":"US",
    "sg:address":"545 Pine Ave SE",
    "sg:city":"Warren",
    "sg:classifiers":[
        {
            "category":"Retail",
            "subcategory":"Laundry & Dry Cleaning",
            "type":"Services"
        }
    ],
    "sg:phone":"+1 330 393 3156",
    "sg:postcode":"44483",
    "sg:province":"OH",
    "sg:tags":[
        "cleaners"
    ],
    "wof:name":"Original Quality Cleaners",
    "wof:placetype":"venue"
},
  "geometry": {"coordinates":[-80.815944,41.232685],"type":"Point"}
}