{
  "type": "Feature",
  "properties": {
    "addr:full": "1986 Spurgeon Hill Rd West Union OH 45693",
    "addr:housenumber": "1986",
    "addr:postcode": "45693",
    "addr:street": "Spurgeon Hill Rd",
    "iso:country": "US",
    "sg:address": "1986 Spurgeon Hill Rd",
    "sg:city": "West Union",
    "sg:classifiers": [
      {
        "category": "Farming",
        "subcategory": "Farm",
        "type": "Manufacturing \u0026 Wholesale Goods"
      }
    ],
    "sg:phone": "+1 937 544 3922",
    "sg:postcode": "45693",
    "sg:province": "OH",
    "sg:tags": [
      "crop",
      "general"
    ],
    "wof:name": "Opal Vanhoose",
    "wof:placetype": "venue"
  },
  "geometry": {"coordinates":[-83.443348,38.828953],"type":"Point"}
}
