{
  "type": "Feature",
  "properties": {
    "addr:full": "9600 S Mason Montgomery Rd Mason OH 45040",
    "addr:housenumber": "9600",
    "addr:postcode": "45040",
    "addr:street": "S Mason Montgomery Rd",
    "iso:country": "US",
    "sg:address": "9600 S Mason Montgomery Rd",
    "sg:city": "Mason",
    "sg:classifiers": [
      {
        "category": "Banks \u0026 Credit Unions",
        "subcategory": "Bank",
        "type": "Services"
      }
    ],
    "sg:phone": "+1 513 336 7880",
    "sg:postcode": "45040",
    "sg:province": "OH",
    "wof:name": "Clermont Savings Bank",
    "wof:placetype": "venue"
  },
  "geometry": {"coordinates":[-84.315085,39.29803],"type":"Point"}
}
