{
  "type": "Feature",
  "properties": {
    "addr:full": "7630 Red Bay Ct Dublin OH 43016",
    "addr:housenumber": "7630",
    "addr:postcode": "43016",
    "addr:street": "Red Bay Ct",
    "iso:country": "US",
    "sg:address": "7630 Red Bay Ct",
    "sg:city": "Dublin",
    "sg:classifiers": [
      {
        "category": "Real Estate",
        "subcategory": "Real Estate Agent",
        "type": "Services"
      }
    ],
    "sg:phone": "+1 614 718 9644",
    "sg:postcode": "43016",
    "sg:province": "OH",
    "sg:tags": [
      "report",
      "information"
    ],
    "wof:name": "Office Space Online",
    "wof:placetype": "venue"
  },
  "geometry": {"coordinates":[-83.107933,40.123649],"type":"Point"}
}
