{
  "type": "Feature",
  "properties": {
    "addr:full": "7802 Munson Rd Mentor OH 44060",
    "addr:housenumber": "7802",
    "addr:postcode": "44060",
    "addr:street": "Munson Rd",
    "iso:country": "US",
    "sg:address": "7802 Munson Rd",
    "sg:city": "Mentor",
    "sg:classifiers": [
      {
        "category": "Shopping",
        "subcategory": "Bicycles \u0026 Sporting Goods",
        "type": "Retail Goods"
      }
    ],
    "sg:phone": "+1 440 257 2170",
    "sg:postcode": "44060",
    "sg:province": "OH",
    "sg:tags": [
      "parts"
    ],
    "wof:name": "Cycle Sport \u0026 Fitness",
    "wof:placetype": "venue"
  },
  "geometry": {"coordinates":[-81.360805,41.704983],"type":"Point"}
}
