{
  "type": "Feature",
  "properties": {
    "iso:country":"US",
    "sg:address":"7802 Munson Rd",
    "sg:city":"Mentor",
    "sg:classifiers":[
        {
            "category":"Shopping",
            "subcategory":"Bicycles & Sporting Goods",
            "type":"Retail Goods"
        }
    ],
    "sg:phone":"+1 440 257 2170",
    "sg:postcode":"44060",
    "sg:province":"OH",
    "sg:tags":[
        "parts"
    ],
    "wof:name":"Cycle Sport & Fitness",
    "wof:placetype":"venue"
},
  "geometry": {"coordinates":[-81.360805,41.704983],"type":"Point"}
}