{
  "type": "Feature",
  "properties": {
    "addr:full": "5399 E Provident Dr Cincinnati OH 45246",
    "addr:housenumber": "5399",
    "addr:postcode": "45246",
    "addr:street": "E Provident Dr",
    "iso:country": "US",
    "sg:address": "5399 E Provident Dr",
    "sg:city": "Cincinnati",
    "sg:phone": "+1 513 860 9553",
    "sg:postcode": "45246",
    "sg:province": "OH",
    "sg:tags": [
      "product",
      "petroleum"
    ],
    "wof:name": "Valvoline International Inc",
    "wof:placetype": "venue"
  },
  "geometry": {"coordinates":[-84.445268,39.313695],"type":"Point"}
}
