{
  "type": "Feature",
  "properties": {
    "addr:full":"3185 Lilly Mar Ct Dublin OH 43017",
    "addr:housenumber":"3185",
    "addr:postcode":"43017",
    "addr:street":"Lilly Mar Ct",
    "iso:country":"US",
    "sg:address":"3185 Lilly Mar Ct",
    "sg:city":"Dublin",
    "sg:classifiers":[
        {
            "category":"Professional",
            "subcategory":"Computer Services",
            "type":"Services"
        }
    ],
    "sg:phone":"+1 614 791 8111",
    "sg:postcode":"43017",
    "sg:province":"OH",
    "sg:tags":[
        "consultant",
        "designer"
    ],
    "wof:name":"AEC Resources",
    "wof:placetype":"venue"
},
  "geometry": {"coordinates":[-83.101023,40.096038],"type":"Point"}
}