{
  "type": "Feature",
  "properties": {
    "iso:country":"US",
    "sg:address":"238 High St",
    "sg:city":"Wadsworth",
    "sg:classifiers":[
        {
            "category":"Manufacturing",
            "subcategory":"Printing",
            "type":"Manufacturing & Wholesale Goods"
        }
    ],
    "sg:phone":"+1 330 335 8326",
    "sg:postcode":"44281",
    "sg:province":"OH",
    "sg:tags":[
        "screen"
    ],
    "wof:name":"Custom Sportswear Imprints",
    "wof:placetype":"venue"
},
  "geometry": {"coordinates":[-81.72975700000001,41.029172],"type":"Point"}
}