{
  "type": "Feature",
  "properties": {
    "addr:full":"223 E Main St Troy OH 45373",
    "addr:housenumber":"223",
    "addr:postcode":"45373",
    "addr:street":"E Main St",
    "iso:country":"US",
    "sg:address":"223 E Main St",
    "sg:city":"Troy",
    "sg:classifiers":[
        {
            "category":"Organizations",
            "subcategory":"Professional Association",
            "type":"Services"
        }
    ],
    "sg:phone":"+1 937 339 4810",
    "sg:postcode":"45373",
    "sg:province":"OH",
    "wof:name":"Salvation Army Community",
    "wof:placetype":"venue"
},
  "geometry": {"coordinates":[-84.200484,40.038439],"type":"Point"}
}