{
  "type": "Feature",
  "properties": {
    "addr:full": "5240 Lester Rd Cincinnati OH 45213",
    "addr:housenumber": "5240",
    "addr:postcode": "45213",
    "addr:street": "Lester Rd",
    "iso:country": "US",
    "sg:address": "5240 Lester Rd",
    "sg:city": "Cincinnati",
    "sg:classifiers": [
      {
        "category": "Retail",
        "subcategory": "Repair Shop",
        "type": "Services"
      }
    ],
    "sg:phone": "+1 513 321 8101",
    "sg:postcode": "45213",
    "sg:province": "OH",
    "sg:tags": [
      "equipment",
      "conditioning",
      "air"
    ],
    "sg:website": "www.tjdyer.com",
    "wof:name": "Thomas Dyer Mechanical Svc",
    "wof:placetype": "venue"
  },
  "geometry": {"coordinates":[-84.432429,39.169898],"type":"Point"}
}
