{
  "type": "Feature",
  "properties": {
    "iso:country":"US",
    "sg:address":"863 S 30th St",
    "sg:city":"Heath",
    "sg:classifiers":[
        {
            "category":"Shopping",
            "subcategory":"Musical Instruments",
            "type":"Retail Goods"
        }
    ],
    "sg:phone":"+1 740 344 5252",
    "sg:postcode":"43056",
    "sg:province":"OH",
    "sg:tags":[
        "repair"
    ],
    "wof:name":"Sheets & Sons Music",
    "wof:placetype":"venue"
},
  "geometry": {"coordinates":[-82.443288,40.029291],"type":"Point"}
}