{
  "type": "Feature",
  "properties": {
    "iso:country":"US",
    "sg:address":"506 Aukerman St",
    "sg:city":"Eaton",
    "sg:classifiers":[
        {
            "category":"Education",
            "subcategory":"School",
            "type":"Public Place"
        }
    ],
    "sg:phone":"+1 937 456 5173",
    "sg:postcode":"45320",
    "sg:province":"OH",
    "sg:website":"www.easteagles.com",
    "wof:name":"East Elementary School",
    "wof:placetype":"venue"
},
  "geometry": {"coordinates":[-84.629464,39.74892],"type":"Point"}
}