{
  "type": "Feature",
  "properties": {
    "addr:full": "37151 Ben Hur Ave Willoughby OH 44094",
    "addr:housenumber": "37151",
    "addr:postcode": "44094",
    "addr:street": "Ben Hur Ave",
    "iso:country": "US",
    "sg:address": "37151 Ben Hur Ave",
    "sg:city": "Willoughby",
    "sg:classifiers": [
      {
        "category": "Communications",
        "subcategory": "Film \u0026 Video Production",
        "type": "Services"
      }
    ],
    "sg:phone": "+1 440 946 0396",
    "sg:postcode": "44094",
    "sg:province": "OH",
    "sg:tags": [
      "sound",
      "consultant",
      "system"
    ],
    "wof:name": "Gratec Inc",
    "wof:placetype": "venue"
  },
  "geometry": {"coordinates":[-81.417802,41.64422],"type":"Point"}
}
