{
  "type": "Feature",
  "properties": {
    "iso:country":"US",
    "sg:address":"1798 Columbus-Sandusky Rd S",
    "sg:city":"Marion",
    "sg:classifiers":[
        {
            "category":"Farming",
            "subcategory":"Farm",
            "type":"Manufacturing & Wholesale Goods"
        }
    ],
    "sg:phone":"+1 740 389 5332",
    "sg:postcode":"43302",
    "sg:province":"OH",
    "sg:tags":[
        "crop",
        "general"
    ],
    "wof:name":"Fetter Farms",
    "wof:placetype":"venue"
},
  "geometry": {"coordinates":[-83.048456,40.554744],"type":"Point"}
}