{
  "type": "Feature",
  "properties": {
    "addr:full": "1798 Columbus-Sandusky Rd S Marion OH 43302",
    "addr:housenumber": "1798",
    "addr:postcode": "43302",
    "addr:street": "Columbus-Sandusky Rd S",
    "iso:country": "US",
    "sg:address": "1798 Columbus-Sandusky Rd S",
    "sg:city": "Marion",
    "sg:classifiers": [
      {
        "category": "Farming",
        "subcategory": "Farm",
        "type": "Manufacturing \u0026 Wholesale Goods"
      }
    ],
    "sg:phone": "+1 740 389 5332",
    "sg:postcode": "43302",
    "sg:province": "OH",
    "sg:tags": [
      "crop",
      "general"
    ],
    "wof:name": "Fetter Farms",
    "wof:placetype": "venue"
  },
  "geometry": {"coordinates":[-83.048456,40.554744],"type":"Point"}
}
