{
  "type": "Feature",
  "properties": {
    "addr:full":"3537 Elm Tree Rd N St Paris OH 43072",
    "addr:housenumber":"3537",
    "addr:postcode":"43072",
    "addr:street":"Elm Tree Rd N St",
    "iso:country":"US",
    "sg:address":"3537 Elm Tree Rd N",
    "sg:city":"St Paris",
    "sg:classifiers":[
        {
            "category":"Organizations",
            "subcategory":"Religious Organization",
            "type":"Services"
        }
    ],
    "sg:phone":"+1 937 857 9090",
    "sg:postcode":"43072",
    "sg:province":"OH",
    "sg:tags":[
        "church"
    ],
    "wof:name":"Christian Worship Ctr",
    "wof:placetype":"venue"
},
  "geometry": {"coordinates":[-84.01318499999999,40.175851],"type":"Point"}
}