{
  "type": "Feature",
  "properties": {
    "iso:country":"US",
    "sg:address":"749 3rd Ave",
    "sg:city":"Gallipolis",
    "sg:classifiers":[
        {
            "category":"Retail",
            "subcategory":"Repair Shop",
            "type":"Services"
        }
    ],
    "sg:phone":"+1 740 446 2413",
    "sg:postcode":"45631",
    "sg:province":"OH",
    "sg:tags":[
        "television",
        "radio"
    ],
    "wof:name":"Davis Electronics",
    "wof:placetype":"venue"
},
  "geometry": {"coordinates":[-82.198768,38.813431],"type":"Point"}
}