{
  "type": "Feature",
  "properties": {
    "addr:full": "2092 S Alex Rd Dayton OH 45449",
    "addr:housenumber": "2092",
    "addr:postcode": "45449",
    "addr:street": "S Alex Rd",
    "iso:country": "US",
    "sg:address": "2092 S Alex Rd",
    "sg:city": "Dayton",
    "sg:classifiers": [
      {
        "category": "Retail",
        "subcategory": "Laundry \u0026 Dry Cleaning",
        "type": "Services"
      }
    ],
    "sg:phone": "+1 937 859 6127",
    "sg:postcode": "45449",
    "sg:province": "OH",
    "sg:tags": [
      "drycleaning",
      "plant"
    ],
    "wof:name": "Capitol Cleaners 52179",
    "wof:placetype": "venue"
  },
  "geometry": {"coordinates":[-84.243129,39.645725],"type":"Point"}
}
