{
  "type": "Feature",
  "properties": {
    "addr:full": "2200 S Green Rd Cleveland OH 44121",
    "addr:housenumber": "2200",
    "addr:postcode": "44121",
    "addr:street": "S Green Rd",
    "iso:country": "US",
    "sg:address": "2200 S Green Rd",
    "sg:city": "Cleveland",
    "sg:classifiers": [
      {
        "category": "Social Services",
        "subcategory": "Child Care",
        "type": "Services"
      }
    ],
    "sg:phone": "+1 216 381 3273",
    "sg:postcode": "44121",
    "sg:province": "OH",
    "sg:website": "www.teecleve.org",
    "wof:name": "Preschool Child Care",
    "wof:placetype": "venue"
  },
  "geometry": {"coordinates":[-81.518315,41.50008],"type":"Point"}
}
