{
  "type": "Feature",
  "properties": {
    "addr:full":"707 Radio Dr Lewis Center OH 43035",
    "addr:housenumber":"707",
    "addr:postcode":"43035",
    "addr:street":"Radio Dr",
    "iso:country":"US",
    "sg:address":"707 Radio Dr",
    "sg:city":"Lewis Center",
    "sg:classifiers":[
        {
            "category":"Professional",
            "type":"Services"
        },
        {
            "category":"Manufacturing",
            "subcategory":"Retail Goods",
            "type":"Manufacturing & Wholesale Goods"
        }
    ],
    "sg:phone":"+1 740 549 0300",
    "sg:postcode":"43035",
    "sg:province":"OH",
    "sg:tags":[
        "manufacturer"
    ],
    "wof:name":"Amerihua International Ent Inc",
    "wof:placetype":"venue"
},
  "geometry": {"coordinates":[-83.008945,40.158609],"type":"Point"}
}