{
  "type": "Feature",
  "properties": {
    "iso:country":"US",
    "sg:address":"812 Clarendon Ave NW",
    "sg:city":"Canton",
    "sg:classifiers":[
        {
            "category":"Building & Trades",
            "subcategory":"Plumbing",
            "type":"Services"
        }
    ],
    "sg:phone":"+1 330 456 3291",
    "sg:postcode":"44708",
    "sg:province":"OH",
    "sg:tags":[
        "contractor"
    ],
    "wof:name":"American Pro Plumbing",
    "wof:placetype":"venue"
},
  "geometry": {"coordinates":[-81.40334,40.805794],"type":"Point"}
}