{
  "type": "Feature",
  "properties": {
    "iso:country":"US",
    "sg:address":"925 Euclid Ave",
    "sg:city":"Cleveland",
    "sg:classifiers":[
        {
            "category":"Building & Trades",
            "subcategory":"Construction",
            "type":"Services"
        }
    ],
    "sg:phone":"+1 216 781 6604",
    "sg:postcode":"44115",
    "sg:province":"OH",
    "sg:tags":[
        "system",
        "specialty",
        "heating",
        "contractor",
        "air conditioning"
    ],
    "wof:name":"Schneider Air Conditioning Contractors",
    "wof:placetype":"venue"
},
  "geometry": {"coordinates":[-81.686696,41.500256],"type":"Point"}
}