{
  "type": "Feature",
  "properties": {
    "addr:full": "925 Euclid Ave Cleveland OH 44115",
    "addr:housenumber": "925",
    "addr:postcode": "44115",
    "addr:street": "Euclid Ave",
    "iso:country": "US",
    "sg:address": "925 Euclid Ave",
    "sg:city": "Cleveland",
    "sg:classifiers": [
      {
        "category": "Building \u0026 Trades",
        "subcategory": "Construction",
        "type": "Services"
      }
    ],
    "sg:phone": "+1 216 781 6604",
    "sg:postcode": "44115",
    "sg:province": "OH",
    "sg:tags": [
      "system",
      "specialty",
      "heating",
      "contractor",
      "air conditioning"
    ],
    "wof:name": "Schneider Air Conditioning Contractors",
    "wof:placetype": "venue"
  },
  "geometry": {"coordinates":[-81.686696,41.500256],"type":"Point"}
}
