{
  "type": "Feature",
  "properties": {
    "iso:country":"US",
    "sg:address":"5901 Colerain Ave",
    "sg:city":"Cincinnati",
    "sg:classifiers":[
        {
            "category":"Banks & Credit Unions",
            "subcategory":"Bank",
            "type":"Services"
        }
    ],
    "sg:phone":"+1 513 923 4100",
    "sg:postcode":"45239",
    "sg:province":"OH",
    "sg:tags":[
        "federal",
        "loan",
        "broker",
        "savings",
        "real estate",
        "institution"
    ],
    "sg:website":"www.guardiansavingsbank.com",
    "wof:name":"Guardian Savings Bank Fsb",
    "wof:placetype":"venue"
},
  "geometry": {"coordinates":[-84.581705,39.203522],"type":"Point"}
}