{
  "type": "Feature",
  "properties": {
    "addr:full":"1501 N Marginal Rd Cleveland OH 44114",
    "addr:housenumber":"1501",
    "addr:postcode":"44114",
    "addr:street":"N Marginal Rd",
    "iso:country":"US",
    "sg:address":"1501 N Marginal Rd",
    "sg:city":"Cleveland",
    "sg:phone":"+1 216 664 0790",
    "sg:postcode":"44114",
    "sg:province":"OH",
    "wof:name":"Cleveland Burke Airport",
    "wof:placetype":"venue"
},
  "geometry": {"coordinates":[-81.688953,41.51037],"type":"Point"}
}