{
  "type": "Feature",
  "properties": {
    "addr:full": "44 Eswin St Cincinnati OH 45218",
    "addr:housenumber": "44",
    "addr:postcode": "45218",
    "addr:street": "Eswin St",
    "iso:country": "US",
    "sg:address": "44 Eswin St",
    "sg:city": "Cincinnati",
    "sg:classifiers": [
      {
        "category": "Professional",
        "subcategory": "Engineering",
        "type": "Services"
      }
    ],
    "sg:phone": "+1 513 825 2289",
    "sg:postcode": "45218",
    "sg:province": "OH",
    "sg:tags": [
      "engineer"
    ],
    "wof:name": "Dat-Design Aero Technology",
    "wof:placetype": "venue"
  },
  "geometry": {"coordinates":[-84.522824,39.269432],"type":"Point"}
}
