{
  "type": "Feature",
  "properties": {
    "iso:country":"US",
    "sg:address":"16 W High St",
    "sg:city":"Mt Gilead",
    "sg:classifiers":[
        {
            "category":"Retail",
            "subcategory":"Laundry & Dry Cleaning",
            "type":"Services"
        }
    ],
    "sg:phone":"+1 419 946 1966",
    "sg:postcode":"43338",
    "sg:province":"OH",
    "sg:tags":[
        "cleaners"
    ],
    "wof:name":"Kimmel Corp",
    "wof:placetype":"venue"
},
  "geometry": {"coordinates":[-82.829131,40.54937],"type":"Point"}
}