{
  "type": "Feature",
  "properties": {
    "iso:country":"US",
    "sg:address":"121 W Liberty St",
    "sg:city":"Wooster",
    "sg:classifiers":[
        {
            "category":"Professional",
            "subcategory":"Lawyer & Legal Services",
            "type":"Services"
        }
    ],
    "sg:phone":"+1 330 264 6000",
    "sg:postcode":"44691",
    "sg:province":"OH",
    "sg:tags":[
        "attorney"
    ],
    "wof:name":"Macala Baasten Mc Kinley Piatt",
    "wof:placetype":"venue"
},
  "geometry": {"coordinates":[-81.940179,40.798252],"type":"Point"}
}