{
  "type": "Feature",
  "properties": {
    "addr:full":"446 E Weber St Toledo OH 43608",
    "addr:housenumber":"446",
    "addr:postcode":"43608",
    "addr:street":"E Weber St",
    "iso:country":"US",
    "sg:address":"446 E Weber St",
    "sg:city":"Toledo",
    "sg:classifiers":[
        {
            "category":"Personal",
            "subcategory":"Beauty Salon",
            "type":"Services"
        }
    ],
    "sg:phone":"+1 419 727 1210",
    "sg:postcode":"43608",
    "sg:province":"OH",
    "wof:name":"Jayshawn's Braids & Weaves",
    "wof:placetype":"venue"
},
  "geometry": {"coordinates":[-83.534903,41.681407],"type":"Point"}
}