{
  "type": "Feature",
  "properties": {
    "addr:full":"251 Brentwood Dr Marion OH 43302",
    "addr:housenumber":"251",
    "addr:postcode":"43302",
    "addr:street":"Brentwood Dr",
    "iso:country":"US",
    "sg:address":"251 Brentwood Dr",
    "sg:city":"Marion",
    "sg:classifiers":[
        {
            "category":"Building & Trades",
            "subcategory":"Construction",
            "type":"Services"
        }
    ],
    "sg:phone":"+1 740 382 4658",
    "sg:postcode":"43302",
    "sg:province":"OH",
    "sg:tags":[
        "fence",
        "contractor"
    ],
    "wof:name":"Dan Lee's Fence Co",
    "wof:placetype":"venue"
},
  "geometry": {"coordinates":[-83.15601100000001,40.585658],"type":"Point"}
}