{
  "type": "Feature",
  "properties": {
    "iso:country":"US",
    "sg:address":"104 W Franklin St",
    "sg:city":"Bellbrook",
    "sg:classifiers":[
        {
            "category":"Wholesale",
            "subcategory":"Wine & Distilled Alcoholic Beverages",
            "type":"Manufacturing & Wholesale Goods"
        },
        {
            "category":"Food & Beverages",
            "subcategory":"Liquor & Beverages",
            "type":"Retail Goods"
        }
    ],
    "sg:phone":"+1 937 848 4514",
    "sg:postcode":"45305",
    "sg:province":"OH",
    "sg:tags":[
        "beer",
        "ale"
    ],
    "wof:name":"Bellbrook Drive-Thru LLC",
    "wof:placetype":"venue"
},
  "geometry": {"coordinates":[-84.07237600000001,39.636166],"type":"Point"}
}