{
  "type": "Feature",
  "properties": {
    "addr:full": "104 W Franklin St Bellbrook OH 45305",
    "addr:housenumber": "104",
    "addr:postcode": "45305",
    "addr:street": "W Franklin St",
    "iso:country": "US",
    "sg:address": "104 W Franklin St",
    "sg:city": "Bellbrook",
    "sg:classifiers": [
      {
        "category": "Wholesale",
        "subcategory": "Wine \u0026 Distilled Alcoholic Beverages",
        "type": "Manufacturing \u0026 Wholesale Goods"
      },
      {
        "category": "Food \u0026 Beverages",
        "subcategory": "Liquor \u0026 Beverages",
        "type": "Retail Goods"
      }
    ],
    "sg:phone": "+1 937 848 4514",
    "sg:postcode": "45305",
    "sg:province": "OH",
    "sg:tags": [
      "beer",
      "ale"
    ],
    "wof:name": "Bellbrook Drive-Thru LLC",
    "wof:placetype": "venue"
  },
  "geometry": {"coordinates":[-84.072376,39.636166],"type":"Point"}
}
