{
  "type": "Feature",
  "properties": {
    "addr:full": "3833 S Main St Mineral Ridge OH 44440",
    "addr:housenumber": "3833",
    "addr:postcode": "44440",
    "addr:street": "S Main St",
    "iso:country": "US",
    "sg:address": "3833 S Main St",
    "sg:city": "Mineral Ridge",
    "sg:classifiers": [
      {
        "category": "Organizations",
        "subcategory": "Religious Organization",
        "type": "Services"
      }
    ],
    "sg:phone": "+1 330 505 2167",
    "sg:postcode": "44440",
    "sg:province": "OH",
    "sg:tags": [
      "church"
    ],
    "wof:name": "Eastminster Presbytery",
    "wof:placetype": "venue"
  },
  "geometry": {"coordinates":[-80.768953,41.137415],"type":"Point"}
}
