{
  "type": "Feature",
  "properties": {
    "iso:country":"US",
    "sg:address":"2149 Prairie Rd",
    "sg:city":"Wilmington",
    "sg:classifiers":[
        {
            "category":"Shopping",
            "subcategory":"Gifts & Souvenirs",
            "type":"Retail Goods"
        }
    ],
    "sg:phone":"+1 937 382 0597",
    "sg:postcode":"45177",
    "sg:province":"OH",
    "wof:name":"Tillies Attic",
    "wof:placetype":"venue"
},
  "geometry": {"coordinates":[-83.810102,39.458166],"type":"Point"}
}