{
  "type": "Feature",
  "properties": {
    "addr:full": "2149 Prairie Rd Wilmington OH 45177",
    "addr:housenumber": "2149",
    "addr:postcode": "45177",
    "addr:street": "Prairie Rd",
    "iso:country": "US",
    "sg:address": "2149 Prairie Rd",
    "sg:city": "Wilmington",
    "sg:classifiers": [
      {
        "category": "Shopping",
        "subcategory": "Gifts \u0026 Souvenirs",
        "type": "Retail Goods"
      }
    ],
    "sg:phone": "+1 937 382 0597",
    "sg:postcode": "45177",
    "sg:province": "OH",
    "wof:name": "Tillies Attic",
    "wof:placetype": "venue"
  },
  "geometry": {"coordinates":[-83.810102,39.458166],"type":"Point"}
}
