{
  "type": "Feature",
  "properties": {
    "iso:country":"US",
    "sg:address":"5225 Trenton Rd",
    "sg:city":"Trenton",
    "sg:classifiers":[
        {
            "category":"Organizations",
            "subcategory":"Membership Organization",
            "type":"Services"
        }
    ],
    "sg:phone":"+1 513 867 5727",
    "sg:postcode":"45067",
    "sg:province":"OH",
    "sg:tags":[
        "executive"
    ],
    "wof:name":"Animal Shelter Butler County",
    "wof:placetype":"venue"
},
  "geometry": {"coordinates":[-84.47869799999999,39.470724],"type":"Point"}
}