{
  "type": "Feature",
  "properties": {
    "iso:country":"US",
    "sg:address":"3067 New Washington Rd",
    "sg:city":"Bloomville",
    "sg:classifiers":[
        {
            "category":"Manufacturing",
            "subcategory":"Signs",
            "type":"Manufacturing & Wholesale Goods"
        }
    ],
    "sg:phone":"+1 419 284 3580",
    "sg:postcode":"44818",
    "sg:province":"OH",
    "wof:name":"Custom Sign Co",
    "wof:placetype":"venue"
},
  "geometry": {"coordinates":[-82.97203,40.964735],"type":"Point"}
}