{
  "type": "Feature",
  "properties": {
    "iso:country":"US",
    "sg:address":"4902 Grantwood Dr",
    "sg:city":"Cleveland",
    "sg:classifiers":[
        {
            "category":"Professional",
            "subcategory":"Business Services",
            "type":"Services"
        }
    ],
    "sg:phone":"+1 216 252 8178",
    "sg:postcode":"44134",
    "sg:province":"OH",
    "sg:tags":[
        "repossessing"
    ],
    "wof:name":"Cuyahoga Recovery & Automotive",
    "wof:placetype":"venue"
},
  "geometry": {"coordinates":[-81.722149,41.396072],"type":"Point"}
}