{
  "type": "Feature",
  "properties": {
    "addr:full": "100 Lincoln Way E Massillon OH 44646",
    "addr:housenumber": "100",
    "addr:postcode": "44646",
    "addr:street": "Lincoln Way E",
    "iso:country": "US",
    "sg:address": "100 Lincoln Way E",
    "sg:city": "Massillon",
    "sg:classifiers": [
      {
        "category": "Professional",
        "type": "Services"
      }
    ],
    "sg:phone": "+1 330 834 9309",
    "sg:postcode": "44646",
    "sg:province": "OH",
    "sg:tags": [
      "establishment"
    ],
    "wof:name": "Grand Mill Centre",
    "wof:placetype": "venue"
  },
  "geometry": {"coordinates":[-81.521253,40.797008],"type":"Point"}
}
