{
  "type": "Feature",
  "properties": {
    "iso:country":"US",
    "sg:address":"1049 Sherwood Ave",
    "sg:city":"Marysville",
    "sg:classifiers":[
        {
            "category":"Building & Trades",
            "subcategory":"Construction",
            "type":"Services"
        }
    ],
    "sg:phone":"+1 937 642 1421",
    "sg:postcode":"43040",
    "sg:province":"OH",
    "sg:tags":[
        "hanging",
        "contractor"
    ],
    "wof:name":"Constance L Simpson",
    "wof:placetype":"venue"
},
  "geometry": {"coordinates":[-83.385196,40.227166],"type":"Point"}
}