{
  "type": "Feature",
  "properties": {
    "iso:country":"US",
    "sg:address":"2100 Springmill Rd",
    "sg:city":"Mansfield",
    "sg:classifiers":[
        {
            "category":"Autos & Motor Vehicles",
            "subcategory":"Automobile Sales",
            "type":"Retail Goods"
        }
    ],
    "sg:phone":"+1 419 747 5216",
    "sg:postcode":"44903",
    "sg:province":"OH",
    "sg:tags":[
        "used"
    ],
    "wof:name":"Sams Auto Sales Inc",
    "wof:placetype":"venue"
},
  "geometry": {"coordinates":[-82.590118,40.810524],"type":"Point"}
}