{
  "type": "Feature",
  "properties": {
    "addr:full":"3613 Gamble Ave Cincinnati OH 45211",
    "addr:housenumber":"3613",
    "addr:postcode":"45211",
    "addr:street":"Gamble Ave",
    "iso:country":"US",
    "sg:address":"3613 Gamble Ave",
    "sg:city":"Cincinnati",
    "sg:classifiers":[
        {
            "category":"Building & Trades",
            "subcategory":"Construction",
            "type":"Services"
        }
    ],
    "sg:phone":"+1 513 661 5776",
    "sg:postcode":"45211",
    "sg:province":"OH",
    "sg:tags":[
        "house"
    ],
    "wof:name":"Dennis Miller Contractin",
    "wof:placetype":"venue"
},
  "geometry": {"coordinates":[-84.611259,39.155362],"type":"Point"}
}