{
  "type": "Feature",
  "properties": {
    "addr:full":"114 Orchard St West Manchester OH 45382",
    "addr:housenumber":"114",
    "addr:postcode":"45382",
    "addr:street":"Orchard St",
    "iso:country":"US",
    "sg:address":"114 Orchard St",
    "sg:city":"West Manchester",
    "sg:classifiers":[
        {
            "category":"Organizations",
            "subcategory":"Religious Organization",
            "type":"Services"
        }
    ],
    "sg:phone":"+1 937 223 5111",
    "sg:postcode":"45382",
    "sg:province":"OH",
    "sg:tags":[
        "church"
    ],
    "wof:name":"United Church Of Christ",
    "wof:placetype":"venue"
},
  "geometry": {"coordinates":[-84.627633,39.903056],"type":"Point"}
}