{
  "type": "Feature",
  "properties": {
    "addr:full":"3121 Market St Youngstown OH 44507",
    "addr:housenumber":"3121",
    "addr:postcode":"44507",
    "addr:street":"Market St",
    "iso:country":"US",
    "sg:address":"3121 Market St",
    "sg:city":"Youngstown",
    "sg:classifiers":[
        {
            "category":"Government",
            "subcategory":"Fire Station",
            "type":"Public Place"
        }
    ],
    "sg:phone":"+1 330 536 6255",
    "sg:postcode":"44507",
    "sg:province":"OH",
    "sg:tags":[
        "protection"
    ],
    "wof:name":"Lowellville Fire Dept",
    "wof:placetype":"venue"
},
  "geometry": {"coordinates":[-80.660775,41.067309],"type":"Point"}
}