{
  "type": "Feature",
  "properties": {
    "iso:country":"US",
    "sg:address":"7790 Chippewa Rd",
    "sg:city":"Brecksville",
    "sg:classifiers":[
        {
            "category":"Banks & Credit Unions",
            "subcategory":"Bank",
            "type":"Services"
        }
    ],
    "sg:phone":"+1 440 526 2283",
    "sg:postcode":"44141",
    "sg:province":"OH",
    "sg:tags":[
        "national"
    ],
    "wof:name":"Keybank National Association",
    "wof:placetype":"venue"
},
  "geometry": {"coordinates":[-81.62185100000001,41.320126],"type":"Point"}
}