{
  "type": "Feature",
  "properties": {
    "addr:full": "7790 Chippewa Rd Brecksville OH 44141",
    "addr:housenumber": "7790",
    "addr:postcode": "44141",
    "addr:street": "Chippewa Rd",
    "iso:country": "US",
    "sg:address": "7790 Chippewa Rd",
    "sg:city": "Brecksville",
    "sg:classifiers": [
      {
        "category": "Banks \u0026 Credit Unions",
        "subcategory": "Bank",
        "type": "Services"
      }
    ],
    "sg:phone": "+1 440 526 2283",
    "sg:postcode": "44141",
    "sg:province": "OH",
    "sg:tags": [
      "national"
    ],
    "wof:name": "Keybank National Association",
    "wof:placetype": "venue"
  },
  "geometry": {"coordinates":[-81.621851,41.320126],"type":"Point"}
}
