{
  "type": "Feature",
  "properties": {
    "addr:full": "7760 Olentangy River Rd Columbus OH 43235",
    "addr:housenumber": "7760",
    "addr:postcode": "43235",
    "addr:street": "Olentangy River Rd",
    "iso:country": "US",
    "sg:address": "7760 Olentangy River Rd",
    "sg:city": "Columbus",
    "sg:classifiers": [
      {
        "category": "Social Services",
        "type": "Services"
      }
    ],
    "sg:phone": "+1 614 785 8122",
    "sg:postcode": "43235",
    "sg:province": "OH",
    "sg:tags": [
      "counselor",
      "marriage",
      "family"
    ],
    "wof:name": "Private Counseling Svc",
    "wof:placetype": "venue"
  },
  "geometry": {"coordinates":[-83.03571,40.122165],"type":"Point"}
}
