{
  "type": "Feature",
  "properties": {
    "iso:country":"US",
    "sg:address":"228 E 3rd St",
    "sg:city":"Dover",
    "sg:classifiers":[
        {
            "category":"Organizations",
            "subcategory":"Religious Organization",
            "type":"Services"
        }
    ],
    "sg:phone":"+1 330 364 3113",
    "sg:postcode":"44622",
    "sg:province":"OH",
    "sg:tags":[
        "church"
    ],
    "wof:name":"Dover Alliance Church",
    "wof:placetype":"venue"
},
  "geometry": {"coordinates":[-81.474816,40.523518],"type":"Point"}
}