{
  "type": "Feature",
  "properties": {
    "iso:country":"US",
    "sg:address":"41340 National Rd",
    "sg:city":"Belmont",
    "sg:classifiers":[
        {
            "category":"Professional",
            "subcategory":"Business Services",
            "type":"Services"
        }
    ],
    "sg:phone":"+1 740 782 0110",
    "sg:postcode":"43718",
    "sg:province":"OH",
    "sg:tags":[
        "auctioneer"
    ],
    "wof:name":"Yoder & Frey Auctioneers Inc",
    "wof:placetype":"venue"
},
  "geometry": {"coordinates":[-81.05514599999999,40.067483],"type":"Point"}
}