{
  "type": "Feature",
  "properties": {
    "addr:full": "41340 National Rd Belmont OH 43718",
    "addr:housenumber": "41340",
    "addr:postcode": "43718",
    "addr:street": "National Rd",
    "iso:country": "US",
    "sg:address": "41340 National Rd",
    "sg:city": "Belmont",
    "sg:classifiers": [
      {
        "category": "Professional",
        "subcategory": "Business Services",
        "type": "Services"
      }
    ],
    "sg:phone": "+1 740 782 0110",
    "sg:postcode": "43718",
    "sg:province": "OH",
    "sg:tags": [
      "auctioneer"
    ],
    "wof:name": "Yoder \u0026 Frey Auctioneers Inc",
    "wof:placetype": "venue"
  },
  "geometry": {"coordinates":[-81.055146,40.067483],"type":"Point"}
}
