{
  "type": "Feature",
  "properties": {
    "addr:full": "403 S Water St Kent OH 44240",
    "addr:housenumber": "403",
    "addr:postcode": "44240",
    "addr:street": "S Water St",
    "iso:country": "US",
    "sg:address": "403 S Water St",
    "sg:city": "Kent",
    "sg:classifiers": [
      {
        "category": "Retail",
        "subcategory": "Car Wash",
        "type": "Services"
      }
    ],
    "sg:phone": "+1 330 676 9880",
    "sg:postcode": "44240",
    "sg:province": "OH",
    "sg:tags": [
      "polishing",
      "washing"
    ],
    "wof:name": "Magic Wash Detail \u0026 Tint",
    "wof:placetype": "venue"
  },
  "geometry": {"coordinates":[-81.358149,41.150099],"type":"Point"}
}
