{
  "type": "Feature",
  "properties": {
    "addr:full": "842 Northland Blvd Cincinnati OH 45240",
    "addr:housenumber": "842",
    "addr:postcode": "45240",
    "addr:street": "Northland Blvd",
    "iso:country": "US",
    "sg:address": "842 Northland Blvd",
    "sg:city": "Cincinnati",
    "sg:classifiers": [
      {
        "category": "Professional",
        "type": "Services"
      }
    ],
    "sg:phone": "+1 513 648 9792",
    "sg:postcode": "45240",
    "sg:province": "OH",
    "wof:name": "Scott Jackson",
    "wof:placetype": "venue"
  },
  "geometry": {"coordinates":[-84.508716,39.275904],"type":"Point"}
}
