{
  "type": "Feature",
  "properties": {
    "addr:full": "205 S Broadway St Greenville OH 45331",
    "addr:housenumber": "205",
    "addr:postcode": "45331",
    "addr:street": "S Broadway St",
    "iso:country": "US",
    "sg:address": "205 S Broadway St",
    "sg:city": "Greenville",
    "sg:classifiers": [
      {
        "category": "Museum",
        "type": "Entertainment"
      }
    ],
    "sg:phone": "+1 937 548 5250",
    "sg:postcode": "45331",
    "sg:province": "OH",
    "sg:tags": [
      "gallery"
    ],
    "sg:website": "www.garstmuseum.org",
    "wof:name": "Garst Museum",
    "wof:placetype": "venue"
  },
  "geometry": {"coordinates":[-84.634266,40.103316],"type":"Point"}
}
