{
  "type": "Feature",
  "properties": {
    "addr:full": "7014 Saint Clair Ave Cleveland OH 44103",
    "addr:housenumber": "7014",
    "addr:postcode": "44103",
    "addr:street": "Saint Clair Ave",
    "iso:country": "US",
    "sg:address": "7014 Saint Clair Ave",
    "sg:city": "Cleveland",
    "sg:classifiers": [
      {
        "category": "Manufacturing",
        "subcategory": "Toys \u0026 Sporting Goods",
        "type": "Manufacturing \u0026 Wholesale Goods"
      }
    ],
    "sg:phone": "+1 216 431 9844",
    "sg:postcode": "44103",
    "sg:province": "OH",
    "sg:tags": [
      "equipment",
      "fishing",
      "mfg"
    ],
    "wof:name": "T J Mfg Inc",
    "wof:placetype": "venue"
  },
  "geometry": {"coordinates":[-81.639755,41.527696],"type":"Point"}
}
