{
  "type": "Feature",
  "properties": {
    "addr:full":"537 S Broadway St Greenville OH 45331",
    "addr:housenumber":"537",
    "addr:postcode":"45331",
    "addr:street":"S Broadway St",
    "iso:country":"US",
    "sg:address":"537 S Broadway St",
    "sg:city":"Greenville",
    "sg:classifiers":[
        {
            "category":"Organizations",
            "subcategory":"Professional Association",
            "type":"Services"
        }
    ],
    "sg:phone":"+1 937 548 5158",
    "sg:postcode":"45331",
    "sg:province":"OH",
    "sg:tags":[
        "chambers",
        "commerce"
    ],
    "wof:name":"Darke County Visitors Bureau",
    "wof:placetype":"venue"
},
  "geometry": {"coordinates":[-84.63120600000001,40.100487],"type":"Point"}
}