{
  "type": "Feature",
  "properties": {
    "addr:full": "11356 State Rte 729 New Vienna OH 45159",
    "addr:housenumber": "11356",
    "addr:postcode": "45159",
    "addr:street": "State Rte 729",
    "iso:country": "US",
    "sg:address": "11356 State Rte 729",
    "sg:city": "New Vienna",
    "sg:classifiers": [
      {
        "category": "Farming",
        "subcategory": "Livestock Farm",
        "type": "Manufacturing \u0026 Wholesale Goods"
      }
    ],
    "sg:phone": "+1 937 987 2505",
    "sg:postcode": "45159",
    "sg:province": "OH",
    "sg:tags": [
      "beef",
      "feedlot",
      "cattle"
    ],
    "wof:name": "Dave Harner",
    "wof:placetype": "venue"
  },
  "geometry": {"coordinates":[-83.68693,39.370585],"type":"Point"}
}
