{
  "type": "Feature",
  "properties": {
    "iso:country":"US",
    "sg:address":"11356 State Rte 729",
    "sg:city":"New Vienna",
    "sg:classifiers":[
        {
            "category":"Farming",
            "subcategory":"Livestock Farm",
            "type":"Manufacturing & Wholesale Goods"
        }
    ],
    "sg:phone":"+1 937 987 2505",
    "sg:postcode":"45159",
    "sg:province":"OH",
    "sg:tags":[
        "beef",
        "feedlot",
        "cattle"
    ],
    "wof:name":"Dave Harner",
    "wof:placetype":"venue"
},
  "geometry": {"coordinates":[-83.68693,39.370585],"type":"Point"}
}