{
  "type": "Feature",
  "properties": {
    "addr:full": "1160 E Turkeyfoot Lake Rd Akron OH 44312",
    "addr:housenumber": "1160",
    "addr:postcode": "44312",
    "addr:street": "E Turkeyfoot Lake Rd",
    "iso:country": "US",
    "sg:address": "1160 E Turkeyfoot Lake Rd",
    "sg:city": "Akron",
    "sg:classifiers": [
      {
        "category": "Real Estate",
        "subcategory": "Real Estate Operator",
        "type": "Services"
      }
    ],
    "sg:phone": "+1 330 644 5898",
    "sg:postcode": "44312",
    "sg:province": "OH",
    "sg:tags": [
      "site"
    ],
    "wof:name": "Rex Hill Mobile Estates \u0026 Sls",
    "wof:placetype": "venue"
  },
  "geometry": {"coordinates":[-81.482901,40.974339],"type":"Point"}
}
