{
  "type": "Feature",
  "properties": {
    "addr:full": "10701 East Blvd Cleveland OH 44106",
    "addr:housenumber": "10701",
    "addr:postcode": "44106",
    "addr:street": "East Blvd",
    "iso:country": "US",
    "sg:address": "10701 East Blvd",
    "sg:city": "Cleveland",
    "sg:classifiers": [
      {
        "category": "Wholesale",
        "subcategory": "Chemicals \u0026 Plastics",
        "type": "Manufacturing \u0026 Wholesale Goods"
      }
    ],
    "sg:phone": "+1 216 521 9255",
    "sg:postcode": "44106",
    "sg:province": "OH",
    "wof:name": "James Patrick Deery",
    "wof:placetype": "venue"
  },
  "geometry": {"coordinates":[-81.61335,41.51264],"type":"Point"}
}
