{
  "type": "Feature",
  "properties": {
    "iso:country":"US",
    "sg:address":"1840 Town Park Blvd",
    "sg:city":"Uniontown",
    "sg:classifiers":[
        {
            "category":"Restaurant",
            "type":"Food & Drink"
        }
    ],
    "sg:phone":"+1 330 896 4433",
    "sg:postcode":"44685",
    "sg:province":"OH",
    "wof:name":"Legends Sports Pub & Grille",
    "wof:placetype":"venue"
},
  "geometry": {"coordinates":[-81.466685,40.950539],"type":"Point"}
}