{
  "type": "Feature",
  "properties": {
    "addr:full": "1840 Town Park Blvd Uniontown OH 44685",
    "addr:housenumber": "1840",
    "addr:postcode": "44685",
    "addr:street": "Town Park Blvd",
    "iso:country": "US",
    "sg:address": "1840 Town Park Blvd",
    "sg:city": "Uniontown",
    "sg:classifiers": [
      {
        "category": "Restaurant",
        "type": "Food \u0026 Drink"
      }
    ],
    "sg:phone": "+1 330 896 4433",
    "sg:postcode": "44685",
    "sg:province": "OH",
    "wof:name": "Legends Sports Pub \u0026 Grille",
    "wof:placetype": "venue"
  },
  "geometry": {"coordinates":[-81.466685,40.950539],"type":"Point"}
}
