{
  "type": "Feature",
  "properties": {
    "iso:country":"US",
    "sg:address":"365 McCoy Rd",
    "sg:city":"Peebles",
    "sg:phone":"+1 937 587 3035",
    "sg:postcode":"45660",
    "sg:province":"OH",
    "sg:tags":[
        "farm",
        "corn"
    ],
    "wof:name":"Frank Mc Coy",
    "wof:placetype":"venue"
},
  "geometry": {"coordinates":[-83.374988,38.9941],"type":"Point"}
}