{
  "type": "Feature",
  "properties": {
    "addr:full": "365 McCoy Rd Peebles OH 45660",
    "addr:housenumber": "365",
    "addr:postcode": "45660",
    "addr:street": "Mccoy Rd",
    "iso:country": "US",
    "sg:address": "365 McCoy Rd",
    "sg:city": "Peebles",
    "sg:phone": "+1 937 587 3035",
    "sg:postcode": "45660",
    "sg:province": "OH",
    "sg:tags": [
      "farm",
      "corn"
    ],
    "wof:name": "Frank Mc Coy",
    "wof:placetype": "venue"
  },
  "geometry": {"coordinates":[-83.374988,38.9941],"type":"Point"}
}
