{
  "type": "Feature",
  "properties": {
    "addr:full":"420 Beecher Rd Gahanna OH 43230",
    "addr:housenumber":"420",
    "addr:postcode":"43230",
    "addr:street":"Beecher Rd",
    "iso:country":"US",
    "sg:address":"420 Beecher Rd",
    "sg:city":"Gahanna",
    "sg:classifiers":[
        {
            "category":"Health Services",
            "subcategory":"Doctor",
            "type":"Services"
        }
    ],
    "sg:phone":"+1 614 939 5200",
    "sg:postcode":"43230",
    "sg:province":"OH",
    "sg:tags":[
        "dentist"
    ],
    "wof:name":"Beecher Ridge Dental Inc",
    "wof:placetype":"venue"
},
  "geometry": {"coordinates":[-82.86667199999999,40.046248],"type":"Point"}
}