{
  "type": "Feature",
  "properties": {
    "iso:country":"US",
    "sg:address":"5096 Gause Rd",
    "sg:city":"Coldwater",
    "sg:classifiers":[
        {
            "category":"Farming",
            "subcategory":"Farm",
            "type":"Manufacturing & Wholesale Goods"
        }
    ],
    "sg:phone":"+1 419 942 1463",
    "sg:postcode":"45828",
    "sg:province":"OH",
    "sg:tags":[
        "crop",
        "general"
    ],
    "wof:name":"Paul Tobe",
    "wof:placetype":"venue"
},
  "geometry": {"coordinates":[-84.66668799999999,40.498411],"type":"Point"}
}