{
  "type": "Feature",
  "properties": {
    "addr:full": "5096 Gause Rd Coldwater OH 45828",
    "addr:housenumber": "5096",
    "addr:postcode": "45828",
    "addr:street": "Gause Rd",
    "iso:country": "US",
    "sg:address": "5096 Gause Rd",
    "sg:city": "Coldwater",
    "sg:classifiers": [
      {
        "category": "Farming",
        "subcategory": "Farm",
        "type": "Manufacturing \u0026 Wholesale Goods"
      }
    ],
    "sg:phone": "+1 419 942 1463",
    "sg:postcode": "45828",
    "sg:province": "OH",
    "sg:tags": [
      "crop",
      "general"
    ],
    "wof:name": "Paul Tobe",
    "wof:placetype": "venue"
  },
  "geometry": {"coordinates":[-84.666688,40.498411],"type":"Point"}
}
