{
  "type": "Feature",
  "properties": {
    "iso:country":"US",
    "sg:address":"5477 Brandywine Ln",
    "sg:city":"Milford",
    "sg:classifiers":[
        {
            "category":"Personal",
            "type":"Services"
        },
        {
            "category":"Professional",
            "subcategory":"Art Services",
            "type":"Services"
        },
        {
            "category":"Communications",
            "subcategory":"Film & Video Production",
            "type":"Services"
        }
    ],
    "sg:phone":"+1 513 576 9390",
    "sg:postcode":"45150",
    "sg:province":"OH",
    "sg:tags":[
        "photographer",
        "photography",
        "videography",
        "aerial",
        "wedding"
    ],
    "wof:name":"Aero Cam Aerial Photography",
    "wof:placetype":"venue"
},
  "geometry": {"coordinates":[-84.23225100000001,39.165959],"type":"Point"}
}