{
  "type": "Feature",
  "properties": {
    "addr:full": "5477 Brandywine Ln Milford OH 45150",
    "addr:housenumber": "5477",
    "addr:postcode": "45150",
    "addr:street": "Brandywine Ln",
    "iso:country": "US",
    "sg:address": "5477 Brandywine Ln",
    "sg:city": "Milford",
    "sg:classifiers": [
      {
        "category": "Personal",
        "type": "Services"
      },
      {
        "category": "Professional",
        "subcategory": "Art Services",
        "type": "Services"
      },
      {
        "category": "Communications",
        "subcategory": "Film \u0026 Video Production",
        "type": "Services"
      }
    ],
    "sg:phone": "+1 513 576 9390",
    "sg:postcode": "45150",
    "sg:province": "OH",
    "sg:tags": [
      "photographer",
      "photography",
      "videography",
      "aerial",
      "wedding"
    ],
    "wof:name": "Aero Cam Aerial Photography",
    "wof:placetype": "venue"
  },
  "geometry": {"coordinates":[-84.232251,39.165959],"type":"Point"}
}
