{
  "type": "Feature",
  "properties": {
    "iso:country":"US",
    "sg:address":"1889 W Market St",
    "sg:city":"Akron",
    "sg:classifiers":[
        {
            "category":"Shopping",
            "subcategory":"Music",
            "type":"Retail Goods"
        }
    ],
    "sg:phone":"+1 330 836 0016",
    "sg:postcode":"44313",
    "sg:province":"OH",
    "wof:name":"Quonset Hut",
    "wof:placetype":"venue"
},
  "geometry": {"coordinates":[-81.576393,41.112724],"type":"Point"}
}