{
  "type": "Feature",
  "properties": {
    "iso:country":"US",
    "sg:address":"245 E Main St",
    "sg:city":"Ottawa",
    "sg:classifiers":[
        {
            "category":"Government",
            "subcategory":"Court House",
            "type":"Public Place"
        }
    ],
    "sg:phone":"+1 419 523 3012",
    "sg:postcode":"45875",
    "sg:province":"OH",
    "sg:tags":[
        "county"
    ],
    "wof:name":"Putnam County Juvenile Court",
    "wof:placetype":"venue"
},
  "geometry": {"coordinates":[-84.045822,41.019188],"type":"Point"}
}