{
  "type": "Feature",
  "properties": {
    "iso:country":"US",
    "sg:address":"527 Portage Trl",
    "sg:city":"Cuyahoga Falls",
    "sg:classifiers":[
        {
            "category":"Wholesale",
            "subcategory":"Non-durable Goods",
            "type":"Manufacturing & Wholesale Goods"
        }
    ],
    "sg:phone":"+1 330 945 4410",
    "sg:postcode":"44221",
    "sg:province":"OH",
    "sg:tags":[
        "ad",
        "specialty"
    ],
    "wof:name":"Sunset Gifts Ad Specialties",
    "wof:placetype":"venue"
},
  "geometry": {"coordinates":[-81.489583,41.13816],"type":"Point"}
}