{
  "type": "Feature",
  "properties": {
    "addr:full": "2066 Valley St Dayton OH 45404",
    "addr:housenumber": "2066",
    "addr:postcode": "45404",
    "addr:street": "Valley St",
    "iso:country": "US",
    "sg:address": "2066 Valley St",
    "sg:city": "Dayton",
    "sg:classifiers": [
      {
        "category": "Wholesale",
        "subcategory": "Chemicals \u0026 Plastics",
        "type": "Manufacturing \u0026 Wholesale Goods"
      },
      {
        "category": "Manufacturing",
        "subcategory": "Rubber \u0026 Plastics",
        "type": "Manufacturing \u0026 Wholesale Goods"
      }
    ],
    "sg:phone": "+1 937 237 8800",
    "sg:postcode": "45404",
    "sg:province": "OH",
    "sg:tags": [
      "product"
    ],
    "sg:website": "www.lairdplastics.com",
    "wof:name": "Laird Plastics Inc",
    "wof:placetype": "venue"
  },
  "geometry": {"coordinates":[-84.145565,39.788239],"type":"Point"}
}
