{
  "type": "Feature",
  "properties": {
    "iso:country":"US",
    "sg:address":"2066 Valley St",
    "sg:city":"Dayton",
    "sg:classifiers":[
        {
            "category":"Wholesale",
            "subcategory":"Chemicals & Plastics",
            "type":"Manufacturing & Wholesale Goods"
        },
        {
            "category":"Manufacturing",
            "subcategory":"Rubber & Plastics",
            "type":"Manufacturing & Wholesale Goods"
        }
    ],
    "sg:phone":"+1 937 237 8800",
    "sg:postcode":"45404",
    "sg:province":"OH",
    "sg:tags":[
        "product"
    ],
    "sg:website":"www.lairdplastics.com",
    "wof:name":"Laird Plastics Inc",
    "wof:placetype":"venue"
},
  "geometry": {"coordinates":[-84.145565,39.788239],"type":"Point"}
}