{
  "type": "Feature",
  "properties": {
    "addr:full": "2916 Parsons Ave Columbus OH 43207",
    "addr:housenumber": "2916",
    "addr:postcode": "43207",
    "addr:street": "Parsons Ave",
    "iso:country": "US",
    "sg:address": "2916 Parsons Ave",
    "sg:city": "Columbus",
    "sg:classifiers": [
      {
        "category": "Freight",
        "type": "Transportation"
      }
    ],
    "sg:phone": "+1 614 497 3487",
    "sg:postcode": "43207",
    "sg:province": "OH",
    "sg:tags": [
      "hauling"
    ],
    "wof:name": "Young Hauling",
    "wof:placetype": "venue"
  },
  "geometry": {"coordinates":[-82.98585,39.905456],"type":"Point"}
}
