{
  "type": "Feature",
  "properties": {
    "iso:country":"US",
    "sg:address":"800 Brooksedge Blvd",
    "sg:city":"Westerville",
    "sg:classifiers":[
        {
            "category":"Banks & Credit Unions",
            "subcategory":"Bank",
            "type":"Services"
        }
    ],
    "sg:phone":"+1 614 244 0380",
    "sg:postcode":"43081",
    "sg:province":"OH",
    "sg:tags":[
        "national",
        "commercial"
    ],
    "wof:name":"Cbrei Banc 1 Portfolio",
    "wof:placetype":"venue"
},
  "geometry": {"coordinates":[-82.93241399999999,40.105911],"type":"Point"}
}