{
  "type": "Feature",
  "properties": {
    "iso:country":"US",
    "sg:address":"1001 Beatrice Dr",
    "sg:city":"Dayton",
    "sg:classifiers":[
        {
            "category":"Organizations",
            "subcategory":"Religious Organization",
            "type":"Services"
        }
    ],
    "sg:phone":"+1 937 237 0763",
    "sg:postcode":"45404",
    "sg:province":"OH",
    "sg:tags":[
        "church"
    ],
    "wof:name":"Greater Galilee Bapt Church",
    "wof:placetype":"venue"
},
  "geometry": {"coordinates":[-84.133467,39.802921],"type":"Point"}
}