{
  "type": "Feature",
  "properties": {
    "addr:full": "842 30th St NW Massillon OH 44647",
    "addr:housenumber": "842",
    "addr:postcode": "44647",
    "addr:street": "30Th St Nw",
    "iso:country": "US",
    "sg:address": "842 30th St NW",
    "sg:city": "Massillon",
    "sg:classifiers": [
      {
        "category": "Building \u0026 Trades",
        "subcategory": "Electrical",
        "type": "Services"
      }
    ],
    "sg:phone": "+1 330 832 2244",
    "sg:postcode": "44647",
    "sg:province": "OH",
    "sg:tags": [
      "electrical",
      "electric",
      "contractor"
    ],
    "wof:name": "Baker Electric Co",
    "wof:placetype": "venue"
  },
  "geometry": {"coordinates":[-81.565773,40.796882],"type":"Point"}
}
