{
  "type": "Feature",
  "properties": {
    "addr:full": "830 Bechtle Ave Springfield OH 45504",
    "addr:housenumber": "830",
    "addr:postcode": "45504",
    "addr:street": "Bechtle Ave",
    "iso:country": "US",
    "sg:address": "830 Bechtle Ave",
    "sg:city": "Springfield",
    "sg:classifiers": [
      {
        "category": "Restaurant",
        "type": "Food \u0026 Drink"
      }
    ],
    "sg:phone": "+1 937 323 9900",
    "sg:postcode": "45504",
    "sg:province": "OH",
    "wof:name": "Scooters Contemprary Dining",
    "wof:placetype": "venue"
  },
  "geometry": {"coordinates":[-83.834528,39.936008],"type":"Point"}
}
