{
  "type": "Feature",
  "properties": {
    "addr:full": "4974 State Rte 121 Greenville OH 45331",
    "addr:housenumber": "4974",
    "addr:postcode": "45331",
    "addr:street": "State Rte 121",
    "iso:country": "US",
    "sg:address": "4974 State Rte 121",
    "sg:city": "Greenville",
    "sg:classifiers": [
      {
        "category": "Building \u0026 Trades",
        "subcategory": "Construction",
        "type": "Services"
      }
    ],
    "sg:phone": "+1 937 547 0620",
    "sg:postcode": "45331",
    "sg:province": "OH",
    "sg:tags": [
      "residential"
    ],
    "wof:name": "P E B Contractors",
    "wof:placetype": "venue"
  },
  "geometry": {"coordinates":[-84.652658,40.060883],"type":"Point"}
}
