{
  "type": "Feature",
  "properties": {
    "addr:full": "2380 Southeast Blvd Salem OH 44460",
    "addr:housenumber": "2380",
    "addr:postcode": "44460",
    "addr:street": "Southeast Blvd",
    "iso:country": "US",
    "sg:address": "2380 Southeast Blvd",
    "sg:city": "Salem",
    "sg:classifiers": [
      {
        "category": "Health Services",
        "subcategory": "Clinic",
        "type": "Services"
      }
    ],
    "sg:phone": "+1 330 332 0426",
    "sg:postcode": "44460",
    "sg:province": "OH",
    "sg:tags": [
      "specialty",
      "outpatient"
    ],
    "wof:name": "Ohio Sports \u0026 Spine Institute",
    "wof:placetype": "venue"
  },
  "geometry": {"coordinates":[-80.830423,40.898633],"type":"Point"}
}
