{
  "type": "Feature",
  "properties": {
    "addr:full":"1300 Morrical Blvd Findlay OH 45840",
    "addr:housenumber":"1300",
    "addr:postcode":"45840",
    "addr:street":"Morrical Blvd",
    "iso:country":"US",
    "sg:address":"1300 Morrical Blvd",
    "sg:city":"Findlay",
    "sg:classifiers":[
        {
            "category":"Manufacturing",
            "subcategory":"Metals",
            "type":"Manufacturing & Wholesale Goods"
        }
    ],
    "sg:phone":"+1 419 425 6400",
    "sg:postcode":"45840",
    "sg:province":"OH",
    "sg:tags":[
        "equipment",
        "pressurization"
    ],
    "sg:website":"www.herculestire.com",
    "wof:name":"Hercules Tire & Rubber Co",
    "wof:placetype":"venue"
},
  "geometry": {"coordinates":[-83.679149,41.023286],"type":"Point"}
}