{
  "type": "Feature",
  "properties": {
    "addr:full": "1121 Sherman Ave NW New Philadelphia OH 44663",
    "addr:housenumber": "1121",
    "addr:postcode": "44663",
    "addr:street": "Sherman Ave Nw New Philadelphia",
    "iso:country": "US",
    "sg:address": "1121 Sherman Ave NW",
    "sg:city": "New Philadelphia",
    "sg:classifiers": [
      {
        "category": "Retail",
        "subcategory": "Auto Repair",
        "type": "Services"
      }
    ],
    "sg:phone": "+1 330 364 3210",
    "sg:postcode": "44663",
    "sg:province": "OH",
    "sg:tags": [
      "repairing",
      "automobile"
    ],
    "wof:name": "Dave's Auto \u0026 Towing",
    "wof:placetype": "venue"
  },
  "geometry": {"coordinates":[-81.46678,40.50008],"type":"Point"}
}
