{
  "type": "Feature",
  "properties": {
    "iso:country":"US",
    "sg:address":"1121 Sherman Ave NW",
    "sg:city":"New Philadelphia",
    "sg:classifiers":[
        {
            "category":"Retail",
            "subcategory":"Auto Repair",
            "type":"Services"
        }
    ],
    "sg:phone":"+1 330 364 3210",
    "sg:postcode":"44663",
    "sg:province":"OH",
    "sg:tags":[
        "repairing",
        "automobile"
    ],
    "wof:name":"Dave's Auto & Towing",
    "wof:placetype":"venue"
},
  "geometry": {"coordinates":[-81.46678,40.50008],"type":"Point"}
}