{
  "type": "Feature",
  "properties": {
    "addr:full": "4240 East Rd Lima OH 45807",
    "addr:housenumber": "4240",
    "addr:postcode": "45807",
    "addr:street": "East Rd",
    "iso:country": "US",
    "sg:address": "4240 East Rd",
    "sg:city": "Lima",
    "sg:classifiers": [
      {
        "category": "Professional",
        "type": "Services"
      }
    ],
    "sg:phone": "+1 419 331 5583",
    "sg:postcode": "45807",
    "sg:province": "OH",
    "sg:tags": [
      "establishment"
    ],
    "wof:name": "Global International Ind",
    "wof:placetype": "venue"
  },
  "geometry": {"coordinates":[-84.179847,40.773039],"type":"Point"}
}
