{
  "type": "Feature",
  "properties": {
    "iso:country":"US",
    "sg:address":"330 Walnut St",
    "sg:city":"Perrysburg",
    "sg:classifiers":[
        {
            "category":"Government",
            "subcategory":"Police Station",
            "type":"Public Place"
        }
    ],
    "sg:phone":"+1 419 872 8001",
    "sg:postcode":"43551",
    "sg:province":"OH",
    "sg:tags":[
        "department"
    ],
    "wof:name":"Perrysburg Police Dept",
    "wof:placetype":"venue"
},
  "geometry": {"coordinates":[-83.63015900000001,41.556431],"type":"Point"}
}