{
  "type": "Feature",
  "properties": {
    "addr:full":"5514 Manchester Rd Akron OH 44319",
    "addr:housenumber":"5514",
    "addr:postcode":"44319",
    "addr:street":"Manchester Rd",
    "iso:country":"US",
    "sg:address":"5514 Manchester Rd",
    "sg:city":"Akron",
    "sg:classifiers":[
        {
            "category":"Building & Trades",
            "subcategory":"Construction",
            "type":"Services"
        },
        {
            "category":"Building & Trades",
            "subcategory":"Landscaping Services",
            "type":"Services"
        }
    ],
    "sg:phone":"+1 330 882 8200",
    "sg:postcode":"44319",
    "sg:province":"OH",
    "sg:tags":[
        "excavation",
        "landscape",
        "contractor"
    ],
    "wof:name":"Blair Landscaping Co",
    "wof:placetype":"venue"
},
  "geometry": {"coordinates":[-81.566208,40.960401],"type":"Point"}
}