{
  "type": "Feature",
  "properties": {
    "addr:full": "18500 5th St Beloit OH 44609",
    "addr:housenumber": "18500",
    "addr:postcode": "44609",
    "addr:street": "5Th St",
    "iso:country": "US",
    "sg:address": "18500 5th St",
    "sg:city": "Beloit",
    "sg:classifiers": [
      {
        "category": "Personal",
        "subcategory": "Tanning Parlor",
        "type": "Services"
      },
      {
        "category": "Personal",
        "subcategory": "Beauty Salon",
        "type": "Services"
      }
    ],
    "sg:phone": "+1 330 938 9368",
    "sg:postcode": "44609",
    "sg:province": "OH",
    "sg:tags": [
      "shop"
    ],
    "wof:name": "Today's Look",
    "wof:placetype": "venue"
  },
  "geometry": {"coordinates":[-81.005366,40.92329],"type":"Point"}
}
