{
  "type": "Feature",
  "properties": {
    "iso:country":"US",
    "sg:address":"6272 Mayfield Rd",
    "sg:city":"Cleveland",
    "sg:classifiers":[
        {
            "category":"Professional",
            "type":"Services"
        },
        {
            "category":"Professional",
            "subcategory":"Business Services",
            "type":"Services"
        },
        {
            "category":"Professional",
            "subcategory":"Printing & Photocopies",
            "type":"Services"
        },
        {
            "category":"Shopping",
            "subcategory":"Stationery & Office Supplies",
            "type":"Retail Goods"
        },
        {
            "category":"Manufacturing",
            "subcategory":"Printing",
            "type":"Manufacturing & Wholesale Goods"
        },
        {
            "category":"Manufacturing",
            "subcategory":"Signs",
            "type":"Manufacturing & Wholesale Goods"
        }
    ],
    "sg:phone":"+1 440 461 2679",
    "sg:postcode":"44124",
    "sg:province":"OH",
    "sg:tags":[
        "machine",
        "document",
        "duplicating",
        "shipping",
        "materials-shipping",
        "packaging",
        "packing",
        "imaging",
        "copying",
        "digital",
        "copy"
    ],
    "sg:website":"http://www.fedex.com/Dropoff/start?FY11-FXO-YELLOWPAGES",
    "wof:name":"FedEx Office Print & Ship Center",
    "wof:placetype":"venue"
},
  "geometry": {"coordinates":[-81.453299,41.5201],"type":"Point"}
}