{
  "type": "Feature",
  "properties": {
    "iso:country":"US",
    "sg:address":"1109 Siler St",
    "sg:city":"Fremont",
    "sg:classifiers":[
        {
            "category":"Manufacturing",
            "subcategory":"Tools & Machinery",
            "type":"Manufacturing & Wholesale Goods"
        }
    ],
    "sg:phone":"+1 419 332 5490",
    "sg:postcode":"43420",
    "sg:province":"OH",
    "sg:tags":[
        "machine",
        "shop"
    ],
    "wof:name":"Park Tool & Die Co Inc",
    "wof:placetype":"venue"
},
  "geometry": {"coordinates":[-83.133639,41.332259],"type":"Point"}
}