{
  "type": "Feature",
  "properties": {
    "addr:full": "1109 Siler St Fremont OH 43420",
    "addr:housenumber": "1109",
    "addr:postcode": "43420",
    "addr:street": "Siler St",
    "iso:country": "US",
    "sg:address": "1109 Siler St",
    "sg:city": "Fremont",
    "sg:classifiers": [
      {
        "category": "Manufacturing",
        "subcategory": "Tools \u0026 Machinery",
        "type": "Manufacturing \u0026 Wholesale Goods"
      }
    ],
    "sg:phone": "+1 419 332 5490",
    "sg:postcode": "43420",
    "sg:province": "OH",
    "sg:tags": [
      "machine",
      "shop"
    ],
    "wof:name": "Park Tool \u0026 Die Co Inc",
    "wof:placetype": "venue"
  },
  "geometry": {"coordinates":[-83.133639,41.332259],"type":"Point"}
}
