{
  "type": "Feature",
  "properties": {
    "iso:country":"US",
    "sg:address":"3632 Swauger Valley Rd",
    "sg:city":"Portsmouth",
    "sg:classifiers":[
        {
            "category":"Social Services",
            "subcategory":"Child Care",
            "type":"Services"
        }
    ],
    "sg:phone":"+1 740 820 2874",
    "sg:postcode":"45662",
    "sg:province":"OH",
    "wof:name":"Cathy's Home Daycare",
    "wof:placetype":"venue"
},
  "geometry": {"coordinates":[-82.887984,38.813652],"type":"Point"}
}