{
  "type": "Feature",
  "properties": {
    "iso:country":"US",
    "sg:address":"3908 Tannery Hill",
    "sg:city":"Ashtabula",
    "sg:classifiers":[
        {
            "category":"Bars & Pubs",
            "type":"Food & Drink"
        }
    ],
    "sg:phone":"+1 440 998 7099",
    "sg:postcode":"44004",
    "sg:province":"OH",
    "sg:tags":[
        "club",
        "night"
    ],
    "wof:name":"Eden's Apple",
    "wof:placetype":"venue"
},
  "geometry": {"coordinates":[-80.780402,41.872049],"type":"Point"}
}