{
  "type": "Feature",
  "properties": {
    "addr:full": "3908 Tannery Hill Ashtabula OH 44004",
    "addr:housenumber": "3908",
    "addr:postcode": "44004",
    "addr:street": "Tannery Hill",
    "iso:country": "US",
    "sg:address": "3908 Tannery Hill",
    "sg:city": "Ashtabula",
    "sg:classifiers": [
      {
        "category": "Bars \u0026 Pubs",
        "type": "Food \u0026 Drink"
      }
    ],
    "sg:phone": "+1 440 998 7099",
    "sg:postcode": "44004",
    "sg:province": "OH",
    "sg:tags": [
      "club",
      "night"
    ],
    "wof:name": "Eden's Apple",
    "wof:placetype": "venue"
  },
  "geometry": {"coordinates":[-80.780402,41.872049],"type":"Point"}
}
