{
  "type": "Feature",
  "properties": {
    "addr:full":"4929 Winchester Pike Columbus OH 43232",
    "addr:housenumber":"4929",
    "addr:postcode":"43232",
    "addr:street":"Winchester Pike",
    "iso:country":"US",
    "sg:address":"4929 Winchester Pike",
    "sg:city":"Columbus",
    "sg:classifiers":[
        {
            "category":"Freight",
            "type":"Transportation"
        }
    ],
    "sg:phone":"+1 614 837 6765",
    "sg:postcode":"43232",
    "sg:province":"OH",
    "sg:tags":[
        "operator",
        "local",
        "trucking"
    ],
    "wof:name":"Overmeyer Trucking Inc",
    "wof:placetype":"venue"
},
  "geometry": {"coordinates":[-82.86904800000001,39.893293],"type":"Point"}
}