{
  "type": "Feature",
  "properties": {
    "addr:full": "700 China St Roseville OH 43777",
    "addr:housenumber": "700",
    "addr:postcode": "43777",
    "addr:street": "China St",
    "iso:country": "US",
    "sg:address": "700 China St",
    "sg:city": "Roseville",
    "sg:classifiers": [
      {
        "category": "Professional",
        "type": "Services"
      }
    ],
    "sg:phone": "+1 740 697 0106",
    "sg:postcode": "43777",
    "sg:province": "OH",
    "sg:tags": [
      "establishment"
    ],
    "wof:name": "Precision Cast Parts",
    "wof:placetype": "venue"
  },
  "geometry": {"coordinates":[-82.095919,39.777715],"type":"Point"}
}
