{
  "type": "Feature",
  "properties": {
    "iso:country":"US",
    "sg:address":"900 Hemlock Ln",
    "sg:city":"Northfield",
    "sg:classifiers":[
        {
            "category":"Building & Trades",
            "subcategory":"Construction",
            "type":"Services"
        }
    ],
    "sg:phone":"+1 330 467 3000",
    "sg:postcode":"44067",
    "sg:province":"OH",
    "sg:tags":[
        "excavating",
        "contractor"
    ],
    "wof:name":"Bradco Construction Co Inc",
    "wof:placetype":"venue"
},
  "geometry": {"coordinates":[-81.567823,41.307514],"type":"Point"}
}