{
  "type": "Feature",
  "properties": {
    "addr:full": "746 Wheeling Ave Cambridge OH 43725",
    "addr:housenumber": "746",
    "addr:postcode": "43725",
    "addr:street": "Wheeling Ave",
    "iso:country": "US",
    "sg:address": "746 Wheeling Ave",
    "sg:city": "Cambridge",
    "sg:classifiers": [
      {
        "category": "Personal",
        "subcategory": "Beauty Salon",
        "type": "Services"
      }
    ],
    "sg:phone": "+1 740 432 1824",
    "sg:postcode": "43725",
    "sg:province": "OH",
    "wof:name": "Vogue Hair Salon",
    "wof:placetype": "venue"
  },
  "geometry": {"coordinates":[-81.59164,40.024732],"type":"Point"}
}
