{
  "type": "Feature",
  "properties": {
    "addr:full": "76 West Ave Tallmadge OH 44278",
    "addr:housenumber": "76",
    "addr:postcode": "44278",
    "addr:street": "West Ave",
    "iso:country": "US",
    "sg:address": "76 West Ave",
    "sg:city": "Tallmadge",
    "sg:classifiers": [
      {
        "category": "Restaurant",
        "type": "Food \u0026 Drink"
      }
    ],
    "sg:phone": "+1 330 634 9967",
    "sg:postcode": "44278",
    "sg:province": "OH",
    "wof:name": "Firehouse Grill \u0026 Pub",
    "wof:placetype": "venue"
  },
  "geometry": {"coordinates":[-81.44575,41.101573],"type":"Point"}
}
