{
  "type": "Feature",
  "properties": {
    "iso:country":"US",
    "sg:address":"76 West Ave",
    "sg:city":"Tallmadge",
    "sg:classifiers":[
        {
            "category":"Restaurant",
            "type":"Food & Drink"
        }
    ],
    "sg:phone":"+1 330 634 9967",
    "sg:postcode":"44278",
    "sg:province":"OH",
    "wof:name":"Firehouse Grill & Pub",
    "wof:placetype":"venue"
},
  "geometry": {"coordinates":[-81.44575,41.101573],"type":"Point"}
}