{
  "type": "Feature",
  "properties": {
    "iso:country":"US",
    "sg:address":"39446 State Rte 517",
    "sg:city":"Lisbon",
    "sg:classifiers":[
        {
            "category":"Organizations",
            "subcategory":"Religious Organization",
            "type":"Services"
        }
    ],
    "sg:phone":"+1 330 424 9111",
    "sg:postcode":"44432",
    "sg:province":"OH",
    "sg:tags":[
        "clergy"
    ],
    "wof:name":"Herbert De Long",
    "wof:placetype":"venue"
},
  "geometry": {"coordinates":[-80.758131,40.787735],"type":"Point"}
}