{
  "type": "Feature",
  "properties": {
    "addr:full":"76 W Clinton St Millersburg OH 44654",
    "addr:housenumber":"76",
    "addr:postcode":"44654",
    "addr:street":"W Clinton St",
    "iso:country":"US",
    "sg:address":"76 W Clinton St",
    "sg:city":"Millersburg",
    "sg:classifiers":[
        {
            "category":"Government",
            "subcategory":"Office",
            "type":"Public Place"
        }
    ],
    "sg:phone":"+1 330 674 2811",
    "sg:postcode":"44654",
    "sg:province":"OH",
    "wof:name":"Holmes County Farm Svc Agency",
    "wof:placetype":"venue"
},
  "geometry": {"coordinates":[-81.917709,40.555555],"type":"Point"}
}