{
  "type": "Feature",
  "properties": {
    "addr:full":"731 Beta Dr Cleveland OH 44143",
    "addr:housenumber":"731",
    "addr:postcode":"44143",
    "addr:street":"Beta Dr",
    "iso:country":"US",
    "sg:address":"731 Beta Dr",
    "sg:city":"Cleveland",
    "sg:classifiers":[
        {
            "category":"Professional",
            "subcategory":"Testing Lab",
            "type":"Services"
        },
        {
            "category":"Retail",
            "subcategory":"Repair Shop",
            "type":"Services"
        }
    ],
    "sg:phone":"+1 440 442 8080",
    "sg:postcode":"44143",
    "sg:province":"OH",
    "sg:tags":[
        "calibration"
    ],
    "sg:website":"www.dynamictechnology.com",
    "wof:name":"Dynamic Technology Inc",
    "wof:placetype":"venue"
},
  "geometry": {"coordinates":[-81.445021,41.542756],"type":"Point"}
}