{
  "type": "Feature",
  "properties": {
    "addr:full":"32 N Main St Marshallville OH 44645",
    "addr:housenumber":"32",
    "addr:postcode":"44645",
    "addr:street":"N Main St",
    "iso:country":"US",
    "sg:address":"32 N Main St",
    "sg:city":"Marshallville",
    "sg:classifiers":[
        {
            "category":"Restaurant",
            "type":"Food & Drink"
        }
    ],
    "sg:phone":"+1 330 855 7171",
    "sg:postcode":"44645",
    "sg:province":"OH",
    "sg:tags":[
        "eating"
    ],
    "wof:name":"Sam's Pizza",
    "wof:placetype":"venue"
},
  "geometry": {"coordinates":[-81.73390999999999,40.904993],"type":"Point"}
}