{
  "type": "Feature",
  "properties": {
    "addr:full": "1040 Harrison Ave Harrison OH 45030",
    "addr:housenumber": "1040",
    "addr:postcode": "45030",
    "addr:street": "Harrison Ave",
    "iso:country": "US",
    "sg:address": "1040 Harrison Ave",
    "sg:city": "Harrison",
    "sg:classifiers": [
      {
        "category": "Building \u0026 Trades",
        "subcategory": "Construction",
        "type": "Services"
      }
    ],
    "sg:phone": "+1 513 367 9026",
    "sg:postcode": "45030",
    "sg:province": "OH",
    "sg:tags": [
      "general",
      "contractor"
    ],
    "wof:name": "Jim Lane Construction",
    "wof:placetype": "venue"
  },
  "geometry": {"coordinates":[-84.808631,39.260597],"type":"Point"}
}
