{
  "type": "Feature",
  "properties": {
    "addr:full": "7019 Pineview Dr Dayton OH 45424",
    "addr:housenumber": "7019",
    "addr:postcode": "45424",
    "addr:street": "Pineview Dr",
    "iso:country": "US",
    "sg:address": "7019 Pineview Dr",
    "sg:city": "Dayton",
    "sg:classifiers": [
      {
        "category": "Home \u0026 Garden",
        "subcategory": "Building Materials",
        "type": "Retail Goods"
      }
    ],
    "sg:phone": "+1 937 236 1722",
    "sg:postcode": "45424",
    "sg:province": "OH",
    "sg:tags": [
      "windows"
    ],
    "wof:name": "Aaron's Windows Doors \u0026 Siding",
    "wof:placetype": "venue"
  },
  "geometry": {"coordinates":[-84.141336,39.857607],"type":"Point"}
}
