{
  "type": "Feature",
  "properties": {
    "addr:full": "3 Mount Vernon Ave Mt Vernon OH 43050",
    "addr:housenumber": "3",
    "addr:postcode": "43050",
    "addr:street": "Mount Vernon Ave",
    "iso:country": "US",
    "sg:address": "3 Mount Vernon Ave",
    "sg:city": "Mt Vernon",
    "sg:classifiers": [
      {
        "category": "Wholesale",
        "subcategory": "Groceries",
        "type": "Manufacturing \u0026 Wholesale Goods"
      }
    ],
    "sg:phone": "+1 740 392 0111",
    "sg:postcode": "43050",
    "sg:province": "OH",
    "sg:tags": [
      "food",
      "product",
      "health"
    ],
    "wof:name": "ABC Health Food Store",
    "wof:placetype": "venue"
  },
  "geometry": {"coordinates":[-82.485368,40.384896],"type":"Point"}
}
