{
  "type": "Feature",
  "properties": {
    "addr:full":"1 Public Sq Cleveland OH 44113",
    "addr:housenumber":"1",
    "addr:postcode":"44113",
    "addr:street":"Public Sq",
    "iso:country":"US",
    "sg:address":"1 Public Sq",
    "sg:city":"Cleveland",
    "sg:classifiers":[
        {
            "category":"Professional",
            "subcategory":"Lawyer & Legal Services",
            "type":"Services"
        }
    ],
    "sg:phone":"+1 216 241 2977",
    "sg:postcode":"44113",
    "sg:province":"OH",
    "sg:tags":[
        "attorney"
    ],
    "wof:name":"Gerald F Cooper",
    "wof:placetype":"venue"
},
  "geometry": {"coordinates":[-81.69497699999999,41.499826],"type":"Point"}
}