{
  "type": "Feature",
  "properties": {
    "addr:full": "43 Pruitt Blvd Akron OH 44310",
    "addr:housenumber": "43",
    "addr:postcode": "44310",
    "addr:street": "Pruitt Blvd",
    "iso:country": "US",
    "sg:address": "43 Pruitt Blvd",
    "sg:city": "Akron",
    "sg:phone": "+1 330 633 6060",
    "sg:postcode": "44310",
    "sg:province": "OH",
    "sg:website": "http://www.mphonda.com",
    "wof:name": "Mike Pruitt Honda",
    "wof:placetype": "venue"
  },
  "geometry": {"coordinates":[-81.493353,41.114583],"type":"Point"}
}
