{
  "type": "Feature",
  "properties": {
    "iso:country":"US",
    "sg:address":"3181 Larchmont Ave NE",
    "sg:city":"Warren",
    "sg:classifiers":[
        {
            "category":"Professional",
            "type":"Services"
        }
    ],
    "sg:phone":"+1 330 372 5420",
    "sg:postcode":"44483",
    "sg:province":"OH",
    "sg:tags":[
        "establishment"
    ],
    "wof:name":"CTGY",
    "wof:placetype":"venue"
},
  "geometry": {"coordinates":[-80.801805,41.266918],"type":"Point"}
}