{
  "type": "Feature",
  "properties": {
    "iso:country":"US",
    "sg:address":"1170 W State St",
    "sg:city":"Alliance",
    "sg:classifiers":[
        {
            "category":"Personal",
            "subcategory":"Beauty Salon",
            "type":"Services"
        }
    ],
    "sg:phone":"+1 330 829 9909",
    "sg:postcode":"44601",
    "sg:province":"OH",
    "sg:tags":[
        "shop"
    ],
    "wof:name":"Exotic Nails",
    "wof:placetype":"venue"
},
  "geometry": {"coordinates":[-81.123227,40.901748],"type":"Point"}
}