{
  "type": "Feature",
  "properties": {
    "iso:country":"US",
    "sg:address":"268 W Mitchell Ave",
    "sg:city":"Cincinnati",
    "sg:classifiers":[
        {
            "category":"Autos & Motor Vehicles",
            "subcategory":"Automobile Sales",
            "type":"Retail Goods"
        }
    ],
    "sg:phone":"+1 513 541 4212",
    "sg:postcode":"45232",
    "sg:province":"OH",
    "wof:name":"Parts Department",
    "wof:placetype":"venue"
},
  "geometry": {"coordinates":[-84.512913,39.165602],"type":"Point"}
}