{
  "type": "Feature",
  "properties": {
    "addr:full": "105 Keswick Dr Hudson OH 44236",
    "addr:housenumber": "105",
    "addr:postcode": "44236",
    "addr:street": "Keswick Dr",
    "iso:country": "US",
    "sg:address": "105 Keswick Dr",
    "sg:city": "Hudson",
    "sg:classifiers": [
      {
        "category": "Manufacturing",
        "subcategory": "Rubber \u0026 Plastics",
        "type": "Manufacturing \u0026 Wholesale Goods"
      }
    ],
    "sg:phone": "+1 330 650 9578",
    "sg:postcode": "44236",
    "sg:province": "OH",
    "sg:tags": [
      "composite"
    ],
    "wof:name": "Polywire Tough Composites Ltd",
    "wof:placetype": "venue"
  },
  "geometry": {"coordinates":[-81.431667,41.231411],"type":"Point"}
}
