{
  "type": "Feature",
  "properties": {
    "addr:full":"1250 Sutton Rd Cincinnati OH 45230",
    "addr:housenumber":"1250",
    "addr:postcode":"45230",
    "addr:street":"Sutton Rd",
    "iso:country":"US",
    "sg:address":"1250 Sutton Rd",
    "sg:city":"Cincinnati",
    "sg:classifiers":[
        {
            "category":"Building & Trades",
            "subcategory":"Construction",
            "type":"Services"
        }
    ],
    "sg:phone":"+1 513 233 2104",
    "sg:postcode":"45230",
    "sg:province":"OH",
    "sg:tags":[
        "carpentry",
        "contractor"
    ],
    "wof:name":"Bragg McGraw Carpentry LLC",
    "wof:placetype":"venue"
},
  "geometry": {"coordinates":[-84.391836,39.075771],"type":"Point"}
}