{
  "type": "Feature",
  "properties": {
    "addr:full": "819 Carpenter Rd Loveland OH 45140",
    "addr:housenumber": "819",
    "addr:postcode": "45140",
    "addr:street": "Carpenter Rd",
    "iso:country": "US",
    "sg:address": "819 Carpenter Rd",
    "sg:city": "Loveland",
    "sg:classifiers": [
      {
        "category": "Professional",
        "type": "Services"
      }
    ],
    "sg:phone": "+1 513 554 8729",
    "sg:postcode": "45140",
    "sg:province": "OH",
    "wof:name": "Kelley Maher",
    "wof:placetype": "venue"
  },
  "geometry": {"coordinates":[-84.26053,39.210942],"type":"Point"}
}
