{
  "type": "Feature",
  "properties": {
    "addr:full": "8916 State Rte 188 Circleville OH 43113",
    "addr:housenumber": "8916",
    "addr:postcode": "43113",
    "addr:street": "State Rte 188",
    "iso:country": "US",
    "sg:address": "8916 State Rte 188",
    "sg:city": "Circleville",
    "sg:classifiers": [
      {
        "category": "Building \u0026 Trades",
        "subcategory": "Plumbing",
        "type": "Services"
      }
    ],
    "sg:phone": "+1 740 474 3765",
    "sg:postcode": "43113",
    "sg:province": "OH",
    "sg:tags": [
      "heating",
      "contractor"
    ],
    "wof:name": "Cook's Refrigeration Svc",
    "wof:placetype": "venue"
  },
  "geometry": {"coordinates":[-82.855803,39.668273],"type":"Point"}
}
