{
  "type": "Feature",
  "properties": {
    "iso:country":"US",
    "sg:address":"8916 State Rte 188",
    "sg:city":"Circleville",
    "sg:classifiers":[
        {
            "category":"Building & Trades",
            "subcategory":"Plumbing",
            "type":"Services"
        }
    ],
    "sg:phone":"+1 740 474 3765",
    "sg:postcode":"43113",
    "sg:province":"OH",
    "sg:tags":[
        "heating",
        "contractor"
    ],
    "wof:name":"Cook's Refrigeration Svc",
    "wof:placetype":"venue"
},
  "geometry": {"coordinates":[-82.85580299999999,39.668273],"type":"Point"}
}