{
  "type": "Feature",
  "properties": {
    "addr:full": "34300 Vine St Willowick OH 44095",
    "addr:housenumber": "34300",
    "addr:postcode": "44095",
    "addr:street": "Vine St",
    "iso:country": "US",
    "sg:address": "34300 Vine St",
    "sg:city": "Willowick",
    "sg:classifiers": [
      {
        "category": "Retail",
        "subcategory": "Auto Repair",
        "type": "Services"
      }
    ],
    "sg:phone": "+1 440 269 7900",
    "sg:postcode": "44095",
    "sg:province": "OH",
    "sg:tags": [
      "repairing",
      "automobile"
    ],
    "wof:name": "Monro Muffler Brake \u0026 Svc",
    "wof:placetype": "venue"
  },
  "geometry": {"coordinates":[-81.442813,41.642537],"type":"Point"}
}
