{
  "type": "Feature",
  "properties": {
    "iso:country":"US",
    "sg:address":"34300 Vine St",
    "sg:city":"Willowick",
    "sg:classifiers":[
        {
            "category":"Retail",
            "subcategory":"Auto Repair",
            "type":"Services"
        }
    ],
    "sg:phone":"+1 440 269 7900",
    "sg:postcode":"44095",
    "sg:province":"OH",
    "sg:tags":[
        "repairing",
        "automobile"
    ],
    "wof:name":"Monro Muffler Brake & Svc",
    "wof:placetype":"venue"
},
  "geometry": {"coordinates":[-81.442813,41.642537],"type":"Point"}
}