{
  "type": "Feature",
  "properties": {
    "addr:full": "9 Main St Ripley OH 45167",
    "addr:housenumber": "9",
    "addr:postcode": "45167",
    "addr:street": "Main St",
    "iso:country": "US",
    "sg:address": "9 Main St",
    "sg:city": "Ripley",
    "sg:classifiers": [
      {
        "category": "Health Services",
        "subcategory": "Doctor",
        "type": "Services"
      }
    ],
    "sg:phone": "+1 937 392 0005",
    "sg:postcode": "45167",
    "sg:province": "OH",
    "sg:tags": [
      "physician",
      "surgeon"
    ],
    "wof:name": "Riverview Primary Care",
    "wof:placetype": "venue"
  },
  "geometry": {"coordinates":[-83.846153,38.745158],"type":"Point"}
}
