{
  "type": "Feature",
  "properties": {
    "addr:full": "7129 State Rte 5 Ravenna OH 44266",
    "addr:housenumber": "7129",
    "addr:postcode": "44266",
    "addr:street": "State Rte 5",
    "iso:country": "US",
    "sg:address": "7129 State Rte 5",
    "sg:city": "Ravenna",
    "sg:classifiers": [
      {
        "category": "Building \u0026 Trades",
        "subcategory": "Construction",
        "type": "Services"
      }
    ],
    "sg:phone": "+1 330 297 6859",
    "sg:postcode": "44266",
    "sg:province": "OH",
    "sg:tags": [
      "contractor"
    ],
    "wof:name": "Jim Litsinger Roofing",
    "wof:placetype": "venue"
  },
  "geometry": {"coordinates":[-81.132629,41.155365],"type":"Point"}
}
