{
  "type": "Feature",
  "properties": {
    "iso:country":"US",
    "sg:address":"2682 Joseph Rd",
    "sg:city":"Luckey",
    "sg:classifiers":[
        {
            "category":"Organizations",
            "subcategory":"Religious Organization",
            "type":"Services"
        }
    ],
    "sg:phone":"+1 419 837 9168",
    "sg:postcode":"43443",
    "sg:province":"OH",
    "sg:tags":[
        "clergy"
    ],
    "wof:name":"Milton C Mann",
    "wof:placetype":"venue"
},
  "geometry": {"coordinates":[-83.44776899999999,41.464694],"type":"Point"}
}