{
  "type": "Feature",
  "properties": {
    "addr:full":"118 E 2nd St Waverly OH 45690",
    "addr:housenumber":"118",
    "addr:postcode":"45690",
    "addr:street":"E 2Nd St",
    "iso:country":"US",
    "sg:address":"118 E 2nd St",
    "sg:city":"Waverly",
    "sg:classifiers":[
        {
            "category":"Banks & Credit Unions",
            "subcategory":"Investment Brokerage",
            "type":"Services"
        }
    ],
    "sg:phone":"+1 740 947 0504",
    "sg:postcode":"45690",
    "sg:province":"OH",
    "sg:tags":[
        "security"
    ],
    "wof:name":"Edward Jones Co",
    "wof:placetype":"venue"
},
  "geometry": {"coordinates":[-82.98338699999999,39.12677],"type":"Point"}
}