{
  "type": "Feature",
  "properties": {
    "iso:country":"US",
    "sg:address":"79 N 2nd St",
    "sg:city":"Newark",
    "sg:classifiers":[
        {
            "category":"Autos & Motor Vehicles",
            "subcategory":"Automobile Sales",
            "type":"Retail Goods"
        }
    ],
    "sg:phone":"+1 740 349 7226",
    "sg:postcode":"43055",
    "sg:province":"OH",
    "sg:tags":[
        "car",
        "dealer"
    ],
    "wof:name":"Dennis' Used Cars",
    "wof:placetype":"venue"
},
  "geometry": {"coordinates":[-82.401811,40.060098],"type":"Point"}
}