{
  "type": "Feature",
  "properties": {
    "addr:full": "1293 Blackoak Cir Westerville OH 43081",
    "addr:housenumber": "1293",
    "addr:postcode": "43081",
    "addr:street": "Blackoak Cir",
    "iso:country": "US",
    "sg:address": "1293 Blackoak Cir",
    "sg:city": "Westerville",
    "sg:classifiers": [
      {
        "category": "Professional",
        "subcategory": "Management \u0026 Consulting",
        "type": "Services"
      }
    ],
    "sg:phone": "+1 614 882 2315",
    "sg:postcode": "43081",
    "sg:province": "OH",
    "sg:tags": [
      "consultant",
      "business"
    ],
    "wof:name": "Hevel Consulting Group",
    "wof:placetype": "venue"
  },
  "geometry": {"coordinates":[-82.890909,40.11531],"type":"Point"}
}
