{
  "type": "Feature",
  "properties": {
    "iso:country":"US",
    "sg:address":"1293 Blackoak Cir",
    "sg:city":"Westerville",
    "sg:classifiers":[
        {
            "category":"Professional",
            "subcategory":"Management & Consulting",
            "type":"Services"
        }
    ],
    "sg:phone":"+1 614 882 2315",
    "sg:postcode":"43081",
    "sg:province":"OH",
    "sg:tags":[
        "consultant",
        "business"
    ],
    "wof:name":"Hevel Consulting Group",
    "wof:placetype":"venue"
},
  "geometry": {"coordinates":[-82.89090899999999,40.11531],"type":"Point"}
}