{
  "type": "Feature",
  "properties": {
    "addr:full":"400 W Broad St Columbus OH 43215",
    "addr:housenumber":"400",
    "addr:postcode":"43215",
    "addr:street":"W Broad St",
    "iso:country":"US",
    "sg:address":"400 W Broad St",
    "sg:city":"Columbus",
    "sg:classifiers":[
        {
            "category":"Autos & Motor Vehicles",
            "subcategory":"Automobile Sales",
            "type":"Retail Goods"
        }
    ],
    "sg:phone":"+1 614 469 0509",
    "sg:postcode":"43215",
    "sg:province":"OH",
    "sg:tags":[
        "car",
        "dealer"
    ],
    "wof:name":"Market Place Motors",
    "wof:placetype":"venue"
},
  "geometry": {"coordinates":[-83.01182799999999,39.960853],"type":"Point"}
}