{
  "type": "Feature",
  "properties": {
    "iso:country":"US",
    "sg:address":"655 E 162nd St",
    "sg:city":"Cleveland",
    "sg:classifiers":[
        {
            "category":"Education",
            "subcategory":"School",
            "type":"Public Place"
        }
    ],
    "sg:phone":"+1 216 531 2872",
    "sg:postcode":"44110",
    "sg:province":"OH",
    "sg:tags":[
        "middle"
    ],
    "wof:name":"Margaret Spellacy Middle Schl",
    "wof:placetype":"venue"
},
  "geometry": {"coordinates":[-81.567472,41.563073],"type":"Point"}
}