{
  "type": "Feature",
  "properties": {
    "addr:full": "3065 E 14th Ave Columbus OH 43219",
    "addr:housenumber": "3065",
    "addr:postcode": "43219",
    "addr:street": "E 14Th Ave",
    "iso:country": "US",
    "sg:address": "3065 E 14th Ave",
    "sg:city": "Columbus",
    "sg:classifiers": [
      {
        "category": "Wholesale",
        "subcategory": "Computers",
        "type": "Manufacturing \u0026 Wholesale Goods"
      },
      {
        "category": "Manufacturing",
        "subcategory": "Tools \u0026 Machinery",
        "type": "Manufacturing \u0026 Wholesale Goods"
      }
    ],
    "sg:phone": "+1 614 258 5586",
    "sg:postcode": "43219",
    "sg:province": "OH",
    "sg:tags": [
      "equipment",
      "peripheral"
    ],
    "wof:name": "Capital Media Group LLC",
    "wof:placetype": "venue"
  },
  "geometry": {"coordinates":[-82.929177,39.993921],"type":"Point"}
}
