{
  "type": "Feature",
  "properties": {
    "addr:full": "864 Marmion Ave Youngstown OH 44502",
    "addr:housenumber": "864",
    "addr:postcode": "44502",
    "addr:street": "Marmion Ave",
    "iso:country": "US",
    "sg:address": "864 Marmion Ave",
    "sg:city": "Youngstown",
    "sg:classifiers": [
      {
        "category": "Building \u0026 Trades",
        "subcategory": "Construction",
        "type": "Services"
      }
    ],
    "sg:phone": "+1 330 788 8820",
    "sg:postcode": "44502",
    "sg:province": "OH",
    "sg:tags": [
      "wallpaper",
      "contractor"
    ],
    "wof:name": "Bonnie Beryl Anderson",
    "wof:placetype": "venue"
  },
  "geometry": {"coordinates":[-80.63872,41.071303],"type":"Point"}
}
