{
  "type": "Feature",
  "properties": {
    "addr:full": "1907 Cleveland Rd W Sandusky OH 44870",
    "addr:housenumber": "1907",
    "addr:postcode": "44870",
    "addr:street": "Cleveland Rd W",
    "iso:country": "US",
    "sg:address": "1907 Cleveland Rd W",
    "sg:city": "Sandusky",
    "sg:classifiers": [
      {
        "category": "Insurance",
        "subcategory": "Insurance Agent",
        "type": "Services"
      }
    ],
    "sg:phone": "+1 419 626 5673",
    "sg:postcode": "44870",
    "sg:province": "OH",
    "wof:name": "Valli Bail Bond Agency",
    "wof:placetype": "venue"
  },
  "geometry": {"coordinates":[-82.681379,41.441817],"type":"Point"}
}
