{
  "type": "Feature",
  "properties": {
    "addr:full": "91 N Main St Swanton OH 43558",
    "addr:housenumber": "91",
    "addr:postcode": "43558",
    "addr:street": "N Main St",
    "iso:country": "US",
    "sg:address": "91 N Main St",
    "sg:city": "Swanton",
    "sg:classifiers": [
      {
        "category": "Personal",
        "subcategory": "Barber",
        "type": "Services"
      }
    ],
    "sg:phone": "+1 419 826 4805",
    "sg:postcode": "43558",
    "sg:province": "OH",
    "wof:name": "Style Plus Barber Shop",
    "wof:placetype": "venue"
  },
  "geometry": {"coordinates":[-83.890915,41.588702],"type":"Point"}
}
