{
  "type": "Feature",
  "properties": {
    "addr:full": "5931 Linworth Rd Columbus OH 43085",
    "addr:housenumber": "5931",
    "addr:postcode": "43085",
    "addr:street": "Linworth Rd",
    "iso:country": "US",
    "sg:address": "5931 Linworth Rd",
    "sg:city": "Columbus",
    "sg:classifiers": [
      {
        "category": "Professional",
        "subcategory": "Management \u0026 Consulting",
        "type": "Services"
      }
    ],
    "sg:phone": "+1 614 255 5686",
    "sg:postcode": "43085",
    "sg:province": "OH",
    "sg:tags": [
      "loan",
      "broker"
    ],
    "wof:name": "Pomeroy Financial Planning",
    "wof:placetype": "venue"
  },
  "geometry": {"coordinates":[-83.049955,40.084855],"type":"Point"}
}
