{
  "type": "Feature",
  "properties": {
    "addr:full":"5265 Defiance Trl Delphos OH 45833",
    "addr:housenumber":"5265",
    "addr:postcode":"45833",
    "addr:street":"Defiance Trl",
    "iso:country":"US",
    "sg:address":"5265 Defiance Trl",
    "sg:city":"Delphos",
    "sg:phone":"+1 419 692 3102",
    "sg:postcode":"45833",
    "sg:province":"OH",
    "sg:tags":[
        "farm",
        "corn",
        "soybean"
    ],
    "wof:name":"Ed Ulrich",
    "wof:placetype":"venue"
},
  "geometry": {"coordinates":[-84.286248,40.82769],"type":"Point"}
}