{
  "type": "Feature",
  "properties": {
    "iso:country":"US",
    "sg:address":"16161 Northvale Blvd",
    "sg:city":"Cleveland",
    "sg:classifiers":[
        {
            "category":"Real Estate",
            "subcategory":"Real Estate Agent",
            "type":"Services"
        }
    ],
    "sg:phone":"+1 216 932 9226",
    "sg:postcode":"44112",
    "sg:province":"OH",
    "wof:name":"Techni Co Op Inc",
    "wof:placetype":"venue"
},
  "geometry": {"coordinates":[-81.565365,41.525559],"type":"Point"}
}