{
  "type": "Feature",
  "properties": {
    "addr:full":"2390 Baty Rd Elida OH 45807",
    "addr:postcode":"2390;45807",
    "addr:street":"Baty Rd",
    "iso:country":"US",
    "sg:address":"2390 Baty Rd",
    "sg:city":"Elida",
    "sg:classifiers":[
        {
            "category":"Retail",
            "subcategory":"Laundry & Dry Cleaning",
            "type":"Services"
        }
    ],
    "sg:phone":"+1 419 339 1915",
    "sg:postcode":"45807",
    "sg:province":"OH",
    "sg:tags":[
        "garment",
        "agent",
        "cleaners"
    ],
    "wof:name":"Shawnee Dry Cleaners Inc",
    "wof:placetype":"venue"
},
  "geometry": {"coordinates":[-84.18433899999999,40.770294],"type":"Point"}
}