{
  "type": "Feature",
  "properties": {
    "addr:full": "10130 Manore Rd Grand Rapids OH 43522",
    "addr:housenumber": "10130",
    "addr:postcode": "43522",
    "addr:street": "Manore Rd",
    "iso:country": "US",
    "sg:address": "10130 Manore Rd",
    "sg:city": "Grand Rapids",
    "sg:classifiers": [
      {
        "category": "Farming",
        "subcategory": "Farm",
        "type": "Manufacturing \u0026 Wholesale Goods"
      }
    ],
    "sg:phone": "+1 419 832 2705",
    "sg:postcode": "43522",
    "sg:province": "OH",
    "sg:tags": [
      "crop",
      "general"
    ],
    "wof:name": "Krohn Farms Inc",
    "wof:placetype": "venue"
  },
  "geometry": {"coordinates":[-83.864397,41.456342],"type":"Point"}
}
