{
  "type": "Feature",
  "properties": {
    "iso:country":"US",
    "sg:address":"10130 Manore Rd",
    "sg:city":"Grand Rapids",
    "sg:classifiers":[
        {
            "category":"Farming",
            "subcategory":"Farm",
            "type":"Manufacturing & Wholesale Goods"
        }
    ],
    "sg:phone":"+1 419 832 2705",
    "sg:postcode":"43522",
    "sg:province":"OH",
    "sg:tags":[
        "crop",
        "general"
    ],
    "wof:name":"Krohn Farms Inc",
    "wof:placetype":"venue"
},
  "geometry": {"coordinates":[-83.864397,41.456342],"type":"Point"}
}