{
  "type": "Feature",
  "properties": {
    "addr:full":"4771 Lock 14 Rd St Marys OH 45885",
    "addr:housenumber":"4771;14",
    "addr:postcode":"45885",
    "addr:street":"Lock;Rd",
    "iso:country":"US",
    "sg:address":"4771 Lock 14 Rd",
    "sg:city":"St Marys",
    "sg:classifiers":[
        {
            "category":"Shopping",
            "subcategory":"Discount & Variety Stores",
            "type":"Retail Goods"
        }
    ],
    "sg:phone":"+1 419 394 4525",
    "sg:postcode":"45885",
    "sg:province":"OH",
    "sg:tags":[
        "merchandise",
        "general"
    ],
    "wof:name":"Newbauer Group",
    "wof:placetype":"venue"
},
  "geometry": {"coordinates":[-84.36505099999999,40.601024],"type":"Point"}
}