{
  "type": "Feature",
  "properties": {
    "iso:country":"US",
    "sg:address":"6705 Dillon Hills Dr",
    "sg:city":"Nashport",
    "sg:classifiers":[
        {
            "category":"Government",
            "subcategory":"Fire Station",
            "type":"Public Place"
        }
    ],
    "sg:phone":"+1 740 453 1888",
    "sg:postcode":"43830",
    "sg:province":"OH",
    "sg:tags":[
        "protection"
    ],
    "wof:name":"Licking Township Emergency",
    "wof:placetype":"venue"
},
  "geometry": {"coordinates":[-82.11913,40.035147],"type":"Point"}
}