{
  "type": "Feature",
  "properties": {
    "iso:country":"US",
    "sg:address":"7009 State Rte 49",
    "sg:city":"Celina",
    "sg:classifiers":[
        {
            "category":"Government",
            "subcategory":"Office",
            "type":"Public Place"
        }
    ],
    "sg:phone":"+1 419 942 1550",
    "sg:postcode":"45822",
    "sg:province":"OH",
    "wof:name":"Mercer County Dog Warden",
    "wof:placetype":"venue"
},
  "geometry": {"coordinates":[-84.784588,40.55324],"type":"Point"}
}