{
  "type": "Feature",
  "properties": {
    "addr:full":"3373 Wilkinson Dr Fairlawn OH 44333",
    "addr:housenumber":"3373",
    "addr:postcode":"44333",
    "addr:street":"Wilkinson Dr",
    "iso:country":"US",
    "sg:address":"3373 Wilkinson Dr",
    "sg:city":"Fairlawn",
    "sg:classifiers":[
        {
            "category":"Professional",
            "subcategory":"Employment Agencies",
            "type":"Services"
        }
    ],
    "sg:phone":"+1 330 666 0552",
    "sg:postcode":"44333",
    "sg:province":"OH",
    "sg:tags":[
        "opportunity"
    ],
    "wof:name":"Health Care Advantage",
    "wof:placetype":"venue"
},
  "geometry": {"coordinates":[-81.63383899999999,41.122607],"type":"Point"}
}