{
  "type": "Feature",
  "properties": {
    "addr:full": "6934 Middlebrook Blvd Cleveland OH 44130",
    "addr:housenumber": "6934",
    "addr:postcode": "44130",
    "addr:street": "Middlebrook Blvd",
    "iso:country": "US",
    "sg:address": "6934 Middlebrook Blvd",
    "sg:city": "Cleveland",
    "sg:classifiers": [
      {
        "category": "Building \u0026 Trades",
        "subcategory": "Cleaning \u0026 Sanitation",
        "type": "Services"
      }
    ],
    "sg:phone": "+1 216 676 6970",
    "sg:postcode": "44130",
    "sg:province": "OH",
    "sg:tags": [
      "snow",
      "removal"
    ],
    "wof:name": "Snow-B-Gone",
    "wof:placetype": "venue"
  },
  "geometry": {"coordinates":[-81.811224,41.37767],"type":"Point"}
}
