{
  "type": "Feature",
  "properties": {
    "addr:full": "2787 E Peterson Rd Troy OH 45373",
    "addr:housenumber": "2787",
    "addr:postcode": "45373",
    "addr:street": "E Peterson Rd",
    "iso:country": "US",
    "sg:address": "2787 E Peterson Rd",
    "sg:city": "Troy",
    "sg:classifiers": [
      {
        "category": "Health Services",
        "subcategory": "Clinic",
        "type": "Services"
      }
    ],
    "sg:phone": "+1 937 339 4185",
    "sg:postcode": "45373",
    "sg:province": "OH",
    "sg:tags": [
      "wellness",
      "program"
    ],
    "wof:name": "Health Education Svc",
    "wof:placetype": "venue"
  },
  "geometry": {"coordinates":[-84.146541,40.103479],"type":"Point"}
}
