{
  "type": "Feature",
  "properties": {
    "addr:full":"727 Elliott Ave Cincinnati OH 45215",
    "addr:housenumber":"727",
    "addr:postcode":"45215",
    "addr:street":"Elliott Ave",
    "iso:country":"US",
    "sg:address":"727 Elliott Ave",
    "sg:city":"Cincinnati",
    "sg:classifiers":[
        {
            "category":"Building & Trades",
            "subcategory":"Construction",
            "type":"Services"
        }
    ],
    "sg:phone":"+1 513 761 0403",
    "sg:postcode":"45215",
    "sg:province":"OH",
    "sg:tags":[
        "carpentry",
        "contractor"
    ],
    "wof:name":"Frank J Feldhaus & Son",
    "wof:placetype":"venue"
},
  "geometry": {"coordinates":[-84.450855,39.218185],"type":"Point"}
}