{
  "type": "Feature",
  "properties": {
    "addr:full":"7560 Colerain Ave Cincinnati OH 45239",
    "addr:postcode":"7560;45239",
    "addr:street":"Colerain Ave",
    "iso:country":"US",
    "sg:address":"7560 Colerain Ave",
    "sg:city":"Cincinnati",
    "sg:classifiers":[
        {
            "category":"Bars & Pubs",
            "type":"Food & Drink"
        }
    ],
    "sg:phone":"+1 513 522 0400",
    "sg:postcode":"45239",
    "sg:province":"OH",
    "sg:tags":[
        "drinking"
    ],
    "wof:name":"Groesbeck Tavern",
    "wof:placetype":"venue"
},
  "geometry": {"coordinates":[-84.58484799999999,39.213999],"type":"Point"}
}