{
  "type": "Feature",
  "properties": {
    "iso:country":"US",
    "sg:address":"198 Narrows Rd",
    "sg:city":"Rayland",
    "sg:classifiers":[
        {
            "category":"Shopping",
            "subcategory":"Clothing, Apparel, & Fashions",
            "type":"Retail Goods"
        }
    ],
    "sg:phone":"+1 740 859 2278",
    "sg:postcode":"43943",
    "sg:province":"OH",
    "sg:tags":[
        "alteration"
    ],
    "wof:name":"BBST Of Needles Wax & Wood",
    "wof:placetype":"venue"
},
  "geometry": {"coordinates":[-80.692123,40.18778],"type":"Point"}
}