{
  "type": "Feature",
  "properties": {
    "addr:full": "198 Narrows Rd Rayland OH 43943",
    "addr:housenumber": "198",
    "addr:postcode": "43943",
    "addr:street": "Narrows Rd",
    "iso:country": "US",
    "sg:address": "198 Narrows Rd",
    "sg:city": "Rayland",
    "sg:classifiers": [
      {
        "category": "Shopping",
        "subcategory": "Clothing, Apparel, \u0026 Fashions",
        "type": "Retail Goods"
      }
    ],
    "sg:phone": "+1 740 859 2278",
    "sg:postcode": "43943",
    "sg:province": "OH",
    "sg:tags": [
      "alteration"
    ],
    "wof:name": "BBST Of Needles Wax \u0026 Wood",
    "wof:placetype": "venue"
  },
  "geometry": {"coordinates":[-80.692123,40.18778],"type":"Point"}
}
