{
  "type": "Feature",
  "properties": {
    "addr:full": "7838 Links View Cir Westerville OH 43082",
    "addr:housenumber": "7838",
    "addr:postcode": "43082",
    "addr:street": "Links View Cir",
    "iso:country": "US",
    "sg:address": "7838 Links View Cir",
    "sg:city": "Westerville",
    "sg:classifiers": [
      {
        "category": "Wholesale",
        "subcategory": "Stationery",
        "type": "Manufacturing \u0026 Wholesale Goods"
      }
    ],
    "sg:phone": "+1 614 523 1350",
    "sg:postcode": "43082",
    "sg:province": "OH",
    "sg:tags": [
      "box",
      "fiber"
    ],
    "sg:website": "www.webco-pkg.com",
    "wof:name": "Webco Packaging Co",
    "wof:placetype": "venue"
  },
  "geometry": {"coordinates":[-82.898971,40.17772],"type":"Point"}
}
