{
  "type": "Feature",
  "properties": {
    "iso:country":"US",
    "sg:address":"7394 Market St",
    "sg:city":"Boardman",
    "sg:classifiers":[
        {
            "category":"Shopping",
            "subcategory":"Bicycles & Sporting Goods",
            "type":"Retail Goods"
        }
    ],
    "sg:phone":"+1 330 758 8090",
    "sg:postcode":"44512",
    "sg:province":"OH",
    "sg:tags":[
        "owner",
        "equipment",
        "exercise"
    ],
    "wof:name":"Cycle Sales Co",
    "wof:placetype":"venue"
},
  "geometry": {"coordinates":[-80.66279900000001,41.021076],"type":"Point"}
}