{
  "type": "Feature",
  "properties": {
    "addr:full": "494 W Aurora Rd Northfield OH 44067",
    "addr:housenumber": "494",
    "addr:postcode": "44067",
    "addr:street": "W Aurora Rd",
    "iso:country": "US",
    "sg:address": "494 W Aurora Rd",
    "sg:city": "Northfield",
    "sg:classifiers": [
      {
        "category": "Banks \u0026 Credit Unions",
        "subcategory": "Bank",
        "type": "Services"
      }
    ],
    "sg:phone": "+1 330 468 1600",
    "sg:postcode": "44067",
    "sg:province": "OH",
    "sg:tags": [
      "national",
      "commercial"
    ],
    "sg:website": "www.charterone.com",
    "wof:name": "Charter One Bank NA",
    "wof:placetype": "venue"
  },
  "geometry": {"coordinates":[-81.557172,41.314289],"type":"Point"}
}
