{
  "type": "Feature",
  "properties": {
    "addr:full":"9709 Montgomery Rd Cincinnati OH 45242",
    "addr:housenumber":"9709",
    "addr:postcode":"45242",
    "addr:street":"Montgomery Rd",
    "iso:country":"US",
    "sg:address":"9709 Montgomery Rd",
    "sg:city":"Cincinnati",
    "sg:classifiers":[
        {
            "category":"Health Services",
            "subcategory":"Chiropractor",
            "type":"Services"
        }
    ],
    "sg:phone":"+1 513 793 6104",
    "sg:postcode":"45242",
    "sg:province":"OH",
    "wof:name":"Advanced Chiropractic Rehab",
    "wof:placetype":"venue"
},
  "geometry": {"coordinates":[-84.352228,39.232032],"type":"Point"}
}