{
  "type": "Feature",
  "properties": {
    "addr:full": "4462 Denison Ave Cleveland OH 44109",
    "addr:housenumber": "4462",
    "addr:postcode": "44109",
    "addr:street": "Denison Ave",
    "iso:country": "US",
    "sg:address": "4462 Denison Ave",
    "sg:city": "Cleveland",
    "sg:classifiers": [
      {
        "category": "Freight",
        "type": "Transportation"
      }
    ],
    "sg:phone": "+1 216 351 3018",
    "sg:postcode": "44109",
    "sg:province": "OH",
    "sg:tags": [
      "consultant"
    ],
    "wof:name": "Horizon Freight Systems",
    "wof:placetype": "venue"
  },
  "geometry": {"coordinates":[-81.71593,41.452908],"type":"Point"}
}
