{
  "type": "Feature",
  "properties": {
    "addr:full": "1111 Saint Gregory St Cincinnati OH 45202",
    "addr:housenumber": "1111",
    "addr:postcode": "45202",
    "addr:street": "Saint Gregory St",
    "iso:country": "US",
    "sg:address": "1111 Saint Gregory St",
    "sg:city": "Cincinnati",
    "sg:classifiers": [
      {
        "category": "Shopping",
        "subcategory": "Jewelry",
        "type": "Retail Goods"
      }
    ],
    "sg:phone": "+1 513 381 8414",
    "sg:postcode": "45202",
    "sg:province": "OH",
    "sg:tags": [
      "jeweler"
    ],
    "wof:name": "Briani \u0026 Miotto Co",
    "wof:placetype": "venue"
  },
  "geometry": {"coordinates":[-84.497761,39.107969],"type":"Point"}
}
