{
  "type": "Feature",
  "properties": {
    "addr:full": "3513 Ivy Hill Cir Cortland OH 44410",
    "addr:housenumber": "3513",
    "addr:postcode": "44410",
    "addr:street": "Ivy Hill Cir",
    "iso:country": "US",
    "sg:address": "3513 Ivy Hill Cir",
    "sg:city": "Cortland",
    "sg:classifiers": [
      {
        "category": "Building \u0026 Trades",
        "subcategory": "Construction",
        "type": "Services"
      }
    ],
    "sg:phone": "+1 330 372 2137",
    "sg:postcode": "44410",
    "sg:province": "OH",
    "sg:tags": [
      "concrete",
      "commercial",
      "structure"
    ],
    "wof:name": "123 Concrete Inc",
    "wof:placetype": "venue"
  },
  "geometry": {"coordinates":[-80.758927,41.28839],"type":"Point"}
}
