{
  "type": "Feature",
  "properties": {
    "addr:full":"1185 Fergus Dr Dayton OH 45430",
    "addr:housenumber":"1185",
    "addr:postcode":"45430",
    "addr:street":"Fergus Dr",
    "iso:country":"US",
    "sg:address":"1185 Fergus Dr",
    "sg:city":"Dayton",
    "sg:classifiers":[
        {
            "category":"Manufacturing",
            "subcategory":"Food",
            "type":"Manufacturing & Wholesale Goods"
        }
    ],
    "sg:phone":"+1 937 320 1409",
    "sg:postcode":"45430",
    "sg:province":"OH",
    "sg:tags":[
        "product",
        "retail",
        "bakery",
        "mfg"
    ],
    "wof:name":"Countryside Cafe & Doughnuts",
    "wof:placetype":"venue"
},
  "geometry": {"coordinates":[-84.076442,39.722231],"type":"Point"}
}