{
  "type": "Feature",
  "properties": {
    "addr:full": "235 Selma Rd Springfield OH 45505",
    "addr:housenumber": "235",
    "addr:postcode": "45505",
    "addr:street": "Selma Rd",
    "iso:country": "US",
    "sg:address": "235 Selma Rd",
    "sg:city": "Springfield",
    "sg:classifiers": [
      {
        "category": "Food \u0026 Beverages",
        "subcategory": "Fruits \u0026 Vegetables",
        "type": "Retail Goods"
      }
    ],
    "sg:phone": "+1 937 325 2602",
    "sg:postcode": "45505",
    "sg:province": "OH",
    "wof:name": "Selma Road Fruit Market",
    "wof:placetype": "venue"
  },
  "geometry": {"coordinates":[-83.806938,39.91723],"type":"Point"}
}
