{
  "type": "Feature",
  "properties": {
    "addr:full":"61233 Southgate Rd Cambridge OH 43725",
    "addr:housenumber":"61233",
    "addr:postcode":"43725",
    "addr:street":"Southgate Rd",
    "iso:country":"US",
    "sg:address":"61233 Southgate Rd",
    "sg:city":"Cambridge",
    "sg:classifiers":[
        {
            "category":"Real Estate",
            "subcategory":"Real Estate Agent",
            "type":"Services"
        }
    ],
    "sg:phone":"+1 740 439 2400",
    "sg:postcode":"43725",
    "sg:province":"OH",
    "wof:name":"Bonnie Czigans Expert Realtors",
    "wof:placetype":"venue"
},
  "geometry": {"coordinates":[-81.574062,39.987513],"type":"Point"}
}