{
  "type": "Feature",
  "properties": {
    "addr:full": "25776 Flory Rd Defiance OH 43512",
    "addr:postcode": "25776;43512",
    "addr:street": "Flory Rd",
    "iso:country": "US",
    "sg:address": "25776 Flory Rd",
    "sg:city": "Defiance",
    "sg:phone": "+1 419 497 3937",
    "sg:postcode": "43512",
    "sg:province": "OH",
    "sg:tags": [
      "farm",
      "grain",
      "cash"
    ],
    "wof:name": "Charles Hornish",
    "wof:placetype": "venue"
  },
  "geometry": {"coordinates":[-84.32971,41.340469],"type":"Point"}
}
