{
  "type": "Feature",
  "properties": {
    "addr:full": "6920 Upper Valley Rd Dayton OH 45424",
    "addr:housenumber": "6920",
    "addr:postcode": "45424",
    "addr:street": "Upper Valley Rd",
    "iso:country": "US",
    "sg:address": "6920 Upper Valley Rd",
    "sg:city": "Dayton",
    "sg:classifiers": [
      {
        "category": "Freight",
        "type": "Transportation"
      }
    ],
    "sg:phone": "+1 937 873 9227",
    "sg:postcode": "45424",
    "sg:province": "OH",
    "sg:tags": [
      "mover"
    ],
    "wof:name": "Orbit Movers \u0026 Erectors",
    "wof:placetype": "venue"
  },
  "geometry": {"coordinates":[-84.061543,39.829144],"type":"Point"}
}
