{
  "type": "Feature",
  "properties": {
    "addr:full": "40 Wyoming St Dayton OH 45409",
    "addr:housenumber": "40",
    "addr:postcode": "45409",
    "addr:street": "Wyoming St",
    "iso:country": "US",
    "sg:address": "40 Wyoming St",
    "sg:city": "Dayton",
    "sg:classifiers": [
      {
        "category": "Organizations",
        "subcategory": "Membership Organization",
        "type": "Services"
      }
    ],
    "sg:phone": "+1 937 223 8223",
    "sg:postcode": "45409",
    "sg:province": "OH",
    "sg:tags": [
      "hospital",
      "general"
    ],
    "sg:website": "www.lifeconnectionofohio.org",
    "wof:name": "Life Connection Of Ohio",
    "wof:placetype": "venue"
  },
  "geometry": {"coordinates":[-84.185136,39.744433],"type":"Point"}
}
