{
  "type": "Feature",
  "properties": {
    "iso:country":"US",
    "sg:address":"5067 Turney Rd",
    "sg:city":"Cleveland",
    "sg:classifiers":[
        {
            "category":"Retail",
            "subcategory":"Car Wash",
            "type":"Services"
        }
    ],
    "sg:phone":"+1 216 587 1800",
    "sg:postcode":"44125",
    "sg:province":"OH",
    "sg:tags":[
        "polishing",
        "washing"
    ],
    "wof:name":"Mr P's Car Wash",
    "wof:placetype":"venue"
},
  "geometry": {"coordinates":[-81.610563,41.423528],"type":"Point"}
}