{
  "type": "Feature",
  "properties": {
    "iso:country":"US",
    "sg:address":"2930 Edison St NW",
    "sg:city":"Uniontown",
    "sg:classifiers":[
        {
            "category":"Utilities",
            "subcategory":"Telephone",
            "type":"Services"
        }
    ],
    "sg:phone":"+1 330 699 5699",
    "sg:postcode":"44685",
    "sg:province":"OH",
    "sg:tags":[
        "distance",
        "company",
        "long",
        "access",
        "internet",
        "local"
    ],
    "wof:name":"Acction Communications",
    "wof:placetype":"venue"
},
  "geometry": {"coordinates":[-81.40039,40.97617],"type":"Point"}
}