{
  "type": "Feature",
  "properties": {
    "addr:full":"1 W Main St Mc Connelsville OH 43756",
    "addr:housenumber":"1",
    "addr:postcode":"43756",
    "addr:street":"W Main St",
    "iso:country":"US",
    "sg:address":"1 W Main St",
    "sg:city":"Mc Connelsville",
    "sg:classifiers":[
        {
            "category":"Insurance",
            "subcategory":"Insurance Agent",
            "type":"Services"
        }
    ],
    "sg:phone":"+1 740 962 2451",
    "sg:postcode":"43756",
    "sg:province":"OH",
    "wof:name":"Coulson Insurance",
    "wof:placetype":"venue"
},
  "geometry": {"coordinates":[-81.853914,39.648855],"type":"Point"}
}