{
  "type": "Feature",
  "properties": {
    "iso:country":"US",
    "sg:address":"5590 Ridgewood Rd E",
    "sg:city":"Springfield",
    "sg:classifiers":[
        {
            "category":"Shopping",
            "subcategory":"Gifts & Souvenirs",
            "type":"Retail Goods"
        }
    ],
    "sg:phone":"+1 937 399 8037",
    "sg:postcode":"45503",
    "sg:province":"OH",
    "wof:name":"Esther Belle Inc",
    "wof:placetype":"venue"
},
  "geometry": {"coordinates":[-83.77011299999999,40.002252],"type":"Point"}
}