{
  "type": "Feature",
  "properties": {
    "addr:full": "5590 Ridgewood Rd E Springfield OH 45503",
    "addr:housenumber": "5590",
    "addr:postcode": "45503",
    "addr:street": "Ridgewood Rd E",
    "iso:country": "US",
    "sg:address": "5590 Ridgewood Rd E",
    "sg:city": "Springfield",
    "sg:classifiers": [
      {
        "category": "Shopping",
        "subcategory": "Gifts \u0026 Souvenirs",
        "type": "Retail Goods"
      }
    ],
    "sg:phone": "+1 937 399 8037",
    "sg:postcode": "45503",
    "sg:province": "OH",
    "wof:name": "Esther Belle Inc",
    "wof:placetype": "venue"
  },
  "geometry": {"coordinates":[-83.770113,40.002252],"type":"Point"}
}
