{
  "type": "Feature",
  "properties": {
    "addr:full": "209 N Main St Delphos OH 45833",
    "addr:housenumber": "209",
    "addr:postcode": "45833",
    "addr:street": "N Main St",
    "iso:country": "US",
    "sg:address": "209 N Main St",
    "sg:city": "Delphos",
    "sg:classifiers": [
      {
        "category": "Restaurant",
        "type": "Food \u0026 Drink"
      }
    ],
    "sg:phone": "+1 419 692 7414",
    "sg:postcode": "45833",
    "sg:province": "OH",
    "wof:name": "Johnny A's Grill \u0026 Spirits",
    "wof:placetype": "venue"
  },
  "geometry": {"coordinates":[-84.339802,40.844918],"type":"Point"}
}
