{
  "type": "Feature",
  "properties": {
    "iso:country":"US",
    "sg:address":"12340 Bass Lake Rd",
    "sg:city":"Chardon",
    "sg:classifiers":[
        {
            "category":"Health Services",
            "subcategory":"Hospital",
            "type":"Services"
        }
    ],
    "sg:phone":"+1 440 285 4040",
    "sg:postcode":"44024",
    "sg:province":"OH",
    "sg:tags":[
        "rehabilitation"
    ],
    "wof:name":"Heather Hill Hlth & Care Hosp",
    "wof:placetype":"venue"
},
  "geometry": {"coordinates":[-81.21669300000001,41.530415],"type":"Point"}
}