{
  "type": "Feature",
  "properties": {
    "iso:country":"US",
    "sg:address":"7936 Scioto-Darby Rd",
    "sg:city":"Orient",
    "sg:classifiers":[
        {
            "category":"Building & Trades",
            "subcategory":"Construction",
            "type":"Services"
        }
    ],
    "sg:phone":"+1 614 877 0060",
    "sg:postcode":"43146",
    "sg:province":"OH",
    "sg:tags":[
        "contractor"
    ],
    "wof:name":"S M Clay Contracting",
    "wof:placetype":"venue"
},
  "geometry": {"coordinates":[-83.083058,39.763191],"type":"Point"}
}