{
  "type": "Feature",
  "properties": {
    "addr:full":"170 Bowen St Logan OH 43138",
    "addr:housenumber":"170",
    "addr:postcode":"43138",
    "addr:street":"Bowen St",
    "iso:country":"US",
    "sg:address":"170 Bowen St",
    "sg:city":"Logan",
    "sg:classifiers":[
        {
            "category":"Restaurant",
            "type":"Food & Drink"
        }
    ],
    "sg:phone":"+1 740 385 4894",
    "sg:postcode":"43138",
    "sg:province":"OH",
    "wof:name":"Wendys",
    "wof:placetype":"venue"
},
  "geometry": {"coordinates":[-82.406488,39.536986],"type":"Point"}
}