{
  "type": "Feature",
  "properties": {
    "addr:full": "4526 Weiner Ln Cincinnati OH 45244",
    "addr:housenumber": "4526",
    "addr:postcode": "45244",
    "addr:street": "Weiner Ln",
    "iso:country": "US",
    "sg:address": "4526 Weiner Ln",
    "sg:city": "Cincinnati",
    "sg:classifiers": [
      {
        "category": "Retail",
        "subcategory": "Animal Services",
        "type": "Services"
      }
    ],
    "sg:phone": "+1 513 528 0382",
    "sg:postcode": "45244",
    "sg:province": "OH",
    "sg:tags": [
      "boarding",
      "grooming",
      "dog",
      "kennel",
      "cat"
    ],
    "sg:website": "www.blueridgekennel.com",
    "wof:name": "Blue Ridge Kennel Ltd",
    "wof:placetype": "venue"
  },
  "geometry": {"coordinates":[-84.302696,39.105457],"type":"Point"}
}
