{
  "type": "Feature",
  "properties": {
    "iso:country":"US",
    "sg:address":"1422 E Livingston Ave",
    "sg:city":"Columbus",
    "sg:classifiers":[
        {
            "category":"Shopping",
            "subcategory":"Pharmacy",
            "type":"Retail Goods"
        }
    ],
    "sg:phone":"+1 614 258 1991",
    "sg:postcode":"43205",
    "sg:province":"OH",
    "sg:tags":[
        "proprietary",
        "drug",
        "store"
    ],
    "wof:name":"Dollar Dealz Beauty Supply Inc",
    "wof:placetype":"venue"
},
  "geometry": {"coordinates":[-82.960776,39.949231],"type":"Point"}
}