{
  "type": "Feature",
  "properties": {
    "iso:country":"US",
    "sg:address":"24067 W River Rd",
    "sg:city":"Perrysburg",
    "sg:classifiers":[
        {
            "category":"Wholesale",
            "subcategory":"Farm Supplies",
            "type":"Manufacturing & Wholesale Goods"
        }
    ],
    "sg:phone":"+1 419 878 0529",
    "sg:postcode":"43551",
    "sg:province":"OH",
    "sg:tags":[
        "livestock"
    ],
    "wof:name":"Riverstone Farm LLC",
    "wof:placetype":"venue"
},
  "geometry": {"coordinates":[-83.700485,41.5236],"type":"Point"}
}