{
  "type": "Feature",
  "properties": {
    "addr:full": "24067 W River Rd Perrysburg OH 43551",
    "addr:housenumber": "24067",
    "addr:postcode": "43551",
    "addr:street": "W River Rd",
    "iso:country": "US",
    "sg:address": "24067 W River Rd",
    "sg:city": "Perrysburg",
    "sg:classifiers": [
      {
        "category": "Wholesale",
        "subcategory": "Farm Supplies",
        "type": "Manufacturing \u0026 Wholesale Goods"
      }
    ],
    "sg:phone": "+1 419 878 0529",
    "sg:postcode": "43551",
    "sg:province": "OH",
    "sg:tags": [
      "livestock"
    ],
    "wof:name": "Riverstone Farm LLC",
    "wof:placetype": "venue"
  },
  "geometry": {"coordinates":[-83.700485,41.5236],"type":"Point"}
}
