{
  "type": "Feature",
  "properties": {
    "iso:country":"US",
    "sg:address":"600 Hampton Woods Dr",
    "sg:city":"Marion",
    "sg:classifiers":[
        {
            "category":"Real Estate",
            "subcategory":"Real Estate Operator",
            "type":"Services"
        }
    ],
    "sg:phone":"+1 740 389 3064",
    "sg:postcode":"43302",
    "sg:province":"OH",
    "sg:tags":[
        "condominium"
    ],
    "wof:name":"Villas Of Hampton Woods",
    "wof:placetype":"venue"
},
  "geometry": {"coordinates":[-83.10449699999999,40.564596],"type":"Point"}
}