{
  "type": "Feature",
  "properties": {
    "addr:full": "4900 Neo Pkwy Cleveland OH 44128",
    "addr:postcode": "4900;44128",
    "addr:street": "Neo Pkwy",
    "iso:country": "US",
    "sg:address": "4900 Neo Pkwy",
    "sg:city": "Cleveland",
    "sg:classifiers": [
      {
        "category": "Building \u0026 Trades",
        "subcategory": "Construction",
        "type": "Services"
      }
    ],
    "sg:phone": "+1 216 663 4600",
    "sg:postcode": "44128",
    "sg:province": "OH",
    "sg:tags": [
      "general",
      "contractor"
    ],
    "wof:name": "Nowak Construction Corp",
    "wof:placetype": "venue"
  },
  "geometry": {"coordinates":[-81.573264,41.425157],"type":"Point"}
}
