{
  "type": "Feature",
  "properties": {
    "iso:country":"US",
    "sg:address":"1060 W Main St",
    "sg:city":"Ravenna",
    "sg:classifiers":[
        {
            "category":"Banks & Credit Unions",
            "subcategory":"Bank",
            "type":"Services"
        }
    ],
    "sg:phone":"+1 330 296 0300",
    "sg:postcode":"44266",
    "sg:province":"OH",
    "sg:tags":[
        "cashing",
        "check"
    ],
    "wof:name":"American Payroll Advance",
    "wof:placetype":"venue"
},
  "geometry": {"coordinates":[-81.261466,41.158447],"type":"Point"}
}