{
  "type": "Feature",
  "properties": {
    "addr:full": "715 Kingsbury St Maumee OH 43537",
    "addr:housenumber": "715",
    "addr:postcode": "43537",
    "addr:street": "Kingsbury St",
    "iso:country": "US",
    "sg:address": "715 Kingsbury St",
    "sg:city": "Maumee",
    "sg:classifiers": [
      {
        "category": "Real Estate",
        "subcategory": "Real Estate Agent",
        "type": "Services"
      }
    ],
    "sg:phone": "+1 419 887 1561",
    "sg:postcode": "43537",
    "sg:province": "OH",
    "wof:name": "J A Morrin Realty Inc",
    "wof:placetype": "venue"
  },
  "geometry": {"coordinates":[-83.66129,41.564776],"type":"Point"}
}
