{
  "type": "Feature",
  "properties": {
    "addr:full":"7380 Skyland Ct Blacklick OH 43004",
    "addr:housenumber":"7380",
    "addr:postcode":"43004",
    "addr:street":"Skyland Ct",
    "iso:country":"US",
    "sg:address":"7380 Skyland Ct",
    "sg:city":"Blacklick",
    "sg:classifiers":[
        {
            "category":"Building & Trades",
            "subcategory":"Construction",
            "type":"Services"
        }
    ],
    "sg:phone":"+1 614 575 8112",
    "sg:postcode":"43004",
    "sg:province":"OH",
    "sg:tags":[
        "house",
        "engineering"
    ],
    "wof:name":"Integrate Prof Cnstr Serv",
    "wof:placetype":"venue"
},
  "geometry": {"coordinates":[-82.815443,40.015326],"type":"Point"}
}