{
  "type": "Feature",
  "properties": {
    "iso:country":"US",
    "sg:address":"1330 Plainfield Rd",
    "sg:city":"Cleveland",
    "sg:classifiers":[
        {
            "category":"Building & Trades",
            "subcategory":"Construction",
            "type":"Services"
        }
    ],
    "sg:phone":"+1 216 382 3264",
    "sg:postcode":"44121",
    "sg:province":"OH",
    "sg:tags":[
        "house"
    ],
    "wof:name":"Mj Improvements LLC",
    "wof:placetype":"venue"
},
  "geometry": {"coordinates":[-81.534402,41.523431],"type":"Point"}
}