{
  "type": "Feature",
  "properties": {
    "iso:country":"US",
    "sg:address":"343 W 1st Ave",
    "sg:city":"Columbus",
    "sg:classifiers":[
        {
            "category":"Building & Trades",
            "subcategory":"Construction",
            "type":"Services"
        }
    ],
    "sg:phone":"+1 614 559 3899",
    "sg:postcode":"43201",
    "sg:province":"OH",
    "sg:tags":[
        "painter"
    ],
    "wof:name":"Kmb Homevisions",
    "wof:placetype":"venue"
},
  "geometry": {"coordinates":[-83.013893,39.980417],"type":"Point"}
}