{
  "type": "Feature",
  "properties": {
    "addr:full":"4365 Lisa Dr Tipp City OH 45371",
    "addr:housenumber":"4365",
    "addr:postcode":"45371",
    "addr:street":"Lisa Dr",
    "iso:country":"US",
    "sg:address":"4365 Lisa Dr",
    "sg:city":"Tipp City",
    "sg:classifiers":[
        {
            "category":"Manufacturing",
            "subcategory":"Apparel",
            "type":"Manufacturing & Wholesale Goods"
        }
    ],
    "sg:phone":"+1 937 667 7756",
    "sg:postcode":"45371",
    "sg:province":"OH",
    "sg:tags":[
        "accessory"
    ],
    "sg:website":"www.aegeanapparel.com",
    "wof:name":"Aegean Apparrel",
    "wof:placetype":"venue"
},
  "geometry": {"coordinates":[-84.14105600000001,39.889084],"type":"Point"}
}