{
  "type": "Feature",
  "properties": {
    "addr:full":"20 Crozier Ct Granville OH 43023",
    "addr:housenumber":"20",
    "addr:postcode":"43023",
    "addr:street":"Crozier Ct",
    "iso:country":"US",
    "sg:address":"20 Crozier Ct",
    "sg:city":"Granville",
    "sg:classifiers":[
        {
            "category":"Building & Trades",
            "subcategory":"Cleaning & Sanitation",
            "type":"Services"
        }
    ],
    "sg:phone":"+1 740 587 3980",
    "sg:postcode":"43023",
    "sg:province":"OH",
    "sg:tags":[
        "fireplace",
        "chimney"
    ],
    "wof:name":"Kleen Sweep",
    "wof:placetype":"venue"
},
  "geometry": {"coordinates":[-82.505067,40.086041],"type":"Point"}
}