{
  "type": "Feature",
  "properties": {
    "iso:country":"US",
    "sg:address":"616 Orville St",
    "sg:city":"Fairborn",
    "sg:classifiers":[
        {
            "category":"Organizations",
            "subcategory":"Labor Organization",
            "type":"Services"
        }
    ],
    "sg:phone":"+1 937 879 3398",
    "sg:postcode":"45324",
    "sg:province":"OH",
    "wof:name":"Fairborn Fire Fighters Assn",
    "wof:placetype":"venue"
},
  "geometry": {"coordinates":[-84.041693,39.792687],"type":"Point"}
}