{
  "type": "Feature",
  "properties": {
    "addr:full": "104 Montrose Ave Delaware OH 43015",
    "addr:housenumber": "104",
    "addr:postcode": "43015",
    "addr:street": "Montrose Ave",
    "iso:country": "US",
    "sg:address": "104 Montrose Ave",
    "sg:city": "Delaware",
    "sg:classifiers": [
      {
        "category": "Shopping",
        "subcategory": "Bicycles \u0026 Sporting Goods",
        "type": "Retail Goods"
      }
    ],
    "sg:phone": "+1 740 363 4926",
    "sg:postcode": "43015",
    "sg:province": "OH",
    "wof:name": "Red Mountain Press",
    "wof:placetype": "venue"
  },
  "geometry": {"coordinates":[-83.079511,40.297145],"type":"Point"}
}
