{
  "type": "Feature",
  "properties": {
    "addr:full":"10775 Mahoning Ave North Jackson OH 44451",
    "addr:housenumber":"10775",
    "addr:postcode":"44451",
    "addr:street":"Mahoning Ave North",
    "iso:country":"US",
    "sg:address":"10775 Mahoning Ave",
    "sg:city":"North Jackson",
    "sg:classifiers":[
        {
            "category":"Education",
            "subcategory":"Library",
            "type":"Public Place"
        }
    ],
    "sg:phone":"+1 330 538 2455",
    "sg:postcode":"44451",
    "sg:province":"OH",
    "wof:name":"North Jackson Library",
    "wof:placetype":"venue"
},
  "geometry": {"coordinates":[-80.85358600000001,41.100087],"type":"Point"}
}