{
  "type": "Feature",
  "properties": {
    "iso:country":"US",
    "sg:address":"1572 Mentor Ave",
    "sg:city":"Painesville",
    "sg:classifiers":[
        {
            "category":"Retail",
            "subcategory":"Auto Repair",
            "type":"Services"
        }
    ],
    "sg:phone":"+1 440 352 1998",
    "sg:postcode":"44077",
    "sg:province":"OH",
    "sg:tags":[
        "general"
    ],
    "wof:name":"Lube Stop Inc",
    "wof:placetype":"venue"
},
  "geometry": {"coordinates":[-81.27909699999999,41.698122],"type":"Point"}
}