{
  "type": "Feature",
  "properties": {
    "addr:full":"2510 Consaul St Toledo OH 43605",
    "addr:housenumber":"2510",
    "addr:postcode":"43605",
    "addr:street":"Consaul St",
    "iso:country":"US",
    "sg:address":"2510 Consaul St",
    "sg:city":"Toledo",
    "sg:classifiers":[
        {
            "category":"Real Estate",
            "subcategory":"Real Estate Operator",
            "type":"Services"
        }
    ],
    "sg:phone":"+1 419 691 7266",
    "sg:postcode":"43605",
    "sg:province":"OH",
    "sg:tags":[
        "mobile",
        "home",
        "community"
    ],
    "wof:name":"Ridgewood Community",
    "wof:placetype":"venue"
},
  "geometry": {"coordinates":[-83.48873,41.658428],"type":"Point"}
}