{
  "type": "Feature",
  "properties": {
    "iso:country":"US",
    "sg:address":"7177 County Line Rd",
    "sg:city":"Hubbard",
    "sg:classifiers":[
        {
            "category":"Shopping",
            "subcategory":"Computers & Home Electronics",
            "type":"Retail Goods"
        },
        {
            "category":"Shopping",
            "subcategory":"Musical Instruments",
            "type":"Retail Goods"
        }
    ],
    "sg:phone":"+1 330 534 5951",
    "sg:postcode":"44425",
    "sg:province":"OH",
    "sg:tags":[
        "music",
        "pro",
        "installation",
        "sales"
    ],
    "wof:name":"Tonetronix",
    "wof:placetype":"venue"
},
  "geometry": {"coordinates":[-80.55255699999999,41.133396],"type":"Point"}
}