{
  "type": "Feature",
  "properties": {
    "addr:full": "34565 Lakeview Dr Solon OH 44139",
    "addr:housenumber": "34565",
    "addr:postcode": "44139",
    "addr:street": "Lakeview Dr",
    "iso:country": "US",
    "sg:address": "34565 Lakeview Dr",
    "sg:city": "Solon",
    "sg:classifiers": [
      {
        "category": "Real Estate",
        "subcategory": "Real Estate Agent",
        "type": "Services"
      }
    ],
    "sg:phone": "+1 440 248 2527",
    "sg:postcode": "44139",
    "sg:province": "OH",
    "wof:name": "Mignogna \u0026 Associates Inc",
    "wof:placetype": "venue"
  },
  "geometry": {"coordinates":[-81.430776,41.400286],"type":"Point"}
}
