{
  "type": "Feature",
  "properties": {
    "iso:country":"US",
    "sg:address":"34565 Lakeview Dr",
    "sg:city":"Solon",
    "sg:classifiers":[
        {
            "category":"Real Estate",
            "subcategory":"Real Estate Agent",
            "type":"Services"
        }
    ],
    "sg:phone":"+1 440 248 2527",
    "sg:postcode":"44139",
    "sg:province":"OH",
    "wof:name":"Mignogna & Associates Inc",
    "wof:placetype":"venue"
},
  "geometry": {"coordinates":[-81.43077599999999,41.400286],"type":"Point"}
}