{
  "type": "Feature",
  "properties": {
    "addr:full": "637 Franklin Ave Englewood OH 45322",
    "addr:housenumber": "637",
    "addr:postcode": "45322",
    "addr:street": "Franklin Ave",
    "iso:country": "US",
    "sg:address": "637 Franklin Ave",
    "sg:city": "Englewood",
    "sg:classifiers": [
      {
        "category": "Building \u0026 Trades",
        "subcategory": "Landscaping Services",
        "type": "Services"
      }
    ],
    "sg:phone": "+1 937 836 5598",
    "sg:postcode": "45322",
    "sg:province": "OH",
    "wof:name": "Tackett Tree Experts",
    "wof:placetype": "venue"
  },
  "geometry": {"coordinates":[-84.320826,39.902147],"type":"Point"}
}
