{
  "type": "Feature",
  "properties": {
    "addr:full":"854 Lehigh Ave Mansfield OH 44905",
    "addr:housenumber":"854",
    "addr:postcode":"44905",
    "addr:street":"Lehigh Ave",
    "iso:country":"US",
    "sg:address":"854 Lehigh Ave",
    "sg:city":"Mansfield",
    "sg:classifiers":[
        {
            "category":"Building & Trades",
            "subcategory":"Construction",
            "type":"Services"
        }
    ],
    "sg:phone":"+1 419 589 9153",
    "sg:postcode":"44905",
    "sg:province":"OH",
    "sg:tags":[
        "concrete",
        "contractor"
    ],
    "wof:name":"Fred Sowders",
    "wof:placetype":"venue"
},
  "geometry": {"coordinates":[-82.482501,40.77881],"type":"Point"}
}