{
  "type": "Feature",
  "properties": {
    "iso:country":"US",
    "sg:address":"405 E Vine St",
    "sg:city":"Mt Vernon",
    "sg:classifiers":[
        {
            "category":"Organizations",
            "subcategory":"Religious Organization",
            "type":"Services"
        }
    ],
    "sg:phone":"+1 740 393 2641",
    "sg:postcode":"43050",
    "sg:province":"OH",
    "sg:tags":[
        "clergy"
    ],
    "wof:name":"William R O'Hara",
    "wof:placetype":"venue"
},
  "geometry": {"coordinates":[-82.479012,40.392398],"type":"Point"}
}