{
  "type": "Feature",
  "properties": {
    "addr:full":"3783 Tanager Dr Gahanna OH 43230",
    "addr:housenumber":"3783",
    "addr:postcode":"43230",
    "addr:street":"Tanager Dr",
    "iso:country":"US",
    "sg:address":"3783 Tanager Dr",
    "sg:city":"Gahanna",
    "sg:classifiers":[
        {
            "category":"Manufacturing",
            "subcategory":"Printing",
            "type":"Manufacturing & Wholesale Goods"
        }
    ],
    "sg:phone":"+1 614 471 6309",
    "sg:postcode":"43230",
    "sg:province":"OH",
    "sg:tags":[
        "commercial"
    ],
    "wof:name":"Leffingwell's Classic Creation",
    "wof:placetype":"venue"
},
  "geometry": {"coordinates":[-82.91918699999999,40.069256],"type":"Point"}
}