{
  "type": "Feature",
  "properties": {
    "addr:full": "1120 E Stroop Rd Dayton OH 45429",
    "addr:housenumber": "1120",
    "addr:postcode": "45429",
    "addr:street": "E Stroop Rd",
    "iso:country": "US",
    "sg:address": "1120 E Stroop Rd",
    "sg:city": "Dayton",
    "sg:classifiers": [
      {
        "category": "Retail",
        "subcategory": "Laundry \u0026 Dry Cleaning",
        "type": "Services"
      }
    ],
    "sg:phone": "+1 937 296 1338",
    "sg:postcode": "45429",
    "sg:province": "OH",
    "sg:tags": [
      "cleaners"
    ],
    "wof:name": "Fine Cleaners",
    "wof:placetype": "venue"
  },
  "geometry": {"coordinates":[-84.14687,39.688762],"type":"Point"}
}
