{
  "type": "Feature",
  "properties": {
    "iso:country":"US",
    "sg:address":"1120 E Stroop Rd",
    "sg:city":"Dayton",
    "sg:classifiers":[
        {
            "category":"Retail",
            "subcategory":"Laundry & Dry Cleaning",
            "type":"Services"
        }
    ],
    "sg:phone":"+1 937 296 1338",
    "sg:postcode":"45429",
    "sg:province":"OH",
    "sg:tags":[
        "cleaners"
    ],
    "wof:name":"Fine Cleaners",
    "wof:placetype":"venue"
},
  "geometry": {"coordinates":[-84.14687000000001,39.688762],"type":"Point"}
}