{
  "type": "Feature",
  "properties": {
    "addr:full": "3739 Highview Ave SW Canton OH 44706",
    "addr:housenumber": "3739",
    "addr:postcode": "44706",
    "addr:street": "Highview Ave Sw",
    "iso:country": "US",
    "sg:address": "3739 Highview Ave SW",
    "sg:city": "Canton",
    "sg:classifiers": [
      {
        "category": "Shopping",
        "subcategory": "Hobbies, Toys, \u0026 Games",
        "type": "Retail Goods"
      }
    ],
    "sg:phone": "+1 330 484 0537",
    "sg:postcode": "44706",
    "sg:province": "OH",
    "wof:name": "Designs For Teen Dolls \u0026 Such",
    "wof:placetype": "venue"
  },
  "geometry": {"coordinates":[-81.380865,40.752853],"type":"Point"}
}
