{
  "type": "Feature",
  "properties": {
    "addr:full":"4501 Kenny Rd Columbus OH 43220",
    "addr:housenumber":"4501",
    "addr:postcode":"43220",
    "addr:street":"Kenny Rd",
    "iso:country":"US",
    "sg:address":"4501 Kenny Rd",
    "sg:city":"Columbus",
    "sg:classifiers":[
        {
            "category":"Personal",
            "subcategory":"Beauty Salon",
            "type":"Services"
        }
    ],
    "sg:phone":"+1 614 457 0769",
    "sg:postcode":"43220",
    "sg:province":"OH",
    "sg:tags":[
        "manicuring"
    ],
    "wof:name":"Tranz Nails",
    "wof:placetype":"venue"
},
  "geometry": {"coordinates":[-83.04964699999999,40.053052],"type":"Point"}
}