{
  "type": "Feature",
  "properties": {
    "addr:full": "6239 Stocksdale Rd Union City OH 45390",
    "addr:housenumber": "6239",
    "addr:postcode": "45390",
    "addr:street": "Stocksdale Rd",
    "iso:country": "US",
    "sg:address": "6239 Stocksdale Rd",
    "sg:city": "Union City",
    "sg:classifiers": [
      {
        "category": "Farming",
        "subcategory": "Farm",
        "type": "Manufacturing \u0026 Wholesale Goods"
      }
    ],
    "sg:phone": "+1 937 548 7557",
    "sg:postcode": "45390",
    "sg:province": "OH",
    "sg:tags": [
      "crop",
      "general"
    ],
    "wof:name": "Calvin Bowman Farm Inc",
    "wof:placetype": "venue"
  },
  "geometry": {"coordinates":[-84.803951,40.097349],"type":"Point"}
}
