{
  "type": "Feature",
  "properties": {
    "iso:country":"US",
    "sg:address":"6239 Stocksdale Rd",
    "sg:city":"Union City",
    "sg:classifiers":[
        {
            "category":"Farming",
            "subcategory":"Farm",
            "type":"Manufacturing & Wholesale Goods"
        }
    ],
    "sg:phone":"+1 937 548 7557",
    "sg:postcode":"45390",
    "sg:province":"OH",
    "sg:tags":[
        "crop",
        "general"
    ],
    "wof:name":"Calvin Bowman Farm Inc",
    "wof:placetype":"venue"
},
  "geometry": {"coordinates":[-84.803951,40.097349],"type":"Point"}
}