{
  "type": "Feature",
  "properties": {
    "addr:full": "1508 Hess St Columbus OH 43212",
    "addr:housenumber": "1508",
    "addr:postcode": "43212",
    "addr:street": "Hess St",
    "iso:country": "US",
    "sg:address": "1508 Hess St",
    "sg:city": "Columbus",
    "sg:classifiers": [
      {
        "category": "Shopping",
        "subcategory": "Clothing, Apparel, \u0026 Fashions",
        "type": "Retail Goods"
      }
    ],
    "sg:phone": "+1 614 261 7202",
    "sg:postcode": "43212",
    "sg:province": "OH",
    "sg:tags": [
      "family"
    ],
    "wof:name": "Ragorama",
    "wof:placetype": "venue"
  },
  "geometry": {"coordinates":[-83.031432,39.991011],"type":"Point"}
}
