{
  "type": "Feature",
  "properties": {
    "addr:full":"3525 Canfield Rd Youngstown OH 44511",
    "addr:housenumber":"3525",
    "addr:postcode":"44511",
    "addr:street":"Canfield Rd",
    "iso:country":"US",
    "sg:address":"3525 Canfield Rd",
    "sg:city":"Youngstown",
    "sg:classifiers":[
        {
            "category":"Banks & Credit Unions",
            "subcategory":"Bank",
            "type":"Services"
        }
    ],
    "sg:phone":"+1 330 792 7905",
    "sg:postcode":"44511",
    "sg:province":"OH",
    "wof:name":"Charter One Bank",
    "wof:placetype":"venue"
},
  "geometry": {"coordinates":[-80.70745599999999,41.063422],"type":"Point"}
}