{
  "type": "Feature",
  "properties": {
    "addr:full":"503 N Cable Rd Lima OH 45805",
    "addr:housenumber":"503",
    "addr:postcode":"45805",
    "addr:street":"N Cable Rd",
    "iso:country":"US",
    "sg:address":"503 N Cable Rd",
    "sg:city":"Lima",
    "sg:classifiers":[
        {
            "category":"Education",
            "subcategory":"School",
            "type":"Public Place"
        }
    ],
    "sg:phone":"+1 419 998 2150",
    "sg:postcode":"45805",
    "sg:province":"OH",
    "sg:website":"www.limacityschools.org",
    "wof:name":"Lima West Middle School",
    "wof:placetype":"venue"
},
  "geometry": {"coordinates":[-84.147025,40.746573],"type":"Point"}
}