{
  "type": "Feature",
  "properties": {
    "iso:country":"US",
    "sg:address":"214 S Main St",
    "sg:city":"Swanton",
    "sg:classifiers":[
        {
            "category":"Arts & Performance",
            "subcategory":"Theater",
            "type":"Entertainment"
        }
    ],
    "sg:phone":"+1 419 461 1692",
    "sg:postcode":"43558",
    "sg:province":"OH",
    "sg:tags":[
        "clown"
    ],
    "wof:name":"A-1 Happy The Clown",
    "wof:placetype":"venue"
},
  "geometry": {"coordinates":[-83.88968,41.58682],"type":"Point"}
}