{
  "type": "Feature",
  "properties": {
    "addr:full":"22180 Industrial Park Dr Genoa OH 43430",
    "addr:housenumber":"22180",
    "addr:postcode":"43430",
    "addr:street":"Industrial Park Dr",
    "iso:country":"US",
    "sg:address":"22180 Industrial Park Dr",
    "sg:city":"Genoa",
    "sg:classifiers":[
        {
            "category":"Manufacturing",
            "subcategory":"Metals",
            "type":"Manufacturing & Wholesale Goods"
        }
    ],
    "sg:phone":"+1 419 855 4301",
    "sg:postcode":"43430",
    "sg:province":"OH",
    "sg:tags":[
        "product",
        "wire",
        "fabricated"
    ],
    "wof:name":"Superior Wire & Metal Spec",
    "wof:placetype":"venue"
},
  "geometry": {"coordinates":[-83.366111,41.507553],"type":"Point"}
}