{
  "type": "Feature",
  "properties": {
    "iso:country":"US",
    "sg:address":"10101 Arborwood Dr",
    "sg:city":"Cincinnati",
    "sg:classifiers":[
        {
            "category":"Real Estate",
            "subcategory":"Real Estate Operator",
            "type":"Services"
        }
    ],
    "sg:phone":"+1 513 385 3752",
    "sg:postcode":"45251",
    "sg:province":"OH",
    "sg:tags":[
        "building",
        "apartment"
    ],
    "wof:name":"Northgate Meadows",
    "wof:placetype":"venue"
},
  "geometry": {"coordinates":[-84.58844499999999,39.253857],"type":"Point"}
}