{
  "type": "Feature",
  "properties": {
    "iso:country":"US",
    "sg:address":"851 2nd St",
    "sg:city":"Perrysburg",
    "sg:classifiers":[
        {
            "category":"Wholesale",
            "subcategory":"Non-durable Goods",
            "type":"Manufacturing & Wholesale Goods"
        }
    ],
    "sg:phone":"+1 419 824 2468",
    "sg:postcode":"43551",
    "sg:province":"OH",
    "wof:name":"CDI International Inc",
    "wof:placetype":"venue"
},
  "geometry": {"coordinates":[-83.547314,41.58892],"type":"Point"}
}