{
  "type": "Feature",
  "properties": {
    "iso:country":"US",
    "sg:address":"4175 Portobello Dr",
    "sg:city":"Gahanna",
    "sg:classifiers":[
        {
            "category":"Personal",
            "type":"Services"
        }
    ],
    "sg:phone":"+1 614 337 1645",
    "sg:postcode":"43230",
    "sg:province":"OH",
    "sg:tags":[
        "control",
        "weight"
    ],
    "wof:name":"Herbalife Distributor",
    "wof:placetype":"venue"
},
  "geometry": {"coordinates":[-82.903834,40.0623],"type":"Point"}
}