{
  "type": "Feature",
  "properties": {
    "addr:full": "13600 Deise Ave Cleveland OH 44110",
    "addr:postcode": "13600;44110",
    "addr:street": "Deise Ave",
    "iso:country": "US",
    "sg:address": "13600 Deise Ave",
    "sg:city": "Cleveland",
    "sg:classifiers": [
      {
        "category": "Communications",
        "subcategory": "Film \u0026 Video Production",
        "type": "Services"
      }
    ],
    "sg:phone": "+1 216 249 8900",
    "sg:postcode": "44110",
    "sg:province": "OH",
    "sg:tags": [
      "taping"
    ],
    "wof:name": "Prestige Production \u0026 Prestige",
    "wof:placetype": "venue"
  },
  "geometry": {"coordinates":[-81.585224,41.559883],"type":"Point"}
}
