{
  "type": "Feature",
  "properties": {
    "iso:country":"US",
    "sg:address":"13600 Deise Ave",
    "sg:city":"Cleveland",
    "sg:classifiers":[
        {
            "category":"Communications",
            "subcategory":"Film & Video Production",
            "type":"Services"
        }
    ],
    "sg:phone":"+1 216 249 8900",
    "sg:postcode":"44110",
    "sg:province":"OH",
    "sg:tags":[
        "taping"
    ],
    "wof:name":"Prestige Production & Prestige",
    "wof:placetype":"venue"
},
  "geometry": {"coordinates":[-81.585224,41.559883],"type":"Point"}
}