{
  "type": "Feature",
  "properties": {
    "addr:full": "14680 S Cheshire St Burton OH 44021",
    "addr:housenumber": "14680",
    "addr:postcode": "44021",
    "addr:street": "S Cheshire St",
    "iso:country": "US",
    "sg:address": "14680 S Cheshire St",
    "sg:city": "Burton",
    "sg:classifiers": [
      {
        "category": "Insurance",
        "subcategory": "Insurance Agent",
        "type": "Services"
      }
    ],
    "sg:phone": "+1 440 834 4344",
    "sg:postcode": "44021",
    "sg:province": "OH",
    "wof:name": "Prout \u0026 Assoc",
    "wof:placetype": "venue"
  },
  "geometry": {"coordinates":[-81.144991,41.464954],"type":"Point"}
}
