{
  "type": "Feature",
  "properties": {
    "iso:country":"US",
    "sg:address":"14680 S Cheshire St",
    "sg:city":"Burton",
    "sg:classifiers":[
        {
            "category":"Insurance",
            "subcategory":"Insurance Agent",
            "type":"Services"
        }
    ],
    "sg:phone":"+1 440 834 4344",
    "sg:postcode":"44021",
    "sg:province":"OH",
    "wof:name":"Prout & Assoc",
    "wof:placetype":"venue"
},
  "geometry": {"coordinates":[-81.144991,41.464954],"type":"Point"}
}