{
  "type": "Feature",
  "properties": {
    "addr:full": "1310 Fountaine Dr Upper Arlington OH 43221",
    "addr:housenumber": "1310",
    "addr:postcode": "43221",
    "addr:street": "Fountaine Dr",
    "iso:country": "US",
    "sg:address": "1310 Fountaine Dr",
    "sg:city": "Upper Arlington",
    "sg:classifiers": [
      {
        "category": "Professional",
        "subcategory": "Lawyer \u0026 Legal Services",
        "type": "Services"
      }
    ],
    "sg:phone": "+1 614 457 6991",
    "sg:postcode": "43221",
    "sg:province": "OH",
    "sg:tags": [
      "attorney"
    ],
    "wof:name": "Joseph H Yearling",
    "wof:placetype": "venue"
  },
  "geometry": {"coordinates":[-83.050517,40.029196],"type":"Point"}
}
