{
  "type": "Feature",
  "properties": {
    "addr:full": "7564 Tyler Blvd Mentor OH 44060",
    "addr:housenumber": "7564",
    "addr:postcode": "44060",
    "addr:street": "Tyler Blvd",
    "iso:country": "US",
    "sg:address": "7564 Tyler Blvd",
    "sg:city": "Mentor",
    "sg:classifiers": [
      {
        "category": "Manufacturing",
        "subcategory": "Metals",
        "type": "Manufacturing \u0026 Wholesale Goods"
      },
      {
        "category": "Manufacturing",
        "subcategory": "Tools \u0026 Machinery",
        "type": "Manufacturing \u0026 Wholesale Goods"
      }
    ],
    "sg:phone": "+1 440 946 6179",
    "sg:postcode": "44060",
    "sg:province": "OH",
    "sg:tags": [
      "production",
      "industrial",
      "grinding",
      "mfg"
    ],
    "wof:name": "Bob's Grinding Co Inc",
    "wof:placetype": "venue"
  },
  "geometry": {"coordinates":[-81.358839,41.679164],"type":"Point"}
}
