{
  "type": "Feature",
  "properties": {
    "iso:country":"US",
    "sg:address":"7564 Tyler Blvd",
    "sg:city":"Mentor",
    "sg:classifiers":[
        {
            "category":"Manufacturing",
            "subcategory":"Metals",
            "type":"Manufacturing & Wholesale Goods"
        },
        {
            "category":"Manufacturing",
            "subcategory":"Tools & Machinery",
            "type":"Manufacturing & Wholesale Goods"
        }
    ],
    "sg:phone":"+1 440 946 6179",
    "sg:postcode":"44060",
    "sg:province":"OH",
    "sg:tags":[
        "production",
        "industrial",
        "grinding",
        "mfg"
    ],
    "wof:name":"Bob's Grinding Co Inc",
    "wof:placetype":"venue"
},
  "geometry": {"coordinates":[-81.358839,41.679164],"type":"Point"}
}