{
  "type": "Feature",
  "properties": {
    "iso:country":"US",
    "sg:address":"6800 Caine Rd",
    "sg:city":"Columbus",
    "sg:classifiers":[
        {
            "category":"Personal",
            "subcategory":"Beauty Salon",
            "type":"Services"
        }
    ],
    "sg:phone":"+1 614 761 3600",
    "sg:postcode":"43235",
    "sg:province":"OH",
    "sg:tags":[
        "shop"
    ],
    "wof:name":"Details A Specialty Salon",
    "wof:placetype":"venue"
},
  "geometry": {"coordinates":[-83.08914799999999,40.10586],"type":"Point"}
}