{
  "type": "Feature",
  "properties": {
    "addr:full":"3304 Stones Throw Ave Poland OH 44514",
    "addr:housenumber":"3304",
    "addr:postcode":"44514",
    "addr:street":"Stones Throw Ave",
    "iso:country":"US",
    "sg:address":"3304 Stones Throw Ave",
    "sg:city":"Poland",
    "sg:classifiers":[
        {
            "category":"Health Services",
            "subcategory":"Doctor",
            "type":"Services"
        }
    ],
    "sg:phone":"+1 330 707 1115",
    "sg:postcode":"44514",
    "sg:province":"OH",
    "sg:tags":[
        "physician",
        "surgeon"
    ],
    "wof:name":"Sayed Yossef Inc",
    "wof:placetype":"venue"
},
  "geometry": {"coordinates":[-80.589186,41.024657],"type":"Point"}
}