{
  "type": "Feature",
  "properties": {
    "iso:country":"US",
    "sg:address":"5372 W 130th St",
    "sg:city":"Cleveland",
    "sg:classifiers":[
        {
            "category":"Manufacturing",
            "subcategory":"Metals",
            "type":"Manufacturing & Wholesale Goods"
        }
    ],
    "sg:phone":"+1 216 267 2550",
    "sg:postcode":"44142",
    "sg:province":"OH",
    "sg:tags":[
        "mfg",
        "material",
        "friction",
        "metallic"
    ],
    "wof:name":"Wellman Friction Products",
    "wof:placetype":"venue"
},
  "geometry": {"coordinates":[-81.783731,41.415717],"type":"Point"}
}