{
  "type": "Feature",
  "properties": {
    "addr:full": "1669 W 130th St Hinckley OH 44233",
    "addr:housenumber": "1669",
    "addr:postcode": "44233",
    "addr:street": "W 130Th St",
    "iso:country": "US",
    "sg:address": "1669 W 130th St",
    "sg:city": "Hinckley",
    "sg:classifiers": [
      {
        "category": "Wholesale",
        "subcategory": "Hardware",
        "type": "Manufacturing \u0026 Wholesale Goods"
      },
      {
        "category": "Building \u0026 Trades",
        "subcategory": "Plumbing",
        "type": "Services"
      }
    ],
    "sg:phone": "+1 330 220 1557",
    "sg:postcode": "44233",
    "sg:province": "OH",
    "sg:tags": [
      "heating",
      "air",
      "warm",
      "refrigeration",
      "conditioning",
      "refrigerating"
    ],
    "sg:website": "www.tempcontrolohio.com",
    "wof:name": "Temperature Control Maint",
    "wof:placetype": "venue"
  },
  "geometry": {"coordinates":[-81.784878,41.227261],"type":"Point"}
}
