{
  "type": "Feature",
  "properties": {
    "addr:full": "202 Lavender Ln Madison OH 44057",
    "addr:housenumber": "202",
    "addr:postcode": "44057",
    "addr:street": "Lavender Ln",
    "iso:country": "US",
    "sg:address": "202 Lavender Ln",
    "sg:city": "Madison",
    "sg:classifiers": [
      {
        "category": "Real Estate",
        "subcategory": "Real Estate Agent",
        "type": "Services"
      },
      {
        "category": "Building \u0026 Trades",
        "subcategory": "Construction",
        "type": "Services"
      }
    ],
    "sg:phone": "+1 440 428 8186",
    "sg:postcode": "44057",
    "sg:province": "OH",
    "sg:tags": [
      "contractor"
    ],
    "wof:name": "Sweet Brier Place",
    "wof:placetype": "venue"
  },
  "geometry": {"coordinates":[-81.051594,41.781155],"type":"Point"}
}
