{
  "type": "Feature",
  "properties": {
    "iso:country":"US",
    "sg:address":"10235 Colerain Ave",
    "sg:city":"Cincinnati",
    "sg:classifiers":[
        {
            "category":"Building & Trades",
            "subcategory":"Equipment Rental",
            "type":"Services"
        }
    ],
    "sg:phone":"+1 513 741 6800",
    "sg:postcode":"45251",
    "sg:province":"OH",
    "sg:tags":[
        "leasing"
    ],
    "wof:name":"Nationsrent Inc",
    "wof:placetype":"venue"
},
  "geometry": {"coordinates":[-84.602433,39.259311],"type":"Point"}
}