{
  "type": "Feature",
  "properties": {
    "iso:country":"US",
    "sg:address":"207 S Court St",
    "sg:city":"Medina",
    "sg:classifiers":[
        {
            "category":"Shopping",
            "subcategory":"Gifts & Souvenirs",
            "type":"Retail Goods"
        }
    ],
    "sg:phone":"+1 330 725 3559",
    "sg:postcode":"44256",
    "sg:province":"OH",
    "wof:name":"Accents",
    "wof:placetype":"venue"
},
  "geometry": {"coordinates":[-81.864068,41.137731],"type":"Point"}
}