{
  "type": "Feature",
  "properties": {
    "addr:full": "207 S Court St Medina OH 44256",
    "addr:housenumber": "207",
    "addr:postcode": "44256",
    "addr:street": "S Court St",
    "iso:country": "US",
    "sg:address": "207 S Court St",
    "sg:city": "Medina",
    "sg:classifiers": [
      {
        "category": "Shopping",
        "subcategory": "Gifts \u0026 Souvenirs",
        "type": "Retail Goods"
      }
    ],
    "sg:phone": "+1 330 725 3559",
    "sg:postcode": "44256",
    "sg:province": "OH",
    "wof:name": "Accents",
    "wof:placetype": "venue"
  },
  "geometry": {"coordinates":[-81.864068,41.137731],"type":"Point"}
}
