{
  "type": "Feature",
  "properties": {
    "addr:full":"30 Park St Berea OH 44017",
    "addr:housenumber":"30",
    "addr:postcode":"44017",
    "addr:street":"Park St",
    "iso:country":"US",
    "sg:address":"30 Park St",
    "sg:city":"Berea",
    "sg:classifiers":[
        {
            "category":"Building & Trades",
            "subcategory":"Construction",
            "type":"Services"
        }
    ],
    "sg:phone":"+1 440 239 3100",
    "sg:postcode":"44017",
    "sg:province":"OH",
    "sg:tags":[
        "resurfacing",
        "laying",
        "refinishing",
        "floor"
    ],
    "wof:name":"River Floors",
    "wof:placetype":"venue"
},
  "geometry": {"coordinates":[-81.854698,41.36767],"type":"Point"}
}