{
  "type": "Feature",
  "properties": {
    "addr:full": "11808 Hamilton Ave Cincinnati OH 45231",
    "addr:housenumber": "11808",
    "addr:postcode": "45231",
    "addr:street": "Hamilton Ave",
    "iso:country": "US",
    "sg:address": "11808 Hamilton Ave",
    "sg:city": "Cincinnati",
    "sg:classifiers": [
      {
        "category": "Retail",
        "subcategory": "Animal Services",
        "type": "Services"
      }
    ],
    "sg:phone": "+1 513 825 3153",
    "sg:postcode": "45231",
    "sg:province": "OH",
    "sg:tags": [
      "training",
      "dog"
    ],
    "wof:name": "Causby Angel",
    "wof:placetype": "venue"
  },
  "geometry": {"coordinates":[-84.563493,39.297359],"type":"Point"}
}
