{
  "type": "Feature",
  "properties": {
    "iso:country":"US",
    "sg:address":"207 S Walnut St",
    "sg:city":"Bryan",
    "sg:classifiers":[
        {
            "category":"Professional",
            "type":"Services"
        }
    ],
    "sg:phone":"+1 419 633 9229",
    "sg:postcode":"43506",
    "sg:province":"OH",
    "sg:tags":[
        "establishment"
    ],
    "wof:name":"Street Dreams",
    "wof:placetype":"venue"
},
  "geometry": {"coordinates":[-84.54962,41.473226],"type":"Point"}
}