{
  "type": "Feature",
  "properties": {
    "addr:full":"6960 Long Rd Canal Winchester OH 43110",
    "addr:housenumber":"6960",
    "addr:postcode":"43110",
    "addr:street":"Long Rd",
    "iso:country":"US",
    "sg:address":"6960 Long Rd",
    "sg:city":"Canal Winchester",
    "sg:classifiers":[
        {
            "category":"Home & Garden",
            "subcategory":"Carpets & Floor Coverings",
            "type":"Retail Goods"
        }
    ],
    "sg:phone":"+1 614 837 8597",
    "sg:postcode":"43110",
    "sg:province":"OH",
    "sg:tags":[
        "dealer",
        "rug"
    ],
    "wof:name":"Poor Old Peddlers Carpet Barn",
    "wof:placetype":"venue"
},
  "geometry": {"coordinates":[-82.817269,39.906883],"type":"Point"}
}