{
  "type": "Feature",
  "properties": {
    "addr:full":"228 Rainbow Ave Sunbury OH 43074",
    "addr:housenumber":"228",
    "addr:postcode":"43074",
    "addr:street":"Rainbow Ave",
    "iso:country":"US",
    "sg:address":"228 Rainbow Ave",
    "sg:city":"Sunbury",
    "sg:classifiers":[
        {
            "category":"Building & Trades",
            "subcategory":"Construction",
            "type":"Services"
        }
    ],
    "sg:phone":"+1 740 965 4292",
    "sg:postcode":"43074",
    "sg:province":"OH",
    "sg:tags":[
        "hanging",
        "contractor"
    ],
    "wof:name":"Kenney Painting",
    "wof:placetype":"venue"
},
  "geometry": {"coordinates":[-82.851955,40.246264],"type":"Point"}
}