{
  "type": "Feature",
  "properties": {
    "iso:country":"US",
    "sg:address":"7180 Center St",
    "sg:city":"Mentor",
    "sg:classifiers":[
        {
            "category":"Manufacturing",
            "subcategory":"Lumber",
            "type":"Manufacturing & Wholesale Goods"
        }
    ],
    "sg:phone":"+1 440 974 9663",
    "sg:postcode":"44060",
    "sg:province":"OH",
    "sg:website":"www.mentorlumber.com",
    "wof:name":"Mentor Lumber & Supply Co",
    "wof:placetype":"venue"
},
  "geometry": {"coordinates":[-81.339798,41.676449],"type":"Point"}
}