{
  "type": "Feature",
  "properties": {
    "addr:full": "1198 Lake Shore Blvd Akron OH 44301",
    "addr:housenumber": "1198",
    "addr:postcode": "44301",
    "addr:street": "Lake Shore Blvd",
    "iso:country": "US",
    "sg:address": "1198 Lake Shore Blvd",
    "sg:city": "Akron",
    "sg:classifiers": [
      {
        "category": "Building \u0026 Trades",
        "subcategory": "Construction",
        "type": "Services"
      }
    ],
    "sg:phone": "+1 330 376 3777",
    "sg:postcode": "44301",
    "sg:province": "OH",
    "sg:tags": [
      "fence",
      "contractor"
    ],
    "wof:name": "Affordable Patios \u0026 Walls",
    "wof:placetype": "venue"
  },
  "geometry": {"coordinates":[-81.541358,41.053657],"type":"Point"}
}
