{
  "type": "Feature",
  "properties": {
    "addr:full":"1453 Grandview Ave Columbus OH 43212",
    "addr:housenumber":"1453",
    "addr:postcode":"43212",
    "addr:street":"Grandview Ave",
    "iso:country":"US",
    "sg:address":"1453 Grandview Ave",
    "sg:city":"Columbus",
    "sg:classifiers":[
        {
            "category":"Restaurant",
            "type":"Food & Drink"
        }
    ],
    "sg:menulink":"http://www.allmenus.com/oh/columbus/19516-wg-grinders/menu/",
    "sg:phone":"+1 614 481 7700",
    "sg:postcode":"43212",
    "sg:province":"OH",
    "sg:tags":[
        "wrap",
        "american",
        "sandwich",
        "pizza"
    ],
    "wof:name":"W.G. Grinders",
    "wof:placetype":"venue"
},
  "geometry": {"coordinates":[-83.044532,39.987216],"type":"Point"}
}