{
  "type": "Feature",
  "properties": {
    "addr:full": "1534 Allentown Rd Lima OH 45805",
    "addr:housenumber": "1534",
    "addr:postcode": "45805",
    "addr:street": "Allentown Rd",
    "iso:country": "US",
    "sg:address": "1534 Allentown Rd",
    "sg:city": "Lima",
    "sg:classifiers": [
      {
        "category": "Shopping",
        "subcategory": "Florist",
        "type": "Retail Goods"
      }
    ],
    "sg:phone": "+1 419 991 4446",
    "sg:postcode": "45805",
    "sg:province": "OH",
    "sg:tags": [
      "shop",
      "flower"
    ],
    "wof:name": "Cottage Flower Shoppe",
    "wof:placetype": "venue"
  },
  "geometry": {"coordinates":[-84.132943,40.744847],"type":"Point"}
}
