{
  "type": "Feature",
  "properties": {
    "addr:full": "415 E Main St Columbus OH 43215",
    "addr:housenumber": "415",
    "addr:postcode": "43215",
    "addr:street": "E Main St",
    "iso:country": "US",
    "sg:address": "415 E Main St",
    "sg:city": "Columbus",
    "sg:classifiers": [
      {
        "category": "Real Estate",
        "subcategory": "Real Estate Agent",
        "type": "Services"
      },
      {
        "category": "Organizations",
        "subcategory": "Professional Association",
        "type": "Services"
      }
    ],
    "sg:phone": "+1 614 280 0899",
    "sg:postcode": "43215",
    "sg:province": "OH",
    "sg:website": "www.urbangrowth.org",
    "wof:name": "Columbus Urban Growth Corp",
    "wof:placetype": "venue"
  },
  "geometry": {"coordinates":[-82.986878,39.957499],"type":"Point"}
}
