{
  "type": "Feature",
  "properties": {
    "addr:full": "3710 Chelton Rd Cleveland OH 44120",
    "addr:housenumber": "3710",
    "addr:postcode": "44120",
    "addr:street": "Chelton Rd",
    "iso:country": "US",
    "sg:address": "3710 Chelton Rd",
    "sg:city": "Cleveland",
    "sg:classifiers": [
      {
        "category": "Real Estate",
        "subcategory": "Real Estate Agent",
        "type": "Services"
      }
    ],
    "sg:phone": "+1 216 751 2555",
    "sg:postcode": "44120",
    "sg:province": "OH",
    "wof:name": "Excel",
    "wof:placetype": "venue"
  },
  "geometry": {"coordinates":[-81.567182,41.457971],"type":"Point"}
}
