{
  "type": "Feature",
  "properties": {
    "addr:full":"3239 Jefferson Ave Cincinnati OH 45220",
    "addr:housenumber":"3239",
    "addr:postcode":"45220",
    "addr:street":"Jefferson Ave",
    "iso:country":"US",
    "sg:address":"3239 Jefferson Ave",
    "sg:city":"Cincinnati",
    "sg:classifiers":[
        {
            "category":"Restaurant",
            "type":"Food & Drink"
        }
    ],
    "sg:phone":"+1 513 221 8327",
    "sg:postcode":"45220",
    "sg:province":"OH",
    "sg:tags":[
        "shop",
        "coffee"
    ],
    "wof:name":"Hannahs Tea Cafe",
    "wof:placetype":"venue"
},
  "geometry": {"coordinates":[-84.512586,39.139337],"type":"Point"}
}