{
  "type": "Feature",
  "properties": {
    "iso:country":"US",
    "sg:address":"5192 Chillicothe Rd",
    "sg:city":"Novelty",
    "sg:classifiers":[
        {
            "category":"Health Services",
            "subcategory":"Doctor",
            "type":"Services"
        }
    ],
    "sg:phone":"+1 440 338 3661",
    "sg:postcode":"44072",
    "sg:province":"OH",
    "sg:tags":[
        "podiatrist"
    ],
    "wof:name":"Peterson Ted S DPM",
    "wof:placetype":"venue"
},
  "geometry": {"coordinates":[-81.34030199999999,41.465199],"type":"Point"}
}