{
  "type": "Feature",
  "properties": {
    "addr:full": "204 Lewisville Rd Woodsfield OH 43793",
    "addr:housenumber": "204",
    "addr:postcode": "43793",
    "addr:street": "Lewisville Rd",
    "iso:country": "US",
    "sg:address": "204 Lewisville Rd",
    "sg:city": "Woodsfield",
    "sg:classifiers": [
      {
        "category": "Food \u0026 Beverages",
        "subcategory": "Groceries \u0026 Convenience Stores",
        "type": "Retail Goods"
      }
    ],
    "sg:phone": "+1 740 472 5475",
    "sg:postcode": "43793",
    "sg:province": "OH",
    "wof:name": "Duke \u0026 Duchess Shoppe",
    "wof:placetype": "venue"
  },
  "geometry": {"coordinates":[-81.119104,39.763695],"type":"Point"}
}
