{
  "type": "Feature",
  "properties": {
    "iso:country":"US",
    "sg:address":"204 Lewisville Rd",
    "sg:city":"Woodsfield",
    "sg:classifiers":[
        {
            "category":"Food & Beverages",
            "subcategory":"Groceries & Convenience Stores",
            "type":"Retail Goods"
        }
    ],
    "sg:phone":"+1 740 472 5475",
    "sg:postcode":"43793",
    "sg:province":"OH",
    "wof:name":"Duke & Duchess Shoppe",
    "wof:placetype":"venue"
},
  "geometry": {"coordinates":[-81.11910399999999,39.763695],"type":"Point"}
}