{
  "type": "Feature",
  "properties": {
    "iso:country":"US",
    "sg:address":"9547 Hunt Rd",
    "sg:city":"St Louisville",
    "sg:classifiers":[
        {
            "category":"Real Estate",
            "subcategory":"Real Estate Agent",
            "type":"Services"
        }
    ],
    "sg:phone":"+1 740 745 1233",
    "sg:postcode":"43071",
    "sg:province":"OH",
    "sg:tags":[
        "inspection"
    ],
    "wof:name":"Platinum Home Inspections",
    "wof:placetype":"venue"
},
  "geometry": {"coordinates":[-82.367113,40.192257],"type":"Point"}
}