{
  "type": "Feature",
  "properties": {
    "iso:country":"US",
    "sg:address":"55 Nye Rd",
    "sg:city":"Painesville",
    "sg:classifiers":[
        {
            "category":"Government",
            "subcategory":"Fire Station",
            "type":"Public Place"
        }
    ],
    "sg:phone":"+1 440 352 7443",
    "sg:postcode":"44077",
    "sg:province":"OH",
    "sg:tags":[
        "department"
    ],
    "sg:website":"www.pvilletwp.com",
    "wof:name":"Painesville Twp Fire Dept #1",
    "wof:placetype":"venue"
},
  "geometry": {"coordinates":[-81.28440399999999,41.698272],"type":"Point"}
}