{
  "type": "Feature",
  "properties": {
    "addr:full": "914 National Rd Bridgeport OH 43912",
    "addr:housenumber": "914",
    "addr:postcode": "43912",
    "addr:street": "National Rd",
    "iso:country": "US",
    "sg:address": "914 National Rd",
    "sg:city": "Bridgeport",
    "sg:classifiers": [
      {
        "category": "Shopping",
        "subcategory": "Discount \u0026 Variety Stores",
        "type": "Retail Goods"
      },
      {
        "category": "Shopping",
        "subcategory": "Department Store",
        "type": "Retail Goods"
      }
    ],
    "sg:phone": "+1 740 633 5252",
    "sg:postcode": "43912",
    "sg:province": "OH",
    "wof:name": "Family Dollar Stores",
    "wof:placetype": "venue"
  },
  "geometry": {"coordinates":[-80.761191,40.070698],"type":"Point"}
}
