{
  "type": "Feature",
  "properties": {
    "addr:full": "18970 Wells Rd Jackson Center OH 45334",
    "addr:housenumber": "18970",
    "addr:postcode": "45334",
    "addr:street": "Wells Rd",
    "iso:country": "US",
    "sg:address": "18970 Wells Rd",
    "sg:city": "Jackson Center",
    "sg:classifiers": [
      {
        "category": "Retail",
        "subcategory": "Auto Repair",
        "type": "Services"
      }
    ],
    "sg:phone": "+1 937 596 6141",
    "sg:postcode": "45334",
    "sg:province": "OH",
    "sg:tags": [
      "recreational",
      "vehicle"
    ],
    "wof:name": "Bailey's RV Svc",
    "wof:placetype": "venue"
  },
  "geometry": {"coordinates":[-84.076525,40.410361],"type":"Point"}
}
