{
  "type": "Feature",
  "properties": {
    "iso:country":"US",
    "sg:address":"18970 Wells Rd",
    "sg:city":"Jackson Center",
    "sg:classifiers":[
        {
            "category":"Retail",
            "subcategory":"Auto Repair",
            "type":"Services"
        }
    ],
    "sg:phone":"+1 937 596 6141",
    "sg:postcode":"45334",
    "sg:province":"OH",
    "sg:tags":[
        "recreational",
        "vehicle"
    ],
    "wof:name":"Bailey's RV Svc",
    "wof:placetype":"venue"
},
  "geometry": {"coordinates":[-84.076525,40.410361],"type":"Point"}
}