{
  "type": "Feature",
  "properties": {
    "iso:country":"US",
    "sg:address":"2275 E 55th St",
    "sg:city":"Cleveland",
    "sg:classifiers":[
        {
            "category":"Building & Trades",
            "subcategory":"Construction",
            "type":"Services"
        }
    ],
    "sg:phone":"+1 216 432 1320",
    "sg:postcode":"44103",
    "sg:province":"OH",
    "sg:tags":[
        "general",
        "contractor"
    ],
    "wof:name":"CCA Construction",
    "wof:placetype":"venue"
},
  "geometry": {"coordinates":[-81.651636,41.496868],"type":"Point"}
}