{
  "type": "Feature",
  "properties": {
    "addr:full": "9503 Brandywine Rd Northfield OH 44067",
    "addr:housenumber": "9503",
    "addr:postcode": "44067",
    "addr:street": "Brandywine Rd",
    "iso:country": "US",
    "sg:address": "9503 Brandywine Rd",
    "sg:city": "Northfield",
    "sg:classifiers": [
      {
        "category": "Professional",
        "type": "Services"
      }
    ],
    "sg:phone": "+1 330 468 7819",
    "sg:postcode": "44067",
    "sg:province": "OH",
    "sg:tags": [
      "establishment"
    ],
    "wof:name": "Electrotech Industrial",
    "wof:placetype": "venue"
  },
  "geometry": {"coordinates":[-81.538935,41.314208],"type":"Point"}
}
