{
  "type": "Feature",
  "properties": {
    "addr:full": "2586 Tiller Ln Columbus OH 43231",
    "addr:housenumber": "2586",
    "addr:postcode": "43231",
    "addr:street": "Tiller Ln",
    "iso:country": "US",
    "sg:address": "2586 Tiller Ln",
    "sg:city": "Columbus",
    "sg:classifiers": [
      {
        "category": "Professional",
        "subcategory": "Advertising",
        "type": "Services"
      }
    ],
    "sg:phone": "+1 614 901 0381",
    "sg:postcode": "43231",
    "sg:province": "OH",
    "wof:name": "UNLIMITEDLC.COM",
    "wof:placetype": "venue"
  },
  "geometry": {"coordinates":[-82.947582,40.097086],"type":"Point"}
}
