{
  "type": "Feature",
  "properties": {
    "addr:full":"1001 Monroe St Bellevue OH 44811",
    "addr:housenumber":"1001",
    "addr:postcode":"44811",
    "addr:street":"Monroe St",
    "iso:country":"US",
    "sg:address":"1001 Monroe St",
    "sg:city":"Bellevue",
    "sg:classifiers":[
        {
            "category":"Organizations",
            "subcategory":"Religious Organization",
            "type":"Services"
        }
    ],
    "sg:phone":"+1 419 483 0120",
    "sg:postcode":"44811",
    "sg:province":"OH",
    "sg:tags":[
        "church"
    ],
    "wof:name":"Bellevue Alliance Church",
    "wof:placetype":"venue"
},
  "geometry": {"coordinates":[-82.822683,41.26495],"type":"Point"}
}