{
  "type": "Feature",
  "properties": {
    "addr:full": "6500 Sawmill Rd Columbus OH 43235",
    "addr:housenumber": "6500",
    "addr:postcode": "43235",
    "addr:street": "Sawmill Rd",
    "iso:country": "US",
    "sg:address": "6500 Sawmill Rd",
    "sg:city": "Columbus",
    "sg:classifiers": [
      {
        "category": "Shopping",
        "subcategory": "Optical Goods",
        "type": "Retail Goods"
      }
    ],
    "sg:phone": "+1 614 798 0260",
    "sg:postcode": "43235",
    "sg:province": "OH",
    "sg:website": "www.lenscrafters.com",
    "wof:name": "Lens Crafters",
    "wof:placetype": "venue"
  },
  "geometry": {"coordinates":[-83.091216,40.101863],"type":"Point"}
}
