{
  "type": "Feature",
  "properties": {
    "addr:full": "686 Prospect Ave E Cleveland OH 44115",
    "addr:housenumber": "686",
    "addr:postcode": "44115",
    "addr:street": "Prospect Ave E",
    "iso:country": "US",
    "sg:address": "686 Prospect Ave E",
    "sg:city": "Cleveland",
    "sg:classifiers": [
      {
        "category": "Insurance",
        "subcategory": "Insurance Agent",
        "type": "Services"
      }
    ],
    "sg:phone": "+1 440 243 5555",
    "sg:postcode": "44115",
    "sg:province": "OH",
    "wof:name": "State Farm Insurance",
    "wof:placetype": "venue"
  },
  "geometry": {"coordinates":[-81.687829,41.498522],"type":"Point"}
}
