{
  "type": "Feature",
  "properties": {
    "iso:country":"US",
    "sg:address":"733 3rd St",
    "sg:city":"Findlay",
    "sg:classifiers":[
        {
            "category":"Real Estate",
            "subcategory":"Real Estate Agent",
            "type":"Services"
        }
    ],
    "sg:phone":"+1 419 424 0537",
    "sg:postcode":"45840",
    "sg:province":"OH",
    "wof:name":"Gibbons Investments LLC",
    "wof:placetype":"venue"
},
  "geometry": {"coordinates":[-83.639639,41.026293],"type":"Point"}
}