{
  "type": "Feature",
  "properties": {
    "addr:full": "22701 Lake Rd Cleveland OH 44116",
    "addr:housenumber": "22701",
    "addr:postcode": "44116",
    "addr:street": "Lake Rd",
    "iso:country": "US",
    "sg:address": "22701 Lake Rd",
    "sg:city": "Cleveland",
    "sg:classifiers": [
      {
        "category": "Health Services",
        "subcategory": "Nursing And Care Facility",
        "type": "Services"
      },
      {
        "category": "Real Estate",
        "subcategory": "Real Estate Operator",
        "type": "Services"
      }
    ],
    "sg:phone": "+1 440 333 5400",
    "sg:postcode": "44116",
    "sg:province": "OH",
    "sg:tags": [
      "skilled",
      "apartment"
    ],
    "sg:website": "www.normandyretirement.com",
    "wof:name": "Normandy Manor of Rocky River",
    "wof:placetype": "venue"
  },
  "geometry": {"coordinates":[-81.87219,41.481463],"type":"Point"}
}
