{
  "type": "Feature",
  "properties": {
    "addr:full":"109 Poland Ave Struthers OH 44471",
    "addr:housenumber":"109",
    "addr:postcode":"44471",
    "addr:street":"Poland Ave",
    "iso:country":"US",
    "sg:address":"109 Poland Ave",
    "sg:city":"Struthers",
    "sg:classifiers":[
        {
            "category":"Retail",
            "subcategory":"Auto Repair",
            "type":"Services"
        }
    ],
    "sg:phone":"+1 330 755 2255",
    "sg:postcode":"44471",
    "sg:province":"OH",
    "sg:tags":[
        "body",
        "automobile",
        "painting"
    ],
    "wof:name":"Cox's Custom Auto Inc",
    "wof:placetype":"venue"
},
  "geometry": {"coordinates":[-80.59184399999999,41.054244],"type":"Point"}
}