{
  "type": "Feature",
  "properties": {
    "addr:full":"111 E Nationwide Blvd Columbus OH 43215",
    "addr:housenumber":"111",
    "addr:postcode":"43215",
    "addr:street":"E Nationwide Blvd",
    "iso:country":"US",
    "sg:address":"111 E Nationwide Blvd",
    "sg:city":"Columbus",
    "sg:classifiers":[
        {
            "category":"Travel",
            "subcategory":"Hotels & Motels",
            "type":"Entertainment"
        }
    ],
    "sg:phone":"+1 614 224 6539",
    "sg:postcode":"43215",
    "sg:province":"OH",
    "wof:name":"Red Roof Inn Columbus Downtown",
    "wof:placetype":"venue"
},
  "geometry": {"coordinates":[-82.997457,39.969001],"type":"Point"}
}