{
  "type": "Feature",
  "properties": {
    "addr:full": "878 Miller Rd Lebanon OH 45036",
    "addr:housenumber": "878",
    "addr:postcode": "45036",
    "addr:street": "Miller Rd",
    "iso:country": "US",
    "sg:address": "878 Miller Rd",
    "sg:city": "Lebanon",
    "sg:classifiers": [
      {
        "category": "Organizations",
        "subcategory": "Religious Organization",
        "type": "Services"
      }
    ],
    "sg:phone": "+1 513 932 5061",
    "sg:postcode": "45036",
    "sg:province": "OH",
    "sg:tags": [
      "clergy"
    ],
    "wof:name": "Orville R Robinson",
    "wof:placetype": "venue"
  },
  "geometry": {"coordinates":[-84.221601,39.45846],"type":"Point"}
}
