{
  "type": "Feature",
  "properties": {
    "iso:country":"US",
    "sg:address":"878 Miller Rd",
    "sg:city":"Lebanon",
    "sg:classifiers":[
        {
            "category":"Organizations",
            "subcategory":"Religious Organization",
            "type":"Services"
        }
    ],
    "sg:phone":"+1 513 932 5061",
    "sg:postcode":"45036",
    "sg:province":"OH",
    "sg:tags":[
        "clergy"
    ],
    "wof:name":"Orville R Robinson",
    "wof:placetype":"venue"
},
  "geometry": {"coordinates":[-84.22160100000001,39.45846],"type":"Point"}
}