{
  "type": "Feature",
  "properties": {
    "addr:full":"7511 Worthington Galena Rd Worthington OH 43085",
    "addr:housenumber":"7511",
    "addr:postcode":"43085",
    "addr:street":"Worthington Galena Rd",
    "iso:country":"US",
    "sg:address":"7511 Worthington Galena Rd",
    "sg:city":"Worthington",
    "sg:classifiers":[
        {
            "category":"Retail",
            "subcategory":"Repair Shop",
            "type":"Services"
        }
    ],
    "sg:phone":"+1 614 431 2100",
    "sg:postcode":"43085",
    "sg:province":"OH",
    "sg:tags":[
        "scooter",
        "motorcycle",
        "motor"
    ],
    "wof:name":"Aggressive Motor Sports",
    "wof:placetype":"venue"
},
  "geometry": {"coordinates":[-82.988484,40.118083],"type":"Point"}
}