{
  "type": "Feature",
  "properties": {
    "iso:country":"US",
    "sg:address":"5142 Wilson Mills Rd",
    "sg:city":"Cleveland",
    "sg:classifiers":[
        {
            "category":"Restaurant",
            "type":"Food & Drink"
        }
    ],
    "sg:phone":"+1 440 446 1122",
    "sg:postcode":"44143",
    "sg:province":"OH",
    "sg:tags":[
        "buffet"
    ],
    "wof:name":"Hometown Buffet 44",
    "wof:placetype":"venue"
},
  "geometry": {"coordinates":[-81.49163,41.538937],"type":"Point"}
}