{
  "type": "Feature",
  "properties": {
    "addr:full":"9105 Woodland Ave Cleveland OH 44104",
    "addr:housenumber":"9105",
    "addr:postcode":"44104",
    "addr:street":"Woodland Ave",
    "iso:country":"US",
    "sg:address":"9105 Woodland Ave",
    "sg:city":"Cleveland",
    "sg:classifiers":[
        {
            "category":"Organizations",
            "subcategory":"Religious Organization",
            "type":"Services"
        }
    ],
    "sg:phone":"+1 216 791 2194",
    "sg:postcode":"44104",
    "sg:province":"OH",
    "sg:tags":[
        "church"
    ],
    "wof:name":"Faith Holiness Temple",
    "wof:placetype":"venue"
},
  "geometry": {"coordinates":[-81.622715,41.488328],"type":"Point"}
}