{
  "type": "Feature",
  "properties": {
    "iso:country":"US",
    "sg:address":"2270 Dixie Hwy",
    "sg:city":"Hamilton",
    "sg:classifiers":[
        {
            "category":"Government",
            "subcategory":"Office",
            "type":"Public Place"
        }
    ],
    "sg:phone":"+1 513 785 6500",
    "sg:postcode":"45015",
    "sg:province":"OH",
    "sg:website":"www.butlercountyjobcenter.com",
    "wof:name":"Butler County Job Ctr",
    "wof:placetype":"venue"
},
  "geometry": {"coordinates":[-84.548693,39.373198],"type":"Point"}
}