{
  "type": "Feature",
  "properties": {
    "addr:full": "7255 Poe Ave Dayton OH 45414",
    "addr:housenumber": "7255",
    "addr:postcode": "45414",
    "addr:street": "Poe Ave",
    "iso:country": "US",
    "sg:address": "7255 Poe Ave",
    "sg:city": "Dayton",
    "sg:classifiers": [
      {
        "category": "Autos \u0026 Motor Vehicles",
        "subcategory": "Auto Supplies",
        "type": "Retail Goods"
      }
    ],
    "sg:phone": "+1 937 424 1029",
    "sg:postcode": "45414",
    "sg:province": "OH",
    "sg:tags": [
      "automobile",
      "parts"
    ],
    "wof:name": "EJM Motorsports",
    "wof:placetype": "venue"
  },
  "geometry": {"coordinates":[-84.188642,39.852532],"type":"Point"}
}
