{
  "type": "Feature",
  "properties": {
    "iso:country":"US",
    "sg:address":"3050 Myers Rd",
    "sg:city":"Springfield",
    "sg:classifiers":[
        {
            "category":"Building & Trades",
            "subcategory":"Construction",
            "type":"Services"
        }
    ],
    "sg:phone":"+1 937 323 1606",
    "sg:postcode":"45502",
    "sg:province":"OH",
    "sg:tags":[
        "excavation",
        "concrete",
        "contractor"
    ],
    "wof:name":"Austin Benchmark Excavating",
    "wof:placetype":"venue"
},
  "geometry": {"coordinates":[-83.93734499999999,39.964538],"type":"Point"}
}