{
  "type": "Feature",
  "properties": {
    "addr:full": "16034 Co Hwy 23 Loudonville OH 44842",
    "addr:housenumber": "16034",
    "addr:postcode": "44842",
    "addr:street": "Co Hwy 23",
    "iso:country": "US",
    "sg:address": "16034 Co Hwy 23",
    "sg:city": "Loudonville",
    "sg:classifiers": [
      {
        "category": "Manufacturing",
        "subcategory": "Buildings",
        "type": "Manufacturing \u0026 Wholesale Goods"
      }
    ],
    "sg:phone": "+1 419 994 5835",
    "sg:postcode": "44842",
    "sg:province": "OH",
    "sg:tags": [
      "home",
      "log",
      "cabin"
    ],
    "wof:name": "Eagle Cedar Log Homes",
    "wof:placetype": "venue"
  },
  "geometry": {"coordinates":[-82.191223,40.584678],"type":"Point"}
}
