{
  "type": "Feature",
  "properties": {
    "iso:country":"US",
    "sg:address":"1452 Franklin Ave",
    "sg:city":"Salem",
    "sg:classifiers":[
        {
            "category":"Professional",
            "subcategory":"Accounting & Tax Preparation",
            "type":"Services"
        }
    ],
    "sg:phone":"+1 330 337 9526",
    "sg:postcode":"44460",
    "sg:province":"OH",
    "sg:tags":[
        "accountant"
    ],
    "wof:name":"Thorne Management",
    "wof:placetype":"venue"
},
  "geometry": {"coordinates":[-80.83800599999999,40.888564],"type":"Point"}
}