{
  "type": "Feature",
  "properties": {
    "addr:full": "1452 Franklin Ave Salem OH 44460",
    "addr:housenumber": "1452",
    "addr:postcode": "44460",
    "addr:street": "Franklin Ave",
    "iso:country": "US",
    "sg:address": "1452 Franklin Ave",
    "sg:city": "Salem",
    "sg:classifiers": [
      {
        "category": "Professional",
        "subcategory": "Accounting \u0026 Tax Preparation",
        "type": "Services"
      }
    ],
    "sg:phone": "+1 330 337 9526",
    "sg:postcode": "44460",
    "sg:province": "OH",
    "sg:tags": [
      "accountant"
    ],
    "wof:name": "Thorne Management",
    "wof:placetype": "venue"
  },
  "geometry": {"coordinates":[-80.838006,40.888564],"type":"Point"}
}
