{
  "type": "Feature",
  "properties": {
    "addr:full": "2873 Taylortown Rd Shelby OH 44875",
    "addr:housenumber": "2873",
    "addr:postcode": "44875",
    "addr:street": "Taylortown Rd",
    "iso:country": "US",
    "sg:address": "2873 Taylortown Rd",
    "sg:city": "Shelby",
    "sg:phone": "+1 419 347 5057",
    "sg:postcode": "44875",
    "sg:province": "OH",
    "sg:tags": [
      "wheat",
      "beef",
      "farm",
      "corn",
      "soybean",
      "cattle"
    ],
    "wof:name": "Steven Stover Farms",
    "wof:placetype": "venue"
  },
  "geometry": {"coordinates":[-82.621425,40.857533],"type":"Point"}
}
