{
  "type": "Feature",
  "properties": {
    "addr:full": "14544 Co Rd 6 Metamora OH 43540",
    "addr:housenumber": "14544",
    "addr:postcode": "43540",
    "addr:street": "Co Rd 6",
    "iso:country": "US",
    "sg:address": "14544 Co Rd 6",
    "sg:city": "Metamora",
    "sg:classifiers": [
      {
        "category": "Education",
        "subcategory": "School",
        "type": "Public Place"
      }
    ],
    "sg:phone": "+1 419 644 1375",
    "sg:postcode": "43540",
    "sg:province": "OH",
    "wof:name": "Schools Bus Garage",
    "wof:placetype": "venue"
  },
  "geometry": {"coordinates":[-83.975302,41.679136],"type":"Point"}
}
