{
  "type": "Feature",
  "properties": {
    "addr:full": "25575 Aurora Rd Cleveland OH 44146",
    "addr:housenumber": "25575",
    "addr:postcode": "44146",
    "addr:street": "Aurora Rd",
    "iso:country": "US",
    "sg:address": "25575 Aurora Rd",
    "sg:city": "Cleveland",
    "sg:classifiers": [
      {
        "category": "Restaurant",
        "type": "Food \u0026 Drink"
      }
    ],
    "sg:phone": "+1 216 374 2600",
    "sg:postcode": "44146",
    "sg:province": "OH",
    "wof:name": "Subway Sandwiches \u0026 Salads",
    "wof:placetype": "venue"
  },
  "geometry": {"coordinates":[-81.488902,41.404787],"type":"Point"}
}
