{
  "type": "Feature",
  "properties": {
    "iso:country":"US",
    "sg:address":"25575 Aurora Rd",
    "sg:city":"Cleveland",
    "sg:classifiers":[
        {
            "category":"Restaurant",
            "type":"Food & Drink"
        }
    ],
    "sg:phone":"+1 216 374 2600",
    "sg:postcode":"44146",
    "sg:province":"OH",
    "wof:name":"Subway Sandwiches & Salads",
    "wof:placetype":"venue"
},
  "geometry": {"coordinates":[-81.488902,41.404787],"type":"Point"}
}