{
  "type": "Feature",
  "properties": {
    "addr:full": "1800 Snow Rd Cleveland OH 44134",
    "addr:housenumber": "1800",
    "addr:postcode": "44134",
    "addr:street": "Snow Rd",
    "iso:country": "US",
    "sg:address": "1800 Snow Rd",
    "sg:city": "Cleveland",
    "sg:classifiers": [
      {
        "category": "Shopping",
        "subcategory": "Pharmacy",
        "type": "Retail Goods"
      }
    ],
    "sg:phone": "+1 216 749 6339",
    "sg:postcode": "44134",
    "sg:province": "OH",
    "wof:name": "Rite Aid",
    "wof:placetype": "venue"
  },
  "geometry": {"coordinates":[-81.697916,41.40515],"type":"Point"}
}
