{
  "type": "Feature",
  "properties": {
    "iso:country":"US",
    "sg:address":"607 Lincoln Way W",
    "sg:city":"Massillon",
    "sg:classifiers":[
        {
            "category":"Restaurant",
            "type":"Food & Drink"
        }
    ],
    "sg:phone":"+1 330 832 8292",
    "sg:postcode":"44647",
    "sg:province":"OH",
    "sg:tags":[
        "eating"
    ],
    "wof:name":"Top of Viaduct",
    "wof:placetype":"venue"
},
  "geometry": {"coordinates":[-81.530929,40.794179],"type":"Point"}
}