{
  "type": "Feature",
  "properties": {
    "addr:full": "538 N Main St Cadiz OH 43907",
    "addr:housenumber": "538",
    "addr:postcode": "43907",
    "addr:street": "N Main St",
    "iso:country": "US",
    "sg:address": "538 N Main St",
    "sg:city": "Cadiz",
    "sg:classifiers": [
      {
        "category": "Government",
        "subcategory": "Office",
        "type": "Public Place"
      }
    ],
    "sg:phone": "+1 740 942 3354",
    "sg:postcode": "43907",
    "sg:province": "OH",
    "wof:name": "Ohio Drivers Exams \u0026 Testing",
    "wof:placetype": "venue"
  },
  "geometry": {"coordinates":[-80.992418,40.276737],"type":"Point"}
}
