{
  "type": "Feature",
  "properties": {
    "addr:full":"494 E 4th St Uhrichsville OH 44683",
    "addr:housenumber":"494",
    "addr:postcode":"44683",
    "addr:street":"E 4Th St",
    "iso:country":"US",
    "sg:address":"494 E 4th St",
    "sg:city":"Uhrichsville",
    "sg:classifiers":[
        {
            "category":"Autos & Motor Vehicles",
            "subcategory":"Fuel & Gas Station",
            "type":"Retail Goods"
        }
    ],
    "sg:phone":"+1 740 922 1933",
    "sg:postcode":"44683",
    "sg:province":"OH",
    "sg:tags":[
        "station",
        "gasoline",
        "oil"
    ],
    "wof:name":"Certified Oil Corp",
    "wof:placetype":"venue"
},
  "geometry": {"coordinates":[-81.339249,40.392894],"type":"Point"}
}