{
  "type": "Feature",
  "properties": {
    "iso:country":"US",
    "sg:address":"1001 Lakeside Ave E",
    "sg:city":"Cleveland",
    "sg:classifiers":[
        {
            "category":"Professional",
            "subcategory":"Engineering",
            "type":"Services"
        }
    ],
    "sg:phone":"+1 216 875 4000",
    "sg:postcode":"44114",
    "sg:province":"OH",
    "sg:tags":[
        "s",
        "architectural",
        "landscape"
    ],
    "wof:name":"HWH Archtcts-Ngineers-Planners",
    "wof:placetype":"venue"
},
  "geometry": {"coordinates":[-81.69128499999999,41.50566],"type":"Point"}
}