{
  "type": "Feature",
  "properties": {
    "addr:full": "4147 Elida Rd Lima OH 45807",
    "addr:housenumber": "4147",
    "addr:postcode": "45807",
    "addr:street": "Elida Rd",
    "iso:country": "US",
    "sg:address": "4147 Elida Rd",
    "sg:city": "Lima",
    "sg:classifiers": [
      {
        "category": "Home \u0026 Garden",
        "subcategory": "Home Furnishings",
        "type": "Retail Goods"
      }
    ],
    "sg:phone": "+1 419 224 4656",
    "sg:postcode": "45807",
    "sg:province": "OH",
    "sg:tags": [
      "fireplace"
    ],
    "wof:name": "Kerns Fireplace \u0026 Spa",
    "wof:placetype": "venue"
  },
  "geometry": {"coordinates":[-84.175843,40.775357],"type":"Point"}
}
