{
  "type": "Feature",
  "properties": {
    "addr:full": "43455 County Line Rd Columbiana OH 44408",
    "addr:housenumber": "43455",
    "addr:postcode": "44408",
    "addr:street": "County Line Rd",
    "iso:country": "US",
    "sg:address": "43455 County Line Rd",
    "sg:city": "Columbiana",
    "sg:classifiers": [
      {
        "category": "Building \u0026 Trades",
        "subcategory": "Electrical",
        "type": "Services"
      }
    ],
    "sg:phone": "+1 330 482 4593",
    "sg:postcode": "44408",
    "sg:province": "OH",
    "sg:tags": [
      "industrial",
      "electrician",
      "contractors-commercial",
      "electric"
    ],
    "wof:name": "Good's Electric",
    "wof:placetype": "venue"
  },
  "geometry": {"coordinates":[-80.678635,40.899939],"type":"Point"}
}
