{
  "type": "Feature",
  "properties": {
    "addr:full": "889 Commercial Pkwy Dover OH 44622",
    "addr:housenumber": "889",
    "addr:postcode": "44622",
    "addr:street": "Commercial Pkwy",
    "iso:country": "US",
    "sg:address": "889 Commercial Pkwy",
    "sg:city": "Dover",
    "sg:classifiers": [
      {
        "category": "Travel",
        "subcategory": "Hotels \u0026 Motels",
        "type": "Entertainment"
      }
    ],
    "sg:phone": "+1 330 364 7724",
    "sg:postcode": "44622",
    "sg:province": "OH",
    "wof:name": "Hospitality Inn",
    "wof:placetype": "venue"
  },
  "geometry": {"coordinates":[-81.48957,40.520931],"type":"Point"}
}
