{
  "type": "Feature",
  "properties": {
    "iso:country":"US",
    "sg:address":"7945 Airport Hwy",
    "sg:city":"Holland",
    "sg:classifiers":[
        {
            "category":"Wholesale",
            "subcategory":"Machinery & Supplies",
            "type":"Manufacturing & Wholesale Goods"
        }
    ],
    "sg:phone":"+1 419 867 6767",
    "sg:postcode":"43528",
    "sg:province":"OH",
    "wof:name":"Freedom Machinery",
    "wof:placetype":"venue"
},
  "geometry": {"coordinates":[-83.735465,41.610302],"type":"Point"}
}