{
  "type": "Feature",
  "properties": {
    "addr:full": "1090 N High St Hillsboro OH 45133",
    "addr:housenumber": "1090",
    "addr:postcode": "45133",
    "addr:street": "N High St",
    "iso:country": "US",
    "sg:address": "1090 N High St",
    "sg:city": "Hillsboro",
    "sg:classifiers": [
      {
        "category": "Government",
        "subcategory": "Office",
        "type": "Public Place"
      }
    ],
    "sg:phone": "+1 937 393 0920",
    "sg:postcode": "45133",
    "sg:province": "OH",
    "sg:tags": [
      "development",
      "federal",
      "planning",
      "dev",
      "rural"
    ],
    "wof:name": "USDA Rural Development",
    "wof:placetype": "venue"
  },
  "geometry": {"coordinates":[-83.608292,39.219625],"type":"Point"}
}
