{
  "type": "Feature",
  "properties": {
    "addr:full": "7310 Brown Rd Athens OH 45701",
    "addr:housenumber": "7310",
    "addr:postcode": "45701",
    "addr:street": "Brown Rd",
    "iso:country": "US",
    "sg:address": "7310 Brown Rd",
    "sg:city": "Athens",
    "sg:classifiers": [
      {
        "category": "Building \u0026 Trades",
        "subcategory": "Electrical",
        "type": "Services"
      }
    ],
    "sg:phone": "+1 740 593 7741",
    "sg:postcode": "45701",
    "sg:province": "OH",
    "sg:tags": [
      "consultant",
      "ergonomic"
    ],
    "wof:name": "Ergonomic Solutions",
    "wof:placetype": "venue"
  },
  "geometry": {"coordinates":[-82.184055,39.307258],"type":"Point"}
}
