{
  "type": "Feature",
  "properties": {
    "addr:full": "2733 Glendale Ave Toledo OH 43614",
    "addr:housenumber": "2733",
    "addr:postcode": "43614",
    "addr:street": "Glendale Ave",
    "iso:country": "US",
    "sg:address": "2733 Glendale Ave",
    "sg:city": "Toledo",
    "sg:classifiers": [
      {
        "category": "Building \u0026 Trades",
        "subcategory": "Plumbing",
        "type": "Services"
      }
    ],
    "sg:phone": "+1 419 382 1234",
    "sg:postcode": "43614",
    "sg:province": "OH",
    "sg:tags": [
      "plumbing",
      "contractor"
    ],
    "wof:name": "George F Peters \u0026 Son Plumbing",
    "wof:placetype": "venue"
  },
  "geometry": {"coordinates":[-83.608652,41.612076],"type":"Point"}
}
