{
  "type": "Feature",
  "properties": {
    "addr:full":"3133 Waterfall Way Cleveland OH 44145",
    "addr:housenumber":"3133",
    "addr:postcode":"44145",
    "addr:street":"Waterfall Way",
    "iso:country":"US",
    "sg:address":"3133 Waterfall Way",
    "sg:city":"Cleveland",
    "sg:classifiers":[
        {
            "category":"Building & Trades",
            "subcategory":"Construction",
            "type":"Services"
        }
    ],
    "sg:phone":"+1 440 892 3834",
    "sg:postcode":"44145",
    "sg:province":"OH",
    "sg:tags":[
        "general",
        "nonresidential",
        "contractor"
    ],
    "wof:name":"Fortuna Construction Company",
    "wof:placetype":"venue"
},
  "geometry": {"coordinates":[-81.967462,41.442684],"type":"Point"}
}