{
  "type": "Feature",
  "properties": {
    "addr:full": "34425 Lorain Rd North Ridgeville OH 44039",
    "addr:housenumber": "34425",
    "addr:postcode": "44039",
    "addr:street": "Lorain Rd",
    "iso:country": "US",
    "sg:address": "34425 Lorain Rd",
    "sg:city": "North Ridgeville",
    "sg:classifiers": [
      {
        "category": "Freight",
        "type": "Transportation"
      }
    ],
    "sg:phone": "+1 440 327 2449",
    "sg:postcode": "44039",
    "sg:province": "OH",
    "sg:tags": [
      "commercial",
      "storage",
      "special",
      "general"
    ],
    "wof:name": "Fields Stor-All Ltd",
    "wof:placetype": "venue"
  },
  "geometry": {"coordinates":[-81.993718,41.372319],"type":"Point"}
}
