{
  "type": "Feature",
  "properties": {
    "addr:full": "226 Connecticut Ave Lorain OH 44052",
    "addr:housenumber": "226",
    "addr:postcode": "44052",
    "addr:street": "Connecticut Ave",
    "iso:country": "US",
    "sg:address": "226 Connecticut Ave",
    "sg:city": "Lorain",
    "sg:classifiers": [
      {
        "category": "Manufacturing",
        "subcategory": "Food",
        "type": "Manufacturing \u0026 Wholesale Goods"
      }
    ],
    "sg:phone": "+1 440 288 0146",
    "sg:postcode": "44052",
    "sg:province": "OH",
    "sg:tags": [
      "canning"
    ],
    "sg:website": "www.clovervale.com",
    "wof:name": "Clovervale Foods Inc",
    "wof:placetype": "venue"
  },
  "geometry": {"coordinates":[-82.168873,41.471171],"type":"Point"}
}
