{
  "type": "Feature",
  "properties": {
    "addr:full": "647 E Main St Lancaster OH 43130",
    "addr:housenumber": "647",
    "addr:postcode": "43130",
    "addr:street": "E Main St",
    "iso:country": "US",
    "sg:address": "647 E Main St",
    "sg:city": "Lancaster",
    "sg:classifiers": [
      {
        "category": "Autos \u0026 Motor Vehicles",
        "subcategory": "Auto Supplies",
        "type": "Retail Goods"
      }
    ],
    "sg:phone": "+1 740 653 4290",
    "sg:postcode": "43130",
    "sg:province": "OH",
    "sg:tags": [
      "automobile",
      "stereo",
      "radio"
    ],
    "wof:name": "Auto Restylers",
    "wof:placetype": "venue"
  },
  "geometry": {"coordinates":[-82.589186,39.71356],"type":"Point"}
}
