{
  "type": "Feature",
  "properties": {
    "iso:country":"US",
    "sg:address":"7243 Wooster Pike",
    "sg:city":"Cincinnati",
    "sg:classifiers":[
        {
            "category":"Professional",
            "subcategory":"Lawyer & Legal Services",
            "type":"Services"
        }
    ],
    "sg:phone":"+1 513 561 7755",
    "sg:postcode":"45227",
    "sg:province":"OH",
    "sg:tags":[
        "attorney"
    ],
    "wof:name":"Elizabeth D Corr",
    "wof:placetype":"venue"
},
  "geometry": {"coordinates":[-84.366414,39.144138],"type":"Point"}
}