{
  "type": "Feature",
  "properties": {
    "addr:full": "36 W Columbus St Pickerington OH 43147",
    "addr:housenumber": "36",
    "addr:postcode": "43147",
    "addr:street": "W Columbus St",
    "iso:country": "US",
    "sg:address": "36 W Columbus St",
    "sg:city": "Pickerington",
    "sg:classifiers": [
      {
        "category": "Wholesale",
        "subcategory": "Home Furnishings",
        "type": "Manufacturing \u0026 Wholesale Goods"
      }
    ],
    "sg:phone": "+1 614 834 3392",
    "sg:postcode": "43147",
    "sg:province": "OH",
    "wof:name": "Olde Ivy Cottage",
    "wof:placetype": "venue"
  },
  "geometry": {"coordinates":[-82.755542,39.884227],"type":"Point"}
}
