{
  "type": "Feature",
  "properties": {
    "addr:full": "1819 Wheatfield Way Loveland OH 45140",
    "addr:housenumber": "1819",
    "addr:postcode": "45140",
    "addr:street": "Wheatfield Way",
    "iso:country": "US",
    "sg:address": "1819 Wheatfield Way",
    "sg:city": "Loveland",
    "sg:classifiers": [
      {
        "category": "Building \u0026 Trades",
        "subcategory": "Construction",
        "type": "Services"
      }
    ],
    "sg:phone": "+1 513 575 4313",
    "sg:postcode": "45140",
    "sg:province": "OH",
    "sg:tags": [
      "house"
    ],
    "wof:name": "Cooper Construction",
    "wof:placetype": "venue"
  },
  "geometry": {"coordinates":[-84.225812,39.216484],"type":"Point"}
}
