{
  "type": "Feature",
  "properties": {
    "addr:full":"12709 Superior Ave Cleveland OH 44112",
    "addr:housenumber":"12709",
    "addr:postcode":"44112",
    "addr:street":"Superior Ave",
    "iso:country":"US",
    "sg:address":"12709 Superior Ave",
    "sg:city":"Cleveland",
    "sg:classifiers":[
        {
            "category":"Personal",
            "subcategory":"Barber",
            "type":"Services"
        }
    ],
    "sg:phone":"+1 216 761 9109",
    "sg:postcode":"44112",
    "sg:province":"OH",
    "wof:name":"Executive Barber Shop",
    "wof:placetype":"venue"
},
  "geometry": {"coordinates":[-81.595456,41.523134],"type":"Point"}
}