{
  "type": "Feature",
  "properties": {
    "addr:full":"8503 Twp Rd 79 Millersburg OH 44654",
    "addr:housenumber":"8503;79",
    "addr:postcode":"44654",
    "addr:street":"Twp Rd",
    "iso:country":"US",
    "sg:address":"8503 Twp Rd 79",
    "sg:city":"Millersburg",
    "sg:phone":"+1 330 674 3316",
    "sg:postcode":"44654",
    "sg:province":"OH",
    "sg:tags":[
        "farm",
        "field",
        "crop"
    ],
    "wof:name":"Dean Chancy",
    "wof:placetype":"venue"
},
  "geometry": {"coordinates":[-81.936525,40.47294],"type":"Point"}
}