{
  "type": "Feature",
  "properties": {
    "iso:country":"US",
    "sg:address":"5213 Sunrise View Cir",
    "sg:city":"Middletown",
    "sg:classifiers":[
        {
            "category":"Wholesale",
            "subcategory":"Construction Materials",
            "type":"Manufacturing & Wholesale Goods"
        }
    ],
    "sg:phone":"+1 513 777 5216",
    "sg:postcode":"45044",
    "sg:province":"OH",
    "sg:tags":[
        "farm",
        "labor",
        "contractor"
    ],
    "wof:name":"Mad Dog Composites",
    "wof:placetype":"venue"
},
  "geometry": {"coordinates":[-84.363681,39.419437],"type":"Point"}
}