{
  "type": "Feature",
  "properties": {
    "iso:country":"US",
    "sg:address":"284 Lear St",
    "sg:city":"Columbus",
    "sg:classifiers":[
        {
            "category":"Real Estate",
            "subcategory":"Real Estate Operator",
            "type":"Services"
        }
    ],
    "sg:phone":"+1 614 296 3425",
    "sg:postcode":"43206",
    "sg:province":"OH",
    "sg:tags":[
        "building",
        "parks"
    ],
    "wof:name":"Donley Investve",
    "wof:placetype":"venue"
},
  "geometry": {"coordinates":[-82.99053,39.949874],"type":"Point"}
}