{
  "type": "Feature",
  "properties": {
    "addr:full":"19825 Saint Clair Ave Cleveland OH 44117",
    "addr:housenumber":"19825",
    "addr:postcode":"44117",
    "addr:street":"Saint Clair Ave",
    "iso:country":"US",
    "sg:address":"19825 Saint Clair Ave",
    "sg:city":"Cleveland",
    "sg:classifiers":[
        {
            "category":"Home & Garden",
            "subcategory":"Building Materials",
            "type":"Retail Goods"
        },
        {
            "category":"Retail",
            "subcategory":"Auto Repair",
            "type":"Services"
        }
    ],
    "sg:phone":"+1 216 531 9191",
    "sg:postcode":"44117",
    "sg:province":"OH",
    "sg:tags":[
        "plate",
        "window",
        "installation",
        "glass",
        "automobile"
    ],
    "wof:name":"Comet Glass Co",
    "wof:placetype":"venue"
},
  "geometry": {"coordinates":[-81.540008,41.57885],"type":"Point"}
}