{
  "type": "Feature",
  "properties": {
    "iso:country":"US",
    "sg:address":"30311 Clemens Rd",
    "sg:city":"Westlake",
    "sg:classifiers":[
        {
            "category":"Wholesale",
            "subcategory":"Machinery & Supplies",
            "type":"Manufacturing & Wholesale Goods"
        }
    ],
    "sg:phone":"+1 440 871 9600",
    "sg:postcode":"44145",
    "sg:province":"OH",
    "sg:tags":[
        "durable",
        "industrial"
    ],
    "wof:name":"E L Hatton Sales Company",
    "wof:placetype":"venue"
},
  "geometry": {"coordinates":[-81.957166,41.470541],"type":"Point"}
}