{
  "type": "Feature",
  "properties": {
    "iso:country":"US",
    "sg:address":"4495 Blacksnake Hill Rd NE",
    "sg:city":"Dover",
    "sg:classifiers":[
        {
            "category":"Personal",
            "type":"Services"
        }
    ],
    "sg:phone":"+1 330 364 3321",
    "sg:postcode":"44622",
    "sg:province":"OH",
    "sg:tags":[
        "therapist",
        "massage"
    ],
    "wof:name":"Healing Touch Therapies",
    "wof:placetype":"venue"
},
  "geometry": {"coordinates":[-81.453935,40.548366],"type":"Point"}
}