{
  "type": "Feature",
  "properties": {
    "addr:full": "54 E Main St Logan OH 43138",
    "addr:housenumber": "54",
    "addr:postcode": "43138",
    "addr:street": "E Main St",
    "iso:country": "US",
    "sg:address": "54 E Main St",
    "sg:city": "Logan",
    "sg:classifiers": [
      {
        "category": "Shopping",
        "subcategory": "Books",
        "type": "Retail Goods"
      }
    ],
    "sg:phone": "+1 740 385 2850",
    "sg:postcode": "43138",
    "sg:province": "OH",
    "wof:name": "Christian Bookstore",
    "wof:placetype": "venue"
  },
  "geometry": {"coordinates":[-82.407778,39.540136],"type":"Point"}
}
