{
  "type": "Feature",
  "properties": {
    "addr:full":"1200 Portage Trl Cuyahoga Falls OH 44223",
    "addr:housenumber":"1200",
    "addr:postcode":"44223",
    "addr:street":"Portage Trl",
    "iso:country":"US",
    "sg:address":"1200 Portage Trl",
    "sg:city":"Cuyahoga Falls",
    "sg:classifiers":[
        {
            "category":"Professional",
            "subcategory":"Accounting & Tax Preparation",
            "type":"Services"
        }
    ],
    "sg:phone":"+1 330 923 8801",
    "sg:postcode":"44223",
    "sg:province":"OH",
    "sg:tags":[
        "return",
        "filing"
    ],
    "wof:name":"Falls Tax Svc",
    "wof:placetype":"venue"
},
  "geometry": {"coordinates":[-81.497334,41.142925],"type":"Point"}
}