{
  "type": "Feature",
  "properties": {
    "addr:full": "2640 Colonel Glenn Hwy Fairborn OH 45431",
    "addr:housenumber": "2640",
    "addr:postcode": "45431",
    "addr:street": "Colonel Glenn Hwy",
    "iso:country": "US",
    "sg:address": "2640 Colonel Glenn Hwy",
    "sg:city": "Fairborn",
    "sg:classifiers": [
      {
        "category": "Restaurant",
        "type": "Food \u0026 Drink"
      }
    ],
    "sg:phone": "+1 937 426 4688",
    "sg:postcode": "45431",
    "sg:province": "OH",
    "sg:tags": [
      "eating"
    ],
    "wof:name": "Flying Pizza Inc",
    "wof:placetype": "venue"
  },
  "geometry": {"coordinates":[-84.04394,39.78822],"type":"Point"}
}
