{
  "type": "Feature",
  "properties": {
    "iso:country":"US",
    "sg:address":"2640 Colonel Glenn Hwy",
    "sg:city":"Fairborn",
    "sg:classifiers":[
        {
            "category":"Restaurant",
            "type":"Food & Drink"
        }
    ],
    "sg:phone":"+1 937 426 4688",
    "sg:postcode":"45431",
    "sg:province":"OH",
    "sg:tags":[
        "eating"
    ],
    "wof:name":"Flying Pizza Inc",
    "wof:placetype":"venue"
},
  "geometry": {"coordinates":[-84.04394000000001,39.78822],"type":"Point"}
}