{
  "type": "Feature",
  "properties": {
    "iso:country":"US",
    "sg:address":"1200 Valley Belt Rd",
    "sg:city":"Cleveland",
    "sg:classifiers":[
        {
            "category":"Retail",
            "subcategory":"Repair Shop",
            "type":"Services"
        }
    ],
    "sg:phone":"+1 216 749 2010",
    "sg:postcode":"44131",
    "sg:province":"OH",
    "sg:tags":[
        "related"
    ],
    "wof:name":"North Coast Repair Inc",
    "wof:placetype":"venue"
},
  "geometry": {"coordinates":[-81.65600999999999,41.417645],"type":"Point"}
}