{
  "type": "Feature",
  "properties": {
    "addr:full": "1200 Valley Belt Rd Cleveland OH 44131",
    "addr:housenumber": "1200",
    "addr:postcode": "44131",
    "addr:street": "Valley Belt Rd",
    "iso:country": "US",
    "sg:address": "1200 Valley Belt Rd",
    "sg:city": "Cleveland",
    "sg:classifiers": [
      {
        "category": "Retail",
        "subcategory": "Repair Shop",
        "type": "Services"
      }
    ],
    "sg:phone": "+1 216 749 2010",
    "sg:postcode": "44131",
    "sg:province": "OH",
    "sg:tags": [
      "related"
    ],
    "wof:name": "North Coast Repair Inc",
    "wof:placetype": "venue"
  },
  "geometry": {"coordinates":[-81.65601,41.417645],"type":"Point"}
}
