{
  "type": "Feature",
  "properties": {
    "addr:full": "212 Kater Ave Harrison OH 45030",
    "addr:housenumber": "212",
    "addr:postcode": "45030",
    "addr:street": "Kater Ave",
    "iso:country": "US",
    "sg:address": "212 Kater Ave",
    "sg:city": "Harrison",
    "sg:classifiers": [
      {
        "category": "Organizations",
        "subcategory": "Religious Organization",
        "type": "Services"
      }
    ],
    "sg:phone": "+1 513 367 9013",
    "sg:postcode": "45030",
    "sg:province": "OH",
    "sg:tags": [
      "clergy"
    ],
    "wof:name": "H W Shackleford",
    "wof:placetype": "venue"
  },
  "geometry": {"coordinates":[-84.817327,39.259758],"type":"Point"}
}
