{
  "type": "Feature",
  "properties": {
    "addr:full":"940 E David Rd Dayton OH 45429",
    "addr:housenumber":"940",
    "addr:postcode":"45429",
    "addr:street":"E David Rd",
    "iso:country":"US",
    "sg:address":"940 E David Rd",
    "sg:city":"Dayton",
    "sg:classifiers":[
        {
            "category":"Professional",
            "subcategory":"Management & Consulting",
            "type":"Services"
        }
    ],
    "sg:phone":"+1 937 436 2715",
    "sg:postcode":"45429",
    "sg:province":"OH",
    "sg:tags":[
        "food"
    ],
    "wof:name":"Sodexho",
    "wof:placetype":"venue"
},
  "geometry": {"coordinates":[-84.15148000000001,39.680964],"type":"Point"}
}