{
  "type": "Feature",
  "properties": {
    "iso:country":"US",
    "sg:address":"401 Vinton Ave",
    "sg:city":"Mc Arthur",
    "sg:classifiers":[
        {
            "category":"Organizations",
            "subcategory":"Religious Organization",
            "type":"Services"
        }
    ],
    "sg:phone":"+1 740 596 5381",
    "sg:postcode":"45651",
    "sg:province":"OH",
    "sg:tags":[
        "church"
    ],
    "sg:website":"www.ccinoh.org",
    "wof:name":"First Christian Church",
    "wof:placetype":"venue"
},
  "geometry": {"coordinates":[-82.48397199999999,39.251593],"type":"Point"}
}