{
  "type": "Feature",
  "properties": {
    "addr:full": "4707 Coulson Dr Dayton OH 45418",
    "addr:housenumber": "4707",
    "addr:postcode": "45418",
    "addr:street": "Coulson Dr",
    "iso:country": "US",
    "sg:address": "4707 Coulson Dr",
    "sg:city": "Dayton",
    "sg:classifiers": [
      {
        "category": "Food \u0026 Beverages",
        "subcategory": "Liquor \u0026 Beverages",
        "type": "Retail Goods"
      }
    ],
    "sg:phone": "+1 937 263 1124",
    "sg:postcode": "45418",
    "sg:province": "OH",
    "sg:tags": [
      "alcoholic"
    ],
    "wof:name": "Danick Inc",
    "wof:placetype": "venue"
  },
  "geometry": {"coordinates":[-84.267865,39.726381],"type":"Point"}
}
