{
  "type": "Feature",
  "properties": {
    "iso:country":"US",
    "sg:address":"2349 Center Rd",
    "sg:city":"Austinburg",
    "sg:classifiers":[
        {
            "category":"Autos & Motor Vehicles",
            "subcategory":"Fuel & Gas Station",
            "type":"Retail Goods"
        }
    ],
    "sg:phone":"+1 440 275 1515",
    "sg:postcode":"44082",
    "sg:province":"OH",
    "sg:tags":[
        "station",
        "gasoline"
    ],
    "wof:name":"Flying J Travel Plaza",
    "wof:placetype":"venue"
},
  "geometry": {"coordinates":[-80.572155,41.78948],"type":"Point"}
}