{
  "type": "Feature",
  "properties": {
    "addr:full": "1815 Baltimore St Defiance OH 43512",
    "addr:housenumber": "1815",
    "addr:postcode": "43512",
    "addr:street": "Baltimore St",
    "iso:country": "US",
    "sg:address": "1815 Baltimore St",
    "sg:city": "Defiance",
    "sg:classifiers": [
      {
        "category": "Manufacturing",
        "subcategory": "Printing",
        "type": "Manufacturing \u0026 Wholesale Goods"
      }
    ],
    "sg:phone": "+1 419 782 9898",
    "sg:postcode": "43512",
    "sg:province": "OH",
    "sg:tags": [
      "commercial"
    ],
    "wof:name": "Hilltop Printing",
    "wof:placetype": "venue"
  },
  "geometry": {"coordinates":[-84.39184,41.276845],"type":"Point"}
}
