{
  "type": "Feature",
  "properties": {
    "iso:country":"US",
    "sg:address":"1808 Williams Pl",
    "sg:city":"Steubenville",
    "sg:classifiers":[
        {
            "category":"Organizations",
            "subcategory":"Religious Organization",
            "type":"Services"
        }
    ],
    "sg:phone":"+1 740 284 9823",
    "sg:postcode":"43952",
    "sg:province":"OH",
    "sg:tags":[
        "clergy"
    ],
    "wof:name":"Dean J Dimon",
    "wof:placetype":"venue"
},
  "geometry": {"coordinates":[-80.63542,40.373698],"type":"Point"}
}