{
  "type": "Feature",
  "properties": {
    "addr:full": "2038 Anderson Ferry Rd Cincinnati OH 45238",
    "addr:housenumber": "2038",
    "addr:postcode": "45238",
    "addr:street": "Anderson Ferry Rd",
    "iso:country": "US",
    "sg:address": "2038 Anderson Ferry Rd",
    "sg:city": "Cincinnati",
    "sg:classifiers": [
      {
        "category": "Insurance",
        "subcategory": "Insurance Agent",
        "type": "Services"
      }
    ],
    "sg:phone": "+1 513 347 9492",
    "sg:postcode": "45238",
    "sg:province": "OH",
    "wof:name": "American Family Insurance",
    "wof:placetype": "venue"
  },
  "geometry": {"coordinates":[-84.61605,39.126912],"type":"Point"}
}
