{
  "type": "Feature",
  "properties": {
    "addr:full": "5830 Flaig Dr Fairfield OH 45014",
    "addr:housenumber": "5830",
    "addr:postcode": "45014",
    "addr:street": "Flaig Dr",
    "iso:country": "US",
    "sg:address": "5830 Flaig Dr",
    "sg:city": "Fairfield",
    "sg:classifiers": [
      {
        "category": "Building \u0026 Trades",
        "subcategory": "Construction",
        "type": "Services"
      }
    ],
    "sg:phone": "+1 513 870 0064",
    "sg:postcode": "45014",
    "sg:province": "OH",
    "sg:tags": [
      "hanging",
      "contractor"
    ],
    "wof:name": "Faux Finish Interiors",
    "wof:placetype": "venue"
  },
  "geometry": {"coordinates":[-84.523504,39.316223],"type":"Point"}
}
