{
  "type": "Feature",
  "properties": {
    "addr:full":"610 Lauretta Dr Steubenville OH 43952",
    "addr:housenumber":"610",
    "addr:postcode":"43952",
    "addr:street":"Lauretta Dr",
    "iso:country":"US",
    "sg:address":"610 Lauretta Dr",
    "sg:city":"Steubenville",
    "sg:classifiers":[
        {
            "category":"Building & Trades",
            "subcategory":"Construction",
            "type":"Services"
        }
    ],
    "sg:phone":"+1 740 266 3568",
    "sg:postcode":"43952",
    "sg:province":"OH",
    "sg:tags":[
        "house",
        "contractor",
        "roofing"
    ],
    "wof:name":"Homol Construction & Home Inc",
    "wof:placetype":"venue"
},
  "geometry": {"coordinates":[-80.66363800000001,40.363876],"type":"Point"}
}