{
  "type": "Feature",
  "properties": {
    "iso:country":"US",
    "sg:address":"421 N Main St",
    "sg:city":"Payne",
    "sg:classifiers":[
        {
            "category":"Freight",
            "type":"Transportation"
        }
    ],
    "sg:phone":"+1 419 263 2066",
    "sg:postcode":"45880",
    "sg:province":"OH",
    "sg:tags":[
        "commercial",
        "storage"
    ],
    "wof:name":"Storage Depot",
    "wof:placetype":"venue"
},
  "geometry": {"coordinates":[-84.726816,41.083601],"type":"Point"}
}