{
  "type": "Feature",
  "properties": {
    "addr:full": "7701 State Rte 213 Toronto OH 43964",
    "addr:housenumber": "7701",
    "addr:postcode": "43964",
    "addr:street": "State Rte 213",
    "iso:country": "US",
    "sg:address": "7701 State Rte 213",
    "sg:city": "Toronto",
    "sg:classifiers": [
      {
        "category": "Retail",
        "subcategory": "Animal Services",
        "type": "Services"
      }
    ],
    "sg:phone": "+1 740 544 5152",
    "sg:postcode": "43964",
    "sg:province": "OH",
    "sg:tags": [
      "pet",
      "grooming",
      "washing"
    ],
    "wof:name": "Angel's Pet Svc",
    "wof:placetype": "venue"
  },
  "geometry": {"coordinates":[-80.668973,40.475854],"type":"Point"}
}
