{
  "type": "Feature",
  "properties": {
    "iso:country":"US",
    "sg:address":"7701 State Rte 213",
    "sg:city":"Toronto",
    "sg:classifiers":[
        {
            "category":"Retail",
            "subcategory":"Animal Services",
            "type":"Services"
        }
    ],
    "sg:phone":"+1 740 544 5152",
    "sg:postcode":"43964",
    "sg:province":"OH",
    "sg:tags":[
        "pet",
        "grooming",
        "washing"
    ],
    "wof:name":"Angel's Pet Svc",
    "wof:placetype":"venue"
},
  "geometry": {"coordinates":[-80.66897299999999,40.475854],"type":"Point"}
}