{
  "type": "Feature",
  "properties": {
    "iso:country":"US",
    "sg:address":"8581 Twp Rd 551",
    "sg:city":"Shreve",
    "sg:phone":"+1 330 567 3935",
    "sg:postcode":"44676",
    "sg:province":"OH",
    "sg:tags":[
        "farm",
        "grain",
        "cash"
    ],
    "wof:name":"Harvey John",
    "wof:placetype":"venue"
},
  "geometry": {"coordinates":[-81.988034,40.645501],"type":"Point"}
}