{
  "type": "Feature",
  "properties": {
    "addr:full": "6458 US Hwy 6 Vickery OH 43464",
    "addr:housenumber": "6458",
    "addr:postcode": "43464",
    "addr:street": "Us Hwy 6",
    "iso:country": "US",
    "sg:address": "6458 US Hwy 6",
    "sg:city": "Vickery",
    "sg:phone": "+1 419 684 5435",
    "sg:postcode": "43464",
    "sg:province": "OH",
    "sg:tags": [
      "farm",
      "corn",
      "wheat",
      "soybean"
    ],
    "wof:name": "Meggitt Farms",
    "wof:placetype": "venue"
  },
  "geometry": {"coordinates":[-82.884197,41.419284],"type":"Point"}
}
