{
  "type": "Feature",
  "properties": {
    "addr:full":"703 Co Rd 33 Bluffton OH 45817",
    "addr:housenumber":"703;33",
    "addr:postcode":"45817",
    "addr:street":"Co Rd",
    "iso:country":"US",
    "sg:address":"703 Co Rd 33",
    "sg:city":"Bluffton",
    "sg:classifiers":[
        {
            "category":"Farming",
            "subcategory":"Farm",
            "type":"Manufacturing & Wholesale Goods"
        }
    ],
    "sg:phone":"+1 419 358 5302",
    "sg:postcode":"45817",
    "sg:province":"OH",
    "sg:tags":[
        "crop",
        "general"
    ],
    "wof:name":"Wayne Bracy",
    "wof:placetype":"venue"
},
  "geometry": {"coordinates":[-83.872399,40.899689],"type":"Point"}
}