{
  "type": "Feature",
  "properties": {
    "addr:full": "100 S Main Ave Sidney OH 45365",
    "addr:housenumber": "100",
    "addr:postcode": "45365",
    "addr:street": "S Main Ave",
    "iso:country": "US",
    "sg:address": "100 S Main Ave",
    "sg:city": "Sidney",
    "sg:classifiers": [
      {
        "category": "Professional",
        "subcategory": "Lawyer \u0026 Legal Services",
        "type": "Services"
      }
    ],
    "sg:phone": "+1 937 492 1271",
    "sg:postcode": "45365",
    "sg:province": "OH",
    "sg:tags": [
      "attorney"
    ],
    "sg:website": "www.fgks-law.com",
    "wof:name": "Faulkner Garmhausen Keister",
    "wof:placetype": "venue"
  },
  "geometry": {"coordinates":[-84.155104,40.285602],"type":"Point"}
}
