{
  "type": "Feature",
  "properties": {
    "iso:country":"US",
    "sg:address":"100 S Main Ave",
    "sg:city":"Sidney",
    "sg:classifiers":[
        {
            "category":"Professional",
            "subcategory":"Lawyer & Legal Services",
            "type":"Services"
        }
    ],
    "sg:phone":"+1 937 492 1271",
    "sg:postcode":"45365",
    "sg:province":"OH",
    "sg:tags":[
        "attorney"
    ],
    "sg:website":"www.fgks-law.com",
    "wof:name":"Faulkner Garmhausen Keister",
    "wof:placetype":"venue"
},
  "geometry": {"coordinates":[-84.15510399999999,40.285602],"type":"Point"}
}