{
  "type": "Feature",
  "properties": {
    "addr:full":"435 Riverdale Dr Willoughby OH 44095",
    "addr:housenumber":"435",
    "addr:postcode":"44095",
    "addr:street":"Riverdale Dr",
    "iso:country":"US",
    "sg:address":"435 Riverdale Dr",
    "sg:city":"Willoughby",
    "sg:classifiers":[
        {
            "category":"Arts & Performance",
            "subcategory":"Theater",
            "type":"Entertainment"
        }
    ],
    "sg:phone":"+1 440 951 5834",
    "sg:postcode":"44095",
    "sg:province":"OH",
    "sg:tags":[
        "live",
        "music"
    ],
    "wof:name":"Just Music Productions",
    "wof:placetype":"venue"
},
  "geometry": {"coordinates":[-81.411773,41.677114],"type":"Point"}
}