{
  "type": "Feature",
  "properties": {
    "addr:full": "2131 Cloverdale Dr Mansfield OH 44903",
    "addr:housenumber": "2131",
    "addr:postcode": "44903",
    "addr:street": "Cloverdale Dr",
    "iso:country": "US",
    "sg:address": "2131 Cloverdale Dr",
    "sg:city": "Mansfield",
    "sg:classifiers": [
      {
        "category": "Professional",
        "type": "Services"
      }
    ],
    "sg:phone": "+1 419 756 6454",
    "sg:postcode": "44903",
    "sg:province": "OH",
    "sg:tags": [
      "establishment"
    ],
    "wof:name": "Citation Corp",
    "wof:placetype": "venue"
  },
  "geometry": {"coordinates":[-82.525615,40.701223],"type":"Point"}
}
