{
  "type": "Feature",
  "properties": {
    "addr:full": "21665 Center Ridge Rd Rocky River OH 44116",
    "addr:housenumber": "21665",
    "addr:postcode": "44116",
    "addr:street": "Center Ridge Rd",
    "iso:country": "US",
    "sg:address": "21665 Center Ridge Rd",
    "sg:city": "Rocky River",
    "sg:classifiers": [
      {
        "category": "Restaurant",
        "type": "Food \u0026 Drink"
      }
    ],
    "sg:menulink": "http://www.allmenus.com/oh/rocky-river/150830-boston-market/menu/",
    "sg:phone": "+1 440 331 0060",
    "sg:postcode": "44116",
    "sg:province": "OH",
    "sg:tags": [
      "barbecue",
      "american",
      "soup"
    ],
    "wof:name": "Boston Market",
    "wof:placetype": "venue"
  },
  "geometry": {"coordinates":[-81.859485,41.459786],"type":"Point"}
}
