{
  "type": "Feature",
  "properties": {
    "addr:full":"9735 State Rte 201 Dayton OH 45424",
    "addr:housenumber":"9735",
    "addr:postcode":"45424",
    "addr:street":"State Rte 201",
    "iso:country":"US",
    "sg:address":"9735 State Rte 201",
    "sg:city":"Dayton",
    "sg:classifiers":[
        {
            "category":"Manufacturing",
            "subcategory":"Tools & Machinery",
            "type":"Manufacturing & Wholesale Goods"
        }
    ],
    "sg:phone":"+1 937 845 8424",
    "sg:postcode":"45424",
    "sg:province":"OH",
    "sg:tags":[
        "manufacture",
        "core",
        "foundry"
    ],
    "wof:name":"Sinel Company Inc",
    "wof:placetype":"venue"
},
  "geometry": {"coordinates":[-84.098298,39.881958],"type":"Point"}
}