{
  "type": "Feature",
  "properties": {
    "addr:full":"666 Forest Fair Dr Cincinnati OH 45240",
    "addr:housenumber":"666",
    "addr:postcode":"45240",
    "addr:street":"Forest Fair Dr",
    "iso:country":"US",
    "sg:address":"666 Forest Fair Dr",
    "sg:city":"Cincinnati",
    "sg:classifiers":[
        {
            "category":"Food & Beverages",
            "subcategory":"Bakery",
            "type":"Retail Goods"
        }
    ],
    "sg:phone":"+1 513 671 1333",
    "sg:postcode":"45240",
    "sg:province":"OH",
    "sg:tags":[
        "cookie",
        "cracker"
    ],
    "sg:website":"www.greatamericancookies.com",
    "wof:name":"Great American Cookie Co",
    "wof:placetype":"venue"
},
  "geometry": {"coordinates":[-84.52035600000001,39.301107],"type":"Point"}
}