{
  "type": "Feature",
  "properties": {
    "iso:country":"US",
    "sg:address":"1700 W Market St",
    "sg:city":"Akron",
    "sg:classifiers":[
        {
            "category":"Real Estate",
            "subcategory":"Real Estate Agent",
            "type":"Services"
        }
    ],
    "sg:phone":"+1 330 869 9926",
    "sg:postcode":"44313",
    "sg:province":"OH",
    "wof:name":"Real Estate Resolutions Inc",
    "wof:placetype":"venue"
},
  "geometry": {"coordinates":[-81.569534,41.109586],"type":"Point"}
}