{
  "type": "Feature",
  "properties": {
    "iso:country":"US",
    "sg:address":"2061 W 10th St",
    "sg:city":"Cleveland",
    "sg:classifiers":[
        {
            "category":"Restaurant",
            "type":"Food & Drink"
        }
    ],
    "sg:phone":"+1 216 579 0200",
    "sg:postcode":"44113",
    "sg:province":"OH",
    "sg:tags":[
        "eating"
    ],
    "wof:name":"Fat Cats",
    "wof:placetype":"venue"
},
  "geometry": {"coordinates":[-81.687641,41.484568],"type":"Point"}
}