{
  "type": "Feature",
  "properties": {
    "addr:full": "27 S Paint St Chillicothe OH 45601",
    "addr:housenumber": "27",
    "addr:postcode": "45601",
    "addr:street": "S Paint St",
    "iso:country": "US",
    "sg:address": "27 S Paint St",
    "sg:city": "Chillicothe",
    "sg:classifiers": [
      {
        "category": "Insurance",
        "subcategory": "Hazard Insurance",
        "type": "Services"
      }
    ],
    "sg:phone": "+1 740 772 1979",
    "sg:postcode": "45601",
    "sg:province": "OH",
    "sg:tags": [
      "bond"
    ],
    "wof:name": "A",
    "wof:placetype": "venue"
  },
  "geometry": {"coordinates":[-82.981904,39.33271],"type":"Point"}
}
