{
  "type": "Feature",
  "properties": {
    "iso:country":"US",
    "sg:address":"705 Deatrick St",
    "sg:city":"Defiance",
    "sg:classifiers":[
        {
            "category":"Banks & Credit Unions",
            "subcategory":"Bank",
            "type":"Services"
        }
    ],
    "sg:phone":"+1 419 783 8915",
    "sg:postcode":"43512",
    "sg:province":"OH",
    "sg:website":"www.thebank-sbt.com",
    "wof:name":"State Bank & Trust Co",
    "wof:placetype":"venue"
},
  "geometry": {"coordinates":[-84.37661,41.276796],"type":"Point"}
}