{
  "type": "Feature",
  "properties": {
    "addr:full": "520 Springville Ave Fostoria OH 44830",
    "addr:housenumber": "520",
    "addr:postcode": "44830",
    "addr:street": "Springville Ave",
    "iso:country": "US",
    "sg:address": "520 Springville Ave",
    "sg:city": "Fostoria",
    "sg:classifiers": [
      {
        "category": "Home \u0026 Garden",
        "subcategory": "Carpets \u0026 Floor Coverings",
        "type": "Retail Goods"
      }
    ],
    "sg:phone": "+1 419 435 8148",
    "sg:postcode": "44830",
    "sg:province": "OH",
    "sg:tags": [
      "dealer",
      "rug"
    ],
    "wof:name": "Carpet Mart",
    "wof:placetype": "venue"
  },
  "geometry": {"coordinates":[-83.401676,41.148171],"type":"Point"}
}
