{
  "type": "Feature",
  "properties": {
    "addr:full": "3737 Embassy Pkwy Fairlawn OH 44333",
    "addr:housenumber": "3737",
    "addr:postcode": "44333",
    "addr:street": "Embassy Pkwy",
    "iso:country": "US",
    "sg:address": "3737 Embassy Pkwy",
    "sg:city": "Fairlawn",
    "sg:classifiers": [
      {
        "category": "Wholesale",
        "subcategory": "Dairy",
        "type": "Manufacturing \u0026 Wholesale Goods"
      }
    ],
    "sg:phone": "+1 330 670 7800",
    "sg:postcode": "44333",
    "sg:province": "OH",
    "sg:tags": [
      "product"
    ],
    "sg:website": "www.dfamilk.com",
    "wof:name": "Dairy Farmers Of America",
    "wof:placetype": "venue"
  },
  "geometry": {"coordinates":[-81.648205,41.14227],"type":"Point"}
}
