{
  "type": "Feature",
  "properties": {
    "iso:country":"US",
    "sg:address":"3737 Embassy Pkwy",
    "sg:city":"Fairlawn",
    "sg:classifiers":[
        {
            "category":"Wholesale",
            "subcategory":"Dairy",
            "type":"Manufacturing & Wholesale Goods"
        }
    ],
    "sg:phone":"+1 330 670 7800",
    "sg:postcode":"44333",
    "sg:province":"OH",
    "sg:tags":[
        "product"
    ],
    "sg:website":"www.dfamilk.com",
    "wof:name":"Dairy Farmers Of America",
    "wof:placetype":"venue"
},
  "geometry": {"coordinates":[-81.648205,41.14227],"type":"Point"}
}