{
  "type": "Feature",
  "properties": {
    "addr:full": "425 Canton Rd Steubenville OH 43953",
    "addr:housenumber": "425",
    "addr:postcode": "43953",
    "addr:street": "Canton Rd",
    "iso:country": "US",
    "sg:address": "425 Canton Rd",
    "sg:city": "Steubenville",
    "sg:classifiers": [
      {
        "category": "Shopping",
        "subcategory": "Pets \u0026 Pet Supplies",
        "type": "Retail Goods"
      }
    ],
    "sg:phone": "+1 740 266 6300",
    "sg:postcode": "43953",
    "sg:province": "OH",
    "sg:tags": [
      "food",
      "furnishing",
      "dog",
      "store",
      "cat"
    ],
    "wof:name": "The Puppy Place",
    "wof:placetype": "venue"
  },
  "geometry": {"coordinates":[-80.711872,40.381097],"type":"Point"}
}
