{
  "type": "Feature",
  "properties": {
    "addr:full": "1867 W Market St Akron OH 44313",
    "addr:housenumber": "1867",
    "addr:postcode": "44313",
    "addr:street": "W Market St",
    "iso:country": "US",
    "sg:address": "1867 W Market St",
    "sg:city": "Akron",
    "sg:classifiers": [
      {
        "category": "Shopping",
        "subcategory": "Used Merchandise",
        "type": "Retail Goods"
      }
    ],
    "sg:phone": "+1 330 867 4155",
    "sg:postcode": "44313",
    "sg:province": "OH",
    "sg:tags": [
      "shop",
      "consignment"
    ],
    "wof:name": "Act II Boutique",
    "wof:placetype": "venue"
  },
  "geometry": {"coordinates":[-81.57472,41.111971],"type":"Point"}
}
