{
  "type": "Feature",
  "properties": {
    "addr:full": "105 E Elm St Wauseon OH 43567",
    "addr:housenumber": "105",
    "addr:postcode": "43567",
    "addr:street": "E Elm St",
    "iso:country": "US",
    "sg:address": "105 E Elm St",
    "sg:city": "Wauseon",
    "sg:classifiers": [
      {
        "category": "Insurance",
        "subcategory": "Insurance Agent",
        "type": "Services"
      }
    ],
    "sg:phone": "+1 419 335 9736",
    "sg:postcode": "43567",
    "sg:province": "OH",
    "wof:name": "Sally's Insurance",
    "wof:placetype": "venue"
  },
  "geometry": {"coordinates":[-84.138192,41.549788],"type":"Point"}
}
