{
  "type": "Feature",
  "properties": {
    "addr:full": "4559 Grafton Rd Brunswick OH 44212",
    "addr:housenumber": "4559",
    "addr:postcode": "44212",
    "addr:street": "Grafton Rd",
    "iso:country": "US",
    "sg:address": "4559 Grafton Rd",
    "sg:city": "Brunswick",
    "sg:classifiers": [
      {
        "category": "Building \u0026 Trades",
        "subcategory": "Construction",
        "type": "Services"
      }
    ],
    "sg:phone": "+1 440 238 4392",
    "sg:postcode": "44212",
    "sg:province": "OH",
    "sg:tags": [
      "insulation",
      "contractor"
    ],
    "wof:name": "ABC Insulation Company",
    "wof:placetype": "venue"
  },
  "geometry": {"coordinates":[-81.848605,41.260961],"type":"Point"}
}
