{
  "type": "Feature",
  "properties": {
    "iso:country":"US",
    "sg:address":"130 W Ward St",
    "sg:city":"Versailles",
    "sg:classifiers":[
        {
            "category":"Education",
            "subcategory":"School",
            "type":"Public Place"
        }
    ],
    "sg:phone":"+1 937 526 4681",
    "sg:postcode":"45380",
    "sg:province":"OH",
    "sg:website":"www.versailles.k12.oh.us",
    "wof:name":"Versailles Elementary",
    "wof:placetype":"venue"
},
  "geometry": {"coordinates":[-84.485964,40.220723],"type":"Point"}
}