{
  "type": "Feature",
  "properties": {
    "addr:full":"4190 Burbank Rd Wooster OH 44691",
    "addr:housenumber":"4190",
    "addr:postcode":"44691",
    "addr:street":"Burbank Rd",
    "iso:country":"US",
    "sg:address":"4190 Burbank Rd",
    "sg:city":"Wooster",
    "sg:classifiers":[
        {
            "category":"Food & Beverages",
            "subcategory":"Liquor & Beverages",
            "type":"Retail Goods"
        }
    ],
    "sg:phone":"+1 330 202 9028",
    "sg:postcode":"44691",
    "sg:province":"OH",
    "sg:tags":[
        "alcoholic"
    ],
    "wof:name":"Gary's Liquor Agency",
    "wof:placetype":"venue"
},
  "geometry": {"coordinates":[-81.946511,40.84972],"type":"Point"}
}