{
  "type": "Feature",
  "properties": {
    "addr:full": "448 Sun Valley Dr Akron OH 44333",
    "addr:housenumber": "448",
    "addr:postcode": "44333",
    "addr:street": "Sun Valley Dr",
    "iso:country": "US",
    "sg:address": "448 Sun Valley Dr",
    "sg:city": "Akron",
    "sg:classifiers": [
      {
        "category": "Professional",
        "type": "Services"
      }
    ],
    "sg:phone": "+1 330 836 9865",
    "sg:postcode": "44333",
    "sg:province": "OH",
    "wof:name": "George P \u0026 Georgia J Tsar",
    "wof:placetype": "venue"
  },
  "geometry": {"coordinates":[-81.608448,41.137996],"type":"Point"}
}
