{
  "type": "Feature",
  "properties": {
    "addr:full": "2144 Jodilee Ct Columbus OH 43228",
    "addr:housenumber": "2144",
    "addr:postcode": "43228",
    "addr:street": "Jodilee Ct",
    "iso:country": "US",
    "sg:address": "2144 Jodilee Ct",
    "sg:city": "Columbus",
    "sg:classifiers": [
      {
        "category": "Manufacturing",
        "subcategory": "Printing",
        "type": "Manufacturing \u0026 Wholesale Goods"
      }
    ],
    "sg:phone": "+1 614 272 6625",
    "sg:postcode": "43228",
    "sg:province": "OH",
    "sg:tags": [
      "publisher"
    ],
    "wof:name": "Pearson Education",
    "wof:placetype": "venue"
  },
  "geometry": {"coordinates":[-83.107666,39.997022],"type":"Point"}
}
