{
  "type": "Feature",
  "properties": {
    "iso:country":"US",
    "sg:address":"2144 Jodilee Ct",
    "sg:city":"Columbus",
    "sg:classifiers":[
        {
            "category":"Manufacturing",
            "subcategory":"Printing",
            "type":"Manufacturing & Wholesale Goods"
        }
    ],
    "sg:phone":"+1 614 272 6625",
    "sg:postcode":"43228",
    "sg:province":"OH",
    "sg:tags":[
        "publisher"
    ],
    "wof:name":"Pearson Education",
    "wof:placetype":"venue"
},
  "geometry": {"coordinates":[-83.10766599999999,39.997022],"type":"Point"}
}