{
  "type": "Feature",
  "properties": {
    "addr:full": "12523 Buckeye Rd Cleveland OH 44120",
    "addr:housenumber": "12523",
    "addr:postcode": "44120",
    "addr:street": "Buckeye Rd",
    "iso:country": "US",
    "sg:address": "12523 Buckeye Rd",
    "sg:city": "Cleveland",
    "sg:classifiers": [
      {
        "category": "Health Services",
        "subcategory": "Hospital",
        "type": "Services"
      }
    ],
    "sg:phone": "+1 216 752 3260",
    "sg:postcode": "44120",
    "sg:province": "OH",
    "sg:tags": [
      "mental"
    ],
    "wof:name": "Home For TLC",
    "wof:placetype": "venue"
  },
  "geometry": {"coordinates":[-81.595225,41.480262],"type":"Point"}
}
