{
  "type": "Feature",
  "properties": {
    "addr:full":"2045 Perrysburg Holland Rd Holland OH 43528",
    "addr:postcode":"2045;43528",
    "addr:street":"Holland Rd",
    "iso:country":"US",
    "sg:address":"2045 Perrysburg Holland Rd",
    "sg:city":"Holland",
    "sg:classifiers":[
        {
            "category":"Building & Trades",
            "subcategory":"Construction",
            "type":"Services"
        }
    ],
    "sg:phone":"+1 419 725 6302",
    "sg:postcode":"43528",
    "sg:province":"OH",
    "sg:tags":[
        "home",
        "builder"
    ],
    "wof:name":"Lutheran Homes Society",
    "wof:placetype":"venue"
},
  "geometry": {"coordinates":[-83.692184,41.601402],"type":"Point"}
}