{
  "type": "Feature",
  "properties": {
    "addr:full": "1270 N Fairfield Rd Dayton OH 45432",
    "addr:housenumber": "1270",
    "addr:postcode": "45432",
    "addr:street": "N Fairfield Rd",
    "iso:country": "US",
    "sg:address": "1270 N Fairfield Rd",
    "sg:city": "Dayton",
    "sg:classifiers": [
      {
        "category": "Professional",
        "subcategory": "Engineering",
        "type": "Services"
      }
    ],
    "sg:phone": "+1 937 426 2808",
    "sg:postcode": "45432",
    "sg:province": "OH",
    "sg:tags": [
      "motion"
    ],
    "wof:name": "UTC",
    "wof:placetype": "venue"
  },
  "geometry": {"coordinates":[-84.057109,39.727134],"type":"Point"}
}
