{
  "type": "Feature",
  "properties": {
    "addr:full":"9312 Union Ave Cleveland OH 44105",
    "addr:housenumber":"9312",
    "addr:postcode":"44105",
    "addr:street":"Union Ave",
    "iso:country":"US",
    "sg:address":"9312 Union Ave",
    "sg:city":"Cleveland",
    "sg:classifiers":[
        {
            "category":"Organizations",
            "subcategory":"Religious Organization",
            "type":"Services"
        }
    ],
    "sg:phone":"+1 216 883 8044",
    "sg:postcode":"44105",
    "sg:province":"OH",
    "sg:tags":[
        "church"
    ],
    "wof:name":"United Missionary Baptist Chr",
    "wof:placetype":"venue"
},
  "geometry": {"coordinates":[-81.616843,41.463459],"type":"Point"}
}