{
  "type": "Feature",
  "properties": {
    "addr:full": "41 Pineview Dr Painesville OH 44077",
    "addr:housenumber": "41",
    "addr:postcode": "44077",
    "addr:street": "Pineview Dr",
    "iso:country": "US",
    "sg:address": "41 Pineview Dr",
    "sg:city": "Painesville",
    "sg:classifiers": [
      {
        "category": "Professional",
        "type": "Services"
      }
    ],
    "sg:phone": "+1 440 354 2798",
    "sg:postcode": "44077",
    "sg:province": "OH",
    "wof:name": "Free \u0026 Accepted Masons of",
    "wof:placetype": "venue"
  },
  "geometry": {"coordinates":[-81.210334,41.732102],"type":"Point"}
}
