{
  "type": "Feature",
  "properties": {
    "iso:country":"US",
    "sg:address":"631 High St",
    "sg:city":"Ironton",
    "sg:classifiers":[
        {
            "category":"Restaurant",
            "type":"Food & Drink"
        }
    ],
    "sg:phone":"+1 740 533 9117",
    "sg:postcode":"45638",
    "sg:province":"OH",
    "sg:tags":[
        "eating"
    ],
    "wof:name":"Gionnavini Pizza",
    "wof:placetype":"venue"
},
  "geometry": {"coordinates":[-82.64460699999999,38.502229],"type":"Point"}
}