{
  "type": "Feature",
  "properties": {
    "addr:full": "631 High St Ironton OH 45638",
    "addr:housenumber": "631",
    "addr:postcode": "45638",
    "addr:street": "High St",
    "iso:country": "US",
    "sg:address": "631 High St",
    "sg:city": "Ironton",
    "sg:classifiers": [
      {
        "category": "Restaurant",
        "type": "Food \u0026 Drink"
      }
    ],
    "sg:phone": "+1 740 533 9117",
    "sg:postcode": "45638",
    "sg:province": "OH",
    "sg:tags": [
      "eating"
    ],
    "wof:name": "Gionnavini Pizza",
    "wof:placetype": "venue"
  },
  "geometry": {"coordinates":[-82.644607,38.502229],"type":"Point"}
}
