{
  "type": "Feature",
  "properties": {
    "iso:country":"US",
    "sg:address":"720 Columbus-Sandusky Rd S",
    "sg:city":"Marion",
    "sg:classifiers":[
        {
            "category":"Education",
            "subcategory":"School",
            "type":"Public Place"
        }
    ],
    "sg:phone":"+1 740 725 5500",
    "sg:postcode":"43302",
    "sg:province":"OH",
    "wof:name":"Heritage Elementary School",
    "wof:placetype":"venue"
},
  "geometry": {"coordinates":[-83.043102,40.572233],"type":"Point"}
}