{
  "type": "Feature",
  "properties": {
    "addr:full": "2519 Longines Rd Dayton OH 45414",
    "addr:housenumber": "2519",
    "addr:postcode": "45414",
    "addr:street": "Longines Rd",
    "iso:country": "US",
    "sg:address": "2519 Longines Rd",
    "sg:city": "Dayton",
    "sg:classifiers": [
      {
        "category": "Retail",
        "subcategory": "Auto Repair",
        "type": "Services"
      }
    ],
    "sg:phone": "+1 937 277 2886",
    "sg:postcode": "45414",
    "sg:province": "OH",
    "sg:tags": [
      "body",
      "automobile",
      "painting"
    ],
    "wof:name": "Jerry's Auto Repair",
    "wof:placetype": "venue"
  },
  "geometry": {"coordinates":[-84.184719,39.822665],"type":"Point"}
}
