{
  "type": "Feature",
  "properties": {
    "addr:full": "325 Bayview Rd Bay Village OH 44140",
    "addr:housenumber": "325",
    "addr:postcode": "44140",
    "addr:street": "Bayview Rd",
    "iso:country": "US",
    "sg:address": "325 Bayview Rd",
    "sg:city": "Bay Village",
    "sg:classifiers": [
      {
        "category": "Professional",
        "subcategory": "Management \u0026 Consulting",
        "type": "Services"
      }
    ],
    "sg:phone": "+1 440 871 8910",
    "sg:postcode": "44140",
    "sg:province": "OH",
    "wof:name": "Marketing 101",
    "wof:placetype": "venue"
  },
  "geometry": {"coordinates":[-81.95096,41.492243],"type":"Point"}
}
