{
  "type": "Feature",
  "properties": {
    "addr:full": "370 S 5th St Columbus OH 43215",
    "addr:housenumber": "370",
    "addr:postcode": "43215",
    "addr:street": "S 5Th St",
    "iso:country": "US",
    "sg:address": "370 S 5th St",
    "sg:city": "Columbus",
    "sg:classifiers": [
      {
        "category": "Social Services",
        "type": "Services"
      }
    ],
    "sg:phone": "+1 614 341 7700",
    "sg:postcode": "43215",
    "sg:province": "OH",
    "sg:tags": [
      "organization",
      "anti",
      "advocacy"
    ],
    "wof:name": "Childrens Hunger Alliance",
    "wof:placetype": "venue"
  },
  "geometry": {"coordinates":[-82.993181,39.956866],"type":"Point"}
}
