{
  "type": "Feature",
  "properties": {
    "iso:country":"US",
    "sg:address":"3895 Eber Rd",
    "sg:city":"Monclova",
    "sg:classifiers":[
        {
            "category":"Shopping",
            "type":"Retail Goods"
        }
    ],
    "sg:phone":"+1 419 865 9555",
    "sg:postcode":"43542",
    "sg:province":"OH",
    "sg:tags":[
        "merchandise"
    ],
    "wof:name":"Giving Basket Boutique",
    "wof:placetype":"venue"
},
  "geometry": {"coordinates":[-83.78618,41.56958],"type":"Point"}
}