{
  "type": "Feature",
  "properties": {
    "addr:full": "6423 Heritage Park Blvd Dayton OH 45424",
    "addr:housenumber": "6423",
    "addr:postcode": "45424",
    "addr:street": "Heritage Park Blvd",
    "iso:country": "US",
    "sg:address": "6423 Heritage Park Blvd",
    "sg:city": "Dayton",
    "sg:classifiers": [
      {
        "category": "Professional",
        "type": "Services"
      }
    ],
    "sg:phone": "+1 937 237 7914",
    "sg:postcode": "45424",
    "sg:province": "OH",
    "wof:name": "Glenn H Stumpff",
    "wof:placetype": "venue"
  },
  "geometry": {"coordinates":[-84.094585,39.82755],"type":"Point"}
}
