{
  "type": "Feature",
  "properties": {
    "addr:full": "60 W Aurora Rd Northfield OH 44067",
    "addr:housenumber": "60",
    "addr:postcode": "44067",
    "addr:street": "W Aurora Rd",
    "iso:country": "US",
    "sg:address": "60 W Aurora Rd",
    "sg:city": "Northfield",
    "sg:classifiers": [
      {
        "category": "Restaurant",
        "type": "Food \u0026 Drink"
      }
    ],
    "sg:phone": "+1 330 467 7410",
    "sg:postcode": "44067",
    "sg:province": "OH",
    "sg:tags": [
      "eating"
    ],
    "wof:name": "Fire Dept",
    "wof:placetype": "venue"
  },
  "geometry": {"coordinates":[-81.543911,41.314266],"type":"Point"}
}
