{
  "type": "Feature",
  "properties": {
    "addr:full":"117 E 5th St Marysville OH 43040",
    "addr:housenumber":"117",
    "addr:postcode":"43040",
    "addr:street":"E 5Th St",
    "iso:country":"US",
    "sg:address":"117 E 5th St",
    "sg:city":"Marysville",
    "sg:classifiers":[
        {
            "category":"Restaurant",
            "type":"Food & Drink"
        }
    ],
    "sg:phone":"+1 937 642 9200",
    "sg:postcode":"43040",
    "sg:province":"OH",
    "sg:tags":[
        "eating"
    ],
    "wof:name":"Java Town",
    "wof:placetype":"venue"
},
  "geometry": {"coordinates":[-83.366777,40.236325],"type":"Point"}
}