{
  "type": "Feature",
  "properties": {
    "addr:full": "7100 Hidden Valley Dr Amherst OH 44001",
    "addr:housenumber": "7100",
    "addr:postcode": "44001",
    "addr:street": "Hidden Valley Dr",
    "iso:country": "US",
    "sg:address": "7100 Hidden Valley Dr",
    "sg:city": "Amherst",
    "sg:classifiers": [
      {
        "category": "Building \u0026 Trades",
        "subcategory": "Construction",
        "type": "Services"
      }
    ],
    "sg:phone": "+1 440 988 5964",
    "sg:postcode": "44001",
    "sg:province": "OH",
    "sg:tags": [
      "contractor"
    ],
    "wof:name": "Ftb Inc",
    "wof:placetype": "venue"
  },
  "geometry": {"coordinates":[-82.190001,41.397238],"type":"Point"}
}
