{
  "type": "Feature",
  "properties": {
    "addr:full": "900 Sahara Trl Youngstown OH 44514",
    "addr:housenumber": "900",
    "addr:postcode": "44514",
    "addr:street": "Sahara Trl",
    "iso:country": "US",
    "sg:address": "900 Sahara Trl",
    "sg:city": "Youngstown",
    "sg:classifiers": [
      {
        "category": "Health Services",
        "subcategory": "Doctor",
        "type": "Services"
      }
    ],
    "sg:phone": "+1 330 965 8390",
    "sg:postcode": "44514",
    "sg:province": "OH",
    "sg:tags": [
      "physician",
      "surgeon",
      "medical"
    ],
    "sg:website": "www.thereproductivecenter.com",
    "wof:name": "Reproductive Center The",
    "wof:placetype": "venue"
  },
  "geometry": {"coordinates":[-80.638492,40.989107],"type":"Point"}
}
