{
  "type": "Feature",
  "properties": {
    "addr:full": "3322 W 90th St Cleveland OH 44102",
    "addr:housenumber": "3322",
    "addr:postcode": "44102",
    "addr:street": "W 90Th St",
    "iso:country": "US",
    "sg:address": "3322 W 90th St",
    "sg:city": "Cleveland",
    "sg:classifiers": [
      {
        "category": "Food \u0026 Beverages",
        "subcategory": "Groceries \u0026 Convenience Stores",
        "type": "Retail Goods"
      }
    ],
    "sg:phone": "+1 216 281 1937",
    "sg:postcode": "44102",
    "sg:province": "OH",
    "wof:name": "Johns Food Mart",
    "wof:placetype": "venue"
  },
  "geometry": {"coordinates":[-81.745873,41.463397],"type":"Point"}
}
