{
  "type": "Feature",
  "properties": {
    "addr:full":"4819 Laurel Rd Brunswick OH 44212",
    "addr:housenumber":"4819",
    "addr:postcode":"44212",
    "addr:street":"Laurel Rd",
    "iso:country":"US",
    "sg:address":"4819 Laurel Rd",
    "sg:city":"Brunswick",
    "sg:classifiers":[
        {
            "category":"Building & Trades",
            "subcategory":"Construction",
            "type":"Services"
        }
    ],
    "sg:phone":"+1 330 225 4880",
    "sg:postcode":"44212",
    "sg:province":"OH",
    "sg:tags":[
        "concrete",
        "masonry",
        "contractor"
    ],
    "wof:name":"Roy E Grumbling Masonry Inc",
    "wof:placetype":"venue"
},
  "geometry": {"coordinates":[-81.857996,41.226707],"type":"Point"}
}