{
  "type": "Feature",
  "properties": {
    "addr:full":"1787 Elmore St Cincinnati OH 45223",
    "addr:housenumber":"1787",
    "addr:postcode":"45223",
    "addr:street":"Elmore St",
    "iso:country":"US",
    "sg:address":"1787 Elmore St",
    "sg:city":"Cincinnati",
    "sg:classifiers":[
        {
            "category":"Personal",
            "subcategory":"Barber",
            "type":"Services"
        }
    ],
    "sg:phone":"+1 513 681 0523",
    "sg:postcode":"45223",
    "sg:province":"OH",
    "wof:name":"Als Barber Shop",
    "wof:placetype":"venue"
},
  "geometry": {"coordinates":[-84.54765999999999,39.155629],"type":"Point"}
}