{
  "type": "Feature",
  "properties": {
    "addr:full": "2156 US Rte 35 W Englewood OH 45320",
    "addr:housenumber": "2156",
    "addr:postcode": "45320",
    "addr:street": "Us Rte 35 W",
    "iso:country": "US",
    "sg:address": "2156 US Rte 35 W",
    "sg:city": "Englewood",
    "sg:classifiers": [
      {
        "category": "Building \u0026 Trades",
        "subcategory": "Landscaping Services",
        "type": "Services"
      }
    ],
    "sg:phone": "+1 740 335 5990",
    "sg:postcode": "45320",
    "sg:province": "OH",
    "wof:name": "Bentleys Mowing Service",
    "wof:placetype": "venue"
  },
  "geometry": {"coordinates":[-84.66739,39.76161],"type":"Point"}
}
