{
  "type": "Feature",
  "properties": {
    "addr:full":"3345 Dempsey Rd Westerville OH 43081",
    "addr:housenumber":"3345",
    "addr:postcode":"43081",
    "addr:street":"Dempsey Rd",
    "iso:country":"US",
    "sg:address":"3345 Dempsey Rd",
    "sg:city":"Westerville",
    "sg:classifiers":[
        {
            "category":"Retail",
            "subcategory":"Car Wash",
            "type":"Services"
        }
    ],
    "sg:phone":"+1 614 899 1595",
    "sg:postcode":"43081",
    "sg:province":"OH",
    "sg:tags":[
        "polishing",
        "washing"
    ],
    "wof:name":"Miracle Car Wash",
    "wof:placetype":"venue"
},
  "geometry": {"coordinates":[-82.922937,40.095574],"type":"Point"}
}