{
  "type": "Feature",
  "properties": {
    "addr:full": "4555 Groves Rd Columbus OH 43232",
    "addr:housenumber": "4555",
    "addr:postcode": "43232",
    "addr:street": "Groves Rd",
    "iso:country": "US",
    "sg:address": "4555 Groves Rd",
    "sg:city": "Columbus",
    "sg:classifiers": [
      {
        "category": "Building \u0026 Trades",
        "subcategory": "Cleaning \u0026 Sanitation",
        "type": "Services"
      }
    ],
    "sg:phone": "+1 614 755 7775",
    "sg:postcode": "43232",
    "sg:province": "OH",
    "sg:tags": [
      "property",
      "maintenance"
    ],
    "wof:name": "Property Care Svc",
    "wof:placetype": "venue"
  },
  "geometry": {"coordinates":[-82.874067,39.929839],"type":"Point"}
}
