{
  "type": "Feature",
  "properties": {
    "iso:country":"US",
    "sg:address":"4555 Groves Rd",
    "sg:city":"Columbus",
    "sg:classifiers":[
        {
            "category":"Building & Trades",
            "subcategory":"Cleaning & Sanitation",
            "type":"Services"
        }
    ],
    "sg:phone":"+1 614 755 7775",
    "sg:postcode":"43232",
    "sg:province":"OH",
    "sg:tags":[
        "property",
        "maintenance"
    ],
    "wof:name":"Property Care Svc",
    "wof:placetype":"venue"
},
  "geometry": {"coordinates":[-82.874067,39.929839],"type":"Point"}
}