{
  "type": "Feature",
  "properties": {
    "addr:full": "955 E Columbus St Kenton OH 43326",
    "addr:housenumber": "955",
    "addr:postcode": "43326",
    "addr:street": "E Columbus St",
    "iso:country": "US",
    "sg:address": "955 E Columbus St",
    "sg:city": "Kenton",
    "sg:classifiers": [
      {
        "category": "Restaurant",
        "type": "Food \u0026 Drink"
      }
    ],
    "sg:phone": "+1 419 675 2382",
    "sg:postcode": "43326",
    "sg:province": "OH",
    "sg:tags": [
      "eating"
    ],
    "wof:name": "En Lai Chinese Restaurant",
    "wof:placetype": "venue"
  },
  "geometry": {"coordinates":[-83.593091,40.651373],"type":"Point"}
}
