{
  "type": "Feature",
  "properties": {
    "addr:full":"33 N High St Columbus OH 43215",
    "addr:housenumber":"33",
    "addr:postcode":"43215",
    "addr:street":"N High St",
    "iso:country":"US",
    "sg:address":"33 N High St",
    "sg:city":"Columbus",
    "sg:classifiers":[
        {
            "category":"Health Services",
            "subcategory":"Doctor",
            "type":"Services"
        }
    ],
    "sg:phone":"+1 614 221 2910",
    "sg:postcode":"43215",
    "sg:province":"OH",
    "sg:tags":[
        "dentist"
    ],
    "wof:name":"Richard D Sherman DDS",
    "wof:placetype":"venue"
},
  "geometry": {"coordinates":[-83.000978,39.963543],"type":"Point"}
}