{
  "type": "Feature",
  "properties": {
    "addr:full": "13999 Darby Creek Rd Orient OH 43146",
    "addr:housenumber": "13999",
    "addr:postcode": "43146",
    "addr:street": "Darby Creek Rd",
    "iso:country": "US",
    "sg:address": "13999 Darby Creek Rd",
    "sg:city": "Orient",
    "sg:phone": "+1 614 877 9961",
    "sg:postcode": "43146",
    "sg:province": "OH",
    "sg:tags": [
      "farm",
      "grain",
      "cash"
    ],
    "wof:name": "Helen Carter",
    "wof:placetype": "venue"
  },
  "geometry": {"coordinates":[-83.140543,39.735193],"type":"Point"}
}
