{
  "type": "Feature",
  "properties": {
    "iso:country":"US",
    "sg:address":"666 E Hudson St",
    "sg:city":"Columbus",
    "sg:classifiers":[
        {
            "category":"Autos & Motor Vehicles",
            "subcategory":"Fuel & Gas Station",
            "type":"Retail Goods"
        }
    ],
    "sg:phone":"+1 614 447 1833",
    "sg:postcode":"43211",
    "sg:province":"OH",
    "sg:tags":[
        "oil"
    ],
    "wof:name":"Shell Oil Co",
    "wof:placetype":"venue"
},
  "geometry": {"coordinates":[-82.993205,40.014893],"type":"Point"}
}