{
  "type": "Feature",
  "properties": {
    "addr:full": "666 E Hudson St Columbus OH 43211",
    "addr:housenumber": "666",
    "addr:postcode": "43211",
    "addr:street": "E Hudson St",
    "iso:country": "US",
    "sg:address": "666 E Hudson St",
    "sg:city": "Columbus",
    "sg:classifiers": [
      {
        "category": "Autos \u0026 Motor Vehicles",
        "subcategory": "Fuel \u0026 Gas Station",
        "type": "Retail Goods"
      }
    ],
    "sg:phone": "+1 614 447 1833",
    "sg:postcode": "43211",
    "sg:province": "OH",
    "sg:tags": [
      "oil"
    ],
    "wof:name": "Shell Oil Co",
    "wof:placetype": "venue"
  },
  "geometry": {"coordinates":[-82.993205,40.014893],"type":"Point"}
}
