{
  "type": "Feature",
  "properties": {
    "addr:full":"34200 Vine St Willowick OH 44095",
    "addr:housenumber":"34200",
    "addr:postcode":"44095",
    "addr:street":"Vine St",
    "iso:country":"US",
    "sg:address":"34200 Vine St",
    "sg:city":"Willowick",
    "sg:classifiers":[
        {
            "category":"Shopping",
            "subcategory":"Optical Goods",
            "type":"Retail Goods"
        }
    ],
    "sg:phone":"+1 440 942 9315",
    "sg:postcode":"44095",
    "sg:province":"OH",
    "wof:name":"Wal-Mart Vision Ctr",
    "wof:placetype":"venue"
},
  "geometry": {"coordinates":[-81.44392999999999,41.642535],"type":"Point"}
}