{
  "type": "Feature",
  "properties": {
    "addr:full":"502 N Center St Lagrange OH 44050",
    "addr:housenumber":"502",
    "addr:postcode":"44050",
    "addr:street":"N Center St",
    "iso:country":"US",
    "sg:address":"502 N Center St",
    "sg:city":"Lagrange",
    "sg:classifiers":[
        {
            "category":"Organizations",
            "subcategory":"Religious Organization",
            "type":"Services"
        }
    ],
    "sg:phone":"+1 440 355 6366",
    "sg:postcode":"44050",
    "sg:province":"OH",
    "sg:tags":[
        "church"
    ],
    "wof:name":"Lagrange Church Of God",
    "wof:placetype":"venue"
},
  "geometry": {"coordinates":[-82.119681,41.243151],"type":"Point"}
}