{
  "type": "Feature",
  "properties": {
    "iso:country":"US",
    "sg:address":"922 E State St",
    "sg:city":"Athens",
    "sg:classifiers":[
        {
            "category":"Restaurant",
            "type":"Food & Drink"
        }
    ],
    "sg:menulink":"http://www.allmenus.com/oh/athens/195514-mcdonalds/menu/",
    "sg:postcode":"45701",
    "sg:province":"OH",
    "sg:tags":[
        "burger",
        "american"
    ],
    "wof:name":"McDonald's",
    "wof:placetype":"venue"
},
  "geometry": {"coordinates":[-82.069698,39.337005],"type":"Point"}
}