{
  "type": "Feature",
  "properties": {
    "addr:full":"23507 US Hwy 23 Circleville OH 43113",
    "addr:housenumber":"23507",
    "addr:postcode":"43113",
    "addr:street":"Us Hwy 23",
    "iso:country":"US",
    "sg:address":"23507 US Hwy 23",
    "sg:city":"Circleville",
    "sg:classifiers":[
        {
            "category":"Personal",
            "subcategory":"Beauty Salon",
            "type":"Services"
        }
    ],
    "sg:phone":"+1 740 474 9011",
    "sg:postcode":"43113",
    "sg:province":"OH",
    "wof:name":"Fiesta Hair Fashions",
    "wof:placetype":"venue"
},
  "geometry": {"coordinates":[-82.954179,39.589337],"type":"Point"}
}