{
  "type": "Feature",
  "properties": {
    "iso:country":"US",
    "sg:address":"21 US Rte 40 E",
    "sg:city":"Lewisburg",
    "sg:classifiers":[
        {
            "category":"Food & Beverages",
            "subcategory":"Groceries & Convenience Stores",
            "type":"Retail Goods"
        }
    ],
    "sg:phone":"+1 937 678 8245",
    "sg:postcode":"45338",
    "sg:province":"OH",
    "wof:name":"Bob's Nickel-Saver",
    "wof:placetype":"venue"
},
  "geometry": {"coordinates":[-84.62819399999999,39.848147],"type":"Point"}
}