{
  "type": "Feature",
  "properties": {
    "addr:full": "21 US Rte 40 E Lewisburg OH 45338",
    "addr:housenumber": "21",
    "addr:postcode": "45338",
    "addr:street": "Us Rte 40 E",
    "iso:country": "US",
    "sg:address": "21 US Rte 40 E",
    "sg:city": "Lewisburg",
    "sg:classifiers": [
      {
        "category": "Food \u0026 Beverages",
        "subcategory": "Groceries \u0026 Convenience Stores",
        "type": "Retail Goods"
      }
    ],
    "sg:phone": "+1 937 678 8245",
    "sg:postcode": "45338",
    "sg:province": "OH",
    "wof:name": "Bob's Nickel-Saver",
    "wof:placetype": "venue"
  },
  "geometry": {"coordinates":[-84.628194,39.848147],"type":"Point"}
}
