{
  "type": "Feature",
  "properties": {
    "iso:country":"US",
    "sg:address":"447 W. Dussel Dr.",
    "sg:city":"Maumee",
    "sg:classifiers":[
        {
            "category":"Education",
            "subcategory":"College",
            "type":"Public Place"
        },
        {
            "category":"Health Services",
            "subcategory":"Dentist",
            "type":"Services"
        }
    ],
    "sg:phone":"+1 419 724 1774",
    "sg:postcode":"43537",
    "sg:province":"OH",
    "sg:tags":[
        "information",
        "school",
        "dental",
        "dentists-periodontists",
        "dentists-endodontists",
        "referral"
    ],
    "sg:website":"http://www.cornerdental.com",
    "wof:name":"Corner Dental",
    "wof:placetype":"venue"
},
  "geometry": {"coordinates":[-83.67828799999999,41.580446],"type":"Point"}
}