{
  "type": "Feature",
  "properties": {
    "addr:full":"2712 Sherwood Dr Lima OH 45805",
    "addr:housenumber":"2712",
    "addr:postcode":"45805",
    "addr:street":"Sherwood Dr",
    "iso:country":"US",
    "sg:address":"2712 Sherwood Dr",
    "sg:city":"Lima",
    "sg:classifiers":[
        {
            "category":"Wholesale",
            "subcategory":"Construction Materials",
            "type":"Manufacturing & Wholesale Goods"
        }
    ],
    "sg:phone":"+1 419 222 2556",
    "sg:postcode":"45805",
    "sg:province":"OH",
    "sg:tags":[
        "lumber"
    ],
    "wof:name":"Neely and Company",
    "wof:placetype":"venue"
},
  "geometry": {"coordinates":[-84.154162,40.755523],"type":"Point"}
}