{
  "type": "Feature",
  "properties": {
    "addr:full":"1820 McClain Rd Lima OH 45804",
    "addr:housenumber":"1820",
    "addr:postcode":"45804",
    "addr:street":"Mcclain Rd",
    "iso:country":"US",
    "sg:address":"1820 McClain Rd",
    "sg:city":"Lima",
    "sg:classifiers":[
        {
            "category":"Manufacturing",
            "subcategory":"Metals",
            "type":"Manufacturing & Wholesale Goods"
        }
    ],
    "sg:phone":"+1 419 222 4412",
    "sg:postcode":"45804",
    "sg:province":"OH",
    "sg:tags":[
        "steel",
        "blast",
        "works",
        "mfg",
        "shape",
        "furnace"
    ],
    "wof:name":"Superior Forge & Steel Corp",
    "wof:placetype":"venue"
},
  "geometry": {"coordinates":[-84.108378,40.709722],"type":"Point"}
}