{
  "type": "Feature",
  "properties": {
    "addr:full":"1615 Main St Peninsula OH 44264",
    "addr:housenumber":"1615",
    "addr:postcode":"44264",
    "addr:street":"Main St",
    "iso:country":"US",
    "sg:address":"1615 Main St",
    "sg:city":"Peninsula",
    "sg:classifiers":[
        {
            "category":"Restaurant",
            "type":"Food & Drink"
        }
    ],
    "sg:phone":"+1 330 657 2770",
    "sg:postcode":"44264",
    "sg:province":"OH",
    "wof:name":"Winking Lizard Tavern",
    "wof:placetype":"venue"
},
  "geometry": {"coordinates":[-81.549302,41.24133],"type":"Point"}
}