{
  "type": "Feature",
  "properties": {
    "addr:full":"3583 E Broad St Columbus OH 43213",
    "addr:housenumber":"3583",
    "addr:postcode":"43213",
    "addr:street":"E Broad St",
    "iso:country":"US",
    "sg:address":"3583 E Broad St",
    "sg:city":"Columbus",
    "sg:classifiers":[
        {
            "category":"Shopping",
            "subcategory":"Pharmacy",
            "type":"Retail Goods"
        }
    ],
    "sg:phone":"+1 614 237 9111",
    "sg:postcode":"43213",
    "sg:province":"OH",
    "sg:tags":[
        "photofinishing",
        "laboratory"
    ],
    "wof:name":"Walgreens",
    "wof:placetype":"venue"
},
  "geometry": {"coordinates":[-82.903887,39.973015],"type":"Point"}
}