{
  "type": "Feature",
  "properties": {
    "addr:full":"4049 N Dayton Xenia Rd Dayton OH 45432",
    "addr:housenumber":"4049",
    "addr:postcode":"45432",
    "addr:street":"N Dayton Xenia Rd",
    "iso:country":"US",
    "sg:address":"4049 N Dayton Xenia Rd",
    "sg:city":"Dayton",
    "sg:classifiers":[
        {
            "category":"Health Services",
            "subcategory":"Doctor",
            "type":"Services"
        }
    ],
    "sg:phone":"+1 937 429 3880",
    "sg:postcode":"45432",
    "sg:province":"OH",
    "sg:tags":[
        "dentist"
    ],
    "wof:name":"Michael C Ross DDS",
    "wof:placetype":"venue"
},
  "geometry": {"coordinates":[-84.08497199999999,39.737516],"type":"Point"}
}