{
  "type": "Feature",
  "properties": {
    "addr:full": "699 Race St Cincinnati OH 45202",
    "addr:housenumber": "699",
    "addr:postcode": "45202",
    "addr:street": "Race St",
    "iso:country": "US",
    "sg:address": "699 Race St",
    "sg:city": "Cincinnati",
    "sg:classifiers": [
      {
        "category": "Shopping",
        "subcategory": "Department Store",
        "type": "Retail Goods"
      }
    ],
    "sg:phone": "+1 513 361 4410",
    "sg:postcode": "45202",
    "sg:province": "OH",
    "sg:tags": [
      "dept"
    ],
    "wof:name": "Lazarus-Macys",
    "wof:placetype": "venue"
  },
  "geometry": {"coordinates":[-84.51516,39.103111],"type":"Point"}
}
