{
  "type": "Feature",
  "properties": {
    "iso:country":"US",
    "sg:address":"12280 State Rte 38",
    "sg:city":"Marysville",
    "sg:phone":"+1 937 642 3180",
    "sg:postcode":"43040",
    "sg:province":"OH",
    "sg:tags":[
        "farm",
        "soybean"
    ],
    "wof:name":"Norman Eirich",
    "wof:placetype":"venue"
},
  "geometry": {"coordinates":[-83.383224,40.178999],"type":"Point"}
}