{
  "type": "Feature",
  "properties": {
    "addr:full":"8505 State Rte 534 Mesopotamia OH 44439",
    "addr:housenumber":"8505",
    "addr:postcode":"44439",
    "addr:street":"State Rte 534",
    "iso:country":"US",
    "sg:address":"8505 State Rte 534",
    "sg:city":"Mesopotamia",
    "sg:classifiers":[
        {
            "category":"Travel",
            "subcategory":"Hotels & Motels",
            "type":"Entertainment"
        }
    ],
    "sg:phone":"+1 440 693 4186",
    "sg:postcode":"44439",
    "sg:province":"OH",
    "sg:tags":[
        "breakfast",
        "accommodation",
        "bed"
    ],
    "wof:name":"Old Stone House B & B",
    "wof:placetype":"venue"
},
  "geometry": {"coordinates":[-80.95497,41.451423],"type":"Point"}
}