{
  "type": "Feature",
  "properties": {
    "addr:full": "474 Newell St Painesville OH 44077",
    "addr:housenumber": "474",
    "addr:postcode": "44077",
    "addr:street": "Newell St",
    "iso:country": "US",
    "sg:address": "474 Newell St",
    "sg:city": "Painesville",
    "sg:classifiers": [
      {
        "category": "Manufacturing",
        "subcategory": "Rubber \u0026 Plastics",
        "type": "Manufacturing \u0026 Wholesale Goods"
      }
    ],
    "sg:phone": "+1 440 352 3321",
    "sg:postcode": "44077",
    "sg:province": "OH",
    "sg:tags": [
      "extruded",
      "molded",
      "mfg"
    ],
    "wof:name": "S A S Rubber",
    "wof:placetype": "venue"
  },
  "geometry": {"coordinates":[-81.266396,41.719655],"type":"Point"}
}
