{
  "type": "Feature",
  "properties": {
    "addr:full":"11491 Fostoria Rd Bradner OH 43406",
    "addr:housenumber":"11491",
    "addr:postcode":"43406",
    "addr:street":"Fostoria Rd",
    "iso:country":"US",
    "sg:address":"11491 Fostoria Rd",
    "sg:city":"Bradner",
    "sg:classifiers":[
        {
            "category":"Home & Garden",
            "subcategory":"Hardware",
            "type":"Retail Goods"
        }
    ],
    "sg:phone":"+1 419 288 2051",
    "sg:postcode":"43406",
    "sg:province":"OH",
    "sg:tags":[
        "craft"
    ],
    "wof:name":"Bradner True Value Hardware",
    "wof:placetype":"venue"
},
  "geometry": {"coordinates":[-83.41816799999999,41.312526],"type":"Point"}
}