{
  "type": "Feature",
  "properties": {
    "addr:full":"157 S Main St Mansfield OH 44902",
    "addr:housenumber":"157",
    "addr:postcode":"44902",
    "addr:street":"S Main St",
    "iso:country":"US",
    "sg:address":"157 S Main St",
    "sg:city":"Mansfield",
    "sg:classifiers":[
        {
            "category":"Banks & Credit Unions",
            "subcategory":"Bank",
            "type":"Services"
        }
    ],
    "sg:phone":"+1 419 522 7927",
    "sg:postcode":"44902",
    "sg:province":"OH",
    "sg:tags":[
        "loan"
    ],
    "sg:website":"www.swainmortgage.com",
    "wof:name":"Swain Mortgage Co",
    "wof:placetype":"venue"
},
  "geometry": {"coordinates":[-82.515856,40.754073],"type":"Point"}
}