{
  "type": "Feature",
  "properties": {
    "addr:full": "15 E Winter St Delaware OH 43015",
    "addr:housenumber": "15",
    "addr:postcode": "43015",
    "addr:street": "E Winter St",
    "iso:country": "US",
    "sg:address": "15 E Winter St",
    "sg:city": "Delaware",
    "sg:classifiers": [
      {
        "category": "Restaurant",
        "type": "Food \u0026 Drink"
      }
    ],
    "sg:phone": "+1 740 369 5792",
    "sg:postcode": "43015",
    "sg:province": "OH",
    "sg:tags": [
      "sandwich"
    ],
    "wof:name": "Chelley Belly Soup Sandwich",
    "wof:placetype": "venue"
  },
  "geometry": {"coordinates":[-83.067213,40.300216],"type":"Point"}
}
