{
  "type": "Feature",
  "properties": {
    "addr:full": "8148 Springboro Pike Miamisburg OH 45342",
    "addr:housenumber": "8148",
    "addr:postcode": "45342",
    "addr:street": "Springboro Pike",
    "iso:country": "US",
    "sg:address": "8148 Springboro Pike",
    "sg:city": "Miamisburg",
    "sg:classifiers": [
      {
        "category": "Personal",
        "subcategory": "Beauty Salon",
        "type": "Services"
      }
    ],
    "sg:phone": "+1 937 435 5123",
    "sg:postcode": "45342",
    "sg:province": "OH",
    "sg:tags": [
      "shop"
    ],
    "wof:name": "Bo Rics 010 Inc",
    "wof:placetype": "venue"
  },
  "geometry": {"coordinates":[-84.225705,39.63125],"type":"Point"}
}
