{
  "type": "Feature",
  "properties": {
    "addr:full":"305 E 13th St Cincinnati OH 45202",
    "addr:housenumber":"305",
    "addr:postcode":"45202",
    "addr:street":"E 13Th St",
    "iso:country":"US",
    "sg:address":"305 E 13th St",
    "sg:city":"Cincinnati",
    "sg:classifiers":[
        {
            "category":"Shopping",
            "subcategory":"Music",
            "type":"Retail Goods"
        }
    ],
    "sg:phone":"+1 513 721 2029",
    "sg:postcode":"45202",
    "sg:province":"OH",
    "wof:name":"Most Slept On Records Inc",
    "wof:placetype":"venue"
},
  "geometry": {"coordinates":[-84.509773,39.110045],"type":"Point"}
}