{
  "type": "Feature",
  "properties": {
    "addr:full": "125 W Kemper Rd Cincinnati OH 45246",
    "addr:housenumber": "125",
    "addr:postcode": "45246",
    "addr:street": "W Kemper Rd",
    "iso:country": "US",
    "sg:address": "125 W Kemper Rd",
    "sg:city": "Cincinnati",
    "sg:classifiers": [
      {
        "category": "Home \u0026 Garden",
        "subcategory": "Household Appliances",
        "type": "Retail Goods"
      }
    ],
    "sg:phone": "+1 513 671 1500",
    "sg:postcode": "45246",
    "sg:province": "OH",
    "wof:name": "Oreck Authorized Sales \u0026 Svc",
    "wof:placetype": "venue"
  },
  "geometry": {"coordinates":[-84.471845,39.287642],"type":"Point"}
}
