{
  "type": "Feature",
  "properties": {
    "iso:country":"US",
    "sg:address":"125 W Kemper Rd",
    "sg:city":"Cincinnati",
    "sg:classifiers":[
        {
            "category":"Home & Garden",
            "subcategory":"Household Appliances",
            "type":"Retail Goods"
        }
    ],
    "sg:phone":"+1 513 671 1500",
    "sg:postcode":"45246",
    "sg:province":"OH",
    "wof:name":"Oreck Authorized Sales & Svc",
    "wof:placetype":"venue"
},
  "geometry": {"coordinates":[-84.471845,39.287642],"type":"Point"}
}