{
  "type": "Feature",
  "properties": {
    "addr:full": "162 W Union St Athens OH 45701",
    "addr:housenumber": "162",
    "addr:postcode": "45701",
    "addr:street": "W Union St",
    "iso:country": "US",
    "sg:address": "162 W Union St",
    "sg:city": "Athens",
    "sg:classifiers": [
      {
        "category": "Banks \u0026 Credit Unions",
        "subcategory": "Investment Brokerage",
        "type": "Services"
      }
    ],
    "sg:phone": "+1 740 593 3306",
    "sg:postcode": "45701",
    "sg:province": "OH",
    "sg:tags": [
      "security"
    ],
    "wof:name": "Fifth Third Securities Inc",
    "wof:placetype": "venue"
  },
  "geometry": {"coordinates":[-82.10808,39.329503],"type":"Point"}
}
