{
  "type": "Feature",
  "properties": {
    "addr:full": "35534 State Rte 683 Mc Arthur OH 45651",
    "addr:housenumber": "35534",
    "addr:postcode": "45651",
    "addr:street": "State Rte 683 Mc Arthur",
    "iso:country": "US",
    "sg:address": "35534 State Rte 683",
    "sg:city": "Mc Arthur",
    "sg:classifiers": [
      {
        "category": "Manufacturing",
        "subcategory": "Lumber",
        "type": "Manufacturing \u0026 Wholesale Goods"
      }
    ],
    "sg:phone": "+1 740 596 5834",
    "sg:postcode": "45651",
    "sg:province": "OH",
    "sg:tags": [
      "logging"
    ],
    "wof:name": "Lemay Logging",
    "wof:placetype": "venue"
  },
  "geometry": {"coordinates":[-82.560504,39.219118],"type":"Point"}
}
