{
  "type": "Feature",
  "properties": {
    "iso:country":"US",
    "sg:address":"35534 State Rte 683",
    "sg:city":"Mc Arthur",
    "sg:classifiers":[
        {
            "category":"Manufacturing",
            "subcategory":"Lumber",
            "type":"Manufacturing & Wholesale Goods"
        }
    ],
    "sg:phone":"+1 740 596 5834",
    "sg:postcode":"45651",
    "sg:province":"OH",
    "sg:tags":[
        "logging"
    ],
    "wof:name":"Lemay Logging",
    "wof:placetype":"venue"
},
  "geometry": {"coordinates":[-82.56050399999999,39.219118],"type":"Point"}
}