{
  "type": "Feature",
  "properties": {
    "iso:country":"US",
    "sg:address":"7394 E Huntington Dr",
    "sg:city":"Youngstown",
    "sg:classifiers":[
        {
            "category":"Professional",
            "type":"Services"
        }
    ],
    "sg:phone":"+1 330 758 7755",
    "sg:postcode":"44512",
    "sg:province":"OH",
    "wof:name":"Tacalo Nicolas",
    "wof:placetype":"venue"
},
  "geometry": {"coordinates":[-80.706546,41.017936],"type":"Point"}
}