{
  "type": "Feature",
  "properties": {
    "iso:country":"US",
    "sg:address":"650 Ackerman Rd",
    "sg:city":"Columbus",
    "sg:classifiers":[
        {
            "category":"Professional",
            "subcategory":"Management & Consulting",
            "type":"Services"
        }
    ],
    "sg:phone":"+1 614 261 2000",
    "sg:postcode":"43202",
    "sg:province":"OH",
    "sg:tags":[
        "marketing",
        "program"
    ],
    "wof:name":"ABB Inc",
    "wof:placetype":"venue"
},
  "geometry": {"coordinates":[-83.032338,40.018522],"type":"Point"}
}