{
  "type": "Feature",
  "properties": {
    "iso:country":"US",
    "sg:address":"12666 Luthman Rd",
    "sg:city":"Minster",
    "sg:classifiers":[
        {
            "category":"Farming",
            "subcategory":"Farm",
            "type":"Manufacturing & Wholesale Goods"
        }
    ],
    "sg:phone":"+1 419 628 3090",
    "sg:postcode":"45865",
    "sg:province":"OH",
    "wof:name":"Berning Family Farms",
    "wof:placetype":"venue"
},
  "geometry": {"coordinates":[-84.29742299999999,40.385511],"type":"Point"}
}