{
  "type": "Feature",
  "properties": {
    "addr:full": "12666 Luthman Rd Minster OH 45865",
    "addr:housenumber": "12666",
    "addr:postcode": "45865",
    "addr:street": "Luthman Rd",
    "iso:country": "US",
    "sg:address": "12666 Luthman Rd",
    "sg:city": "Minster",
    "sg:classifiers": [
      {
        "category": "Farming",
        "subcategory": "Farm",
        "type": "Manufacturing \u0026 Wholesale Goods"
      }
    ],
    "sg:phone": "+1 419 628 3090",
    "sg:postcode": "45865",
    "sg:province": "OH",
    "wof:name": "Berning Family Farms",
    "wof:placetype": "venue"
  },
  "geometry": {"coordinates":[-84.297423,40.385511],"type":"Point"}
}
