{
  "type": "Feature",
  "properties": {
    "iso:country":"US",
    "sg:address":"1229 Perrysburg Rd",
    "sg:city":"Fostoria",
    "sg:classifiers":[
        {
            "category":"Real Estate",
            "subcategory":"Real Estate Operator",
            "type":"Services"
        }
    ],
    "sg:phone":"+1 419 435 9520",
    "sg:postcode":"44830",
    "sg:province":"OH",
    "sg:tags":[
        "building",
        "apartment"
    ],
    "wof:name":"Portage View Apartments",
    "wof:placetype":"venue"
},
  "geometry": {"coordinates":[-83.422752,41.173017],"type":"Point"}
}