{
  "type": "Feature",
  "properties": {
    "addr:full": "1090 Shangrila Dr Cincinnati OH 45230",
    "addr:housenumber": "1090",
    "addr:postcode": "45230",
    "addr:street": "Shangrila Dr",
    "iso:country": "US",
    "sg:address": "1090 Shangrila Dr",
    "sg:city": "Cincinnati",
    "sg:classifiers": [
      {
        "category": "Professional",
        "type": "Services"
      }
    ],
    "sg:phone": "+1 513 624 0703",
    "sg:postcode": "45230",
    "sg:province": "OH",
    "wof:name": "Racecab of Greater Cincinnati",
    "wof:placetype": "venue"
  },
  "geometry": {"coordinates":[-84.3561,39.072379],"type":"Point"}
}
