{
  "type": "Feature",
  "properties": {
    "addr:full": "820 16th Ave Middletown OH 45044",
    "addr:housenumber": "820",
    "addr:postcode": "45044",
    "addr:street": "16Th Ave",
    "iso:country": "US",
    "sg:address": "820 16th Ave",
    "sg:city": "Middletown",
    "sg:classifiers": [
      {
        "category": "Shopping",
        "subcategory": "Jewelry",
        "type": "Retail Goods"
      }
    ],
    "sg:phone": "+1 513 424 6836",
    "sg:postcode": "45044",
    "sg:province": "OH",
    "wof:name": "Walt \u0026 Son",
    "wof:placetype": "venue"
  },
  "geometry": {"coordinates":[-84.410949,39.499562],"type":"Point"}
}
