{
  "type": "Feature",
  "properties": {
    "iso:country":"US",
    "sg:address":"4812 Dierker Rd",
    "sg:city":"Columbus",
    "sg:classifiers":[
        {
            "category":"Retail",
            "subcategory":"Auto Rental",
            "type":"Services"
        }
    ],
    "sg:phone":"+1 614 457 3800",
    "sg:postcode":"43220",
    "sg:province":"OH",
    "sg:tags":[
        "automobile",
        "leasing"
    ],
    "wof:name":"Premier Auto Leasing",
    "wof:placetype":"venue"
},
  "geometry": {"coordinates":[-83.075496,40.056616],"type":"Point"}
}