{
  "type": "Feature",
  "properties": {
    "addr:full": "400 Linden Ave Dayton OH 45403",
    "addr:housenumber": "400",
    "addr:postcode": "45403",
    "addr:street": "Linden Ave",
    "iso:country": "US",
    "sg:address": "400 Linden Ave",
    "sg:city": "Dayton",
    "sg:classifiers": [
      {
        "category": "Manufacturing",
        "subcategory": "Chemicals \u0026 Compounds",
        "type": "Manufacturing \u0026 Wholesale Goods"
      }
    ],
    "sg:phone": "+1 937 252 2989",
    "sg:postcode": "45403",
    "sg:province": "OH",
    "sg:website": "www.exciton.com",
    "wof:name": "Exciton Inc",
    "wof:placetype": "venue"
  },
  "geometry": {"coordinates":[-84.156055,39.756501],"type":"Point"}
}
