{
  "type": "Feature",
  "properties": {
    "iso:country":"US",
    "sg:address":"2488 Pontius St NE",
    "sg:city":"Hartville",
    "sg:classifiers":[
        {
            "category":"Freight",
            "type":"Transportation"
        }
    ],
    "sg:phone":"+1 330 877 8466",
    "sg:postcode":"44632",
    "sg:province":"OH",
    "sg:tags":[
        "operator",
        "local",
        "trucking"
    ],
    "wof:name":"Destiny Trucking",
    "wof:placetype":"venue"
},
  "geometry": {"coordinates":[-81.30559700000001,40.988483],"type":"Point"}
}