{
  "type": "Feature",
  "properties": {
    "addr:full": "1391 W 110th St Cleveland OH 44102",
    "addr:housenumber": "1391",
    "addr:postcode": "44102",
    "addr:street": "W 110Th St",
    "iso:country": "US",
    "sg:address": "1391 W 110th St",
    "sg:city": "Cleveland",
    "sg:classifiers": [
      {
        "category": "Professional",
        "subcategory": "Business Services",
        "type": "Services"
      }
    ],
    "sg:phone": "+1 216 521 4455",
    "sg:postcode": "44102",
    "sg:province": "OH",
    "sg:tags": [
      "packaging",
      "assembly",
      "contract"
    ],
    "sg:website": "www.americanin.com",
    "wof:name": "American Insourcing",
    "wof:placetype": "venue"
  },
  "geometry": {"coordinates":[-81.762641,41.482306],"type":"Point"}
}
