{
  "type": "Feature",
  "properties": {
    "iso:country":"US",
    "sg:address":"4583 W 150th St",
    "sg:city":"Cleveland",
    "sg:classifiers":[
        {
            "category":"Shopping",
            "subcategory":"Gifts & Souvenirs",
            "type":"Retail Goods"
        }
    ],
    "sg:phone":"+1 216 252 1449",
    "sg:postcode":"44135",
    "sg:province":"OH",
    "sg:tags":[
        "shop"
    ],
    "wof:name":"Cheap Gifts",
    "wof:placetype":"venue"
},
  "geometry": {"coordinates":[-81.801282,41.428923],"type":"Point"}
}