{
  "type": "Feature",
  "properties": {
    "addr:full":"332 S Lincoln St Kent OH 44240",
    "addr:housenumber":"332",
    "addr:postcode":"44240",
    "addr:street":"S Lincoln St",
    "iso:country":"US",
    "sg:address":"332 S Lincoln St",
    "sg:city":"Kent",
    "sg:classifiers":[
        {
            "category":"Shopping",
            "subcategory":"Books",
            "type":"Retail Goods"
        }
    ],
    "sg:phone":"+1 330 673 4730",
    "sg:postcode":"44240",
    "sg:province":"OH",
    "sg:tags":[
        "dealer"
    ],
    "sg:website":"www.duboisbook.com",
    "wof:name":"Dubois Book Store Inc",
    "wof:placetype":"venue"
},
  "geometry": {"coordinates":[-81.35142500000001,41.150366],"type":"Point"}
}