{
  "type": "Feature",
  "properties": {
    "addr:full": "8098 State Rte 243 South Point OH 45680",
    "addr:housenumber": "8098",
    "addr:postcode": "45680",
    "addr:street": "State Rte 243",
    "iso:country": "US",
    "sg:address": "8098 State Rte 243",
    "sg:city": "South Point",
    "sg:classifiers": [
      {
        "category": "Autos \u0026 Motor Vehicles",
        "subcategory": "Automobile Sales",
        "type": "Retail Goods"
      }
    ],
    "sg:phone": "+1 740 867 6334",
    "sg:postcode": "45680",
    "sg:province": "OH",
    "sg:tags": [
      "car",
      "dealer"
    ],
    "wof:name": "Jordan Forest Products",
    "wof:placetype": "venue"
  },
  "geometry": {"coordinates":[-82.535312,38.493068],"type":"Point"}
}
