{
  "type": "Feature",
  "properties": {
    "addr:full":"1900 E 30th St Cleveland OH 44114",
    "addr:housenumber":"1900",
    "addr:postcode":"44114",
    "addr:street":"E 30Th St",
    "iso:country":"US",
    "sg:address":"1900 E 30th St",
    "sg:city":"Cleveland",
    "sg:classifiers":[
        {
            "category":"Real Estate",
            "subcategory":"Real Estate Services",
            "type":"Services"
        },
        {
            "category":"Real Estate",
            "subcategory":"Real Estate Operator",
            "type":"Services"
        }
    ],
    "sg:phone":"+1 216 241 2535",
    "sg:postcode":"44114",
    "sg:province":"OH",
    "sg:tags":[
        "vacancy",
        "apartment",
        "rental",
        "listing"
    ],
    "wof:name":"1900 East Thirtieth St",
    "wof:placetype":"venue"
},
  "geometry": {"coordinates":[-81.667793,41.504509],"type":"Point"}
}