{
  "type": "Feature",
  "properties": {
    "addr:full": "438 W 1st St Uhrichsville OH 44683",
    "addr:housenumber": "438",
    "addr:postcode": "44683",
    "addr:street": "W 1St St",
    "iso:country": "US",
    "sg:address": "438 W 1st St",
    "sg:city": "Uhrichsville",
    "sg:classifiers": [
      {
        "category": "Shopping",
        "type": "Retail Goods"
      }
    ],
    "sg:phone": "+1 740 922 0617",
    "sg:postcode": "44683",
    "sg:province": "OH",
    "sg:tags": [
      "chemical"
    ],
    "wof:name": "Quality",
    "wof:placetype": "venue"
  },
  "geometry": {"coordinates":[-81.350485,40.390026],"type":"Point"}
}
