{
  "type": "Feature",
  "properties": {
    "addr:full": "11061 Prospect Rd Strongsville OH 44149",
    "addr:housenumber": "11061",
    "addr:postcode": "44149",
    "addr:street": "Prospect Rd",
    "iso:country": "US",
    "sg:address": "11061 Prospect Rd",
    "sg:city": "Strongsville",
    "sg:classifiers": [
      {
        "category": "Food \u0026 Beverages",
        "subcategory": "Meat \u0026 Fish",
        "type": "Retail Goods"
      }
    ],
    "sg:phone": "+1 440 846 8440",
    "sg:postcode": "44149",
    "sg:province": "OH",
    "sg:tags": [
      "seafood"
    ],
    "wof:name": "Strongsville Seafood",
    "wof:placetype": "venue"
  },
  "geometry": {"coordinates":[-81.85756,41.336062],"type":"Point"}
}
