{
  "type": "Feature",
  "properties": {
    "iso:country":"US",
    "sg:address":"3700 Northfield Rd",
    "sg:city":"Cleveland",
    "sg:classifiers":[
        {
            "category":"Government",
            "subcategory":"Office",
            "type":"Public Place"
        },
        {
            "category":"Government",
            "subcategory":"Fire Station",
            "type":"Public Place"
        },
        {
            "category":"Government",
            "subcategory":"Police Station",
            "type":"Public Place"
        }
    ],
    "sg:phone":"+1 216 591 1021",
    "sg:postcode":"44122",
    "sg:province":"OH",
    "sg:tags":[
        "department",
        "protection",
        "village"
    ],
    "wof:name":"Highland Hills Police Dept",
    "wof:placetype":"venue"
},
  "geometry": {"coordinates":[-81.533096,41.459901],"type":"Point"}
}