{
  "type": "Feature",
  "properties": {
    "iso:country":"US",
    "sg:address":"404 Ashland Ave",
    "sg:city":"Wapakoneta",
    "sg:classifiers":[
        {
            "category":"Utilities",
            "subcategory":"Telephone",
            "type":"Services"
        }
    ],
    "sg:phone":"+1 419 739 2171",
    "sg:postcode":"45895",
    "sg:province":"OH",
    "sg:tags":[
        "company"
    ],
    "wof:name":"Telephone Service Co",
    "wof:placetype":"venue"
},
  "geometry": {"coordinates":[-84.19990900000001,40.558597],"type":"Point"}
}