{
  "type": "Feature",
  "properties": {
    "addr:full": "404 Ashland Ave Wapakoneta OH 45895",
    "addr:housenumber": "404",
    "addr:postcode": "45895",
    "addr:street": "Ashland Ave",
    "iso:country": "US",
    "sg:address": "404 Ashland Ave",
    "sg:city": "Wapakoneta",
    "sg:classifiers": [
      {
        "category": "Utilities",
        "subcategory": "Telephone",
        "type": "Services"
      }
    ],
    "sg:phone": "+1 419 739 2171",
    "sg:postcode": "45895",
    "sg:province": "OH",
    "sg:tags": [
      "company"
    ],
    "wof:name": "Telephone Service Co",
    "wof:placetype": "venue"
  },
  "geometry": {"coordinates":[-84.199909,40.558597],"type":"Point"}
}
