{
  "type": "Feature",
  "properties": {
    "addr:full":"2896 Woodbury Rd Cleveland OH 44120",
    "addr:housenumber":"2896",
    "addr:postcode":"44120",
    "addr:street":"Woodbury Rd",
    "iso:country":"US",
    "sg:address":"2896 Woodbury Rd",
    "sg:city":"Cleveland",
    "sg:classifiers":[
        {
            "category":"Professional",
            "subcategory":"Management & Consulting",
            "type":"Services"
        }
    ],
    "sg:phone":"+1 216 991 1956",
    "sg:postcode":"44120",
    "sg:province":"OH",
    "sg:tags":[
        "consultant",
        "business"
    ],
    "wof:name":"Social Consultants",
    "wof:placetype":"venue"
},
  "geometry": {"coordinates":[-81.576685,41.478141],"type":"Point"}
}