{
  "type": "Feature",
  "properties": {
    "iso:country":"US",
    "sg:address":"1009 Middle St",
    "sg:city":"Wapakoneta",
    "sg:classifiers":[
        {
            "category":"Building & Trades",
            "subcategory":"Construction",
            "type":"Services"
        }
    ],
    "sg:phone":"+1 419 739 9115",
    "sg:postcode":"45895",
    "sg:province":"OH",
    "sg:tags":[
        "general",
        "contractor"
    ],
    "wof:name":"Cutter Contracting",
    "wof:placetype":"venue"
},
  "geometry": {"coordinates":[-84.181016,40.569855],"type":"Point"}
}