{
  "type": "Feature",
  "properties": {
    "iso:country":"US",
    "sg:address":"3540 Pleasant Hill Rd",
    "sg:city":"Waverly",
    "sg:classifiers":[
        {
            "category":"Building & Trades",
            "subcategory":"Plumbing",
            "type":"Services"
        }
    ],
    "sg:phone":"+1 740 941 4822",
    "sg:postcode":"45690",
    "sg:province":"OH",
    "sg:tags":[
        "contractor"
    ],
    "wof:name":"Comfort Heating & Cooling",
    "wof:placetype":"venue"
},
  "geometry": {"coordinates":[-83.027671,39.14121],"type":"Point"}
}