{
  "type": "Feature",
  "properties": {
    "addr:full": "3450 State Rte 219 New Bremen OH 45869",
    "addr:housenumber": "3450",
    "addr:postcode": "45869",
    "addr:street": "State Rte 219",
    "iso:country": "US",
    "sg:address": "3450 State Rte 219",
    "sg:city": "New Bremen",
    "sg:classifiers": [
      {
        "category": "Building \u0026 Trades",
        "subcategory": "Landscaping Services",
        "type": "Services"
      }
    ],
    "sg:phone": "+1 419 394 6093",
    "sg:postcode": "45869",
    "sg:province": "OH",
    "sg:tags": [
      "lawn",
      "contractor",
      "landscape",
      "maintenance",
      "grounds"
    ],
    "wof:name": "Vehorn Lawn Care Svc",
    "wof:placetype": "venue"
  },
  "geometry": {"coordinates":[-84.38834,40.495035],"type":"Point"}
}
