{
  "type": "Feature",
  "properties": {
    "addr:full":"2542 Germantown St Dayton OH 45408",
    "addr:housenumber":"2542",
    "addr:postcode":"45408",
    "addr:street":"Germantown St",
    "iso:country":"US",
    "sg:address":"2542 Germantown St",
    "sg:city":"Dayton",
    "sg:classifiers":[
        {
            "category":"Education",
            "subcategory":"Library",
            "type":"Public Place"
        }
    ],
    "sg:phone":"+1 937 227 9510",
    "sg:postcode":"45408",
    "sg:province":"OH",
    "wof:name":"Madden Hills Branch Library",
    "wof:placetype":"venue"
},
  "geometry": {"coordinates":[-84.235094,39.740432],"type":"Point"}
}