{
  "type": "Feature",
  "properties": {
    "iso:country":"US",
    "sg:address":"201 E Main St",
    "sg:city":"Deshler",
    "sg:classifiers":[
        {
            "category":"Retail",
            "subcategory":"Auto Repair",
            "type":"Services"
        }
    ],
    "sg:phone":"+1 419 278 1319",
    "sg:postcode":"43516",
    "sg:province":"OH",
    "sg:tags":[
        "repairing",
        "automobile"
    ],
    "wof:name":"T N T's Body Shop",
    "wof:placetype":"venue"
},
  "geometry": {"coordinates":[-83.89978499999999,41.206342],"type":"Point"}
}