{
  "type": "Feature",
  "properties": {
    "addr:full": "212 W Bowman St Wooster OH 44691",
    "addr:housenumber": "212",
    "addr:postcode": "44691",
    "addr:street": "W Bowman St",
    "iso:country": "US",
    "sg:address": "212 W Bowman St",
    "sg:city": "Wooster",
    "sg:classifiers": [
      {
        "category": "Real Estate",
        "subcategory": "Architect",
        "type": "Services"
      }
    ],
    "sg:phone": "+1 330 262 7785",
    "sg:postcode": "44691",
    "sg:province": "OH",
    "wof:name": "Speirs Architectural Design",
    "wof:placetype": "venue"
  },
  "geometry": {"coordinates":[-81.943295,40.804408],"type":"Point"}
}
