{
  "type": "Feature",
  "properties": {
    "addr:full":"4280 Jennifer Dr Hamilton IN 45013",
    "addr:housenumber":"4280",
    "addr:postcode":"45013",
    "addr:street":"Jennifer Dr",
    "iso:country":"US",
    "sg:address":"4280 Jennifer Dr",
    "sg:city":"Hamilton",
    "sg:classifiers":[
        {
            "category":"Building & Trades",
            "subcategory":"Landscaping Services",
            "type":"Services"
        }
    ],
    "sg:phone":"+1 513 738 1919",
    "sg:postcode":"45013",
    "sg:province":"IN",
    "sg:tags":[
        "landscape"
    ],
    "wof:name":"Peters Landscaping",
    "wof:placetype":"venue"
},
  "geometry": {"coordinates":[-84.660871,39.314989],"type":"Point"}
}