{
  "type": "Feature",
  "properties": {
    "addr:full": "153 Carpenter Rd N Brunswick OH 44212",
    "addr:housenumber": "153",
    "addr:postcode": "44212",
    "addr:street": "Carpenter Rd N",
    "iso:country": "US",
    "sg:address": "153 Carpenter Rd N",
    "sg:city": "Brunswick",
    "sg:phone": "+1 330 273 1976",
    "sg:postcode": "44212",
    "sg:province": "OH",
    "sg:tags": [
      "farm",
      "corn",
      "soybean"
    ],
    "wof:name": "Waite Farms",
    "wof:placetype": "venue"
  },
  "geometry": {"coordinates":[-81.807827,41.270606],"type":"Point"}
}
