{
  "type": "Feature",
  "properties": {
    "iso:country":"US",
    "sg:address":"1914 Seminary Rd",
    "sg:city":"Milan",
    "sg:classifiers":[
        {
            "category":"Shopping",
            "subcategory":"Clothing, Apparel, & Fashions",
            "type":"Retail Goods"
        }
    ],
    "sg:phone":"+1 419 499 2132",
    "sg:postcode":"44846",
    "sg:province":"OH",
    "wof:name":"Joseph & Jo Ann Taylor",
    "wof:placetype":"venue"
},
  "geometry": {"coordinates":[-82.588901,41.289611],"type":"Point"}
}