{
  "type": "Feature",
  "properties": {
    "iso:country":"US",
    "sg:address":"3630 E Kemper Rd",
    "sg:city":"Cincinnati",
    "sg:classifiers":[
        {
            "category":"Wholesale",
            "subcategory":"Chemicals & Plastics",
            "type":"Manufacturing & Wholesale Goods"
        }
    ],
    "sg:phone":"+1 513 956 4600",
    "sg:postcode":"45241",
    "sg:province":"OH",
    "sg:tags":[
        "distributes",
        "product",
        "branded",
        "commercial",
        "cleaning"
    ],
    "wof:name":"Consumer Branded Prof Pdts",
    "wof:placetype":"venue"
},
  "geometry": {"coordinates":[-84.40714199999999,39.283144],"type":"Point"}
}