{
  "type": "Feature",
  "properties": {
    "addr:full": "3630 E Kemper Rd Cincinnati OH 45241",
    "addr:housenumber": "3630",
    "addr:postcode": "45241",
    "addr:street": "E Kemper Rd",
    "iso:country": "US",
    "sg:address": "3630 E Kemper Rd",
    "sg:city": "Cincinnati",
    "sg:classifiers": [
      {
        "category": "Wholesale",
        "subcategory": "Chemicals \u0026 Plastics",
        "type": "Manufacturing \u0026 Wholesale Goods"
      }
    ],
    "sg:phone": "+1 513 956 4600",
    "sg:postcode": "45241",
    "sg:province": "OH",
    "sg:tags": [
      "distributes",
      "product",
      "branded",
      "commercial",
      "cleaning"
    ],
    "wof:name": "Consumer Branded Prof Pdts",
    "wof:placetype": "venue"
  },
  "geometry": {"coordinates":[-84.407142,39.283144],"type":"Point"}
}
