{
  "type": "Feature",
  "properties": {
    "addr:full":"225 Collins Ave Marysville OH 43040",
    "addr:housenumber":"225",
    "addr:postcode":"43040",
    "addr:street":"Collins Ave",
    "iso:country":"US",
    "sg:address":"225 Collins Ave",
    "sg:city":"Marysville",
    "sg:classifiers":[
        {
            "category":"Retail",
            "subcategory":"Laundry & Dry Cleaning",
            "type":"Services"
        }
    ],
    "sg:phone":"+1 937 642 8398",
    "sg:postcode":"43040",
    "sg:province":"OH",
    "wof:name":"Collins Ave Laundry",
    "wof:placetype":"venue"
},
  "geometry": {"coordinates":[-83.37085500000001,40.230911],"type":"Point"}
}