{
  "type": "Feature",
  "properties": {
    "addr:full":"615 W 2nd St Defiance OH 43512",
    "addr:housenumber":"615",
    "addr:postcode":"43512",
    "addr:street":"W 2Nd St",
    "iso:country":"US",
    "sg:address":"615 W 2nd St",
    "sg:city":"Defiance",
    "sg:classifiers":[
        {
            "category":"Retail",
            "subcategory":"Laundry & Dry Cleaning",
            "type":"Services"
        }
    ],
    "sg:phone":"+1 419 782 5866",
    "sg:postcode":"43512",
    "sg:province":"OH",
    "sg:tags":[
        "cleaners"
    ],
    "wof:name":"Deluxe Cleaners",
    "wof:placetype":"venue"
},
  "geometry": {"coordinates":[-84.362315,41.286716],"type":"Point"}
}