{
  "type": "Feature",
  "properties": {
    "addr:full": "4470 Beechwood Ave Alliance OH 44601",
    "addr:housenumber": "4470",
    "addr:postcode": "44601",
    "addr:street": "Beechwood Ave",
    "iso:country": "US",
    "sg:address": "4470 Beechwood Ave",
    "sg:city": "Alliance",
    "sg:classifiers": [
      {
        "category": "Organizations",
        "subcategory": "Religious Organization",
        "type": "Services"
      }
    ],
    "sg:phone": "+1 330 821 0670",
    "sg:postcode": "44601",
    "sg:province": "OH",
    "sg:tags": [
      "church"
    ],
    "wof:name": "Freeburg Church-The Brethren",
    "wof:placetype": "venue"
  },
  "geometry": {"coordinates":[-81.133829,40.876605],"type":"Point"}
}
