{
  "type": "Feature",
  "properties": {
    "iso:country":"US",
    "sg:address":"170 Pearl St",
    "sg:city":"Jackson",
    "sg:classifiers":[
        {
            "category":"Organizations",
            "subcategory":"Community Association",
            "type":"Services"
        }
    ],
    "sg:phone":"+1 740 286 4200",
    "sg:postcode":"45640",
    "sg:province":"OH",
    "sg:tags":[
        "military"
    ],
    "sg:website":"www.dav.org",
    "wof:name":"Disabled American Veterans",
    "wof:placetype":"venue"
},
  "geometry": {"coordinates":[-82.63975499999999,39.052431],"type":"Point"}
}