{
  "type": "Feature",
  "properties": {
    "addr:full": "671 Camden Yard Ct Columbus OH 43235",
    "addr:housenumber": "671",
    "addr:postcode": "43235",
    "addr:street": "Camden Yard Ct",
    "iso:country": "US",
    "sg:address": "671 Camden Yard Ct",
    "sg:city": "Columbus",
    "sg:classifiers": [
      {
        "category": "Professional",
        "subcategory": "Management \u0026 Consulting",
        "type": "Services"
      }
    ],
    "sg:phone": "+1 614 457 9219",
    "sg:postcode": "43235",
    "sg:province": "OH",
    "sg:tags": [
      "business"
    ],
    "wof:name": "Corporate Fin Assoc of Clumbus",
    "wof:placetype": "venue"
  },
  "geometry": {"coordinates":[-83.03778,40.066041],"type":"Point"}
}
