{
  "type": "Feature",
  "properties": {
    "iso:country":"US",
    "sg:address":"2189 Pamer Dr",
    "sg:city":"Akron",
    "sg:classifiers":[
        {
            "category":"Building & Trades",
            "subcategory":"Landscaping Services",
            "type":"Services"
        }
    ],
    "sg:phone":"+1 330 773 8921",
    "sg:postcode":"44319",
    "sg:province":"OH",
    "wof:name":"Pro Cut Lawn Service",
    "wof:placetype":"venue"
},
  "geometry": {"coordinates":[-81.503585,41.019275],"type":"Point"}
}