{
  "type": "Feature",
  "properties": {
    "addr:full": "500 E Front St Perrysburg OH 43551",
    "addr:housenumber": "500",
    "addr:postcode": "43551",
    "addr:street": "E Front St",
    "iso:country": "US",
    "sg:address": "500 E Front St",
    "sg:city": "Perrysburg",
    "sg:classifiers": [
      {
        "category": "Professional",
        "subcategory": "Art Services",
        "type": "Services"
      }
    ],
    "sg:phone": "+1 419 873 0500",
    "sg:postcode": "43551",
    "sg:province": "OH",
    "sg:tags": [
      "graphic",
      "designer"
    ],
    "wof:name": "Lesniewicz",
    "wof:placetype": "venue"
  },
  "geometry": {"coordinates":[-83.618321,41.564775],"type":"Point"}
}
