{
  "type": "Feature",
  "properties": {
    "iso:country":"US",
    "sg:address":"308 Hoopengarner St",
    "sg:city":"Wapakoneta",
    "sg:classifiers":[
        {
            "category":"Organizations",
            "subcategory":"Religious Organization",
            "type":"Services"
        }
    ],
    "sg:phone":"+1 419 738 7352",
    "sg:postcode":"45895",
    "sg:province":"OH",
    "sg:tags":[
        "church"
    ],
    "wof:name":"Williams Street Chapel",
    "wof:placetype":"venue"
},
  "geometry": {"coordinates":[-84.19931,40.577997],"type":"Point"}
}