{
  "type": "Feature",
  "properties": {
    "addr:full": "960 Kenmore Blvd Akron OH 44314",
    "addr:housenumber": "960",
    "addr:postcode": "44314",
    "addr:street": "Kenmore Blvd",
    "iso:country": "US",
    "sg:address": "960 Kenmore Blvd",
    "sg:city": "Akron",
    "sg:classifiers": [
      {
        "category": "Shopping",
        "subcategory": "Used Merchandise",
        "type": "Retail Goods"
      }
    ],
    "sg:phone": "+1 330 753 3222",
    "sg:postcode": "44314",
    "sg:province": "OH",
    "sg:tags": [
      "appliance"
    ],
    "wof:name": "Anshutz Appliance",
    "wof:placetype": "venue"
  },
  "geometry": {"coordinates":[-81.557556,41.043603],"type":"Point"}
}
