{
  "type": "Feature",
  "properties": {
    "iso:country":"US",
    "sg:address":"960 Kenmore Blvd",
    "sg:city":"Akron",
    "sg:classifiers":[
        {
            "category":"Shopping",
            "subcategory":"Used Merchandise",
            "type":"Retail Goods"
        }
    ],
    "sg:phone":"+1 330 753 3222",
    "sg:postcode":"44314",
    "sg:province":"OH",
    "sg:tags":[
        "appliance"
    ],
    "wof:name":"Anshutz Appliance",
    "wof:placetype":"venue"
},
  "geometry": {"coordinates":[-81.55755600000001,41.043603],"type":"Point"}
}