{
  "type": "Feature",
  "properties": {
    "addr:full": "2721 Daleford Ave NE Canton OH 44705",
    "addr:housenumber": "2721",
    "addr:postcode": "44705",
    "addr:street": "Daleford Ave Ne",
    "iso:country": "US",
    "sg:address": "2721 Daleford Ave NE",
    "sg:city": "Canton",
    "sg:classifiers": [
      {
        "category": "Wholesale",
        "subcategory": "Non-durable Goods",
        "type": "Manufacturing \u0026 Wholesale Goods"
      }
    ],
    "sg:phone": "+1 330 454 9484",
    "sg:postcode": "44705",
    "sg:province": "OH",
    "sg:tags": [
      "pet",
      "supply"
    ],
    "wof:name": "Heddy Peddy Dashers",
    "wof:placetype": "venue"
  },
  "geometry": {"coordinates":[-81.323397,40.82753],"type":"Point"}
}
