{
  "type": "Feature",
  "properties": {
    "iso:country":"US",
    "sg:address":"2721 Daleford Ave NE",
    "sg:city":"Canton",
    "sg:classifiers":[
        {
            "category":"Wholesale",
            "subcategory":"Non-durable Goods",
            "type":"Manufacturing & Wholesale Goods"
        }
    ],
    "sg:phone":"+1 330 454 9484",
    "sg:postcode":"44705",
    "sg:province":"OH",
    "sg:tags":[
        "pet",
        "supply"
    ],
    "wof:name":"Heddy Peddy Dashers",
    "wof:placetype":"venue"
},
  "geometry": {"coordinates":[-81.323397,40.82753],"type":"Point"}
}