{
  "type": "Feature",
  "properties": {
    "iso:country":"US",
    "sg:address":"16697 S Franklin St",
    "sg:city":"Chagrin Falls",
    "sg:classifiers":[
        {
            "category":"Organizations",
            "subcategory":"Religious Organization",
            "type":"Services"
        }
    ],
    "sg:phone":"+1 440 247 5485",
    "sg:postcode":"44023",
    "sg:province":"OH",
    "wof:name":"Union Bethel A M E Church",
    "wof:placetype":"venue"
},
  "geometry": {"coordinates":[-81.391701,41.415501],"type":"Point"}
}