{
  "type": "Feature",
  "properties": {
    "addr:full": "3308 State Rte 183 Atwater OH 44201",
    "addr:housenumber": "3308",
    "addr:postcode": "44201",
    "addr:street": "State Rte 183",
    "iso:country": "US",
    "sg:address": "3308 State Rte 183",
    "sg:city": "Atwater",
    "sg:classifiers": [
      {
        "category": "Manufacturing",
        "subcategory": "Rubber \u0026 Plastics",
        "type": "Manufacturing \u0026 Wholesale Goods"
      }
    ],
    "sg:phone": "+1 330 947 3277",
    "sg:postcode": "44201",
    "sg:province": "OH",
    "sg:tags": [
      "product",
      "printing",
      "metal"
    ],
    "wof:name": "Design Plastics",
    "wof:placetype": "venue"
  },
  "geometry": {"coordinates":[-81.145777,41.081475],"type":"Point"}
}
