{
  "type": "Feature",
  "properties": {
    "iso:country":"US",
    "sg:address":"3308 State Rte 183",
    "sg:city":"Atwater",
    "sg:classifiers":[
        {
            "category":"Manufacturing",
            "subcategory":"Rubber & Plastics",
            "type":"Manufacturing & Wholesale Goods"
        }
    ],
    "sg:phone":"+1 330 947 3277",
    "sg:postcode":"44201",
    "sg:province":"OH",
    "sg:tags":[
        "product",
        "printing",
        "metal"
    ],
    "wof:name":"Design Plastics",
    "wof:placetype":"venue"
},
  "geometry": {"coordinates":[-81.145777,41.081475],"type":"Point"}
}