{
  "type": "Feature",
  "properties": {
    "addr:full": "12600 Triskett Rd Cleveland OH 44111",
    "addr:housenumber": "12600",
    "addr:postcode": "44111",
    "addr:street": "Triskett Rd",
    "iso:country": "US",
    "sg:address": "12600 Triskett Rd",
    "sg:city": "Cleveland",
    "sg:classifiers": [
      {
        "category": "Building \u0026 Trades",
        "subcategory": "Construction",
        "type": "Services"
      }
    ],
    "sg:phone": "+1 440 333 3572",
    "sg:postcode": "44111",
    "sg:province": "OH",
    "sg:tags": [
      "general",
      "contractor"
    ],
    "wof:name": "Krueger Grealis \u0026 Assoc Inc",
    "wof:placetype": "venue"
  },
  "geometry": {"coordinates":[-81.777851,41.464563],"type":"Point"}
}
