{
  "type": "Feature",
  "properties": {
    "addr:full":"1900 Elida Rd Lima OH 45805",
    "addr:postcode":"1900;45805",
    "addr:street":"Elida Rd",
    "iso:country":"US",
    "sg:address":"1900 Elida Rd",
    "sg:city":"Lima",
    "sg:classifiers":[
        {
            "category":"Retail",
            "subcategory":"Portrait Studio",
            "type":"Services"
        }
    ],
    "sg:phone":"+1 419 228 1111",
    "sg:postcode":"45805",
    "sg:province":"OH",
    "sg:tags":[
        "photographer"
    ],
    "wof:name":"Studio One",
    "wof:placetype":"venue"
},
  "geometry": {"coordinates":[-84.13835899999999,40.757703],"type":"Point"}
}