{
  "type": "Feature",
  "properties": {
    "iso:country":"US",
    "sg:address":"402 Aetna St",
    "sg:city":"Martins Ferry",
    "sg:classifiers":[
        {
            "category":"Restaurant",
            "type":"Food & Drink"
        }
    ],
    "sg:menulink":"http://www.allmenus.com/oh/pease/237776-rax/menu/",
    "sg:phone":"+1 330 339 4447",
    "sg:postcode":"43935",
    "sg:province":"OH",
    "sg:tags":[
        "wrap",
        "american",
        "sandwich"
    ],
    "wof:name":"Rax",
    "wof:placetype":"venue"
},
  "geometry": {"coordinates":[-80.734988,40.084879],"type":"Point"}
}