{
  "type": "Feature",
  "properties": {
    "iso:country":"US",
    "sg:address":"10907 Hollow Rd SW",
    "sg:city":"Pataskala",
    "sg:classifiers":[
        {
            "category":"Banks & Credit Unions",
            "subcategory":"Financial Services",
            "type":"Services"
        }
    ],
    "sg:phone":"+1 740 927 8843",
    "sg:postcode":"43062",
    "sg:province":"OH",
    "sg:tags":[
        "investment",
        "closed"
    ],
    "wof:name":"S&C Iacono Ltd",
    "wof:placetype":"venue"
},
  "geometry": {"coordinates":[-82.693095,40.039267],"type":"Point"}
}