{
  "type": "Feature",
  "properties": {
    "addr:full": "10907 Hollow Rd SW Pataskala OH 43062",
    "addr:housenumber": "10907",
    "addr:postcode": "43062",
    "addr:street": "Hollow Rd Sw",
    "iso:country": "US",
    "sg:address": "10907 Hollow Rd SW",
    "sg:city": "Pataskala",
    "sg:classifiers": [
      {
        "category": "Banks \u0026 Credit Unions",
        "subcategory": "Financial Services",
        "type": "Services"
      }
    ],
    "sg:phone": "+1 740 927 8843",
    "sg:postcode": "43062",
    "sg:province": "OH",
    "sg:tags": [
      "investment",
      "closed"
    ],
    "wof:name": "S\u0026C Iacono Ltd",
    "wof:placetype": "venue"
  },
  "geometry": {"coordinates":[-82.693095,40.039267],"type":"Point"}
}
