{
  "type": "Feature",
  "properties": {
    "addr:full": "2600 N Reynolds Rd Toledo OH 43615",
    "addr:housenumber": "2600",
    "addr:postcode": "43615",
    "addr:street": "N Reynolds Rd",
    "iso:country": "US",
    "sg:address": "2600 N Reynolds Rd",
    "sg:city": "Toledo",
    "sg:classifiers": [
      {
        "category": "Professional",
        "subcategory": "Accounting \u0026 Tax Preparation",
        "type": "Services"
      }
    ],
    "sg:phone": "+1 419 536 3784",
    "sg:postcode": "43615",
    "sg:province": "OH",
    "sg:tags": [
      "bookkeeping",
      "general"
    ],
    "wof:name": "Bourquin \u0026 Assoc",
    "wof:placetype": "venue"
  },
  "geometry": {"coordinates":[-83.668083,41.669937],"type":"Point"}
}
