{
  "type": "Feature",
  "properties": {
    "iso:country":"US",
    "sg:address":"400 Reading Rd",
    "sg:city":"Mason",
    "sg:classifiers":[
        {
            "category":"Retail",
            "subcategory":"Funeral Services",
            "type":"Services"
        }
    ],
    "sg:phone":"+1 513 398 2911",
    "sg:postcode":"45040",
    "sg:province":"OH",
    "sg:tags":[
        "director"
    ],
    "sg:website":"http://www.shortenandryan.com",
    "wof:name":"Shorten & Ryan Funeral Home Inc",
    "wof:placetype":"venue"
},
  "geometry": {"coordinates":[-84.315224,39.35762],"type":"Point"}
}