{
  "type": "Feature",
  "properties": {
    "iso:country":"US",
    "sg:address":"111 Mound St",
    "sg:city":"Brookville",
    "sg:classifiers":[
        {
            "category":"Professional",
            "subcategory":"Accounting & Tax Preparation",
            "type":"Services"
        }
    ],
    "sg:phone":"+1 937 833 4914",
    "sg:postcode":"45309",
    "sg:province":"OH",
    "sg:tags":[
        "accountant"
    ],
    "wof:name":"Sdt Communications Inc",
    "wof:placetype":"venue"
},
  "geometry": {"coordinates":[-84.42195100000001,39.835366],"type":"Point"}
}