{
  "type": "Feature",
  "properties": {
    "addr:full":"51 S Souder Ave Columbus OH 43222",
    "addr:housenumber":"51",
    "addr:postcode":"43222",
    "addr:street":"S Souder Ave",
    "iso:country":"US",
    "sg:address":"51 S Souder Ave",
    "sg:city":"Columbus",
    "sg:classifiers":[
        {
            "category":"Health Services",
            "subcategory":"Doctor",
            "type":"Services"
        }
    ],
    "sg:phone":"+1 614 228 4262",
    "sg:postcode":"43222",
    "sg:province":"OH",
    "sg:tags":[
        "physician",
        "surgeon"
    ],
    "wof:name":"Columbus Bone Joint & Hand",
    "wof:placetype":"venue"
},
  "geometry": {"coordinates":[-83.02287099999999,39.958728],"type":"Point"}
}