{
  "type": "Feature",
  "properties": {
    "iso:country":"US",
    "sg:address":"42 Regina Dr",
    "sg:city":"Hubbard",
    "sg:classifiers":[
        {
            "category":"Shopping",
            "subcategory":"Discount & Variety Stores",
            "type":"Retail Goods"
        }
    ],
    "sg:phone":"+1 330 534 2060",
    "sg:postcode":"44425",
    "sg:province":"OH",
    "wof:name":"Diana S",
    "wof:placetype":"venue"
},
  "geometry": {"coordinates":[-80.58274900000001,41.168731],"type":"Point"}
}