{
  "type": "Feature",
  "properties": {
    "addr:full": "42 Regina Dr Hubbard OH 44425",
    "addr:housenumber": "42",
    "addr:postcode": "44425",
    "addr:street": "Regina Dr",
    "iso:country": "US",
    "sg:address": "42 Regina Dr",
    "sg:city": "Hubbard",
    "sg:classifiers": [
      {
        "category": "Shopping",
        "subcategory": "Discount \u0026 Variety Stores",
        "type": "Retail Goods"
      }
    ],
    "sg:phone": "+1 330 534 2060",
    "sg:postcode": "44425",
    "sg:province": "OH",
    "wof:name": "Diana S",
    "wof:placetype": "venue"
  },
  "geometry": {"coordinates":[-80.582749,41.168731],"type":"Point"}
}
