{
  "type": "Feature",
  "properties": {
    "addr:full":"11540 Winton Rd Cincinnati OH 45240",
    "addr:housenumber":"11540",
    "addr:postcode":"45240",
    "addr:street":"Winton Rd",
    "iso:country":"US",
    "sg:address":"11540 Winton Rd",
    "sg:city":"Cincinnati",
    "sg:classifiers":[
        {
            "category":"Autos & Motor Vehicles",
            "subcategory":"Auto Supplies",
            "type":"Retail Goods"
        }
    ],
    "sg:phone":"+1 513 851 7777",
    "sg:postcode":"45240",
    "sg:province":"OH",
    "sg:tags":[
        "parts",
        "accessory"
    ],
    "sg:website":"www.autozone.com",
    "wof:name":"Autozone",
    "wof:placetype":"venue"
},
  "geometry": {"coordinates":[-84.52234300000001,39.284503],"type":"Point"}
}