{
  "type": "Feature",
  "properties": {
    "addr:full":"4683 Corduroy Rd Mentor OH 44060",
    "addr:housenumber":"4683",
    "addr:postcode":"44060",
    "addr:street":"Corduroy Rd",
    "iso:country":"US",
    "sg:address":"4683 Corduroy Rd",
    "sg:city":"Mentor",
    "sg:classifiers":[
        {
            "category":"Organizations",
            "subcategory":"Community Association",
            "type":"Services"
        }
    ],
    "sg:phone":"+1 440 209 8450",
    "sg:postcode":"44060",
    "sg:province":"OH",
    "sg:tags":[
        "military"
    ],
    "wof:name":"Post 40 Veteran's Career Ctr",
    "wof:placetype":"venue"
},
  "geometry": {"coordinates":[-81.311369,41.740807],"type":"Point"}
}