{
  "type": "Feature",
  "properties": {
    "iso:country":"US",
    "sg:address":"1106 Lincoln Hwy",
    "sg:city":"Wapakoneta",
    "sg:classifiers":[
        {
            "category":"Banks & Credit Unions",
            "subcategory":"Investment Brokerage",
            "type":"Services"
        }
    ],
    "sg:phone":"+1 419 738 4849",
    "sg:postcode":"45895",
    "sg:province":"OH",
    "sg:tags":[
        "security"
    ],
    "wof:name":"Edward Jones Investments",
    "wof:placetype":"venue"
},
  "geometry": {"coordinates":[-84.20271200000001,40.581738],"type":"Point"}
}