{
  "type": "Feature",
  "properties": {
    "addr:full": "8885 Basil Western Rd Canal Winchester OH 43110",
    "addr:housenumber": "8885",
    "addr:postcode": "43110",
    "addr:street": "Basil Western Rd",
    "iso:country": "US",
    "sg:address": "8885 Basil Western Rd",
    "sg:city": "Canal Winchester",
    "sg:classifiers": [
      {
        "category": "Building \u0026 Trades",
        "subcategory": "Construction",
        "type": "Services"
      }
    ],
    "sg:phone": "+1 614 836 9626",
    "sg:postcode": "43110",
    "sg:province": "OH",
    "sg:tags": [
      "house"
    ],
    "wof:name": "Z Man Construction",
    "wof:placetype": "venue"
  },
  "geometry": {"coordinates":[-82.761452,39.842624],"type":"Point"}
}
