{
  "type": "Feature",
  "properties": {
    "addr:full": "115 S Miami St Quincy OH 43343",
    "addr:housenumber": "115",
    "addr:postcode": "43343",
    "addr:street": "S Miami St",
    "iso:country": "US",
    "sg:address": "115 S Miami St",
    "sg:city": "Quincy",
    "sg:classifiers": [
      {
        "category": "Government",
        "subcategory": "Office",
        "type": "Public Place"
      }
    ],
    "sg:phone": "+1 937 585 5314",
    "sg:postcode": "43343",
    "sg:province": "OH",
    "sg:tags": [
      "village"
    ],
    "wof:name": "Quincy Village Hall",
    "wof:placetype": "venue"
  },
  "geometry": {"coordinates":[-83.968545,40.298066],"type":"Point"}
}
