{
  "type": "Feature",
  "properties": {
    "addr:full":"3022 Camden Sugar Valley Rd Eaton OH 45320",
    "addr:housenumber":"3022",
    "addr:postcode":"45320",
    "addr:street":"Camden Sugar Valley Rd",
    "iso:country":"US",
    "sg:address":"3022 Camden Sugar Valley Rd",
    "sg:city":"Eaton",
    "sg:classifiers":[
        {
            "category":"Social Services",
            "subcategory":"Child Care",
            "type":"Services"
        }
    ],
    "sg:phone":"+1 937 456 2225",
    "sg:postcode":"45320",
    "sg:province":"OH",
    "sg:tags":[
        "day"
    ],
    "wof:name":"Bright Beginngs Chld Cr Presch",
    "wof:placetype":"venue"
},
  "geometry": {"coordinates":[-84.712964,39.690024],"type":"Point"}
}