{
  "type": "Feature",
  "properties": {
    "iso:country":"US",
    "sg:address":"5242 Tractor Rd",
    "sg:city":"Toledo",
    "sg:classifiers":[
        {
            "category":"Building & Trades",
            "subcategory":"Construction",
            "type":"Services"
        }
    ],
    "sg:phone":"+1 419 478 3771",
    "sg:postcode":"43612",
    "sg:province":"OH",
    "sg:tags":[
        "roofing",
        "contractor"
    ],
    "wof:name":"L & S Roofing",
    "wof:placetype":"venue"
},
  "geometry": {"coordinates":[-83.55285600000001,41.707267],"type":"Point"}
}