{
  "type": "Feature",
  "properties": {
    "addr:full": "5242 Tractor Rd Toledo OH 43612",
    "addr:postcode": "5242;43612",
    "addr:street": "Tractor Rd",
    "iso:country": "US",
    "sg:address": "5242 Tractor Rd",
    "sg:city": "Toledo",
    "sg:classifiers": [
      {
        "category": "Building \u0026 Trades",
        "subcategory": "Construction",
        "type": "Services"
      }
    ],
    "sg:phone": "+1 419 478 3771",
    "sg:postcode": "43612",
    "sg:province": "OH",
    "sg:tags": [
      "roofing",
      "contractor"
    ],
    "wof:name": "L \u0026 S Roofing",
    "wof:placetype": "venue"
  },
  "geometry": {"coordinates":[-83.552856,41.707267],"type":"Point"}
}
