{
  "type": "Feature",
  "properties": {
    "addr:full": "10200 Beloit Snodes Rd Beloit OH 44609",
    "addr:housenumber": "10200",
    "addr:postcode": "44609",
    "addr:street": "Beloit Snodes Rd",
    "iso:country": "US",
    "sg:address": "10200 Beloit Snodes Rd",
    "sg:city": "Beloit",
    "sg:classifiers": [
      {
        "category": "Freight",
        "type": "Transportation"
      }
    ],
    "sg:phone": "+1 330 584 7266",
    "sg:postcode": "44609",
    "sg:province": "OH",
    "sg:tags": [
      "operator",
      "trucking"
    ],
    "wof:name": "CTS Trucking",
    "wof:placetype": "venue"
  },
  "geometry": {"coordinates":[-80.993644,40.962517],"type":"Point"}
}
