{
  "type": "Feature",
  "properties": {
    "addr:full": "9734 Independence Blvd Cleveland OH 44130",
    "addr:housenumber": "9734",
    "addr:postcode": "44130",
    "addr:street": "Independence Blvd",
    "iso:country": "US",
    "sg:address": "9734 Independence Blvd",
    "sg:city": "Cleveland",
    "sg:classifiers": [
      {
        "category": "Food \u0026 Beverages",
        "subcategory": "Candy",
        "type": "Retail Goods"
      }
    ],
    "sg:phone": "+1 440 842 4382",
    "sg:postcode": "44130",
    "sg:province": "OH",
    "sg:tags": [
      "confectionery"
    ],
    "wof:name": "Godiva Chocolatier Inc",
    "wof:placetype": "venue"
  },
  "geometry": {"coordinates":[-81.753554,41.373991],"type":"Point"}
}
