{
  "type": "Feature",
  "properties": {
    "addr:full": "321 W South St St Marys OH 45885",
    "addr:housenumber": "321",
    "addr:postcode": "45885",
    "addr:street": "W South St",
    "iso:country": "US",
    "sg:address": "321 W South St",
    "sg:city": "St Marys",
    "sg:classifiers": [
      {
        "category": "Building \u0026 Trades",
        "subcategory": "Construction",
        "type": "Services"
      }
    ],
    "sg:phone": "+1 419 394 8643",
    "sg:postcode": "45885",
    "sg:province": "OH",
    "sg:tags": [
      "general",
      "contractor"
    ],
    "wof:name": "Huwer Renovating",
    "wof:placetype": "venue"
  },
  "geometry": {"coordinates":[-84.389863,40.541051],"type":"Point"}
}
