{
  "type": "Feature",
  "properties": {
    "iso:country":"US",
    "sg:address":"321 W South St",
    "sg:city":"St Marys",
    "sg:classifiers":[
        {
            "category":"Building & Trades",
            "subcategory":"Construction",
            "type":"Services"
        }
    ],
    "sg:phone":"+1 419 394 8643",
    "sg:postcode":"45885",
    "sg:province":"OH",
    "sg:tags":[
        "general",
        "contractor"
    ],
    "wof:name":"Huwer Renovating",
    "wof:placetype":"venue"
},
  "geometry": {"coordinates":[-84.38986300000001,40.541051],"type":"Point"}
}