{
  "type": "Feature",
  "properties": {
    "addr:full":"15 River Rd Hinckley OH 44233",
    "addr:housenumber":"15",
    "addr:postcode":"44233",
    "addr:street":"River Rd",
    "iso:country":"US",
    "sg:address":"15 River Rd",
    "sg:city":"Hinckley",
    "sg:classifiers":[
        {
            "category":"Building & Trades",
            "subcategory":"Construction",
            "type":"Services"
        }
    ],
    "sg:phone":"+1 440 237 2934",
    "sg:postcode":"44233",
    "sg:province":"OH",
    "sg:tags":[
        "general"
    ],
    "wof:name":"Riegler Construction",
    "wof:placetype":"venue"
},
  "geometry": {"coordinates":[-81.72084,41.276543],"type":"Point"}
}