{
  "type": "Feature",
  "properties": {
    "addr:full":"2163 W North Bend Rd Cincinnati OH 45224",
    "addr:housenumber":"2163",
    "addr:postcode":"45224",
    "addr:street":"W North Bend Rd",
    "iso:country":"US",
    "sg:address":"2163 W North Bend Rd",
    "sg:city":"Cincinnati",
    "sg:classifiers":[
        {
            "category":"Organizations",
            "subcategory":"Religious Organization",
            "type":"Services"
        }
    ],
    "sg:phone":"+1 513 681 4907",
    "sg:postcode":"45224",
    "sg:province":"OH",
    "sg:tags":[
        "clergy"
    ],
    "wof:name":"Sol Prophett",
    "wof:placetype":"venue"
},
  "geometry": {"coordinates":[-84.56272199999999,39.202001],"type":"Point"}
}