{
  "type": "Feature",
  "properties": {
    "iso:country":"US",
    "sg:address":"2765 N Snyder Rd",
    "sg:city":"Trotwood",
    "sg:classifiers":[
        {
            "category":"Sports & Exercise",
            "subcategory":"Golf",
            "type":"Entertainment"
        }
    ],
    "sg:phone":"+1 937 854 1951",
    "sg:postcode":"45426",
    "sg:province":"OH",
    "sg:tags":[
        "course"
    ],
    "wof:name":"Larch Tree Golf Course",
    "wof:placetype":"venue"
},
  "geometry": {"coordinates":[-84.330139,39.775872],"type":"Point"}
}