{
  "type": "Feature",
  "properties": {
    "addr:full":"1200 E Broad St Elyria OH 44035",
    "addr:housenumber":"1200",
    "addr:postcode":"44035",
    "addr:street":"E Broad St",
    "iso:country":"US",
    "sg:address":"1200 E Broad St",
    "sg:city":"Elyria",
    "sg:classifiers":[
        {
            "category":"Insurance",
            "subcategory":"Insurance Agent",
            "type":"Services"
        },
        {
            "category":"Insurance",
            "subcategory":"Hazard Insurance",
            "type":"Services"
        }
    ],
    "sg:phone":"+1 440 366 4653",
    "sg:postcode":"44035",
    "sg:province":"OH",
    "sg:tags":[
        "property",
        "commercial",
        "casualty",
        "business"
    ],
    "sg:website":"http://www.hoveykaiser.com",
    "wof:name":"Kaiser Hovey Insurance Associates Inc",
    "wof:placetype":"venue"
},
  "geometry": {"coordinates":[-82.07092299999999,41.36282],"type":"Point"}
}