{
  "type": "Feature",
  "properties": {
    "addr:full":"1930 Mentor Ave Painesville OH 44077",
    "addr:housenumber":"1930",
    "addr:postcode":"44077",
    "addr:street":"Mentor Ave",
    "iso:country":"US",
    "sg:address":"1930 Mentor Ave",
    "sg:city":"Painesville",
    "sg:classifiers":[
        {
            "category":"Real Estate",
            "subcategory":"Real Estate Agent",
            "type":"Services"
        }
    ],
    "sg:phone":"+1 440 951 1410",
    "sg:postcode":"44077",
    "sg:province":"OH",
    "wof:name":"Hunter Realty",
    "wof:placetype":"venue"
},
  "geometry": {"coordinates":[-81.285175,41.692773],"type":"Point"}
}