{
  "type": "Feature",
  "properties": {
    "iso:country":"US",
    "sg:address":"6862 Pearl Rd",
    "sg:city":"Cleveland",
    "sg:classifiers":[
        {
            "category":"Autos & Motor Vehicles",
            "subcategory":"Auto Supplies",
            "type":"Retail Goods"
        }
    ],
    "sg:phone":"+1 440 884 7733",
    "sg:postcode":"44130",
    "sg:province":"OH",
    "sg:tags":[
        "automobile",
        "parts"
    ],
    "wof:name":"Murray's Discount Auto Store",
    "wof:placetype":"venue"
},
  "geometry": {"coordinates":[-81.789981,41.378633],"type":"Point"}
}