{
  "type": "Feature",
  "properties": {
    "addr:full":"2800 Fostoria Ave Findlay OH 45840",
    "addr:housenumber":"2800",
    "addr:postcode":"45840",
    "addr:street":"Fostoria Ave",
    "iso:country":"US",
    "sg:address":"2800 Fostoria Ave",
    "sg:city":"Findlay",
    "sg:classifiers":[
        {
            "category":"Wholesale",
            "subcategory":"Machinery & Supplies",
            "type":"Manufacturing & Wholesale Goods"
        }
    ],
    "sg:phone":"+1 419 422 2912",
    "sg:postcode":"45840",
    "sg:province":"OH",
    "sg:tags":[
        "bucket",
        "hoisting"
    ],
    "sg:website":"www.werkbrau.com",
    "wof:name":"WERK-Brau Co",
    "wof:placetype":"venue"
},
  "geometry": {"coordinates":[-83.60771200000001,41.063117],"type":"Point"}
}