{
  "type": "Feature",
  "properties": {
    "addr:full": "4743 State Rte 41 NW Washington Ct Hs OH 43160",
    "addr:housenumber": "4743",
    "addr:postcode": "43160",
    "addr:street": "State Rte 41 Nw",
    "iso:country": "US",
    "sg:address": "4743 State Rte 41 NW",
    "sg:city": "Washington Ct Hs",
    "sg:classifiers": [
      {
        "category": "Shopping",
        "subcategory": "Computers \u0026 Home Electronics",
        "type": "Retail Goods"
      }
    ],
    "sg:phone": "+1 740 335 5334",
    "sg:postcode": "43160",
    "sg:province": "OH",
    "sg:tags": [
      "audio"
    ],
    "wof:name": "Stritenberger Audio",
    "wof:placetype": "venue"
  },
  "geometry": {"coordinates":[-83.488867,39.584237],"type":"Point"}
}
