{
  "type": "Feature",
  "properties": {
    "addr:full": "875 N 3rd St Tipp City OH 45371",
    "addr:housenumber": "875",
    "addr:postcode": "45371",
    "addr:street": "N 3Rd St",
    "iso:country": "US",
    "sg:address": "875 N 3rd St",
    "sg:city": "Tipp City",
    "sg:classifiers": [
      {
        "category": "Wholesale",
        "subcategory": "Chemicals \u0026 Plastics",
        "type": "Manufacturing \u0026 Wholesale Goods"
      }
    ],
    "sg:phone": "+1 937 667 4461",
    "sg:postcode": "45371",
    "sg:province": "OH",
    "sg:tags": [
      "adhesive",
      "glue"
    ],
    "sg:website": "www.dap.com",
    "wof:name": "Dap Inc",
    "wof:placetype": "venue"
  },
  "geometry": {"coordinates":[-84.173974,39.978374],"type":"Point"}
}
