{
  "type": "Feature",
  "properties": {
    "addr:full": "3823 Croydon Dr NW Canton OH 44718",
    "addr:housenumber": "3823",
    "addr:postcode": "44718",
    "addr:street": "Croydon Dr Nw",
    "iso:country": "US",
    "sg:address": "3823 Croydon Dr NW",
    "sg:city": "Canton",
    "sg:classifiers": [
      {
        "category": "Utilities",
        "subcategory": "Cable",
        "type": "Services"
      }
    ],
    "sg:phone": "+1 330 492 3043",
    "sg:postcode": "44718",
    "sg:province": "OH",
    "sg:tags": [
      "television"
    ],
    "wof:name": "Warner Cable",
    "wof:placetype": "venue"
  },
  "geometry": {"coordinates":[-81.416959,40.836051],"type":"Point"}
}
