{
  "type": "Feature",
  "properties": {
    "addr:full":"22756 Harms Rd Cleveland OH 44143",
    "addr:postcode":"22756;44143",
    "addr:street":"Harms Rd",
    "iso:country":"US",
    "sg:address":"22756 Harms Rd",
    "sg:city":"Cleveland",
    "sg:classifiers":[
        {
            "category":"Building & Trades",
            "subcategory":"Landscaping Services",
            "type":"Services"
        }
    ],
    "sg:phone":"+1 216 486 5493",
    "sg:postcode":"44143",
    "sg:province":"OH",
    "sg:tags":[
        "landscape"
    ],
    "wof:name":"John Gorican Landscaping",
    "wof:placetype":"venue"
},
  "geometry": {"coordinates":[-81.522462,41.559916],"type":"Point"}
}