{
  "type": "Feature",
  "properties": {
    "addr:full": "330 Portland St Celina OH 45822",
    "addr:housenumber": "330",
    "addr:postcode": "45822",
    "addr:street": "Portland St",
    "iso:country": "US",
    "sg:address": "330 Portland St",
    "sg:city": "Celina",
    "sg:classifiers": [
      {
        "category": "Personal",
        "subcategory": "Beauty Salon",
        "type": "Services"
      }
    ],
    "sg:phone": "+1 419 584 0050",
    "sg:postcode": "45822",
    "sg:province": "OH",
    "wof:name": "Xpressions A Styling Studio",
    "wof:placetype": "venue"
  },
  "geometry": {"coordinates":[-84.585413,40.546634],"type":"Point"}
}
