{
  "type": "Feature",
  "properties": {
    "addr:full": "8025 Golfview Ct Columbus OH 43235",
    "addr:housenumber": "8025",
    "addr:postcode": "43235",
    "addr:street": "Golfview Ct",
    "iso:country": "US",
    "sg:address": "8025 Golfview Ct",
    "sg:city": "Columbus",
    "sg:classifiers": [
      {
        "category": "Real Estate",
        "subcategory": "Real Estate Agent",
        "type": "Services"
      }
    ],
    "sg:phone": "+1 614 888 9272",
    "sg:postcode": "43235",
    "sg:province": "OH",
    "wof:name": "Neil E Crabbe \u0026 Co Realtor",
    "wof:placetype": "venue"
  },
  "geometry": {"coordinates":[-83.049501,40.129659],"type":"Point"}
}
