{
  "type": "Feature",
  "properties": {
    "addr:full": "1650 W Market St Akron OH 44313",
    "addr:housenumber": "1650",
    "addr:postcode": "44313",
    "addr:street": "W Market St",
    "iso:country": "US",
    "sg:address": "1650 W Market St",
    "sg:city": "Akron",
    "sg:classifiers": [
      {
        "category": "Professional",
        "subcategory": "Employment Agencies",
        "type": "Services"
      }
    ],
    "sg:phone": "+1 234 678 5401",
    "sg:postcode": "44313",
    "sg:province": "OH",
    "sg:tags": [
      "opportunity",
      "temporary",
      "contractor"
    ],
    "wof:name": "In Demand Staffing",
    "wof:placetype": "venue"
  },
  "geometry": {"coordinates":[-81.568169,41.109039],"type":"Point"}
}
