{
  "type": "Feature",
  "properties": {
    "addr:full":"2700 W State St Alliance OH 44601",
    "addr:housenumber":"2700",
    "addr:postcode":"44601",
    "addr:street":"W State St",
    "iso:country":"US",
    "sg:address":"2700 W State St",
    "sg:city":"Alliance",
    "sg:classifiers":[
        {
            "category":"Professional",
            "subcategory":"Accounting & Tax Preparation",
            "type":"Services"
        }
    ],
    "sg:phone":"+1 330 829 1762",
    "sg:postcode":"44601",
    "sg:province":"OH",
    "sg:tags":[
        "return",
        "filing"
    ],
    "wof:name":"H & R Block Tax Svc",
    "wof:placetype":"venue"
},
  "geometry": {"coordinates":[-81.15889300000001,40.901953],"type":"Point"}
}