{
  "type": "Feature",
  "properties": {
    "addr:full":"101 Glendale Milford Rd Cincinnati OH 45215",
    "addr:housenumber":"101",
    "addr:postcode":"45215",
    "addr:street":"Glendale Milford Rd",
    "iso:country":"US",
    "sg:address":"101 Glendale Milford Rd",
    "sg:city":"Cincinnati",
    "sg:classifiers":[
        {
            "category":"Freight",
            "type":"Transportation"
        }
    ],
    "sg:phone":"+1 513 772 8828",
    "sg:postcode":"45215",
    "sg:province":"OH",
    "sg:tags":[
        "storage"
    ],
    "wof:name":"American Self Storage",
    "wof:placetype":"venue"
},
  "geometry": {"coordinates":[-84.46866,39.25766],"type":"Point"}
}