{
  "type": "Feature",
  "properties": {
    "iso:country":"US",
    "sg:address":"897 N Court St",
    "sg:city":"Medina",
    "sg:classifiers":[
        {
            "category":"Coffee & Tea",
            "type":"Food & Drink"
        }
    ],
    "sg:menulink":"http://www.allmenus.com/oh/medina-city/124841-starbucks-coffee/menu/",
    "sg:phone":"+1 330 721 7947",
    "sg:postcode":"44256",
    "sg:province":"OH",
    "sg:tags":[
        "american"
    ],
    "wof:name":"Starbucks Coffee",
    "wof:placetype":"venue"
},
  "geometry": {"coordinates":[-81.86323400000001,41.15156],"type":"Point"}
}