{
  "type": "Feature",
  "properties": {
    "addr:full": "626 Cherry St Findlay OH 45840",
    "addr:housenumber": "626",
    "addr:postcode": "45840",
    "addr:street": "Cherry St",
    "iso:country": "US",
    "sg:address": "626 Cherry St",
    "sg:city": "Findlay",
    "sg:classifiers": [
      {
        "category": "Building \u0026 Trades",
        "subcategory": "Cleaning \u0026 Sanitation",
        "type": "Services"
      }
    ],
    "sg:phone": "+1 419 422 3972",
    "sg:postcode": "45840",
    "sg:province": "OH",
    "sg:tags": [
      "butler",
      "maid",
      "maintenance"
    ],
    "wof:name": "Findlay Home Cleaning Service",
    "wof:placetype": "venue"
  },
  "geometry": {"coordinates":[-83.638264,41.045429],"type":"Point"}
}
