{
  "type": "Feature",
  "properties": {
    "iso:country":"US",
    "sg:address":"626 Cherry St",
    "sg:city":"Findlay",
    "sg:classifiers":[
        {
            "category":"Building & Trades",
            "subcategory":"Cleaning & Sanitation",
            "type":"Services"
        }
    ],
    "sg:phone":"+1 419 422 3972",
    "sg:postcode":"45840",
    "sg:province":"OH",
    "sg:tags":[
        "butler",
        "maid",
        "maintenance"
    ],
    "wof:name":"Findlay Home Cleaning Service",
    "wof:placetype":"venue"
},
  "geometry": {"coordinates":[-83.63826400000001,41.045429],"type":"Point"}
}