{
  "type": "Feature",
  "properties": {
    "addr:full": "5175 Emerald Pkwy Dublin OH 43017",
    "addr:housenumber": "5175",
    "addr:postcode": "43017",
    "addr:street": "Emerald Pkwy",
    "iso:country": "US",
    "sg:address": "5175 Emerald Pkwy",
    "sg:city": "Dublin",
    "sg:classifiers": [
      {
        "category": "Utilities",
        "subcategory": "Mobile Phone",
        "type": "Services"
      }
    ],
    "sg:phone": "+1 614 798 9216",
    "sg:postcode": "43017",
    "sg:province": "OH",
    "sg:tags": [
      "telephone",
      "cellular"
    ],
    "wof:name": "Verizon Wireless",
    "wof:placetype": "venue"
  },
  "geometry": {"coordinates":[-83.130235,40.105641],"type":"Point"}
}
