{
  "type": "Feature",
  "properties": {
    "addr:full": "332 N Prospect St Marion OH 43302",
    "addr:housenumber": "332",
    "addr:postcode": "43302",
    "addr:street": "N Prospect St",
    "iso:country": "US",
    "sg:address": "332 N Prospect St",
    "sg:city": "Marion",
    "sg:classifiers": [
      {
        "category": "Autos \u0026 Motor Vehicles",
        "subcategory": "Automobile Sales",
        "type": "Retail Goods"
      }
    ],
    "sg:phone": "+1 740 387 5227",
    "sg:postcode": "43302",
    "sg:province": "OH",
    "sg:tags": [
      "used"
    ],
    "wof:name": "Harding Sales",
    "wof:placetype": "venue"
  },
  "geometry": {"coordinates":[-83.130671,40.59368],"type":"Point"}
}
