{
  "type": "Feature",
  "properties": {
    "addr:full":"1800 Oakwood Ave Napoleon OH 43545",
    "addr:housenumber":"1800",
    "addr:postcode":"43545",
    "addr:street":"Oakwood Ave",
    "iso:country":"US",
    "sg:address":"1800 Oakwood Ave",
    "sg:city":"Napoleon",
    "sg:classifiers":[
        {
            "category":"Real Estate",
            "subcategory":"Real Estate Operator",
            "type":"Services"
        }
    ],
    "sg:phone":"+1 419 592 0552",
    "sg:postcode":"43545",
    "sg:province":"OH",
    "sg:tags":[
        "building",
        "apartment"
    ],
    "wof:name":"Oakwood Village Apartments",
    "wof:placetype":"venue"
},
  "geometry": {"coordinates":[-84.120351,41.408122],"type":"Point"}
}