{
  "type": "Feature",
  "properties": {
    "addr:full":"19160 Story Rd Cleveland OH 44116",
    "addr:housenumber":"19160",
    "addr:postcode":"44116",
    "addr:street":"Story Rd",
    "iso:country":"US",
    "sg:address":"19160 Story Rd",
    "sg:city":"Cleveland",
    "sg:classifiers":[
        {
            "category":"Home & Garden",
            "subcategory":"Building Materials",
            "type":"Retail Goods"
        },
        {
            "category":"Building & Trades",
            "subcategory":"Construction",
            "type":"Services"
        }
    ],
    "sg:phone":"+1 440 356 2902",
    "sg:postcode":"44116",
    "sg:province":"OH",
    "sg:tags":[
        "mixed",
        "concrete",
        "contractor"
    ],
    "wof:name":"Concrete Express",
    "wof:placetype":"venue"
},
  "geometry": {"coordinates":[-81.835374,41.460119],"type":"Point"}
}