{
  "type": "Feature",
  "properties": {
    "addr:full":"8071 Morris Rd Hilliard OH 43026",
    "addr:housenumber":"8071",
    "addr:postcode":"43026",
    "addr:street":"Morris Rd",
    "iso:country":"US",
    "sg:address":"8071 Morris Rd",
    "sg:city":"Hilliard",
    "sg:classifiers":[
        {
            "category":"Real Estate",
            "subcategory":"Real Estate Agent",
            "type":"Services"
        }
    ],
    "sg:phone":"+1 614 771 7502",
    "sg:postcode":"43026",
    "sg:province":"OH",
    "wof:name":"S & D Investments",
    "wof:placetype":"venue"
},
  "geometry": {"coordinates":[-83.22071699999999,40.001173],"type":"Point"}
}