{
  "type": "Feature",
  "properties": {
    "iso:country":"US",
    "sg:address":"311 Elm St",
    "sg:city":"Cincinnati",
    "sg:classifiers":[
        {
            "category":"Professional",
            "type":"Services"
        }
    ],
    "sg:phone":"+1 513 412 7950",
    "sg:postcode":"45215",
    "sg:province":"OH",
    "sg:tags":[
        "establishment"
    ],
    "wof:name":"Logical",
    "wof:placetype":"venue"
},
  "geometry": {"coordinates":[-84.464051,39.229786],"type":"Point"}
}