{
  "type": "Feature",
  "properties": {
    "iso:country":"US",
    "sg:address":"601 E Main St",
    "sg:city":"Chillicothe",
    "sg:classifiers":[
        {
            "category":"Shopping",
            "subcategory":"Gifts & Souvenirs",
            "type":"Retail Goods"
        }
    ],
    "sg:phone":"+1 740 773 7368",
    "sg:postcode":"45601",
    "sg:province":"OH",
    "sg:tags":[
        "shop"
    ],
    "wof:name":"Gift Post",
    "wof:placetype":"venue"
},
  "geometry": {"coordinates":[-82.96361899999999,39.336014],"type":"Point"}
}