{
  "type": "Feature",
  "properties": {
    "addr:full": "601 E Main St Chillicothe OH 45601",
    "addr:housenumber": "601",
    "addr:postcode": "45601",
    "addr:street": "E Main St",
    "iso:country": "US",
    "sg:address": "601 E Main St",
    "sg:city": "Chillicothe",
    "sg:classifiers": [
      {
        "category": "Shopping",
        "subcategory": "Gifts \u0026 Souvenirs",
        "type": "Retail Goods"
      }
    ],
    "sg:phone": "+1 740 773 7368",
    "sg:postcode": "45601",
    "sg:province": "OH",
    "sg:tags": [
      "shop"
    ],
    "wof:name": "Gift Post",
    "wof:placetype": "venue"
  },
  "geometry": {"coordinates":[-82.963619,39.336014],"type":"Point"}
}
