{
  "type": "Feature",
  "properties": {
    "iso:country":"US",
    "sg:address":"206 Market St",
    "sg:city":"Brookville",
    "sg:classifiers":[
        {
            "category":"Building & Trades",
            "subcategory":"Construction",
            "type":"Services"
        }
    ],
    "sg:phone":"+1 937 833 1733",
    "sg:postcode":"45309",
    "sg:province":"OH",
    "sg:tags":[
        "nonresidential"
    ],
    "wof:name":"Modern Image",
    "wof:placetype":"venue"
},
  "geometry": {"coordinates":[-84.411277,39.836862],"type":"Point"}
}