{
  "type": "Feature",
  "properties": {
    "iso:country":"US",
    "sg:address":"5859 Harvey Cir",
    "sg:city":"Cincinnati",
    "sg:classifiers":[
        {
            "category":"Professional",
            "subcategory":"Lawyer & Legal Services",
            "type":"Services"
        }
    ],
    "sg:phone":"+1 513 922 5757",
    "sg:postcode":"45233",
    "sg:province":"OH",
    "wof:name":"Henkel Richard E Lwyr",
    "wof:placetype":"venue"
},
  "geometry": {"coordinates":[-84.641998,39.0998],"type":"Point"}
}