{
  "type": "Feature",
  "properties": {
    "addr:full":"303 Osceola Ave Defiance OH 43512",
    "addr:housenumber":"303",
    "addr:postcode":"43512",
    "addr:street":"Osceola Ave",
    "iso:country":"US",
    "sg:address":"303 Osceola Ave",
    "sg:city":"Defiance",
    "sg:classifiers":[
        {
            "category":"Organizations",
            "subcategory":"Religious Organization",
            "type":"Services"
        }
    ],
    "sg:phone":"+1 419 784 1029",
    "sg:postcode":"43512",
    "sg:province":"OH",
    "sg:tags":[
        "clergy"
    ],
    "wof:name":"Harold Driver",
    "wof:placetype":"venue"
},
  "geometry": {"coordinates":[-84.344859,41.283954],"type":"Point"}
}