{
  "type": "Feature",
  "properties": {
    "iso:country":"US",
    "sg:address":"835 W Fremont Rd",
    "sg:city":"Port Clinton",
    "sg:classifiers":[
        {
            "category":"Food & Beverages",
            "subcategory":"Groceries & Convenience Stores",
            "type":"Retail Goods"
        },
        {
            "category":"Food & Beverages",
            "subcategory":"Liquor & Beverages",
            "type":"Retail Goods"
        }
    ],
    "sg:phone":"+1 419 732 7716",
    "sg:postcode":"43452",
    "sg:province":"OH",
    "sg:tags":[
        "alcoholic"
    ],
    "wof:name":"Rich's Drive Thru",
    "wof:placetype":"venue"
},
  "geometry": {"coordinates":[-82.954239,41.506664],"type":"Point"}
}