{
  "type": "Feature",
  "properties": {
    "iso:country":"US",
    "sg:address":"100 Matterhorn Dr",
    "sg:city":"Bluffton",
    "sg:classifiers":[
        {
            "category":"Real Estate",
            "subcategory":"Real Estate Operator",
            "type":"Services"
        }
    ],
    "sg:phone":"+1 419 358 6600",
    "sg:postcode":"45817",
    "sg:province":"OH",
    "sg:tags":[
        "mobile",
        "home",
        "court"
    ],
    "wof:name":"Alpine Village",
    "wof:placetype":"venue"
},
  "geometry": {"coordinates":[-83.87887000000001,40.900237],"type":"Point"}
}