{
  "type": "Feature",
  "properties": {
    "iso:country":"US",
    "sg:address":"1220 Market Ave S",
    "sg:city":"Canton",
    "sg:classifiers":[
        {
            "category":"Wholesale",
            "subcategory":"Machinery & Supplies",
            "type":"Manufacturing & Wholesale Goods"
        }
    ],
    "sg:phone":"+1 330 456 3000",
    "sg:postcode":"44707",
    "sg:province":"OH",
    "sg:tags":[
        "equipment",
        "industrial"
    ],
    "wof:name":"Ohio Fastener and Tool",
    "wof:placetype":"venue"
},
  "geometry": {"coordinates":[-81.37947699999999,40.788408],"type":"Point"}
}