{
  "type": "Feature",
  "properties": {
    "iso:country":"US",
    "sg:address":"636 Main St",
    "sg:city":"Genoa",
    "sg:classifiers":[
        {
            "category":"Retail",
            "subcategory":"Auto Repair",
            "type":"Services"
        }
    ],
    "sg:phone":"+1 419 855 7700",
    "sg:postcode":"43430",
    "sg:province":"OH",
    "sg:tags":[
        "repairing",
        "automobile"
    ],
    "wof:name":"Palmer Stein Truck & Auto",
    "wof:placetype":"venue"
},
  "geometry": {"coordinates":[-83.358727,41.519614],"type":"Point"}
}