{
  "type": "Feature",
  "properties": {
    "addr:full":"824 E Exchange St Akron OH 44306",
    "addr:housenumber":"824",
    "addr:postcode":"44306",
    "addr:street":"E Exchange St",
    "iso:country":"US",
    "sg:address":"824 E Exchange St",
    "sg:city":"Akron",
    "sg:classifiers":[
        {
            "category":"Shopping",
            "subcategory":"Hobbies, Toys, & Games",
            "type":"Retail Goods"
        }
    ],
    "sg:phone":"+1 330 535 7777",
    "sg:postcode":"44306",
    "sg:province":"OH",
    "sg:tags":[
        "supply"
    ],
    "wof:name":"Skill Games Of Ohio",
    "wof:placetype":"venue"
},
  "geometry": {"coordinates":[-81.49369900000001,41.071025],"type":"Point"}
}