{
  "type": "Feature",
  "properties": {
    "addr:full": "1 Oak Meadow Dr Pataskala OH 43062",
    "addr:housenumber": "1",
    "addr:postcode": "43062",
    "addr:street": "Oak Meadow Dr",
    "iso:country": "US",
    "sg:address": "1 Oak Meadow Dr",
    "sg:city": "Pataskala",
    "sg:classifiers": [
      {
        "category": "Retail",
        "subcategory": "Laundry \u0026 Dry Cleaning",
        "type": "Services"
      }
    ],
    "sg:phone": "+1 740 927 2221",
    "sg:postcode": "43062",
    "sg:province": "OH",
    "sg:tags": [
      "cleaners",
      "rug",
      "carpet"
    ],
    "wof:name": "Performance Carpet Cleaning",
    "wof:placetype": "venue"
  },
  "geometry": {"coordinates":[-82.677912,40.003246],"type":"Point"}
}
