{
  "type": "Feature",
  "properties": {
    "iso:country":"US",
    "sg:address":"1 Oak Meadow Dr",
    "sg:city":"Pataskala",
    "sg:classifiers":[
        {
            "category":"Retail",
            "subcategory":"Laundry & Dry Cleaning",
            "type":"Services"
        }
    ],
    "sg:phone":"+1 740 927 2221",
    "sg:postcode":"43062",
    "sg:province":"OH",
    "sg:tags":[
        "cleaners",
        "rug",
        "carpet"
    ],
    "wof:name":"Performance Carpet Cleaning",
    "wof:placetype":"venue"
},
  "geometry": {"coordinates":[-82.67791200000001,40.003246],"type":"Point"}
}