{
  "type": "Feature",
  "properties": {
    "addr:full":"2925 Vernon Pl Cincinnati OH 45219",
    "addr:housenumber":"2925",
    "addr:postcode":"45219",
    "addr:street":"Vernon Pl",
    "iso:country":"US",
    "sg:address":"2925 Vernon Pl",
    "sg:city":"Cincinnati",
    "sg:classifiers":[
        {
            "category":"Health Services",
            "subcategory":"Doctor",
            "type":"Services"
        }
    ],
    "sg:phone":"+1 513 936 0700",
    "sg:postcode":"45219",
    "sg:province":"OH",
    "sg:tags":[
        "physician",
        "surgeon"
    ],
    "wof:name":"Great Cincinnati Gastro Assoc",
    "wof:placetype":"venue"
},
  "geometry": {"coordinates":[-84.49988399999999,39.131998],"type":"Point"}
}