{
  "type": "Feature",
  "properties": {
    "addr:full": "2507 Shadow Ridge Ln Akron OH 44333",
    "addr:housenumber": "2507",
    "addr:postcode": "44333",
    "addr:street": "Shadow Ridge Ln",
    "iso:country": "US",
    "sg:address": "2507 Shadow Ridge Ln",
    "sg:city": "Akron",
    "sg:classifiers": [
      {
        "category": "Government",
        "subcategory": "Office",
        "type": "Public Place"
      }
    ],
    "sg:phone": "+1 330 665 1838",
    "sg:postcode": "44333",
    "sg:province": "OH",
    "sg:tags": [
      "development"
    ],
    "wof:name": "MJB LLC",
    "wof:placetype": "venue"
  },
  "geometry": {"coordinates":[-81.621512,41.114569],"type":"Point"}
}
