{
  "type": "Feature",
  "properties": {
    "addr:full":"570 State Rte 741 Lebanon OH 45036",
    "addr:housenumber":"570",
    "addr:postcode":"45036",
    "addr:street":"State Rte 741",
    "iso:country":"US",
    "sg:address":"570 State Rte 741",
    "sg:city":"Lebanon",
    "sg:classifiers":[
        {
            "category":"Government",
            "subcategory":"Office",
            "type":"Public Place"
        }
    ],
    "sg:phone":"+1 513 261 2247",
    "sg:postcode":"45036",
    "sg:province":"OH",
    "wof:name":"Warren Cnty Cancer Family Care",
    "wof:placetype":"venue"
},
  "geometry": {"coordinates":[-84.27853899999999,39.445286],"type":"Point"}
}