{
  "type": "Feature",
  "properties": {
    "iso:country":"US",
    "sg:address":"1287 Worthington Woods Blvd",
    "sg:city":"Worthington",
    "sg:classifiers":[
        {
            "category":"Professional",
            "subcategory":"Accounting & Tax Preparation",
            "type":"Services"
        }
    ],
    "sg:phone":"+1 614 781 1777",
    "sg:postcode":"43085",
    "sg:province":"OH",
    "sg:tags":[
        "accountant"
    ],
    "wof:name":"Marino & Co Inc",
    "wof:placetype":"venue"
},
  "geometry": {"coordinates":[-82.98344,40.117881],"type":"Point"}
}