{
  "type": "Feature",
  "properties": {
    "addr:full": "1200 Industrial Dr Fort Recovery OH 45846",
    "addr:housenumber": "1200",
    "addr:postcode": "45846",
    "addr:street": "Industrial Dr",
    "iso:country": "US",
    "sg:address": "1200 Industrial Dr",
    "sg:city": "Fort Recovery",
    "sg:classifiers": [
      {
        "category": "Manufacturing",
        "subcategory": "Metals",
        "type": "Manufacturing \u0026 Wholesale Goods"
      }
    ],
    "sg:phone": "+1 419 375 3005",
    "sg:postcode": "45846",
    "sg:province": "OH",
    "sg:tags": [
      "plumbing",
      "hardware",
      "mfg"
    ],
    "wof:name": "Fort Recovery Industries Inc",
    "wof:placetype": "venue"
  },
  "geometry": {"coordinates":[-84.773606,40.40096],"type":"Point"}
}
