{
  "type": "Feature",
  "properties": {
    "addr:full": "7800 Bader Rd NW Baltimore OH 43105",
    "addr:housenumber": "7800",
    "addr:postcode": "43105",
    "addr:street": "Bader Rd Nw",
    "iso:country": "US",
    "sg:address": "7800 Bader Rd NW",
    "sg:city": "Baltimore",
    "sg:phone": "+1 740 862 4529",
    "sg:postcode": "43105",
    "sg:province": "OH",
    "sg:tags": [
      "farm",
      "corn",
      "wheat",
      "soybean"
    ],
    "wof:name": "Inland Meadows",
    "wof:placetype": "venue"
  },
  "geometry": {"coordinates":[-82.654319,39.839941],"type":"Point"}
}
