{
  "type": "Feature",
  "properties": {
    "addr:full": "133 W Water St Prospect OH 43342",
    "addr:housenumber": "133",
    "addr:postcode": "43342",
    "addr:street": "W Water St",
    "iso:country": "US",
    "sg:address": "133 W Water St",
    "sg:city": "Prospect",
    "sg:classifiers": [
      {
        "category": "Restaurant",
        "type": "Food \u0026 Drink"
      }
    ],
    "sg:menulink": "http://www.allmenus.com/oh/prospect/134128-subway/menu/",
    "sg:phone": "+1 740 494 2512",
    "sg:postcode": "43342",
    "sg:province": "OH",
    "sg:tags": [
      "american",
      "sandwich"
    ],
    "wof:name": "Subway",
    "wof:placetype": "venue"
  },
  "geometry": {"coordinates":[-83.190817,40.449885],"type":"Point"}
}
