{
  "type": "Feature",
  "properties": {
    "addr:full": "8890 Bechtel Rd Elyria OH 44035",
    "addr:postcode": "8890;44035",
    "addr:street": "Bechtel Rd",
    "iso:country": "US",
    "sg:address": "8890 Bechtel Rd",
    "sg:city": "Elyria",
    "sg:classifiers": [
      {
        "category": "Manufacturing",
        "subcategory": "Tools \u0026 Machinery",
        "type": "Manufacturing \u0026 Wholesale Goods"
      }
    ],
    "sg:phone": "+1 440 323 3792",
    "sg:postcode": "44035",
    "sg:province": "OH",
    "sg:tags": [
      "computer",
      "electronic",
      "mfg"
    ],
    "wof:name": "London Specialties Co",
    "wof:placetype": "venue"
  },
  "geometry": {"coordinates":[-82.175616,41.356021],"type":"Point"}
}
