{
  "type": "Feature",
  "properties": {
    "iso:country":"US",
    "sg:address":"8890 Bechtel Rd",
    "sg:city":"Elyria",
    "sg:classifiers":[
        {
            "category":"Manufacturing",
            "subcategory":"Tools & Machinery",
            "type":"Manufacturing & Wholesale Goods"
        }
    ],
    "sg:phone":"+1 440 323 3792",
    "sg:postcode":"44035",
    "sg:province":"OH",
    "sg:tags":[
        "computer",
        "electronic",
        "mfg"
    ],
    "wof:name":"London Specialties Co",
    "wof:placetype":"venue"
},
  "geometry": {"coordinates":[-82.17561600000001,41.356021],"type":"Point"}
}