{
  "type": "Feature",
  "properties": {
    "addr:full":"3060 Jasper Rd Xenia OH 45385",
    "addr:housenumber":"3060",
    "addr:postcode":"45385",
    "addr:street":"Jasper Rd",
    "iso:country":"US",
    "sg:address":"3060 Jasper Rd",
    "sg:city":"Xenia",
    "sg:classifiers":[
        {
            "category":"Organizations",
            "subcategory":"Religious Organization",
            "type":"Services"
        }
    ],
    "sg:phone":"+1 937 372 3031",
    "sg:postcode":"45385",
    "sg:province":"OH",
    "sg:tags":[
        "church"
    ],
    "wof:name":"New Jasper United Methodist",
    "wof:placetype":"venue"
},
  "geometry": {"coordinates":[-83.82559000000001,39.656532],"type":"Point"}
}