{
  "type": "Feature",
  "properties": {
    "addr:full": "7016 Corporate Way Dayton OH 45459",
    "addr:housenumber": "7016",
    "addr:postcode": "45459",
    "addr:street": "Corporate Way",
    "iso:country": "US",
    "sg:address": "7016 Corporate Way",
    "sg:city": "Dayton",
    "sg:classifiers": [
      {
        "category": "Real Estate",
        "subcategory": "Real Estate Services",
        "type": "Services"
      }
    ],
    "sg:phone": "+1 937 438 2000",
    "sg:postcode": "45459",
    "sg:province": "OH",
    "sg:tags": [
      "company",
      "title"
    ],
    "sg:website": "www.sterlinglandtitle.com",
    "wof:name": "Sterling Land Title Agency Inc",
    "wof:placetype": "venue"
  },
  "geometry": {"coordinates":[-84.159819,39.643695],"type":"Point"}
}
