{
  "type": "Feature",
  "properties": {
    "addr:full": "6600 Sanborn Rd Ashtabula OH 44004",
    "addr:postcode": "6600;44004",
    "addr:street": "Sanborn Rd",
    "iso:country": "US",
    "sg:address": "6600 Sanborn Rd",
    "sg:city": "Ashtabula",
    "sg:classifiers": [
      {
        "category": "Building \u0026 Trades",
        "subcategory": "Electrical",
        "type": "Services"
      }
    ],
    "sg:phone": "+1 440 998 0695",
    "sg:postcode": "44004",
    "sg:province": "OH",
    "sg:tags": [
      "electric",
      "contractor"
    ],
    "wof:name": "APL Electric",
    "wof:placetype": "venue"
  },
  "geometry": {"coordinates":[-80.824744,41.843236],"type":"Point"}
}
