{
  "type": "Feature",
  "properties": {
    "iso:country":"US",
    "sg:address":"6600 Sanborn Rd",
    "sg:city":"Ashtabula",
    "sg:classifiers":[
        {
            "category":"Building & Trades",
            "subcategory":"Electrical",
            "type":"Services"
        }
    ],
    "sg:phone":"+1 440 998 0695",
    "sg:postcode":"44004",
    "sg:province":"OH",
    "sg:tags":[
        "electric",
        "contractor"
    ],
    "wof:name":"APL Electric",
    "wof:placetype":"venue"
},
  "geometry": {"coordinates":[-80.824744,41.843236],"type":"Point"}
}