{
  "type": "Feature",
  "properties": {
    "iso:country":"US",
    "sg:address":"3921 Mayfield Rd",
    "sg:city":"Cleveland",
    "sg:classifiers":[
        {
            "category":"Building & Trades",
            "subcategory":"Landscaping Services",
            "type":"Services"
        }
    ],
    "sg:phone":"+1 216 291 0902",
    "sg:postcode":"44121",
    "sg:province":"OH",
    "sg:tags":[
        "tree"
    ],
    "wof:name":"Hall's Tree Svc",
    "wof:placetype":"venue"
},
  "geometry": {"coordinates":[-81.539508,41.520762],"type":"Point"}
}