{
  "type": "Feature",
  "properties": {
    "addr:full":"4410 Middle St Homeworth OH 44634",
    "addr:housenumber":"4410",
    "addr:postcode":"44634",
    "addr:street":"Middle St",
    "iso:country":"US",
    "sg:address":"4410 Middle St",
    "sg:city":"Homeworth",
    "sg:classifiers":[
        {
            "category":"Insurance",
            "subcategory":"Insurance Agent",
            "type":"Services"
        }
    ],
    "sg:phone":"+1 330 525 0217",
    "sg:postcode":"44634",
    "sg:province":"OH",
    "wof:name":"West & KNOX Mutual Insurance",
    "wof:placetype":"venue"
},
  "geometry": {"coordinates":[-81.066878,40.836822],"type":"Point"}
}