{
  "type": "Feature",
  "properties": {
    "addr:full": "1345 W Mound St Columbus OH 43223",
    "addr:housenumber": "1345",
    "addr:postcode": "43223",
    "addr:street": "W Mound St",
    "iso:country": "US",
    "sg:address": "1345 W Mound St",
    "sg:city": "Columbus",
    "sg:classifiers": [
      {
        "category": "Freight",
        "type": "Transportation"
      }
    ],
    "sg:phone": "+1 614 221 5108",
    "sg:postcode": "43223",
    "sg:province": "OH",
    "sg:tags": [
      "operator",
      "local",
      "trucking"
    ],
    "wof:name": "K \u0026 R Express Systems Inc",
    "wof:placetype": "venue"
  },
  "geometry": {"coordinates":[-83.033986,39.946222],"type":"Point"}
}
