{
  "type": "Feature",
  "properties": {
    "addr:full": "3110 Olentangy River Rd Columbus OH 43202",
    "addr:housenumber": "3110",
    "addr:postcode": "43202",
    "addr:street": "Olentangy River Rd",
    "iso:country": "US",
    "sg:address": "3110 Olentangy River Rd",
    "sg:city": "Columbus",
    "sg:classifiers": [
      {
        "category": "Professional",
        "type": "Services"
      }
    ],
    "sg:phone": "+1 614 261 4553",
    "sg:postcode": "43202",
    "sg:province": "OH",
    "sg:tags": [
      "establishment"
    ],
    "wof:name": "ITA Inc",
    "wof:placetype": "venue"
  },
  "geometry": {"coordinates":[-83.029504,40.029233],"type":"Point"}
}
