{
  "type": "Feature",
  "properties": {
    "addr:full": "611 W Market St Akron OH 44303",
    "addr:housenumber": "611",
    "addr:postcode": "44303",
    "addr:street": "W Market St",
    "iso:country": "US",
    "sg:address": "611 W Market St",
    "sg:city": "Akron",
    "sg:classifiers": [
      {
        "category": "Banks \u0026 Credit Unions",
        "subcategory": "Bank",
        "type": "Services"
      }
    ],
    "sg:phone": "+1 330 376 6811",
    "sg:postcode": "44303",
    "sg:province": "OH",
    "sg:tags": [
      "search",
      "title",
      "company",
      "mortgage",
      "banker"
    ],
    "wof:name": "First Akron Corporation",
    "wof:placetype": "venue"
  },
  "geometry": {"coordinates":[-81.537465,41.094075],"type":"Point"}
}
