{
  "type": "Feature",
  "properties": {
    "addr:full":"374 Newton St Canfield OH 44406",
    "addr:housenumber":"374",
    "addr:postcode":"44406",
    "addr:street":"Newton St",
    "iso:country":"US",
    "sg:address":"374 Newton St",
    "sg:city":"Canfield",
    "sg:classifiers":[
        {
            "category":"Banks & Credit Unions",
            "subcategory":"Financial Services",
            "type":"Services"
        },
        {
            "category":"Shopping",
            "subcategory":"Photographic Equipment",
            "type":"Retail Goods"
        }
    ],
    "sg:phone":"+1 330 702 0257",
    "sg:postcode":"44406",
    "sg:province":"OH",
    "sg:tags":[
        "supply",
        "franchising"
    ],
    "wof:name":"1 Hour Photo",
    "wof:placetype":"venue"
},
  "geometry": {"coordinates":[-80.770349,41.020755],"type":"Point"}
}