{
  "type": "Feature",
  "properties": {
    "addr:full": "3077 N Ridge Rd Perry OH 44081",
    "addr:housenumber": "3077",
    "addr:postcode": "44081",
    "addr:street": "N Ridge Rd",
    "iso:country": "US",
    "sg:address": "3077 N Ridge Rd",
    "sg:city": "Perry",
    "sg:classifiers": [
      {
        "category": "Home \u0026 Garden",
        "subcategory": "Garden Supply",
        "type": "Retail Goods"
      }
    ],
    "sg:phone": "+1 440 259 2318",
    "sg:postcode": "44081",
    "sg:province": "OH",
    "sg:tags": [
      "ornamental",
      "nursery"
    ],
    "wof:name": "Lambo Nursery",
    "wof:placetype": "venue"
  },
  "geometry": {"coordinates":[-81.17244,41.770746],"type":"Point"}
}
