{
  "type": "Feature",
  "properties": {
    "addr:full":"32730 Walker Rd Avon Lake OH 44012",
    "addr:housenumber":"32730",
    "addr:postcode":"44012",
    "addr:street":"Walker Rd",
    "iso:country":"US",
    "sg:address":"32730 Walker Rd",
    "sg:city":"Avon Lake",
    "sg:classifiers":[
        {
            "category":"Banks & Credit Unions",
            "subcategory":"Bank",
            "type":"Services"
        }
    ],
    "sg:phone":"+1 440 933 4575",
    "sg:postcode":"44012",
    "sg:province":"OH",
    "wof:name":"US Bank",
    "wof:placetype":"venue"
},
  "geometry": {"coordinates":[-82.021272,41.49324],"type":"Point"}
}