{
  "type": "Feature",
  "properties": {
    "iso:country":"US",
    "sg:address":"1317 Hull Rd",
    "sg:city":"Sandusky",
    "sg:classifiers":[
        {
            "category":"Shopping",
            "type":"Retail Goods"
        }
    ],
    "sg:phone":"+1 419 625 9111",
    "sg:postcode":"44870",
    "sg:province":"OH",
    "sg:tags":[
        "hearing",
        "equipment",
        "supply",
        "impaired"
    ],
    "wof:name":"Wright's Audiology & Hearing",
    "wof:placetype":"venue"
},
  "geometry": {"coordinates":[-82.666922,41.414646],"type":"Point"}
}