{
  "type": "Feature",
  "properties": {
    "addr:full": "1317 Hull Rd Sandusky OH 44870",
    "addr:housenumber": "1317",
    "addr:postcode": "44870",
    "addr:street": "Hull Rd",
    "iso:country": "US",
    "sg:address": "1317 Hull Rd",
    "sg:city": "Sandusky",
    "sg:classifiers": [
      {
        "category": "Shopping",
        "type": "Retail Goods"
      }
    ],
    "sg:phone": "+1 419 625 9111",
    "sg:postcode": "44870",
    "sg:province": "OH",
    "sg:tags": [
      "hearing",
      "equipment",
      "supply",
      "impaired"
    ],
    "wof:name": "Wright's Audiology \u0026 Hearing",
    "wof:placetype": "venue"
  },
  "geometry": {"coordinates":[-82.666922,41.414646],"type":"Point"}
}
