{
  "type": "Feature",
  "properties": {
    "addr:full": "1800 Euclid Ave Cleveland OH 44115",
    "addr:housenumber": "1800",
    "addr:postcode": "44115",
    "addr:street": "Euclid Ave",
    "iso:country": "US",
    "sg:address": "1800 Euclid Ave",
    "sg:city": "Cleveland",
    "sg:classifiers": [
      {
        "category": "Restaurant",
        "type": "Food \u0026 Drink"
      }
    ],
    "sg:menulink": "http://www.allmenus.com/oh/cleveland/134242-subway/menu/",
    "sg:phone": "+1 216 687 1017",
    "sg:postcode": "44115",
    "sg:province": "OH",
    "sg:tags": [
      "american",
      "sandwich"
    ],
    "wof:name": "Subway",
    "wof:placetype": "venue"
  },
  "geometry": {"coordinates":[-81.678333,41.500737],"type":"Point"}
}
