{
  "type": "Feature",
  "properties": {
    "iso:country":"US",
    "sg:address":"201 N Main St",
    "sg:city":"Rockford",
    "sg:classifiers":[
        {
            "category":"Government",
            "subcategory":"Fire Station",
            "type":"Public Place"
        }
    ],
    "sg:phone":"+1 419 363 3611",
    "sg:postcode":"45882",
    "sg:province":"OH",
    "sg:tags":[
        "department"
    ],
    "wof:name":"Rockford Fire Dept",
    "wof:placetype":"venue"
},
  "geometry": {"coordinates":[-84.646424,40.693053],"type":"Point"}
}