{
  "type": "Feature",
  "properties": {
    "addr:full": "5275 Washington Rd Albany OH 45710",
    "addr:housenumber": "5275",
    "addr:postcode": "45710",
    "addr:street": "Washington Rd",
    "iso:country": "US",
    "sg:address": "5275 Washington Rd",
    "sg:city": "Albany",
    "sg:classifiers": [
      {
        "category": "Farming",
        "subcategory": "Farm \u0026 Veterinary Services",
        "type": "Manufacturing \u0026 Wholesale Goods"
      }
    ],
    "sg:phone": "+1 740 698 0841",
    "sg:postcode": "45710",
    "sg:province": "OH",
    "sg:tags": [
      "breeder",
      "livestock"
    ],
    "wof:name": "United Gamefowl Breeders Assn",
    "wof:placetype": "venue"
  },
  "geometry": {"coordinates":[-82.203533,39.227237],"type":"Point"}
}
