{
  "type": "Feature",
  "properties": {
    "iso:country":"US",
    "sg:address":"5275 Washington Rd",
    "sg:city":"Albany",
    "sg:classifiers":[
        {
            "category":"Farming",
            "subcategory":"Farm & Veterinary Services",
            "type":"Manufacturing & Wholesale Goods"
        }
    ],
    "sg:phone":"+1 740 698 0841",
    "sg:postcode":"45710",
    "sg:province":"OH",
    "sg:tags":[
        "breeder",
        "livestock"
    ],
    "wof:name":"United Gamefowl Breeders Assn",
    "wof:placetype":"venue"
},
  "geometry": {"coordinates":[-82.20353299999999,39.227237],"type":"Point"}
}