{
  "type": "Feature",
  "properties": {
    "iso:country":"US",
    "sg:address":"1177 Faultless Dr",
    "sg:city":"Ashland",
    "sg:classifiers":[
        {
            "category":"Manufacturing",
            "subcategory":"Textiles",
            "type":"Manufacturing & Wholesale Goods"
        }
    ],
    "sg:phone":"+1 419 289 9739",
    "sg:postcode":"44805",
    "sg:province":"OH",
    "sg:tags":[
        "fiberglass",
        "mfg",
        "reinforced"
    ],
    "sg:website":"www.kar-delplastics.com",
    "wof:name":"Kar-Del Plastics Inc",
    "wof:placetype":"venue"
},
  "geometry": {"coordinates":[-82.332947,40.887244],"type":"Point"}
}