{
  "type": "Feature",
  "properties": {
    "addr:full": "1621 Tiffin Ave Findlay OH 45840",
    "addr:housenumber": "1621",
    "addr:postcode": "45840",
    "addr:street": "Tiffin Ave",
    "iso:country": "US",
    "sg:address": "1621 Tiffin Ave",
    "sg:city": "Findlay",
    "sg:classifiers": [
      {
        "category": "Real Estate",
        "subcategory": "Real Estate Agent",
        "type": "Services"
      }
    ],
    "sg:phone": "+1 419 423 8004",
    "sg:postcode": "45840",
    "sg:province": "OH",
    "sg:website": "www.realestatefindlay.com",
    "wof:name": "Re/Max Realty",
    "wof:placetype": "venue"
  },
  "geometry": {"coordinates":[-83.6192,41.051878],"type":"Point"}
}
