{
  "type": "Feature",
  "properties": {
    "iso:country":"US",
    "sg:address":"1207 Vail Ave",
    "sg:city":"Middletown",
    "sg:classifiers":[
        {
            "category":"Personal",
            "subcategory":"Barber",
            "type":"Services"
        }
    ],
    "sg:phone":"+1 513 422 1814",
    "sg:postcode":"45042",
    "sg:province":"OH",
    "wof:name":"Ray's Barber Shop",
    "wof:placetype":"venue"
},
  "geometry": {"coordinates":[-84.400854,39.516199],"type":"Point"}
}