{
  "type": "Feature",
  "properties": {
    "addr:full": "1903 Cleveland Rd W Sandusky OH 44870",
    "addr:housenumber": "1903",
    "addr:postcode": "44870",
    "addr:street": "Cleveland Rd W",
    "iso:country": "US",
    "sg:address": "1903 Cleveland Rd W",
    "sg:city": "Sandusky",
    "sg:classifiers": [
      {
        "category": "Home \u0026 Garden",
        "subcategory": "Building Materials",
        "type": "Retail Goods"
      }
    ],
    "sg:phone": "+1 419 621 7677",
    "sg:postcode": "44870",
    "sg:province": "OH",
    "wof:name": "Kitchens By Java",
    "wof:placetype": "venue"
  },
  "geometry": {"coordinates":[-82.681441,41.4419],"type":"Point"}
}
