{
  "type": "Feature",
  "properties": {
    "addr:full": "1090 State Rte 28 Milford OH 45150",
    "addr:housenumber": "1090",
    "addr:postcode": "45150",
    "addr:street": "State Rte 28",
    "iso:country": "US",
    "sg:address": "1090 State Rte 28",
    "sg:city": "Milford",
    "sg:classifiers": [
      {
        "category": "Cinema",
        "subcategory": "Movie Rental",
        "type": "Entertainment"
      }
    ],
    "sg:phone": "+1 513 575 0441",
    "sg:postcode": "45150",
    "sg:province": "OH",
    "sg:tags": [
      "leasing",
      "video",
      "disc",
      "tape"
    ],
    "sg:website": "www.blockbuster.com",
    "wof:name": "Blockbuster Video",
    "wof:placetype": "venue"
  },
  "geometry": {"coordinates":[-84.238472,39.194303],"type":"Point"}
}
