{
  "type": "Feature",
  "properties": {
    "addr:full":"14951 Orrville St NW North Lawrence OH 44666",
    "addr:housenumber":"14951",
    "addr:postcode":"44666",
    "addr:street":"Orrville St Nw North",
    "iso:country":"US",
    "sg:address":"14951 Orrville St NW",
    "sg:city":"North Lawrence",
    "sg:classifiers":[
        {
            "category":"Organizations",
            "subcategory":"Religious Organization",
            "type":"Services"
        }
    ],
    "sg:phone":"+1 330 832 9126",
    "sg:postcode":"44666",
    "sg:province":"OH",
    "sg:tags":[
        "clergy"
    ],
    "wof:name":"Chapel Of The Cross United Chr",
    "wof:placetype":"venue"
},
  "geometry": {"coordinates":[-81.63142499999999,40.852039],"type":"Point"}
}