{
  "type": "Feature",
  "properties": {
    "addr:full": "101 William St Yorkville OH 43971",
    "addr:housenumber": "101",
    "addr:postcode": "43971",
    "addr:street": "William St",
    "iso:country": "US",
    "sg:address": "101 William St",
    "sg:city": "Yorkville",
    "sg:classifiers": [
      {
        "category": "Insurance",
        "subcategory": "Insurance Agent",
        "type": "Services"
      }
    ],
    "sg:phone": "+1 740 859 2143",
    "sg:postcode": "43971",
    "sg:province": "OH",
    "wof:name": "Del Vecchio Agency",
    "wof:placetype": "venue"
  },
  "geometry": {"coordinates":[-80.706266,40.15938],"type":"Point"}
}
