{
  "type": "Feature",
  "properties": {
    "addr:full": "200 Putnam St Marietta OH 45750",
    "addr:housenumber": "200",
    "addr:postcode": "45750",
    "addr:street": "Putnam St",
    "iso:country": "US",
    "sg:address": "200 Putnam St",
    "sg:city": "Marietta",
    "sg:classifiers": [
      {
        "category": "Personal",
        "subcategory": "Shoe Repair \u0026 Shine",
        "type": "Services"
      }
    ],
    "sg:phone": "+1 740 373 6640",
    "sg:postcode": "45750",
    "sg:province": "OH",
    "sg:tags": [
      "repairing",
      "boot"
    ],
    "sg:website": "www.cobblerjohn.com",
    "wof:name": "Cobbler John's",
    "wof:placetype": "venue"
  },
  "geometry": {"coordinates":[-81.453311,39.416191],"type":"Point"}
}
