{
  "type": "Feature",
  "properties": {
    "iso:country":"US",
    "sg:address":"1460 Scott Rd",
    "sg:city":"Swanton",
    "sg:classifiers":[
        {
            "category":"Utilities",
            "subcategory":"Electric",
            "type":"Services"
        }
    ],
    "sg:phone":"+1 419 826 5015",
    "sg:postcode":"43558",
    "sg:province":"OH",
    "sg:tags":[
        "company"
    ],
    "wof:name":"Purchasing Power Plus",
    "wof:placetype":"venue"
},
  "geometry": {"coordinates":[-83.864099,41.612877],"type":"Point"}
}