{
  "type": "Feature",
  "properties": {
    "addr:full": "592 12th St Carrollton OH 44615",
    "addr:housenumber": "592",
    "addr:postcode": "44615",
    "addr:street": "12Th St",
    "iso:country": "US",
    "sg:address": "592 12th St",
    "sg:city": "Carrollton",
    "sg:classifiers": [
      {
        "category": "Shopping",
        "subcategory": "Pharmacy",
        "type": "Retail Goods"
      }
    ],
    "sg:phone": "+1 330 627 9005",
    "sg:postcode": "44615",
    "sg:province": "OH",
    "sg:website": "www.discount-drugmart.com",
    "wof:name": "Discount Drug Mart Inc",
    "wof:placetype": "venue"
  },
  "geometry": {"coordinates":[-81.090935,40.589491],"type":"Point"}
}
