{
  "type": "Feature",
  "properties": {
    "iso:country":"US",
    "sg:address":"592 12th St",
    "sg:city":"Carrollton",
    "sg:classifiers":[
        {
            "category":"Shopping",
            "subcategory":"Pharmacy",
            "type":"Retail Goods"
        }
    ],
    "sg:phone":"+1 330 627 9005",
    "sg:postcode":"44615",
    "sg:province":"OH",
    "sg:website":"www.discount-drugmart.com",
    "wof:name":"Discount Drug Mart Inc",
    "wof:placetype":"venue"
},
  "geometry": {"coordinates":[-81.090935,40.589491],"type":"Point"}
}