{
  "type": "Feature",
  "properties": {
    "addr:full":"5865 Stillwell Rd Piqua OH 45356",
    "addr:housenumber":"5865",
    "addr:postcode":"45356",
    "addr:street":"Stillwell Rd",
    "iso:country":"US",
    "sg:address":"5865 Stillwell Rd",
    "sg:city":"Piqua",
    "sg:classifiers":[
        {
            "category":"Shopping",
            "subcategory":"Florist",
            "type":"Retail Goods"
        }
    ],
    "sg:phone":"+1 937 773 6511",
    "sg:postcode":"45356",
    "sg:province":"OH",
    "wof:name":"Specialty Floral Designs",
    "wof:placetype":"venue"
},
  "geometry": {"coordinates":[-84.278306,40.122255],"type":"Point"}
}