{
  "type": "Feature",
  "properties": {
    "addr:full": "2559 Montana Ave Cincinnati OH 45211",
    "addr:housenumber": "2559",
    "addr:postcode": "45211",
    "addr:street": "Montana Ave",
    "iso:country": "US",
    "sg:address": "2559 Montana Ave",
    "sg:city": "Cincinnati",
    "sg:classifiers": [
      {
        "category": "Organizations",
        "subcategory": "Religious Organization",
        "type": "Services"
      }
    ],
    "sg:phone": "+1 513 661 0884",
    "sg:postcode": "45211",
    "sg:province": "OH",
    "sg:tags": [
      "church"
    ],
    "wof:name": "Montana Ave Church Of-Nazarene",
    "wof:placetype": "venue"
  },
  "geometry": {"coordinates":[-84.580865,39.155005],"type":"Point"}
}
