{
  "type": "Feature",
  "properties": {
    "iso:country":"US",
    "sg:address":"474 Maple Circle Dr",
    "sg:city":"Cincinnati",
    "sg:classifiers":[
        {
            "category":"Retail",
            "subcategory":"Portrait Studio",
            "type":"Services"
        }
    ],
    "sg:phone":"+1 513 771 5859",
    "sg:postcode":"45246",
    "sg:province":"OH",
    "sg:tags":[
        "photography"
    ],
    "wof:name":"Virtual Home Tours",
    "wof:placetype":"venue"
},
  "geometry": {"coordinates":[-84.488866,39.299974],"type":"Point"}
}