{
  "type": "Feature",
  "properties": {
    "addr:full":"8022 Glenwood Ave Youngstown OH 44512",
    "addr:housenumber":"8022",
    "addr:postcode":"44512",
    "addr:street":"Glenwood Ave",
    "iso:country":"US",
    "sg:address":"8022 Glenwood Ave",
    "sg:city":"Youngstown",
    "sg:classifiers":[
        {
            "category":"Building & Trades",
            "subcategory":"Electrical",
            "type":"Services"
        }
    ],
    "sg:phone":"+1 330 774 5848",
    "sg:postcode":"44512",
    "sg:province":"OH",
    "sg:tags":[
        "electric",
        "contractor"
    ],
    "wof:name":"Hunter Extended Electric Svc",
    "wof:placetype":"venue"
},
  "geometry": {"coordinates":[-80.672372,41.006372],"type":"Point"}
}