{
  "type": "Feature",
  "properties": {
    "addr:full": "411 Dumbarton Blvd Cleveland OH 44143",
    "addr:housenumber": "411",
    "addr:postcode": "44143",
    "addr:street": "Dumbarton Blvd",
    "iso:country": "US",
    "sg:address": "411 Dumbarton Blvd",
    "sg:city": "Cleveland",
    "sg:classifiers": [
      {
        "category": "Home \u0026 Garden",
        "subcategory": "Building Materials",
        "type": "Retail Goods"
      }
    ],
    "sg:phone": "+1 216 531 8227",
    "sg:postcode": "44143",
    "sg:province": "OH",
    "sg:tags": [
      "windows"
    ],
    "wof:name": "Storey Windows \u0026 Improvements",
    "wof:placetype": "venue"
  },
  "geometry": {"coordinates":[-81.51015,41.552917],"type":"Point"}
}
