{
  "type": "Feature",
  "properties": {
    "addr:full": "714 E Monument Ave Dayton OH 45402",
    "addr:housenumber": "714",
    "addr:postcode": "45402",
    "addr:street": "E Monument Ave",
    "iso:country": "US",
    "sg:address": "714 E Monument Ave",
    "sg:city": "Dayton",
    "sg:classifiers": [
      {
        "category": "Professional",
        "subcategory": "Computer Services",
        "type": "Services"
      }
    ],
    "sg:phone": "+1 937 531 6592",
    "sg:postcode": "45402",
    "sg:province": "OH",
    "sg:tags": [
      "information",
      "technology"
    ],
    "wof:name": "Metro Stocks LLC",
    "wof:placetype": "venue"
  },
  "geometry": {"coordinates":[-84.179906,39.765766],"type":"Point"}
}
