{
  "type": "Feature",
  "properties": {
    "iso:country":"US",
    "sg:address":"10216 Saint Clair Ave",
    "sg:city":"Cleveland",
    "sg:classifiers":[
        {
            "category":"Shopping",
            "subcategory":"Books",
            "type":"Retail Goods"
        }
    ],
    "sg:phone":"+1 216 451 2738",
    "sg:postcode":"44108",
    "sg:province":"OH",
    "sg:tags":[
        "dealer"
    ],
    "wof:name":"Kingdom Revival Center",
    "wof:placetype":"venue"
},
  "geometry": {"coordinates":[-81.617324,41.53785],"type":"Point"}
}