{
  "type": "Feature",
  "properties": {
    "addr:full":"1009 Sargent St Cincinnati OH 45203",
    "addr:housenumber":"1009",
    "addr:postcode":"45203",
    "addr:street":"Sargent St",
    "iso:country":"US",
    "sg:address":"1009 Sargent St",
    "sg:city":"Cincinnati",
    "sg:classifiers":[
        {
            "category":"Wholesale",
            "subcategory":"Construction Materials",
            "type":"Manufacturing & Wholesale Goods"
        }
    ],
    "sg:phone":"+1 513 721 6555",
    "sg:postcode":"45203",
    "sg:province":"OH",
    "sg:website":"www.muellerroofing.com",
    "wof:name":"Mueller Roofing Distributors",
    "wof:placetype":"venue"
},
  "geometry": {"coordinates":[-84.53344,39.098819],"type":"Point"}
}