{
  "type": "Feature",
  "properties": {
    "addr:full": "6465 S Sunbury Rd Westerville OH 43081",
    "addr:housenumber": "6465",
    "addr:postcode": "43081",
    "addr:street": "S Sunbury Rd",
    "iso:country": "US",
    "sg:address": "6465 S Sunbury Rd",
    "sg:city": "Westerville",
    "sg:classifiers": [
      {
        "category": "Banks \u0026 Credit Unions",
        "subcategory": "Investment Brokerage",
        "type": "Services"
      }
    ],
    "sg:phone": "+1 614 890 8214",
    "sg:postcode": "43081",
    "sg:province": "OH",
    "sg:tags": [
      "consultant",
      "planning",
      "financial"
    ],
    "wof:name": "J M Venditelli",
    "wof:placetype": "venue"
  },
  "geometry": {"coordinates":[-82.893489,40.091063],"type":"Point"}
}
