{
  "type": "Feature",
  "properties": {
    "iso:country":"US",
    "sg:address":"1150 W State St",
    "sg:city":"Alliance",
    "sg:classifiers":[
        {
            "category":"Personal",
            "subcategory":"Beauty Salon",
            "type":"Services"
        }
    ],
    "sg:phone":"+1 330 823 3163",
    "sg:postcode":"44601",
    "sg:province":"OH",
    "wof:name":"Cec & Co",
    "wof:placetype":"venue"
},
  "geometry": {"coordinates":[-81.121904,40.901739],"type":"Point"}
}