{
  "type": "Feature",
  "properties": {
    "addr:full": "2481 Boudinot Ave Cincinnati OH 45238",
    "addr:housenumber": "2481",
    "addr:postcode": "45238",
    "addr:street": "Boudinot Ave",
    "iso:country": "US",
    "sg:address": "2481 Boudinot Ave",
    "sg:city": "Cincinnati",
    "sg:classifiers": [
      {
        "category": "Professional",
        "type": "Services"
      }
    ],
    "sg:phone": "+1 513 389 5930",
    "sg:postcode": "45238",
    "sg:province": "OH",
    "sg:tags": [
      "establishment"
    ],
    "wof:name": "Metamor",
    "wof:placetype": "venue"
  },
  "geometry": {"coordinates":[-84.605166,39.132331],"type":"Point"}
}
