{
  "type": "Feature",
  "properties": {
    "addr:full": "1796 Wilton Rd Cleveland OH 44118",
    "addr:housenumber": "1796",
    "addr:postcode": "44118",
    "addr:street": "Wilton Rd",
    "iso:country": "US",
    "sg:address": "1796 Wilton Rd",
    "sg:city": "Cleveland",
    "sg:classifiers": [
      {
        "category": "Building \u0026 Trades",
        "subcategory": "Plumbing",
        "type": "Services"
      }
    ],
    "sg:phone": "+1 216 397 9792",
    "sg:postcode": "44118",
    "sg:province": "OH",
    "sg:tags": [
      "contractor"
    ],
    "wof:name": "Mikes Heating \u0026 Cooling",
    "wof:placetype": "venue"
  },
  "geometry": {"coordinates":[-81.576091,41.510737],"type":"Point"}
}
