{
  "type": "Feature",
  "properties": {
    "iso:country":"US",
    "sg:address":"1796 Wilton Rd",
    "sg:city":"Cleveland",
    "sg:classifiers":[
        {
            "category":"Building & Trades",
            "subcategory":"Plumbing",
            "type":"Services"
        }
    ],
    "sg:phone":"+1 216 397 9792",
    "sg:postcode":"44118",
    "sg:province":"OH",
    "sg:tags":[
        "contractor"
    ],
    "wof:name":"Mikes Heating & Cooling",
    "wof:placetype":"venue"
},
  "geometry": {"coordinates":[-81.576091,41.510737],"type":"Point"}
}