{
  "type": "Feature",
  "properties": {
    "addr:full": "18341 Station Rd Columbia Station OH 44028",
    "addr:housenumber": "18341",
    "addr:postcode": "44028",
    "addr:street": "Station Rd",
    "iso:country": "US",
    "sg:address": "18341 Station Rd",
    "sg:city": "Columbia Station",
    "sg:classifiers": [
      {
        "category": "Building \u0026 Trades",
        "subcategory": "Construction",
        "type": "Services"
      }
    ],
    "sg:phone": "+1 440 236 3388",
    "sg:postcode": "44028",
    "sg:province": "OH",
    "sg:tags": [
      "specializing",
      "rough",
      "framing",
      "contractor"
    ],
    "wof:name": "Skinner Construction Inc",
    "wof:placetype": "venue"
  },
  "geometry": {"coordinates":[-81.955729,41.284741],"type":"Point"}
}
