{
  "type": "Feature",
  "properties": {
    "iso:country":"US",
    "sg:address":"1053 Sundance Dr",
    "sg:city":"Cincinnati",
    "sg:classifiers":[
        {
            "category":"Banks & Credit Unions",
            "subcategory":"Financial Services",
            "type":"Services"
        }
    ],
    "sg:phone":"+1 513 941 7128",
    "sg:postcode":"45233",
    "sg:province":"OH",
    "sg:tags":[
        "investment",
        "closed"
    ],
    "wof:name":"Viel Nutzen Group",
    "wof:placetype":"venue"
},
  "geometry": {"coordinates":[-84.66931099999999,39.116468],"type":"Point"}
}