{
  "type": "Feature",
  "properties": {
    "addr:full":"10 Water St Shelby OH 44875",
    "addr:housenumber":"10",
    "addr:postcode":"44875",
    "addr:street":"Water St",
    "iso:country":"US",
    "sg:address":"10 Water St",
    "sg:city":"Shelby",
    "sg:classifiers":[
        {
            "category":"Building & Trades",
            "subcategory":"Plumbing",
            "type":"Services"
        }
    ],
    "sg:phone":"+1 419 342 4126",
    "sg:postcode":"44875",
    "sg:province":"OH",
    "sg:tags":[
        "septic"
    ],
    "wof:name":"A Plus Rooter & Septic Svc",
    "wof:placetype":"venue"
},
  "geometry": {"coordinates":[-82.661018,40.881467],"type":"Point"}
}