{
  "type": "Feature",
  "properties": {
    "addr:full": "59960 Southgate Rd Byesville OH 43723",
    "addr:housenumber": "59960",
    "addr:postcode": "43723",
    "addr:street": "Southgate Rd",
    "iso:country": "US",
    "sg:address": "59960 Southgate Rd",
    "sg:city": "Byesville",
    "sg:classifiers": [
      {
        "category": "Shopping",
        "subcategory": "Clothing, Apparel, \u0026 Fashions",
        "type": "Retail Goods"
      }
    ],
    "sg:phone": "+1 740 685 2008",
    "sg:postcode": "43723",
    "sg:province": "OH",
    "sg:tags": [
      "t"
    ],
    "wof:name": "Creative TS",
    "wof:placetype": "venue"
  },
  "geometry": {"coordinates":[-81.547542,39.971146],"type":"Point"}
}
