{
  "type": "Feature",
  "properties": {
    "iso:country":"US",
    "sg:address":"1660 S 2nd St",
    "sg:city":"Coshocton",
    "sg:classifiers":[
        {
            "category":"Wholesale",
            "subcategory":"Meat",
            "type":"Manufacturing & Wholesale Goods"
        }
    ],
    "sg:phone":"+1 740 622 6433",
    "sg:postcode":"43812",
    "sg:province":"OH",
    "sg:tags":[
        "product",
        "processed",
        "mfg"
    ],
    "sg:website":"www.kraft.com",
    "wof:name":"Kraft Foods",
    "wof:placetype":"venue"
},
  "geometry": {"coordinates":[-81.870726,40.249561],"type":"Point"}
}