{
  "type": "Feature",
  "properties": {
    "addr:full": "1660 S 2nd St Coshocton OH 43812",
    "addr:housenumber": "1660",
    "addr:postcode": "43812",
    "addr:street": "S 2Nd St",
    "iso:country": "US",
    "sg:address": "1660 S 2nd St",
    "sg:city": "Coshocton",
    "sg:classifiers": [
      {
        "category": "Wholesale",
        "subcategory": "Meat",
        "type": "Manufacturing \u0026 Wholesale Goods"
      }
    ],
    "sg:phone": "+1 740 622 6433",
    "sg:postcode": "43812",
    "sg:province": "OH",
    "sg:tags": [
      "product",
      "processed",
      "mfg"
    ],
    "sg:website": "www.kraft.com",
    "wof:name": "Kraft Foods",
    "wof:placetype": "venue"
  },
  "geometry": {"coordinates":[-81.870726,40.249561],"type":"Point"}
}
