{
  "type": "Feature",
  "properties": {
    "iso:country":"US",
    "sg:address":"439 N High St",
    "sg:city":"Columbus",
    "sg:classifiers":[
        {
            "category":"Restaurant",
            "type":"Food & Drink"
        }
    ],
    "sg:phone":"+1 614 221 3574",
    "sg:postcode":"43215",
    "sg:province":"OH",
    "wof:name":"Guido's Speakeasy",
    "wof:placetype":"venue"
},
  "geometry": {"coordinates":[-83.002499,39.971318],"type":"Point"}
}