{
  "type": "Feature",
  "properties": {
    "addr:full": "3915 W 3rd St Dayton OH 45417",
    "addr:housenumber": "3915",
    "addr:postcode": "45417",
    "addr:street": "W 3Rd St",
    "iso:country": "US",
    "sg:address": "3915 W 3rd St",
    "sg:city": "Dayton",
    "sg:classifiers": [
      {
        "category": "Shopping",
        "subcategory": "Used Merchandise",
        "type": "Retail Goods"
      },
      {
        "category": "Home \u0026 Garden",
        "subcategory": "Household Appliances",
        "type": "Retail Goods"
      }
    ],
    "sg:phone": "+1 937 262 9831",
    "sg:postcode": "45417",
    "sg:province": "OH",
    "wof:name": "Mel's Service \u0026 Appliances",
    "wof:placetype": "venue"
  },
  "geometry": {"coordinates":[-84.251672,39.749717],"type":"Point"}
}
