{
  "type": "Feature",
  "properties": {
    "iso:country":"US",
    "sg:address":"3915 W 3rd St",
    "sg:city":"Dayton",
    "sg:classifiers":[
        {
            "category":"Shopping",
            "subcategory":"Used Merchandise",
            "type":"Retail Goods"
        },
        {
            "category":"Home & Garden",
            "subcategory":"Household Appliances",
            "type":"Retail Goods"
        }
    ],
    "sg:phone":"+1 937 262 9831",
    "sg:postcode":"45417",
    "sg:province":"OH",
    "wof:name":"Mel's Service & Appliances",
    "wof:placetype":"venue"
},
  "geometry": {"coordinates":[-84.251672,39.749717],"type":"Point"}
}