{
  "type": "Feature",
  "properties": {
    "iso:country":"US",
    "sg:address":"2913 W Elm St",
    "sg:city":"Lima",
    "sg:classifiers":[
        {
            "category":"Freight",
            "type":"Transportation"
        }
    ],
    "sg:phone":"+1 419 221 1432",
    "sg:postcode":"45805",
    "sg:province":"OH",
    "sg:tags":[
        "commercial",
        "storage"
    ],
    "wof:name":"American Self Storage",
    "wof:placetype":"venue"
},
  "geometry": {"coordinates":[-84.157892,40.736946],"type":"Point"}
}