{
  "type": "Feature",
  "properties": {
    "iso:country":"US",
    "sg:address":"46890 W Hamilton St",
    "sg:city":"Oberlin",
    "sg:classifiers":[
        {
            "category":"Building & Trades",
            "subcategory":"Construction",
            "type":"Services"
        }
    ],
    "sg:phone":"+1 440 775 4725",
    "sg:postcode":"44074",
    "sg:province":"OH",
    "sg:tags":[
        "house"
    ],
    "wof:name":"George E Clark Builders",
    "wof:placetype":"venue"
},
  "geometry": {"coordinates":[-82.237633,41.279817],"type":"Point"}
}