{
  "type": "Feature",
  "properties": {
    "iso:country":"US",
    "sg:address":"4713 Elyria Ave",
    "sg:city":"Lorain",
    "sg:classifiers":[
        {
            "category":"Freight",
            "type":"Transportation"
        }
    ],
    "sg:phone":"+1 440 233 7545",
    "sg:postcode":"44055",
    "sg:province":"OH",
    "sg:tags":[
        "operator",
        "trucking"
    ],
    "wof:name":"Revercomb Trucking Co",
    "wof:placetype":"venue"
},
  "geometry": {"coordinates":[-82.146199,41.424766],"type":"Point"}
}