{
  "type": "Feature",
  "properties": {
    "iso:country":"US",
    "sg:address":"2277 W Twp Rd 98",
    "sg:city":"Tiffin",
    "sg:classifiers":[
        {
            "category":"Real Estate",
            "subcategory":"Real Estate Operator",
            "type":"Services"
        }
    ],
    "sg:phone":"+1 419 447 0261",
    "sg:postcode":"44883",
    "sg:province":"OH",
    "sg:tags":[
        "building",
        "apartment"
    ],
    "wof:name":"Bbb Properties Ltd",
    "wof:placetype":"venue"
},
  "geometry": {"coordinates":[-83.213916,41.080055],"type":"Point"}
}