{
  "type": "Feature",
  "properties": {
    "addr:full":"501 Grand Lake Rd Celina OH 45822",
    "addr:housenumber":"501",
    "addr:postcode":"45822",
    "addr:street":"Grand Lake Rd",
    "iso:country":"US",
    "sg:address":"501 Grand Lake Rd",
    "sg:city":"Celina",
    "sg:classifiers":[
        {
            "category":"Restaurant",
            "type":"Food & Drink"
        }
    ],
    "sg:phone":"+1 419 586 1117",
    "sg:postcode":"45822",
    "sg:province":"OH",
    "sg:tags":[
        "eating"
    ],
    "wof:name":"Orchard Tree Family Restaurant",
    "wof:placetype":"venue"
},
  "geometry": {"coordinates":[-84.55134,40.553519],"type":"Point"}
}