{
  "type": "Feature",
  "properties": {
    "iso:country":"US",
    "sg:address":"275 McCullough Rd",
    "sg:city":"Sharpsville",
    "sg:phone":"+1   ",
    "sg:postcode":"16150",
    "sg:province":"OH",
    "sg:tags":[
        "farm",
        "corn"
    ],
    "wof:name":"Mc Cullough Brothers",
    "wof:placetype":"venue"
},
  "geometry": {"coordinates":[-80.363457,41.262702],"type":"Point"}
}