{
  "type": "Feature",
  "properties": {
    "addr:full": "275 McCullough Rd Sharpsville OH 16150",
    "addr:housenumber": "275",
    "addr:postcode": "16150",
    "addr:street": "Mccullough Rd",
    "iso:country": "US",
    "sg:address": "275 McCullough Rd",
    "sg:city": "Sharpsville",
    "sg:phone": "+1   ",
    "sg:postcode": "16150",
    "sg:province": "OH",
    "sg:tags": [
      "farm",
      "corn"
    ],
    "wof:name": "Mc Cullough Brothers",
    "wof:placetype": "venue"
  },
  "geometry": {"coordinates":[-80.363457,41.262702],"type":"Point"}
}
