{
  "type": "Feature",
  "properties": {
    "addr:full": "8900 N Dixie Dr Dayton OH 45414",
    "addr:housenumber": "8900",
    "addr:postcode": "45414",
    "addr:street": "N Dixie Dr",
    "iso:country": "US",
    "sg:address": "8900 N Dixie Dr",
    "sg:city": "Dayton",
    "sg:classifiers": [
      {
        "category": "Real Estate",
        "subcategory": "Real Estate Agent",
        "type": "Services"
      }
    ],
    "sg:phone": "+1 937 454 4970",
    "sg:postcode": "45414",
    "sg:province": "OH",
    "wof:name": "Marilyn Barker",
    "wof:placetype": "venue"
  },
  "geometry": {"coordinates":[-84.198956,39.86047],"type":"Point"}
}
