{
  "type": "Feature",
  "properties": {
    "iso:country":"US",
    "sg:address":"799 W Wayne St",
    "sg:city":"Lima",
    "sg:classifiers":[
        {
            "category":"Shopping",
            "subcategory":"Clothing, Apparel, & Fashions",
            "type":"Retail Goods"
        }
    ],
    "sg:phone":"+1 419 222 7700",
    "sg:postcode":"45801",
    "sg:province":"OH",
    "sg:tags":[
        "law",
        "uniform"
    ],
    "wof:name":"Cop Shop",
    "wof:placetype":"venue"
},
  "geometry": {"coordinates":[-84.115484,40.744012],"type":"Point"}
}