{
  "type": "Feature",
  "properties": {
    "addr:full": "8635 Mayfield Rd Chesterland OH 44026",
    "addr:housenumber": "8635",
    "addr:postcode": "44026",
    "addr:street": "Mayfield Rd",
    "iso:country": "US",
    "sg:address": "8635 Mayfield Rd",
    "sg:city": "Chesterland",
    "sg:classifiers": [
      {
        "category": "Health Services",
        "subcategory": "Health Practitioner",
        "type": "Services"
      }
    ],
    "sg:phone": "+1 440 729 0343",
    "sg:postcode": "44026",
    "sg:province": "OH",
    "sg:tags": [
      "psychologist"
    ],
    "wof:name": "Little Place Counseling",
    "wof:placetype": "venue"
  },
  "geometry": {"coordinates":[-81.331952,41.521972],"type":"Point"}
}
