{
  "type": "Feature",
  "properties": {
    "addr:full":"4754 Davis Rd Perry OH 44081",
    "addr:housenumber":"4754",
    "addr:postcode":"44081",
    "addr:street":"Davis Rd",
    "iso:country":"US",
    "sg:address":"4754 Davis Rd",
    "sg:city":"Perry",
    "sg:classifiers":[
        {
            "category":"Food & Beverages",
            "subcategory":"Groceries & Convenience Stores",
            "type":"Retail Goods"
        }
    ],
    "sg:phone":"+1 440 259 4141",
    "sg:postcode":"44081",
    "sg:province":"OH",
    "wof:name":"Burnetts Market",
    "wof:placetype":"venue"
},
  "geometry": {"coordinates":[-81.12945999999999,41.769231],"type":"Point"}
}