{
  "type": "Feature",
  "properties": {
    "iso:country":"US",
    "sg:address":"220 Eastview Dr",
    "sg:city":"Cleveland",
    "sg:classifiers":[
        {
            "category":"Freight",
            "type":"Transportation"
        }
    ],
    "sg:phone":"+1 216 741 1288",
    "sg:postcode":"44131",
    "sg:province":"OH",
    "wof:name":"Collated Products Corp",
    "wof:placetype":"venue"
},
  "geometry": {"coordinates":[-81.674735,41.42784],"type":"Point"}
}