{
  "type": "Feature",
  "properties": {
    "addr:full": "6037 O'Sweeney Ln Dublin OH 43016",
    "addr:postcode": "6037;43016",
    "addr:street": "O'Sweeney Ln",
    "iso:country": "US",
    "sg:address": "6037 O'Sweeney Ln",
    "sg:city": "Dublin",
    "sg:classifiers": [
      {
        "category": "Real Estate",
        "subcategory": "Real Estate Agent",
        "type": "Services"
      }
    ],
    "sg:phone": "+1 614 791 3010",
    "sg:postcode": "43016",
    "sg:province": "OH",
    "sg:tags": [
      "inspection"
    ],
    "wof:name": "ACS Home Inspection",
    "wof:placetype": "venue"
  },
  "geometry": {"coordinates":[-83.014702,40.287836],"type":"Point"}
}
