{
  "type": "Feature",
  "properties": {
    "addr:full": "118 S Market St West Union OH 45693",
    "addr:housenumber": "118",
    "addr:postcode": "45693",
    "addr:street": "S Market St",
    "iso:country": "US",
    "sg:address": "118 S Market St",
    "sg:city": "West Union",
    "sg:classifiers": [
      {
        "category": "Retail",
        "subcategory": "Repair Shop",
        "type": "Services"
      }
    ],
    "sg:phone": "+1 937 544 2721",
    "sg:postcode": "45693",
    "sg:province": "OH",
    "sg:tags": [
      "supply"
    ],
    "wof:name": "West Union Mower Service",
    "wof:placetype": "venue"
  },
  "geometry": {"coordinates":[-83.545745,38.793904],"type":"Point"}
}
