{
  "type": "Feature",
  "properties": {
    "addr:full": "856 Lakeland Dr Westerville OH 43081",
    "addr:housenumber": "856",
    "addr:postcode": "43081",
    "addr:street": "Lakeland Dr",
    "iso:country": "US",
    "sg:address": "856 Lakeland Dr",
    "sg:city": "Westerville",
    "sg:classifiers": [
      {
        "category": "Autos \u0026 Motor Vehicles",
        "subcategory": "Automobile Sales",
        "type": "Retail Goods"
      }
    ],
    "sg:phone": "+1 614 252 9955",
    "sg:postcode": "43081",
    "sg:province": "OH",
    "sg:tags": [
      "used"
    ],
    "wof:name": "Cassady Auto Sales \u0026 Service",
    "wof:placetype": "venue"
  },
  "geometry": {"coordinates":[-82.901612,40.130994],"type":"Point"}
}
