{
  "type": "Feature",
  "properties": {
    "iso:country":"US",
    "sg:address":"856 Lakeland Dr",
    "sg:city":"Westerville",
    "sg:classifiers":[
        {
            "category":"Autos & Motor Vehicles",
            "subcategory":"Automobile Sales",
            "type":"Retail Goods"
        }
    ],
    "sg:phone":"+1 614 252 9955",
    "sg:postcode":"43081",
    "sg:province":"OH",
    "sg:tags":[
        "used"
    ],
    "wof:name":"Cassady Auto Sales & Service",
    "wof:placetype":"venue"
},
  "geometry": {"coordinates":[-82.901612,40.130994],"type":"Point"}
}