{
  "type": "Feature",
  "properties": {
    "addr:full": "1507 W Market St Baltimore OH 43105",
    "addr:housenumber": "1507",
    "addr:postcode": "43105",
    "addr:street": "W Market St",
    "iso:country": "US",
    "sg:address": "1507 W Market St",
    "sg:city": "Baltimore",
    "sg:classifiers": [
      {
        "category": "Retail",
        "subcategory": "Auto Repair",
        "type": "Services"
      }
    ],
    "sg:phone": "+1 740 862 3603",
    "sg:postcode": "43105",
    "sg:province": "OH",
    "sg:tags": [
      "repairing",
      "automobile"
    ],
    "wof:name": "Two Brothers Auto \u0026 Truck Rpr",
    "wof:placetype": "venue"
  },
  "geometry": {"coordinates":[-82.620895,39.845748],"type":"Point"}
}
