{
  "type": "Feature",
  "properties": {
    "addr:full":"5665 Hoover Rd Grove City OH 43123",
    "addr:housenumber":"5665",
    "addr:postcode":"43123",
    "addr:street":"Hoover Rd",
    "iso:country":"US",
    "sg:address":"5665 Hoover Rd",
    "sg:city":"Grove City",
    "sg:classifiers":[
        {
            "category":"Organizations",
            "subcategory":"Non-profit Organization",
            "type":"Services"
        },
        {
            "category":"Social Services",
            "subcategory":"Adult Care",
            "type":"Services"
        }
    ],
    "sg:phone":"+1 614 875 2371",
    "sg:postcode":"43123",
    "sg:province":"OH",
    "sg:tags":[
        "residential",
        "treatment",
        "ctr"
    ],
    "wof:name":"Buckeye Ranch Inc",
    "wof:placetype":"venue"
},
  "geometry": {"coordinates":[-83.07212199999999,39.845185],"type":"Point"}
}