{
  "type": "Feature",
  "properties": {
    "iso:country":"US",
    "sg:address":"21512 Center Ridge Rd",
    "sg:city":"Cleveland",
    "sg:classifiers":[
        {
            "category":"Retail",
            "subcategory":"Auto Repair",
            "type":"Services"
        }
    ],
    "sg:phone":"+1 440 333 9933",
    "sg:postcode":"44116",
    "sg:province":"OH",
    "sg:tags":[
        "repairing",
        "automobile"
    ],
    "wof:name":"Drellishaks Service Center",
    "wof:placetype":"venue"
},
  "geometry": {"coordinates":[-81.854656,41.461277],"type":"Point"}
}