{
  "type": "Feature",
  "properties": {
    "addr:full": "20508 Southgate Park Blvd Cleveland OH 44137",
    "addr:housenumber": "20508",
    "addr:postcode": "44137",
    "addr:street": "Southgate Park Blvd",
    "iso:country": "US",
    "sg:address": "20508 Southgate Park Blvd",
    "sg:city": "Cleveland",
    "sg:classifiers": [
      {
        "category": "Shopping",
        "subcategory": "Clothing, Apparel, \u0026 Fashions",
        "type": "Retail Goods"
      }
    ],
    "sg:phone": "+1 216 475 1722",
    "sg:postcode": "44137",
    "sg:province": "OH",
    "sg:tags": [
      "tailor"
    ],
    "wof:name": "Curtis \u0026 Marilyn Gibsons",
    "wof:placetype": "venue"
  },
  "geometry": {"coordinates":[-81.534019,41.414144],"type":"Point"}
}
