{
  "type": "Feature",
  "properties": {
    "iso:country":"US",
    "sg:address":"20508 Southgate Park Blvd",
    "sg:city":"Cleveland",
    "sg:classifiers":[
        {
            "category":"Shopping",
            "subcategory":"Clothing, Apparel, & Fashions",
            "type":"Retail Goods"
        }
    ],
    "sg:phone":"+1 216 475 1722",
    "sg:postcode":"44137",
    "sg:province":"OH",
    "sg:tags":[
        "tailor"
    ],
    "wof:name":"Curtis & Marilyn Gibsons",
    "wof:placetype":"venue"
},
  "geometry": {"coordinates":[-81.534019,41.414144],"type":"Point"}
}