{
  "type": "Feature",
  "properties": {
    "addr:full": "3833 Herr Rd Sylvania OH 43560",
    "addr:housenumber": "3833",
    "addr:postcode": "43560",
    "addr:street": "Herr Rd",
    "iso:country": "US",
    "sg:address": "3833 Herr Rd",
    "sg:city": "Sylvania",
    "sg:classifiers": [
      {
        "category": "Banks \u0026 Credit Unions",
        "subcategory": "Financial Services",
        "type": "Services"
      }
    ],
    "sg:phone": "+1 419 842 0029",
    "sg:postcode": "43560",
    "sg:province": "OH",
    "sg:tags": [
      "trust",
      "investment",
      "real estate"
    ],
    "wof:name": "L B P Ltd",
    "wof:placetype": "venue"
  },
  "geometry": {"coordinates":[-83.756796,41.68535],"type":"Point"}
}
