{
  "type": "Feature",
  "properties": {
    "iso:country":"US",
    "sg:address":"28 W Main St",
    "sg:city":"Shelby",
    "sg:classifiers":[
        {
            "category":"Health Services",
            "subcategory":"Doctor",
            "type":"Services"
        }
    ],
    "sg:phone":"+1 419 342 0000",
    "sg:postcode":"44875",
    "sg:province":"OH",
    "sg:tags":[
        "clinic"
    ],
    "wof:name":"Shaw Ott Medical",
    "wof:placetype":"venue"
},
  "geometry": {"coordinates":[-82.660595,40.881417],"type":"Point"}
}