{
  "type": "Feature",
  "properties": {
    "addr:full": "117 E Crocker St Bradner OH 43406",
    "addr:housenumber": "117",
    "addr:postcode": "43406",
    "addr:street": "E Crocker St",
    "iso:country": "US",
    "sg:address": "117 E Crocker St",
    "sg:city": "Bradner",
    "sg:classifiers": [
      {
        "category": "Government",
        "subcategory": "Fire Station",
        "type": "Public Place"
      }
    ],
    "sg:phone": "+1 419 288 2012",
    "sg:postcode": "43406",
    "sg:province": "OH",
    "sg:tags": [
      "department"
    ],
    "wof:name": "Fire Department",
    "wof:placetype": "venue"
  },
  "geometry": {"coordinates":[-83.435866,41.322829],"type":"Point"}
}
