{
  "type": "Feature",
  "properties": {
    "addr:full":"181 N Hamilton Rd Columbus OH 43213",
    "addr:housenumber":"181",
    "addr:postcode":"43213",
    "addr:street":"N Hamilton Rd",
    "iso:country":"US",
    "sg:address":"181 N Hamilton Rd",
    "sg:city":"Columbus",
    "sg:classifiers":[
        {
            "category":"Building & Trades",
            "subcategory":"Construction",
            "type":"Services"
        }
    ],
    "sg:phone":"+1 614 864 2067",
    "sg:postcode":"43213",
    "sg:province":"OH",
    "sg:tags":[
        "hanging",
        "contractor"
    ],
    "wof:name":"Bookout Painting",
    "wof:placetype":"venue"
},
  "geometry": {"coordinates":[-82.873924,39.977489],"type":"Point"}
}