{
  "type": "Feature",
  "properties": {
    "addr:full":"161 N Washington St Millersburg OH 44654",
    "addr:housenumber":"161",
    "addr:postcode":"44654",
    "addr:street":"N Washington St",
    "iso:country":"US",
    "sg:address":"161 N Washington St",
    "sg:city":"Millersburg",
    "sg:classifiers":[
        {
            "category":"Professional",
            "subcategory":"Accounting & Tax Preparation",
            "type":"Services"
        }
    ],
    "sg:phone":"+1 330 674 8466",
    "sg:postcode":"44654",
    "sg:province":"OH",
    "sg:tags":[
        "accountant"
    ],
    "wof:name":"Bromund and Byler Inc",
    "wof:placetype":"venue"
},
  "geometry": {"coordinates":[-81.91834799999999,40.555837],"type":"Point"}
}