{
  "type": "Feature",
  "properties": {
    "addr:full": "3000 Hospital Dr Batavia OH 45103",
    "addr:housenumber": "3000",
    "addr:postcode": "45103",
    "addr:street": "Hospital Dr",
    "iso:country": "US",
    "sg:address": "3000 Hospital Dr",
    "sg:city": "Batavia",
    "sg:classifiers": [
      {
        "category": "Shopping",
        "subcategory": "Gifts \u0026 Souvenirs",
        "type": "Retail Goods"
      }
    ],
    "sg:phone": "+1 513 732 8218",
    "sg:postcode": "45103",
    "sg:province": "OH",
    "wof:name": "Charmae Gift Shop",
    "wof:placetype": "venue"
  },
  "geometry": {"coordinates":[-84.146042,39.078962],"type":"Point"}
}
