{
  "type": "Feature",
  "properties": {
    "addr:full":"10800 Pearl Rd Cleveland OH 44136",
    "addr:housenumber":"10800",
    "addr:postcode":"44136",
    "addr:street":"Pearl Rd",
    "iso:country":"US",
    "sg:address":"10800 Pearl Rd",
    "sg:city":"Cleveland",
    "sg:classifiers":[
        {
            "category":"Professional",
            "subcategory":"Management & Consulting",
            "type":"Services"
        }
    ],
    "sg:phone":"+1 440 238 7880",
    "sg:postcode":"44136",
    "sg:province":"OH",
    "sg:tags":[
        "consultant",
        "publishing"
    ],
    "wof:name":"Tabpi",
    "wof:placetype":"venue"
},
  "geometry": {"coordinates":[-81.836887,41.331184],"type":"Point"}
}