{
  "type": "Feature",
  "properties": {
    "addr:full":"5691 Routzong Rd Greenville OH 45331",
    "addr:housenumber":"5691",
    "addr:postcode":"45331",
    "addr:street":"Routzong Rd",
    "iso:country":"US",
    "sg:address":"5691 Routzong Rd",
    "sg:city":"Greenville",
    "sg:classifiers":[
        {
            "category":"Real Estate",
            "subcategory":"Real Estate Operator",
            "type":"Services"
        }
    ],
    "sg:phone":"+1 937 548 7986",
    "sg:postcode":"45331",
    "sg:province":"OH",
    "sg:tags":[
        "property",
        "lessor"
    ],
    "wof:name":"Donnie Baker",
    "wof:placetype":"venue"
},
  "geometry": {"coordinates":[-84.525935,40.082511],"type":"Point"}
}