{
  "type": "Feature",
  "properties": {
    "addr:full": "222 Front Ave SW New Philadelphia OH 44663",
    "addr:housenumber": "222",
    "addr:postcode": "44663",
    "addr:street": "Front Ave Sw",
    "iso:country": "US",
    "sg:address": "222 Front Ave SW",
    "sg:city": "New Philadelphia",
    "sg:classifiers": [
      {
        "category": "Personal",
        "subcategory": "Beauty Salon",
        "type": "Services"
      }
    ],
    "sg:phone": "+1 330 339 6541",
    "sg:postcode": "44663",
    "sg:province": "OH",
    "wof:name": "Yong's Salon",
    "wof:placetype": "venue"
  },
  "geometry": {"coordinates":[-81.44846,40.488212],"type":"Point"}
}
