{
  "type": "Feature",
  "properties": {
    "iso:country":"US",
    "sg:address":"6879 Southland Dr",
    "sg:city":"Cleveland",
    "sg:classifiers":[
        {
            "category":"Personal",
            "subcategory":"Barber",
            "type":"Services"
        }
    ],
    "sg:phone":"+1 440 842 1057",
    "sg:postcode":"44130",
    "sg:province":"OH",
    "wof:name":"Frank's Barber Shop",
    "wof:placetype":"venue"
},
  "geometry": {"coordinates":[-81.786838,41.378347],"type":"Point"}
}