{
  "type": "Feature",
  "properties": {
    "addr:full": "4242 Needmore Rd Dayton OH 45424",
    "addr:housenumber": "4242",
    "addr:postcode": "45424",
    "addr:street": "Needmore Rd",
    "iso:country": "US",
    "sg:address": "4242 Needmore Rd",
    "sg:city": "Dayton",
    "sg:classifiers": [
      {
        "category": "Organizations",
        "subcategory": "Religious Organization",
        "type": "Services"
      }
    ],
    "sg:phone": "+1 937 233 2970",
    "sg:postcode": "45424",
    "sg:province": "OH",
    "sg:tags": [
      "church"
    ],
    "sg:website": "www.landmarkbaptistdayton.com",
    "wof:name": "Landmark Baptist Church",
    "wof:placetype": "venue"
  },
  "geometry": {"coordinates":[-84.139236,39.820763],"type":"Point"}
}
