{
  "type": "Feature",
  "properties": {
    "addr:full": "5471 State Rte 274 W Huntsville OH 43324",
    "addr:housenumber": "5471",
    "addr:postcode": "43324",
    "addr:street": "State Rte 274 W",
    "iso:country": "US",
    "sg:address": "5471 State Rte 274 W",
    "sg:city": "Huntsville",
    "sg:classifiers": [
      {
        "category": "Building \u0026 Trades",
        "subcategory": "Construction",
        "type": "Services"
      }
    ],
    "sg:phone": "+1 937 686 6383",
    "sg:postcode": "43324",
    "sg:province": "OH",
    "sg:tags": [
      "home",
      "improvement"
    ],
    "wof:name": "B G Lawn \u0026 Home Maintenance",
    "wof:placetype": "venue"
  },
  "geometry": {"coordinates":[-83.814644,40.446155],"type":"Point"}
}
