{
  "type": "Feature",
  "properties": {
    "iso:country":"US",
    "sg:address":"52 W Whittier St",
    "sg:city":"Columbus",
    "sg:phone":"+1 614 444 8800",
    "sg:postcode":"43206",
    "sg:province":"OH",
    "sg:website":"http://www.terrysherman-law.com",
    "wof:name":"Terry K Sherman",
    "wof:placetype":"venue"
},
  "geometry": {"coordinates":[-82.998909,39.94408],"type":"Point"}
}