{
  "type": "Feature",
  "properties": {
    "addr:full":"887 W Maple St Hartville OH 44632",
    "addr:housenumber":"887",
    "addr:postcode":"44632",
    "addr:street":"W Maple St",
    "iso:country":"US",
    "sg:address":"887 W Maple St",
    "sg:city":"Hartville",
    "sg:classifiers":[
        {
            "category":"Shopping",
            "subcategory":"Hobbies, Toys, & Games",
            "type":"Retail Goods"
        }
    ],
    "sg:phone":"+1 330 877 8697",
    "sg:postcode":"44632",
    "sg:province":"OH",
    "wof:name":"Iq Toys and Games Inc",
    "wof:placetype":"venue"
},
  "geometry": {"coordinates":[-81.344909,40.96752],"type":"Point"}
}