{
  "type": "Feature",
  "properties": {
    "iso:country":"US",
    "sg:address":"874 US Hwy 250 N",
    "sg:city":"Ashland",
    "sg:classifiers":[
        {
            "category":"Autos & Motor Vehicles",
            "subcategory":"Auto Supplies",
            "type":"Retail Goods"
        }
    ],
    "sg:phone":"+1 419 962 4334",
    "sg:postcode":"44805",
    "sg:province":"OH",
    "sg:tags":[
        "tire"
    ],
    "wof:name":"Myers Tires LLC",
    "wof:placetype":"venue"
},
  "geometry": {"coordinates":[-82.319003,40.875177],"type":"Point"}
}