{
  "type": "Feature",
  "properties": {
    "iso:country":"US",
    "sg:address":"1256 Rand Ave",
    "sg:city":"Columbus",
    "sg:classifiers":[
        {
            "category":"Real Estate",
            "subcategory":"Real Estate Operator",
            "type":"Services"
        }
    ],
    "sg:phone":"+1 614 237 1792",
    "sg:postcode":"43227",
    "sg:province":"OH",
    "sg:tags":[
        "owner",
        "building",
        "apartment"
    ],
    "wof:name":"Colonial Village Apartments",
    "wof:placetype":"venue"
},
  "geometry": {"coordinates":[-82.900728,39.946516],"type":"Point"}
}