{
  "type": "Feature",
  "properties": {
    "iso:country":"US",
    "sg:address":"7795 S State Rte 48",
    "sg:city":"Maineville",
    "sg:classifiers":[
        {
            "category":"Banks & Credit Unions",
            "subcategory":"Bank",
            "type":"Services"
        }
    ],
    "sg:phone":"+1 513 677 2203",
    "sg:postcode":"45039",
    "sg:province":"OH",
    "wof:name":"Lebanon Citizens National Bank",
    "wof:placetype":"venue"
},
  "geometry": {"coordinates":[-84.220919,39.318757],"type":"Point"}
}