{
  "type": "Feature",
  "properties": {
    "iso:country":"US",
    "sg:address":"3766 Fishcreek Rd",
    "sg:city":"Stow",
    "sg:classifiers":[
        {
            "category":"Education",
            "subcategory":"Vocational School",
            "type":"Public Place"
        }
    ],
    "sg:phone":"+1 330 676 0022",
    "sg:postcode":"44224",
    "sg:province":"OH",
    "sg:tags":[
        "processing",
        "datum"
    ],
    "wof:name":"Razorleaf Corp",
    "wof:placetype":"venue"
},
  "geometry": {"coordinates":[-81.401488,41.1614],"type":"Point"}
}