{
  "type": "Feature",
  "properties": {
    "iso:country":"US",
    "sg:address":"8035 Hamilton Ave",
    "sg:city":"Cincinnati",
    "sg:classifiers":[
        {
            "category":"Health Services",
            "subcategory":"Chiropractor",
            "type":"Services"
        }
    ],
    "sg:phone":"+1 513 522 3600",
    "sg:postcode":"45231",
    "sg:province":"OH",
    "wof:name":"Wells Health Care",
    "wof:placetype":"venue"
},
  "geometry": {"coordinates":[-84.547521,39.240692],"type":"Point"}
}