{
  "type": "Feature",
  "properties": {
    "addr:full":"10686 Loveland Madeira Rd Loveland OH 45140",
    "addr:housenumber":"10686",
    "addr:postcode":"45140",
    "addr:street":"Loveland Madeira Rd",
    "iso:country":"US",
    "sg:address":"10686 Loveland Madeira Rd",
    "sg:city":"Loveland",
    "sg:classifiers":[
        {
            "category":"Freight",
            "type":"Transportation"
        }
    ],
    "sg:phone":"+1 513 697 7407",
    "sg:postcode":"45140",
    "sg:province":"OH",
    "sg:tags":[
        "storage"
    ],
    "wof:name":"Loveland Self Storage",
    "wof:placetype":"venue"
},
  "geometry": {"coordinates":[-84.296442,39.250931],"type":"Point"}
}