{
  "type": "Feature",
  "properties": {
    "iso:country":"US",
    "sg:address":"4924 N Summit St",
    "sg:city":"Toledo",
    "sg:classifiers":[
        {
            "category":"Building & Trades",
            "subcategory":"Plumbing",
            "type":"Services"
        }
    ],
    "sg:phone":"+1 419 726 9335",
    "sg:postcode":"43611",
    "sg:province":"OH",
    "sg:tags":[
        "plumbing",
        "contractor"
    ],
    "sg:website":"www.interiorchannel.net",
    "wof:name":"Rooter Pro",
    "wof:placetype":"venue"
},
  "geometry": {"coordinates":[-83.478956,41.712573],"type":"Point"}
}