{
  "type": "Feature",
  "properties": {
    "iso:country":"US",
    "sg:address":"2614 Spring Grove Ave",
    "sg:city":"Cincinnati",
    "sg:classifiers":[
        {
            "category":"Manufacturing",
            "subcategory":"Printing",
            "type":"Manufacturing & Wholesale Goods"
        }
    ],
    "sg:phone":"+1 513 542 7154",
    "sg:postcode":"45214",
    "sg:province":"OH",
    "sg:tags":[
        "offset"
    ],
    "wof:name":"Ideas & Ad Ventures Inc",
    "wof:placetype":"venue"
},
  "geometry": {"coordinates":[-84.53671,39.130404],"type":"Point"}
}