{
  "type": "Feature",
  "properties": {
    "addr:full": "6920 Morgan Rd Cleves OH 45002",
    "addr:housenumber": "6920",
    "addr:postcode": "45002",
    "addr:street": "Morgan Rd",
    "iso:country": "US",
    "sg:address": "6920 Morgan Rd",
    "sg:city": "Cleves",
    "sg:classifiers": [
      {
        "category": "Retail",
        "subcategory": "Animal Services",
        "type": "Services"
      }
    ],
    "sg:phone": "+1 513 379 2589",
    "sg:postcode": "45002",
    "sg:province": "OH",
    "sg:tags": [
      "training",
      "dog"
    ],
    "wof:name": "No Bones About It Dog Training",
    "wof:placetype": "venue"
  },
  "geometry": {"coordinates":[-84.755492,39.217078],"type":"Point"}
}
