{
  "type": "Feature",
  "properties": {
    "iso:country":"US",
    "sg:address":"13660 Station Rd",
    "sg:city":"Columbia Station",
    "sg:classifiers":[
        {
            "category":"Home & Garden",
            "subcategory":"Building Materials",
            "type":"Retail Goods"
        },
        {
            "category":"Manufacturing",
            "subcategory":"Motor Vehicles & Parts",
            "type":"Manufacturing & Wholesale Goods"
        }
    ],
    "sg:phone":"+1 440 236 6009",
    "sg:postcode":"44028",
    "sg:province":"OH",
    "sg:tags":[
        "mfg",
        "propane",
        "energy",
        "equipment",
        "construction",
        "conservation",
        "prod"
    ],
    "wof:name":"Superior Energy Systems Ltd",
    "wof:placetype":"venue"
},
  "geometry": {"coordinates":[-81.94556300000001,41.316064],"type":"Point"}
}