{
  "type": "Feature",
  "properties": {
    "addr:full": "2800 Superior Ave E Cleveland OH 44114",
    "addr:housenumber": "2800",
    "addr:postcode": "44114",
    "addr:street": "Superior Ave E",
    "iso:country": "US",
    "sg:address": "2800 Superior Ave E",
    "sg:city": "Cleveland",
    "sg:classifiers": [
      {
        "category": "Home \u0026 Garden",
        "subcategory": "Furniture",
        "type": "Retail Goods"
      }
    ],
    "sg:phone": "+1 216 830 2626",
    "sg:postcode": "44114",
    "sg:province": "OH",
    "sg:tags": [
      "store"
    ],
    "wof:name": "Cuyahoga Furniture",
    "wof:placetype": "venue"
  },
  "geometry": {"coordinates":[-81.671516,41.51017],"type":"Point"}
}
