{
  "type": "Feature",
  "properties": {
    "addr:full":"17392 Twp Rd 50 Forest OH 45843",
    "addr:housenumber":"50",
    "addr:postcode":"17392;45843",
    "addr:street":"Twp Rd",
    "iso:country":"US",
    "sg:address":"17392 Twp Rd 50",
    "sg:city":"Forest",
    "sg:phone":"+1 419 273 2814",
    "sg:postcode":"45843",
    "sg:province":"OH",
    "sg:tags":[
        "farm",
        "corn",
        "wheat",
        "soybean"
    ],
    "wof:name":"Kellogg Farms",
    "wof:placetype":"venue"
},
  "geometry": {"coordinates":[-83.549952,40.759908],"type":"Point"}
}