{
  "type": "Feature",
  "properties": {
    "addr:full":"5 Triangle Park Dr Cincinnati OH 45246",
    "addr:housenumber":"5",
    "addr:postcode":"45246",
    "addr:street":"Triangle Park Dr",
    "iso:country":"US",
    "sg:address":"5 Triangle Park Dr",
    "sg:city":"Cincinnati",
    "sg:classifiers":[
        {
            "category":"Shopping",
            "subcategory":"Stationery & Office Supplies",
            "type":"Retail Goods"
        }
    ],
    "sg:phone":"+1 513 326 6060",
    "sg:postcode":"45246",
    "sg:province":"OH",
    "wof:name":"Tri State Office Supplies",
    "wof:placetype":"venue"
},
  "geometry": {"coordinates":[-84.447428,39.289031],"type":"Point"}
}