{
  "type": "Feature",
  "properties": {
    "iso:country":"US",
    "sg:address":"326 N Water St",
    "sg:city":"Loudonville",
    "sg:classifiers":[
        {
            "category":"Wholesale",
            "subcategory":"Non-durable Goods",
            "type":"Manufacturing & Wholesale Goods"
        }
    ],
    "sg:phone":"+1 419 994 4313",
    "sg:postcode":"44842",
    "sg:province":"OH",
    "sg:tags":[
        "advertising"
    ],
    "sg:website":"www.raindropad.com",
    "wof:name":"Raindrop Advertising & Spec",
    "wof:placetype":"venue"
},
  "geometry": {"coordinates":[-82.23486,40.638382],"type":"Point"}
}