{
  "type": "Feature",
  "properties": {
    "addr:full": "326 N Water St Loudonville OH 44842",
    "addr:housenumber": "326",
    "addr:postcode": "44842",
    "addr:street": "N Water St",
    "iso:country": "US",
    "sg:address": "326 N Water St",
    "sg:city": "Loudonville",
    "sg:classifiers": [
      {
        "category": "Wholesale",
        "subcategory": "Non-durable Goods",
        "type": "Manufacturing \u0026 Wholesale Goods"
      }
    ],
    "sg:phone": "+1 419 994 4313",
    "sg:postcode": "44842",
    "sg:province": "OH",
    "sg:tags": [
      "advertising"
    ],
    "sg:website": "www.raindropad.com",
    "wof:name": "Raindrop Advertising \u0026 Spec",
    "wof:placetype": "venue"
  },
  "geometry": {"coordinates":[-82.23486,40.638382],"type":"Point"}
}
