{
  "type": "Feature",
  "properties": {
    "addr:full":"14567 Madison Ave Cleveland OH 44107",
    "addr:housenumber":"14567",
    "addr:postcode":"44107",
    "addr:street":"Madison Ave",
    "iso:country":"US",
    "sg:address":"14567 Madison Ave",
    "sg:city":"Cleveland",
    "sg:classifiers":[
        {
            "category":"Real Estate",
            "subcategory":"Surveying",
            "type":"Services"
        },
        {
            "category":"Building & Trades",
            "subcategory":"Landscaping Services",
            "type":"Services"
        }
    ],
    "sg:phone":"+1 216 521 6960",
    "sg:postcode":"44107",
    "sg:province":"OH",
    "sg:tags":[
        "surveyor",
        "landscape"
    ],
    "wof:name":"Lakewood Surveys",
    "wof:placetype":"venue"
},
  "geometry": {"coordinates":[-81.797546,41.477121],"type":"Point"}
}