{
  "type": "Feature",
  "properties": {
    "iso:country":"US",
    "sg:address":"4031 S Main St",
    "sg:city":"Akron",
    "sg:classifiers":[
        {
            "category":"Restaurant",
            "type":"Food & Drink"
        }
    ],
    "sg:phone":"+1 330 644 8288",
    "sg:postcode":"44319",
    "sg:province":"OH",
    "sg:tags":[
        "eating"
    ],
    "wof:name":"China House",
    "wof:placetype":"venue"
},
  "geometry": {"coordinates":[-81.522569,40.977389],"type":"Point"}
}