{
  "type": "Feature",
  "properties": {
    "addr:full": "215 Seth Ave Jackson OH 45640",
    "addr:housenumber": "215",
    "addr:postcode": "45640",
    "addr:street": "Seth Ave",
    "iso:country": "US",
    "sg:address": "215 Seth Ave",
    "sg:city": "Jackson",
    "sg:classifiers": [
      {
        "category": "Health Services",
        "subcategory": "Nursing And Care Facility",
        "type": "Services"
      }
    ],
    "sg:phone": "+1 740 286 7551",
    "sg:postcode": "45640",
    "sg:province": "OH",
    "sg:tags": [
      "skilled",
      "intermediate"
    ],
    "sg:website": "www.fourwindsnursing.org",
    "wof:name": "Four Winds Nursing Facility",
    "wof:placetype": "venue"
  },
  "geometry": {"coordinates":[-82.573608,39.072947],"type":"Point"}
}
