{
  "type": "Feature",
  "properties": {
    "addr:full": "4331 Dorset Dr Dayton OH 45405",
    "addr:housenumber": "4331",
    "addr:postcode": "45405",
    "addr:street": "Dorset Dr",
    "iso:country": "US",
    "sg:address": "4331 Dorset Dr",
    "sg:city": "Dayton",
    "sg:classifiers": [
      {
        "category": "Building \u0026 Trades",
        "subcategory": "Construction",
        "type": "Services"
      }
    ],
    "sg:phone": "+1 937 274 8090",
    "sg:postcode": "45405",
    "sg:province": "OH",
    "sg:tags": [
      "house",
      "nonresidential"
    ],
    "wof:name": "Capstone Construction Company",
    "wof:placetype": "venue"
  },
  "geometry": {"coordinates":[-84.232768,39.806552],"type":"Point"}
}
