{
  "type": "Feature",
  "properties": {
    "addr:full":"10171 E Pike Rd Cambridge OH 43725",
    "addr:housenumber":"10171",
    "addr:postcode":"43725",
    "addr:street":"E Pike Rd",
    "iso:country":"US",
    "sg:address":"10171 E Pike Rd",
    "sg:city":"Cambridge",
    "sg:classifiers":[
        {
            "category":"Real Estate",
            "subcategory":"Developer",
            "type":"Services"
        }
    ],
    "sg:phone":"+1 740 432 3200",
    "sg:postcode":"43725",
    "sg:province":"OH",
    "sg:tags":[
        "cemetery"
    ],
    "wof:name":"Guernsey County Memory Gardens",
    "wof:placetype":"venue"
},
  "geometry": {"coordinates":[-81.55136899999999,40.025693],"type":"Point"}
}