{
  "type": "Feature",
  "properties": {
    "addr:full":"899 E Broad St Columbus OH 43205",
    "addr:housenumber":"899",
    "addr:postcode":"43205",
    "addr:street":"E Broad St",
    "iso:country":"US",
    "sg:address":"899 E Broad St",
    "sg:city":"Columbus",
    "sg:classifiers":[
        {
            "category":"Social Services",
            "type":"Services"
        }
    ],
    "sg:phone":"+1 614 224 2043",
    "sg:postcode":"43205",
    "sg:province":"OH",
    "sg:tags":[
        "organization",
        "welfare"
    ],
    "wof:name":"Permanent Family Solutions Net",
    "wof:placetype":"venue"
},
  "geometry": {"coordinates":[-82.976676,39.964881],"type":"Point"}
}