{
  "type": "Feature",
  "properties": {
    "addr:full":"1263 W Ohio Pike Amelia OH 45102",
    "addr:housenumber":"1263",
    "addr:postcode":"45102",
    "addr:street":"W Ohio Pike",
    "iso:country":"US",
    "sg:address":"1263 W Ohio Pike",
    "sg:city":"Amelia",
    "sg:classifiers":[
        {
            "category":"Autos & Motor Vehicles",
            "subcategory":"Fuel & Gas Station",
            "type":"Retail Goods"
        }
    ],
    "sg:phone":"+1 513 752 9954",
    "sg:postcode":"45102",
    "sg:province":"OH",
    "sg:tags":[
        "station",
        "gasoline"
    ],
    "wof:name":"Sunoco",
    "wof:placetype":"venue"
},
  "geometry": {"coordinates":[-84.231481,39.037983],"type":"Point"}
}