{
  "type": "Feature",
  "properties": {
    "addr:full": "172 E State St Columbus OH 43215",
    "addr:housenumber": "172",
    "addr:postcode": "43215",
    "addr:street": "E State St",
    "iso:country": "US",
    "sg:address": "172 E State St",
    "sg:city": "Columbus",
    "sg:classifiers": [
      {
        "category": "Professional",
        "subcategory": "Research",
        "type": "Services"
      }
    ],
    "sg:phone": "+1 614 221 9226",
    "sg:postcode": "43215",
    "sg:province": "OH",
    "sg:tags": [
      "environmental",
      "ecological"
    ],
    "wof:name": "Steven H White \u0026 Assoc",
    "wof:placetype": "venue"
  },
  "geometry": {"coordinates":[-82.995261,39.960783],"type":"Point"}
}
