{
  "type": "Feature",
  "properties": {
    "addr:full":"3136 W Sylvania Ave Toledo OH 43613",
    "addr:housenumber":"3136",
    "addr:postcode":"43613",
    "addr:street":"W Sylvania Ave",
    "iso:country":"US",
    "sg:address":"3136 W Sylvania Ave",
    "sg:city":"Toledo",
    "sg:classifiers":[
        {
            "category":"Shopping",
            "subcategory":"Used Merchandise",
            "type":"Retail Goods"
        }
    ],
    "sg:phone":"+1 419 471 0073",
    "sg:postcode":"43613",
    "sg:province":"OH",
    "sg:tags":[
        "shop",
        "resale",
        "consignment",
        "clothes"
    ],
    "wof:name":"Growing Years Too",
    "wof:placetype":"venue"
},
  "geometry": {"coordinates":[-83.620677,41.691925],"type":"Point"}
}