{
  "type": "Feature",
  "properties": {
    "addr:full":"420 Prospect St Fairport Harbor OH 44077",
    "addr:housenumber":"420",
    "addr:postcode":"44077",
    "addr:street":"Prospect St",
    "iso:country":"US",
    "sg:address":"420 Prospect St",
    "sg:city":"Fairport Harbor",
    "sg:classifiers":[
        {
            "category":"Building & Trades",
            "subcategory":"Landscaping Services",
            "type":"Services"
        }
    ],
    "sg:phone":"+1 440 358 9701",
    "sg:postcode":"44077",
    "sg:province":"OH",
    "sg:tags":[
        "landscape",
        "contractor"
    ],
    "wof:name":"Peabody Landscape Group",
    "wof:placetype":"venue"
},
  "geometry": {"coordinates":[-81.270883,41.757842],"type":"Point"}
}