{
  "type": "Feature",
  "properties": {
    "iso:country":"US",
    "sg:address":"6044 E US Hwy 36",
    "sg:city":"Cable",
    "sg:classifiers":[
        {
            "category":"Professional",
            "type":"Services"
        }
    ],
    "sg:phone":"+1 937 653 5125",
    "sg:postcode":"43009",
    "sg:province":"OH",
    "wof:name":"James L Bartlett",
    "wof:placetype":"venue"
},
  "geometry": {"coordinates":[-83.63301,40.116422],"type":"Point"}
}