{
  "type": "Feature",
  "properties": {
    "addr:full": "6044 E US Hwy 36 Cable OH 43009",
    "addr:housenumber": "6044",
    "addr:postcode": "43009",
    "addr:street": "E Us Hwy 36",
    "iso:country": "US",
    "sg:address": "6044 E US Hwy 36",
    "sg:city": "Cable",
    "sg:classifiers": [
      {
        "category": "Professional",
        "type": "Services"
      }
    ],
    "sg:phone": "+1 937 653 5125",
    "sg:postcode": "43009",
    "sg:province": "OH",
    "wof:name": "James L Bartlett",
    "wof:placetype": "venue"
  },
  "geometry": {"coordinates":[-83.63301,40.116422],"type":"Point"}
}
