{
  "type": "Feature",
  "properties": {
    "iso:country":"US",
    "sg:address":"2791 State Rte 14",
    "sg:city":"Rootstown",
    "sg:classifiers":[
        {
            "category":"Building & Trades",
            "subcategory":"Plumbing",
            "type":"Services"
        }
    ],
    "sg:phone":"+1 330 947 0648",
    "sg:postcode":"44272",
    "sg:province":"OH",
    "sg:tags":[
        "tank",
        "septic",
        "contractor"
    ],
    "wof:name":"Steven Cutlip Excavating",
    "wof:placetype":"venue"
},
  "geometry": {"coordinates":[-81.099015,41.062462],"type":"Point"}
}