{
  "type": "Feature",
  "properties": {
    "iso:country":"US",
    "sg:address":"10920 Deer Run Dr",
    "sg:city":"Grafton",
    "sg:classifiers":[
        {
            "category":"Real Estate",
            "subcategory":"Real Estate Operator",
            "type":"Services"
        }
    ],
    "sg:phone":"+1 440 748 2589",
    "sg:postcode":"44044",
    "sg:province":"OH",
    "sg:tags":[
        "building",
        "nonresidential"
    ],
    "wof:name":"Osborne Properties",
    "wof:placetype":"venue"
},
  "geometry": {"coordinates":[-82.057066,41.327252],"type":"Point"}
}