{
  "type": "Feature",
  "properties": {
    "addr:full": "705 Lakeview Plaza Blvd Worthington OH 43085",
    "addr:housenumber": "705",
    "addr:postcode": "43085",
    "addr:street": "Lakeview Plaza Blvd",
    "iso:country": "US",
    "sg:address": "705 Lakeview Plaza Blvd",
    "sg:city": "Worthington",
    "sg:classifiers": [
      {
        "category": "Professional",
        "subcategory": "Business Services",
        "type": "Services"
      }
    ],
    "sg:phone": "+1 614 436 7417",
    "sg:postcode": "43085",
    "sg:province": "OH",
    "sg:tags": [
      "event"
    ],
    "sg:website": "www.kaleidoscopeinternational.com",
    "wof:name": "Kaleidoscope Enterprises Intl",
    "wof:placetype": "venue"
  },
  "geometry": {"coordinates":[-82.997304,40.112804],"type":"Point"}
}
