{
  "type": "Feature",
  "properties": {
    "iso:country":"US",
    "sg:address":"75 Public Sq",
    "sg:city":"Cleveland",
    "sg:classifiers":[
        {
            "category":"Professional",
            "subcategory":"Lawyer & Legal Services",
            "type":"Services"
        }
    ],
    "sg:phone":"+1 216 696 4600",
    "sg:postcode":"44113",
    "sg:province":"OH",
    "sg:tags":[
        "attorney"
    ],
    "wof:name":"Thomas G De Franco Atty At Law",
    "wof:placetype":"venue"
},
  "geometry": {"coordinates":[-81.694492,41.500271],"type":"Point"}
}