{
  "type": "Feature",
  "properties": {
    "addr:full": "301 Treeworth Blvd Cleveland OH 44147",
    "addr:housenumber": "301",
    "addr:postcode": "44147",
    "addr:street": "Treeworth Blvd",
    "iso:country": "US",
    "sg:address": "301 Treeworth Blvd",
    "sg:city": "Cleveland",
    "sg:classifiers": [
      {
        "category": "Building \u0026 Trades",
        "subcategory": "Construction",
        "type": "Services"
      }
    ],
    "sg:phone": "+1 440 526 5630",
    "sg:postcode": "44147",
    "sg:province": "OH",
    "sg:tags": [
      "general",
      "contractor"
    ],
    "wof:name": "First Choice Maintenance",
    "wof:placetype": "venue"
  },
  "geometry": {"coordinates":[-81.65395,41.315749],"type":"Point"}
}
