{
  "type": "Feature",
  "properties": {
    "addr:full":"6407 Kalbfleisch Rd Middletown OH 45042",
    "addr:housenumber":"6407",
    "addr:postcode":"45042",
    "addr:street":"Kalbfleisch Rd",
    "iso:country":"US",
    "sg:address":"6407 Kalbfleisch Rd",
    "sg:city":"Middletown",
    "sg:classifiers":[
        {
            "category":"Retail",
            "subcategory":"Repair Shop",
            "type":"Services"
        }
    ],
    "sg:phone":"+1 513 420 0123",
    "sg:postcode":"45042",
    "sg:province":"OH",
    "sg:tags":[
        "scooter",
        "motorcycle",
        "motor"
    ],
    "wof:name":"Caudill's Pro Cycle",
    "wof:placetype":"venue"
},
  "geometry": {"coordinates":[-84.445959,39.568565],"type":"Point"}
}