{
  "type": "Feature",
  "properties": {
    "iso:country":"US",
    "sg:address":"1431 Shoreline Way",
    "sg:city":"Loveland",
    "sg:classifiers":[
        {
            "category":"Retail",
            "subcategory":"Veterinary Services",
            "type":"Services"
        }
    ],
    "sg:phone":"+1 513 677 0137",
    "sg:postcode":"45140",
    "sg:province":"OH",
    "wof:name":"Lynch Animal Hospital",
    "wof:placetype":"venue"
},
  "geometry": {"coordinates":[-84.24601,39.242019],"type":"Point"}
}