{
  "type": "Feature",
  "properties": {
    "addr:full": "7707 Paragon Rd Dayton OH 45459",
    "addr:housenumber": "7707",
    "addr:postcode": "45459",
    "addr:street": "Paragon Rd",
    "iso:country": "US",
    "sg:address": "7707 Paragon Rd",
    "sg:city": "Dayton",
    "sg:classifiers": [
      {
        "category": "Health Services",
        "subcategory": "Health Practitioner",
        "type": "Services"
      }
    ],
    "sg:phone": "+1 937 436 1985",
    "sg:postcode": "45459",
    "sg:province": "OH",
    "sg:tags": [
      "dietitian"
    ],
    "wof:name": "Monica A Cengia",
    "wof:placetype": "venue"
  },
  "geometry": {"coordinates":[-84.181213,39.630568],"type":"Point"}
}
