{
  "type": "Feature",
  "properties": {
    "addr:full": "41 Commerce Park Dr Westerville OH 43082",
    "addr:housenumber": "41",
    "addr:postcode": "43082",
    "addr:street": "Commerce Park Dr",
    "iso:country": "US",
    "sg:address": "41 Commerce Park Dr",
    "sg:city": "Westerville",
    "sg:classifiers": [
      {
        "category": "Health Services",
        "subcategory": "Doctor",
        "type": "Services"
      }
    ],
    "sg:phone": "+1 614 797 3277",
    "sg:postcode": "43082",
    "sg:province": "OH",
    "sg:tags": [
      "physician",
      "surgeon"
    ],
    "wof:name": "Central Ohio Ear Nose \u0026 Throat",
    "wof:placetype": "venue"
  },
  "geometry": {"coordinates":[-82.925884,40.139864],"type":"Point"}
}
