{
  "type": "Feature",
  "properties": {
    "iso:country":"US",
    "sg:address":"128 Southpark Center",
    "sg:city":"Cleveland",
    "sg:classifiers":[
        {
            "category":"Shopping",
            "subcategory":"Clothing, Apparel, & Fashions",
            "type":"Retail Goods"
        }
    ],
    "sg:phone":"+1 440 846 1478",
    "sg:postcode":"44136",
    "sg:province":"OH",
    "sg:tags":[
        "lingerie"
    ],
    "wof:name":"Victoria's Secret",
    "wof:placetype":"venue"
},
  "geometry": {"coordinates":[-81.820449,41.310925],"type":"Point"}
}