{
  "type": "Feature",
  "properties": {
    "iso:country":"US",
    "sg:address":"2198 State Rte 136",
    "sg:city":"Hillsboro",
    "sg:classifiers":[
        {
            "category":"Retail",
            "subcategory":"Animal Services",
            "type":"Services"
        }
    ],
    "sg:phone":"+1 937 927 5614",
    "sg:postcode":"45133",
    "sg:province":"OH",
    "sg:tags":[
        "pet",
        "training"
    ],
    "wof:name":"Chaparral Dog Training Center",
    "wof:placetype":"venue"
},
  "geometry": {"coordinates":[-83.66193699999999,39.058854],"type":"Point"}
}