{
  "type": "Feature",
  "properties": {
    "iso:country":"US",
    "sg:address":"222 Illinois Ave",
    "sg:city":"Maumee",
    "sg:classifiers":[
        {
            "category":"Autos & Motor Vehicles",
            "subcategory":"Auto Supplies",
            "type":"Retail Goods"
        },
        {
            "category":"Retail",
            "subcategory":"Auto Repair",
            "type":"Services"
        }
    ],
    "sg:phone":"+1 419 893 7006",
    "sg:postcode":"43537",
    "sg:province":"OH",
    "sg:tags":[
        "repairing",
        "automobile",
        "accessory",
        "automotive",
        "general"
    ],
    "sg:website":"www.4wddiv.com",
    "wof:name":"4 Wheel Drive Diversified Inc",
    "wof:placetype":"venue"
},
  "geometry": {"coordinates":[-83.65758,41.566954],"type":"Point"}
}