{
  "type": "Feature",
  "properties": {
    "addr:full": "107 N Main St Payne OH 45880",
    "addr:housenumber": "107",
    "addr:postcode": "45880",
    "addr:street": "N Main St",
    "iso:country": "US",
    "sg:address": "107 N Main St",
    "sg:city": "Payne",
    "sg:classifiers": [
      {
        "category": "Farming",
        "subcategory": "Farm \u0026 Veterinary Services",
        "type": "Manufacturing \u0026 Wholesale Goods"
      }
    ],
    "sg:phone": "+1 419 263 3011",
    "sg:postcode": "45880",
    "sg:province": "OH",
    "sg:tags": [
      "management"
    ],
    "wof:name": "R K Brady Corp",
    "wof:placetype": "venue"
  },
  "geometry": {"coordinates":[-84.72663,41.080079],"type":"Point"}
}
