{
  "type": "Feature",
  "properties": {
    "iso:country":"US",
    "sg:address":"107 N Main St",
    "sg:city":"Payne",
    "sg:classifiers":[
        {
            "category":"Farming",
            "subcategory":"Farm & Veterinary Services",
            "type":"Manufacturing & Wholesale Goods"
        }
    ],
    "sg:phone":"+1 419 263 3011",
    "sg:postcode":"45880",
    "sg:province":"OH",
    "sg:tags":[
        "management"
    ],
    "wof:name":"R K Brady Corp",
    "wof:placetype":"venue"
},
  "geometry": {"coordinates":[-84.72663,41.080079],"type":"Point"}
}