{
  "type": "Feature",
  "properties": {
    "addr:full": "965 Norwich Ave NW Massillon OH 44646",
    "addr:housenumber": "965",
    "addr:postcode": "44646",
    "addr:street": "Norwich Ave Nw",
    "iso:country": "US",
    "sg:address": "965 Norwich Ave NW",
    "sg:city": "Massillon",
    "sg:classifiers": [
      {
        "category": "Real Estate",
        "subcategory": "Real Estate Operator",
        "type": "Services"
      }
    ],
    "sg:phone": "+1 330 832 7524",
    "sg:postcode": "44646",
    "sg:province": "OH",
    "sg:tags": [
      "building",
      "nonresidential"
    ],
    "wof:name": "Merlin Properties Stark County",
    "wof:placetype": "venue"
  },
  "geometry": {"coordinates":[-81.476608,40.807665],"type":"Point"}
}
