{
  "type": "Feature",
  "properties": {
    "iso:country":"US",
    "sg:address":"34521 Vine St",
    "sg:city":"Willowick",
    "sg:classifiers":[
        {
            "category":"Personal",
            "subcategory":"Beauty Salon",
            "type":"Services"
        }
    ],
    "sg:phone":"+1 440 942 8105",
    "sg:postcode":"44095",
    "sg:province":"OH",
    "wof:name":"Elaine's Beauty Salon",
    "wof:placetype":"venue"
},
  "geometry": {"coordinates":[-81.441956,41.642612],"type":"Point"}
}