{
  "type": "Feature",
  "properties": {
    "iso:country":"US",
    "sg:address":"23715 Mercantile Rd",
    "sg:city":"Cleveland",
    "sg:classifiers":[
        {
            "category":"Professional",
            "subcategory":"Art Services",
            "type":"Services"
        }
    ],
    "sg:phone":"+1 216 514 0501",
    "sg:postcode":"44122",
    "sg:province":"OH",
    "sg:tags":[
        "photographer"
    ],
    "wof:name":"Beth Segal Photography",
    "wof:placetype":"venue"
},
  "geometry": {"coordinates":[-81.513232,41.45871],"type":"Point"}
}