{
  "type": "Feature",
  "properties": {
    "iso:country":"US",
    "sg:address":"206 E Sandusky St",
    "sg:city":"Findlay",
    "sg:classifiers":[
        {
            "category":"Personal",
            "subcategory":"Barber",
            "type":"Services"
        }
    ],
    "sg:phone":"+1 419 422 3783",
    "sg:postcode":"45840",
    "sg:province":"OH",
    "wof:name":"Razor's Edge",
    "wof:placetype":"venue"
},
  "geometry": {"coordinates":[-83.646918,41.037085],"type":"Point"}
}