{
  "type": "Feature",
  "properties": {
    "addr:full":"722 Mulberry Rd SE Canton OH 44707",
    "addr:housenumber":"722",
    "addr:postcode":"44707",
    "addr:street":"Mulberry Rd Se",
    "iso:country":"US",
    "sg:address":"722 Mulberry Rd SE",
    "sg:city":"Canton",
    "sg:classifiers":[
        {
            "category":"Manufacturing",
            "subcategory":"Tools & Machinery",
            "type":"Manufacturing & Wholesale Goods"
        }
    ],
    "sg:phone":"+1 330 454 6147",
    "sg:postcode":"44707",
    "sg:province":"OH",
    "sg:tags":[
        "machine",
        "shop"
    ],
    "wof:name":"R A Griffin Co Inc",
    "wof:placetype":"venue"
},
  "geometry": {"coordinates":[-81.369727,40.794221],"type":"Point"}
}