{
  "type": "Feature",
  "properties": {
    "addr:full":"460 1st St SE Brewster OH 44613",
    "addr:housenumber":"460",
    "addr:postcode":"44613",
    "addr:street":"1St St Se",
    "iso:country":"US",
    "sg:address":"460 1st St SE",
    "sg:city":"Brewster",
    "sg:classifiers":[
        {
            "category":"Real Estate",
            "subcategory":"Real Estate Operator",
            "type":"Services"
        }
    ],
    "sg:phone":"+1 330 767 4133",
    "sg:postcode":"44613",
    "sg:province":"OH",
    "sg:tags":[
        "court",
        "mobile",
        "community",
        "operates",
        "home",
        "trailer"
    ],
    "wof:name":"Brewster Mobile Home Estates",
    "wof:placetype":"venue"
},
  "geometry": {"coordinates":[-81.59171600000001,40.712268],"type":"Point"}
}