{
  "type": "Feature",
  "properties": {
    "iso:country":"US",
    "sg:address":"30730 Bayridge Blvd",
    "sg:city":"Willowick",
    "sg:classifiers":[
        {
            "category":"Home & Garden",
            "subcategory":"Hardware",
            "type":"Retail Goods"
        }
    ],
    "sg:phone":"+1 440 944 4724",
    "sg:postcode":"44095",
    "sg:province":"OH",
    "sg:tags":[
        "tool",
        "used"
    ],
    "wof:name":"Lake Tools",
    "wof:placetype":"venue"
},
  "geometry": {"coordinates":[-81.47307000000001,41.639385],"type":"Point"}
}