{
  "type": "Feature",
  "properties": {
    "iso:country":"US",
    "sg:address":"3569 Ridge Rd",
    "sg:city":"Cleveland",
    "sg:classifiers":[
        {
            "category":"Health Services",
            "subcategory":"Doctor",
            "type":"Services"
        }
    ],
    "sg:phone":"+1 440 878 2500",
    "sg:postcode":"44102",
    "sg:province":"OH",
    "sg:tags":[
        "physician",
        "surgeon"
    ],
    "wof:name":"Nicholas W Davis MD",
    "wof:placetype":"venue"
},
  "geometry": {"coordinates":[-81.738338,41.461101],"type":"Point"}
}