{
  "type": "Feature",
  "properties": {
    "iso:country":"US",
    "sg:address":"5648 Meadowood Ln",
    "sg:city":"Westerville",
    "sg:classifiers":[
        {
            "category":"Wholesale",
            "subcategory":"Toys & Hobbies",
            "type":"Manufacturing & Wholesale Goods"
        }
    ],
    "sg:phone":"+1 614 899 1502",
    "sg:postcode":"43082",
    "sg:province":"OH",
    "wof:name":"Serv Pro Enterprises",
    "wof:placetype":"venue"
},
  "geometry": {"coordinates":[-82.934417,40.168679],"type":"Point"}
}