{
  "type": "Feature",
  "properties": {
    "addr:full":"18400 Euclid Ave Cleveland OH 44112",
    "addr:housenumber":"18400",
    "addr:postcode":"44112",
    "addr:street":"Euclid Ave",
    "iso:country":"US",
    "sg:address":"18400 Euclid Ave",
    "sg:city":"Cleveland",
    "sg:phone":"+1 216 481 1320",
    "sg:postcode":"44112",
    "sg:province":"OH",
    "wof:name":"Weber's Health Foods",
    "wof:placetype":"venue"
},
  "geometry": {"coordinates":[-81.549622,41.55735],"type":"Point"}
}