{
  "type": "Feature",
  "properties": {
    "addr:full":"109 Monroe St Monroeville OH 44847",
    "addr:housenumber":"109",
    "addr:postcode":"44847",
    "addr:street":"Monroe St",
    "iso:country":"US",
    "sg:address":"109 Monroe St",
    "sg:city":"Monroeville",
    "sg:classifiers":[
        {
            "category":"Retail",
            "subcategory":"Funeral Services",
            "type":"Services"
        }
    ],
    "sg:phone":"+1 419 465 2475",
    "sg:postcode":"44847",
    "sg:province":"OH",
    "sg:tags":[
        "director"
    ],
    "wof:name":"Jump & Pfeil Funeral Home",
    "wof:placetype":"venue"
},
  "geometry": {"coordinates":[-82.69929,41.243284],"type":"Point"}
}