{
  "type": "Feature",
  "properties": {
    "addr:full": "11443 Colerain Ave Cincinnati OH 45252",
    "addr:housenumber": "11443",
    "addr:postcode": "45252",
    "addr:street": "Colerain Ave",
    "iso:country": "US",
    "sg:address": "11443 Colerain Ave",
    "sg:city": "Cincinnati",
    "sg:classifiers": [
      {
        "category": "Farming",
        "subcategory": "Nursery",
        "type": "Manufacturing \u0026 Wholesale Goods"
      }
    ],
    "sg:phone": "+1 513 741 8455",
    "sg:postcode": "45252",
    "sg:province": "OH",
    "sg:tags": [
      "ornamental",
      "greenhouse"
    ],
    "sg:website": "www.diefenbachergreenhouses.com",
    "wof:name": "Diefenbacher Greenhouses Inc",
    "wof:placetype": "venue"
  },
  "geometry": {"coordinates":[-84.617123,39.29054],"type":"Point"}
}
