{
  "type": "Feature",
  "properties": {
    "iso:country":"US",
    "sg:address":"11443 Colerain Ave",
    "sg:city":"Cincinnati",
    "sg:classifiers":[
        {
            "category":"Farming",
            "subcategory":"Nursery",
            "type":"Manufacturing & Wholesale Goods"
        }
    ],
    "sg:phone":"+1 513 741 8455",
    "sg:postcode":"45252",
    "sg:province":"OH",
    "sg:tags":[
        "ornamental",
        "greenhouse"
    ],
    "sg:website":"www.diefenbachergreenhouses.com",
    "wof:name":"Diefenbacher Greenhouses Inc",
    "wof:placetype":"venue"
},
  "geometry": {"coordinates":[-84.61712300000001,39.29054],"type":"Point"}
}