{
  "type": "Feature",
  "properties": {
    "addr:full": "1307 W High St Bryan OH 43506",
    "addr:housenumber": "1307",
    "addr:postcode": "43506",
    "addr:street": "W High St",
    "iso:country": "US",
    "sg:address": "1307 W High St",
    "sg:city": "Bryan",
    "sg:classifiers": [
      {
        "category": "Bars \u0026 Pubs",
        "type": "Food \u0026 Drink"
      }
    ],
    "sg:phone": "+1 419 636 6817",
    "sg:postcode": "43506",
    "sg:province": "OH",
    "sg:tags": [
      "drinking"
    ],
    "wof:name": "OBryans",
    "wof:placetype": "venue"
  },
  "geometry": {"coordinates":[-84.570632,41.474454],"type":"Point"}
}
