{
  "type": "Feature",
  "properties": {
    "iso:country":"US",
    "sg:address":"1307 W High St",
    "sg:city":"Bryan",
    "sg:classifiers":[
        {
            "category":"Bars & Pubs",
            "type":"Food & Drink"
        }
    ],
    "sg:phone":"+1 419 636 6817",
    "sg:postcode":"43506",
    "sg:province":"OH",
    "sg:tags":[
        "drinking"
    ],
    "wof:name":"OBryans",
    "wof:placetype":"venue"
},
  "geometry": {"coordinates":[-84.570632,41.474454],"type":"Point"}
}