{
  "type": "Feature",
  "properties": {
    "iso:country":"US",
    "sg:address":"5194 Blazer Pkwy",
    "sg:city":"Dublin",
    "sg:classifiers":[
        {
            "category":"Health Services",
            "subcategory":"Optometrist",
            "type":"Services"
        }
    ],
    "sg:phone":"+1 614 764 8956",
    "sg:postcode":"43017",
    "sg:province":"OH",
    "wof:name":"Murphy Wright & Lex",
    "wof:placetype":"venue"
},
  "geometry": {"coordinates":[-83.128091,40.07587],"type":"Point"}
}