{
  "type": "Feature",
  "properties": {
    "iso:country":"US",
    "sg:address":"117 N Monroe St",
    "sg:city":"Fremont",
    "sg:classifiers":[
        {
            "category":"Bars & Pubs",
            "type":"Food & Drink"
        }
    ],
    "sg:phone":"+1 419 332 5519",
    "sg:postcode":"43420",
    "sg:province":"OH",
    "sg:tags":[
        "drinking"
    ],
    "wof:name":"Depot Bar",
    "wof:placetype":"venue"
},
  "geometry": {"coordinates":[-83.125051,41.347053],"type":"Point"}
}