{
  "type": "Feature",
  "properties": {
    "addr:full": "6501 Plainfield Ave Cleveland OH 44144",
    "addr:housenumber": "6501",
    "addr:postcode": "44144",
    "addr:street": "Plainfield Ave",
    "iso:country": "US",
    "sg:address": "6501 Plainfield Ave",
    "sg:city": "Cleveland",
    "sg:classifiers": [
      {
        "category": "Professional",
        "subcategory": "Lawyer \u0026 Legal Services",
        "type": "Services"
      }
    ],
    "sg:phone": "+1 216 661 3580",
    "sg:postcode": "44144",
    "sg:province": "OH",
    "sg:tags": [
      "attorney"
    ],
    "wof:name": "James S Mc Clelland",
    "wof:placetype": "venue"
  },
  "geometry": {"coordinates":[-81.734039,41.442424],"type":"Point"}
}
