{
  "type": "Feature",
  "properties": {
    "iso:country":"US",
    "sg:address":"6060 Center Hill Ave",
    "sg:city":"Cincinnati",
    "sg:classifiers":[
        {
            "category":"Building & Trades",
            "subcategory":"Construction",
            "type":"Services"
        }
    ],
    "sg:phone":"+1 513 634 7900",
    "sg:postcode":"45224",
    "sg:province":"OH",
    "wof:name":"Hunt Construction Group Inc",
    "wof:placetype":"venue"
},
  "geometry": {"coordinates":[-84.506327,39.195833],"type":"Point"}
}