{
  "type": "Feature",
  "properties": {
    "addr:full": "1 Ridgewood Ave Mount Vernon OH 43050",
    "addr:housenumber": "1",
    "addr:postcode": "43050",
    "addr:street": "Ridgewood Ave",
    "iso:country": "US",
    "sg:address": "1 Ridgewood Ave",
    "sg:city": "Mount Vernon",
    "sg:classifiers": [
      {
        "category": "Real Estate",
        "subcategory": "Real Estate Operator",
        "type": "Services"
      }
    ],
    "sg:phone": "+1 740 397 8633",
    "sg:postcode": "43050",
    "sg:province": "OH",
    "sg:tags": [
      "property",
      "lessor"
    ],
    "wof:name": "Stan Tyson",
    "wof:placetype": "venue"
  },
  "geometry": {"coordinates":[-82.495595,40.391359],"type":"Point"}
}
