{
  "type": "Feature",
  "properties": {
    "addr:full": "8502 Angola Rd Holland OH 43528",
    "addr:housenumber": "8502",
    "addr:postcode": "43528",
    "addr:street": "Angola Rd",
    "iso:country": "US",
    "sg:address": "8502 Angola Rd",
    "sg:city": "Holland",
    "sg:classifiers": [
      {
        "category": "Home \u0026 Garden",
        "subcategory": "Garden Supply",
        "type": "Retail Goods"
      }
    ],
    "sg:phone": "+1 419 392 8281",
    "sg:postcode": "43528",
    "sg:province": "OH",
    "sg:tags": [
      "fountain",
      "display"
    ],
    "wof:name": "Ponds Of Pleasure",
    "wof:placetype": "venue"
  },
  "geometry": {"coordinates":[-83.744281,41.624988],"type":"Point"}
}
