{
  "type": "Feature",
  "properties": {
    "addr:full": "5564 Wilson Mills Rd Cleveland OH 44143",
    "addr:housenumber": "5564",
    "addr:postcode": "44143",
    "addr:street": "Wilson Mills Rd",
    "iso:country": "US",
    "sg:address": "5564 Wilson Mills Rd",
    "sg:city": "Cleveland",
    "sg:classifiers": [
      {
        "category": "Health Services",
        "subcategory": "Doctor",
        "type": "Services"
      }
    ],
    "sg:phone": "+1 440 442 3900",
    "sg:postcode": "44143",
    "sg:province": "OH",
    "sg:tags": [
      "dentist"
    ],
    "wof:name": "Dieter H Myers DDS",
    "wof:placetype": "venue"
  },
  "geometry": {"coordinates":[-81.478537,41.538912],"type":"Point"}
}
