{
  "type": "Feature",
  "properties": {
    "addr:full": "172 N Broadway St New Philadelphia OH 44663",
    "addr:housenumber": "172",
    "addr:postcode": "44663",
    "addr:street": "N Broadway St",
    "iso:country": "US",
    "sg:address": "172 N Broadway St",
    "sg:city": "New Philadelphia",
    "sg:classifiers": [
      {
        "category": "Education",
        "subcategory": "School",
        "type": "Public Place"
      }
    ],
    "sg:phone": "+1 330 364 1306",
    "sg:postcode": "44663",
    "sg:province": "OH",
    "wof:name": "Educational Service Ctr",
    "wof:placetype": "venue"
  },
  "geometry": {"coordinates":[-81.445238,40.49092],"type":"Point"}
}
