{
  "type": "Feature",
  "properties": {
    "iso:country":"US",
    "sg:address":"172 N Broadway St",
    "sg:city":"New Philadelphia",
    "sg:classifiers":[
        {
            "category":"Education",
            "subcategory":"School",
            "type":"Public Place"
        }
    ],
    "sg:phone":"+1 330 364 1306",
    "sg:postcode":"44663",
    "sg:province":"OH",
    "wof:name":"Educational Service Ctr",
    "wof:placetype":"venue"
},
  "geometry": {"coordinates":[-81.445238,40.49092],"type":"Point"}
}