{
  "type": "Feature",
  "properties": {
    "addr:full": "1435 Main St Cincinnati OH 45202",
    "addr:housenumber": "1435",
    "addr:postcode": "45202",
    "addr:street": "Main St",
    "iso:country": "US",
    "sg:address": "1435 Main St",
    "sg:city": "Cincinnati",
    "sg:classifiers": [
      {
        "category": "Personal",
        "type": "Services"
      }
    ],
    "sg:phone": "+1 513 621 1646",
    "sg:postcode": "45202",
    "sg:province": "OH",
    "sg:tags": [
      "program",
      "physical",
      "exercise",
      "fitness"
    ],
    "wof:name": "Strategic Fitness Training",
    "wof:placetype": "venue"
  },
  "geometry": {"coordinates":[-84.512577,39.112609],"type":"Point"}
}
