{
  "type": "Feature",
  "properties": {
    "iso:country":"US",
    "sg:address":"330 Howard St",
    "sg:city":"Bridgeport",
    "sg:classifiers":[
        {
            "category":"Building & Trades",
            "subcategory":"Construction",
            "type":"Services"
        }
    ],
    "sg:phone":"+1 740 633 1987",
    "sg:postcode":"43912",
    "sg:province":"OH",
    "sg:tags":[
        "nonresidential"
    ],
    "wof:name":"Kenco Construction",
    "wof:placetype":"venue"
},
  "geometry": {"coordinates":[-80.74372700000001,40.070014],"type":"Point"}
}