{
  "type": "Feature",
  "properties": {
    "addr:full": "330 Howard St Bridgeport OH 43912",
    "addr:housenumber": "330",
    "addr:postcode": "43912",
    "addr:street": "Howard St",
    "iso:country": "US",
    "sg:address": "330 Howard St",
    "sg:city": "Bridgeport",
    "sg:classifiers": [
      {
        "category": "Building \u0026 Trades",
        "subcategory": "Construction",
        "type": "Services"
      }
    ],
    "sg:phone": "+1 740 633 1987",
    "sg:postcode": "43912",
    "sg:province": "OH",
    "sg:tags": [
      "nonresidential"
    ],
    "wof:name": "Kenco Construction",
    "wof:placetype": "venue"
  },
  "geometry": {"coordinates":[-80.743727,40.070014],"type":"Point"}
}
