{
  "type": "Feature",
  "properties": {
    "iso:country":"US",
    "sg:address":"8 N Court St",
    "sg:city":"Athens",
    "sg:classifiers":[
        {
            "category":"Ice Cream",
            "type":"Food & Drink"
        }
    ],
    "sg:menulink":"http://www.allmenus.com/oh/athens/184232-cold-stone-creamery/menu/",
    "sg:phone":"+1 740 592 9900",
    "sg:postcode":"45701",
    "sg:province":"OH",
    "sg:tags":[
        "smoothy",
        "juice",
        "american"
    ],
    "wof:name":"Cold Stone Creamery",
    "wof:placetype":"venue"
},
  "geometry": {"coordinates":[-82.101077,39.329339],"type":"Point"}
}