{
  "type": "Feature",
  "properties": {
    "iso:country":"US",
    "sg:address":"2074 Iuka Ave",
    "sg:city":"Columbus",
    "sg:classifiers":[
        {
            "category":"Freight",
            "type":"Transportation"
        }
    ],
    "sg:phone":"+1 614 299 5546",
    "sg:postcode":"43201",
    "sg:province":"OH",
    "sg:tags":[
        "hauling"
    ],
    "wof:name":"Pinewood Transport Ltd",
    "wof:placetype":"venue"
},
  "geometry": {"coordinates":[-82.998263,40.006679],"type":"Point"}
}