{
  "type": "Feature",
  "properties": {
    "addr:full":"3553 Tuttle Ave Cleveland OH 44111",
    "addr:housenumber":"3553",
    "addr:postcode":"44111",
    "addr:street":"Tuttle Ave",
    "iso:country":"US",
    "sg:address":"3553 Tuttle Ave",
    "sg:city":"Cleveland",
    "sg:classifiers":[
        {
            "category":"Building & Trades",
            "subcategory":"Construction",
            "type":"Services"
        }
    ],
    "sg:phone":"+1 216 941 0984",
    "sg:postcode":"44111",
    "sg:province":"OH",
    "sg:tags":[
        "house"
    ],
    "wof:name":"Brewka Contracting",
    "wof:placetype":"venue"
},
  "geometry": {"coordinates":[-81.807113,41.456954],"type":"Point"}
}