{
  "type": "Feature",
  "properties": {
    "addr:full": "3047 State Rte 131 Batavia OH 45103",
    "addr:housenumber": "3047",
    "addr:postcode": "45103",
    "addr:street": "State Rte 131",
    "iso:country": "US",
    "sg:address": "3047 State Rte 131",
    "sg:city": "Batavia",
    "sg:classifiers": [
      {
        "category": "Building \u0026 Trades",
        "subcategory": "Construction",
        "type": "Services"
      }
    ],
    "sg:phone": "+1 513 625 4450",
    "sg:postcode": "45103",
    "sg:province": "OH",
    "sg:tags": [
      "house"
    ],
    "wof:name": "Luthy Loren/Quality Build",
    "wof:placetype": "venue"
  },
  "geometry": {"coordinates":[-84.058403,39.180748],"type":"Point"}
}
