{
  "type": "Feature",
  "properties": {
    "addr:full":"2240 Stumbo Rd S Mansfield OH 44906",
    "addr:housenumber":"2240",
    "addr:postcode":"44906",
    "addr:street":"Stumbo Rd",
    "iso:country":"US",
    "sg:address":"2240 Stumbo Rd S",
    "sg:city":"Mansfield",
    "sg:classifiers":[
        {
            "category":"Education",
            "subcategory":"Special Training",
            "type":"Public Place"
        }
    ],
    "sg:phone":"+1 419 529 5550",
    "sg:postcode":"44906",
    "sg:province":"OH",
    "sg:tags":[
        "instruction",
        "driving"
    ],
    "wof:name":"Richland Driving Academy",
    "wof:placetype":"venue"
},
  "geometry": {"coordinates":[-82.594099,40.765577],"type":"Point"}
}