{
  "type": "Feature",
  "properties": {
    "iso:country":"US",
    "sg:address":"2980 S Charleston Rd",
    "sg:city":"South Charleston",
    "sg:phone":"+1 937 462 8569",
    "sg:postcode":"45368",
    "sg:province":"OH",
    "sg:tags":[
        "farm",
        "corn"
    ],
    "wof:name":"Kevin Snyder",
    "wof:placetype":"venue"
},
  "geometry": {"coordinates":[-83.679237,39.753464],"type":"Point"}
}