{
  "type": "Feature",
  "properties": {
    "addr:full": "107 Oakwood Dr Columbus Grove OH 45830",
    "addr:housenumber": "107",
    "addr:postcode": "45830",
    "addr:street": "Oakwood Dr Columbus Grove",
    "iso:country": "US",
    "sg:address": "107 Oakwood Dr",
    "sg:city": "Columbus Grove",
    "sg:classifiers": [
      {
        "category": "Home \u0026 Garden",
        "subcategory": "Household Appliances",
        "type": "Retail Goods"
      }
    ],
    "sg:phone": "+1 419 659 2969",
    "sg:postcode": "45830",
    "sg:province": "OH",
    "wof:name": "Daniel L Maag Appliance Svc",
    "wof:placetype": "venue"
  },
  "geometry": {"coordinates":[-84.06094,40.920208],"type":"Point"}
}
