{
  "type": "Feature",
  "properties": {
    "iso:country":"US",
    "sg:address":"4761 State Rte 152",
    "sg:city":"Richmond",
    "sg:classifiers":[
        {
            "category":"Farming",
            "subcategory":"Livestock Farm",
            "type":"Manufacturing & Wholesale Goods"
        }
    ],
    "sg:phone":"+1 740 765 4955",
    "sg:postcode":"43944",
    "sg:province":"OH",
    "sg:tags":[
        "beef",
        "corn",
        "crop",
        "field",
        "cattle",
        "feedlot"
    ],
    "wof:name":"Randolph Farms",
    "wof:placetype":"venue"
},
  "geometry": {"coordinates":[-80.78036,40.387369],"type":"Point"}
}