{
  "type": "Feature",
  "properties": {
    "iso:country":"US",
    "sg:address":"5819 Cheviot Rd",
    "sg:city":"Cincinnati",
    "sg:classifiers":[
        {
            "category":"Health Services",
            "subcategory":"Doctor",
            "type":"Services"
        }
    ],
    "sg:phone":"+1 513 741 8200",
    "sg:postcode":"45247",
    "sg:province":"OH",
    "sg:tags":[
        "medical",
        "imaging"
    ],
    "wof:name":"Westside Medical Imaging",
    "wof:placetype":"venue"
},
  "geometry": {"coordinates":[-84.600949,39.199661],"type":"Point"}
}