{
  "type": "Feature",
  "properties": {
    "iso:country":"US",
    "sg:address":"4600 Mcauley Pl Ste 200",
    "sg:city":"Cincinnati",
    "sg:classifiers":[
        {
            "category":"Professional",
            "subcategory":"Advertising",
            "type":"Services"
        }
    ],
    "sg:phone":"+1 513 307 3566",
    "sg:postcode":"45242",
    "sg:province":"OH",
    "sg:tags":[
        "distributing",
        "sample",
        "service-circular"
    ],
    "sg:website":"http://www.ibm.com",
    "wof:name":"Ibm",
    "wof:placetype":"venue"
},
  "geometry": {"coordinates":[-84.38050800000001,39.245831],"type":"Point"}
}