{
  "type": "Feature",
  "properties": {
    "iso:country":"US",
    "sg:address":"6038 Co Rd 1",
    "sg:city":"Kansas",
    "sg:classifiers":[
        {
            "category":"Professional",
            "subcategory":"Business Services",
            "type":"Services"
        },
        {
            "category":"Manufacturing",
            "subcategory":"Printing",
            "type":"Manufacturing & Wholesale Goods"
        }
    ],
    "sg:phone":"+1 419 457 7635",
    "sg:postcode":"44841",
    "sg:province":"OH",
    "sg:tags":[
        "personal",
        "commercial",
        "embroidery"
    ],
    "wof:name":"Gresuzy's Ink Spot",
    "wof:placetype":"venue"
},
  "geometry": {"coordinates":[-83.293313,41.253738],"type":"Point"}
}