{
  "type": "Feature",
  "properties": {
    "iso:country":"US",
    "sg:address":"20600 Chagrin Blvd",
    "sg:city":"Cleveland",
    "sg:classifiers":[
        {
            "category":"Manufacturing",
            "subcategory":"Electronics",
            "type":"Manufacturing & Wholesale Goods"
        }
    ],
    "sg:phone":"+1 216 921 3500",
    "sg:postcode":"44122",
    "sg:province":"OH",
    "sg:tags":[
        "import",
        "product",
        "sourcing"
    ],
    "wof:name":"Smith International Enterprise",
    "wof:placetype":"venue"
},
  "geometry": {"coordinates":[-81.534119,41.46448],"type":"Point"}
}