{
  "type": "Feature",
  "properties": {
    "addr:full": "200 S Wall St Columbus OH 43215",
    "addr:housenumber": "200",
    "addr:postcode": "43215",
    "addr:street": "S Wall St",
    "iso:country": "US",
    "sg:address": "200 S Wall St",
    "sg:city": "Columbus",
    "sg:classifiers": [
      {
        "category": "Recreation",
        "type": "Entertainment"
      }
    ],
    "sg:phone": "+1 614 221 0700",
    "sg:postcode": "43215",
    "sg:province": "OH",
    "sg:tags": [
      "martial",
      "arts",
      "instruction"
    ],
    "wof:name": "Central Ohio Martial Arts Inc",
    "wof:placetype": "venue"
  },
  "geometry": {"coordinates":[-83.000555,39.957432],"type":"Point"}
}
