{
  "type": "Feature",
  "properties": {
    "addr:full":"4700 Rean Meadow Dr Dayton OH 45440",
    "addr:postcode":"4700;45440",
    "addr:street":"Rean Meadow Dr",
    "iso:country":"US",
    "sg:address":"4700 Rean Meadow Dr",
    "sg:city":"Dayton",
    "sg:classifiers":[
        {
            "category":"Retail",
            "subcategory":"Repair Shop",
            "type":"Services"
        }
    ],
    "sg:phone":"+1 937 434 4543",
    "sg:postcode":"45440",
    "sg:province":"OH",
    "sg:tags":[
        "good"
    ],
    "wof:name":"Day Foam Company",
    "wof:placetype":"venue"
},
  "geometry": {"coordinates":[-84.117965,39.673507],"type":"Point"}
}