{
  "type": "Feature",
  "properties": {
    "iso:country":"US",
    "sg:address":"26086 Euclid Ave",
    "sg:city":"Euclid",
    "sg:classifiers":[
        {
            "category":"Autos & Motor Vehicles",
            "subcategory":"Auto Supplies",
            "type":"Retail Goods"
        },
        {
            "category":"Retail",
            "subcategory":"Auto Repair",
            "type":"Services"
        }
    ],
    "sg:phone":"+1 216 289 8833",
    "sg:postcode":"44132",
    "sg:province":"OH",
    "sg:tags":[
        "lube",
        "oil",
        "tire"
    ],
    "sg:website":"http://www.firestonecompleteautocare.com/?s_kwcid=IYP_NTL",
    "wof:name":"Firestone Complete Auto Care Store",
    "wof:placetype":"venue"
},
  "geometry": {"coordinates":[-81.500496,41.588855],"type":"Point"}
}