{
  "type": "Feature",
  "properties": {
    "iso:country":"US",
    "sg:address":"473 Old State Rte 74",
    "sg:city":"Cincinnati",
    "sg:classifiers":[
        {
            "category":"Health Services",
            "subcategory":"Doctor",
            "type":"Services"
        }
    ],
    "sg:phone":"+1 513 688 1326",
    "sg:postcode":"45244",
    "sg:province":"OH",
    "sg:tags":[
        "physician",
        "surgeon"
    ],
    "wof:name":"General & Vascular Surgical",
    "wof:placetype":"venue"
},
  "geometry": {"coordinates":[-84.304283,39.107741],"type":"Point"}
}