{
  "type": "Feature",
  "properties": {
    "addr:full": "3510 Snouffer Rd Columbus OH 43235",
    "addr:housenumber": "3510",
    "addr:postcode": "43235",
    "addr:street": "Snouffer Rd",
    "iso:country": "US",
    "sg:address": "3510 Snouffer Rd",
    "sg:city": "Columbus",
    "sg:classifiers": [
      {
        "category": "Insurance",
        "subcategory": "Insurance Agent",
        "type": "Services"
      }
    ],
    "sg:phone": "+1 614 799 2525",
    "sg:postcode": "43235",
    "sg:province": "OH",
    "wof:name": "American National Insurance Co",
    "wof:placetype": "venue"
  },
  "geometry": {"coordinates":[-83.08234,40.104371],"type":"Point"}
}
