{
  "type": "Feature",
  "properties": {
    "addr:full": "20883 Peoria Loop Rd Raymond OH 43067",
    "addr:housenumber": "20883",
    "addr:postcode": "43067",
    "addr:street": "Peoria Loop Rd",
    "iso:country": "US",
    "sg:address": "20883 Peoria Loop Rd",
    "sg:city": "Raymond",
    "sg:classifiers": [
      {
        "category": "Freight",
        "type": "Transportation"
      }
    ],
    "sg:phone": "+1 937 246 2031",
    "sg:postcode": "43067",
    "sg:province": "OH",
    "sg:tags": [
      "local",
      "trucking"
    ],
    "wof:name": "Tillman Trucking Inc",
    "wof:placetype": "venue"
  },
  "geometry": {"coordinates":[-83.449296,40.311615],"type":"Point"}
}
