{
  "type": "Feature",
  "properties": {
    "addr:full": "23679 Angela Dr Cleveland OH 44128",
    "addr:housenumber": "23679",
    "addr:postcode": "44128",
    "addr:street": "Angela Dr",
    "iso:country": "US",
    "sg:address": "23679 Angela Dr",
    "sg:city": "Cleveland",
    "sg:classifiers": [
      {
        "category": "Place Of Worship",
        "type": "Public Place"
      },
      {
        "category": "Organizations",
        "subcategory": "Religious Organization",
        "type": "Services"
      }
    ],
    "sg:phone": "+1 216 662 1122",
    "sg:postcode": "44128",
    "sg:province": "OH",
    "sg:tags": [
      "clergy",
      "church"
    ],
    "wof:name": "Emmett Harrison Rev",
    "wof:placetype": "venue"
  },
  "geometry": {"coordinates":[-81.51254,41.432892],"type":"Point"}
}
