{
  "type": "Feature",
  "properties": {
    "addr:full": "6888 Center St Mentor OH 44060",
    "addr:housenumber": "6888",
    "addr:postcode": "44060",
    "addr:street": "Center St",
    "iso:country": "US",
    "sg:address": "6888 Center St",
    "sg:city": "Mentor",
    "sg:classifiers": [
      {
        "category": "Restaurant",
        "type": "Food \u0026 Drink"
      }
    ],
    "sg:phone": "+1 440 255 8810",
    "sg:postcode": "44060",
    "sg:province": "OH",
    "sg:tags": [
      "eating"
    ],
    "wof:name": "Best Friends Restaurant Inc",
    "wof:placetype": "venue"
  },
  "geometry": {"coordinates":[-81.339401,41.6852],"type":"Point"}
}
