{
  "type": "Feature",
  "properties": {
    "addr:full": "222 W Center St Marion OH 43302",
    "addr:housenumber": "222",
    "addr:postcode": "43302",
    "addr:street": "W Center St",
    "iso:country": "US",
    "sg:address": "222 W Center St",
    "sg:city": "Marion",
    "sg:classifiers": [
      {
        "category": "Recreation",
        "type": "Entertainment"
      }
    ],
    "sg:phone": "+1 740 223 4160",
    "sg:postcode": "43302",
    "sg:province": "OH",
    "sg:tags": [
      "parks"
    ],
    "wof:name": "Marion County Park District",
    "wof:placetype": "venue"
  },
  "geometry": {"coordinates":[-83.132094,40.588522],"type":"Point"}
}
