{
  "type": "Feature",
  "properties": {
    "addr:full": "6161 Busch Blvd Columbus OH 43229",
    "addr:housenumber": "6161",
    "addr:postcode": "43229",
    "addr:street": "Busch Blvd",
    "iso:country": "US",
    "sg:address": "6161 Busch Blvd",
    "sg:city": "Columbus",
    "sg:classifiers": [
      {
        "category": "Building \u0026 Trades",
        "subcategory": "Construction",
        "type": "Services"
      }
    ],
    "sg:phone": "+1 614 985 0319",
    "sg:postcode": "43229",
    "sg:province": "OH",
    "sg:tags": [
      "demolition",
      "contractor"
    ],
    "wof:name": "Construction Labor Demolition",
    "wof:placetype": "venue"
  },
  "geometry": {"coordinates":[-82.992685,40.090008],"type":"Point"}
}
