{
  "type": "Feature",
  "properties": {
    "addr:full": "1233 NE Catawba Rd Port Clinton OH 43452",
    "addr:housenumber": "1233",
    "addr:postcode": "43452",
    "addr:street": "Ne Catawba Rd",
    "iso:country": "US",
    "sg:address": "1233 NE Catawba Rd",
    "sg:city": "Port Clinton",
    "sg:classifiers": [
      {
        "category": "Building \u0026 Trades",
        "subcategory": "Construction",
        "type": "Services"
      }
    ],
    "sg:phone": "+1 419 797 2837",
    "sg:postcode": "43452",
    "sg:province": "OH",
    "sg:tags": [
      "painter"
    ],
    "wof:name": "Major League Paint \u0026 Papering",
    "wof:placetype": "venue"
  },
  "geometry": {"coordinates":[-82.850124,41.54059],"type":"Point"}
}
