{
  "type": "Feature",
  "properties": {
    "iso:country":"US",
    "sg:address":"1233 NE Catawba Rd",
    "sg:city":"Port Clinton",
    "sg:classifiers":[
        {
            "category":"Building & Trades",
            "subcategory":"Construction",
            "type":"Services"
        }
    ],
    "sg:phone":"+1 419 797 2837",
    "sg:postcode":"43452",
    "sg:province":"OH",
    "sg:tags":[
        "painter"
    ],
    "wof:name":"Major League Paint & Papering",
    "wof:placetype":"venue"
},
  "geometry": {"coordinates":[-82.85012399999999,41.54059],"type":"Point"}
}