{
  "type": "Feature",
  "properties": {
    "addr:full": "475 E 200th St Cleveland OH 44119",
    "addr:housenumber": "475",
    "addr:postcode": "44119",
    "addr:street": "E 200Th St",
    "iso:country": "US",
    "sg:address": "475 E 200th St",
    "sg:city": "Cleveland",
    "sg:classifiers": [
      {
        "category": "Shopping",
        "subcategory": "Gifts \u0026 Souvenirs",
        "type": "Retail Goods"
      }
    ],
    "sg:phone": "+1 216 383 8845",
    "sg:postcode": "44119",
    "sg:province": "OH",
    "wof:name": "Grandmagibbsangelbibscom",
    "wof:placetype": "venue"
  },
  "geometry": {"coordinates":[-81.540158,41.593129],"type":"Point"}
}
