{
  "type": "Feature",
  "properties": {
    "iso:country":"US",
    "sg:address":"475 E 200th St",
    "sg:city":"Cleveland",
    "sg:classifiers":[
        {
            "category":"Shopping",
            "subcategory":"Gifts & Souvenirs",
            "type":"Retail Goods"
        }
    ],
    "sg:phone":"+1 216 383 8845",
    "sg:postcode":"44119",
    "sg:province":"OH",
    "wof:name":"Grandmagibbsangelbibscom",
    "wof:placetype":"venue"
},
  "geometry": {"coordinates":[-81.540158,41.593129],"type":"Point"}
}