{
  "type": "Feature",
  "properties": {
    "addr:full": "7164 Beechmont Ave Cincinnati OH 45230",
    "addr:housenumber": "7164",
    "addr:postcode": "45230",
    "addr:street": "Beechmont Ave",
    "iso:country": "US",
    "sg:address": "7164 Beechmont Ave",
    "sg:city": "Cincinnati",
    "sg:classifiers": [
      {
        "category": "Organizations",
        "subcategory": "Religious Organization",
        "type": "Services"
      }
    ],
    "sg:phone": "+1 513 232 1160",
    "sg:postcode": "45230",
    "sg:province": "OH",
    "sg:tags": [
      "church"
    ],
    "sg:website": "www.riversidechurchonline.org",
    "wof:name": "Riverside Church",
    "wof:placetype": "venue"
  },
  "geometry": {"coordinates":[-84.363127,39.074598],"type":"Point"}
}
