{
  "type": "Feature",
  "properties": {
    "iso:country":"US",
    "sg:address":"1197 E 305th St",
    "sg:city":"Wickliffe",
    "sg:classifiers":[
        {
            "category":"Professional",
            "subcategory":"Employment Agencies",
            "type":"Services"
        }
    ],
    "sg:phone":"+1 440 585 5115",
    "sg:postcode":"44092",
    "sg:province":"OH",
    "wof:name":"505 Human Resources Inc",
    "wof:placetype":"venue"
},
  "geometry": {"coordinates":[-81.458393,41.622351],"type":"Point"}
}