{
  "type": "Feature",
  "properties": {
    "iso:country":"US",
    "sg:address":"1180 Nilles Rd",
    "sg:city":"Fairfield",
    "sg:classifiers":[
        {
            "category":"Health Services",
            "subcategory":"Medical Lab",
            "type":"Services"
        }
    ],
    "sg:phone":"+1 513 939 2888",
    "sg:postcode":"45014",
    "sg:province":"OH",
    "sg:tags":[
        "laboratory"
    ],
    "wof:name":"Compunet Labs",
    "wof:placetype":"venue"
},
  "geometry": {"coordinates":[-84.541838,39.336818],"type":"Point"}
}