{
  "type": "Feature",
  "properties": {
    "addr:full":"7383 Lauren J Dr Mentor OH 44060",
    "addr:housenumber":"7383",
    "addr:postcode":"44060",
    "addr:street":"Lauren J Dr",
    "iso:country":"US",
    "sg:address":"7383 Lauren J Dr",
    "sg:city":"Mentor",
    "sg:classifiers":[
        {
            "category":"Professional",
            "type":"Services"
        },
        {
            "category":"Shopping",
            "subcategory":"Shoes",
            "type":"Retail Goods"
        }
    ],
    "sg:phone":"+1 440 255 5373",
    "sg:postcode":"44060",
    "sg:province":"OH",
    "sg:tags":[
        "establishment"
    ],
    "wof:name":"A R Sacco Corp",
    "wof:placetype":"venue"
},
  "geometry": {"coordinates":[-81.347982,41.66592],"type":"Point"}
}