{
  "type": "Feature",
  "properties": {
    "addr:full": "4106 Pearl Rd Cleveland OH 44109",
    "addr:housenumber": "4106",
    "addr:postcode": "44109",
    "addr:street": "Pearl Rd",
    "iso:country": "US",
    "sg:address": "4106 Pearl Rd",
    "sg:city": "Cleveland",
    "sg:classifiers": [
      {
        "category": "Retail",
        "subcategory": "Auto Repair",
        "type": "Services"
      }
    ],
    "sg:phone": "+1 216 741 4603",
    "sg:postcode": "44109",
    "sg:province": "OH",
    "sg:tags": [
      "repairing",
      "automobile"
    ],
    "wof:name": "Trinity Auto Svc Ctr",
    "wof:placetype": "venue"
  },
  "geometry": {"coordinates":[-81.703642,41.443848],"type":"Point"}
}
