{
  "type": "Feature",
  "properties": {
    "iso:country":"US",
    "sg:address":"30901 Lake Shore Blvd",
    "sg:city":"Willowick",
    "sg:classifiers":[
        {
            "category":"Real Estate",
            "subcategory":"Real Estate Operator",
            "type":"Services"
        }
    ],
    "sg:phone":"+1 440 585 5093",
    "sg:postcode":"44095",
    "sg:province":"OH",
    "sg:tags":[
        "apartment"
    ],
    "sg:website":"www.shoregate.com",
    "wof:name":"Shoregate Towers Apartments",
    "wof:placetype":"venue"
},
  "geometry": {"coordinates":[-81.472983,41.640408],"type":"Point"}
}