{
  "type": "Feature",
  "properties": {
    "iso:country":"US",
    "sg:address":"9978 State Rte 49",
    "sg:city":"Rockford",
    "sg:classifiers":[
        {
            "category":"Organizations",
            "subcategory":"Religious Organization",
            "type":"Services"
        }
    ],
    "sg:phone":"+1 419 942 1850",
    "sg:postcode":"45882",
    "sg:province":"OH",
    "sg:tags":[
        "church"
    ],
    "wof:name":"Chattanooga Methodist Church",
    "wof:placetype":"venue"
},
  "geometry": {"coordinates":[-84.784955,40.639735],"type":"Point"}
}