{
  "type": "Feature",
  "properties": {
    "addr:full": "307 W Main St Kent OH 44240",
    "addr:housenumber": "307",
    "addr:postcode": "44240",
    "addr:street": "W Main St",
    "iso:country": "US",
    "sg:address": "307 W Main St",
    "sg:city": "Kent",
    "sg:classifiers": [
      {
        "category": "Health Services",
        "subcategory": "Doctor",
        "type": "Services"
      }
    ],
    "sg:phone": "+1 330 650 2299",
    "sg:postcode": "44240",
    "sg:province": "OH",
    "sg:tags": [
      "medical"
    ],
    "wof:name": "Robert P Spittler MD",
    "wof:placetype": "venue"
  },
  "geometry": {"coordinates":[-81.36083,41.153844],"type":"Point"}
}
