{
  "type": "Feature",
  "properties": {
    "addr:full": "2227 N Verity Pkwy Middletown OH 45042",
    "addr:housenumber": "2227",
    "addr:postcode": "45042",
    "addr:street": "N Verity Pkwy",
    "iso:country": "US",
    "sg:address": "2227 N Verity Pkwy",
    "sg:city": "Middletown",
    "sg:classifiers": [
      {
        "category": "Restaurant",
        "type": "Food \u0026 Drink"
      }
    ],
    "sg:phone": "+1 513 422 1112",
    "sg:postcode": "45042",
    "sg:province": "OH",
    "sg:tags": [
      "eating"
    ],
    "wof:name": "Subway",
    "wof:placetype": "venue"
  },
  "geometry": {"coordinates":[-84.38797,39.526112],"type":"Point"}
}
