{
  "type": "Feature",
  "properties": {
    "iso:country":"US",
    "sg:address":"369 S Monroe St",
    "sg:city":"Tiffin",
    "sg:classifiers":[
        {
            "category":"Building & Trades",
            "subcategory":"Construction",
            "type":"Services"
        }
    ],
    "sg:phone":"+1 419 447 7963",
    "sg:postcode":"44883",
    "sg:province":"OH",
    "sg:tags":[
        "house"
    ],
    "wof:name":"Reinhart Home Improvement",
    "wof:placetype":"venue"
},
  "geometry": {"coordinates":[-83.176906,41.106439],"type":"Point"}
}