{
  "type": "Feature",
  "properties": {
    "addr:full":"703 S 7th St Greenfield OH 45123",
    "addr:housenumber":"703",
    "addr:postcode":"45123",
    "addr:street":"S 7Th St",
    "iso:country":"US",
    "sg:address":"703 S 7th St",
    "sg:city":"Greenfield",
    "sg:classifiers":[
        {
            "category":"Food & Beverages",
            "subcategory":"Groceries & Convenience Stores",
            "type":"Retail Goods"
        }
    ],
    "sg:phone":"+1 937 981 0154",
    "sg:postcode":"45123",
    "sg:province":"OH",
    "sg:tags":[
        "grocer"
    ],
    "wof:name":"Charlie's Market",
    "wof:placetype":"venue"
},
  "geometry": {"coordinates":[-83.390084,39.344712],"type":"Point"}
}