{
  "type": "Feature",
  "properties": {
    "addr:full":"350 E Main St New Lebanon OH 45345",
    "addr:housenumber":"350",
    "addr:postcode":"45345",
    "addr:street":"E Main St",
    "iso:country":"US",
    "sg:address":"350 E Main St",
    "sg:city":"New Lebanon",
    "sg:classifiers":[
        {
            "category":"Restaurant",
            "type":"Food & Drink"
        }
    ],
    "sg:phone":"+1 937 687 2224",
    "sg:postcode":"45345",
    "sg:province":"OH",
    "wof:name":"Mc Donald's",
    "wof:placetype":"venue"
},
  "geometry": {"coordinates":[-84.379621,39.745609],"type":"Point"}
}