{
  "type": "Feature",
  "properties": {
    "iso:country":"US",
    "sg:address":"451 W Market St",
    "sg:city":"Akron",
    "sg:classifiers":[
        {
            "category":"Organizations",
            "subcategory":"Religious Organization",
            "type":"Services"
        }
    ],
    "sg:phone":"+1 330 375 1366",
    "sg:postcode":"44303",
    "sg:province":"OH",
    "sg:tags":[
        "church"
    ],
    "wof:name":"Remnant Of Faith Assembly",
    "wof:placetype":"venue"
},
  "geometry": {"coordinates":[-81.530478,41.091111],"type":"Point"}
}