{
  "type": "Feature",
  "properties": {
    "addr:full": "825 W Maple St Hartville OH 44632",
    "addr:housenumber": "825",
    "addr:postcode": "44632",
    "addr:street": "W Maple St",
    "iso:country": "US",
    "sg:address": "825 W Maple St",
    "sg:city": "Hartville",
    "sg:classifiers": [
      {
        "category": "Retail",
        "subcategory": "Auto Repair",
        "type": "Services"
      }
    ],
    "sg:phone": "+1 330 877 3181",
    "sg:postcode": "44632",
    "sg:province": "OH",
    "sg:tags": [
      "automobile",
      "lubrication"
    ],
    "wof:name": "Fast Lube",
    "wof:placetype": "venue"
  },
  "geometry": {"coordinates":[-81.346798,40.967987],"type":"Point"}
}
