{
  "type": "Feature",
  "properties": {
    "addr:full": "900 Clover Ln Lebanon OH 45036",
    "addr:housenumber": "900",
    "addr:postcode": "45036",
    "addr:street": "Clover Ln",
    "iso:country": "US",
    "sg:address": "900 Clover Ln",
    "sg:city": "Lebanon",
    "sg:classifiers": [
      {
        "category": "Restaurant",
        "type": "Food \u0026 Drink"
      }
    ],
    "sg:phone": "+1 513 932 4400",
    "sg:postcode": "45036",
    "sg:province": "OH",
    "wof:name": "Best Cafe",
    "wof:placetype": "venue"
  },
  "geometry": {"coordinates":[-84.219596,39.419987],"type":"Point"}
}
