{
  "type": "Feature",
  "properties": {
    "iso:country":"US",
    "sg:address":"900 Clover Ln",
    "sg:city":"Lebanon",
    "sg:classifiers":[
        {
            "category":"Restaurant",
            "type":"Food & Drink"
        }
    ],
    "sg:phone":"+1 513 932 4400",
    "sg:postcode":"45036",
    "sg:province":"OH",
    "wof:name":"Best Cafe",
    "wof:placetype":"venue"
},
  "geometry": {"coordinates":[-84.219596,39.419987],"type":"Point"}
}