{
  "type": "Feature",
  "properties": {
    "addr:full":"4940 Scioto Darby Rd Hilliard OH 43026",
    "addr:housenumber":"4940",
    "addr:postcode":"43026",
    "addr:street":"Scioto Darby Rd",
    "iso:country":"US",
    "sg:address":"4940 Scioto Darby Rd",
    "sg:city":"Hilliard",
    "sg:classifiers":[
        {
            "category":"Social Services",
            "subcategory":"Child Care",
            "type":"Services"
        }
    ],
    "sg:phone":"+1 614 777 4320",
    "sg:postcode":"43026",
    "sg:province":"OH",
    "sg:website":"www.citykids.columbus.oh.us",
    "wof:name":"City Kids Daycare",
    "wof:placetype":"venue"
},
  "geometry": {"coordinates":[-83.14219900000001,40.020126],"type":"Point"}
}