{
  "type": "Feature",
  "properties": {
    "addr:full": "60 S Cypress Ave Columbus OH 43222",
    "addr:housenumber": "60",
    "addr:postcode": "43222",
    "addr:street": "S Cypress Ave",
    "iso:country": "US",
    "sg:address": "60 S Cypress Ave",
    "sg:city": "Columbus",
    "sg:classifiers": [
      {
        "category": "Organizations",
        "subcategory": "Religious Organization",
        "type": "Services"
      }
    ],
    "sg:phone": "+1 614 461 4663",
    "sg:postcode": "43222",
    "sg:province": "OH",
    "sg:tags": [
      "church"
    ],
    "sg:website": "www.smemorial.org",
    "wof:name": "Stewart Meml Christian Mthdst",
    "wof:placetype": "venue"
  },
  "geometry": {"coordinates":[-83.028937,39.957502],"type":"Point"}
}
