{
  "type": "Feature",
  "properties": {
    "addr:full":"13805 Allentown Rd Spencerville OH 45887",
    "addr:housenumber":"13805",
    "addr:postcode":"45887",
    "addr:street":"Allentown Rd",
    "iso:country":"US",
    "sg:address":"13805 Allentown Rd",
    "sg:city":"Spencerville",
    "sg:phone":"+1 419 647 4558",
    "sg:postcode":"45887",
    "sg:province":"OH",
    "sg:tags":[
        "farm",
        "corn",
        "soybean"
    ],
    "wof:name":"Hubert Warnecke Farms",
    "wof:placetype":"venue"
},
  "geometry": {"coordinates":[-84.37477800000001,40.735793],"type":"Point"}
}