{
  "type": "Feature",
  "properties": {
    "addr:full": "3416 Shaw Ave Cincinnati OH 45208",
    "addr:housenumber": "3416",
    "addr:postcode": "45208",
    "addr:street": "Shaw Ave",
    "iso:country": "US",
    "sg:address": "3416 Shaw Ave",
    "sg:city": "Cincinnati",
    "sg:classifiers": [
      {
        "category": "Insurance",
        "subcategory": "Insurance Agent",
        "type": "Services"
      }
    ],
    "sg:phone": "+1 513 871 2429",
    "sg:postcode": "45208",
    "sg:province": "OH",
    "wof:name": "Federated Insurance",
    "wof:placetype": "venue"
  },
  "geometry": {"coordinates":[-84.439869,39.137638],"type":"Point"}
}
