{
  "type": "Feature",
  "properties": {
    "addr:full":"15618 Cricket Ln East Liverpool OH 43920",
    "addr:housenumber":"15618",
    "addr:postcode":"43920",
    "addr:street":"Cricket Ln",
    "iso:country":"US",
    "sg:address":"15618 Cricket Ln",
    "sg:city":"East Liverpool",
    "sg:classifiers":[
        {
            "category":"Personal",
            "subcategory":"Tattoo Parlor",
            "type":"Services"
        }
    ],
    "sg:phone":"+1 330 382 1444",
    "sg:postcode":"43920",
    "sg:province":"OH",
    "sg:tags":[
        "tattooing"
    ],
    "wof:name":"L A Tattoing",
    "wof:placetype":"venue"
},
  "geometry": {"coordinates":[-80.566423,40.675087],"type":"Point"}
}