{
  "type": "Feature",
  "properties": {
    "iso:country":"US",
    "sg:address":"5900 Roche Dr",
    "sg:city":"Columbus",
    "sg:classifiers":[
        {
            "category":"Banks & Credit Unions",
            "subcategory":"Bank",
            "type":"Services"
        }
    ],
    "sg:phone":"+1 614 433 7313",
    "sg:postcode":"43229",
    "sg:province":"OH",
    "sg:tags":[
        "lender",
        "mortgage"
    ],
    "wof:name":"Mortgage Placement Services",
    "wof:placetype":"venue"
},
  "geometry": {"coordinates":[-82.990298,40.086887],"type":"Point"}
}