{
  "type": "Feature",
  "properties": {
    "iso:country":"US",
    "sg:address":"920 Oak Lea Dr",
    "sg:city":"Troy",
    "sg:classifiers":[
        {
            "category":"Professional",
            "type":"Services"
        }
    ],
    "sg:phone":"+1 937 335 1971",
    "sg:postcode":"45373",
    "sg:province":"OH",
    "wof:name":"String ME Along Designs",
    "wof:placetype":"venue"
},
  "geometry": {"coordinates":[-84.21833599999999,39.98293],"type":"Point"}
}