{
  "type": "Feature",
  "properties": {
    "addr:full":"36625 Vine St Willoughby OH 44094",
    "addr:housenumber":"36625",
    "addr:postcode":"44094",
    "addr:street":"Vine St",
    "iso:country":"US",
    "sg:address":"36625 Vine St",
    "sg:city":"Willoughby",
    "sg:classifiers":[
        {
            "category":"Insurance",
            "subcategory":"Insurance Agent",
            "type":"Services"
        }
    ],
    "sg:phone":"+1 440 953 0217",
    "sg:postcode":"44094",
    "sg:province":"OH",
    "wof:name":"Allstate",
    "wof:placetype":"venue"
},
  "geometry": {"coordinates":[-81.42668,41.642631],"type":"Point"}
}