{
  "type": "Feature",
  "properties": {
    "addr:full":"37801 Deible Rd Logan OH 43138",
    "addr:postcode":"37801;43138",
    "addr:street":"Deible Rd",
    "iso:country":"US",
    "sg:address":"37801 Deible Rd",
    "sg:city":"Logan",
    "sg:classifiers":[
        {
            "category":"Manufacturing",
            "subcategory":"Lumber",
            "type":"Manufacturing & Wholesale Goods"
        }
    ],
    "sg:phone":"+1 740 380 9250",
    "sg:postcode":"43138",
    "sg:province":"OH",
    "sg:tags":[
        "forestry"
    ],
    "wof:name":"New Growth Forestry LLC",
    "wof:placetype":"venue"
},
  "geometry": {"coordinates":[-82.30350900000001,39.554072],"type":"Point"}
}