{
  "type": "Feature",
  "properties": {
    "addr:full":"6455 Wheatstone Ct Maumee OH 43537",
    "addr:housenumber":"6455",
    "addr:postcode":"43537",
    "addr:street":"Wheatstone Ct",
    "iso:country":"US",
    "sg:address":"6455 Wheatstone Ct",
    "sg:city":"Maumee",
    "sg:classifiers":[
        {
            "category":"Banks & Credit Unions",
            "subcategory":"Investment Brokerage",
            "type":"Services"
        }
    ],
    "sg:phone":"+1 419 861 2241",
    "sg:postcode":"43537",
    "sg:province":"OH",
    "sg:tags":[
        "security"
    ],
    "wof:name":"Sterling Assets",
    "wof:placetype":"venue"
},
  "geometry": {"coordinates":[-83.695438,41.577742],"type":"Point"}
}