{
  "type": "Feature",
  "properties": {
    "addr:full":"305 Piedmont Rd Columbus OH 43214",
    "addr:housenumber":"305",
    "addr:postcode":"43214",
    "addr:street":"Piedmont Rd",
    "iso:country":"US",
    "sg:address":"305 Piedmont Rd",
    "sg:city":"Columbus",
    "sg:classifiers":[
        {
            "category":"Wholesale",
            "subcategory":"Non-durable Goods",
            "type":"Manufacturing & Wholesale Goods"
        }
    ],
    "sg:phone":"+1 614 352 2538",
    "sg:postcode":"43214",
    "sg:province":"OH",
    "sg:tags":[
        "advertising"
    ],
    "wof:name":"Highiwire Promotions & Apparel",
    "wof:placetype":"venue"
},
  "geometry": {"coordinates":[-83.010963,40.035062],"type":"Point"}
}