{
  "type": "Feature",
  "properties": {
    "addr:full": "3858 Highland Ave Shadyside OH 43947",
    "addr:housenumber": "3858",
    "addr:postcode": "43947",
    "addr:street": "Highland Ave",
    "iso:country": "US",
    "sg:address": "3858 Highland Ave",
    "sg:city": "Shadyside",
    "sg:classifiers": [
      {
        "category": "Autos \u0026 Motor Vehicles",
        "subcategory": "Automobile Sales",
        "type": "Retail Goods"
      }
    ],
    "sg:phone": "+1 740 671 9005",
    "sg:postcode": "43947",
    "sg:province": "OH",
    "sg:tags": [
      "car",
      "dealer"
    ],
    "wof:name": "Bond Hardware \u0026 Marine",
    "wof:placetype": "venue"
  },
  "geometry": {"coordinates":[-80.746086,39.970881],"type":"Point"}
}
