{
  "type": "Feature",
  "properties": {
    "iso:country":"US",
    "sg:address":"3858 Highland Ave",
    "sg:city":"Shadyside",
    "sg:classifiers":[
        {
            "category":"Autos & Motor Vehicles",
            "subcategory":"Automobile Sales",
            "type":"Retail Goods"
        }
    ],
    "sg:phone":"+1 740 671 9005",
    "sg:postcode":"43947",
    "sg:province":"OH",
    "sg:tags":[
        "car",
        "dealer"
    ],
    "wof:name":"Bond Hardware & Marine",
    "wof:placetype":"venue"
},
  "geometry": {"coordinates":[-80.74608600000001,39.970881],"type":"Point"}
}