{
  "type": "Feature",
  "properties": {
    "addr:full": "205 S Lincoln Ave Bridgeport OH 43912",
    "addr:housenumber": "205",
    "addr:postcode": "43912",
    "addr:street": "S Lincoln Ave",
    "iso:country": "US",
    "sg:address": "205 S Lincoln Ave",
    "sg:city": "Bridgeport",
    "sg:classifiers": [
      {
        "category": "Retail",
        "subcategory": "Auto Repair",
        "type": "Services"
      }
    ],
    "sg:phone": "+1 740 633 6400",
    "sg:postcode": "43912",
    "sg:province": "OH",
    "sg:tags": [
      "wrecker"
    ],
    "wof:name": "A-1 Braden's Towing \u0026 Auto Rpr",
    "wof:placetype": "venue"
  },
  "geometry": {"coordinates":[-80.740441,40.069756],"type":"Point"}
}
