{
  "type": "Feature",
  "properties": {
    "iso:country":"US",
    "sg:address":"120 W Jefferson St",
    "sg:city":"New Carlisle",
    "sg:classifiers":[
        {
            "category":"Shopping",
            "subcategory":"Florist",
            "type":"Retail Goods"
        }
    ],
    "sg:phone":"+1 937 845 1940",
    "sg:postcode":"45344",
    "sg:province":"OH",
    "wof:name":"Creative Designs Flower Shop",
    "wof:placetype":"venue"
},
  "geometry": {"coordinates":[-84.026518,39.936023],"type":"Point"}
}