{
  "type": "Feature",
  "properties": {
    "addr:full": "1515 Fairfield Ave Cleveland OH 44113",
    "addr:housenumber": "1515",
    "addr:postcode": "44113",
    "addr:street": "Fairfield Ave",
    "iso:country": "US",
    "sg:address": "1515 Fairfield Ave",
    "sg:city": "Cleveland",
    "sg:classifiers": [
      {
        "category": "Manufacturing",
        "subcategory": "Metals",
        "type": "Manufacturing \u0026 Wholesale Goods"
      }
    ],
    "sg:phone": "+1 216 522 0348",
    "sg:postcode": "44113",
    "sg:province": "OH",
    "sg:tags": [
      "screw",
      "nut",
      "bolt"
    ],
    "wof:name": "Precision Screw \u0026 Bolt Inc",
    "wof:placetype": "venue"
  },
  "geometry": {"coordinates":[-81.692841,41.482276],"type":"Point"}
}
