{
  "type": "Feature",
  "properties": {
    "iso:country":"US",
    "sg:address":"1515 Fairfield Ave",
    "sg:city":"Cleveland",
    "sg:classifiers":[
        {
            "category":"Manufacturing",
            "subcategory":"Metals",
            "type":"Manufacturing & Wholesale Goods"
        }
    ],
    "sg:phone":"+1 216 522 0348",
    "sg:postcode":"44113",
    "sg:province":"OH",
    "sg:tags":[
        "screw",
        "nut",
        "bolt"
    ],
    "wof:name":"Precision Screw & Bolt Inc",
    "wof:placetype":"venue"
},
  "geometry": {"coordinates":[-81.692841,41.482276],"type":"Point"}
}