{
  "type": "Feature",
  "properties": {
    "addr:full":"565 N Howard St Akron OH 44310",
    "addr:housenumber":"565",
    "addr:postcode":"44310",
    "addr:street":"N Howard St",
    "iso:country":"US",
    "sg:address":"565 N Howard St",
    "sg:city":"Akron",
    "sg:classifiers":[
        {
            "category":"Shopping",
            "subcategory":"Photographic Equipment",
            "type":"Retail Goods"
        }
    ],
    "sg:phone":"+1 330 801 3925",
    "sg:postcode":"44310",
    "sg:province":"OH",
    "sg:tags":[
        "supply"
    ],
    "wof:name":"Photo Tec",
    "wof:placetype":"venue"
},
  "geometry": {"coordinates":[-81.515311,41.100095],"type":"Point"}
}