{
  "type": "Feature",
  "properties": {
    "iso:country":"US",
    "sg:address":"1007 Western Ave",
    "sg:city":"Findlay",
    "sg:classifiers":[
        {
            "category":"Banks & Credit Unions",
            "subcategory":"Bank",
            "type":"Services"
        }
    ],
    "sg:phone":"+1 419 422 5626",
    "sg:postcode":"45840",
    "sg:province":"OH",
    "sg:tags":[
        "federal",
        "loan",
        "broker"
    ],
    "wof:name":"Millstream Area Credit Union",
    "wof:placetype":"venue"
},
  "geometry": {"coordinates":[-83.659764,41.030297],"type":"Point"}
}