{
  "type": "Feature",
  "properties": {
    "addr:full": "777 W Elm St Washington Ct Hs OH 43160",
    "addr:housenumber": "777",
    "addr:postcode": "43160",
    "addr:street": "W Elm St",
    "iso:country": "US",
    "sg:address": "777 W Elm St",
    "sg:city": "Washington Ct Hs",
    "sg:classifiers": [
      {
        "category": "Organizations",
        "subcategory": "Labor Organization",
        "type": "Services"
      }
    ],
    "sg:phone": "+1 740 335 3499",
    "sg:postcode": "43160",
    "sg:province": "OH",
    "wof:name": "Local One Thirty Two Plasters",
    "wof:placetype": "venue"
  },
  "geometry": {"coordinates":[-83.442619,39.523541],"type":"Point"}
}
