{
  "type": "Feature",
  "properties": {
    "addr:full": "3818 Red Bank Rd Cincinnati OH 45227",
    "addr:housenumber": "3818",
    "addr:postcode": "45227",
    "addr:street": "Red Bank Rd",
    "iso:country": "US",
    "sg:address": "3818 Red Bank Rd",
    "sg:city": "Cincinnati",
    "sg:classifiers": [
      {
        "category": "Wholesale",
        "subcategory": "Hardware",
        "type": "Manufacturing \u0026 Wholesale Goods"
      }
    ],
    "sg:phone": "+1 513 527 2300",
    "sg:postcode": "45227",
    "sg:province": "OH",
    "sg:tags": [
      "supply",
      "parts",
      "air",
      "warm",
      "conditioning",
      "representative"
    ],
    "sg:website": "www.stoermer-anderson.com",
    "wof:name": "Stoermer-Anderson Inc",
    "wof:placetype": "venue"
  },
  "geometry": {"coordinates":[-84.405089,39.144378],"type":"Point"}
}
