{
  "type": "Feature",
  "properties": {
    "iso:country":"US",
    "sg:address":"3930 Edwards Rd",
    "sg:city":"Cincinnati",
    "sg:classifiers":[
        {
            "category":"Real Estate",
            "subcategory":"Architect",
            "type":"Services"
        }
    ],
    "sg:phone":"+1 513 841 0400",
    "sg:postcode":"45244",
    "sg:province":"OH",
    "wof:name":"Arch-Image 2",
    "wof:placetype":"venue"
},
  "geometry": {"coordinates":[-84.340867,39.128797],"type":"Point"}
}