{
  "type": "Feature",
  "properties": {
    "addr:full": "2123 Auburn Ave Cincinnati OH 45219",
    "addr:housenumber": "2123",
    "addr:postcode": "45219",
    "addr:street": "Auburn Ave",
    "iso:country": "US",
    "sg:address": "2123 Auburn Ave",
    "sg:city": "Cincinnati",
    "sg:classifiers": [
      {
        "category": "Professional",
        "type": "Services"
      }
    ],
    "sg:phone": "+1 513 333 0404",
    "sg:postcode": "45219",
    "sg:province": "OH",
    "wof:name": "Verisuite",
    "wof:placetype": "venue"
  },
  "geometry": {"coordinates":[-84.508665,39.120184],"type":"Point"}
}
