{
  "type": "Feature",
  "properties": {
    "iso:country":"US",
    "sg:address":"6836 Shiloh Rd",
    "sg:city":"Goshen",
    "sg:classifiers":[
        {
            "category":"Manufacturing",
            "subcategory":"Wood Products",
            "type":"Manufacturing & Wholesale Goods"
        }
    ],
    "sg:phone":"+1 513 625 6447",
    "sg:postcode":"45122",
    "sg:province":"OH",
    "sg:tags":[
        "pallet",
        "skid"
    ],
    "wof:name":"Strong Manufacturers",
    "wof:placetype":"venue"
},
  "geometry": {"coordinates":[-84.115232,39.236214],"type":"Point"}
}