{
  "type": "Feature",
  "properties": {
    "iso:country":"US",
    "sg:address":"214 W Main St",
    "sg:city":"Verona",
    "sg:classifiers":[
        {
            "category":"Manufacturing",
            "subcategory":"Printing",
            "type":"Manufacturing & Wholesale Goods"
        }
    ],
    "sg:phone":"+1 937 884 5568",
    "sg:postcode":"45378",
    "sg:province":"OH",
    "sg:tags":[
        "screen"
    ],
    "sg:website":"www.admasterline.com",
    "wof:name":"Ad Master Supply",
    "wof:placetype":"venue"
},
  "geometry": {"coordinates":[-84.492337,39.903164],"type":"Point"}
}