{
  "type": "Feature",
  "properties": {
    "addr:full":"4996 Pumpkin Ridge Rd West Union OH 45693",
    "addr:housenumber":"4996",
    "addr:postcode":"45693",
    "addr:street":"Pumpkin Ridge Rd",
    "iso:country":"US",
    "sg:address":"4996 Pumpkin Ridge Rd",
    "sg:city":"West Union",
    "sg:classifiers":[
        {
            "category":"Organizations",
            "subcategory":"Religious Organization",
            "type":"Services"
        }
    ],
    "sg:phone":"+1 937 544 2996",
    "sg:postcode":"45693",
    "sg:province":"OH",
    "sg:tags":[
        "clergy"
    ],
    "wof:name":"Rodney Brewer",
    "wof:placetype":"venue"
},
  "geometry": {"coordinates":[-83.5484,38.787153],"type":"Point"}
}