{
  "type": "Feature",
  "properties": {
    "addr:full": "1120 Georgesville Rd Columbus OH 43228",
    "addr:housenumber": "1120",
    "addr:postcode": "43228",
    "addr:street": "Georgesville Rd",
    "iso:country": "US",
    "sg:address": "1120 Georgesville Rd",
    "sg:city": "Columbus",
    "sg:classifiers": [
      {
        "category": "Shopping",
        "subcategory": "Stationery \u0026 Office Supplies",
        "type": "Retail Goods"
      }
    ],
    "sg:phone": "+1 614 279 6636",
    "sg:postcode": "43228",
    "sg:province": "OH",
    "wof:name": "Recio Office Supply",
    "wof:placetype": "venue"
  },
  "geometry": {"coordinates":[-83.116616,39.929115],"type":"Point"}
}
