{
  "type": "Feature",
  "properties": {
    "iso:country":"US",
    "sg:address":"1120 Georgesville Rd",
    "sg:city":"Columbus",
    "sg:classifiers":[
        {
            "category":"Shopping",
            "subcategory":"Stationery & Office Supplies",
            "type":"Retail Goods"
        }
    ],
    "sg:phone":"+1 614 279 6636",
    "sg:postcode":"43228",
    "sg:province":"OH",
    "wof:name":"Recio Office Supply",
    "wof:placetype":"venue"
},
  "geometry": {"coordinates":[-83.11661599999999,39.929115],"type":"Point"}
}