{
  "type": "Feature",
  "properties": {
    "addr:full": "6064 W Central Ave Toledo OH 43615",
    "addr:housenumber": "6064",
    "addr:postcode": "43615",
    "addr:street": "W Central Ave",
    "iso:country": "US",
    "sg:address": "6064 W Central Ave",
    "sg:city": "Toledo",
    "sg:classifiers": [
      {
        "category": "Autos \u0026 Motor Vehicles",
        "subcategory": "Automobile Sales",
        "type": "Retail Goods"
      }
    ],
    "sg:phone": "+1 419 841 4201",
    "sg:postcode": "43615",
    "sg:province": "OH",
    "sg:tags": [
      "used"
    ],
    "wof:name": "Grogan",
    "wof:placetype": "venue"
  },
  "geometry": {"coordinates":[-83.687187,41.676146],"type":"Point"}
}
