{
  "type": "Feature",
  "properties": {
    "addr:full":"2335 US Hwy 20 Clyde OH 43410",
    "addr:housenumber":"2335",
    "addr:postcode":"43410",
    "addr:street":"Us Hwy 20",
    "iso:country":"US",
    "sg:address":"2335 US Hwy 20",
    "sg:city":"Clyde",
    "sg:classifiers":[
        {
            "category":"Home & Garden",
            "subcategory":"Carpets & Floor Coverings",
            "type":"Retail Goods"
        }
    ],
    "sg:phone":"+1 419 483 4200",
    "sg:postcode":"43410",
    "sg:province":"OH",
    "sg:tags":[
        "dealer",
        "rug"
    ],
    "wof:name":"York Carpet Outlet",
    "wof:placetype":"venue"
},
  "geometry": {"coordinates":[-83.04694499999999,41.329454],"type":"Point"}
}