{
  "type": "Feature",
  "properties": {
    "addr:full":"119 S Main St Ridgeway OH 43345",
    "addr:housenumber":"119",
    "addr:postcode":"43345",
    "addr:street":"S Main St",
    "iso:country":"US",
    "sg:address":"119 S Main St",
    "sg:city":"Ridgeway",
    "sg:classifiers":[
        {
            "category":"Home & Garden",
            "subcategory":"Hardware",
            "type":"Retail Goods"
        }
    ],
    "sg:phone":"+1 937 363 2685",
    "sg:postcode":"43345",
    "sg:province":"OH",
    "wof:name":"Mouser Hardware",
    "wof:placetype":"venue"
},
  "geometry": {"coordinates":[-83.573228,40.514952],"type":"Point"}
}