{
  "type": "Feature",
  "properties": {
    "iso:country":"US",
    "sg:address":"468 State Rte 587",
    "sg:city":"Fostoria",
    "sg:classifiers":[
        {
            "category":"Building & Trades",
            "subcategory":"Plumbing",
            "type":"Services"
        }
    ],
    "sg:phone":"+1 419 435 3977",
    "sg:postcode":"44830",
    "sg:province":"OH",
    "sg:tags":[
        "septic"
    ],
    "wof:name":"Bugner's Sewer & Septic Clng",
    "wof:placetype":"venue"
},
  "geometry": {"coordinates":[-83.388211,41.129732],"type":"Point"}
}