{
  "type": "Feature",
  "properties": {
    "iso:country":"US",
    "sg:address":"417 Prospect Ave E",
    "sg:city":"Cleveland",
    "sg:classifiers":[
        {
            "category":"Shopping",
            "subcategory":"Jewelry",
            "type":"Retail Goods"
        }
    ],
    "sg:phone":"+1 216 241 7715",
    "sg:postcode":"44115",
    "sg:province":"OH",
    "sg:tags":[
        "jeweler"
    ],
    "wof:name":"Star Jewelry",
    "wof:placetype":"venue"
},
  "geometry": {"coordinates":[-81.688913,41.498539],"type":"Point"}
}