{
  "type": "Feature",
  "properties": {
    "iso:country":"US",
    "sg:address":"990 Gahanna Pkwy",
    "sg:city":"Gahanna",
    "sg:classifiers":[
        {
            "category":"Manufacturing",
            "subcategory":"Rubber & Plastics",
            "type":"Manufacturing & Wholesale Goods"
        }
    ],
    "sg:phone":"+1 614 759 6550",
    "sg:postcode":"43230",
    "sg:province":"OH",
    "sg:website":"www.advancedplasticsystems.com",
    "wof:name":"ADVANCED Plastic Systems",
    "wof:placetype":"venue"
},
  "geometry": {"coordinates":[-82.84545799999999,39.9926],"type":"Point"}
}