{
  "type": "Feature",
  "properties": {
    "iso:country":"US",
    "sg:address":"100 E 5th St",
    "sg:city":"Cincinnati",
    "sg:classifiers":[
        {
            "category":"Government",
            "subcategory":"Court House",
            "type":"Public Place"
        }
    ],
    "sg:phone":"+1 513 564 7200",
    "sg:postcode":"45202",
    "sg:province":"OH",
    "wof:name":"6th Circuit Court",
    "wof:placetype":"venue"
},
  "geometry": {"coordinates":[-84.50974600000001,39.101589],"type":"Point"}
}