{
  "type": "Feature",
  "properties": {
    "addr:full": "24600 Center Ridge Rd Cleveland OH 44145",
    "addr:housenumber": "24600",
    "addr:postcode": "44145",
    "addr:street": "Center Ridge Rd",
    "iso:country": "US",
    "sg:address": "24600 Center Ridge Rd",
    "sg:city": "Cleveland",
    "sg:classifiers": [
      {
        "category": "Insurance",
        "subcategory": "Hazard Insurance",
        "type": "Services"
      },
      {
        "category": "Insurance",
        "subcategory": "Insurance Agent",
        "type": "Services"
      }
    ],
    "sg:phone": "+1 440 899 9100",
    "sg:postcode": "44145",
    "sg:province": "OH",
    "sg:tags": [
      "profit",
      "sharing",
      "pension",
      "plan"
    ],
    "wof:name": "R \u0026 K Pension Consultants Inc",
    "wof:placetype": "venue"
  },
  "geometry": {"coordinates":[-81.890756,41.458101],"type":"Point"}
}
