{
  "type": "Feature",
  "properties": {
    "addr:full":"5330 Co Rd 9 Edison OH 43320",
    "addr:housenumber":"5330",
    "addr:postcode":"43320",
    "addr:street":"Co Rd 9",
    "iso:country":"US",
    "sg:address":"5330 Co Rd 9",
    "sg:city":"Edison",
    "sg:classifiers":[
        {
            "category":"Retail",
            "subcategory":"Portrait Studio",
            "type":"Services"
        }
    ],
    "sg:phone":"+1 419 947 9225",
    "sg:postcode":"43320",
    "sg:province":"OH",
    "sg:tags":[
        "photographer"
    ],
    "wof:name":"Images 4 Kids",
    "wof:placetype":"venue"
},
  "geometry": {"coordinates":[-82.86283299999999,40.551148],"type":"Point"}
}