{
  "type": "Feature",
  "properties": {
    "addr:full": "42 N. Phelps St. Youngstown OH 44503",
    "addr:housenumber": "42",
    "addr:postcode": "44503",
    "addr:street": "N. Phelps St.",
    "iso:country": "US",
    "sg:address": "42 N. Phelps St.",
    "sg:city": "Youngstown",
    "sg:classifiers": [
      {
        "category": "Professional",
        "subcategory": "Lawyer \u0026 Legal Services",
        "type": "Services"
      }
    ],
    "sg:phone": "+1 330 757 6609",
    "sg:postcode": "44503",
    "sg:province": "OH",
    "sg:tags": [
      "attorney",
      "criminal",
      "law"
    ],
    "sg:website": "http://www.cartwright-jones.com",
    "wof:name": "Rhys B. Cartwright-Jones, Esq.",
    "wof:placetype": "venue"
  },
  "geometry": {"coordinates":[-80.650404,41.100786],"type":"Point"}
}
