{
  "type": "Feature",
  "properties": {
    "addr:full": "135 W 9th St Cincinnati OH 45202",
    "addr:housenumber": "135",
    "addr:postcode": "45202",
    "addr:street": "W 9Th St",
    "iso:country": "US",
    "sg:address": "135 W 9th St",
    "sg:city": "Cincinnati",
    "sg:classifiers": [
      {
        "category": "Real Estate",
        "subcategory": "Real Estate Operator",
        "type": "Services"
      }
    ],
    "sg:phone": "+1 513 381 0974",
    "sg:postcode": "45202",
    "sg:province": "OH",
    "sg:tags": [
      "building",
      "apartment"
    ],
    "wof:name": "Dorothy E Jamieson",
    "wof:placetype": "venue"
  },
  "geometry": {"coordinates":[-84.516696,39.104906],"type":"Point"}
}
