{
  "type": "Feature",
  "properties": {
    "addr:full":"13511 Euclid Ave Cleveland OH 44112",
    "addr:housenumber":"13511",
    "addr:postcode":"44112",
    "addr:street":"Euclid Ave",
    "iso:country":"US",
    "sg:address":"13511 Euclid Ave",
    "sg:city":"Cleveland",
    "sg:classifiers":[
        {
            "category":"Shopping",
            "subcategory":"Clothing, Apparel, & Fashions",
            "type":"Retail Goods"
        }
    ],
    "sg:phone":"+1 216 851 9719",
    "sg:postcode":"44112",
    "sg:province":"OH",
    "wof:name":"Michelle Enterprise Inc",
    "wof:placetype":"venue"
},
  "geometry": {"coordinates":[-81.58805099999999,41.524627],"type":"Point"}
}