{
  "type": "Feature",
  "properties": {
    "addr:full":"17009 Lorain Ave Cleveland OH 44111",
    "addr:housenumber":"17009",
    "addr:postcode":"44111",
    "addr:street":"Lorain Ave",
    "iso:country":"US",
    "sg:address":"17009 Lorain Ave",
    "sg:city":"Cleveland",
    "sg:classifiers":[
        {
            "category":"Personal",
            "subcategory":"Beauty Salon",
            "type":"Services"
        },
        {
            "category":"Personal",
            "subcategory":"Barber",
            "type":"Services"
        }
    ],
    "sg:phone":"+1 216 688 1330",
    "sg:postcode":"44111",
    "sg:province":"OH",
    "sg:tags":[
        "hair",
        "accessory",
        "stylist",
        "supply"
    ],
    "sg:website":"http://www.greatclips.com/",
    "wof:name":"Great Clips",
    "wof:placetype":"venue"
},
  "geometry": {"coordinates":[-81.816667,41.450145],"type":"Point"}
}