{
  "type": "Feature",
  "properties": {
    "addr:full": "3401 Jimes Emory Rd Oak Hill OH 45656",
    "addr:housenumber": "3401",
    "addr:postcode": "45656",
    "addr:street": "Jimes Emory Rd",
    "iso:country": "US",
    "sg:address": "3401 Jimes Emory Rd",
    "sg:city": "Oak Hill",
    "sg:classifiers": [
      {
        "category": "Organizations",
        "subcategory": "Religious Organization",
        "type": "Services"
      }
    ],
    "sg:phone": "+1 740 682 2700",
    "sg:postcode": "45656",
    "sg:province": "OH",
    "sg:tags": [
      "church"
    ],
    "wof:name": "Corinth Missionary Baptist",
    "wof:placetype": "venue"
  },
  "geometry": {"coordinates":[-82.467336,38.852578],"type":"Point"}
}
