{
  "type": "Feature",
  "properties": {
    "iso:country":"US",
    "sg:address":"4837 Kirk Rd",
    "sg:city":"Youngstown",
    "sg:classifiers":[
        {
            "category":"Building & Trades",
            "subcategory":"Construction",
            "type":"Services"
        }
    ],
    "sg:phone":"+1 330 545 4445",
    "sg:postcode":"44515",
    "sg:province":"OH",
    "sg:tags":[
        "painter"
    ],
    "wof:name":"David Ritchie",
    "wof:placetype":"venue"
},
  "geometry": {"coordinates":[-80.741339,41.068899],"type":"Point"}
}