{
  "type": "Feature",
  "properties": {
    "addr:full":"606 Congress Ct Dayton OH 45415",
    "addr:housenumber":"606",
    "addr:postcode":"45415",
    "addr:street":"Congress Ct",
    "iso:country":"US",
    "sg:address":"606 Congress Ct",
    "sg:city":"Dayton",
    "sg:classifiers":[
        {
            "category":"Manufacturing",
            "subcategory":"Retail Goods",
            "type":"Manufacturing & Wholesale Goods"
        }
    ],
    "sg:phone":"+1 937 275 8574",
    "sg:postcode":"45415",
    "sg:province":"OH",
    "sg:tags":[
        "product",
        "merchandise",
        "mfg"
    ],
    "wof:name":"Copeland Craft Co",
    "wof:placetype":"venue"
},
  "geometry": {"coordinates":[-84.225645,39.829823],"type":"Point"}
}