{
  "type": "Feature",
  "properties": {
    "addr:full": "151 Lynwood Ln Lancaster OH 43130",
    "addr:housenumber": "151",
    "addr:postcode": "43130",
    "addr:street": "Lynwood Ln",
    "iso:country": "US",
    "sg:address": "151 Lynwood Ln",
    "sg:city": "Lancaster",
    "sg:classifiers": [
      {
        "category": "Cinema",
        "subcategory": "Drive-in Theater",
        "type": "Entertainment"
      }
    ],
    "sg:phone": "+1 740 654 4525",
    "sg:postcode": "43130",
    "sg:province": "OH",
    "sg:tags": [
      "drive"
    ],
    "wof:name": "Skyview Concessions",
    "wof:placetype": "venue"
  },
  "geometry": {"coordinates":[-82.549873,39.722599],"type":"Point"}
}
