{
  "type": "Feature",
  "properties": {
    "iso:country":"US",
    "sg:address":"151 Lynwood Ln",
    "sg:city":"Lancaster",
    "sg:classifiers":[
        {
            "category":"Cinema",
            "subcategory":"Drive-in Theater",
            "type":"Entertainment"
        }
    ],
    "sg:phone":"+1 740 654 4525",
    "sg:postcode":"43130",
    "sg:province":"OH",
    "sg:tags":[
        "drive"
    ],
    "wof:name":"Skyview Concessions",
    "wof:placetype":"venue"
},
  "geometry": {"coordinates":[-82.54987300000001,39.722599],"type":"Point"}
}