{
  "type": "Feature",
  "properties": {
    "iso:country":"US",
    "sg:address":"1117 W Fairview Ave",
    "sg:city":"Dayton",
    "sg:classifiers":[
        {
            "category":"Organizations",
            "subcategory":"Community Association",
            "type":"Services"
        }
    ],
    "sg:phone":"+1 937 278 8955",
    "sg:postcode":"45406",
    "sg:province":"OH",
    "wof:name":"Toastmasters International",
    "wof:placetype":"venue"
},
  "geometry": {"coordinates":[-84.22906,39.7874],"type":"Point"}
}