{
  "type": "Feature",
  "properties": {
    "iso:country":"US",
    "sg:address":"222 Graceland Blvd",
    "sg:city":"Columbus",
    "sg:classifiers":[
        {
            "category":"Home & Garden",
            "subcategory":"Furniture",
            "type":"Retail Goods"
        }
    ],
    "sg:phone":"+1 614 436 1022",
    "sg:postcode":"43214",
    "sg:province":"OH",
    "wof:name":"Seasonal Concepts",
    "wof:placetype":"venue"
},
  "geometry": {"coordinates":[-83.019902,40.065994],"type":"Point"}
}