{
  "type": "Feature",
  "properties": {
    "addr:full":"1 Federal Plz W Youngstown OH 44503",
    "addr:housenumber":"1",
    "addr:postcode":"44503",
    "addr:street":"Federal Plz W",
    "iso:country":"US",
    "sg:address":"1 Federal Plz W",
    "sg:city":"Youngstown",
    "sg:classifiers":[
        {
            "category":"Banks & Credit Unions",
            "subcategory":"Bank",
            "type":"Services"
        }
    ],
    "sg:phone":"+1 330 747 0292",
    "sg:postcode":"44503",
    "sg:province":"OH",
    "sg:website":"www.fnb-online.com",
    "wof:name":"First National Bank",
    "wof:placetype":"venue"
},
  "geometry": {"coordinates":[-80.651748,41.101105],"type":"Point"}
}