{
  "type": "Feature",
  "properties": {
    "addr:full": "48248 Main St Cameron OH 43914",
    "addr:housenumber": "48248",
    "addr:postcode": "43914",
    "addr:street": "Main St",
    "iso:country": "US",
    "sg:address": "48248 Main St",
    "sg:city": "Cameron",
    "sg:classifiers": [
      {
        "category": "Education",
        "subcategory": "School",
        "type": "Public Place"
      }
    ],
    "sg:phone": "+1 740 458 9072",
    "sg:postcode": "43914",
    "sg:province": "OH",
    "wof:name": "Monroe Central High School",
    "wof:placetype": "venue"
  },
  "geometry": {"coordinates":[-80.944415,39.769006],"type":"Point"}
}
