{
  "type": "Feature",
  "properties": {
    "iso:country":"US",
    "sg:address":"48248 Main St",
    "sg:city":"Cameron",
    "sg:classifiers":[
        {
            "category":"Education",
            "subcategory":"School",
            "type":"Public Place"
        }
    ],
    "sg:phone":"+1 740 458 9072",
    "sg:postcode":"43914",
    "sg:province":"OH",
    "wof:name":"Monroe Central High School",
    "wof:placetype":"venue"
},
  "geometry": {"coordinates":[-80.94441500000001,39.769006],"type":"Point"}
}