{
  "type": "Feature",
  "properties": {
    "addr:full":"6050 State Rte 14 Ravenna OH 44266",
    "addr:housenumber":"6050",
    "addr:postcode":"44266",
    "addr:street":"State Rte 14",
    "iso:country":"US",
    "sg:address":"6050 State Rte 14",
    "sg:city":"Ravenna",
    "sg:classifiers":[
        {
            "category":"Mining & Drilling",
            "type":"Manufacturing & Wholesale Goods"
        }
    ],
    "sg:phone":"+1 330 297 5508",
    "sg:postcode":"44266",
    "sg:province":"OH",
    "sg:tags":[
        "gas",
        "produce",
        "well"
    ],
    "wof:name":"King Energy Inc",
    "wof:placetype":"venue"
},
  "geometry": {"coordinates":[-81.215583,41.152977],"type":"Point"}
}