{
  "type": "Feature",
  "properties": {
    "addr:full": "910 Race St Cincinnati OH 45202",
    "addr:housenumber": "910",
    "addr:postcode": "45202",
    "addr:street": "Race St",
    "iso:country": "US",
    "sg:address": "910 Race St",
    "sg:city": "Cincinnati",
    "sg:classifiers": [
      {
        "category": "Manufacturing",
        "subcategory": "Printing",
        "type": "Manufacturing \u0026 Wholesale Goods"
      }
    ],
    "sg:phone": "+1 513 381 3558",
    "sg:postcode": "45202",
    "sg:province": "OH",
    "sg:tags": [
      "printer"
    ],
    "wof:name": "Minit-Print-It",
    "wof:placetype": "venue"
  },
  "geometry": {"coordinates":[-84.515687,39.105491],"type":"Point"}
}
