{
  "type": "Feature",
  "properties": {
    "addr:full":"5511 Roberts Rd Hilliard OH 43026",
    "addr:housenumber":"5511",
    "addr:postcode":"43026",
    "addr:street":"Roberts Rd",
    "iso:country":"US",
    "sg:address":"5511 Roberts Rd",
    "sg:city":"Hilliard",
    "sg:classifiers":[
        {
            "category":"Retail",
            "subcategory":"Laundry & Dry Cleaning",
            "type":"Services"
        }
    ],
    "sg:phone":"+1 614 529 0050",
    "sg:postcode":"43026",
    "sg:province":"OH",
    "sg:tags":[
        "drycleaning",
        "plant"
    ],
    "wof:name":"Swan Cleaners",
    "wof:placetype":"venue"
},
  "geometry": {"coordinates":[-83.15594,40.003854],"type":"Point"}
}