{
  "type": "Feature",
  "properties": {
    "addr:full":"2709 Woodburn Ave Cincinnati OH 45206",
    "addr:housenumber":"2709",
    "addr:postcode":"45206",
    "addr:street":"Woodburn Ave",
    "iso:country":"US",
    "sg:address":"2709 Woodburn Ave",
    "sg:city":"Cincinnati",
    "sg:classifiers":[
        {
            "category":"Building & Trades",
            "subcategory":"Equipment Rental",
            "type":"Services"
        }
    ],
    "sg:phone":"+1 513 961 1122",
    "sg:postcode":"45206",
    "sg:province":"OH",
    "sg:tags":[
        "yard"
    ],
    "sg:website":"www.schulhoff-tool.com",
    "wof:name":"Schulhoff Equipment Rental",
    "wof:placetype":"venue"
},
  "geometry": {"coordinates":[-84.477727,39.128311],"type":"Point"}
}