{
  "type": "Feature",
  "properties": {
    "iso:country":"US",
    "sg:address":"3205 Daytona Ave",
    "sg:city":"Cincinnati",
    "sg:classifiers":[
        {
            "category":"Restaurant",
            "type":"Food & Drink"
        }
    ],
    "sg:phone":"+1 513 662 6503",
    "sg:postcode":"45211",
    "sg:province":"OH",
    "sg:tags":[
        "eating"
    ],
    "wof:name":"T L N A Domino Sugar",
    "wof:placetype":"venue"
},
  "geometry": {"coordinates":[-84.60888,39.14654],"type":"Point"}
}