{
  "type": "Feature",
  "properties": {
    "addr:full":"10152 Colerain Ave Cincinnati OH 45251",
    "addr:postcode":"10152;45251",
    "addr:street":"Colerain Ave",
    "iso:country":"US",
    "sg:address":"10152 Colerain Ave",
    "sg:city":"Cincinnati",
    "sg:classifiers":[
        {
            "category":"Restaurant",
            "type":"Food & Drink"
        }
    ],
    "sg:phone":"+1 513 759 6340",
    "sg:postcode":"45251",
    "sg:province":"OH",
    "wof:name":"Wendys",
    "wof:placetype":"venue"
},
  "geometry": {"coordinates":[-84.604542,39.263963],"type":"Point"}
}