{
  "type": "Feature",
  "properties": {
    "iso:country":"US",
    "sg:address":"44 Village Sq",
    "sg:city":"Cincinnati",
    "sg:classifiers":[
        {
            "category":"Organizations",
            "subcategory":"Non-profit Organization",
            "type":"Services"
        }
    ],
    "sg:phone":"+1 513 771 8722",
    "sg:postcode":"45246",
    "sg:province":"OH",
    "wof:name":"Glendale Heritage Preservation",
    "wof:placetype":"venue"
},
  "geometry": {"coordinates":[-84.459155,39.271322],"type":"Point"}
}