{
  "type": "Feature",
  "properties": {
    "addr:full":"140 E Market St Akron OH 44308",
    "addr:housenumber":"140",
    "addr:postcode":"44308",
    "addr:street":"E Market St",
    "iso:country":"US",
    "sg:address":"140 E Market St",
    "sg:city":"Akron",
    "sg:classifiers":[
        {
            "category":"Museum",
            "type":"Entertainment"
        }
    ],
    "sg:phone":"+1 330 376 8480",
    "sg:postcode":"44308",
    "sg:province":"OH",
    "sg:tags":[
        "organization",
        "arts",
        "information"
    ],
    "wof:name":"Akron Area Arts Alliance",
    "wof:placetype":"venue"
},
  "geometry": {"coordinates":[-81.512248,41.083378],"type":"Point"}
}