{
  "type": "Feature",
  "properties": {
    "iso:country":"US",
    "sg:address":"3988 Magnolia Dr",
    "sg:city":"Brunswick",
    "sg:classifiers":[
        {
            "category":"Shopping",
            "subcategory":"Gifts & Souvenirs",
            "type":"Retail Goods"
        }
    ],
    "sg:phone":"+1 330 273 2132",
    "sg:postcode":"44212",
    "sg:province":"OH",
    "sg:tags":[
        "shop",
        "as",
        "novelty",
        "operates"
    ],
    "wof:name":"Sarah E Elkins",
    "wof:placetype":"venue"
},
  "geometry": {"coordinates":[-81.82875900000001,41.268615],"type":"Point"}
}