{
  "type": "Feature",
  "properties": {
    "addr:full": "3988 Magnolia Dr Brunswick OH 44212",
    "addr:housenumber": "3988",
    "addr:postcode": "44212",
    "addr:street": "Magnolia Dr",
    "iso:country": "US",
    "sg:address": "3988 Magnolia Dr",
    "sg:city": "Brunswick",
    "sg:classifiers": [
      {
        "category": "Shopping",
        "subcategory": "Gifts \u0026 Souvenirs",
        "type": "Retail Goods"
      }
    ],
    "sg:phone": "+1 330 273 2132",
    "sg:postcode": "44212",
    "sg:province": "OH",
    "sg:tags": [
      "shop",
      "as",
      "novelty",
      "operates"
    ],
    "wof:name": "Sarah E Elkins",
    "wof:placetype": "venue"
  },
  "geometry": {"coordinates":[-81.828759,41.268615],"type":"Point"}
}
