{
  "type": "Feature",
  "properties": {
    "addr:full":"7486 Feder Rd Galloway OH 43119",
    "addr:housenumber":"7486",
    "addr:postcode":"43119",
    "addr:street":"Feder Rd",
    "iso:country":"US",
    "sg:address":"7486 Feder Rd",
    "sg:city":"Galloway",
    "sg:classifiers":[
        {
            "category":"Building & Trades",
            "subcategory":"Construction",
            "type":"Services"
        }
    ],
    "sg:phone":"+1 614 878 9753",
    "sg:postcode":"43119",
    "sg:province":"OH",
    "sg:tags":[
        "residential",
        "commercial",
        "painting",
        "contractor"
    ],
    "wof:name":"Reber Enterprises Inc",
    "wof:placetype":"venue"
},
  "geometry": {"coordinates":[-83.20835700000001,39.971694],"type":"Point"}
}