{
  "type": "Feature",
  "properties": {
    "addr:full": "227 Castle Blvd Akron OH 44313",
    "addr:housenumber": "227",
    "addr:postcode": "44313",
    "addr:street": "Castle Blvd",
    "iso:country": "US",
    "sg:address": "227 Castle Blvd",
    "sg:city": "Akron",
    "sg:classifiers": [
      {
        "category": "Shopping",
        "subcategory": "Hobbies, Toys, \u0026 Games",
        "type": "Retail Goods"
      }
    ],
    "sg:phone": "+1 330 864 0790",
    "sg:postcode": "44313",
    "sg:province": "OH",
    "wof:name": "Anj Sales",
    "wof:placetype": "venue"
  },
  "geometry": {"coordinates":[-81.561285,41.115771],"type":"Point"}
}
