{
  "type": "Feature",
  "properties": {
    "iso:country":"US",
    "sg:address":"227 Castle Blvd",
    "sg:city":"Akron",
    "sg:classifiers":[
        {
            "category":"Shopping",
            "subcategory":"Hobbies, Toys, & Games",
            "type":"Retail Goods"
        }
    ],
    "sg:phone":"+1 330 864 0790",
    "sg:postcode":"44313",
    "sg:province":"OH",
    "wof:name":"Anj Sales",
    "wof:placetype":"venue"
},
  "geometry": {"coordinates":[-81.561285,41.115771],"type":"Point"}
}