{
  "type": "Feature",
  "properties": {
    "addr:full":"2911 Pemberton Rd Laura OH 45339",
    "addr:housenumber":"2911",
    "addr:postcode":"45339",
    "addr:street":"Pemberton Rd",
    "iso:country":"US",
    "sg:address":"2911 Pemberton Rd",
    "sg:city":"Laura",
    "sg:classifiers":[
        {
            "category":"Personal",
            "subcategory":"Beauty Salon",
            "type":"Services"
        }
    ],
    "sg:phone":"+1 937 947 0030",
    "sg:postcode":"45339",
    "sg:province":"OH",
    "wof:name":"Bonni's Cut & Style",
    "wof:placetype":"venue"
},
  "geometry": {"coordinates":[-84.408755,39.998173],"type":"Point"}
}