{
  "type": "Feature",
  "properties": {
    "addr:full": "7396 Hudson Park Dr Hudson OH 44236",
    "addr:housenumber": "7396",
    "addr:postcode": "44236",
    "addr:street": "Hudson Park Dr",
    "iso:country": "US",
    "sg:address": "7396 Hudson Park Dr",
    "sg:city": "Hudson",
    "sg:classifiers": [
      {
        "category": "Real Estate",
        "subcategory": "Real Estate Agent",
        "type": "Services"
      }
    ],
    "sg:phone": "+1 330 656 1286",
    "sg:postcode": "44236",
    "sg:province": "OH",
    "wof:name": "Enterprises",
    "wof:placetype": "venue"
  },
  "geometry": {"coordinates":[-81.417365,41.259676],"type":"Point"}
}
