{
  "type": "Feature",
  "properties": {
    "addr:full": "3578 Kettering Blvd Dayton OH 45439",
    "addr:housenumber": "3578",
    "addr:postcode": "45439",
    "addr:street": "Kettering Blvd",
    "iso:country": "US",
    "sg:address": "3578 Kettering Blvd",
    "sg:city": "Dayton",
    "sg:classifiers": [
      {
        "category": "Autos \u0026 Motor Vehicles",
        "subcategory": "Auto Supplies",
        "type": "Retail Goods"
      }
    ],
    "sg:phone": "+1 937 294 2699",
    "sg:postcode": "45439",
    "sg:province": "OH",
    "sg:tags": [
      "tire"
    ],
    "wof:name": "Fattboyz",
    "wof:placetype": "venue"
  },
  "geometry": {"coordinates":[-84.20681,39.702089],"type":"Point"}
}
