{
  "type": "Feature",
  "properties": {
    "addr:full": "1304 S 22nd St Columbus OH 43206",
    "addr:housenumber": "1304",
    "addr:postcode": "43206",
    "addr:street": "S 22Nd St",
    "iso:country": "US",
    "sg:address": "1304 S 22nd St",
    "sg:city": "Columbus",
    "sg:classifiers": [
      {
        "category": "Banks \u0026 Credit Unions",
        "subcategory": "Investment Brokerage",
        "type": "Services"
      },
      {
        "category": "Bars \u0026 Pubs",
        "type": "Food \u0026 Drink"
      }
    ],
    "sg:phone": "+1 614 445 6283",
    "sg:postcode": "43206",
    "sg:province": "OH",
    "sg:tags": [
      "drinking"
    ],
    "wof:name": "Second Wind Investments Corp",
    "wof:placetype": "venue"
  },
  "geometry": {"coordinates":[-82.973589,39.938518],"type":"Point"}
}
