{
  "type": "Feature",
  "properties": {
    "iso:country":"US",
    "sg:address":"19800 State Rte 47",
    "sg:city":"Maplewood",
    "sg:classifiers":[
        {
            "category":"Building & Trades",
            "subcategory":"Construction",
            "type":"Services"
        }
    ],
    "sg:phone":"+1 937 498 1000",
    "sg:postcode":"45340",
    "sg:province":"OH",
    "sg:tags":[
        "hanging",
        "home",
        "improvement",
        "contractor"
    ],
    "wof:name":"AE&e Painting",
    "wof:placetype":"venue"
},
  "geometry": {"coordinates":[-84.057773,40.353885],"type":"Point"}
}