{
  "type": "Feature",
  "properties": {
    "addr:full": "2100 W 4th St Mansfield OH 44906",
    "addr:housenumber": "2100",
    "addr:postcode": "44906",
    "addr:street": "W 4Th St",
    "iso:country": "US",
    "sg:address": "2100 W 4th St",
    "sg:city": "Mansfield",
    "sg:classifiers": [
      {
        "category": "Restaurant",
        "type": "Food \u0026 Drink"
      }
    ],
    "sg:menulink": "http://www.allmenus.com/oh/five-corners/44064-bob-evans/menu/",
    "sg:phone": "+1 419 747 4178",
    "sg:postcode": "44906",
    "sg:province": "OH",
    "sg:tags": [
      "american"
    ],
    "wof:name": "Bob Evans",
    "wof:placetype": "venue"
  },
  "geometry": {"coordinates":[-82.588856,40.772149],"type":"Point"}
}
