{
  "type": "Feature",
  "properties": {
    "iso:country":"US",
    "sg:address":"14326 S Park Blvd",
    "sg:city":"Cleveland",
    "sg:classifiers":[
        {
            "category":"Health Services",
            "subcategory":"Health Practitioner",
            "type":"Services"
        }
    ],
    "sg:phone":"+1 216 932 1530",
    "sg:postcode":"44120",
    "sg:province":"OH",
    "sg:tags":[
        "psychologist"
    ],
    "wof:name":"Frances S Baker Inc",
    "wof:placetype":"venue"
},
  "geometry": {"coordinates":[-81.581321,41.487876],"type":"Point"}
}