{
  "type": "Feature",
  "properties": {
    "addr:full":"3828 Elm Rd NE Warren OH 44483",
    "addr:housenumber":"3828",
    "addr:postcode":"44483",
    "addr:street":"Elm Rd Ne",
    "iso:country":"US",
    "sg:address":"3828 Elm Rd NE",
    "sg:city":"Warren",
    "sg:classifiers":[
        {
            "category":"Autos & Motor Vehicles",
            "subcategory":"Auto Supplies",
            "type":"Retail Goods"
        }
    ],
    "sg:phone":"+1 330 372 6036",
    "sg:postcode":"44483",
    "sg:province":"OH",
    "wof:name":"Advance Auto Parts",
    "wof:placetype":"venue"
},
  "geometry": {"coordinates":[-80.78004199999999,41.271474],"type":"Point"}
}