{
  "type": "Feature",
  "properties": {
    "iso:country":"US",
    "sg:address":"1815 E Ohio Pike",
    "sg:city":"Amelia",
    "sg:classifiers":[
        {
            "category":"Personal",
            "subcategory":"Beauty Salon",
            "type":"Services"
        }
    ],
    "sg:phone":"+1 513 797 9600",
    "sg:postcode":"45102",
    "sg:province":"OH",
    "wof:name":"Smart Style Family Hair Salon",
    "wof:placetype":"venue"
},
  "geometry": {"coordinates":[-84.198967,39.018385],"type":"Point"}
}