{
  "type": "Feature",
  "properties": {
    "addr:full": "16022 E High St Middlefield OH 44062",
    "addr:housenumber": "16022",
    "addr:postcode": "44062",
    "addr:street": "E High St",
    "iso:country": "US",
    "sg:address": "16022 E High St",
    "sg:city": "Middlefield",
    "sg:classifiers": [
      {
        "category": "Health Services",
        "subcategory": "Doctor",
        "type": "Services"
      }
    ],
    "sg:phone": "+1 440 632 1908",
    "sg:postcode": "44062",
    "sg:province": "OH",
    "sg:tags": [
      "dentist"
    ],
    "wof:name": "Gilbert J Farrell DDS",
    "wof:placetype": "venue"
  },
  "geometry": {"coordinates":[-81.070421,41.461896],"type":"Point"}
}
