{
  "type": "Feature",
  "properties": {
    "iso:country":"US",
    "sg:address":"16022 E High St",
    "sg:city":"Middlefield",
    "sg:classifiers":[
        {
            "category":"Health Services",
            "subcategory":"Doctor",
            "type":"Services"
        }
    ],
    "sg:phone":"+1 440 632 1908",
    "sg:postcode":"44062",
    "sg:province":"OH",
    "sg:tags":[
        "dentist"
    ],
    "wof:name":"Gilbert J Farrell DDS",
    "wof:placetype":"venue"
},
  "geometry": {"coordinates":[-81.070421,41.461896],"type":"Point"}
}