{
  "type": "Feature",
  "properties": {
    "addr:full":"819 Colorado Dr Xenia OH 45385",
    "addr:housenumber":"819",
    "addr:postcode":"45385",
    "addr:street":"Colorado Dr",
    "iso:country":"US",
    "sg:address":"819 Colorado Dr",
    "sg:city":"Xenia",
    "sg:classifiers":[
        {
            "category":"Education",
            "subcategory":"School",
            "type":"Public Place"
        }
    ],
    "sg:phone":"+1 937 372 1251",
    "sg:postcode":"45385",
    "sg:province":"OH",
    "wof:name":"McKinley Elementary School",
    "wof:placetype":"venue"
},
  "geometry": {"coordinates":[-83.97048599999999,39.671463],"type":"Point"}
}