{
  "type": "Feature",
  "properties": {
    "addr:full": "8022 Sandstone Dr Northfield OH 44067",
    "addr:housenumber": "8022",
    "addr:postcode": "44067",
    "addr:street": "Sandstone Dr",
    "iso:country": "US",
    "sg:address": "8022 Sandstone Dr",
    "sg:city": "Northfield",
    "sg:classifiers": [
      {
        "category": "Building \u0026 Trades",
        "subcategory": "Construction",
        "type": "Services"
      }
    ],
    "sg:phone": "+1 330 468 8797",
    "sg:postcode": "44067",
    "sg:province": "OH",
    "sg:tags": [
      "residential"
    ],
    "wof:name": "Blue Marlin Builders LLC",
    "wof:placetype": "venue"
  },
  "geometry": {"coordinates":[-81.5679,41.333247],"type":"Point"}
}
