{
  "type": "Feature",
  "properties": {
    "addr:full":"2740 Gallia St Portsmouth OH 45662",
    "addr:postcode":"2740;45662",
    "addr:street":"Gallia St",
    "iso:country":"US",
    "sg:address":"2740 Gallia St",
    "sg:city":"Portsmouth",
    "sg:classifiers":[
        {
            "category":"Autos & Motor Vehicles",
            "subcategory":"Auto Supplies",
            "type":"Retail Goods"
        }
    ],
    "sg:phone":"+1 740 354 3929",
    "sg:postcode":"45662",
    "sg:province":"OH",
    "sg:tags":[
        "automobile",
        "parts"
    ],
    "sg:website":"www.autozone.com",
    "wof:name":"Autozone",
    "wof:placetype":"venue"
},
  "geometry": {"coordinates":[-82.96613600000001,38.739693],"type":"Point"}
}