{
  "type": "Feature",
  "properties": {
    "iso:country":"US",
    "sg:address":"716 Mound Rd",
    "sg:city":"Miamisburg",
    "sg:classifiers":[
        {
            "category":"Retail",
            "subcategory":"Auto Repair",
            "type":"Services"
        }
    ],
    "sg:phone":"+1 937 865 0746",
    "sg:postcode":"45342",
    "sg:province":"OH",
    "sg:tags":[
        "wrecker"
    ],
    "wof:name":"A & V Towing",
    "wof:placetype":"venue"
},
  "geometry": {"coordinates":[-84.27851099999999,39.621828],"type":"Point"}
}