{
  "type": "Feature",
  "properties": {
    "iso:country":"US",
    "sg:address":"826 Westpoint Pkwy",
    "sg:city":"Cleveland",
    "sg:classifiers":[
        {
            "category":"Professional",
            "subcategory":"Management & Consulting",
            "type":"Services"
        }
    ],
    "sg:phone":"+1 440 617 0333",
    "sg:postcode":"44145",
    "sg:province":"OH",
    "wof:name":"LTC Risk Management",
    "wof:placetype":"venue"
},
  "geometry": {"coordinates":[-81.888139,41.471689],"type":"Point"}
}