{
  "type": "Feature",
  "properties": {
    "addr:full": "5530 Pearl Rd Cleveland OH 44129",
    "addr:housenumber": "5530",
    "addr:postcode": "44129",
    "addr:street": "Pearl Rd",
    "iso:country": "US",
    "sg:address": "5530 Pearl Rd",
    "sg:city": "Cleveland",
    "sg:classifiers": [
      {
        "category": "Real Estate",
        "subcategory": "Real Estate Agent",
        "type": "Services"
      }
    ],
    "sg:phone": "+1 440 887 9990",
    "sg:postcode": "44129",
    "sg:province": "OH",
    "wof:name": "Real Estate Corner Inc",
    "wof:placetype": "venue"
  },
  "geometry": {"coordinates":[-81.736238,41.411998],"type":"Point"}
}
