{
  "type": "Feature",
  "properties": {
    "iso:country":"US",
    "sg:address":"1722 Fulton Rd",
    "sg:city":"Cleveland",
    "sg:classifiers":[
        {
            "category":"Banks & Credit Unions",
            "subcategory":"Financial Services",
            "type":"Services"
        }
    ],
    "sg:phone":"+1 216 241 6780",
    "sg:postcode":"44113",
    "sg:province":"OH",
    "sg:tags":[
        "company",
        "holding"
    ],
    "wof:name":"4319x Holdings LLC",
    "wof:placetype":"venue"
},
  "geometry": {"coordinates":[-81.70904,41.486416],"type":"Point"}
}