{
  "type": "Feature",
  "properties": {
    "addr:full": "2610 Sunset Blvd Steubenville OH 43952",
    "addr:housenumber": "2610",
    "addr:postcode": "43952",
    "addr:street": "Sunset Blvd",
    "iso:country": "US",
    "sg:address": "2610 Sunset Blvd",
    "sg:city": "Steubenville",
    "sg:classifiers": [
      {
        "category": "Banks \u0026 Credit Unions",
        "subcategory": "Bank",
        "type": "Services"
      }
    ],
    "sg:phone": "+1 740 264 6472",
    "sg:postcode": "43952",
    "sg:province": "OH",
    "sg:tags": [
      "depository",
      "banking"
    ],
    "wof:name": "Payday Express",
    "wof:placetype": "venue"
  },
  "geometry": {"coordinates":[-80.651027,40.374217],"type":"Point"}
}
