{
  "type": "Feature",
  "properties": {
    "iso:country":"US",
    "sg:address":"365 Victoria Rd",
    "sg:city":"Youngstown",
    "sg:classifiers":[
        {
            "category":"Shopping",
            "subcategory":"Discount & Variety Stores",
            "type":"Retail Goods"
        }
    ],
    "sg:phone":"+1 330 792 2702",
    "sg:postcode":"44515",
    "sg:province":"OH",
    "sg:tags":[
        "merchandise",
        "general"
    ],
    "wof:name":"HMS Products Co",
    "wof:placetype":"venue"
},
  "geometry": {"coordinates":[-80.784621,41.10397],"type":"Point"}
}