{
  "type": "Feature",
  "properties": {
    "addr:full":"31081 Lincoln Rd Westlake OH 44145",
    "addr:housenumber":"31081",
    "addr:postcode":"44145",
    "addr:street":"Lincoln Rd",
    "iso:country":"US",
    "sg:address":"31081 Lincoln Rd",
    "sg:city":"Westlake",
    "sg:classifiers":[
        {
            "category":"Professional",
            "subcategory":"Computer Services",
            "type":"Services"
        }
    ],
    "sg:phone":"+1 440 250 0126",
    "sg:postcode":"44145",
    "sg:province":"OH",
    "wof:name":"Exposight",
    "wof:placetype":"venue"
},
  "geometry": {"coordinates":[-81.967752,41.4311],"type":"Point"}
}